package com.google.android.gms.internal.measurement;

import com.google.android.gms.common.internal.Preconditions;
import com.google.android.gms.common.util.VisibleForTesting;
import com.tencent.matrix.trace.core.AppMethodBeat;
import java.math.BigDecimal;
import java.util.ArrayList;
import java.util.Arrays;
import java.util.List;
import java.util.Locale;
import java.util.regex.Matcher;
import java.util.regex.Pattern;
import java.util.regex.PatternSyntaxException;

final class zzeb extends zzjq
{
  zzeb(zzjr paramzzjr)
  {
    super(paramzzjr);
  }

  private final Boolean zza(double paramDouble, zzkg paramzzkg)
  {
    AppMethodBeat.i(68589);
    try
    {
      BigDecimal localBigDecimal = new java/math/BigDecimal;
      localBigDecimal.<init>(paramDouble);
      paramzzkg = zza(localBigDecimal, paramzzkg, Math.ulp(paramDouble));
      AppMethodBeat.o(68589);
      return paramzzkg;
    }
    catch (NumberFormatException paramzzkg)
    {
      while (true)
      {
        paramzzkg = null;
        AppMethodBeat.o(68589);
      }
    }
  }

  private final Boolean zza(long paramLong, zzkg paramzzkg)
  {
    AppMethodBeat.i(68588);
    try
    {
      BigDecimal localBigDecimal = new java/math/BigDecimal;
      localBigDecimal.<init>(paramLong);
      paramzzkg = zza(localBigDecimal, paramzzkg, 0.0D);
      AppMethodBeat.o(68588);
      return paramzzkg;
    }
    catch (NumberFormatException paramzzkg)
    {
      while (true)
      {
        paramzzkg = null;
        AppMethodBeat.o(68588);
      }
    }
  }

  @VisibleForTesting
  private static Boolean zza(Boolean paramBoolean, boolean paramBoolean1)
  {
    AppMethodBeat.i(68585);
    if (paramBoolean == null)
    {
      paramBoolean = null;
      AppMethodBeat.o(68585);
    }
    while (true)
    {
      return paramBoolean;
      paramBoolean = Boolean.valueOf(paramBoolean.booleanValue() ^ paramBoolean1);
      AppMethodBeat.o(68585);
    }
  }

  private final Boolean zza(String paramString1, int paramInt, boolean paramBoolean, String paramString2, List<String> paramList, String paramString3)
  {
    AppMethodBeat.i(68587);
    if (paramString1 == null)
    {
      AppMethodBeat.o(68587);
      paramString1 = null;
    }
    while (true)
    {
      label16: return paramString1;
      if (paramInt == 6)
      {
        if ((paramList == null) || (paramList.size() == 0))
        {
          AppMethodBeat.o(68587);
          paramString1 = null;
        }
      }
      else if (paramString2 == null)
      {
        AppMethodBeat.o(68587);
        paramString1 = null;
      }
      else
      {
        String str = paramString1;
        if (!paramBoolean)
          if (paramInt != 1)
            break label130;
        label130: for (str = paramString1; ; str = paramString1.toUpperCase(Locale.ENGLISH))
          switch (paramInt)
          {
          default:
            AppMethodBeat.o(68587);
            paramString1 = null;
            break label16;
          case 1:
          case 2:
          case 3:
          case 4:
          case 5:
          case 6:
          }
        if (paramBoolean)
          paramInt = 0;
        try
        {
          while (true)
          {
            paramBoolean = Pattern.compile(paramString3, paramInt).matcher(str).matches();
            paramString1 = Boolean.valueOf(paramBoolean);
            AppMethodBeat.o(68587);
            break;
            paramInt = 66;
          }
        }
        catch (PatternSyntaxException paramString1)
        {
          zzge().zzip().zzg("Invalid regular expression in REGEXP audience filter. expression", paramString3);
          AppMethodBeat.o(68587);
          paramString1 = null;
        }
        continue;
        paramString1 = Boolean.valueOf(str.startsWith(paramString2));
        AppMethodBeat.o(68587);
        continue;
        paramString1 = Boolean.valueOf(str.endsWith(paramString2));
        AppMethodBeat.o(68587);
        continue;
        paramString1 = Boolean.valueOf(str.contains(paramString2));
        AppMethodBeat.o(68587);
        continue;
        paramString1 = Boolean.valueOf(str.equals(paramString2));
        AppMethodBeat.o(68587);
        continue;
        paramString1 = Boolean.valueOf(paramList.contains(str));
        AppMethodBeat.o(68587);
      }
    }
  }

  private final Boolean zza(String paramString, zzkg paramzzkg)
  {
    Object localObject = null;
    AppMethodBeat.i(68590);
    if (!zzka.zzck(paramString))
    {
      AppMethodBeat.o(68590);
      paramString = localObject;
    }
    while (true)
    {
      return paramString;
      try
      {
        BigDecimal localBigDecimal = new java/math/BigDecimal;
        localBigDecimal.<init>(paramString);
        paramString = zza(localBigDecimal, paramzzkg, 0.0D);
        AppMethodBeat.o(68590);
      }
      catch (NumberFormatException paramString)
      {
        AppMethodBeat.o(68590);
        paramString = localObject;
      }
    }
  }

  @VisibleForTesting
  private final Boolean zza(String paramString, zzki paramzzki)
  {
    int i = 0;
    Object localObject = null;
    String str = null;
    AppMethodBeat.i(68586);
    Preconditions.checkNotNull(paramzzki);
    if (paramString == null)
    {
      AppMethodBeat.o(68586);
      paramString = str;
    }
    while (true)
    {
      return paramString;
      if ((paramzzki.zzash == null) || (paramzzki.zzash.intValue() == 0))
      {
        AppMethodBeat.o(68586);
        paramString = str;
      }
      else if (paramzzki.zzash.intValue() == 6)
      {
        if ((paramzzki.zzask != null) && (paramzzki.zzask.length != 0))
          break;
        AppMethodBeat.o(68586);
        paramString = str;
      }
      else
      {
        if (paramzzki.zzasi != null)
          break;
        AppMethodBeat.o(68586);
        paramString = str;
      }
    }
    int j = paramzzki.zzash.intValue();
    boolean bool;
    if ((paramzzki.zzasj != null) && (paramzzki.zzasj.booleanValue()))
    {
      bool = true;
      label145: if ((!bool) && (j != 1) && (j != 6))
        break label217;
      str = paramzzki.zzasi;
      label169: if (paramzzki.zzask != null)
        break label232;
    }
    label217: label232: String[] arrayOfString;
    for (paramzzki = null; ; paramzzki = Arrays.asList(arrayOfString))
    {
      if (j == 1)
        localObject = str;
      paramString = zza(paramString, j, bool, str, paramzzki, localObject);
      AppMethodBeat.o(68586);
      break;
      bool = false;
      break label145;
      str = paramzzki.zzasi.toUpperCase(Locale.ENGLISH);
      break label169;
      arrayOfString = paramzzki.zzask;
      if (!bool)
        break label252;
    }
    label252: ArrayList localArrayList = new ArrayList();
    int k = arrayOfString.length;
    while (true)
    {
      paramzzki = localArrayList;
      if (i >= k)
        break;
      localArrayList.add(arrayOfString[i].toUpperCase(Locale.ENGLISH));
      i++;
    }
  }

  @VisibleForTesting
  private static Boolean zza(BigDecimal paramBigDecimal, zzkg paramzzkg, double paramDouble)
  {
    boolean bool1 = true;
    boolean bool2 = true;
    boolean bool3 = true;
    boolean bool4 = true;
    boolean bool5 = true;
    AppMethodBeat.i(68591);
    Preconditions.checkNotNull(paramzzkg);
    if ((paramzzkg.zzarz == null) || (paramzzkg.zzarz.intValue() == 0))
    {
      AppMethodBeat.o(68591);
      paramBigDecimal = null;
    }
    BigDecimal localBigDecimal1;
    BigDecimal localBigDecimal3;
    while (true)
    {
      return paramBigDecimal;
      if (paramzzkg.zzarz.intValue() == 4)
      {
        if ((paramzzkg.zzasc == null) || (paramzzkg.zzasd == null))
        {
          AppMethodBeat.o(68591);
          paramBigDecimal = null;
        }
      }
      else if (paramzzkg.zzasb == null)
      {
        AppMethodBeat.o(68591);
        paramBigDecimal = null;
      }
      else
      {
        int i = paramzzkg.zzarz.intValue();
        if (paramzzkg.zzarz.intValue() == 4)
        {
          if ((!zzka.zzck(paramzzkg.zzasc)) || (!zzka.zzck(paramzzkg.zzasd)))
          {
            AppMethodBeat.o(68591);
            paramBigDecimal = null;
          }
        }
        else
        {
          while (true)
          {
            try
            {
              localBigDecimal1 = new java/math/BigDecimal;
              localBigDecimal1.<init>(paramzzkg.zzasc);
              BigDecimal localBigDecimal2 = new java/math/BigDecimal;
              localBigDecimal2.<init>(paramzzkg.zzasd);
              localBigDecimal3 = null;
              paramzzkg = localBigDecimal2;
              if (i != 4)
                break label271;
              if (localBigDecimal1 != null)
                break label276;
              AppMethodBeat.o(68591);
              paramBigDecimal = null;
            }
            catch (NumberFormatException paramBigDecimal)
            {
              AppMethodBeat.o(68591);
              paramBigDecimal = null;
            }
            break;
            if (!zzka.zzck(paramzzkg.zzasb))
            {
              AppMethodBeat.o(68591);
              paramBigDecimal = null;
              break;
            }
            try
            {
              localBigDecimal3 = new BigDecimal(paramzzkg.zzasb);
              paramzzkg = null;
              localBigDecimal1 = null;
            }
            catch (NumberFormatException paramBigDecimal)
            {
              AppMethodBeat.o(68591);
              paramBigDecimal = null;
            }
          }
          continue;
          label271: if (localBigDecimal3 != null);
          switch (i)
          {
          default:
            label276: AppMethodBeat.o(68591);
            paramBigDecimal = null;
          case 1:
          case 2:
          case 3:
          case 4:
          }
        }
      }
    }
    if (paramBigDecimal.compareTo(localBigDecimal3) == -1);
    while (true)
    {
      paramBigDecimal = Boolean.valueOf(bool5);
      AppMethodBeat.o(68591);
      break;
      bool5 = false;
    }
    if (paramBigDecimal.compareTo(localBigDecimal3) == 1);
    for (bool5 = bool1; ; bool5 = false)
    {
      paramBigDecimal = Boolean.valueOf(bool5);
      AppMethodBeat.o(68591);
      break;
    }
    if (paramDouble != 0.0D)
    {
      if ((paramBigDecimal.compareTo(localBigDecimal3.subtract(new BigDecimal(paramDouble).multiply(new BigDecimal(2)))) == 1) && (paramBigDecimal.compareTo(localBigDecimal3.add(new BigDecimal(paramDouble).multiply(new BigDecimal(2)))) == -1));
      for (bool5 = bool2; ; bool5 = false)
      {
        paramBigDecimal = Boolean.valueOf(bool5);
        AppMethodBeat.o(68591);
        break;
      }
    }
    if (paramBigDecimal.compareTo(localBigDecimal3) == 0);
    for (bool5 = bool3; ; bool5 = false)
    {
      paramBigDecimal = Boolean.valueOf(bool5);
      AppMethodBeat.o(68591);
      break;
    }
    if ((paramBigDecimal.compareTo(localBigDecimal1) != -1) && (paramBigDecimal.compareTo(paramzzkg) != 1));
    for (bool5 = bool4; ; bool5 = false)
    {
      paramBigDecimal = Boolean.valueOf(bool5);
      AppMethodBeat.o(68591);
      break;
    }
  }

  // ERROR //
  final zzkm[] zza(String paramString, zzkn[] paramArrayOfzzkn, zzks[] paramArrayOfzzks)
  {
    // Byte code:
    //   0: ldc 225
    //   2: invokestatic 20	com/tencent/matrix/trace/core/AppMethodBeat:i	(I)V
    //   5: aload_1
    //   6: invokestatic 229	com/google/android/gms/common/internal/Preconditions:checkNotEmpty	(Ljava/lang/String;)Ljava/lang/String;
    //   9: pop
    //   10: new 231	java/util/HashSet
    //   13: dup
    //   14: invokespecial 232	java/util/HashSet:<init>	()V
    //   17: astore 4
    //   19: new 234	android/support/v4/f/a
    //   22: dup
    //   23: invokespecial 235	android/support/v4/f/a:<init>	()V
    //   26: astore 5
    //   28: new 234	android/support/v4/f/a
    //   31: dup
    //   32: invokespecial 235	android/support/v4/f/a:<init>	()V
    //   35: astore 6
    //   37: new 234	android/support/v4/f/a
    //   40: dup
    //   41: invokespecial 235	android/support/v4/f/a:<init>	()V
    //   44: astore 7
    //   46: aload_0
    //   47: invokevirtual 241	com/google/android/gms/internal/measurement/zzjp:zzix	()Lcom/google/android/gms/internal/measurement/zzei;
    //   50: aload_1
    //   51: invokevirtual 247	com/google/android/gms/internal/measurement/zzei:zzbf	(Ljava/lang/String;)Ljava/util/Map;
    //   54: astore 8
    //   56: aload 8
    //   58: ifnull +316 -> 374
    //   61: aload 8
    //   63: invokeinterface 253 1 0
    //   68: invokeinterface 259 1 0
    //   73: astore 9
    //   75: aload 9
    //   77: invokeinterface 264 1 0
    //   82: ifeq +292 -> 374
    //   85: aload 9
    //   87: invokeinterface 268 1 0
    //   92: checkcast 158	java/lang/Integer
    //   95: invokevirtual 161	java/lang/Integer:intValue	()I
    //   98: istore 10
    //   100: aload 8
    //   102: iload 10
    //   104: invokestatic 271	java/lang/Integer:valueOf	(I)Ljava/lang/Integer;
    //   107: invokeinterface 274 2 0
    //   112: checkcast 276	com/google/android/gms/internal/measurement/zzkr
    //   115: astore 11
    //   117: aload 6
    //   119: iload 10
    //   121: invokestatic 271	java/lang/Integer:valueOf	(I)Ljava/lang/Integer;
    //   124: invokeinterface 274 2 0
    //   129: checkcast 278	java/util/BitSet
    //   132: astore 12
    //   134: aload 7
    //   136: iload 10
    //   138: invokestatic 271	java/lang/Integer:valueOf	(I)Ljava/lang/Integer;
    //   141: invokeinterface 274 2 0
    //   146: checkcast 278	java/util/BitSet
    //   149: astore 13
    //   151: aload 12
    //   153: astore 14
    //   155: aload 12
    //   157: ifnonnull +51 -> 208
    //   160: new 278	java/util/BitSet
    //   163: dup
    //   164: invokespecial 279	java/util/BitSet:<init>	()V
    //   167: astore 14
    //   169: aload 6
    //   171: iload 10
    //   173: invokestatic 271	java/lang/Integer:valueOf	(I)Ljava/lang/Integer;
    //   176: aload 14
    //   178: invokeinterface 283 3 0
    //   183: pop
    //   184: new 278	java/util/BitSet
    //   187: dup
    //   188: invokespecial 279	java/util/BitSet:<init>	()V
    //   191: astore 13
    //   193: aload 7
    //   195: iload 10
    //   197: invokestatic 271	java/lang/Integer:valueOf	(I)Ljava/lang/Integer;
    //   200: aload 13
    //   202: invokeinterface 283 3 0
    //   207: pop
    //   208: iconst_0
    //   209: istore 15
    //   211: iload 15
    //   213: aload 11
    //   215: getfield 287	com/google/android/gms/internal/measurement/zzkr:zzauk	[J
    //   218: arraylength
    //   219: bipush 6
    //   221: ishl
    //   222: if_icmpge +72 -> 294
    //   225: aload 11
    //   227: getfield 287	com/google/android/gms/internal/measurement/zzkr:zzauk	[J
    //   230: iload 15
    //   232: invokestatic 290	com/google/android/gms/internal/measurement/zzka:zza	([JI)Z
    //   235: ifeq +53 -> 288
    //   238: aload_0
    //   239: invokevirtual 99	com/google/android/gms/internal/measurement/zzhg:zzge	()Lcom/google/android/gms/internal/measurement/zzfg;
    //   242: invokevirtual 293	com/google/android/gms/internal/measurement/zzfg:zzit	()Lcom/google/android/gms/internal/measurement/zzfi;
    //   245: ldc_w 295
    //   248: iload 10
    //   250: invokestatic 271	java/lang/Integer:valueOf	(I)Ljava/lang/Integer;
    //   253: iload 15
    //   255: invokestatic 271	java/lang/Integer:valueOf	(I)Ljava/lang/Integer;
    //   258: invokevirtual 299	com/google/android/gms/internal/measurement/zzfi:zze	(Ljava/lang/String;Ljava/lang/Object;Ljava/lang/Object;)V
    //   261: aload 13
    //   263: iload 15
    //   265: invokevirtual 302	java/util/BitSet:set	(I)V
    //   268: aload 11
    //   270: getfield 305	com/google/android/gms/internal/measurement/zzkr:zzaul	[J
    //   273: iload 15
    //   275: invokestatic 290	com/google/android/gms/internal/measurement/zzka:zza	([JI)Z
    //   278: ifeq +10 -> 288
    //   281: aload 14
    //   283: iload 15
    //   285: invokevirtual 302	java/util/BitSet:set	(I)V
    //   288: iinc 15 1
    //   291: goto -80 -> 211
    //   294: new 307	com/google/android/gms/internal/measurement/zzkm
    //   297: dup
    //   298: invokespecial 308	com/google/android/gms/internal/measurement/zzkm:<init>	()V
    //   301: astore 12
    //   303: aload 5
    //   305: iload 10
    //   307: invokestatic 271	java/lang/Integer:valueOf	(I)Ljava/lang/Integer;
    //   310: aload 12
    //   312: invokeinterface 283 3 0
    //   317: pop
    //   318: aload 12
    //   320: getstatic 311	java/lang/Boolean:FALSE	Ljava/lang/Boolean;
    //   323: putfield 314	com/google/android/gms/internal/measurement/zzkm:zzasy	Ljava/lang/Boolean;
    //   326: aload 12
    //   328: aload 11
    //   330: putfield 318	com/google/android/gms/internal/measurement/zzkm:zzasx	Lcom/google/android/gms/internal/measurement/zzkr;
    //   333: aload 12
    //   335: new 276	com/google/android/gms/internal/measurement/zzkr
    //   338: dup
    //   339: invokespecial 319	com/google/android/gms/internal/measurement/zzkr:<init>	()V
    //   342: putfield 322	com/google/android/gms/internal/measurement/zzkm:zzasw	Lcom/google/android/gms/internal/measurement/zzkr;
    //   345: aload 12
    //   347: getfield 322	com/google/android/gms/internal/measurement/zzkm:zzasw	Lcom/google/android/gms/internal/measurement/zzkr;
    //   350: aload 14
    //   352: invokestatic 325	com/google/android/gms/internal/measurement/zzka:zza	(Ljava/util/BitSet;)[J
    //   355: putfield 305	com/google/android/gms/internal/measurement/zzkr:zzaul	[J
    //   358: aload 12
    //   360: getfield 322	com/google/android/gms/internal/measurement/zzkm:zzasw	Lcom/google/android/gms/internal/measurement/zzkr;
    //   363: aload 13
    //   365: invokestatic 325	com/google/android/gms/internal/measurement/zzka:zza	(Ljava/util/BitSet;)[J
    //   368: putfield 287	com/google/android/gms/internal/measurement/zzkr:zzauk	[J
    //   371: goto -296 -> 75
    //   374: aload_2
    //   375: ifnull +2335 -> 2710
    //   378: aconst_null
    //   379: astore 13
    //   381: lconst_0
    //   382: lstore 16
    //   384: aconst_null
    //   385: astore 12
    //   387: new 234	android/support/v4/f/a
    //   390: dup
    //   391: invokespecial 235	android/support/v4/f/a:<init>	()V
    //   394: astore 18
    //   396: aload_2
    //   397: arraylength
    //   398: istore 19
    //   400: iconst_0
    //   401: istore 10
    //   403: iload 10
    //   405: iload 19
    //   407: if_icmpge +2303 -> 2710
    //   410: aload_2
    //   411: iload 10
    //   413: aaload
    //   414: astore 11
    //   416: aload 11
    //   418: getfield 330	com/google/android/gms/internal/measurement/zzkn:name	Ljava/lang/String;
    //   421: astore 8
    //   423: aload 11
    //   425: getfield 334	com/google/android/gms/internal/measurement/zzkn:zzata	[Lcom/google/android/gms/internal/measurement/zzko;
    //   428: astore 14
    //   430: aload_0
    //   431: invokevirtual 338	com/google/android/gms/internal/measurement/zzhg:zzgg	()Lcom/google/android/gms/internal/measurement/zzef;
    //   434: aload_1
    //   435: getstatic 344	com/google/android/gms/internal/measurement/zzew:zzahv	Lcom/google/android/gms/internal/measurement/zzex;
    //   438: invokevirtual 350	com/google/android/gms/internal/measurement/zzef:zzd	(Ljava/lang/String;Lcom/google/android/gms/internal/measurement/zzex;)Z
    //   441: ifeq +3653 -> 4094
    //   444: aload_0
    //   445: invokevirtual 354	com/google/android/gms/internal/measurement/zzhg:zzgb	()Lcom/google/android/gms/internal/measurement/zzka;
    //   448: pop
    //   449: aload 11
    //   451: ldc_w 356
    //   454: invokestatic 360	com/google/android/gms/internal/measurement/zzka:zzb	(Lcom/google/android/gms/internal/measurement/zzkn;Ljava/lang/String;)Ljava/lang/Object;
    //   457: checkcast 362	java/lang/Long
    //   460: astore 9
    //   462: aload 9
    //   464: ifnull +77 -> 541
    //   467: iconst_1
    //   468: istore 15
    //   470: iload 15
    //   472: ifeq +75 -> 547
    //   475: aload 8
    //   477: ldc_w 364
    //   480: invokevirtual 128	java/lang/String:equals	(Ljava/lang/Object;)Z
    //   483: ifeq +64 -> 547
    //   486: iconst_1
    //   487: istore 20
    //   489: iload 20
    //   491: ifeq +712 -> 1203
    //   494: aload_0
    //   495: invokevirtual 354	com/google/android/gms/internal/measurement/zzhg:zzgb	()Lcom/google/android/gms/internal/measurement/zzka;
    //   498: pop
    //   499: aload 11
    //   501: ldc_w 366
    //   504: invokestatic 360	com/google/android/gms/internal/measurement/zzka:zzb	(Lcom/google/android/gms/internal/measurement/zzkn;Ljava/lang/String;)Ljava/lang/Object;
    //   507: checkcast 74	java/lang/String
    //   510: astore 8
    //   512: aload 8
    //   514: invokestatic 371	android/text/TextUtils:isEmpty	(Ljava/lang/CharSequence;)Z
    //   517: ifeq +36 -> 553
    //   520: aload_0
    //   521: invokevirtual 99	com/google/android/gms/internal/measurement/zzhg:zzge	()Lcom/google/android/gms/internal/measurement/zzfg;
    //   524: invokevirtual 374	com/google/android/gms/internal/measurement/zzfg:zzim	()Lcom/google/android/gms/internal/measurement/zzfi;
    //   527: ldc_w 376
    //   530: aload 9
    //   532: invokevirtual 113	com/google/android/gms/internal/measurement/zzfi:zzg	(Ljava/lang/String;Ljava/lang/Object;)V
    //   535: iinc 10 1
    //   538: goto -135 -> 403
    //   541: iconst_0
    //   542: istore 15
    //   544: goto -74 -> 470
    //   547: iconst_0
    //   548: istore 20
    //   550: goto -61 -> 489
    //   553: aload 13
    //   555: ifnull +22 -> 577
    //   558: aload 12
    //   560: ifnull +17 -> 577
    //   563: aload 9
    //   565: invokevirtual 380	java/lang/Long:longValue	()J
    //   568: aload 12
    //   570: invokevirtual 380	java/lang/Long:longValue	()J
    //   573: lcmp
    //   574: ifeq +3543 -> 4117
    //   577: aload_0
    //   578: invokevirtual 241	com/google/android/gms/internal/measurement/zzjp:zzix	()Lcom/google/android/gms/internal/measurement/zzei;
    //   581: aload_1
    //   582: aload 9
    //   584: invokevirtual 383	com/google/android/gms/internal/measurement/zzei:zza	(Ljava/lang/String;Ljava/lang/Long;)Landroid/util/Pair;
    //   587: astore 21
    //   589: aload 21
    //   591: ifnull +11 -> 602
    //   594: aload 21
    //   596: getfield 389	android/util/Pair:first	Ljava/lang/Object;
    //   599: ifnonnull +23 -> 622
    //   602: aload_0
    //   603: invokevirtual 99	com/google/android/gms/internal/measurement/zzhg:zzge	()Lcom/google/android/gms/internal/measurement/zzfg;
    //   606: invokevirtual 374	com/google/android/gms/internal/measurement/zzfg:zzim	()Lcom/google/android/gms/internal/measurement/zzfi;
    //   609: ldc_w 391
    //   612: aload 8
    //   614: aload 9
    //   616: invokevirtual 299	com/google/android/gms/internal/measurement/zzfi:zze	(Ljava/lang/String;Ljava/lang/Object;Ljava/lang/Object;)V
    //   619: goto -84 -> 535
    //   622: aload 21
    //   624: getfield 389	android/util/Pair:first	Ljava/lang/Object;
    //   627: checkcast 327	com/google/android/gms/internal/measurement/zzkn
    //   630: astore 13
    //   632: aload 21
    //   634: getfield 394	android/util/Pair:second	Ljava/lang/Object;
    //   637: checkcast 362	java/lang/Long
    //   640: invokevirtual 380	java/lang/Long:longValue	()J
    //   643: lstore 16
    //   645: aload_0
    //   646: invokevirtual 354	com/google/android/gms/internal/measurement/zzhg:zzgb	()Lcom/google/android/gms/internal/measurement/zzka;
    //   649: pop
    //   650: aload 13
    //   652: ldc_w 356
    //   655: invokestatic 360	com/google/android/gms/internal/measurement/zzka:zzb	(Lcom/google/android/gms/internal/measurement/zzkn;Ljava/lang/String;)Ljava/lang/Object;
    //   658: checkcast 362	java/lang/Long
    //   661: astore 12
    //   663: lload 16
    //   665: lconst_1
    //   666: lsub
    //   667: lstore 16
    //   669: lload 16
    //   671: lconst_0
    //   672: lcmp
    //   673: ifgt +157 -> 830
    //   676: aload_0
    //   677: invokevirtual 241	com/google/android/gms/internal/measurement/zzjp:zzix	()Lcom/google/android/gms/internal/measurement/zzei;
    //   680: astore 9
    //   682: aload 9
    //   684: invokevirtual 397	com/google/android/gms/internal/measurement/zzhg:zzab	()V
    //   687: aload 9
    //   689: invokevirtual 99	com/google/android/gms/internal/measurement/zzhg:zzge	()Lcom/google/android/gms/internal/measurement/zzfg;
    //   692: invokevirtual 293	com/google/android/gms/internal/measurement/zzfg:zzit	()Lcom/google/android/gms/internal/measurement/zzfi;
    //   695: ldc_w 399
    //   698: aload_1
    //   699: invokevirtual 113	com/google/android/gms/internal/measurement/zzfi:zzg	(Ljava/lang/String;Ljava/lang/Object;)V
    //   702: aload 9
    //   704: invokevirtual 403	com/google/android/gms/internal/measurement/zzei:getWritableDatabase	()Landroid/database/sqlite/SQLiteDatabase;
    //   707: ldc_w 405
    //   710: iconst_1
    //   711: anewarray 74	java/lang/String
    //   714: dup
    //   715: iconst_0
    //   716: aload_1
    //   717: aastore
    //   718: invokevirtual 411	android/database/sqlite/SQLiteDatabase:execSQL	(Ljava/lang/String;[Ljava/lang/Object;)V
    //   721: aload 13
    //   723: getfield 334	com/google/android/gms/internal/measurement/zzkn:zzata	[Lcom/google/android/gms/internal/measurement/zzko;
    //   726: arraylength
    //   727: aload 14
    //   729: arraylength
    //   730: iadd
    //   731: anewarray 413	com/google/android/gms/internal/measurement/zzko
    //   734: astore 9
    //   736: iconst_0
    //   737: istore 15
    //   739: aload 13
    //   741: getfield 334	com/google/android/gms/internal/measurement/zzkn:zzata	[Lcom/google/android/gms/internal/measurement/zzko;
    //   744: astore 21
    //   746: aload 21
    //   748: arraylength
    //   749: istore 22
    //   751: iconst_0
    //   752: istore 20
    //   754: iload 20
    //   756: iload 22
    //   758: if_icmpge +90 -> 848
    //   761: aload 21
    //   763: iload 20
    //   765: aaload
    //   766: astore 23
    //   768: aload_0
    //   769: invokevirtual 354	com/google/android/gms/internal/measurement/zzhg:zzgb	()Lcom/google/android/gms/internal/measurement/zzka;
    //   772: pop
    //   773: aload 11
    //   775: aload 23
    //   777: getfield 414	com/google/android/gms/internal/measurement/zzko:name	Ljava/lang/String;
    //   780: invokestatic 417	com/google/android/gms/internal/measurement/zzka:zza	(Lcom/google/android/gms/internal/measurement/zzkn;Ljava/lang/String;)Lcom/google/android/gms/internal/measurement/zzko;
    //   783: ifnonnull +3358 -> 4141
    //   786: iload 15
    //   788: iconst_1
    //   789: iadd
    //   790: istore 24
    //   792: aload 9
    //   794: iload 15
    //   796: aload 23
    //   798: aastore
    //   799: iload 24
    //   801: istore 15
    //   803: iinc 20 1
    //   806: goto -52 -> 754
    //   809: astore 21
    //   811: aload 9
    //   813: invokevirtual 99	com/google/android/gms/internal/measurement/zzhg:zzge	()Lcom/google/android/gms/internal/measurement/zzfg;
    //   816: invokevirtual 374	com/google/android/gms/internal/measurement/zzfg:zzim	()Lcom/google/android/gms/internal/measurement/zzfi;
    //   819: ldc_w 419
    //   822: aload 21
    //   824: invokevirtual 113	com/google/android/gms/internal/measurement/zzfi:zzg	(Ljava/lang/String;Ljava/lang/Object;)V
    //   827: goto -106 -> 721
    //   830: aload_0
    //   831: invokevirtual 241	com/google/android/gms/internal/measurement/zzjp:zzix	()Lcom/google/android/gms/internal/measurement/zzei;
    //   834: aload_1
    //   835: aload 9
    //   837: lload 16
    //   839: aload 13
    //   841: invokevirtual 422	com/google/android/gms/internal/measurement/zzei:zza	(Ljava/lang/String;Ljava/lang/Long;JLcom/google/android/gms/internal/measurement/zzkn;)Z
    //   844: pop
    //   845: goto -124 -> 721
    //   848: iload 15
    //   850: ifle +315 -> 1165
    //   853: aload 14
    //   855: arraylength
    //   856: istore 24
    //   858: iconst_0
    //   859: istore 20
    //   861: iload 20
    //   863: iload 24
    //   865: if_icmpge +22 -> 887
    //   868: aload 9
    //   870: iload 15
    //   872: aload 14
    //   874: iload 20
    //   876: aaload
    //   877: aastore
    //   878: iinc 20 1
    //   881: iinc 15 1
    //   884: goto -23 -> 861
    //   887: iload 15
    //   889: aload 9
    //   891: arraylength
    //   892: if_icmpne +258 -> 1150
    //   895: aload 9
    //   897: astore 14
    //   899: aload 12
    //   901: astore 9
    //   903: aload 13
    //   905: astore 12
    //   907: aload 9
    //   909: astore 13
    //   911: aload 8
    //   913: astore 9
    //   915: aload 14
    //   917: astore 8
    //   919: aload_0
    //   920: invokevirtual 241	com/google/android/gms/internal/measurement/zzjp:zzix	()Lcom/google/android/gms/internal/measurement/zzei;
    //   923: aload_1
    //   924: aload 11
    //   926: getfield 330	com/google/android/gms/internal/measurement/zzkn:name	Ljava/lang/String;
    //   929: invokevirtual 426	com/google/android/gms/internal/measurement/zzei:zzf	(Ljava/lang/String;Ljava/lang/String;)Lcom/google/android/gms/internal/measurement/zzeq;
    //   932: astore 14
    //   934: aload 14
    //   936: ifnonnull +402 -> 1338
    //   939: aload_0
    //   940: invokevirtual 99	com/google/android/gms/internal/measurement/zzhg:zzge	()Lcom/google/android/gms/internal/measurement/zzfg;
    //   943: invokevirtual 105	com/google/android/gms/internal/measurement/zzfg:zzip	()Lcom/google/android/gms/internal/measurement/zzfi;
    //   946: ldc_w 428
    //   949: aload_1
    //   950: invokestatic 432	com/google/android/gms/internal/measurement/zzfg:zzbm	(Ljava/lang/String;)Ljava/lang/Object;
    //   953: aload_0
    //   954: invokevirtual 436	com/google/android/gms/internal/measurement/zzhg:zzga	()Lcom/google/android/gms/internal/measurement/zzfe;
    //   957: aload 9
    //   959: invokevirtual 441	com/google/android/gms/internal/measurement/zzfe:zzbj	(Ljava/lang/String;)Ljava/lang/String;
    //   962: invokevirtual 299	com/google/android/gms/internal/measurement/zzfi:zze	(Ljava/lang/String;Ljava/lang/Object;Ljava/lang/Object;)V
    //   965: new 443	com/google/android/gms/internal/measurement/zzeq
    //   968: dup
    //   969: aload_1
    //   970: aload 11
    //   972: getfield 330	com/google/android/gms/internal/measurement/zzkn:name	Ljava/lang/String;
    //   975: lconst_1
    //   976: lconst_1
    //   977: aload 11
    //   979: getfield 447	com/google/android/gms/internal/measurement/zzkn:zzatb	Ljava/lang/Long;
    //   982: invokevirtual 380	java/lang/Long:longValue	()J
    //   985: lconst_0
    //   986: aconst_null
    //   987: aconst_null
    //   988: aconst_null
    //   989: invokespecial 450	com/google/android/gms/internal/measurement/zzeq:<init>	(Ljava/lang/String;Ljava/lang/String;JJJJLjava/lang/Long;Ljava/lang/Long;Ljava/lang/Boolean;)V
    //   992: astore 14
    //   994: aload_0
    //   995: invokevirtual 241	com/google/android/gms/internal/measurement/zzjp:zzix	()Lcom/google/android/gms/internal/measurement/zzei;
    //   998: aload 14
    //   1000: invokevirtual 453	com/google/android/gms/internal/measurement/zzei:zza	(Lcom/google/android/gms/internal/measurement/zzeq;)V
    //   1003: aload 14
    //   1005: getfield 457	com/google/android/gms/internal/measurement/zzeq:zzafr	J
    //   1008: lstore 25
    //   1010: aload 18
    //   1012: aload 9
    //   1014: invokeinterface 274 2 0
    //   1019: checkcast 249	java/util/Map
    //   1022: astore 11
    //   1024: aload 11
    //   1026: ifnonnull +3112 -> 4138
    //   1029: aload_0
    //   1030: invokevirtual 241	com/google/android/gms/internal/measurement/zzjp:zzix	()Lcom/google/android/gms/internal/measurement/zzei;
    //   1033: aload_1
    //   1034: aload 9
    //   1036: invokevirtual 461	com/google/android/gms/internal/measurement/zzei:zzk	(Ljava/lang/String;Ljava/lang/String;)Ljava/util/Map;
    //   1039: astore 11
    //   1041: aload 11
    //   1043: astore 14
    //   1045: aload 11
    //   1047: ifnonnull +12 -> 1059
    //   1050: new 234	android/support/v4/f/a
    //   1053: dup
    //   1054: invokespecial 235	android/support/v4/f/a:<init>	()V
    //   1057: astore 14
    //   1059: aload 18
    //   1061: aload 9
    //   1063: aload 14
    //   1065: invokeinterface 283 3 0
    //   1070: pop
    //   1071: aload 14
    //   1073: astore 11
    //   1075: aload 11
    //   1077: invokeinterface 253 1 0
    //   1082: invokeinterface 259 1 0
    //   1087: astore 27
    //   1089: aload 27
    //   1091: invokeinterface 264 1 0
    //   1096: ifeq +3027 -> 4123
    //   1099: aload 27
    //   1101: invokeinterface 268 1 0
    //   1106: checkcast 158	java/lang/Integer
    //   1109: invokevirtual 161	java/lang/Integer:intValue	()I
    //   1112: istore 24
    //   1114: aload 4
    //   1116: iload 24
    //   1118: invokestatic 271	java/lang/Integer:valueOf	(I)Ljava/lang/Integer;
    //   1121: invokeinterface 462 2 0
    //   1126: ifeq +222 -> 1348
    //   1129: aload_0
    //   1130: invokevirtual 99	com/google/android/gms/internal/measurement/zzhg:zzge	()Lcom/google/android/gms/internal/measurement/zzfg;
    //   1133: invokevirtual 293	com/google/android/gms/internal/measurement/zzfg:zzit	()Lcom/google/android/gms/internal/measurement/zzfi;
    //   1136: ldc_w 464
    //   1139: iload 24
    //   1141: invokestatic 271	java/lang/Integer:valueOf	(I)Ljava/lang/Integer;
    //   1144: invokevirtual 113	com/google/android/gms/internal/measurement/zzfi:zzg	(Ljava/lang/String;Ljava/lang/Object;)V
    //   1147: goto -58 -> 1089
    //   1150: aload 9
    //   1152: iload 15
    //   1154: invokestatic 468	java/util/Arrays:copyOf	([Ljava/lang/Object;I)[Ljava/lang/Object;
    //   1157: checkcast 469	[Lcom/google/android/gms/internal/measurement/zzko;
    //   1160: astore 14
    //   1162: goto -263 -> 899
    //   1165: aload_0
    //   1166: invokevirtual 99	com/google/android/gms/internal/measurement/zzhg:zzge	()Lcom/google/android/gms/internal/measurement/zzfg;
    //   1169: invokevirtual 105	com/google/android/gms/internal/measurement/zzfg:zzip	()Lcom/google/android/gms/internal/measurement/zzfi;
    //   1172: ldc_w 471
    //   1175: aload 8
    //   1177: invokevirtual 113	com/google/android/gms/internal/measurement/zzfi:zzg	(Ljava/lang/String;Ljava/lang/Object;)V
    //   1180: aload 8
    //   1182: astore 9
    //   1184: aload 12
    //   1186: astore 21
    //   1188: aload 13
    //   1190: astore 12
    //   1192: aload 14
    //   1194: astore 8
    //   1196: aload 21
    //   1198: astore 13
    //   1200: goto -281 -> 919
    //   1203: iload 15
    //   1205: ifeq +2889 -> 4094
    //   1208: aload_0
    //   1209: invokevirtual 354	com/google/android/gms/internal/measurement/zzhg:zzgb	()Lcom/google/android/gms/internal/measurement/zzka;
    //   1212: pop
    //   1213: lconst_0
    //   1214: invokestatic 474	java/lang/Long:valueOf	(J)Ljava/lang/Long;
    //   1217: astore 13
    //   1219: aload 11
    //   1221: ldc_w 476
    //   1224: invokestatic 360	com/google/android/gms/internal/measurement/zzka:zzb	(Lcom/google/android/gms/internal/measurement/zzkn;Ljava/lang/String;)Ljava/lang/Object;
    //   1227: astore 12
    //   1229: aload 12
    //   1231: ifnonnull +58 -> 1289
    //   1234: aload 13
    //   1236: checkcast 362	java/lang/Long
    //   1239: invokevirtual 380	java/lang/Long:longValue	()J
    //   1242: lstore 16
    //   1244: lload 16
    //   1246: lconst_0
    //   1247: lcmp
    //   1248: ifgt +48 -> 1296
    //   1251: aload_0
    //   1252: invokevirtual 99	com/google/android/gms/internal/measurement/zzhg:zzge	()Lcom/google/android/gms/internal/measurement/zzfg;
    //   1255: invokevirtual 105	com/google/android/gms/internal/measurement/zzfg:zzip	()Lcom/google/android/gms/internal/measurement/zzfi;
    //   1258: ldc_w 478
    //   1261: aload 8
    //   1263: invokevirtual 113	com/google/android/gms/internal/measurement/zzfi:zzg	(Ljava/lang/String;Ljava/lang/Object;)V
    //   1266: aload 8
    //   1268: astore 21
    //   1270: aload 9
    //   1272: astore 13
    //   1274: aload 11
    //   1276: astore 12
    //   1278: aload 14
    //   1280: astore 8
    //   1282: aload 21
    //   1284: astore 9
    //   1286: goto -367 -> 919
    //   1289: aload 12
    //   1291: astore 13
    //   1293: goto -59 -> 1234
    //   1296: aload_0
    //   1297: invokevirtual 241	com/google/android/gms/internal/measurement/zzjp:zzix	()Lcom/google/android/gms/internal/measurement/zzei;
    //   1300: aload_1
    //   1301: aload 9
    //   1303: lload 16
    //   1305: aload 11
    //   1307: invokevirtual 422	com/google/android/gms/internal/measurement/zzei:zza	(Ljava/lang/String;Ljava/lang/Long;JLcom/google/android/gms/internal/measurement/zzkn;)Z
    //   1310: pop
    //   1311: aload 14
    //   1313: astore 21
    //   1315: aload 8
    //   1317: astore 14
    //   1319: aload 9
    //   1321: astore 13
    //   1323: aload 11
    //   1325: astore 12
    //   1327: aload 21
    //   1329: astore 8
    //   1331: aload 14
    //   1333: astore 9
    //   1335: goto -416 -> 919
    //   1338: aload 14
    //   1340: invokevirtual 482	com/google/android/gms/internal/measurement/zzeq:zzie	()Lcom/google/android/gms/internal/measurement/zzeq;
    //   1343: astore 14
    //   1345: goto -351 -> 994
    //   1348: aload 5
    //   1350: iload 24
    //   1352: invokestatic 271	java/lang/Integer:valueOf	(I)Ljava/lang/Integer;
    //   1355: invokeinterface 274 2 0
    //   1360: checkcast 307	com/google/android/gms/internal/measurement/zzkm
    //   1363: astore 14
    //   1365: aload 6
    //   1367: iload 24
    //   1369: invokestatic 271	java/lang/Integer:valueOf	(I)Ljava/lang/Integer;
    //   1372: invokeinterface 274 2 0
    //   1377: checkcast 278	java/util/BitSet
    //   1380: astore 21
    //   1382: aload 7
    //   1384: iload 24
    //   1386: invokestatic 271	java/lang/Integer:valueOf	(I)Ljava/lang/Integer;
    //   1389: invokeinterface 274 2 0
    //   1394: checkcast 278	java/util/BitSet
    //   1397: astore 23
    //   1399: aload 14
    //   1401: ifnonnull +2719 -> 4120
    //   1404: new 307	com/google/android/gms/internal/measurement/zzkm
    //   1407: dup
    //   1408: invokespecial 308	com/google/android/gms/internal/measurement/zzkm:<init>	()V
    //   1411: astore 14
    //   1413: aload 5
    //   1415: iload 24
    //   1417: invokestatic 271	java/lang/Integer:valueOf	(I)Ljava/lang/Integer;
    //   1420: aload 14
    //   1422: invokeinterface 283 3 0
    //   1427: pop
    //   1428: aload 14
    //   1430: getstatic 485	java/lang/Boolean:TRUE	Ljava/lang/Boolean;
    //   1433: putfield 314	com/google/android/gms/internal/measurement/zzkm:zzasy	Ljava/lang/Boolean;
    //   1436: new 278	java/util/BitSet
    //   1439: dup
    //   1440: invokespecial 279	java/util/BitSet:<init>	()V
    //   1443: astore 21
    //   1445: aload 6
    //   1447: iload 24
    //   1449: invokestatic 271	java/lang/Integer:valueOf	(I)Ljava/lang/Integer;
    //   1452: aload 21
    //   1454: invokeinterface 283 3 0
    //   1459: pop
    //   1460: new 278	java/util/BitSet
    //   1463: dup
    //   1464: invokespecial 279	java/util/BitSet:<init>	()V
    //   1467: astore 23
    //   1469: aload 7
    //   1471: iload 24
    //   1473: invokestatic 271	java/lang/Integer:valueOf	(I)Ljava/lang/Integer;
    //   1476: aload 23
    //   1478: invokeinterface 283 3 0
    //   1483: pop
    //   1484: aload 11
    //   1486: iload 24
    //   1488: invokestatic 271	java/lang/Integer:valueOf	(I)Ljava/lang/Integer;
    //   1491: invokeinterface 274 2 0
    //   1496: checkcast 62	java/util/List
    //   1499: invokeinterface 486 1 0
    //   1504: astore 28
    //   1506: aload 28
    //   1508: invokeinterface 264 1 0
    //   1513: ifeq -424 -> 1089
    //   1516: aload 28
    //   1518: invokeinterface 268 1 0
    //   1523: checkcast 488	com/google/android/gms/internal/measurement/zzke
    //   1526: astore 29
    //   1528: aload_0
    //   1529: invokevirtual 99	com/google/android/gms/internal/measurement/zzhg:zzge	()Lcom/google/android/gms/internal/measurement/zzfg;
    //   1532: iconst_2
    //   1533: invokevirtual 492	com/google/android/gms/internal/measurement/zzfg:isLoggable	(I)Z
    //   1536: ifeq +60 -> 1596
    //   1539: aload_0
    //   1540: invokevirtual 99	com/google/android/gms/internal/measurement/zzhg:zzge	()Lcom/google/android/gms/internal/measurement/zzfg;
    //   1543: invokevirtual 293	com/google/android/gms/internal/measurement/zzfg:zzit	()Lcom/google/android/gms/internal/measurement/zzfi;
    //   1546: ldc_w 494
    //   1549: iload 24
    //   1551: invokestatic 271	java/lang/Integer:valueOf	(I)Ljava/lang/Integer;
    //   1554: aload 29
    //   1556: getfield 497	com/google/android/gms/internal/measurement/zzke:zzarp	Ljava/lang/Integer;
    //   1559: aload_0
    //   1560: invokevirtual 436	com/google/android/gms/internal/measurement/zzhg:zzga	()Lcom/google/android/gms/internal/measurement/zzfe;
    //   1563: aload 29
    //   1565: getfield 500	com/google/android/gms/internal/measurement/zzke:zzarq	Ljava/lang/String;
    //   1568: invokevirtual 441	com/google/android/gms/internal/measurement/zzfe:zzbj	(Ljava/lang/String;)Ljava/lang/String;
    //   1571: invokevirtual 503	com/google/android/gms/internal/measurement/zzfi:zzd	(Ljava/lang/String;Ljava/lang/Object;Ljava/lang/Object;Ljava/lang/Object;)V
    //   1574: aload_0
    //   1575: invokevirtual 99	com/google/android/gms/internal/measurement/zzhg:zzge	()Lcom/google/android/gms/internal/measurement/zzfg;
    //   1578: invokevirtual 293	com/google/android/gms/internal/measurement/zzfg:zzit	()Lcom/google/android/gms/internal/measurement/zzfi;
    //   1581: ldc_w 505
    //   1584: aload_0
    //   1585: invokevirtual 436	com/google/android/gms/internal/measurement/zzhg:zzga	()Lcom/google/android/gms/internal/measurement/zzfe;
    //   1588: aload 29
    //   1590: invokevirtual 508	com/google/android/gms/internal/measurement/zzfe:zza	(Lcom/google/android/gms/internal/measurement/zzke;)Ljava/lang/String;
    //   1593: invokevirtual 113	com/google/android/gms/internal/measurement/zzfi:zzg	(Ljava/lang/String;Ljava/lang/Object;)V
    //   1596: aload 29
    //   1598: getfield 497	com/google/android/gms/internal/measurement/zzke:zzarp	Ljava/lang/Integer;
    //   1601: ifnull +17 -> 1618
    //   1604: aload 29
    //   1606: getfield 497	com/google/android/gms/internal/measurement/zzke:zzarp	Ljava/lang/Integer;
    //   1609: invokevirtual 161	java/lang/Integer:intValue	()I
    //   1612: sipush 256
    //   1615: if_icmple +31 -> 1646
    //   1618: aload_0
    //   1619: invokevirtual 99	com/google/android/gms/internal/measurement/zzhg:zzge	()Lcom/google/android/gms/internal/measurement/zzfg;
    //   1622: invokevirtual 105	com/google/android/gms/internal/measurement/zzfg:zzip	()Lcom/google/android/gms/internal/measurement/zzfi;
    //   1625: ldc_w 510
    //   1628: aload_1
    //   1629: invokestatic 432	com/google/android/gms/internal/measurement/zzfg:zzbm	(Ljava/lang/String;)Ljava/lang/Object;
    //   1632: aload 29
    //   1634: getfield 497	com/google/android/gms/internal/measurement/zzke:zzarp	Ljava/lang/Integer;
    //   1637: invokestatic 513	java/lang/String:valueOf	(Ljava/lang/Object;)Ljava/lang/String;
    //   1640: invokevirtual 299	com/google/android/gms/internal/measurement/zzfi:zze	(Ljava/lang/String;Ljava/lang/Object;Ljava/lang/Object;)V
    //   1643: goto -137 -> 1506
    //   1646: aload 21
    //   1648: aload 29
    //   1650: getfield 497	com/google/android/gms/internal/measurement/zzke:zzarp	Ljava/lang/Integer;
    //   1653: invokevirtual 161	java/lang/Integer:intValue	()I
    //   1656: invokevirtual 515	java/util/BitSet:get	(I)Z
    //   1659: ifeq +29 -> 1688
    //   1662: aload_0
    //   1663: invokevirtual 99	com/google/android/gms/internal/measurement/zzhg:zzge	()Lcom/google/android/gms/internal/measurement/zzfg;
    //   1666: invokevirtual 293	com/google/android/gms/internal/measurement/zzfg:zzit	()Lcom/google/android/gms/internal/measurement/zzfi;
    //   1669: ldc_w 517
    //   1672: iload 24
    //   1674: invokestatic 271	java/lang/Integer:valueOf	(I)Ljava/lang/Integer;
    //   1677: aload 29
    //   1679: getfield 497	com/google/android/gms/internal/measurement/zzke:zzarp	Ljava/lang/Integer;
    //   1682: invokevirtual 299	com/google/android/gms/internal/measurement/zzfi:zze	(Ljava/lang/String;Ljava/lang/Object;Ljava/lang/Object;)V
    //   1685: goto -179 -> 1506
    //   1688: aload 29
    //   1690: getfield 521	com/google/android/gms/internal/measurement/zzke:zzart	Lcom/google/android/gms/internal/measurement/zzkg;
    //   1693: ifnull +90 -> 1783
    //   1696: aload_0
    //   1697: lload 25
    //   1699: aload 29
    //   1701: getfield 521	com/google/android/gms/internal/measurement/zzke:zzart	Lcom/google/android/gms/internal/measurement/zzkg;
    //   1704: invokespecial 523	com/google/android/gms/internal/measurement/zzeb:zza	(JLcom/google/android/gms/internal/measurement/zzkg;)Ljava/lang/Boolean;
    //   1707: astore 14
    //   1709: aload 14
    //   1711: ifnonnull +56 -> 1767
    //   1714: aconst_null
    //   1715: astore 14
    //   1717: aload_0
    //   1718: invokevirtual 99	com/google/android/gms/internal/measurement/zzhg:zzge	()Lcom/google/android/gms/internal/measurement/zzfg;
    //   1721: invokevirtual 293	com/google/android/gms/internal/measurement/zzfg:zzit	()Lcom/google/android/gms/internal/measurement/zzfi;
    //   1724: astore 30
    //   1726: aload 14
    //   1728: ifnonnull +938 -> 2666
    //   1731: ldc_w 525
    //   1734: astore 31
    //   1736: aload 30
    //   1738: ldc_w 527
    //   1741: aload 31
    //   1743: invokevirtual 113	com/google/android/gms/internal/measurement/zzfi:zzg	(Ljava/lang/String;Ljava/lang/Object;)V
    //   1746: aload 14
    //   1748: ifnonnull +925 -> 2673
    //   1751: aload 4
    //   1753: iload 24
    //   1755: invokestatic 271	java/lang/Integer:valueOf	(I)Ljava/lang/Integer;
    //   1758: invokeinterface 528 2 0
    //   1763: pop
    //   1764: goto -258 -> 1506
    //   1767: aload 14
    //   1769: invokevirtual 51	java/lang/Boolean:booleanValue	()Z
    //   1772: ifne +11 -> 1783
    //   1775: getstatic 311	java/lang/Boolean:FALSE	Ljava/lang/Boolean;
    //   1778: astore 14
    //   1780: goto -63 -> 1717
    //   1783: new 231	java/util/HashSet
    //   1786: dup
    //   1787: invokespecial 232	java/util/HashSet:<init>	()V
    //   1790: astore 14
    //   1792: aload 29
    //   1794: getfield 532	com/google/android/gms/internal/measurement/zzke:zzarr	[Lcom/google/android/gms/internal/measurement/zzkf;
    //   1797: astore 31
    //   1799: aload 31
    //   1801: arraylength
    //   1802: istore 20
    //   1804: iconst_0
    //   1805: istore 15
    //   1807: iload 15
    //   1809: iload 20
    //   1811: if_icmpge +68 -> 1879
    //   1814: aload 31
    //   1816: iload 15
    //   1818: aaload
    //   1819: astore 30
    //   1821: aload 30
    //   1823: getfield 537	com/google/android/gms/internal/measurement/zzkf:zzary	Ljava/lang/String;
    //   1826: invokestatic 371	android/text/TextUtils:isEmpty	(Ljava/lang/CharSequence;)Z
    //   1829: ifeq +31 -> 1860
    //   1832: aload_0
    //   1833: invokevirtual 99	com/google/android/gms/internal/measurement/zzhg:zzge	()Lcom/google/android/gms/internal/measurement/zzfg;
    //   1836: invokevirtual 105	com/google/android/gms/internal/measurement/zzfg:zzip	()Lcom/google/android/gms/internal/measurement/zzfi;
    //   1839: ldc_w 539
    //   1842: aload_0
    //   1843: invokevirtual 436	com/google/android/gms/internal/measurement/zzhg:zzga	()Lcom/google/android/gms/internal/measurement/zzfe;
    //   1846: aload 9
    //   1848: invokevirtual 441	com/google/android/gms/internal/measurement/zzfe:zzbj	(Ljava/lang/String;)Ljava/lang/String;
    //   1851: invokevirtual 113	com/google/android/gms/internal/measurement/zzfi:zzg	(Ljava/lang/String;Ljava/lang/Object;)V
    //   1854: aconst_null
    //   1855: astore 14
    //   1857: goto -140 -> 1717
    //   1860: aload 14
    //   1862: aload 30
    //   1864: getfield 537	com/google/android/gms/internal/measurement/zzkf:zzary	Ljava/lang/String;
    //   1867: invokeinterface 528 2 0
    //   1872: pop
    //   1873: iinc 15 1
    //   1876: goto -69 -> 1807
    //   1879: new 234	android/support/v4/f/a
    //   1882: dup
    //   1883: invokespecial 235	android/support/v4/f/a:<init>	()V
    //   1886: astore 31
    //   1888: aload 8
    //   1890: arraylength
    //   1891: istore 20
    //   1893: iconst_0
    //   1894: istore 15
    //   1896: iload 15
    //   1898: iload 20
    //   1900: if_icmpge +155 -> 2055
    //   1903: aload 8
    //   1905: iload 15
    //   1907: aaload
    //   1908: astore 30
    //   1910: aload 14
    //   1912: aload 30
    //   1914: getfield 414	com/google/android/gms/internal/measurement/zzko:name	Ljava/lang/String;
    //   1917: invokeinterface 462 2 0
    //   1922: ifeq +29 -> 1951
    //   1925: aload 30
    //   1927: getfield 542	com/google/android/gms/internal/measurement/zzko:zzate	Ljava/lang/Long;
    //   1930: ifnull +27 -> 1957
    //   1933: aload 31
    //   1935: aload 30
    //   1937: getfield 414	com/google/android/gms/internal/measurement/zzko:name	Ljava/lang/String;
    //   1940: aload 30
    //   1942: getfield 542	com/google/android/gms/internal/measurement/zzko:zzate	Ljava/lang/Long;
    //   1945: invokeinterface 283 3 0
    //   1950: pop
    //   1951: iinc 15 1
    //   1954: goto -58 -> 1896
    //   1957: aload 30
    //   1959: getfield 546	com/google/android/gms/internal/measurement/zzko:zzarc	Ljava/lang/Double;
    //   1962: ifnull +24 -> 1986
    //   1965: aload 31
    //   1967: aload 30
    //   1969: getfield 414	com/google/android/gms/internal/measurement/zzko:name	Ljava/lang/String;
    //   1972: aload 30
    //   1974: getfield 546	com/google/android/gms/internal/measurement/zzko:zzarc	Ljava/lang/Double;
    //   1977: invokeinterface 283 3 0
    //   1982: pop
    //   1983: goto -32 -> 1951
    //   1986: aload 30
    //   1988: getfield 549	com/google/android/gms/internal/measurement/zzko:zzajf	Ljava/lang/String;
    //   1991: ifnull +24 -> 2015
    //   1994: aload 31
    //   1996: aload 30
    //   1998: getfield 414	com/google/android/gms/internal/measurement/zzko:name	Ljava/lang/String;
    //   2001: aload 30
    //   2003: getfield 549	com/google/android/gms/internal/measurement/zzko:zzajf	Ljava/lang/String;
    //   2006: invokeinterface 283 3 0
    //   2011: pop
    //   2012: goto -61 -> 1951
    //   2015: aload_0
    //   2016: invokevirtual 99	com/google/android/gms/internal/measurement/zzhg:zzge	()Lcom/google/android/gms/internal/measurement/zzfg;
    //   2019: invokevirtual 105	com/google/android/gms/internal/measurement/zzfg:zzip	()Lcom/google/android/gms/internal/measurement/zzfi;
    //   2022: ldc_w 551
    //   2025: aload_0
    //   2026: invokevirtual 436	com/google/android/gms/internal/measurement/zzhg:zzga	()Lcom/google/android/gms/internal/measurement/zzfe;
    //   2029: aload 9
    //   2031: invokevirtual 441	com/google/android/gms/internal/measurement/zzfe:zzbj	(Ljava/lang/String;)Ljava/lang/String;
    //   2034: aload_0
    //   2035: invokevirtual 436	com/google/android/gms/internal/measurement/zzhg:zzga	()Lcom/google/android/gms/internal/measurement/zzfe;
    //   2038: aload 30
    //   2040: getfield 414	com/google/android/gms/internal/measurement/zzko:name	Ljava/lang/String;
    //   2043: invokevirtual 554	com/google/android/gms/internal/measurement/zzfe:zzbk	(Ljava/lang/String;)Ljava/lang/String;
    //   2046: invokevirtual 299	com/google/android/gms/internal/measurement/zzfi:zze	(Ljava/lang/String;Ljava/lang/Object;Ljava/lang/Object;)V
    //   2049: aconst_null
    //   2050: astore 14
    //   2052: goto -335 -> 1717
    //   2055: aload 29
    //   2057: getfield 532	com/google/android/gms/internal/measurement/zzke:zzarr	[Lcom/google/android/gms/internal/measurement/zzkf;
    //   2060: astore 30
    //   2062: aload 30
    //   2064: arraylength
    //   2065: istore 22
    //   2067: iconst_0
    //   2068: istore 15
    //   2070: iload 15
    //   2072: iload 22
    //   2074: if_icmpge +584 -> 2658
    //   2077: aload 30
    //   2079: iload 15
    //   2081: aaload
    //   2082: astore 14
    //   2084: getstatic 485	java/lang/Boolean:TRUE	Ljava/lang/Boolean;
    //   2087: aload 14
    //   2089: getfield 557	com/google/android/gms/internal/measurement/zzkf:zzarx	Ljava/lang/Boolean;
    //   2092: invokevirtual 558	java/lang/Boolean:equals	(Ljava/lang/Object;)Z
    //   2095: istore 32
    //   2097: aload 14
    //   2099: getfield 537	com/google/android/gms/internal/measurement/zzkf:zzary	Ljava/lang/String;
    //   2102: astore 33
    //   2104: aload 33
    //   2106: invokestatic 371	android/text/TextUtils:isEmpty	(Ljava/lang/CharSequence;)Z
    //   2109: ifeq +31 -> 2140
    //   2112: aload_0
    //   2113: invokevirtual 99	com/google/android/gms/internal/measurement/zzhg:zzge	()Lcom/google/android/gms/internal/measurement/zzfg;
    //   2116: invokevirtual 105	com/google/android/gms/internal/measurement/zzfg:zzip	()Lcom/google/android/gms/internal/measurement/zzfi;
    //   2119: ldc_w 560
    //   2122: aload_0
    //   2123: invokevirtual 436	com/google/android/gms/internal/measurement/zzhg:zzga	()Lcom/google/android/gms/internal/measurement/zzfe;
    //   2126: aload 9
    //   2128: invokevirtual 441	com/google/android/gms/internal/measurement/zzfe:zzbj	(Ljava/lang/String;)Ljava/lang/String;
    //   2131: invokevirtual 113	com/google/android/gms/internal/measurement/zzfi:zzg	(Ljava/lang/String;Ljava/lang/Object;)V
    //   2134: aconst_null
    //   2135: astore 14
    //   2137: goto -420 -> 1717
    //   2140: aload 31
    //   2142: aload 33
    //   2144: invokeinterface 274 2 0
    //   2149: astore 34
    //   2151: aload 34
    //   2153: instanceof 362
    //   2156: ifeq +111 -> 2267
    //   2159: aload 14
    //   2161: getfield 563	com/google/android/gms/internal/measurement/zzkf:zzarw	Lcom/google/android/gms/internal/measurement/zzkg;
    //   2164: ifnonnull +40 -> 2204
    //   2167: aload_0
    //   2168: invokevirtual 99	com/google/android/gms/internal/measurement/zzhg:zzge	()Lcom/google/android/gms/internal/measurement/zzfg;
    //   2171: invokevirtual 105	com/google/android/gms/internal/measurement/zzfg:zzip	()Lcom/google/android/gms/internal/measurement/zzfi;
    //   2174: ldc_w 565
    //   2177: aload_0
    //   2178: invokevirtual 436	com/google/android/gms/internal/measurement/zzhg:zzga	()Lcom/google/android/gms/internal/measurement/zzfe;
    //   2181: aload 9
    //   2183: invokevirtual 441	com/google/android/gms/internal/measurement/zzfe:zzbj	(Ljava/lang/String;)Ljava/lang/String;
    //   2186: aload_0
    //   2187: invokevirtual 436	com/google/android/gms/internal/measurement/zzhg:zzga	()Lcom/google/android/gms/internal/measurement/zzfe;
    //   2190: aload 33
    //   2192: invokevirtual 554	com/google/android/gms/internal/measurement/zzfe:zzbk	(Ljava/lang/String;)Ljava/lang/String;
    //   2195: invokevirtual 299	com/google/android/gms/internal/measurement/zzfi:zze	(Ljava/lang/String;Ljava/lang/Object;Ljava/lang/Object;)V
    //   2198: aconst_null
    //   2199: astore 14
    //   2201: goto -484 -> 1717
    //   2204: aload_0
    //   2205: aload 34
    //   2207: checkcast 362	java/lang/Long
    //   2210: invokevirtual 380	java/lang/Long:longValue	()J
    //   2213: aload 14
    //   2215: getfield 563	com/google/android/gms/internal/measurement/zzkf:zzarw	Lcom/google/android/gms/internal/measurement/zzkg;
    //   2218: invokespecial 523	com/google/android/gms/internal/measurement/zzeb:zza	(JLcom/google/android/gms/internal/measurement/zzkg;)Ljava/lang/Boolean;
    //   2221: astore 14
    //   2223: aload 14
    //   2225: ifnonnull +9 -> 2234
    //   2228: aconst_null
    //   2229: astore 14
    //   2231: goto -514 -> 1717
    //   2234: aload 14
    //   2236: invokevirtual 51	java/lang/Boolean:booleanValue	()Z
    //   2239: ifne +22 -> 2261
    //   2242: iconst_1
    //   2243: istore 20
    //   2245: iload 20
    //   2247: iload 32
    //   2249: ixor
    //   2250: ifeq +402 -> 2652
    //   2253: getstatic 311	java/lang/Boolean:FALSE	Ljava/lang/Boolean;
    //   2256: astore 14
    //   2258: goto -541 -> 1717
    //   2261: iconst_0
    //   2262: istore 20
    //   2264: goto -19 -> 2245
    //   2267: aload 34
    //   2269: instanceof 567
    //   2272: ifeq +111 -> 2383
    //   2275: aload 14
    //   2277: getfield 563	com/google/android/gms/internal/measurement/zzkf:zzarw	Lcom/google/android/gms/internal/measurement/zzkg;
    //   2280: ifnonnull +40 -> 2320
    //   2283: aload_0
    //   2284: invokevirtual 99	com/google/android/gms/internal/measurement/zzhg:zzge	()Lcom/google/android/gms/internal/measurement/zzfg;
    //   2287: invokevirtual 105	com/google/android/gms/internal/measurement/zzfg:zzip	()Lcom/google/android/gms/internal/measurement/zzfi;
    //   2290: ldc_w 569
    //   2293: aload_0
    //   2294: invokevirtual 436	com/google/android/gms/internal/measurement/zzhg:zzga	()Lcom/google/android/gms/internal/measurement/zzfe;
    //   2297: aload 9
    //   2299: invokevirtual 441	com/google/android/gms/internal/measurement/zzfe:zzbj	(Ljava/lang/String;)Ljava/lang/String;
    //   2302: aload_0
    //   2303: invokevirtual 436	com/google/android/gms/internal/measurement/zzhg:zzga	()Lcom/google/android/gms/internal/measurement/zzfe;
    //   2306: aload 33
    //   2308: invokevirtual 554	com/google/android/gms/internal/measurement/zzfe:zzbk	(Ljava/lang/String;)Ljava/lang/String;
    //   2311: invokevirtual 299	com/google/android/gms/internal/measurement/zzfi:zze	(Ljava/lang/String;Ljava/lang/Object;Ljava/lang/Object;)V
    //   2314: aconst_null
    //   2315: astore 14
    //   2317: goto -600 -> 1717
    //   2320: aload_0
    //   2321: aload 34
    //   2323: checkcast 567	java/lang/Double
    //   2326: invokevirtual 573	java/lang/Double:doubleValue	()D
    //   2329: aload 14
    //   2331: getfield 563	com/google/android/gms/internal/measurement/zzkf:zzarw	Lcom/google/android/gms/internal/measurement/zzkg;
    //   2334: invokespecial 575	com/google/android/gms/internal/measurement/zzeb:zza	(DLcom/google/android/gms/internal/measurement/zzkg;)Ljava/lang/Boolean;
    //   2337: astore 14
    //   2339: aload 14
    //   2341: ifnonnull +9 -> 2350
    //   2344: aconst_null
    //   2345: astore 14
    //   2347: goto -630 -> 1717
    //   2350: aload 14
    //   2352: invokevirtual 51	java/lang/Boolean:booleanValue	()Z
    //   2355: ifne +22 -> 2377
    //   2358: iconst_1
    //   2359: istore 20
    //   2361: iload 20
    //   2363: iload 32
    //   2365: ixor
    //   2366: ifeq +286 -> 2652
    //   2369: getstatic 311	java/lang/Boolean:FALSE	Ljava/lang/Boolean;
    //   2372: astore 14
    //   2374: goto -657 -> 1717
    //   2377: iconst_0
    //   2378: istore 20
    //   2380: goto -19 -> 2361
    //   2383: aload 34
    //   2385: instanceof 74
    //   2388: ifeq +183 -> 2571
    //   2391: aload 14
    //   2393: getfield 579	com/google/android/gms/internal/measurement/zzkf:zzarv	Lcom/google/android/gms/internal/measurement/zzki;
    //   2396: ifnull +30 -> 2426
    //   2399: aload_0
    //   2400: aload 34
    //   2402: checkcast 74	java/lang/String
    //   2405: aload 14
    //   2407: getfield 579	com/google/android/gms/internal/measurement/zzkf:zzarv	Lcom/google/android/gms/internal/measurement/zzki;
    //   2410: invokespecial 581	com/google/android/gms/internal/measurement/zzeb:zza	(Ljava/lang/String;Lcom/google/android/gms/internal/measurement/zzki;)Ljava/lang/Boolean;
    //   2413: astore 14
    //   2415: aload 14
    //   2417: ifnonnull +121 -> 2538
    //   2420: aconst_null
    //   2421: astore 14
    //   2423: goto -706 -> 1717
    //   2426: aload 14
    //   2428: getfield 563	com/google/android/gms/internal/measurement/zzkf:zzarw	Lcom/google/android/gms/internal/measurement/zzkg;
    //   2431: ifnull +70 -> 2501
    //   2434: aload 34
    //   2436: checkcast 74	java/lang/String
    //   2439: invokestatic 139	com/google/android/gms/internal/measurement/zzka:zzck	(Ljava/lang/String;)Z
    //   2442: ifeq +22 -> 2464
    //   2445: aload_0
    //   2446: aload 34
    //   2448: checkcast 74	java/lang/String
    //   2451: aload 14
    //   2453: getfield 563	com/google/android/gms/internal/measurement/zzkf:zzarw	Lcom/google/android/gms/internal/measurement/zzkg;
    //   2456: invokespecial 583	com/google/android/gms/internal/measurement/zzeb:zza	(Ljava/lang/String;Lcom/google/android/gms/internal/measurement/zzkg;)Ljava/lang/Boolean;
    //   2459: astore 14
    //   2461: goto -46 -> 2415
    //   2464: aload_0
    //   2465: invokevirtual 99	com/google/android/gms/internal/measurement/zzhg:zzge	()Lcom/google/android/gms/internal/measurement/zzfg;
    //   2468: invokevirtual 105	com/google/android/gms/internal/measurement/zzfg:zzip	()Lcom/google/android/gms/internal/measurement/zzfi;
    //   2471: ldc_w 585
    //   2474: aload_0
    //   2475: invokevirtual 436	com/google/android/gms/internal/measurement/zzhg:zzga	()Lcom/google/android/gms/internal/measurement/zzfe;
    //   2478: aload 9
    //   2480: invokevirtual 441	com/google/android/gms/internal/measurement/zzfe:zzbj	(Ljava/lang/String;)Ljava/lang/String;
    //   2483: aload_0
    //   2484: invokevirtual 436	com/google/android/gms/internal/measurement/zzhg:zzga	()Lcom/google/android/gms/internal/measurement/zzfe;
    //   2487: aload 33
    //   2489: invokevirtual 554	com/google/android/gms/internal/measurement/zzfe:zzbk	(Ljava/lang/String;)Ljava/lang/String;
    //   2492: invokevirtual 299	com/google/android/gms/internal/measurement/zzfi:zze	(Ljava/lang/String;Ljava/lang/Object;Ljava/lang/Object;)V
    //   2495: aconst_null
    //   2496: astore 14
    //   2498: goto -781 -> 1717
    //   2501: aload_0
    //   2502: invokevirtual 99	com/google/android/gms/internal/measurement/zzhg:zzge	()Lcom/google/android/gms/internal/measurement/zzfg;
    //   2505: invokevirtual 105	com/google/android/gms/internal/measurement/zzfg:zzip	()Lcom/google/android/gms/internal/measurement/zzfi;
    //   2508: ldc_w 587
    //   2511: aload_0
    //   2512: invokevirtual 436	com/google/android/gms/internal/measurement/zzhg:zzga	()Lcom/google/android/gms/internal/measurement/zzfe;
    //   2515: aload 9
    //   2517: invokevirtual 441	com/google/android/gms/internal/measurement/zzfe:zzbj	(Ljava/lang/String;)Ljava/lang/String;
    //   2520: aload_0
    //   2521: invokevirtual 436	com/google/android/gms/internal/measurement/zzhg:zzga	()Lcom/google/android/gms/internal/measurement/zzfe;
    //   2524: aload 33
    //   2526: invokevirtual 554	com/google/android/gms/internal/measurement/zzfe:zzbk	(Ljava/lang/String;)Ljava/lang/String;
    //   2529: invokevirtual 299	com/google/android/gms/internal/measurement/zzfi:zze	(Ljava/lang/String;Ljava/lang/Object;Ljava/lang/Object;)V
    //   2532: aconst_null
    //   2533: astore 14
    //   2535: goto -818 -> 1717
    //   2538: aload 14
    //   2540: invokevirtual 51	java/lang/Boolean:booleanValue	()Z
    //   2543: ifne +22 -> 2565
    //   2546: iconst_1
    //   2547: istore 20
    //   2549: iload 20
    //   2551: iload 32
    //   2553: ixor
    //   2554: ifeq +98 -> 2652
    //   2557: getstatic 311	java/lang/Boolean:FALSE	Ljava/lang/Boolean;
    //   2560: astore 14
    //   2562: goto -845 -> 1717
    //   2565: iconst_0
    //   2566: istore 20
    //   2568: goto -19 -> 2549
    //   2571: aload 34
    //   2573: ifnonnull +42 -> 2615
    //   2576: aload_0
    //   2577: invokevirtual 99	com/google/android/gms/internal/measurement/zzhg:zzge	()Lcom/google/android/gms/internal/measurement/zzfg;
    //   2580: invokevirtual 293	com/google/android/gms/internal/measurement/zzfg:zzit	()Lcom/google/android/gms/internal/measurement/zzfi;
    //   2583: ldc_w 589
    //   2586: aload_0
    //   2587: invokevirtual 436	com/google/android/gms/internal/measurement/zzhg:zzga	()Lcom/google/android/gms/internal/measurement/zzfe;
    //   2590: aload 9
    //   2592: invokevirtual 441	com/google/android/gms/internal/measurement/zzfe:zzbj	(Ljava/lang/String;)Ljava/lang/String;
    //   2595: aload_0
    //   2596: invokevirtual 436	com/google/android/gms/internal/measurement/zzhg:zzga	()Lcom/google/android/gms/internal/measurement/zzfe;
    //   2599: aload 33
    //   2601: invokevirtual 554	com/google/android/gms/internal/measurement/zzfe:zzbk	(Ljava/lang/String;)Ljava/lang/String;
    //   2604: invokevirtual 299	com/google/android/gms/internal/measurement/zzfi:zze	(Ljava/lang/String;Ljava/lang/Object;Ljava/lang/Object;)V
    //   2607: getstatic 311	java/lang/Boolean:FALSE	Ljava/lang/Boolean;
    //   2610: astore 14
    //   2612: goto -895 -> 1717
    //   2615: aload_0
    //   2616: invokevirtual 99	com/google/android/gms/internal/measurement/zzhg:zzge	()Lcom/google/android/gms/internal/measurement/zzfg;
    //   2619: invokevirtual 105	com/google/android/gms/internal/measurement/zzfg:zzip	()Lcom/google/android/gms/internal/measurement/zzfi;
    //   2622: ldc_w 591
    //   2625: aload_0
    //   2626: invokevirtual 436	com/google/android/gms/internal/measurement/zzhg:zzga	()Lcom/google/android/gms/internal/measurement/zzfe;
    //   2629: aload 9
    //   2631: invokevirtual 441	com/google/android/gms/internal/measurement/zzfe:zzbj	(Ljava/lang/String;)Ljava/lang/String;
    //   2634: aload_0
    //   2635: invokevirtual 436	com/google/android/gms/internal/measurement/zzhg:zzga	()Lcom/google/android/gms/internal/measurement/zzfe;
    //   2638: aload 33
    //   2640: invokevirtual 554	com/google/android/gms/internal/measurement/zzfe:zzbk	(Ljava/lang/String;)Ljava/lang/String;
    //   2643: invokevirtual 299	com/google/android/gms/internal/measurement/zzfi:zze	(Ljava/lang/String;Ljava/lang/Object;Ljava/lang/Object;)V
    //   2646: aconst_null
    //   2647: astore 14
    //   2649: goto -932 -> 1717
    //   2652: iinc 15 1
    //   2655: goto -585 -> 2070
    //   2658: getstatic 485	java/lang/Boolean:TRUE	Ljava/lang/Boolean;
    //   2661: astore 14
    //   2663: goto -946 -> 1717
    //   2666: aload 14
    //   2668: astore 31
    //   2670: goto -934 -> 1736
    //   2673: aload 23
    //   2675: aload 29
    //   2677: getfield 497	com/google/android/gms/internal/measurement/zzke:zzarp	Ljava/lang/Integer;
    //   2680: invokevirtual 161	java/lang/Integer:intValue	()I
    //   2683: invokevirtual 302	java/util/BitSet:set	(I)V
    //   2686: aload 14
    //   2688: invokevirtual 51	java/lang/Boolean:booleanValue	()Z
    //   2691: ifeq -1185 -> 1506
    //   2694: aload 21
    //   2696: aload 29
    //   2698: getfield 497	com/google/android/gms/internal/measurement/zzke:zzarp	Ljava/lang/Integer;
    //   2701: invokevirtual 161	java/lang/Integer:intValue	()I
    //   2704: invokevirtual 302	java/util/BitSet:set	(I)V
    //   2707: goto -1201 -> 1506
    //   2710: aload_3
    //   2711: ifnull +980 -> 3691
    //   2714: new 234	android/support/v4/f/a
    //   2717: dup
    //   2718: invokespecial 235	android/support/v4/f/a:<init>	()V
    //   2721: astore 11
    //   2723: aload_3
    //   2724: arraylength
    //   2725: istore 10
    //   2727: iconst_0
    //   2728: istore 15
    //   2730: iload 15
    //   2732: iload 10
    //   2734: if_icmpge +957 -> 3691
    //   2737: aload_3
    //   2738: iload 15
    //   2740: aaload
    //   2741: astore 9
    //   2743: aload 11
    //   2745: aload 9
    //   2747: getfield 594	com/google/android/gms/internal/measurement/zzks:name	Ljava/lang/String;
    //   2750: invokeinterface 274 2 0
    //   2755: checkcast 249	java/util/Map
    //   2758: astore 14
    //   2760: aload 14
    //   2762: ifnonnull +1329 -> 4091
    //   2765: aload_0
    //   2766: invokevirtual 241	com/google/android/gms/internal/measurement/zzjp:zzix	()Lcom/google/android/gms/internal/measurement/zzei;
    //   2769: aload_1
    //   2770: aload 9
    //   2772: getfield 594	com/google/android/gms/internal/measurement/zzks:name	Ljava/lang/String;
    //   2775: invokevirtual 597	com/google/android/gms/internal/measurement/zzei:zzl	(Ljava/lang/String;Ljava/lang/String;)Ljava/util/Map;
    //   2778: astore 14
    //   2780: aload 14
    //   2782: astore_2
    //   2783: aload 14
    //   2785: ifnonnull +11 -> 2796
    //   2788: new 234	android/support/v4/f/a
    //   2791: dup
    //   2792: invokespecial 235	android/support/v4/f/a:<init>	()V
    //   2795: astore_2
    //   2796: aload 11
    //   2798: aload 9
    //   2800: getfield 594	com/google/android/gms/internal/measurement/zzks:name	Ljava/lang/String;
    //   2803: aload_2
    //   2804: invokeinterface 283 3 0
    //   2809: pop
    //   2810: aload_2
    //   2811: astore 14
    //   2813: aload 14
    //   2815: invokeinterface 253 1 0
    //   2820: invokeinterface 259 1 0
    //   2825: astore 21
    //   2827: aload 21
    //   2829: invokeinterface 264 1 0
    //   2834: ifeq +851 -> 3685
    //   2837: aload 21
    //   2839: invokeinterface 268 1 0
    //   2844: checkcast 158	java/lang/Integer
    //   2847: invokevirtual 161	java/lang/Integer:intValue	()I
    //   2850: istore 20
    //   2852: aload 4
    //   2854: iload 20
    //   2856: invokestatic 271	java/lang/Integer:valueOf	(I)Ljava/lang/Integer;
    //   2859: invokeinterface 462 2 0
    //   2864: ifeq +24 -> 2888
    //   2867: aload_0
    //   2868: invokevirtual 99	com/google/android/gms/internal/measurement/zzhg:zzge	()Lcom/google/android/gms/internal/measurement/zzfg;
    //   2871: invokevirtual 293	com/google/android/gms/internal/measurement/zzfg:zzit	()Lcom/google/android/gms/internal/measurement/zzfi;
    //   2874: ldc_w 464
    //   2877: iload 20
    //   2879: invokestatic 271	java/lang/Integer:valueOf	(I)Ljava/lang/Integer;
    //   2882: invokevirtual 113	com/google/android/gms/internal/measurement/zzfi:zzg	(Ljava/lang/String;Ljava/lang/Object;)V
    //   2885: goto -58 -> 2827
    //   2888: aload 5
    //   2890: iload 20
    //   2892: invokestatic 271	java/lang/Integer:valueOf	(I)Ljava/lang/Integer;
    //   2895: invokeinterface 274 2 0
    //   2900: checkcast 307	com/google/android/gms/internal/measurement/zzkm
    //   2903: astore_2
    //   2904: aload 6
    //   2906: iload 20
    //   2908: invokestatic 271	java/lang/Integer:valueOf	(I)Ljava/lang/Integer;
    //   2911: invokeinterface 274 2 0
    //   2916: checkcast 278	java/util/BitSet
    //   2919: astore 13
    //   2921: aload 7
    //   2923: iload 20
    //   2925: invokestatic 271	java/lang/Integer:valueOf	(I)Ljava/lang/Integer;
    //   2928: invokeinterface 274 2 0
    //   2933: checkcast 278	java/util/BitSet
    //   2936: astore 12
    //   2938: aload_2
    //   2939: ifnonnull +80 -> 3019
    //   2942: new 307	com/google/android/gms/internal/measurement/zzkm
    //   2945: dup
    //   2946: invokespecial 308	com/google/android/gms/internal/measurement/zzkm:<init>	()V
    //   2949: astore_2
    //   2950: aload 5
    //   2952: iload 20
    //   2954: invokestatic 271	java/lang/Integer:valueOf	(I)Ljava/lang/Integer;
    //   2957: aload_2
    //   2958: invokeinterface 283 3 0
    //   2963: pop
    //   2964: aload_2
    //   2965: getstatic 485	java/lang/Boolean:TRUE	Ljava/lang/Boolean;
    //   2968: putfield 314	com/google/android/gms/internal/measurement/zzkm:zzasy	Ljava/lang/Boolean;
    //   2971: new 278	java/util/BitSet
    //   2974: dup
    //   2975: invokespecial 279	java/util/BitSet:<init>	()V
    //   2978: astore 13
    //   2980: aload 6
    //   2982: iload 20
    //   2984: invokestatic 271	java/lang/Integer:valueOf	(I)Ljava/lang/Integer;
    //   2987: aload 13
    //   2989: invokeinterface 283 3 0
    //   2994: pop
    //   2995: new 278	java/util/BitSet
    //   2998: dup
    //   2999: invokespecial 279	java/util/BitSet:<init>	()V
    //   3002: astore 12
    //   3004: aload 7
    //   3006: iload 20
    //   3008: invokestatic 271	java/lang/Integer:valueOf	(I)Ljava/lang/Integer;
    //   3011: aload 12
    //   3013: invokeinterface 283 3 0
    //   3018: pop
    //   3019: aload 14
    //   3021: iload 20
    //   3023: invokestatic 271	java/lang/Integer:valueOf	(I)Ljava/lang/Integer;
    //   3026: invokeinterface 274 2 0
    //   3031: checkcast 62	java/util/List
    //   3034: invokeinterface 486 1 0
    //   3039: astore 23
    //   3041: aload 23
    //   3043: invokeinterface 264 1 0
    //   3048: ifeq -221 -> 2827
    //   3051: aload 23
    //   3053: invokeinterface 268 1 0
    //   3058: checkcast 599	com/google/android/gms/internal/measurement/zzkh
    //   3061: astore 31
    //   3063: aload_0
    //   3064: invokevirtual 99	com/google/android/gms/internal/measurement/zzhg:zzge	()Lcom/google/android/gms/internal/measurement/zzfg;
    //   3067: iconst_2
    //   3068: invokevirtual 492	com/google/android/gms/internal/measurement/zzfg:isLoggable	(I)Z
    //   3071: ifeq +60 -> 3131
    //   3074: aload_0
    //   3075: invokevirtual 99	com/google/android/gms/internal/measurement/zzhg:zzge	()Lcom/google/android/gms/internal/measurement/zzfg;
    //   3078: invokevirtual 293	com/google/android/gms/internal/measurement/zzfg:zzit	()Lcom/google/android/gms/internal/measurement/zzfi;
    //   3081: ldc_w 601
    //   3084: iload 20
    //   3086: invokestatic 271	java/lang/Integer:valueOf	(I)Ljava/lang/Integer;
    //   3089: aload 31
    //   3091: getfield 602	com/google/android/gms/internal/measurement/zzkh:zzarp	Ljava/lang/Integer;
    //   3094: aload_0
    //   3095: invokevirtual 436	com/google/android/gms/internal/measurement/zzhg:zzga	()Lcom/google/android/gms/internal/measurement/zzfe;
    //   3098: aload 31
    //   3100: getfield 605	com/google/android/gms/internal/measurement/zzkh:zzasf	Ljava/lang/String;
    //   3103: invokevirtual 608	com/google/android/gms/internal/measurement/zzfe:zzbl	(Ljava/lang/String;)Ljava/lang/String;
    //   3106: invokevirtual 503	com/google/android/gms/internal/measurement/zzfi:zzd	(Ljava/lang/String;Ljava/lang/Object;Ljava/lang/Object;Ljava/lang/Object;)V
    //   3109: aload_0
    //   3110: invokevirtual 99	com/google/android/gms/internal/measurement/zzhg:zzge	()Lcom/google/android/gms/internal/measurement/zzfg;
    //   3113: invokevirtual 293	com/google/android/gms/internal/measurement/zzfg:zzit	()Lcom/google/android/gms/internal/measurement/zzfi;
    //   3116: ldc_w 505
    //   3119: aload_0
    //   3120: invokevirtual 436	com/google/android/gms/internal/measurement/zzhg:zzga	()Lcom/google/android/gms/internal/measurement/zzfe;
    //   3123: aload 31
    //   3125: invokevirtual 611	com/google/android/gms/internal/measurement/zzfe:zza	(Lcom/google/android/gms/internal/measurement/zzkh;)Ljava/lang/String;
    //   3128: invokevirtual 113	com/google/android/gms/internal/measurement/zzfi:zzg	(Ljava/lang/String;Ljava/lang/Object;)V
    //   3131: aload 31
    //   3133: getfield 602	com/google/android/gms/internal/measurement/zzkh:zzarp	Ljava/lang/Integer;
    //   3136: ifnull +17 -> 3153
    //   3139: aload 31
    //   3141: getfield 602	com/google/android/gms/internal/measurement/zzkh:zzarp	Ljava/lang/Integer;
    //   3144: invokevirtual 161	java/lang/Integer:intValue	()I
    //   3147: sipush 256
    //   3150: if_icmple +44 -> 3194
    //   3153: aload_0
    //   3154: invokevirtual 99	com/google/android/gms/internal/measurement/zzhg:zzge	()Lcom/google/android/gms/internal/measurement/zzfg;
    //   3157: invokevirtual 105	com/google/android/gms/internal/measurement/zzfg:zzip	()Lcom/google/android/gms/internal/measurement/zzfi;
    //   3160: ldc_w 613
    //   3163: aload_1
    //   3164: invokestatic 432	com/google/android/gms/internal/measurement/zzfg:zzbm	(Ljava/lang/String;)Ljava/lang/Object;
    //   3167: aload 31
    //   3169: getfield 602	com/google/android/gms/internal/measurement/zzkh:zzarp	Ljava/lang/Integer;
    //   3172: invokestatic 513	java/lang/String:valueOf	(Ljava/lang/Object;)Ljava/lang/String;
    //   3175: invokevirtual 299	com/google/android/gms/internal/measurement/zzfi:zze	(Ljava/lang/String;Ljava/lang/Object;Ljava/lang/Object;)V
    //   3178: aload 4
    //   3180: iload 20
    //   3182: invokestatic 271	java/lang/Integer:valueOf	(I)Ljava/lang/Integer;
    //   3185: invokeinterface 528 2 0
    //   3190: pop
    //   3191: goto -364 -> 2827
    //   3194: aload 13
    //   3196: aload 31
    //   3198: getfield 602	com/google/android/gms/internal/measurement/zzkh:zzarp	Ljava/lang/Integer;
    //   3201: invokevirtual 161	java/lang/Integer:intValue	()I
    //   3204: invokevirtual 515	java/util/BitSet:get	(I)Z
    //   3207: ifeq +29 -> 3236
    //   3210: aload_0
    //   3211: invokevirtual 99	com/google/android/gms/internal/measurement/zzhg:zzge	()Lcom/google/android/gms/internal/measurement/zzfg;
    //   3214: invokevirtual 293	com/google/android/gms/internal/measurement/zzfg:zzit	()Lcom/google/android/gms/internal/measurement/zzfi;
    //   3217: ldc_w 615
    //   3220: iload 20
    //   3222: invokestatic 271	java/lang/Integer:valueOf	(I)Ljava/lang/Integer;
    //   3225: aload 31
    //   3227: getfield 602	com/google/android/gms/internal/measurement/zzkh:zzarp	Ljava/lang/Integer;
    //   3230: invokevirtual 299	com/google/android/gms/internal/measurement/zzfi:zze	(Ljava/lang/String;Ljava/lang/Object;Ljava/lang/Object;)V
    //   3233: goto -192 -> 3041
    //   3236: aload 31
    //   3238: getfield 619	com/google/android/gms/internal/measurement/zzkh:zzasg	Lcom/google/android/gms/internal/measurement/zzkf;
    //   3241: astore_2
    //   3242: aload_2
    //   3243: ifnonnull +78 -> 3321
    //   3246: aload_0
    //   3247: invokevirtual 99	com/google/android/gms/internal/measurement/zzhg:zzge	()Lcom/google/android/gms/internal/measurement/zzfg;
    //   3250: invokevirtual 105	com/google/android/gms/internal/measurement/zzfg:zzip	()Lcom/google/android/gms/internal/measurement/zzfi;
    //   3253: ldc_w 621
    //   3256: aload_0
    //   3257: invokevirtual 436	com/google/android/gms/internal/measurement/zzhg:zzga	()Lcom/google/android/gms/internal/measurement/zzfe;
    //   3260: aload 9
    //   3262: getfield 594	com/google/android/gms/internal/measurement/zzks:name	Ljava/lang/String;
    //   3265: invokevirtual 608	com/google/android/gms/internal/measurement/zzfe:zzbl	(Ljava/lang/String;)Ljava/lang/String;
    //   3268: invokevirtual 113	com/google/android/gms/internal/measurement/zzfi:zzg	(Ljava/lang/String;Ljava/lang/Object;)V
    //   3271: aconst_null
    //   3272: astore_2
    //   3273: aload_0
    //   3274: invokevirtual 99	com/google/android/gms/internal/measurement/zzhg:zzge	()Lcom/google/android/gms/internal/measurement/zzfg;
    //   3277: invokevirtual 293	com/google/android/gms/internal/measurement/zzfg:zzit	()Lcom/google/android/gms/internal/measurement/zzfi;
    //   3280: astore 18
    //   3282: aload_2
    //   3283: ifnonnull +360 -> 3643
    //   3286: ldc_w 525
    //   3289: astore 8
    //   3291: aload 18
    //   3293: ldc_w 623
    //   3296: aload 8
    //   3298: invokevirtual 113	com/google/android/gms/internal/measurement/zzfi:zzg	(Ljava/lang/String;Ljava/lang/Object;)V
    //   3301: aload_2
    //   3302: ifnonnull +347 -> 3649
    //   3305: aload 4
    //   3307: iload 20
    //   3309: invokestatic 271	java/lang/Integer:valueOf	(I)Ljava/lang/Integer;
    //   3312: invokeinterface 528 2 0
    //   3317: pop
    //   3318: goto -277 -> 3041
    //   3321: getstatic 485	java/lang/Boolean:TRUE	Ljava/lang/Boolean;
    //   3324: aload_2
    //   3325: getfield 557	com/google/android/gms/internal/measurement/zzkf:zzarx	Ljava/lang/Boolean;
    //   3328: invokevirtual 558	java/lang/Boolean:equals	(Ljava/lang/Object;)Z
    //   3331: istore 32
    //   3333: aload 9
    //   3335: getfield 624	com/google/android/gms/internal/measurement/zzks:zzate	Ljava/lang/Long;
    //   3338: ifnull +65 -> 3403
    //   3341: aload_2
    //   3342: getfield 563	com/google/android/gms/internal/measurement/zzkf:zzarw	Lcom/google/android/gms/internal/measurement/zzkg;
    //   3345: ifnonnull +33 -> 3378
    //   3348: aload_0
    //   3349: invokevirtual 99	com/google/android/gms/internal/measurement/zzhg:zzge	()Lcom/google/android/gms/internal/measurement/zzfg;
    //   3352: invokevirtual 105	com/google/android/gms/internal/measurement/zzfg:zzip	()Lcom/google/android/gms/internal/measurement/zzfi;
    //   3355: ldc_w 626
    //   3358: aload_0
    //   3359: invokevirtual 436	com/google/android/gms/internal/measurement/zzhg:zzga	()Lcom/google/android/gms/internal/measurement/zzfe;
    //   3362: aload 9
    //   3364: getfield 594	com/google/android/gms/internal/measurement/zzks:name	Ljava/lang/String;
    //   3367: invokevirtual 608	com/google/android/gms/internal/measurement/zzfe:zzbl	(Ljava/lang/String;)Ljava/lang/String;
    //   3370: invokevirtual 113	com/google/android/gms/internal/measurement/zzfi:zzg	(Ljava/lang/String;Ljava/lang/Object;)V
    //   3373: aconst_null
    //   3374: astore_2
    //   3375: goto -102 -> 3273
    //   3378: aload_0
    //   3379: aload 9
    //   3381: getfield 624	com/google/android/gms/internal/measurement/zzks:zzate	Ljava/lang/Long;
    //   3384: invokevirtual 380	java/lang/Long:longValue	()J
    //   3387: aload_2
    //   3388: getfield 563	com/google/android/gms/internal/measurement/zzkf:zzarw	Lcom/google/android/gms/internal/measurement/zzkg;
    //   3391: invokespecial 523	com/google/android/gms/internal/measurement/zzeb:zza	(JLcom/google/android/gms/internal/measurement/zzkg;)Ljava/lang/Boolean;
    //   3394: iload 32
    //   3396: invokestatic 628	com/google/android/gms/internal/measurement/zzeb:zza	(Ljava/lang/Boolean;Z)Ljava/lang/Boolean;
    //   3399: astore_2
    //   3400: goto -127 -> 3273
    //   3403: aload 9
    //   3405: getfield 629	com/google/android/gms/internal/measurement/zzks:zzarc	Ljava/lang/Double;
    //   3408: ifnull +65 -> 3473
    //   3411: aload_2
    //   3412: getfield 563	com/google/android/gms/internal/measurement/zzkf:zzarw	Lcom/google/android/gms/internal/measurement/zzkg;
    //   3415: ifnonnull +33 -> 3448
    //   3418: aload_0
    //   3419: invokevirtual 99	com/google/android/gms/internal/measurement/zzhg:zzge	()Lcom/google/android/gms/internal/measurement/zzfg;
    //   3422: invokevirtual 105	com/google/android/gms/internal/measurement/zzfg:zzip	()Lcom/google/android/gms/internal/measurement/zzfi;
    //   3425: ldc_w 631
    //   3428: aload_0
    //   3429: invokevirtual 436	com/google/android/gms/internal/measurement/zzhg:zzga	()Lcom/google/android/gms/internal/measurement/zzfe;
    //   3432: aload 9
    //   3434: getfield 594	com/google/android/gms/internal/measurement/zzks:name	Ljava/lang/String;
    //   3437: invokevirtual 608	com/google/android/gms/internal/measurement/zzfe:zzbl	(Ljava/lang/String;)Ljava/lang/String;
    //   3440: invokevirtual 113	com/google/android/gms/internal/measurement/zzfi:zzg	(Ljava/lang/String;Ljava/lang/Object;)V
    //   3443: aconst_null
    //   3444: astore_2
    //   3445: goto -172 -> 3273
    //   3448: aload_0
    //   3449: aload 9
    //   3451: getfield 629	com/google/android/gms/internal/measurement/zzks:zzarc	Ljava/lang/Double;
    //   3454: invokevirtual 573	java/lang/Double:doubleValue	()D
    //   3457: aload_2
    //   3458: getfield 563	com/google/android/gms/internal/measurement/zzkf:zzarw	Lcom/google/android/gms/internal/measurement/zzkg;
    //   3461: invokespecial 575	com/google/android/gms/internal/measurement/zzeb:zza	(DLcom/google/android/gms/internal/measurement/zzkg;)Ljava/lang/Boolean;
    //   3464: iload 32
    //   3466: invokestatic 628	com/google/android/gms/internal/measurement/zzeb:zza	(Ljava/lang/Boolean;Z)Ljava/lang/Boolean;
    //   3469: astore_2
    //   3470: goto -197 -> 3273
    //   3473: aload 9
    //   3475: getfield 632	com/google/android/gms/internal/measurement/zzks:zzajf	Ljava/lang/String;
    //   3478: ifnull +135 -> 3613
    //   3481: aload_2
    //   3482: getfield 579	com/google/android/gms/internal/measurement/zzkf:zzarv	Lcom/google/android/gms/internal/measurement/zzki;
    //   3485: ifnonnull +106 -> 3591
    //   3488: aload_2
    //   3489: getfield 563	com/google/android/gms/internal/measurement/zzkf:zzarw	Lcom/google/android/gms/internal/measurement/zzkg;
    //   3492: ifnonnull +33 -> 3525
    //   3495: aload_0
    //   3496: invokevirtual 99	com/google/android/gms/internal/measurement/zzhg:zzge	()Lcom/google/android/gms/internal/measurement/zzfg;
    //   3499: invokevirtual 105	com/google/android/gms/internal/measurement/zzfg:zzip	()Lcom/google/android/gms/internal/measurement/zzfi;
    //   3502: ldc_w 634
    //   3505: aload_0
    //   3506: invokevirtual 436	com/google/android/gms/internal/measurement/zzhg:zzga	()Lcom/google/android/gms/internal/measurement/zzfe;
    //   3509: aload 9
    //   3511: getfield 594	com/google/android/gms/internal/measurement/zzks:name	Ljava/lang/String;
    //   3514: invokevirtual 608	com/google/android/gms/internal/measurement/zzfe:zzbl	(Ljava/lang/String;)Ljava/lang/String;
    //   3517: invokevirtual 113	com/google/android/gms/internal/measurement/zzfi:zzg	(Ljava/lang/String;Ljava/lang/Object;)V
    //   3520: aconst_null
    //   3521: astore_2
    //   3522: goto -249 -> 3273
    //   3525: aload 9
    //   3527: getfield 632	com/google/android/gms/internal/measurement/zzks:zzajf	Ljava/lang/String;
    //   3530: invokestatic 139	com/google/android/gms/internal/measurement/zzka:zzck	(Ljava/lang/String;)Z
    //   3533: ifeq +25 -> 3558
    //   3536: aload_0
    //   3537: aload 9
    //   3539: getfield 632	com/google/android/gms/internal/measurement/zzks:zzajf	Ljava/lang/String;
    //   3542: aload_2
    //   3543: getfield 563	com/google/android/gms/internal/measurement/zzkf:zzarw	Lcom/google/android/gms/internal/measurement/zzkg;
    //   3546: invokespecial 583	com/google/android/gms/internal/measurement/zzeb:zza	(Ljava/lang/String;Lcom/google/android/gms/internal/measurement/zzkg;)Ljava/lang/Boolean;
    //   3549: iload 32
    //   3551: invokestatic 628	com/google/android/gms/internal/measurement/zzeb:zza	(Ljava/lang/Boolean;Z)Ljava/lang/Boolean;
    //   3554: astore_2
    //   3555: goto -282 -> 3273
    //   3558: aload_0
    //   3559: invokevirtual 99	com/google/android/gms/internal/measurement/zzhg:zzge	()Lcom/google/android/gms/internal/measurement/zzfg;
    //   3562: invokevirtual 105	com/google/android/gms/internal/measurement/zzfg:zzip	()Lcom/google/android/gms/internal/measurement/zzfi;
    //   3565: ldc_w 636
    //   3568: aload_0
    //   3569: invokevirtual 436	com/google/android/gms/internal/measurement/zzhg:zzga	()Lcom/google/android/gms/internal/measurement/zzfe;
    //   3572: aload 9
    //   3574: getfield 594	com/google/android/gms/internal/measurement/zzks:name	Ljava/lang/String;
    //   3577: invokevirtual 608	com/google/android/gms/internal/measurement/zzfe:zzbl	(Ljava/lang/String;)Ljava/lang/String;
    //   3580: aload 9
    //   3582: getfield 632	com/google/android/gms/internal/measurement/zzks:zzajf	Ljava/lang/String;
    //   3585: invokevirtual 299	com/google/android/gms/internal/measurement/zzfi:zze	(Ljava/lang/String;Ljava/lang/Object;Ljava/lang/Object;)V
    //   3588: goto -68 -> 3520
    //   3591: aload_0
    //   3592: aload 9
    //   3594: getfield 632	com/google/android/gms/internal/measurement/zzks:zzajf	Ljava/lang/String;
    //   3597: aload_2
    //   3598: getfield 579	com/google/android/gms/internal/measurement/zzkf:zzarv	Lcom/google/android/gms/internal/measurement/zzki;
    //   3601: invokespecial 581	com/google/android/gms/internal/measurement/zzeb:zza	(Ljava/lang/String;Lcom/google/android/gms/internal/measurement/zzki;)Ljava/lang/Boolean;
    //   3604: iload 32
    //   3606: invokestatic 628	com/google/android/gms/internal/measurement/zzeb:zza	(Ljava/lang/Boolean;Z)Ljava/lang/Boolean;
    //   3609: astore_2
    //   3610: goto -337 -> 3273
    //   3613: aload_0
    //   3614: invokevirtual 99	com/google/android/gms/internal/measurement/zzhg:zzge	()Lcom/google/android/gms/internal/measurement/zzfg;
    //   3617: invokevirtual 105	com/google/android/gms/internal/measurement/zzfg:zzip	()Lcom/google/android/gms/internal/measurement/zzfi;
    //   3620: ldc_w 638
    //   3623: aload_0
    //   3624: invokevirtual 436	com/google/android/gms/internal/measurement/zzhg:zzga	()Lcom/google/android/gms/internal/measurement/zzfe;
    //   3627: aload 9
    //   3629: getfield 594	com/google/android/gms/internal/measurement/zzks:name	Ljava/lang/String;
    //   3632: invokevirtual 608	com/google/android/gms/internal/measurement/zzfe:zzbl	(Ljava/lang/String;)Ljava/lang/String;
    //   3635: invokevirtual 113	com/google/android/gms/internal/measurement/zzfi:zzg	(Ljava/lang/String;Ljava/lang/Object;)V
    //   3638: aconst_null
    //   3639: astore_2
    //   3640: goto -367 -> 3273
    //   3643: aload_2
    //   3644: astore 8
    //   3646: goto -355 -> 3291
    //   3649: aload 12
    //   3651: aload 31
    //   3653: getfield 602	com/google/android/gms/internal/measurement/zzkh:zzarp	Ljava/lang/Integer;
    //   3656: invokevirtual 161	java/lang/Integer:intValue	()I
    //   3659: invokevirtual 302	java/util/BitSet:set	(I)V
    //   3662: aload_2
    //   3663: invokevirtual 51	java/lang/Boolean:booleanValue	()Z
    //   3666: ifeq -625 -> 3041
    //   3669: aload 13
    //   3671: aload 31
    //   3673: getfield 602	com/google/android/gms/internal/measurement/zzkh:zzarp	Ljava/lang/Integer;
    //   3676: invokevirtual 161	java/lang/Integer:intValue	()I
    //   3679: invokevirtual 302	java/util/BitSet:set	(I)V
    //   3682: goto -641 -> 3041
    //   3685: iinc 15 1
    //   3688: goto -958 -> 2730
    //   3691: aload 6
    //   3693: invokeinterface 639 1 0
    //   3698: anewarray 307	com/google/android/gms/internal/measurement/zzkm
    //   3701: astore 14
    //   3703: aload 6
    //   3705: invokeinterface 253 1 0
    //   3710: invokeinterface 259 1 0
    //   3715: astore_3
    //   3716: iconst_0
    //   3717: istore 15
    //   3719: aload_3
    //   3720: invokeinterface 264 1 0
    //   3725: ifeq +345 -> 4070
    //   3728: aload_3
    //   3729: invokeinterface 268 1 0
    //   3734: checkcast 158	java/lang/Integer
    //   3737: invokevirtual 161	java/lang/Integer:intValue	()I
    //   3740: istore 20
    //   3742: aload 4
    //   3744: iload 20
    //   3746: invokestatic 271	java/lang/Integer:valueOf	(I)Ljava/lang/Integer;
    //   3749: invokeinterface 462 2 0
    //   3754: ifne -35 -> 3719
    //   3757: aload 5
    //   3759: iload 20
    //   3761: invokestatic 271	java/lang/Integer:valueOf	(I)Ljava/lang/Integer;
    //   3764: invokeinterface 274 2 0
    //   3769: checkcast 307	com/google/android/gms/internal/measurement/zzkm
    //   3772: astore_2
    //   3773: aload_2
    //   3774: ifnonnull +314 -> 4088
    //   3777: new 307	com/google/android/gms/internal/measurement/zzkm
    //   3780: dup
    //   3781: invokespecial 308	com/google/android/gms/internal/measurement/zzkm:<init>	()V
    //   3784: astore_2
    //   3785: iload 15
    //   3787: iconst_1
    //   3788: iadd
    //   3789: istore 10
    //   3791: aload 14
    //   3793: iload 15
    //   3795: aload_2
    //   3796: aastore
    //   3797: aload_2
    //   3798: iload 20
    //   3800: invokestatic 271	java/lang/Integer:valueOf	(I)Ljava/lang/Integer;
    //   3803: putfield 642	com/google/android/gms/internal/measurement/zzkm:zzarl	Ljava/lang/Integer;
    //   3806: aload_2
    //   3807: new 276	com/google/android/gms/internal/measurement/zzkr
    //   3810: dup
    //   3811: invokespecial 319	com/google/android/gms/internal/measurement/zzkr:<init>	()V
    //   3814: putfield 322	com/google/android/gms/internal/measurement/zzkm:zzasw	Lcom/google/android/gms/internal/measurement/zzkr;
    //   3817: aload_2
    //   3818: getfield 322	com/google/android/gms/internal/measurement/zzkm:zzasw	Lcom/google/android/gms/internal/measurement/zzkr;
    //   3821: aload 6
    //   3823: iload 20
    //   3825: invokestatic 271	java/lang/Integer:valueOf	(I)Ljava/lang/Integer;
    //   3828: invokeinterface 274 2 0
    //   3833: checkcast 278	java/util/BitSet
    //   3836: invokestatic 325	com/google/android/gms/internal/measurement/zzka:zza	(Ljava/util/BitSet;)[J
    //   3839: putfield 305	com/google/android/gms/internal/measurement/zzkr:zzaul	[J
    //   3842: aload_2
    //   3843: getfield 322	com/google/android/gms/internal/measurement/zzkm:zzasw	Lcom/google/android/gms/internal/measurement/zzkr;
    //   3846: aload 7
    //   3848: iload 20
    //   3850: invokestatic 271	java/lang/Integer:valueOf	(I)Ljava/lang/Integer;
    //   3853: invokeinterface 274 2 0
    //   3858: checkcast 278	java/util/BitSet
    //   3861: invokestatic 325	com/google/android/gms/internal/measurement/zzka:zza	(Ljava/util/BitSet;)[J
    //   3864: putfield 287	com/google/android/gms/internal/measurement/zzkr:zzauk	[J
    //   3867: aload_0
    //   3868: invokevirtual 241	com/google/android/gms/internal/measurement/zzjp:zzix	()Lcom/google/android/gms/internal/measurement/zzei;
    //   3871: astore 13
    //   3873: aload_2
    //   3874: getfield 322	com/google/android/gms/internal/measurement/zzkm:zzasw	Lcom/google/android/gms/internal/measurement/zzkr;
    //   3877: astore 8
    //   3879: aload 13
    //   3881: invokevirtual 645	com/google/android/gms/internal/measurement/zzjq:zzch	()V
    //   3884: aload 13
    //   3886: invokevirtual 397	com/google/android/gms/internal/measurement/zzhg:zzab	()V
    //   3889: aload_1
    //   3890: invokestatic 229	com/google/android/gms/common/internal/Preconditions:checkNotEmpty	(Ljava/lang/String;)Ljava/lang/String;
    //   3893: pop
    //   3894: aload 8
    //   3896: invokestatic 150	com/google/android/gms/common/internal/Preconditions:checkNotNull	(Ljava/lang/Object;)Ljava/lang/Object;
    //   3899: pop
    //   3900: aload 8
    //   3902: invokevirtual 650	com/google/android/gms/internal/measurement/zzace:zzvm	()I
    //   3905: newarray byte
    //   3907: astore_2
    //   3908: aload_2
    //   3909: iconst_0
    //   3910: aload_2
    //   3911: arraylength
    //   3912: invokestatic 655	com/google/android/gms/internal/measurement/zzabw:zzb	([BII)Lcom/google/android/gms/internal/measurement/zzabw;
    //   3915: astore 12
    //   3917: aload 8
    //   3919: aload 12
    //   3921: invokevirtual 658	com/google/android/gms/internal/measurement/zzace:zza	(Lcom/google/android/gms/internal/measurement/zzabw;)V
    //   3924: aload 12
    //   3926: invokevirtual 661	com/google/android/gms/internal/measurement/zzabw:zzve	()V
    //   3929: new 663	android/content/ContentValues
    //   3932: dup
    //   3933: invokespecial 664	android/content/ContentValues:<init>	()V
    //   3936: astore 12
    //   3938: aload 12
    //   3940: ldc_w 666
    //   3943: aload_1
    //   3944: invokevirtual 669	android/content/ContentValues:put	(Ljava/lang/String;Ljava/lang/String;)V
    //   3947: aload 12
    //   3949: ldc_w 671
    //   3952: iload 20
    //   3954: invokestatic 271	java/lang/Integer:valueOf	(I)Ljava/lang/Integer;
    //   3957: invokevirtual 674	android/content/ContentValues:put	(Ljava/lang/String;Ljava/lang/Integer;)V
    //   3960: aload 12
    //   3962: ldc_w 676
    //   3965: aload_2
    //   3966: invokevirtual 679	android/content/ContentValues:put	(Ljava/lang/String;[B)V
    //   3969: aload 13
    //   3971: invokevirtual 403	com/google/android/gms/internal/measurement/zzei:getWritableDatabase	()Landroid/database/sqlite/SQLiteDatabase;
    //   3974: ldc_w 681
    //   3977: aconst_null
    //   3978: aload 12
    //   3980: iconst_5
    //   3981: invokevirtual 685	android/database/sqlite/SQLiteDatabase:insertWithOnConflict	(Ljava/lang/String;Ljava/lang/String;Landroid/content/ContentValues;I)J
    //   3984: ldc2_w 686
    //   3987: lcmp
    //   3988: ifne +21 -> 4009
    //   3991: aload 13
    //   3993: invokevirtual 99	com/google/android/gms/internal/measurement/zzhg:zzge	()Lcom/google/android/gms/internal/measurement/zzfg;
    //   3996: invokevirtual 374	com/google/android/gms/internal/measurement/zzfg:zzim	()Lcom/google/android/gms/internal/measurement/zzfi;
    //   3999: ldc_w 689
    //   4002: aload_1
    //   4003: invokestatic 432	com/google/android/gms/internal/measurement/zzfg:zzbm	(Ljava/lang/String;)Ljava/lang/Object;
    //   4006: invokevirtual 113	com/google/android/gms/internal/measurement/zzfi:zzg	(Ljava/lang/String;Ljava/lang/Object;)V
    //   4009: iload 10
    //   4011: istore 15
    //   4013: goto -294 -> 3719
    //   4016: astore_2
    //   4017: aload 13
    //   4019: invokevirtual 99	com/google/android/gms/internal/measurement/zzhg:zzge	()Lcom/google/android/gms/internal/measurement/zzfg;
    //   4022: invokevirtual 374	com/google/android/gms/internal/measurement/zzfg:zzim	()Lcom/google/android/gms/internal/measurement/zzfi;
    //   4025: ldc_w 691
    //   4028: aload_1
    //   4029: invokestatic 432	com/google/android/gms/internal/measurement/zzfg:zzbm	(Ljava/lang/String;)Ljava/lang/Object;
    //   4032: aload_2
    //   4033: invokevirtual 299	com/google/android/gms/internal/measurement/zzfi:zze	(Ljava/lang/String;Ljava/lang/Object;Ljava/lang/Object;)V
    //   4036: iload 10
    //   4038: istore 15
    //   4040: goto -321 -> 3719
    //   4043: astore_2
    //   4044: aload 13
    //   4046: invokevirtual 99	com/google/android/gms/internal/measurement/zzhg:zzge	()Lcom/google/android/gms/internal/measurement/zzfg;
    //   4049: invokevirtual 374	com/google/android/gms/internal/measurement/zzfg:zzim	()Lcom/google/android/gms/internal/measurement/zzfi;
    //   4052: ldc_w 693
    //   4055: aload_1
    //   4056: invokestatic 432	com/google/android/gms/internal/measurement/zzfg:zzbm	(Ljava/lang/String;)Ljava/lang/Object;
    //   4059: aload_2
    //   4060: invokevirtual 299	com/google/android/gms/internal/measurement/zzfi:zze	(Ljava/lang/String;Ljava/lang/Object;Ljava/lang/Object;)V
    //   4063: iload 10
    //   4065: istore 15
    //   4067: goto -348 -> 3719
    //   4070: aload 14
    //   4072: iload 15
    //   4074: invokestatic 468	java/util/Arrays:copyOf	([Ljava/lang/Object;I)[Ljava/lang/Object;
    //   4077: checkcast 695	[Lcom/google/android/gms/internal/measurement/zzkm;
    //   4080: astore_1
    //   4081: ldc 225
    //   4083: invokestatic 37	com/tencent/matrix/trace/core/AppMethodBeat:o	(I)V
    //   4086: aload_1
    //   4087: areturn
    //   4088: goto -303 -> 3785
    //   4091: goto -1278 -> 2813
    //   4094: aload 8
    //   4096: astore 9
    //   4098: aload 12
    //   4100: astore 21
    //   4102: aload 13
    //   4104: astore 12
    //   4106: aload 14
    //   4108: astore 8
    //   4110: aload 21
    //   4112: astore 13
    //   4114: goto -3195 -> 919
    //   4117: goto -3454 -> 663
    //   4120: goto -2636 -> 1484
    //   4123: aload 13
    //   4125: astore 14
    //   4127: aload 12
    //   4129: astore 13
    //   4131: aload 14
    //   4133: astore 12
    //   4135: goto -3600 -> 535
    //   4138: goto -3063 -> 1075
    //   4141: goto -3338 -> 803
    //
    // Exception table:
    //   from	to	target	type
    //   702	721	809	android/database/sqlite/SQLiteException
    //   3900	3929	4016	java/io/IOException
    //   3969	4009	4043	android/database/sqlite/SQLiteException
  }

  protected final boolean zzhf()
  {
    return false;
  }
}

/* Location:           C:\Users\Lin\Downloads\dex-tools-2.1-SNAPSHOT\dex-tools-2.1-SNAPSHOT\classes3-dex2jar.jar
 * Qualified Name:     com.google.android.gms.internal.measurement.zzeb
 * JD-Core Version:    0.6.2
 */