package com.tencent.xweb.xwalk.b;

import com.tencent.matrix.trace.core.AppMethodBeat;
import java.io.File;
import org.w3c.dom.Element;
import org.w3c.dom.NodeList;
import org.xwalk.core.XWalkInitializer;

public final class a
{
  private static int a(Element paramElement, String paramString)
  {
    int i = 0;
    AppMethodBeat.i(85448);
    if (paramElement == null)
      AppMethodBeat.o(85448);
    while (true)
    {
      return i;
      paramElement = paramElement.getAttribute(paramString);
      if ((paramElement == null) || (paramElement.isEmpty()))
      {
        AppMethodBeat.o(85448);
      }
      else
      {
        i = Integer.parseInt(paramElement);
        AppMethodBeat.o(85448);
      }
    }
  }

  // ERROR //
  public static String a(File paramFile, int paramInt, String paramString)
  {
    // Byte code:
    //   0: iconst_0
    //   1: istore_3
    //   2: aconst_null
    //   3: astore 4
    //   5: ldc 51
    //   7: invokestatic 25	com/tencent/matrix/trace/core/AppMethodBeat:i	(I)V
    //   10: iload_1
    //   11: newarray byte
    //   13: astore 5
    //   15: new 53	java/io/FileInputStream
    //   18: astore 6
    //   20: aload 6
    //   22: aload_0
    //   23: invokespecial 57	java/io/FileInputStream:<init>	(Ljava/io/File;)V
    //   26: aload 6
    //   28: aload 5
    //   30: iconst_0
    //   31: aload 5
    //   33: arraylength
    //   34: invokevirtual 61	java/io/FileInputStream:read	([BII)I
    //   37: istore_1
    //   38: aload 5
    //   40: arraylength
    //   41: istore 7
    //   43: iload_1
    //   44: iload 7
    //   46: if_icmpeq +29 -> 75
    //   49: aload 6
    //   51: invokevirtual 65	java/io/FileInputStream:close	()V
    //   54: ldc 51
    //   56: invokestatic 28	com/tencent/matrix/trace/core/AppMethodBeat:o	(I)V
    //   59: aload 4
    //   61: astore_0
    //   62: aload_0
    //   63: areturn
    //   64: astore_0
    //   65: ldc 67
    //   67: ldc 69
    //   69: invokestatic 75	org/xwalk/core/Log:e	(Ljava/lang/String;Ljava/lang/String;)V
    //   72: goto -18 -> 54
    //   75: new 36	java/lang/String
    //   78: astore_0
    //   79: aload_0
    //   80: aload 5
    //   82: iconst_0
    //   83: iload_1
    //   84: invokespecial 78	java/lang/String:<init>	([BII)V
    //   87: aload_0
    //   88: aload_2
    //   89: invokevirtual 81	java/lang/String:indexOf	(Ljava/lang/String;)I
    //   92: istore_1
    //   93: iload_1
    //   94: ifge +30 -> 124
    //   97: aload 6
    //   99: invokevirtual 65	java/io/FileInputStream:close	()V
    //   102: ldc 51
    //   104: invokestatic 28	com/tencent/matrix/trace/core/AppMethodBeat:o	(I)V
    //   107: aload 4
    //   109: astore_0
    //   110: goto -48 -> 62
    //   113: astore_0
    //   114: ldc 67
    //   116: ldc 69
    //   118: invokestatic 75	org/xwalk/core/Log:e	(Ljava/lang/String;Ljava/lang/String;)V
    //   121: goto -19 -> 102
    //   124: aload_0
    //   125: iload_1
    //   126: invokevirtual 85	java/lang/String:substring	(I)Ljava/lang/String;
    //   129: astore_0
    //   130: ldc 87
    //   132: invokestatic 93	java/security/MessageDigest:getInstance	(Ljava/lang/String;)Ljava/security/MessageDigest;
    //   135: aload_0
    //   136: invokevirtual 97	java/lang/String:getBytes	()[B
    //   139: invokevirtual 101	java/security/MessageDigest:digest	([B)[B
    //   142: astore_2
    //   143: aload_2
    //   144: ifnull +10 -> 154
    //   147: aload_2
    //   148: arraylength
    //   149: istore_1
    //   150: iload_1
    //   151: ifne +30 -> 181
    //   154: aload 6
    //   156: invokevirtual 65	java/io/FileInputStream:close	()V
    //   159: ldc 51
    //   161: invokestatic 28	com/tencent/matrix/trace/core/AppMethodBeat:o	(I)V
    //   164: aload 4
    //   166: astore_0
    //   167: goto -105 -> 62
    //   170: astore_0
    //   171: ldc 67
    //   173: ldc 69
    //   175: invokestatic 75	org/xwalk/core/Log:e	(Ljava/lang/String;Ljava/lang/String;)V
    //   178: goto -19 -> 159
    //   181: new 103	java/lang/StringBuilder
    //   184: astore 5
    //   186: aload 5
    //   188: aload_2
    //   189: arraylength
    //   190: invokespecial 105	java/lang/StringBuilder:<init>	(I)V
    //   193: aload_2
    //   194: arraylength
    //   195: istore 7
    //   197: iload_3
    //   198: istore_1
    //   199: iload_1
    //   200: iload 7
    //   202: if_icmpge +42 -> 244
    //   205: aload_2
    //   206: iload_1
    //   207: baload
    //   208: sipush 255
    //   211: iand
    //   212: invokestatic 108	java/lang/Integer:toHexString	(I)Ljava/lang/String;
    //   215: astore_0
    //   216: aload_0
    //   217: invokevirtual 112	java/lang/String:length	()I
    //   220: iconst_1
    //   221: if_icmpne +10 -> 231
    //   224: aload 5
    //   226: iconst_0
    //   227: invokevirtual 116	java/lang/StringBuilder:append	(I)Ljava/lang/StringBuilder;
    //   230: pop
    //   231: aload 5
    //   233: aload_0
    //   234: invokevirtual 119	java/lang/StringBuilder:append	(Ljava/lang/String;)Ljava/lang/StringBuilder;
    //   237: pop
    //   238: iinc 1 1
    //   241: goto -42 -> 199
    //   244: aload 5
    //   246: invokevirtual 123	java/lang/StringBuilder:toString	()Ljava/lang/String;
    //   249: invokevirtual 126	java/lang/String:toUpperCase	()Ljava/lang/String;
    //   252: astore_0
    //   253: aload 6
    //   255: invokevirtual 65	java/io/FileInputStream:close	()V
    //   258: ldc 51
    //   260: invokestatic 28	com/tencent/matrix/trace/core/AppMethodBeat:o	(I)V
    //   263: goto -201 -> 62
    //   266: astore_2
    //   267: ldc 67
    //   269: ldc 69
    //   271: invokestatic 75	org/xwalk/core/Log:e	(Ljava/lang/String;Ljava/lang/String;)V
    //   274: goto -16 -> 258
    //   277: astore_0
    //   278: aconst_null
    //   279: astore 6
    //   281: aload 6
    //   283: ifnull +8 -> 291
    //   286: aload 6
    //   288: invokevirtual 65	java/io/FileInputStream:close	()V
    //   291: ldc 51
    //   293: invokestatic 28	com/tencent/matrix/trace/core/AppMethodBeat:o	(I)V
    //   296: aload 4
    //   298: astore_0
    //   299: goto -237 -> 62
    //   302: astore_0
    //   303: ldc 67
    //   305: ldc 69
    //   307: invokestatic 75	org/xwalk/core/Log:e	(Ljava/lang/String;Ljava/lang/String;)V
    //   310: goto -19 -> 291
    //   313: astore_0
    //   314: aconst_null
    //   315: astore_2
    //   316: aload_2
    //   317: ifnull +7 -> 324
    //   320: aload_2
    //   321: invokevirtual 65	java/io/FileInputStream:close	()V
    //   324: ldc 51
    //   326: invokestatic 28	com/tencent/matrix/trace/core/AppMethodBeat:o	(I)V
    //   329: aload_0
    //   330: athrow
    //   331: astore_2
    //   332: ldc 67
    //   334: ldc 69
    //   336: invokestatic 75	org/xwalk/core/Log:e	(Ljava/lang/String;Ljava/lang/String;)V
    //   339: goto -15 -> 324
    //   342: astore_0
    //   343: aload 6
    //   345: astore_2
    //   346: goto -30 -> 316
    //   349: astore_0
    //   350: goto -69 -> 281
    //
    // Exception table:
    //   from	to	target	type
    //   49	54	64	java/lang/Exception
    //   97	102	113	java/lang/Exception
    //   154	159	170	java/lang/Exception
    //   253	258	266	java/lang/Exception
    //   10	26	277	java/lang/Exception
    //   286	291	302	java/lang/Exception
    //   10	26	313	finally
    //   320	324	331	java/lang/Exception
    //   26	43	342	finally
    //   75	93	342	finally
    //   124	143	342	finally
    //   147	150	342	finally
    //   181	197	342	finally
    //   205	231	342	finally
    //   231	238	342	finally
    //   244	253	342	finally
    //   26	43	349	java/lang/Exception
    //   75	93	349	java/lang/Exception
    //   124	143	349	java/lang/Exception
    //   147	150	349	java/lang/Exception
    //   181	197	349	java/lang/Exception
    //   205	231	349	java/lang/Exception
    //   231	238	349	java/lang/Exception
    //   244	253	349	java/lang/Exception
  }

  private static void a(a.a parama, Element paramElement)
  {
    AppMethodBeat.i(85451);
    if (paramElement == null)
      AppMethodBeat.o(85451);
    while (true)
    {
      return;
      try
      {
        paramElement = paramElement.getElementsByTagName("command");
        if ((paramElement != null) && (paramElement.getLength() != 0))
        {
          parama.ATe = new com.tencent.xweb.c.a.a[paramElement.getLength()];
          for (int i = 0; i < paramElement.getLength(); i++)
          {
            com.tencent.xweb.c.a.a locala = new com/tencent/xweb/c/a$a;
            locala.<init>();
            Element localElement = (Element)paramElement.item(i);
            locala.AOK.AOQ = a(localElement, "apkMin");
            locala.AOK.AOR = a(localElement, "apkMax");
            locala.AOK.AOO = a(localElement, "sdkMin");
            locala.AOK.AOP = a(localElement, "sdkMax");
            locala.AOK.AOS = a(localElement, "apiMin");
            locala.AOK.AOT = a(localElement, "apiMax");
            locala.AOK.AOU = localElement.getAttribute("forbidDeviceRegex");
            locala.AOK.AOV = localElement.getAttribute("whiteDeviceRegex");
            locala.AOK.APb = localElement.getAttribute("forbidAppRegex");
            locala.AOK.APc = localElement.getAttribute("whiteAppRegex");
            locala.AOK.AOW = a(localElement, "grayMin");
            locala.AOK.AOX = a(localElement, "grayMax");
            locala.AOK.AOY = a(localElement, "chromeMin");
            locala.AOK.AOZ = a(localElement, "chromeMax");
            locala.AOK.APa = a(localElement, "usertype");
            locala.AOL = localElement.getAttribute("optype");
            locala.AOM = localElement.getAttribute("opvalue");
            locala.AON = localElement.getAttribute("module");
            locala.AOK.APd = a(localElement, "x5sdkmin");
            locala.AOK.APe = a(localElement, "x5sdkmax");
            locala.AOK.APf = a(localElement, "x5coremin");
            locala.AOK.APg = a(localElement, "x5coremax");
            parama.ATe[i] = locala;
          }
        }
        AppMethodBeat.o(85451);
      }
      catch (Exception parama)
      {
        AppMethodBeat.o(85451);
      }
    }
  }

  private static a.b[] a(Element paramElement)
  {
    AppMethodBeat.i(85450);
    NodeList localNodeList = paramElement.getElementsByTagName("Patch");
    if ((localNodeList != null) && (localNodeList.getLength() != 0))
    {
      paramElement = new a.b[localNodeList.getLength()];
      for (int i = 0; i < localNodeList.getLength(); i++)
      {
        a.b localb = new a.b();
        Element localElement = (Element)localNodeList.item(i);
        localb.ATg = localElement.getAttribute("url");
        localb.ATf = a(localElement, "targetVersion");
        localb.ATb = localElement.getAttribute("md5");
        localb.ATh = b(localElement, "useCellular");
        localb.bUseCdn = b(localElement, "useCdn");
        paramElement[i] = localb;
      }
      AppMethodBeat.o(85450);
    }
    while (true)
    {
      return paramElement;
      paramElement = null;
      AppMethodBeat.o(85450);
    }
  }

  public static a.a avv(String paramString)
  {
    Object localObject = null;
    AppMethodBeat.i(85446);
    if (paramString == null)
    {
      XWalkInitializer.addXWalkInitializeLog("parse config failed ,path is empty");
      AppMethodBeat.o(85446);
      paramString = localObject;
    }
    while (true)
    {
      return paramString;
      paramString = new File(paramString);
      if (!paramString.exists())
      {
        XWalkInitializer.addXWalkInitializeLog("parse config failed ,file not exist");
        AppMethodBeat.o(85446);
        paramString = localObject;
      }
      else
      {
        paramString = j(paramString, a(paramString, (int)paramString.length(), "<Versions>"));
        AppMethodBeat.o(85446);
      }
    }
  }

  private static boolean b(Element paramElement, String paramString)
  {
    boolean bool = false;
    AppMethodBeat.i(85449);
    if (paramElement == null)
      AppMethodBeat.o(85449);
    while (true)
    {
      return bool;
      paramElement = paramElement.getAttribute(paramString);
      if ((paramElement == null) || (paramElement.isEmpty()))
      {
        AppMethodBeat.o(85449);
      }
      else
      {
        bool = Boolean.parseBoolean(paramElement);
        AppMethodBeat.o(85449);
      }
    }
  }

  // ERROR //
  private static a.a j(File paramFile, String paramString)
  {
    // Byte code:
    //   0: ldc_w 351
    //   3: invokestatic 25	com/tencent/matrix/trace/core/AppMethodBeat:i	(I)V
    //   6: invokestatic 357	javax/xml/parsers/DocumentBuilderFactory:newInstance	()Ljavax/xml/parsers/DocumentBuilderFactory;
    //   9: astore_2
    //   10: new 53	java/io/FileInputStream
    //   13: astore_3
    //   14: aload_3
    //   15: aload_0
    //   16: invokespecial 57	java/io/FileInputStream:<init>	(Ljava/io/File;)V
    //   19: aload_3
    //   20: astore_0
    //   21: new 6	com/tencent/xweb/xwalk/b/a$a
    //   24: astore 4
    //   26: aload_3
    //   27: astore_0
    //   28: aload 4
    //   30: invokespecial 358	com/tencent/xweb/xwalk/b/a$a:<init>	()V
    //   33: aload_3
    //   34: astore_0
    //   35: aload_2
    //   36: invokevirtual 362	javax/xml/parsers/DocumentBuilderFactory:newDocumentBuilder	()Ljavax/xml/parsers/DocumentBuilder;
    //   39: aload_3
    //   40: invokevirtual 368	javax/xml/parsers/DocumentBuilder:parse	(Ljava/io/InputStream;)Lorg/w3c/dom/Document;
    //   43: invokeinterface 374 1 0
    //   48: astore_2
    //   49: aload_2
    //   50: ifnonnull +37 -> 87
    //   53: aload_3
    //   54: astore_0
    //   55: ldc_w 376
    //   58: invokestatic 317	org/xwalk/core/XWalkInitializer:addXWalkInitializeLog	(Ljava/lang/String;)V
    //   61: aload_3
    //   62: invokevirtual 65	java/io/FileInputStream:close	()V
    //   65: ldc_w 351
    //   68: invokestatic 28	com/tencent/matrix/trace/core/AppMethodBeat:o	(I)V
    //   71: aconst_null
    //   72: astore_0
    //   73: aload_0
    //   74: areturn
    //   75: astore_0
    //   76: ldc 67
    //   78: ldc_w 378
    //   81: invokestatic 75	org/xwalk/core/Log:e	(Ljava/lang/String;Ljava/lang/String;)V
    //   84: goto -19 -> 65
    //   87: aload_3
    //   88: astore_0
    //   89: aload 4
    //   91: aload_2
    //   92: ldc_w 380
    //   95: invokeinterface 34 2 0
    //   100: putfield 381	com/tencent/xweb/xwalk/b/a$a:ATb	Ljava/lang/String;
    //   103: aload_3
    //   104: astore_0
    //   105: aload 4
    //   107: getfield 381	com/tencent/xweb/xwalk/b/a$a:ATb	Ljava/lang/String;
    //   110: ifnull +17 -> 127
    //   113: aload_3
    //   114: astore_0
    //   115: aload 4
    //   117: getfield 381	com/tencent/xweb/xwalk/b/a$a:ATb	Ljava/lang/String;
    //   120: aload_1
    //   121: invokevirtual 384	java/lang/String:equalsIgnoreCase	(Ljava/lang/String;)Z
    //   124: ifne +46 -> 170
    //   127: aload_3
    //   128: astore_0
    //   129: ldc2_w 385
    //   132: invokestatic 392	com/tencent/xweb/util/f:nI	(J)V
    //   135: aload_3
    //   136: astore_0
    //   137: ldc_w 394
    //   140: invokestatic 317	org/xwalk/core/XWalkInitializer:addXWalkInitializeLog	(Ljava/lang/String;)V
    //   143: aload_3
    //   144: invokevirtual 65	java/io/FileInputStream:close	()V
    //   147: ldc_w 351
    //   150: invokestatic 28	com/tencent/matrix/trace/core/AppMethodBeat:o	(I)V
    //   153: aconst_null
    //   154: astore_0
    //   155: goto -82 -> 73
    //   158: astore_0
    //   159: ldc 67
    //   161: ldc_w 378
    //   164: invokestatic 75	org/xwalk/core/Log:e	(Ljava/lang/String;Ljava/lang/String;)V
    //   167: goto -20 -> 147
    //   170: aload_3
    //   171: astore_0
    //   172: aload 4
    //   174: aload_2
    //   175: ldc_w 396
    //   178: invokeinterface 34 2 0
    //   183: putfield 399	com/tencent/xweb/xwalk/b/a$a:ATc	Ljava/lang/String;
    //   186: aload_3
    //   187: astore_0
    //   188: aload 4
    //   190: aload_2
    //   191: invokestatic 401	com/tencent/xweb/xwalk/b/a:a	(Lcom/tencent/xweb/xwalk/b/a$a;Lorg/w3c/dom/Element;)V
    //   194: aload_3
    //   195: astore_0
    //   196: aload_2
    //   197: ldc_w 403
    //   200: invokeinterface 134 2 0
    //   205: astore 5
    //   207: aload 5
    //   209: ifnull +555 -> 764
    //   212: aload_3
    //   213: astore_0
    //   214: aload 5
    //   216: invokeinterface 139 1 0
    //   221: ifeq +543 -> 764
    //   224: aload_3
    //   225: astore_0
    //   226: aload 4
    //   228: aload 5
    //   230: invokeinterface 139 1 0
    //   235: anewarray 14	com/tencent/xweb/xwalk/b/a$e
    //   238: putfield 407	com/tencent/xweb/xwalk/b/a$a:ATd	[Lcom/tencent/xweb/xwalk/b/a$e;
    //   241: iconst_0
    //   242: istore 6
    //   244: aload_3
    //   245: astore_0
    //   246: iload 6
    //   248: aload 5
    //   250: invokeinterface 139 1 0
    //   255: if_icmpge +509 -> 764
    //   258: aload_3
    //   259: astore_0
    //   260: new 14	com/tencent/xweb/xwalk/b/a$e
    //   263: astore_2
    //   264: aload_3
    //   265: astore_0
    //   266: aload_2
    //   267: invokespecial 408	com/tencent/xweb/xwalk/b/a$e:<init>	()V
    //   270: aload_3
    //   271: astore_0
    //   272: aload 5
    //   274: iload 6
    //   276: invokeinterface 151 2 0
    //   281: checkcast 30	org/w3c/dom/Element
    //   284: astore_1
    //   285: aload_3
    //   286: astore_0
    //   287: aload_2
    //   288: aload_1
    //   289: ldc_w 410
    //   292: invokeinterface 34 2 0
    //   297: putfield 411	com/tencent/xweb/xwalk/b/a$e:ATg	Ljava/lang/String;
    //   300: aload_3
    //   301: astore_0
    //   302: aload_2
    //   303: aload_1
    //   304: ldc_w 288
    //   307: invokeinterface 34 2 0
    //   312: putfield 412	com/tencent/xweb/xwalk/b/a$e:ATb	Ljava/lang/String;
    //   315: aload_3
    //   316: astore_0
    //   317: aload_2
    //   318: getfield 413	com/tencent/xweb/xwalk/b/a$e:AOK	Lcom/tencent/xweb/c/a$b;
    //   321: aload_1
    //   322: ldc 192
    //   324: invokeinterface 34 2 0
    //   329: putfield 196	com/tencent/xweb/c/a$b:AOU	Ljava/lang/String;
    //   332: aload_3
    //   333: astore_0
    //   334: aload_2
    //   335: getfield 413	com/tencent/xweb/xwalk/b/a$e:AOK	Lcom/tencent/xweb/c/a$b;
    //   338: aload_1
    //   339: ldc 198
    //   341: invokeinterface 34 2 0
    //   346: putfield 201	com/tencent/xweb/c/a$b:AOV	Ljava/lang/String;
    //   349: aload_3
    //   350: astore_0
    //   351: aload_2
    //   352: getfield 413	com/tencent/xweb/xwalk/b/a$e:AOK	Lcom/tencent/xweb/c/a$b;
    //   355: aload_1
    //   356: ldc 157
    //   358: invokestatic 159	com/tencent/xweb/xwalk/b/a:a	(Lorg/w3c/dom/Element;Ljava/lang/String;)I
    //   361: putfield 165	com/tencent/xweb/c/a$b:AOQ	I
    //   364: aload_3
    //   365: astore_0
    //   366: aload_2
    //   367: getfield 413	com/tencent/xweb/xwalk/b/a$e:AOK	Lcom/tencent/xweb/c/a$b;
    //   370: aload_1
    //   371: ldc 167
    //   373: invokestatic 159	com/tencent/xweb/xwalk/b/a:a	(Lorg/w3c/dom/Element;Ljava/lang/String;)I
    //   376: putfield 170	com/tencent/xweb/c/a$b:AOR	I
    //   379: aload_3
    //   380: astore_0
    //   381: aload_2
    //   382: getfield 413	com/tencent/xweb/xwalk/b/a$e:AOK	Lcom/tencent/xweb/c/a$b;
    //   385: aload_1
    //   386: ldc 172
    //   388: invokestatic 159	com/tencent/xweb/xwalk/b/a:a	(Lorg/w3c/dom/Element;Ljava/lang/String;)I
    //   391: putfield 175	com/tencent/xweb/c/a$b:AOO	I
    //   394: aload_3
    //   395: astore_0
    //   396: aload_2
    //   397: getfield 413	com/tencent/xweb/xwalk/b/a$e:AOK	Lcom/tencent/xweb/c/a$b;
    //   400: aload_1
    //   401: ldc 177
    //   403: invokestatic 159	com/tencent/xweb/xwalk/b/a:a	(Lorg/w3c/dom/Element;Ljava/lang/String;)I
    //   406: putfield 180	com/tencent/xweb/c/a$b:AOP	I
    //   409: aload_3
    //   410: astore_0
    //   411: aload_2
    //   412: getfield 413	com/tencent/xweb/xwalk/b/a$e:AOK	Lcom/tencent/xweb/c/a$b;
    //   415: aload_1
    //   416: ldc 182
    //   418: invokestatic 159	com/tencent/xweb/xwalk/b/a:a	(Lorg/w3c/dom/Element;Ljava/lang/String;)I
    //   421: putfield 185	com/tencent/xweb/c/a$b:AOS	I
    //   424: aload_3
    //   425: astore_0
    //   426: aload_2
    //   427: getfield 413	com/tencent/xweb/xwalk/b/a$e:AOK	Lcom/tencent/xweb/c/a$b;
    //   430: aload_1
    //   431: ldc 187
    //   433: invokestatic 159	com/tencent/xweb/xwalk/b/a:a	(Lorg/w3c/dom/Element;Ljava/lang/String;)I
    //   436: putfield 190	com/tencent/xweb/c/a$b:AOT	I
    //   439: aload_3
    //   440: astore_0
    //   441: aload_2
    //   442: aload_1
    //   443: ldc_w 415
    //   446: invokestatic 159	com/tencent/xweb/xwalk/b/a:a	(Lorg/w3c/dom/Element;Ljava/lang/String;)I
    //   449: putfield 418	com/tencent/xweb/xwalk/b/a$e:ATl	I
    //   452: aload_3
    //   453: astore_0
    //   454: aload_2
    //   455: aload_1
    //   456: ldc_w 420
    //   459: invokestatic 159	com/tencent/xweb/xwalk/b/a:a	(Lorg/w3c/dom/Element;Ljava/lang/String;)I
    //   462: putfield 423	com/tencent/xweb/xwalk/b/a$e:ATn	I
    //   465: aload_3
    //   466: astore_0
    //   467: aload_2
    //   468: aload_1
    //   469: ldc_w 293
    //   472: invokestatic 297	com/tencent/xweb/xwalk/b/a:b	(Lorg/w3c/dom/Element;Ljava/lang/String;)Z
    //   475: putfield 424	com/tencent/xweb/xwalk/b/a$e:ATh	Z
    //   478: aload_3
    //   479: astore_0
    //   480: aload_2
    //   481: getfield 413	com/tencent/xweb/xwalk/b/a$e:AOK	Lcom/tencent/xweb/c/a$b;
    //   484: aload_1
    //   485: ldc 213
    //   487: invokestatic 159	com/tencent/xweb/xwalk/b/a:a	(Lorg/w3c/dom/Element;Ljava/lang/String;)I
    //   490: putfield 216	com/tencent/xweb/c/a$b:AOW	I
    //   493: aload_3
    //   494: astore_0
    //   495: aload_2
    //   496: getfield 413	com/tencent/xweb/xwalk/b/a$e:AOK	Lcom/tencent/xweb/c/a$b;
    //   499: aload_1
    //   500: ldc 218
    //   502: invokestatic 159	com/tencent/xweb/xwalk/b/a:a	(Lorg/w3c/dom/Element;Ljava/lang/String;)I
    //   505: putfield 221	com/tencent/xweb/c/a$b:AOX	I
    //   508: aload_3
    //   509: astore_0
    //   510: aload_2
    //   511: getfield 413	com/tencent/xweb/xwalk/b/a$e:AOK	Lcom/tencent/xweb/c/a$b;
    //   514: aload_1
    //   515: ldc 223
    //   517: invokestatic 159	com/tencent/xweb/xwalk/b/a:a	(Lorg/w3c/dom/Element;Ljava/lang/String;)I
    //   520: putfield 226	com/tencent/xweb/c/a$b:AOY	I
    //   523: aload_3
    //   524: astore_0
    //   525: aload_2
    //   526: getfield 413	com/tencent/xweb/xwalk/b/a$e:AOK	Lcom/tencent/xweb/c/a$b;
    //   529: aload_1
    //   530: ldc 228
    //   532: invokestatic 159	com/tencent/xweb/xwalk/b/a:a	(Lorg/w3c/dom/Element;Ljava/lang/String;)I
    //   535: putfield 231	com/tencent/xweb/c/a$b:AOZ	I
    //   538: aload_3
    //   539: astore_0
    //   540: aload_2
    //   541: getfield 413	com/tencent/xweb/xwalk/b/a$e:AOK	Lcom/tencent/xweb/c/a$b;
    //   544: aload_1
    //   545: ldc 233
    //   547: invokestatic 159	com/tencent/xweb/xwalk/b/a:a	(Lorg/w3c/dom/Element;Ljava/lang/String;)I
    //   550: putfield 236	com/tencent/xweb/c/a$b:APa	I
    //   553: aload_3
    //   554: astore_0
    //   555: aload_2
    //   556: aload_1
    //   557: ldc_w 303
    //   560: invokestatic 297	com/tencent/xweb/xwalk/b/a:b	(Lorg/w3c/dom/Element;Ljava/lang/String;)Z
    //   563: putfield 425	com/tencent/xweb/xwalk/b/a$e:bUseCdn	Z
    //   566: aload_3
    //   567: astore_0
    //   568: aload_2
    //   569: getfield 413	com/tencent/xweb/xwalk/b/a$e:AOK	Lcom/tencent/xweb/c/a$b;
    //   572: aload_1
    //   573: ldc 253
    //   575: invokestatic 159	com/tencent/xweb/xwalk/b/a:a	(Lorg/w3c/dom/Element;Ljava/lang/String;)I
    //   578: putfield 256	com/tencent/xweb/c/a$b:APd	I
    //   581: aload_3
    //   582: astore_0
    //   583: aload_2
    //   584: getfield 413	com/tencent/xweb/xwalk/b/a$e:AOK	Lcom/tencent/xweb/c/a$b;
    //   587: aload_1
    //   588: ldc_w 258
    //   591: invokestatic 159	com/tencent/xweb/xwalk/b/a:a	(Lorg/w3c/dom/Element;Ljava/lang/String;)I
    //   594: putfield 261	com/tencent/xweb/c/a$b:APe	I
    //   597: aload_3
    //   598: astore_0
    //   599: aload_2
    //   600: getfield 413	com/tencent/xweb/xwalk/b/a$e:AOK	Lcom/tencent/xweb/c/a$b;
    //   603: aload_1
    //   604: ldc_w 263
    //   607: invokestatic 159	com/tencent/xweb/xwalk/b/a:a	(Lorg/w3c/dom/Element;Ljava/lang/String;)I
    //   610: putfield 266	com/tencent/xweb/c/a$b:APf	I
    //   613: aload_3
    //   614: astore_0
    //   615: aload_2
    //   616: getfield 413	com/tencent/xweb/xwalk/b/a$e:AOK	Lcom/tencent/xweb/c/a$b;
    //   619: aload_1
    //   620: ldc_w 268
    //   623: invokestatic 159	com/tencent/xweb/xwalk/b/a:a	(Lorg/w3c/dom/Element;Ljava/lang/String;)I
    //   626: putfield 271	com/tencent/xweb/c/a$b:APg	I
    //   629: aload_3
    //   630: astore_0
    //   631: aload_1
    //   632: ldc_w 427
    //   635: invokeinterface 34 2 0
    //   640: astore 7
    //   642: aload 7
    //   644: ifnull +24 -> 668
    //   647: aload_3
    //   648: astore_0
    //   649: aload 7
    //   651: invokevirtual 40	java/lang/String:isEmpty	()Z
    //   654: ifne +14 -> 668
    //   657: aload_3
    //   658: astore_0
    //   659: aload_2
    //   660: aload 7
    //   662: invokestatic 344	java/lang/Boolean:parseBoolean	(Ljava/lang/String;)Z
    //   665: putfield 430	com/tencent/xweb/xwalk/b/a$e:bTryUseSharedCore	Z
    //   668: aload_3
    //   669: astore_0
    //   670: aload_2
    //   671: getfield 434	com/tencent/xweb/xwalk/b/a$e:ATo	Lcom/tencent/xweb/xwalk/b/a$f;
    //   674: astore 7
    //   676: aload 7
    //   678: ifnull +59 -> 737
    //   681: aload_3
    //   682: astore_0
    //   683: aload_1
    //   684: ldc_w 436
    //   687: invokeinterface 134 2 0
    //   692: astore 8
    //   694: aload 8
    //   696: ifnull +41 -> 737
    //   699: aload_3
    //   700: astore_0
    //   701: aload 8
    //   703: invokeinterface 139 1 0
    //   708: ifeq +29 -> 737
    //   711: aload_3
    //   712: astore_0
    //   713: aload 7
    //   715: aload 8
    //   717: iconst_0
    //   718: invokeinterface 151 2 0
    //   723: checkcast 30	org/w3c/dom/Element
    //   726: ldc_w 438
    //   729: invokeinterface 34 2 0
    //   734: putfield 441	com/tencent/xweb/xwalk/b/a$f:ATp	Ljava/lang/String;
    //   737: aload_3
    //   738: astore_0
    //   739: aload_2
    //   740: aload_1
    //   741: invokestatic 443	com/tencent/xweb/xwalk/b/a:a	(Lorg/w3c/dom/Element;)[Lcom/tencent/xweb/xwalk/b/a$b;
    //   744: putfield 447	com/tencent/xweb/xwalk/b/a$e:ATm	[Lcom/tencent/xweb/xwalk/b/a$b;
    //   747: aload_3
    //   748: astore_0
    //   749: aload 4
    //   751: getfield 407	com/tencent/xweb/xwalk/b/a$a:ATd	[Lcom/tencent/xweb/xwalk/b/a$e;
    //   754: iload 6
    //   756: aload_2
    //   757: aastore
    //   758: iinc 6 1
    //   761: goto -517 -> 244
    //   764: aload_3
    //   765: invokevirtual 65	java/io/FileInputStream:close	()V
    //   768: aload 4
    //   770: astore_0
    //   771: ldc_w 351
    //   774: invokestatic 28	com/tencent/matrix/trace/core/AppMethodBeat:o	(I)V
    //   777: goto -704 -> 73
    //   780: astore_0
    //   781: ldc 67
    //   783: ldc_w 378
    //   786: invokestatic 75	org/xwalk/core/Log:e	(Ljava/lang/String;Ljava/lang/String;)V
    //   789: aload 4
    //   791: astore_0
    //   792: goto -21 -> 771
    //   795: astore_0
    //   796: aconst_null
    //   797: astore_3
    //   798: aconst_null
    //   799: astore_1
    //   800: aload_3
    //   801: astore_0
    //   802: ldc_w 376
    //   805: invokestatic 317	org/xwalk/core/XWalkInitializer:addXWalkInitializeLog	(Ljava/lang/String;)V
    //   808: aload_1
    //   809: astore_0
    //   810: aload_3
    //   811: ifnull -40 -> 771
    //   814: aload_3
    //   815: invokevirtual 65	java/io/FileInputStream:close	()V
    //   818: aload_1
    //   819: astore_0
    //   820: goto -49 -> 771
    //   823: astore_0
    //   824: ldc 67
    //   826: ldc_w 378
    //   829: invokestatic 75	org/xwalk/core/Log:e	(Ljava/lang/String;Ljava/lang/String;)V
    //   832: aload_1
    //   833: astore_0
    //   834: goto -63 -> 771
    //   837: astore_0
    //   838: aconst_null
    //   839: astore_3
    //   840: aconst_null
    //   841: astore_1
    //   842: aload_3
    //   843: astore_0
    //   844: ldc_w 376
    //   847: invokestatic 317	org/xwalk/core/XWalkInitializer:addXWalkInitializeLog	(Ljava/lang/String;)V
    //   850: aload_1
    //   851: astore_0
    //   852: aload_3
    //   853: ifnull -82 -> 771
    //   856: aload_3
    //   857: invokevirtual 65	java/io/FileInputStream:close	()V
    //   860: aload_1
    //   861: astore_0
    //   862: goto -91 -> 771
    //   865: astore_0
    //   866: ldc 67
    //   868: ldc_w 378
    //   871: invokestatic 75	org/xwalk/core/Log:e	(Ljava/lang/String;Ljava/lang/String;)V
    //   874: aload_1
    //   875: astore_0
    //   876: goto -105 -> 771
    //   879: astore_0
    //   880: aconst_null
    //   881: astore_3
    //   882: aconst_null
    //   883: astore_1
    //   884: aload_3
    //   885: astore_0
    //   886: ldc_w 376
    //   889: invokestatic 317	org/xwalk/core/XWalkInitializer:addXWalkInitializeLog	(Ljava/lang/String;)V
    //   892: aload_1
    //   893: astore_0
    //   894: aload_3
    //   895: ifnull -124 -> 771
    //   898: aload_3
    //   899: invokevirtual 65	java/io/FileInputStream:close	()V
    //   902: aload_1
    //   903: astore_0
    //   904: goto -133 -> 771
    //   907: astore_0
    //   908: ldc 67
    //   910: ldc_w 378
    //   913: invokestatic 75	org/xwalk/core/Log:e	(Ljava/lang/String;Ljava/lang/String;)V
    //   916: aload_1
    //   917: astore_0
    //   918: goto -147 -> 771
    //   921: astore_1
    //   922: aconst_null
    //   923: astore_0
    //   924: aload_0
    //   925: ifnull +7 -> 932
    //   928: aload_0
    //   929: invokevirtual 65	java/io/FileInputStream:close	()V
    //   932: ldc_w 351
    //   935: invokestatic 28	com/tencent/matrix/trace/core/AppMethodBeat:o	(I)V
    //   938: aload_1
    //   939: athrow
    //   940: astore_0
    //   941: ldc 67
    //   943: ldc_w 378
    //   946: invokestatic 75	org/xwalk/core/Log:e	(Ljava/lang/String;Ljava/lang/String;)V
    //   949: goto -17 -> 932
    //   952: astore_1
    //   953: goto -29 -> 924
    //   956: astore_0
    //   957: aconst_null
    //   958: astore_1
    //   959: goto -75 -> 884
    //   962: astore_0
    //   963: aload 4
    //   965: astore_1
    //   966: goto -82 -> 884
    //   969: astore_0
    //   970: aconst_null
    //   971: astore_1
    //   972: goto -130 -> 842
    //   975: astore_0
    //   976: aload 4
    //   978: astore_1
    //   979: goto -137 -> 842
    //   982: astore_0
    //   983: aconst_null
    //   984: astore_1
    //   985: goto -185 -> 800
    //   988: astore_0
    //   989: aload 4
    //   991: astore_1
    //   992: goto -192 -> 800
    //
    // Exception table:
    //   from	to	target	type
    //   61	65	75	java/lang/Exception
    //   143	147	158	java/lang/Exception
    //   764	768	780	java/lang/Exception
    //   10	19	795	javax/xml/parsers/ParserConfigurationException
    //   814	818	823	java/lang/Exception
    //   10	19	837	org/xml/sax/SAXException
    //   856	860	865	java/lang/Exception
    //   10	19	879	java/io/IOException
    //   898	902	907	java/lang/Exception
    //   10	19	921	finally
    //   928	932	940	java/lang/Exception
    //   21	26	952	finally
    //   28	33	952	finally
    //   35	49	952	finally
    //   55	61	952	finally
    //   89	103	952	finally
    //   105	113	952	finally
    //   115	127	952	finally
    //   129	135	952	finally
    //   137	143	952	finally
    //   172	186	952	finally
    //   188	194	952	finally
    //   196	207	952	finally
    //   214	224	952	finally
    //   226	241	952	finally
    //   246	258	952	finally
    //   260	264	952	finally
    //   266	270	952	finally
    //   272	285	952	finally
    //   287	300	952	finally
    //   302	315	952	finally
    //   317	332	952	finally
    //   334	349	952	finally
    //   351	364	952	finally
    //   366	379	952	finally
    //   381	394	952	finally
    //   396	409	952	finally
    //   411	424	952	finally
    //   426	439	952	finally
    //   441	452	952	finally
    //   454	465	952	finally
    //   467	478	952	finally
    //   480	493	952	finally
    //   495	508	952	finally
    //   510	523	952	finally
    //   525	538	952	finally
    //   540	553	952	finally
    //   555	566	952	finally
    //   568	581	952	finally
    //   583	597	952	finally
    //   599	613	952	finally
    //   615	629	952	finally
    //   631	642	952	finally
    //   649	657	952	finally
    //   659	668	952	finally
    //   670	676	952	finally
    //   683	694	952	finally
    //   701	711	952	finally
    //   713	737	952	finally
    //   739	747	952	finally
    //   749	758	952	finally
    //   802	808	952	finally
    //   844	850	952	finally
    //   886	892	952	finally
    //   21	26	956	java/io/IOException
    //   28	33	956	java/io/IOException
    //   35	49	962	java/io/IOException
    //   55	61	962	java/io/IOException
    //   89	103	962	java/io/IOException
    //   105	113	962	java/io/IOException
    //   115	127	962	java/io/IOException
    //   129	135	962	java/io/IOException
    //   137	143	962	java/io/IOException
    //   172	186	962	java/io/IOException
    //   188	194	962	java/io/IOException
    //   196	207	962	java/io/IOException
    //   214	224	962	java/io/IOException
    //   226	241	962	java/io/IOException
    //   246	258	962	java/io/IOException
    //   260	264	962	java/io/IOException
    //   266	270	962	java/io/IOException
    //   272	285	962	java/io/IOException
    //   287	300	962	java/io/IOException
    //   302	315	962	java/io/IOException
    //   317	332	962	java/io/IOException
    //   334	349	962	java/io/IOException
    //   351	364	962	java/io/IOException
    //   366	379	962	java/io/IOException
    //   381	394	962	java/io/IOException
    //   396	409	962	java/io/IOException
    //   411	424	962	java/io/IOException
    //   426	439	962	java/io/IOException
    //   441	452	962	java/io/IOException
    //   454	465	962	java/io/IOException
    //   467	478	962	java/io/IOException
    //   480	493	962	java/io/IOException
    //   495	508	962	java/io/IOException
    //   510	523	962	java/io/IOException
    //   525	538	962	java/io/IOException
    //   540	553	962	java/io/IOException
    //   555	566	962	java/io/IOException
    //   568	581	962	java/io/IOException
    //   583	597	962	java/io/IOException
    //   599	613	962	java/io/IOException
    //   615	629	962	java/io/IOException
    //   631	642	962	java/io/IOException
    //   649	657	962	java/io/IOException
    //   659	668	962	java/io/IOException
    //   670	676	962	java/io/IOException
    //   683	694	962	java/io/IOException
    //   701	711	962	java/io/IOException
    //   713	737	962	java/io/IOException
    //   739	747	962	java/io/IOException
    //   749	758	962	java/io/IOException
    //   21	26	969	org/xml/sax/SAXException
    //   28	33	969	org/xml/sax/SAXException
    //   35	49	975	org/xml/sax/SAXException
    //   55	61	975	org/xml/sax/SAXException
    //   89	103	975	org/xml/sax/SAXException
    //   105	113	975	org/xml/sax/SAXException
    //   115	127	975	org/xml/sax/SAXException
    //   129	135	975	org/xml/sax/SAXException
    //   137	143	975	org/xml/sax/SAXException
    //   172	186	975	org/xml/sax/SAXException
    //   188	194	975	org/xml/sax/SAXException
    //   196	207	975	org/xml/sax/SAXException
    //   214	224	975	org/xml/sax/SAXException
    //   226	241	975	org/xml/sax/SAXException
    //   246	258	975	org/xml/sax/SAXException
    //   260	264	975	org/xml/sax/SAXException
    //   266	270	975	org/xml/sax/SAXException
    //   272	285	975	org/xml/sax/SAXException
    //   287	300	975	org/xml/sax/SAXException
    //   302	315	975	org/xml/sax/SAXException
    //   317	332	975	org/xml/sax/SAXException
    //   334	349	975	org/xml/sax/SAXException
    //   351	364	975	org/xml/sax/SAXException
    //   366	379	975	org/xml/sax/SAXException
    //   381	394	975	org/xml/sax/SAXException
    //   396	409	975	org/xml/sax/SAXException
    //   411	424	975	org/xml/sax/SAXException
    //   426	439	975	org/xml/sax/SAXException
    //   441	452	975	org/xml/sax/SAXException
    //   454	465	975	org/xml/sax/SAXException
    //   467	478	975	org/xml/sax/SAXException
    //   480	493	975	org/xml/sax/SAXException
    //   495	508	975	org/xml/sax/SAXException
    //   510	523	975	org/xml/sax/SAXException
    //   525	538	975	org/xml/sax/SAXException
    //   540	553	975	org/xml/sax/SAXException
    //   555	566	975	org/xml/sax/SAXException
    //   568	581	975	org/xml/sax/SAXException
    //   583	597	975	org/xml/sax/SAXException
    //   599	613	975	org/xml/sax/SAXException
    //   615	629	975	org/xml/sax/SAXException
    //   631	642	975	org/xml/sax/SAXException
    //   649	657	975	org/xml/sax/SAXException
    //   659	668	975	org/xml/sax/SAXException
    //   670	676	975	org/xml/sax/SAXException
    //   683	694	975	org/xml/sax/SAXException
    //   701	711	975	org/xml/sax/SAXException
    //   713	737	975	org/xml/sax/SAXException
    //   739	747	975	org/xml/sax/SAXException
    //   749	758	975	org/xml/sax/SAXException
    //   21	26	982	javax/xml/parsers/ParserConfigurationException
    //   28	33	982	javax/xml/parsers/ParserConfigurationException
    //   35	49	988	javax/xml/parsers/ParserConfigurationException
    //   55	61	988	javax/xml/parsers/ParserConfigurationException
    //   89	103	988	javax/xml/parsers/ParserConfigurationException
    //   105	113	988	javax/xml/parsers/ParserConfigurationException
    //   115	127	988	javax/xml/parsers/ParserConfigurationException
    //   129	135	988	javax/xml/parsers/ParserConfigurationException
    //   137	143	988	javax/xml/parsers/ParserConfigurationException
    //   172	186	988	javax/xml/parsers/ParserConfigurationException
    //   188	194	988	javax/xml/parsers/ParserConfigurationException
    //   196	207	988	javax/xml/parsers/ParserConfigurationException
    //   214	224	988	javax/xml/parsers/ParserConfigurationException
    //   226	241	988	javax/xml/parsers/ParserConfigurationException
    //   246	258	988	javax/xml/parsers/ParserConfigurationException
    //   260	264	988	javax/xml/parsers/ParserConfigurationException
    //   266	270	988	javax/xml/parsers/ParserConfigurationException
    //   272	285	988	javax/xml/parsers/ParserConfigurationException
    //   287	300	988	javax/xml/parsers/ParserConfigurationException
    //   302	315	988	javax/xml/parsers/ParserConfigurationException
    //   317	332	988	javax/xml/parsers/ParserConfigurationException
    //   334	349	988	javax/xml/parsers/ParserConfigurationException
    //   351	364	988	javax/xml/parsers/ParserConfigurationException
    //   366	379	988	javax/xml/parsers/ParserConfigurationException
    //   381	394	988	javax/xml/parsers/ParserConfigurationException
    //   396	409	988	javax/xml/parsers/ParserConfigurationException
    //   411	424	988	javax/xml/parsers/ParserConfigurationException
    //   426	439	988	javax/xml/parsers/ParserConfigurationException
    //   441	452	988	javax/xml/parsers/ParserConfigurationException
    //   454	465	988	javax/xml/parsers/ParserConfigurationException
    //   467	478	988	javax/xml/parsers/ParserConfigurationException
    //   480	493	988	javax/xml/parsers/ParserConfigurationException
    //   495	508	988	javax/xml/parsers/ParserConfigurationException
    //   510	523	988	javax/xml/parsers/ParserConfigurationException
    //   525	538	988	javax/xml/parsers/ParserConfigurationException
    //   540	553	988	javax/xml/parsers/ParserConfigurationException
    //   555	566	988	javax/xml/parsers/ParserConfigurationException
    //   568	581	988	javax/xml/parsers/ParserConfigurationException
    //   583	597	988	javax/xml/parsers/ParserConfigurationException
    //   599	613	988	javax/xml/parsers/ParserConfigurationException
    //   615	629	988	javax/xml/parsers/ParserConfigurationException
    //   631	642	988	javax/xml/parsers/ParserConfigurationException
    //   649	657	988	javax/xml/parsers/ParserConfigurationException
    //   659	668	988	javax/xml/parsers/ParserConfigurationException
    //   670	676	988	javax/xml/parsers/ParserConfigurationException
    //   683	694	988	javax/xml/parsers/ParserConfigurationException
    //   701	711	988	javax/xml/parsers/ParserConfigurationException
    //   713	737	988	javax/xml/parsers/ParserConfigurationException
    //   739	747	988	javax/xml/parsers/ParserConfigurationException
    //   749	758	988	javax/xml/parsers/ParserConfigurationException
  }

  // ERROR //
  public static a.c k(File paramFile, String paramString)
  {
    // Byte code:
    //   0: ldc_w 450
    //   3: invokestatic 25	com/tencent/matrix/trace/core/AppMethodBeat:i	(I)V
    //   6: invokestatic 357	javax/xml/parsers/DocumentBuilderFactory:newInstance	()Ljavax/xml/parsers/DocumentBuilderFactory;
    //   9: astore_2
    //   10: new 53	java/io/FileInputStream
    //   13: astore_3
    //   14: aload_3
    //   15: aload_0
    //   16: invokespecial 57	java/io/FileInputStream:<init>	(Ljava/io/File;)V
    //   19: aload_3
    //   20: astore_0
    //   21: new 10	com/tencent/xweb/xwalk/b/a$c
    //   24: astore 4
    //   26: aload_3
    //   27: astore_0
    //   28: aload 4
    //   30: invokespecial 451	com/tencent/xweb/xwalk/b/a$c:<init>	()V
    //   33: aload_3
    //   34: astore_0
    //   35: aload_2
    //   36: invokevirtual 362	javax/xml/parsers/DocumentBuilderFactory:newDocumentBuilder	()Ljavax/xml/parsers/DocumentBuilder;
    //   39: aload_3
    //   40: invokevirtual 368	javax/xml/parsers/DocumentBuilder:parse	(Ljava/io/InputStream;)Lorg/w3c/dom/Document;
    //   43: invokeinterface 374 1 0
    //   48: astore_2
    //   49: aload_2
    //   50: ifnonnull +37 -> 87
    //   53: aload_3
    //   54: astore_0
    //   55: ldc_w 453
    //   58: invokestatic 317	org/xwalk/core/XWalkInitializer:addXWalkInitializeLog	(Ljava/lang/String;)V
    //   61: aload_3
    //   62: invokevirtual 65	java/io/FileInputStream:close	()V
    //   65: ldc_w 450
    //   68: invokestatic 28	com/tencent/matrix/trace/core/AppMethodBeat:o	(I)V
    //   71: aconst_null
    //   72: astore_0
    //   73: aload_0
    //   74: areturn
    //   75: astore_0
    //   76: ldc 67
    //   78: ldc_w 455
    //   81: invokestatic 75	org/xwalk/core/Log:e	(Ljava/lang/String;Ljava/lang/String;)V
    //   84: goto -19 -> 65
    //   87: aload_3
    //   88: astore_0
    //   89: aload 4
    //   91: aload_2
    //   92: ldc_w 380
    //   95: invokeinterface 34 2 0
    //   100: putfield 456	com/tencent/xweb/xwalk/b/a$c:ATb	Ljava/lang/String;
    //   103: aload_3
    //   104: astore_0
    //   105: aload 4
    //   107: getfield 456	com/tencent/xweb/xwalk/b/a$c:ATb	Ljava/lang/String;
    //   110: ifnull +17 -> 127
    //   113: aload_3
    //   114: astore_0
    //   115: aload 4
    //   117: getfield 456	com/tencent/xweb/xwalk/b/a$c:ATb	Ljava/lang/String;
    //   120: aload_1
    //   121: invokevirtual 384	java/lang/String:equalsIgnoreCase	(Ljava/lang/String;)Z
    //   124: ifne +38 -> 162
    //   127: aload_3
    //   128: astore_0
    //   129: ldc_w 458
    //   132: invokestatic 317	org/xwalk/core/XWalkInitializer:addXWalkInitializeLog	(Ljava/lang/String;)V
    //   135: aload_3
    //   136: invokevirtual 65	java/io/FileInputStream:close	()V
    //   139: ldc_w 450
    //   142: invokestatic 28	com/tencent/matrix/trace/core/AppMethodBeat:o	(I)V
    //   145: aconst_null
    //   146: astore_0
    //   147: goto -74 -> 73
    //   150: astore_0
    //   151: ldc 67
    //   153: ldc_w 455
    //   156: invokestatic 75	org/xwalk/core/Log:e	(Ljava/lang/String;Ljava/lang/String;)V
    //   159: goto -20 -> 139
    //   162: aload_3
    //   163: astore_0
    //   164: aload 4
    //   166: aload_2
    //   167: ldc_w 396
    //   170: invokeinterface 34 2 0
    //   175: putfield 459	com/tencent/xweb/xwalk/b/a$c:ATc	Ljava/lang/String;
    //   178: aload_3
    //   179: astore_0
    //   180: aload_2
    //   181: ldc_w 461
    //   184: invokeinterface 134 2 0
    //   189: astore_1
    //   190: aload_1
    //   191: ifnull +522 -> 713
    //   194: aload_3
    //   195: astore_0
    //   196: aload_1
    //   197: invokeinterface 139 1 0
    //   202: ifeq +511 -> 713
    //   205: aload_3
    //   206: astore_0
    //   207: aload 4
    //   209: aload_1
    //   210: invokeinterface 139 1 0
    //   215: anewarray 12	com/tencent/xweb/xwalk/b/a$d
    //   218: putfield 465	com/tencent/xweb/xwalk/b/a$c:ATi	[Lcom/tencent/xweb/xwalk/b/a$d;
    //   221: iconst_0
    //   222: istore 5
    //   224: aload_3
    //   225: astore_0
    //   226: iload 5
    //   228: aload_1
    //   229: invokeinterface 139 1 0
    //   234: if_icmpge +479 -> 713
    //   237: aload_3
    //   238: astore_0
    //   239: aload_1
    //   240: iload 5
    //   242: invokeinterface 151 2 0
    //   247: checkcast 30	org/w3c/dom/Element
    //   250: astore_2
    //   251: aload_3
    //   252: astore_0
    //   253: new 12	com/tencent/xweb/xwalk/b/a$d
    //   256: astore 6
    //   258: aload_3
    //   259: astore_0
    //   260: aload 6
    //   262: invokespecial 466	com/tencent/xweb/xwalk/b/a$d:<init>	()V
    //   265: aload_3
    //   266: astore_0
    //   267: aload 6
    //   269: aload_2
    //   270: ldc_w 468
    //   273: invokeinterface 34 2 0
    //   278: putfield 471	com/tencent/xweb/xwalk/b/a$d:ATj	Ljava/lang/String;
    //   281: aload_3
    //   282: astore_0
    //   283: aload 6
    //   285: aload_2
    //   286: ldc_w 420
    //   289: invokestatic 159	com/tencent/xweb/xwalk/b/a:a	(Lorg/w3c/dom/Element;Ljava/lang/String;)I
    //   292: putfield 474	com/tencent/xweb/xwalk/b/a$d:ATk	I
    //   295: aload_3
    //   296: astore_0
    //   297: aload 6
    //   299: aload_2
    //   300: ldc_w 410
    //   303: invokeinterface 34 2 0
    //   308: putfield 475	com/tencent/xweb/xwalk/b/a$d:ATg	Ljava/lang/String;
    //   311: aload_3
    //   312: astore_0
    //   313: aload 6
    //   315: aload_2
    //   316: ldc_w 288
    //   319: invokeinterface 34 2 0
    //   324: putfield 476	com/tencent/xweb/xwalk/b/a$d:ATb	Ljava/lang/String;
    //   327: aload_3
    //   328: astore_0
    //   329: aload 6
    //   331: aload_2
    //   332: ldc_w 293
    //   335: invokestatic 297	com/tencent/xweb/xwalk/b/a:b	(Lorg/w3c/dom/Element;Ljava/lang/String;)Z
    //   338: putfield 477	com/tencent/xweb/xwalk/b/a$d:ATh	Z
    //   341: aload_3
    //   342: astore_0
    //   343: aload 6
    //   345: aload_2
    //   346: ldc_w 303
    //   349: invokestatic 297	com/tencent/xweb/xwalk/b/a:b	(Lorg/w3c/dom/Element;Ljava/lang/String;)Z
    //   352: putfield 478	com/tencent/xweb/xwalk/b/a$d:bUseCdn	Z
    //   355: aload_3
    //   356: astore_0
    //   357: aload 6
    //   359: aload_2
    //   360: ldc_w 415
    //   363: invokestatic 159	com/tencent/xweb/xwalk/b/a:a	(Lorg/w3c/dom/Element;Ljava/lang/String;)I
    //   366: putfield 479	com/tencent/xweb/xwalk/b/a$d:ATl	I
    //   369: aload_3
    //   370: astore_0
    //   371: aload 6
    //   373: getfield 480	com/tencent/xweb/xwalk/b/a$d:AOK	Lcom/tencent/xweb/c/a$b;
    //   376: aload_2
    //   377: ldc 172
    //   379: invokestatic 159	com/tencent/xweb/xwalk/b/a:a	(Lorg/w3c/dom/Element;Ljava/lang/String;)I
    //   382: putfield 175	com/tencent/xweb/c/a$b:AOO	I
    //   385: aload_3
    //   386: astore_0
    //   387: aload 6
    //   389: getfield 480	com/tencent/xweb/xwalk/b/a$d:AOK	Lcom/tencent/xweb/c/a$b;
    //   392: aload_2
    //   393: ldc 177
    //   395: invokestatic 159	com/tencent/xweb/xwalk/b/a:a	(Lorg/w3c/dom/Element;Ljava/lang/String;)I
    //   398: putfield 180	com/tencent/xweb/c/a$b:AOP	I
    //   401: aload_3
    //   402: astore_0
    //   403: aload 6
    //   405: getfield 480	com/tencent/xweb/xwalk/b/a$d:AOK	Lcom/tencent/xweb/c/a$b;
    //   408: aload_2
    //   409: ldc 157
    //   411: invokestatic 159	com/tencent/xweb/xwalk/b/a:a	(Lorg/w3c/dom/Element;Ljava/lang/String;)I
    //   414: putfield 165	com/tencent/xweb/c/a$b:AOQ	I
    //   417: aload_3
    //   418: astore_0
    //   419: aload 6
    //   421: getfield 480	com/tencent/xweb/xwalk/b/a$d:AOK	Lcom/tencent/xweb/c/a$b;
    //   424: aload_2
    //   425: ldc 167
    //   427: invokestatic 159	com/tencent/xweb/xwalk/b/a:a	(Lorg/w3c/dom/Element;Ljava/lang/String;)I
    //   430: putfield 170	com/tencent/xweb/c/a$b:AOR	I
    //   433: aload_3
    //   434: astore_0
    //   435: aload 6
    //   437: getfield 480	com/tencent/xweb/xwalk/b/a$d:AOK	Lcom/tencent/xweb/c/a$b;
    //   440: aload_2
    //   441: ldc 182
    //   443: invokestatic 159	com/tencent/xweb/xwalk/b/a:a	(Lorg/w3c/dom/Element;Ljava/lang/String;)I
    //   446: putfield 185	com/tencent/xweb/c/a$b:AOS	I
    //   449: aload_3
    //   450: astore_0
    //   451: aload 6
    //   453: getfield 480	com/tencent/xweb/xwalk/b/a$d:AOK	Lcom/tencent/xweb/c/a$b;
    //   456: aload_2
    //   457: ldc 187
    //   459: invokestatic 159	com/tencent/xweb/xwalk/b/a:a	(Lorg/w3c/dom/Element;Ljava/lang/String;)I
    //   462: putfield 190	com/tencent/xweb/c/a$b:AOT	I
    //   465: aload_3
    //   466: astore_0
    //   467: aload 6
    //   469: getfield 480	com/tencent/xweb/xwalk/b/a$d:AOK	Lcom/tencent/xweb/c/a$b;
    //   472: aload_2
    //   473: ldc 213
    //   475: invokestatic 159	com/tencent/xweb/xwalk/b/a:a	(Lorg/w3c/dom/Element;Ljava/lang/String;)I
    //   478: putfield 216	com/tencent/xweb/c/a$b:AOW	I
    //   481: aload_3
    //   482: astore_0
    //   483: aload 6
    //   485: getfield 480	com/tencent/xweb/xwalk/b/a$d:AOK	Lcom/tencent/xweb/c/a$b;
    //   488: aload_2
    //   489: ldc 218
    //   491: invokestatic 159	com/tencent/xweb/xwalk/b/a:a	(Lorg/w3c/dom/Element;Ljava/lang/String;)I
    //   494: putfield 221	com/tencent/xweb/c/a$b:AOX	I
    //   497: aload_3
    //   498: astore_0
    //   499: aload 6
    //   501: getfield 480	com/tencent/xweb/xwalk/b/a$d:AOK	Lcom/tencent/xweb/c/a$b;
    //   504: aload_2
    //   505: ldc 223
    //   507: invokestatic 159	com/tencent/xweb/xwalk/b/a:a	(Lorg/w3c/dom/Element;Ljava/lang/String;)I
    //   510: putfield 226	com/tencent/xweb/c/a$b:AOY	I
    //   513: aload_3
    //   514: astore_0
    //   515: aload 6
    //   517: getfield 480	com/tencent/xweb/xwalk/b/a$d:AOK	Lcom/tencent/xweb/c/a$b;
    //   520: aload_2
    //   521: ldc 228
    //   523: invokestatic 159	com/tencent/xweb/xwalk/b/a:a	(Lorg/w3c/dom/Element;Ljava/lang/String;)I
    //   526: putfield 231	com/tencent/xweb/c/a$b:AOZ	I
    //   529: aload_3
    //   530: astore_0
    //   531: aload 6
    //   533: getfield 480	com/tencent/xweb/xwalk/b/a$d:AOK	Lcom/tencent/xweb/c/a$b;
    //   536: aload_2
    //   537: ldc 233
    //   539: invokestatic 159	com/tencent/xweb/xwalk/b/a:a	(Lorg/w3c/dom/Element;Ljava/lang/String;)I
    //   542: putfield 236	com/tencent/xweb/c/a$b:APa	I
    //   545: aload_3
    //   546: astore_0
    //   547: aload 6
    //   549: getfield 480	com/tencent/xweb/xwalk/b/a$d:AOK	Lcom/tencent/xweb/c/a$b;
    //   552: aload_2
    //   553: ldc 192
    //   555: invokeinterface 34 2 0
    //   560: putfield 196	com/tencent/xweb/c/a$b:AOU	Ljava/lang/String;
    //   563: aload_3
    //   564: astore_0
    //   565: aload 6
    //   567: getfield 480	com/tencent/xweb/xwalk/b/a$d:AOK	Lcom/tencent/xweb/c/a$b;
    //   570: aload_2
    //   571: ldc 198
    //   573: invokeinterface 34 2 0
    //   578: putfield 201	com/tencent/xweb/c/a$b:AOV	Ljava/lang/String;
    //   581: aload_3
    //   582: astore_0
    //   583: aload 6
    //   585: getfield 480	com/tencent/xweb/xwalk/b/a$d:AOK	Lcom/tencent/xweb/c/a$b;
    //   588: aload_2
    //   589: ldc 203
    //   591: invokeinterface 34 2 0
    //   596: putfield 206	com/tencent/xweb/c/a$b:APb	Ljava/lang/String;
    //   599: aload_3
    //   600: astore_0
    //   601: aload 6
    //   603: getfield 480	com/tencent/xweb/xwalk/b/a$d:AOK	Lcom/tencent/xweb/c/a$b;
    //   606: aload_2
    //   607: ldc 208
    //   609: invokeinterface 34 2 0
    //   614: putfield 211	com/tencent/xweb/c/a$b:APc	Ljava/lang/String;
    //   617: aload_3
    //   618: astore_0
    //   619: aload 6
    //   621: getfield 480	com/tencent/xweb/xwalk/b/a$d:AOK	Lcom/tencent/xweb/c/a$b;
    //   624: aload_2
    //   625: ldc 253
    //   627: invokestatic 159	com/tencent/xweb/xwalk/b/a:a	(Lorg/w3c/dom/Element;Ljava/lang/String;)I
    //   630: putfield 256	com/tencent/xweb/c/a$b:APd	I
    //   633: aload_3
    //   634: astore_0
    //   635: aload 6
    //   637: getfield 480	com/tencent/xweb/xwalk/b/a$d:AOK	Lcom/tencent/xweb/c/a$b;
    //   640: aload_2
    //   641: ldc_w 258
    //   644: invokestatic 159	com/tencent/xweb/xwalk/b/a:a	(Lorg/w3c/dom/Element;Ljava/lang/String;)I
    //   647: putfield 261	com/tencent/xweb/c/a$b:APe	I
    //   650: aload_3
    //   651: astore_0
    //   652: aload 6
    //   654: getfield 480	com/tencent/xweb/xwalk/b/a$d:AOK	Lcom/tencent/xweb/c/a$b;
    //   657: aload_2
    //   658: ldc_w 263
    //   661: invokestatic 159	com/tencent/xweb/xwalk/b/a:a	(Lorg/w3c/dom/Element;Ljava/lang/String;)I
    //   664: putfield 266	com/tencent/xweb/c/a$b:APf	I
    //   667: aload_3
    //   668: astore_0
    //   669: aload 6
    //   671: getfield 480	com/tencent/xweb/xwalk/b/a$d:AOK	Lcom/tencent/xweb/c/a$b;
    //   674: aload_2
    //   675: ldc_w 268
    //   678: invokestatic 159	com/tencent/xweb/xwalk/b/a:a	(Lorg/w3c/dom/Element;Ljava/lang/String;)I
    //   681: putfield 271	com/tencent/xweb/c/a$b:APg	I
    //   684: aload_3
    //   685: astore_0
    //   686: aload 6
    //   688: aload_2
    //   689: invokestatic 443	com/tencent/xweb/xwalk/b/a:a	(Lorg/w3c/dom/Element;)[Lcom/tencent/xweb/xwalk/b/a$b;
    //   692: putfield 481	com/tencent/xweb/xwalk/b/a$d:ATm	[Lcom/tencent/xweb/xwalk/b/a$b;
    //   695: aload_3
    //   696: astore_0
    //   697: aload 4
    //   699: getfield 465	com/tencent/xweb/xwalk/b/a$c:ATi	[Lcom/tencent/xweb/xwalk/b/a$d;
    //   702: iload 5
    //   704: aload 6
    //   706: aastore
    //   707: iinc 5 1
    //   710: goto -486 -> 224
    //   713: aload_3
    //   714: invokevirtual 65	java/io/FileInputStream:close	()V
    //   717: aload 4
    //   719: astore_0
    //   720: ldc_w 450
    //   723: invokestatic 28	com/tencent/matrix/trace/core/AppMethodBeat:o	(I)V
    //   726: goto -653 -> 73
    //   729: astore_0
    //   730: ldc 67
    //   732: ldc_w 455
    //   735: invokestatic 75	org/xwalk/core/Log:e	(Ljava/lang/String;Ljava/lang/String;)V
    //   738: aload 4
    //   740: astore_0
    //   741: goto -21 -> 720
    //   744: astore_0
    //   745: aconst_null
    //   746: astore_3
    //   747: aconst_null
    //   748: astore_1
    //   749: aload_3
    //   750: astore_0
    //   751: ldc_w 483
    //   754: invokestatic 317	org/xwalk/core/XWalkInitializer:addXWalkInitializeLog	(Ljava/lang/String;)V
    //   757: aload_1
    //   758: astore_0
    //   759: aload_3
    //   760: ifnull -40 -> 720
    //   763: aload_3
    //   764: invokevirtual 65	java/io/FileInputStream:close	()V
    //   767: aload_1
    //   768: astore_0
    //   769: goto -49 -> 720
    //   772: astore_0
    //   773: ldc 67
    //   775: ldc_w 455
    //   778: invokestatic 75	org/xwalk/core/Log:e	(Ljava/lang/String;Ljava/lang/String;)V
    //   781: aload_1
    //   782: astore_0
    //   783: goto -63 -> 720
    //   786: astore_0
    //   787: aconst_null
    //   788: astore_3
    //   789: aconst_null
    //   790: astore_1
    //   791: aload_3
    //   792: astore_0
    //   793: ldc_w 485
    //   796: invokestatic 317	org/xwalk/core/XWalkInitializer:addXWalkInitializeLog	(Ljava/lang/String;)V
    //   799: aload_1
    //   800: astore_0
    //   801: aload_3
    //   802: ifnull -82 -> 720
    //   805: aload_3
    //   806: invokevirtual 65	java/io/FileInputStream:close	()V
    //   809: aload_1
    //   810: astore_0
    //   811: goto -91 -> 720
    //   814: astore_0
    //   815: ldc 67
    //   817: ldc_w 455
    //   820: invokestatic 75	org/xwalk/core/Log:e	(Ljava/lang/String;Ljava/lang/String;)V
    //   823: aload_1
    //   824: astore_0
    //   825: goto -105 -> 720
    //   828: astore_0
    //   829: aconst_null
    //   830: astore_3
    //   831: aconst_null
    //   832: astore_1
    //   833: aload_3
    //   834: astore_0
    //   835: ldc_w 487
    //   838: invokestatic 317	org/xwalk/core/XWalkInitializer:addXWalkInitializeLog	(Ljava/lang/String;)V
    //   841: aload_1
    //   842: astore_0
    //   843: aload_3
    //   844: ifnull -124 -> 720
    //   847: aload_3
    //   848: invokevirtual 65	java/io/FileInputStream:close	()V
    //   851: aload_1
    //   852: astore_0
    //   853: goto -133 -> 720
    //   856: astore_0
    //   857: ldc 67
    //   859: ldc_w 455
    //   862: invokestatic 75	org/xwalk/core/Log:e	(Ljava/lang/String;Ljava/lang/String;)V
    //   865: aload_1
    //   866: astore_0
    //   867: goto -147 -> 720
    //   870: astore_1
    //   871: aconst_null
    //   872: astore_0
    //   873: aload_0
    //   874: ifnull +7 -> 881
    //   877: aload_0
    //   878: invokevirtual 65	java/io/FileInputStream:close	()V
    //   881: ldc_w 450
    //   884: invokestatic 28	com/tencent/matrix/trace/core/AppMethodBeat:o	(I)V
    //   887: aload_1
    //   888: athrow
    //   889: astore_0
    //   890: ldc 67
    //   892: ldc_w 455
    //   895: invokestatic 75	org/xwalk/core/Log:e	(Ljava/lang/String;Ljava/lang/String;)V
    //   898: goto -17 -> 881
    //   901: astore_1
    //   902: goto -29 -> 873
    //   905: astore_0
    //   906: aconst_null
    //   907: astore_1
    //   908: goto -75 -> 833
    //   911: astore_0
    //   912: aload 4
    //   914: astore_1
    //   915: goto -82 -> 833
    //   918: astore_0
    //   919: aconst_null
    //   920: astore_1
    //   921: goto -130 -> 791
    //   924: astore_0
    //   925: aload 4
    //   927: astore_1
    //   928: goto -137 -> 791
    //   931: astore_0
    //   932: aconst_null
    //   933: astore_1
    //   934: goto -185 -> 749
    //   937: astore_0
    //   938: aload 4
    //   940: astore_1
    //   941: goto -192 -> 749
    //
    // Exception table:
    //   from	to	target	type
    //   61	65	75	java/lang/Exception
    //   135	139	150	java/lang/Exception
    //   713	717	729	java/lang/Exception
    //   10	19	744	javax/xml/parsers/ParserConfigurationException
    //   763	767	772	java/lang/Exception
    //   10	19	786	org/xml/sax/SAXException
    //   805	809	814	java/lang/Exception
    //   10	19	828	java/io/IOException
    //   847	851	856	java/lang/Exception
    //   10	19	870	finally
    //   877	881	889	java/lang/Exception
    //   21	26	901	finally
    //   28	33	901	finally
    //   35	49	901	finally
    //   55	61	901	finally
    //   89	103	901	finally
    //   105	113	901	finally
    //   115	127	901	finally
    //   129	135	901	finally
    //   164	178	901	finally
    //   180	190	901	finally
    //   196	205	901	finally
    //   207	221	901	finally
    //   226	237	901	finally
    //   239	251	901	finally
    //   253	258	901	finally
    //   260	265	901	finally
    //   267	281	901	finally
    //   283	295	901	finally
    //   297	311	901	finally
    //   313	327	901	finally
    //   329	341	901	finally
    //   343	355	901	finally
    //   357	369	901	finally
    //   371	385	901	finally
    //   387	401	901	finally
    //   403	417	901	finally
    //   419	433	901	finally
    //   435	449	901	finally
    //   451	465	901	finally
    //   467	481	901	finally
    //   483	497	901	finally
    //   499	513	901	finally
    //   515	529	901	finally
    //   531	545	901	finally
    //   547	563	901	finally
    //   565	581	901	finally
    //   583	599	901	finally
    //   601	617	901	finally
    //   619	633	901	finally
    //   635	650	901	finally
    //   652	667	901	finally
    //   669	684	901	finally
    //   686	695	901	finally
    //   697	707	901	finally
    //   751	757	901	finally
    //   793	799	901	finally
    //   835	841	901	finally
    //   21	26	905	java/io/IOException
    //   28	33	905	java/io/IOException
    //   35	49	911	java/io/IOException
    //   55	61	911	java/io/IOException
    //   89	103	911	java/io/IOException
    //   105	113	911	java/io/IOException
    //   115	127	911	java/io/IOException
    //   129	135	911	java/io/IOException
    //   164	178	911	java/io/IOException
    //   180	190	911	java/io/IOException
    //   196	205	911	java/io/IOException
    //   207	221	911	java/io/IOException
    //   226	237	911	java/io/IOException
    //   239	251	911	java/io/IOException
    //   253	258	911	java/io/IOException
    //   260	265	911	java/io/IOException
    //   267	281	911	java/io/IOException
    //   283	295	911	java/io/IOException
    //   297	311	911	java/io/IOException
    //   313	327	911	java/io/IOException
    //   329	341	911	java/io/IOException
    //   343	355	911	java/io/IOException
    //   357	369	911	java/io/IOException
    //   371	385	911	java/io/IOException
    //   387	401	911	java/io/IOException
    //   403	417	911	java/io/IOException
    //   419	433	911	java/io/IOException
    //   435	449	911	java/io/IOException
    //   451	465	911	java/io/IOException
    //   467	481	911	java/io/IOException
    //   483	497	911	java/io/IOException
    //   499	513	911	java/io/IOException
    //   515	529	911	java/io/IOException
    //   531	545	911	java/io/IOException
    //   547	563	911	java/io/IOException
    //   565	581	911	java/io/IOException
    //   583	599	911	java/io/IOException
    //   601	617	911	java/io/IOException
    //   619	633	911	java/io/IOException
    //   635	650	911	java/io/IOException
    //   652	667	911	java/io/IOException
    //   669	684	911	java/io/IOException
    //   686	695	911	java/io/IOException
    //   697	707	911	java/io/IOException
    //   21	26	918	org/xml/sax/SAXException
    //   28	33	918	org/xml/sax/SAXException
    //   35	49	924	org/xml/sax/SAXException
    //   55	61	924	org/xml/sax/SAXException
    //   89	103	924	org/xml/sax/SAXException
    //   105	113	924	org/xml/sax/SAXException
    //   115	127	924	org/xml/sax/SAXException
    //   129	135	924	org/xml/sax/SAXException
    //   164	178	924	org/xml/sax/SAXException
    //   180	190	924	org/xml/sax/SAXException
    //   196	205	924	org/xml/sax/SAXException
    //   207	221	924	org/xml/sax/SAXException
    //   226	237	924	org/xml/sax/SAXException
    //   239	251	924	org/xml/sax/SAXException
    //   253	258	924	org/xml/sax/SAXException
    //   260	265	924	org/xml/sax/SAXException
    //   267	281	924	org/xml/sax/SAXException
    //   283	295	924	org/xml/sax/SAXException
    //   297	311	924	org/xml/sax/SAXException
    //   313	327	924	org/xml/sax/SAXException
    //   329	341	924	org/xml/sax/SAXException
    //   343	355	924	org/xml/sax/SAXException
    //   357	369	924	org/xml/sax/SAXException
    //   371	385	924	org/xml/sax/SAXException
    //   387	401	924	org/xml/sax/SAXException
    //   403	417	924	org/xml/sax/SAXException
    //   419	433	924	org/xml/sax/SAXException
    //   435	449	924	org/xml/sax/SAXException
    //   451	465	924	org/xml/sax/SAXException
    //   467	481	924	org/xml/sax/SAXException
    //   483	497	924	org/xml/sax/SAXException
    //   499	513	924	org/xml/sax/SAXException
    //   515	529	924	org/xml/sax/SAXException
    //   531	545	924	org/xml/sax/SAXException
    //   547	563	924	org/xml/sax/SAXException
    //   565	581	924	org/xml/sax/SAXException
    //   583	599	924	org/xml/sax/SAXException
    //   601	617	924	org/xml/sax/SAXException
    //   619	633	924	org/xml/sax/SAXException
    //   635	650	924	org/xml/sax/SAXException
    //   652	667	924	org/xml/sax/SAXException
    //   669	684	924	org/xml/sax/SAXException
    //   686	695	924	org/xml/sax/SAXException
    //   697	707	924	org/xml/sax/SAXException
    //   21	26	931	javax/xml/parsers/ParserConfigurationException
    //   28	33	931	javax/xml/parsers/ParserConfigurationException
    //   35	49	937	javax/xml/parsers/ParserConfigurationException
    //   55	61	937	javax/xml/parsers/ParserConfigurationException
    //   89	103	937	javax/xml/parsers/ParserConfigurationException
    //   105	113	937	javax/xml/parsers/ParserConfigurationException
    //   115	127	937	javax/xml/parsers/ParserConfigurationException
    //   129	135	937	javax/xml/parsers/ParserConfigurationException
    //   164	178	937	javax/xml/parsers/ParserConfigurationException
    //   180	190	937	javax/xml/parsers/ParserConfigurationException
    //   196	205	937	javax/xml/parsers/ParserConfigurationException
    //   207	221	937	javax/xml/parsers/ParserConfigurationException
    //   226	237	937	javax/xml/parsers/ParserConfigurationException
    //   239	251	937	javax/xml/parsers/ParserConfigurationException
    //   253	258	937	javax/xml/parsers/ParserConfigurationException
    //   260	265	937	javax/xml/parsers/ParserConfigurationException
    //   267	281	937	javax/xml/parsers/ParserConfigurationException
    //   283	295	937	javax/xml/parsers/ParserConfigurationException
    //   297	311	937	javax/xml/parsers/ParserConfigurationException
    //   313	327	937	javax/xml/parsers/ParserConfigurationException
    //   329	341	937	javax/xml/parsers/ParserConfigurationException
    //   343	355	937	javax/xml/parsers/ParserConfigurationException
    //   357	369	937	javax/xml/parsers/ParserConfigurationException
    //   371	385	937	javax/xml/parsers/ParserConfigurationException
    //   387	401	937	javax/xml/parsers/ParserConfigurationException
    //   403	417	937	javax/xml/parsers/ParserConfigurationException
    //   419	433	937	javax/xml/parsers/ParserConfigurationException
    //   435	449	937	javax/xml/parsers/ParserConfigurationException
    //   451	465	937	javax/xml/parsers/ParserConfigurationException
    //   467	481	937	javax/xml/parsers/ParserConfigurationException
    //   483	497	937	javax/xml/parsers/ParserConfigurationException
    //   499	513	937	javax/xml/parsers/ParserConfigurationException
    //   515	529	937	javax/xml/parsers/ParserConfigurationException
    //   531	545	937	javax/xml/parsers/ParserConfigurationException
    //   547	563	937	javax/xml/parsers/ParserConfigurationException
    //   565	581	937	javax/xml/parsers/ParserConfigurationException
    //   583	599	937	javax/xml/parsers/ParserConfigurationException
    //   601	617	937	javax/xml/parsers/ParserConfigurationException
    //   619	633	937	javax/xml/parsers/ParserConfigurationException
    //   635	650	937	javax/xml/parsers/ParserConfigurationException
    //   652	667	937	javax/xml/parsers/ParserConfigurationException
    //   669	684	937	javax/xml/parsers/ParserConfigurationException
    //   686	695	937	javax/xml/parsers/ParserConfigurationException
    //   697	707	937	javax/xml/parsers/ParserConfigurationException
  }
}

/* Location:           C:\Users\Lin\Downloads\dex-tools-2.1-SNAPSHOT\dex-tools-2.1-SNAPSHOT\classes3-dex2jar.jar
 * Qualified Name:     com.tencent.xweb.xwalk.b.a
 * JD-Core Version:    0.6.2
 */