package a.i.b.a.c.g;

import com.tencent.matrix.trace.core.AppMethodBeat;

public enum z$a
{
  final z.b BBj;
  final int BBk;

  static
  {
    // Byte code:
    //   0: ldc 38
    //   2: invokestatic 44	com/tencent/matrix/trace/core/AppMethodBeat:i	(I)V
    //   5: new 2	a/i/b/a/c/g/z$a
    //   8: dup
    //   9: ldc 46
    //   11: iconst_0
    //   12: getstatic 51	a/i/b/a/c/g/z$b:BBp	La/i/b/a/c/g/z$b;
    //   15: iconst_1
    //   16: invokespecial 55	a/i/b/a/c/g/z$a:<init>	(Ljava/lang/String;ILa/i/b/a/c/g/z$b;I)V
    //   19: putstatic 57	a/i/b/a/c/g/z$a:BAR	La/i/b/a/c/g/z$a;
    //   22: new 2	a/i/b/a/c/g/z$a
    //   25: dup
    //   26: ldc 59
    //   28: iconst_1
    //   29: getstatic 62	a/i/b/a/c/g/z$b:BBo	La/i/b/a/c/g/z$b;
    //   32: iconst_5
    //   33: invokespecial 55	a/i/b/a/c/g/z$a:<init>	(Ljava/lang/String;ILa/i/b/a/c/g/z$b;I)V
    //   36: putstatic 64	a/i/b/a/c/g/z$a:BAS	La/i/b/a/c/g/z$a;
    //   39: new 2	a/i/b/a/c/g/z$a
    //   42: dup
    //   43: ldc 66
    //   45: iconst_2
    //   46: getstatic 69	a/i/b/a/c/g/z$b:BBn	La/i/b/a/c/g/z$b;
    //   49: iconst_0
    //   50: invokespecial 55	a/i/b/a/c/g/z$a:<init>	(Ljava/lang/String;ILa/i/b/a/c/g/z$b;I)V
    //   53: putstatic 71	a/i/b/a/c/g/z$a:BAT	La/i/b/a/c/g/z$a;
    //   56: new 2	a/i/b/a/c/g/z$a
    //   59: dup
    //   60: ldc 73
    //   62: iconst_3
    //   63: getstatic 69	a/i/b/a/c/g/z$b:BBn	La/i/b/a/c/g/z$b;
    //   66: iconst_0
    //   67: invokespecial 55	a/i/b/a/c/g/z$a:<init>	(Ljava/lang/String;ILa/i/b/a/c/g/z$b;I)V
    //   70: putstatic 75	a/i/b/a/c/g/z$a:BAU	La/i/b/a/c/g/z$a;
    //   73: new 2	a/i/b/a/c/g/z$a
    //   76: dup
    //   77: ldc 77
    //   79: iconst_4
    //   80: getstatic 80	a/i/b/a/c/g/z$b:BBm	La/i/b/a/c/g/z$b;
    //   83: iconst_0
    //   84: invokespecial 55	a/i/b/a/c/g/z$a:<init>	(Ljava/lang/String;ILa/i/b/a/c/g/z$b;I)V
    //   87: putstatic 82	a/i/b/a/c/g/z$a:BAV	La/i/b/a/c/g/z$a;
    //   90: new 2	a/i/b/a/c/g/z$a
    //   93: dup
    //   94: ldc 84
    //   96: iconst_5
    //   97: getstatic 69	a/i/b/a/c/g/z$b:BBn	La/i/b/a/c/g/z$b;
    //   100: iconst_1
    //   101: invokespecial 55	a/i/b/a/c/g/z$a:<init>	(Ljava/lang/String;ILa/i/b/a/c/g/z$b;I)V
    //   104: putstatic 86	a/i/b/a/c/g/z$a:BAW	La/i/b/a/c/g/z$a;
    //   107: new 2	a/i/b/a/c/g/z$a
    //   110: dup
    //   111: ldc 88
    //   113: bipush 6
    //   115: getstatic 80	a/i/b/a/c/g/z$b:BBm	La/i/b/a/c/g/z$b;
    //   118: iconst_5
    //   119: invokespecial 55	a/i/b/a/c/g/z$a:<init>	(Ljava/lang/String;ILa/i/b/a/c/g/z$b;I)V
    //   122: putstatic 90	a/i/b/a/c/g/z$a:BAX	La/i/b/a/c/g/z$a;
    //   125: new 2	a/i/b/a/c/g/z$a
    //   128: dup
    //   129: ldc 92
    //   131: bipush 7
    //   133: getstatic 95	a/i/b/a/c/g/z$b:BBq	La/i/b/a/c/g/z$b;
    //   136: iconst_0
    //   137: invokespecial 55	a/i/b/a/c/g/z$a:<init>	(Ljava/lang/String;ILa/i/b/a/c/g/z$b;I)V
    //   140: putstatic 97	a/i/b/a/c/g/z$a:BAY	La/i/b/a/c/g/z$a;
    //   143: new 99	a/i/b/a/c/g/z$a$1
    //   146: dup
    //   147: ldc 101
    //   149: getstatic 104	a/i/b/a/c/g/z$b:BBr	La/i/b/a/c/g/z$b;
    //   152: invokespecial 107	a/i/b/a/c/g/z$a$1:<init>	(Ljava/lang/String;La/i/b/a/c/g/z$b;)V
    //   155: putstatic 109	a/i/b/a/c/g/z$a:BAZ	La/i/b/a/c/g/z$a;
    //   158: new 10	a/i/b/a/c/g/z$a$2
    //   161: dup
    //   162: ldc 111
    //   164: getstatic 114	a/i/b/a/c/g/z$b:BBu	La/i/b/a/c/g/z$b;
    //   167: invokespecial 115	a/i/b/a/c/g/z$a$2:<init>	(Ljava/lang/String;La/i/b/a/c/g/z$b;)V
    //   170: putstatic 117	a/i/b/a/c/g/z$a:BBa	La/i/b/a/c/g/z$a;
    //   173: new 119	a/i/b/a/c/g/z$a$3
    //   176: dup
    //   177: ldc 121
    //   179: getstatic 114	a/i/b/a/c/g/z$b:BBu	La/i/b/a/c/g/z$b;
    //   182: invokespecial 122	a/i/b/a/c/g/z$a$3:<init>	(Ljava/lang/String;La/i/b/a/c/g/z$b;)V
    //   185: putstatic 124	a/i/b/a/c/g/z$a:BBb	La/i/b/a/c/g/z$a;
    //   188: new 126	a/i/b/a/c/g/z$a$4
    //   191: dup
    //   192: ldc 128
    //   194: getstatic 131	a/i/b/a/c/g/z$b:BBs	La/i/b/a/c/g/z$b;
    //   197: invokespecial 132	a/i/b/a/c/g/z$a$4:<init>	(Ljava/lang/String;La/i/b/a/c/g/z$b;)V
    //   200: putstatic 134	a/i/b/a/c/g/z$a:BBc	La/i/b/a/c/g/z$a;
    //   203: new 2	a/i/b/a/c/g/z$a
    //   206: dup
    //   207: ldc 136
    //   209: bipush 12
    //   211: getstatic 80	a/i/b/a/c/g/z$b:BBm	La/i/b/a/c/g/z$b;
    //   214: iconst_0
    //   215: invokespecial 55	a/i/b/a/c/g/z$a:<init>	(Ljava/lang/String;ILa/i/b/a/c/g/z$b;I)V
    //   218: putstatic 138	a/i/b/a/c/g/z$a:BBd	La/i/b/a/c/g/z$a;
    //   221: new 2	a/i/b/a/c/g/z$a
    //   224: dup
    //   225: ldc 140
    //   227: bipush 13
    //   229: getstatic 143	a/i/b/a/c/g/z$b:BBt	La/i/b/a/c/g/z$b;
    //   232: iconst_0
    //   233: invokespecial 55	a/i/b/a/c/g/z$a:<init>	(Ljava/lang/String;ILa/i/b/a/c/g/z$b;I)V
    //   236: putstatic 145	a/i/b/a/c/g/z$a:BBe	La/i/b/a/c/g/z$a;
    //   239: new 2	a/i/b/a/c/g/z$a
    //   242: dup
    //   243: ldc 147
    //   245: bipush 14
    //   247: getstatic 80	a/i/b/a/c/g/z$b:BBm	La/i/b/a/c/g/z$b;
    //   250: iconst_5
    //   251: invokespecial 55	a/i/b/a/c/g/z$a:<init>	(Ljava/lang/String;ILa/i/b/a/c/g/z$b;I)V
    //   254: putstatic 149	a/i/b/a/c/g/z$a:BBf	La/i/b/a/c/g/z$a;
    //   257: new 2	a/i/b/a/c/g/z$a
    //   260: dup
    //   261: ldc 151
    //   263: bipush 15
    //   265: getstatic 69	a/i/b/a/c/g/z$b:BBn	La/i/b/a/c/g/z$b;
    //   268: iconst_1
    //   269: invokespecial 55	a/i/b/a/c/g/z$a:<init>	(Ljava/lang/String;ILa/i/b/a/c/g/z$b;I)V
    //   272: putstatic 153	a/i/b/a/c/g/z$a:BBg	La/i/b/a/c/g/z$a;
    //   275: new 2	a/i/b/a/c/g/z$a
    //   278: dup
    //   279: ldc 155
    //   281: bipush 16
    //   283: getstatic 80	a/i/b/a/c/g/z$b:BBm	La/i/b/a/c/g/z$b;
    //   286: iconst_0
    //   287: invokespecial 55	a/i/b/a/c/g/z$a:<init>	(Ljava/lang/String;ILa/i/b/a/c/g/z$b;I)V
    //   290: putstatic 157	a/i/b/a/c/g/z$a:BBh	La/i/b/a/c/g/z$a;
    //   293: new 2	a/i/b/a/c/g/z$a
    //   296: dup
    //   297: ldc 159
    //   299: bipush 17
    //   301: getstatic 69	a/i/b/a/c/g/z$b:BBn	La/i/b/a/c/g/z$b;
    //   304: iconst_0
    //   305: invokespecial 55	a/i/b/a/c/g/z$a:<init>	(Ljava/lang/String;ILa/i/b/a/c/g/z$b;I)V
    //   308: putstatic 161	a/i/b/a/c/g/z$a:BBi	La/i/b/a/c/g/z$a;
    //   311: bipush 18
    //   313: anewarray 2	a/i/b/a/c/g/z$a
    //   316: dup
    //   317: iconst_0
    //   318: getstatic 57	a/i/b/a/c/g/z$a:BAR	La/i/b/a/c/g/z$a;
    //   321: aastore
    //   322: dup
    //   323: iconst_1
    //   324: getstatic 64	a/i/b/a/c/g/z$a:BAS	La/i/b/a/c/g/z$a;
    //   327: aastore
    //   328: dup
    //   329: iconst_2
    //   330: getstatic 71	a/i/b/a/c/g/z$a:BAT	La/i/b/a/c/g/z$a;
    //   333: aastore
    //   334: dup
    //   335: iconst_3
    //   336: getstatic 75	a/i/b/a/c/g/z$a:BAU	La/i/b/a/c/g/z$a;
    //   339: aastore
    //   340: dup
    //   341: iconst_4
    //   342: getstatic 82	a/i/b/a/c/g/z$a:BAV	La/i/b/a/c/g/z$a;
    //   345: aastore
    //   346: dup
    //   347: iconst_5
    //   348: getstatic 86	a/i/b/a/c/g/z$a:BAW	La/i/b/a/c/g/z$a;
    //   351: aastore
    //   352: dup
    //   353: bipush 6
    //   355: getstatic 90	a/i/b/a/c/g/z$a:BAX	La/i/b/a/c/g/z$a;
    //   358: aastore
    //   359: dup
    //   360: bipush 7
    //   362: getstatic 97	a/i/b/a/c/g/z$a:BAY	La/i/b/a/c/g/z$a;
    //   365: aastore
    //   366: dup
    //   367: bipush 8
    //   369: getstatic 109	a/i/b/a/c/g/z$a:BAZ	La/i/b/a/c/g/z$a;
    //   372: aastore
    //   373: dup
    //   374: bipush 9
    //   376: getstatic 117	a/i/b/a/c/g/z$a:BBa	La/i/b/a/c/g/z$a;
    //   379: aastore
    //   380: dup
    //   381: bipush 10
    //   383: getstatic 124	a/i/b/a/c/g/z$a:BBb	La/i/b/a/c/g/z$a;
    //   386: aastore
    //   387: dup
    //   388: bipush 11
    //   390: getstatic 134	a/i/b/a/c/g/z$a:BBc	La/i/b/a/c/g/z$a;
    //   393: aastore
    //   394: dup
    //   395: bipush 12
    //   397: getstatic 138	a/i/b/a/c/g/z$a:BBd	La/i/b/a/c/g/z$a;
    //   400: aastore
    //   401: dup
    //   402: bipush 13
    //   404: getstatic 145	a/i/b/a/c/g/z$a:BBe	La/i/b/a/c/g/z$a;
    //   407: aastore
    //   408: dup
    //   409: bipush 14
    //   411: getstatic 149	a/i/b/a/c/g/z$a:BBf	La/i/b/a/c/g/z$a;
    //   414: aastore
    //   415: dup
    //   416: bipush 15
    //   418: getstatic 153	a/i/b/a/c/g/z$a:BBg	La/i/b/a/c/g/z$a;
    //   421: aastore
    //   422: dup
    //   423: bipush 16
    //   425: getstatic 157	a/i/b/a/c/g/z$a:BBh	La/i/b/a/c/g/z$a;
    //   428: aastore
    //   429: dup
    //   430: bipush 17
    //   432: getstatic 161	a/i/b/a/c/g/z$a:BBi	La/i/b/a/c/g/z$a;
    //   435: aastore
    //   436: putstatic 163	a/i/b/a/c/g/z$a:BBl	[La/i/b/a/c/g/z$a;
    //   439: ldc 38
    //   441: invokestatic 166	com/tencent/matrix/trace/core/AppMethodBeat:o	(I)V
    //   444: return
  }

  private z$a(z.b paramb, int paramInt)
  {
    this.BBj = paramb;
    this.BBk = paramInt;
  }

  public boolean eiN()
  {
    return true;
  }
}

/* Location:           C:\Users\Lin\Downloads\dex-tools-2.1-SNAPSHOT\dex-tools-2.1-SNAPSHOT\classes2-dex2jar.jar
 * Qualified Name:     a.i.b.a.c.g.z.a
 * JD-Core Version:    0.6.2
 */