package com.tencent.mm.plugin.backup.bakoldlogic.bakoldpcmodel;

final class f$5
  implements Runnable
{
  f$5(f paramf, int paramInt)
  {
  }

  // ERROR //
  public final void run()
  {
    // Byte code:
    //   0: sipush 17867
    //   3: invokestatic 31	com/tencent/matrix/trace/core/AppMethodBeat:i	(I)V
    //   6: invokestatic 36	com/tencent/mm/plugin/backup/c/e:reset	()V
    //   9: invokestatic 39	com/tencent/mm/plugin/backup/c/e:aST	()V
    //   12: new 41	com/tencent/mm/plugin/backup/bakoldlogic/bakoldmodel/c
    //   15: dup
    //   16: invokespecial 42	com/tencent/mm/plugin/backup/bakoldlogic/bakoldmodel/c:<init>	()V
    //   19: astore_1
    //   20: aload_1
    //   21: invokevirtual 45	com/tencent/mm/plugin/backup/bakoldlogic/bakoldmodel/c:begin	()V
    //   24: new 47	java/util/HashMap
    //   27: dup
    //   28: invokespecial 48	java/util/HashMap:<init>	()V
    //   31: astore_2
    //   32: new 50	java/util/HashSet
    //   35: dup
    //   36: invokespecial 51	java/util/HashSet:<init>	()V
    //   39: astore_3
    //   40: aload_0
    //   41: getfield 16	com/tencent/mm/plugin/backup/bakoldlogic/bakoldpcmodel/f$5:jzZ	Lcom/tencent/mm/plugin/backup/bakoldlogic/bakoldpcmodel/f;
    //   44: getfield 55	com/tencent/mm/plugin/backup/bakoldlogic/bakoldpcmodel/f:jzS	Ljava/util/List;
    //   47: invokeinterface 61 1 0
    //   52: astore 4
    //   54: iconst_0
    //   55: istore 5
    //   57: aload 4
    //   59: invokeinterface 67 1 0
    //   64: ifeq +204 -> 268
    //   67: aload 4
    //   69: invokeinterface 71 1 0
    //   74: checkcast 73	com/tencent/mm/plugin/backup/i/t
    //   77: astore 6
    //   79: new 75	java/lang/StringBuilder
    //   82: dup
    //   83: invokespecial 76	java/lang/StringBuilder:<init>	()V
    //   86: invokestatic 82	com/tencent/mm/plugin/backup/bakoldlogic/a/a:aUy	()Ljava/lang/String;
    //   89: invokevirtual 86	java/lang/StringBuilder:append	(Ljava/lang/String;)Ljava/lang/StringBuilder;
    //   92: ldc 88
    //   94: invokevirtual 86	java/lang/StringBuilder:append	(Ljava/lang/String;)Ljava/lang/StringBuilder;
    //   97: aload 6
    //   99: getfield 92	com/tencent/mm/plugin/backup/i/t:ID	Ljava/lang/String;
    //   102: invokestatic 96	com/tencent/mm/plugin/backup/bakoldlogic/a/a:Fb	(Ljava/lang/String;)Ljava/lang/String;
    //   105: invokevirtual 86	java/lang/StringBuilder:append	(Ljava/lang/String;)Ljava/lang/StringBuilder;
    //   108: aload 6
    //   110: getfield 92	com/tencent/mm/plugin/backup/i/t:ID	Ljava/lang/String;
    //   113: invokevirtual 86	java/lang/StringBuilder:append	(Ljava/lang/String;)Ljava/lang/StringBuilder;
    //   116: invokevirtual 99	java/lang/StringBuilder:toString	()Ljava/lang/String;
    //   119: astore 6
    //   121: aload_0
    //   122: getfield 16	com/tencent/mm/plugin/backup/bakoldlogic/bakoldpcmodel/f$5:jzZ	Lcom/tencent/mm/plugin/backup/bakoldlogic/bakoldpcmodel/f;
    //   125: aload 6
    //   127: aload_2
    //   128: aload_1
    //   129: aload_3
    //   130: invokevirtual 103	com/tencent/mm/plugin/backup/bakoldlogic/bakoldpcmodel/f:a	(Ljava/lang/String;Ljava/util/HashMap;Lcom/tencent/mm/plugin/backup/bakoldlogic/bakoldmodel/c;Ljava/util/HashSet;)I
    //   133: istore 7
    //   135: iload 7
    //   137: ifge +21 -> 158
    //   140: aload_1
    //   141: invokevirtual 106	com/tencent/mm/plugin/backup/bakoldlogic/bakoldmodel/c:end	()V
    //   144: ldc 108
    //   146: ldc 110
    //   148: invokestatic 116	com/tencent/mm/sdk/platformtools/ab:w	(Ljava/lang/String;Ljava/lang/String;)V
    //   151: sipush 17867
    //   154: invokestatic 119	com/tencent/matrix/trace/core/AppMethodBeat:o	(I)V
    //   157: return
    //   158: iload 7
    //   160: iload 5
    //   162: iadd
    //   163: istore 5
    //   165: aload_0
    //   166: getfield 16	com/tencent/mm/plugin/backup/bakoldlogic/bakoldpcmodel/f$5:jzZ	Lcom/tencent/mm/plugin/backup/bakoldlogic/bakoldpcmodel/f;
    //   169: iload 5
    //   171: aload_0
    //   172: getfield 18	com/tencent/mm/plugin/backup/bakoldlogic/bakoldpcmodel/f$5:jAb	I
    //   175: invokevirtual 123	com/tencent/mm/plugin/backup/bakoldlogic/bakoldpcmodel/f:dB	(II)V
    //   178: ldc 108
    //   180: ldc 125
    //   182: iconst_1
    //   183: anewarray 4	java/lang/Object
    //   186: dup
    //   187: iconst_0
    //   188: iload 5
    //   190: invokestatic 131	java/lang/Integer:valueOf	(I)Ljava/lang/Integer;
    //   193: aastore
    //   194: invokestatic 134	com/tencent/mm/sdk/platformtools/ab:i	(Ljava/lang/String;Ljava/lang/String;[Ljava/lang/Object;)V
    //   197: goto -140 -> 57
    //   200: astore 6
    //   202: ldc 108
    //   204: new 75	java/lang/StringBuilder
    //   207: dup
    //   208: ldc 136
    //   210: invokespecial 139	java/lang/StringBuilder:<init>	(Ljava/lang/String;)V
    //   213: aload 6
    //   215: invokevirtual 140	java/lang/Exception:toString	()Ljava/lang/String;
    //   218: invokevirtual 86	java/lang/StringBuilder:append	(Ljava/lang/String;)Ljava/lang/StringBuilder;
    //   221: invokevirtual 99	java/lang/StringBuilder:toString	()Ljava/lang/String;
    //   224: invokestatic 143	com/tencent/mm/sdk/platformtools/ab:e	(Ljava/lang/String;Ljava/lang/String;)V
    //   227: ldc 108
    //   229: aload 6
    //   231: ldc 145
    //   233: iconst_0
    //   234: anewarray 4	java/lang/Object
    //   237: invokestatic 149	com/tencent/mm/sdk/platformtools/ab:printErrStackTrace	(Ljava/lang/String;Ljava/lang/Throwable;Ljava/lang/String;[Ljava/lang/Object;)V
    //   240: ldc 108
    //   242: new 75	java/lang/StringBuilder
    //   245: dup
    //   246: ldc 151
    //   248: invokespecial 139	java/lang/StringBuilder:<init>	(Ljava/lang/String;)V
    //   251: aload 6
    //   253: invokevirtual 140	java/lang/Exception:toString	()Ljava/lang/String;
    //   256: invokevirtual 86	java/lang/StringBuilder:append	(Ljava/lang/String;)Ljava/lang/StringBuilder;
    //   259: invokevirtual 99	java/lang/StringBuilder:toString	()Ljava/lang/String;
    //   262: invokestatic 154	com/tencent/mm/sdk/platformtools/ab:f	(Ljava/lang/String;Ljava/lang/String;)V
    //   265: goto -208 -> 57
    //   268: aload_2
    //   269: invokestatic 160	com/tencent/mm/plugin/backup/bakoldlogic/d/d:k	(Ljava/util/HashMap;)V
    //   272: aload_1
    //   273: invokevirtual 106	com/tencent/mm/plugin/backup/bakoldlogic/bakoldmodel/c:end	()V
    //   276: aload_0
    //   277: getfield 16	com/tencent/mm/plugin/backup/bakoldlogic/bakoldpcmodel/f$5:jzZ	Lcom/tencent/mm/plugin/backup/bakoldlogic/bakoldpcmodel/f;
    //   280: bipush 100
    //   282: bipush 100
    //   284: invokevirtual 123	com/tencent/mm/plugin/backup/bakoldlogic/bakoldpcmodel/f:dB	(II)V
    //   287: ldc 108
    //   289: ldc 162
    //   291: invokestatic 164	com/tencent/mm/sdk/platformtools/ab:i	(Ljava/lang/String;Ljava/lang/String;)V
    //   294: invokestatic 167	com/tencent/mm/sdk/platformtools/ab:dot	()V
    //   297: invokestatic 173	com/tencent/mm/plugin/backup/bakoldlogic/d/b:aUY	()Lcom/tencent/mm/plugin/backup/bakoldlogic/d/b;
    //   300: astore 6
    //   302: aload 6
    //   304: new 175	com/tencent/mm/plugin/backup/bakoldlogic/d/b$2
    //   307: dup
    //   308: aload 6
    //   310: new 177	com/tencent/mm/plugin/backup/bakoldlogic/bakoldpcmodel/f$5$1
    //   313: dup
    //   314: aload_0
    //   315: invokespecial 180	com/tencent/mm/plugin/backup/bakoldlogic/bakoldpcmodel/f$5$1:<init>	(Lcom/tencent/mm/plugin/backup/bakoldlogic/bakoldpcmodel/f$5;)V
    //   318: invokespecial 183	com/tencent/mm/plugin/backup/bakoldlogic/d/b$2:<init>	(Lcom/tencent/mm/plugin/backup/bakoldlogic/d/b;Ljava/lang/Runnable;)V
    //   321: bipush 10
    //   323: invokevirtual 187	com/tencent/mm/plugin/backup/bakoldlogic/d/b:c	(Ljava/lang/Runnable;I)V
    //   326: sipush 17867
    //   329: invokestatic 119	com/tencent/matrix/trace/core/AppMethodBeat:o	(I)V
    //   332: goto -175 -> 157
    //   335: astore 6
    //   337: goto -135 -> 202
    //
    // Exception table:
    //   from	to	target	type
    //   121	135	200	java/lang/Exception
    //   140	151	200	java/lang/Exception
    //   165	197	335	java/lang/Exception
  }
}

/* Location:           C:\Users\Lin\Downloads\dex-tools-2.1-SNAPSHOT\dex-tools-2.1-SNAPSHOT\classes7-dex2jar.jar
 * Qualified Name:     com.tencent.mm.plugin.backup.bakoldlogic.bakoldpcmodel.f.5
 * JD-Core Version:    0.6.2
 */