package com.tencent.mm.plugin.sns.model;

import com.tencent.matrix.trace.core.AppMethodBeat;
import com.tencent.mm.plugin.report.service.h;
import com.tencent.mm.plugin.sns.data.i;
import com.tencent.mm.plugin.sns.storage.n;
import com.tencent.mm.plugin.sns.storage.o;
import com.tencent.mm.protocal.protobuf.TimeLineObject;
import com.tencent.mm.protocal.protobuf.bau;
import com.tencent.mm.protocal.protobuf.bav;
import com.tencent.mm.protocal.protobuf.cbv;
import com.tencent.mm.protocal.protobuf.uf;
import com.tencent.mm.sdk.platformtools.ab;
import com.tencent.mm.sdk.platformtools.bo;
import java.util.LinkedList;
import java.util.List;

public final class ak
{
  // ERROR //
  private static String cnZ()
  {
    // Byte code:
    //   0: ldc 9
    //   2: invokestatic 15	com/tencent/matrix/trace/core/AppMethodBeat:i	(I)V
    //   5: invokestatic 21	com/tencent/mm/sdk/platformtools/ah:getContext	()Landroid/content/Context;
    //   8: astore_0
    //   9: aload_0
    //   10: ifnonnull +19 -> 29
    //   13: ldc 23
    //   15: ldc 25
    //   17: invokestatic 31	com/tencent/mm/sdk/platformtools/ab:e	(Ljava/lang/String;Ljava/lang/String;)V
    //   20: aconst_null
    //   21: astore_1
    //   22: ldc 9
    //   24: invokestatic 34	com/tencent/matrix/trace/core/AppMethodBeat:o	(I)V
    //   27: aload_1
    //   28: areturn
    //   29: iconst_0
    //   30: istore_2
    //   31: aload_0
    //   32: ldc 36
    //   34: invokevirtual 42	android/content/Context:getSystemService	(Ljava/lang/String;)Ljava/lang/Object;
    //   37: checkcast 44	android/net/ConnectivityManager
    //   40: invokevirtual 48	android/net/ConnectivityManager:getActiveNetworkInfo	()Landroid/net/NetworkInfo;
    //   43: astore_1
    //   44: aload_1
    //   45: invokevirtual 54	android/net/NetworkInfo:getSubtype	()I
    //   48: istore_3
    //   49: aload_1
    //   50: invokevirtual 57	android/net/NetworkInfo:getType	()I
    //   53: istore 4
    //   55: iload 4
    //   57: iconst_1
    //   58: if_icmpne +231 -> 289
    //   61: iconst_1
    //   62: istore_2
    //   63: ldc 23
    //   65: ldc 59
    //   67: iconst_1
    //   68: anewarray 4	java/lang/Object
    //   71: dup
    //   72: iconst_0
    //   73: iload_2
    //   74: invokestatic 65	java/lang/Integer:valueOf	(I)Ljava/lang/Integer;
    //   77: aastore
    //   78: invokestatic 68	com/tencent/mm/sdk/platformtools/ab:i	(Ljava/lang/String;Ljava/lang/String;[Ljava/lang/Object;)V
    //   81: ldc 70
    //   83: astore 5
    //   85: ldc 70
    //   87: astore 6
    //   89: aload_0
    //   90: ldc 72
    //   92: invokevirtual 42	android/content/Context:getSystemService	(Ljava/lang/String;)Ljava/lang/Object;
    //   95: checkcast 74	android/net/wifi/WifiManager
    //   98: astore 7
    //   100: new 76	java/lang/StringBuffer
    //   103: astore 8
    //   105: aload 8
    //   107: invokespecial 80	java/lang/StringBuffer:<init>	()V
    //   110: new 76	java/lang/StringBuffer
    //   113: astore 9
    //   115: aload 9
    //   117: invokespecial 80	java/lang/StringBuffer:<init>	()V
    //   120: new 76	java/lang/StringBuffer
    //   123: astore 10
    //   125: aload 10
    //   127: invokespecial 80	java/lang/StringBuffer:<init>	()V
    //   130: iconst_0
    //   131: istore 11
    //   133: iconst_0
    //   134: istore 4
    //   136: new 82	java/util/ArrayList
    //   139: astore_1
    //   140: aload_1
    //   141: invokespecial 83	java/util/ArrayList:<init>	()V
    //   144: aload 8
    //   146: invokestatic 21	com/tencent/mm/sdk/platformtools/ah:getContext	()Landroid/content/Context;
    //   149: invokestatic 89	com/tencent/mm/sdk/platformtools/at:gE	(Landroid/content/Context;)Ljava/lang/String;
    //   152: invokevirtual 93	java/lang/StringBuffer:append	(Ljava/lang/String;)Ljava/lang/StringBuffer;
    //   155: pop
    //   156: aload 9
    //   158: invokestatic 21	com/tencent/mm/sdk/platformtools/ah:getContext	()Landroid/content/Context;
    //   161: invokestatic 96	com/tencent/mm/sdk/platformtools/at:gF	(Landroid/content/Context;)Ljava/lang/String;
    //   164: invokevirtual 93	java/lang/StringBuffer:append	(Ljava/lang/String;)Ljava/lang/StringBuffer;
    //   167: pop
    //   168: invokestatic 21	com/tencent/mm/sdk/platformtools/ah:getContext	()Landroid/content/Context;
    //   171: invokestatic 96	com/tencent/mm/sdk/platformtools/at:gF	(Landroid/content/Context;)Ljava/lang/String;
    //   174: astore 12
    //   176: aload_1
    //   177: aload 12
    //   179: invokevirtual 100	java/util/ArrayList:add	(Ljava/lang/Object;)Z
    //   182: pop
    //   183: aload 7
    //   185: invokevirtual 104	android/net/wifi/WifiManager:getScanResults	()Ljava/util/List;
    //   188: astore 7
    //   190: aload 7
    //   192: ifnull +309 -> 501
    //   195: new 106	com/tencent/mm/plugin/sns/model/ak$1
    //   198: astore 13
    //   200: aload 13
    //   202: invokespecial 107	com/tencent/mm/plugin/sns/model/ak$1:<init>	()V
    //   205: aload 7
    //   207: aload 13
    //   209: invokestatic 113	java/util/Collections:sort	(Ljava/util/List;Ljava/util/Comparator;)V
    //   212: aload 7
    //   214: invokeinterface 119 1 0
    //   219: astore 7
    //   221: bipush 20
    //   223: istore_3
    //   224: iload 4
    //   226: istore 11
    //   228: aload 7
    //   230: invokeinterface 125 1 0
    //   235: ifeq +266 -> 501
    //   238: aload 7
    //   240: invokeinterface 129 1 0
    //   245: checkcast 131	android/net/wifi/ScanResult
    //   248: astore 13
    //   250: aload 13
    //   252: ifnull -28 -> 224
    //   255: aload 13
    //   257: getfield 135	android/net/wifi/ScanResult:BSSID	Ljava/lang/String;
    //   260: invokestatic 141	com/tencent/mm/sdk/platformtools/bo:isNullOrNil	(Ljava/lang/String;)Z
    //   263: ifne -39 -> 224
    //   266: aload 13
    //   268: getfield 135	android/net/wifi/ScanResult:BSSID	Ljava/lang/String;
    //   271: aload 12
    //   273: invokevirtual 146	java/lang/String:equals	(Ljava/lang/Object;)Z
    //   276: ifeq +110 -> 386
    //   279: aload 13
    //   281: getfield 150	android/net/wifi/ScanResult:level	I
    //   284: istore 4
    //   286: goto -62 -> 224
    //   289: iload_3
    //   290: bipush 13
    //   292: if_icmpeq +15 -> 307
    //   295: iload_3
    //   296: bipush 15
    //   298: if_icmpeq +9 -> 307
    //   301: iload_3
    //   302: bipush 14
    //   304: if_icmpne +8 -> 312
    //   307: iconst_4
    //   308: istore_2
    //   309: goto -246 -> 63
    //   312: iload_3
    //   313: iconst_3
    //   314: if_icmpeq +25 -> 339
    //   317: iload_3
    //   318: iconst_4
    //   319: if_icmpeq +20 -> 339
    //   322: iload_3
    //   323: iconst_5
    //   324: if_icmpeq +15 -> 339
    //   327: iload_3
    //   328: bipush 6
    //   330: if_icmpeq +9 -> 339
    //   333: iload_3
    //   334: bipush 12
    //   336: if_icmpne +8 -> 344
    //   339: iconst_3
    //   340: istore_2
    //   341: goto -278 -> 63
    //   344: iload_3
    //   345: iconst_1
    //   346: if_icmpeq +8 -> 354
    //   349: iload_3
    //   350: iconst_2
    //   351: if_icmpne +8 -> 359
    //   354: iconst_2
    //   355: istore_2
    //   356: goto -293 -> 63
    //   359: iconst_0
    //   360: istore_2
    //   361: goto -298 -> 63
    //   364: astore_1
    //   365: ldc 23
    //   367: ldc 152
    //   369: iconst_1
    //   370: anewarray 4	java/lang/Object
    //   373: dup
    //   374: iconst_0
    //   375: aload_1
    //   376: invokestatic 156	com/tencent/mm/sdk/platformtools/bo:l	(Ljava/lang/Throwable;)Ljava/lang/String;
    //   379: aastore
    //   380: invokestatic 158	com/tencent/mm/sdk/platformtools/ab:e	(Ljava/lang/String;Ljava/lang/String;[Ljava/lang/Object;)V
    //   383: goto -320 -> 63
    //   386: iload 4
    //   388: istore 11
    //   390: iload_3
    //   391: ifle +110 -> 501
    //   394: aload 8
    //   396: ldc 160
    //   398: invokevirtual 93	java/lang/StringBuffer:append	(Ljava/lang/String;)Ljava/lang/StringBuffer;
    //   401: pop
    //   402: aload 8
    //   404: aload 13
    //   406: getfield 163	android/net/wifi/ScanResult:SSID	Ljava/lang/String;
    //   409: invokestatic 167	com/tencent/mm/sdk/platformtools/bo:nullAsNil	(Ljava/lang/String;)Ljava/lang/String;
    //   412: ldc 160
    //   414: ldc 70
    //   416: invokevirtual 171	java/lang/String:replace	(Ljava/lang/CharSequence;Ljava/lang/CharSequence;)Ljava/lang/String;
    //   419: ldc 173
    //   421: ldc 70
    //   423: invokevirtual 171	java/lang/String:replace	(Ljava/lang/CharSequence;Ljava/lang/CharSequence;)Ljava/lang/String;
    //   426: invokevirtual 93	java/lang/StringBuffer:append	(Ljava/lang/String;)Ljava/lang/StringBuffer;
    //   429: pop
    //   430: aload 9
    //   432: ldc 160
    //   434: invokevirtual 93	java/lang/StringBuffer:append	(Ljava/lang/String;)Ljava/lang/StringBuffer;
    //   437: pop
    //   438: aload 9
    //   440: aload 13
    //   442: getfield 135	android/net/wifi/ScanResult:BSSID	Ljava/lang/String;
    //   445: invokestatic 167	com/tencent/mm/sdk/platformtools/bo:nullAsNil	(Ljava/lang/String;)Ljava/lang/String;
    //   448: ldc 160
    //   450: ldc 70
    //   452: invokevirtual 171	java/lang/String:replace	(Ljava/lang/CharSequence;Ljava/lang/CharSequence;)Ljava/lang/String;
    //   455: ldc 173
    //   457: ldc 70
    //   459: invokevirtual 171	java/lang/String:replace	(Ljava/lang/CharSequence;Ljava/lang/CharSequence;)Ljava/lang/String;
    //   462: invokevirtual 93	java/lang/StringBuffer:append	(Ljava/lang/String;)Ljava/lang/StringBuffer;
    //   465: pop
    //   466: aload_1
    //   467: aload 13
    //   469: getfield 135	android/net/wifi/ScanResult:BSSID	Ljava/lang/String;
    //   472: invokevirtual 100	java/util/ArrayList:add	(Ljava/lang/Object;)Z
    //   475: pop
    //   476: aload 10
    //   478: ldc 160
    //   480: invokevirtual 93	java/lang/StringBuffer:append	(Ljava/lang/String;)Ljava/lang/StringBuffer;
    //   483: pop
    //   484: aload 10
    //   486: aload 13
    //   488: getfield 150	android/net/wifi/ScanResult:level	I
    //   491: invokevirtual 176	java/lang/StringBuffer:append	(I)Ljava/lang/StringBuffer;
    //   494: pop
    //   495: iinc 3 255
    //   498: goto -274 -> 224
    //   501: aload 8
    //   503: invokevirtual 179	java/lang/StringBuffer:toString	()Ljava/lang/String;
    //   506: astore_1
    //   507: aload 9
    //   509: invokevirtual 179	java/lang/StringBuffer:toString	()Ljava/lang/String;
    //   512: astore 13
    //   514: aload 13
    //   516: astore 5
    //   518: new 181	java/lang/StringBuilder
    //   521: astore 9
    //   523: aload 13
    //   525: astore 5
    //   527: aload 9
    //   529: invokespecial 182	java/lang/StringBuilder:<init>	()V
    //   532: aload 13
    //   534: astore 5
    //   536: aload 9
    //   538: iload 11
    //   540: invokevirtual 185	java/lang/StringBuilder:append	(I)Ljava/lang/StringBuilder;
    //   543: aload 10
    //   545: invokevirtual 179	java/lang/StringBuffer:toString	()Ljava/lang/String;
    //   548: invokevirtual 188	java/lang/StringBuilder:append	(Ljava/lang/String;)Ljava/lang/StringBuilder;
    //   551: invokevirtual 189	java/lang/StringBuilder:toString	()Ljava/lang/String;
    //   554: astore 10
    //   556: aload 10
    //   558: astore 6
    //   560: aload_1
    //   561: astore 14
    //   563: ldc 23
    //   565: ldc 191
    //   567: iconst_3
    //   568: anewarray 4	java/lang/Object
    //   571: dup
    //   572: iconst_0
    //   573: aload 13
    //   575: aastore
    //   576: dup
    //   577: iconst_1
    //   578: aload 14
    //   580: aastore
    //   581: dup
    //   582: iconst_2
    //   583: aload 6
    //   585: aastore
    //   586: invokestatic 194	com/tencent/mm/sdk/platformtools/ab:d	(Ljava/lang/String;Ljava/lang/String;[Ljava/lang/Object;)V
    //   589: aload_0
    //   590: ldc 196
    //   592: invokevirtual 42	android/content/Context:getSystemService	(Ljava/lang/String;)Ljava/lang/Object;
    //   595: checkcast 198	android/telephony/TelephonyManager
    //   598: astore_1
    //   599: aload_1
    //   600: ifnull +983 -> 1583
    //   603: aload_1
    //   604: invokevirtual 201	android/telephony/TelephonyManager:getNetworkOperatorName	()Ljava/lang/String;
    //   607: astore 5
    //   609: aload 5
    //   611: astore_1
    //   612: aload 5
    //   614: invokestatic 141	com/tencent/mm/sdk/platformtools/bo:isNullOrNil	(Ljava/lang/String;)Z
    //   617: ifeq +6 -> 623
    //   620: ldc 70
    //   622: astore_1
    //   623: aload_1
    //   624: astore 15
    //   626: ldc 23
    //   628: ldc 203
    //   630: iconst_1
    //   631: anewarray 4	java/lang/Object
    //   634: dup
    //   635: iconst_0
    //   636: aload 15
    //   638: aastore
    //   639: invokestatic 68	com/tencent/mm/sdk/platformtools/ab:i	(Ljava/lang/String;Ljava/lang/String;[Ljava/lang/Object;)V
    //   642: ldc 70
    //   644: astore 12
    //   646: ldc 70
    //   648: astore 9
    //   650: ldc 70
    //   652: astore 5
    //   654: ldc 70
    //   656: astore_1
    //   657: aload_0
    //   658: invokestatic 207	com/tencent/mm/sdk/platformtools/at:gJ	(Landroid/content/Context;)Ljava/util/List;
    //   661: astore 16
    //   663: iconst_0
    //   664: istore 4
    //   666: ldc 70
    //   668: astore_1
    //   669: aload_1
    //   670: astore 7
    //   672: aload 5
    //   674: astore 10
    //   676: aload 9
    //   678: astore 8
    //   680: aload 12
    //   682: astore_0
    //   683: iload 4
    //   685: aload 16
    //   687: invokeinterface 210 1 0
    //   692: if_icmpge +599 -> 1291
    //   695: aload_1
    //   696: astore 7
    //   698: aload 5
    //   700: astore 10
    //   702: aload 9
    //   704: astore 8
    //   706: aload 12
    //   708: astore_0
    //   709: aload 16
    //   711: iload 4
    //   713: invokeinterface 214 2 0
    //   718: checkcast 216	com/tencent/mm/sdk/platformtools/at$a
    //   721: astore 17
    //   723: aload_1
    //   724: astore 7
    //   726: aload 5
    //   728: astore 10
    //   730: aload 9
    //   732: astore 8
    //   734: aload 12
    //   736: astore_0
    //   737: aload 17
    //   739: getfield 219	com/tencent/mm/sdk/platformtools/at$a:org	Ljava/lang/String;
    //   742: ldc 70
    //   744: invokestatic 223	com/tencent/mm/sdk/platformtools/bo:bc	(Ljava/lang/String;Ljava/lang/String;)Ljava/lang/String;
    //   747: astore 12
    //   749: aload_1
    //   750: astore 7
    //   752: aload 5
    //   754: astore 10
    //   756: aload 9
    //   758: astore 8
    //   760: aload 12
    //   762: astore_0
    //   763: aload 17
    //   765: getfield 226	com/tencent/mm/sdk/platformtools/at$a:orh	Ljava/lang/String;
    //   768: ldc 70
    //   770: invokestatic 223	com/tencent/mm/sdk/platformtools/bo:bc	(Ljava/lang/String;Ljava/lang/String;)Ljava/lang/String;
    //   773: astore 18
    //   775: aload 5
    //   777: astore 9
    //   779: aload_1
    //   780: astore 7
    //   782: aload 5
    //   784: astore 10
    //   786: aload 18
    //   788: astore 8
    //   790: aload 12
    //   792: astore_0
    //   793: aload 5
    //   795: invokevirtual 229	java/lang/String:length	()I
    //   798: ifle +101 -> 899
    //   801: aload 5
    //   803: astore 9
    //   805: aload_1
    //   806: astore 7
    //   808: aload 5
    //   810: astore 10
    //   812: aload 18
    //   814: astore 8
    //   816: aload 12
    //   818: astore_0
    //   819: aload 17
    //   821: getfield 232	com/tencent/mm/sdk/platformtools/at$a:ori	Ljava/lang/String;
    //   824: invokestatic 141	com/tencent/mm/sdk/platformtools/bo:isNullOrNil	(Ljava/lang/String;)Z
    //   827: ifne +72 -> 899
    //   830: aload_1
    //   831: astore 7
    //   833: aload 5
    //   835: astore 10
    //   837: aload 18
    //   839: astore 8
    //   841: aload 12
    //   843: astore_0
    //   844: new 181	java/lang/StringBuilder
    //   847: astore 9
    //   849: aload_1
    //   850: astore 7
    //   852: aload 5
    //   854: astore 10
    //   856: aload 18
    //   858: astore 8
    //   860: aload 12
    //   862: astore_0
    //   863: aload 9
    //   865: invokespecial 182	java/lang/StringBuilder:<init>	()V
    //   868: aload_1
    //   869: astore 7
    //   871: aload 5
    //   873: astore 10
    //   875: aload 18
    //   877: astore 8
    //   879: aload 12
    //   881: astore_0
    //   882: aload 9
    //   884: aload 5
    //   886: invokevirtual 188	java/lang/StringBuilder:append	(Ljava/lang/String;)Ljava/lang/StringBuilder;
    //   889: ldc 160
    //   891: invokevirtual 188	java/lang/StringBuilder:append	(Ljava/lang/String;)Ljava/lang/StringBuilder;
    //   894: invokevirtual 189	java/lang/StringBuilder:toString	()Ljava/lang/String;
    //   897: astore 9
    //   899: aload 9
    //   901: astore 5
    //   903: aload_1
    //   904: astore 7
    //   906: aload 9
    //   908: astore 10
    //   910: aload 18
    //   912: astore 8
    //   914: aload 12
    //   916: astore_0
    //   917: aload 17
    //   919: getfield 232	com/tencent/mm/sdk/platformtools/at$a:ori	Ljava/lang/String;
    //   922: invokestatic 141	com/tencent/mm/sdk/platformtools/bo:isNullOrNil	(Ljava/lang/String;)Z
    //   925: ifne +75 -> 1000
    //   928: aload_1
    //   929: astore 7
    //   931: aload 9
    //   933: astore 10
    //   935: aload 18
    //   937: astore 8
    //   939: aload 12
    //   941: astore_0
    //   942: new 181	java/lang/StringBuilder
    //   945: astore 5
    //   947: aload_1
    //   948: astore 7
    //   950: aload 9
    //   952: astore 10
    //   954: aload 18
    //   956: astore 8
    //   958: aload 12
    //   960: astore_0
    //   961: aload 5
    //   963: invokespecial 182	java/lang/StringBuilder:<init>	()V
    //   966: aload_1
    //   967: astore 7
    //   969: aload 9
    //   971: astore 10
    //   973: aload 18
    //   975: astore 8
    //   977: aload 12
    //   979: astore_0
    //   980: aload 5
    //   982: aload 9
    //   984: invokevirtual 188	java/lang/StringBuilder:append	(Ljava/lang/String;)Ljava/lang/StringBuilder;
    //   987: aload 17
    //   989: getfield 232	com/tencent/mm/sdk/platformtools/at$a:ori	Ljava/lang/String;
    //   992: invokevirtual 188	java/lang/StringBuilder:append	(Ljava/lang/String;)Ljava/lang/StringBuilder;
    //   995: invokevirtual 189	java/lang/StringBuilder:toString	()Ljava/lang/String;
    //   998: astore 5
    //   1000: aload_1
    //   1001: astore 9
    //   1003: aload_1
    //   1004: astore 7
    //   1006: aload 5
    //   1008: astore 10
    //   1010: aload 18
    //   1012: astore 8
    //   1014: aload 12
    //   1016: astore_0
    //   1017: aload_1
    //   1018: invokevirtual 229	java/lang/String:length	()I
    //   1021: ifle +99 -> 1120
    //   1024: aload_1
    //   1025: astore 9
    //   1027: aload_1
    //   1028: astore 7
    //   1030: aload 5
    //   1032: astore 10
    //   1034: aload 18
    //   1036: astore 8
    //   1038: aload 12
    //   1040: astore_0
    //   1041: aload 17
    //   1043: getfield 235	com/tencent/mm/sdk/platformtools/at$a:tzp	Ljava/lang/String;
    //   1046: invokestatic 141	com/tencent/mm/sdk/platformtools/bo:isNullOrNil	(Ljava/lang/String;)Z
    //   1049: ifne +71 -> 1120
    //   1052: aload_1
    //   1053: astore 7
    //   1055: aload 5
    //   1057: astore 10
    //   1059: aload 18
    //   1061: astore 8
    //   1063: aload 12
    //   1065: astore_0
    //   1066: new 181	java/lang/StringBuilder
    //   1069: astore 9
    //   1071: aload_1
    //   1072: astore 7
    //   1074: aload 5
    //   1076: astore 10
    //   1078: aload 18
    //   1080: astore 8
    //   1082: aload 12
    //   1084: astore_0
    //   1085: aload 9
    //   1087: invokespecial 182	java/lang/StringBuilder:<init>	()V
    //   1090: aload_1
    //   1091: astore 7
    //   1093: aload 5
    //   1095: astore 10
    //   1097: aload 18
    //   1099: astore 8
    //   1101: aload 12
    //   1103: astore_0
    //   1104: aload 9
    //   1106: aload_1
    //   1107: invokevirtual 188	java/lang/StringBuilder:append	(Ljava/lang/String;)Ljava/lang/StringBuilder;
    //   1110: ldc 160
    //   1112: invokevirtual 188	java/lang/StringBuilder:append	(Ljava/lang/String;)Ljava/lang/StringBuilder;
    //   1115: invokevirtual 189	java/lang/StringBuilder:toString	()Ljava/lang/String;
    //   1118: astore 9
    //   1120: aload 9
    //   1122: astore 7
    //   1124: aload 5
    //   1126: astore 10
    //   1128: aload 18
    //   1130: astore 8
    //   1132: aload 12
    //   1134: astore_0
    //   1135: aload 17
    //   1137: getfield 235	com/tencent/mm/sdk/platformtools/at$a:tzp	Ljava/lang/String;
    //   1140: invokestatic 141	com/tencent/mm/sdk/platformtools/bo:isNullOrNil	(Ljava/lang/String;)Z
    //   1143: ifne +434 -> 1577
    //   1146: aload 9
    //   1148: astore 7
    //   1150: aload 5
    //   1152: astore 10
    //   1154: aload 18
    //   1156: astore 8
    //   1158: aload 12
    //   1160: astore_0
    //   1161: new 181	java/lang/StringBuilder
    //   1164: astore_1
    //   1165: aload 9
    //   1167: astore 7
    //   1169: aload 5
    //   1171: astore 10
    //   1173: aload 18
    //   1175: astore 8
    //   1177: aload 12
    //   1179: astore_0
    //   1180: aload_1
    //   1181: invokespecial 182	java/lang/StringBuilder:<init>	()V
    //   1184: aload 9
    //   1186: astore 7
    //   1188: aload 5
    //   1190: astore 10
    //   1192: aload 18
    //   1194: astore 8
    //   1196: aload 12
    //   1198: astore_0
    //   1199: aload_1
    //   1200: aload 9
    //   1202: invokevirtual 188	java/lang/StringBuilder:append	(Ljava/lang/String;)Ljava/lang/StringBuilder;
    //   1205: aload 17
    //   1207: getfield 235	com/tencent/mm/sdk/platformtools/at$a:tzp	Ljava/lang/String;
    //   1210: invokevirtual 188	java/lang/StringBuilder:append	(Ljava/lang/String;)Ljava/lang/StringBuilder;
    //   1213: invokevirtual 189	java/lang/StringBuilder:toString	()Ljava/lang/String;
    //   1216: astore_1
    //   1217: iinc 4 1
    //   1220: aload 18
    //   1222: astore 9
    //   1224: goto -555 -> 669
    //   1227: astore 10
    //   1229: ldc 70
    //   1231: astore_1
    //   1232: ldc 23
    //   1234: ldc 237
    //   1236: iconst_1
    //   1237: anewarray 4	java/lang/Object
    //   1240: dup
    //   1241: iconst_0
    //   1242: aload 10
    //   1244: invokestatic 156	com/tencent/mm/sdk/platformtools/bo:l	(Ljava/lang/Throwable;)Ljava/lang/String;
    //   1247: aastore
    //   1248: invokestatic 158	com/tencent/mm/sdk/platformtools/ab:e	(Ljava/lang/String;Ljava/lang/String;[Ljava/lang/Object;)V
    //   1251: aload_1
    //   1252: astore 14
    //   1254: aload 5
    //   1256: astore 13
    //   1258: goto -695 -> 563
    //   1261: astore_1
    //   1262: ldc 70
    //   1264: astore 5
    //   1266: ldc 23
    //   1268: ldc 152
    //   1270: iconst_1
    //   1271: anewarray 4	java/lang/Object
    //   1274: dup
    //   1275: iconst_0
    //   1276: aload_1
    //   1277: invokestatic 156	com/tencent/mm/sdk/platformtools/bo:l	(Ljava/lang/Throwable;)Ljava/lang/String;
    //   1280: aastore
    //   1281: invokestatic 158	com/tencent/mm/sdk/platformtools/ab:e	(Ljava/lang/String;Ljava/lang/String;[Ljava/lang/Object;)V
    //   1284: aload 5
    //   1286: astore 15
    //   1288: goto -662 -> 626
    //   1291: ldc 23
    //   1293: ldc 239
    //   1295: iconst_4
    //   1296: anewarray 4	java/lang/Object
    //   1299: dup
    //   1300: iconst_0
    //   1301: aload 12
    //   1303: aastore
    //   1304: dup
    //   1305: iconst_1
    //   1306: aload 9
    //   1308: aastore
    //   1309: dup
    //   1310: iconst_2
    //   1311: aload 5
    //   1313: aastore
    //   1314: dup
    //   1315: iconst_3
    //   1316: aload_1
    //   1317: aastore
    //   1318: invokestatic 194	com/tencent/mm/sdk/platformtools/ab:d	(Ljava/lang/String;Ljava/lang/String;[Ljava/lang/Object;)V
    //   1321: new 181	java/lang/StringBuilder
    //   1324: dup
    //   1325: invokespecial 182	java/lang/StringBuilder:<init>	()V
    //   1328: astore 10
    //   1330: aload 10
    //   1332: iload_2
    //   1333: invokevirtual 185	java/lang/StringBuilder:append	(I)Ljava/lang/StringBuilder;
    //   1336: ldc 241
    //   1338: invokevirtual 188	java/lang/StringBuilder:append	(Ljava/lang/String;)Ljava/lang/StringBuilder;
    //   1341: pop
    //   1342: aload 10
    //   1344: aload 14
    //   1346: ldc 241
    //   1348: ldc 173
    //   1350: invokevirtual 171	java/lang/String:replace	(Ljava/lang/CharSequence;Ljava/lang/CharSequence;)Ljava/lang/String;
    //   1353: invokevirtual 188	java/lang/StringBuilder:append	(Ljava/lang/String;)Ljava/lang/StringBuilder;
    //   1356: ldc 241
    //   1358: invokevirtual 188	java/lang/StringBuilder:append	(Ljava/lang/String;)Ljava/lang/StringBuilder;
    //   1361: pop
    //   1362: aload 10
    //   1364: aload 13
    //   1366: ldc 241
    //   1368: ldc 173
    //   1370: invokevirtual 171	java/lang/String:replace	(Ljava/lang/CharSequence;Ljava/lang/CharSequence;)Ljava/lang/String;
    //   1373: invokevirtual 188	java/lang/StringBuilder:append	(Ljava/lang/String;)Ljava/lang/StringBuilder;
    //   1376: ldc 241
    //   1378: invokevirtual 188	java/lang/StringBuilder:append	(Ljava/lang/String;)Ljava/lang/StringBuilder;
    //   1381: pop
    //   1382: aload 10
    //   1384: aload 6
    //   1386: ldc 241
    //   1388: ldc 173
    //   1390: invokevirtual 171	java/lang/String:replace	(Ljava/lang/CharSequence;Ljava/lang/CharSequence;)Ljava/lang/String;
    //   1393: invokevirtual 188	java/lang/StringBuilder:append	(Ljava/lang/String;)Ljava/lang/StringBuilder;
    //   1396: ldc 241
    //   1398: invokevirtual 188	java/lang/StringBuilder:append	(Ljava/lang/String;)Ljava/lang/StringBuilder;
    //   1401: pop
    //   1402: aload 10
    //   1404: aload 15
    //   1406: ldc 241
    //   1408: ldc 173
    //   1410: invokevirtual 171	java/lang/String:replace	(Ljava/lang/CharSequence;Ljava/lang/CharSequence;)Ljava/lang/String;
    //   1413: invokevirtual 188	java/lang/StringBuilder:append	(Ljava/lang/String;)Ljava/lang/StringBuilder;
    //   1416: ldc 241
    //   1418: invokevirtual 188	java/lang/StringBuilder:append	(Ljava/lang/String;)Ljava/lang/StringBuilder;
    //   1421: pop
    //   1422: aload 10
    //   1424: aload 12
    //   1426: ldc 241
    //   1428: ldc 173
    //   1430: invokevirtual 171	java/lang/String:replace	(Ljava/lang/CharSequence;Ljava/lang/CharSequence;)Ljava/lang/String;
    //   1433: invokevirtual 188	java/lang/StringBuilder:append	(Ljava/lang/String;)Ljava/lang/StringBuilder;
    //   1436: ldc 241
    //   1438: invokevirtual 188	java/lang/StringBuilder:append	(Ljava/lang/String;)Ljava/lang/StringBuilder;
    //   1441: pop
    //   1442: aload 10
    //   1444: aload 9
    //   1446: ldc 241
    //   1448: ldc 173
    //   1450: invokevirtual 171	java/lang/String:replace	(Ljava/lang/CharSequence;Ljava/lang/CharSequence;)Ljava/lang/String;
    //   1453: invokevirtual 188	java/lang/StringBuilder:append	(Ljava/lang/String;)Ljava/lang/StringBuilder;
    //   1456: ldc 241
    //   1458: invokevirtual 188	java/lang/StringBuilder:append	(Ljava/lang/String;)Ljava/lang/StringBuilder;
    //   1461: pop
    //   1462: aload 10
    //   1464: aload 5
    //   1466: ldc 241
    //   1468: ldc 173
    //   1470: invokevirtual 171	java/lang/String:replace	(Ljava/lang/CharSequence;Ljava/lang/CharSequence;)Ljava/lang/String;
    //   1473: invokevirtual 188	java/lang/StringBuilder:append	(Ljava/lang/String;)Ljava/lang/StringBuilder;
    //   1476: ldc 241
    //   1478: invokevirtual 188	java/lang/StringBuilder:append	(Ljava/lang/String;)Ljava/lang/StringBuilder;
    //   1481: pop
    //   1482: aload 10
    //   1484: aload_1
    //   1485: ldc 241
    //   1487: ldc 173
    //   1489: invokevirtual 171	java/lang/String:replace	(Ljava/lang/CharSequence;Ljava/lang/CharSequence;)Ljava/lang/String;
    //   1492: invokevirtual 188	java/lang/StringBuilder:append	(Ljava/lang/String;)Ljava/lang/StringBuilder;
    //   1495: pop
    //   1496: aload 10
    //   1498: invokevirtual 189	java/lang/StringBuilder:toString	()Ljava/lang/String;
    //   1501: astore_1
    //   1502: ldc 9
    //   1504: invokestatic 34	com/tencent/matrix/trace/core/AppMethodBeat:o	(I)V
    //   1507: goto -1480 -> 27
    //   1510: astore 7
    //   1512: aload 12
    //   1514: astore_0
    //   1515: aload 9
    //   1517: astore 8
    //   1519: aload 5
    //   1521: astore 10
    //   1523: ldc 23
    //   1525: ldc 152
    //   1527: iconst_1
    //   1528: anewarray 4	java/lang/Object
    //   1531: dup
    //   1532: iconst_0
    //   1533: aload 7
    //   1535: invokestatic 156	com/tencent/mm/sdk/platformtools/bo:l	(Ljava/lang/Throwable;)Ljava/lang/String;
    //   1538: aastore
    //   1539: invokestatic 158	com/tencent/mm/sdk/platformtools/ab:e	(Ljava/lang/String;Ljava/lang/String;[Ljava/lang/Object;)V
    //   1542: aload 10
    //   1544: astore 5
    //   1546: aload 8
    //   1548: astore 9
    //   1550: aload_0
    //   1551: astore 12
    //   1553: goto -262 -> 1291
    //   1556: astore 5
    //   1558: aload 7
    //   1560: astore_1
    //   1561: aload 5
    //   1563: astore 7
    //   1565: goto -42 -> 1523
    //   1568: astore_1
    //   1569: goto -303 -> 1266
    //   1572: astore 10
    //   1574: goto -342 -> 1232
    //   1577: aload 9
    //   1579: astore_1
    //   1580: goto -363 -> 1217
    //   1583: ldc 70
    //   1585: astore_1
    //   1586: goto -963 -> 623
    //
    // Exception table:
    //   from	to	target	type
    //   31	55	364	java/lang/Exception
    //   89	130	1227	java/lang/Exception
    //   136	190	1227	java/lang/Exception
    //   195	221	1227	java/lang/Exception
    //   228	250	1227	java/lang/Exception
    //   255	286	1227	java/lang/Exception
    //   394	495	1227	java/lang/Exception
    //   501	507	1227	java/lang/Exception
    //   589	599	1261	java/lang/Exception
    //   603	609	1261	java/lang/Exception
    //   657	663	1510	java/lang/Exception
    //   683	695	1556	java/lang/Exception
    //   709	723	1556	java/lang/Exception
    //   737	749	1556	java/lang/Exception
    //   763	775	1556	java/lang/Exception
    //   793	801	1556	java/lang/Exception
    //   819	830	1556	java/lang/Exception
    //   844	849	1556	java/lang/Exception
    //   863	868	1556	java/lang/Exception
    //   882	899	1556	java/lang/Exception
    //   917	928	1556	java/lang/Exception
    //   942	947	1556	java/lang/Exception
    //   961	966	1556	java/lang/Exception
    //   980	1000	1556	java/lang/Exception
    //   1017	1024	1556	java/lang/Exception
    //   1041	1052	1556	java/lang/Exception
    //   1066	1071	1556	java/lang/Exception
    //   1085	1090	1556	java/lang/Exception
    //   1104	1120	1556	java/lang/Exception
    //   1135	1146	1556	java/lang/Exception
    //   1161	1165	1556	java/lang/Exception
    //   1180	1184	1556	java/lang/Exception
    //   1199	1217	1556	java/lang/Exception
    //   612	620	1568	java/lang/Exception
    //   507	514	1572	java/lang/Exception
    //   518	523	1572	java/lang/Exception
    //   527	532	1572	java/lang/Exception
    //   536	556	1572	java/lang/Exception
  }

  public static void iN(long paramLong)
  {
    AppMethodBeat.i(36565);
    if (paramLong == 0L)
      AppMethodBeat.o(36565);
    while (true)
    {
      return;
      Object localObject1 = af.cnF().kD(paramLong);
      if (localObject1 == null)
      {
        AppMethodBeat.o(36565);
      }
      else if (((n)localObject1).field_type != 1)
      {
        AppMethodBeat.o(36565);
      }
      else
      {
        Object localObject2 = ((n)localObject1).cqM();
        if (localObject2 == null)
        {
          AppMethodBeat.o(36565);
        }
        else
        {
          LinkedList localLinkedList1 = ((bav)localObject2).wFr;
          LinkedList localLinkedList2 = ((n)localObject1).cqu().xfI.wbK;
          int i = Math.min(localLinkedList1.size(), localLinkedList2.size());
          localObject1 = "";
          if (i > 0)
          {
            localObject2 = cnZ();
            localObject1 = localObject2;
            if (bo.isNullOrNil((String)localObject2))
              AppMethodBeat.o(36565);
          }
          else
          {
            for (int j = 0; j < i; j++)
            {
              cbv localcbv = (cbv)localLinkedList1.get(j);
              Object localObject3 = new StringBuffer();
              localObject2 = (bau)localLinkedList2.get(j);
              ((StringBuffer)localObject3).append("||index: ".concat(String.valueOf(j)));
              ((StringBuffer)localObject3).append("||item poi lat " + localcbv.xbm + " " + localcbv.xbn);
              ((StringBuffer)localObject3).append("||item poi accuracy loctype " + localcbv.bEJ + " " + localcbv.rkk);
              ((StringBuffer)localObject3).append("||item pic lat " + localcbv.xbk + " " + localcbv.xbl);
              ((StringBuffer)localObject3).append("||item exitime:" + localcbv.xbp + " filetime: " + localcbv.xbq);
              ((StringBuffer)localObject3).append("||item source: " + localcbv.xbo);
              ((StringBuffer)localObject3).append("||url" + ((bau)localObject2).Url);
              localObject3 = ((bau)localObject2).Url;
              localObject2 = localObject3;
              if (((String)localObject3).startsWith("http://mmsns.qpic.cn/mmsns/"))
              {
                int k = ((String)localObject3).lastIndexOf("/");
                localObject2 = localObject3;
                if (k > 27)
                {
                  localObject2 = localObject3;
                  if (k < ((String)localObject3).length())
                    localObject2 = ((String)localObject3).substring(27, k);
                }
              }
              localObject2 = (String)localObject2 + "," + i.jV(paramLong) + "," + j + "," + bo.anT() + "," + localcbv.xbo + "," + localcbv.xbq + "," + localcbv.xbp + "," + localcbv.xbl + "," + localcbv.xbk + "," + localcbv.xbn + "," + localcbv.xbm + "," + (String)localObject1 + "," + localcbv.bEJ + "," + localcbv.rkk;
              ab.d("MicroMsg.SnsItemReportHelper", "report:%s", new Object[] { localObject2 });
              h.pYm.X(11985, (String)localObject2);
            }
            AppMethodBeat.o(36565);
          }
        }
      }
    }
  }
}

/* Location:           C:\Users\Lin\Downloads\dex-tools-2.1-SNAPSHOT\dex-tools-2.1-SNAPSHOT\classes5-dex2jar.jar
 * Qualified Name:     com.tencent.mm.plugin.sns.model.ak
 * JD-Core Version:    0.6.2
 */