package com.tencent.mm.plugin.webview.ui.tools;

import com.tencent.mm.ui.base.n.d;

final class j$10
  implements n.d
{
  j$10(j paramj)
  {
  }

  // ERROR //
  public final void onMMMenuItemSelected(android.view.MenuItem paramMenuItem, int paramInt)
  {
    // Byte code:
    //   0: iconst_0
    //   1: istore_2
    //   2: sipush 7652
    //   5: invokestatic 32	com/tencent/matrix/trace/core/AppMethodBeat:i	(I)V
    //   8: aload_0
    //   9: getfield 17	com/tencent/mm/plugin/webview/ui/tools/j$10:utN	Lcom/tencent/mm/plugin/webview/ui/tools/j;
    //   12: iconst_0
    //   13: putfield 36	com/tencent/mm/plugin/webview/ui/tools/j:utJ	Z
    //   16: aload_1
    //   17: invokestatic 40	com/tencent/mm/plugin/webview/ui/tools/j:g	(Landroid/view/MenuItem;)Z
    //   20: ifeq +120 -> 140
    //   23: aload_1
    //   24: invokeinterface 46 1 0
    //   29: checkcast 48	com/tencent/mm/m/d$b
    //   32: astore_3
    //   33: aload_3
    //   34: ifnull +99 -> 133
    //   37: aload_0
    //   38: getfield 17	com/tencent/mm/plugin/webview/ui/tools/j$10:utN	Lcom/tencent/mm/plugin/webview/ui/tools/j;
    //   41: invokevirtual 52	com/tencent/mm/plugin/webview/ui/tools/j:cZv	()Lcom/tencent/mm/plugin/webview/ui/tools/WebViewUI;
    //   44: getfield 58	com/tencent/mm/plugin/webview/ui/tools/WebViewUI:uhz	Lcom/tencent/mm/plugin/webview/ui/tools/jsapi/d;
    //   47: astore_1
    //   48: ldc 60
    //   50: ldc 62
    //   52: invokestatic 67	com/tencent/mm/sdk/platformtools/ab:i	(Ljava/lang/String;Ljava/lang/String;)V
    //   55: new 69	java/util/HashMap
    //   58: dup
    //   59: invokespecial 70	java/util/HashMap:<init>	()V
    //   62: astore 4
    //   64: aload 4
    //   66: ldc 72
    //   68: aload_3
    //   69: getfield 75	com/tencent/mm/m/d$b:key	Ljava/lang/String;
    //   72: invokevirtual 79	java/util/HashMap:put	(Ljava/lang/Object;Ljava/lang/Object;)Ljava/lang/Object;
    //   75: pop
    //   76: aload 4
    //   78: ldc 81
    //   80: aload_3
    //   81: getfield 83	com/tencent/mm/m/d$b:title	Ljava/lang/String;
    //   84: invokevirtual 79	java/util/HashMap:put	(Ljava/lang/Object;Ljava/lang/Object;)Ljava/lang/Object;
    //   87: pop
    //   88: ldc 85
    //   90: aload 4
    //   92: aload_1
    //   93: getfield 90	com/tencent/mm/plugin/webview/ui/tools/jsapi/d:uFv	Z
    //   96: aload_1
    //   97: getfield 93	com/tencent/mm/plugin/webview/ui/tools/jsapi/d:uFw	Ljava/lang/String;
    //   100: invokestatic 99	com/tencent/mm/plugin/webview/ui/tools/jsapi/i$a:b	(Ljava/lang/String;Ljava/util/Map;ZLjava/lang/String;)Ljava/lang/String;
    //   103: astore_3
    //   104: aload_1
    //   105: getfield 103	com/tencent/mm/plugin/webview/ui/tools/jsapi/d:uFo	Lcom/tencent/mm/ui/widget/MMWebView;
    //   108: new 105	java/lang/StringBuilder
    //   111: dup
    //   112: ldc 107
    //   114: invokespecial 110	java/lang/StringBuilder:<init>	(Ljava/lang/String;)V
    //   117: aload_3
    //   118: invokevirtual 114	java/lang/StringBuilder:append	(Ljava/lang/String;)Ljava/lang/StringBuilder;
    //   121: ldc 116
    //   123: invokevirtual 114	java/lang/StringBuilder:append	(Ljava/lang/String;)Ljava/lang/StringBuilder;
    //   126: invokevirtual 120	java/lang/StringBuilder:toString	()Ljava/lang/String;
    //   129: aconst_null
    //   130: invokevirtual 126	com/tencent/mm/ui/widget/MMWebView:evaluateJavascript	(Ljava/lang/String;Landroid/webkit/ValueCallback;)V
    //   133: sipush 7652
    //   136: invokestatic 129	com/tencent/matrix/trace/core/AppMethodBeat:o	(I)V
    //   139: return
    //   140: aload_1
    //   141: invokeinterface 133 1 0
    //   146: tableswitch	default:+170 -> 316, 1:+446->592, 2:+720->866, 3:+1109->1255, 4:+170->316, 5:+1228->1374, 6:+1737->1883, 7:+2007->2153, 8:+2376->2522, 9:+2551->2697, 10:+2667->2813, 11:+1457->1603, 12:+2748->2894, 13:+170->316, 14:+2895->3041, 15:+3054->3200, 16:+3135->3281, 17:+3216->3362, 18:+3297->3443, 19:+3378->3524, 20:+3969->4115, 21:+4208->4354, 22:+4383->4529, 23:+620->766, 24:+4851->4997, 25:+3459->3605, 26:+3688->3834, 27:+350->496, 28:+1654->1800, 29:+5177->5323, 30:+170->316, 31:+5257->5403, 32:+170->316, 33:+4622->4768, 34:+5397->5543, 35:+5502->5648, 36:+5591->5737, 37:+2296->2442, 38:+947->1093, 39:+1028->1174
    //   317: getfield 17	com/tencent/mm/plugin/webview/ui/tools/j$10:utN	Lcom/tencent/mm/plugin/webview/ui/tools/j;
    //   320: invokevirtual 52	com/tencent/mm/plugin/webview/ui/tools/j:cZv	()Lcom/tencent/mm/plugin/webview/ui/tools/WebViewUI;
    //   323: getfield 137	com/tencent/mm/plugin/webview/ui/tools/WebViewUI:ulI	Lcom/tencent/mm/plugin/webview/model/aq;
    //   326: invokevirtual 143	com/tencent/mm/plugin/webview/model/aq:cYc	()Lcom/tencent/mm/plugin/webview/model/aq$e;
    //   329: astore_3
    //   330: aload_3
    //   331: iconst_3
    //   332: anewarray 4	java/lang/Object
    //   335: dup
    //   336: iconst_0
    //   337: aload_0
    //   338: getfield 17	com/tencent/mm/plugin/webview/ui/tools/j$10:utN	Lcom/tencent/mm/plugin/webview/ui/tools/j;
    //   341: invokevirtual 52	com/tencent/mm/plugin/webview/ui/tools/j:cZv	()Lcom/tencent/mm/plugin/webview/ui/tools/WebViewUI;
    //   344: getfield 146	com/tencent/mm/plugin/webview/ui/tools/WebViewUI:cOG	Ljava/lang/String;
    //   347: aastore
    //   348: dup
    //   349: iconst_1
    //   350: bipush 16
    //   352: invokestatic 152	java/lang/Integer:valueOf	(I)Ljava/lang/Integer;
    //   355: aastore
    //   356: dup
    //   357: iconst_2
    //   358: iconst_1
    //   359: invokestatic 152	java/lang/Integer:valueOf	(I)Ljava/lang/Integer;
    //   362: aastore
    //   363: putfield 158	com/tencent/mm/plugin/webview/model/aq$e:une	[Ljava/lang/Object;
    //   366: aload_3
    //   367: aload_0
    //   368: getfield 17	com/tencent/mm/plugin/webview/ui/tools/j$10:utN	Lcom/tencent/mm/plugin/webview/ui/tools/j;
    //   371: invokevirtual 52	com/tencent/mm/plugin/webview/ui/tools/j:cZv	()Lcom/tencent/mm/plugin/webview/ui/tools/WebViewUI;
    //   374: getfield 162	com/tencent/mm/plugin/webview/ui/tools/WebViewUI:icy	Lcom/tencent/mm/plugin/webview/stub/d;
    //   377: invokevirtual 165	com/tencent/mm/plugin/webview/model/aq$e:b	(Lcom/tencent/mm/plugin/webview/stub/d;)V
    //   380: new 105	java/lang/StringBuilder
    //   383: dup
    //   384: invokespecial 166	java/lang/StringBuilder:<init>	()V
    //   387: aload_1
    //   388: invokeinterface 170 1 0
    //   393: invokevirtual 173	java/lang/StringBuilder:append	(Ljava/lang/Object;)Ljava/lang/StringBuilder;
    //   396: invokevirtual 120	java/lang/StringBuilder:toString	()Ljava/lang/String;
    //   399: astore_3
    //   400: aload_3
    //   401: invokestatic 179	com/tencent/mm/sdk/platformtools/bo:isNullOrNil	(Ljava/lang/String;)Z
    //   404: ifne +5643 -> 6047
    //   407: new 181	android/os/Bundle
    //   410: astore_1
    //   411: aload_1
    //   412: invokespecial 182	android/os/Bundle:<init>	()V
    //   415: aload_1
    //   416: ldc 184
    //   418: aload_3
    //   419: invokevirtual 187	android/os/Bundle:putString	(Ljava/lang/String;Ljava/lang/String;)V
    //   422: aload_0
    //   423: getfield 17	com/tencent/mm/plugin/webview/ui/tools/j$10:utN	Lcom/tencent/mm/plugin/webview/ui/tools/j;
    //   426: invokevirtual 52	com/tencent/mm/plugin/webview/ui/tools/j:cZv	()Lcom/tencent/mm/plugin/webview/ui/tools/WebViewUI;
    //   429: getfield 162	com/tencent/mm/plugin/webview/ui/tools/WebViewUI:icy	Lcom/tencent/mm/plugin/webview/stub/d;
    //   432: bipush 50
    //   434: aload_1
    //   435: invokeinterface 192 3 0
    //   440: astore_1
    //   441: aload_1
    //   442: ifnull +5618 -> 6060
    //   445: aload_1
    //   446: ldc 194
    //   448: invokevirtual 198	android/os/Bundle:getInt	(Ljava/lang/String;)I
    //   451: istore_2
    //   452: iload_2
    //   453: iconst_2
    //   454: if_icmpne +5372 -> 5826
    //   457: iconst_1
    //   458: istore_2
    //   459: aload_1
    //   460: ldc 194
    //   462: invokevirtual 198	android/os/Bundle:getInt	(Ljava/lang/String;)I
    //   465: istore 5
    //   467: iload 5
    //   469: iconst_3
    //   470: if_icmpne +5361 -> 5831
    //   473: iconst_1
    //   474: istore_2
    //   475: iload_2
    //   476: ifeq +5380 -> 5856
    //   479: aload_0
    //   480: getfield 17	com/tencent/mm/plugin/webview/ui/tools/j$10:utN	Lcom/tencent/mm/plugin/webview/ui/tools/j;
    //   483: aload_3
    //   484: invokevirtual 201	com/tencent/mm/plugin/webview/ui/tools/j:afF	(Ljava/lang/String;)V
    //   487: sipush 7652
    //   490: invokestatic 129	com/tencent/matrix/trace/core/AppMethodBeat:o	(I)V
    //   493: goto -354 -> 139
    //   496: aload_0
    //   497: getfield 17	com/tencent/mm/plugin/webview/ui/tools/j$10:utN	Lcom/tencent/mm/plugin/webview/ui/tools/j;
    //   500: invokevirtual 52	com/tencent/mm/plugin/webview/ui/tools/j:cZv	()Lcom/tencent/mm/plugin/webview/ui/tools/WebViewUI;
    //   503: getfield 137	com/tencent/mm/plugin/webview/ui/tools/WebViewUI:ulI	Lcom/tencent/mm/plugin/webview/model/aq;
    //   506: invokevirtual 143	com/tencent/mm/plugin/webview/model/aq:cYc	()Lcom/tencent/mm/plugin/webview/model/aq$e;
    //   509: astore_1
    //   510: aload_1
    //   511: iconst_3
    //   512: anewarray 4	java/lang/Object
    //   515: dup
    //   516: iconst_0
    //   517: aload_0
    //   518: getfield 17	com/tencent/mm/plugin/webview/ui/tools/j$10:utN	Lcom/tencent/mm/plugin/webview/ui/tools/j;
    //   521: invokevirtual 52	com/tencent/mm/plugin/webview/ui/tools/j:cZv	()Lcom/tencent/mm/plugin/webview/ui/tools/WebViewUI;
    //   524: getfield 146	com/tencent/mm/plugin/webview/ui/tools/WebViewUI:cOG	Ljava/lang/String;
    //   527: aastore
    //   528: dup
    //   529: iconst_1
    //   530: bipush 32
    //   532: invokestatic 152	java/lang/Integer:valueOf	(I)Ljava/lang/Integer;
    //   535: aastore
    //   536: dup
    //   537: iconst_2
    //   538: iconst_1
    //   539: invokestatic 152	java/lang/Integer:valueOf	(I)Ljava/lang/Integer;
    //   542: aastore
    //   543: putfield 158	com/tencent/mm/plugin/webview/model/aq$e:une	[Ljava/lang/Object;
    //   546: aload_1
    //   547: aload_0
    //   548: getfield 17	com/tencent/mm/plugin/webview/ui/tools/j$10:utN	Lcom/tencent/mm/plugin/webview/ui/tools/j;
    //   551: invokevirtual 52	com/tencent/mm/plugin/webview/ui/tools/j:cZv	()Lcom/tencent/mm/plugin/webview/ui/tools/WebViewUI;
    //   554: getfield 162	com/tencent/mm/plugin/webview/ui/tools/WebViewUI:icy	Lcom/tencent/mm/plugin/webview/stub/d;
    //   557: invokevirtual 165	com/tencent/mm/plugin/webview/model/aq$e:b	(Lcom/tencent/mm/plugin/webview/stub/d;)V
    //   560: aload_0
    //   561: getfield 17	com/tencent/mm/plugin/webview/ui/tools/j$10:utN	Lcom/tencent/mm/plugin/webview/ui/tools/j;
    //   564: invokevirtual 52	com/tencent/mm/plugin/webview/ui/tools/j:cZv	()Lcom/tencent/mm/plugin/webview/ui/tools/WebViewUI;
    //   567: invokevirtual 205	com/tencent/mm/plugin/webview/ui/tools/WebViewUI:cWG	()Z
    //   570: ifne +5477 -> 6047
    //   573: aload_0
    //   574: getfield 17	com/tencent/mm/plugin/webview/ui/tools/j$10:utN	Lcom/tencent/mm/plugin/webview/ui/tools/j;
    //   577: invokevirtual 52	com/tencent/mm/plugin/webview/ui/tools/j:cZv	()Lcom/tencent/mm/plugin/webview/ui/tools/WebViewUI;
    //   580: invokevirtual 208	com/tencent/mm/plugin/webview/ui/tools/WebViewUI:finish	()V
    //   583: sipush 7652
    //   586: invokestatic 129	com/tencent/matrix/trace/core/AppMethodBeat:o	(I)V
    //   589: goto -450 -> 139
    //   592: aload_0
    //   593: getfield 17	com/tencent/mm/plugin/webview/ui/tools/j$10:utN	Lcom/tencent/mm/plugin/webview/ui/tools/j;
    //   596: invokevirtual 211	com/tencent/mm/plugin/webview/ui/tools/a:cZv	()Lcom/tencent/mm/plugin/webview/ui/tools/WebViewUI;
    //   599: invokevirtual 215	com/tencent/mm/plugin/webview/ui/tools/WebViewUI:getIntent	()Landroid/content/Intent;
    //   602: ldc 217
    //   604: invokevirtual 223	android/content/Intent:getStringExtra	(Ljava/lang/String;)Ljava/lang/String;
    //   607: astore_1
    //   608: aload_0
    //   609: getfield 17	com/tencent/mm/plugin/webview/ui/tools/j$10:utN	Lcom/tencent/mm/plugin/webview/ui/tools/j;
    //   612: invokevirtual 211	com/tencent/mm/plugin/webview/ui/tools/a:cZv	()Lcom/tencent/mm/plugin/webview/ui/tools/WebViewUI;
    //   615: invokevirtual 215	com/tencent/mm/plugin/webview/ui/tools/WebViewUI:getIntent	()Landroid/content/Intent;
    //   618: ldc 225
    //   620: invokevirtual 223	android/content/Intent:getStringExtra	(Ljava/lang/String;)Ljava/lang/String;
    //   623: astore_3
    //   624: aload_0
    //   625: getfield 17	com/tencent/mm/plugin/webview/ui/tools/j$10:utN	Lcom/tencent/mm/plugin/webview/ui/tools/j;
    //   628: invokevirtual 211	com/tencent/mm/plugin/webview/ui/tools/a:cZv	()Lcom/tencent/mm/plugin/webview/ui/tools/WebViewUI;
    //   631: invokevirtual 215	com/tencent/mm/plugin/webview/ui/tools/WebViewUI:getIntent	()Landroid/content/Intent;
    //   634: ldc 227
    //   636: invokevirtual 223	android/content/Intent:getStringExtra	(Ljava/lang/String;)Ljava/lang/String;
    //   639: astore 4
    //   641: aload_0
    //   642: getfield 17	com/tencent/mm/plugin/webview/ui/tools/j$10:utN	Lcom/tencent/mm/plugin/webview/ui/tools/j;
    //   645: invokevirtual 52	com/tencent/mm/plugin/webview/ui/tools/j:cZv	()Lcom/tencent/mm/plugin/webview/ui/tools/WebViewUI;
    //   648: getfield 137	com/tencent/mm/plugin/webview/ui/tools/WebViewUI:ulI	Lcom/tencent/mm/plugin/webview/model/aq;
    //   651: invokevirtual 143	com/tencent/mm/plugin/webview/model/aq:cYc	()Lcom/tencent/mm/plugin/webview/model/aq$e;
    //   654: astore 6
    //   656: aload 6
    //   658: bipush 6
    //   660: anewarray 4	java/lang/Object
    //   663: dup
    //   664: iconst_0
    //   665: aload_0
    //   666: getfield 17	com/tencent/mm/plugin/webview/ui/tools/j$10:utN	Lcom/tencent/mm/plugin/webview/ui/tools/j;
    //   669: invokevirtual 52	com/tencent/mm/plugin/webview/ui/tools/j:cZv	()Lcom/tencent/mm/plugin/webview/ui/tools/WebViewUI;
    //   672: getfield 146	com/tencent/mm/plugin/webview/ui/tools/WebViewUI:cOG	Ljava/lang/String;
    //   675: aastore
    //   676: dup
    //   677: iconst_1
    //   678: iconst_1
    //   679: invokestatic 152	java/lang/Integer:valueOf	(I)Ljava/lang/Integer;
    //   682: aastore
    //   683: dup
    //   684: iconst_2
    //   685: iconst_1
    //   686: invokestatic 152	java/lang/Integer:valueOf	(I)Ljava/lang/Integer;
    //   689: aastore
    //   690: dup
    //   691: iconst_3
    //   692: aload_1
    //   693: aastore
    //   694: dup
    //   695: iconst_4
    //   696: aload_3
    //   697: aastore
    //   698: dup
    //   699: iconst_5
    //   700: aload 4
    //   702: aastore
    //   703: putfield 158	com/tencent/mm/plugin/webview/model/aq$e:une	[Ljava/lang/Object;
    //   706: aload 6
    //   708: aload_0
    //   709: getfield 17	com/tencent/mm/plugin/webview/ui/tools/j$10:utN	Lcom/tencent/mm/plugin/webview/ui/tools/j;
    //   712: invokevirtual 52	com/tencent/mm/plugin/webview/ui/tools/j:cZv	()Lcom/tencent/mm/plugin/webview/ui/tools/WebViewUI;
    //   715: getfield 162	com/tencent/mm/plugin/webview/ui/tools/WebViewUI:icy	Lcom/tencent/mm/plugin/webview/stub/d;
    //   718: invokevirtual 165	com/tencent/mm/plugin/webview/model/aq$e:b	(Lcom/tencent/mm/plugin/webview/stub/d;)V
    //   721: aload_0
    //   722: getfield 17	com/tencent/mm/plugin/webview/ui/tools/j$10:utN	Lcom/tencent/mm/plugin/webview/ui/tools/j;
    //   725: invokevirtual 52	com/tencent/mm/plugin/webview/ui/tools/j:cZv	()Lcom/tencent/mm/plugin/webview/ui/tools/WebViewUI;
    //   728: aload_0
    //   729: getfield 17	com/tencent/mm/plugin/webview/ui/tools/j$10:utN	Lcom/tencent/mm/plugin/webview/ui/tools/j;
    //   732: invokevirtual 52	com/tencent/mm/plugin/webview/ui/tools/j:cZv	()Lcom/tencent/mm/plugin/webview/ui/tools/WebViewUI;
    //   735: getfield 231	com/tencent/mm/plugin/webview/ui/tools/WebViewUI:icz	Lcom/tencent/mm/plugin/webview/ui/tools/k;
    //   738: invokevirtual 237	com/tencent/mm/plugin/webview/ui/tools/k:cZT	()Lcom/tencent/mm/protocal/GeneralControlWrapper;
    //   741: invokevirtual 242	com/tencent/mm/protocal/GeneralControlWrapper:dmm	()Z
    //   744: putfield 245	com/tencent/mm/plugin/webview/ui/tools/WebViewUI:uvr	Z
    //   747: aload_0
    //   748: getfield 17	com/tencent/mm/plugin/webview/ui/tools/j$10:utN	Lcom/tencent/mm/plugin/webview/ui/tools/j;
    //   751: invokevirtual 52	com/tencent/mm/plugin/webview/ui/tools/j:cZv	()Lcom/tencent/mm/plugin/webview/ui/tools/WebViewUI;
    //   754: invokevirtual 248	com/tencent/mm/plugin/webview/ui/tools/WebViewUI:clH	()V
    //   757: sipush 7652
    //   760: invokestatic 129	com/tencent/matrix/trace/core/AppMethodBeat:o	(I)V
    //   763: goto -624 -> 139
    //   766: new 219	android/content/Intent
    //   769: dup
    //   770: invokespecial 249	android/content/Intent:<init>	()V
    //   773: astore_1
    //   774: aload_0
    //   775: getfield 17	com/tencent/mm/plugin/webview/ui/tools/j$10:utN	Lcom/tencent/mm/plugin/webview/ui/tools/j;
    //   778: invokevirtual 211	com/tencent/mm/plugin/webview/ui/tools/a:cZv	()Lcom/tencent/mm/plugin/webview/ui/tools/WebViewUI;
    //   781: invokevirtual 215	com/tencent/mm/plugin/webview/ui/tools/WebViewUI:getIntent	()Landroid/content/Intent;
    //   784: ldc 251
    //   786: invokevirtual 223	android/content/Intent:getStringExtra	(Ljava/lang/String;)Ljava/lang/String;
    //   789: astore_3
    //   790: aload_3
    //   791: ifnull +42 -> 833
    //   794: aload_1
    //   795: ldc 253
    //   797: iconst_1
    //   798: invokevirtual 257	android/content/Intent:putExtra	(Ljava/lang/String;Z)Landroid/content/Intent;
    //   801: pop
    //   802: aload_1
    //   803: ldc 251
    //   805: aload_3
    //   806: invokevirtual 260	android/content/Intent:putExtra	(Ljava/lang/String;Ljava/lang/String;)Landroid/content/Intent;
    //   809: pop
    //   810: aload_0
    //   811: getfield 17	com/tencent/mm/plugin/webview/ui/tools/j$10:utN	Lcom/tencent/mm/plugin/webview/ui/tools/j;
    //   814: invokevirtual 52	com/tencent/mm/plugin/webview/ui/tools/j:cZv	()Lcom/tencent/mm/plugin/webview/ui/tools/WebViewUI;
    //   817: ldc_w 262
    //   820: aload_1
    //   821: invokestatic 268	com/tencent/mm/bp/d:f	(Landroid/content/Context;Ljava/lang/String;Landroid/content/Intent;)V
    //   824: sipush 7652
    //   827: invokestatic 129	com/tencent/matrix/trace/core/AppMethodBeat:o	(I)V
    //   830: goto -691 -> 139
    //   833: aload_1
    //   834: ldc_w 270
    //   837: aload_0
    //   838: getfield 17	com/tencent/mm/plugin/webview/ui/tools/j$10:utN	Lcom/tencent/mm/plugin/webview/ui/tools/j;
    //   841: invokevirtual 211	com/tencent/mm/plugin/webview/ui/tools/a:cZv	()Lcom/tencent/mm/plugin/webview/ui/tools/WebViewUI;
    //   844: invokevirtual 215	com/tencent/mm/plugin/webview/ui/tools/WebViewUI:getIntent	()Landroid/content/Intent;
    //   847: ldc_w 272
    //   850: ldc2_w 273
    //   853: invokevirtual 278	android/content/Intent:getLongExtra	(Ljava/lang/String;J)J
    //   856: invokestatic 283	java/lang/Long:valueOf	(J)Ljava/lang/Long;
    //   859: invokevirtual 286	android/content/Intent:putExtra	(Ljava/lang/String;Ljava/io/Serializable;)Landroid/content/Intent;
    //   862: pop
    //   863: goto -53 -> 810
    //   866: aload_0
    //   867: getfield 17	com/tencent/mm/plugin/webview/ui/tools/j$10:utN	Lcom/tencent/mm/plugin/webview/ui/tools/j;
    //   870: invokevirtual 211	com/tencent/mm/plugin/webview/ui/tools/a:cZv	()Lcom/tencent/mm/plugin/webview/ui/tools/WebViewUI;
    //   873: invokevirtual 215	com/tencent/mm/plugin/webview/ui/tools/WebViewUI:getIntent	()Landroid/content/Intent;
    //   876: ldc 217
    //   878: invokevirtual 223	android/content/Intent:getStringExtra	(Ljava/lang/String;)Ljava/lang/String;
    //   881: astore_3
    //   882: aload_0
    //   883: getfield 17	com/tencent/mm/plugin/webview/ui/tools/j$10:utN	Lcom/tencent/mm/plugin/webview/ui/tools/j;
    //   886: invokevirtual 211	com/tencent/mm/plugin/webview/ui/tools/a:cZv	()Lcom/tencent/mm/plugin/webview/ui/tools/WebViewUI;
    //   889: invokevirtual 215	com/tencent/mm/plugin/webview/ui/tools/WebViewUI:getIntent	()Landroid/content/Intent;
    //   892: ldc 225
    //   894: invokevirtual 223	android/content/Intent:getStringExtra	(Ljava/lang/String;)Ljava/lang/String;
    //   897: astore 4
    //   899: aload_0
    //   900: getfield 17	com/tencent/mm/plugin/webview/ui/tools/j$10:utN	Lcom/tencent/mm/plugin/webview/ui/tools/j;
    //   903: invokevirtual 211	com/tencent/mm/plugin/webview/ui/tools/a:cZv	()Lcom/tencent/mm/plugin/webview/ui/tools/WebViewUI;
    //   906: invokevirtual 215	com/tencent/mm/plugin/webview/ui/tools/WebViewUI:getIntent	()Landroid/content/Intent;
    //   909: ldc 227
    //   911: invokevirtual 223	android/content/Intent:getStringExtra	(Ljava/lang/String;)Ljava/lang/String;
    //   914: astore 6
    //   916: aload_0
    //   917: getfield 17	com/tencent/mm/plugin/webview/ui/tools/j$10:utN	Lcom/tencent/mm/plugin/webview/ui/tools/j;
    //   920: invokevirtual 52	com/tencent/mm/plugin/webview/ui/tools/j:cZv	()Lcom/tencent/mm/plugin/webview/ui/tools/WebViewUI;
    //   923: getfield 137	com/tencent/mm/plugin/webview/ui/tools/WebViewUI:ulI	Lcom/tencent/mm/plugin/webview/model/aq;
    //   926: invokevirtual 143	com/tencent/mm/plugin/webview/model/aq:cYc	()Lcom/tencent/mm/plugin/webview/model/aq$e;
    //   929: astore_1
    //   930: aload_1
    //   931: bipush 6
    //   933: anewarray 4	java/lang/Object
    //   936: dup
    //   937: iconst_0
    //   938: aload_0
    //   939: getfield 17	com/tencent/mm/plugin/webview/ui/tools/j$10:utN	Lcom/tencent/mm/plugin/webview/ui/tools/j;
    //   942: invokevirtual 52	com/tencent/mm/plugin/webview/ui/tools/j:cZv	()Lcom/tencent/mm/plugin/webview/ui/tools/WebViewUI;
    //   945: getfield 146	com/tencent/mm/plugin/webview/ui/tools/WebViewUI:cOG	Ljava/lang/String;
    //   948: aastore
    //   949: dup
    //   950: iconst_1
    //   951: iconst_2
    //   952: invokestatic 152	java/lang/Integer:valueOf	(I)Ljava/lang/Integer;
    //   955: aastore
    //   956: dup
    //   957: iconst_2
    //   958: iconst_1
    //   959: invokestatic 152	java/lang/Integer:valueOf	(I)Ljava/lang/Integer;
    //   962: aastore
    //   963: dup
    //   964: iconst_3
    //   965: aload_3
    //   966: aastore
    //   967: dup
    //   968: iconst_4
    //   969: aload 4
    //   971: aastore
    //   972: dup
    //   973: iconst_5
    //   974: aload 6
    //   976: aastore
    //   977: putfield 158	com/tencent/mm/plugin/webview/model/aq$e:une	[Ljava/lang/Object;
    //   980: aload_1
    //   981: aload_0
    //   982: getfield 17	com/tencent/mm/plugin/webview/ui/tools/j$10:utN	Lcom/tencent/mm/plugin/webview/ui/tools/j;
    //   985: invokevirtual 52	com/tencent/mm/plugin/webview/ui/tools/j:cZv	()Lcom/tencent/mm/plugin/webview/ui/tools/WebViewUI;
    //   988: getfield 162	com/tencent/mm/plugin/webview/ui/tools/WebViewUI:icy	Lcom/tencent/mm/plugin/webview/stub/d;
    //   991: invokevirtual 165	com/tencent/mm/plugin/webview/model/aq$e:b	(Lcom/tencent/mm/plugin/webview/stub/d;)V
    //   994: aload_0
    //   995: getfield 17	com/tencent/mm/plugin/webview/ui/tools/j$10:utN	Lcom/tencent/mm/plugin/webview/ui/tools/j;
    //   998: invokevirtual 52	com/tencent/mm/plugin/webview/ui/tools/j:cZv	()Lcom/tencent/mm/plugin/webview/ui/tools/WebViewUI;
    //   1001: aload_0
    //   1002: getfield 17	com/tencent/mm/plugin/webview/ui/tools/j$10:utN	Lcom/tencent/mm/plugin/webview/ui/tools/j;
    //   1005: invokevirtual 52	com/tencent/mm/plugin/webview/ui/tools/j:cZv	()Lcom/tencent/mm/plugin/webview/ui/tools/WebViewUI;
    //   1008: getfield 231	com/tencent/mm/plugin/webview/ui/tools/WebViewUI:icz	Lcom/tencent/mm/plugin/webview/ui/tools/k;
    //   1011: invokevirtual 237	com/tencent/mm/plugin/webview/ui/tools/k:cZT	()Lcom/tencent/mm/protocal/GeneralControlWrapper;
    //   1014: invokevirtual 242	com/tencent/mm/protocal/GeneralControlWrapper:dmm	()Z
    //   1017: putfield 245	com/tencent/mm/plugin/webview/ui/tools/WebViewUI:uvr	Z
    //   1020: aload_0
    //   1021: getfield 17	com/tencent/mm/plugin/webview/ui/tools/j$10:utN	Lcom/tencent/mm/plugin/webview/ui/tools/j;
    //   1024: getfield 290	com/tencent/mm/plugin/webview/ui/tools/j:utG	Ljava/util/HashMap;
    //   1027: aload_0
    //   1028: getfield 17	com/tencent/mm/plugin/webview/ui/tools/j$10:utN	Lcom/tencent/mm/plugin/webview/ui/tools/j;
    //   1031: invokevirtual 52	com/tencent/mm/plugin/webview/ui/tools/j:cZv	()Lcom/tencent/mm/plugin/webview/ui/tools/WebViewUI;
    //   1034: getfield 293	com/tencent/mm/plugin/webview/ui/tools/WebViewUI:pzf	Lcom/tencent/mm/ui/widget/MMWebView;
    //   1037: invokevirtual 296	com/tencent/mm/ui/widget/MMWebView:getUrl	()Ljava/lang/String;
    //   1040: invokevirtual 300	java/util/HashMap:containsKey	(Ljava/lang/Object;)Z
    //   1043: ifeq +33 -> 1076
    //   1046: aload_0
    //   1047: getfield 17	com/tencent/mm/plugin/webview/ui/tools/j$10:utN	Lcom/tencent/mm/plugin/webview/ui/tools/j;
    //   1050: getfield 290	com/tencent/mm/plugin/webview/ui/tools/j:utG	Ljava/util/HashMap;
    //   1053: aload_0
    //   1054: getfield 17	com/tencent/mm/plugin/webview/ui/tools/j$10:utN	Lcom/tencent/mm/plugin/webview/ui/tools/j;
    //   1057: invokevirtual 52	com/tencent/mm/plugin/webview/ui/tools/j:cZv	()Lcom/tencent/mm/plugin/webview/ui/tools/WebViewUI;
    //   1060: getfield 293	com/tencent/mm/plugin/webview/ui/tools/WebViewUI:pzf	Lcom/tencent/mm/ui/widget/MMWebView;
    //   1063: invokevirtual 296	com/tencent/mm/ui/widget/MMWebView:getUrl	()Ljava/lang/String;
    //   1066: invokevirtual 304	java/util/HashMap:get	(Ljava/lang/Object;)Ljava/lang/Object;
    //   1069: checkcast 148	java/lang/Integer
    //   1072: invokevirtual 307	java/lang/Integer:intValue	()I
    //   1075: istore_2
    //   1076: aload_0
    //   1077: getfield 17	com/tencent/mm/plugin/webview/ui/tools/j$10:utN	Lcom/tencent/mm/plugin/webview/ui/tools/j;
    //   1080: iload_2
    //   1081: invokestatic 311	com/tencent/mm/plugin/webview/ui/tools/j:a	(Lcom/tencent/mm/plugin/webview/ui/tools/j;I)V
    //   1084: sipush 7652
    //   1087: invokestatic 129	com/tencent/matrix/trace/core/AppMethodBeat:o	(I)V
    //   1090: goto -951 -> 139
    //   1093: aload_0
    //   1094: getfield 17	com/tencent/mm/plugin/webview/ui/tools/j$10:utN	Lcom/tencent/mm/plugin/webview/ui/tools/j;
    //   1097: invokevirtual 52	com/tencent/mm/plugin/webview/ui/tools/j:cZv	()Lcom/tencent/mm/plugin/webview/ui/tools/WebViewUI;
    //   1100: getfield 137	com/tencent/mm/plugin/webview/ui/tools/WebViewUI:ulI	Lcom/tencent/mm/plugin/webview/model/aq;
    //   1103: invokevirtual 143	com/tencent/mm/plugin/webview/model/aq:cYc	()Lcom/tencent/mm/plugin/webview/model/aq$e;
    //   1106: astore_1
    //   1107: aload_1
    //   1108: iconst_3
    //   1109: anewarray 4	java/lang/Object
    //   1112: dup
    //   1113: iconst_0
    //   1114: aload_0
    //   1115: getfield 17	com/tencent/mm/plugin/webview/ui/tools/j$10:utN	Lcom/tencent/mm/plugin/webview/ui/tools/j;
    //   1118: invokevirtual 52	com/tencent/mm/plugin/webview/ui/tools/j:cZv	()Lcom/tencent/mm/plugin/webview/ui/tools/WebViewUI;
    //   1121: getfield 146	com/tencent/mm/plugin/webview/ui/tools/WebViewUI:cOG	Ljava/lang/String;
    //   1124: aastore
    //   1125: dup
    //   1126: iconst_1
    //   1127: bipush 36
    //   1129: invokestatic 152	java/lang/Integer:valueOf	(I)Ljava/lang/Integer;
    //   1132: aastore
    //   1133: dup
    //   1134: iconst_2
    //   1135: iconst_1
    //   1136: invokestatic 152	java/lang/Integer:valueOf	(I)Ljava/lang/Integer;
    //   1139: aastore
    //   1140: putfield 158	com/tencent/mm/plugin/webview/model/aq$e:une	[Ljava/lang/Object;
    //   1143: aload_1
    //   1144: aload_0
    //   1145: getfield 17	com/tencent/mm/plugin/webview/ui/tools/j$10:utN	Lcom/tencent/mm/plugin/webview/ui/tools/j;
    //   1148: invokevirtual 52	com/tencent/mm/plugin/webview/ui/tools/j:cZv	()Lcom/tencent/mm/plugin/webview/ui/tools/WebViewUI;
    //   1151: getfield 162	com/tencent/mm/plugin/webview/ui/tools/WebViewUI:icy	Lcom/tencent/mm/plugin/webview/stub/d;
    //   1154: invokevirtual 165	com/tencent/mm/plugin/webview/model/aq$e:b	(Lcom/tencent/mm/plugin/webview/stub/d;)V
    //   1157: aload_0
    //   1158: getfield 17	com/tencent/mm/plugin/webview/ui/tools/j$10:utN	Lcom/tencent/mm/plugin/webview/ui/tools/j;
    //   1161: iconst_1
    //   1162: invokestatic 313	com/tencent/mm/plugin/webview/ui/tools/j:b	(Lcom/tencent/mm/plugin/webview/ui/tools/j;I)V
    //   1165: sipush 7652
    //   1168: invokestatic 129	com/tencent/matrix/trace/core/AppMethodBeat:o	(I)V
    //   1171: goto -1032 -> 139
    //   1174: aload_0
    //   1175: getfield 17	com/tencent/mm/plugin/webview/ui/tools/j$10:utN	Lcom/tencent/mm/plugin/webview/ui/tools/j;
    //   1178: invokevirtual 52	com/tencent/mm/plugin/webview/ui/tools/j:cZv	()Lcom/tencent/mm/plugin/webview/ui/tools/WebViewUI;
    //   1181: getfield 137	com/tencent/mm/plugin/webview/ui/tools/WebViewUI:ulI	Lcom/tencent/mm/plugin/webview/model/aq;
    //   1184: invokevirtual 143	com/tencent/mm/plugin/webview/model/aq:cYc	()Lcom/tencent/mm/plugin/webview/model/aq$e;
    //   1187: astore_1
    //   1188: aload_1
    //   1189: iconst_3
    //   1190: anewarray 4	java/lang/Object
    //   1193: dup
    //   1194: iconst_0
    //   1195: aload_0
    //   1196: getfield 17	com/tencent/mm/plugin/webview/ui/tools/j$10:utN	Lcom/tencent/mm/plugin/webview/ui/tools/j;
    //   1199: invokevirtual 52	com/tencent/mm/plugin/webview/ui/tools/j:cZv	()Lcom/tencent/mm/plugin/webview/ui/tools/WebViewUI;
    //   1202: getfield 146	com/tencent/mm/plugin/webview/ui/tools/WebViewUI:cOG	Ljava/lang/String;
    //   1205: aastore
    //   1206: dup
    //   1207: iconst_1
    //   1208: bipush 37
    //   1210: invokestatic 152	java/lang/Integer:valueOf	(I)Ljava/lang/Integer;
    //   1213: aastore
    //   1214: dup
    //   1215: iconst_2
    //   1216: iconst_1
    //   1217: invokestatic 152	java/lang/Integer:valueOf	(I)Ljava/lang/Integer;
    //   1220: aastore
    //   1221: putfield 158	com/tencent/mm/plugin/webview/model/aq$e:une	[Ljava/lang/Object;
    //   1224: aload_1
    //   1225: aload_0
    //   1226: getfield 17	com/tencent/mm/plugin/webview/ui/tools/j$10:utN	Lcom/tencent/mm/plugin/webview/ui/tools/j;
    //   1229: invokevirtual 52	com/tencent/mm/plugin/webview/ui/tools/j:cZv	()Lcom/tencent/mm/plugin/webview/ui/tools/WebViewUI;
    //   1232: getfield 162	com/tencent/mm/plugin/webview/ui/tools/WebViewUI:icy	Lcom/tencent/mm/plugin/webview/stub/d;
    //   1235: invokevirtual 165	com/tencent/mm/plugin/webview/model/aq$e:b	(Lcom/tencent/mm/plugin/webview/stub/d;)V
    //   1238: aload_0
    //   1239: getfield 17	com/tencent/mm/plugin/webview/ui/tools/j$10:utN	Lcom/tencent/mm/plugin/webview/ui/tools/j;
    //   1242: iconst_0
    //   1243: invokestatic 313	com/tencent/mm/plugin/webview/ui/tools/j:b	(Lcom/tencent/mm/plugin/webview/ui/tools/j;I)V
    //   1246: sipush 7652
    //   1249: invokestatic 129	com/tencent/matrix/trace/core/AppMethodBeat:o	(I)V
    //   1252: goto -1113 -> 139
    //   1255: aload_0
    //   1256: getfield 17	com/tencent/mm/plugin/webview/ui/tools/j$10:utN	Lcom/tencent/mm/plugin/webview/ui/tools/j;
    //   1259: invokevirtual 52	com/tencent/mm/plugin/webview/ui/tools/j:cZv	()Lcom/tencent/mm/plugin/webview/ui/tools/WebViewUI;
    //   1262: getfield 137	com/tencent/mm/plugin/webview/ui/tools/WebViewUI:ulI	Lcom/tencent/mm/plugin/webview/model/aq;
    //   1265: invokevirtual 143	com/tencent/mm/plugin/webview/model/aq:cYc	()Lcom/tencent/mm/plugin/webview/model/aq$e;
    //   1268: astore_1
    //   1269: aload_1
    //   1270: iconst_3
    //   1271: anewarray 4	java/lang/Object
    //   1274: dup
    //   1275: iconst_0
    //   1276: aload_0
    //   1277: getfield 17	com/tencent/mm/plugin/webview/ui/tools/j$10:utN	Lcom/tencent/mm/plugin/webview/ui/tools/j;
    //   1280: invokevirtual 52	com/tencent/mm/plugin/webview/ui/tools/j:cZv	()Lcom/tencent/mm/plugin/webview/ui/tools/WebViewUI;
    //   1283: getfield 146	com/tencent/mm/plugin/webview/ui/tools/WebViewUI:cOG	Ljava/lang/String;
    //   1286: aastore
    //   1287: dup
    //   1288: iconst_1
    //   1289: iconst_3
    //   1290: invokestatic 152	java/lang/Integer:valueOf	(I)Ljava/lang/Integer;
    //   1293: aastore
    //   1294: dup
    //   1295: iconst_2
    //   1296: iconst_1
    //   1297: invokestatic 152	java/lang/Integer:valueOf	(I)Ljava/lang/Integer;
    //   1300: aastore
    //   1301: putfield 158	com/tencent/mm/plugin/webview/model/aq$e:une	[Ljava/lang/Object;
    //   1304: aload_1
    //   1305: aload_0
    //   1306: getfield 17	com/tencent/mm/plugin/webview/ui/tools/j$10:utN	Lcom/tencent/mm/plugin/webview/ui/tools/j;
    //   1309: invokevirtual 52	com/tencent/mm/plugin/webview/ui/tools/j:cZv	()Lcom/tencent/mm/plugin/webview/ui/tools/WebViewUI;
    //   1312: getfield 162	com/tencent/mm/plugin/webview/ui/tools/WebViewUI:icy	Lcom/tencent/mm/plugin/webview/stub/d;
    //   1315: invokevirtual 165	com/tencent/mm/plugin/webview/model/aq$e:b	(Lcom/tencent/mm/plugin/webview/stub/d;)V
    //   1318: getstatic 319	com/tencent/mm/plugin/report/service/h:pYm	Lcom/tencent/mm/plugin/report/service/h;
    //   1321: ldc2_w 320
    //   1324: ldc2_w 322
    //   1327: lconst_1
    //   1328: iconst_0
    //   1329: invokevirtual 326	com/tencent/mm/plugin/report/service/h:a	(JJJZ)V
    //   1332: aload_0
    //   1333: getfield 17	com/tencent/mm/plugin/webview/ui/tools/j$10:utN	Lcom/tencent/mm/plugin/webview/ui/tools/j;
    //   1336: invokevirtual 52	com/tencent/mm/plugin/webview/ui/tools/j:cZv	()Lcom/tencent/mm/plugin/webview/ui/tools/WebViewUI;
    //   1339: aload_0
    //   1340: getfield 17	com/tencent/mm/plugin/webview/ui/tools/j$10:utN	Lcom/tencent/mm/plugin/webview/ui/tools/j;
    //   1343: invokevirtual 52	com/tencent/mm/plugin/webview/ui/tools/j:cZv	()Lcom/tencent/mm/plugin/webview/ui/tools/WebViewUI;
    //   1346: getfield 231	com/tencent/mm/plugin/webview/ui/tools/WebViewUI:icz	Lcom/tencent/mm/plugin/webview/ui/tools/k;
    //   1349: invokevirtual 237	com/tencent/mm/plugin/webview/ui/tools/k:cZT	()Lcom/tencent/mm/protocal/GeneralControlWrapper;
    //   1352: invokevirtual 242	com/tencent/mm/protocal/GeneralControlWrapper:dmm	()Z
    //   1355: putfield 245	com/tencent/mm/plugin/webview/ui/tools/WebViewUI:uvr	Z
    //   1358: aload_0
    //   1359: getfield 17	com/tencent/mm/plugin/webview/ui/tools/j$10:utN	Lcom/tencent/mm/plugin/webview/ui/tools/j;
    //   1362: invokevirtual 329	com/tencent/mm/plugin/webview/ui/tools/j:cZO	()V
    //   1365: sipush 7652
    //   1368: invokestatic 129	com/tencent/matrix/trace/core/AppMethodBeat:o	(I)V
    //   1371: goto -1232 -> 139
    //   1374: aload_0
    //   1375: getfield 17	com/tencent/mm/plugin/webview/ui/tools/j$10:utN	Lcom/tencent/mm/plugin/webview/ui/tools/j;
    //   1378: invokevirtual 52	com/tencent/mm/plugin/webview/ui/tools/j:cZv	()Lcom/tencent/mm/plugin/webview/ui/tools/WebViewUI;
    //   1381: getfield 137	com/tencent/mm/plugin/webview/ui/tools/WebViewUI:ulI	Lcom/tencent/mm/plugin/webview/model/aq;
    //   1384: invokevirtual 143	com/tencent/mm/plugin/webview/model/aq:cYc	()Lcom/tencent/mm/plugin/webview/model/aq$e;
    //   1387: astore_1
    //   1388: aload_1
    //   1389: iconst_3
    //   1390: anewarray 4	java/lang/Object
    //   1393: dup
    //   1394: iconst_0
    //   1395: aload_0
    //   1396: getfield 17	com/tencent/mm/plugin/webview/ui/tools/j$10:utN	Lcom/tencent/mm/plugin/webview/ui/tools/j;
    //   1399: invokevirtual 52	com/tencent/mm/plugin/webview/ui/tools/j:cZv	()Lcom/tencent/mm/plugin/webview/ui/tools/WebViewUI;
    //   1402: getfield 146	com/tencent/mm/plugin/webview/ui/tools/WebViewUI:cOG	Ljava/lang/String;
    //   1405: aastore
    //   1406: dup
    //   1407: iconst_1
    //   1408: iconst_4
    //   1409: invokestatic 152	java/lang/Integer:valueOf	(I)Ljava/lang/Integer;
    //   1412: aastore
    //   1413: dup
    //   1414: iconst_2
    //   1415: iconst_1
    //   1416: invokestatic 152	java/lang/Integer:valueOf	(I)Ljava/lang/Integer;
    //   1419: aastore
    //   1420: putfield 158	com/tencent/mm/plugin/webview/model/aq$e:une	[Ljava/lang/Object;
    //   1423: aload_1
    //   1424: aload_0
    //   1425: getfield 17	com/tencent/mm/plugin/webview/ui/tools/j$10:utN	Lcom/tencent/mm/plugin/webview/ui/tools/j;
    //   1428: invokevirtual 52	com/tencent/mm/plugin/webview/ui/tools/j:cZv	()Lcom/tencent/mm/plugin/webview/ui/tools/WebViewUI;
    //   1431: getfield 162	com/tencent/mm/plugin/webview/ui/tools/WebViewUI:icy	Lcom/tencent/mm/plugin/webview/stub/d;
    //   1434: invokevirtual 165	com/tencent/mm/plugin/webview/model/aq$e:b	(Lcom/tencent/mm/plugin/webview/stub/d;)V
    //   1437: aload_0
    //   1438: getfield 17	com/tencent/mm/plugin/webview/ui/tools/j$10:utN	Lcom/tencent/mm/plugin/webview/ui/tools/j;
    //   1441: invokevirtual 52	com/tencent/mm/plugin/webview/ui/tools/j:cZv	()Lcom/tencent/mm/plugin/webview/ui/tools/WebViewUI;
    //   1444: getfield 332	com/tencent/mm/plugin/webview/ui/tools/WebViewUI:uwb	Ljava/util/HashMap;
    //   1447: aload_0
    //   1448: getfield 17	com/tencent/mm/plugin/webview/ui/tools/j$10:utN	Lcom/tencent/mm/plugin/webview/ui/tools/j;
    //   1451: invokevirtual 52	com/tencent/mm/plugin/webview/ui/tools/j:cZv	()Lcom/tencent/mm/plugin/webview/ui/tools/WebViewUI;
    //   1454: getfield 293	com/tencent/mm/plugin/webview/ui/tools/WebViewUI:pzf	Lcom/tencent/mm/ui/widget/MMWebView;
    //   1457: invokevirtual 296	com/tencent/mm/ui/widget/MMWebView:getUrl	()Ljava/lang/String;
    //   1460: invokevirtual 304	java/util/HashMap:get	(Ljava/lang/Object;)Ljava/lang/Object;
    //   1463: checkcast 334	java/lang/String
    //   1466: astore_3
    //   1467: aload_3
    //   1468: astore_1
    //   1469: aload_3
    //   1470: ifnonnull +19 -> 1489
    //   1473: aload_0
    //   1474: getfield 17	com/tencent/mm/plugin/webview/ui/tools/j$10:utN	Lcom/tencent/mm/plugin/webview/ui/tools/j;
    //   1477: invokevirtual 211	com/tencent/mm/plugin/webview/ui/tools/a:cZv	()Lcom/tencent/mm/plugin/webview/ui/tools/WebViewUI;
    //   1480: invokevirtual 215	com/tencent/mm/plugin/webview/ui/tools/WebViewUI:getIntent	()Landroid/content/Intent;
    //   1483: ldc 227
    //   1485: invokevirtual 223	android/content/Intent:getStringExtra	(Ljava/lang/String;)Ljava/lang/String;
    //   1488: astore_1
    //   1489: aload_0
    //   1490: getfield 17	com/tencent/mm/plugin/webview/ui/tools/j$10:utN	Lcom/tencent/mm/plugin/webview/ui/tools/j;
    //   1493: astore 4
    //   1495: aload 4
    //   1497: invokevirtual 52	com/tencent/mm/plugin/webview/ui/tools/j:cZv	()Lcom/tencent/mm/plugin/webview/ui/tools/WebViewUI;
    //   1500: getfield 58	com/tencent/mm/plugin/webview/ui/tools/WebViewUI:uhz	Lcom/tencent/mm/plugin/webview/ui/tools/jsapi/d;
    //   1503: ifnull +48 -> 1551
    //   1506: new 181	android/os/Bundle
    //   1509: dup
    //   1510: invokespecial 182	android/os/Bundle:<init>	()V
    //   1513: astore_3
    //   1514: aload_3
    //   1515: ldc_w 336
    //   1518: bipush 43
    //   1520: invokevirtual 340	android/os/Bundle:putInt	(Ljava/lang/String;I)V
    //   1523: aload 4
    //   1525: invokevirtual 52	com/tencent/mm/plugin/webview/ui/tools/j:cZv	()Lcom/tencent/mm/plugin/webview/ui/tools/WebViewUI;
    //   1528: getfield 58	com/tencent/mm/plugin/webview/ui/tools/WebViewUI:uhz	Lcom/tencent/mm/plugin/webview/ui/tools/jsapi/d;
    //   1531: astore 4
    //   1533: aload 4
    //   1535: getfield 341	com/tencent/mm/plugin/webview/ui/tools/jsapi/d:icy	Lcom/tencent/mm/plugin/webview/stub/d;
    //   1538: bipush 21
    //   1540: aload_3
    //   1541: aload 4
    //   1543: getfield 345	com/tencent/mm/plugin/webview/ui/tools/jsapi/d:uqj	I
    //   1546: invokeinterface 348 4 0
    //   1551: aload_0
    //   1552: getfield 17	com/tencent/mm/plugin/webview/ui/tools/j$10:utN	Lcom/tencent/mm/plugin/webview/ui/tools/j;
    //   1555: invokevirtual 52	com/tencent/mm/plugin/webview/ui/tools/j:cZv	()Lcom/tencent/mm/plugin/webview/ui/tools/WebViewUI;
    //   1558: aload_1
    //   1559: invokevirtual 351	com/tencent/mm/plugin/webview/ui/tools/WebViewUI:afK	(Ljava/lang/String;)V
    //   1562: sipush 7652
    //   1565: invokestatic 129	com/tencent/matrix/trace/core/AppMethodBeat:o	(I)V
    //   1568: goto -1429 -> 139
    //   1571: astore_3
    //   1572: ldc 60
    //   1574: aload_3
    //   1575: ldc_w 353
    //   1578: iconst_0
    //   1579: anewarray 4	java/lang/Object
    //   1582: invokestatic 357	com/tencent/mm/sdk/platformtools/ab:printErrStackTrace	(Ljava/lang/String;Ljava/lang/Throwable;Ljava/lang/String;[Ljava/lang/Object;)V
    //   1585: ldc 60
    //   1587: ldc_w 359
    //   1590: aload_3
    //   1591: invokestatic 362	java/lang/String:valueOf	(Ljava/lang/Object;)Ljava/lang/String;
    //   1594: invokevirtual 365	java/lang/String:concat	(Ljava/lang/String;)Ljava/lang/String;
    //   1597: invokestatic 368	com/tencent/mm/sdk/platformtools/ab:w	(Ljava/lang/String;Ljava/lang/String;)V
    //   1600: goto -49 -> 1551
    //   1603: aload_0
    //   1604: getfield 17	com/tencent/mm/plugin/webview/ui/tools/j$10:utN	Lcom/tencent/mm/plugin/webview/ui/tools/j;
    //   1607: invokevirtual 52	com/tencent/mm/plugin/webview/ui/tools/j:cZv	()Lcom/tencent/mm/plugin/webview/ui/tools/WebViewUI;
    //   1610: getfield 137	com/tencent/mm/plugin/webview/ui/tools/WebViewUI:ulI	Lcom/tencent/mm/plugin/webview/model/aq;
    //   1613: invokevirtual 143	com/tencent/mm/plugin/webview/model/aq:cYc	()Lcom/tencent/mm/plugin/webview/model/aq$e;
    //   1616: astore_1
    //   1617: aload_1
    //   1618: iconst_3
    //   1619: anewarray 4	java/lang/Object
    //   1622: dup
    //   1623: iconst_0
    //   1624: aload_0
    //   1625: getfield 17	com/tencent/mm/plugin/webview/ui/tools/j$10:utN	Lcom/tencent/mm/plugin/webview/ui/tools/j;
    //   1628: invokevirtual 52	com/tencent/mm/plugin/webview/ui/tools/j:cZv	()Lcom/tencent/mm/plugin/webview/ui/tools/WebViewUI;
    //   1631: getfield 146	com/tencent/mm/plugin/webview/ui/tools/WebViewUI:cOG	Ljava/lang/String;
    //   1634: aastore
    //   1635: dup
    //   1636: iconst_1
    //   1637: bipush 8
    //   1639: invokestatic 152	java/lang/Integer:valueOf	(I)Ljava/lang/Integer;
    //   1642: aastore
    //   1643: dup
    //   1644: iconst_2
    //   1645: iconst_1
    //   1646: invokestatic 152	java/lang/Integer:valueOf	(I)Ljava/lang/Integer;
    //   1649: aastore
    //   1650: putfield 158	com/tencent/mm/plugin/webview/model/aq$e:une	[Ljava/lang/Object;
    //   1653: aload_1
    //   1654: aload_0
    //   1655: getfield 17	com/tencent/mm/plugin/webview/ui/tools/j$10:utN	Lcom/tencent/mm/plugin/webview/ui/tools/j;
    //   1658: invokevirtual 52	com/tencent/mm/plugin/webview/ui/tools/j:cZv	()Lcom/tencent/mm/plugin/webview/ui/tools/WebViewUI;
    //   1661: getfield 162	com/tencent/mm/plugin/webview/ui/tools/WebViewUI:icy	Lcom/tencent/mm/plugin/webview/stub/d;
    //   1664: invokevirtual 165	com/tencent/mm/plugin/webview/model/aq$e:b	(Lcom/tencent/mm/plugin/webview/stub/d;)V
    //   1667: aload_0
    //   1668: getfield 17	com/tencent/mm/plugin/webview/ui/tools/j$10:utN	Lcom/tencent/mm/plugin/webview/ui/tools/j;
    //   1671: invokevirtual 52	com/tencent/mm/plugin/webview/ui/tools/j:cZv	()Lcom/tencent/mm/plugin/webview/ui/tools/WebViewUI;
    //   1674: getfield 372	com/tencent/mm/plugin/webview/ui/tools/WebViewUI:uvb	Landroid/view/View;
    //   1677: invokevirtual 377	android/view/View:getVisibility	()I
    //   1680: bipush 8
    //   1682: if_icmpne +54 -> 1736
    //   1685: aload_0
    //   1686: getfield 17	com/tencent/mm/plugin/webview/ui/tools/j$10:utN	Lcom/tencent/mm/plugin/webview/ui/tools/j;
    //   1689: invokevirtual 52	com/tencent/mm/plugin/webview/ui/tools/j:cZv	()Lcom/tencent/mm/plugin/webview/ui/tools/WebViewUI;
    //   1692: ldc_w 378
    //   1695: invokestatic 384	android/view/animation/AnimationUtils:loadAnimation	(Landroid/content/Context;I)Landroid/view/animation/Animation;
    //   1698: astore_1
    //   1699: aload_0
    //   1700: getfield 17	com/tencent/mm/plugin/webview/ui/tools/j$10:utN	Lcom/tencent/mm/plugin/webview/ui/tools/j;
    //   1703: invokevirtual 52	com/tencent/mm/plugin/webview/ui/tools/j:cZv	()Lcom/tencent/mm/plugin/webview/ui/tools/WebViewUI;
    //   1706: getfield 372	com/tencent/mm/plugin/webview/ui/tools/WebViewUI:uvb	Landroid/view/View;
    //   1709: aload_1
    //   1710: invokevirtual 388	android/view/View:startAnimation	(Landroid/view/animation/Animation;)V
    //   1713: aload_0
    //   1714: getfield 17	com/tencent/mm/plugin/webview/ui/tools/j$10:utN	Lcom/tencent/mm/plugin/webview/ui/tools/j;
    //   1717: invokevirtual 52	com/tencent/mm/plugin/webview/ui/tools/j:cZv	()Lcom/tencent/mm/plugin/webview/ui/tools/WebViewUI;
    //   1720: getfield 372	com/tencent/mm/plugin/webview/ui/tools/WebViewUI:uvb	Landroid/view/View;
    //   1723: iconst_0
    //   1724: invokevirtual 391	android/view/View:setVisibility	(I)V
    //   1727: sipush 7652
    //   1730: invokestatic 129	com/tencent/matrix/trace/core/AppMethodBeat:o	(I)V
    //   1733: goto -1594 -> 139
    //   1736: aload_0
    //   1737: getfield 17	com/tencent/mm/plugin/webview/ui/tools/j$10:utN	Lcom/tencent/mm/plugin/webview/ui/tools/j;
    //   1740: invokevirtual 52	com/tencent/mm/plugin/webview/ui/tools/j:cZv	()Lcom/tencent/mm/plugin/webview/ui/tools/WebViewUI;
    //   1743: ldc_w 392
    //   1746: invokestatic 384	android/view/animation/AnimationUtils:loadAnimation	(Landroid/content/Context;I)Landroid/view/animation/Animation;
    //   1749: astore_1
    //   1750: aload_1
    //   1751: new 394	com/tencent/mm/plugin/webview/ui/tools/j$10$1
    //   1754: dup
    //   1755: aload_0
    //   1756: invokespecial 397	com/tencent/mm/plugin/webview/ui/tools/j$10$1:<init>	(Lcom/tencent/mm/plugin/webview/ui/tools/j$10;)V
    //   1759: invokevirtual 403	android/view/animation/Animation:setAnimationListener	(Landroid/view/animation/Animation$AnimationListener;)V
    //   1762: aload_0
    //   1763: getfield 17	com/tencent/mm/plugin/webview/ui/tools/j$10:utN	Lcom/tencent/mm/plugin/webview/ui/tools/j;
    //   1766: invokevirtual 52	com/tencent/mm/plugin/webview/ui/tools/j:cZv	()Lcom/tencent/mm/plugin/webview/ui/tools/WebViewUI;
    //   1769: getfield 372	com/tencent/mm/plugin/webview/ui/tools/WebViewUI:uvb	Landroid/view/View;
    //   1772: aload_1
    //   1773: invokevirtual 388	android/view/View:startAnimation	(Landroid/view/animation/Animation;)V
    //   1776: aload_0
    //   1777: getfield 17	com/tencent/mm/plugin/webview/ui/tools/j$10:utN	Lcom/tencent/mm/plugin/webview/ui/tools/j;
    //   1780: invokevirtual 52	com/tencent/mm/plugin/webview/ui/tools/j:cZv	()Lcom/tencent/mm/plugin/webview/ui/tools/WebViewUI;
    //   1783: getfield 372	com/tencent/mm/plugin/webview/ui/tools/WebViewUI:uvb	Landroid/view/View;
    //   1786: bipush 8
    //   1788: invokevirtual 391	android/view/View:setVisibility	(I)V
    //   1791: sipush 7652
    //   1794: invokestatic 129	com/tencent/matrix/trace/core/AppMethodBeat:o	(I)V
    //   1797: goto -1658 -> 139
    //   1800: aload_0
    //   1801: getfield 17	com/tencent/mm/plugin/webview/ui/tools/j$10:utN	Lcom/tencent/mm/plugin/webview/ui/tools/j;
    //   1804: invokevirtual 52	com/tencent/mm/plugin/webview/ui/tools/j:cZv	()Lcom/tencent/mm/plugin/webview/ui/tools/WebViewUI;
    //   1807: getfield 137	com/tencent/mm/plugin/webview/ui/tools/WebViewUI:ulI	Lcom/tencent/mm/plugin/webview/model/aq;
    //   1810: invokevirtual 143	com/tencent/mm/plugin/webview/model/aq:cYc	()Lcom/tencent/mm/plugin/webview/model/aq$e;
    //   1813: astore_1
    //   1814: aload_1
    //   1815: iconst_3
    //   1816: anewarray 4	java/lang/Object
    //   1819: dup
    //   1820: iconst_0
    //   1821: aload_0
    //   1822: getfield 17	com/tencent/mm/plugin/webview/ui/tools/j$10:utN	Lcom/tencent/mm/plugin/webview/ui/tools/j;
    //   1825: invokevirtual 52	com/tencent/mm/plugin/webview/ui/tools/j:cZv	()Lcom/tencent/mm/plugin/webview/ui/tools/WebViewUI;
    //   1828: getfield 146	com/tencent/mm/plugin/webview/ui/tools/WebViewUI:cOG	Ljava/lang/String;
    //   1831: aastore
    //   1832: dup
    //   1833: iconst_1
    //   1834: bipush 10
    //   1836: invokestatic 152	java/lang/Integer:valueOf	(I)Ljava/lang/Integer;
    //   1839: aastore
    //   1840: dup
    //   1841: iconst_2
    //   1842: iconst_1
    //   1843: invokestatic 152	java/lang/Integer:valueOf	(I)Ljava/lang/Integer;
    //   1846: aastore
    //   1847: putfield 158	com/tencent/mm/plugin/webview/model/aq$e:une	[Ljava/lang/Object;
    //   1850: aload_1
    //   1851: aload_0
    //   1852: getfield 17	com/tencent/mm/plugin/webview/ui/tools/j$10:utN	Lcom/tencent/mm/plugin/webview/ui/tools/j;
    //   1855: invokevirtual 52	com/tencent/mm/plugin/webview/ui/tools/j:cZv	()Lcom/tencent/mm/plugin/webview/ui/tools/WebViewUI;
    //   1858: getfield 162	com/tencent/mm/plugin/webview/ui/tools/WebViewUI:icy	Lcom/tencent/mm/plugin/webview/stub/d;
    //   1861: invokevirtual 165	com/tencent/mm/plugin/webview/model/aq$e:b	(Lcom/tencent/mm/plugin/webview/stub/d;)V
    //   1864: aload_0
    //   1865: getfield 17	com/tencent/mm/plugin/webview/ui/tools/j$10:utN	Lcom/tencent/mm/plugin/webview/ui/tools/j;
    //   1868: invokevirtual 52	com/tencent/mm/plugin/webview/ui/tools/j:cZv	()Lcom/tencent/mm/plugin/webview/ui/tools/WebViewUI;
    //   1871: invokevirtual 406	com/tencent/mm/plugin/webview/ui/tools/WebViewUI:aYe	()V
    //   1874: sipush 7652
    //   1877: invokestatic 129	com/tencent/matrix/trace/core/AppMethodBeat:o	(I)V
    //   1880: goto -1741 -> 139
    //   1883: aload_0
    //   1884: getfield 17	com/tencent/mm/plugin/webview/ui/tools/j$10:utN	Lcom/tencent/mm/plugin/webview/ui/tools/j;
    //   1887: invokevirtual 52	com/tencent/mm/plugin/webview/ui/tools/j:cZv	()Lcom/tencent/mm/plugin/webview/ui/tools/WebViewUI;
    //   1890: getfield 137	com/tencent/mm/plugin/webview/ui/tools/WebViewUI:ulI	Lcom/tencent/mm/plugin/webview/model/aq;
    //   1893: invokevirtual 143	com/tencent/mm/plugin/webview/model/aq:cYc	()Lcom/tencent/mm/plugin/webview/model/aq$e;
    //   1896: astore_1
    //   1897: aload_1
    //   1898: iconst_3
    //   1899: anewarray 4	java/lang/Object
    //   1902: dup
    //   1903: iconst_0
    //   1904: aload_0
    //   1905: getfield 17	com/tencent/mm/plugin/webview/ui/tools/j$10:utN	Lcom/tencent/mm/plugin/webview/ui/tools/j;
    //   1908: invokevirtual 52	com/tencent/mm/plugin/webview/ui/tools/j:cZv	()Lcom/tencent/mm/plugin/webview/ui/tools/WebViewUI;
    //   1911: getfield 146	com/tencent/mm/plugin/webview/ui/tools/WebViewUI:cOG	Ljava/lang/String;
    //   1914: aastore
    //   1915: dup
    //   1916: iconst_1
    //   1917: iconst_5
    //   1918: invokestatic 152	java/lang/Integer:valueOf	(I)Ljava/lang/Integer;
    //   1921: aastore
    //   1922: dup
    //   1923: iconst_2
    //   1924: iconst_1
    //   1925: invokestatic 152	java/lang/Integer:valueOf	(I)Ljava/lang/Integer;
    //   1928: aastore
    //   1929: putfield 158	com/tencent/mm/plugin/webview/model/aq$e:une	[Ljava/lang/Object;
    //   1932: aload_1
    //   1933: aload_0
    //   1934: getfield 17	com/tencent/mm/plugin/webview/ui/tools/j$10:utN	Lcom/tencent/mm/plugin/webview/ui/tools/j;
    //   1937: invokevirtual 52	com/tencent/mm/plugin/webview/ui/tools/j:cZv	()Lcom/tencent/mm/plugin/webview/ui/tools/WebViewUI;
    //   1940: getfield 162	com/tencent/mm/plugin/webview/ui/tools/WebViewUI:icy	Lcom/tencent/mm/plugin/webview/stub/d;
    //   1943: invokevirtual 165	com/tencent/mm/plugin/webview/model/aq$e:b	(Lcom/tencent/mm/plugin/webview/stub/d;)V
    //   1946: aload_0
    //   1947: getfield 17	com/tencent/mm/plugin/webview/ui/tools/j$10:utN	Lcom/tencent/mm/plugin/webview/ui/tools/j;
    //   1950: astore 4
    //   1952: aload 4
    //   1954: invokevirtual 52	com/tencent/mm/plugin/webview/ui/tools/j:cZv	()Lcom/tencent/mm/plugin/webview/ui/tools/WebViewUI;
    //   1957: getfield 293	com/tencent/mm/plugin/webview/ui/tools/WebViewUI:pzf	Lcom/tencent/mm/ui/widget/MMWebView;
    //   1960: ifnonnull +21 -> 1981
    //   1963: ldc_w 408
    //   1966: ldc_w 410
    //   1969: invokestatic 413	com/tencent/mm/sdk/platformtools/ab:e	(Ljava/lang/String;Ljava/lang/String;)V
    //   1972: sipush 7652
    //   1975: invokestatic 129	com/tencent/matrix/trace/core/AppMethodBeat:o	(I)V
    //   1978: goto -1839 -> 139
    //   1981: aload 4
    //   1983: invokevirtual 52	com/tencent/mm/plugin/webview/ui/tools/j:cZv	()Lcom/tencent/mm/plugin/webview/ui/tools/WebViewUI;
    //   1986: getfield 293	com/tencent/mm/plugin/webview/ui/tools/WebViewUI:pzf	Lcom/tencent/mm/ui/widget/MMWebView;
    //   1989: invokevirtual 296	com/tencent/mm/ui/widget/MMWebView:getUrl	()Ljava/lang/String;
    //   1992: astore_1
    //   1993: aload_1
    //   1994: ifnull +10 -> 2004
    //   1997: aload_1
    //   1998: invokevirtual 416	java/lang/String:length	()I
    //   2001: ifne +21 -> 2022
    //   2004: ldc_w 408
    //   2007: ldc_w 418
    //   2010: invokestatic 413	com/tencent/mm/sdk/platformtools/ab:e	(Ljava/lang/String;Ljava/lang/String;)V
    //   2013: sipush 7652
    //   2016: invokestatic 129	com/tencent/matrix/trace/core/AppMethodBeat:o	(I)V
    //   2019: goto -1880 -> 139
    //   2022: aload 4
    //   2024: invokevirtual 52	com/tencent/mm/plugin/webview/ui/tools/j:cZv	()Lcom/tencent/mm/plugin/webview/ui/tools/WebViewUI;
    //   2027: getfield 162	com/tencent/mm/plugin/webview/ui/tools/WebViewUI:icy	Lcom/tencent/mm/plugin/webview/stub/d;
    //   2030: aload_1
    //   2031: invokeinterface 421 2 0
    //   2036: astore_3
    //   2037: aload_3
    //   2038: astore_1
    //   2039: aload 4
    //   2041: invokevirtual 52	com/tencent/mm/plugin/webview/ui/tools/j:cZv	()Lcom/tencent/mm/plugin/webview/ui/tools/WebViewUI;
    //   2044: invokevirtual 425	com/tencent/mm/plugin/webview/ui/tools/WebViewUI:getApplication	()Landroid/app/Application;
    //   2047: ldc_w 427
    //   2050: invokevirtual 433	android/app/Application:getSystemService	(Ljava/lang/String;)Ljava/lang/Object;
    //   2053: checkcast 435	android/text/ClipboardManager
    //   2056: astore_3
    //   2057: aload_3
    //   2058: ifnull +77 -> 2135
    //   2061: aload_3
    //   2062: aload_1
    //   2063: invokevirtual 439	android/text/ClipboardManager:setText	(Ljava/lang/CharSequence;)V
    //   2066: aload 4
    //   2068: invokevirtual 52	com/tencent/mm/plugin/webview/ui/tools/j:cZv	()Lcom/tencent/mm/plugin/webview/ui/tools/WebViewUI;
    //   2071: aload 4
    //   2073: invokevirtual 52	com/tencent/mm/plugin/webview/ui/tools/j:cZv	()Lcom/tencent/mm/plugin/webview/ui/tools/WebViewUI;
    //   2076: ldc_w 440
    //   2079: invokevirtual 444	com/tencent/mm/plugin/webview/ui/tools/WebViewUI:getString	(I)Ljava/lang/String;
    //   2082: iconst_0
    //   2083: invokestatic 450	android/widget/Toast:makeText	(Landroid/content/Context;Ljava/lang/CharSequence;I)Landroid/widget/Toast;
    //   2086: invokevirtual 453	android/widget/Toast:show	()V
    //   2089: sipush 7652
    //   2092: invokestatic 129	com/tencent/matrix/trace/core/AppMethodBeat:o	(I)V
    //   2095: goto -1956 -> 139
    //   2098: astore_1
    //   2099: ldc_w 408
    //   2102: aload_1
    //   2103: ldc_w 455
    //   2106: iconst_0
    //   2107: anewarray 4	java/lang/Object
    //   2110: invokestatic 357	com/tencent/mm/sdk/platformtools/ab:printErrStackTrace	(Ljava/lang/String;Ljava/lang/Throwable;Ljava/lang/String;[Ljava/lang/Object;)V
    //   2113: sipush 7652
    //   2116: invokestatic 129	com/tencent/matrix/trace/core/AppMethodBeat:o	(I)V
    //   2119: goto -1980 -> 139
    //   2122: astore_3
    //   2123: ldc_w 408
    //   2126: ldc_w 457
    //   2129: invokestatic 413	com/tencent/mm/sdk/platformtools/ab:e	(Ljava/lang/String;Ljava/lang/String;)V
    //   2132: goto -93 -> 2039
    //   2135: ldc_w 408
    //   2138: ldc_w 459
    //   2141: invokestatic 413	com/tencent/mm/sdk/platformtools/ab:e	(Ljava/lang/String;Ljava/lang/String;)V
    //   2144: sipush 7652
    //   2147: invokestatic 129	com/tencent/matrix/trace/core/AppMethodBeat:o	(I)V
    //   2150: goto -2011 -> 139
    //   2153: aload_0
    //   2154: getfield 17	com/tencent/mm/plugin/webview/ui/tools/j$10:utN	Lcom/tencent/mm/plugin/webview/ui/tools/j;
    //   2157: invokevirtual 52	com/tencent/mm/plugin/webview/ui/tools/j:cZv	()Lcom/tencent/mm/plugin/webview/ui/tools/WebViewUI;
    //   2160: getfield 137	com/tencent/mm/plugin/webview/ui/tools/WebViewUI:ulI	Lcom/tencent/mm/plugin/webview/model/aq;
    //   2163: invokevirtual 143	com/tencent/mm/plugin/webview/model/aq:cYc	()Lcom/tencent/mm/plugin/webview/model/aq$e;
    //   2166: astore_1
    //   2167: aload_1
    //   2168: iconst_3
    //   2169: anewarray 4	java/lang/Object
    //   2172: dup
    //   2173: iconst_0
    //   2174: aload_0
    //   2175: getfield 17	com/tencent/mm/plugin/webview/ui/tools/j$10:utN	Lcom/tencent/mm/plugin/webview/ui/tools/j;
    //   2178: invokevirtual 52	com/tencent/mm/plugin/webview/ui/tools/j:cZv	()Lcom/tencent/mm/plugin/webview/ui/tools/WebViewUI;
    //   2181: getfield 146	com/tencent/mm/plugin/webview/ui/tools/WebViewUI:cOG	Ljava/lang/String;
    //   2184: aastore
    //   2185: dup
    //   2186: iconst_1
    //   2187: bipush 13
    //   2189: invokestatic 152	java/lang/Integer:valueOf	(I)Ljava/lang/Integer;
    //   2192: aastore
    //   2193: dup
    //   2194: iconst_2
    //   2195: iconst_1
    //   2196: invokestatic 152	java/lang/Integer:valueOf	(I)Ljava/lang/Integer;
    //   2199: aastore
    //   2200: putfield 158	com/tencent/mm/plugin/webview/model/aq$e:une	[Ljava/lang/Object;
    //   2203: aload_1
    //   2204: aload_0
    //   2205: getfield 17	com/tencent/mm/plugin/webview/ui/tools/j$10:utN	Lcom/tencent/mm/plugin/webview/ui/tools/j;
    //   2208: invokevirtual 52	com/tencent/mm/plugin/webview/ui/tools/j:cZv	()Lcom/tencent/mm/plugin/webview/ui/tools/WebViewUI;
    //   2211: getfield 162	com/tencent/mm/plugin/webview/ui/tools/WebViewUI:icy	Lcom/tencent/mm/plugin/webview/stub/d;
    //   2214: invokevirtual 165	com/tencent/mm/plugin/webview/model/aq$e:b	(Lcom/tencent/mm/plugin/webview/stub/d;)V
    //   2217: aload_0
    //   2218: getfield 17	com/tencent/mm/plugin/webview/ui/tools/j$10:utN	Lcom/tencent/mm/plugin/webview/ui/tools/j;
    //   2221: invokevirtual 52	com/tencent/mm/plugin/webview/ui/tools/j:cZv	()Lcom/tencent/mm/plugin/webview/ui/tools/WebViewUI;
    //   2224: astore 4
    //   2226: aload 4
    //   2228: getfield 162	com/tencent/mm/plugin/webview/ui/tools/WebViewUI:icy	Lcom/tencent/mm/plugin/webview/stub/d;
    //   2231: astore 6
    //   2233: aload 4
    //   2235: invokevirtual 462	com/tencent/mm/plugin/webview/ui/tools/WebViewUI:isFinishing	()Z
    //   2238: ifne +150 -> 2388
    //   2241: aload 4
    //   2243: invokevirtual 465	com/tencent/mm/plugin/webview/ui/tools/WebViewUI:dae	()Ljava/lang/String;
    //   2246: astore_3
    //   2247: aload_3
    //   2248: invokestatic 179	com/tencent/mm/sdk/platformtools/bo:isNullOrNil	(Ljava/lang/String;)Z
    //   2251: ifeq +21 -> 2272
    //   2254: ldc_w 467
    //   2257: ldc_w 469
    //   2260: invokestatic 413	com/tencent/mm/sdk/platformtools/ab:e	(Ljava/lang/String;Ljava/lang/String;)V
    //   2263: sipush 7652
    //   2266: invokestatic 129	com/tencent/matrix/trace/core/AppMethodBeat:o	(I)V
    //   2269: goto -2130 -> 139
    //   2272: aload_3
    //   2273: astore_1
    //   2274: aload 6
    //   2276: ifnull +12 -> 2288
    //   2279: aload 6
    //   2281: aload_3
    //   2282: invokeinterface 421 2 0
    //   2287: astore_1
    //   2288: aload_1
    //   2289: astore_3
    //   2290: aload_1
    //   2291: ldc_w 471
    //   2294: invokevirtual 474	java/lang/String:startsWith	(Ljava/lang/String;)Z
    //   2297: ifne +26 -> 2323
    //   2300: aload_1
    //   2301: astore_3
    //   2302: aload_1
    //   2303: ldc_w 476
    //   2306: invokevirtual 474	java/lang/String:startsWith	(Ljava/lang/String;)Z
    //   2309: ifne +14 -> 2323
    //   2312: ldc_w 471
    //   2315: aload_1
    //   2316: invokestatic 362	java/lang/String:valueOf	(Ljava/lang/Object;)Ljava/lang/String;
    //   2319: invokevirtual 365	java/lang/String:concat	(Ljava/lang/String;)Ljava/lang/String;
    //   2322: astore_3
    //   2323: new 219	android/content/Intent
    //   2326: dup
    //   2327: ldc_w 478
    //   2330: aload_3
    //   2331: invokestatic 484	android/net/Uri:parse	(Ljava/lang/String;)Landroid/net/Uri;
    //   2334: invokespecial 487	android/content/Intent:<init>	(Ljava/lang/String;Landroid/net/Uri;)V
    //   2337: astore_1
    //   2338: aload 4
    //   2340: invokestatic 491	com/tencent/mm/sdk/platformtools/bo:gT	(Landroid/content/Context;)Z
    //   2343: ifne +9 -> 2352
    //   2346: invokestatic 496	com/tencent/mm/sdk/platformtools/g:dnY	()Z
    //   2349: ifeq +71 -> 2420
    //   2352: aload 4
    //   2354: aload_1
    //   2355: invokevirtual 500	com/tencent/mm/plugin/webview/ui/tools/WebViewUI:startActivity	(Landroid/content/Intent;)V
    //   2358: sipush 7652
    //   2361: invokestatic 129	com/tencent/matrix/trace/core/AppMethodBeat:o	(I)V
    //   2364: goto -2225 -> 139
    //   2367: astore_1
    //   2368: ldc_w 467
    //   2371: ldc_w 502
    //   2374: iconst_1
    //   2375: anewarray 4	java/lang/Object
    //   2378: dup
    //   2379: iconst_0
    //   2380: aload_1
    //   2381: invokevirtual 505	java/lang/Exception:getMessage	()Ljava/lang/String;
    //   2384: aastore
    //   2385: invokestatic 508	com/tencent/mm/sdk/platformtools/ab:e	(Ljava/lang/String;Ljava/lang/String;[Ljava/lang/Object;)V
    //   2388: sipush 7652
    //   2391: invokestatic 129	com/tencent/matrix/trace/core/AppMethodBeat:o	(I)V
    //   2394: goto -2255 -> 139
    //   2397: astore_1
    //   2398: ldc_w 467
    //   2401: ldc_w 510
    //   2404: iconst_1
    //   2405: anewarray 4	java/lang/Object
    //   2408: dup
    //   2409: iconst_0
    //   2410: aload_1
    //   2411: aastore
    //   2412: invokestatic 508	com/tencent/mm/sdk/platformtools/ab:e	(Ljava/lang/String;Ljava/lang/String;[Ljava/lang/Object;)V
    //   2415: aload_3
    //   2416: astore_1
    //   2417: goto -129 -> 2288
    //   2420: aload 4
    //   2422: aload 4
    //   2424: aload_1
    //   2425: aload_3
    //   2426: invokestatic 515	com/tencent/mm/plugin/webview/modeltools/a:a	(Landroid/app/Activity;Landroid/content/Intent;Ljava/lang/String;)Landroid/content/Intent;
    //   2429: iconst_2
    //   2430: invokevirtual 519	com/tencent/mm/plugin/webview/ui/tools/WebViewUI:startActivityForResult	(Landroid/content/Intent;I)V
    //   2433: sipush 7652
    //   2436: invokestatic 129	com/tencent/matrix/trace/core/AppMethodBeat:o	(I)V
    //   2439: goto -2300 -> 139
    //   2442: aload_0
    //   2443: getfield 17	com/tencent/mm/plugin/webview/ui/tools/j$10:utN	Lcom/tencent/mm/plugin/webview/ui/tools/j;
    //   2446: invokevirtual 52	com/tencent/mm/plugin/webview/ui/tools/j:cZv	()Lcom/tencent/mm/plugin/webview/ui/tools/WebViewUI;
    //   2449: getfield 137	com/tencent/mm/plugin/webview/ui/tools/WebViewUI:ulI	Lcom/tencent/mm/plugin/webview/model/aq;
    //   2452: invokevirtual 143	com/tencent/mm/plugin/webview/model/aq:cYc	()Lcom/tencent/mm/plugin/webview/model/aq$e;
    //   2455: astore_1
    //   2456: aload_1
    //   2457: iconst_3
    //   2458: anewarray 4	java/lang/Object
    //   2461: dup
    //   2462: iconst_0
    //   2463: aload_0
    //   2464: getfield 17	com/tencent/mm/plugin/webview/ui/tools/j$10:utN	Lcom/tencent/mm/plugin/webview/ui/tools/j;
    //   2467: invokevirtual 52	com/tencent/mm/plugin/webview/ui/tools/j:cZv	()Lcom/tencent/mm/plugin/webview/ui/tools/WebViewUI;
    //   2470: getfield 146	com/tencent/mm/plugin/webview/ui/tools/WebViewUI:cOG	Ljava/lang/String;
    //   2473: aastore
    //   2474: dup
    //   2475: iconst_1
    //   2476: bipush 35
    //   2478: invokestatic 152	java/lang/Integer:valueOf	(I)Ljava/lang/Integer;
    //   2481: aastore
    //   2482: dup
    //   2483: iconst_2
    //   2484: iconst_1
    //   2485: invokestatic 152	java/lang/Integer:valueOf	(I)Ljava/lang/Integer;
    //   2488: aastore
    //   2489: putfield 158	com/tencent/mm/plugin/webview/model/aq$e:une	[Ljava/lang/Object;
    //   2492: aload_1
    //   2493: aload_0
    //   2494: getfield 17	com/tencent/mm/plugin/webview/ui/tools/j$10:utN	Lcom/tencent/mm/plugin/webview/ui/tools/j;
    //   2497: invokevirtual 52	com/tencent/mm/plugin/webview/ui/tools/j:cZv	()Lcom/tencent/mm/plugin/webview/ui/tools/WebViewUI;
    //   2500: getfield 162	com/tencent/mm/plugin/webview/ui/tools/WebViewUI:icy	Lcom/tencent/mm/plugin/webview/stub/d;
    //   2503: invokevirtual 165	com/tencent/mm/plugin/webview/model/aq$e:b	(Lcom/tencent/mm/plugin/webview/stub/d;)V
    //   2506: aload_0
    //   2507: getfield 17	com/tencent/mm/plugin/webview/ui/tools/j$10:utN	Lcom/tencent/mm/plugin/webview/ui/tools/j;
    //   2510: invokestatic 521	com/tencent/mm/plugin/webview/ui/tools/j:a	(Lcom/tencent/mm/plugin/webview/ui/tools/j;)V
    //   2513: sipush 7652
    //   2516: invokestatic 129	com/tencent/matrix/trace/core/AppMethodBeat:o	(I)V
    //   2519: goto -2380 -> 139
    //   2522: aload_0
    //   2523: getfield 17	com/tencent/mm/plugin/webview/ui/tools/j$10:utN	Lcom/tencent/mm/plugin/webview/ui/tools/j;
    //   2526: invokevirtual 52	com/tencent/mm/plugin/webview/ui/tools/j:cZv	()Lcom/tencent/mm/plugin/webview/ui/tools/WebViewUI;
    //   2529: getfield 137	com/tencent/mm/plugin/webview/ui/tools/WebViewUI:ulI	Lcom/tencent/mm/plugin/webview/model/aq;
    //   2532: invokevirtual 143	com/tencent/mm/plugin/webview/model/aq:cYc	()Lcom/tencent/mm/plugin/webview/model/aq$e;
    //   2535: astore_1
    //   2536: aload_1
    //   2537: iconst_3
    //   2538: anewarray 4	java/lang/Object
    //   2541: dup
    //   2542: iconst_0
    //   2543: aload_0
    //   2544: getfield 17	com/tencent/mm/plugin/webview/ui/tools/j$10:utN	Lcom/tencent/mm/plugin/webview/ui/tools/j;
    //   2547: invokevirtual 52	com/tencent/mm/plugin/webview/ui/tools/j:cZv	()Lcom/tencent/mm/plugin/webview/ui/tools/WebViewUI;
    //   2550: getfield 146	com/tencent/mm/plugin/webview/ui/tools/WebViewUI:cOG	Ljava/lang/String;
    //   2553: aastore
    //   2554: dup
    //   2555: iconst_1
    //   2556: bipush 15
    //   2558: invokestatic 152	java/lang/Integer:valueOf	(I)Ljava/lang/Integer;
    //   2561: aastore
    //   2562: dup
    //   2563: iconst_2
    //   2564: iconst_1
    //   2565: invokestatic 152	java/lang/Integer:valueOf	(I)Ljava/lang/Integer;
    //   2568: aastore
    //   2569: putfield 158	com/tencent/mm/plugin/webview/model/aq$e:une	[Ljava/lang/Object;
    //   2572: aload_1
    //   2573: aload_0
    //   2574: getfield 17	com/tencent/mm/plugin/webview/ui/tools/j$10:utN	Lcom/tencent/mm/plugin/webview/ui/tools/j;
    //   2577: invokevirtual 52	com/tencent/mm/plugin/webview/ui/tools/j:cZv	()Lcom/tencent/mm/plugin/webview/ui/tools/WebViewUI;
    //   2580: getfield 162	com/tencent/mm/plugin/webview/ui/tools/WebViewUI:icy	Lcom/tencent/mm/plugin/webview/stub/d;
    //   2583: invokevirtual 165	com/tencent/mm/plugin/webview/model/aq$e:b	(Lcom/tencent/mm/plugin/webview/stub/d;)V
    //   2586: aload_0
    //   2587: getfield 17	com/tencent/mm/plugin/webview/ui/tools/j$10:utN	Lcom/tencent/mm/plugin/webview/ui/tools/j;
    //   2590: astore_1
    //   2591: aload_1
    //   2592: invokevirtual 52	com/tencent/mm/plugin/webview/ui/tools/j:cZv	()Lcom/tencent/mm/plugin/webview/ui/tools/WebViewUI;
    //   2595: getfield 58	com/tencent/mm/plugin/webview/ui/tools/WebViewUI:uhz	Lcom/tencent/mm/plugin/webview/ui/tools/jsapi/d;
    //   2598: ldc_w 523
    //   2601: iconst_1
    //   2602: invokevirtual 527	com/tencent/mm/plugin/webview/ui/tools/jsapi/d:bJ	(Ljava/lang/String;Z)V
    //   2605: aload_1
    //   2606: invokevirtual 52	com/tencent/mm/plugin/webview/ui/tools/j:cZv	()Lcom/tencent/mm/plugin/webview/ui/tools/WebViewUI;
    //   2609: getfield 58	com/tencent/mm/plugin/webview/ui/tools/WebViewUI:uhz	Lcom/tencent/mm/plugin/webview/ui/tools/jsapi/d;
    //   2612: astore_3
    //   2613: aload_3
    //   2614: getfield 530	com/tencent/mm/plugin/webview/ui/tools/jsapi/d:ready	Z
    //   2617: ifne +20 -> 2637
    //   2620: ldc 60
    //   2622: ldc_w 532
    //   2625: invokestatic 413	com/tencent/mm/sdk/platformtools/ab:e	(Ljava/lang/String;Ljava/lang/String;)V
    //   2628: sipush 7652
    //   2631: invokestatic 129	com/tencent/matrix/trace/core/AppMethodBeat:o	(I)V
    //   2634: goto -2495 -> 139
    //   2637: ldc_w 534
    //   2640: new 69	java/util/HashMap
    //   2643: dup
    //   2644: invokespecial 70	java/util/HashMap:<init>	()V
    //   2647: aload_3
    //   2648: getfield 90	com/tencent/mm/plugin/webview/ui/tools/jsapi/d:uFv	Z
    //   2651: aload_3
    //   2652: getfield 93	com/tencent/mm/plugin/webview/ui/tools/jsapi/d:uFw	Ljava/lang/String;
    //   2655: invokestatic 99	com/tencent/mm/plugin/webview/ui/tools/jsapi/i$a:b	(Ljava/lang/String;Ljava/util/Map;ZLjava/lang/String;)Ljava/lang/String;
    //   2658: astore_1
    //   2659: aload_3
    //   2660: getfield 103	com/tencent/mm/plugin/webview/ui/tools/jsapi/d:uFo	Lcom/tencent/mm/ui/widget/MMWebView;
    //   2663: new 105	java/lang/StringBuilder
    //   2666: dup
    //   2667: ldc 107
    //   2669: invokespecial 110	java/lang/StringBuilder:<init>	(Ljava/lang/String;)V
    //   2672: aload_1
    //   2673: invokevirtual 114	java/lang/StringBuilder:append	(Ljava/lang/String;)Ljava/lang/StringBuilder;
    //   2676: ldc 116
    //   2678: invokevirtual 114	java/lang/StringBuilder:append	(Ljava/lang/String;)Ljava/lang/StringBuilder;
    //   2681: invokevirtual 120	java/lang/StringBuilder:toString	()Ljava/lang/String;
    //   2684: aconst_null
    //   2685: invokevirtual 126	com/tencent/mm/ui/widget/MMWebView:evaluateJavascript	(Ljava/lang/String;Landroid/webkit/ValueCallback;)V
    //   2688: sipush 7652
    //   2691: invokestatic 129	com/tencent/matrix/trace/core/AppMethodBeat:o	(I)V
    //   2694: goto -2555 -> 139
    //   2697: aload_0
    //   2698: getfield 17	com/tencent/mm/plugin/webview/ui/tools/j$10:utN	Lcom/tencent/mm/plugin/webview/ui/tools/j;
    //   2701: invokevirtual 52	com/tencent/mm/plugin/webview/ui/tools/j:cZv	()Lcom/tencent/mm/plugin/webview/ui/tools/WebViewUI;
    //   2704: getfield 137	com/tencent/mm/plugin/webview/ui/tools/WebViewUI:ulI	Lcom/tencent/mm/plugin/webview/model/aq;
    //   2707: invokevirtual 143	com/tencent/mm/plugin/webview/model/aq:cYc	()Lcom/tencent/mm/plugin/webview/model/aq$e;
    //   2710: astore_1
    //   2711: aload_1
    //   2712: iconst_3
    //   2713: anewarray 4	java/lang/Object
    //   2716: dup
    //   2717: iconst_0
    //   2718: aload_0
    //   2719: getfield 17	com/tencent/mm/plugin/webview/ui/tools/j$10:utN	Lcom/tencent/mm/plugin/webview/ui/tools/j;
    //   2722: invokevirtual 52	com/tencent/mm/plugin/webview/ui/tools/j:cZv	()Lcom/tencent/mm/plugin/webview/ui/tools/WebViewUI;
    //   2725: getfield 146	com/tencent/mm/plugin/webview/ui/tools/WebViewUI:cOG	Ljava/lang/String;
    //   2728: aastore
    //   2729: dup
    //   2730: iconst_1
    //   2731: bipush 7
    //   2733: invokestatic 152	java/lang/Integer:valueOf	(I)Ljava/lang/Integer;
    //   2736: aastore
    //   2737: dup
    //   2738: iconst_2
    //   2739: iconst_1
    //   2740: invokestatic 152	java/lang/Integer:valueOf	(I)Ljava/lang/Integer;
    //   2743: aastore
    //   2744: putfield 158	com/tencent/mm/plugin/webview/model/aq$e:une	[Ljava/lang/Object;
    //   2747: aload_1
    //   2748: aload_0
    //   2749: getfield 17	com/tencent/mm/plugin/webview/ui/tools/j$10:utN	Lcom/tencent/mm/plugin/webview/ui/tools/j;
    //   2752: invokevirtual 52	com/tencent/mm/plugin/webview/ui/tools/j:cZv	()Lcom/tencent/mm/plugin/webview/ui/tools/WebViewUI;
    //   2755: getfield 162	com/tencent/mm/plugin/webview/ui/tools/WebViewUI:icy	Lcom/tencent/mm/plugin/webview/stub/d;
    //   2758: invokevirtual 165	com/tencent/mm/plugin/webview/model/aq$e:b	(Lcom/tencent/mm/plugin/webview/stub/d;)V
    //   2761: aload_0
    //   2762: getfield 17	com/tencent/mm/plugin/webview/ui/tools/j$10:utN	Lcom/tencent/mm/plugin/webview/ui/tools/j;
    //   2765: astore_1
    //   2766: aload_1
    //   2767: invokevirtual 52	com/tencent/mm/plugin/webview/ui/tools/j:cZv	()Lcom/tencent/mm/plugin/webview/ui/tools/WebViewUI;
    //   2770: aload_1
    //   2771: invokevirtual 52	com/tencent/mm/plugin/webview/ui/tools/j:cZv	()Lcom/tencent/mm/plugin/webview/ui/tools/WebViewUI;
    //   2774: ldc_w 535
    //   2777: invokevirtual 444	com/tencent/mm/plugin/webview/ui/tools/WebViewUI:getString	(I)Ljava/lang/String;
    //   2780: aconst_null
    //   2781: aconst_null
    //   2782: aload_1
    //   2783: invokevirtual 52	com/tencent/mm/plugin/webview/ui/tools/j:cZv	()Lcom/tencent/mm/plugin/webview/ui/tools/WebViewUI;
    //   2786: ldc_w 536
    //   2789: invokevirtual 444	com/tencent/mm/plugin/webview/ui/tools/WebViewUI:getString	(I)Ljava/lang/String;
    //   2792: new 538	com/tencent/mm/plugin/webview/ui/tools/j$7
    //   2795: dup
    //   2796: aload_1
    //   2797: invokespecial 540	com/tencent/mm/plugin/webview/ui/tools/j$7:<init>	(Lcom/tencent/mm/plugin/webview/ui/tools/j;)V
    //   2800: invokestatic 545	com/tencent/mm/ui/base/h:a	(Landroid/content/Context;Ljava/lang/String;Ljava/util/List;Ljava/util/List;Ljava/lang/String;Lcom/tencent/mm/ui/base/h$d;)Landroid/app/Dialog;
    //   2803: pop
    //   2804: sipush 7652
    //   2807: invokestatic 129	com/tencent/matrix/trace/core/AppMethodBeat:o	(I)V
    //   2810: goto -2671 -> 139
    //   2813: aload_0
    //   2814: getfield 17	com/tencent/mm/plugin/webview/ui/tools/j$10:utN	Lcom/tencent/mm/plugin/webview/ui/tools/j;
    //   2817: invokevirtual 52	com/tencent/mm/plugin/webview/ui/tools/j:cZv	()Lcom/tencent/mm/plugin/webview/ui/tools/WebViewUI;
    //   2820: getfield 137	com/tencent/mm/plugin/webview/ui/tools/WebViewUI:ulI	Lcom/tencent/mm/plugin/webview/model/aq;
    //   2823: invokevirtual 143	com/tencent/mm/plugin/webview/model/aq:cYc	()Lcom/tencent/mm/plugin/webview/model/aq$e;
    //   2826: astore_1
    //   2827: aload_1
    //   2828: iconst_3
    //   2829: anewarray 4	java/lang/Object
    //   2832: dup
    //   2833: iconst_0
    //   2834: aload_0
    //   2835: getfield 17	com/tencent/mm/plugin/webview/ui/tools/j$10:utN	Lcom/tencent/mm/plugin/webview/ui/tools/j;
    //   2838: invokevirtual 52	com/tencent/mm/plugin/webview/ui/tools/j:cZv	()Lcom/tencent/mm/plugin/webview/ui/tools/WebViewUI;
    //   2841: getfield 146	com/tencent/mm/plugin/webview/ui/tools/WebViewUI:cOG	Ljava/lang/String;
    //   2844: aastore
    //   2845: dup
    //   2846: iconst_1
    //   2847: bipush 11
    //   2849: invokestatic 152	java/lang/Integer:valueOf	(I)Ljava/lang/Integer;
    //   2852: aastore
    //   2853: dup
    //   2854: iconst_2
    //   2855: iconst_1
    //   2856: invokestatic 152	java/lang/Integer:valueOf	(I)Ljava/lang/Integer;
    //   2859: aastore
    //   2860: putfield 158	com/tencent/mm/plugin/webview/model/aq$e:une	[Ljava/lang/Object;
    //   2863: aload_1
    //   2864: aload_0
    //   2865: getfield 17	com/tencent/mm/plugin/webview/ui/tools/j$10:utN	Lcom/tencent/mm/plugin/webview/ui/tools/j;
    //   2868: invokevirtual 52	com/tencent/mm/plugin/webview/ui/tools/j:cZv	()Lcom/tencent/mm/plugin/webview/ui/tools/WebViewUI;
    //   2871: getfield 162	com/tencent/mm/plugin/webview/ui/tools/WebViewUI:icy	Lcom/tencent/mm/plugin/webview/stub/d;
    //   2874: invokevirtual 165	com/tencent/mm/plugin/webview/model/aq$e:b	(Lcom/tencent/mm/plugin/webview/stub/d;)V
    //   2877: aload_0
    //   2878: getfield 17	com/tencent/mm/plugin/webview/ui/tools/j$10:utN	Lcom/tencent/mm/plugin/webview/ui/tools/j;
    //   2881: aconst_null
    //   2882: invokevirtual 548	com/tencent/mm/plugin/webview/ui/tools/j:afG	(Ljava/lang/String;)V
    //   2885: sipush 7652
    //   2888: invokestatic 129	com/tencent/matrix/trace/core/AppMethodBeat:o	(I)V
    //   2891: goto -2752 -> 139
    //   2894: aload_0
    //   2895: getfield 17	com/tencent/mm/plugin/webview/ui/tools/j$10:utN	Lcom/tencent/mm/plugin/webview/ui/tools/j;
    //   2898: invokevirtual 52	com/tencent/mm/plugin/webview/ui/tools/j:cZv	()Lcom/tencent/mm/plugin/webview/ui/tools/WebViewUI;
    //   2901: getfield 137	com/tencent/mm/plugin/webview/ui/tools/WebViewUI:ulI	Lcom/tencent/mm/plugin/webview/model/aq;
    //   2904: invokevirtual 143	com/tencent/mm/plugin/webview/model/aq:cYc	()Lcom/tencent/mm/plugin/webview/model/aq$e;
    //   2907: astore_1
    //   2908: aload_1
    //   2909: iconst_3
    //   2910: anewarray 4	java/lang/Object
    //   2913: dup
    //   2914: iconst_0
    //   2915: aload_0
    //   2916: getfield 17	com/tencent/mm/plugin/webview/ui/tools/j$10:utN	Lcom/tencent/mm/plugin/webview/ui/tools/j;
    //   2919: invokevirtual 52	com/tencent/mm/plugin/webview/ui/tools/j:cZv	()Lcom/tencent/mm/plugin/webview/ui/tools/WebViewUI;
    //   2922: getfield 146	com/tencent/mm/plugin/webview/ui/tools/WebViewUI:cOG	Ljava/lang/String;
    //   2925: aastore
    //   2926: dup
    //   2927: iconst_1
    //   2928: bipush 6
    //   2930: invokestatic 152	java/lang/Integer:valueOf	(I)Ljava/lang/Integer;
    //   2933: aastore
    //   2934: dup
    //   2935: iconst_2
    //   2936: iconst_1
    //   2937: invokestatic 152	java/lang/Integer:valueOf	(I)Ljava/lang/Integer;
    //   2940: aastore
    //   2941: putfield 158	com/tencent/mm/plugin/webview/model/aq$e:une	[Ljava/lang/Object;
    //   2944: aload_1
    //   2945: aload_0
    //   2946: getfield 17	com/tencent/mm/plugin/webview/ui/tools/j$10:utN	Lcom/tencent/mm/plugin/webview/ui/tools/j;
    //   2949: invokevirtual 52	com/tencent/mm/plugin/webview/ui/tools/j:cZv	()Lcom/tencent/mm/plugin/webview/ui/tools/WebViewUI;
    //   2952: getfield 162	com/tencent/mm/plugin/webview/ui/tools/WebViewUI:icy	Lcom/tencent/mm/plugin/webview/stub/d;
    //   2955: invokevirtual 165	com/tencent/mm/plugin/webview/model/aq$e:b	(Lcom/tencent/mm/plugin/webview/stub/d;)V
    //   2958: new 219	android/content/Intent
    //   2961: dup
    //   2962: invokespecial 249	android/content/Intent:<init>	()V
    //   2965: astore_1
    //   2966: aload_1
    //   2967: ldc_w 550
    //   2970: iconst_2
    //   2971: invokevirtual 553	android/content/Intent:putExtra	(Ljava/lang/String;I)Landroid/content/Intent;
    //   2974: pop
    //   2975: aload_1
    //   2976: ldc_w 555
    //   2979: aload_0
    //   2980: getfield 17	com/tencent/mm/plugin/webview/ui/tools/j$10:utN	Lcom/tencent/mm/plugin/webview/ui/tools/j;
    //   2983: invokevirtual 211	com/tencent/mm/plugin/webview/ui/tools/a:cZv	()Lcom/tencent/mm/plugin/webview/ui/tools/WebViewUI;
    //   2986: invokevirtual 215	com/tencent/mm/plugin/webview/ui/tools/WebViewUI:getIntent	()Landroid/content/Intent;
    //   2989: ldc_w 557
    //   2992: ldc2_w 558
    //   2995: invokevirtual 278	android/content/Intent:getLongExtra	(Ljava/lang/String;J)J
    //   2998: invokevirtual 562	android/content/Intent:putExtra	(Ljava/lang/String;J)Landroid/content/Intent;
    //   3001: pop
    //   3002: aload_0
    //   3003: getfield 17	com/tencent/mm/plugin/webview/ui/tools/j$10:utN	Lcom/tencent/mm/plugin/webview/ui/tools/j;
    //   3006: invokevirtual 52	com/tencent/mm/plugin/webview/ui/tools/j:cZv	()Lcom/tencent/mm/plugin/webview/ui/tools/WebViewUI;
    //   3009: ldc_w 564
    //   3012: aload_1
    //   3013: invokestatic 568	com/tencent/mm/plugin/fav/a/b:b	(Landroid/content/Context;Ljava/lang/String;Landroid/content/Intent;)V
    //   3016: aload_0
    //   3017: getfield 17	com/tencent/mm/plugin/webview/ui/tools/j$10:utN	Lcom/tencent/mm/plugin/webview/ui/tools/j;
    //   3020: invokevirtual 52	com/tencent/mm/plugin/webview/ui/tools/j:cZv	()Lcom/tencent/mm/plugin/webview/ui/tools/WebViewUI;
    //   3023: getfield 137	com/tencent/mm/plugin/webview/ui/tools/WebViewUI:ulI	Lcom/tencent/mm/plugin/webview/model/aq;
    //   3026: ldc_w 570
    //   3029: invokevirtual 573	com/tencent/mm/plugin/webview/model/aq:aeG	(Ljava/lang/String;)V
    //   3032: sipush 7652
    //   3035: invokestatic 129	com/tencent/matrix/trace/core/AppMethodBeat:o	(I)V
    //   3038: goto -2899 -> 139
    //   3041: aload_0
    //   3042: getfield 17	com/tencent/mm/plugin/webview/ui/tools/j$10:utN	Lcom/tencent/mm/plugin/webview/ui/tools/j;
    //   3045: invokevirtual 52	com/tencent/mm/plugin/webview/ui/tools/j:cZv	()Lcom/tencent/mm/plugin/webview/ui/tools/WebViewUI;
    //   3048: getfield 137	com/tencent/mm/plugin/webview/ui/tools/WebViewUI:ulI	Lcom/tencent/mm/plugin/webview/model/aq;
    //   3051: invokevirtual 143	com/tencent/mm/plugin/webview/model/aq:cYc	()Lcom/tencent/mm/plugin/webview/model/aq$e;
    //   3054: astore_1
    //   3055: aload_1
    //   3056: iconst_3
    //   3057: anewarray 4	java/lang/Object
    //   3060: dup
    //   3061: iconst_0
    //   3062: aload_0
    //   3063: getfield 17	com/tencent/mm/plugin/webview/ui/tools/j$10:utN	Lcom/tencent/mm/plugin/webview/ui/tools/j;
    //   3066: invokevirtual 52	com/tencent/mm/plugin/webview/ui/tools/j:cZv	()Lcom/tencent/mm/plugin/webview/ui/tools/WebViewUI;
    //   3069: getfield 146	com/tencent/mm/plugin/webview/ui/tools/WebViewUI:cOG	Ljava/lang/String;
    //   3072: aastore
    //   3073: dup
    //   3074: iconst_1
    //   3075: bipush 9
    //   3077: invokestatic 152	java/lang/Integer:valueOf	(I)Ljava/lang/Integer;
    //   3080: aastore
    //   3081: dup
    //   3082: iconst_2
    //   3083: iconst_1
    //   3084: invokestatic 152	java/lang/Integer:valueOf	(I)Ljava/lang/Integer;
    //   3087: aastore
    //   3088: putfield 158	com/tencent/mm/plugin/webview/model/aq$e:une	[Ljava/lang/Object;
    //   3091: aload_1
    //   3092: aload_0
    //   3093: getfield 17	com/tencent/mm/plugin/webview/ui/tools/j$10:utN	Lcom/tencent/mm/plugin/webview/ui/tools/j;
    //   3096: invokevirtual 52	com/tencent/mm/plugin/webview/ui/tools/j:cZv	()Lcom/tencent/mm/plugin/webview/ui/tools/WebViewUI;
    //   3099: getfield 162	com/tencent/mm/plugin/webview/ui/tools/WebViewUI:icy	Lcom/tencent/mm/plugin/webview/stub/d;
    //   3102: invokevirtual 165	com/tencent/mm/plugin/webview/model/aq$e:b	(Lcom/tencent/mm/plugin/webview/stub/d;)V
    //   3105: aload_0
    //   3106: getfield 17	com/tencent/mm/plugin/webview/ui/tools/j$10:utN	Lcom/tencent/mm/plugin/webview/ui/tools/j;
    //   3109: invokevirtual 52	com/tencent/mm/plugin/webview/ui/tools/j:cZv	()Lcom/tencent/mm/plugin/webview/ui/tools/WebViewUI;
    //   3112: getfield 576	com/tencent/mm/plugin/webview/ui/tools/WebViewUI:uvZ	Z
    //   3115: ifne +62 -> 3177
    //   3118: aload_0
    //   3119: getfield 17	com/tencent/mm/plugin/webview/ui/tools/j$10:utN	Lcom/tencent/mm/plugin/webview/ui/tools/j;
    //   3122: aload_0
    //   3123: getfield 17	com/tencent/mm/plugin/webview/ui/tools/j$10:utN	Lcom/tencent/mm/plugin/webview/ui/tools/j;
    //   3126: invokevirtual 52	com/tencent/mm/plugin/webview/ui/tools/j:cZv	()Lcom/tencent/mm/plugin/webview/ui/tools/WebViewUI;
    //   3129: getfield 293	com/tencent/mm/plugin/webview/ui/tools/WebViewUI:pzf	Lcom/tencent/mm/ui/widget/MMWebView;
    //   3132: invokevirtual 296	com/tencent/mm/ui/widget/MMWebView:getUrl	()Ljava/lang/String;
    //   3135: aload_0
    //   3136: getfield 17	com/tencent/mm/plugin/webview/ui/tools/j$10:utN	Lcom/tencent/mm/plugin/webview/ui/tools/j;
    //   3139: invokevirtual 52	com/tencent/mm/plugin/webview/ui/tools/j:cZv	()Lcom/tencent/mm/plugin/webview/ui/tools/WebViewUI;
    //   3142: getfield 293	com/tencent/mm/plugin/webview/ui/tools/WebViewUI:pzf	Lcom/tencent/mm/ui/widget/MMWebView;
    //   3145: invokevirtual 580	com/tencent/mm/ui/widget/MMWebView:getSettings	()Lcom/tencent/xweb/p;
    //   3148: invokevirtual 585	com/tencent/xweb/p:getUserAgentString	()Ljava/lang/String;
    //   3151: aload_0
    //   3152: getfield 17	com/tencent/mm/plugin/webview/ui/tools/j$10:utN	Lcom/tencent/mm/plugin/webview/ui/tools/j;
    //   3155: getfield 588	com/tencent/mm/plugin/webview/ui/tools/j:width	I
    //   3158: aload_0
    //   3159: getfield 17	com/tencent/mm/plugin/webview/ui/tools/j$10:utN	Lcom/tencent/mm/plugin/webview/ui/tools/j;
    //   3162: getfield 591	com/tencent/mm/plugin/webview/ui/tools/j:height	I
    //   3165: invokestatic 594	com/tencent/mm/plugin/webview/ui/tools/j:a	(Lcom/tencent/mm/plugin/webview/ui/tools/j;Ljava/lang/String;Ljava/lang/String;II)V
    //   3168: sipush 7652
    //   3171: invokestatic 129	com/tencent/matrix/trace/core/AppMethodBeat:o	(I)V
    //   3174: goto -3035 -> 139
    //   3177: aload_0
    //   3178: getfield 17	com/tencent/mm/plugin/webview/ui/tools/j$10:utN	Lcom/tencent/mm/plugin/webview/ui/tools/j;
    //   3181: aload_0
    //   3182: getfield 17	com/tencent/mm/plugin/webview/ui/tools/j$10:utN	Lcom/tencent/mm/plugin/webview/ui/tools/j;
    //   3185: getfield 597	com/tencent/mm/plugin/webview/ui/tools/j:utE	Ljava/lang/String;
    //   3188: invokestatic 600	com/tencent/mm/plugin/webview/ui/tools/j:a	(Lcom/tencent/mm/plugin/webview/ui/tools/j;Ljava/lang/String;)V
    //   3191: sipush 7652
    //   3194: invokestatic 129	com/tencent/matrix/trace/core/AppMethodBeat:o	(I)V
    //   3197: goto -3058 -> 139
    //   3200: aload_0
    //   3201: getfield 17	com/tencent/mm/plugin/webview/ui/tools/j$10:utN	Lcom/tencent/mm/plugin/webview/ui/tools/j;
    //   3204: invokevirtual 52	com/tencent/mm/plugin/webview/ui/tools/j:cZv	()Lcom/tencent/mm/plugin/webview/ui/tools/WebViewUI;
    //   3207: getfield 137	com/tencent/mm/plugin/webview/ui/tools/WebViewUI:ulI	Lcom/tencent/mm/plugin/webview/model/aq;
    //   3210: invokevirtual 143	com/tencent/mm/plugin/webview/model/aq:cYc	()Lcom/tencent/mm/plugin/webview/model/aq$e;
    //   3213: astore_3
    //   3214: aload_3
    //   3215: iconst_3
    //   3216: anewarray 4	java/lang/Object
    //   3219: dup
    //   3220: iconst_0
    //   3221: aload_0
    //   3222: getfield 17	com/tencent/mm/plugin/webview/ui/tools/j$10:utN	Lcom/tencent/mm/plugin/webview/ui/tools/j;
    //   3225: invokevirtual 52	com/tencent/mm/plugin/webview/ui/tools/j:cZv	()Lcom/tencent/mm/plugin/webview/ui/tools/WebViewUI;
    //   3228: getfield 146	com/tencent/mm/plugin/webview/ui/tools/WebViewUI:cOG	Ljava/lang/String;
    //   3231: aastore
    //   3232: dup
    //   3233: iconst_1
    //   3234: bipush 19
    //   3236: invokestatic 152	java/lang/Integer:valueOf	(I)Ljava/lang/Integer;
    //   3239: aastore
    //   3240: dup
    //   3241: iconst_2
    //   3242: iconst_1
    //   3243: invokestatic 152	java/lang/Integer:valueOf	(I)Ljava/lang/Integer;
    //   3246: aastore
    //   3247: putfield 158	com/tencent/mm/plugin/webview/model/aq$e:une	[Ljava/lang/Object;
    //   3250: aload_3
    //   3251: aload_0
    //   3252: getfield 17	com/tencent/mm/plugin/webview/ui/tools/j$10:utN	Lcom/tencent/mm/plugin/webview/ui/tools/j;
    //   3255: invokevirtual 52	com/tencent/mm/plugin/webview/ui/tools/j:cZv	()Lcom/tencent/mm/plugin/webview/ui/tools/WebViewUI;
    //   3258: getfield 162	com/tencent/mm/plugin/webview/ui/tools/WebViewUI:icy	Lcom/tencent/mm/plugin/webview/stub/d;
    //   3261: invokevirtual 165	com/tencent/mm/plugin/webview/model/aq$e:b	(Lcom/tencent/mm/plugin/webview/stub/d;)V
    //   3264: aload_0
    //   3265: getfield 17	com/tencent/mm/plugin/webview/ui/tools/j$10:utN	Lcom/tencent/mm/plugin/webview/ui/tools/j;
    //   3268: aload_1
    //   3269: invokestatic 603	com/tencent/mm/plugin/webview/ui/tools/j:a	(Lcom/tencent/mm/plugin/webview/ui/tools/j;Landroid/view/MenuItem;)V
    //   3272: sipush 7652
    //   3275: invokestatic 129	com/tencent/matrix/trace/core/AppMethodBeat:o	(I)V
    //   3278: goto -3139 -> 139
    //   3281: aload_0
    //   3282: getfield 17	com/tencent/mm/plugin/webview/ui/tools/j$10:utN	Lcom/tencent/mm/plugin/webview/ui/tools/j;
    //   3285: invokevirtual 52	com/tencent/mm/plugin/webview/ui/tools/j:cZv	()Lcom/tencent/mm/plugin/webview/ui/tools/WebViewUI;
    //   3288: getfield 137	com/tencent/mm/plugin/webview/ui/tools/WebViewUI:ulI	Lcom/tencent/mm/plugin/webview/model/aq;
    //   3291: invokevirtual 143	com/tencent/mm/plugin/webview/model/aq:cYc	()Lcom/tencent/mm/plugin/webview/model/aq$e;
    //   3294: astore_3
    //   3295: aload_3
    //   3296: iconst_3
    //   3297: anewarray 4	java/lang/Object
    //   3300: dup
    //   3301: iconst_0
    //   3302: aload_0
    //   3303: getfield 17	com/tencent/mm/plugin/webview/ui/tools/j$10:utN	Lcom/tencent/mm/plugin/webview/ui/tools/j;
    //   3306: invokevirtual 52	com/tencent/mm/plugin/webview/ui/tools/j:cZv	()Lcom/tencent/mm/plugin/webview/ui/tools/WebViewUI;
    //   3309: getfield 146	com/tencent/mm/plugin/webview/ui/tools/WebViewUI:cOG	Ljava/lang/String;
    //   3312: aastore
    //   3313: dup
    //   3314: iconst_1
    //   3315: bipush 21
    //   3317: invokestatic 152	java/lang/Integer:valueOf	(I)Ljava/lang/Integer;
    //   3320: aastore
    //   3321: dup
    //   3322: iconst_2
    //   3323: iconst_1
    //   3324: invokestatic 152	java/lang/Integer:valueOf	(I)Ljava/lang/Integer;
    //   3327: aastore
    //   3328: putfield 158	com/tencent/mm/plugin/webview/model/aq$e:une	[Ljava/lang/Object;
    //   3331: aload_3
    //   3332: aload_0
    //   3333: getfield 17	com/tencent/mm/plugin/webview/ui/tools/j$10:utN	Lcom/tencent/mm/plugin/webview/ui/tools/j;
    //   3336: invokevirtual 52	com/tencent/mm/plugin/webview/ui/tools/j:cZv	()Lcom/tencent/mm/plugin/webview/ui/tools/WebViewUI;
    //   3339: getfield 162	com/tencent/mm/plugin/webview/ui/tools/WebViewUI:icy	Lcom/tencent/mm/plugin/webview/stub/d;
    //   3342: invokevirtual 165	com/tencent/mm/plugin/webview/model/aq$e:b	(Lcom/tencent/mm/plugin/webview/stub/d;)V
    //   3345: aload_0
    //   3346: getfield 17	com/tencent/mm/plugin/webview/ui/tools/j$10:utN	Lcom/tencent/mm/plugin/webview/ui/tools/j;
    //   3349: aload_1
    //   3350: invokestatic 603	com/tencent/mm/plugin/webview/ui/tools/j:a	(Lcom/tencent/mm/plugin/webview/ui/tools/j;Landroid/view/MenuItem;)V
    //   3353: sipush 7652
    //   3356: invokestatic 129	com/tencent/matrix/trace/core/AppMethodBeat:o	(I)V
    //   3359: goto -3220 -> 139
    //   3362: aload_0
    //   3363: getfield 17	com/tencent/mm/plugin/webview/ui/tools/j$10:utN	Lcom/tencent/mm/plugin/webview/ui/tools/j;
    //   3366: invokevirtual 52	com/tencent/mm/plugin/webview/ui/tools/j:cZv	()Lcom/tencent/mm/plugin/webview/ui/tools/WebViewUI;
    //   3369: getfield 137	com/tencent/mm/plugin/webview/ui/tools/WebViewUI:ulI	Lcom/tencent/mm/plugin/webview/model/aq;
    //   3372: invokevirtual 143	com/tencent/mm/plugin/webview/model/aq:cYc	()Lcom/tencent/mm/plugin/webview/model/aq$e;
    //   3375: astore_3
    //   3376: aload_3
    //   3377: iconst_3
    //   3378: anewarray 4	java/lang/Object
    //   3381: dup
    //   3382: iconst_0
    //   3383: aload_0
    //   3384: getfield 17	com/tencent/mm/plugin/webview/ui/tools/j$10:utN	Lcom/tencent/mm/plugin/webview/ui/tools/j;
    //   3387: invokevirtual 52	com/tencent/mm/plugin/webview/ui/tools/j:cZv	()Lcom/tencent/mm/plugin/webview/ui/tools/WebViewUI;
    //   3390: getfield 146	com/tencent/mm/plugin/webview/ui/tools/WebViewUI:cOG	Ljava/lang/String;
    //   3393: aastore
    //   3394: dup
    //   3395: iconst_1
    //   3396: bipush 20
    //   3398: invokestatic 152	java/lang/Integer:valueOf	(I)Ljava/lang/Integer;
    //   3401: aastore
    //   3402: dup
    //   3403: iconst_2
    //   3404: iconst_1
    //   3405: invokestatic 152	java/lang/Integer:valueOf	(I)Ljava/lang/Integer;
    //   3408: aastore
    //   3409: putfield 158	com/tencent/mm/plugin/webview/model/aq$e:une	[Ljava/lang/Object;
    //   3412: aload_3
    //   3413: aload_0
    //   3414: getfield 17	com/tencent/mm/plugin/webview/ui/tools/j$10:utN	Lcom/tencent/mm/plugin/webview/ui/tools/j;
    //   3417: invokevirtual 52	com/tencent/mm/plugin/webview/ui/tools/j:cZv	()Lcom/tencent/mm/plugin/webview/ui/tools/WebViewUI;
    //   3420: getfield 162	com/tencent/mm/plugin/webview/ui/tools/WebViewUI:icy	Lcom/tencent/mm/plugin/webview/stub/d;
    //   3423: invokevirtual 165	com/tencent/mm/plugin/webview/model/aq$e:b	(Lcom/tencent/mm/plugin/webview/stub/d;)V
    //   3426: aload_0
    //   3427: getfield 17	com/tencent/mm/plugin/webview/ui/tools/j$10:utN	Lcom/tencent/mm/plugin/webview/ui/tools/j;
    //   3430: aload_1
    //   3431: invokestatic 603	com/tencent/mm/plugin/webview/ui/tools/j:a	(Lcom/tencent/mm/plugin/webview/ui/tools/j;Landroid/view/MenuItem;)V
    //   3434: sipush 7652
    //   3437: invokestatic 129	com/tencent/matrix/trace/core/AppMethodBeat:o	(I)V
    //   3440: goto -3301 -> 139
    //   3443: aload_0
    //   3444: getfield 17	com/tencent/mm/plugin/webview/ui/tools/j$10:utN	Lcom/tencent/mm/plugin/webview/ui/tools/j;
    //   3447: invokevirtual 52	com/tencent/mm/plugin/webview/ui/tools/j:cZv	()Lcom/tencent/mm/plugin/webview/ui/tools/WebViewUI;
    //   3450: getfield 137	com/tencent/mm/plugin/webview/ui/tools/WebViewUI:ulI	Lcom/tencent/mm/plugin/webview/model/aq;
    //   3453: invokevirtual 143	com/tencent/mm/plugin/webview/model/aq:cYc	()Lcom/tencent/mm/plugin/webview/model/aq$e;
    //   3456: astore_3
    //   3457: aload_3
    //   3458: iconst_3
    //   3459: anewarray 4	java/lang/Object
    //   3462: dup
    //   3463: iconst_0
    //   3464: aload_0
    //   3465: getfield 17	com/tencent/mm/plugin/webview/ui/tools/j$10:utN	Lcom/tencent/mm/plugin/webview/ui/tools/j;
    //   3468: invokevirtual 52	com/tencent/mm/plugin/webview/ui/tools/j:cZv	()Lcom/tencent/mm/plugin/webview/ui/tools/WebViewUI;
    //   3471: getfield 146	com/tencent/mm/plugin/webview/ui/tools/WebViewUI:cOG	Ljava/lang/String;
    //   3474: aastore
    //   3475: dup
    //   3476: iconst_1
    //   3477: bipush 22
    //   3479: invokestatic 152	java/lang/Integer:valueOf	(I)Ljava/lang/Integer;
    //   3482: aastore
    //   3483: dup
    //   3484: iconst_2
    //   3485: iconst_1
    //   3486: invokestatic 152	java/lang/Integer:valueOf	(I)Ljava/lang/Integer;
    //   3489: aastore
    //   3490: putfield 158	com/tencent/mm/plugin/webview/model/aq$e:une	[Ljava/lang/Object;
    //   3493: aload_3
    //   3494: aload_0
    //   3495: getfield 17	com/tencent/mm/plugin/webview/ui/tools/j$10:utN	Lcom/tencent/mm/plugin/webview/ui/tools/j;
    //   3498: invokevirtual 52	com/tencent/mm/plugin/webview/ui/tools/j:cZv	()Lcom/tencent/mm/plugin/webview/ui/tools/WebViewUI;
    //   3501: getfield 162	com/tencent/mm/plugin/webview/ui/tools/WebViewUI:icy	Lcom/tencent/mm/plugin/webview/stub/d;
    //   3504: invokevirtual 165	com/tencent/mm/plugin/webview/model/aq$e:b	(Lcom/tencent/mm/plugin/webview/stub/d;)V
    //   3507: aload_0
    //   3508: getfield 17	com/tencent/mm/plugin/webview/ui/tools/j$10:utN	Lcom/tencent/mm/plugin/webview/ui/tools/j;
    //   3511: aload_1
    //   3512: invokestatic 603	com/tencent/mm/plugin/webview/ui/tools/j:a	(Lcom/tencent/mm/plugin/webview/ui/tools/j;Landroid/view/MenuItem;)V
    //   3515: sipush 7652
    //   3518: invokestatic 129	com/tencent/matrix/trace/core/AppMethodBeat:o	(I)V
    //   3521: goto -3382 -> 139
    //   3524: aload_0
    //   3525: getfield 17	com/tencent/mm/plugin/webview/ui/tools/j$10:utN	Lcom/tencent/mm/plugin/webview/ui/tools/j;
    //   3528: invokevirtual 52	com/tencent/mm/plugin/webview/ui/tools/j:cZv	()Lcom/tencent/mm/plugin/webview/ui/tools/WebViewUI;
    //   3531: getfield 137	com/tencent/mm/plugin/webview/ui/tools/WebViewUI:ulI	Lcom/tencent/mm/plugin/webview/model/aq;
    //   3534: invokevirtual 143	com/tencent/mm/plugin/webview/model/aq:cYc	()Lcom/tencent/mm/plugin/webview/model/aq$e;
    //   3537: astore_3
    //   3538: aload_3
    //   3539: iconst_3
    //   3540: anewarray 4	java/lang/Object
    //   3543: dup
    //   3544: iconst_0
    //   3545: aload_0
    //   3546: getfield 17	com/tencent/mm/plugin/webview/ui/tools/j$10:utN	Lcom/tencent/mm/plugin/webview/ui/tools/j;
    //   3549: invokevirtual 52	com/tencent/mm/plugin/webview/ui/tools/j:cZv	()Lcom/tencent/mm/plugin/webview/ui/tools/WebViewUI;
    //   3552: getfield 146	com/tencent/mm/plugin/webview/ui/tools/WebViewUI:cOG	Ljava/lang/String;
    //   3555: aastore
    //   3556: dup
    //   3557: iconst_1
    //   3558: bipush 23
    //   3560: invokestatic 152	java/lang/Integer:valueOf	(I)Ljava/lang/Integer;
    //   3563: aastore
    //   3564: dup
    //   3565: iconst_2
    //   3566: iconst_1
    //   3567: invokestatic 152	java/lang/Integer:valueOf	(I)Ljava/lang/Integer;
    //   3570: aastore
    //   3571: putfield 158	com/tencent/mm/plugin/webview/model/aq$e:une	[Ljava/lang/Object;
    //   3574: aload_3
    //   3575: aload_0
    //   3576: getfield 17	com/tencent/mm/plugin/webview/ui/tools/j$10:utN	Lcom/tencent/mm/plugin/webview/ui/tools/j;
    //   3579: invokevirtual 52	com/tencent/mm/plugin/webview/ui/tools/j:cZv	()Lcom/tencent/mm/plugin/webview/ui/tools/WebViewUI;
    //   3582: getfield 162	com/tencent/mm/plugin/webview/ui/tools/WebViewUI:icy	Lcom/tencent/mm/plugin/webview/stub/d;
    //   3585: invokevirtual 165	com/tencent/mm/plugin/webview/model/aq$e:b	(Lcom/tencent/mm/plugin/webview/stub/d;)V
    //   3588: aload_0
    //   3589: getfield 17	com/tencent/mm/plugin/webview/ui/tools/j$10:utN	Lcom/tencent/mm/plugin/webview/ui/tools/j;
    //   3592: aload_1
    //   3593: invokestatic 603	com/tencent/mm/plugin/webview/ui/tools/j:a	(Lcom/tencent/mm/plugin/webview/ui/tools/j;Landroid/view/MenuItem;)V
    //   3596: sipush 7652
    //   3599: invokestatic 129	com/tencent/matrix/trace/core/AppMethodBeat:o	(I)V
    //   3602: goto -3463 -> 139
    //   3605: aload_0
    //   3606: getfield 17	com/tencent/mm/plugin/webview/ui/tools/j$10:utN	Lcom/tencent/mm/plugin/webview/ui/tools/j;
    //   3609: invokevirtual 52	com/tencent/mm/plugin/webview/ui/tools/j:cZv	()Lcom/tencent/mm/plugin/webview/ui/tools/WebViewUI;
    //   3612: getfield 137	com/tencent/mm/plugin/webview/ui/tools/WebViewUI:ulI	Lcom/tencent/mm/plugin/webview/model/aq;
    //   3615: invokevirtual 143	com/tencent/mm/plugin/webview/model/aq:cYc	()Lcom/tencent/mm/plugin/webview/model/aq$e;
    //   3618: astore_1
    //   3619: aload_1
    //   3620: iconst_3
    //   3621: anewarray 4	java/lang/Object
    //   3624: dup
    //   3625: iconst_0
    //   3626: aload_0
    //   3627: getfield 17	com/tencent/mm/plugin/webview/ui/tools/j$10:utN	Lcom/tencent/mm/plugin/webview/ui/tools/j;
    //   3630: invokevirtual 52	com/tencent/mm/plugin/webview/ui/tools/j:cZv	()Lcom/tencent/mm/plugin/webview/ui/tools/WebViewUI;
    //   3633: getfield 146	com/tencent/mm/plugin/webview/ui/tools/WebViewUI:cOG	Ljava/lang/String;
    //   3636: aastore
    //   3637: dup
    //   3638: iconst_1
    //   3639: bipush 26
    //   3641: invokestatic 152	java/lang/Integer:valueOf	(I)Ljava/lang/Integer;
    //   3644: aastore
    //   3645: dup
    //   3646: iconst_2
    //   3647: iconst_1
    //   3648: invokestatic 152	java/lang/Integer:valueOf	(I)Ljava/lang/Integer;
    //   3651: aastore
    //   3652: putfield 158	com/tencent/mm/plugin/webview/model/aq$e:une	[Ljava/lang/Object;
    //   3655: aload_1
    //   3656: aload_0
    //   3657: getfield 17	com/tencent/mm/plugin/webview/ui/tools/j$10:utN	Lcom/tencent/mm/plugin/webview/ui/tools/j;
    //   3660: invokevirtual 52	com/tencent/mm/plugin/webview/ui/tools/j:cZv	()Lcom/tencent/mm/plugin/webview/ui/tools/WebViewUI;
    //   3663: getfield 162	com/tencent/mm/plugin/webview/ui/tools/WebViewUI:icy	Lcom/tencent/mm/plugin/webview/stub/d;
    //   3666: invokevirtual 165	com/tencent/mm/plugin/webview/model/aq$e:b	(Lcom/tencent/mm/plugin/webview/stub/d;)V
    //   3669: aload_0
    //   3670: getfield 17	com/tencent/mm/plugin/webview/ui/tools/j$10:utN	Lcom/tencent/mm/plugin/webview/ui/tools/j;
    //   3673: astore_1
    //   3674: aload_1
    //   3675: invokevirtual 52	com/tencent/mm/plugin/webview/ui/tools/j:cZv	()Lcom/tencent/mm/plugin/webview/ui/tools/WebViewUI;
    //   3678: getfield 58	com/tencent/mm/plugin/webview/ui/tools/WebViewUI:uhz	Lcom/tencent/mm/plugin/webview/ui/tools/jsapi/d;
    //   3681: ldc_w 605
    //   3684: iconst_1
    //   3685: invokevirtual 527	com/tencent/mm/plugin/webview/ui/tools/jsapi/d:bJ	(Ljava/lang/String;Z)V
    //   3688: aload_1
    //   3689: invokevirtual 52	com/tencent/mm/plugin/webview/ui/tools/j:cZv	()Lcom/tencent/mm/plugin/webview/ui/tools/WebViewUI;
    //   3692: getfield 58	com/tencent/mm/plugin/webview/ui/tools/WebViewUI:uhz	Lcom/tencent/mm/plugin/webview/ui/tools/jsapi/d;
    //   3695: astore_1
    //   3696: aload_1
    //   3697: getfield 530	com/tencent/mm/plugin/webview/ui/tools/jsapi/d:ready	Z
    //   3700: ifne +20 -> 3720
    //   3703: ldc 60
    //   3705: ldc_w 607
    //   3708: invokestatic 413	com/tencent/mm/sdk/platformtools/ab:e	(Ljava/lang/String;Ljava/lang/String;)V
    //   3711: sipush 7652
    //   3714: invokestatic 129	com/tencent/matrix/trace/core/AppMethodBeat:o	(I)V
    //   3717: goto -3578 -> 139
    //   3720: ldc_w 609
    //   3723: new 69	java/util/HashMap
    //   3726: dup
    //   3727: invokespecial 70	java/util/HashMap:<init>	()V
    //   3730: aload_1
    //   3731: getfield 90	com/tencent/mm/plugin/webview/ui/tools/jsapi/d:uFv	Z
    //   3734: aload_1
    //   3735: getfield 93	com/tencent/mm/plugin/webview/ui/tools/jsapi/d:uFw	Ljava/lang/String;
    //   3738: invokestatic 99	com/tencent/mm/plugin/webview/ui/tools/jsapi/i$a:b	(Ljava/lang/String;Ljava/util/Map;ZLjava/lang/String;)Ljava/lang/String;
    //   3741: astore_3
    //   3742: aload_1
    //   3743: getfield 103	com/tencent/mm/plugin/webview/ui/tools/jsapi/d:uFo	Lcom/tencent/mm/ui/widget/MMWebView;
    //   3746: new 105	java/lang/StringBuilder
    //   3749: dup
    //   3750: ldc 107
    //   3752: invokespecial 110	java/lang/StringBuilder:<init>	(Ljava/lang/String;)V
    //   3755: aload_3
    //   3756: invokevirtual 114	java/lang/StringBuilder:append	(Ljava/lang/String;)Ljava/lang/StringBuilder;
    //   3759: ldc 116
    //   3761: invokevirtual 114	java/lang/StringBuilder:append	(Ljava/lang/String;)Ljava/lang/StringBuilder;
    //   3764: invokevirtual 120	java/lang/StringBuilder:toString	()Ljava/lang/String;
    //   3767: aconst_null
    //   3768: invokevirtual 126	com/tencent/mm/ui/widget/MMWebView:evaluateJavascript	(Ljava/lang/String;Landroid/webkit/ValueCallback;)V
    //   3771: aload_1
    //   3772: getfield 341	com/tencent/mm/plugin/webview/ui/tools/jsapi/d:icy	Lcom/tencent/mm/plugin/webview/stub/d;
    //   3775: ldc_w 611
    //   3778: ldc_w 613
    //   3781: aload_1
    //   3782: getfield 345	com/tencent/mm/plugin/webview/ui/tools/jsapi/d:uqj	I
    //   3785: invokeinterface 617 4 0
    //   3790: sipush 7652
    //   3793: invokestatic 129	com/tencent/matrix/trace/core/AppMethodBeat:o	(I)V
    //   3796: goto -3657 -> 139
    //   3799: astore_1
    //   3800: ldc 60
    //   3802: new 105	java/lang/StringBuilder
    //   3805: dup
    //   3806: ldc_w 619
    //   3809: invokespecial 110	java/lang/StringBuilder:<init>	(Ljava/lang/String;)V
    //   3812: aload_1
    //   3813: invokevirtual 505	java/lang/Exception:getMessage	()Ljava/lang/String;
    //   3816: invokevirtual 114	java/lang/StringBuilder:append	(Ljava/lang/String;)Ljava/lang/StringBuilder;
    //   3819: invokevirtual 120	java/lang/StringBuilder:toString	()Ljava/lang/String;
    //   3822: invokestatic 368	com/tencent/mm/sdk/platformtools/ab:w	(Ljava/lang/String;Ljava/lang/String;)V
    //   3825: sipush 7652
    //   3828: invokestatic 129	com/tencent/matrix/trace/core/AppMethodBeat:o	(I)V
    //   3831: goto -3692 -> 139
    //   3834: aload_0
    //   3835: getfield 17	com/tencent/mm/plugin/webview/ui/tools/j$10:utN	Lcom/tencent/mm/plugin/webview/ui/tools/j;
    //   3838: invokevirtual 52	com/tencent/mm/plugin/webview/ui/tools/j:cZv	()Lcom/tencent/mm/plugin/webview/ui/tools/WebViewUI;
    //   3841: getfield 137	com/tencent/mm/plugin/webview/ui/tools/WebViewUI:ulI	Lcom/tencent/mm/plugin/webview/model/aq;
    //   3844: invokevirtual 143	com/tencent/mm/plugin/webview/model/aq:cYc	()Lcom/tencent/mm/plugin/webview/model/aq$e;
    //   3847: astore_1
    //   3848: aload_1
    //   3849: iconst_3
    //   3850: anewarray 4	java/lang/Object
    //   3853: dup
    //   3854: iconst_0
    //   3855: aload_0
    //   3856: getfield 17	com/tencent/mm/plugin/webview/ui/tools/j$10:utN	Lcom/tencent/mm/plugin/webview/ui/tools/j;
    //   3859: invokevirtual 52	com/tencent/mm/plugin/webview/ui/tools/j:cZv	()Lcom/tencent/mm/plugin/webview/ui/tools/WebViewUI;
    //   3862: getfield 146	com/tencent/mm/plugin/webview/ui/tools/WebViewUI:cOG	Ljava/lang/String;
    //   3865: aastore
    //   3866: dup
    //   3867: iconst_1
    //   3868: bipush 27
    //   3870: invokestatic 152	java/lang/Integer:valueOf	(I)Ljava/lang/Integer;
    //   3873: aastore
    //   3874: dup
    //   3875: iconst_2
    //   3876: iconst_1
    //   3877: invokestatic 152	java/lang/Integer:valueOf	(I)Ljava/lang/Integer;
    //   3880: aastore
    //   3881: putfield 158	com/tencent/mm/plugin/webview/model/aq$e:une	[Ljava/lang/Object;
    //   3884: aload_1
    //   3885: aload_0
    //   3886: getfield 17	com/tencent/mm/plugin/webview/ui/tools/j$10:utN	Lcom/tencent/mm/plugin/webview/ui/tools/j;
    //   3889: invokevirtual 52	com/tencent/mm/plugin/webview/ui/tools/j:cZv	()Lcom/tencent/mm/plugin/webview/ui/tools/WebViewUI;
    //   3892: getfield 162	com/tencent/mm/plugin/webview/ui/tools/WebViewUI:icy	Lcom/tencent/mm/plugin/webview/stub/d;
    //   3895: invokevirtual 165	com/tencent/mm/plugin/webview/model/aq$e:b	(Lcom/tencent/mm/plugin/webview/stub/d;)V
    //   3898: aload_0
    //   3899: getfield 17	com/tencent/mm/plugin/webview/ui/tools/j$10:utN	Lcom/tencent/mm/plugin/webview/ui/tools/j;
    //   3902: astore 4
    //   3904: aconst_null
    //   3905: astore_3
    //   3906: aload 4
    //   3908: invokevirtual 52	com/tencent/mm/plugin/webview/ui/tools/j:cZv	()Lcom/tencent/mm/plugin/webview/ui/tools/WebViewUI;
    //   3911: getfield 162	com/tencent/mm/plugin/webview/ui/tools/WebViewUI:icy	Lcom/tencent/mm/plugin/webview/stub/d;
    //   3914: aload 4
    //   3916: invokevirtual 52	com/tencent/mm/plugin/webview/ui/tools/j:cZv	()Lcom/tencent/mm/plugin/webview/ui/tools/WebViewUI;
    //   3919: getfield 293	com/tencent/mm/plugin/webview/ui/tools/WebViewUI:pzf	Lcom/tencent/mm/ui/widget/MMWebView;
    //   3922: invokevirtual 296	com/tencent/mm/ui/widget/MMWebView:getUrl	()Ljava/lang/String;
    //   3925: invokeinterface 421 2 0
    //   3930: astore_1
    //   3931: aload_1
    //   3932: astore_3
    //   3933: aload_3
    //   3934: astore_1
    //   3935: aload_3
    //   3936: invokestatic 179	com/tencent/mm/sdk/platformtools/bo:isNullOrNil	(Ljava/lang/String;)Z
    //   3939: ifeq +12 -> 3951
    //   3942: aload 4
    //   3944: invokevirtual 52	com/tencent/mm/plugin/webview/ui/tools/j:cZv	()Lcom/tencent/mm/plugin/webview/ui/tools/WebViewUI;
    //   3947: getfield 146	com/tencent/mm/plugin/webview/ui/tools/WebViewUI:cOG	Ljava/lang/String;
    //   3950: astore_1
    //   3951: new 105	java/lang/StringBuilder
    //   3954: astore_3
    //   3955: aload_3
    //   3956: ldc_w 621
    //   3959: invokespecial 110	java/lang/StringBuilder:<init>	(Ljava/lang/String;)V
    //   3962: aload_3
    //   3963: aload_1
    //   3964: ldc_w 623
    //   3967: invokestatic 629	com/tencent/mm/compatible/util/q:encode	(Ljava/lang/String;Ljava/lang/String;)Ljava/lang/String;
    //   3970: invokevirtual 114	java/lang/StringBuilder:append	(Ljava/lang/String;)Ljava/lang/StringBuilder;
    //   3973: invokevirtual 120	java/lang/StringBuilder:toString	()Ljava/lang/String;
    //   3976: astore_3
    //   3977: aload_3
    //   3978: astore_1
    //   3979: ldc_w 408
    //   3982: ldc_w 631
    //   3985: iconst_1
    //   3986: anewarray 4	java/lang/Object
    //   3989: dup
    //   3990: iconst_0
    //   3991: aload_1
    //   3992: aastore
    //   3993: invokestatic 633	com/tencent/mm/sdk/platformtools/ab:i	(Ljava/lang/String;Ljava/lang/String;[Ljava/lang/Object;)V
    //   3996: new 219	android/content/Intent
    //   3999: dup
    //   4000: ldc_w 478
    //   4003: aload_1
    //   4004: invokestatic 484	android/net/Uri:parse	(Ljava/lang/String;)Landroid/net/Uri;
    //   4007: invokespecial 487	android/content/Intent:<init>	(Ljava/lang/String;Landroid/net/Uri;)V
    //   4010: astore_1
    //   4011: aload_1
    //   4012: ldc_w 634
    //   4015: invokevirtual 638	android/content/Intent:addFlags	(I)Landroid/content/Intent;
    //   4018: pop
    //   4019: aload 4
    //   4021: invokevirtual 52	com/tencent/mm/plugin/webview/ui/tools/j:cZv	()Lcom/tencent/mm/plugin/webview/ui/tools/WebViewUI;
    //   4024: aload_1
    //   4025: invokestatic 642	com/tencent/mm/sdk/platformtools/bo:k	(Landroid/content/Context;Landroid/content/Intent;)Z
    //   4028: ifeq +69 -> 4097
    //   4031: aload 4
    //   4033: invokevirtual 52	com/tencent/mm/plugin/webview/ui/tools/j:cZv	()Lcom/tencent/mm/plugin/webview/ui/tools/WebViewUI;
    //   4036: aload_1
    //   4037: invokevirtual 500	com/tencent/mm/plugin/webview/ui/tools/WebViewUI:startActivity	(Landroid/content/Intent;)V
    //   4040: sipush 7652
    //   4043: invokestatic 129	com/tencent/matrix/trace/core/AppMethodBeat:o	(I)V
    //   4046: goto -3907 -> 139
    //   4049: astore_1
    //   4050: ldc_w 408
    //   4053: ldc_w 644
    //   4056: iconst_1
    //   4057: anewarray 4	java/lang/Object
    //   4060: dup
    //   4061: iconst_0
    //   4062: aload_1
    //   4063: invokevirtual 505	java/lang/Exception:getMessage	()Ljava/lang/String;
    //   4066: aastore
    //   4067: invokestatic 508	com/tencent/mm/sdk/platformtools/ab:e	(Ljava/lang/String;Ljava/lang/String;[Ljava/lang/Object;)V
    //   4070: goto -137 -> 3933
    //   4073: astore_3
    //   4074: ldc_w 408
    //   4077: ldc_w 646
    //   4080: iconst_1
    //   4081: anewarray 4	java/lang/Object
    //   4084: dup
    //   4085: iconst_0
    //   4086: aload_3
    //   4087: invokevirtual 505	java/lang/Exception:getMessage	()Ljava/lang/String;
    //   4090: aastore
    //   4091: invokestatic 508	com/tencent/mm/sdk/platformtools/ab:e	(Ljava/lang/String;Ljava/lang/String;[Ljava/lang/Object;)V
    //   4094: goto -115 -> 3979
    //   4097: ldc_w 408
    //   4100: ldc_w 648
    //   4103: invokestatic 413	com/tencent/mm/sdk/platformtools/ab:e	(Ljava/lang/String;Ljava/lang/String;)V
    //   4106: sipush 7652
    //   4109: invokestatic 129	com/tencent/matrix/trace/core/AppMethodBeat:o	(I)V
    //   4112: goto -3973 -> 139
    //   4115: aload_0
    //   4116: getfield 17	com/tencent/mm/plugin/webview/ui/tools/j$10:utN	Lcom/tencent/mm/plugin/webview/ui/tools/j;
    //   4119: invokevirtual 52	com/tencent/mm/plugin/webview/ui/tools/j:cZv	()Lcom/tencent/mm/plugin/webview/ui/tools/WebViewUI;
    //   4122: aload_0
    //   4123: getfield 17	com/tencent/mm/plugin/webview/ui/tools/j$10:utN	Lcom/tencent/mm/plugin/webview/ui/tools/j;
    //   4126: invokevirtual 52	com/tencent/mm/plugin/webview/ui/tools/j:cZv	()Lcom/tencent/mm/plugin/webview/ui/tools/WebViewUI;
    //   4129: getfield 231	com/tencent/mm/plugin/webview/ui/tools/WebViewUI:icz	Lcom/tencent/mm/plugin/webview/ui/tools/k;
    //   4132: invokevirtual 237	com/tencent/mm/plugin/webview/ui/tools/k:cZT	()Lcom/tencent/mm/protocal/GeneralControlWrapper;
    //   4135: invokevirtual 242	com/tencent/mm/protocal/GeneralControlWrapper:dmm	()Z
    //   4138: putfield 245	com/tencent/mm/plugin/webview/ui/tools/WebViewUI:uvr	Z
    //   4141: aload_0
    //   4142: getfield 17	com/tencent/mm/plugin/webview/ui/tools/j$10:utN	Lcom/tencent/mm/plugin/webview/ui/tools/j;
    //   4145: invokevirtual 52	com/tencent/mm/plugin/webview/ui/tools/j:cZv	()Lcom/tencent/mm/plugin/webview/ui/tools/WebViewUI;
    //   4148: getfield 137	com/tencent/mm/plugin/webview/ui/tools/WebViewUI:ulI	Lcom/tencent/mm/plugin/webview/model/aq;
    //   4151: invokevirtual 143	com/tencent/mm/plugin/webview/model/aq:cYc	()Lcom/tencent/mm/plugin/webview/model/aq$e;
    //   4154: astore_1
    //   4155: aload_1
    //   4156: iconst_3
    //   4157: anewarray 4	java/lang/Object
    //   4160: dup
    //   4161: iconst_0
    //   4162: aload_0
    //   4163: getfield 17	com/tencent/mm/plugin/webview/ui/tools/j$10:utN	Lcom/tencent/mm/plugin/webview/ui/tools/j;
    //   4166: invokevirtual 52	com/tencent/mm/plugin/webview/ui/tools/j:cZv	()Lcom/tencent/mm/plugin/webview/ui/tools/WebViewUI;
    //   4169: getfield 146	com/tencent/mm/plugin/webview/ui/tools/WebViewUI:cOG	Ljava/lang/String;
    //   4172: aastore
    //   4173: dup
    //   4174: iconst_1
    //   4175: bipush 17
    //   4177: invokestatic 152	java/lang/Integer:valueOf	(I)Ljava/lang/Integer;
    //   4180: aastore
    //   4181: dup
    //   4182: iconst_2
    //   4183: iconst_1
    //   4184: invokestatic 152	java/lang/Integer:valueOf	(I)Ljava/lang/Integer;
    //   4187: aastore
    //   4188: putfield 158	com/tencent/mm/plugin/webview/model/aq$e:une	[Ljava/lang/Object;
    //   4191: aload_1
    //   4192: aload_0
    //   4193: getfield 17	com/tencent/mm/plugin/webview/ui/tools/j$10:utN	Lcom/tencent/mm/plugin/webview/ui/tools/j;
    //   4196: invokevirtual 52	com/tencent/mm/plugin/webview/ui/tools/j:cZv	()Lcom/tencent/mm/plugin/webview/ui/tools/WebViewUI;
    //   4199: getfield 162	com/tencent/mm/plugin/webview/ui/tools/WebViewUI:icy	Lcom/tencent/mm/plugin/webview/stub/d;
    //   4202: invokevirtual 165	com/tencent/mm/plugin/webview/model/aq$e:b	(Lcom/tencent/mm/plugin/webview/stub/d;)V
    //   4205: aload_0
    //   4206: getfield 17	com/tencent/mm/plugin/webview/ui/tools/j$10:utN	Lcom/tencent/mm/plugin/webview/ui/tools/j;
    //   4209: astore_1
    //   4210: aload_1
    //   4211: invokevirtual 52	com/tencent/mm/plugin/webview/ui/tools/j:cZv	()Lcom/tencent/mm/plugin/webview/ui/tools/WebViewUI;
    //   4214: getfield 58	com/tencent/mm/plugin/webview/ui/tools/WebViewUI:uhz	Lcom/tencent/mm/plugin/webview/ui/tools/jsapi/d;
    //   4217: ldc_w 650
    //   4220: iconst_1
    //   4221: invokevirtual 527	com/tencent/mm/plugin/webview/ui/tools/jsapi/d:bJ	(Ljava/lang/String;Z)V
    //   4224: aload_1
    //   4225: invokevirtual 52	com/tencent/mm/plugin/webview/ui/tools/j:cZv	()Lcom/tencent/mm/plugin/webview/ui/tools/WebViewUI;
    //   4228: getfield 58	com/tencent/mm/plugin/webview/ui/tools/WebViewUI:uhz	Lcom/tencent/mm/plugin/webview/ui/tools/jsapi/d;
    //   4231: astore_1
    //   4232: aload_1
    //   4233: getfield 530	com/tencent/mm/plugin/webview/ui/tools/jsapi/d:ready	Z
    //   4236: ifne +20 -> 4256
    //   4239: ldc 60
    //   4241: ldc_w 652
    //   4244: invokestatic 413	com/tencent/mm/sdk/platformtools/ab:e	(Ljava/lang/String;Ljava/lang/String;)V
    //   4247: sipush 7652
    //   4250: invokestatic 129	com/tencent/matrix/trace/core/AppMethodBeat:o	(I)V
    //   4253: goto -4114 -> 139
    //   4256: aload_1
    //   4257: iconst_1
    //   4258: invokevirtual 656	com/tencent/mm/plugin/webview/ui/tools/jsapi/d:JL	(I)Landroid/os/Bundle;
    //   4261: astore_3
    //   4262: aload_3
    //   4263: ifnull +31 -> 4294
    //   4266: aload_3
    //   4267: ldc_w 658
    //   4270: iconst_0
    //   4271: invokevirtual 662	android/os/Bundle:getBoolean	(Ljava/lang/String;Z)Z
    //   4274: ifeq +20 -> 4294
    //   4277: aload_1
    //   4278: aload_3
    //   4279: ldc_w 650
    //   4282: invokevirtual 666	com/tencent/mm/plugin/webview/ui/tools/jsapi/d:h	(Landroid/os/Bundle;Ljava/lang/String;)V
    //   4285: sipush 7652
    //   4288: invokestatic 129	com/tencent/matrix/trace/core/AppMethodBeat:o	(I)V
    //   4291: goto -4152 -> 139
    //   4294: ldc_w 668
    //   4297: new 69	java/util/HashMap
    //   4300: dup
    //   4301: invokespecial 70	java/util/HashMap:<init>	()V
    //   4304: aload_1
    //   4305: getfield 90	com/tencent/mm/plugin/webview/ui/tools/jsapi/d:uFv	Z
    //   4308: aload_1
    //   4309: getfield 93	com/tencent/mm/plugin/webview/ui/tools/jsapi/d:uFw	Ljava/lang/String;
    //   4312: invokestatic 99	com/tencent/mm/plugin/webview/ui/tools/jsapi/i$a:b	(Ljava/lang/String;Ljava/util/Map;ZLjava/lang/String;)Ljava/lang/String;
    //   4315: astore_3
    //   4316: aload_1
    //   4317: getfield 103	com/tencent/mm/plugin/webview/ui/tools/jsapi/d:uFo	Lcom/tencent/mm/ui/widget/MMWebView;
    //   4320: new 105	java/lang/StringBuilder
    //   4323: dup
    //   4324: ldc 107
    //   4326: invokespecial 110	java/lang/StringBuilder:<init>	(Ljava/lang/String;)V
    //   4329: aload_3
    //   4330: invokevirtual 114	java/lang/StringBuilder:append	(Ljava/lang/String;)Ljava/lang/StringBuilder;
    //   4333: ldc 116
    //   4335: invokevirtual 114	java/lang/StringBuilder:append	(Ljava/lang/String;)Ljava/lang/StringBuilder;
    //   4338: invokevirtual 120	java/lang/StringBuilder:toString	()Ljava/lang/String;
    //   4341: aconst_null
    //   4342: invokevirtual 126	com/tencent/mm/ui/widget/MMWebView:evaluateJavascript	(Ljava/lang/String;Landroid/webkit/ValueCallback;)V
    //   4345: sipush 7652
    //   4348: invokestatic 129	com/tencent/matrix/trace/core/AppMethodBeat:o	(I)V
    //   4351: goto -4212 -> 139
    //   4354: aload_0
    //   4355: getfield 17	com/tencent/mm/plugin/webview/ui/tools/j$10:utN	Lcom/tencent/mm/plugin/webview/ui/tools/j;
    //   4358: invokevirtual 52	com/tencent/mm/plugin/webview/ui/tools/j:cZv	()Lcom/tencent/mm/plugin/webview/ui/tools/WebViewUI;
    //   4361: getfield 137	com/tencent/mm/plugin/webview/ui/tools/WebViewUI:ulI	Lcom/tencent/mm/plugin/webview/model/aq;
    //   4364: invokevirtual 143	com/tencent/mm/plugin/webview/model/aq:cYc	()Lcom/tencent/mm/plugin/webview/model/aq$e;
    //   4367: astore_1
    //   4368: aload_1
    //   4369: iconst_3
    //   4370: anewarray 4	java/lang/Object
    //   4373: dup
    //   4374: iconst_0
    //   4375: aload_0
    //   4376: getfield 17	com/tencent/mm/plugin/webview/ui/tools/j$10:utN	Lcom/tencent/mm/plugin/webview/ui/tools/j;
    //   4379: invokevirtual 52	com/tencent/mm/plugin/webview/ui/tools/j:cZv	()Lcom/tencent/mm/plugin/webview/ui/tools/WebViewUI;
    //   4382: getfield 146	com/tencent/mm/plugin/webview/ui/tools/WebViewUI:cOG	Ljava/lang/String;
    //   4385: aastore
    //   4386: dup
    //   4387: iconst_1
    //   4388: bipush 18
    //   4390: invokestatic 152	java/lang/Integer:valueOf	(I)Ljava/lang/Integer;
    //   4393: aastore
    //   4394: dup
    //   4395: iconst_2
    //   4396: iconst_1
    //   4397: invokestatic 152	java/lang/Integer:valueOf	(I)Ljava/lang/Integer;
    //   4400: aastore
    //   4401: putfield 158	com/tencent/mm/plugin/webview/model/aq$e:une	[Ljava/lang/Object;
    //   4404: aload_1
    //   4405: aload_0
    //   4406: getfield 17	com/tencent/mm/plugin/webview/ui/tools/j$10:utN	Lcom/tencent/mm/plugin/webview/ui/tools/j;
    //   4409: invokevirtual 52	com/tencent/mm/plugin/webview/ui/tools/j:cZv	()Lcom/tencent/mm/plugin/webview/ui/tools/WebViewUI;
    //   4412: getfield 162	com/tencent/mm/plugin/webview/ui/tools/WebViewUI:icy	Lcom/tencent/mm/plugin/webview/stub/d;
    //   4415: invokevirtual 165	com/tencent/mm/plugin/webview/model/aq$e:b	(Lcom/tencent/mm/plugin/webview/stub/d;)V
    //   4418: aload_0
    //   4419: getfield 17	com/tencent/mm/plugin/webview/ui/tools/j$10:utN	Lcom/tencent/mm/plugin/webview/ui/tools/j;
    //   4422: astore_1
    //   4423: aload_1
    //   4424: invokevirtual 52	com/tencent/mm/plugin/webview/ui/tools/j:cZv	()Lcom/tencent/mm/plugin/webview/ui/tools/WebViewUI;
    //   4427: getfield 58	com/tencent/mm/plugin/webview/ui/tools/WebViewUI:uhz	Lcom/tencent/mm/plugin/webview/ui/tools/jsapi/d;
    //   4430: ldc_w 670
    //   4433: iconst_1
    //   4434: invokevirtual 527	com/tencent/mm/plugin/webview/ui/tools/jsapi/d:bJ	(Ljava/lang/String;Z)V
    //   4437: aload_1
    //   4438: invokevirtual 52	com/tencent/mm/plugin/webview/ui/tools/j:cZv	()Lcom/tencent/mm/plugin/webview/ui/tools/WebViewUI;
    //   4441: getfield 58	com/tencent/mm/plugin/webview/ui/tools/WebViewUI:uhz	Lcom/tencent/mm/plugin/webview/ui/tools/jsapi/d;
    //   4444: astore_1
    //   4445: aload_1
    //   4446: getfield 530	com/tencent/mm/plugin/webview/ui/tools/jsapi/d:ready	Z
    //   4449: ifne +20 -> 4469
    //   4452: ldc 60
    //   4454: ldc_w 672
    //   4457: invokestatic 413	com/tencent/mm/sdk/platformtools/ab:e	(Ljava/lang/String;Ljava/lang/String;)V
    //   4460: sipush 7652
    //   4463: invokestatic 129	com/tencent/matrix/trace/core/AppMethodBeat:o	(I)V
    //   4466: goto -4327 -> 139
    //   4469: ldc_w 674
    //   4472: new 69	java/util/HashMap
    //   4475: dup
    //   4476: invokespecial 70	java/util/HashMap:<init>	()V
    //   4479: aload_1
    //   4480: getfield 90	com/tencent/mm/plugin/webview/ui/tools/jsapi/d:uFv	Z
    //   4483: aload_1
    //   4484: getfield 93	com/tencent/mm/plugin/webview/ui/tools/jsapi/d:uFw	Ljava/lang/String;
    //   4487: invokestatic 99	com/tencent/mm/plugin/webview/ui/tools/jsapi/i$a:b	(Ljava/lang/String;Ljava/util/Map;ZLjava/lang/String;)Ljava/lang/String;
    //   4490: astore_3
    //   4491: aload_1
    //   4492: getfield 103	com/tencent/mm/plugin/webview/ui/tools/jsapi/d:uFo	Lcom/tencent/mm/ui/widget/MMWebView;
    //   4495: new 105	java/lang/StringBuilder
    //   4498: dup
    //   4499: ldc 107
    //   4501: invokespecial 110	java/lang/StringBuilder:<init>	(Ljava/lang/String;)V
    //   4504: aload_3
    //   4505: invokevirtual 114	java/lang/StringBuilder:append	(Ljava/lang/String;)Ljava/lang/StringBuilder;
    //   4508: ldc 116
    //   4510: invokevirtual 114	java/lang/StringBuilder:append	(Ljava/lang/String;)Ljava/lang/StringBuilder;
    //   4513: invokevirtual 120	java/lang/StringBuilder:toString	()Ljava/lang/String;
    //   4516: aconst_null
    //   4517: invokevirtual 126	com/tencent/mm/ui/widget/MMWebView:evaluateJavascript	(Ljava/lang/String;Landroid/webkit/ValueCallback;)V
    //   4520: sipush 7652
    //   4523: invokestatic 129	com/tencent/matrix/trace/core/AppMethodBeat:o	(I)V
    //   4526: goto -4387 -> 139
    //   4529: aload_0
    //   4530: getfield 17	com/tencent/mm/plugin/webview/ui/tools/j$10:utN	Lcom/tencent/mm/plugin/webview/ui/tools/j;
    //   4533: invokevirtual 52	com/tencent/mm/plugin/webview/ui/tools/j:cZv	()Lcom/tencent/mm/plugin/webview/ui/tools/WebViewUI;
    //   4536: aload_0
    //   4537: getfield 17	com/tencent/mm/plugin/webview/ui/tools/j$10:utN	Lcom/tencent/mm/plugin/webview/ui/tools/j;
    //   4540: invokevirtual 52	com/tencent/mm/plugin/webview/ui/tools/j:cZv	()Lcom/tencent/mm/plugin/webview/ui/tools/WebViewUI;
    //   4543: getfield 231	com/tencent/mm/plugin/webview/ui/tools/WebViewUI:icz	Lcom/tencent/mm/plugin/webview/ui/tools/k;
    //   4546: invokevirtual 237	com/tencent/mm/plugin/webview/ui/tools/k:cZT	()Lcom/tencent/mm/protocal/GeneralControlWrapper;
    //   4549: invokevirtual 242	com/tencent/mm/protocal/GeneralControlWrapper:dmm	()Z
    //   4552: putfield 245	com/tencent/mm/plugin/webview/ui/tools/WebViewUI:uvr	Z
    //   4555: aload_0
    //   4556: getfield 17	com/tencent/mm/plugin/webview/ui/tools/j$10:utN	Lcom/tencent/mm/plugin/webview/ui/tools/j;
    //   4559: invokevirtual 52	com/tencent/mm/plugin/webview/ui/tools/j:cZv	()Lcom/tencent/mm/plugin/webview/ui/tools/WebViewUI;
    //   4562: getfield 137	com/tencent/mm/plugin/webview/ui/tools/WebViewUI:ulI	Lcom/tencent/mm/plugin/webview/model/aq;
    //   4565: invokevirtual 143	com/tencent/mm/plugin/webview/model/aq:cYc	()Lcom/tencent/mm/plugin/webview/model/aq$e;
    //   4568: astore_1
    //   4569: aload_1
    //   4570: iconst_3
    //   4571: anewarray 4	java/lang/Object
    //   4574: dup
    //   4575: iconst_0
    //   4576: aload_0
    //   4577: getfield 17	com/tencent/mm/plugin/webview/ui/tools/j$10:utN	Lcom/tencent/mm/plugin/webview/ui/tools/j;
    //   4580: invokevirtual 52	com/tencent/mm/plugin/webview/ui/tools/j:cZv	()Lcom/tencent/mm/plugin/webview/ui/tools/WebViewUI;
    //   4583: getfield 146	com/tencent/mm/plugin/webview/ui/tools/WebViewUI:cOG	Ljava/lang/String;
    //   4586: aastore
    //   4587: dup
    //   4588: iconst_1
    //   4589: bipush 24
    //   4591: invokestatic 152	java/lang/Integer:valueOf	(I)Ljava/lang/Integer;
    //   4594: aastore
    //   4595: dup
    //   4596: iconst_2
    //   4597: iconst_1
    //   4598: invokestatic 152	java/lang/Integer:valueOf	(I)Ljava/lang/Integer;
    //   4601: aastore
    //   4602: putfield 158	com/tencent/mm/plugin/webview/model/aq$e:une	[Ljava/lang/Object;
    //   4605: aload_1
    //   4606: aload_0
    //   4607: getfield 17	com/tencent/mm/plugin/webview/ui/tools/j$10:utN	Lcom/tencent/mm/plugin/webview/ui/tools/j;
    //   4610: invokevirtual 52	com/tencent/mm/plugin/webview/ui/tools/j:cZv	()Lcom/tencent/mm/plugin/webview/ui/tools/WebViewUI;
    //   4613: getfield 162	com/tencent/mm/plugin/webview/ui/tools/WebViewUI:icy	Lcom/tencent/mm/plugin/webview/stub/d;
    //   4616: invokevirtual 165	com/tencent/mm/plugin/webview/model/aq$e:b	(Lcom/tencent/mm/plugin/webview/stub/d;)V
    //   4619: aload_0
    //   4620: getfield 17	com/tencent/mm/plugin/webview/ui/tools/j$10:utN	Lcom/tencent/mm/plugin/webview/ui/tools/j;
    //   4623: astore_1
    //   4624: aload_1
    //   4625: invokevirtual 52	com/tencent/mm/plugin/webview/ui/tools/j:cZv	()Lcom/tencent/mm/plugin/webview/ui/tools/WebViewUI;
    //   4628: getfield 58	com/tencent/mm/plugin/webview/ui/tools/WebViewUI:uhz	Lcom/tencent/mm/plugin/webview/ui/tools/jsapi/d;
    //   4631: ldc_w 676
    //   4634: iconst_1
    //   4635: invokevirtual 527	com/tencent/mm/plugin/webview/ui/tools/jsapi/d:bJ	(Ljava/lang/String;Z)V
    //   4638: aload_1
    //   4639: invokevirtual 52	com/tencent/mm/plugin/webview/ui/tools/j:cZv	()Lcom/tencent/mm/plugin/webview/ui/tools/WebViewUI;
    //   4642: getfield 58	com/tencent/mm/plugin/webview/ui/tools/WebViewUI:uhz	Lcom/tencent/mm/plugin/webview/ui/tools/jsapi/d;
    //   4645: astore_1
    //   4646: aload_1
    //   4647: getfield 530	com/tencent/mm/plugin/webview/ui/tools/jsapi/d:ready	Z
    //   4650: ifne +20 -> 4670
    //   4653: ldc 60
    //   4655: ldc_w 678
    //   4658: invokestatic 413	com/tencent/mm/sdk/platformtools/ab:e	(Ljava/lang/String;Ljava/lang/String;)V
    //   4661: sipush 7652
    //   4664: invokestatic 129	com/tencent/matrix/trace/core/AppMethodBeat:o	(I)V
    //   4667: goto -4528 -> 139
    //   4670: aload_1
    //   4671: iconst_1
    //   4672: invokevirtual 656	com/tencent/mm/plugin/webview/ui/tools/jsapi/d:JL	(I)Landroid/os/Bundle;
    //   4675: astore_3
    //   4676: aload_3
    //   4677: ifnull +31 -> 4708
    //   4680: aload_3
    //   4681: ldc_w 658
    //   4684: iconst_0
    //   4685: invokevirtual 662	android/os/Bundle:getBoolean	(Ljava/lang/String;Z)Z
    //   4688: ifeq +20 -> 4708
    //   4691: aload_1
    //   4692: aload_3
    //   4693: ldc_w 676
    //   4696: invokevirtual 666	com/tencent/mm/plugin/webview/ui/tools/jsapi/d:h	(Landroid/os/Bundle;Ljava/lang/String;)V
    //   4699: sipush 7652
    //   4702: invokestatic 129	com/tencent/matrix/trace/core/AppMethodBeat:o	(I)V
    //   4705: goto -4566 -> 139
    //   4708: ldc_w 680
    //   4711: new 69	java/util/HashMap
    //   4714: dup
    //   4715: invokespecial 70	java/util/HashMap:<init>	()V
    //   4718: aload_1
    //   4719: getfield 90	com/tencent/mm/plugin/webview/ui/tools/jsapi/d:uFv	Z
    //   4722: aload_1
    //   4723: getfield 93	com/tencent/mm/plugin/webview/ui/tools/jsapi/d:uFw	Ljava/lang/String;
    //   4726: invokestatic 99	com/tencent/mm/plugin/webview/ui/tools/jsapi/i$a:b	(Ljava/lang/String;Ljava/util/Map;ZLjava/lang/String;)Ljava/lang/String;
    //   4729: astore_3
    //   4730: aload_1
    //   4731: getfield 103	com/tencent/mm/plugin/webview/ui/tools/jsapi/d:uFo	Lcom/tencent/mm/ui/widget/MMWebView;
    //   4734: new 105	java/lang/StringBuilder
    //   4737: dup
    //   4738: ldc 107
    //   4740: invokespecial 110	java/lang/StringBuilder:<init>	(Ljava/lang/String;)V
    //   4743: aload_3
    //   4744: invokevirtual 114	java/lang/StringBuilder:append	(Ljava/lang/String;)Ljava/lang/StringBuilder;
    //   4747: ldc 116
    //   4749: invokevirtual 114	java/lang/StringBuilder:append	(Ljava/lang/String;)Ljava/lang/StringBuilder;
    //   4752: invokevirtual 120	java/lang/StringBuilder:toString	()Ljava/lang/String;
    //   4755: aconst_null
    //   4756: invokevirtual 126	com/tencent/mm/ui/widget/MMWebView:evaluateJavascript	(Ljava/lang/String;Landroid/webkit/ValueCallback;)V
    //   4759: sipush 7652
    //   4762: invokestatic 129	com/tencent/matrix/trace/core/AppMethodBeat:o	(I)V
    //   4765: goto -4626 -> 139
    //   4768: aload_0
    //   4769: getfield 17	com/tencent/mm/plugin/webview/ui/tools/j$10:utN	Lcom/tencent/mm/plugin/webview/ui/tools/j;
    //   4772: invokevirtual 52	com/tencent/mm/plugin/webview/ui/tools/j:cZv	()Lcom/tencent/mm/plugin/webview/ui/tools/WebViewUI;
    //   4775: getfield 137	com/tencent/mm/plugin/webview/ui/tools/WebViewUI:ulI	Lcom/tencent/mm/plugin/webview/model/aq;
    //   4778: invokevirtual 143	com/tencent/mm/plugin/webview/model/aq:cYc	()Lcom/tencent/mm/plugin/webview/model/aq$e;
    //   4781: astore_1
    //   4782: aload_1
    //   4783: iconst_3
    //   4784: anewarray 4	java/lang/Object
    //   4787: dup
    //   4788: iconst_0
    //   4789: aload_0
    //   4790: getfield 17	com/tencent/mm/plugin/webview/ui/tools/j$10:utN	Lcom/tencent/mm/plugin/webview/ui/tools/j;
    //   4793: invokevirtual 52	com/tencent/mm/plugin/webview/ui/tools/j:cZv	()Lcom/tencent/mm/plugin/webview/ui/tools/WebViewUI;
    //   4796: getfield 146	com/tencent/mm/plugin/webview/ui/tools/WebViewUI:cOG	Ljava/lang/String;
    //   4799: aastore
    //   4800: dup
    //   4801: iconst_1
    //   4802: bipush 14
    //   4804: invokestatic 152	java/lang/Integer:valueOf	(I)Ljava/lang/Integer;
    //   4807: aastore
    //   4808: dup
    //   4809: iconst_2
    //   4810: iconst_1
    //   4811: invokestatic 152	java/lang/Integer:valueOf	(I)Ljava/lang/Integer;
    //   4814: aastore
    //   4815: putfield 158	com/tencent/mm/plugin/webview/model/aq$e:une	[Ljava/lang/Object;
    //   4818: aload_1
    //   4819: aload_0
    //   4820: getfield 17	com/tencent/mm/plugin/webview/ui/tools/j$10:utN	Lcom/tencent/mm/plugin/webview/ui/tools/j;
    //   4823: invokevirtual 52	com/tencent/mm/plugin/webview/ui/tools/j:cZv	()Lcom/tencent/mm/plugin/webview/ui/tools/WebViewUI;
    //   4826: getfield 162	com/tencent/mm/plugin/webview/ui/tools/WebViewUI:icy	Lcom/tencent/mm/plugin/webview/stub/d;
    //   4829: invokevirtual 165	com/tencent/mm/plugin/webview/model/aq$e:b	(Lcom/tencent/mm/plugin/webview/stub/d;)V
    //   4832: aload_0
    //   4833: getfield 17	com/tencent/mm/plugin/webview/ui/tools/j$10:utN	Lcom/tencent/mm/plugin/webview/ui/tools/j;
    //   4836: astore_1
    //   4837: aload_1
    //   4838: invokevirtual 52	com/tencent/mm/plugin/webview/ui/tools/j:cZv	()Lcom/tencent/mm/plugin/webview/ui/tools/WebViewUI;
    //   4841: getfield 58	com/tencent/mm/plugin/webview/ui/tools/WebViewUI:uhz	Lcom/tencent/mm/plugin/webview/ui/tools/jsapi/d;
    //   4844: ldc_w 605
    //   4847: iconst_1
    //   4848: invokevirtual 527	com/tencent/mm/plugin/webview/ui/tools/jsapi/d:bJ	(Ljava/lang/String;Z)V
    //   4851: aload_1
    //   4852: invokevirtual 52	com/tencent/mm/plugin/webview/ui/tools/j:cZv	()Lcom/tencent/mm/plugin/webview/ui/tools/WebViewUI;
    //   4855: getfield 58	com/tencent/mm/plugin/webview/ui/tools/WebViewUI:uhz	Lcom/tencent/mm/plugin/webview/ui/tools/jsapi/d;
    //   4858: astore_1
    //   4859: aload_1
    //   4860: getfield 530	com/tencent/mm/plugin/webview/ui/tools/jsapi/d:ready	Z
    //   4863: ifne +20 -> 4883
    //   4866: ldc 60
    //   4868: ldc_w 682
    //   4871: invokestatic 413	com/tencent/mm/sdk/platformtools/ab:e	(Ljava/lang/String;Ljava/lang/String;)V
    //   4874: sipush 7652
    //   4877: invokestatic 129	com/tencent/matrix/trace/core/AppMethodBeat:o	(I)V
    //   4880: goto -4741 -> 139
    //   4883: ldc_w 609
    //   4886: new 69	java/util/HashMap
    //   4889: dup
    //   4890: invokespecial 70	java/util/HashMap:<init>	()V
    //   4893: aload_1
    //   4894: getfield 90	com/tencent/mm/plugin/webview/ui/tools/jsapi/d:uFv	Z
    //   4897: aload_1
    //   4898: getfield 93	com/tencent/mm/plugin/webview/ui/tools/jsapi/d:uFw	Ljava/lang/String;
    //   4901: invokestatic 99	com/tencent/mm/plugin/webview/ui/tools/jsapi/i$a:b	(Ljava/lang/String;Ljava/util/Map;ZLjava/lang/String;)Ljava/lang/String;
    //   4904: astore_3
    //   4905: aload_1
    //   4906: getfield 103	com/tencent/mm/plugin/webview/ui/tools/jsapi/d:uFo	Lcom/tencent/mm/ui/widget/MMWebView;
    //   4909: new 105	java/lang/StringBuilder
    //   4912: dup
    //   4913: ldc 107
    //   4915: invokespecial 110	java/lang/StringBuilder:<init>	(Ljava/lang/String;)V
    //   4918: aload_3
    //   4919: invokevirtual 114	java/lang/StringBuilder:append	(Ljava/lang/String;)Ljava/lang/StringBuilder;
    //   4922: ldc 116
    //   4924: invokevirtual 114	java/lang/StringBuilder:append	(Ljava/lang/String;)Ljava/lang/StringBuilder;
    //   4927: invokevirtual 120	java/lang/StringBuilder:toString	()Ljava/lang/String;
    //   4930: aconst_null
    //   4931: invokevirtual 126	com/tencent/mm/ui/widget/MMWebView:evaluateJavascript	(Ljava/lang/String;Landroid/webkit/ValueCallback;)V
    //   4934: aload_1
    //   4935: getfield 341	com/tencent/mm/plugin/webview/ui/tools/jsapi/d:icy	Lcom/tencent/mm/plugin/webview/stub/d;
    //   4938: ldc_w 611
    //   4941: ldc_w 684
    //   4944: aload_1
    //   4945: getfield 345	com/tencent/mm/plugin/webview/ui/tools/jsapi/d:uqj	I
    //   4948: invokeinterface 617 4 0
    //   4953: sipush 7652
    //   4956: invokestatic 129	com/tencent/matrix/trace/core/AppMethodBeat:o	(I)V
    //   4959: goto -4820 -> 139
    //   4962: astore_1
    //   4963: ldc 60
    //   4965: new 105	java/lang/StringBuilder
    //   4968: dup
    //   4969: ldc_w 619
    //   4972: invokespecial 110	java/lang/StringBuilder:<init>	(Ljava/lang/String;)V
    //   4975: aload_1
    //   4976: invokevirtual 505	java/lang/Exception:getMessage	()Ljava/lang/String;
    //   4979: invokevirtual 114	java/lang/StringBuilder:append	(Ljava/lang/String;)Ljava/lang/StringBuilder;
    //   4982: invokevirtual 120	java/lang/StringBuilder:toString	()Ljava/lang/String;
    //   4985: invokestatic 368	com/tencent/mm/sdk/platformtools/ab:w	(Ljava/lang/String;Ljava/lang/String;)V
    //   4988: sipush 7652
    //   4991: invokestatic 129	com/tencent/matrix/trace/core/AppMethodBeat:o	(I)V
    //   4994: goto -4855 -> 139
    //   4997: aload_0
    //   4998: getfield 17	com/tencent/mm/plugin/webview/ui/tools/j$10:utN	Lcom/tencent/mm/plugin/webview/ui/tools/j;
    //   5001: invokevirtual 52	com/tencent/mm/plugin/webview/ui/tools/j:cZv	()Lcom/tencent/mm/plugin/webview/ui/tools/WebViewUI;
    //   5004: getfield 137	com/tencent/mm/plugin/webview/ui/tools/WebViewUI:ulI	Lcom/tencent/mm/plugin/webview/model/aq;
    //   5007: invokevirtual 143	com/tencent/mm/plugin/webview/model/aq:cYc	()Lcom/tencent/mm/plugin/webview/model/aq$e;
    //   5010: astore_1
    //   5011: aload_1
    //   5012: iconst_3
    //   5013: anewarray 4	java/lang/Object
    //   5016: dup
    //   5017: iconst_0
    //   5018: aload_0
    //   5019: getfield 17	com/tencent/mm/plugin/webview/ui/tools/j$10:utN	Lcom/tencent/mm/plugin/webview/ui/tools/j;
    //   5022: invokevirtual 52	com/tencent/mm/plugin/webview/ui/tools/j:cZv	()Lcom/tencent/mm/plugin/webview/ui/tools/WebViewUI;
    //   5025: getfield 146	com/tencent/mm/plugin/webview/ui/tools/WebViewUI:cOG	Ljava/lang/String;
    //   5028: aastore
    //   5029: dup
    //   5030: iconst_1
    //   5031: bipush 16
    //   5033: invokestatic 152	java/lang/Integer:valueOf	(I)Ljava/lang/Integer;
    //   5036: aastore
    //   5037: dup
    //   5038: iconst_2
    //   5039: iconst_1
    //   5040: invokestatic 152	java/lang/Integer:valueOf	(I)Ljava/lang/Integer;
    //   5043: aastore
    //   5044: putfield 158	com/tencent/mm/plugin/webview/model/aq$e:une	[Ljava/lang/Object;
    //   5047: aload_1
    //   5048: aload_0
    //   5049: getfield 17	com/tencent/mm/plugin/webview/ui/tools/j$10:utN	Lcom/tencent/mm/plugin/webview/ui/tools/j;
    //   5052: invokevirtual 52	com/tencent/mm/plugin/webview/ui/tools/j:cZv	()Lcom/tencent/mm/plugin/webview/ui/tools/WebViewUI;
    //   5055: getfield 162	com/tencent/mm/plugin/webview/ui/tools/WebViewUI:icy	Lcom/tencent/mm/plugin/webview/stub/d;
    //   5058: invokevirtual 165	com/tencent/mm/plugin/webview/model/aq$e:b	(Lcom/tencent/mm/plugin/webview/stub/d;)V
    //   5061: aload_0
    //   5062: getfield 17	com/tencent/mm/plugin/webview/ui/tools/j$10:utN	Lcom/tencent/mm/plugin/webview/ui/tools/j;
    //   5065: astore_1
    //   5066: new 181	android/os/Bundle
    //   5069: astore_3
    //   5070: aload_3
    //   5071: invokespecial 182	android/os/Bundle:<init>	()V
    //   5074: aload_3
    //   5075: ldc_w 686
    //   5078: ldc_w 688
    //   5081: invokevirtual 187	android/os/Bundle:putString	(Ljava/lang/String;Ljava/lang/String;)V
    //   5084: aload_1
    //   5085: invokevirtual 52	com/tencent/mm/plugin/webview/ui/tools/j:cZv	()Lcom/tencent/mm/plugin/webview/ui/tools/WebViewUI;
    //   5088: getfield 162	com/tencent/mm/plugin/webview/ui/tools/WebViewUI:icy	Lcom/tencent/mm/plugin/webview/stub/d;
    //   5091: bipush 71
    //   5093: aload_3
    //   5094: invokeinterface 192 3 0
    //   5099: ldc_w 688
    //   5102: invokevirtual 692	android/os/Bundle:getStringArrayList	(Ljava/lang/String;)Ljava/util/ArrayList;
    //   5105: astore 4
    //   5107: aload 4
    //   5109: ifnull +13 -> 5122
    //   5112: aload 4
    //   5114: invokevirtual 697	java/util/ArrayList:size	()I
    //   5117: istore_2
    //   5118: iload_2
    //   5119: ifgt +12 -> 5131
    //   5122: sipush 7652
    //   5125: invokestatic 129	com/tencent/matrix/trace/core/AppMethodBeat:o	(I)V
    //   5128: goto -4989 -> 139
    //   5131: aload 4
    //   5133: invokevirtual 697	java/util/ArrayList:size	()I
    //   5136: iconst_1
    //   5137: if_icmpne +25 -> 5162
    //   5140: aload_1
    //   5141: aload 4
    //   5143: iconst_0
    //   5144: invokevirtual 700	java/util/ArrayList:get	(I)Ljava/lang/Object;
    //   5147: checkcast 334	java/lang/String
    //   5150: invokevirtual 201	com/tencent/mm/plugin/webview/ui/tools/j:afF	(Ljava/lang/String;)V
    //   5153: sipush 7652
    //   5156: invokestatic 129	com/tencent/matrix/trace/core/AppMethodBeat:o	(I)V
    //   5159: goto -5020 -> 139
    //   5162: aload_1
    //   5163: aload 4
    //   5165: invokevirtual 704	com/tencent/mm/plugin/webview/ui/tools/j:ec	(Ljava/util/List;)V
    //   5168: new 706	com/tencent/mm/ui/tools/j
    //   5171: astore_3
    //   5172: aload_3
    //   5173: aload_1
    //   5174: invokevirtual 52	com/tencent/mm/plugin/webview/ui/tools/j:cZv	()Lcom/tencent/mm/plugin/webview/ui/tools/WebViewUI;
    //   5177: invokespecial 709	com/tencent/mm/ui/tools/j:<init>	(Landroid/content/Context;)V
    //   5180: aload_3
    //   5181: aload_1
    //   5182: invokevirtual 52	com/tencent/mm/plugin/webview/ui/tools/j:cZv	()Lcom/tencent/mm/plugin/webview/ui/tools/WebViewUI;
    //   5185: getfield 293	com/tencent/mm/plugin/webview/ui/tools/WebViewUI:pzf	Lcom/tencent/mm/ui/widget/MMWebView;
    //   5188: aload_1
    //   5189: invokevirtual 52	com/tencent/mm/plugin/webview/ui/tools/j:cZv	()Lcom/tencent/mm/plugin/webview/ui/tools/WebViewUI;
    //   5192: aconst_null
    //   5193: invokevirtual 712	com/tencent/mm/ui/tools/j:a	(Landroid/view/View;Landroid/view/View$OnCreateContextMenuListener;Lcom/tencent/mm/ui/base/n$d;)V
    //   5196: new 714	com/tencent/mm/plugin/webview/ui/tools/j$16
    //   5199: astore 6
    //   5201: aload 6
    //   5203: aload_1
    //   5204: invokespecial 715	com/tencent/mm/plugin/webview/ui/tools/j$16:<init>	(Lcom/tencent/mm/plugin/webview/ui/tools/j;)V
    //   5207: aload_3
    //   5208: aload 6
    //   5210: putfield 719	com/tencent/mm/ui/tools/j:zFT	Lcom/tencent/mm/ui/base/n$a;
    //   5213: new 721	com/tencent/mm/plugin/webview/ui/tools/j$2
    //   5216: astore 6
    //   5218: aload 6
    //   5220: aload_1
    //   5221: invokespecial 722	com/tencent/mm/plugin/webview/ui/tools/j$2:<init>	(Lcom/tencent/mm/plugin/webview/ui/tools/j;)V
    //   5224: aload_3
    //   5225: aload 6
    //   5227: putfield 726	com/tencent/mm/ui/tools/j:zFU	Lcom/tencent/mm/ui/base/n$b;
    //   5230: aload_1
    //   5231: invokevirtual 52	com/tencent/mm/plugin/webview/ui/tools/j:cZv	()Lcom/tencent/mm/plugin/webview/ui/tools/WebViewUI;
    //   5234: getfield 293	com/tencent/mm/plugin/webview/ui/tools/WebViewUI:pzf	Lcom/tencent/mm/ui/widget/MMWebView;
    //   5237: astore 6
    //   5239: new 728	com/tencent/mm/plugin/webview/ui/tools/j$3
    //   5242: astore 7
    //   5244: aload 7
    //   5246: aload_1
    //   5247: aload 4
    //   5249: invokespecial 731	com/tencent/mm/plugin/webview/ui/tools/j$3:<init>	(Lcom/tencent/mm/plugin/webview/ui/tools/j;Ljava/util/ArrayList;)V
    //   5252: new 733	com/tencent/mm/plugin/webview/ui/tools/j$4
    //   5255: astore 4
    //   5257: aload 4
    //   5259: aload_1
    //   5260: invokespecial 734	com/tencent/mm/plugin/webview/ui/tools/j$4:<init>	(Lcom/tencent/mm/plugin/webview/ui/tools/j;)V
    //   5263: aload_3
    //   5264: aload 6
    //   5266: aload 7
    //   5268: aload 4
    //   5270: invokevirtual 736	com/tencent/mm/ui/tools/j:b	(Landroid/view/View;Landroid/view/View$OnCreateContextMenuListener;Lcom/tencent/mm/ui/base/n$d;)V
    //   5273: aload_3
    //   5274: invokevirtual 740	com/tencent/mm/ui/tools/j:cuu	()Landroid/app/Dialog;
    //   5277: pop
    //   5278: sipush 7652
    //   5281: invokestatic 129	com/tencent/matrix/trace/core/AppMethodBeat:o	(I)V
    //   5284: goto -5145 -> 139
    //   5287: astore_1
    //   5288: ldc_w 408
    //   5291: new 105	java/lang/StringBuilder
    //   5294: dup
    //   5295: ldc_w 742
    //   5298: invokespecial 110	java/lang/StringBuilder:<init>	(Ljava/lang/String;)V
    //   5301: aload_1
    //   5302: invokevirtual 505	java/lang/Exception:getMessage	()Ljava/lang/String;
    //   5305: invokevirtual 114	java/lang/StringBuilder:append	(Ljava/lang/String;)Ljava/lang/StringBuilder;
    //   5308: invokevirtual 120	java/lang/StringBuilder:toString	()Ljava/lang/String;
    //   5311: invokestatic 368	com/tencent/mm/sdk/platformtools/ab:w	(Ljava/lang/String;Ljava/lang/String;)V
    //   5314: sipush 7652
    //   5317: invokestatic 129	com/tencent/matrix/trace/core/AppMethodBeat:o	(I)V
    //   5320: goto -5181 -> 139
    //   5323: aload_0
    //   5324: getfield 17	com/tencent/mm/plugin/webview/ui/tools/j$10:utN	Lcom/tencent/mm/plugin/webview/ui/tools/j;
    //   5327: invokevirtual 52	com/tencent/mm/plugin/webview/ui/tools/j:cZv	()Lcom/tencent/mm/plugin/webview/ui/tools/WebViewUI;
    //   5330: getfield 137	com/tencent/mm/plugin/webview/ui/tools/WebViewUI:ulI	Lcom/tencent/mm/plugin/webview/model/aq;
    //   5333: invokevirtual 143	com/tencent/mm/plugin/webview/model/aq:cYc	()Lcom/tencent/mm/plugin/webview/model/aq$e;
    //   5336: astore_1
    //   5337: aload_1
    //   5338: iconst_3
    //   5339: anewarray 4	java/lang/Object
    //   5342: dup
    //   5343: iconst_0
    //   5344: aload_0
    //   5345: getfield 17	com/tencent/mm/plugin/webview/ui/tools/j$10:utN	Lcom/tencent/mm/plugin/webview/ui/tools/j;
    //   5348: invokevirtual 52	com/tencent/mm/plugin/webview/ui/tools/j:cZv	()Lcom/tencent/mm/plugin/webview/ui/tools/WebViewUI;
    //   5351: getfield 146	com/tencent/mm/plugin/webview/ui/tools/WebViewUI:cOG	Ljava/lang/String;
    //   5354: aastore
    //   5355: dup
    //   5356: iconst_1
    //   5357: bipush 31
    //   5359: invokestatic 152	java/lang/Integer:valueOf	(I)Ljava/lang/Integer;
    //   5362: aastore
    //   5363: dup
    //   5364: iconst_2
    //   5365: iconst_1
    //   5366: invokestatic 152	java/lang/Integer:valueOf	(I)Ljava/lang/Integer;
    //   5369: aastore
    //   5370: putfield 158	com/tencent/mm/plugin/webview/model/aq$e:une	[Ljava/lang/Object;
    //   5373: aload_1
    //   5374: aload_0
    //   5375: getfield 17	com/tencent/mm/plugin/webview/ui/tools/j$10:utN	Lcom/tencent/mm/plugin/webview/ui/tools/j;
    //   5378: invokevirtual 52	com/tencent/mm/plugin/webview/ui/tools/j:cZv	()Lcom/tencent/mm/plugin/webview/ui/tools/WebViewUI;
    //   5381: getfield 162	com/tencent/mm/plugin/webview/ui/tools/WebViewUI:icy	Lcom/tencent/mm/plugin/webview/stub/d;
    //   5384: invokevirtual 165	com/tencent/mm/plugin/webview/model/aq$e:b	(Lcom/tencent/mm/plugin/webview/stub/d;)V
    //   5387: aload_0
    //   5388: getfield 17	com/tencent/mm/plugin/webview/ui/tools/j$10:utN	Lcom/tencent/mm/plugin/webview/ui/tools/j;
    //   5391: invokevirtual 745	com/tencent/mm/plugin/webview/ui/tools/j:cZR	()V
    //   5394: sipush 7652
    //   5397: invokestatic 129	com/tencent/matrix/trace/core/AppMethodBeat:o	(I)V
    //   5400: goto -5261 -> 139
    //   5403: getstatic 319	com/tencent/mm/plugin/report/service/h:pYm	Lcom/tencent/mm/plugin/report/service/h;
    //   5406: ldc2_w 746
    //   5409: lconst_1
    //   5410: lconst_1
    //   5411: iconst_0
    //   5412: invokevirtual 326	com/tencent/mm/plugin/report/service/h:a	(JJJZ)V
    //   5415: aload_0
    //   5416: getfield 17	com/tencent/mm/plugin/webview/ui/tools/j$10:utN	Lcom/tencent/mm/plugin/webview/ui/tools/j;
    //   5419: invokevirtual 52	com/tencent/mm/plugin/webview/ui/tools/j:cZv	()Lcom/tencent/mm/plugin/webview/ui/tools/WebViewUI;
    //   5422: getfield 137	com/tencent/mm/plugin/webview/ui/tools/WebViewUI:ulI	Lcom/tencent/mm/plugin/webview/model/aq;
    //   5425: invokevirtual 143	com/tencent/mm/plugin/webview/model/aq:cYc	()Lcom/tencent/mm/plugin/webview/model/aq$e;
    //   5428: astore_1
    //   5429: aload_1
    //   5430: iconst_3
    //   5431: anewarray 4	java/lang/Object
    //   5434: dup
    //   5435: iconst_0
    //   5436: aload_0
    //   5437: getfield 17	com/tencent/mm/plugin/webview/ui/tools/j$10:utN	Lcom/tencent/mm/plugin/webview/ui/tools/j;
    //   5440: invokevirtual 52	com/tencent/mm/plugin/webview/ui/tools/j:cZv	()Lcom/tencent/mm/plugin/webview/ui/tools/WebViewUI;
    //   5443: getfield 146	com/tencent/mm/plugin/webview/ui/tools/WebViewUI:cOG	Ljava/lang/String;
    //   5446: aastore
    //   5447: dup
    //   5448: iconst_1
    //   5449: bipush 28
    //   5451: invokestatic 152	java/lang/Integer:valueOf	(I)Ljava/lang/Integer;
    //   5454: aastore
    //   5455: dup
    //   5456: iconst_2
    //   5457: iconst_1
    //   5458: invokestatic 152	java/lang/Integer:valueOf	(I)Ljava/lang/Integer;
    //   5461: aastore
    //   5462: putfield 158	com/tencent/mm/plugin/webview/model/aq$e:une	[Ljava/lang/Object;
    //   5465: aload_1
    //   5466: aload_0
    //   5467: getfield 17	com/tencent/mm/plugin/webview/ui/tools/j$10:utN	Lcom/tencent/mm/plugin/webview/ui/tools/j;
    //   5470: invokevirtual 52	com/tencent/mm/plugin/webview/ui/tools/j:cZv	()Lcom/tencent/mm/plugin/webview/ui/tools/WebViewUI;
    //   5473: getfield 162	com/tencent/mm/plugin/webview/ui/tools/WebViewUI:icy	Lcom/tencent/mm/plugin/webview/stub/d;
    //   5476: invokevirtual 165	com/tencent/mm/plugin/webview/model/aq$e:b	(Lcom/tencent/mm/plugin/webview/stub/d;)V
    //   5479: aload_0
    //   5480: getfield 17	com/tencent/mm/plugin/webview/ui/tools/j$10:utN	Lcom/tencent/mm/plugin/webview/ui/tools/j;
    //   5483: invokevirtual 52	com/tencent/mm/plugin/webview/ui/tools/j:cZv	()Lcom/tencent/mm/plugin/webview/ui/tools/WebViewUI;
    //   5486: getfield 751	com/tencent/mm/plugin/webview/ui/tools/WebViewUI:uvj	Lcom/tencent/mm/plugin/webview/ui/tools/widget/WebViewSearchContentInputFooter;
    //   5489: invokevirtual 756	com/tencent/mm/plugin/webview/ui/tools/widget/WebViewSearchContentInputFooter:isShown	()Z
    //   5492: ifne +555 -> 6047
    //   5495: aload_0
    //   5496: getfield 17	com/tencent/mm/plugin/webview/ui/tools/j$10:utN	Lcom/tencent/mm/plugin/webview/ui/tools/j;
    //   5499: invokevirtual 52	com/tencent/mm/plugin/webview/ui/tools/j:cZv	()Lcom/tencent/mm/plugin/webview/ui/tools/WebViewUI;
    //   5502: getfield 751	com/tencent/mm/plugin/webview/ui/tools/WebViewUI:uvj	Lcom/tencent/mm/plugin/webview/ui/tools/widget/WebViewSearchContentInputFooter;
    //   5505: invokevirtual 759	com/tencent/mm/plugin/webview/ui/tools/widget/WebViewSearchContentInputFooter:reset	()V
    //   5508: aload_0
    //   5509: getfield 17	com/tencent/mm/plugin/webview/ui/tools/j$10:utN	Lcom/tencent/mm/plugin/webview/ui/tools/j;
    //   5512: invokevirtual 52	com/tencent/mm/plugin/webview/ui/tools/j:cZv	()Lcom/tencent/mm/plugin/webview/ui/tools/WebViewUI;
    //   5515: getfield 751	com/tencent/mm/plugin/webview/ui/tools/WebViewUI:uvj	Lcom/tencent/mm/plugin/webview/ui/tools/widget/WebViewSearchContentInputFooter;
    //   5518: invokevirtual 762	com/tencent/mm/plugin/webview/ui/tools/widget/WebViewSearchContentInputFooter:dcX	()V
    //   5521: aload_0
    //   5522: getfield 17	com/tencent/mm/plugin/webview/ui/tools/j$10:utN	Lcom/tencent/mm/plugin/webview/ui/tools/j;
    //   5525: invokevirtual 52	com/tencent/mm/plugin/webview/ui/tools/j:cZv	()Lcom/tencent/mm/plugin/webview/ui/tools/WebViewUI;
    //   5528: getfield 751	com/tencent/mm/plugin/webview/ui/tools/WebViewUI:uvj	Lcom/tencent/mm/plugin/webview/ui/tools/widget/WebViewSearchContentInputFooter;
    //   5531: invokevirtual 763	com/tencent/mm/plugin/webview/ui/tools/widget/WebViewSearchContentInputFooter:show	()V
    //   5534: sipush 7652
    //   5537: invokestatic 129	com/tencent/matrix/trace/core/AppMethodBeat:o	(I)V
    //   5540: goto -5401 -> 139
    //   5543: aload_0
    //   5544: getfield 17	com/tencent/mm/plugin/webview/ui/tools/j$10:utN	Lcom/tencent/mm/plugin/webview/ui/tools/j;
    //   5547: astore_1
    //   5548: ldc_w 408
    //   5551: ldc_w 765
    //   5554: invokestatic 67	com/tencent/mm/sdk/platformtools/ab:i	(Ljava/lang/String;Ljava/lang/String;)V
    //   5557: aload_1
    //   5558: invokevirtual 52	com/tencent/mm/plugin/webview/ui/tools/j:cZv	()Lcom/tencent/mm/plugin/webview/ui/tools/WebViewUI;
    //   5561: getfield 58	com/tencent/mm/plugin/webview/ui/tools/WebViewUI:uhz	Lcom/tencent/mm/plugin/webview/ui/tools/jsapi/d;
    //   5564: ifnull +75 -> 5639
    //   5567: aload_1
    //   5568: invokevirtual 52	com/tencent/mm/plugin/webview/ui/tools/j:cZv	()Lcom/tencent/mm/plugin/webview/ui/tools/WebViewUI;
    //   5571: getfield 58	com/tencent/mm/plugin/webview/ui/tools/WebViewUI:uhz	Lcom/tencent/mm/plugin/webview/ui/tools/jsapi/d;
    //   5574: astore_1
    //   5575: aload_1
    //   5576: getfield 530	com/tencent/mm/plugin/webview/ui/tools/jsapi/d:ready	Z
    //   5579: ifne +20 -> 5599
    //   5582: ldc 60
    //   5584: ldc_w 767
    //   5587: invokestatic 413	com/tencent/mm/sdk/platformtools/ab:e	(Ljava/lang/String;Ljava/lang/String;)V
    //   5590: sipush 7652
    //   5593: invokestatic 129	com/tencent/matrix/trace/core/AppMethodBeat:o	(I)V
    //   5596: goto -5457 -> 139
    //   5599: ldc 60
    //   5601: ldc_w 769
    //   5604: invokestatic 67	com/tencent/mm/sdk/platformtools/ab:i	(Ljava/lang/String;Ljava/lang/String;)V
    //   5607: new 771	com/tencent/mm/plugin/webview/ui/tools/jsapi/d$19
    //   5610: dup
    //   5611: aload_1
    //   5612: ldc_w 773
    //   5615: new 69	java/util/HashMap
    //   5618: dup
    //   5619: invokespecial 70	java/util/HashMap:<init>	()V
    //   5622: aload_1
    //   5623: getfield 90	com/tencent/mm/plugin/webview/ui/tools/jsapi/d:uFv	Z
    //   5626: aload_1
    //   5627: getfield 93	com/tencent/mm/plugin/webview/ui/tools/jsapi/d:uFw	Ljava/lang/String;
    //   5630: invokestatic 99	com/tencent/mm/plugin/webview/ui/tools/jsapi/i$a:b	(Ljava/lang/String;Ljava/util/Map;ZLjava/lang/String;)Ljava/lang/String;
    //   5633: invokespecial 776	com/tencent/mm/plugin/webview/ui/tools/jsapi/d$19:<init>	(Lcom/tencent/mm/plugin/webview/ui/tools/jsapi/d;Ljava/lang/String;)V
    //   5636: invokestatic 782	com/tencent/mm/sdk/platformtools/al:d	(Ljava/lang/Runnable;)V
    //   5639: sipush 7652
    //   5642: invokestatic 129	com/tencent/matrix/trace/core/AppMethodBeat:o	(I)V
    //   5645: goto -5506 -> 139
    //   5648: aload_0
    //   5649: getfield 17	com/tencent/mm/plugin/webview/ui/tools/j$10:utN	Lcom/tencent/mm/plugin/webview/ui/tools/j;
    //   5652: invokevirtual 52	com/tencent/mm/plugin/webview/ui/tools/j:cZv	()Lcom/tencent/mm/plugin/webview/ui/tools/WebViewUI;
    //   5655: getfield 137	com/tencent/mm/plugin/webview/ui/tools/WebViewUI:ulI	Lcom/tencent/mm/plugin/webview/model/aq;
    //   5658: invokevirtual 143	com/tencent/mm/plugin/webview/model/aq:cYc	()Lcom/tencent/mm/plugin/webview/model/aq$e;
    //   5661: astore_1
    //   5662: aload_1
    //   5663: iconst_3
    //   5664: anewarray 4	java/lang/Object
    //   5667: dup
    //   5668: iconst_0
    //   5669: aload_0
    //   5670: getfield 17	com/tencent/mm/plugin/webview/ui/tools/j$10:utN	Lcom/tencent/mm/plugin/webview/ui/tools/j;
    //   5673: invokevirtual 52	com/tencent/mm/plugin/webview/ui/tools/j:cZv	()Lcom/tencent/mm/plugin/webview/ui/tools/WebViewUI;
    //   5676: getfield 146	com/tencent/mm/plugin/webview/ui/tools/WebViewUI:cOG	Ljava/lang/String;
    //   5679: aastore
    //   5680: dup
    //   5681: iconst_1
    //   5682: bipush 33
    //   5684: invokestatic 152	java/lang/Integer:valueOf	(I)Ljava/lang/Integer;
    //   5687: aastore
    //   5688: dup
    //   5689: iconst_2
    //   5690: iconst_1
    //   5691: invokestatic 152	java/lang/Integer:valueOf	(I)Ljava/lang/Integer;
    //   5694: aastore
    //   5695: putfield 158	com/tencent/mm/plugin/webview/model/aq$e:une	[Ljava/lang/Object;
    //   5698: aload_1
    //   5699: aload_0
    //   5700: getfield 17	com/tencent/mm/plugin/webview/ui/tools/j$10:utN	Lcom/tencent/mm/plugin/webview/ui/tools/j;
    //   5703: invokevirtual 52	com/tencent/mm/plugin/webview/ui/tools/j:cZv	()Lcom/tencent/mm/plugin/webview/ui/tools/WebViewUI;
    //   5706: getfield 162	com/tencent/mm/plugin/webview/ui/tools/WebViewUI:icy	Lcom/tencent/mm/plugin/webview/stub/d;
    //   5709: invokevirtual 165	com/tencent/mm/plugin/webview/model/aq$e:b	(Lcom/tencent/mm/plugin/webview/stub/d;)V
    //   5712: aload_0
    //   5713: getfield 17	com/tencent/mm/plugin/webview/ui/tools/j$10:utN	Lcom/tencent/mm/plugin/webview/ui/tools/j;
    //   5716: invokevirtual 52	com/tencent/mm/plugin/webview/ui/tools/j:cZv	()Lcom/tencent/mm/plugin/webview/ui/tools/WebViewUI;
    //   5719: getfield 786	com/tencent/mm/plugin/webview/ui/tools/WebViewUI:uie	Lcom/tencent/mm/plugin/webview/ui/tools/bag/h;
    //   5722: iconst_0
    //   5723: invokeinterface 792 2 0
    //   5728: sipush 7652
    //   5731: invokestatic 129	com/tencent/matrix/trace/core/AppMethodBeat:o	(I)V
    //   5734: goto -5595 -> 139
    //   5737: aload_0
    //   5738: getfield 17	com/tencent/mm/plugin/webview/ui/tools/j$10:utN	Lcom/tencent/mm/plugin/webview/ui/tools/j;
    //   5741: invokevirtual 52	com/tencent/mm/plugin/webview/ui/tools/j:cZv	()Lcom/tencent/mm/plugin/webview/ui/tools/WebViewUI;
    //   5744: getfield 137	com/tencent/mm/plugin/webview/ui/tools/WebViewUI:ulI	Lcom/tencent/mm/plugin/webview/model/aq;
    //   5747: invokevirtual 143	com/tencent/mm/plugin/webview/model/aq:cYc	()Lcom/tencent/mm/plugin/webview/model/aq$e;
    //   5750: astore_1
    //   5751: aload_1
    //   5752: iconst_3
    //   5753: anewarray 4	java/lang/Object
    //   5756: dup
    //   5757: iconst_0
    //   5758: aload_0
    //   5759: getfield 17	com/tencent/mm/plugin/webview/ui/tools/j$10:utN	Lcom/tencent/mm/plugin/webview/ui/tools/j;
    //   5762: invokevirtual 52	com/tencent/mm/plugin/webview/ui/tools/j:cZv	()Lcom/tencent/mm/plugin/webview/ui/tools/WebViewUI;
    //   5765: getfield 146	com/tencent/mm/plugin/webview/ui/tools/WebViewUI:cOG	Ljava/lang/String;
    //   5768: aastore
    //   5769: dup
    //   5770: iconst_1
    //   5771: bipush 34
    //   5773: invokestatic 152	java/lang/Integer:valueOf	(I)Ljava/lang/Integer;
    //   5776: aastore
    //   5777: dup
    //   5778: iconst_2
    //   5779: iconst_1
    //   5780: invokestatic 152	java/lang/Integer:valueOf	(I)Ljava/lang/Integer;
    //   5783: aastore
    //   5784: putfield 158	com/tencent/mm/plugin/webview/model/aq$e:une	[Ljava/lang/Object;
    //   5787: aload_1
    //   5788: aload_0
    //   5789: getfield 17	com/tencent/mm/plugin/webview/ui/tools/j$10:utN	Lcom/tencent/mm/plugin/webview/ui/tools/j;
    //   5792: invokevirtual 52	com/tencent/mm/plugin/webview/ui/tools/j:cZv	()Lcom/tencent/mm/plugin/webview/ui/tools/WebViewUI;
    //   5795: getfield 162	com/tencent/mm/plugin/webview/ui/tools/WebViewUI:icy	Lcom/tencent/mm/plugin/webview/stub/d;
    //   5798: invokevirtual 165	com/tencent/mm/plugin/webview/model/aq$e:b	(Lcom/tencent/mm/plugin/webview/stub/d;)V
    //   5801: aload_0
    //   5802: getfield 17	com/tencent/mm/plugin/webview/ui/tools/j$10:utN	Lcom/tencent/mm/plugin/webview/ui/tools/j;
    //   5805: invokevirtual 52	com/tencent/mm/plugin/webview/ui/tools/j:cZv	()Lcom/tencent/mm/plugin/webview/ui/tools/WebViewUI;
    //   5808: getfield 786	com/tencent/mm/plugin/webview/ui/tools/WebViewUI:uie	Lcom/tencent/mm/plugin/webview/ui/tools/bag/h;
    //   5811: iconst_1
    //   5812: invokeinterface 792 2 0
    //   5817: sipush 7652
    //   5820: invokestatic 129	com/tencent/matrix/trace/core/AppMethodBeat:o	(I)V
    //   5823: goto -5684 -> 139
    //   5826: iconst_0
    //   5827: istore_2
    //   5828: goto -5369 -> 459
    //   5831: iconst_0
    //   5832: istore_2
    //   5833: goto -5358 -> 475
    //   5836: astore_1
    //   5837: iconst_0
    //   5838: istore_2
    //   5839: ldc_w 408
    //   5842: aload_1
    //   5843: ldc_w 353
    //   5846: iconst_0
    //   5847: anewarray 4	java/lang/Object
    //   5850: invokestatic 357	com/tencent/mm/sdk/platformtools/ab:printErrStackTrace	(Ljava/lang/String;Ljava/lang/Throwable;Ljava/lang/String;[Ljava/lang/Object;)V
    //   5853: goto -5378 -> 475
    //   5856: aload_0
    //   5857: getfield 17	com/tencent/mm/plugin/webview/ui/tools/j$10:utN	Lcom/tencent/mm/plugin/webview/ui/tools/j;
    //   5860: astore_1
    //   5861: aload_1
    //   5862: invokevirtual 52	com/tencent/mm/plugin/webview/ui/tools/j:cZv	()Lcom/tencent/mm/plugin/webview/ui/tools/WebViewUI;
    //   5865: getfield 58	com/tencent/mm/plugin/webview/ui/tools/WebViewUI:uhz	Lcom/tencent/mm/plugin/webview/ui/tools/jsapi/d;
    //   5868: ldc_w 605
    //   5871: iconst_0
    //   5872: invokevirtual 527	com/tencent/mm/plugin/webview/ui/tools/jsapi/d:bJ	(Ljava/lang/String;Z)V
    //   5875: aload_1
    //   5876: invokevirtual 52	com/tencent/mm/plugin/webview/ui/tools/j:cZv	()Lcom/tencent/mm/plugin/webview/ui/tools/WebViewUI;
    //   5879: getfield 58	com/tencent/mm/plugin/webview/ui/tools/WebViewUI:uhz	Lcom/tencent/mm/plugin/webview/ui/tools/jsapi/d;
    //   5882: astore_1
    //   5883: aload_1
    //   5884: getfield 530	com/tencent/mm/plugin/webview/ui/tools/jsapi/d:ready	Z
    //   5887: ifne +20 -> 5907
    //   5890: ldc 60
    //   5892: ldc_w 794
    //   5895: invokestatic 413	com/tencent/mm/sdk/platformtools/ab:e	(Ljava/lang/String;Ljava/lang/String;)V
    //   5898: sipush 7652
    //   5901: invokestatic 129	com/tencent/matrix/trace/core/AppMethodBeat:o	(I)V
    //   5904: goto -5765 -> 139
    //   5907: new 69	java/util/HashMap
    //   5910: dup
    //   5911: invokespecial 70	java/util/HashMap:<init>	()V
    //   5914: astore 4
    //   5916: aload 4
    //   5918: ldc_w 611
    //   5921: ldc_w 796
    //   5924: invokevirtual 79	java/util/HashMap:put	(Ljava/lang/Object;Ljava/lang/Object;)Ljava/lang/Object;
    //   5927: pop
    //   5928: ldc_w 609
    //   5931: aload 4
    //   5933: aload_1
    //   5934: getfield 90	com/tencent/mm/plugin/webview/ui/tools/jsapi/d:uFv	Z
    //   5937: aload_1
    //   5938: getfield 93	com/tencent/mm/plugin/webview/ui/tools/jsapi/d:uFw	Ljava/lang/String;
    //   5941: invokestatic 99	com/tencent/mm/plugin/webview/ui/tools/jsapi/i$a:b	(Ljava/lang/String;Ljava/util/Map;ZLjava/lang/String;)Ljava/lang/String;
    //   5944: astore 4
    //   5946: aload_1
    //   5947: getfield 103	com/tencent/mm/plugin/webview/ui/tools/jsapi/d:uFo	Lcom/tencent/mm/ui/widget/MMWebView;
    //   5950: new 105	java/lang/StringBuilder
    //   5953: dup
    //   5954: ldc 107
    //   5956: invokespecial 110	java/lang/StringBuilder:<init>	(Ljava/lang/String;)V
    //   5959: aload 4
    //   5961: invokevirtual 114	java/lang/StringBuilder:append	(Ljava/lang/String;)Ljava/lang/StringBuilder;
    //   5964: ldc 116
    //   5966: invokevirtual 114	java/lang/StringBuilder:append	(Ljava/lang/String;)Ljava/lang/StringBuilder;
    //   5969: invokevirtual 120	java/lang/StringBuilder:toString	()Ljava/lang/String;
    //   5972: aconst_null
    //   5973: invokevirtual 126	com/tencent/mm/ui/widget/MMWebView:evaluateJavascript	(Ljava/lang/String;Landroid/webkit/ValueCallback;)V
    //   5976: aload_1
    //   5977: getfield 341	com/tencent/mm/plugin/webview/ui/tools/jsapi/d:icy	Lcom/tencent/mm/plugin/webview/stub/d;
    //   5980: ldc_w 798
    //   5983: aload_3
    //   5984: aload_1
    //   5985: getfield 345	com/tencent/mm/plugin/webview/ui/tools/jsapi/d:uqj	I
    //   5988: invokeinterface 617 4 0
    //   5993: aload_1
    //   5994: getfield 341	com/tencent/mm/plugin/webview/ui/tools/jsapi/d:icy	Lcom/tencent/mm/plugin/webview/stub/d;
    //   5997: ldc_w 611
    //   6000: ldc_w 796
    //   6003: aload_1
    //   6004: getfield 345	com/tencent/mm/plugin/webview/ui/tools/jsapi/d:uqj	I
    //   6007: invokeinterface 617 4 0
    //   6012: sipush 7652
    //   6015: invokestatic 129	com/tencent/matrix/trace/core/AppMethodBeat:o	(I)V
    //   6018: goto -5879 -> 139
    //   6021: astore_1
    //   6022: ldc 60
    //   6024: new 105	java/lang/StringBuilder
    //   6027: dup
    //   6028: ldc_w 619
    //   6031: invokespecial 110	java/lang/StringBuilder:<init>	(Ljava/lang/String;)V
    //   6034: aload_1
    //   6035: invokevirtual 505	java/lang/Exception:getMessage	()Ljava/lang/String;
    //   6038: invokevirtual 114	java/lang/StringBuilder:append	(Ljava/lang/String;)Ljava/lang/StringBuilder;
    //   6041: invokevirtual 120	java/lang/StringBuilder:toString	()Ljava/lang/String;
    //   6044: invokestatic 368	com/tencent/mm/sdk/platformtools/ab:w	(Ljava/lang/String;Ljava/lang/String;)V
    //   6047: sipush 7652
    //   6050: invokestatic 129	com/tencent/matrix/trace/core/AppMethodBeat:o	(I)V
    //   6053: goto -5914 -> 139
    //   6056: astore_1
    //   6057: goto -218 -> 5839
    //   6060: iconst_0
    //   6061: istore_2
    //   6062: goto -5587 -> 475
    //
    // Exception table:
    //   from	to	target	type
    //   1533	1551	1571	java/lang/Exception
    //   2061	2095	2098	java/lang/Exception
    //   2135	2144	2098	java/lang/Exception
    //   2022	2037	2122	java/lang/Exception
    //   2338	2352	2367	java/lang/Exception
    //   2352	2364	2367	java/lang/Exception
    //   2420	2433	2367	java/lang/Exception
    //   2279	2288	2397	java/lang/Exception
    //   3771	3790	3799	java/lang/Exception
    //   3906	3931	4049	java/lang/Exception
    //   3951	3977	4073	java/lang/Exception
    //   4934	4953	4962	java/lang/Exception
    //   5066	5107	5287	java/lang/Exception
    //   5112	5118	5287	java/lang/Exception
    //   5131	5153	5287	java/lang/Exception
    //   5162	5278	5287	java/lang/Exception
    //   407	441	5836	android/os/RemoteException
    //   445	452	5836	android/os/RemoteException
    //   5976	6012	6021	java/lang/Exception
    //   459	467	6056	android/os/RemoteException
  }
}

/* Location:           C:\Users\Lin\Downloads\dex-tools-2.1-SNAPSHOT\dex-tools-2.1-SNAPSHOT\classes3-dex2jar.jar
 * Qualified Name:     com.tencent.mm.plugin.webview.ui.tools.j.10
 * JD-Core Version:    0.6.2
 */