package com.tencent.mm.plugin.webview.ui.tools;

import com.tencent.mm.ui.base.n.c;

final class j$12
  implements n.c
{
  j$12(j paramj)
  {
  }

  // ERROR //
  public final void a(com.tencent.mm.ui.base.l paraml)
  {
    // Byte code:
    //   0: sipush 7653
    //   3: invokestatic 32	com/tencent/matrix/trace/core/AppMethodBeat:i	(I)V
    //   6: getstatic 38	com/tencent/mm/plugin/report/service/h:pYm	Lcom/tencent/mm/plugin/report/service/h;
    //   9: ldc2_w 39
    //   12: lconst_0
    //   13: lconst_1
    //   14: iconst_0
    //   15: invokevirtual 43	com/tencent/mm/plugin/report/service/h:a	(JJJZ)V
    //   18: aload_1
    //   19: invokevirtual 48	com/tencent/mm/ui/base/l:clear	()V
    //   22: aload_0
    //   23: getfield 17	com/tencent/mm/plugin/webview/ui/tools/j$12:utN	Lcom/tencent/mm/plugin/webview/ui/tools/j;
    //   26: getfield 52	com/tencent/mm/plugin/webview/ui/tools/j:utM	Ljava/lang/Boolean;
    //   29: invokevirtual 58	java/lang/Boolean:booleanValue	()Z
    //   32: ifeq +90 -> 122
    //   35: aload_0
    //   36: getfield 17	com/tencent/mm/plugin/webview/ui/tools/j$12:utN	Lcom/tencent/mm/plugin/webview/ui/tools/j;
    //   39: getfield 62	com/tencent/mm/plugin/webview/ui/tools/j:utL	Ljava/util/ArrayList;
    //   42: invokevirtual 68	java/util/ArrayList:size	()I
    //   45: istore_2
    //   46: iconst_0
    //   47: istore_3
    //   48: iload_3
    //   49: iload_2
    //   50: if_icmpge +65 -> 115
    //   53: aload_0
    //   54: getfield 17	com/tencent/mm/plugin/webview/ui/tools/j$12:utN	Lcom/tencent/mm/plugin/webview/ui/tools/j;
    //   57: getfield 62	com/tencent/mm/plugin/webview/ui/tools/j:utL	Ljava/util/ArrayList;
    //   60: iload_3
    //   61: invokevirtual 72	java/util/ArrayList:get	(I)Ljava/lang/Object;
    //   64: checkcast 74	com/tencent/mm/m/d$b
    //   67: astore 4
    //   69: aload_1
    //   70: aload 4
    //   72: getfield 78	com/tencent/mm/m/d$b:id	I
    //   75: aload 4
    //   77: getfield 82	com/tencent/mm/m/d$b:title	Ljava/lang/String;
    //   80: invokevirtual 86	com/tencent/mm/ui/base/l:e	(ILjava/lang/CharSequence;)Landroid/view/MenuItem;
    //   83: checkcast 88	com/tencent/mm/ui/base/m
    //   86: astore 5
    //   88: aload 5
    //   90: aload 4
    //   92: putfield 92	com/tencent/mm/ui/base/m:yvW	Landroid/view/ContextMenu$ContextMenuInfo;
    //   95: aload 5
    //   97: aconst_null
    //   98: invokevirtual 96	com/tencent/mm/ui/base/m:setIcon	(Landroid/graphics/drawable/Drawable;)Landroid/view/MenuItem;
    //   101: pop
    //   102: aload 5
    //   104: iconst_0
    //   105: invokevirtual 99	com/tencent/mm/ui/base/m:setIcon	(I)Landroid/view/MenuItem;
    //   108: pop
    //   109: iinc 3 1
    //   112: goto -64 -> 48
    //   115: sipush 7653
    //   118: invokestatic 102	com/tencent/matrix/trace/core/AppMethodBeat:o	(I)V
    //   121: return
    //   122: aload_0
    //   123: getfield 17	com/tencent/mm/plugin/webview/ui/tools/j$12:utN	Lcom/tencent/mm/plugin/webview/ui/tools/j;
    //   126: invokevirtual 106	com/tencent/mm/plugin/webview/ui/tools/j:cZv	()Lcom/tencent/mm/plugin/webview/ui/tools/WebViewUI;
    //   129: invokevirtual 112	com/tencent/mm/plugin/webview/ui/tools/WebViewUI:dar	()Ljava/util/LinkedList;
    //   132: astore 6
    //   134: aload 6
    //   136: ifnull +299 -> 435
    //   139: iconst_0
    //   140: istore_3
    //   141: iload_3
    //   142: aload 6
    //   144: invokevirtual 115	java/util/LinkedList:size	()I
    //   147: if_icmpge +288 -> 435
    //   150: iload_3
    //   151: bipush 8
    //   153: if_icmpge +282 -> 435
    //   156: aload 6
    //   158: iload_3
    //   159: invokevirtual 116	java/util/LinkedList:get	(I)Ljava/lang/Object;
    //   162: checkcast 118	com/tencent/mm/m/d$a
    //   165: astore 5
    //   167: aconst_null
    //   168: astore 4
    //   170: ldc 120
    //   172: aload 5
    //   174: getfield 122	com/tencent/mm/m/d$a:id	Ljava/lang/String;
    //   177: invokestatic 128	com/tencent/mm/sdk/platformtools/bo:nullAsNil	(Ljava/lang/String;)Ljava/lang/String;
    //   180: invokevirtual 134	java/lang/String:equals	(Ljava/lang/Object;)Z
    //   183: ifeq +49 -> 232
    //   186: aload_1
    //   187: bipush 15
    //   189: aload_0
    //   190: getfield 17	com/tencent/mm/plugin/webview/ui/tools/j$12:utN	Lcom/tencent/mm/plugin/webview/ui/tools/j;
    //   193: invokevirtual 106	com/tencent/mm/plugin/webview/ui/tools/j:cZv	()Lcom/tencent/mm/plugin/webview/ui/tools/WebViewUI;
    //   196: ldc 135
    //   198: invokevirtual 139	com/tencent/mm/plugin/webview/ui/tools/WebViewUI:getString	(I)Ljava/lang/String;
    //   201: ldc 140
    //   203: invokevirtual 143	com/tencent/mm/ui/base/l:a	(ILjava/lang/CharSequence;I)Landroid/view/MenuItem;
    //   206: checkcast 88	com/tencent/mm/ui/base/m
    //   209: astore 4
    //   211: aload 4
    //   213: ifnull +13 -> 226
    //   216: aload 4
    //   218: aload 5
    //   220: getfield 146	com/tencent/mm/m/d$a:url	Ljava/lang/String;
    //   223: putfield 149	com/tencent/mm/ui/base/m:hAh	Ljava/lang/String;
    //   226: iinc 3 1
    //   229: goto -88 -> 141
    //   232: ldc 151
    //   234: aload 5
    //   236: getfield 122	com/tencent/mm/m/d$a:id	Ljava/lang/String;
    //   239: invokestatic 128	com/tencent/mm/sdk/platformtools/bo:nullAsNil	(Ljava/lang/String;)Ljava/lang/String;
    //   242: invokevirtual 134	java/lang/String:equals	(Ljava/lang/Object;)Z
    //   245: ifeq +31 -> 276
    //   248: aload_1
    //   249: bipush 16
    //   251: aload_0
    //   252: getfield 17	com/tencent/mm/plugin/webview/ui/tools/j$12:utN	Lcom/tencent/mm/plugin/webview/ui/tools/j;
    //   255: invokevirtual 106	com/tencent/mm/plugin/webview/ui/tools/j:cZv	()Lcom/tencent/mm/plugin/webview/ui/tools/WebViewUI;
    //   258: ldc 152
    //   260: invokevirtual 139	com/tencent/mm/plugin/webview/ui/tools/WebViewUI:getString	(I)Ljava/lang/String;
    //   263: ldc 153
    //   265: invokevirtual 143	com/tencent/mm/ui/base/l:a	(ILjava/lang/CharSequence;I)Landroid/view/MenuItem;
    //   268: checkcast 88	com/tencent/mm/ui/base/m
    //   271: astore 4
    //   273: goto -62 -> 211
    //   276: ldc 155
    //   278: aload 5
    //   280: getfield 122	com/tencent/mm/m/d$a:id	Ljava/lang/String;
    //   283: invokestatic 128	com/tencent/mm/sdk/platformtools/bo:nullAsNil	(Ljava/lang/String;)Ljava/lang/String;
    //   286: invokevirtual 134	java/lang/String:equals	(Ljava/lang/Object;)Z
    //   289: ifeq +31 -> 320
    //   292: aload_1
    //   293: bipush 17
    //   295: aload_0
    //   296: getfield 17	com/tencent/mm/plugin/webview/ui/tools/j$12:utN	Lcom/tencent/mm/plugin/webview/ui/tools/j;
    //   299: invokevirtual 106	com/tencent/mm/plugin/webview/ui/tools/j:cZv	()Lcom/tencent/mm/plugin/webview/ui/tools/WebViewUI;
    //   302: ldc 156
    //   304: invokevirtual 139	com/tencent/mm/plugin/webview/ui/tools/WebViewUI:getString	(I)Ljava/lang/String;
    //   307: ldc 157
    //   309: invokevirtual 143	com/tencent/mm/ui/base/l:a	(ILjava/lang/CharSequence;I)Landroid/view/MenuItem;
    //   312: checkcast 88	com/tencent/mm/ui/base/m
    //   315: astore 4
    //   317: goto -106 -> 211
    //   320: ldc 159
    //   322: aload 5
    //   324: getfield 122	com/tencent/mm/m/d$a:id	Ljava/lang/String;
    //   327: invokestatic 128	com/tencent/mm/sdk/platformtools/bo:nullAsNil	(Ljava/lang/String;)Ljava/lang/String;
    //   330: invokevirtual 134	java/lang/String:equals	(Ljava/lang/Object;)Z
    //   333: ifeq +31 -> 364
    //   336: aload_1
    //   337: bipush 18
    //   339: aload_0
    //   340: getfield 17	com/tencent/mm/plugin/webview/ui/tools/j$12:utN	Lcom/tencent/mm/plugin/webview/ui/tools/j;
    //   343: invokevirtual 106	com/tencent/mm/plugin/webview/ui/tools/j:cZv	()Lcom/tencent/mm/plugin/webview/ui/tools/WebViewUI;
    //   346: ldc 160
    //   348: invokevirtual 139	com/tencent/mm/plugin/webview/ui/tools/WebViewUI:getString	(I)Ljava/lang/String;
    //   351: ldc 161
    //   353: invokevirtual 143	com/tencent/mm/ui/base/l:a	(ILjava/lang/CharSequence;I)Landroid/view/MenuItem;
    //   356: checkcast 88	com/tencent/mm/ui/base/m
    //   359: astore 4
    //   361: goto -150 -> 211
    //   364: ldc 163
    //   366: aload 5
    //   368: getfield 122	com/tencent/mm/m/d$a:id	Ljava/lang/String;
    //   371: invokestatic 128	com/tencent/mm/sdk/platformtools/bo:nullAsNil	(Ljava/lang/String;)Ljava/lang/String;
    //   374: invokevirtual 134	java/lang/String:equals	(Ljava/lang/Object;)Z
    //   377: ifeq -166 -> 211
    //   380: aload_1
    //   381: bipush 19
    //   383: aload_0
    //   384: getfield 17	com/tencent/mm/plugin/webview/ui/tools/j$12:utN	Lcom/tencent/mm/plugin/webview/ui/tools/j;
    //   387: invokevirtual 106	com/tencent/mm/plugin/webview/ui/tools/j:cZv	()Lcom/tencent/mm/plugin/webview/ui/tools/WebViewUI;
    //   390: ldc 164
    //   392: invokevirtual 139	com/tencent/mm/plugin/webview/ui/tools/WebViewUI:getString	(I)Ljava/lang/String;
    //   395: ldc 165
    //   397: invokevirtual 143	com/tencent/mm/ui/base/l:a	(ILjava/lang/CharSequence;I)Landroid/view/MenuItem;
    //   400: checkcast 88	com/tencent/mm/ui/base/m
    //   403: astore 4
    //   405: goto -194 -> 211
    //   408: astore 4
    //   410: ldc 167
    //   412: new 169	java/lang/StringBuilder
    //   415: dup
    //   416: ldc 171
    //   418: invokespecial 174	java/lang/StringBuilder:<init>	(Ljava/lang/String;)V
    //   421: aload 4
    //   423: invokevirtual 178	java/lang/Exception:getMessage	()Ljava/lang/String;
    //   426: invokevirtual 182	java/lang/StringBuilder:append	(Ljava/lang/String;)Ljava/lang/StringBuilder;
    //   429: invokevirtual 185	java/lang/StringBuilder:toString	()Ljava/lang/String;
    //   432: invokestatic 190	com/tencent/mm/sdk/platformtools/ab:e	(Ljava/lang/String;Ljava/lang/String;)V
    //   435: aload_0
    //   436: getfield 17	com/tencent/mm/plugin/webview/ui/tools/j$12:utN	Lcom/tencent/mm/plugin/webview/ui/tools/j;
    //   439: invokevirtual 106	com/tencent/mm/plugin/webview/ui/tools/j:cZv	()Lcom/tencent/mm/plugin/webview/ui/tools/WebViewUI;
    //   442: getfield 194	com/tencent/mm/plugin/webview/ui/tools/WebViewUI:icz	Lcom/tencent/mm/plugin/webview/ui/tools/k;
    //   445: ifnull +19 -> 464
    //   448: aload_0
    //   449: getfield 17	com/tencent/mm/plugin/webview/ui/tools/j$12:utN	Lcom/tencent/mm/plugin/webview/ui/tools/j;
    //   452: invokevirtual 106	com/tencent/mm/plugin/webview/ui/tools/j:cZv	()Lcom/tencent/mm/plugin/webview/ui/tools/WebViewUI;
    //   455: getfield 194	com/tencent/mm/plugin/webview/ui/tools/WebViewUI:icz	Lcom/tencent/mm/plugin/webview/ui/tools/k;
    //   458: invokevirtual 200	com/tencent/mm/plugin/webview/ui/tools/k:cZS	()Lcom/tencent/mm/protocal/JsapiPermissionWrapper;
    //   461: ifnonnull +19 -> 480
    //   464: ldc 167
    //   466: ldc 202
    //   468: invokestatic 190	com/tencent/mm/sdk/platformtools/ab:e	(Ljava/lang/String;Ljava/lang/String;)V
    //   471: sipush 7653
    //   474: invokestatic 102	com/tencent/matrix/trace/core/AppMethodBeat:o	(I)V
    //   477: goto -356 -> 121
    //   480: aload_0
    //   481: getfield 17	com/tencent/mm/plugin/webview/ui/tools/j$12:utN	Lcom/tencent/mm/plugin/webview/ui/tools/j;
    //   484: invokevirtual 106	com/tencent/mm/plugin/webview/ui/tools/j:cZv	()Lcom/tencent/mm/plugin/webview/ui/tools/WebViewUI;
    //   487: getfield 194	com/tencent/mm/plugin/webview/ui/tools/WebViewUI:icz	Lcom/tencent/mm/plugin/webview/ui/tools/k;
    //   490: invokevirtual 200	com/tencent/mm/plugin/webview/ui/tools/k:cZS	()Lcom/tencent/mm/protocal/JsapiPermissionWrapper;
    //   493: astore 6
    //   495: aload_0
    //   496: getfield 17	com/tencent/mm/plugin/webview/ui/tools/j$12:utN	Lcom/tencent/mm/plugin/webview/ui/tools/j;
    //   499: invokevirtual 106	com/tencent/mm/plugin/webview/ui/tools/j:cZv	()Lcom/tencent/mm/plugin/webview/ui/tools/WebViewUI;
    //   502: invokevirtual 205	com/tencent/mm/plugin/webview/ui/tools/WebViewUI:cWO	()Z
    //   505: ifeq +66 -> 571
    //   508: aload_0
    //   509: getfield 17	com/tencent/mm/plugin/webview/ui/tools/j$12:utN	Lcom/tencent/mm/plugin/webview/ui/tools/j;
    //   512: bipush 35
    //   514: invokestatic 209	com/tencent/mm/plugin/webview/ui/tools/j:c	(Lcom/tencent/mm/plugin/webview/ui/tools/j;I)Z
    //   517: ifeq +2502 -> 3019
    //   520: aload_0
    //   521: getfield 17	com/tencent/mm/plugin/webview/ui/tools/j$12:utN	Lcom/tencent/mm/plugin/webview/ui/tools/j;
    //   524: bipush 35
    //   526: invokevirtual 213	com/tencent/mm/plugin/webview/ui/tools/j:Jn	(I)Z
    //   529: ifeq +2490 -> 3019
    //   532: aload_0
    //   533: getfield 17	com/tencent/mm/plugin/webview/ui/tools/j$12:utN	Lcom/tencent/mm/plugin/webview/ui/tools/j;
    //   536: invokevirtual 106	com/tencent/mm/plugin/webview/ui/tools/j:cZv	()Lcom/tencent/mm/plugin/webview/ui/tools/WebViewUI;
    //   539: getfield 217	com/tencent/mm/plugin/webview/ui/tools/WebViewUI:uie	Lcom/tencent/mm/plugin/webview/ui/tools/bag/h;
    //   542: invokeinterface 222 1 0
    //   547: ifne +2472 -> 3019
    //   550: aload_1
    //   551: bipush 35
    //   553: aload_0
    //   554: getfield 17	com/tencent/mm/plugin/webview/ui/tools/j$12:utN	Lcom/tencent/mm/plugin/webview/ui/tools/j;
    //   557: invokevirtual 106	com/tencent/mm/plugin/webview/ui/tools/j:cZv	()Lcom/tencent/mm/plugin/webview/ui/tools/WebViewUI;
    //   560: ldc 223
    //   562: invokevirtual 139	com/tencent/mm/plugin/webview/ui/tools/WebViewUI:getString	(I)Ljava/lang/String;
    //   565: ldc 224
    //   567: invokevirtual 143	com/tencent/mm/ui/base/l:a	(ILjava/lang/CharSequence;I)Landroid/view/MenuItem;
    //   570: pop
    //   571: aload_0
    //   572: getfield 17	com/tencent/mm/plugin/webview/ui/tools/j$12:utN	Lcom/tencent/mm/plugin/webview/ui/tools/j;
    //   575: iconst_1
    //   576: invokestatic 209	com/tencent/mm/plugin/webview/ui/tools/j:c	(Lcom/tencent/mm/plugin/webview/ui/tools/j;I)Z
    //   579: ifeq +51 -> 630
    //   582: aload 6
    //   584: bipush 21
    //   586: invokestatic 227	com/tencent/mm/plugin/webview/ui/tools/j:a	(Lcom/tencent/mm/protocal/JsapiPermissionWrapper;I)Z
    //   589: ifeq +41 -> 630
    //   592: aload_0
    //   593: getfield 17	com/tencent/mm/plugin/webview/ui/tools/j$12:utN	Lcom/tencent/mm/plugin/webview/ui/tools/j;
    //   596: iconst_1
    //   597: invokevirtual 213	com/tencent/mm/plugin/webview/ui/tools/j:Jn	(I)Z
    //   600: ifeq +30 -> 630
    //   603: aload_1
    //   604: iconst_1
    //   605: aload_0
    //   606: getfield 17	com/tencent/mm/plugin/webview/ui/tools/j$12:utN	Lcom/tencent/mm/plugin/webview/ui/tools/j;
    //   609: invokevirtual 106	com/tencent/mm/plugin/webview/ui/tools/j:cZv	()Lcom/tencent/mm/plugin/webview/ui/tools/WebViewUI;
    //   612: ldc 228
    //   614: invokevirtual 139	com/tencent/mm/plugin/webview/ui/tools/WebViewUI:getString	(I)Ljava/lang/String;
    //   617: ldc 229
    //   619: aload 6
    //   621: bipush 21
    //   623: invokestatic 232	com/tencent/mm/plugin/webview/ui/tools/j:b	(Lcom/tencent/mm/protocal/JsapiPermissionWrapper;I)Z
    //   626: invokevirtual 235	com/tencent/mm/ui/base/l:a	(ILjava/lang/CharSequence;IZ)Landroid/view/MenuItem;
    //   629: pop
    //   630: aload_0
    //   631: getfield 17	com/tencent/mm/plugin/webview/ui/tools/j$12:utN	Lcom/tencent/mm/plugin/webview/ui/tools/j;
    //   634: iconst_2
    //   635: invokestatic 209	com/tencent/mm/plugin/webview/ui/tools/j:c	(Lcom/tencent/mm/plugin/webview/ui/tools/j;I)Z
    //   638: ifeq +51 -> 689
    //   641: aload 6
    //   643: bipush 23
    //   645: invokestatic 227	com/tencent/mm/plugin/webview/ui/tools/j:a	(Lcom/tencent/mm/protocal/JsapiPermissionWrapper;I)Z
    //   648: ifeq +41 -> 689
    //   651: aload_0
    //   652: getfield 17	com/tencent/mm/plugin/webview/ui/tools/j$12:utN	Lcom/tencent/mm/plugin/webview/ui/tools/j;
    //   655: iconst_2
    //   656: invokevirtual 213	com/tencent/mm/plugin/webview/ui/tools/j:Jn	(I)Z
    //   659: ifeq +30 -> 689
    //   662: aload_1
    //   663: iconst_2
    //   664: aload_0
    //   665: getfield 17	com/tencent/mm/plugin/webview/ui/tools/j$12:utN	Lcom/tencent/mm/plugin/webview/ui/tools/j;
    //   668: invokevirtual 106	com/tencent/mm/plugin/webview/ui/tools/j:cZv	()Lcom/tencent/mm/plugin/webview/ui/tools/WebViewUI;
    //   671: ldc 236
    //   673: invokevirtual 139	com/tencent/mm/plugin/webview/ui/tools/WebViewUI:getString	(I)Ljava/lang/String;
    //   676: ldc 237
    //   678: aload 6
    //   680: bipush 23
    //   682: invokestatic 232	com/tencent/mm/plugin/webview/ui/tools/j:b	(Lcom/tencent/mm/protocal/JsapiPermissionWrapper;I)Z
    //   685: invokevirtual 235	com/tencent/mm/ui/base/l:a	(ILjava/lang/CharSequence;IZ)Landroid/view/MenuItem;
    //   688: pop
    //   689: iconst_m1
    //   690: istore_2
    //   691: iconst_m1
    //   692: istore 7
    //   694: iload_2
    //   695: istore_3
    //   696: new 239	android/os/Bundle
    //   699: astore 4
    //   701: iload_2
    //   702: istore_3
    //   703: aload 4
    //   705: invokespecial 240	android/os/Bundle:<init>	()V
    //   708: iload_2
    //   709: istore_3
    //   710: aload 4
    //   712: ldc 242
    //   714: aload_0
    //   715: getfield 17	com/tencent/mm/plugin/webview/ui/tools/j$12:utN	Lcom/tencent/mm/plugin/webview/ui/tools/j;
    //   718: invokevirtual 106	com/tencent/mm/plugin/webview/ui/tools/j:cZv	()Lcom/tencent/mm/plugin/webview/ui/tools/WebViewUI;
    //   721: invokevirtual 245	java/lang/Object:hashCode	()I
    //   724: invokevirtual 249	android/os/Bundle:putInt	(Ljava/lang/String;I)V
    //   727: iload_2
    //   728: istore_3
    //   729: aload 4
    //   731: ldc 251
    //   733: aload_0
    //   734: getfield 17	com/tencent/mm/plugin/webview/ui/tools/j$12:utN	Lcom/tencent/mm/plugin/webview/ui/tools/j;
    //   737: invokevirtual 106	com/tencent/mm/plugin/webview/ui/tools/j:cZv	()Lcom/tencent/mm/plugin/webview/ui/tools/WebViewUI;
    //   740: getfield 255	com/tencent/mm/plugin/webview/ui/tools/WebViewUI:pzf	Lcom/tencent/mm/ui/widget/MMWebView;
    //   743: invokevirtual 260	com/tencent/mm/ui/widget/MMWebView:getUrl	()Ljava/lang/String;
    //   746: invokevirtual 263	android/os/Bundle:putString	(Ljava/lang/String;Ljava/lang/String;)V
    //   749: iload_2
    //   750: istore_3
    //   751: aload_0
    //   752: getfield 17	com/tencent/mm/plugin/webview/ui/tools/j$12:utN	Lcom/tencent/mm/plugin/webview/ui/tools/j;
    //   755: invokevirtual 106	com/tencent/mm/plugin/webview/ui/tools/j:cZv	()Lcom/tencent/mm/plugin/webview/ui/tools/WebViewUI;
    //   758: getfield 267	com/tencent/mm/plugin/webview/ui/tools/WebViewUI:icy	Lcom/tencent/mm/plugin/webview/stub/d;
    //   761: bipush 109
    //   763: aload 4
    //   765: invokeinterface 273 3 0
    //   770: astore 4
    //   772: iload 7
    //   774: istore 8
    //   776: iload_2
    //   777: istore_3
    //   778: aload 4
    //   780: ifnull +30 -> 810
    //   783: iload_2
    //   784: istore_3
    //   785: aload 4
    //   787: ldc_w 275
    //   790: iconst_0
    //   791: invokevirtual 279	android/os/Bundle:getInt	(Ljava/lang/String;I)I
    //   794: istore_2
    //   795: iload_2
    //   796: istore_3
    //   797: aload 4
    //   799: ldc_w 281
    //   802: iconst_m1
    //   803: invokevirtual 279	android/os/Bundle:getInt	(Ljava/lang/String;I)I
    //   806: istore 8
    //   808: iload_2
    //   809: istore_3
    //   810: iload_3
    //   811: iconst_1
    //   812: if_icmpne +55 -> 867
    //   815: aload_0
    //   816: getfield 17	com/tencent/mm/plugin/webview/ui/tools/j$12:utN	Lcom/tencent/mm/plugin/webview/ui/tools/j;
    //   819: bipush 38
    //   821: invokestatic 209	com/tencent/mm/plugin/webview/ui/tools/j:c	(Lcom/tencent/mm/plugin/webview/ui/tools/j;I)Z
    //   824: ifeq +2286 -> 3110
    //   827: aload_0
    //   828: getfield 17	com/tencent/mm/plugin/webview/ui/tools/j$12:utN	Lcom/tencent/mm/plugin/webview/ui/tools/j;
    //   831: bipush 38
    //   833: invokevirtual 213	com/tencent/mm/plugin/webview/ui/tools/j:Jn	(I)Z
    //   836: ifeq +2274 -> 3110
    //   839: iload 8
    //   841: ifne +2269 -> 3110
    //   844: aload_1
    //   845: bipush 38
    //   847: aload_0
    //   848: getfield 17	com/tencent/mm/plugin/webview/ui/tools/j$12:utN	Lcom/tencent/mm/plugin/webview/ui/tools/j;
    //   851: invokevirtual 106	com/tencent/mm/plugin/webview/ui/tools/j:cZv	()Lcom/tencent/mm/plugin/webview/ui/tools/WebViewUI;
    //   854: ldc_w 282
    //   857: invokevirtual 139	com/tencent/mm/plugin/webview/ui/tools/WebViewUI:getString	(I)Ljava/lang/String;
    //   860: ldc_w 283
    //   863: invokevirtual 143	com/tencent/mm/ui/base/l:a	(ILjava/lang/CharSequence;I)Landroid/view/MenuItem;
    //   866: pop
    //   867: aload_0
    //   868: getfield 17	com/tencent/mm/plugin/webview/ui/tools/j$12:utN	Lcom/tencent/mm/plugin/webview/ui/tools/j;
    //   871: iconst_3
    //   872: invokestatic 209	com/tencent/mm/plugin/webview/ui/tools/j:c	(Lcom/tencent/mm/plugin/webview/ui/tools/j;I)Z
    //   875: ifeq +136 -> 1011
    //   878: aload_0
    //   879: getfield 17	com/tencent/mm/plugin/webview/ui/tools/j$12:utN	Lcom/tencent/mm/plugin/webview/ui/tools/j;
    //   882: invokevirtual 106	com/tencent/mm/plugin/webview/ui/tools/j:cZv	()Lcom/tencent/mm/plugin/webview/ui/tools/WebViewUI;
    //   885: getfield 287	com/tencent/mm/plugin/webview/ui/tools/WebViewUI:uvu	Z
    //   888: ifeq +61 -> 949
    //   891: aload_0
    //   892: getfield 17	com/tencent/mm/plugin/webview/ui/tools/j$12:utN	Lcom/tencent/mm/plugin/webview/ui/tools/j;
    //   895: invokevirtual 106	com/tencent/mm/plugin/webview/ui/tools/j:cZv	()Lcom/tencent/mm/plugin/webview/ui/tools/WebViewUI;
    //   898: getfield 290	com/tencent/mm/plugin/webview/ui/tools/WebViewUI:uxf	Ljava/lang/String;
    //   901: invokestatic 294	com/tencent/mm/sdk/platformtools/bo:isNullOrNil	(Ljava/lang/String;)Z
    //   904: ifne +107 -> 1011
    //   907: aload_0
    //   908: getfield 17	com/tencent/mm/plugin/webview/ui/tools/j$12:utN	Lcom/tencent/mm/plugin/webview/ui/tools/j;
    //   911: invokevirtual 106	com/tencent/mm/plugin/webview/ui/tools/j:cZv	()Lcom/tencent/mm/plugin/webview/ui/tools/WebViewUI;
    //   914: getfield 297	com/tencent/mm/plugin/webview/ui/tools/WebViewUI:uxe	Ljava/lang/String;
    //   917: invokestatic 294	com/tencent/mm/sdk/platformtools/bo:isNullOrNil	(Ljava/lang/String;)Z
    //   920: ifne +91 -> 1011
    //   923: aload_0
    //   924: getfield 17	com/tencent/mm/plugin/webview/ui/tools/j$12:utN	Lcom/tencent/mm/plugin/webview/ui/tools/j;
    //   927: invokevirtual 106	com/tencent/mm/plugin/webview/ui/tools/j:cZv	()Lcom/tencent/mm/plugin/webview/ui/tools/WebViewUI;
    //   930: getfield 290	com/tencent/mm/plugin/webview/ui/tools/WebViewUI:uxf	Ljava/lang/String;
    //   933: aload_0
    //   934: getfield 17	com/tencent/mm/plugin/webview/ui/tools/j$12:utN	Lcom/tencent/mm/plugin/webview/ui/tools/j;
    //   937: invokevirtual 106	com/tencent/mm/plugin/webview/ui/tools/j:cZv	()Lcom/tencent/mm/plugin/webview/ui/tools/WebViewUI;
    //   940: getfield 297	com/tencent/mm/plugin/webview/ui/tools/WebViewUI:uxe	Ljava/lang/String;
    //   943: invokevirtual 300	java/lang/String:startsWith	(Ljava/lang/String;)Z
    //   946: ifne +65 -> 1011
    //   949: aload 6
    //   951: sipush 323
    //   954: invokestatic 227	com/tencent/mm/plugin/webview/ui/tools/j:a	(Lcom/tencent/mm/protocal/JsapiPermissionWrapper;I)Z
    //   957: ifeq +54 -> 1011
    //   960: aload_0
    //   961: getfield 17	com/tencent/mm/plugin/webview/ui/tools/j$12:utN	Lcom/tencent/mm/plugin/webview/ui/tools/j;
    //   964: invokevirtual 303	com/tencent/mm/plugin/webview/ui/tools/j:cZQ	()Z
    //   967: ifeq +44 -> 1011
    //   970: aload_0
    //   971: getfield 17	com/tencent/mm/plugin/webview/ui/tools/j$12:utN	Lcom/tencent/mm/plugin/webview/ui/tools/j;
    //   974: iconst_3
    //   975: invokevirtual 213	com/tencent/mm/plugin/webview/ui/tools/j:Jn	(I)Z
    //   978: ifeq +33 -> 1011
    //   981: aload_1
    //   982: iconst_3
    //   983: aload_0
    //   984: getfield 17	com/tencent/mm/plugin/webview/ui/tools/j$12:utN	Lcom/tencent/mm/plugin/webview/ui/tools/j;
    //   987: invokevirtual 106	com/tencent/mm/plugin/webview/ui/tools/j:cZv	()Lcom/tencent/mm/plugin/webview/ui/tools/WebViewUI;
    //   990: ldc_w 304
    //   993: invokevirtual 139	com/tencent/mm/plugin/webview/ui/tools/WebViewUI:getString	(I)Ljava/lang/String;
    //   996: ldc_w 305
    //   999: aload 6
    //   1001: sipush 323
    //   1004: invokestatic 232	com/tencent/mm/plugin/webview/ui/tools/j:b	(Lcom/tencent/mm/protocal/JsapiPermissionWrapper;I)Z
    //   1007: invokevirtual 235	com/tencent/mm/ui/base/l:a	(ILjava/lang/CharSequence;IZ)Landroid/view/MenuItem;
    //   1010: pop
    //   1011: aload_0
    //   1012: getfield 17	com/tencent/mm/plugin/webview/ui/tools/j$12:utN	Lcom/tencent/mm/plugin/webview/ui/tools/j;
    //   1015: invokevirtual 308	com/tencent/mm/plugin/webview/ui/tools/a:cZv	()Lcom/tencent/mm/plugin/webview/ui/tools/WebViewUI;
    //   1018: invokevirtual 312	com/tencent/mm/plugin/webview/ui/tools/WebViewUI:getIntent	()Landroid/content/Intent;
    //   1021: ldc_w 314
    //   1024: invokevirtual 319	android/content/Intent:getStringExtra	(Ljava/lang/String;)Ljava/lang/String;
    //   1027: astore 4
    //   1029: aload_0
    //   1030: getfield 17	com/tencent/mm/plugin/webview/ui/tools/j$12:utN	Lcom/tencent/mm/plugin/webview/ui/tools/j;
    //   1033: invokevirtual 308	com/tencent/mm/plugin/webview/ui/tools/a:cZv	()Lcom/tencent/mm/plugin/webview/ui/tools/WebViewUI;
    //   1036: invokevirtual 312	com/tencent/mm/plugin/webview/ui/tools/WebViewUI:getIntent	()Landroid/content/Intent;
    //   1039: ldc_w 321
    //   1042: ldc2_w 322
    //   1045: invokevirtual 327	android/content/Intent:getLongExtra	(Ljava/lang/String;J)J
    //   1048: lstore 9
    //   1050: aload_0
    //   1051: getfield 17	com/tencent/mm/plugin/webview/ui/tools/j$12:utN	Lcom/tencent/mm/plugin/webview/ui/tools/j;
    //   1054: bipush 23
    //   1056: invokestatic 209	com/tencent/mm/plugin/webview/ui/tools/j:c	(Lcom/tencent/mm/plugin/webview/ui/tools/j;I)Z
    //   1059: ifeq +48 -> 1107
    //   1062: aload_0
    //   1063: getfield 17	com/tencent/mm/plugin/webview/ui/tools/j$12:utN	Lcom/tencent/mm/plugin/webview/ui/tools/j;
    //   1066: invokevirtual 106	com/tencent/mm/plugin/webview/ui/tools/j:cZv	()Lcom/tencent/mm/plugin/webview/ui/tools/WebViewUI;
    //   1069: getfield 267	com/tencent/mm/plugin/webview/ui/tools/WebViewUI:icy	Lcom/tencent/mm/plugin/webview/stub/d;
    //   1072: lload 9
    //   1074: aload 4
    //   1076: invokeinterface 331 4 0
    //   1081: ifeq +26 -> 1107
    //   1084: aload_1
    //   1085: bipush 23
    //   1087: aload_0
    //   1088: getfield 17	com/tencent/mm/plugin/webview/ui/tools/j$12:utN	Lcom/tencent/mm/plugin/webview/ui/tools/j;
    //   1091: invokevirtual 106	com/tencent/mm/plugin/webview/ui/tools/j:cZv	()Lcom/tencent/mm/plugin/webview/ui/tools/WebViewUI;
    //   1094: ldc_w 332
    //   1097: invokevirtual 139	com/tencent/mm/plugin/webview/ui/tools/WebViewUI:getString	(I)Ljava/lang/String;
    //   1100: ldc_w 333
    //   1103: invokevirtual 143	com/tencent/mm/ui/base/l:a	(ILjava/lang/CharSequence;I)Landroid/view/MenuItem;
    //   1106: pop
    //   1107: aload_0
    //   1108: getfield 17	com/tencent/mm/plugin/webview/ui/tools/j$12:utN	Lcom/tencent/mm/plugin/webview/ui/tools/j;
    //   1111: bipush 31
    //   1113: invokestatic 209	com/tencent/mm/plugin/webview/ui/tools/j:c	(Lcom/tencent/mm/plugin/webview/ui/tools/j;I)Z
    //   1116: ifeq +26 -> 1142
    //   1119: aload_1
    //   1120: bipush 31
    //   1122: aload_0
    //   1123: getfield 17	com/tencent/mm/plugin/webview/ui/tools/j$12:utN	Lcom/tencent/mm/plugin/webview/ui/tools/j;
    //   1126: invokevirtual 106	com/tencent/mm/plugin/webview/ui/tools/j:cZv	()Lcom/tencent/mm/plugin/webview/ui/tools/WebViewUI;
    //   1129: ldc_w 334
    //   1132: invokevirtual 139	com/tencent/mm/plugin/webview/ui/tools/WebViewUI:getString	(I)Ljava/lang/String;
    //   1135: ldc_w 335
    //   1138: invokevirtual 143	com/tencent/mm/ui/base/l:a	(ILjava/lang/CharSequence;I)Landroid/view/MenuItem;
    //   1141: pop
    //   1142: aload_0
    //   1143: getfield 17	com/tencent/mm/plugin/webview/ui/tools/j$12:utN	Lcom/tencent/mm/plugin/webview/ui/tools/j;
    //   1146: bipush 6
    //   1148: invokestatic 209	com/tencent/mm/plugin/webview/ui/tools/j:c	(Lcom/tencent/mm/plugin/webview/ui/tools/j;I)Z
    //   1151: ifeq +55 -> 1206
    //   1154: aload 6
    //   1156: bipush 44
    //   1158: invokestatic 227	com/tencent/mm/plugin/webview/ui/tools/j:a	(Lcom/tencent/mm/protocal/JsapiPermissionWrapper;I)Z
    //   1161: ifeq +45 -> 1206
    //   1164: aload_0
    //   1165: getfield 17	com/tencent/mm/plugin/webview/ui/tools/j$12:utN	Lcom/tencent/mm/plugin/webview/ui/tools/j;
    //   1168: bipush 6
    //   1170: invokevirtual 213	com/tencent/mm/plugin/webview/ui/tools/j:Jn	(I)Z
    //   1173: ifeq +33 -> 1206
    //   1176: aload_1
    //   1177: bipush 6
    //   1179: aload_0
    //   1180: getfield 17	com/tencent/mm/plugin/webview/ui/tools/j$12:utN	Lcom/tencent/mm/plugin/webview/ui/tools/j;
    //   1183: invokevirtual 106	com/tencent/mm/plugin/webview/ui/tools/j:cZv	()Lcom/tencent/mm/plugin/webview/ui/tools/WebViewUI;
    //   1186: ldc_w 336
    //   1189: invokevirtual 139	com/tencent/mm/plugin/webview/ui/tools/WebViewUI:getString	(I)Ljava/lang/String;
    //   1192: ldc_w 337
    //   1195: aload 6
    //   1197: bipush 44
    //   1199: invokestatic 232	com/tencent/mm/plugin/webview/ui/tools/j:b	(Lcom/tencent/mm/protocal/JsapiPermissionWrapper;I)Z
    //   1202: invokevirtual 235	com/tencent/mm/ui/base/l:a	(ILjava/lang/CharSequence;IZ)Landroid/view/MenuItem;
    //   1205: pop
    //   1206: aload 6
    //   1208: getfield 343	com/tencent/mm/protocal/JsapiPermissionWrapper:vxM	[B
    //   1211: ifnull +198 -> 1409
    //   1214: aload_0
    //   1215: getfield 17	com/tencent/mm/plugin/webview/ui/tools/j$12:utN	Lcom/tencent/mm/plugin/webview/ui/tools/j;
    //   1218: invokevirtual 106	com/tencent/mm/plugin/webview/ui/tools/j:cZv	()Lcom/tencent/mm/plugin/webview/ui/tools/WebViewUI;
    //   1221: getfield 287	com/tencent/mm/plugin/webview/ui/tools/WebViewUI:uvu	Z
    //   1224: ifeq +185 -> 1409
    //   1227: aload_0
    //   1228: getfield 17	com/tencent/mm/plugin/webview/ui/tools/j$12:utN	Lcom/tencent/mm/plugin/webview/ui/tools/j;
    //   1231: invokevirtual 106	com/tencent/mm/plugin/webview/ui/tools/j:cZv	()Lcom/tencent/mm/plugin/webview/ui/tools/WebViewUI;
    //   1234: getfield 290	com/tencent/mm/plugin/webview/ui/tools/WebViewUI:uxf	Ljava/lang/String;
    //   1237: invokestatic 294	com/tencent/mm/sdk/platformtools/bo:isNullOrNil	(Ljava/lang/String;)Z
    //   1240: ifne +169 -> 1409
    //   1243: aload_0
    //   1244: getfield 17	com/tencent/mm/plugin/webview/ui/tools/j$12:utN	Lcom/tencent/mm/plugin/webview/ui/tools/j;
    //   1247: invokevirtual 106	com/tencent/mm/plugin/webview/ui/tools/j:cZv	()Lcom/tencent/mm/plugin/webview/ui/tools/WebViewUI;
    //   1250: getfield 297	com/tencent/mm/plugin/webview/ui/tools/WebViewUI:uxe	Ljava/lang/String;
    //   1253: invokestatic 294	com/tencent/mm/sdk/platformtools/bo:isNullOrNil	(Ljava/lang/String;)Z
    //   1256: ifne +153 -> 1409
    //   1259: aload_0
    //   1260: getfield 17	com/tencent/mm/plugin/webview/ui/tools/j$12:utN	Lcom/tencent/mm/plugin/webview/ui/tools/j;
    //   1263: invokevirtual 106	com/tencent/mm/plugin/webview/ui/tools/j:cZv	()Lcom/tencent/mm/plugin/webview/ui/tools/WebViewUI;
    //   1266: getfield 290	com/tencent/mm/plugin/webview/ui/tools/WebViewUI:uxf	Ljava/lang/String;
    //   1269: aload_0
    //   1270: getfield 17	com/tencent/mm/plugin/webview/ui/tools/j$12:utN	Lcom/tencent/mm/plugin/webview/ui/tools/j;
    //   1273: invokevirtual 106	com/tencent/mm/plugin/webview/ui/tools/j:cZv	()Lcom/tencent/mm/plugin/webview/ui/tools/WebViewUI;
    //   1276: getfield 297	com/tencent/mm/plugin/webview/ui/tools/WebViewUI:uxe	Ljava/lang/String;
    //   1279: invokevirtual 300	java/lang/String:startsWith	(Ljava/lang/String;)Z
    //   1282: ifeq +127 -> 1409
    //   1285: aload_0
    //   1286: getfield 17	com/tencent/mm/plugin/webview/ui/tools/j$12:utN	Lcom/tencent/mm/plugin/webview/ui/tools/j;
    //   1289: invokevirtual 308	com/tencent/mm/plugin/webview/ui/tools/a:cZv	()Lcom/tencent/mm/plugin/webview/ui/tools/WebViewUI;
    //   1292: invokevirtual 312	com/tencent/mm/plugin/webview/ui/tools/WebViewUI:getIntent	()Landroid/content/Intent;
    //   1295: ldc_w 345
    //   1298: iconst_1
    //   1299: invokevirtual 349	android/content/Intent:getBooleanExtra	(Ljava/lang/String;Z)Z
    //   1302: ifeq +107 -> 1409
    //   1305: aload_0
    //   1306: getfield 17	com/tencent/mm/plugin/webview/ui/tools/j$12:utN	Lcom/tencent/mm/plugin/webview/ui/tools/j;
    //   1309: invokevirtual 303	com/tencent/mm/plugin/webview/ui/tools/j:cZQ	()Z
    //   1312: ifeq +97 -> 1409
    //   1315: aload_0
    //   1316: getfield 17	com/tencent/mm/plugin/webview/ui/tools/j$12:utN	Lcom/tencent/mm/plugin/webview/ui/tools/j;
    //   1319: bipush 12
    //   1321: invokestatic 209	com/tencent/mm/plugin/webview/ui/tools/j:c	(Lcom/tencent/mm/plugin/webview/ui/tools/j;I)Z
    //   1324: ifeq +38 -> 1362
    //   1327: aload_0
    //   1328: getfield 17	com/tencent/mm/plugin/webview/ui/tools/j$12:utN	Lcom/tencent/mm/plugin/webview/ui/tools/j;
    //   1331: bipush 12
    //   1333: invokevirtual 213	com/tencent/mm/plugin/webview/ui/tools/j:Jn	(I)Z
    //   1336: ifeq +26 -> 1362
    //   1339: aload_1
    //   1340: bipush 12
    //   1342: aload_0
    //   1343: getfield 17	com/tencent/mm/plugin/webview/ui/tools/j$12:utN	Lcom/tencent/mm/plugin/webview/ui/tools/j;
    //   1346: invokevirtual 106	com/tencent/mm/plugin/webview/ui/tools/j:cZv	()Lcom/tencent/mm/plugin/webview/ui/tools/WebViewUI;
    //   1349: ldc_w 350
    //   1352: invokevirtual 139	com/tencent/mm/plugin/webview/ui/tools/WebViewUI:getString	(I)Ljava/lang/String;
    //   1355: ldc_w 351
    //   1358: invokevirtual 143	com/tencent/mm/ui/base/l:a	(ILjava/lang/CharSequence;I)Landroid/view/MenuItem;
    //   1361: pop
    //   1362: aload_0
    //   1363: getfield 17	com/tencent/mm/plugin/webview/ui/tools/j$12:utN	Lcom/tencent/mm/plugin/webview/ui/tools/j;
    //   1366: bipush 9
    //   1368: invokestatic 209	com/tencent/mm/plugin/webview/ui/tools/j:c	(Lcom/tencent/mm/plugin/webview/ui/tools/j;I)Z
    //   1371: ifeq +38 -> 1409
    //   1374: aload_0
    //   1375: getfield 17	com/tencent/mm/plugin/webview/ui/tools/j$12:utN	Lcom/tencent/mm/plugin/webview/ui/tools/j;
    //   1378: bipush 9
    //   1380: invokevirtual 213	com/tencent/mm/plugin/webview/ui/tools/j:Jn	(I)Z
    //   1383: ifeq +26 -> 1409
    //   1386: aload_1
    //   1387: bipush 9
    //   1389: aload_0
    //   1390: getfield 17	com/tencent/mm/plugin/webview/ui/tools/j$12:utN	Lcom/tencent/mm/plugin/webview/ui/tools/j;
    //   1393: invokevirtual 106	com/tencent/mm/plugin/webview/ui/tools/j:cZv	()Lcom/tencent/mm/plugin/webview/ui/tools/WebViewUI;
    //   1396: ldc_w 352
    //   1399: invokevirtual 139	com/tencent/mm/plugin/webview/ui/tools/WebViewUI:getString	(I)Ljava/lang/String;
    //   1402: ldc_w 353
    //   1405: invokevirtual 143	com/tencent/mm/ui/base/l:a	(ILjava/lang/CharSequence;I)Landroid/view/MenuItem;
    //   1408: pop
    //   1409: aload_0
    //   1410: getfield 17	com/tencent/mm/plugin/webview/ui/tools/j$12:utN	Lcom/tencent/mm/plugin/webview/ui/tools/j;
    //   1413: invokevirtual 308	com/tencent/mm/plugin/webview/ui/tools/a:cZv	()Lcom/tencent/mm/plugin/webview/ui/tools/WebViewUI;
    //   1416: invokevirtual 312	com/tencent/mm/plugin/webview/ui/tools/WebViewUI:getIntent	()Landroid/content/Intent;
    //   1419: ldc_w 355
    //   1422: invokevirtual 319	android/content/Intent:getStringExtra	(Ljava/lang/String;)Ljava/lang/String;
    //   1425: astore 4
    //   1427: aload 4
    //   1429: invokestatic 294	com/tencent/mm/sdk/platformtools/bo:isNullOrNil	(Ljava/lang/String;)Z
    //   1432: ifne +44 -> 1476
    //   1435: aload_0
    //   1436: getfield 17	com/tencent/mm/plugin/webview/ui/tools/j$12:utN	Lcom/tencent/mm/plugin/webview/ui/tools/j;
    //   1439: invokevirtual 106	com/tencent/mm/plugin/webview/ui/tools/j:cZv	()Lcom/tencent/mm/plugin/webview/ui/tools/WebViewUI;
    //   1442: getfield 267	com/tencent/mm/plugin/webview/ui/tools/WebViewUI:icy	Lcom/tencent/mm/plugin/webview/stub/d;
    //   1445: aload 4
    //   1447: invokeinterface 358 2 0
    //   1452: istore 11
    //   1454: iload 11
    //   1456: ifne +1782 -> 3238
    //   1459: aload_0
    //   1460: getfield 17	com/tencent/mm/plugin/webview/ui/tools/j$12:utN	Lcom/tencent/mm/plugin/webview/ui/tools/j;
    //   1463: invokevirtual 106	com/tencent/mm/plugin/webview/ui/tools/j:cZv	()Lcom/tencent/mm/plugin/webview/ui/tools/WebViewUI;
    //   1466: getfield 267	com/tencent/mm/plugin/webview/ui/tools/WebViewUI:icy	Lcom/tencent/mm/plugin/webview/stub/d;
    //   1469: aload 4
    //   1471: invokeinterface 361 2 0
    //   1476: aload_0
    //   1477: getfield 17	com/tencent/mm/plugin/webview/ui/tools/j$12:utN	Lcom/tencent/mm/plugin/webview/ui/tools/j;
    //   1480: bipush 34
    //   1482: invokestatic 209	com/tencent/mm/plugin/webview/ui/tools/j:c	(Lcom/tencent/mm/plugin/webview/ui/tools/j;I)Z
    //   1485: ifeq +57 -> 1542
    //   1488: aload 6
    //   1490: sipush 313
    //   1493: invokestatic 227	com/tencent/mm/plugin/webview/ui/tools/j:a	(Lcom/tencent/mm/protocal/JsapiPermissionWrapper;I)Z
    //   1496: ifeq +46 -> 1542
    //   1499: aload_0
    //   1500: getfield 17	com/tencent/mm/plugin/webview/ui/tools/j$12:utN	Lcom/tencent/mm/plugin/webview/ui/tools/j;
    //   1503: bipush 34
    //   1505: invokevirtual 213	com/tencent/mm/plugin/webview/ui/tools/j:Jn	(I)Z
    //   1508: ifeq +34 -> 1542
    //   1511: aload_1
    //   1512: bipush 34
    //   1514: aload_0
    //   1515: getfield 17	com/tencent/mm/plugin/webview/ui/tools/j$12:utN	Lcom/tencent/mm/plugin/webview/ui/tools/j;
    //   1518: invokevirtual 106	com/tencent/mm/plugin/webview/ui/tools/j:cZv	()Lcom/tencent/mm/plugin/webview/ui/tools/WebViewUI;
    //   1521: ldc_w 362
    //   1524: invokevirtual 139	com/tencent/mm/plugin/webview/ui/tools/WebViewUI:getString	(I)Ljava/lang/String;
    //   1527: ldc_w 363
    //   1530: aload 6
    //   1532: sipush 313
    //   1535: invokestatic 232	com/tencent/mm/plugin/webview/ui/tools/j:b	(Lcom/tencent/mm/protocal/JsapiPermissionWrapper;I)Z
    //   1538: invokevirtual 235	com/tencent/mm/ui/base/l:a	(ILjava/lang/CharSequence;IZ)Landroid/view/MenuItem;
    //   1541: pop
    //   1542: aload_0
    //   1543: getfield 17	com/tencent/mm/plugin/webview/ui/tools/j$12:utN	Lcom/tencent/mm/plugin/webview/ui/tools/j;
    //   1546: bipush 7
    //   1548: invokestatic 209	com/tencent/mm/plugin/webview/ui/tools/j:c	(Lcom/tencent/mm/plugin/webview/ui/tools/j;I)Z
    //   1551: ifeq +55 -> 1606
    //   1554: aload 6
    //   1556: bipush 45
    //   1558: invokestatic 227	com/tencent/mm/plugin/webview/ui/tools/j:a	(Lcom/tencent/mm/protocal/JsapiPermissionWrapper;I)Z
    //   1561: ifeq +45 -> 1606
    //   1564: aload_0
    //   1565: getfield 17	com/tencent/mm/plugin/webview/ui/tools/j$12:utN	Lcom/tencent/mm/plugin/webview/ui/tools/j;
    //   1568: bipush 7
    //   1570: invokevirtual 213	com/tencent/mm/plugin/webview/ui/tools/j:Jn	(I)Z
    //   1573: ifeq +33 -> 1606
    //   1576: aload_1
    //   1577: bipush 7
    //   1579: aload_0
    //   1580: getfield 17	com/tencent/mm/plugin/webview/ui/tools/j$12:utN	Lcom/tencent/mm/plugin/webview/ui/tools/j;
    //   1583: invokevirtual 106	com/tencent/mm/plugin/webview/ui/tools/j:cZv	()Lcom/tencent/mm/plugin/webview/ui/tools/WebViewUI;
    //   1586: ldc_w 364
    //   1589: invokevirtual 139	com/tencent/mm/plugin/webview/ui/tools/WebViewUI:getString	(I)Ljava/lang/String;
    //   1592: ldc_w 365
    //   1595: aload 6
    //   1597: bipush 45
    //   1599: invokestatic 232	com/tencent/mm/plugin/webview/ui/tools/j:b	(Lcom/tencent/mm/protocal/JsapiPermissionWrapper;I)Z
    //   1602: invokevirtual 235	com/tencent/mm/ui/base/l:a	(ILjava/lang/CharSequence;IZ)Landroid/view/MenuItem;
    //   1605: pop
    //   1606: aload_0
    //   1607: getfield 17	com/tencent/mm/plugin/webview/ui/tools/j$12:utN	Lcom/tencent/mm/plugin/webview/ui/tools/j;
    //   1610: bipush 37
    //   1612: invokestatic 209	com/tencent/mm/plugin/webview/ui/tools/j:c	(Lcom/tencent/mm/plugin/webview/ui/tools/j;I)Z
    //   1615: ifeq +62 -> 1677
    //   1618: aload_0
    //   1619: getfield 17	com/tencent/mm/plugin/webview/ui/tools/j$12:utN	Lcom/tencent/mm/plugin/webview/ui/tools/j;
    //   1622: invokevirtual 106	com/tencent/mm/plugin/webview/ui/tools/j:cZv	()Lcom/tencent/mm/plugin/webview/ui/tools/WebViewUI;
    //   1625: pop
    //   1626: aload_0
    //   1627: getfield 17	com/tencent/mm/plugin/webview/ui/tools/j$12:utN	Lcom/tencent/mm/plugin/webview/ui/tools/j;
    //   1630: invokevirtual 106	com/tencent/mm/plugin/webview/ui/tools/j:cZv	()Lcom/tencent/mm/plugin/webview/ui/tools/WebViewUI;
    //   1633: getfield 255	com/tencent/mm/plugin/webview/ui/tools/WebViewUI:pzf	Lcom/tencent/mm/ui/widget/MMWebView;
    //   1636: invokestatic 370	com/tencent/mm/plugin/webview/b:b	(Lcom/tencent/xweb/WebView;)Z
    //   1639: ifeq +38 -> 1677
    //   1642: aload_0
    //   1643: getfield 17	com/tencent/mm/plugin/webview/ui/tools/j$12:utN	Lcom/tencent/mm/plugin/webview/ui/tools/j;
    //   1646: bipush 37
    //   1648: invokevirtual 213	com/tencent/mm/plugin/webview/ui/tools/j:Jn	(I)Z
    //   1651: ifeq +26 -> 1677
    //   1654: aload_1
    //   1655: bipush 37
    //   1657: aload_0
    //   1658: getfield 17	com/tencent/mm/plugin/webview/ui/tools/j$12:utN	Lcom/tencent/mm/plugin/webview/ui/tools/j;
    //   1661: invokevirtual 106	com/tencent/mm/plugin/webview/ui/tools/j:cZv	()Lcom/tencent/mm/plugin/webview/ui/tools/WebViewUI;
    //   1664: ldc_w 371
    //   1667: invokevirtual 139	com/tencent/mm/plugin/webview/ui/tools/WebViewUI:getString	(I)Ljava/lang/String;
    //   1670: ldc_w 372
    //   1673: invokevirtual 143	com/tencent/mm/ui/base/l:a	(ILjava/lang/CharSequence;I)Landroid/view/MenuItem;
    //   1676: pop
    //   1677: aload_0
    //   1678: getfield 17	com/tencent/mm/plugin/webview/ui/tools/j$12:utN	Lcom/tencent/mm/plugin/webview/ui/tools/j;
    //   1681: bipush 24
    //   1683: invokestatic 209	com/tencent/mm/plugin/webview/ui/tools/j:c	(Lcom/tencent/mm/plugin/webview/ui/tools/j;I)Z
    //   1686: ifeq +133 -> 1819
    //   1689: aload 6
    //   1691: bipush 43
    //   1693: invokestatic 227	com/tencent/mm/plugin/webview/ui/tools/j:a	(Lcom/tencent/mm/protocal/JsapiPermissionWrapper;I)Z
    //   1696: ifeq +123 -> 1819
    //   1699: aload_0
    //   1700: getfield 17	com/tencent/mm/plugin/webview/ui/tools/j$12:utN	Lcom/tencent/mm/plugin/webview/ui/tools/j;
    //   1703: bipush 24
    //   1705: invokevirtual 213	com/tencent/mm/plugin/webview/ui/tools/j:Jn	(I)Z
    //   1708: ifeq +111 -> 1819
    //   1711: aload_0
    //   1712: getfield 17	com/tencent/mm/plugin/webview/ui/tools/j$12:utN	Lcom/tencent/mm/plugin/webview/ui/tools/j;
    //   1715: invokevirtual 106	com/tencent/mm/plugin/webview/ui/tools/j:cZv	()Lcom/tencent/mm/plugin/webview/ui/tools/WebViewUI;
    //   1718: ldc_w 374
    //   1721: invokestatic 380	com/tencent/mm/pluginsdk/model/app/p:u	(Landroid/content/Context;Ljava/lang/String;)Z
    //   1724: ifne +95 -> 1819
    //   1727: new 239	android/os/Bundle
    //   1730: astore 4
    //   1732: aload 4
    //   1734: invokespecial 240	android/os/Bundle:<init>	()V
    //   1737: aload 4
    //   1739: ldc_w 382
    //   1742: ldc_w 384
    //   1745: invokevirtual 263	android/os/Bundle:putString	(Ljava/lang/String;Ljava/lang/String;)V
    //   1748: aload_0
    //   1749: getfield 17	com/tencent/mm/plugin/webview/ui/tools/j$12:utN	Lcom/tencent/mm/plugin/webview/ui/tools/j;
    //   1752: invokevirtual 106	com/tencent/mm/plugin/webview/ui/tools/j:cZv	()Lcom/tencent/mm/plugin/webview/ui/tools/WebViewUI;
    //   1755: getfield 267	com/tencent/mm/plugin/webview/ui/tools/WebViewUI:icy	Lcom/tencent/mm/plugin/webview/stub/d;
    //   1758: bipush 71
    //   1760: aload 4
    //   1762: invokeinterface 273 3 0
    //   1767: astore 4
    //   1769: aload 4
    //   1771: ifnull +1686 -> 3457
    //   1774: aload 4
    //   1776: ldc_w 384
    //   1779: invokevirtual 387	android/os/Bundle:getBoolean	(Ljava/lang/String;)Z
    //   1782: istore 11
    //   1784: iload 11
    //   1786: ifeq +33 -> 1819
    //   1789: aload_1
    //   1790: bipush 24
    //   1792: aload_0
    //   1793: getfield 17	com/tencent/mm/plugin/webview/ui/tools/j$12:utN	Lcom/tencent/mm/plugin/webview/ui/tools/j;
    //   1796: invokevirtual 106	com/tencent/mm/plugin/webview/ui/tools/j:cZv	()Lcom/tencent/mm/plugin/webview/ui/tools/WebViewUI;
    //   1799: ldc_w 388
    //   1802: invokevirtual 139	com/tencent/mm/plugin/webview/ui/tools/WebViewUI:getString	(I)Ljava/lang/String;
    //   1805: ldc_w 389
    //   1808: aload 6
    //   1810: bipush 43
    //   1812: invokestatic 232	com/tencent/mm/plugin/webview/ui/tools/j:b	(Lcom/tencent/mm/protocal/JsapiPermissionWrapper;I)Z
    //   1815: invokevirtual 235	com/tencent/mm/ui/base/l:a	(ILjava/lang/CharSequence;IZ)Landroid/view/MenuItem;
    //   1818: pop
    //   1819: aload_0
    //   1820: getfield 17	com/tencent/mm/plugin/webview/ui/tools/j$12:utN	Lcom/tencent/mm/plugin/webview/ui/tools/j;
    //   1823: bipush 11
    //   1825: invokestatic 209	com/tencent/mm/plugin/webview/ui/tools/j:c	(Lcom/tencent/mm/plugin/webview/ui/tools/j;I)Z
    //   1828: ifeq +55 -> 1883
    //   1831: aload 6
    //   1833: bipush 18
    //   1835: invokestatic 227	com/tencent/mm/plugin/webview/ui/tools/j:a	(Lcom/tencent/mm/protocal/JsapiPermissionWrapper;I)Z
    //   1838: ifeq +45 -> 1883
    //   1841: aload_0
    //   1842: getfield 17	com/tencent/mm/plugin/webview/ui/tools/j$12:utN	Lcom/tencent/mm/plugin/webview/ui/tools/j;
    //   1845: bipush 11
    //   1847: invokevirtual 213	com/tencent/mm/plugin/webview/ui/tools/j:Jn	(I)Z
    //   1850: ifeq +33 -> 1883
    //   1853: aload_1
    //   1854: bipush 11
    //   1856: aload_0
    //   1857: getfield 17	com/tencent/mm/plugin/webview/ui/tools/j$12:utN	Lcom/tencent/mm/plugin/webview/ui/tools/j;
    //   1860: invokevirtual 106	com/tencent/mm/plugin/webview/ui/tools/j:cZv	()Lcom/tencent/mm/plugin/webview/ui/tools/WebViewUI;
    //   1863: ldc_w 390
    //   1866: invokevirtual 139	com/tencent/mm/plugin/webview/ui/tools/WebViewUI:getString	(I)Ljava/lang/String;
    //   1869: ldc_w 391
    //   1872: aload 6
    //   1874: bipush 18
    //   1876: invokestatic 232	com/tencent/mm/plugin/webview/ui/tools/j:b	(Lcom/tencent/mm/protocal/JsapiPermissionWrapper;I)Z
    //   1879: invokevirtual 235	com/tencent/mm/ui/base/l:a	(ILjava/lang/CharSequence;IZ)Landroid/view/MenuItem;
    //   1882: pop
    //   1883: aload_0
    //   1884: getfield 17	com/tencent/mm/plugin/webview/ui/tools/j$12:utN	Lcom/tencent/mm/plugin/webview/ui/tools/j;
    //   1887: bipush 28
    //   1889: invokestatic 209	com/tencent/mm/plugin/webview/ui/tools/j:c	(Lcom/tencent/mm/plugin/webview/ui/tools/j;I)Z
    //   1892: ifeq +38 -> 1930
    //   1895: aload_0
    //   1896: getfield 17	com/tencent/mm/plugin/webview/ui/tools/j$12:utN	Lcom/tencent/mm/plugin/webview/ui/tools/j;
    //   1899: bipush 28
    //   1901: invokevirtual 213	com/tencent/mm/plugin/webview/ui/tools/j:Jn	(I)Z
    //   1904: ifeq +26 -> 1930
    //   1907: aload_1
    //   1908: bipush 28
    //   1910: aload_0
    //   1911: getfield 17	com/tencent/mm/plugin/webview/ui/tools/j$12:utN	Lcom/tencent/mm/plugin/webview/ui/tools/j;
    //   1914: invokevirtual 106	com/tencent/mm/plugin/webview/ui/tools/j:cZv	()Lcom/tencent/mm/plugin/webview/ui/tools/WebViewUI;
    //   1917: ldc_w 392
    //   1920: invokevirtual 139	com/tencent/mm/plugin/webview/ui/tools/WebViewUI:getString	(I)Ljava/lang/String;
    //   1923: ldc_w 393
    //   1926: invokevirtual 143	com/tencent/mm/ui/base/l:a	(ILjava/lang/CharSequence;I)Landroid/view/MenuItem;
    //   1929: pop
    //   1930: aload_0
    //   1931: getfield 17	com/tencent/mm/plugin/webview/ui/tools/j$12:utN	Lcom/tencent/mm/plugin/webview/ui/tools/j;
    //   1934: bipush 14
    //   1936: invokestatic 209	com/tencent/mm/plugin/webview/ui/tools/j:c	(Lcom/tencent/mm/plugin/webview/ui/tools/j;I)Z
    //   1939: ifeq +68 -> 2007
    //   1942: aload 6
    //   1944: bipush 73
    //   1946: invokestatic 227	com/tencent/mm/plugin/webview/ui/tools/j:a	(Lcom/tencent/mm/protocal/JsapiPermissionWrapper;I)Z
    //   1949: ifeq +58 -> 2007
    //   1952: aload_0
    //   1953: getfield 17	com/tencent/mm/plugin/webview/ui/tools/j$12:utN	Lcom/tencent/mm/plugin/webview/ui/tools/j;
    //   1956: bipush 14
    //   1958: invokevirtual 213	com/tencent/mm/plugin/webview/ui/tools/j:Jn	(I)Z
    //   1961: ifeq +46 -> 2007
    //   1964: aload_0
    //   1965: getfield 17	com/tencent/mm/plugin/webview/ui/tools/j$12:utN	Lcom/tencent/mm/plugin/webview/ui/tools/j;
    //   1968: invokevirtual 106	com/tencent/mm/plugin/webview/ui/tools/j:cZv	()Lcom/tencent/mm/plugin/webview/ui/tools/WebViewUI;
    //   1971: getfield 396	com/tencent/mm/plugin/webview/ui/tools/WebViewUI:uvZ	Z
    //   1974: ifne +33 -> 2007
    //   1977: aload_1
    //   1978: bipush 14
    //   1980: aload_0
    //   1981: getfield 17	com/tencent/mm/plugin/webview/ui/tools/j$12:utN	Lcom/tencent/mm/plugin/webview/ui/tools/j;
    //   1984: invokevirtual 106	com/tencent/mm/plugin/webview/ui/tools/j:cZv	()Lcom/tencent/mm/plugin/webview/ui/tools/WebViewUI;
    //   1987: ldc_w 397
    //   1990: invokevirtual 139	com/tencent/mm/plugin/webview/ui/tools/WebViewUI:getString	(I)Ljava/lang/String;
    //   1993: ldc_w 398
    //   1996: aload 6
    //   1998: bipush 73
    //   2000: invokestatic 232	com/tencent/mm/plugin/webview/ui/tools/j:b	(Lcom/tencent/mm/protocal/JsapiPermissionWrapper;I)Z
    //   2003: invokevirtual 235	com/tencent/mm/ui/base/l:a	(ILjava/lang/CharSequence;IZ)Landroid/view/MenuItem;
    //   2006: pop
    //   2007: aload_0
    //   2008: getfield 17	com/tencent/mm/plugin/webview/ui/tools/j$12:utN	Lcom/tencent/mm/plugin/webview/ui/tools/j;
    //   2011: bipush 14
    //   2013: invokestatic 209	com/tencent/mm/plugin/webview/ui/tools/j:c	(Lcom/tencent/mm/plugin/webview/ui/tools/j;I)Z
    //   2016: ifeq +51 -> 2067
    //   2019: aload_0
    //   2020: getfield 17	com/tencent/mm/plugin/webview/ui/tools/j$12:utN	Lcom/tencent/mm/plugin/webview/ui/tools/j;
    //   2023: invokevirtual 106	com/tencent/mm/plugin/webview/ui/tools/j:cZv	()Lcom/tencent/mm/plugin/webview/ui/tools/WebViewUI;
    //   2026: getfield 396	com/tencent/mm/plugin/webview/ui/tools/WebViewUI:uvZ	Z
    //   2029: ifeq +38 -> 2067
    //   2032: aload_0
    //   2033: getfield 17	com/tencent/mm/plugin/webview/ui/tools/j$12:utN	Lcom/tencent/mm/plugin/webview/ui/tools/j;
    //   2036: bipush 14
    //   2038: invokevirtual 213	com/tencent/mm/plugin/webview/ui/tools/j:Jn	(I)Z
    //   2041: ifeq +26 -> 2067
    //   2044: aload_1
    //   2045: bipush 14
    //   2047: aload_0
    //   2048: getfield 17	com/tencent/mm/plugin/webview/ui/tools/j$12:utN	Lcom/tencent/mm/plugin/webview/ui/tools/j;
    //   2051: invokevirtual 106	com/tencent/mm/plugin/webview/ui/tools/j:cZv	()Lcom/tencent/mm/plugin/webview/ui/tools/WebViewUI;
    //   2054: ldc_w 399
    //   2057: invokevirtual 139	com/tencent/mm/plugin/webview/ui/tools/WebViewUI:getString	(I)Ljava/lang/String;
    //   2060: ldc_w 333
    //   2063: invokevirtual 143	com/tencent/mm/ui/base/l:a	(ILjava/lang/CharSequence;I)Landroid/view/MenuItem;
    //   2066: pop
    //   2067: aload_0
    //   2068: getfield 17	com/tencent/mm/plugin/webview/ui/tools/j$12:utN	Lcom/tencent/mm/plugin/webview/ui/tools/j;
    //   2071: bipush 10
    //   2073: invokestatic 209	com/tencent/mm/plugin/webview/ui/tools/j:c	(Lcom/tencent/mm/plugin/webview/ui/tools/j;I)Z
    //   2076: ifeq +55 -> 2131
    //   2079: aload 6
    //   2081: bipush 47
    //   2083: invokestatic 227	com/tencent/mm/plugin/webview/ui/tools/j:a	(Lcom/tencent/mm/protocal/JsapiPermissionWrapper;I)Z
    //   2086: ifeq +45 -> 2131
    //   2089: aload_0
    //   2090: getfield 17	com/tencent/mm/plugin/webview/ui/tools/j$12:utN	Lcom/tencent/mm/plugin/webview/ui/tools/j;
    //   2093: bipush 10
    //   2095: invokevirtual 213	com/tencent/mm/plugin/webview/ui/tools/j:Jn	(I)Z
    //   2098: ifeq +33 -> 2131
    //   2101: aload_1
    //   2102: bipush 10
    //   2104: aload_0
    //   2105: getfield 17	com/tencent/mm/plugin/webview/ui/tools/j$12:utN	Lcom/tencent/mm/plugin/webview/ui/tools/j;
    //   2108: invokevirtual 106	com/tencent/mm/plugin/webview/ui/tools/j:cZv	()Lcom/tencent/mm/plugin/webview/ui/tools/WebViewUI;
    //   2111: ldc_w 400
    //   2114: invokevirtual 139	com/tencent/mm/plugin/webview/ui/tools/WebViewUI:getString	(I)Ljava/lang/String;
    //   2117: ldc_w 401
    //   2120: aload 6
    //   2122: bipush 47
    //   2124: invokestatic 232	com/tencent/mm/plugin/webview/ui/tools/j:b	(Lcom/tencent/mm/protocal/JsapiPermissionWrapper;I)Z
    //   2127: invokevirtual 235	com/tencent/mm/ui/base/l:a	(ILjava/lang/CharSequence;IZ)Landroid/view/MenuItem;
    //   2130: pop
    //   2131: aload_0
    //   2132: getfield 17	com/tencent/mm/plugin/webview/ui/tools/j$12:utN	Lcom/tencent/mm/plugin/webview/ui/tools/j;
    //   2135: bipush 8
    //   2137: invokestatic 209	com/tencent/mm/plugin/webview/ui/tools/j:c	(Lcom/tencent/mm/plugin/webview/ui/tools/j;I)Z
    //   2140: ifeq +87 -> 2227
    //   2143: aload 6
    //   2145: bipush 36
    //   2147: invokestatic 227	com/tencent/mm/plugin/webview/ui/tools/j:a	(Lcom/tencent/mm/protocal/JsapiPermissionWrapper;I)Z
    //   2150: ifeq +77 -> 2227
    //   2153: aload_0
    //   2154: getfield 17	com/tencent/mm/plugin/webview/ui/tools/j$12:utN	Lcom/tencent/mm/plugin/webview/ui/tools/j;
    //   2157: bipush 8
    //   2159: invokevirtual 213	com/tencent/mm/plugin/webview/ui/tools/j:Jn	(I)Z
    //   2162: ifeq +65 -> 2227
    //   2165: aconst_null
    //   2166: astore 4
    //   2168: aload_0
    //   2169: getfield 17	com/tencent/mm/plugin/webview/ui/tools/j$12:utN	Lcom/tencent/mm/plugin/webview/ui/tools/j;
    //   2172: invokevirtual 106	com/tencent/mm/plugin/webview/ui/tools/j:cZv	()Lcom/tencent/mm/plugin/webview/ui/tools/WebViewUI;
    //   2175: getfield 267	com/tencent/mm/plugin/webview/ui/tools/WebViewUI:icy	Lcom/tencent/mm/plugin/webview/stub/d;
    //   2178: invokeinterface 404 1 0
    //   2183: astore 5
    //   2185: aload 5
    //   2187: astore 4
    //   2189: aload 4
    //   2191: invokestatic 294	com/tencent/mm/sdk/platformtools/bo:isNullOrNil	(Ljava/lang/String;)Z
    //   2194: ifne +1269 -> 3463
    //   2197: aload_1
    //   2198: bipush 8
    //   2200: aload_0
    //   2201: getfield 17	com/tencent/mm/plugin/webview/ui/tools/j$12:utN	Lcom/tencent/mm/plugin/webview/ui/tools/j;
    //   2204: invokevirtual 106	com/tencent/mm/plugin/webview/ui/tools/j:cZv	()Lcom/tencent/mm/plugin/webview/ui/tools/WebViewUI;
    //   2207: ldc_w 405
    //   2210: invokevirtual 139	com/tencent/mm/plugin/webview/ui/tools/WebViewUI:getString	(I)Ljava/lang/String;
    //   2213: ldc_w 406
    //   2216: aload 6
    //   2218: bipush 36
    //   2220: invokestatic 232	com/tencent/mm/plugin/webview/ui/tools/j:b	(Lcom/tencent/mm/protocal/JsapiPermissionWrapper;I)Z
    //   2223: invokevirtual 235	com/tencent/mm/ui/base/l:a	(ILjava/lang/CharSequence;IZ)Landroid/view/MenuItem;
    //   2226: pop
    //   2227: aload_0
    //   2228: getfield 17	com/tencent/mm/plugin/webview/ui/tools/j$12:utN	Lcom/tencent/mm/plugin/webview/ui/tools/j;
    //   2231: bipush 33
    //   2233: invokestatic 209	com/tencent/mm/plugin/webview/ui/tools/j:c	(Lcom/tencent/mm/plugin/webview/ui/tools/j;I)Z
    //   2236: ifeq +83 -> 2319
    //   2239: aload 6
    //   2241: bipush 31
    //   2243: invokestatic 227	com/tencent/mm/plugin/webview/ui/tools/j:a	(Lcom/tencent/mm/protocal/JsapiPermissionWrapper;I)Z
    //   2246: ifeq +73 -> 2319
    //   2249: aload_0
    //   2250: getfield 17	com/tencent/mm/plugin/webview/ui/tools/j$12:utN	Lcom/tencent/mm/plugin/webview/ui/tools/j;
    //   2253: bipush 30
    //   2255: invokevirtual 213	com/tencent/mm/plugin/webview/ui/tools/j:Jn	(I)Z
    //   2258: ifeq +61 -> 2319
    //   2261: aload_0
    //   2262: getfield 17	com/tencent/mm/plugin/webview/ui/tools/j$12:utN	Lcom/tencent/mm/plugin/webview/ui/tools/j;
    //   2265: invokevirtual 106	com/tencent/mm/plugin/webview/ui/tools/j:cZv	()Lcom/tencent/mm/plugin/webview/ui/tools/WebViewUI;
    //   2268: getfield 267	com/tencent/mm/plugin/webview/ui/tools/WebViewUI:icy	Lcom/tencent/mm/plugin/webview/stub/d;
    //   2271: bipush 78
    //   2273: aconst_null
    //   2274: invokeinterface 273 3 0
    //   2279: ldc_w 408
    //   2282: iconst_0
    //   2283: invokevirtual 410	android/os/Bundle:getBoolean	(Ljava/lang/String;Z)Z
    //   2286: ifeq +33 -> 2319
    //   2289: aload_1
    //   2290: bipush 33
    //   2292: aload_0
    //   2293: getfield 17	com/tencent/mm/plugin/webview/ui/tools/j$12:utN	Lcom/tencent/mm/plugin/webview/ui/tools/j;
    //   2296: invokevirtual 106	com/tencent/mm/plugin/webview/ui/tools/j:cZv	()Lcom/tencent/mm/plugin/webview/ui/tools/WebViewUI;
    //   2299: ldc_w 411
    //   2302: invokevirtual 139	com/tencent/mm/plugin/webview/ui/tools/WebViewUI:getString	(I)Ljava/lang/String;
    //   2305: ldc_w 412
    //   2308: aload 6
    //   2310: bipush 31
    //   2312: invokestatic 232	com/tencent/mm/plugin/webview/ui/tools/j:b	(Lcom/tencent/mm/protocal/JsapiPermissionWrapper;I)Z
    //   2315: invokevirtual 235	com/tencent/mm/ui/base/l:a	(ILjava/lang/CharSequence;IZ)Landroid/view/MenuItem;
    //   2318: pop
    //   2319: aload_0
    //   2320: getfield 17	com/tencent/mm/plugin/webview/ui/tools/j$12:utN	Lcom/tencent/mm/plugin/webview/ui/tools/j;
    //   2323: bipush 25
    //   2325: invokestatic 209	com/tencent/mm/plugin/webview/ui/tools/j:c	(Lcom/tencent/mm/plugin/webview/ui/tools/j;I)Z
    //   2328: ifeq +85 -> 2413
    //   2331: aload 6
    //   2333: sipush 322
    //   2336: invokestatic 227	com/tencent/mm/plugin/webview/ui/tools/j:a	(Lcom/tencent/mm/protocal/JsapiPermissionWrapper;I)Z
    //   2339: ifeq +74 -> 2413
    //   2342: aload_0
    //   2343: getfield 17	com/tencent/mm/plugin/webview/ui/tools/j$12:utN	Lcom/tencent/mm/plugin/webview/ui/tools/j;
    //   2346: invokevirtual 106	com/tencent/mm/plugin/webview/ui/tools/j:cZv	()Lcom/tencent/mm/plugin/webview/ui/tools/WebViewUI;
    //   2349: invokestatic 418	com/tencent/wework/api/WWAPIFactory:jv	(Landroid/content/Context;)Lcom/tencent/wework/api/IWWAPI;
    //   2352: invokeinterface 423 1 0
    //   2357: ifeq +56 -> 2413
    //   2360: aload_0
    //   2361: getfield 17	com/tencent/mm/plugin/webview/ui/tools/j$12:utN	Lcom/tencent/mm/plugin/webview/ui/tools/j;
    //   2364: bipush 25
    //   2366: invokevirtual 213	com/tencent/mm/plugin/webview/ui/tools/j:Jn	(I)Z
    //   2369: ifeq +44 -> 2413
    //   2372: aload_1
    //   2373: bipush 25
    //   2375: aload_0
    //   2376: getfield 17	com/tencent/mm/plugin/webview/ui/tools/j$12:utN	Lcom/tencent/mm/plugin/webview/ui/tools/j;
    //   2379: invokevirtual 106	com/tencent/mm/plugin/webview/ui/tools/j:cZv	()Lcom/tencent/mm/plugin/webview/ui/tools/WebViewUI;
    //   2382: ldc_w 424
    //   2385: iconst_1
    //   2386: anewarray 4	java/lang/Object
    //   2389: dup
    //   2390: iconst_0
    //   2391: ldc_w 426
    //   2394: aastore
    //   2395: invokevirtual 429	com/tencent/mm/plugin/webview/ui/tools/WebViewUI:getString	(I[Ljava/lang/Object;)Ljava/lang/String;
    //   2398: ldc_w 430
    //   2401: aload 6
    //   2403: sipush 322
    //   2406: invokestatic 232	com/tencent/mm/plugin/webview/ui/tools/j:b	(Lcom/tencent/mm/protocal/JsapiPermissionWrapper;I)Z
    //   2409: invokevirtual 235	com/tencent/mm/ui/base/l:a	(ILjava/lang/CharSequence;IZ)Landroid/view/MenuItem;
    //   2412: pop
    //   2413: aload_0
    //   2414: getfield 17	com/tencent/mm/plugin/webview/ui/tools/j$12:utN	Lcom/tencent/mm/plugin/webview/ui/tools/j;
    //   2417: bipush 26
    //   2419: invokestatic 209	com/tencent/mm/plugin/webview/ui/tools/j:c	(Lcom/tencent/mm/plugin/webview/ui/tools/j;I)Z
    //   2422: ifeq +83 -> 2505
    //   2425: aload 6
    //   2427: sipush 278
    //   2430: invokestatic 227	com/tencent/mm/plugin/webview/ui/tools/j:a	(Lcom/tencent/mm/protocal/JsapiPermissionWrapper;I)Z
    //   2433: ifeq +72 -> 2505
    //   2436: aload_0
    //   2437: getfield 17	com/tencent/mm/plugin/webview/ui/tools/j$12:utN	Lcom/tencent/mm/plugin/webview/ui/tools/j;
    //   2440: invokevirtual 106	com/tencent/mm/plugin/webview/ui/tools/j:cZv	()Lcom/tencent/mm/plugin/webview/ui/tools/WebViewUI;
    //   2443: aload_0
    //   2444: getfield 17	com/tencent/mm/plugin/webview/ui/tools/j$12:utN	Lcom/tencent/mm/plugin/webview/ui/tools/j;
    //   2447: invokevirtual 106	com/tencent/mm/plugin/webview/ui/tools/j:cZv	()Lcom/tencent/mm/plugin/webview/ui/tools/WebViewUI;
    //   2450: getfield 255	com/tencent/mm/plugin/webview/ui/tools/WebViewUI:pzf	Lcom/tencent/mm/ui/widget/MMWebView;
    //   2453: invokevirtual 260	com/tencent/mm/ui/widget/MMWebView:getUrl	()Ljava/lang/String;
    //   2456: invokestatic 435	com/tencent/mm/plugin/webview/stub/a:bl	(Landroid/content/Context;Ljava/lang/String;)Z
    //   2459: ifeq +46 -> 2505
    //   2462: aload_0
    //   2463: getfield 17	com/tencent/mm/plugin/webview/ui/tools/j$12:utN	Lcom/tencent/mm/plugin/webview/ui/tools/j;
    //   2466: bipush 26
    //   2468: invokevirtual 213	com/tencent/mm/plugin/webview/ui/tools/j:Jn	(I)Z
    //   2471: ifeq +34 -> 2505
    //   2474: aload_1
    //   2475: bipush 26
    //   2477: aload_0
    //   2478: getfield 17	com/tencent/mm/plugin/webview/ui/tools/j$12:utN	Lcom/tencent/mm/plugin/webview/ui/tools/j;
    //   2481: invokevirtual 106	com/tencent/mm/plugin/webview/ui/tools/j:cZv	()Lcom/tencent/mm/plugin/webview/ui/tools/WebViewUI;
    //   2484: ldc_w 436
    //   2487: invokevirtual 139	com/tencent/mm/plugin/webview/ui/tools/WebViewUI:getString	(I)Ljava/lang/String;
    //   2490: ldc_w 437
    //   2493: aload 6
    //   2495: sipush 278
    //   2498: invokestatic 232	com/tencent/mm/plugin/webview/ui/tools/j:b	(Lcom/tencent/mm/protocal/JsapiPermissionWrapper;I)Z
    //   2501: invokevirtual 235	com/tencent/mm/ui/base/l:a	(ILjava/lang/CharSequence;IZ)Landroid/view/MenuItem;
    //   2504: pop
    //   2505: aload_0
    //   2506: getfield 17	com/tencent/mm/plugin/webview/ui/tools/j$12:utN	Lcom/tencent/mm/plugin/webview/ui/tools/j;
    //   2509: bipush 20
    //   2511: invokestatic 209	com/tencent/mm/plugin/webview/ui/tools/j:c	(Lcom/tencent/mm/plugin/webview/ui/tools/j;I)Z
    //   2514: ifeq +68 -> 2582
    //   2517: aload 6
    //   2519: bipush 91
    //   2521: invokestatic 227	com/tencent/mm/plugin/webview/ui/tools/j:a	(Lcom/tencent/mm/protocal/JsapiPermissionWrapper;I)Z
    //   2524: ifeq +58 -> 2582
    //   2527: aload_0
    //   2528: getfield 17	com/tencent/mm/plugin/webview/ui/tools/j$12:utN	Lcom/tencent/mm/plugin/webview/ui/tools/j;
    //   2531: invokevirtual 106	com/tencent/mm/plugin/webview/ui/tools/j:cZv	()Lcom/tencent/mm/plugin/webview/ui/tools/WebViewUI;
    //   2534: invokestatic 441	com/tencent/mm/plugin/webview/stub/a:fq	(Landroid/content/Context;)Z
    //   2537: ifeq +45 -> 2582
    //   2540: aload_0
    //   2541: getfield 17	com/tencent/mm/plugin/webview/ui/tools/j$12:utN	Lcom/tencent/mm/plugin/webview/ui/tools/j;
    //   2544: bipush 20
    //   2546: invokevirtual 213	com/tencent/mm/plugin/webview/ui/tools/j:Jn	(I)Z
    //   2549: ifeq +33 -> 2582
    //   2552: aload_1
    //   2553: bipush 20
    //   2555: aload_0
    //   2556: getfield 17	com/tencent/mm/plugin/webview/ui/tools/j$12:utN	Lcom/tencent/mm/plugin/webview/ui/tools/j;
    //   2559: invokevirtual 106	com/tencent/mm/plugin/webview/ui/tools/j:cZv	()Lcom/tencent/mm/plugin/webview/ui/tools/WebViewUI;
    //   2562: ldc_w 442
    //   2565: invokevirtual 139	com/tencent/mm/plugin/webview/ui/tools/WebViewUI:getString	(I)Ljava/lang/String;
    //   2568: ldc_w 443
    //   2571: aload 6
    //   2573: bipush 91
    //   2575: invokestatic 232	com/tencent/mm/plugin/webview/ui/tools/j:b	(Lcom/tencent/mm/protocal/JsapiPermissionWrapper;I)Z
    //   2578: invokevirtual 235	com/tencent/mm/ui/base/l:a	(ILjava/lang/CharSequence;IZ)Landroid/view/MenuItem;
    //   2581: pop
    //   2582: aload_0
    //   2583: getfield 17	com/tencent/mm/plugin/webview/ui/tools/j$12:utN	Lcom/tencent/mm/plugin/webview/ui/tools/j;
    //   2586: bipush 22
    //   2588: invokestatic 209	com/tencent/mm/plugin/webview/ui/tools/j:c	(Lcom/tencent/mm/plugin/webview/ui/tools/j;I)Z
    //   2591: ifeq +70 -> 2661
    //   2594: aload 6
    //   2596: sipush 133
    //   2599: invokestatic 227	com/tencent/mm/plugin/webview/ui/tools/j:a	(Lcom/tencent/mm/protocal/JsapiPermissionWrapper;I)Z
    //   2602: ifeq +59 -> 2661
    //   2605: aload_0
    //   2606: getfield 17	com/tencent/mm/plugin/webview/ui/tools/j$12:utN	Lcom/tencent/mm/plugin/webview/ui/tools/j;
    //   2609: invokevirtual 106	com/tencent/mm/plugin/webview/ui/tools/j:cZv	()Lcom/tencent/mm/plugin/webview/ui/tools/WebViewUI;
    //   2612: invokestatic 441	com/tencent/mm/plugin/webview/stub/a:fq	(Landroid/content/Context;)Z
    //   2615: ifeq +46 -> 2661
    //   2618: aload_0
    //   2619: getfield 17	com/tencent/mm/plugin/webview/ui/tools/j$12:utN	Lcom/tencent/mm/plugin/webview/ui/tools/j;
    //   2622: bipush 22
    //   2624: invokevirtual 213	com/tencent/mm/plugin/webview/ui/tools/j:Jn	(I)Z
    //   2627: ifeq +34 -> 2661
    //   2630: aload_1
    //   2631: bipush 22
    //   2633: aload_0
    //   2634: getfield 17	com/tencent/mm/plugin/webview/ui/tools/j$12:utN	Lcom/tencent/mm/plugin/webview/ui/tools/j;
    //   2637: invokevirtual 106	com/tencent/mm/plugin/webview/ui/tools/j:cZv	()Lcom/tencent/mm/plugin/webview/ui/tools/WebViewUI;
    //   2640: ldc_w 444
    //   2643: invokevirtual 139	com/tencent/mm/plugin/webview/ui/tools/WebViewUI:getString	(I)Ljava/lang/String;
    //   2646: ldc_w 445
    //   2649: aload 6
    //   2651: sipush 133
    //   2654: invokestatic 232	com/tencent/mm/plugin/webview/ui/tools/j:b	(Lcom/tencent/mm/protocal/JsapiPermissionWrapper;I)Z
    //   2657: invokevirtual 235	com/tencent/mm/ui/base/l:a	(ILjava/lang/CharSequence;IZ)Landroid/view/MenuItem;
    //   2660: pop
    //   2661: aload_0
    //   2662: getfield 17	com/tencent/mm/plugin/webview/ui/tools/j$12:utN	Lcom/tencent/mm/plugin/webview/ui/tools/j;
    //   2665: iconst_0
    //   2666: invokestatic 209	com/tencent/mm/plugin/webview/ui/tools/j:c	(Lcom/tencent/mm/plugin/webview/ui/tools/j;I)Z
    //   2669: ifeq +124 -> 2793
    //   2672: aload 6
    //   2674: bipush 43
    //   2676: invokestatic 227	com/tencent/mm/plugin/webview/ui/tools/j:a	(Lcom/tencent/mm/protocal/JsapiPermissionWrapper;I)Z
    //   2679: ifeq +114 -> 2793
    //   2682: aload_0
    //   2683: getfield 17	com/tencent/mm/plugin/webview/ui/tools/j$12:utN	Lcom/tencent/mm/plugin/webview/ui/tools/j;
    //   2686: iconst_0
    //   2687: invokevirtual 213	com/tencent/mm/plugin/webview/ui/tools/j:Jn	(I)Z
    //   2690: ifeq +103 -> 2793
    //   2693: aload_0
    //   2694: getfield 17	com/tencent/mm/plugin/webview/ui/tools/j$12:utN	Lcom/tencent/mm/plugin/webview/ui/tools/j;
    //   2697: invokevirtual 106	com/tencent/mm/plugin/webview/ui/tools/j:cZv	()Lcom/tencent/mm/plugin/webview/ui/tools/WebViewUI;
    //   2700: getfield 267	com/tencent/mm/plugin/webview/ui/tools/WebViewUI:icy	Lcom/tencent/mm/plugin/webview/stub/d;
    //   2703: invokeinterface 448 1 0
    //   2708: ifeq +85 -> 2793
    //   2711: aload_0
    //   2712: getfield 17	com/tencent/mm/plugin/webview/ui/tools/j$12:utN	Lcom/tencent/mm/plugin/webview/ui/tools/j;
    //   2715: invokevirtual 106	com/tencent/mm/plugin/webview/ui/tools/j:cZv	()Lcom/tencent/mm/plugin/webview/ui/tools/WebViewUI;
    //   2718: getfield 267	com/tencent/mm/plugin/webview/ui/tools/WebViewUI:icy	Lcom/tencent/mm/plugin/webview/stub/d;
    //   2721: invokeinterface 452 1 0
    //   2726: astore 5
    //   2728: aload 5
    //   2730: invokeinterface 458 1 0
    //   2735: astore 4
    //   2737: aload 4
    //   2739: invokeinterface 463 1 0
    //   2744: ifeq +749 -> 3493
    //   2747: aload_1
    //   2748: aload 4
    //   2750: invokeinterface 467 1 0
    //   2755: checkcast 130	java/lang/String
    //   2758: invokevirtual 471	com/tencent/mm/ui/base/l:add	(Ljava/lang/CharSequence;)Landroid/view/MenuItem;
    //   2761: pop
    //   2762: goto -25 -> 2737
    //   2765: astore 4
    //   2767: ldc 167
    //   2769: new 169	java/lang/StringBuilder
    //   2772: dup
    //   2773: ldc_w 473
    //   2776: invokespecial 174	java/lang/StringBuilder:<init>	(Ljava/lang/String;)V
    //   2779: aload 4
    //   2781: invokevirtual 178	java/lang/Exception:getMessage	()Ljava/lang/String;
    //   2784: invokevirtual 182	java/lang/StringBuilder:append	(Ljava/lang/String;)Ljava/lang/StringBuilder;
    //   2787: invokevirtual 185	java/lang/StringBuilder:toString	()Ljava/lang/String;
    //   2790: invokestatic 476	com/tencent/mm/sdk/platformtools/ab:w	(Ljava/lang/String;Ljava/lang/String;)V
    //   2793: aload_0
    //   2794: getfield 17	com/tencent/mm/plugin/webview/ui/tools/j$12:utN	Lcom/tencent/mm/plugin/webview/ui/tools/j;
    //   2797: bipush 27
    //   2799: invokestatic 209	com/tencent/mm/plugin/webview/ui/tools/j:c	(Lcom/tencent/mm/plugin/webview/ui/tools/j;I)Z
    //   2802: ifeq +55 -> 2857
    //   2805: aload_0
    //   2806: getfield 17	com/tencent/mm/plugin/webview/ui/tools/j$12:utN	Lcom/tencent/mm/plugin/webview/ui/tools/j;
    //   2809: invokevirtual 106	com/tencent/mm/plugin/webview/ui/tools/j:cZv	()Lcom/tencent/mm/plugin/webview/ui/tools/WebViewUI;
    //   2812: getfield 480	com/tencent/mm/plugin/webview/ui/tools/WebViewUI:uve	Lcom/tencent/mm/plugin/webview/ui/tools/widget/MovingImageButton;
    //   2815: ifnull +42 -> 2857
    //   2818: aload_0
    //   2819: getfield 17	com/tencent/mm/plugin/webview/ui/tools/j$12:utN	Lcom/tencent/mm/plugin/webview/ui/tools/j;
    //   2822: invokevirtual 106	com/tencent/mm/plugin/webview/ui/tools/j:cZv	()Lcom/tencent/mm/plugin/webview/ui/tools/WebViewUI;
    //   2825: getfield 480	com/tencent/mm/plugin/webview/ui/tools/WebViewUI:uve	Lcom/tencent/mm/plugin/webview/ui/tools/widget/MovingImageButton;
    //   2828: invokevirtual 485	com/tencent/mm/plugin/webview/ui/tools/widget/MovingImageButton:getVisibility	()I
    //   2831: ifne +26 -> 2857
    //   2834: aload_1
    //   2835: bipush 27
    //   2837: aload_0
    //   2838: getfield 17	com/tencent/mm/plugin/webview/ui/tools/j$12:utN	Lcom/tencent/mm/plugin/webview/ui/tools/j;
    //   2841: invokevirtual 106	com/tencent/mm/plugin/webview/ui/tools/j:cZv	()Lcom/tencent/mm/plugin/webview/ui/tools/WebViewUI;
    //   2844: ldc_w 486
    //   2847: invokevirtual 139	com/tencent/mm/plugin/webview/ui/tools/WebViewUI:getString	(I)Ljava/lang/String;
    //   2850: ldc_w 487
    //   2853: invokevirtual 143	com/tencent/mm/ui/base/l:a	(ILjava/lang/CharSequence;I)Landroid/view/MenuItem;
    //   2856: pop
    //   2857: aload_0
    //   2858: getfield 17	com/tencent/mm/plugin/webview/ui/tools/j$12:utN	Lcom/tencent/mm/plugin/webview/ui/tools/j;
    //   2861: invokevirtual 106	com/tencent/mm/plugin/webview/ui/tools/j:cZv	()Lcom/tencent/mm/plugin/webview/ui/tools/WebViewUI;
    //   2864: aload_0
    //   2865: getfield 17	com/tencent/mm/plugin/webview/ui/tools/j$12:utN	Lcom/tencent/mm/plugin/webview/ui/tools/j;
    //   2868: invokevirtual 106	com/tencent/mm/plugin/webview/ui/tools/j:cZv	()Lcom/tencent/mm/plugin/webview/ui/tools/WebViewUI;
    //   2871: getfield 290	com/tencent/mm/plugin/webview/ui/tools/WebViewUI:uxf	Ljava/lang/String;
    //   2874: invokevirtual 490	com/tencent/mm/plugin/webview/ui/tools/WebViewUI:afN	(Ljava/lang/String;)Ljava/lang/String;
    //   2877: astore 5
    //   2879: aload_0
    //   2880: getfield 17	com/tencent/mm/plugin/webview/ui/tools/j$12:utN	Lcom/tencent/mm/plugin/webview/ui/tools/j;
    //   2883: invokevirtual 308	com/tencent/mm/plugin/webview/ui/tools/a:cZv	()Lcom/tencent/mm/plugin/webview/ui/tools/WebViewUI;
    //   2886: invokevirtual 312	com/tencent/mm/plugin/webview/ui/tools/WebViewUI:getIntent	()Landroid/content/Intent;
    //   2889: ldc_w 492
    //   2892: invokevirtual 319	android/content/Intent:getStringExtra	(Ljava/lang/String;)Ljava/lang/String;
    //   2895: astore 4
    //   2897: aload_0
    //   2898: getfield 17	com/tencent/mm/plugin/webview/ui/tools/j$12:utN	Lcom/tencent/mm/plugin/webview/ui/tools/j;
    //   2901: invokevirtual 106	com/tencent/mm/plugin/webview/ui/tools/j:cZv	()Lcom/tencent/mm/plugin/webview/ui/tools/WebViewUI;
    //   2904: getfield 495	com/tencent/mm/plugin/webview/ui/tools/WebViewUI:uvz	Z
    //   2907: ifne +85 -> 2992
    //   2910: aload 5
    //   2912: invokestatic 294	com/tencent/mm/sdk/platformtools/bo:isNullOrNil	(Ljava/lang/String;)Z
    //   2915: ifne +77 -> 2992
    //   2918: aload 4
    //   2920: invokestatic 294	com/tencent/mm/sdk/platformtools/bo:isNullOrNil	(Ljava/lang/String;)Z
    //   2923: ifne +69 -> 2992
    //   2926: aload 6
    //   2928: sipush 255
    //   2931: invokestatic 227	com/tencent/mm/plugin/webview/ui/tools/j:a	(Lcom/tencent/mm/protocal/JsapiPermissionWrapper;I)Z
    //   2934: ifeq +58 -> 2992
    //   2937: aload_0
    //   2938: getfield 17	com/tencent/mm/plugin/webview/ui/tools/j$12:utN	Lcom/tencent/mm/plugin/webview/ui/tools/j;
    //   2941: bipush 29
    //   2943: invokevirtual 213	com/tencent/mm/plugin/webview/ui/tools/j:Jn	(I)Z
    //   2946: ifeq +46 -> 2992
    //   2949: aload_0
    //   2950: getfield 17	com/tencent/mm/plugin/webview/ui/tools/j$12:utN	Lcom/tencent/mm/plugin/webview/ui/tools/j;
    //   2953: bipush 29
    //   2955: invokestatic 209	com/tencent/mm/plugin/webview/ui/tools/j:c	(Lcom/tencent/mm/plugin/webview/ui/tools/j;I)Z
    //   2958: ifeq +34 -> 2992
    //   2961: aload_1
    //   2962: bipush 29
    //   2964: aload_0
    //   2965: getfield 17	com/tencent/mm/plugin/webview/ui/tools/j$12:utN	Lcom/tencent/mm/plugin/webview/ui/tools/j;
    //   2968: invokevirtual 106	com/tencent/mm/plugin/webview/ui/tools/j:cZv	()Lcom/tencent/mm/plugin/webview/ui/tools/WebViewUI;
    //   2971: ldc_w 496
    //   2974: invokevirtual 139	com/tencent/mm/plugin/webview/ui/tools/WebViewUI:getString	(I)Ljava/lang/String;
    //   2977: ldc_w 497
    //   2980: aload 6
    //   2982: sipush 255
    //   2985: invokestatic 232	com/tencent/mm/plugin/webview/ui/tools/j:b	(Lcom/tencent/mm/protocal/JsapiPermissionWrapper;I)Z
    //   2988: invokevirtual 235	com/tencent/mm/ui/base/l:a	(ILjava/lang/CharSequence;IZ)Landroid/view/MenuItem;
    //   2991: pop
    //   2992: aload_0
    //   2993: getfield 17	com/tencent/mm/plugin/webview/ui/tools/j$12:utN	Lcom/tencent/mm/plugin/webview/ui/tools/j;
    //   2996: iconst_1
    //   2997: putfield 500	com/tencent/mm/plugin/webview/ui/tools/j:utJ	Z
    //   3000: aload_0
    //   3001: getfield 17	com/tencent/mm/plugin/webview/ui/tools/j$12:utN	Lcom/tencent/mm/plugin/webview/ui/tools/j;
    //   3004: getfield 504	com/tencent/mm/plugin/webview/ui/tools/j:iHZ	Lcom/tencent/mm/ui/widget/a/d;
    //   3007: invokevirtual 509	com/tencent/mm/ui/widget/a/d:dKX	()V
    //   3010: sipush 7653
    //   3013: invokestatic 102	com/tencent/matrix/trace/core/AppMethodBeat:o	(I)V
    //   3016: goto -2895 -> 121
    //   3019: aload_0
    //   3020: getfield 17	com/tencent/mm/plugin/webview/ui/tools/j$12:utN	Lcom/tencent/mm/plugin/webview/ui/tools/j;
    //   3023: bipush 36
    //   3025: invokevirtual 213	com/tencent/mm/plugin/webview/ui/tools/j:Jn	(I)Z
    //   3028: ifeq -2457 -> 571
    //   3031: aload_0
    //   3032: getfield 17	com/tencent/mm/plugin/webview/ui/tools/j$12:utN	Lcom/tencent/mm/plugin/webview/ui/tools/j;
    //   3035: invokevirtual 106	com/tencent/mm/plugin/webview/ui/tools/j:cZv	()Lcom/tencent/mm/plugin/webview/ui/tools/WebViewUI;
    //   3038: getfield 217	com/tencent/mm/plugin/webview/ui/tools/WebViewUI:uie	Lcom/tencent/mm/plugin/webview/ui/tools/bag/h;
    //   3041: invokeinterface 222 1 0
    //   3046: ifeq -2475 -> 571
    //   3049: aload_1
    //   3050: bipush 36
    //   3052: aload_0
    //   3053: getfield 17	com/tencent/mm/plugin/webview/ui/tools/j$12:utN	Lcom/tencent/mm/plugin/webview/ui/tools/j;
    //   3056: invokevirtual 106	com/tencent/mm/plugin/webview/ui/tools/j:cZv	()Lcom/tencent/mm/plugin/webview/ui/tools/WebViewUI;
    //   3059: ldc_w 510
    //   3062: invokevirtual 139	com/tencent/mm/plugin/webview/ui/tools/WebViewUI:getString	(I)Ljava/lang/String;
    //   3065: ldc_w 511
    //   3068: invokevirtual 143	com/tencent/mm/ui/base/l:a	(ILjava/lang/CharSequence;I)Landroid/view/MenuItem;
    //   3071: pop
    //   3072: goto -2501 -> 571
    //   3075: astore 4
    //   3077: ldc 167
    //   3079: new 169	java/lang/StringBuilder
    //   3082: dup
    //   3083: ldc_w 513
    //   3086: invokespecial 174	java/lang/StringBuilder:<init>	(Ljava/lang/String;)V
    //   3089: aload 4
    //   3091: invokevirtual 514	android/os/RemoteException:getMessage	()Ljava/lang/String;
    //   3094: invokevirtual 182	java/lang/StringBuilder:append	(Ljava/lang/String;)Ljava/lang/StringBuilder;
    //   3097: invokevirtual 185	java/lang/StringBuilder:toString	()Ljava/lang/String;
    //   3100: invokestatic 190	com/tencent/mm/sdk/platformtools/ab:e	(Ljava/lang/String;Ljava/lang/String;)V
    //   3103: iload 7
    //   3105: istore 8
    //   3107: goto -2297 -> 810
    //   3110: aload_0
    //   3111: getfield 17	com/tencent/mm/plugin/webview/ui/tools/j$12:utN	Lcom/tencent/mm/plugin/webview/ui/tools/j;
    //   3114: bipush 39
    //   3116: invokevirtual 213	com/tencent/mm/plugin/webview/ui/tools/j:Jn	(I)Z
    //   3119: ifeq -2252 -> 867
    //   3122: iload 8
    //   3124: iconst_1
    //   3125: if_icmpne -2258 -> 867
    //   3128: aload_1
    //   3129: bipush 39
    //   3131: aload_0
    //   3132: getfield 17	com/tencent/mm/plugin/webview/ui/tools/j$12:utN	Lcom/tencent/mm/plugin/webview/ui/tools/j;
    //   3135: invokevirtual 106	com/tencent/mm/plugin/webview/ui/tools/j:cZv	()Lcom/tencent/mm/plugin/webview/ui/tools/WebViewUI;
    //   3138: ldc_w 515
    //   3141: invokevirtual 139	com/tencent/mm/plugin/webview/ui/tools/WebViewUI:getString	(I)Ljava/lang/String;
    //   3144: ldc_w 516
    //   3147: invokevirtual 143	com/tencent/mm/ui/base/l:a	(ILjava/lang/CharSequence;I)Landroid/view/MenuItem;
    //   3150: pop
    //   3151: goto -2284 -> 867
    //   3154: astore 4
    //   3156: ldc 167
    //   3158: aload 4
    //   3160: ldc_w 518
    //   3163: iconst_0
    //   3164: anewarray 4	java/lang/Object
    //   3167: invokestatic 522	com/tencent/mm/sdk/platformtools/ab:printErrStackTrace	(Ljava/lang/String;Ljava/lang/Throwable;Ljava/lang/String;[Ljava/lang/Object;)V
    //   3170: goto -2063 -> 1107
    //   3173: astore 5
    //   3175: ldc 167
    //   3177: new 169	java/lang/StringBuilder
    //   3180: dup
    //   3181: ldc_w 524
    //   3184: invokespecial 174	java/lang/StringBuilder:<init>	(Ljava/lang/String;)V
    //   3187: aload 5
    //   3189: invokevirtual 178	java/lang/Exception:getMessage	()Ljava/lang/String;
    //   3192: invokevirtual 182	java/lang/StringBuilder:append	(Ljava/lang/String;)Ljava/lang/StringBuilder;
    //   3195: invokevirtual 185	java/lang/StringBuilder:toString	()Ljava/lang/String;
    //   3198: invokestatic 190	com/tencent/mm/sdk/platformtools/ab:e	(Ljava/lang/String;Ljava/lang/String;)V
    //   3201: iconst_0
    //   3202: istore 11
    //   3204: goto -1750 -> 1454
    //   3207: astore 4
    //   3209: ldc 167
    //   3211: new 169	java/lang/StringBuilder
    //   3214: dup
    //   3215: ldc_w 526
    //   3218: invokespecial 174	java/lang/StringBuilder:<init>	(Ljava/lang/String;)V
    //   3221: aload 4
    //   3223: invokevirtual 178	java/lang/Exception:getMessage	()Ljava/lang/String;
    //   3226: invokevirtual 182	java/lang/StringBuilder:append	(Ljava/lang/String;)Ljava/lang/StringBuilder;
    //   3229: invokevirtual 185	java/lang/StringBuilder:toString	()Ljava/lang/String;
    //   3232: invokestatic 190	com/tencent/mm/sdk/platformtools/ab:e	(Ljava/lang/String;Ljava/lang/String;)V
    //   3235: goto -1759 -> 1476
    //   3238: aload_0
    //   3239: getfield 17	com/tencent/mm/plugin/webview/ui/tools/j$12:utN	Lcom/tencent/mm/plugin/webview/ui/tools/j;
    //   3242: invokevirtual 106	com/tencent/mm/plugin/webview/ui/tools/j:cZv	()Lcom/tencent/mm/plugin/webview/ui/tools/WebViewUI;
    //   3245: getfield 267	com/tencent/mm/plugin/webview/ui/tools/WebViewUI:icy	Lcom/tencent/mm/plugin/webview/stub/d;
    //   3248: aload 4
    //   3250: invokeinterface 529 2 0
    //   3255: istore 11
    //   3257: iload 11
    //   3259: ifeq +142 -> 3401
    //   3262: aload 6
    //   3264: bipush 19
    //   3266: invokestatic 227	com/tencent/mm/plugin/webview/ui/tools/j:a	(Lcom/tencent/mm/protocal/JsapiPermissionWrapper;I)Z
    //   3269: istore 12
    //   3271: aload 6
    //   3273: bipush 19
    //   3275: invokestatic 232	com/tencent/mm/plugin/webview/ui/tools/j:b	(Lcom/tencent/mm/protocal/JsapiPermissionWrapper;I)Z
    //   3278: istore 13
    //   3280: aload_0
    //   3281: getfield 17	com/tencent/mm/plugin/webview/ui/tools/j$12:utN	Lcom/tencent/mm/plugin/webview/ui/tools/j;
    //   3284: invokevirtual 106	com/tencent/mm/plugin/webview/ui/tools/j:cZv	()Lcom/tencent/mm/plugin/webview/ui/tools/WebViewUI;
    //   3287: invokevirtual 532	com/tencent/mm/plugin/webview/ui/tools/WebViewUI:das	()Z
    //   3290: istore 14
    //   3292: aload_0
    //   3293: getfield 17	com/tencent/mm/plugin/webview/ui/tools/j$12:utN	Lcom/tencent/mm/plugin/webview/ui/tools/j;
    //   3296: iconst_5
    //   3297: invokestatic 209	com/tencent/mm/plugin/webview/ui/tools/j:c	(Lcom/tencent/mm/plugin/webview/ui/tools/j;I)Z
    //   3300: ifeq -1824 -> 1476
    //   3303: iload 12
    //   3305: ifeq +14 -> 3319
    //   3308: aload_0
    //   3309: getfield 17	com/tencent/mm/plugin/webview/ui/tools/j$12:utN	Lcom/tencent/mm/plugin/webview/ui/tools/j;
    //   3312: iconst_5
    //   3313: invokevirtual 213	com/tencent/mm/plugin/webview/ui/tools/j:Jn	(I)Z
    //   3316: ifne +8 -> 3324
    //   3319: iload 14
    //   3321: ifeq -1845 -> 1476
    //   3324: iload 11
    //   3326: ifeq +96 -> 3422
    //   3329: ldc_w 533
    //   3332: istore_3
    //   3333: iload 14
    //   3335: ifeq +7 -> 3342
    //   3338: ldc_w 534
    //   3341: istore_3
    //   3342: aload_1
    //   3343: iconst_5
    //   3344: aload_0
    //   3345: getfield 17	com/tencent/mm/plugin/webview/ui/tools/j$12:utN	Lcom/tencent/mm/plugin/webview/ui/tools/j;
    //   3348: invokevirtual 106	com/tencent/mm/plugin/webview/ui/tools/j:cZv	()Lcom/tencent/mm/plugin/webview/ui/tools/WebViewUI;
    //   3351: iload_3
    //   3352: invokevirtual 139	com/tencent/mm/plugin/webview/ui/tools/WebViewUI:getString	(I)Ljava/lang/String;
    //   3355: ldc_w 535
    //   3358: iload 13
    //   3360: invokevirtual 235	com/tencent/mm/ui/base/l:a	(ILjava/lang/CharSequence;IZ)Landroid/view/MenuItem;
    //   3363: pop
    //   3364: goto -1888 -> 1476
    //   3367: astore 4
    //   3369: ldc 167
    //   3371: new 169	java/lang/StringBuilder
    //   3374: dup
    //   3375: ldc_w 537
    //   3378: invokespecial 174	java/lang/StringBuilder:<init>	(Ljava/lang/String;)V
    //   3381: aload 4
    //   3383: invokevirtual 178	java/lang/Exception:getMessage	()Ljava/lang/String;
    //   3386: invokevirtual 182	java/lang/StringBuilder:append	(Ljava/lang/String;)Ljava/lang/StringBuilder;
    //   3389: invokevirtual 185	java/lang/StringBuilder:toString	()Ljava/lang/String;
    //   3392: invokestatic 190	com/tencent/mm/sdk/platformtools/ab:e	(Ljava/lang/String;Ljava/lang/String;)V
    //   3395: iconst_0
    //   3396: istore 11
    //   3398: goto -141 -> 3257
    //   3401: aload 6
    //   3403: bipush 20
    //   3405: invokestatic 227	com/tencent/mm/plugin/webview/ui/tools/j:a	(Lcom/tencent/mm/protocal/JsapiPermissionWrapper;I)Z
    //   3408: istore 12
    //   3410: aload 6
    //   3412: bipush 20
    //   3414: invokestatic 232	com/tencent/mm/plugin/webview/ui/tools/j:b	(Lcom/tencent/mm/protocal/JsapiPermissionWrapper;I)Z
    //   3417: istore 13
    //   3419: goto -139 -> 3280
    //   3422: ldc_w 538
    //   3425: istore_3
    //   3426: goto -93 -> 3333
    //   3429: astore 4
    //   3431: ldc 167
    //   3433: new 169	java/lang/StringBuilder
    //   3436: dup
    //   3437: ldc_w 473
    //   3440: invokespecial 174	java/lang/StringBuilder:<init>	(Ljava/lang/String;)V
    //   3443: aload 4
    //   3445: invokevirtual 178	java/lang/Exception:getMessage	()Ljava/lang/String;
    //   3448: invokevirtual 182	java/lang/StringBuilder:append	(Ljava/lang/String;)Ljava/lang/StringBuilder;
    //   3451: invokevirtual 185	java/lang/StringBuilder:toString	()Ljava/lang/String;
    //   3454: invokestatic 476	com/tencent/mm/sdk/platformtools/ab:w	(Ljava/lang/String;Ljava/lang/String;)V
    //   3457: iconst_0
    //   3458: istore 11
    //   3460: goto -1676 -> 1784
    //   3463: ldc 167
    //   3465: ldc_w 540
    //   3468: invokestatic 542	com/tencent/mm/sdk/platformtools/ab:i	(Ljava/lang/String;Ljava/lang/String;)V
    //   3471: goto -1244 -> 2227
    //   3474: astore 4
    //   3476: ldc 167
    //   3478: aload 4
    //   3480: ldc_w 518
    //   3483: iconst_0
    //   3484: anewarray 4	java/lang/Object
    //   3487: invokestatic 522	com/tencent/mm/sdk/platformtools/ab:printErrStackTrace	(Ljava/lang/String;Ljava/lang/Throwable;Ljava/lang/String;[Ljava/lang/Object;)V
    //   3490: goto -1171 -> 2319
    //   3493: aload_0
    //   3494: getfield 17	com/tencent/mm/plugin/webview/ui/tools/j$12:utN	Lcom/tencent/mm/plugin/webview/ui/tools/j;
    //   3497: aload 5
    //   3499: invokestatic 545	com/tencent/mm/plugin/webview/ui/tools/j:a	(Lcom/tencent/mm/plugin/webview/ui/tools/j;Ljava/util/List;)V
    //   3502: goto -709 -> 2793
    //   3505: astore 5
    //   3507: goto -1318 -> 2189
    //
    // Exception table:
    //   from	to	target	type
    //   122	134	408	java/lang/Exception
    //   141	150	408	java/lang/Exception
    //   156	167	408	java/lang/Exception
    //   170	211	408	java/lang/Exception
    //   216	226	408	java/lang/Exception
    //   232	273	408	java/lang/Exception
    //   276	317	408	java/lang/Exception
    //   320	361	408	java/lang/Exception
    //   364	405	408	java/lang/Exception
    //   2661	2737	2765	java/lang/Exception
    //   2737	2762	2765	java/lang/Exception
    //   3493	3502	2765	java/lang/Exception
    //   696	701	3075	android/os/RemoteException
    //   703	708	3075	android/os/RemoteException
    //   710	727	3075	android/os/RemoteException
    //   729	749	3075	android/os/RemoteException
    //   751	772	3075	android/os/RemoteException
    //   785	795	3075	android/os/RemoteException
    //   797	808	3075	android/os/RemoteException
    //   1050	1107	3154	java/lang/Exception
    //   1435	1454	3173	java/lang/Exception
    //   1459	1476	3207	java/lang/Exception
    //   3238	3257	3367	java/lang/Exception
    //   1727	1769	3429	java/lang/Exception
    //   1774	1784	3429	java/lang/Exception
    //   2261	2319	3474	java/lang/Exception
    //   2168	2185	3505	java/lang/Exception
  }
}

/* Location:           C:\Users\Lin\Downloads\dex-tools-2.1-SNAPSHOT\dex-tools-2.1-SNAPSHOT\classes6-dex2jar.jar
 * Qualified Name:     com.tencent.mm.plugin.webview.ui.tools.j.12
 * JD-Core Version:    0.6.2
 */