package com.tencent.mm.plugin.sns.lucky.a;

public final class k
{
  // ERROR //
  public static com.tencent.mm.plugin.sns.h.i h(com.tencent.mm.storage.ac.a parama)
  {
    // Byte code:
    //   0: ldc 9
    //   2: invokestatic 15	com/tencent/matrix/trace/core/AppMethodBeat:i	(I)V
    //   5: new 17	com/tencent/mm/plugin/sns/h/i
    //   8: dup
    //   9: invokespecial 21	com/tencent/mm/plugin/sns/h/i:<init>	()V
    //   12: astore_1
    //   13: invokestatic 27	com/tencent/mm/kernel/g:RQ	()Lcom/tencent/mm/kernel/g;
    //   16: pop
    //   17: invokestatic 31	com/tencent/mm/kernel/g:RP	()Lcom/tencent/mm/kernel/e;
    //   20: invokevirtual 37	com/tencent/mm/kernel/e:Ry	()Lcom/tencent/mm/storage/z;
    //   23: aload_0
    //   24: aconst_null
    //   25: invokevirtual 43	com/tencent/mm/storage/z:get	(Lcom/tencent/mm/storage/ac$a;Ljava/lang/Object;)Ljava/lang/Object;
    //   28: checkcast 45	java/lang/String
    //   31: astore_0
    //   32: aload_0
    //   33: ifnonnull +17 -> 50
    //   36: ldc 47
    //   38: ldc 49
    //   40: invokestatic 54	com/tencent/mm/sdk/platformtools/ab:i	(Ljava/lang/String;Ljava/lang/String;)V
    //   43: ldc 9
    //   45: invokestatic 57	com/tencent/matrix/trace/core/AppMethodBeat:o	(I)V
    //   48: aload_1
    //   49: areturn
    //   50: new 17	com/tencent/mm/plugin/sns/h/i
    //   53: astore_2
    //   54: aload_2
    //   55: invokespecial 21	com/tencent/mm/plugin/sns/h/i:<init>	()V
    //   58: aload_2
    //   59: aload_0
    //   60: ldc 59
    //   62: invokestatic 65	java/nio/charset/Charset:forName	(Ljava/lang/String;)Ljava/nio/charset/Charset;
    //   65: invokevirtual 69	java/lang/String:getBytes	(Ljava/nio/charset/Charset;)[B
    //   68: invokevirtual 73	com/tencent/mm/plugin/sns/h/i:parseFrom	([B)Lcom/tencent/mm/bt/a;
    //   71: checkcast 17	com/tencent/mm/plugin/sns/h/i
    //   74: astore_2
    //   75: aload_2
    //   76: astore_0
    //   77: aload_2
    //   78: ifnonnull +11 -> 89
    //   81: new 17	com/tencent/mm/plugin/sns/h/i
    //   84: astore_0
    //   85: aload_0
    //   86: invokespecial 21	com/tencent/mm/plugin/sns/h/i:<init>	()V
    //   89: aload_0
    //   90: astore_1
    //   91: aload_0
    //   92: ifnonnull +11 -> 103
    //   95: new 17	com/tencent/mm/plugin/sns/h/i
    //   98: dup
    //   99: invokespecial 21	com/tencent/mm/plugin/sns/h/i:<init>	()V
    //   102: astore_1
    //   103: ldc 9
    //   105: invokestatic 57	com/tencent/matrix/trace/core/AppMethodBeat:o	(I)V
    //   108: goto -60 -> 48
    //   111: astore_2
    //   112: aload_1
    //   113: astore_0
    //   114: aload_2
    //   115: astore_1
    //   116: ldc 47
    //   118: new 75	java/lang/StringBuilder
    //   121: dup
    //   122: ldc 77
    //   124: invokespecial 80	java/lang/StringBuilder:<init>	(Ljava/lang/String;)V
    //   127: aload_1
    //   128: invokevirtual 84	java/lang/Exception:getMessage	()Ljava/lang/String;
    //   131: invokevirtual 88	java/lang/StringBuilder:append	(Ljava/lang/String;)Ljava/lang/StringBuilder;
    //   134: invokevirtual 91	java/lang/StringBuilder:toString	()Ljava/lang/String;
    //   137: invokestatic 94	com/tencent/mm/sdk/platformtools/ab:e	(Ljava/lang/String;Ljava/lang/String;)V
    //   140: goto -51 -> 89
    //   143: astore_1
    //   144: aload_2
    //   145: astore_0
    //   146: goto -30 -> 116
    //
    // Exception table:
    //   from	to	target	type
    //   50	75	111	java/lang/Exception
    //   81	89	143	java/lang/Exception
  }
}

/* Location:           C:\Users\Lin\Downloads\dex-tools-2.1-SNAPSHOT\dex-tools-2.1-SNAPSHOT\classes6-dex2jar.jar
 * Qualified Name:     com.tencent.mm.plugin.sns.lucky.a.k
 * JD-Core Version:    0.6.2
 */