package com.tencent.mm.an;

import com.tencent.matrix.trace.core.AppMethodBeat;
import com.tencent.mm.loader.j.b;
import com.tencent.mm.sdk.platformtools.ab;
import com.tencent.mm.sdk.platformtools.ah;
import java.io.File;
import java.util.Iterator;
import java.util.List;

final class c
  implements Runnable
{
  boolean fAA;
  int fAs;
  private c.d fAt;
  c.b fAu;
  private long fAv;
  private long fAw;
  private long fAx;
  String fAy;
  private String fAz;

  c()
  {
    AppMethodBeat.i(58344);
    this.fAs = 0;
    this.fAt = null;
    this.fAu = new c.b();
    this.fAv = 0L;
    this.fAw = 0L;
    this.fAx = 0L;
    this.fAy = null;
    this.fAz = null;
    this.fAA = false;
    if (this.fAy == null)
    {
      this.fAy = (b.eSj + "ProcessDetector");
      File localFile = new File(this.fAy);
      if (!localFile.exists())
        localFile.mkdir();
    }
    if (ah.bqo())
    {
      this.fAz = (this.fAy + "/mm");
      AppMethodBeat.o(58344);
    }
    while (true)
    {
      return;
      if (ah.doE())
        this.fAz = (this.fAy + "/push");
      AppMethodBeat.o(58344);
    }
  }

  private static void a(c.b paramb)
  {
    AppMethodBeat.i(58346);
    if (paramb == null)
      AppMethodBeat.o(58346);
    while (true)
    {
      return;
      long l = System.currentTimeMillis();
      while (true)
      {
        try
        {
          localObject1 = paramb.fAB.iterator();
          if (!((Iterator)localObject1).hasNext())
            break label119;
          localObject2 = (c.d)((Iterator)localObject1).next();
          if (localObject2 != null)
            break label90;
          paramb.fAB.remove(localObject2);
          continue;
        }
        catch (Exception paramb)
        {
          ab.printErrStackTrace("MicroMsg.ActiveDetector.ProcessDetector", paramb, "check data exception.", new Object[0]);
          AppMethodBeat.o(58346);
        }
        break;
        label90: if (l - ((c.d)localObject2).endTime < 86400000L)
          break label119;
        paramb.fAB.remove(localObject2);
      }
      label119: Object localObject1 = paramb.fAC.iterator();
      while (((Iterator)localObject1).hasNext())
      {
        localObject2 = (c.a)((Iterator)localObject1).next();
        if (localObject2 == null)
        {
          paramb.fAC.remove(localObject2);
        }
        else
        {
          if (l - ((c.a)localObject2).time < 86400000L)
            break;
          paramb.fAC.remove(localObject2);
        }
      }
      Object localObject2 = paramb.fAD.iterator();
      while (((Iterator)localObject2).hasNext())
      {
        localObject1 = (c.a)((Iterator)localObject2).next();
        if (localObject1 == null)
        {
          paramb.fAD.remove(localObject1);
        }
        else
        {
          if (l - ((c.a)localObject1).time < 86400000L)
            break;
          paramb.fAD.remove(localObject1);
        }
      }
      localObject2 = paramb.fAE.iterator();
      while (((Iterator)localObject2).hasNext())
      {
        localObject1 = (c.c)((Iterator)localObject2).next();
        if (localObject1 == null)
        {
          paramb.fAE.remove(localObject1);
        }
        else
        {
          if (l - ((c.c)localObject1).fAF < 86400000L)
            break;
          paramb.fAE.remove(localObject1);
        }
      }
      AppMethodBeat.o(58346);
    }
  }

  final void clear()
  {
    this.fAA = false;
    this.fAw = 0L;
    this.fAx = 0L;
  }

  // ERROR //
  public final void run()
  {
    // Byte code:
    //   0: ldc 174
    //   2: invokestatic 40	com/tencent/matrix/trace/core/AppMethodBeat:i	(I)V
    //   5: aload_0
    //   6: invokevirtual 176	com/tencent/mm/an/c:clear	()V
    //   9: aload_0
    //   10: invokestatic 116	java/lang/System:currentTimeMillis	()J
    //   13: putfield 51	com/tencent/mm/an/c:fAw	J
    //   16: aload_0
    //   17: aload_0
    //   18: getfield 51	com/tencent/mm/an/c:fAw	J
    //   21: putfield 53	com/tencent/mm/an/c:fAx	J
    //   24: aload_0
    //   25: new 14	com/tencent/mm/an/c$d
    //   28: dup
    //   29: invokespecial 177	com/tencent/mm/an/c$d:<init>	()V
    //   32: putfield 44	com/tencent/mm/an/c:fAt	Lcom/tencent/mm/an/c$d;
    //   35: aload_0
    //   36: getfield 44	com/tencent/mm/an/c:fAt	Lcom/tencent/mm/an/c$d;
    //   39: invokestatic 183	android/os/Process:myPid	()I
    //   42: aload_0
    //   43: getfield 51	com/tencent/mm/an/c:fAw	J
    //   46: aload_0
    //   47: getfield 53	com/tencent/mm/an/c:fAx	J
    //   50: aload_0
    //   51: getfield 42	com/tencent/mm/an/c:fAs	I
    //   54: invokevirtual 186	com/tencent/mm/an/c$d:a	(IJJI)V
    //   57: aload_0
    //   58: getfield 47	com/tencent/mm/an/c:fAu	Lcom/tencent/mm/an/c$b;
    //   61: getfield 120	com/tencent/mm/an/c$b:fAB	Ljava/util/List;
    //   64: invokeinterface 189 1 0
    //   69: ifeq +83 -> 152
    //   72: new 191	java/io/FileInputStream
    //   75: astore_1
    //   76: aload_1
    //   77: aload_0
    //   78: getfield 57	com/tencent/mm/an/c:fAz	Ljava/lang/String;
    //   81: invokespecial 192	java/io/FileInputStream:<init>	(Ljava/lang/String;)V
    //   84: aload_1
    //   85: invokestatic 198	com/tencent/mm/an/b:x	(Ljava/io/InputStream;)Ljava/lang/Object;
    //   88: checkcast 10	com/tencent/mm/an/c$b
    //   91: astore_1
    //   92: aload_1
    //   93: ifnull +59 -> 152
    //   96: aload_1
    //   97: getfield 157	com/tencent/mm/an/c$b:fAC	Ljava/util/List;
    //   100: aload_0
    //   101: getfield 47	com/tencent/mm/an/c:fAu	Lcom/tencent/mm/an/c$b;
    //   104: getfield 157	com/tencent/mm/an/c$b:fAC	Ljava/util/List;
    //   107: invokeinterface 202 2 0
    //   112: pop
    //   113: aload_1
    //   114: getfield 163	com/tencent/mm/an/c$b:fAD	Ljava/util/List;
    //   117: aload_0
    //   118: getfield 47	com/tencent/mm/an/c:fAu	Lcom/tencent/mm/an/c$b;
    //   121: getfield 163	com/tencent/mm/an/c$b:fAD	Ljava/util/List;
    //   124: invokeinterface 202 2 0
    //   129: pop
    //   130: aload_1
    //   131: getfield 166	com/tencent/mm/an/c$b:fAE	Ljava/util/List;
    //   134: aload_0
    //   135: getfield 47	com/tencent/mm/an/c:fAu	Lcom/tencent/mm/an/c$b;
    //   138: getfield 166	com/tencent/mm/an/c$b:fAE	Ljava/util/List;
    //   141: invokeinterface 202 2 0
    //   146: pop
    //   147: aload_0
    //   148: aload_1
    //   149: putfield 47	com/tencent/mm/an/c:fAu	Lcom/tencent/mm/an/c$b;
    //   152: aload_0
    //   153: getfield 47	com/tencent/mm/an/c:fAu	Lcom/tencent/mm/an/c$b;
    //   156: invokestatic 204	com/tencent/mm/an/c:a	(Lcom/tencent/mm/an/c$b;)V
    //   159: aload_0
    //   160: getfield 47	com/tencent/mm/an/c:fAu	Lcom/tencent/mm/an/c$b;
    //   163: getfield 120	com/tencent/mm/an/c$b:fAB	Ljava/util/List;
    //   166: aload_0
    //   167: getfield 44	com/tencent/mm/an/c:fAt	Lcom/tencent/mm/an/c$d;
    //   170: invokeinterface 207 2 0
    //   175: pop
    //   176: ldc 141
    //   178: ldc 209
    //   180: iconst_3
    //   181: anewarray 4	java/lang/Object
    //   184: dup
    //   185: iconst_0
    //   186: aload_0
    //   187: getfield 47	com/tencent/mm/an/c:fAu	Lcom/tencent/mm/an/c$b;
    //   190: getfield 120	com/tencent/mm/an/c$b:fAB	Ljava/util/List;
    //   193: invokeinterface 212 1 0
    //   198: invokestatic 218	java/lang/Integer:valueOf	(I)Ljava/lang/Integer;
    //   201: aastore
    //   202: dup
    //   203: iconst_1
    //   204: aload_0
    //   205: getfield 47	com/tencent/mm/an/c:fAu	Lcom/tencent/mm/an/c$b;
    //   208: getfield 157	com/tencent/mm/an/c$b:fAC	Ljava/util/List;
    //   211: invokeinterface 212 1 0
    //   216: invokestatic 218	java/lang/Integer:valueOf	(I)Ljava/lang/Integer;
    //   219: aastore
    //   220: dup
    //   221: iconst_2
    //   222: aload_0
    //   223: getfield 47	com/tencent/mm/an/c:fAu	Lcom/tencent/mm/an/c$b;
    //   226: getfield 163	com/tencent/mm/an/c$b:fAD	Ljava/util/List;
    //   229: invokeinterface 212 1 0
    //   234: invokestatic 218	java/lang/Integer:valueOf	(I)Ljava/lang/Integer;
    //   237: aastore
    //   238: invokestatic 221	com/tencent/mm/sdk/platformtools/ab:i	(Ljava/lang/String;Ljava/lang/String;[Ljava/lang/Object;)V
    //   241: aload_0
    //   242: getfield 59	com/tencent/mm/an/c:fAA	Z
    //   245: ifeq +757 -> 1002
    //   248: invokestatic 227	java/lang/Thread:currentThread	()Ljava/lang/Thread;
    //   251: invokevirtual 230	java/lang/Thread:isInterrupted	()Z
    //   254: ifne +748 -> 1002
    //   257: invokestatic 183	android/os/Process:myPid	()I
    //   260: istore_2
    //   261: invokestatic 116	java/lang/System:currentTimeMillis	()J
    //   264: lstore_3
    //   265: aload_0
    //   266: getfield 44	com/tencent/mm/an/c:fAt	Lcom/tencent/mm/an/c$d;
    //   269: astore 5
    //   271: aload_0
    //   272: getfield 53	com/tencent/mm/an/c:fAx	J
    //   275: lstore 6
    //   277: aload_0
    //   278: getfield 42	com/tencent/mm/an/c:fAs	I
    //   281: istore 8
    //   283: lload_3
    //   284: lload 6
    //   286: lsub
    //   287: lstore 9
    //   289: aload 5
    //   291: getfield 233	com/tencent/mm/an/c$d:fAl	I
    //   294: iload 8
    //   296: if_icmpne +12 -> 308
    //   299: lload 9
    //   301: ldc2_w 234
    //   304: lcmp
    //   305: ifle +330 -> 635
    //   308: iload_2
    //   309: lload 6
    //   311: lload_3
    //   312: iload 8
    //   314: invokestatic 239	com/tencent/mm/an/c$d:b	(IJJI)Lcom/tencent/mm/an/c$d;
    //   317: astore_1
    //   318: aload 5
    //   320: getfield 233	com/tencent/mm/an/c$d:fAl	I
    //   323: iload 8
    //   325: if_icmpeq +8 -> 333
    //   328: aload_1
    //   329: iconst_1
    //   330: putfield 242	com/tencent/mm/an/c$d:fAn	Z
    //   333: lload 9
    //   335: ldc2_w 234
    //   338: lcmp
    //   339: ifle +8 -> 347
    //   342: aload_1
    //   343: iconst_0
    //   344: putfield 245	com/tencent/mm/an/c$d:fAm	Z
    //   347: aload_1
    //   348: ifnull +303 -> 651
    //   351: ldc 141
    //   353: ldc 247
    //   355: iconst_1
    //   356: anewarray 4	java/lang/Object
    //   359: dup
    //   360: iconst_0
    //   361: aload_1
    //   362: aastore
    //   363: invokestatic 221	com/tencent/mm/sdk/platformtools/ab:i	(Ljava/lang/String;Ljava/lang/String;[Ljava/lang/Object;)V
    //   366: aload_0
    //   367: aload_1
    //   368: putfield 44	com/tencent/mm/an/c:fAt	Lcom/tencent/mm/an/c$d;
    //   371: aload_0
    //   372: getfield 47	com/tencent/mm/an/c:fAu	Lcom/tencent/mm/an/c$b;
    //   375: getfield 120	com/tencent/mm/an/c$b:fAB	Ljava/util/List;
    //   378: aload_0
    //   379: getfield 44	com/tencent/mm/an/c:fAt	Lcom/tencent/mm/an/c$d;
    //   382: invokeinterface 207 2 0
    //   387: pop
    //   388: ldc 141
    //   390: ldc 249
    //   392: iconst_2
    //   393: anewarray 4	java/lang/Object
    //   396: dup
    //   397: iconst_0
    //   398: aload_0
    //   399: getfield 47	com/tencent/mm/an/c:fAu	Lcom/tencent/mm/an/c$b;
    //   402: getfield 157	com/tencent/mm/an/c$b:fAC	Ljava/util/List;
    //   405: aastore
    //   406: dup
    //   407: iconst_1
    //   408: aload_0
    //   409: getfield 47	com/tencent/mm/an/c:fAu	Lcom/tencent/mm/an/c$b;
    //   412: getfield 163	com/tencent/mm/an/c$b:fAD	Ljava/util/List;
    //   415: aastore
    //   416: invokestatic 252	com/tencent/mm/sdk/platformtools/ab:d	(Ljava/lang/String;Ljava/lang/String;[Ljava/lang/Object;)V
    //   419: aload_0
    //   420: lload_3
    //   421: putfield 53	com/tencent/mm/an/c:fAx	J
    //   424: aload_0
    //   425: getfield 49	com/tencent/mm/an/c:fAv	J
    //   428: lconst_0
    //   429: lcmp
    //   430: ifle +16 -> 446
    //   433: lload_3
    //   434: aload_0
    //   435: getfield 49	com/tencent/mm/an/c:fAv	J
    //   438: lsub
    //   439: ldc2_w 253
    //   442: lcmp
    //   443: ifle +107 -> 550
    //   446: aload_0
    //   447: lload_3
    //   448: putfield 49	com/tencent/mm/an/c:fAv	J
    //   451: aload_0
    //   452: getfield 47	com/tencent/mm/an/c:fAu	Lcom/tencent/mm/an/c$b;
    //   455: ifnull +28 -> 483
    //   458: aload_0
    //   459: getfield 47	com/tencent/mm/an/c:fAu	Lcom/tencent/mm/an/c$b;
    //   462: getfield 120	com/tencent/mm/an/c$b:fAB	Ljava/util/List;
    //   465: ifnull +18 -> 483
    //   468: aload_0
    //   469: getfield 47	com/tencent/mm/an/c:fAu	Lcom/tencent/mm/an/c$b;
    //   472: getfield 120	com/tencent/mm/an/c$b:fAB	Ljava/util/List;
    //   475: invokeinterface 189 1 0
    //   480: ifeq +216 -> 696
    //   483: ldc 141
    //   485: ldc_w 256
    //   488: iconst_1
    //   489: anewarray 4	java/lang/Object
    //   492: dup
    //   493: iconst_0
    //   494: aload_0
    //   495: getfield 44	com/tencent/mm/an/c:fAt	Lcom/tencent/mm/an/c$d;
    //   498: aastore
    //   499: invokestatic 221	com/tencent/mm/sdk/platformtools/ab:i	(Ljava/lang/String;Ljava/lang/String;[Ljava/lang/Object;)V
    //   502: ldc 141
    //   504: ldc_w 258
    //   507: iconst_2
    //   508: anewarray 4	java/lang/Object
    //   511: dup
    //   512: iconst_0
    //   513: aload_0
    //   514: getfield 47	com/tencent/mm/an/c:fAu	Lcom/tencent/mm/an/c$b;
    //   517: getfield 157	com/tencent/mm/an/c$b:fAC	Ljava/util/List;
    //   520: invokeinterface 212 1 0
    //   525: invokestatic 218	java/lang/Integer:valueOf	(I)Ljava/lang/Integer;
    //   528: aastore
    //   529: dup
    //   530: iconst_1
    //   531: aload_0
    //   532: getfield 47	com/tencent/mm/an/c:fAu	Lcom/tencent/mm/an/c$b;
    //   535: getfield 163	com/tencent/mm/an/c$b:fAD	Ljava/util/List;
    //   538: invokeinterface 212 1 0
    //   543: invokestatic 218	java/lang/Integer:valueOf	(I)Ljava/lang/Integer;
    //   546: aastore
    //   547: invokestatic 221	com/tencent/mm/sdk/platformtools/ab:i	(Ljava/lang/String;Ljava/lang/String;[Ljava/lang/Object;)V
    //   550: ldc2_w 259
    //   553: invokestatic 264	java/lang/Thread:sleep	(J)V
    //   556: goto -315 -> 241
    //   559: astore_1
    //   560: ldc 141
    //   562: ldc_w 266
    //   565: iconst_1
    //   566: anewarray 4	java/lang/Object
    //   569: dup
    //   570: iconst_0
    //   571: invokestatic 269	android/os/Process:myTid	()I
    //   574: invokestatic 218	java/lang/Integer:valueOf	(I)Ljava/lang/Integer;
    //   577: aastore
    //   578: invokestatic 221	com/tencent/mm/sdk/platformtools/ab:i	(Ljava/lang/String;Ljava/lang/String;[Ljava/lang/Object;)V
    //   581: invokestatic 227	java/lang/Thread:currentThread	()Ljava/lang/Thread;
    //   584: invokevirtual 272	java/lang/Thread:interrupt	()V
    //   587: aload_0
    //   588: iconst_0
    //   589: putfield 59	com/tencent/mm/an/c:fAA	Z
    //   592: goto -351 -> 241
    //   595: astore_1
    //   596: ldc 141
    //   598: new 61	java/lang/StringBuilder
    //   601: dup
    //   602: ldc_w 274
    //   605: invokespecial 275	java/lang/StringBuilder:<init>	(Ljava/lang/String;)V
    //   608: aload_1
    //   609: invokevirtual 278	java/lang/Exception:getMessage	()Ljava/lang/String;
    //   612: invokevirtual 71	java/lang/StringBuilder:append	(Ljava/lang/String;)Ljava/lang/StringBuilder;
    //   615: invokevirtual 77	java/lang/StringBuilder:toString	()Ljava/lang/String;
    //   618: iconst_1
    //   619: anewarray 4	java/lang/Object
    //   622: dup
    //   623: iconst_0
    //   624: aload_0
    //   625: getfield 57	com/tencent/mm/an/c:fAz	Ljava/lang/String;
    //   628: aastore
    //   629: invokestatic 281	com/tencent/mm/sdk/platformtools/ab:e	(Ljava/lang/String;Ljava/lang/String;[Ljava/lang/Object;)V
    //   632: goto -480 -> 152
    //   635: aload 5
    //   637: iload_2
    //   638: lload 6
    //   640: lload_3
    //   641: iload 8
    //   643: invokevirtual 186	com/tencent/mm/an/c$d:a	(IJJI)V
    //   646: aconst_null
    //   647: astore_1
    //   648: goto -301 -> 347
    //   651: ldc 141
    //   653: ldc_w 283
    //   656: iconst_1
    //   657: anewarray 4	java/lang/Object
    //   660: dup
    //   661: iconst_0
    //   662: aload_0
    //   663: getfield 44	com/tencent/mm/an/c:fAt	Lcom/tencent/mm/an/c$d;
    //   666: aastore
    //   667: invokestatic 252	com/tencent/mm/sdk/platformtools/ab:d	(Ljava/lang/String;Ljava/lang/String;[Ljava/lang/Object;)V
    //   670: goto -282 -> 388
    //   673: astore_1
    //   674: ldc 141
    //   676: ldc_w 285
    //   679: iconst_1
    //   680: anewarray 4	java/lang/Object
    //   683: dup
    //   684: iconst_0
    //   685: aload_1
    //   686: invokevirtual 278	java/lang/Exception:getMessage	()Ljava/lang/String;
    //   689: aastore
    //   690: invokestatic 281	com/tencent/mm/sdk/platformtools/ab:e	(Ljava/lang/String;Ljava/lang/String;[Ljava/lang/Object;)V
    //   693: goto -452 -> 241
    //   696: ldc 141
    //   698: ldc_w 287
    //   701: iconst_1
    //   702: anewarray 4	java/lang/Object
    //   705: dup
    //   706: iconst_0
    //   707: aload_0
    //   708: getfield 57	com/tencent/mm/an/c:fAz	Ljava/lang/String;
    //   711: aastore
    //   712: invokestatic 252	com/tencent/mm/sdk/platformtools/ab:d	(Ljava/lang/String;Ljava/lang/String;[Ljava/lang/Object;)V
    //   715: aload_0
    //   716: getfield 47	com/tencent/mm/an/c:fAu	Lcom/tencent/mm/an/c$b;
    //   719: astore 11
    //   721: new 289	java/io/FileOutputStream
    //   724: astore_1
    //   725: aload_1
    //   726: aload_0
    //   727: getfield 57	com/tencent/mm/an/c:fAz	Ljava/lang/String;
    //   730: invokespecial 290	java/io/FileOutputStream:<init>	(Ljava/lang/String;)V
    //   733: aload 11
    //   735: ifnull -252 -> 483
    //   738: new 292	java/io/ObjectOutputStream
    //   741: astore 5
    //   743: aload 5
    //   745: aload_1
    //   746: invokespecial 295	java/io/ObjectOutputStream:<init>	(Ljava/io/OutputStream;)V
    //   749: aload 5
    //   751: astore_1
    //   752: aload 5
    //   754: aload 11
    //   756: invokevirtual 299	java/io/ObjectOutputStream:writeObject	(Ljava/lang/Object;)V
    //   759: aload 5
    //   761: astore_1
    //   762: aload 5
    //   764: invokevirtual 302	java/io/ObjectOutputStream:flush	()V
    //   767: aload 5
    //   769: invokevirtual 305	java/io/ObjectOutputStream:close	()V
    //   772: goto -289 -> 483
    //   775: astore_1
    //   776: new 61	java/lang/StringBuilder
    //   779: astore 5
    //   781: aload 5
    //   783: ldc_w 307
    //   786: invokespecial 275	java/lang/StringBuilder:<init>	(Ljava/lang/String;)V
    //   789: ldc_w 309
    //   792: aload 5
    //   794: aload_1
    //   795: invokevirtual 278	java/lang/Exception:getMessage	()Ljava/lang/String;
    //   798: invokevirtual 71	java/lang/StringBuilder:append	(Ljava/lang/String;)Ljava/lang/StringBuilder;
    //   801: invokevirtual 77	java/lang/StringBuilder:toString	()Ljava/lang/String;
    //   804: invokestatic 313	com/tencent/mm/sdk/platformtools/ab:w	(Ljava/lang/String;Ljava/lang/String;)V
    //   807: goto -324 -> 483
    //   810: astore 5
    //   812: new 61	java/lang/StringBuilder
    //   815: astore_1
    //   816: aload_1
    //   817: ldc_w 315
    //   820: invokespecial 275	java/lang/StringBuilder:<init>	(Ljava/lang/String;)V
    //   823: ldc 141
    //   825: aload_1
    //   826: aload 5
    //   828: invokevirtual 278	java/lang/Exception:getMessage	()Ljava/lang/String;
    //   831: invokevirtual 71	java/lang/StringBuilder:append	(Ljava/lang/String;)Ljava/lang/StringBuilder;
    //   834: invokevirtual 77	java/lang/StringBuilder:toString	()Ljava/lang/String;
    //   837: iconst_1
    //   838: anewarray 4	java/lang/Object
    //   841: dup
    //   842: iconst_0
    //   843: aload_0
    //   844: getfield 57	com/tencent/mm/an/c:fAz	Ljava/lang/String;
    //   847: aastore
    //   848: invokestatic 281	com/tencent/mm/sdk/platformtools/ab:e	(Ljava/lang/String;Ljava/lang/String;[Ljava/lang/Object;)V
    //   851: goto -368 -> 483
    //   854: astore 11
    //   856: aconst_null
    //   857: astore 5
    //   859: aload 5
    //   861: astore_1
    //   862: new 61	java/lang/StringBuilder
    //   865: astore 12
    //   867: aload 5
    //   869: astore_1
    //   870: aload 12
    //   872: ldc_w 317
    //   875: invokespecial 275	java/lang/StringBuilder:<init>	(Ljava/lang/String;)V
    //   878: aload 5
    //   880: astore_1
    //   881: ldc_w 309
    //   884: aload 12
    //   886: aload 11
    //   888: invokevirtual 278	java/lang/Exception:getMessage	()Ljava/lang/String;
    //   891: invokevirtual 71	java/lang/StringBuilder:append	(Ljava/lang/String;)Ljava/lang/StringBuilder;
    //   894: invokevirtual 77	java/lang/StringBuilder:toString	()Ljava/lang/String;
    //   897: invokestatic 313	com/tencent/mm/sdk/platformtools/ab:w	(Ljava/lang/String;Ljava/lang/String;)V
    //   900: aload 5
    //   902: ifnull -419 -> 483
    //   905: aload 5
    //   907: invokevirtual 305	java/io/ObjectOutputStream:close	()V
    //   910: goto -427 -> 483
    //   913: astore 5
    //   915: new 61	java/lang/StringBuilder
    //   918: astore_1
    //   919: aload_1
    //   920: ldc_w 307
    //   923: invokespecial 275	java/lang/StringBuilder:<init>	(Ljava/lang/String;)V
    //   926: ldc_w 309
    //   929: aload_1
    //   930: aload 5
    //   932: invokevirtual 278	java/lang/Exception:getMessage	()Ljava/lang/String;
    //   935: invokevirtual 71	java/lang/StringBuilder:append	(Ljava/lang/String;)Ljava/lang/StringBuilder;
    //   938: invokevirtual 77	java/lang/StringBuilder:toString	()Ljava/lang/String;
    //   941: invokestatic 313	com/tencent/mm/sdk/platformtools/ab:w	(Ljava/lang/String;Ljava/lang/String;)V
    //   944: goto -461 -> 483
    //   947: astore 5
    //   949: aconst_null
    //   950: astore_1
    //   951: aload_1
    //   952: ifnull +7 -> 959
    //   955: aload_1
    //   956: invokevirtual 305	java/io/ObjectOutputStream:close	()V
    //   959: ldc 174
    //   961: invokestatic 99	com/tencent/matrix/trace/core/AppMethodBeat:o	(I)V
    //   964: aload 5
    //   966: athrow
    //   967: astore_1
    //   968: new 61	java/lang/StringBuilder
    //   971: astore 11
    //   973: aload 11
    //   975: ldc_w 307
    //   978: invokespecial 275	java/lang/StringBuilder:<init>	(Ljava/lang/String;)V
    //   981: ldc_w 309
    //   984: aload 11
    //   986: aload_1
    //   987: invokevirtual 278	java/lang/Exception:getMessage	()Ljava/lang/String;
    //   990: invokevirtual 71	java/lang/StringBuilder:append	(Ljava/lang/String;)Ljava/lang/StringBuilder;
    //   993: invokevirtual 77	java/lang/StringBuilder:toString	()Ljava/lang/String;
    //   996: invokestatic 313	com/tencent/mm/sdk/platformtools/ab:w	(Ljava/lang/String;Ljava/lang/String;)V
    //   999: goto -40 -> 959
    //   1002: ldc 174
    //   1004: invokestatic 99	com/tencent/matrix/trace/core/AppMethodBeat:o	(I)V
    //   1007: return
    //   1008: astore 5
    //   1010: goto -59 -> 951
    //   1013: astore 11
    //   1015: goto -156 -> 859
    //
    // Exception table:
    //   from	to	target	type
    //   257	283	559	java/lang/InterruptedException
    //   289	299	559	java/lang/InterruptedException
    //   308	333	559	java/lang/InterruptedException
    //   342	347	559	java/lang/InterruptedException
    //   351	388	559	java/lang/InterruptedException
    //   388	446	559	java/lang/InterruptedException
    //   446	483	559	java/lang/InterruptedException
    //   483	550	559	java/lang/InterruptedException
    //   550	556	559	java/lang/InterruptedException
    //   635	646	559	java/lang/InterruptedException
    //   651	670	559	java/lang/InterruptedException
    //   696	715	559	java/lang/InterruptedException
    //   715	733	559	java/lang/InterruptedException
    //   767	772	559	java/lang/InterruptedException
    //   776	807	559	java/lang/InterruptedException
    //   812	851	559	java/lang/InterruptedException
    //   905	910	559	java/lang/InterruptedException
    //   915	944	559	java/lang/InterruptedException
    //   955	959	559	java/lang/InterruptedException
    //   959	967	559	java/lang/InterruptedException
    //   968	999	559	java/lang/InterruptedException
    //   72	92	595	java/lang/Exception
    //   96	152	595	java/lang/Exception
    //   257	283	673	java/lang/Exception
    //   289	299	673	java/lang/Exception
    //   308	333	673	java/lang/Exception
    //   342	347	673	java/lang/Exception
    //   351	388	673	java/lang/Exception
    //   388	446	673	java/lang/Exception
    //   446	483	673	java/lang/Exception
    //   483	550	673	java/lang/Exception
    //   550	556	673	java/lang/Exception
    //   635	646	673	java/lang/Exception
    //   651	670	673	java/lang/Exception
    //   696	715	673	java/lang/Exception
    //   812	851	673	java/lang/Exception
    //   767	772	775	java/lang/Exception
    //   715	733	810	java/lang/Exception
    //   776	807	810	java/lang/Exception
    //   915	944	810	java/lang/Exception
    //   959	967	810	java/lang/Exception
    //   968	999	810	java/lang/Exception
    //   738	749	854	java/lang/Exception
    //   905	910	913	java/lang/Exception
    //   738	749	947	finally
    //   955	959	967	java/lang/Exception
    //   752	759	1008	finally
    //   762	767	1008	finally
    //   862	867	1008	finally
    //   870	878	1008	finally
    //   881	900	1008	finally
    //   752	759	1013	java/lang/Exception
    //   762	767	1013	java/lang/Exception
  }
}

/* Location:           C:\Users\Lin\Downloads\dex-tools-2.1-SNAPSHOT\dex-tools-2.1-SNAPSHOT\classes7-dex2jar.jar
 * Qualified Name:     com.tencent.mm.an.c
 * JD-Core Version:    0.6.2
 */