package com.tencent.mm.plugin.webview.model;

import com.tencent.mm.plugin.webview.stub.d;

public final class b$1
  implements Runnable
{
  public b$1(b paramb, String paramString, d paramd)
  {
  }

  // ERROR //
  public final void run()
  {
    // Byte code:
    //   0: sipush 6568
    //   3: invokestatic 35	com/tencent/matrix/trace/core/AppMethodBeat:i	(I)V
    //   6: aload_0
    //   7: getfield 20	com/tencent/mm/plugin/webview/model/b$1:ulJ	Ljava/lang/String;
    //   10: ldc 37
    //   12: invokestatic 43	com/tencent/mm/sdk/platformtools/br:z	(Ljava/lang/String;Ljava/lang/String;)Ljava/util/Map;
    //   15: astore_1
    //   16: new 45	java/util/LinkedList
    //   19: dup
    //   20: invokespecial 46	java/util/LinkedList:<init>	()V
    //   23: astore_2
    //   24: aload_1
    //   25: ifnull +594 -> 619
    //   28: aload_1
    //   29: invokeinterface 52 1 0
    //   34: ifle +585 -> 619
    //   37: iconst_0
    //   38: istore_3
    //   39: iload_3
    //   40: aload_1
    //   41: invokeinterface 52 1 0
    //   46: if_icmpge +74 -> 120
    //   49: new 54	java/lang/StringBuilder
    //   52: dup
    //   53: ldc 56
    //   55: invokespecial 59	java/lang/StringBuilder:<init>	(Ljava/lang/String;)V
    //   58: astore 4
    //   60: iload_3
    //   61: ifne +565 -> 626
    //   64: ldc 61
    //   66: astore 5
    //   68: aload_1
    //   69: aload 4
    //   71: aload 5
    //   73: invokevirtual 65	java/lang/StringBuilder:append	(Ljava/lang/Object;)Ljava/lang/StringBuilder;
    //   76: ldc 67
    //   78: invokevirtual 70	java/lang/StringBuilder:append	(Ljava/lang/String;)Ljava/lang/StringBuilder;
    //   81: invokevirtual 74	java/lang/StringBuilder:toString	()Ljava/lang/String;
    //   84: invokeinterface 78 2 0
    //   89: checkcast 80	java/lang/String
    //   92: astore 5
    //   94: aload 5
    //   96: invokestatic 86	com/tencent/mm/sdk/platformtools/bo:isNullOrNil	(Ljava/lang/String;)Z
    //   99: ifeq +536 -> 635
    //   102: ldc 88
    //   104: ldc 90
    //   106: iconst_1
    //   107: anewarray 4	java/lang/Object
    //   110: dup
    //   111: iconst_0
    //   112: iload_3
    //   113: invokestatic 96	java/lang/Integer:valueOf	(I)Ljava/lang/Integer;
    //   116: aastore
    //   117: invokestatic 101	com/tencent/mm/sdk/platformtools/ab:i	(Ljava/lang/String;Ljava/lang/String;[Ljava/lang/Object;)V
    //   120: iconst_0
    //   121: istore_3
    //   122: new 54	java/lang/StringBuilder
    //   125: dup
    //   126: ldc 56
    //   128: invokespecial 59	java/lang/StringBuilder:<init>	(Ljava/lang/String;)V
    //   131: astore 4
    //   133: iload_3
    //   134: ifne +523 -> 657
    //   137: ldc 61
    //   139: astore 5
    //   141: aload_1
    //   142: aload 4
    //   144: aload 5
    //   146: invokevirtual 65	java/lang/StringBuilder:append	(Ljava/lang/Object;)Ljava/lang/StringBuilder;
    //   149: ldc 103
    //   151: invokevirtual 70	java/lang/StringBuilder:append	(Ljava/lang/String;)Ljava/lang/StringBuilder;
    //   154: invokevirtual 74	java/lang/StringBuilder:toString	()Ljava/lang/String;
    //   157: invokeinterface 78 2 0
    //   162: checkcast 80	java/lang/String
    //   165: astore 4
    //   167: new 54	java/lang/StringBuilder
    //   170: dup
    //   171: ldc 105
    //   173: invokespecial 59	java/lang/StringBuilder:<init>	(Ljava/lang/String;)V
    //   176: astore 6
    //   178: iload_3
    //   179: ifne +487 -> 666
    //   182: ldc 61
    //   184: astore 5
    //   186: aload_1
    //   187: aload 6
    //   189: aload 5
    //   191: invokevirtual 65	java/lang/StringBuilder:append	(Ljava/lang/Object;)Ljava/lang/StringBuilder;
    //   194: invokevirtual 74	java/lang/StringBuilder:toString	()Ljava/lang/String;
    //   197: invokeinterface 78 2 0
    //   202: checkcast 80	java/lang/String
    //   205: astore 5
    //   207: aload 4
    //   209: invokestatic 86	com/tencent/mm/sdk/platformtools/bo:isNullOrNil	(Ljava/lang/String;)Z
    //   212: ifeq +463 -> 675
    //   215: aload 5
    //   217: invokestatic 86	com/tencent/mm/sdk/platformtools/bo:isNullOrNil	(Ljava/lang/String;)Z
    //   220: ifeq +455 -> 675
    //   223: ldc 88
    //   225: ldc 107
    //   227: iconst_1
    //   228: anewarray 4	java/lang/Object
    //   231: dup
    //   232: iconst_0
    //   233: iload_3
    //   234: invokestatic 96	java/lang/Integer:valueOf	(I)Ljava/lang/Integer;
    //   237: aastore
    //   238: invokestatic 101	com/tencent/mm/sdk/platformtools/ab:i	(Ljava/lang/String;Ljava/lang/String;[Ljava/lang/Object;)V
    //   241: aload_0
    //   242: getfield 18	com/tencent/mm/plugin/webview/model/b$1:ulL	Lcom/tencent/mm/plugin/webview/model/b;
    //   245: getfield 111	com/tencent/mm/plugin/webview/model/b:ulI	Lcom/tencent/mm/plugin/webview/model/aq;
    //   248: invokevirtual 117	com/tencent/mm/plugin/webview/model/aq:cXT	()Lcom/tencent/mm/plugin/webview/model/aq$o;
    //   251: astore_1
    //   252: aload_2
    //   253: invokevirtual 121	java/util/LinkedList:iterator	()Ljava/util/Iterator;
    //   256: astore 4
    //   258: aload 4
    //   260: invokeinterface 127 1 0
    //   265: ifeq +518 -> 783
    //   268: aload 4
    //   270: invokeinterface 131 1 0
    //   275: checkcast 80	java/lang/String
    //   278: astore 6
    //   280: invokestatic 137	java/lang/System:currentTimeMillis	()J
    //   283: lstore 7
    //   285: aconst_null
    //   286: astore 5
    //   288: aload 6
    //   290: invokestatic 143	java/net/InetAddress:getByName	(Ljava/lang/String;)Ljava/net/InetAddress;
    //   293: astore_2
    //   294: aload_2
    //   295: astore 5
    //   297: invokestatic 137	java/lang/System:currentTimeMillis	()J
    //   300: lload 7
    //   302: lsub
    //   303: lstore 9
    //   305: aload_2
    //   306: astore 5
    //   308: ldc 88
    //   310: ldc 145
    //   312: iconst_2
    //   313: anewarray 4	java/lang/Object
    //   316: dup
    //   317: iconst_0
    //   318: aload 6
    //   320: aastore
    //   321: dup
    //   322: iconst_1
    //   323: lload 9
    //   325: invokestatic 150	java/lang/Long:valueOf	(J)Ljava/lang/Long;
    //   328: aastore
    //   329: invokestatic 101	com/tencent/mm/sdk/platformtools/ab:i	(Ljava/lang/String;Ljava/lang/String;[Ljava/lang/Object;)V
    //   332: aload_2
    //   333: astore 5
    //   335: aload_1
    //   336: lload 9
    //   338: putfield 156	com/tencent/mm/plugin/webview/model/aq$o:iBv	J
    //   341: aload_1
    //   342: aload 6
    //   344: putfield 159	com/tencent/mm/plugin/webview/model/aq$o:url	Ljava/lang/String;
    //   347: aload 5
    //   349: ifnull +410 -> 759
    //   352: aload_1
    //   353: iconst_1
    //   354: putfield 163	com/tencent/mm/plugin/webview/model/aq$o:cxT	Z
    //   357: aload_0
    //   358: getfield 22	com/tencent/mm/plugin/webview/model/b$1:ulK	Lcom/tencent/mm/plugin/webview/stub/d;
    //   361: astore 6
    //   363: aload 6
    //   365: ifnull -107 -> 258
    //   368: ldc 165
    //   370: ldc 167
    //   372: iconst_4
    //   373: anewarray 4	java/lang/Object
    //   376: dup
    //   377: iconst_0
    //   378: invokestatic 170	com/tencent/mm/plugin/webview/model/aq:aEn	()I
    //   381: invokestatic 96	java/lang/Integer:valueOf	(I)Ljava/lang/Integer;
    //   384: aastore
    //   385: dup
    //   386: iconst_1
    //   387: aload_1
    //   388: getfield 156	com/tencent/mm/plugin/webview/model/aq$o:iBv	J
    //   391: invokestatic 150	java/lang/Long:valueOf	(J)Ljava/lang/Long;
    //   394: aastore
    //   395: dup
    //   396: iconst_2
    //   397: aload_1
    //   398: getfield 159	com/tencent/mm/plugin/webview/model/aq$o:url	Ljava/lang/String;
    //   401: aastore
    //   402: dup
    //   403: iconst_3
    //   404: aload_1
    //   405: getfield 163	com/tencent/mm/plugin/webview/model/aq$o:cxT	Z
    //   408: invokestatic 175	java/lang/Boolean:valueOf	(Z)Ljava/lang/Boolean;
    //   411: aastore
    //   412: invokestatic 101	com/tencent/mm/sdk/platformtools/ab:i	(Ljava/lang/String;Ljava/lang/String;[Ljava/lang/Object;)V
    //   415: aload_1
    //   416: getfield 178	com/tencent/mm/plugin/webview/model/aq$o:uni	Ljava/lang/String;
    //   419: astore_2
    //   420: aload_1
    //   421: getfield 156	com/tencent/mm/plugin/webview/model/aq$o:iBv	J
    //   424: lstore 9
    //   426: invokestatic 184	com/tencent/mm/sdk/platformtools/ah:getContext	()Landroid/content/Context;
    //   429: invokestatic 190	com/tencent/mm/sdk/platformtools/at:getNetType	(Landroid/content/Context;)I
    //   432: istore_3
    //   433: aload_1
    //   434: getfield 159	com/tencent/mm/plugin/webview/model/aq$o:url	Ljava/lang/String;
    //   437: ifnonnull +330 -> 767
    //   440: aload_1
    //   441: getfield 159	com/tencent/mm/plugin/webview/model/aq$o:url	Ljava/lang/String;
    //   444: astore 5
    //   446: aload 6
    //   448: aload_2
    //   449: bipush 11
    //   451: anewarray 4	java/lang/Object
    //   454: dup
    //   455: iconst_0
    //   456: iconst_1
    //   457: invokestatic 96	java/lang/Integer:valueOf	(I)Ljava/lang/Integer;
    //   460: aastore
    //   461: dup
    //   462: iconst_1
    //   463: lload 9
    //   465: invokestatic 150	java/lang/Long:valueOf	(J)Ljava/lang/Long;
    //   468: aastore
    //   469: dup
    //   470: iconst_2
    //   471: iload_3
    //   472: invokestatic 96	java/lang/Integer:valueOf	(I)Ljava/lang/Integer;
    //   475: aastore
    //   476: dup
    //   477: iconst_3
    //   478: aload 5
    //   480: aastore
    //   481: dup
    //   482: iconst_4
    //   483: iconst_0
    //   484: invokestatic 96	java/lang/Integer:valueOf	(I)Ljava/lang/Integer;
    //   487: aastore
    //   488: dup
    //   489: iconst_5
    //   490: iconst_0
    //   491: invokestatic 96	java/lang/Integer:valueOf	(I)Ljava/lang/Integer;
    //   494: aastore
    //   495: dup
    //   496: bipush 6
    //   498: iconst_0
    //   499: invokestatic 96	java/lang/Integer:valueOf	(I)Ljava/lang/Integer;
    //   502: aastore
    //   503: dup
    //   504: bipush 7
    //   506: invokestatic 193	com/tencent/mm/plugin/webview/model/aq:access$000	()I
    //   509: invokestatic 96	java/lang/Integer:valueOf	(I)Ljava/lang/Integer;
    //   512: aastore
    //   513: dup
    //   514: bipush 8
    //   516: invokestatic 196	com/tencent/mm/plugin/webview/model/aq:access$100	()I
    //   519: invokestatic 96	java/lang/Integer:valueOf	(I)Ljava/lang/Integer;
    //   522: aastore
    //   523: dup
    //   524: bipush 9
    //   526: aload_1
    //   527: getfield 200	com/tencent/mm/plugin/webview/model/aq$o:cSQ	I
    //   530: invokestatic 96	java/lang/Integer:valueOf	(I)Ljava/lang/Integer;
    //   533: aastore
    //   534: dup
    //   535: bipush 10
    //   537: aload_1
    //   538: getfield 178	com/tencent/mm/plugin/webview/model/aq$o:uni	Ljava/lang/String;
    //   541: aastore
    //   542: invokestatic 204	com/tencent/mm/plugin/webview/model/aq:b	(Lcom/tencent/mm/plugin/webview/stub/d;Ljava/lang/String;[Ljava/lang/Object;)V
    //   545: aload_1
    //   546: getfield 163	com/tencent/mm/plugin/webview/model/aq$o:cxT	Z
    //   549: ifne +17 -> 566
    //   552: getstatic 210	com/tencent/mm/plugin/report/service/h:pYm	Lcom/tencent/mm/plugin/report/service/h;
    //   555: ldc2_w 211
    //   558: ldc2_w 213
    //   561: lconst_1
    //   562: iconst_1
    //   563: invokevirtual 218	com/tencent/mm/plugin/report/service/h:a	(JJJZ)V
    //   566: getstatic 210	com/tencent/mm/plugin/report/service/h:pYm	Lcom/tencent/mm/plugin/report/service/h;
    //   569: ldc2_w 211
    //   572: lconst_1
    //   573: lconst_1
    //   574: iconst_1
    //   575: invokevirtual 218	com/tencent/mm/plugin/report/service/h:a	(JJJZ)V
    //   578: getstatic 210	com/tencent/mm/plugin/report/service/h:pYm	Lcom/tencent/mm/plugin/report/service/h;
    //   581: ldc2_w 211
    //   584: ldc2_w 219
    //   587: aload_1
    //   588: getfield 156	com/tencent/mm/plugin/webview/model/aq$o:iBv	J
    //   591: iconst_1
    //   592: invokevirtual 218	com/tencent/mm/plugin/report/service/h:a	(JJJZ)V
    //   595: goto -337 -> 258
    //   598: astore 5
    //   600: ldc 88
    //   602: ldc 222
    //   604: iconst_1
    //   605: anewarray 4	java/lang/Object
    //   608: dup
    //   609: iconst_0
    //   610: aload 5
    //   612: invokevirtual 225	java/lang/Exception:getMessage	()Ljava/lang/String;
    //   615: aastore
    //   616: invokestatic 228	com/tencent/mm/sdk/platformtools/ab:e	(Ljava/lang/String;Ljava/lang/String;[Ljava/lang/Object;)V
    //   619: sipush 6568
    //   622: invokestatic 231	com/tencent/matrix/trace/core/AppMethodBeat:o	(I)V
    //   625: return
    //   626: iload_3
    //   627: invokestatic 96	java/lang/Integer:valueOf	(I)Ljava/lang/Integer;
    //   630: astore 5
    //   632: goto -564 -> 68
    //   635: aload_2
    //   636: aload 5
    //   638: invokevirtual 235	java/util/LinkedList:contains	(Ljava/lang/Object;)Z
    //   641: ifne +10 -> 651
    //   644: aload_2
    //   645: aload 5
    //   647: invokevirtual 238	java/util/LinkedList:add	(Ljava/lang/Object;)Z
    //   650: pop
    //   651: iinc 3 1
    //   654: goto -615 -> 39
    //   657: iload_3
    //   658: invokestatic 96	java/lang/Integer:valueOf	(I)Ljava/lang/Integer;
    //   661: astore 5
    //   663: goto -522 -> 141
    //   666: iload_3
    //   667: invokestatic 96	java/lang/Integer:valueOf	(I)Ljava/lang/Integer;
    //   670: astore 5
    //   672: goto -486 -> 186
    //   675: aload 4
    //   677: invokestatic 86	com/tencent/mm/sdk/platformtools/bo:isNullOrNil	(Ljava/lang/String;)Z
    //   680: ifne +19 -> 699
    //   683: aload_2
    //   684: aload 4
    //   686: invokevirtual 235	java/util/LinkedList:contains	(Ljava/lang/Object;)Z
    //   689: ifne +10 -> 699
    //   692: aload_2
    //   693: aload 4
    //   695: invokevirtual 238	java/util/LinkedList:add	(Ljava/lang/Object;)Z
    //   698: pop
    //   699: aload 5
    //   701: invokestatic 86	com/tencent/mm/sdk/platformtools/bo:isNullOrNil	(Ljava/lang/String;)Z
    //   704: ifne +19 -> 723
    //   707: aload_2
    //   708: aload 5
    //   710: invokevirtual 235	java/util/LinkedList:contains	(Ljava/lang/Object;)Z
    //   713: ifne +10 -> 723
    //   716: aload_2
    //   717: aload 5
    //   719: invokevirtual 238	java/util/LinkedList:add	(Ljava/lang/Object;)Z
    //   722: pop
    //   723: iinc 3 1
    //   726: goto -604 -> 122
    //   729: astore_2
    //   730: ldc 88
    //   732: ldc 240
    //   734: iconst_1
    //   735: anewarray 4	java/lang/Object
    //   738: dup
    //   739: iconst_0
    //   740: aload_2
    //   741: invokevirtual 225	java/lang/Exception:getMessage	()Ljava/lang/String;
    //   744: aastore
    //   745: invokestatic 228	com/tencent/mm/sdk/platformtools/ab:e	(Ljava/lang/String;Ljava/lang/String;[Ljava/lang/Object;)V
    //   748: invokestatic 137	java/lang/System:currentTimeMillis	()J
    //   751: lload 7
    //   753: lsub
    //   754: lstore 9
    //   756: goto -421 -> 335
    //   759: aload_1
    //   760: iconst_0
    //   761: putfield 163	com/tencent/mm/plugin/webview/model/aq$o:cxT	Z
    //   764: goto -407 -> 357
    //   767: aload_1
    //   768: getfield 159	com/tencent/mm/plugin/webview/model/aq$o:url	Ljava/lang/String;
    //   771: ldc 242
    //   773: ldc 244
    //   775: invokevirtual 248	java/lang/String:replace	(Ljava/lang/CharSequence;Ljava/lang/CharSequence;)Ljava/lang/String;
    //   778: astore 5
    //   780: goto -334 -> 446
    //   783: sipush 6568
    //   786: invokestatic 231	com/tencent/matrix/trace/core/AppMethodBeat:o	(I)V
    //   789: goto -164 -> 625
    //
    // Exception table:
    //   from	to	target	type
    //   252	258	598	java/lang/Exception
    //   258	285	598	java/lang/Exception
    //   335	347	598	java/lang/Exception
    //   352	357	598	java/lang/Exception
    //   357	363	598	java/lang/Exception
    //   368	446	598	java/lang/Exception
    //   446	566	598	java/lang/Exception
    //   566	595	598	java/lang/Exception
    //   730	756	598	java/lang/Exception
    //   759	764	598	java/lang/Exception
    //   767	780	598	java/lang/Exception
    //   288	294	729	java/lang/Exception
    //   297	305	729	java/lang/Exception
    //   308	332	729	java/lang/Exception
  }
}

/* Location:           C:\Users\Lin\Downloads\dex-tools-2.1-SNAPSHOT\dex-tools-2.1-SNAPSHOT\classes5-dex2jar.jar
 * Qualified Name:     com.tencent.mm.plugin.webview.model.b.1
 * JD-Core Version:    0.6.2
 */