package com.tencent.mm.wallet_core.c;

import android.text.TextUtils;
import com.tencent.mars.smc.IDKey;
import com.tencent.matrix.trace.core.AppMethodBeat;
import com.tencent.mm.plugin.report.service.h;
import com.tencent.mm.sdk.platformtools.ab;
import java.util.ArrayList;
import java.util.Collection;

public final class z
{
  public static long AfW = 0L;
  public static int tPj = 1;
  public static int tPk = 2;

  private static boolean QO(int paramInt)
  {
    if ((paramInt == 1581) || (paramInt == 1685));
    for (boolean bool = true; ; bool = false)
      return bool;
  }

  public static void a(int paramInt1, int paramInt2, int paramInt3, int paramInt4, long paramLong, int paramInt5, String paramString)
  {
    AppMethodBeat.i(49091);
    int i;
    int j;
    if ((hM(paramInt1, paramInt2)) || (hN(paramInt1, paramInt2)) || (hO(paramInt1, paramInt2)) || (QO(paramInt1)) || (hP(paramInt1, paramInt2)))
    {
      ab.i("MicroMsg.WalletReportUtil", "reportIDKeyWalletPay the cmdType is for idkey report cmdType:" + paramInt1 + " cmdid:" + paramInt2);
      i = -1;
      if (paramInt5 != 4)
        break label398;
      i = 132;
      j = i;
      if (i == -1)
      {
        ab.e("MicroMsg.WalletReportUtil", "reportIDKeyWalletPay get ID by scene is -1, the scene is ".concat(String.valueOf(paramInt5)));
        paramInt5 = -1;
        j = paramInt5;
        if (paramInt1 == 385)
        {
          j = paramInt5;
          if (paramInt2 == 74)
            j = 134;
        }
        if ((paramInt1 != 385) || (paramInt2 != 75))
          break label586;
        j = 139;
      }
      label160: paramInt5 = j;
      if (j == -1)
      {
        ab.e("MicroMsg.WalletReportUtil", "reportIDKeyWalletPay the cmdType is for idkey report cmdType:" + paramInt1 + " cmdid:" + paramInt2 + " , ID is -1");
        paramInt5 = -1;
        if (!TextUtils.isEmpty(paramString))
          break label726;
        paramInt5 = -1;
      }
    }
    IDKey localIDKey;
    while (true)
    {
      if (paramInt5 != -1)
        break label762;
      ab.e("MicroMsg.WalletReportUtil", "reportIDKeyWalletPay the processName is for idkey report processName:" + paramString + " , ID is -1");
      AppMethodBeat.o(49091);
      while (true)
      {
        return;
        if ((paramInt1 == 385) && (paramInt2 == 19));
        for (paramInt1 = 1; ; paramInt1 = 0)
        {
          if (paramInt1 == 0)
            break label390;
          paramString = new ArrayList();
          localIDKey = new IDKey();
          localIDKey.SetID(136);
          localIDKey.SetValue(1L);
          localIDKey.SetKey(0);
          paramString.add(localIDKey);
          if ((paramInt3 != 0) || (paramInt4 != 0))
          {
            localIDKey = new IDKey();
            localIDKey.SetID(136);
            localIDKey.SetValue(1L);
            localIDKey.SetKey(1);
            paramString.add(localIDKey);
          }
          h.pYm.b(paramString, true);
          AppMethodBeat.o(49091);
          break;
        }
        label390: AppMethodBeat.o(49091);
      }
      label398: if (paramInt5 == 1)
      {
        i = 163;
        break;
      }
      if ((paramInt5 == 2) || (paramInt5 == 36))
      {
        i = 131;
        break;
      }
      if (paramInt5 == 3)
      {
        i = 130;
        break;
      }
      if (paramInt5 == 5)
      {
        i = 153;
        break;
      }
      if (paramInt5 == 100)
      {
        i = 133;
        break;
      }
      if ((paramInt5 == 6) || (paramInt5 == 1001))
      {
        i = 152;
        break;
      }
      if (paramInt5 == 11)
      {
        i = 134;
        break;
      }
      if (paramInt5 == 21)
      {
        i = 139;
        break;
      }
      if ((paramInt5 == 31) || (paramInt5 == 33) || (paramInt5 == 32))
      {
        i = 118;
        break;
      }
      if (paramInt5 == 37)
      {
        i = 117;
        break;
      }
      if (paramInt5 != 39)
        break;
      i = 298;
      break;
      label586: if (QO(paramInt1))
      {
        j = 117;
        break label160;
      }
      if (hP(paramInt1, paramInt2))
      {
        j = 145;
        break label160;
      }
      if (paramInt1 == 397)
      {
        j = 131;
        break label160;
      }
      if (paramInt1 == 398)
      {
        j = 130;
        break label160;
      }
      if (paramInt1 == 422)
      {
        j = 153;
        break label160;
      }
      if (paramInt1 == 556)
      {
        j = 152;
        break label160;
      }
      if (paramInt1 == 498)
      {
        j = 133;
        break label160;
      }
      if ((paramInt1 == 1544) || (paramInt1 == 1582))
      {
        j = 118;
        break label160;
      }
      if (paramInt1 != 1575)
        break label160;
      j = 117;
      break label160;
      label726: if (paramString.equals("BalanceFetchProcess"))
        paramInt5 = 139;
      else if (paramString.equals("BalanceSaveProcess"))
        paramInt5 = 134;
    }
    label762: paramString = new IDKey();
    paramString.SetID(paramInt5);
    paramString.SetValue(1L);
    label799: Object localObject1;
    Object localObject2;
    Object localObject3;
    if (hM(paramInt1, paramInt2))
    {
      paramString.SetKey(26);
      localObject1 = new ArrayList();
      localIDKey = new IDKey();
      localIDKey.SetID(paramInt5);
      localIDKey.SetValue(1L);
      localObject2 = new IDKey();
      ((IDKey)localObject2).SetID(paramInt5);
      ((IDKey)localObject2).SetValue(1L);
      localObject3 = new IDKey();
      ((IDKey)localObject3).SetID(paramInt5);
      ((IDKey)localObject3).SetValue((int)paramLong);
      if (!hM(paramInt1, paramInt2))
        break label1299;
      localIDKey.SetKey(19);
      if (paramLong > 1000L)
        break label1238;
      ((IDKey)localObject2).SetKey(20);
      ((IDKey)localObject3).SetKey(23);
      label915: ((ArrayList)localObject1).add(localIDKey);
      ((ArrayList)localObject1).add(localObject2);
      ((ArrayList)localObject1).add(localObject3);
      h.pYm.b((ArrayList)localObject1, true);
      localObject3 = new ArrayList();
      if ((paramInt3 != 0) || (paramInt4 != 0))
      {
        localObject2 = new ArrayList();
        localObject1 = new IDKey();
        ((IDKey)localObject1).SetID(paramInt5);
        ((IDKey)localObject1).SetValue(1L);
        localIDKey = new IDKey();
        localIDKey.SetID(paramInt5);
        localIDKey.SetValue(1L);
        if (!hM(paramInt1, paramInt2))
          break label1910;
        ((IDKey)localObject1).SetKey(27);
        if (paramInt4 >= 0)
          break label1896;
        localIDKey.SetKey(28);
      }
    }
    while (true)
    {
      ((ArrayList)localObject2).add(localObject1);
      ((ArrayList)localObject2).add(localIDKey);
      ((ArrayList)localObject3).addAll((Collection)localObject2);
      ((ArrayList)localObject3).add(paramString);
      h.pYm.b((ArrayList)localObject3, true);
      AppMethodBeat.o(49091);
      break;
      if (hN(paramInt1, paramInt2))
      {
        paramString.SetKey(45);
        break label799;
      }
      if (QO(paramInt1))
      {
        if (paramInt1 == 1581)
        {
          paramString.SetKey(64);
          break label799;
        }
        paramString.SetKey(83);
        break label799;
      }
      if (hP(paramInt1, paramInt2))
      {
        if (paramInt2 == 0)
        {
          paramString.SetKey(7);
          break label799;
        }
        paramString.SetKey(26);
        break label799;
      }
      if (hO(paramInt1, paramInt2))
      {
        paramString.SetKey(7);
        break label799;
      }
      ab.e("MicroMsg.WalletReportUtil", "reportIDKeyWalletPay the cmdType is for idkey report cmdType:" + paramInt1 + " cmdid:" + paramInt2 + " , ID is -1");
      AppMethodBeat.o(49091);
      break;
      label1238: if ((paramLong > 1000L) && (paramLong <= 3000L))
      {
        ((IDKey)localObject2).SetKey(21);
        ((IDKey)localObject3).SetKey(24);
        break label915;
      }
      if (paramLong <= 3000L)
        break label915;
      ((IDKey)localObject2).SetKey(22);
      ((IDKey)localObject3).SetKey(25);
      break label915;
      label1299: if (hN(paramInt1, paramInt2))
      {
        localIDKey.SetKey(38);
        if (paramLong <= 1000L)
        {
          ((IDKey)localObject2).SetKey(39);
          ((IDKey)localObject3).SetKey(42);
          break label915;
        }
        if ((paramLong > 1000L) && (paramLong <= 3000L))
        {
          ((IDKey)localObject2).SetKey(40);
          ((IDKey)localObject3).SetKey(43);
          break label915;
        }
        if (paramLong <= 3000L)
          break label915;
        ((IDKey)localObject2).SetKey(41);
        ((IDKey)localObject3).SetKey(44);
        break label915;
      }
      if (paramInt1 == 1581)
      {
        localIDKey.SetKey(57);
        if (paramLong <= 1000L)
        {
          ((IDKey)localObject2).SetKey(58);
          ((IDKey)localObject3).SetKey(61);
          break label915;
        }
        if ((paramLong > 1000L) && (paramLong <= 3000L))
        {
          ((IDKey)localObject2).SetKey(59);
          ((IDKey)localObject3).SetKey(62);
          break label915;
        }
        if (paramLong <= 3000L)
          break label915;
        ((IDKey)localObject2).SetKey(60);
        ((IDKey)localObject3).SetKey(63);
        break label915;
      }
      if (paramInt1 == 1685)
      {
        localIDKey.SetKey(76);
        if (paramLong <= 1000L)
        {
          ((IDKey)localObject2).SetKey(77);
          ((IDKey)localObject3).SetKey(80);
          break label915;
        }
        if ((paramLong > 1000L) && (paramLong <= 3000L))
        {
          ((IDKey)localObject2).SetKey(78);
          ((IDKey)localObject3).SetKey(81);
          break label915;
        }
        if (paramLong <= 3000L)
          break label915;
        ((IDKey)localObject2).SetKey(79);
        ((IDKey)localObject3).SetKey(82);
        break label915;
      }
      if ((paramInt1 == 1558) && (paramInt2 == 0))
      {
        localIDKey.SetKey(0);
        if (paramLong <= 1000L)
        {
          ((IDKey)localObject2).SetKey(1);
          ((IDKey)localObject3).SetKey(4);
          break label915;
        }
        if ((paramLong > 1000L) && (paramLong <= 3000L))
        {
          ((IDKey)localObject2).SetKey(2);
          ((IDKey)localObject3).SetKey(5);
          break label915;
        }
        if (paramLong <= 3000L)
          break label915;
        ((IDKey)localObject2).SetKey(3);
        ((IDKey)localObject3).SetKey(6);
        break label915;
      }
      if ((paramInt1 == 1558) && (paramInt2 == 1))
      {
        localIDKey.SetKey(19);
        if (paramLong <= 1000L)
        {
          ((IDKey)localObject2).SetKey(20);
          ((IDKey)localObject3).SetKey(23);
          break label915;
        }
        if ((paramLong > 1000L) && (paramLong <= 3000L))
        {
          ((IDKey)localObject2).SetKey(21);
          ((IDKey)localObject3).SetKey(24);
          break label915;
        }
        if (paramLong <= 3000L)
          break label915;
        ((IDKey)localObject2).SetKey(22);
        ((IDKey)localObject3).SetKey(25);
        break label915;
      }
      localIDKey.SetKey(0);
      if (paramLong <= 1000L)
      {
        ((IDKey)localObject2).SetKey(1);
        ((IDKey)localObject3).SetKey(4);
        break label915;
      }
      if ((paramLong > 1000L) && (paramLong <= 3000L))
      {
        ((IDKey)localObject2).SetKey(2);
        ((IDKey)localObject3).SetKey(5);
        break label915;
      }
      if (paramLong <= 3000L)
        break label915;
      ((IDKey)localObject2).SetKey(3);
      ((IDKey)localObject3).SetKey(6);
      break label915;
      label1896: if (paramInt4 > 0)
      {
        localIDKey.SetKey(29);
        continue;
        label1910: if (hN(paramInt1, paramInt2))
        {
          ((IDKey)localObject1).SetKey(46);
          if (paramInt4 < 0)
            localIDKey.SetKey(47);
          else if (paramInt4 > 0)
            localIDKey.SetKey(48);
        }
        else if (paramInt1 == 1581)
        {
          ((IDKey)localObject1).SetKey(65);
          if (paramInt4 < 0)
            localIDKey.SetKey(66);
          else if (paramInt4 > 0)
            localIDKey.SetKey(67);
        }
        else if (paramInt1 == 1685)
        {
          ((IDKey)localObject1).SetKey(84);
          if (paramInt4 < 0)
            localIDKey.SetKey(85);
          else if (paramInt4 > 0)
            localIDKey.SetKey(86);
        }
        else if ((paramInt1 == 1558) && (paramInt2 == 0))
        {
          ((IDKey)localObject1).SetKey(8);
          if (paramInt4 < 0)
            localIDKey.SetKey(9);
          else if (paramInt4 > 0)
            localIDKey.SetKey(10);
        }
        else if ((paramInt1 == 1558) && (paramInt2 == 1))
        {
          ((IDKey)localObject1).SetKey(27);
          if (paramInt4 < 0)
            localIDKey.SetKey(28);
          else if (paramInt4 > 0)
            localIDKey.SetKey(29);
        }
        else
        {
          ((IDKey)localObject1).SetKey(8);
          if (paramInt4 < 0)
            localIDKey.SetKey(9);
          else if (paramInt4 > 0)
            localIDKey.SetKey(10);
        }
      }
    }
  }

  // ERROR //
  public static void d(String paramString1, String paramString2, String paramString3, int paramInt, String paramString4)
  {
    // Byte code:
    //   0: ldc 151
    //   2: invokestatic 29	com/tencent/matrix/trace/core/AppMethodBeat:i	(I)V
    //   5: aload_2
    //   6: ifnull +10 -> 16
    //   9: aload_2
    //   10: invokevirtual 155	java/lang/String:length	()I
    //   13: ifgt +9 -> 22
    //   16: ldc 151
    //   18: invokestatic 100	com/tencent/matrix/trace/core/AppMethodBeat:o	(I)V
    //   21: return
    //   22: aconst_null
    //   23: astore 5
    //   25: aconst_null
    //   26: astore 6
    //   28: aconst_null
    //   29: astore 7
    //   31: aload_2
    //   32: iconst_0
    //   33: invokevirtual 159	java/lang/String:charAt	(I)C
    //   36: invokestatic 165	java/lang/Character:isDigit	(C)Z
    //   39: istore 8
    //   41: iload 8
    //   43: ifeq +160 -> 203
    //   46: iconst_0
    //   47: istore 9
    //   49: aload_2
    //   50: astore 10
    //   52: aload 7
    //   54: astore 6
    //   56: aload 6
    //   58: astore 11
    //   60: aload 10
    //   62: astore 5
    //   64: aload 6
    //   66: astore_2
    //   67: aload 10
    //   69: astore 7
    //   71: iload 9
    //   73: aload 10
    //   75: invokevirtual 155	java/lang/String:length	()I
    //   78: if_icmpge +309 -> 387
    //   81: aload 6
    //   83: astore_2
    //   84: aload 10
    //   86: astore 7
    //   88: aload 10
    //   90: iload 9
    //   92: invokevirtual 159	java/lang/String:charAt	(I)C
    //   95: istore 12
    //   97: aload 6
    //   99: astore 11
    //   101: aload 10
    //   103: astore 5
    //   105: aload 6
    //   107: astore_2
    //   108: aload 10
    //   110: astore 7
    //   112: iload 12
    //   114: invokestatic 165	java/lang/Character:isDigit	(C)Z
    //   117: ifne +72 -> 189
    //   120: aload 6
    //   122: astore 11
    //   124: aload 10
    //   126: astore 5
    //   128: aload 6
    //   130: astore_2
    //   131: aload 10
    //   133: astore 7
    //   135: ldc 167
    //   137: iload 12
    //   139: invokestatic 170	java/lang/String:valueOf	(C)Ljava/lang/String;
    //   142: invokevirtual 174	java/lang/String:equalsIgnoreCase	(Ljava/lang/String;)Z
    //   145: ifne +44 -> 189
    //   148: aload 6
    //   150: astore_2
    //   151: aload 10
    //   153: astore 7
    //   155: aload 10
    //   157: iload 9
    //   159: invokevirtual 177	java/lang/String:substring	(I)Ljava/lang/String;
    //   162: invokevirtual 180	java/lang/String:trim	()Ljava/lang/String;
    //   165: astore 11
    //   167: aload 11
    //   169: astore_2
    //   170: aload 10
    //   172: astore 7
    //   174: aload 10
    //   176: iconst_0
    //   177: iload 9
    //   179: iconst_1
    //   180: isub
    //   181: invokevirtual 183	java/lang/String:substring	(II)Ljava/lang/String;
    //   184: invokevirtual 180	java/lang/String:trim	()Ljava/lang/String;
    //   187: astore 5
    //   189: iinc 9 1
    //   192: aload 11
    //   194: astore 6
    //   196: aload 5
    //   198: astore 10
    //   200: goto -144 -> 56
    //   203: iconst_0
    //   204: istore 9
    //   206: aload_2
    //   207: astore 10
    //   209: aload 5
    //   211: astore 6
    //   213: aload 6
    //   215: astore 11
    //   217: aload 10
    //   219: astore 5
    //   221: aload 6
    //   223: astore_2
    //   224: aload 10
    //   226: astore 7
    //   228: iload 9
    //   230: aload 10
    //   232: invokevirtual 155	java/lang/String:length	()I
    //   235: if_icmpge +152 -> 387
    //   238: aload 6
    //   240: astore_2
    //   241: aload 10
    //   243: astore 7
    //   245: aload 10
    //   247: iload 9
    //   249: invokevirtual 159	java/lang/String:charAt	(I)C
    //   252: istore 12
    //   254: aload 6
    //   256: astore_2
    //   257: aload 10
    //   259: astore 7
    //   261: iload 12
    //   263: invokestatic 165	java/lang/Character:isDigit	(C)Z
    //   266: ifne +31 -> 297
    //   269: aload 6
    //   271: astore 11
    //   273: aload 10
    //   275: astore 5
    //   277: aload 6
    //   279: astore_2
    //   280: aload 10
    //   282: astore 7
    //   284: ldc 167
    //   286: iload 12
    //   288: invokestatic 170	java/lang/String:valueOf	(C)Ljava/lang/String;
    //   291: invokevirtual 174	java/lang/String:equalsIgnoreCase	(Ljava/lang/String;)Z
    //   294: ifeq +48 -> 342
    //   297: aload 6
    //   299: astore_2
    //   300: aload 10
    //   302: astore 7
    //   304: aload 10
    //   306: iconst_0
    //   307: iload 9
    //   309: iconst_1
    //   310: isub
    //   311: invokevirtual 183	java/lang/String:substring	(II)Ljava/lang/String;
    //   314: invokevirtual 180	java/lang/String:trim	()Ljava/lang/String;
    //   317: astore 6
    //   319: aload 6
    //   321: astore_2
    //   322: aload 10
    //   324: astore 7
    //   326: aload 10
    //   328: iload 9
    //   330: invokevirtual 177	java/lang/String:substring	(I)Ljava/lang/String;
    //   333: invokevirtual 180	java/lang/String:trim	()Ljava/lang/String;
    //   336: astore 5
    //   338: aload 6
    //   340: astore 11
    //   342: iinc 9 1
    //   345: aload 11
    //   347: astore 6
    //   349: aload 5
    //   351: astore 10
    //   353: goto -140 -> 213
    //   356: astore 10
    //   358: aload_2
    //   359: astore 7
    //   361: aload 6
    //   363: astore_2
    //   364: ldc 46
    //   366: ldc 185
    //   368: iconst_1
    //   369: anewarray 4	java/lang/Object
    //   372: dup
    //   373: iconst_0
    //   374: aload 10
    //   376: aastore
    //   377: invokestatic 188	com/tencent/mm/sdk/platformtools/ab:e	(Ljava/lang/String;Ljava/lang/String;[Ljava/lang/Object;)V
    //   380: aload 7
    //   382: astore 5
    //   384: aload_2
    //   385: astore 11
    //   387: getstatic 127	com/tencent/mm/plugin/report/service/h:pYm	Lcom/tencent/mm/plugin/report/service/h;
    //   390: sipush 10756
    //   393: bipush 6
    //   395: anewarray 4	java/lang/Object
    //   398: dup
    //   399: iconst_0
    //   400: aload_0
    //   401: aastore
    //   402: dup
    //   403: iconst_1
    //   404: aload_1
    //   405: aastore
    //   406: dup
    //   407: iconst_2
    //   408: aload 5
    //   410: aastore
    //   411: dup
    //   412: iconst_3
    //   413: aload 11
    //   415: aastore
    //   416: dup
    //   417: iconst_4
    //   418: iload_3
    //   419: invokestatic 193	java/lang/Integer:valueOf	(I)Ljava/lang/Integer;
    //   422: aastore
    //   423: dup
    //   424: iconst_5
    //   425: aload 4
    //   427: aastore
    //   428: invokevirtual 196	com/tencent/mm/plugin/report/service/h:e	(I[Ljava/lang/Object;)V
    //   431: ldc 151
    //   433: invokestatic 100	com/tencent/matrix/trace/core/AppMethodBeat:o	(I)V
    //   436: goto -415 -> 21
    //   439: astore 10
    //   441: goto -77 -> 364
    //
    // Exception table:
    //   from	to	target	type
    //   31	41	356	java/lang/Exception
    //   71	81	439	java/lang/Exception
    //   88	97	439	java/lang/Exception
    //   112	120	439	java/lang/Exception
    //   135	148	439	java/lang/Exception
    //   155	167	439	java/lang/Exception
    //   174	189	439	java/lang/Exception
    //   228	238	439	java/lang/Exception
    //   245	254	439	java/lang/Exception
    //   261	269	439	java/lang/Exception
    //   284	297	439	java/lang/Exception
    //   304	319	439	java/lang/Exception
    //   326	338	439	java/lang/Exception
  }

  public static void dNW()
  {
    AppMethodBeat.i(49087);
    AfW = System.currentTimeMillis();
    AppMethodBeat.o(49087);
  }

  public static int dNX()
  {
    AppMethodBeat.i(49088);
    int i = (int)((System.currentTimeMillis() - AfW) / 1000L);
    AppMethodBeat.o(49088);
    return i;
  }

  public static void hL(int paramInt1, int paramInt2)
  {
    AppMethodBeat.i(49090);
    h.pYm.e(12097, new Object[] { Integer.valueOf(paramInt1), Integer.valueOf(paramInt2), Long.valueOf(System.currentTimeMillis()) });
    AppMethodBeat.o(49090);
  }

  private static boolean hM(int paramInt1, int paramInt2)
  {
    if ((paramInt1 == 385) && (paramInt2 == 112));
    for (boolean bool = true; ; bool = false)
      return bool;
  }

  private static boolean hN(int paramInt1, int paramInt2)
  {
    boolean bool1 = true;
    if (paramInt1 == 385)
    {
      bool2 = bool1;
      if (paramInt2 != 0)
      {
        bool2 = bool1;
        if (paramInt2 != 1)
          if (paramInt2 != 16)
            break label32;
      }
    }
    label32: for (boolean bool2 = bool1; ; bool2 = false)
      return bool2;
  }

  private static boolean hO(int paramInt1, int paramInt2)
  {
    if ((paramInt1 == 398) || ((paramInt1 == 385) && ((paramInt2 == 74) || (paramInt2 == 75))) || (paramInt1 == 1544) || (paramInt1 == 1582) || (paramInt1 == 498) || (paramInt1 == 397) || (paramInt1 == 1575) || (paramInt1 == 1639) || (paramInt1 == 556) || (paramInt1 == 422));
    for (boolean bool = true; ; bool = false)
      return bool;
  }

  private static boolean hP(int paramInt1, int paramInt2)
  {
    boolean bool1 = true;
    if (paramInt1 == 1558)
    {
      bool2 = bool1;
      if (paramInt2 != 0)
        if (paramInt2 != 1)
          break label24;
    }
    label24: for (boolean bool2 = bool1; ; bool2 = false)
      return bool2;
  }
}

/* Location:           C:\Users\Lin\Downloads\dex-tools-2.1-SNAPSHOT\dex-tools-2.1-SNAPSHOT\classes5-dex2jar.jar
 * Qualified Name:     com.tencent.mm.wallet_core.c.z
 * JD-Core Version:    0.6.2
 */