package com.tencent.mm.plugin.appbrand.l.a;

import com.tencent.matrix.trace.core.AppMethodBeat;
import com.tencent.mm.plugin.appbrand.jsapi.c;
import com.tencent.mm.sdk.platformtools.ab;
import java.net.HttpURLConnection;
import java.util.ArrayList;
import java.util.Map;
import javax.net.ssl.SSLContext;

public final class b
  implements Runnable
{
  public int azs;
  private String filename;
  public String hvr;
  c hvw;
  private final String ibJ;
  public ArrayList<String> ioN;
  private int ioO;
  public String ioR;
  public SSLContext ios;
  private final a ipB;
  public Map<String, String> ipC;
  public volatile int ipD;
  private long ipE;
  private HttpURLConnection ipF;
  public volatile boolean isRunning;
  private long startTime;
  private String uri;

  public b(c paramc, String paramString1, String paramString2, String paramString3, a parama)
  {
    AppMethodBeat.i(108279);
    this.ioO = 15;
    this.isRunning = false;
    this.azs = 60000;
    this.hvw = paramc;
    this.uri = paramString1;
    this.filename = paramString2;
    this.ipB = parama;
    this.startTime = System.currentTimeMillis();
    this.ibJ = paramString3;
    AppMethodBeat.o(108279);
  }

  private int aID()
  {
    AppMethodBeat.i(108282);
    int i = (int)(System.currentTimeMillis() - this.startTime);
    AppMethodBeat.o(108282);
    return i;
  }

  public final void aIP()
  {
    AppMethodBeat.i(108281);
    this.isRunning = false;
    if (this.ipF != null);
    while (true)
    {
      try
      {
        this.ipF.disconnect();
        AppMethodBeat.o(108281);
        return;
      }
      catch (Exception localException)
      {
        ab.printErrStackTrace("MicroMsg.AppBrandDownloadWorker", localException, "abortTask Exception", new Object[0]);
      }
      AppMethodBeat.o(108281);
    }
  }

  // ERROR //
  public final void run()
  {
    // Byte code:
    //   0: ldc 116
    //   2: invokestatic 47	com/tencent/matrix/trace/core/AppMethodBeat:i	(I)V
    //   5: aload_0
    //   6: getfield 58	com/tencent/mm/plugin/appbrand/l/a/b:uri	Ljava/lang/String;
    //   9: invokestatic 122	android/webkit/URLUtil:isHttpsUrl	(Ljava/lang/String;)Z
    //   12: ifne +38 -> 50
    //   15: aload_0
    //   16: getfield 58	com/tencent/mm/plugin/appbrand/l/a/b:uri	Ljava/lang/String;
    //   19: invokestatic 125	android/webkit/URLUtil:isHttpUrl	(Ljava/lang/String;)Z
    //   22: ifne +28 -> 50
    //   25: aload_0
    //   26: getfield 62	com/tencent/mm/plugin/appbrand/l/a/b:ipB	Lcom/tencent/mm/plugin/appbrand/l/a/a;
    //   29: aload_0
    //   30: getfield 60	com/tencent/mm/plugin/appbrand/l/a/b:filename	Ljava/lang/String;
    //   33: aload_0
    //   34: getfield 58	com/tencent/mm/plugin/appbrand/l/a/b:uri	Ljava/lang/String;
    //   37: ldc 127
    //   39: invokeinterface 133 4 0
    //   44: ldc 116
    //   46: invokestatic 75	com/tencent/matrix/trace/core/AppMethodBeat:o	(I)V
    //   49: return
    //   50: aload_0
    //   51: getfield 135	com/tencent/mm/plugin/appbrand/l/a/b:ioN	Ljava/util/ArrayList;
    //   54: ifnull +62 -> 116
    //   57: aload_0
    //   58: getfield 135	com/tencent/mm/plugin/appbrand/l/a/b:ioN	Ljava/util/ArrayList;
    //   61: aload_0
    //   62: getfield 58	com/tencent/mm/plugin/appbrand/l/a/b:uri	Ljava/lang/String;
    //   65: invokestatic 141	com/tencent/mm/plugin/appbrand/l/j:c	(Ljava/util/ArrayList;Ljava/lang/String;)Z
    //   68: ifne +48 -> 116
    //   71: aload_0
    //   72: getfield 62	com/tencent/mm/plugin/appbrand/l/a/b:ipB	Lcom/tencent/mm/plugin/appbrand/l/a/a;
    //   75: aload_0
    //   76: getfield 60	com/tencent/mm/plugin/appbrand/l/a/b:filename	Ljava/lang/String;
    //   79: aload_0
    //   80: getfield 58	com/tencent/mm/plugin/appbrand/l/a/b:uri	Ljava/lang/String;
    //   83: ldc 143
    //   85: invokeinterface 133 4 0
    //   90: ldc 92
    //   92: ldc 145
    //   94: iconst_1
    //   95: anewarray 4	java/lang/Object
    //   98: dup
    //   99: iconst_0
    //   100: aload_0
    //   101: getfield 58	com/tencent/mm/plugin/appbrand/l/a/b:uri	Ljava/lang/String;
    //   104: aastore
    //   105: invokestatic 148	com/tencent/mm/sdk/platformtools/ab:i	(Ljava/lang/String;Ljava/lang/String;[Ljava/lang/Object;)V
    //   108: ldc 116
    //   110: invokestatic 75	com/tencent/matrix/trace/core/AppMethodBeat:o	(I)V
    //   113: goto -64 -> 49
    //   116: iconst_0
    //   117: istore_1
    //   118: iconst_0
    //   119: istore_2
    //   120: iconst_0
    //   121: istore_3
    //   122: iconst_0
    //   123: istore 4
    //   125: iconst_0
    //   126: istore 5
    //   128: iconst_0
    //   129: istore 6
    //   131: iconst_0
    //   132: istore 7
    //   134: iconst_0
    //   135: istore 8
    //   137: iconst_0
    //   138: istore 9
    //   140: iconst_0
    //   141: istore 10
    //   143: iconst_0
    //   144: istore 11
    //   146: aload_0
    //   147: getfield 51	com/tencent/mm/plugin/appbrand/l/a/b:isRunning	Z
    //   150: ifne +70 -> 220
    //   153: aload_0
    //   154: getfield 62	com/tencent/mm/plugin/appbrand/l/a/b:ipB	Lcom/tencent/mm/plugin/appbrand/l/a/a;
    //   157: aload_0
    //   158: getfield 60	com/tencent/mm/plugin/appbrand/l/a/b:filename	Ljava/lang/String;
    //   161: aload_0
    //   162: getfield 58	com/tencent/mm/plugin/appbrand/l/a/b:uri	Ljava/lang/String;
    //   165: ldc 150
    //   167: invokeinterface 133 4 0
    //   172: ldc 152
    //   174: invokestatic 158	com/tencent/luggage/a/e:C	(Ljava/lang/Class;)Lcom/tencent/luggage/a/d;
    //   177: checkcast 152	com/tencent/mm/plugin/appbrand/l/o
    //   180: aload_0
    //   181: getfield 56	com/tencent/mm/plugin/appbrand/l/a/b:hvw	Lcom/tencent/mm/plugin/appbrand/jsapi/c;
    //   184: invokeinterface 164 1 0
    //   189: aload_0
    //   190: getfield 166	com/tencent/mm/plugin/appbrand/l/a/b:ioR	Ljava/lang/String;
    //   193: ldc 168
    //   195: aload_0
    //   196: getfield 58	com/tencent/mm/plugin/appbrand/l/a/b:uri	Ljava/lang/String;
    //   199: lconst_0
    //   200: lconst_0
    //   201: iconst_0
    //   202: iconst_2
    //   203: aload_0
    //   204: invokespecial 170	com/tencent/mm/plugin/appbrand/l/a/b:aID	()I
    //   207: invokeinterface 174 12 0
    //   212: ldc 116
    //   214: invokestatic 75	com/tencent/matrix/trace/core/AppMethodBeat:o	(I)V
    //   217: goto -168 -> 49
    //   220: aload_0
    //   221: invokestatic 68	java/lang/System:currentTimeMillis	()J
    //   224: putfield 176	com/tencent/mm/plugin/appbrand/l/a/b:ipE	J
    //   227: aconst_null
    //   228: astore 12
    //   230: aconst_null
    //   231: astore 13
    //   233: aconst_null
    //   234: astore 14
    //   236: aconst_null
    //   237: astore 15
    //   239: aconst_null
    //   240: astore 16
    //   242: aconst_null
    //   243: astore 17
    //   245: aconst_null
    //   246: astore 18
    //   248: aconst_null
    //   249: astore 19
    //   251: aconst_null
    //   252: astore 20
    //   254: aconst_null
    //   255: astore 21
    //   257: aload_0
    //   258: getfield 62	com/tencent/mm/plugin/appbrand/l/a/b:ipB	Lcom/tencent/mm/plugin/appbrand/l/a/a;
    //   261: aload_0
    //   262: getfield 60	com/tencent/mm/plugin/appbrand/l/a/b:filename	Ljava/lang/String;
    //   265: aload_0
    //   266: getfield 58	com/tencent/mm/plugin/appbrand/l/a/b:uri	Ljava/lang/String;
    //   269: invokeinterface 180 3 0
    //   274: iload 11
    //   276: istore 22
    //   278: iload 6
    //   280: istore 23
    //   282: iload 7
    //   284: istore 24
    //   286: iload 8
    //   288: istore 25
    //   290: iload 9
    //   292: istore 26
    //   294: iload 10
    //   296: istore 27
    //   298: ldc 182
    //   300: invokestatic 158	com/tencent/luggage/a/e:C	(Ljava/lang/Class;)Lcom/tencent/luggage/a/d;
    //   303: checkcast 182	com/tencent/mm/plugin/appbrand/n/a
    //   306: ldc2_w 183
    //   309: lconst_0
    //   310: lconst_1
    //   311: invokeinterface 188 7 0
    //   316: iload 11
    //   318: istore 22
    //   320: iload 6
    //   322: istore 23
    //   324: iload 7
    //   326: istore 24
    //   328: iload 8
    //   330: istore 25
    //   332: iload 9
    //   334: istore 26
    //   336: iload 10
    //   338: istore 27
    //   340: new 190	java/net/URL
    //   343: astore 28
    //   345: iload 11
    //   347: istore 22
    //   349: iload 6
    //   351: istore 23
    //   353: iload 7
    //   355: istore 24
    //   357: iload 8
    //   359: istore 25
    //   361: iload 9
    //   363: istore 26
    //   365: iload 10
    //   367: istore 27
    //   369: aload 28
    //   371: aload_0
    //   372: getfield 58	com/tencent/mm/plugin/appbrand/l/a/b:uri	Ljava/lang/String;
    //   375: invokespecial 193	java/net/URL:<init>	(Ljava/lang/String;)V
    //   378: iload 11
    //   380: istore 22
    //   382: iload 6
    //   384: istore 23
    //   386: iload 7
    //   388: istore 24
    //   390: iload 8
    //   392: istore 25
    //   394: iload 9
    //   396: istore 26
    //   398: iload 10
    //   400: istore 27
    //   402: ldc 92
    //   404: ldc 195
    //   406: iconst_2
    //   407: anewarray 4	java/lang/Object
    //   410: dup
    //   411: iconst_0
    //   412: aload_0
    //   413: getfield 58	com/tencent/mm/plugin/appbrand/l/a/b:uri	Ljava/lang/String;
    //   416: aastore
    //   417: dup
    //   418: iconst_1
    //   419: aload_0
    //   420: getfield 60	com/tencent/mm/plugin/appbrand/l/a/b:filename	Ljava/lang/String;
    //   423: aastore
    //   424: invokestatic 148	com/tencent/mm/sdk/platformtools/ab:i	(Ljava/lang/String;Ljava/lang/String;[Ljava/lang/Object;)V
    //   427: iload 11
    //   429: istore 22
    //   431: iload 6
    //   433: istore 23
    //   435: iload 7
    //   437: istore 24
    //   439: iload 8
    //   441: istore 25
    //   443: iload 9
    //   445: istore 26
    //   447: iload 10
    //   449: istore 27
    //   451: aload_0
    //   452: aload 28
    //   454: invokevirtual 199	java/net/URL:openConnection	()Ljava/net/URLConnection;
    //   457: checkcast 87	java/net/HttpURLConnection
    //   460: putfield 85	com/tencent/mm/plugin/appbrand/l/a/b:ipF	Ljava/net/HttpURLConnection;
    //   463: iload 11
    //   465: istore 22
    //   467: iload 6
    //   469: istore 23
    //   471: iload 7
    //   473: istore 24
    //   475: iload 8
    //   477: istore 25
    //   479: iload 9
    //   481: istore 26
    //   483: iload 10
    //   485: istore 27
    //   487: aload_0
    //   488: getfield 85	com/tencent/mm/plugin/appbrand/l/a/b:ipF	Ljava/net/HttpURLConnection;
    //   491: instanceof 201
    //   494: ifeq +110 -> 604
    //   497: iload 11
    //   499: istore 22
    //   501: iload 6
    //   503: istore 23
    //   505: iload 7
    //   507: istore 24
    //   509: iload 8
    //   511: istore 25
    //   513: iload 9
    //   515: istore 26
    //   517: iload 10
    //   519: istore 27
    //   521: aload_0
    //   522: getfield 203	com/tencent/mm/plugin/appbrand/l/a/b:ios	Ljavax/net/ssl/SSLContext;
    //   525: ifnull +79 -> 604
    //   528: iload 11
    //   530: istore 22
    //   532: iload 6
    //   534: istore 23
    //   536: iload 7
    //   538: istore 24
    //   540: iload 8
    //   542: istore 25
    //   544: iload 9
    //   546: istore 26
    //   548: iload 10
    //   550: istore 27
    //   552: aload_0
    //   553: getfield 85	com/tencent/mm/plugin/appbrand/l/a/b:ipF	Ljava/net/HttpURLConnection;
    //   556: checkcast 201	javax/net/ssl/HttpsURLConnection
    //   559: aload_0
    //   560: getfield 203	com/tencent/mm/plugin/appbrand/l/a/b:ios	Ljavax/net/ssl/SSLContext;
    //   563: invokevirtual 209	javax/net/ssl/SSLContext:getSocketFactory	()Ljavax/net/ssl/SSLSocketFactory;
    //   566: invokevirtual 213	javax/net/ssl/HttpsURLConnection:setSSLSocketFactory	(Ljavax/net/ssl/SSLSocketFactory;)V
    //   569: iload 11
    //   571: istore 22
    //   573: iload 6
    //   575: istore 23
    //   577: iload 7
    //   579: istore 24
    //   581: iload 8
    //   583: istore 25
    //   585: iload 9
    //   587: istore 26
    //   589: iload 10
    //   591: istore 27
    //   593: aload_0
    //   594: getfield 85	com/tencent/mm/plugin/appbrand/l/a/b:ipF	Ljava/net/HttpURLConnection;
    //   597: aload_0
    //   598: getfield 135	com/tencent/mm/plugin/appbrand/l/a/b:ioN	Ljava/util/ArrayList;
    //   601: invokestatic 216	com/tencent/mm/plugin/appbrand/l/j:a	(Ljava/net/HttpURLConnection;Ljava/util/ArrayList;)V
    //   604: iload 11
    //   606: istore 22
    //   608: iload 6
    //   610: istore 23
    //   612: iload 7
    //   614: istore 24
    //   616: iload 8
    //   618: istore 25
    //   620: iload 9
    //   622: istore 26
    //   624: iload 10
    //   626: istore 27
    //   628: aload_0
    //   629: getfield 85	com/tencent/mm/plugin/appbrand/l/a/b:ipF	Ljava/net/HttpURLConnection;
    //   632: iconst_1
    //   633: invokevirtual 220	java/net/HttpURLConnection:setDoInput	(Z)V
    //   636: iload 11
    //   638: istore 22
    //   640: iload 6
    //   642: istore 23
    //   644: iload 7
    //   646: istore 24
    //   648: iload 8
    //   650: istore 25
    //   652: iload 9
    //   654: istore 26
    //   656: iload 10
    //   658: istore 27
    //   660: aload_0
    //   661: getfield 85	com/tencent/mm/plugin/appbrand/l/a/b:ipF	Ljava/net/HttpURLConnection;
    //   664: aload_0
    //   665: getfield 54	com/tencent/mm/plugin/appbrand/l/a/b:azs	I
    //   668: invokevirtual 223	java/net/HttpURLConnection:setConnectTimeout	(I)V
    //   671: iload 11
    //   673: istore 22
    //   675: iload 6
    //   677: istore 23
    //   679: iload 7
    //   681: istore 24
    //   683: iload 8
    //   685: istore 25
    //   687: iload 9
    //   689: istore 26
    //   691: iload 10
    //   693: istore 27
    //   695: aload_0
    //   696: getfield 85	com/tencent/mm/plugin/appbrand/l/a/b:ipF	Ljava/net/HttpURLConnection;
    //   699: aload_0
    //   700: getfield 54	com/tencent/mm/plugin/appbrand/l/a/b:azs	I
    //   703: invokevirtual 226	java/net/HttpURLConnection:setReadTimeout	(I)V
    //   706: iload 11
    //   708: istore 22
    //   710: iload 6
    //   712: istore 23
    //   714: iload 7
    //   716: istore 24
    //   718: iload 8
    //   720: istore 25
    //   722: iload 9
    //   724: istore 26
    //   726: iload 10
    //   728: istore 27
    //   730: aload_0
    //   731: getfield 85	com/tencent/mm/plugin/appbrand/l/a/b:ipF	Ljava/net/HttpURLConnection;
    //   734: iconst_0
    //   735: invokevirtual 229	java/net/HttpURLConnection:setInstanceFollowRedirects	(Z)V
    //   738: iload 11
    //   740: istore 22
    //   742: iload 6
    //   744: istore 23
    //   746: iload 7
    //   748: istore 24
    //   750: iload 8
    //   752: istore 25
    //   754: iload 9
    //   756: istore 26
    //   758: iload 10
    //   760: istore 27
    //   762: aload_0
    //   763: getfield 85	com/tencent/mm/plugin/appbrand/l/a/b:ipF	Ljava/net/HttpURLConnection;
    //   766: ldc 231
    //   768: ldc 233
    //   770: invokevirtual 236	java/net/HttpURLConnection:setRequestProperty	(Ljava/lang/String;Ljava/lang/String;)V
    //   773: iload 11
    //   775: istore 22
    //   777: iload 6
    //   779: istore 23
    //   781: iload 7
    //   783: istore 24
    //   785: iload 8
    //   787: istore 25
    //   789: iload 9
    //   791: istore 26
    //   793: iload 10
    //   795: istore 27
    //   797: aload_0
    //   798: getfield 238	com/tencent/mm/plugin/appbrand/l/a/b:ipC	Ljava/util/Map;
    //   801: ifnull +493 -> 1294
    //   804: iload 11
    //   806: istore 22
    //   808: iload 6
    //   810: istore 23
    //   812: iload 7
    //   814: istore 24
    //   816: iload 8
    //   818: istore 25
    //   820: iload 9
    //   822: istore 26
    //   824: iload 10
    //   826: istore 27
    //   828: ldc 92
    //   830: ldc 240
    //   832: iconst_1
    //   833: anewarray 4	java/lang/Object
    //   836: dup
    //   837: iconst_0
    //   838: aload 28
    //   840: aastore
    //   841: invokestatic 148	com/tencent/mm/sdk/platformtools/ab:i	(Ljava/lang/String;Ljava/lang/String;[Ljava/lang/Object;)V
    //   844: iload 11
    //   846: istore 22
    //   848: iload 6
    //   850: istore 23
    //   852: iload 7
    //   854: istore 24
    //   856: iload 8
    //   858: istore 25
    //   860: iload 9
    //   862: istore 26
    //   864: iload 10
    //   866: istore 27
    //   868: aload_0
    //   869: getfield 238	com/tencent/mm/plugin/appbrand/l/a/b:ipC	Ljava/util/Map;
    //   872: invokeinterface 246 1 0
    //   877: invokeinterface 252 1 0
    //   882: astore 29
    //   884: iload 11
    //   886: istore 22
    //   888: iload 6
    //   890: istore 23
    //   892: iload 7
    //   894: istore 24
    //   896: iload 8
    //   898: istore 25
    //   900: iload 9
    //   902: istore 26
    //   904: iload 10
    //   906: istore 27
    //   908: aload 29
    //   910: invokeinterface 258 1 0
    //   915: ifeq +379 -> 1294
    //   918: iload 11
    //   920: istore 22
    //   922: iload 6
    //   924: istore 23
    //   926: iload 7
    //   928: istore 24
    //   930: iload 8
    //   932: istore 25
    //   934: iload 9
    //   936: istore 26
    //   938: iload 10
    //   940: istore 27
    //   942: aload 29
    //   944: invokeinterface 262 1 0
    //   949: checkcast 264	java/util/Map$Entry
    //   952: astore 30
    //   954: iload 11
    //   956: istore 22
    //   958: iload 6
    //   960: istore 23
    //   962: iload 7
    //   964: istore 24
    //   966: iload 8
    //   968: istore 25
    //   970: iload 9
    //   972: istore 26
    //   974: iload 10
    //   976: istore 27
    //   978: aload_0
    //   979: getfield 85	com/tencent/mm/plugin/appbrand/l/a/b:ipF	Ljava/net/HttpURLConnection;
    //   982: aload 30
    //   984: invokeinterface 267 1 0
    //   989: checkcast 269	java/lang/String
    //   992: aload 30
    //   994: invokeinterface 272 1 0
    //   999: checkcast 269	java/lang/String
    //   1002: invokevirtual 236	java/net/HttpURLConnection:setRequestProperty	(Ljava/lang/String;Ljava/lang/String;)V
    //   1005: iload 11
    //   1007: istore 22
    //   1009: iload 6
    //   1011: istore 23
    //   1013: iload 7
    //   1015: istore 24
    //   1017: iload 8
    //   1019: istore 25
    //   1021: iload 9
    //   1023: istore 26
    //   1025: iload 10
    //   1027: istore 27
    //   1029: ldc 92
    //   1031: ldc_w 274
    //   1034: iconst_3
    //   1035: anewarray 4	java/lang/Object
    //   1038: dup
    //   1039: iconst_0
    //   1040: aload_0
    //   1041: getfield 60	com/tencent/mm/plugin/appbrand/l/a/b:filename	Ljava/lang/String;
    //   1044: aastore
    //   1045: dup
    //   1046: iconst_1
    //   1047: aload 30
    //   1049: invokeinterface 267 1 0
    //   1054: aastore
    //   1055: dup
    //   1056: iconst_2
    //   1057: aload 30
    //   1059: invokeinterface 272 1 0
    //   1064: aastore
    //   1065: invokestatic 148	com/tencent/mm/sdk/platformtools/ab:i	(Ljava/lang/String;Ljava/lang/String;[Ljava/lang/Object;)V
    //   1068: goto -184 -> 884
    //   1071: astore 28
    //   1073: aconst_null
    //   1074: astore 16
    //   1076: aconst_null
    //   1077: astore 15
    //   1079: lconst_0
    //   1080: lstore 31
    //   1082: iload 22
    //   1084: istore 11
    //   1086: iconst_0
    //   1087: istore 6
    //   1089: ldc 182
    //   1091: invokestatic 158	com/tencent/luggage/a/e:C	(Ljava/lang/Class;)Lcom/tencent/luggage/a/d;
    //   1094: checkcast 182	com/tencent/mm/plugin/appbrand/n/a
    //   1097: ldc2_w 183
    //   1100: lconst_1
    //   1101: lconst_1
    //   1102: invokeinterface 188 7 0
    //   1107: ldc 92
    //   1109: aload 28
    //   1111: ldc_w 276
    //   1114: iconst_2
    //   1115: anewarray 4	java/lang/Object
    //   1118: dup
    //   1119: iconst_0
    //   1120: aload_0
    //   1121: getfield 58	com/tencent/mm/plugin/appbrand/l/a/b:uri	Ljava/lang/String;
    //   1124: aastore
    //   1125: dup
    //   1126: iconst_1
    //   1127: aload_0
    //   1128: getfield 60	com/tencent/mm/plugin/appbrand/l/a/b:filename	Ljava/lang/String;
    //   1131: aastore
    //   1132: invokestatic 100	com/tencent/mm/sdk/platformtools/ab:printErrStackTrace	(Ljava/lang/String;Ljava/lang/Throwable;Ljava/lang/String;[Ljava/lang/Object;)V
    //   1135: aload_0
    //   1136: getfield 62	com/tencent/mm/plugin/appbrand/l/a/b:ipB	Lcom/tencent/mm/plugin/appbrand/l/a/a;
    //   1139: aload_0
    //   1140: getfield 60	com/tencent/mm/plugin/appbrand/l/a/b:filename	Ljava/lang/String;
    //   1143: aload_0
    //   1144: getfield 58	com/tencent/mm/plugin/appbrand/l/a/b:uri	Ljava/lang/String;
    //   1147: ldc_w 278
    //   1150: invokeinterface 133 4 0
    //   1155: iload 6
    //   1157: ifeq +5969 -> 7126
    //   1160: ldc 152
    //   1162: invokestatic 158	com/tencent/luggage/a/e:C	(Ljava/lang/Class;)Lcom/tencent/luggage/a/d;
    //   1165: checkcast 152	com/tencent/mm/plugin/appbrand/l/o
    //   1168: aload_0
    //   1169: getfield 56	com/tencent/mm/plugin/appbrand/l/a/b:hvw	Lcom/tencent/mm/plugin/appbrand/jsapi/c;
    //   1172: invokeinterface 164 1 0
    //   1177: aload_0
    //   1178: getfield 166	com/tencent/mm/plugin/appbrand/l/a/b:ioR	Ljava/lang/String;
    //   1181: ldc 168
    //   1183: aload_0
    //   1184: getfield 58	com/tencent/mm/plugin/appbrand/l/a/b:uri	Ljava/lang/String;
    //   1187: lconst_0
    //   1188: lload 31
    //   1190: iload 11
    //   1192: iconst_1
    //   1193: aload_0
    //   1194: invokespecial 170	com/tencent/mm/plugin/appbrand/l/a/b:aID	()I
    //   1197: invokeinterface 174 12 0
    //   1202: ldc 182
    //   1204: invokestatic 158	com/tencent/luggage/a/e:C	(Ljava/lang/Class;)Lcom/tencent/luggage/a/d;
    //   1207: checkcast 182	com/tencent/mm/plugin/appbrand/n/a
    //   1210: ldc2_w 183
    //   1213: ldc2_w 279
    //   1216: lconst_1
    //   1217: invokeinterface 188 7 0
    //   1222: ldc 182
    //   1224: invokestatic 158	com/tencent/luggage/a/e:C	(Ljava/lang/Class;)Lcom/tencent/luggage/a/d;
    //   1227: checkcast 182	com/tencent/mm/plugin/appbrand/n/a
    //   1230: ldc2_w 183
    //   1233: ldc2_w 281
    //   1236: invokestatic 68	java/lang/System:currentTimeMillis	()J
    //   1239: aload_0
    //   1240: getfield 176	com/tencent/mm/plugin/appbrand/l/a/b:ipE	J
    //   1243: lsub
    //   1244: invokeinterface 188 7 0
    //   1249: aload 16
    //   1251: ifnull +8 -> 1259
    //   1254: aload 16
    //   1256: invokevirtual 287	java/io/FileOutputStream:close	()V
    //   1259: aload 15
    //   1261: ifnull +8 -> 1269
    //   1264: aload 15
    //   1266: invokevirtual 290	java/io/InputStream:close	()V
    //   1269: aload_0
    //   1270: invokevirtual 292	com/tencent/mm/plugin/appbrand/l/a/b:aIP	()V
    //   1273: aload_0
    //   1274: getfield 62	com/tencent/mm/plugin/appbrand/l/a/b:ipB	Lcom/tencent/mm/plugin/appbrand/l/a/a;
    //   1277: aload_0
    //   1278: getfield 294	com/tencent/mm/plugin/appbrand/l/a/b:hvr	Ljava/lang/String;
    //   1281: invokeinterface 297 2 0
    //   1286: ldc 116
    //   1288: invokestatic 75	com/tencent/matrix/trace/core/AppMethodBeat:o	(I)V
    //   1291: goto -1242 -> 49
    //   1294: iload 11
    //   1296: istore 22
    //   1298: iload 6
    //   1300: istore 23
    //   1302: iload 7
    //   1304: istore 24
    //   1306: iload 8
    //   1308: istore 25
    //   1310: iload 9
    //   1312: istore 26
    //   1314: iload 10
    //   1316: istore 27
    //   1318: aload_0
    //   1319: getfield 85	com/tencent/mm/plugin/appbrand/l/a/b:ipF	Ljava/net/HttpURLConnection;
    //   1322: ldc_w 299
    //   1325: aload_0
    //   1326: getfield 72	com/tencent/mm/plugin/appbrand/l/a/b:ibJ	Ljava/lang/String;
    //   1329: invokevirtual 236	java/net/HttpURLConnection:setRequestProperty	(Ljava/lang/String;Ljava/lang/String;)V
    //   1332: iload 11
    //   1334: istore 22
    //   1336: iload 6
    //   1338: istore 23
    //   1340: iload 7
    //   1342: istore 24
    //   1344: iload 8
    //   1346: istore 25
    //   1348: iload 9
    //   1350: istore 26
    //   1352: iload 10
    //   1354: istore 27
    //   1356: aload_0
    //   1357: getfield 85	com/tencent/mm/plugin/appbrand/l/a/b:ipF	Ljava/net/HttpURLConnection;
    //   1360: invokestatic 302	com/tencent/mm/plugin/appbrand/l/j:f	(Ljava/net/HttpURLConnection;)Lorg/json/JSONObject;
    //   1363: astore 30
    //   1365: iload 11
    //   1367: istore 22
    //   1369: iload 6
    //   1371: istore 23
    //   1373: iload 7
    //   1375: istore 24
    //   1377: iload 8
    //   1379: istore 25
    //   1381: iload 9
    //   1383: istore 26
    //   1385: iload 10
    //   1387: istore 27
    //   1389: aload_0
    //   1390: getfield 62	com/tencent/mm/plugin/appbrand/l/a/b:ipB	Lcom/tencent/mm/plugin/appbrand/l/a/a;
    //   1393: aload 30
    //   1395: invokeinterface 306 2 0
    //   1400: iload 11
    //   1402: istore 22
    //   1404: iload 6
    //   1406: istore 23
    //   1408: iload 7
    //   1410: istore 24
    //   1412: iload 8
    //   1414: istore 25
    //   1416: iload 9
    //   1418: istore 26
    //   1420: iload 10
    //   1422: istore 27
    //   1424: aload_0
    //   1425: getfield 85	com/tencent/mm/plugin/appbrand/l/a/b:ipF	Ljava/net/HttpURLConnection;
    //   1428: invokevirtual 309	java/net/HttpURLConnection:getContentLength	()I
    //   1431: i2l
    //   1432: lstore 33
    //   1434: iload 11
    //   1436: istore 22
    //   1438: iload 6
    //   1440: istore 23
    //   1442: iload 7
    //   1444: istore 24
    //   1446: iload 8
    //   1448: istore 25
    //   1450: iload 9
    //   1452: istore 26
    //   1454: iload 10
    //   1456: istore 27
    //   1458: aload_0
    //   1459: getfield 85	com/tencent/mm/plugin/appbrand/l/a/b:ipF	Ljava/net/HttpURLConnection;
    //   1462: ldc_w 311
    //   1465: invokevirtual 315	java/net/HttpURLConnection:getHeaderField	(Ljava/lang/String;)Ljava/lang/String;
    //   1468: astore 30
    //   1470: iload 11
    //   1472: istore 22
    //   1474: iload 6
    //   1476: istore 23
    //   1478: iload 7
    //   1480: istore 24
    //   1482: iload 8
    //   1484: istore 25
    //   1486: iload 9
    //   1488: istore 26
    //   1490: iload 10
    //   1492: istore 27
    //   1494: aload 28
    //   1496: invokevirtual 318	java/net/URL:toString	()Ljava/lang/String;
    //   1499: astore 28
    //   1501: iload 11
    //   1503: istore 22
    //   1505: iload 6
    //   1507: istore 23
    //   1509: iload 7
    //   1511: istore 24
    //   1513: iload 8
    //   1515: istore 25
    //   1517: iload 9
    //   1519: istore 26
    //   1521: iload 10
    //   1523: istore 27
    //   1525: aload 30
    //   1527: invokestatic 324	com/tencent/mm/sdk/f/b$a:anJ	(Ljava/lang/String;)Lcom/tencent/mm/sdk/f/b$a;
    //   1530: astore 30
    //   1532: aload 30
    //   1534: ifnonnull +738 -> 2272
    //   1537: iload 11
    //   1539: istore 22
    //   1541: iload 6
    //   1543: istore 23
    //   1545: iload 7
    //   1547: istore 24
    //   1549: iload 8
    //   1551: istore 25
    //   1553: iload 9
    //   1555: istore 26
    //   1557: iload 10
    //   1559: istore 27
    //   1561: aload 28
    //   1563: invokestatic 329	com/tencent/mm/sdk/f/b:ako	(Ljava/lang/String;)Ljava/lang/String;
    //   1566: astore 28
    //   1568: iload 11
    //   1570: istore 22
    //   1572: iload 6
    //   1574: istore 23
    //   1576: iload 7
    //   1578: istore 24
    //   1580: iload 8
    //   1582: istore 25
    //   1584: iload 9
    //   1586: istore 26
    //   1588: iload 10
    //   1590: istore 27
    //   1592: aload_0
    //   1593: getfield 85	com/tencent/mm/plugin/appbrand/l/a/b:ipF	Ljava/net/HttpURLConnection;
    //   1596: invokevirtual 332	java/net/HttpURLConnection:getResponseCode	()I
    //   1599: istore 11
    //   1601: lload 33
    //   1603: lconst_0
    //   1604: lcmp
    //   1605: ifle +48 -> 1653
    //   1608: iload 11
    //   1610: istore 22
    //   1612: iload 11
    //   1614: istore 23
    //   1616: iload 11
    //   1618: istore 24
    //   1620: iload 11
    //   1622: istore 25
    //   1624: iload 11
    //   1626: istore 26
    //   1628: iload 11
    //   1630: istore 27
    //   1632: ldc 182
    //   1634: invokestatic 158	com/tencent/luggage/a/e:C	(Ljava/lang/Class;)Lcom/tencent/luggage/a/d;
    //   1637: checkcast 182	com/tencent/mm/plugin/appbrand/n/a
    //   1640: ldc2_w 183
    //   1643: ldc2_w 333
    //   1646: lload 33
    //   1648: invokeinterface 188 7 0
    //   1653: iload 11
    //   1655: istore 22
    //   1657: iload 11
    //   1659: istore 23
    //   1661: iload 11
    //   1663: istore 24
    //   1665: iload 11
    //   1667: istore 25
    //   1669: iload 11
    //   1671: istore 26
    //   1673: iload 11
    //   1675: istore 27
    //   1677: aload_0
    //   1678: getfield 85	com/tencent/mm/plugin/appbrand/l/a/b:ipF	Ljava/net/HttpURLConnection;
    //   1681: invokestatic 337	com/tencent/mm/plugin/appbrand/l/j:e	(Ljava/net/HttpURLConnection;)Lorg/json/JSONObject;
    //   1684: astore 30
    //   1686: bipush 28
    //   1688: istore 6
    //   1690: iload 11
    //   1692: bipush 100
    //   1694: if_icmplt +716 -> 2410
    //   1697: iload 11
    //   1699: sipush 200
    //   1702: if_icmpge +708 -> 2410
    //   1705: bipush 20
    //   1707: istore 6
    //   1709: iload 11
    //   1711: istore 22
    //   1713: iload 11
    //   1715: istore 23
    //   1717: iload 11
    //   1719: istore 24
    //   1721: iload 11
    //   1723: istore 25
    //   1725: iload 11
    //   1727: istore 26
    //   1729: iload 11
    //   1731: istore 27
    //   1733: ldc 182
    //   1735: invokestatic 158	com/tencent/luggage/a/e:C	(Ljava/lang/Class;)Lcom/tencent/luggage/a/d;
    //   1738: checkcast 182	com/tencent/mm/plugin/appbrand/n/a
    //   1741: ldc2_w 183
    //   1744: iload 6
    //   1746: i2l
    //   1747: lconst_1
    //   1748: invokeinterface 188 7 0
    //   1753: iload 11
    //   1755: istore 22
    //   1757: iload 11
    //   1759: istore 23
    //   1761: iload 11
    //   1763: istore 24
    //   1765: iload 11
    //   1767: istore 25
    //   1769: iload 11
    //   1771: istore 26
    //   1773: iload 11
    //   1775: istore 27
    //   1777: ldc 92
    //   1779: ldc_w 339
    //   1782: iconst_2
    //   1783: anewarray 4	java/lang/Object
    //   1786: dup
    //   1787: iconst_0
    //   1788: iload 11
    //   1790: invokestatic 345	java/lang/Integer:valueOf	(I)Ljava/lang/Integer;
    //   1793: aastore
    //   1794: dup
    //   1795: iconst_1
    //   1796: iload 6
    //   1798: invokestatic 345	java/lang/Integer:valueOf	(I)Ljava/lang/Integer;
    //   1801: aastore
    //   1802: invokestatic 148	com/tencent/mm/sdk/platformtools/ab:i	(Ljava/lang/String;Ljava/lang/String;[Ljava/lang/Object;)V
    //   1805: iload 11
    //   1807: istore 22
    //   1809: iload 11
    //   1811: istore 23
    //   1813: iload 11
    //   1815: istore 24
    //   1817: iload 11
    //   1819: istore 25
    //   1821: iload 11
    //   1823: istore 26
    //   1825: iload 11
    //   1827: istore 27
    //   1829: aload_0
    //   1830: getfield 62	com/tencent/mm/plugin/appbrand/l/a/b:ipB	Lcom/tencent/mm/plugin/appbrand/l/a/a;
    //   1833: aload 30
    //   1835: invokeinterface 306 2 0
    //   1840: iload 11
    //   1842: sipush 200
    //   1845: if_icmpeq +977 -> 2822
    //   1848: iload 11
    //   1850: istore 22
    //   1852: iload 11
    //   1854: istore 23
    //   1856: iload 11
    //   1858: istore 24
    //   1860: iload 11
    //   1862: istore 25
    //   1864: iload 11
    //   1866: istore 26
    //   1868: iload 11
    //   1870: istore 27
    //   1872: ldc 92
    //   1874: ldc_w 347
    //   1877: iconst_3
    //   1878: anewarray 4	java/lang/Object
    //   1881: dup
    //   1882: iconst_0
    //   1883: iload 11
    //   1885: invokestatic 345	java/lang/Integer:valueOf	(I)Ljava/lang/Integer;
    //   1888: aastore
    //   1889: dup
    //   1890: iconst_1
    //   1891: aload_0
    //   1892: getfield 58	com/tencent/mm/plugin/appbrand/l/a/b:uri	Ljava/lang/String;
    //   1895: aastore
    //   1896: dup
    //   1897: iconst_2
    //   1898: aload_0
    //   1899: getfield 60	com/tencent/mm/plugin/appbrand/l/a/b:filename	Ljava/lang/String;
    //   1902: aastore
    //   1903: invokestatic 349	com/tencent/mm/sdk/platformtools/ab:e	(Ljava/lang/String;Ljava/lang/String;[Ljava/lang/Object;)V
    //   1906: iload 11
    //   1908: istore 22
    //   1910: iload 11
    //   1912: istore 23
    //   1914: iload 11
    //   1916: istore 24
    //   1918: iload 11
    //   1920: istore 25
    //   1922: iload 11
    //   1924: istore 26
    //   1926: iload 11
    //   1928: istore 27
    //   1930: iload 11
    //   1932: invokestatic 353	com/tencent/mm/plugin/appbrand/l/j:po	(I)Z
    //   1935: ifeq +887 -> 2822
    //   1938: iload 11
    //   1940: istore 22
    //   1942: iload 11
    //   1944: istore 23
    //   1946: iload 11
    //   1948: istore 24
    //   1950: iload 11
    //   1952: istore 25
    //   1954: iload 11
    //   1956: istore 26
    //   1958: iload 11
    //   1960: istore 27
    //   1962: aload_0
    //   1963: getfield 85	com/tencent/mm/plugin/appbrand/l/a/b:ipF	Ljava/net/HttpURLConnection;
    //   1966: invokestatic 356	com/tencent/mm/plugin/appbrand/l/j:c	(Ljava/net/HttpURLConnection;)Ljava/lang/String;
    //   1969: astore 30
    //   1971: iload 11
    //   1973: istore 22
    //   1975: iload 11
    //   1977: istore 23
    //   1979: iload 11
    //   1981: istore 24
    //   1983: iload 11
    //   1985: istore 25
    //   1987: iload 11
    //   1989: istore 26
    //   1991: iload 11
    //   1993: istore 27
    //   1995: aload 30
    //   1997: invokestatic 362	android/text/TextUtils:isEmpty	(Ljava/lang/CharSequence;)Z
    //   2000: ifne +822 -> 2822
    //   2003: iload 11
    //   2005: istore 22
    //   2007: iload 11
    //   2009: istore 23
    //   2011: iload 11
    //   2013: istore 24
    //   2015: iload 11
    //   2017: istore 25
    //   2019: iload 11
    //   2021: istore 26
    //   2023: iload 11
    //   2025: istore 27
    //   2027: aload_0
    //   2028: getfield 49	com/tencent/mm/plugin/appbrand/l/a/b:ioO	I
    //   2031: istore 6
    //   2033: iload 11
    //   2035: istore 22
    //   2037: iload 11
    //   2039: istore 23
    //   2041: iload 11
    //   2043: istore 24
    //   2045: iload 11
    //   2047: istore 25
    //   2049: iload 11
    //   2051: istore 26
    //   2053: iload 11
    //   2055: istore 27
    //   2057: aload_0
    //   2058: iload 6
    //   2060: iconst_1
    //   2061: isub
    //   2062: putfield 49	com/tencent/mm/plugin/appbrand/l/a/b:ioO	I
    //   2065: iload 6
    //   2067: ifgt +472 -> 2539
    //   2070: iload 11
    //   2072: istore 22
    //   2074: iload 11
    //   2076: istore 23
    //   2078: iload 11
    //   2080: istore 24
    //   2082: iload 11
    //   2084: istore 25
    //   2086: iload 11
    //   2088: istore 26
    //   2090: iload 11
    //   2092: istore 27
    //   2094: ldc 92
    //   2096: ldc_w 364
    //   2099: iconst_1
    //   2100: anewarray 4	java/lang/Object
    //   2103: dup
    //   2104: iconst_0
    //   2105: bipush 15
    //   2107: invokestatic 345	java/lang/Integer:valueOf	(I)Ljava/lang/Integer;
    //   2110: aastore
    //   2111: invokestatic 367	com/tencent/mm/sdk/platformtools/ab:w	(Ljava/lang/String;Ljava/lang/String;[Ljava/lang/Object;)V
    //   2114: iload 11
    //   2116: istore 22
    //   2118: iload 11
    //   2120: istore 23
    //   2122: iload 11
    //   2124: istore 24
    //   2126: iload 11
    //   2128: istore 25
    //   2130: iload 11
    //   2132: istore 26
    //   2134: iload 11
    //   2136: istore 27
    //   2138: aload_0
    //   2139: getfield 62	com/tencent/mm/plugin/appbrand/l/a/b:ipB	Lcom/tencent/mm/plugin/appbrand/l/a/a;
    //   2142: aload_0
    //   2143: getfield 60	com/tencent/mm/plugin/appbrand/l/a/b:filename	Ljava/lang/String;
    //   2146: aload 28
    //   2148: aload_0
    //   2149: getfield 58	com/tencent/mm/plugin/appbrand/l/a/b:uri	Ljava/lang/String;
    //   2152: iload 11
    //   2154: invokeinterface 370 5 0
    //   2159: ldc 152
    //   2161: invokestatic 158	com/tencent/luggage/a/e:C	(Ljava/lang/Class;)Lcom/tencent/luggage/a/d;
    //   2164: checkcast 152	com/tencent/mm/plugin/appbrand/l/o
    //   2167: aload_0
    //   2168: getfield 56	com/tencent/mm/plugin/appbrand/l/a/b:hvw	Lcom/tencent/mm/plugin/appbrand/jsapi/c;
    //   2171: invokeinterface 164 1 0
    //   2176: aload_0
    //   2177: getfield 166	com/tencent/mm/plugin/appbrand/l/a/b:ioR	Ljava/lang/String;
    //   2180: ldc 168
    //   2182: aload_0
    //   2183: getfield 58	com/tencent/mm/plugin/appbrand/l/a/b:uri	Ljava/lang/String;
    //   2186: lconst_0
    //   2187: lconst_0
    //   2188: iload 11
    //   2190: iconst_1
    //   2191: aload_0
    //   2192: invokespecial 170	com/tencent/mm/plugin/appbrand/l/a/b:aID	()I
    //   2195: invokeinterface 174 12 0
    //   2200: ldc 182
    //   2202: invokestatic 158	com/tencent/luggage/a/e:C	(Ljava/lang/Class;)Lcom/tencent/luggage/a/d;
    //   2205: checkcast 182	com/tencent/mm/plugin/appbrand/n/a
    //   2208: ldc2_w 183
    //   2211: ldc2_w 279
    //   2214: lconst_1
    //   2215: invokeinterface 188 7 0
    //   2220: ldc 182
    //   2222: invokestatic 158	com/tencent/luggage/a/e:C	(Ljava/lang/Class;)Lcom/tencent/luggage/a/d;
    //   2225: checkcast 182	com/tencent/mm/plugin/appbrand/n/a
    //   2228: ldc2_w 183
    //   2231: ldc2_w 281
    //   2234: invokestatic 68	java/lang/System:currentTimeMillis	()J
    //   2237: aload_0
    //   2238: getfield 176	com/tencent/mm/plugin/appbrand/l/a/b:ipE	J
    //   2241: lsub
    //   2242: invokeinterface 188 7 0
    //   2247: aload_0
    //   2248: invokevirtual 292	com/tencent/mm/plugin/appbrand/l/a/b:aIP	()V
    //   2251: aload_0
    //   2252: getfield 62	com/tencent/mm/plugin/appbrand/l/a/b:ipB	Lcom/tencent/mm/plugin/appbrand/l/a/a;
    //   2255: aload_0
    //   2256: getfield 294	com/tencent/mm/plugin/appbrand/l/a/b:hvr	Ljava/lang/String;
    //   2259: invokeinterface 297 2 0
    //   2264: ldc 116
    //   2266: invokestatic 75	com/tencent/matrix/trace/core/AppMethodBeat:o	(I)V
    //   2269: goto -2220 -> 49
    //   2272: iload 11
    //   2274: istore 22
    //   2276: iload 6
    //   2278: istore 23
    //   2280: iload 7
    //   2282: istore 24
    //   2284: iload 8
    //   2286: istore 25
    //   2288: iload 9
    //   2290: istore 26
    //   2292: iload 10
    //   2294: istore 27
    //   2296: aload 30
    //   2298: getfield 373	com/tencent/mm/sdk/f/b$a:mimeType	Ljava/lang/String;
    //   2301: ldc_w 375
    //   2304: invokevirtual 378	java/lang/String:contains	(Ljava/lang/CharSequence;)Z
    //   2307: ifeq +69 -> 2376
    //   2310: iload 11
    //   2312: istore 22
    //   2314: iload 6
    //   2316: istore 23
    //   2318: iload 7
    //   2320: istore 24
    //   2322: iload 8
    //   2324: istore 25
    //   2326: iload 9
    //   2328: istore 26
    //   2330: iload 10
    //   2332: istore 27
    //   2334: aload 28
    //   2336: invokestatic 329	com/tencent/mm/sdk/f/b:ako	(Ljava/lang/String;)Ljava/lang/String;
    //   2339: astore 28
    //   2341: iload 11
    //   2343: istore 22
    //   2345: iload 6
    //   2347: istore 23
    //   2349: iload 7
    //   2351: istore 24
    //   2353: iload 8
    //   2355: istore 25
    //   2357: iload 9
    //   2359: istore 26
    //   2361: iload 10
    //   2363: istore 27
    //   2365: aload 28
    //   2367: invokestatic 383	com/tencent/mm/sdk/platformtools/bo:isNullOrNil	(Ljava/lang/String;)Z
    //   2370: ifne +6 -> 2376
    //   2373: goto -805 -> 1568
    //   2376: iload 11
    //   2378: istore 22
    //   2380: iload 6
    //   2382: istore 23
    //   2384: iload 7
    //   2386: istore 24
    //   2388: iload 8
    //   2390: istore 25
    //   2392: iload 9
    //   2394: istore 26
    //   2396: iload 10
    //   2398: istore 27
    //   2400: aload 30
    //   2402: getfield 373	com/tencent/mm/sdk/f/b$a:mimeType	Ljava/lang/String;
    //   2405: astore 28
    //   2407: goto -839 -> 1568
    //   2410: sipush 200
    //   2413: iload 11
    //   2415: if_icmpne +10 -> 2425
    //   2418: bipush 21
    //   2420: istore 6
    //   2422: goto -713 -> 1709
    //   2425: iload 11
    //   2427: sipush 200
    //   2430: if_icmple +18 -> 2448
    //   2433: iload 11
    //   2435: sipush 300
    //   2438: if_icmpge +10 -> 2448
    //   2441: bipush 22
    //   2443: istore 6
    //   2445: goto -736 -> 1709
    //   2448: sipush 302
    //   2451: iload 11
    //   2453: if_icmpne +10 -> 2463
    //   2456: bipush 23
    //   2458: istore 6
    //   2460: goto -751 -> 1709
    //   2463: iload 11
    //   2465: sipush 300
    //   2468: if_icmplt +18 -> 2486
    //   2471: iload 11
    //   2473: sipush 400
    //   2476: if_icmpge +10 -> 2486
    //   2479: bipush 24
    //   2481: istore 6
    //   2483: goto -774 -> 1709
    //   2486: sipush 404
    //   2489: iload 11
    //   2491: if_icmpne +10 -> 2501
    //   2494: bipush 25
    //   2496: istore 6
    //   2498: goto -789 -> 1709
    //   2501: iload 11
    //   2503: sipush 400
    //   2506: if_icmplt +18 -> 2524
    //   2509: iload 11
    //   2511: sipush 500
    //   2514: if_icmpge +10 -> 2524
    //   2517: bipush 26
    //   2519: istore 6
    //   2521: goto -812 -> 1709
    //   2524: iload 11
    //   2526: sipush 500
    //   2529: if_icmplt -820 -> 1709
    //   2532: bipush 27
    //   2534: istore 6
    //   2536: goto -827 -> 1709
    //   2539: iload 11
    //   2541: istore 22
    //   2543: iload 11
    //   2545: istore 23
    //   2547: iload 11
    //   2549: istore 24
    //   2551: iload 11
    //   2553: istore 25
    //   2555: iload 11
    //   2557: istore 26
    //   2559: iload 11
    //   2561: istore 27
    //   2563: ldc 92
    //   2565: ldc_w 385
    //   2568: iconst_3
    //   2569: anewarray 4	java/lang/Object
    //   2572: dup
    //   2573: iconst_0
    //   2574: aload_0
    //   2575: getfield 49	com/tencent/mm/plugin/appbrand/l/a/b:ioO	I
    //   2578: invokestatic 345	java/lang/Integer:valueOf	(I)Ljava/lang/Integer;
    //   2581: aastore
    //   2582: dup
    //   2583: iconst_1
    //   2584: aload_0
    //   2585: getfield 58	com/tencent/mm/plugin/appbrand/l/a/b:uri	Ljava/lang/String;
    //   2588: aastore
    //   2589: dup
    //   2590: iconst_2
    //   2591: aload 30
    //   2593: aastore
    //   2594: invokestatic 148	com/tencent/mm/sdk/platformtools/ab:i	(Ljava/lang/String;Ljava/lang/String;[Ljava/lang/Object;)V
    //   2597: iload 11
    //   2599: istore 22
    //   2601: iload 11
    //   2603: istore 23
    //   2605: iload 11
    //   2607: istore 24
    //   2609: iload 11
    //   2611: istore 25
    //   2613: iload 11
    //   2615: istore 26
    //   2617: iload 11
    //   2619: istore 27
    //   2621: aload_0
    //   2622: aload 30
    //   2624: putfield 58	com/tencent/mm/plugin/appbrand/l/a/b:uri	Ljava/lang/String;
    //   2627: iload 11
    //   2629: istore 22
    //   2631: iload 11
    //   2633: istore 23
    //   2635: iload 11
    //   2637: istore 24
    //   2639: iload 11
    //   2641: istore 25
    //   2643: iload 11
    //   2645: istore 26
    //   2647: iload 11
    //   2649: istore 27
    //   2651: aload_0
    //   2652: invokevirtual 387	com/tencent/mm/plugin/appbrand/l/a/b:run	()V
    //   2655: ldc 152
    //   2657: invokestatic 158	com/tencent/luggage/a/e:C	(Ljava/lang/Class;)Lcom/tencent/luggage/a/d;
    //   2660: checkcast 152	com/tencent/mm/plugin/appbrand/l/o
    //   2663: aload_0
    //   2664: getfield 56	com/tencent/mm/plugin/appbrand/l/a/b:hvw	Lcom/tencent/mm/plugin/appbrand/jsapi/c;
    //   2667: invokeinterface 164 1 0
    //   2672: aload_0
    //   2673: getfield 166	com/tencent/mm/plugin/appbrand/l/a/b:ioR	Ljava/lang/String;
    //   2676: ldc 168
    //   2678: aload_0
    //   2679: getfield 58	com/tencent/mm/plugin/appbrand/l/a/b:uri	Ljava/lang/String;
    //   2682: lconst_0
    //   2683: lconst_0
    //   2684: iload 11
    //   2686: iconst_2
    //   2687: aload_0
    //   2688: invokespecial 170	com/tencent/mm/plugin/appbrand/l/a/b:aID	()I
    //   2691: invokeinterface 174 12 0
    //   2696: ldc 182
    //   2698: invokestatic 158	com/tencent/luggage/a/e:C	(Ljava/lang/Class;)Lcom/tencent/luggage/a/d;
    //   2701: checkcast 182	com/tencent/mm/plugin/appbrand/n/a
    //   2704: ldc2_w 183
    //   2707: ldc2_w 388
    //   2710: lconst_1
    //   2711: invokeinterface 188 7 0
    //   2716: ldc 182
    //   2718: invokestatic 158	com/tencent/luggage/a/e:C	(Ljava/lang/Class;)Lcom/tencent/luggage/a/d;
    //   2721: checkcast 182	com/tencent/mm/plugin/appbrand/n/a
    //   2724: ldc2_w 183
    //   2727: ldc2_w 390
    //   2730: invokestatic 68	java/lang/System:currentTimeMillis	()J
    //   2733: aload_0
    //   2734: getfield 176	com/tencent/mm/plugin/appbrand/l/a/b:ipE	J
    //   2737: lsub
    //   2738: invokeinterface 188 7 0
    //   2743: invokestatic 397	com/tencent/mm/sdk/platformtools/ah:getContext	()Landroid/content/Context;
    //   2746: invokestatic 403	com/tencent/mm/sdk/platformtools/at:getNetType	(Landroid/content/Context;)I
    //   2749: istore 11
    //   2751: iload 11
    //   2753: iconst_m1
    //   2754: if_icmpne +23 -> 2777
    //   2757: ldc 182
    //   2759: invokestatic 158	com/tencent/luggage/a/e:C	(Ljava/lang/Class;)Lcom/tencent/luggage/a/d;
    //   2762: checkcast 182	com/tencent/mm/plugin/appbrand/n/a
    //   2765: ldc2_w 183
    //   2768: ldc2_w 404
    //   2771: lconst_1
    //   2772: invokeinterface 188 7 0
    //   2777: ldc 92
    //   2779: ldc_w 407
    //   2782: iconst_1
    //   2783: anewarray 4	java/lang/Object
    //   2786: dup
    //   2787: iconst_0
    //   2788: iload 11
    //   2790: invokestatic 345	java/lang/Integer:valueOf	(I)Ljava/lang/Integer;
    //   2793: aastore
    //   2794: invokestatic 148	com/tencent/mm/sdk/platformtools/ab:i	(Ljava/lang/String;Ljava/lang/String;[Ljava/lang/Object;)V
    //   2797: aload_0
    //   2798: invokevirtual 292	com/tencent/mm/plugin/appbrand/l/a/b:aIP	()V
    //   2801: aload_0
    //   2802: getfield 62	com/tencent/mm/plugin/appbrand/l/a/b:ipB	Lcom/tencent/mm/plugin/appbrand/l/a/a;
    //   2805: aload_0
    //   2806: getfield 294	com/tencent/mm/plugin/appbrand/l/a/b:hvr	Ljava/lang/String;
    //   2809: invokeinterface 297 2 0
    //   2814: ldc 116
    //   2816: invokestatic 75	com/tencent/matrix/trace/core/AppMethodBeat:o	(I)V
    //   2819: goto -2770 -> 49
    //   2822: iload 11
    //   2824: istore 22
    //   2826: iload 11
    //   2828: istore 23
    //   2830: iload 11
    //   2832: istore 24
    //   2834: iload 11
    //   2836: istore 25
    //   2838: iload 11
    //   2840: istore 26
    //   2842: iload 11
    //   2844: istore 27
    //   2846: aload_0
    //   2847: getfield 85	com/tencent/mm/plugin/appbrand/l/a/b:ipF	Ljava/net/HttpURLConnection;
    //   2850: invokevirtual 309	java/net/HttpURLConnection:getContentLength	()I
    //   2853: istore 6
    //   2855: iload 6
    //   2857: ifle +326 -> 3183
    //   2860: iload 11
    //   2862: istore 22
    //   2864: iload 11
    //   2866: istore 23
    //   2868: iload 11
    //   2870: istore 24
    //   2872: iload 11
    //   2874: istore 25
    //   2876: iload 11
    //   2878: istore 26
    //   2880: iload 11
    //   2882: istore 27
    //   2884: aload_0
    //   2885: getfield 409	com/tencent/mm/plugin/appbrand/l/a/b:ipD	I
    //   2888: ifle +295 -> 3183
    //   2891: iload 11
    //   2893: istore 22
    //   2895: iload 11
    //   2897: istore 23
    //   2899: iload 11
    //   2901: istore 24
    //   2903: iload 11
    //   2905: istore 25
    //   2907: iload 11
    //   2909: istore 26
    //   2911: iload 11
    //   2913: istore 27
    //   2915: iload 6
    //   2917: aload_0
    //   2918: getfield 409	com/tencent/mm/plugin/appbrand/l/a/b:ipD	I
    //   2921: ldc_w 410
    //   2924: imul
    //   2925: if_icmplt +258 -> 3183
    //   2928: iload 11
    //   2930: istore 22
    //   2932: iload 11
    //   2934: istore 23
    //   2936: iload 11
    //   2938: istore 24
    //   2940: iload 11
    //   2942: istore 25
    //   2944: iload 11
    //   2946: istore 26
    //   2948: iload 11
    //   2950: istore 27
    //   2952: ldc 92
    //   2954: ldc_w 412
    //   2957: iconst_1
    //   2958: anewarray 4	java/lang/Object
    //   2961: dup
    //   2962: iconst_0
    //   2963: iload 6
    //   2965: invokestatic 345	java/lang/Integer:valueOf	(I)Ljava/lang/Integer;
    //   2968: aastore
    //   2969: invokestatic 148	com/tencent/mm/sdk/platformtools/ab:i	(Ljava/lang/String;Ljava/lang/String;[Ljava/lang/Object;)V
    //   2972: iload 11
    //   2974: istore 22
    //   2976: iload 11
    //   2978: istore 23
    //   2980: iload 11
    //   2982: istore 24
    //   2984: iload 11
    //   2986: istore 25
    //   2988: iload 11
    //   2990: istore 26
    //   2992: iload 11
    //   2994: istore 27
    //   2996: aload_0
    //   2997: getfield 62	com/tencent/mm/plugin/appbrand/l/a/b:ipB	Lcom/tencent/mm/plugin/appbrand/l/a/a;
    //   3000: aload_0
    //   3001: getfield 60	com/tencent/mm/plugin/appbrand/l/a/b:filename	Ljava/lang/String;
    //   3004: aload_0
    //   3005: getfield 58	com/tencent/mm/plugin/appbrand/l/a/b:uri	Ljava/lang/String;
    //   3008: ldc_w 414
    //   3011: invokeinterface 133 4 0
    //   3016: ldc 152
    //   3018: invokestatic 158	com/tencent/luggage/a/e:C	(Ljava/lang/Class;)Lcom/tencent/luggage/a/d;
    //   3021: checkcast 152	com/tencent/mm/plugin/appbrand/l/o
    //   3024: aload_0
    //   3025: getfield 56	com/tencent/mm/plugin/appbrand/l/a/b:hvw	Lcom/tencent/mm/plugin/appbrand/jsapi/c;
    //   3028: invokeinterface 164 1 0
    //   3033: aload_0
    //   3034: getfield 166	com/tencent/mm/plugin/appbrand/l/a/b:ioR	Ljava/lang/String;
    //   3037: ldc 168
    //   3039: aload_0
    //   3040: getfield 58	com/tencent/mm/plugin/appbrand/l/a/b:uri	Ljava/lang/String;
    //   3043: lconst_0
    //   3044: lconst_0
    //   3045: iload 11
    //   3047: iconst_2
    //   3048: aload_0
    //   3049: invokespecial 170	com/tencent/mm/plugin/appbrand/l/a/b:aID	()I
    //   3052: invokeinterface 174 12 0
    //   3057: ldc 182
    //   3059: invokestatic 158	com/tencent/luggage/a/e:C	(Ljava/lang/Class;)Lcom/tencent/luggage/a/d;
    //   3062: checkcast 182	com/tencent/mm/plugin/appbrand/n/a
    //   3065: ldc2_w 183
    //   3068: ldc2_w 388
    //   3071: lconst_1
    //   3072: invokeinterface 188 7 0
    //   3077: ldc 182
    //   3079: invokestatic 158	com/tencent/luggage/a/e:C	(Ljava/lang/Class;)Lcom/tencent/luggage/a/d;
    //   3082: checkcast 182	com/tencent/mm/plugin/appbrand/n/a
    //   3085: ldc2_w 183
    //   3088: ldc2_w 390
    //   3091: invokestatic 68	java/lang/System:currentTimeMillis	()J
    //   3094: aload_0
    //   3095: getfield 176	com/tencent/mm/plugin/appbrand/l/a/b:ipE	J
    //   3098: lsub
    //   3099: invokeinterface 188 7 0
    //   3104: invokestatic 397	com/tencent/mm/sdk/platformtools/ah:getContext	()Landroid/content/Context;
    //   3107: invokestatic 403	com/tencent/mm/sdk/platformtools/at:getNetType	(Landroid/content/Context;)I
    //   3110: istore 11
    //   3112: iload 11
    //   3114: iconst_m1
    //   3115: if_icmpne +23 -> 3138
    //   3118: ldc 182
    //   3120: invokestatic 158	com/tencent/luggage/a/e:C	(Ljava/lang/Class;)Lcom/tencent/luggage/a/d;
    //   3123: checkcast 182	com/tencent/mm/plugin/appbrand/n/a
    //   3126: ldc2_w 183
    //   3129: ldc2_w 404
    //   3132: lconst_1
    //   3133: invokeinterface 188 7 0
    //   3138: ldc 92
    //   3140: ldc_w 407
    //   3143: iconst_1
    //   3144: anewarray 4	java/lang/Object
    //   3147: dup
    //   3148: iconst_0
    //   3149: iload 11
    //   3151: invokestatic 345	java/lang/Integer:valueOf	(I)Ljava/lang/Integer;
    //   3154: aastore
    //   3155: invokestatic 148	com/tencent/mm/sdk/platformtools/ab:i	(Ljava/lang/String;Ljava/lang/String;[Ljava/lang/Object;)V
    //   3158: aload_0
    //   3159: invokevirtual 292	com/tencent/mm/plugin/appbrand/l/a/b:aIP	()V
    //   3162: aload_0
    //   3163: getfield 62	com/tencent/mm/plugin/appbrand/l/a/b:ipB	Lcom/tencent/mm/plugin/appbrand/l/a/a;
    //   3166: aload_0
    //   3167: getfield 294	com/tencent/mm/plugin/appbrand/l/a/b:hvr	Ljava/lang/String;
    //   3170: invokeinterface 297 2 0
    //   3175: ldc 116
    //   3177: invokestatic 75	com/tencent/matrix/trace/core/AppMethodBeat:o	(I)V
    //   3180: goto -3131 -> 49
    //   3183: iload 11
    //   3185: istore 22
    //   3187: iload 11
    //   3189: istore 23
    //   3191: iload 11
    //   3193: istore 24
    //   3195: iload 11
    //   3197: istore 25
    //   3199: iload 11
    //   3201: istore 27
    //   3203: ldc 233
    //   3205: aload_0
    //   3206: getfield 85	com/tencent/mm/plugin/appbrand/l/a/b:ipF	Ljava/net/HttpURLConnection;
    //   3209: invokevirtual 417	java/net/HttpURLConnection:getContentEncoding	()Ljava/lang/String;
    //   3212: invokevirtual 421	java/lang/String:equals	(Ljava/lang/Object;)Z
    //   3215: ifeq +329 -> 3544
    //   3218: iload 11
    //   3220: istore 22
    //   3222: iload 11
    //   3224: istore 23
    //   3226: iload 11
    //   3228: istore 24
    //   3230: iload 11
    //   3232: istore 25
    //   3234: iload 11
    //   3236: istore 27
    //   3238: new 423	java/util/zip/GZIPInputStream
    //   3241: astore 30
    //   3243: iload 11
    //   3245: istore 22
    //   3247: iload 11
    //   3249: istore 23
    //   3251: iload 11
    //   3253: istore 24
    //   3255: iload 11
    //   3257: istore 25
    //   3259: iload 11
    //   3261: istore 27
    //   3263: aload 30
    //   3265: aload_0
    //   3266: getfield 85	com/tencent/mm/plugin/appbrand/l/a/b:ipF	Ljava/net/HttpURLConnection;
    //   3269: invokevirtual 427	java/net/HttpURLConnection:getInputStream	()Ljava/io/InputStream;
    //   3272: invokespecial 430	java/util/zip/GZIPInputStream:<init>	(Ljava/io/InputStream;)V
    //   3275: aload 30
    //   3277: astore 16
    //   3279: new 432	java/io/File
    //   3282: astore 13
    //   3284: aload 13
    //   3286: aload_0
    //   3287: getfield 60	com/tencent/mm/plugin/appbrand/l/a/b:filename	Ljava/lang/String;
    //   3290: invokespecial 433	java/io/File:<init>	(Ljava/lang/String;)V
    //   3293: aload 13
    //   3295: invokevirtual 436	java/io/File:exists	()Z
    //   3298: ifeq +758 -> 4056
    //   3301: ldc 92
    //   3303: ldc_w 438
    //   3306: iconst_1
    //   3307: anewarray 4	java/lang/Object
    //   3310: dup
    //   3311: iconst_0
    //   3312: aload_0
    //   3313: getfield 60	com/tencent/mm/plugin/appbrand/l/a/b:filename	Ljava/lang/String;
    //   3316: aastore
    //   3317: invokestatic 148	com/tencent/mm/sdk/platformtools/ab:i	(Ljava/lang/String;Ljava/lang/String;[Ljava/lang/Object;)V
    //   3320: aload 13
    //   3322: invokevirtual 441	java/io/File:delete	()Z
    //   3325: ifne +731 -> 4056
    //   3328: ldc 92
    //   3330: ldc_w 443
    //   3333: iconst_1
    //   3334: anewarray 4	java/lang/Object
    //   3337: dup
    //   3338: iconst_0
    //   3339: aload_0
    //   3340: getfield 60	com/tencent/mm/plugin/appbrand/l/a/b:filename	Ljava/lang/String;
    //   3343: aastore
    //   3344: invokestatic 349	com/tencent/mm/sdk/platformtools/ab:e	(Ljava/lang/String;Ljava/lang/String;[Ljava/lang/Object;)V
    //   3347: aload_0
    //   3348: getfield 62	com/tencent/mm/plugin/appbrand/l/a/b:ipB	Lcom/tencent/mm/plugin/appbrand/l/a/a;
    //   3351: aload_0
    //   3352: getfield 60	com/tencent/mm/plugin/appbrand/l/a/b:filename	Ljava/lang/String;
    //   3355: aload_0
    //   3356: getfield 58	com/tencent/mm/plugin/appbrand/l/a/b:uri	Ljava/lang/String;
    //   3359: ldc_w 445
    //   3362: invokeinterface 133 4 0
    //   3367: ldc 152
    //   3369: invokestatic 158	com/tencent/luggage/a/e:C	(Ljava/lang/Class;)Lcom/tencent/luggage/a/d;
    //   3372: checkcast 152	com/tencent/mm/plugin/appbrand/l/o
    //   3375: aload_0
    //   3376: getfield 56	com/tencent/mm/plugin/appbrand/l/a/b:hvw	Lcom/tencent/mm/plugin/appbrand/jsapi/c;
    //   3379: invokeinterface 164 1 0
    //   3384: aload_0
    //   3385: getfield 166	com/tencent/mm/plugin/appbrand/l/a/b:ioR	Ljava/lang/String;
    //   3388: ldc 168
    //   3390: aload_0
    //   3391: getfield 58	com/tencent/mm/plugin/appbrand/l/a/b:uri	Ljava/lang/String;
    //   3394: lconst_0
    //   3395: lconst_0
    //   3396: iload 11
    //   3398: iconst_2
    //   3399: aload_0
    //   3400: invokespecial 170	com/tencent/mm/plugin/appbrand/l/a/b:aID	()I
    //   3403: invokeinterface 174 12 0
    //   3408: ldc 182
    //   3410: invokestatic 158	com/tencent/luggage/a/e:C	(Ljava/lang/Class;)Lcom/tencent/luggage/a/d;
    //   3413: checkcast 182	com/tencent/mm/plugin/appbrand/n/a
    //   3416: ldc2_w 183
    //   3419: ldc2_w 388
    //   3422: lconst_1
    //   3423: invokeinterface 188 7 0
    //   3428: ldc 182
    //   3430: invokestatic 158	com/tencent/luggage/a/e:C	(Ljava/lang/Class;)Lcom/tencent/luggage/a/d;
    //   3433: checkcast 182	com/tencent/mm/plugin/appbrand/n/a
    //   3436: ldc2_w 183
    //   3439: ldc2_w 390
    //   3442: invokestatic 68	java/lang/System:currentTimeMillis	()J
    //   3445: aload_0
    //   3446: getfield 176	com/tencent/mm/plugin/appbrand/l/a/b:ipE	J
    //   3449: lsub
    //   3450: invokeinterface 188 7 0
    //   3455: invokestatic 397	com/tencent/mm/sdk/platformtools/ah:getContext	()Landroid/content/Context;
    //   3458: invokestatic 403	com/tencent/mm/sdk/platformtools/at:getNetType	(Landroid/content/Context;)I
    //   3461: istore 11
    //   3463: iload 11
    //   3465: iconst_m1
    //   3466: if_icmpne +23 -> 3489
    //   3469: ldc 182
    //   3471: invokestatic 158	com/tencent/luggage/a/e:C	(Ljava/lang/Class;)Lcom/tencent/luggage/a/d;
    //   3474: checkcast 182	com/tencent/mm/plugin/appbrand/n/a
    //   3477: ldc2_w 183
    //   3480: ldc2_w 404
    //   3483: lconst_1
    //   3484: invokeinterface 188 7 0
    //   3489: ldc 92
    //   3491: ldc_w 407
    //   3494: iconst_1
    //   3495: anewarray 4	java/lang/Object
    //   3498: dup
    //   3499: iconst_0
    //   3500: iload 11
    //   3502: invokestatic 345	java/lang/Integer:valueOf	(I)Ljava/lang/Integer;
    //   3505: aastore
    //   3506: invokestatic 148	com/tencent/mm/sdk/platformtools/ab:i	(Ljava/lang/String;Ljava/lang/String;[Ljava/lang/Object;)V
    //   3509: aload 16
    //   3511: ifnull +8 -> 3519
    //   3514: aload 16
    //   3516: invokevirtual 290	java/io/InputStream:close	()V
    //   3519: aload_0
    //   3520: invokevirtual 292	com/tencent/mm/plugin/appbrand/l/a/b:aIP	()V
    //   3523: aload_0
    //   3524: getfield 62	com/tencent/mm/plugin/appbrand/l/a/b:ipB	Lcom/tencent/mm/plugin/appbrand/l/a/a;
    //   3527: aload_0
    //   3528: getfield 294	com/tencent/mm/plugin/appbrand/l/a/b:hvr	Ljava/lang/String;
    //   3531: invokeinterface 297 2 0
    //   3536: ldc 116
    //   3538: invokestatic 75	com/tencent/matrix/trace/core/AppMethodBeat:o	(I)V
    //   3541: goto -3492 -> 49
    //   3544: iload 11
    //   3546: istore 22
    //   3548: iload 11
    //   3550: istore 23
    //   3552: iload 11
    //   3554: istore 24
    //   3556: iload 11
    //   3558: istore 25
    //   3560: iload 11
    //   3562: istore 27
    //   3564: ldc_w 447
    //   3567: aload_0
    //   3568: getfield 85	com/tencent/mm/plugin/appbrand/l/a/b:ipF	Ljava/net/HttpURLConnection;
    //   3571: invokevirtual 417	java/net/HttpURLConnection:getContentEncoding	()Ljava/lang/String;
    //   3574: invokevirtual 421	java/lang/String:equals	(Ljava/lang/Object;)Z
    //   3577: ifeq +308 -> 3885
    //   3580: iload 11
    //   3582: istore 22
    //   3584: iload 11
    //   3586: istore 23
    //   3588: iload 11
    //   3590: istore 24
    //   3592: iload 11
    //   3594: istore 25
    //   3596: iload 11
    //   3598: istore 27
    //   3600: aload_0
    //   3601: getfield 85	com/tencent/mm/plugin/appbrand/l/a/b:ipF	Ljava/net/HttpURLConnection;
    //   3604: invokevirtual 427	java/net/HttpURLConnection:getInputStream	()Ljava/io/InputStream;
    //   3607: astore 29
    //   3609: iload 11
    //   3611: istore 22
    //   3613: iload 11
    //   3615: istore 23
    //   3617: iload 11
    //   3619: istore 24
    //   3621: iload 11
    //   3623: istore 25
    //   3625: iload 11
    //   3627: istore 27
    //   3629: new 449	java/util/zip/Inflater
    //   3632: astore 30
    //   3634: iload 11
    //   3636: istore 22
    //   3638: iload 11
    //   3640: istore 23
    //   3642: iload 11
    //   3644: istore 24
    //   3646: iload 11
    //   3648: istore 25
    //   3650: iload 11
    //   3652: istore 27
    //   3654: aload 30
    //   3656: iconst_1
    //   3657: invokespecial 451	java/util/zip/Inflater:<init>	(Z)V
    //   3660: iload 11
    //   3662: istore 22
    //   3664: iload 11
    //   3666: istore 23
    //   3668: iload 11
    //   3670: istore 24
    //   3672: iload 11
    //   3674: istore 25
    //   3676: iload 11
    //   3678: istore 27
    //   3680: new 453	java/util/zip/InflaterInputStream
    //   3683: dup
    //   3684: aload 29
    //   3686: aload 30
    //   3688: invokespecial 456	java/util/zip/InflaterInputStream:<init>	(Ljava/io/InputStream;Ljava/util/zip/Inflater;)V
    //   3691: astore 30
    //   3693: aload 30
    //   3695: astore 16
    //   3697: goto -418 -> 3279
    //   3700: astore 29
    //   3702: iload 11
    //   3704: istore 22
    //   3706: iload 11
    //   3708: istore 23
    //   3710: iload 11
    //   3712: istore 24
    //   3714: iload 11
    //   3716: istore 25
    //   3718: iload 11
    //   3720: istore 26
    //   3722: iload 11
    //   3724: istore 27
    //   3726: ldc 92
    //   3728: aload 29
    //   3730: ldc_w 458
    //   3733: iconst_0
    //   3734: anewarray 4	java/lang/Object
    //   3737: invokestatic 100	com/tencent/mm/sdk/platformtools/ab:printErrStackTrace	(Ljava/lang/String;Ljava/lang/Throwable;Ljava/lang/String;[Ljava/lang/Object;)V
    //   3740: iload 11
    //   3742: istore 22
    //   3744: iload 11
    //   3746: istore 23
    //   3748: iload 11
    //   3750: istore 24
    //   3752: iload 11
    //   3754: istore 25
    //   3756: iload 11
    //   3758: istore 27
    //   3760: ldc 233
    //   3762: aload_0
    //   3763: getfield 85	com/tencent/mm/plugin/appbrand/l/a/b:ipF	Ljava/net/HttpURLConnection;
    //   3766: invokevirtual 417	java/net/HttpURLConnection:getContentEncoding	()Ljava/lang/String;
    //   3769: invokevirtual 421	java/lang/String:equals	(Ljava/lang/Object;)Z
    //   3772: ifeq +149 -> 3921
    //   3775: iload 11
    //   3777: istore 22
    //   3779: iload 11
    //   3781: istore 23
    //   3783: iload 11
    //   3785: istore 24
    //   3787: iload 11
    //   3789: istore 25
    //   3791: iload 11
    //   3793: istore 27
    //   3795: new 423	java/util/zip/GZIPInputStream
    //   3798: astore 30
    //   3800: iload 11
    //   3802: istore 22
    //   3804: iload 11
    //   3806: istore 23
    //   3808: iload 11
    //   3810: istore 24
    //   3812: iload 11
    //   3814: istore 25
    //   3816: iload 11
    //   3818: istore 27
    //   3820: aload 30
    //   3822: aload_0
    //   3823: getfield 85	com/tencent/mm/plugin/appbrand/l/a/b:ipF	Ljava/net/HttpURLConnection;
    //   3826: invokevirtual 461	java/net/HttpURLConnection:getErrorStream	()Ljava/io/InputStream;
    //   3829: invokespecial 430	java/util/zip/GZIPInputStream:<init>	(Ljava/io/InputStream;)V
    //   3832: aload 30
    //   3834: astore 16
    //   3836: goto -557 -> 3279
    //   3839: astore 30
    //   3841: iload 11
    //   3843: istore 22
    //   3845: iload 11
    //   3847: istore 23
    //   3849: iload 11
    //   3851: istore 24
    //   3853: iload 11
    //   3855: istore 25
    //   3857: iload 11
    //   3859: istore 26
    //   3861: iload 11
    //   3863: istore 27
    //   3865: ldc 92
    //   3867: aload 29
    //   3869: ldc_w 463
    //   3872: iconst_0
    //   3873: anewarray 4	java/lang/Object
    //   3876: invokestatic 100	com/tencent/mm/sdk/platformtools/ab:printErrStackTrace	(Ljava/lang/String;Ljava/lang/Throwable;Ljava/lang/String;[Ljava/lang/Object;)V
    //   3879: aconst_null
    //   3880: astore 16
    //   3882: goto -603 -> 3279
    //   3885: iload 11
    //   3887: istore 22
    //   3889: iload 11
    //   3891: istore 23
    //   3893: iload 11
    //   3895: istore 24
    //   3897: iload 11
    //   3899: istore 25
    //   3901: iload 11
    //   3903: istore 27
    //   3905: aload_0
    //   3906: getfield 85	com/tencent/mm/plugin/appbrand/l/a/b:ipF	Ljava/net/HttpURLConnection;
    //   3909: invokevirtual 427	java/net/HttpURLConnection:getInputStream	()Ljava/io/InputStream;
    //   3912: astore 30
    //   3914: aload 30
    //   3916: astore 16
    //   3918: goto -639 -> 3279
    //   3921: iload 11
    //   3923: istore 22
    //   3925: iload 11
    //   3927: istore 23
    //   3929: iload 11
    //   3931: istore 24
    //   3933: iload 11
    //   3935: istore 25
    //   3937: iload 11
    //   3939: istore 27
    //   3941: aload_0
    //   3942: getfield 85	com/tencent/mm/plugin/appbrand/l/a/b:ipF	Ljava/net/HttpURLConnection;
    //   3945: invokevirtual 461	java/net/HttpURLConnection:getErrorStream	()Ljava/io/InputStream;
    //   3948: astore 30
    //   3950: aload 30
    //   3952: astore 16
    //   3954: goto -675 -> 3279
    //   3957: astore 16
    //   3959: ldc 92
    //   3961: aload 16
    //   3963: ldc_w 465
    //   3966: iconst_2
    //   3967: anewarray 4	java/lang/Object
    //   3970: dup
    //   3971: iconst_0
    //   3972: aload_0
    //   3973: getfield 58	com/tencent/mm/plugin/appbrand/l/a/b:uri	Ljava/lang/String;
    //   3976: aastore
    //   3977: dup
    //   3978: iconst_1
    //   3979: aload_0
    //   3980: getfield 60	com/tencent/mm/plugin/appbrand/l/a/b:filename	Ljava/lang/String;
    //   3983: aastore
    //   3984: invokestatic 100	com/tencent/mm/sdk/platformtools/ab:printErrStackTrace	(Ljava/lang/String;Ljava/lang/Throwable;Ljava/lang/String;[Ljava/lang/Object;)V
    //   3987: goto -468 -> 3519
    //   3990: astore 16
    //   3992: ldc 92
    //   3994: aload 16
    //   3996: ldc_w 467
    //   3999: iconst_2
    //   4000: anewarray 4	java/lang/Object
    //   4003: dup
    //   4004: iconst_0
    //   4005: aload_0
    //   4006: getfield 58	com/tencent/mm/plugin/appbrand/l/a/b:uri	Ljava/lang/String;
    //   4009: aastore
    //   4010: dup
    //   4011: iconst_1
    //   4012: aload_0
    //   4013: getfield 60	com/tencent/mm/plugin/appbrand/l/a/b:filename	Ljava/lang/String;
    //   4016: aastore
    //   4017: invokestatic 100	com/tencent/mm/sdk/platformtools/ab:printErrStackTrace	(Ljava/lang/String;Ljava/lang/Throwable;Ljava/lang/String;[Ljava/lang/Object;)V
    //   4020: goto -501 -> 3519
    //   4023: astore 16
    //   4025: ldc 92
    //   4027: aload 16
    //   4029: ldc_w 469
    //   4032: iconst_2
    //   4033: anewarray 4	java/lang/Object
    //   4036: dup
    //   4037: iconst_0
    //   4038: aload_0
    //   4039: getfield 58	com/tencent/mm/plugin/appbrand/l/a/b:uri	Ljava/lang/String;
    //   4042: aastore
    //   4043: dup
    //   4044: iconst_1
    //   4045: aload_0
    //   4046: getfield 60	com/tencent/mm/plugin/appbrand/l/a/b:filename	Ljava/lang/String;
    //   4049: aastore
    //   4050: invokestatic 100	com/tencent/mm/sdk/platformtools/ab:printErrStackTrace	(Ljava/lang/String;Ljava/lang/Throwable;Ljava/lang/String;[Ljava/lang/Object;)V
    //   4053: goto -534 -> 3519
    //   4056: aload 13
    //   4058: invokevirtual 473	java/io/File:getParentFile	()Ljava/io/File;
    //   4061: invokevirtual 436	java/io/File:exists	()Z
    //   4064: ifne +348 -> 4412
    //   4067: ldc 92
    //   4069: ldc_w 475
    //   4072: iconst_1
    //   4073: anewarray 4	java/lang/Object
    //   4076: dup
    //   4077: iconst_0
    //   4078: aload_0
    //   4079: getfield 60	com/tencent/mm/plugin/appbrand/l/a/b:filename	Ljava/lang/String;
    //   4082: aastore
    //   4083: invokestatic 148	com/tencent/mm/sdk/platformtools/ab:i	(Ljava/lang/String;Ljava/lang/String;[Ljava/lang/Object;)V
    //   4086: aload 13
    //   4088: invokevirtual 473	java/io/File:getParentFile	()Ljava/io/File;
    //   4091: invokevirtual 478	java/io/File:mkdirs	()Z
    //   4094: ifne +318 -> 4412
    //   4097: ldc 92
    //   4099: ldc_w 480
    //   4102: iconst_1
    //   4103: anewarray 4	java/lang/Object
    //   4106: dup
    //   4107: iconst_0
    //   4108: aload_0
    //   4109: getfield 60	com/tencent/mm/plugin/appbrand/l/a/b:filename	Ljava/lang/String;
    //   4112: aastore
    //   4113: invokestatic 349	com/tencent/mm/sdk/platformtools/ab:e	(Ljava/lang/String;Ljava/lang/String;[Ljava/lang/Object;)V
    //   4116: aload_0
    //   4117: getfield 62	com/tencent/mm/plugin/appbrand/l/a/b:ipB	Lcom/tencent/mm/plugin/appbrand/l/a/a;
    //   4120: aload_0
    //   4121: getfield 60	com/tencent/mm/plugin/appbrand/l/a/b:filename	Ljava/lang/String;
    //   4124: aload_0
    //   4125: getfield 58	com/tencent/mm/plugin/appbrand/l/a/b:uri	Ljava/lang/String;
    //   4128: ldc_w 482
    //   4131: invokeinterface 133 4 0
    //   4136: ldc 152
    //   4138: invokestatic 158	com/tencent/luggage/a/e:C	(Ljava/lang/Class;)Lcom/tencent/luggage/a/d;
    //   4141: checkcast 152	com/tencent/mm/plugin/appbrand/l/o
    //   4144: aload_0
    //   4145: getfield 56	com/tencent/mm/plugin/appbrand/l/a/b:hvw	Lcom/tencent/mm/plugin/appbrand/jsapi/c;
    //   4148: invokeinterface 164 1 0
    //   4153: aload_0
    //   4154: getfield 166	com/tencent/mm/plugin/appbrand/l/a/b:ioR	Ljava/lang/String;
    //   4157: ldc 168
    //   4159: aload_0
    //   4160: getfield 58	com/tencent/mm/plugin/appbrand/l/a/b:uri	Ljava/lang/String;
    //   4163: lconst_0
    //   4164: lconst_0
    //   4165: iload 11
    //   4167: iconst_2
    //   4168: aload_0
    //   4169: invokespecial 170	com/tencent/mm/plugin/appbrand/l/a/b:aID	()I
    //   4172: invokeinterface 174 12 0
    //   4177: ldc 182
    //   4179: invokestatic 158	com/tencent/luggage/a/e:C	(Ljava/lang/Class;)Lcom/tencent/luggage/a/d;
    //   4182: checkcast 182	com/tencent/mm/plugin/appbrand/n/a
    //   4185: ldc2_w 183
    //   4188: ldc2_w 388
    //   4191: lconst_1
    //   4192: invokeinterface 188 7 0
    //   4197: ldc 182
    //   4199: invokestatic 158	com/tencent/luggage/a/e:C	(Ljava/lang/Class;)Lcom/tencent/luggage/a/d;
    //   4202: checkcast 182	com/tencent/mm/plugin/appbrand/n/a
    //   4205: ldc2_w 183
    //   4208: ldc2_w 390
    //   4211: invokestatic 68	java/lang/System:currentTimeMillis	()J
    //   4214: aload_0
    //   4215: getfield 176	com/tencent/mm/plugin/appbrand/l/a/b:ipE	J
    //   4218: lsub
    //   4219: invokeinterface 188 7 0
    //   4224: invokestatic 397	com/tencent/mm/sdk/platformtools/ah:getContext	()Landroid/content/Context;
    //   4227: invokestatic 403	com/tencent/mm/sdk/platformtools/at:getNetType	(Landroid/content/Context;)I
    //   4230: istore 11
    //   4232: iload 11
    //   4234: iconst_m1
    //   4235: if_icmpne +23 -> 4258
    //   4238: ldc 182
    //   4240: invokestatic 158	com/tencent/luggage/a/e:C	(Ljava/lang/Class;)Lcom/tencent/luggage/a/d;
    //   4243: checkcast 182	com/tencent/mm/plugin/appbrand/n/a
    //   4246: ldc2_w 183
    //   4249: ldc2_w 404
    //   4252: lconst_1
    //   4253: invokeinterface 188 7 0
    //   4258: ldc 92
    //   4260: ldc_w 407
    //   4263: iconst_1
    //   4264: anewarray 4	java/lang/Object
    //   4267: dup
    //   4268: iconst_0
    //   4269: iload 11
    //   4271: invokestatic 345	java/lang/Integer:valueOf	(I)Ljava/lang/Integer;
    //   4274: aastore
    //   4275: invokestatic 148	com/tencent/mm/sdk/platformtools/ab:i	(Ljava/lang/String;Ljava/lang/String;[Ljava/lang/Object;)V
    //   4278: aload 16
    //   4280: ifnull +8 -> 4288
    //   4283: aload 16
    //   4285: invokevirtual 290	java/io/InputStream:close	()V
    //   4288: aload_0
    //   4289: invokevirtual 292	com/tencent/mm/plugin/appbrand/l/a/b:aIP	()V
    //   4292: aload_0
    //   4293: getfield 62	com/tencent/mm/plugin/appbrand/l/a/b:ipB	Lcom/tencent/mm/plugin/appbrand/l/a/a;
    //   4296: aload_0
    //   4297: getfield 294	com/tencent/mm/plugin/appbrand/l/a/b:hvr	Ljava/lang/String;
    //   4300: invokeinterface 297 2 0
    //   4305: ldc 116
    //   4307: invokestatic 75	com/tencent/matrix/trace/core/AppMethodBeat:o	(I)V
    //   4310: goto -4261 -> 49
    //   4313: astore 16
    //   4315: ldc 92
    //   4317: aload 16
    //   4319: ldc_w 465
    //   4322: iconst_2
    //   4323: anewarray 4	java/lang/Object
    //   4326: dup
    //   4327: iconst_0
    //   4328: aload_0
    //   4329: getfield 58	com/tencent/mm/plugin/appbrand/l/a/b:uri	Ljava/lang/String;
    //   4332: aastore
    //   4333: dup
    //   4334: iconst_1
    //   4335: aload_0
    //   4336: getfield 60	com/tencent/mm/plugin/appbrand/l/a/b:filename	Ljava/lang/String;
    //   4339: aastore
    //   4340: invokestatic 100	com/tencent/mm/sdk/platformtools/ab:printErrStackTrace	(Ljava/lang/String;Ljava/lang/Throwable;Ljava/lang/String;[Ljava/lang/Object;)V
    //   4343: goto -55 -> 4288
    //   4346: astore 16
    //   4348: ldc 92
    //   4350: aload 16
    //   4352: ldc_w 467
    //   4355: iconst_2
    //   4356: anewarray 4	java/lang/Object
    //   4359: dup
    //   4360: iconst_0
    //   4361: aload_0
    //   4362: getfield 58	com/tencent/mm/plugin/appbrand/l/a/b:uri	Ljava/lang/String;
    //   4365: aastore
    //   4366: dup
    //   4367: iconst_1
    //   4368: aload_0
    //   4369: getfield 60	com/tencent/mm/plugin/appbrand/l/a/b:filename	Ljava/lang/String;
    //   4372: aastore
    //   4373: invokestatic 100	com/tencent/mm/sdk/platformtools/ab:printErrStackTrace	(Ljava/lang/String;Ljava/lang/Throwable;Ljava/lang/String;[Ljava/lang/Object;)V
    //   4376: goto -88 -> 4288
    //   4379: astore 16
    //   4381: ldc 92
    //   4383: aload 16
    //   4385: ldc_w 469
    //   4388: iconst_2
    //   4389: anewarray 4	java/lang/Object
    //   4392: dup
    //   4393: iconst_0
    //   4394: aload_0
    //   4395: getfield 58	com/tencent/mm/plugin/appbrand/l/a/b:uri	Ljava/lang/String;
    //   4398: aastore
    //   4399: dup
    //   4400: iconst_1
    //   4401: aload_0
    //   4402: getfield 60	com/tencent/mm/plugin/appbrand/l/a/b:filename	Ljava/lang/String;
    //   4405: aastore
    //   4406: invokestatic 100	com/tencent/mm/sdk/platformtools/ab:printErrStackTrace	(Ljava/lang/String;Ljava/lang/Throwable;Ljava/lang/String;[Ljava/lang/Object;)V
    //   4409: goto -121 -> 4288
    //   4412: aload 16
    //   4414: ifnull +6419 -> 10833
    //   4417: new 284	java/io/FileOutputStream
    //   4420: dup
    //   4421: aload 13
    //   4423: invokespecial 485	java/io/FileOutputStream:<init>	(Ljava/io/File;)V
    //   4426: astore 15
    //   4428: iload 6
    //   4430: i2l
    //   4431: lstore 31
    //   4433: lload 31
    //   4435: invokestatic 489	com/tencent/mm/plugin/appbrand/l/j:gr	(J)I
    //   4438: newarray byte
    //   4440: astore 14
    //   4442: iconst_m1
    //   4443: istore 6
    //   4445: lconst_0
    //   4446: lstore 31
    //   4448: aload 16
    //   4450: aload 14
    //   4452: invokevirtual 493	java/io/InputStream:read	([B)I
    //   4455: istore 23
    //   4457: iload 23
    //   4459: iconst_m1
    //   4460: if_icmpeq +1408 -> 5868
    //   4463: aload_0
    //   4464: getfield 51	com/tencent/mm/plugin/appbrand/l/a/b:isRunning	Z
    //   4467: ifeq +1401 -> 5868
    //   4470: aload_0
    //   4471: getfield 56	com/tencent/mm/plugin/appbrand/l/a/b:hvw	Lcom/tencent/mm/plugin/appbrand/jsapi/c;
    //   4474: invokestatic 497	com/tencent/mm/plugin/appbrand/l/j:y	(Lcom/tencent/mm/plugin/appbrand/jsapi/c;)Z
    //   4477: ifeq +338 -> 4815
    //   4480: aload_0
    //   4481: getfield 62	com/tencent/mm/plugin/appbrand/l/a/b:ipB	Lcom/tencent/mm/plugin/appbrand/l/a/a;
    //   4484: aload_0
    //   4485: getfield 60	com/tencent/mm/plugin/appbrand/l/a/b:filename	Ljava/lang/String;
    //   4488: aload_0
    //   4489: getfield 58	com/tencent/mm/plugin/appbrand/l/a/b:uri	Ljava/lang/String;
    //   4492: ldc_w 499
    //   4495: invokeinterface 133 4 0
    //   4500: ldc 152
    //   4502: invokestatic 158	com/tencent/luggage/a/e:C	(Ljava/lang/Class;)Lcom/tencent/luggage/a/d;
    //   4505: checkcast 152	com/tencent/mm/plugin/appbrand/l/o
    //   4508: aload_0
    //   4509: getfield 56	com/tencent/mm/plugin/appbrand/l/a/b:hvw	Lcom/tencent/mm/plugin/appbrand/jsapi/c;
    //   4512: invokeinterface 164 1 0
    //   4517: aload_0
    //   4518: getfield 166	com/tencent/mm/plugin/appbrand/l/a/b:ioR	Ljava/lang/String;
    //   4521: ldc 168
    //   4523: aload_0
    //   4524: getfield 58	com/tencent/mm/plugin/appbrand/l/a/b:uri	Ljava/lang/String;
    //   4527: lconst_0
    //   4528: lload 31
    //   4530: iload 11
    //   4532: iconst_2
    //   4533: aload_0
    //   4534: invokespecial 170	com/tencent/mm/plugin/appbrand/l/a/b:aID	()I
    //   4537: invokeinterface 174 12 0
    //   4542: ldc 182
    //   4544: invokestatic 158	com/tencent/luggage/a/e:C	(Ljava/lang/Class;)Lcom/tencent/luggage/a/d;
    //   4547: checkcast 182	com/tencent/mm/plugin/appbrand/n/a
    //   4550: ldc2_w 183
    //   4553: ldc2_w 388
    //   4556: lconst_1
    //   4557: invokeinterface 188 7 0
    //   4562: ldc 182
    //   4564: invokestatic 158	com/tencent/luggage/a/e:C	(Ljava/lang/Class;)Lcom/tencent/luggage/a/d;
    //   4567: checkcast 182	com/tencent/mm/plugin/appbrand/n/a
    //   4570: ldc2_w 183
    //   4573: ldc2_w 390
    //   4576: invokestatic 68	java/lang/System:currentTimeMillis	()J
    //   4579: aload_0
    //   4580: getfield 176	com/tencent/mm/plugin/appbrand/l/a/b:ipE	J
    //   4583: lsub
    //   4584: invokeinterface 188 7 0
    //   4589: invokestatic 397	com/tencent/mm/sdk/platformtools/ah:getContext	()Landroid/content/Context;
    //   4592: invokestatic 403	com/tencent/mm/sdk/platformtools/at:getNetType	(Landroid/content/Context;)I
    //   4595: istore 11
    //   4597: iload 11
    //   4599: iconst_m1
    //   4600: if_icmpne +23 -> 4623
    //   4603: ldc 182
    //   4605: invokestatic 158	com/tencent/luggage/a/e:C	(Ljava/lang/Class;)Lcom/tencent/luggage/a/d;
    //   4608: checkcast 182	com/tencent/mm/plugin/appbrand/n/a
    //   4611: ldc2_w 183
    //   4614: ldc2_w 404
    //   4617: lconst_1
    //   4618: invokeinterface 188 7 0
    //   4623: ldc 92
    //   4625: ldc_w 407
    //   4628: iconst_1
    //   4629: anewarray 4	java/lang/Object
    //   4632: dup
    //   4633: iconst_0
    //   4634: iload 11
    //   4636: invokestatic 345	java/lang/Integer:valueOf	(I)Ljava/lang/Integer;
    //   4639: aastore
    //   4640: invokestatic 148	com/tencent/mm/sdk/platformtools/ab:i	(Ljava/lang/String;Ljava/lang/String;[Ljava/lang/Object;)V
    //   4643: aload 15
    //   4645: invokevirtual 287	java/io/FileOutputStream:close	()V
    //   4648: aload 16
    //   4650: ifnull +8 -> 4658
    //   4653: aload 16
    //   4655: invokevirtual 290	java/io/InputStream:close	()V
    //   4658: aload_0
    //   4659: invokevirtual 292	com/tencent/mm/plugin/appbrand/l/a/b:aIP	()V
    //   4662: aload_0
    //   4663: getfield 62	com/tencent/mm/plugin/appbrand/l/a/b:ipB	Lcom/tencent/mm/plugin/appbrand/l/a/a;
    //   4666: aload_0
    //   4667: getfield 294	com/tencent/mm/plugin/appbrand/l/a/b:hvr	Ljava/lang/String;
    //   4670: invokeinterface 297 2 0
    //   4675: ldc 116
    //   4677: invokestatic 75	com/tencent/matrix/trace/core/AppMethodBeat:o	(I)V
    //   4680: goto -4631 -> 49
    //   4683: astore 15
    //   4685: ldc 92
    //   4687: aload 15
    //   4689: ldc_w 465
    //   4692: iconst_2
    //   4693: anewarray 4	java/lang/Object
    //   4696: dup
    //   4697: iconst_0
    //   4698: aload_0
    //   4699: getfield 58	com/tencent/mm/plugin/appbrand/l/a/b:uri	Ljava/lang/String;
    //   4702: aastore
    //   4703: dup
    //   4704: iconst_1
    //   4705: aload_0
    //   4706: getfield 60	com/tencent/mm/plugin/appbrand/l/a/b:filename	Ljava/lang/String;
    //   4709: aastore
    //   4710: invokestatic 100	com/tencent/mm/sdk/platformtools/ab:printErrStackTrace	(Ljava/lang/String;Ljava/lang/Throwable;Ljava/lang/String;[Ljava/lang/Object;)V
    //   4713: goto -65 -> 4648
    //   4716: astore 16
    //   4718: ldc 92
    //   4720: aload 16
    //   4722: ldc_w 465
    //   4725: iconst_2
    //   4726: anewarray 4	java/lang/Object
    //   4729: dup
    //   4730: iconst_0
    //   4731: aload_0
    //   4732: getfield 58	com/tencent/mm/plugin/appbrand/l/a/b:uri	Ljava/lang/String;
    //   4735: aastore
    //   4736: dup
    //   4737: iconst_1
    //   4738: aload_0
    //   4739: getfield 60	com/tencent/mm/plugin/appbrand/l/a/b:filename	Ljava/lang/String;
    //   4742: aastore
    //   4743: invokestatic 100	com/tencent/mm/sdk/platformtools/ab:printErrStackTrace	(Ljava/lang/String;Ljava/lang/Throwable;Ljava/lang/String;[Ljava/lang/Object;)V
    //   4746: goto -88 -> 4658
    //   4749: astore 16
    //   4751: ldc 92
    //   4753: aload 16
    //   4755: ldc_w 467
    //   4758: iconst_2
    //   4759: anewarray 4	java/lang/Object
    //   4762: dup
    //   4763: iconst_0
    //   4764: aload_0
    //   4765: getfield 58	com/tencent/mm/plugin/appbrand/l/a/b:uri	Ljava/lang/String;
    //   4768: aastore
    //   4769: dup
    //   4770: iconst_1
    //   4771: aload_0
    //   4772: getfield 60	com/tencent/mm/plugin/appbrand/l/a/b:filename	Ljava/lang/String;
    //   4775: aastore
    //   4776: invokestatic 100	com/tencent/mm/sdk/platformtools/ab:printErrStackTrace	(Ljava/lang/String;Ljava/lang/Throwable;Ljava/lang/String;[Ljava/lang/Object;)V
    //   4779: goto -121 -> 4658
    //   4782: astore 16
    //   4784: ldc 92
    //   4786: aload 16
    //   4788: ldc_w 469
    //   4791: iconst_2
    //   4792: anewarray 4	java/lang/Object
    //   4795: dup
    //   4796: iconst_0
    //   4797: aload_0
    //   4798: getfield 58	com/tencent/mm/plugin/appbrand/l/a/b:uri	Ljava/lang/String;
    //   4801: aastore
    //   4802: dup
    //   4803: iconst_1
    //   4804: aload_0
    //   4805: getfield 60	com/tencent/mm/plugin/appbrand/l/a/b:filename	Ljava/lang/String;
    //   4808: aastore
    //   4809: invokestatic 100	com/tencent/mm/sdk/platformtools/ab:printErrStackTrace	(Ljava/lang/String;Ljava/lang/Throwable;Ljava/lang/String;[Ljava/lang/Object;)V
    //   4812: goto -154 -> 4658
    //   4815: aload 15
    //   4817: aload 14
    //   4819: iconst_0
    //   4820: iload 23
    //   4822: invokevirtual 503	java/io/FileOutputStream:write	([BII)V
    //   4825: lload 31
    //   4827: iload 23
    //   4829: i2l
    //   4830: ladd
    //   4831: lstore 31
    //   4833: iload 6
    //   4835: istore 23
    //   4837: lload 33
    //   4839: lconst_0
    //   4840: lcmp
    //   4841: ifle +288 -> 5129
    //   4844: iload 6
    //   4846: istore 23
    //   4848: lload 31
    //   4850: lstore 35
    //   4852: aload 15
    //   4854: astore 18
    //   4856: lload 31
    //   4858: lstore 37
    //   4860: aload 15
    //   4862: astore 12
    //   4864: lload 31
    //   4866: lstore 39
    //   4868: aload 15
    //   4870: astore 21
    //   4872: lload 31
    //   4874: lstore 41
    //   4876: aload 15
    //   4878: astore 17
    //   4880: lload 31
    //   4882: lstore 43
    //   4884: aload 15
    //   4886: astore 20
    //   4888: lload 31
    //   4890: lstore 45
    //   4892: aload 15
    //   4894: astore 19
    //   4896: aload_0
    //   4897: getfield 51	com/tencent/mm/plugin/appbrand/l/a/b:isRunning	Z
    //   4900: ifeq +229 -> 5129
    //   4903: lload 31
    //   4905: lstore 35
    //   4907: aload 15
    //   4909: astore 18
    //   4911: lload 31
    //   4913: lstore 37
    //   4915: aload 15
    //   4917: astore 12
    //   4919: lload 31
    //   4921: lstore 39
    //   4923: aload 15
    //   4925: astore 21
    //   4927: lload 31
    //   4929: lstore 41
    //   4931: aload 15
    //   4933: astore 17
    //   4935: lload 31
    //   4937: lstore 43
    //   4939: aload 15
    //   4941: astore 20
    //   4943: lload 31
    //   4945: lstore 45
    //   4947: aload 15
    //   4949: astore 19
    //   4951: ldc2_w 504
    //   4954: lload 31
    //   4956: lmul
    //   4957: lload 33
    //   4959: ldiv
    //   4960: l2i
    //   4961: istore 26
    //   4963: iload 6
    //   4965: istore 23
    //   4967: iload 6
    //   4969: iload 26
    //   4971: if_icmpeq +74 -> 5045
    //   4974: lload 31
    //   4976: lstore 35
    //   4978: aload 15
    //   4980: astore 18
    //   4982: lload 31
    //   4984: lstore 37
    //   4986: aload 15
    //   4988: astore 12
    //   4990: lload 31
    //   4992: lstore 39
    //   4994: aload 15
    //   4996: astore 21
    //   4998: lload 31
    //   5000: lstore 41
    //   5002: aload 15
    //   5004: astore 17
    //   5006: lload 31
    //   5008: lstore 43
    //   5010: aload 15
    //   5012: astore 20
    //   5014: lload 31
    //   5016: lstore 45
    //   5018: aload 15
    //   5020: astore 19
    //   5022: aload_0
    //   5023: getfield 62	com/tencent/mm/plugin/appbrand/l/a/b:ipB	Lcom/tencent/mm/plugin/appbrand/l/a/a;
    //   5026: aload_0
    //   5027: getfield 58	com/tencent/mm/plugin/appbrand/l/a/b:uri	Ljava/lang/String;
    //   5030: iload 26
    //   5032: lload 31
    //   5034: lload 33
    //   5036: invokeinterface 508 7 0
    //   5041: iload 26
    //   5043: istore 23
    //   5045: lload 31
    //   5047: lstore 35
    //   5049: aload 15
    //   5051: astore 18
    //   5053: lload 31
    //   5055: lstore 37
    //   5057: aload 15
    //   5059: astore 12
    //   5061: lload 31
    //   5063: lstore 39
    //   5065: aload 15
    //   5067: astore 21
    //   5069: lload 31
    //   5071: lstore 41
    //   5073: aload 15
    //   5075: astore 17
    //   5077: lload 31
    //   5079: lstore 43
    //   5081: aload 15
    //   5083: astore 20
    //   5085: lload 31
    //   5087: lstore 45
    //   5089: aload 15
    //   5091: astore 19
    //   5093: ldc 92
    //   5095: ldc_w 510
    //   5098: iconst_3
    //   5099: anewarray 4	java/lang/Object
    //   5102: dup
    //   5103: iconst_0
    //   5104: lload 31
    //   5106: invokestatic 515	java/lang/Long:valueOf	(J)Ljava/lang/Long;
    //   5109: aastore
    //   5110: dup
    //   5111: iconst_1
    //   5112: lload 33
    //   5114: invokestatic 515	java/lang/Long:valueOf	(J)Ljava/lang/Long;
    //   5117: aastore
    //   5118: dup
    //   5119: iconst_2
    //   5120: iload 26
    //   5122: invokestatic 345	java/lang/Integer:valueOf	(I)Ljava/lang/Integer;
    //   5125: aastore
    //   5126: invokestatic 518	com/tencent/mm/sdk/platformtools/ab:v	(Ljava/lang/String;Ljava/lang/String;[Ljava/lang/Object;)V
    //   5129: lload 31
    //   5131: lconst_0
    //   5132: lcmp
    //   5133: ifle +5693 -> 10826
    //   5136: lload 31
    //   5138: lstore 35
    //   5140: aload 15
    //   5142: astore 18
    //   5144: lload 31
    //   5146: lstore 37
    //   5148: aload 15
    //   5150: astore 12
    //   5152: lload 31
    //   5154: lstore 39
    //   5156: aload 15
    //   5158: astore 21
    //   5160: lload 31
    //   5162: lstore 41
    //   5164: aload 15
    //   5166: astore 17
    //   5168: lload 31
    //   5170: lstore 43
    //   5172: aload 15
    //   5174: astore 20
    //   5176: lload 31
    //   5178: lstore 45
    //   5180: aload 15
    //   5182: astore 19
    //   5184: aload_0
    //   5185: getfield 409	com/tencent/mm/plugin/appbrand/l/a/b:ipD	I
    //   5188: ifle +5638 -> 10826
    //   5191: lload 31
    //   5193: lstore 35
    //   5195: aload 15
    //   5197: astore 18
    //   5199: lload 31
    //   5201: lstore 37
    //   5203: aload 15
    //   5205: astore 12
    //   5207: lload 31
    //   5209: lstore 39
    //   5211: aload 15
    //   5213: astore 21
    //   5215: lload 31
    //   5217: lstore 41
    //   5219: aload 15
    //   5221: astore 17
    //   5223: lload 31
    //   5225: lstore 43
    //   5227: aload 15
    //   5229: astore 20
    //   5231: lload 31
    //   5233: lstore 45
    //   5235: aload 15
    //   5237: astore 19
    //   5239: lload 31
    //   5241: aload_0
    //   5242: getfield 409	com/tencent/mm/plugin/appbrand/l/a/b:ipD	I
    //   5245: i2l
    //   5246: ldc2_w 519
    //   5249: lmul
    //   5250: lcmp
    //   5251: iflt +5575 -> 10826
    //   5254: lload 31
    //   5256: lstore 35
    //   5258: aload 15
    //   5260: astore 18
    //   5262: lload 31
    //   5264: lstore 37
    //   5266: aload 15
    //   5268: astore 12
    //   5270: lload 31
    //   5272: lstore 39
    //   5274: aload 15
    //   5276: astore 21
    //   5278: lload 31
    //   5280: lstore 41
    //   5282: aload 15
    //   5284: astore 17
    //   5286: lload 31
    //   5288: lstore 43
    //   5290: aload 15
    //   5292: astore 20
    //   5294: lload 31
    //   5296: lstore 45
    //   5298: aload 15
    //   5300: astore 19
    //   5302: ldc 92
    //   5304: ldc_w 522
    //   5307: iconst_1
    //   5308: anewarray 4	java/lang/Object
    //   5311: dup
    //   5312: iconst_0
    //   5313: lload 31
    //   5315: invokestatic 515	java/lang/Long:valueOf	(J)Ljava/lang/Long;
    //   5318: aastore
    //   5319: invokestatic 148	com/tencent/mm/sdk/platformtools/ab:i	(Ljava/lang/String;Ljava/lang/String;[Ljava/lang/Object;)V
    //   5322: lload 31
    //   5324: lstore 35
    //   5326: aload 15
    //   5328: astore 18
    //   5330: lload 31
    //   5332: lstore 37
    //   5334: aload 15
    //   5336: astore 12
    //   5338: lload 31
    //   5340: lstore 39
    //   5342: aload 15
    //   5344: astore 21
    //   5346: lload 31
    //   5348: lstore 41
    //   5350: aload 15
    //   5352: astore 17
    //   5354: lload 31
    //   5356: lstore 43
    //   5358: aload 15
    //   5360: astore 20
    //   5362: lload 31
    //   5364: lstore 45
    //   5366: aload 15
    //   5368: astore 19
    //   5370: aload_0
    //   5371: getfield 62	com/tencent/mm/plugin/appbrand/l/a/b:ipB	Lcom/tencent/mm/plugin/appbrand/l/a/a;
    //   5374: aload_0
    //   5375: getfield 60	com/tencent/mm/plugin/appbrand/l/a/b:filename	Ljava/lang/String;
    //   5378: aload_0
    //   5379: getfield 58	com/tencent/mm/plugin/appbrand/l/a/b:uri	Ljava/lang/String;
    //   5382: ldc_w 414
    //   5385: invokeinterface 133 4 0
    //   5390: lload 31
    //   5392: lstore 35
    //   5394: aload 15
    //   5396: astore 18
    //   5398: lload 31
    //   5400: lstore 37
    //   5402: aload 15
    //   5404: astore 12
    //   5406: lload 31
    //   5408: lstore 39
    //   5410: aload 15
    //   5412: astore 21
    //   5414: lload 31
    //   5416: lstore 41
    //   5418: aload 15
    //   5420: astore 17
    //   5422: lload 31
    //   5424: lstore 43
    //   5426: aload 15
    //   5428: astore 20
    //   5430: lload 31
    //   5432: lstore 45
    //   5434: aload 15
    //   5436: astore 19
    //   5438: aload 15
    //   5440: invokestatic 526	com/tencent/mm/sdk/platformtools/bo:b	(Ljava/io/Closeable;)V
    //   5443: lload 31
    //   5445: lstore 35
    //   5447: aload 15
    //   5449: astore 18
    //   5451: lload 31
    //   5453: lstore 37
    //   5455: aload 15
    //   5457: astore 12
    //   5459: lload 31
    //   5461: lstore 39
    //   5463: aload 15
    //   5465: astore 21
    //   5467: lload 31
    //   5469: lstore 41
    //   5471: aload 15
    //   5473: astore 17
    //   5475: lload 31
    //   5477: lstore 43
    //   5479: aload 15
    //   5481: astore 20
    //   5483: lload 31
    //   5485: lstore 45
    //   5487: aload 15
    //   5489: astore 19
    //   5491: aload 16
    //   5493: invokestatic 526	com/tencent/mm/sdk/platformtools/bo:b	(Ljava/io/Closeable;)V
    //   5496: lload 31
    //   5498: lstore 35
    //   5500: aload 15
    //   5502: astore 18
    //   5504: lload 31
    //   5506: lstore 37
    //   5508: aload 15
    //   5510: astore 12
    //   5512: lload 31
    //   5514: lstore 39
    //   5516: aload 15
    //   5518: astore 21
    //   5520: lload 31
    //   5522: lstore 41
    //   5524: aload 15
    //   5526: astore 17
    //   5528: lload 31
    //   5530: lstore 43
    //   5532: aload 15
    //   5534: astore 20
    //   5536: lload 31
    //   5538: lstore 45
    //   5540: aload 15
    //   5542: astore 19
    //   5544: aload 13
    //   5546: invokevirtual 529	java/io/File:getAbsolutePath	()Ljava/lang/String;
    //   5549: invokestatic 534	com/tencent/mm/a/e:deleteFile	(Ljava/lang/String;)Z
    //   5552: pop
    //   5553: ldc 152
    //   5555: invokestatic 158	com/tencent/luggage/a/e:C	(Ljava/lang/Class;)Lcom/tencent/luggage/a/d;
    //   5558: checkcast 152	com/tencent/mm/plugin/appbrand/l/o
    //   5561: aload_0
    //   5562: getfield 56	com/tencent/mm/plugin/appbrand/l/a/b:hvw	Lcom/tencent/mm/plugin/appbrand/jsapi/c;
    //   5565: invokeinterface 164 1 0
    //   5570: aload_0
    //   5571: getfield 166	com/tencent/mm/plugin/appbrand/l/a/b:ioR	Ljava/lang/String;
    //   5574: ldc 168
    //   5576: aload_0
    //   5577: getfield 58	com/tencent/mm/plugin/appbrand/l/a/b:uri	Ljava/lang/String;
    //   5580: lconst_0
    //   5581: lload 31
    //   5583: iload 11
    //   5585: iconst_2
    //   5586: aload_0
    //   5587: invokespecial 170	com/tencent/mm/plugin/appbrand/l/a/b:aID	()I
    //   5590: invokeinterface 174 12 0
    //   5595: ldc 182
    //   5597: invokestatic 158	com/tencent/luggage/a/e:C	(Ljava/lang/Class;)Lcom/tencent/luggage/a/d;
    //   5600: checkcast 182	com/tencent/mm/plugin/appbrand/n/a
    //   5603: ldc2_w 183
    //   5606: ldc2_w 388
    //   5609: lconst_1
    //   5610: invokeinterface 188 7 0
    //   5615: ldc 182
    //   5617: invokestatic 158	com/tencent/luggage/a/e:C	(Ljava/lang/Class;)Lcom/tencent/luggage/a/d;
    //   5620: checkcast 182	com/tencent/mm/plugin/appbrand/n/a
    //   5623: ldc2_w 183
    //   5626: ldc2_w 390
    //   5629: invokestatic 68	java/lang/System:currentTimeMillis	()J
    //   5632: aload_0
    //   5633: getfield 176	com/tencent/mm/plugin/appbrand/l/a/b:ipE	J
    //   5636: lsub
    //   5637: invokeinterface 188 7 0
    //   5642: invokestatic 397	com/tencent/mm/sdk/platformtools/ah:getContext	()Landroid/content/Context;
    //   5645: invokestatic 403	com/tencent/mm/sdk/platformtools/at:getNetType	(Landroid/content/Context;)I
    //   5648: istore 11
    //   5650: iload 11
    //   5652: iconst_m1
    //   5653: if_icmpne +23 -> 5676
    //   5656: ldc 182
    //   5658: invokestatic 158	com/tencent/luggage/a/e:C	(Ljava/lang/Class;)Lcom/tencent/luggage/a/d;
    //   5661: checkcast 182	com/tencent/mm/plugin/appbrand/n/a
    //   5664: ldc2_w 183
    //   5667: ldc2_w 404
    //   5670: lconst_1
    //   5671: invokeinterface 188 7 0
    //   5676: ldc 92
    //   5678: ldc_w 407
    //   5681: iconst_1
    //   5682: anewarray 4	java/lang/Object
    //   5685: dup
    //   5686: iconst_0
    //   5687: iload 11
    //   5689: invokestatic 345	java/lang/Integer:valueOf	(I)Ljava/lang/Integer;
    //   5692: aastore
    //   5693: invokestatic 148	com/tencent/mm/sdk/platformtools/ab:i	(Ljava/lang/String;Ljava/lang/String;[Ljava/lang/Object;)V
    //   5696: aload 15
    //   5698: invokevirtual 287	java/io/FileOutputStream:close	()V
    //   5701: aload 16
    //   5703: ifnull +8 -> 5711
    //   5706: aload 16
    //   5708: invokevirtual 290	java/io/InputStream:close	()V
    //   5711: aload_0
    //   5712: invokevirtual 292	com/tencent/mm/plugin/appbrand/l/a/b:aIP	()V
    //   5715: aload_0
    //   5716: getfield 62	com/tencent/mm/plugin/appbrand/l/a/b:ipB	Lcom/tencent/mm/plugin/appbrand/l/a/a;
    //   5719: aload_0
    //   5720: getfield 294	com/tencent/mm/plugin/appbrand/l/a/b:hvr	Ljava/lang/String;
    //   5723: invokeinterface 297 2 0
    //   5728: ldc 116
    //   5730: invokestatic 75	com/tencent/matrix/trace/core/AppMethodBeat:o	(I)V
    //   5733: goto -5684 -> 49
    //   5736: astore 15
    //   5738: ldc 92
    //   5740: aload 15
    //   5742: ldc_w 465
    //   5745: iconst_2
    //   5746: anewarray 4	java/lang/Object
    //   5749: dup
    //   5750: iconst_0
    //   5751: aload_0
    //   5752: getfield 58	com/tencent/mm/plugin/appbrand/l/a/b:uri	Ljava/lang/String;
    //   5755: aastore
    //   5756: dup
    //   5757: iconst_1
    //   5758: aload_0
    //   5759: getfield 60	com/tencent/mm/plugin/appbrand/l/a/b:filename	Ljava/lang/String;
    //   5762: aastore
    //   5763: invokestatic 100	com/tencent/mm/sdk/platformtools/ab:printErrStackTrace	(Ljava/lang/String;Ljava/lang/Throwable;Ljava/lang/String;[Ljava/lang/Object;)V
    //   5766: goto -65 -> 5701
    //   5769: astore 16
    //   5771: ldc 92
    //   5773: aload 16
    //   5775: ldc_w 465
    //   5778: iconst_2
    //   5779: anewarray 4	java/lang/Object
    //   5782: dup
    //   5783: iconst_0
    //   5784: aload_0
    //   5785: getfield 58	com/tencent/mm/plugin/appbrand/l/a/b:uri	Ljava/lang/String;
    //   5788: aastore
    //   5789: dup
    //   5790: iconst_1
    //   5791: aload_0
    //   5792: getfield 60	com/tencent/mm/plugin/appbrand/l/a/b:filename	Ljava/lang/String;
    //   5795: aastore
    //   5796: invokestatic 100	com/tencent/mm/sdk/platformtools/ab:printErrStackTrace	(Ljava/lang/String;Ljava/lang/Throwable;Ljava/lang/String;[Ljava/lang/Object;)V
    //   5799: goto -88 -> 5711
    //   5802: astore 16
    //   5804: ldc 92
    //   5806: aload 16
    //   5808: ldc_w 467
    //   5811: iconst_2
    //   5812: anewarray 4	java/lang/Object
    //   5815: dup
    //   5816: iconst_0
    //   5817: aload_0
    //   5818: getfield 58	com/tencent/mm/plugin/appbrand/l/a/b:uri	Ljava/lang/String;
    //   5821: aastore
    //   5822: dup
    //   5823: iconst_1
    //   5824: aload_0
    //   5825: getfield 60	com/tencent/mm/plugin/appbrand/l/a/b:filename	Ljava/lang/String;
    //   5828: aastore
    //   5829: invokestatic 100	com/tencent/mm/sdk/platformtools/ab:printErrStackTrace	(Ljava/lang/String;Ljava/lang/Throwable;Ljava/lang/String;[Ljava/lang/Object;)V
    //   5832: goto -121 -> 5711
    //   5835: astore 16
    //   5837: ldc 92
    //   5839: aload 16
    //   5841: ldc_w 469
    //   5844: iconst_2
    //   5845: anewarray 4	java/lang/Object
    //   5848: dup
    //   5849: iconst_0
    //   5850: aload_0
    //   5851: getfield 58	com/tencent/mm/plugin/appbrand/l/a/b:uri	Ljava/lang/String;
    //   5854: aastore
    //   5855: dup
    //   5856: iconst_1
    //   5857: aload_0
    //   5858: getfield 60	com/tencent/mm/plugin/appbrand/l/a/b:filename	Ljava/lang/String;
    //   5861: aastore
    //   5862: invokestatic 100	com/tencent/mm/sdk/platformtools/ab:printErrStackTrace	(Ljava/lang/String;Ljava/lang/Throwable;Ljava/lang/String;[Ljava/lang/Object;)V
    //   5865: goto -154 -> 5711
    //   5868: aload 15
    //   5870: invokevirtual 537	java/io/FileOutputStream:flush	()V
    //   5873: lload 31
    //   5875: lstore 35
    //   5877: aload 15
    //   5879: astore 18
    //   5881: lload 31
    //   5883: lstore 37
    //   5885: aload 15
    //   5887: astore 12
    //   5889: lload 31
    //   5891: lstore 39
    //   5893: aload 15
    //   5895: astore 21
    //   5897: lload 31
    //   5899: lstore 41
    //   5901: aload 15
    //   5903: astore 17
    //   5905: lload 31
    //   5907: lstore 43
    //   5909: aload 15
    //   5911: astore 20
    //   5913: lload 31
    //   5915: lstore 45
    //   5917: aload 15
    //   5919: astore 19
    //   5921: aload_0
    //   5922: getfield 51	com/tencent/mm/plugin/appbrand/l/a/b:isRunning	Z
    //   5925: ifeq +850 -> 6775
    //   5928: lload 31
    //   5930: lstore 35
    //   5932: aload 15
    //   5934: astore 18
    //   5936: lload 31
    //   5938: lstore 37
    //   5940: aload 15
    //   5942: astore 12
    //   5944: lload 31
    //   5946: lstore 39
    //   5948: aload 15
    //   5950: astore 21
    //   5952: lload 31
    //   5954: lstore 41
    //   5956: aload 15
    //   5958: astore 17
    //   5960: lload 31
    //   5962: lstore 43
    //   5964: aload 15
    //   5966: astore 20
    //   5968: lload 31
    //   5970: lstore 45
    //   5972: aload 15
    //   5974: astore 19
    //   5976: aload_0
    //   5977: getfield 62	com/tencent/mm/plugin/appbrand/l/a/b:ipB	Lcom/tencent/mm/plugin/appbrand/l/a/a;
    //   5980: aload_0
    //   5981: getfield 60	com/tencent/mm/plugin/appbrand/l/a/b:filename	Ljava/lang/String;
    //   5984: aload 28
    //   5986: aload_0
    //   5987: getfield 58	com/tencent/mm/plugin/appbrand/l/a/b:uri	Ljava/lang/String;
    //   5990: iload 11
    //   5992: invokeinterface 370 5 0
    //   5997: lload 31
    //   5999: lstore 35
    //   6001: aload 15
    //   6003: astore 18
    //   6005: lload 31
    //   6007: lstore 37
    //   6009: aload 15
    //   6011: astore 12
    //   6013: lload 31
    //   6015: lstore 39
    //   6017: aload 15
    //   6019: astore 21
    //   6021: lload 31
    //   6023: lstore 41
    //   6025: aload 15
    //   6027: astore 17
    //   6029: lload 31
    //   6031: lstore 43
    //   6033: aload 15
    //   6035: astore 20
    //   6037: lload 31
    //   6039: lstore 45
    //   6041: aload 15
    //   6043: astore 19
    //   6045: invokestatic 68	java/lang/System:currentTimeMillis	()J
    //   6048: aload_0
    //   6049: getfield 176	com/tencent/mm/plugin/appbrand/l/a/b:ipE	J
    //   6052: lsub
    //   6053: lstore 47
    //   6055: lload 33
    //   6057: lconst_0
    //   6058: lcmp
    //   6059: ifle +10 -> 6069
    //   6062: lload 47
    //   6064: lconst_0
    //   6065: lcmp
    //   6066: ifgt +254 -> 6320
    //   6069: lload 31
    //   6071: lstore 35
    //   6073: aload 15
    //   6075: astore 18
    //   6077: lload 31
    //   6079: lstore 37
    //   6081: aload 15
    //   6083: astore 12
    //   6085: lload 31
    //   6087: lstore 39
    //   6089: aload 15
    //   6091: astore 21
    //   6093: lload 31
    //   6095: lstore 41
    //   6097: aload 15
    //   6099: astore 17
    //   6101: lload 31
    //   6103: lstore 43
    //   6105: aload 15
    //   6107: astore 20
    //   6109: lload 31
    //   6111: lstore 45
    //   6113: aload 15
    //   6115: astore 19
    //   6117: ldc 92
    //   6119: ldc_w 539
    //   6122: iconst_2
    //   6123: anewarray 4	java/lang/Object
    //   6126: dup
    //   6127: iconst_0
    //   6128: lload 33
    //   6130: invokestatic 515	java/lang/Long:valueOf	(J)Ljava/lang/Long;
    //   6133: aastore
    //   6134: dup
    //   6135: iconst_1
    //   6136: lload 47
    //   6138: invokestatic 515	java/lang/Long:valueOf	(J)Ljava/lang/Long;
    //   6141: aastore
    //   6142: invokestatic 148	com/tencent/mm/sdk/platformtools/ab:i	(Ljava/lang/String;Ljava/lang/String;[Ljava/lang/Object;)V
    //   6145: iconst_1
    //   6146: istore 6
    //   6148: ldc 92
    //   6150: ldc_w 541
    //   6153: iconst_2
    //   6154: anewarray 4	java/lang/Object
    //   6157: dup
    //   6158: iconst_0
    //   6159: aload_0
    //   6160: getfield 60	com/tencent/mm/plugin/appbrand/l/a/b:filename	Ljava/lang/String;
    //   6163: aastore
    //   6164: dup
    //   6165: iconst_1
    //   6166: aload_0
    //   6167: getfield 58	com/tencent/mm/plugin/appbrand/l/a/b:uri	Ljava/lang/String;
    //   6170: aastore
    //   6171: invokestatic 518	com/tencent/mm/sdk/platformtools/ab:v	(Ljava/lang/String;Ljava/lang/String;[Ljava/lang/Object;)V
    //   6174: aload_0
    //   6175: getfield 85	com/tencent/mm/plugin/appbrand/l/a/b:ipF	Ljava/net/HttpURLConnection;
    //   6178: invokevirtual 90	java/net/HttpURLConnection:disconnect	()V
    //   6181: iload 6
    //   6183: ifeq +665 -> 6848
    //   6186: ldc 152
    //   6188: invokestatic 158	com/tencent/luggage/a/e:C	(Ljava/lang/Class;)Lcom/tencent/luggage/a/d;
    //   6191: checkcast 152	com/tencent/mm/plugin/appbrand/l/o
    //   6194: aload_0
    //   6195: getfield 56	com/tencent/mm/plugin/appbrand/l/a/b:hvw	Lcom/tencent/mm/plugin/appbrand/jsapi/c;
    //   6198: invokeinterface 164 1 0
    //   6203: aload_0
    //   6204: getfield 166	com/tencent/mm/plugin/appbrand/l/a/b:ioR	Ljava/lang/String;
    //   6207: ldc 168
    //   6209: aload_0
    //   6210: getfield 58	com/tencent/mm/plugin/appbrand/l/a/b:uri	Ljava/lang/String;
    //   6213: lconst_0
    //   6214: lload 31
    //   6216: iload 11
    //   6218: iconst_1
    //   6219: aload_0
    //   6220: invokespecial 170	com/tencent/mm/plugin/appbrand/l/a/b:aID	()I
    //   6223: invokeinterface 174 12 0
    //   6228: ldc 182
    //   6230: invokestatic 158	com/tencent/luggage/a/e:C	(Ljava/lang/Class;)Lcom/tencent/luggage/a/d;
    //   6233: checkcast 182	com/tencent/mm/plugin/appbrand/n/a
    //   6236: ldc2_w 183
    //   6239: ldc2_w 279
    //   6242: lconst_1
    //   6243: invokeinterface 188 7 0
    //   6248: ldc 182
    //   6250: invokestatic 158	com/tencent/luggage/a/e:C	(Ljava/lang/Class;)Lcom/tencent/luggage/a/d;
    //   6253: checkcast 182	com/tencent/mm/plugin/appbrand/n/a
    //   6256: ldc2_w 183
    //   6259: ldc2_w 281
    //   6262: invokestatic 68	java/lang/System:currentTimeMillis	()J
    //   6265: aload_0
    //   6266: getfield 176	com/tencent/mm/plugin/appbrand/l/a/b:ipE	J
    //   6269: lsub
    //   6270: invokeinterface 188 7 0
    //   6275: aload 15
    //   6277: ifnull +8 -> 6285
    //   6280: aload 15
    //   6282: invokevirtual 287	java/io/FileOutputStream:close	()V
    //   6285: aload 16
    //   6287: ifnull +8 -> 6295
    //   6290: aload 16
    //   6292: invokevirtual 290	java/io/InputStream:close	()V
    //   6295: aload_0
    //   6296: invokevirtual 292	com/tencent/mm/plugin/appbrand/l/a/b:aIP	()V
    //   6299: aload_0
    //   6300: getfield 62	com/tencent/mm/plugin/appbrand/l/a/b:ipB	Lcom/tencent/mm/plugin/appbrand/l/a/a;
    //   6303: aload_0
    //   6304: getfield 294	com/tencent/mm/plugin/appbrand/l/a/b:hvr	Ljava/lang/String;
    //   6307: invokeinterface 297 2 0
    //   6312: ldc 116
    //   6314: invokestatic 75	com/tencent/matrix/trace/core/AppMethodBeat:o	(I)V
    //   6317: goto -6268 -> 49
    //   6320: bipush 34
    //   6322: istore 6
    //   6324: lload 33
    //   6326: l2d
    //   6327: lload 47
    //   6329: l2d
    //   6330: ddiv
    //   6331: ldc2_w 542
    //   6334: dmul
    //   6335: dstore 49
    //   6337: lload 31
    //   6339: lstore 35
    //   6341: aload 15
    //   6343: astore 18
    //   6345: lload 31
    //   6347: lstore 37
    //   6349: aload 15
    //   6351: astore 12
    //   6353: lload 31
    //   6355: lstore 39
    //   6357: aload 15
    //   6359: astore 21
    //   6361: lload 31
    //   6363: lstore 41
    //   6365: aload 15
    //   6367: astore 17
    //   6369: lload 31
    //   6371: lstore 43
    //   6373: aload 15
    //   6375: astore 20
    //   6377: lload 31
    //   6379: lstore 45
    //   6381: aload 15
    //   6383: astore 19
    //   6385: invokestatic 397	com/tencent/mm/sdk/platformtools/ah:getContext	()Landroid/content/Context;
    //   6388: invokestatic 547	com/tencent/mm/sdk/platformtools/at:is2G	(Landroid/content/Context;)Z
    //   6391: ifeq +192 -> 6583
    //   6394: bipush 30
    //   6396: istore 6
    //   6398: lload 31
    //   6400: lstore 35
    //   6402: aload 15
    //   6404: astore 18
    //   6406: lload 31
    //   6408: lstore 37
    //   6410: aload 15
    //   6412: astore 12
    //   6414: lload 31
    //   6416: lstore 39
    //   6418: aload 15
    //   6420: astore 21
    //   6422: lload 31
    //   6424: lstore 41
    //   6426: aload 15
    //   6428: astore 17
    //   6430: lload 31
    //   6432: lstore 43
    //   6434: aload 15
    //   6436: astore 20
    //   6438: lload 31
    //   6440: lstore 45
    //   6442: aload 15
    //   6444: astore 19
    //   6446: ldc 182
    //   6448: invokestatic 158	com/tencent/luggage/a/e:C	(Ljava/lang/Class;)Lcom/tencent/luggage/a/d;
    //   6451: checkcast 182	com/tencent/mm/plugin/appbrand/n/a
    //   6454: ldc2_w 183
    //   6457: iload 6
    //   6459: i2l
    //   6460: dload 49
    //   6462: d2l
    //   6463: invokeinterface 188 7 0
    //   6468: lload 31
    //   6470: lstore 35
    //   6472: aload 15
    //   6474: astore 18
    //   6476: lload 31
    //   6478: lstore 37
    //   6480: aload 15
    //   6482: astore 12
    //   6484: lload 31
    //   6486: lstore 39
    //   6488: aload 15
    //   6490: astore 21
    //   6492: lload 31
    //   6494: lstore 41
    //   6496: aload 15
    //   6498: astore 17
    //   6500: lload 31
    //   6502: lstore 43
    //   6504: aload 15
    //   6506: astore 20
    //   6508: lload 31
    //   6510: lstore 45
    //   6512: aload 15
    //   6514: astore 19
    //   6516: ldc 92
    //   6518: ldc_w 549
    //   6521: iconst_4
    //   6522: anewarray 4	java/lang/Object
    //   6525: dup
    //   6526: iconst_0
    //   6527: lload 33
    //   6529: invokestatic 515	java/lang/Long:valueOf	(J)Ljava/lang/Long;
    //   6532: aastore
    //   6533: dup
    //   6534: iconst_1
    //   6535: lload 47
    //   6537: invokestatic 515	java/lang/Long:valueOf	(J)Ljava/lang/Long;
    //   6540: aastore
    //   6541: dup
    //   6542: iconst_2
    //   6543: dload 49
    //   6545: invokestatic 554	java/lang/Double:valueOf	(D)Ljava/lang/Double;
    //   6548: aastore
    //   6549: dup
    //   6550: iconst_3
    //   6551: iload 6
    //   6553: invokestatic 345	java/lang/Integer:valueOf	(I)Ljava/lang/Integer;
    //   6556: aastore
    //   6557: invokestatic 148	com/tencent/mm/sdk/platformtools/ab:i	(Ljava/lang/String;Ljava/lang/String;[Ljava/lang/Object;)V
    //   6560: goto -415 -> 6145
    //   6563: astore 28
    //   6565: aload 16
    //   6567: astore 15
    //   6569: lload 35
    //   6571: lstore 31
    //   6573: iconst_0
    //   6574: istore 6
    //   6576: aload 18
    //   6578: astore 16
    //   6580: goto -5491 -> 1089
    //   6583: lload 31
    //   6585: lstore 35
    //   6587: aload 15
    //   6589: astore 18
    //   6591: lload 31
    //   6593: lstore 37
    //   6595: aload 15
    //   6597: astore 12
    //   6599: lload 31
    //   6601: lstore 39
    //   6603: aload 15
    //   6605: astore 21
    //   6607: lload 31
    //   6609: lstore 41
    //   6611: aload 15
    //   6613: astore 17
    //   6615: lload 31
    //   6617: lstore 43
    //   6619: aload 15
    //   6621: astore 20
    //   6623: lload 31
    //   6625: lstore 45
    //   6627: aload 15
    //   6629: astore 19
    //   6631: invokestatic 397	com/tencent/mm/sdk/platformtools/ah:getContext	()Landroid/content/Context;
    //   6634: invokestatic 557	com/tencent/mm/sdk/platformtools/at:is3G	(Landroid/content/Context;)Z
    //   6637: ifeq +10 -> 6647
    //   6640: bipush 31
    //   6642: istore 6
    //   6644: goto -246 -> 6398
    //   6647: lload 31
    //   6649: lstore 35
    //   6651: aload 15
    //   6653: astore 18
    //   6655: lload 31
    //   6657: lstore 37
    //   6659: aload 15
    //   6661: astore 12
    //   6663: lload 31
    //   6665: lstore 39
    //   6667: aload 15
    //   6669: astore 21
    //   6671: lload 31
    //   6673: lstore 41
    //   6675: aload 15
    //   6677: astore 17
    //   6679: lload 31
    //   6681: lstore 43
    //   6683: aload 15
    //   6685: astore 20
    //   6687: lload 31
    //   6689: lstore 45
    //   6691: aload 15
    //   6693: astore 19
    //   6695: invokestatic 397	com/tencent/mm/sdk/platformtools/ah:getContext	()Landroid/content/Context;
    //   6698: invokestatic 560	com/tencent/mm/sdk/platformtools/at:is4G	(Landroid/content/Context;)Z
    //   6701: ifeq +10 -> 6711
    //   6704: bipush 32
    //   6706: istore 6
    //   6708: goto -310 -> 6398
    //   6711: lload 31
    //   6713: lstore 35
    //   6715: aload 15
    //   6717: astore 18
    //   6719: lload 31
    //   6721: lstore 37
    //   6723: aload 15
    //   6725: astore 12
    //   6727: lload 31
    //   6729: lstore 39
    //   6731: aload 15
    //   6733: astore 21
    //   6735: lload 31
    //   6737: lstore 41
    //   6739: aload 15
    //   6741: astore 17
    //   6743: lload 31
    //   6745: lstore 43
    //   6747: aload 15
    //   6749: astore 20
    //   6751: lload 31
    //   6753: lstore 45
    //   6755: aload 15
    //   6757: astore 19
    //   6759: invokestatic 397	com/tencent/mm/sdk/platformtools/ah:getContext	()Landroid/content/Context;
    //   6762: invokestatic 563	com/tencent/mm/sdk/platformtools/at:isWifi	(Landroid/content/Context;)Z
    //   6765: ifeq -367 -> 6398
    //   6768: bipush 33
    //   6770: istore 6
    //   6772: goto -374 -> 6398
    //   6775: lload 31
    //   6777: lstore 35
    //   6779: aload 15
    //   6781: astore 18
    //   6783: lload 31
    //   6785: lstore 37
    //   6787: aload 15
    //   6789: astore 12
    //   6791: lload 31
    //   6793: lstore 39
    //   6795: aload 15
    //   6797: astore 21
    //   6799: lload 31
    //   6801: lstore 41
    //   6803: aload 15
    //   6805: astore 17
    //   6807: lload 31
    //   6809: lstore 43
    //   6811: aload 15
    //   6813: astore 20
    //   6815: lload 31
    //   6817: lstore 45
    //   6819: aload 15
    //   6821: astore 19
    //   6823: aload_0
    //   6824: getfield 62	com/tencent/mm/plugin/appbrand/l/a/b:ipB	Lcom/tencent/mm/plugin/appbrand/l/a/a;
    //   6827: aload_0
    //   6828: getfield 60	com/tencent/mm/plugin/appbrand/l/a/b:filename	Ljava/lang/String;
    //   6831: aload_0
    //   6832: getfield 58	com/tencent/mm/plugin/appbrand/l/a/b:uri	Ljava/lang/String;
    //   6835: ldc 150
    //   6837: invokeinterface 133 4 0
    //   6842: iconst_0
    //   6843: istore 6
    //   6845: goto -697 -> 6148
    //   6848: ldc 152
    //   6850: invokestatic 158	com/tencent/luggage/a/e:C	(Ljava/lang/Class;)Lcom/tencent/luggage/a/d;
    //   6853: checkcast 152	com/tencent/mm/plugin/appbrand/l/o
    //   6856: aload_0
    //   6857: getfield 56	com/tencent/mm/plugin/appbrand/l/a/b:hvw	Lcom/tencent/mm/plugin/appbrand/jsapi/c;
    //   6860: invokeinterface 164 1 0
    //   6865: aload_0
    //   6866: getfield 166	com/tencent/mm/plugin/appbrand/l/a/b:ioR	Ljava/lang/String;
    //   6869: ldc 168
    //   6871: aload_0
    //   6872: getfield 58	com/tencent/mm/plugin/appbrand/l/a/b:uri	Ljava/lang/String;
    //   6875: lconst_0
    //   6876: lload 31
    //   6878: iload 11
    //   6880: iconst_2
    //   6881: aload_0
    //   6882: invokespecial 170	com/tencent/mm/plugin/appbrand/l/a/b:aID	()I
    //   6885: invokeinterface 174 12 0
    //   6890: ldc 182
    //   6892: invokestatic 158	com/tencent/luggage/a/e:C	(Ljava/lang/Class;)Lcom/tencent/luggage/a/d;
    //   6895: checkcast 182	com/tencent/mm/plugin/appbrand/n/a
    //   6898: ldc2_w 183
    //   6901: ldc2_w 388
    //   6904: lconst_1
    //   6905: invokeinterface 188 7 0
    //   6910: ldc 182
    //   6912: invokestatic 158	com/tencent/luggage/a/e:C	(Ljava/lang/Class;)Lcom/tencent/luggage/a/d;
    //   6915: checkcast 182	com/tencent/mm/plugin/appbrand/n/a
    //   6918: ldc2_w 183
    //   6921: ldc2_w 390
    //   6924: invokestatic 68	java/lang/System:currentTimeMillis	()J
    //   6927: aload_0
    //   6928: getfield 176	com/tencent/mm/plugin/appbrand/l/a/b:ipE	J
    //   6931: lsub
    //   6932: invokeinterface 188 7 0
    //   6937: invokestatic 397	com/tencent/mm/sdk/platformtools/ah:getContext	()Landroid/content/Context;
    //   6940: invokestatic 403	com/tencent/mm/sdk/platformtools/at:getNetType	(Landroid/content/Context;)I
    //   6943: istore 11
    //   6945: iload 11
    //   6947: iconst_m1
    //   6948: if_icmpne +23 -> 6971
    //   6951: ldc 182
    //   6953: invokestatic 158	com/tencent/luggage/a/e:C	(Ljava/lang/Class;)Lcom/tencent/luggage/a/d;
    //   6956: checkcast 182	com/tencent/mm/plugin/appbrand/n/a
    //   6959: ldc2_w 183
    //   6962: ldc2_w 404
    //   6965: lconst_1
    //   6966: invokeinterface 188 7 0
    //   6971: ldc 92
    //   6973: ldc_w 407
    //   6976: iconst_1
    //   6977: anewarray 4	java/lang/Object
    //   6980: dup
    //   6981: iconst_0
    //   6982: iload 11
    //   6984: invokestatic 345	java/lang/Integer:valueOf	(I)Ljava/lang/Integer;
    //   6987: aastore
    //   6988: invokestatic 148	com/tencent/mm/sdk/platformtools/ab:i	(Ljava/lang/String;Ljava/lang/String;[Ljava/lang/Object;)V
    //   6991: goto -716 -> 6275
    //   6994: astore 15
    //   6996: ldc 92
    //   6998: aload 15
    //   7000: ldc_w 465
    //   7003: iconst_2
    //   7004: anewarray 4	java/lang/Object
    //   7007: dup
    //   7008: iconst_0
    //   7009: aload_0
    //   7010: getfield 58	com/tencent/mm/plugin/appbrand/l/a/b:uri	Ljava/lang/String;
    //   7013: aastore
    //   7014: dup
    //   7015: iconst_1
    //   7016: aload_0
    //   7017: getfield 60	com/tencent/mm/plugin/appbrand/l/a/b:filename	Ljava/lang/String;
    //   7020: aastore
    //   7021: invokestatic 100	com/tencent/mm/sdk/platformtools/ab:printErrStackTrace	(Ljava/lang/String;Ljava/lang/Throwable;Ljava/lang/String;[Ljava/lang/Object;)V
    //   7024: goto -739 -> 6285
    //   7027: astore 16
    //   7029: ldc 92
    //   7031: aload 16
    //   7033: ldc_w 465
    //   7036: iconst_2
    //   7037: anewarray 4	java/lang/Object
    //   7040: dup
    //   7041: iconst_0
    //   7042: aload_0
    //   7043: getfield 58	com/tencent/mm/plugin/appbrand/l/a/b:uri	Ljava/lang/String;
    //   7046: aastore
    //   7047: dup
    //   7048: iconst_1
    //   7049: aload_0
    //   7050: getfield 60	com/tencent/mm/plugin/appbrand/l/a/b:filename	Ljava/lang/String;
    //   7053: aastore
    //   7054: invokestatic 100	com/tencent/mm/sdk/platformtools/ab:printErrStackTrace	(Ljava/lang/String;Ljava/lang/Throwable;Ljava/lang/String;[Ljava/lang/Object;)V
    //   7057: goto -762 -> 6295
    //   7060: astore 16
    //   7062: ldc 92
    //   7064: aload 16
    //   7066: ldc_w 467
    //   7069: iconst_2
    //   7070: anewarray 4	java/lang/Object
    //   7073: dup
    //   7074: iconst_0
    //   7075: aload_0
    //   7076: getfield 58	com/tencent/mm/plugin/appbrand/l/a/b:uri	Ljava/lang/String;
    //   7079: aastore
    //   7080: dup
    //   7081: iconst_1
    //   7082: aload_0
    //   7083: getfield 60	com/tencent/mm/plugin/appbrand/l/a/b:filename	Ljava/lang/String;
    //   7086: aastore
    //   7087: invokestatic 100	com/tencent/mm/sdk/platformtools/ab:printErrStackTrace	(Ljava/lang/String;Ljava/lang/Throwable;Ljava/lang/String;[Ljava/lang/Object;)V
    //   7090: goto -795 -> 6295
    //   7093: astore 16
    //   7095: ldc 92
    //   7097: aload 16
    //   7099: ldc_w 469
    //   7102: iconst_2
    //   7103: anewarray 4	java/lang/Object
    //   7106: dup
    //   7107: iconst_0
    //   7108: aload_0
    //   7109: getfield 58	com/tencent/mm/plugin/appbrand/l/a/b:uri	Ljava/lang/String;
    //   7112: aastore
    //   7113: dup
    //   7114: iconst_1
    //   7115: aload_0
    //   7116: getfield 60	com/tencent/mm/plugin/appbrand/l/a/b:filename	Ljava/lang/String;
    //   7119: aastore
    //   7120: invokestatic 100	com/tencent/mm/sdk/platformtools/ab:printErrStackTrace	(Ljava/lang/String;Ljava/lang/Throwable;Ljava/lang/String;[Ljava/lang/Object;)V
    //   7123: goto -828 -> 6295
    //   7126: ldc 152
    //   7128: invokestatic 158	com/tencent/luggage/a/e:C	(Ljava/lang/Class;)Lcom/tencent/luggage/a/d;
    //   7131: checkcast 152	com/tencent/mm/plugin/appbrand/l/o
    //   7134: aload_0
    //   7135: getfield 56	com/tencent/mm/plugin/appbrand/l/a/b:hvw	Lcom/tencent/mm/plugin/appbrand/jsapi/c;
    //   7138: invokeinterface 164 1 0
    //   7143: aload_0
    //   7144: getfield 166	com/tencent/mm/plugin/appbrand/l/a/b:ioR	Ljava/lang/String;
    //   7147: ldc 168
    //   7149: aload_0
    //   7150: getfield 58	com/tencent/mm/plugin/appbrand/l/a/b:uri	Ljava/lang/String;
    //   7153: lconst_0
    //   7154: lload 31
    //   7156: iload 11
    //   7158: iconst_2
    //   7159: aload_0
    //   7160: invokespecial 170	com/tencent/mm/plugin/appbrand/l/a/b:aID	()I
    //   7163: invokeinterface 174 12 0
    //   7168: ldc 182
    //   7170: invokestatic 158	com/tencent/luggage/a/e:C	(Ljava/lang/Class;)Lcom/tencent/luggage/a/d;
    //   7173: checkcast 182	com/tencent/mm/plugin/appbrand/n/a
    //   7176: ldc2_w 183
    //   7179: ldc2_w 388
    //   7182: lconst_1
    //   7183: invokeinterface 188 7 0
    //   7188: ldc 182
    //   7190: invokestatic 158	com/tencent/luggage/a/e:C	(Ljava/lang/Class;)Lcom/tencent/luggage/a/d;
    //   7193: checkcast 182	com/tencent/mm/plugin/appbrand/n/a
    //   7196: ldc2_w 183
    //   7199: ldc2_w 390
    //   7202: invokestatic 68	java/lang/System:currentTimeMillis	()J
    //   7205: aload_0
    //   7206: getfield 176	com/tencent/mm/plugin/appbrand/l/a/b:ipE	J
    //   7209: lsub
    //   7210: invokeinterface 188 7 0
    //   7215: invokestatic 397	com/tencent/mm/sdk/platformtools/ah:getContext	()Landroid/content/Context;
    //   7218: invokestatic 403	com/tencent/mm/sdk/platformtools/at:getNetType	(Landroid/content/Context;)I
    //   7221: istore 11
    //   7223: iload 11
    //   7225: iconst_m1
    //   7226: if_icmpne +23 -> 7249
    //   7229: ldc 182
    //   7231: invokestatic 158	com/tencent/luggage/a/e:C	(Ljava/lang/Class;)Lcom/tencent/luggage/a/d;
    //   7234: checkcast 182	com/tencent/mm/plugin/appbrand/n/a
    //   7237: ldc2_w 183
    //   7240: ldc2_w 404
    //   7243: lconst_1
    //   7244: invokeinterface 188 7 0
    //   7249: ldc 92
    //   7251: ldc_w 407
    //   7254: iconst_1
    //   7255: anewarray 4	java/lang/Object
    //   7258: dup
    //   7259: iconst_0
    //   7260: iload 11
    //   7262: invokestatic 345	java/lang/Integer:valueOf	(I)Ljava/lang/Integer;
    //   7265: aastore
    //   7266: invokestatic 148	com/tencent/mm/sdk/platformtools/ab:i	(Ljava/lang/String;Ljava/lang/String;[Ljava/lang/Object;)V
    //   7269: goto -6020 -> 1249
    //   7272: astore 16
    //   7274: ldc 92
    //   7276: aload 16
    //   7278: ldc_w 465
    //   7281: iconst_2
    //   7282: anewarray 4	java/lang/Object
    //   7285: dup
    //   7286: iconst_0
    //   7287: aload_0
    //   7288: getfield 58	com/tencent/mm/plugin/appbrand/l/a/b:uri	Ljava/lang/String;
    //   7291: aastore
    //   7292: dup
    //   7293: iconst_1
    //   7294: aload_0
    //   7295: getfield 60	com/tencent/mm/plugin/appbrand/l/a/b:filename	Ljava/lang/String;
    //   7298: aastore
    //   7299: invokestatic 100	com/tencent/mm/sdk/platformtools/ab:printErrStackTrace	(Ljava/lang/String;Ljava/lang/Throwable;Ljava/lang/String;[Ljava/lang/Object;)V
    //   7302: goto -6043 -> 1259
    //   7305: astore 16
    //   7307: ldc 92
    //   7309: aload 16
    //   7311: ldc_w 465
    //   7314: iconst_2
    //   7315: anewarray 4	java/lang/Object
    //   7318: dup
    //   7319: iconst_0
    //   7320: aload_0
    //   7321: getfield 58	com/tencent/mm/plugin/appbrand/l/a/b:uri	Ljava/lang/String;
    //   7324: aastore
    //   7325: dup
    //   7326: iconst_1
    //   7327: aload_0
    //   7328: getfield 60	com/tencent/mm/plugin/appbrand/l/a/b:filename	Ljava/lang/String;
    //   7331: aastore
    //   7332: invokestatic 100	com/tencent/mm/sdk/platformtools/ab:printErrStackTrace	(Ljava/lang/String;Ljava/lang/Throwable;Ljava/lang/String;[Ljava/lang/Object;)V
    //   7335: goto -6066 -> 1269
    //   7338: astore 16
    //   7340: ldc 92
    //   7342: aload 16
    //   7344: ldc_w 467
    //   7347: iconst_2
    //   7348: anewarray 4	java/lang/Object
    //   7351: dup
    //   7352: iconst_0
    //   7353: aload_0
    //   7354: getfield 58	com/tencent/mm/plugin/appbrand/l/a/b:uri	Ljava/lang/String;
    //   7357: aastore
    //   7358: dup
    //   7359: iconst_1
    //   7360: aload_0
    //   7361: getfield 60	com/tencent/mm/plugin/appbrand/l/a/b:filename	Ljava/lang/String;
    //   7364: aastore
    //   7365: invokestatic 100	com/tencent/mm/sdk/platformtools/ab:printErrStackTrace	(Ljava/lang/String;Ljava/lang/Throwable;Ljava/lang/String;[Ljava/lang/Object;)V
    //   7368: goto -6099 -> 1269
    //   7371: astore 16
    //   7373: ldc 92
    //   7375: aload 16
    //   7377: ldc_w 469
    //   7380: iconst_2
    //   7381: anewarray 4	java/lang/Object
    //   7384: dup
    //   7385: iconst_0
    //   7386: aload_0
    //   7387: getfield 58	com/tencent/mm/plugin/appbrand/l/a/b:uri	Ljava/lang/String;
    //   7390: aastore
    //   7391: dup
    //   7392: iconst_1
    //   7393: aload_0
    //   7394: getfield 60	com/tencent/mm/plugin/appbrand/l/a/b:filename	Ljava/lang/String;
    //   7397: aastore
    //   7398: invokestatic 100	com/tencent/mm/sdk/platformtools/ab:printErrStackTrace	(Ljava/lang/String;Ljava/lang/Throwable;Ljava/lang/String;[Ljava/lang/Object;)V
    //   7401: goto -6132 -> 1269
    //   7404: astore 15
    //   7406: lconst_0
    //   7407: lstore 31
    //   7409: iload 23
    //   7411: istore 11
    //   7413: iload 5
    //   7415: istore 26
    //   7417: aload 21
    //   7419: astore 28
    //   7421: lload 31
    //   7423: lstore 41
    //   7425: iload 11
    //   7427: istore 23
    //   7429: aload 28
    //   7431: astore 17
    //   7433: aload 16
    //   7435: astore 21
    //   7437: iload 26
    //   7439: istore 6
    //   7441: ldc 182
    //   7443: invokestatic 158	com/tencent/luggage/a/e:C	(Ljava/lang/Class;)Lcom/tencent/luggage/a/d;
    //   7446: checkcast 182	com/tencent/mm/plugin/appbrand/n/a
    //   7449: ldc2_w 183
    //   7452: ldc2_w 564
    //   7455: lconst_1
    //   7456: invokeinterface 188 7 0
    //   7461: lload 31
    //   7463: lstore 41
    //   7465: iload 11
    //   7467: istore 23
    //   7469: aload 28
    //   7471: astore 17
    //   7473: aload 16
    //   7475: astore 21
    //   7477: iload 26
    //   7479: istore 6
    //   7481: ldc 92
    //   7483: aload 15
    //   7485: ldc_w 567
    //   7488: iconst_2
    //   7489: anewarray 4	java/lang/Object
    //   7492: dup
    //   7493: iconst_0
    //   7494: aload_0
    //   7495: getfield 58	com/tencent/mm/plugin/appbrand/l/a/b:uri	Ljava/lang/String;
    //   7498: aastore
    //   7499: dup
    //   7500: iconst_1
    //   7501: aload_0
    //   7502: getfield 60	com/tencent/mm/plugin/appbrand/l/a/b:filename	Ljava/lang/String;
    //   7505: aastore
    //   7506: invokestatic 100	com/tencent/mm/sdk/platformtools/ab:printErrStackTrace	(Ljava/lang/String;Ljava/lang/Throwable;Ljava/lang/String;[Ljava/lang/Object;)V
    //   7509: lload 31
    //   7511: lstore 41
    //   7513: iload 11
    //   7515: istore 23
    //   7517: aload 28
    //   7519: astore 17
    //   7521: aload 16
    //   7523: astore 21
    //   7525: iload 26
    //   7527: istore 6
    //   7529: aload_0
    //   7530: getfield 62	com/tencent/mm/plugin/appbrand/l/a/b:ipB	Lcom/tencent/mm/plugin/appbrand/l/a/a;
    //   7533: aload_0
    //   7534: getfield 60	com/tencent/mm/plugin/appbrand/l/a/b:filename	Ljava/lang/String;
    //   7537: aload_0
    //   7538: getfield 58	com/tencent/mm/plugin/appbrand/l/a/b:uri	Ljava/lang/String;
    //   7541: ldc_w 569
    //   7544: invokeinterface 133 4 0
    //   7549: iload 26
    //   7551: ifeq +137 -> 7688
    //   7554: ldc 152
    //   7556: invokestatic 158	com/tencent/luggage/a/e:C	(Ljava/lang/Class;)Lcom/tencent/luggage/a/d;
    //   7559: checkcast 152	com/tencent/mm/plugin/appbrand/l/o
    //   7562: aload_0
    //   7563: getfield 56	com/tencent/mm/plugin/appbrand/l/a/b:hvw	Lcom/tencent/mm/plugin/appbrand/jsapi/c;
    //   7566: invokeinterface 164 1 0
    //   7571: aload_0
    //   7572: getfield 166	com/tencent/mm/plugin/appbrand/l/a/b:ioR	Ljava/lang/String;
    //   7575: ldc 168
    //   7577: aload_0
    //   7578: getfield 58	com/tencent/mm/plugin/appbrand/l/a/b:uri	Ljava/lang/String;
    //   7581: lconst_0
    //   7582: lload 31
    //   7584: iload 11
    //   7586: iconst_1
    //   7587: aload_0
    //   7588: invokespecial 170	com/tencent/mm/plugin/appbrand/l/a/b:aID	()I
    //   7591: invokeinterface 174 12 0
    //   7596: ldc 182
    //   7598: invokestatic 158	com/tencent/luggage/a/e:C	(Ljava/lang/Class;)Lcom/tencent/luggage/a/d;
    //   7601: checkcast 182	com/tencent/mm/plugin/appbrand/n/a
    //   7604: ldc2_w 183
    //   7607: ldc2_w 279
    //   7610: lconst_1
    //   7611: invokeinterface 188 7 0
    //   7616: ldc 182
    //   7618: invokestatic 158	com/tencent/luggage/a/e:C	(Ljava/lang/Class;)Lcom/tencent/luggage/a/d;
    //   7621: checkcast 182	com/tencent/mm/plugin/appbrand/n/a
    //   7624: ldc2_w 183
    //   7627: ldc2_w 281
    //   7630: invokestatic 68	java/lang/System:currentTimeMillis	()J
    //   7633: aload_0
    //   7634: getfield 176	com/tencent/mm/plugin/appbrand/l/a/b:ipE	J
    //   7637: lsub
    //   7638: invokeinterface 188 7 0
    //   7643: aload 28
    //   7645: ifnull +8 -> 7653
    //   7648: aload 28
    //   7650: invokevirtual 287	java/io/FileOutputStream:close	()V
    //   7653: aload 16
    //   7655: ifnull +8 -> 7663
    //   7658: aload 16
    //   7660: invokevirtual 290	java/io/InputStream:close	()V
    //   7663: aload_0
    //   7664: invokevirtual 292	com/tencent/mm/plugin/appbrand/l/a/b:aIP	()V
    //   7667: aload_0
    //   7668: getfield 62	com/tencent/mm/plugin/appbrand/l/a/b:ipB	Lcom/tencent/mm/plugin/appbrand/l/a/a;
    //   7671: aload_0
    //   7672: getfield 294	com/tencent/mm/plugin/appbrand/l/a/b:hvr	Ljava/lang/String;
    //   7675: invokeinterface 297 2 0
    //   7680: ldc 116
    //   7682: invokestatic 75	com/tencent/matrix/trace/core/AppMethodBeat:o	(I)V
    //   7685: goto -7636 -> 49
    //   7688: ldc 152
    //   7690: invokestatic 158	com/tencent/luggage/a/e:C	(Ljava/lang/Class;)Lcom/tencent/luggage/a/d;
    //   7693: checkcast 152	com/tencent/mm/plugin/appbrand/l/o
    //   7696: aload_0
    //   7697: getfield 56	com/tencent/mm/plugin/appbrand/l/a/b:hvw	Lcom/tencent/mm/plugin/appbrand/jsapi/c;
    //   7700: invokeinterface 164 1 0
    //   7705: aload_0
    //   7706: getfield 166	com/tencent/mm/plugin/appbrand/l/a/b:ioR	Ljava/lang/String;
    //   7709: ldc 168
    //   7711: aload_0
    //   7712: getfield 58	com/tencent/mm/plugin/appbrand/l/a/b:uri	Ljava/lang/String;
    //   7715: lconst_0
    //   7716: lload 31
    //   7718: iload 11
    //   7720: iconst_2
    //   7721: aload_0
    //   7722: invokespecial 170	com/tencent/mm/plugin/appbrand/l/a/b:aID	()I
    //   7725: invokeinterface 174 12 0
    //   7730: ldc 182
    //   7732: invokestatic 158	com/tencent/luggage/a/e:C	(Ljava/lang/Class;)Lcom/tencent/luggage/a/d;
    //   7735: checkcast 182	com/tencent/mm/plugin/appbrand/n/a
    //   7738: ldc2_w 183
    //   7741: ldc2_w 388
    //   7744: lconst_1
    //   7745: invokeinterface 188 7 0
    //   7750: ldc 182
    //   7752: invokestatic 158	com/tencent/luggage/a/e:C	(Ljava/lang/Class;)Lcom/tencent/luggage/a/d;
    //   7755: checkcast 182	com/tencent/mm/plugin/appbrand/n/a
    //   7758: ldc2_w 183
    //   7761: ldc2_w 390
    //   7764: invokestatic 68	java/lang/System:currentTimeMillis	()J
    //   7767: aload_0
    //   7768: getfield 176	com/tencent/mm/plugin/appbrand/l/a/b:ipE	J
    //   7771: lsub
    //   7772: invokeinterface 188 7 0
    //   7777: invokestatic 397	com/tencent/mm/sdk/platformtools/ah:getContext	()Landroid/content/Context;
    //   7780: invokestatic 403	com/tencent/mm/sdk/platformtools/at:getNetType	(Landroid/content/Context;)I
    //   7783: istore 11
    //   7785: iload 11
    //   7787: iconst_m1
    //   7788: if_icmpne +23 -> 7811
    //   7791: ldc 182
    //   7793: invokestatic 158	com/tencent/luggage/a/e:C	(Ljava/lang/Class;)Lcom/tencent/luggage/a/d;
    //   7796: checkcast 182	com/tencent/mm/plugin/appbrand/n/a
    //   7799: ldc2_w 183
    //   7802: ldc2_w 404
    //   7805: lconst_1
    //   7806: invokeinterface 188 7 0
    //   7811: ldc 92
    //   7813: ldc_w 407
    //   7816: iconst_1
    //   7817: anewarray 4	java/lang/Object
    //   7820: dup
    //   7821: iconst_0
    //   7822: iload 11
    //   7824: invokestatic 345	java/lang/Integer:valueOf	(I)Ljava/lang/Integer;
    //   7827: aastore
    //   7828: invokestatic 148	com/tencent/mm/sdk/platformtools/ab:i	(Ljava/lang/String;Ljava/lang/String;[Ljava/lang/Object;)V
    //   7831: goto -188 -> 7643
    //   7834: astore 15
    //   7836: ldc 92
    //   7838: aload 15
    //   7840: ldc_w 465
    //   7843: iconst_2
    //   7844: anewarray 4	java/lang/Object
    //   7847: dup
    //   7848: iconst_0
    //   7849: aload_0
    //   7850: getfield 58	com/tencent/mm/plugin/appbrand/l/a/b:uri	Ljava/lang/String;
    //   7853: aastore
    //   7854: dup
    //   7855: iconst_1
    //   7856: aload_0
    //   7857: getfield 60	com/tencent/mm/plugin/appbrand/l/a/b:filename	Ljava/lang/String;
    //   7860: aastore
    //   7861: invokestatic 100	com/tencent/mm/sdk/platformtools/ab:printErrStackTrace	(Ljava/lang/String;Ljava/lang/Throwable;Ljava/lang/String;[Ljava/lang/Object;)V
    //   7864: goto -211 -> 7653
    //   7867: astore 16
    //   7869: ldc 92
    //   7871: aload 16
    //   7873: ldc_w 465
    //   7876: iconst_2
    //   7877: anewarray 4	java/lang/Object
    //   7880: dup
    //   7881: iconst_0
    //   7882: aload_0
    //   7883: getfield 58	com/tencent/mm/plugin/appbrand/l/a/b:uri	Ljava/lang/String;
    //   7886: aastore
    //   7887: dup
    //   7888: iconst_1
    //   7889: aload_0
    //   7890: getfield 60	com/tencent/mm/plugin/appbrand/l/a/b:filename	Ljava/lang/String;
    //   7893: aastore
    //   7894: invokestatic 100	com/tencent/mm/sdk/platformtools/ab:printErrStackTrace	(Ljava/lang/String;Ljava/lang/Throwable;Ljava/lang/String;[Ljava/lang/Object;)V
    //   7897: goto -234 -> 7663
    //   7900: astore 16
    //   7902: ldc 92
    //   7904: aload 16
    //   7906: ldc_w 467
    //   7909: iconst_2
    //   7910: anewarray 4	java/lang/Object
    //   7913: dup
    //   7914: iconst_0
    //   7915: aload_0
    //   7916: getfield 58	com/tencent/mm/plugin/appbrand/l/a/b:uri	Ljava/lang/String;
    //   7919: aastore
    //   7920: dup
    //   7921: iconst_1
    //   7922: aload_0
    //   7923: getfield 60	com/tencent/mm/plugin/appbrand/l/a/b:filename	Ljava/lang/String;
    //   7926: aastore
    //   7927: invokestatic 100	com/tencent/mm/sdk/platformtools/ab:printErrStackTrace	(Ljava/lang/String;Ljava/lang/Throwable;Ljava/lang/String;[Ljava/lang/Object;)V
    //   7930: goto -267 -> 7663
    //   7933: astore 16
    //   7935: ldc 92
    //   7937: aload 16
    //   7939: ldc_w 469
    //   7942: iconst_2
    //   7943: anewarray 4	java/lang/Object
    //   7946: dup
    //   7947: iconst_0
    //   7948: aload_0
    //   7949: getfield 58	com/tencent/mm/plugin/appbrand/l/a/b:uri	Ljava/lang/String;
    //   7952: aastore
    //   7953: dup
    //   7954: iconst_1
    //   7955: aload_0
    //   7956: getfield 60	com/tencent/mm/plugin/appbrand/l/a/b:filename	Ljava/lang/String;
    //   7959: aastore
    //   7960: invokestatic 100	com/tencent/mm/sdk/platformtools/ab:printErrStackTrace	(Ljava/lang/String;Ljava/lang/Throwable;Ljava/lang/String;[Ljava/lang/Object;)V
    //   7963: goto -300 -> 7663
    //   7966: astore 15
    //   7968: lconst_0
    //   7969: lstore 31
    //   7971: iload 24
    //   7973: istore 11
    //   7975: iload_1
    //   7976: istore 26
    //   7978: aload 12
    //   7980: astore 16
    //   7982: aload 17
    //   7984: astore 28
    //   7986: lload 31
    //   7988: lstore 41
    //   7990: iload 11
    //   7992: istore 23
    //   7994: aload 28
    //   7996: astore 17
    //   7998: aload 16
    //   8000: astore 21
    //   8002: iload 26
    //   8004: istore 6
    //   8006: ldc 182
    //   8008: invokestatic 158	com/tencent/luggage/a/e:C	(Ljava/lang/Class;)Lcom/tencent/luggage/a/d;
    //   8011: checkcast 182	com/tencent/mm/plugin/appbrand/n/a
    //   8014: ldc2_w 183
    //   8017: ldc2_w 570
    //   8020: lconst_1
    //   8021: invokeinterface 188 7 0
    //   8026: lload 31
    //   8028: lstore 41
    //   8030: iload 11
    //   8032: istore 23
    //   8034: aload 28
    //   8036: astore 17
    //   8038: aload 16
    //   8040: astore 21
    //   8042: iload 26
    //   8044: istore 6
    //   8046: ldc 92
    //   8048: aload 15
    //   8050: ldc_w 573
    //   8053: iconst_2
    //   8054: anewarray 4	java/lang/Object
    //   8057: dup
    //   8058: iconst_0
    //   8059: aload_0
    //   8060: getfield 58	com/tencent/mm/plugin/appbrand/l/a/b:uri	Ljava/lang/String;
    //   8063: aastore
    //   8064: dup
    //   8065: iconst_1
    //   8066: aload_0
    //   8067: getfield 60	com/tencent/mm/plugin/appbrand/l/a/b:filename	Ljava/lang/String;
    //   8070: aastore
    //   8071: invokestatic 100	com/tencent/mm/sdk/platformtools/ab:printErrStackTrace	(Ljava/lang/String;Ljava/lang/Throwable;Ljava/lang/String;[Ljava/lang/Object;)V
    //   8074: lload 31
    //   8076: lstore 41
    //   8078: iload 11
    //   8080: istore 23
    //   8082: aload 28
    //   8084: astore 17
    //   8086: aload 16
    //   8088: astore 21
    //   8090: iload 26
    //   8092: istore 6
    //   8094: aload_0
    //   8095: getfield 62	com/tencent/mm/plugin/appbrand/l/a/b:ipB	Lcom/tencent/mm/plugin/appbrand/l/a/a;
    //   8098: aload_0
    //   8099: getfield 60	com/tencent/mm/plugin/appbrand/l/a/b:filename	Ljava/lang/String;
    //   8102: aload_0
    //   8103: getfield 58	com/tencent/mm/plugin/appbrand/l/a/b:uri	Ljava/lang/String;
    //   8106: ldc_w 575
    //   8109: invokeinterface 133 4 0
    //   8114: iload 26
    //   8116: ifeq +137 -> 8253
    //   8119: ldc 152
    //   8121: invokestatic 158	com/tencent/luggage/a/e:C	(Ljava/lang/Class;)Lcom/tencent/luggage/a/d;
    //   8124: checkcast 152	com/tencent/mm/plugin/appbrand/l/o
    //   8127: aload_0
    //   8128: getfield 56	com/tencent/mm/plugin/appbrand/l/a/b:hvw	Lcom/tencent/mm/plugin/appbrand/jsapi/c;
    //   8131: invokeinterface 164 1 0
    //   8136: aload_0
    //   8137: getfield 166	com/tencent/mm/plugin/appbrand/l/a/b:ioR	Ljava/lang/String;
    //   8140: ldc 168
    //   8142: aload_0
    //   8143: getfield 58	com/tencent/mm/plugin/appbrand/l/a/b:uri	Ljava/lang/String;
    //   8146: lconst_0
    //   8147: lload 31
    //   8149: iload 11
    //   8151: iconst_1
    //   8152: aload_0
    //   8153: invokespecial 170	com/tencent/mm/plugin/appbrand/l/a/b:aID	()I
    //   8156: invokeinterface 174 12 0
    //   8161: ldc 182
    //   8163: invokestatic 158	com/tencent/luggage/a/e:C	(Ljava/lang/Class;)Lcom/tencent/luggage/a/d;
    //   8166: checkcast 182	com/tencent/mm/plugin/appbrand/n/a
    //   8169: ldc2_w 183
    //   8172: ldc2_w 279
    //   8175: lconst_1
    //   8176: invokeinterface 188 7 0
    //   8181: ldc 182
    //   8183: invokestatic 158	com/tencent/luggage/a/e:C	(Ljava/lang/Class;)Lcom/tencent/luggage/a/d;
    //   8186: checkcast 182	com/tencent/mm/plugin/appbrand/n/a
    //   8189: ldc2_w 183
    //   8192: ldc2_w 281
    //   8195: invokestatic 68	java/lang/System:currentTimeMillis	()J
    //   8198: aload_0
    //   8199: getfield 176	com/tencent/mm/plugin/appbrand/l/a/b:ipE	J
    //   8202: lsub
    //   8203: invokeinterface 188 7 0
    //   8208: aload 28
    //   8210: ifnull +8 -> 8218
    //   8213: aload 28
    //   8215: invokevirtual 287	java/io/FileOutputStream:close	()V
    //   8218: aload 16
    //   8220: ifnull +8 -> 8228
    //   8223: aload 16
    //   8225: invokevirtual 290	java/io/InputStream:close	()V
    //   8228: aload_0
    //   8229: invokevirtual 292	com/tencent/mm/plugin/appbrand/l/a/b:aIP	()V
    //   8232: aload_0
    //   8233: getfield 62	com/tencent/mm/plugin/appbrand/l/a/b:ipB	Lcom/tencent/mm/plugin/appbrand/l/a/a;
    //   8236: aload_0
    //   8237: getfield 294	com/tencent/mm/plugin/appbrand/l/a/b:hvr	Ljava/lang/String;
    //   8240: invokeinterface 297 2 0
    //   8245: ldc 116
    //   8247: invokestatic 75	com/tencent/matrix/trace/core/AppMethodBeat:o	(I)V
    //   8250: goto -8201 -> 49
    //   8253: ldc 152
    //   8255: invokestatic 158	com/tencent/luggage/a/e:C	(Ljava/lang/Class;)Lcom/tencent/luggage/a/d;
    //   8258: checkcast 152	com/tencent/mm/plugin/appbrand/l/o
    //   8261: aload_0
    //   8262: getfield 56	com/tencent/mm/plugin/appbrand/l/a/b:hvw	Lcom/tencent/mm/plugin/appbrand/jsapi/c;
    //   8265: invokeinterface 164 1 0
    //   8270: aload_0
    //   8271: getfield 166	com/tencent/mm/plugin/appbrand/l/a/b:ioR	Ljava/lang/String;
    //   8274: ldc 168
    //   8276: aload_0
    //   8277: getfield 58	com/tencent/mm/plugin/appbrand/l/a/b:uri	Ljava/lang/String;
    //   8280: lconst_0
    //   8281: lload 31
    //   8283: iload 11
    //   8285: iconst_2
    //   8286: aload_0
    //   8287: invokespecial 170	com/tencent/mm/plugin/appbrand/l/a/b:aID	()I
    //   8290: invokeinterface 174 12 0
    //   8295: ldc 182
    //   8297: invokestatic 158	com/tencent/luggage/a/e:C	(Ljava/lang/Class;)Lcom/tencent/luggage/a/d;
    //   8300: checkcast 182	com/tencent/mm/plugin/appbrand/n/a
    //   8303: ldc2_w 183
    //   8306: ldc2_w 388
    //   8309: lconst_1
    //   8310: invokeinterface 188 7 0
    //   8315: ldc 182
    //   8317: invokestatic 158	com/tencent/luggage/a/e:C	(Ljava/lang/Class;)Lcom/tencent/luggage/a/d;
    //   8320: checkcast 182	com/tencent/mm/plugin/appbrand/n/a
    //   8323: ldc2_w 183
    //   8326: ldc2_w 390
    //   8329: invokestatic 68	java/lang/System:currentTimeMillis	()J
    //   8332: aload_0
    //   8333: getfield 176	com/tencent/mm/plugin/appbrand/l/a/b:ipE	J
    //   8336: lsub
    //   8337: invokeinterface 188 7 0
    //   8342: invokestatic 397	com/tencent/mm/sdk/platformtools/ah:getContext	()Landroid/content/Context;
    //   8345: invokestatic 403	com/tencent/mm/sdk/platformtools/at:getNetType	(Landroid/content/Context;)I
    //   8348: istore 11
    //   8350: iload 11
    //   8352: iconst_m1
    //   8353: if_icmpne +23 -> 8376
    //   8356: ldc 182
    //   8358: invokestatic 158	com/tencent/luggage/a/e:C	(Ljava/lang/Class;)Lcom/tencent/luggage/a/d;
    //   8361: checkcast 182	com/tencent/mm/plugin/appbrand/n/a
    //   8364: ldc2_w 183
    //   8367: ldc2_w 404
    //   8370: lconst_1
    //   8371: invokeinterface 188 7 0
    //   8376: ldc 92
    //   8378: ldc_w 407
    //   8381: iconst_1
    //   8382: anewarray 4	java/lang/Object
    //   8385: dup
    //   8386: iconst_0
    //   8387: iload 11
    //   8389: invokestatic 345	java/lang/Integer:valueOf	(I)Ljava/lang/Integer;
    //   8392: aastore
    //   8393: invokestatic 148	com/tencent/mm/sdk/platformtools/ab:i	(Ljava/lang/String;Ljava/lang/String;[Ljava/lang/Object;)V
    //   8396: goto -188 -> 8208
    //   8399: astore 15
    //   8401: ldc 92
    //   8403: aload 15
    //   8405: ldc_w 465
    //   8408: iconst_2
    //   8409: anewarray 4	java/lang/Object
    //   8412: dup
    //   8413: iconst_0
    //   8414: aload_0
    //   8415: getfield 58	com/tencent/mm/plugin/appbrand/l/a/b:uri	Ljava/lang/String;
    //   8418: aastore
    //   8419: dup
    //   8420: iconst_1
    //   8421: aload_0
    //   8422: getfield 60	com/tencent/mm/plugin/appbrand/l/a/b:filename	Ljava/lang/String;
    //   8425: aastore
    //   8426: invokestatic 100	com/tencent/mm/sdk/platformtools/ab:printErrStackTrace	(Ljava/lang/String;Ljava/lang/Throwable;Ljava/lang/String;[Ljava/lang/Object;)V
    //   8429: goto -211 -> 8218
    //   8432: astore 16
    //   8434: ldc 92
    //   8436: aload 16
    //   8438: ldc_w 465
    //   8441: iconst_2
    //   8442: anewarray 4	java/lang/Object
    //   8445: dup
    //   8446: iconst_0
    //   8447: aload_0
    //   8448: getfield 58	com/tencent/mm/plugin/appbrand/l/a/b:uri	Ljava/lang/String;
    //   8451: aastore
    //   8452: dup
    //   8453: iconst_1
    //   8454: aload_0
    //   8455: getfield 60	com/tencent/mm/plugin/appbrand/l/a/b:filename	Ljava/lang/String;
    //   8458: aastore
    //   8459: invokestatic 100	com/tencent/mm/sdk/platformtools/ab:printErrStackTrace	(Ljava/lang/String;Ljava/lang/Throwable;Ljava/lang/String;[Ljava/lang/Object;)V
    //   8462: goto -234 -> 8228
    //   8465: astore 16
    //   8467: ldc 92
    //   8469: aload 16
    //   8471: ldc_w 467
    //   8474: iconst_2
    //   8475: anewarray 4	java/lang/Object
    //   8478: dup
    //   8479: iconst_0
    //   8480: aload_0
    //   8481: getfield 58	com/tencent/mm/plugin/appbrand/l/a/b:uri	Ljava/lang/String;
    //   8484: aastore
    //   8485: dup
    //   8486: iconst_1
    //   8487: aload_0
    //   8488: getfield 60	com/tencent/mm/plugin/appbrand/l/a/b:filename	Ljava/lang/String;
    //   8491: aastore
    //   8492: invokestatic 100	com/tencent/mm/sdk/platformtools/ab:printErrStackTrace	(Ljava/lang/String;Ljava/lang/Throwable;Ljava/lang/String;[Ljava/lang/Object;)V
    //   8495: goto -267 -> 8228
    //   8498: astore 16
    //   8500: ldc 92
    //   8502: aload 16
    //   8504: ldc_w 469
    //   8507: iconst_2
    //   8508: anewarray 4	java/lang/Object
    //   8511: dup
    //   8512: iconst_0
    //   8513: aload_0
    //   8514: getfield 58	com/tencent/mm/plugin/appbrand/l/a/b:uri	Ljava/lang/String;
    //   8517: aastore
    //   8518: dup
    //   8519: iconst_1
    //   8520: aload_0
    //   8521: getfield 60	com/tencent/mm/plugin/appbrand/l/a/b:filename	Ljava/lang/String;
    //   8524: aastore
    //   8525: invokestatic 100	com/tencent/mm/sdk/platformtools/ab:printErrStackTrace	(Ljava/lang/String;Ljava/lang/Throwable;Ljava/lang/String;[Ljava/lang/Object;)V
    //   8528: goto -300 -> 8228
    //   8531: astore 15
    //   8533: lconst_0
    //   8534: lstore 31
    //   8536: iload 25
    //   8538: istore 11
    //   8540: iload_2
    //   8541: istore 26
    //   8543: aload 13
    //   8545: astore 16
    //   8547: aload 18
    //   8549: astore 28
    //   8551: lload 31
    //   8553: lstore 41
    //   8555: iload 11
    //   8557: istore 23
    //   8559: aload 28
    //   8561: astore 17
    //   8563: aload 16
    //   8565: astore 21
    //   8567: iload 26
    //   8569: istore 6
    //   8571: ldc 182
    //   8573: invokestatic 158	com/tencent/luggage/a/e:C	(Ljava/lang/Class;)Lcom/tencent/luggage/a/d;
    //   8576: checkcast 182	com/tencent/mm/plugin/appbrand/n/a
    //   8579: ldc2_w 183
    //   8582: ldc2_w 576
    //   8585: lconst_1
    //   8586: invokeinterface 188 7 0
    //   8591: lload 31
    //   8593: lstore 41
    //   8595: iload 11
    //   8597: istore 23
    //   8599: aload 28
    //   8601: astore 17
    //   8603: aload 16
    //   8605: astore 21
    //   8607: iload 26
    //   8609: istore 6
    //   8611: ldc 92
    //   8613: aload 15
    //   8615: ldc_w 579
    //   8618: iconst_2
    //   8619: anewarray 4	java/lang/Object
    //   8622: dup
    //   8623: iconst_0
    //   8624: aload_0
    //   8625: getfield 58	com/tencent/mm/plugin/appbrand/l/a/b:uri	Ljava/lang/String;
    //   8628: aastore
    //   8629: dup
    //   8630: iconst_1
    //   8631: aload_0
    //   8632: getfield 60	com/tencent/mm/plugin/appbrand/l/a/b:filename	Ljava/lang/String;
    //   8635: aastore
    //   8636: invokestatic 100	com/tencent/mm/sdk/platformtools/ab:printErrStackTrace	(Ljava/lang/String;Ljava/lang/Throwable;Ljava/lang/String;[Ljava/lang/Object;)V
    //   8639: lload 31
    //   8641: lstore 41
    //   8643: iload 11
    //   8645: istore 23
    //   8647: aload 28
    //   8649: astore 17
    //   8651: aload 16
    //   8653: astore 21
    //   8655: iload 26
    //   8657: istore 6
    //   8659: aload_0
    //   8660: getfield 62	com/tencent/mm/plugin/appbrand/l/a/b:ipB	Lcom/tencent/mm/plugin/appbrand/l/a/a;
    //   8663: aload_0
    //   8664: getfield 60	com/tencent/mm/plugin/appbrand/l/a/b:filename	Ljava/lang/String;
    //   8667: aload_0
    //   8668: getfield 58	com/tencent/mm/plugin/appbrand/l/a/b:uri	Ljava/lang/String;
    //   8671: ldc_w 581
    //   8674: invokeinterface 133 4 0
    //   8679: iload 26
    //   8681: ifeq +137 -> 8818
    //   8684: ldc 152
    //   8686: invokestatic 158	com/tencent/luggage/a/e:C	(Ljava/lang/Class;)Lcom/tencent/luggage/a/d;
    //   8689: checkcast 152	com/tencent/mm/plugin/appbrand/l/o
    //   8692: aload_0
    //   8693: getfield 56	com/tencent/mm/plugin/appbrand/l/a/b:hvw	Lcom/tencent/mm/plugin/appbrand/jsapi/c;
    //   8696: invokeinterface 164 1 0
    //   8701: aload_0
    //   8702: getfield 166	com/tencent/mm/plugin/appbrand/l/a/b:ioR	Ljava/lang/String;
    //   8705: ldc 168
    //   8707: aload_0
    //   8708: getfield 58	com/tencent/mm/plugin/appbrand/l/a/b:uri	Ljava/lang/String;
    //   8711: lconst_0
    //   8712: lload 31
    //   8714: iload 11
    //   8716: iconst_1
    //   8717: aload_0
    //   8718: invokespecial 170	com/tencent/mm/plugin/appbrand/l/a/b:aID	()I
    //   8721: invokeinterface 174 12 0
    //   8726: ldc 182
    //   8728: invokestatic 158	com/tencent/luggage/a/e:C	(Ljava/lang/Class;)Lcom/tencent/luggage/a/d;
    //   8731: checkcast 182	com/tencent/mm/plugin/appbrand/n/a
    //   8734: ldc2_w 183
    //   8737: ldc2_w 279
    //   8740: lconst_1
    //   8741: invokeinterface 188 7 0
    //   8746: ldc 182
    //   8748: invokestatic 158	com/tencent/luggage/a/e:C	(Ljava/lang/Class;)Lcom/tencent/luggage/a/d;
    //   8751: checkcast 182	com/tencent/mm/plugin/appbrand/n/a
    //   8754: ldc2_w 183
    //   8757: ldc2_w 281
    //   8760: invokestatic 68	java/lang/System:currentTimeMillis	()J
    //   8763: aload_0
    //   8764: getfield 176	com/tencent/mm/plugin/appbrand/l/a/b:ipE	J
    //   8767: lsub
    //   8768: invokeinterface 188 7 0
    //   8773: aload 28
    //   8775: ifnull +8 -> 8783
    //   8778: aload 28
    //   8780: invokevirtual 287	java/io/FileOutputStream:close	()V
    //   8783: aload 16
    //   8785: ifnull +8 -> 8793
    //   8788: aload 16
    //   8790: invokevirtual 290	java/io/InputStream:close	()V
    //   8793: aload_0
    //   8794: invokevirtual 292	com/tencent/mm/plugin/appbrand/l/a/b:aIP	()V
    //   8797: aload_0
    //   8798: getfield 62	com/tencent/mm/plugin/appbrand/l/a/b:ipB	Lcom/tencent/mm/plugin/appbrand/l/a/a;
    //   8801: aload_0
    //   8802: getfield 294	com/tencent/mm/plugin/appbrand/l/a/b:hvr	Ljava/lang/String;
    //   8805: invokeinterface 297 2 0
    //   8810: ldc 116
    //   8812: invokestatic 75	com/tencent/matrix/trace/core/AppMethodBeat:o	(I)V
    //   8815: goto -8766 -> 49
    //   8818: ldc 152
    //   8820: invokestatic 158	com/tencent/luggage/a/e:C	(Ljava/lang/Class;)Lcom/tencent/luggage/a/d;
    //   8823: checkcast 152	com/tencent/mm/plugin/appbrand/l/o
    //   8826: aload_0
    //   8827: getfield 56	com/tencent/mm/plugin/appbrand/l/a/b:hvw	Lcom/tencent/mm/plugin/appbrand/jsapi/c;
    //   8830: invokeinterface 164 1 0
    //   8835: aload_0
    //   8836: getfield 166	com/tencent/mm/plugin/appbrand/l/a/b:ioR	Ljava/lang/String;
    //   8839: ldc 168
    //   8841: aload_0
    //   8842: getfield 58	com/tencent/mm/plugin/appbrand/l/a/b:uri	Ljava/lang/String;
    //   8845: lconst_0
    //   8846: lload 31
    //   8848: iload 11
    //   8850: iconst_2
    //   8851: aload_0
    //   8852: invokespecial 170	com/tencent/mm/plugin/appbrand/l/a/b:aID	()I
    //   8855: invokeinterface 174 12 0
    //   8860: ldc 182
    //   8862: invokestatic 158	com/tencent/luggage/a/e:C	(Ljava/lang/Class;)Lcom/tencent/luggage/a/d;
    //   8865: checkcast 182	com/tencent/mm/plugin/appbrand/n/a
    //   8868: ldc2_w 183
    //   8871: ldc2_w 388
    //   8874: lconst_1
    //   8875: invokeinterface 188 7 0
    //   8880: ldc 182
    //   8882: invokestatic 158	com/tencent/luggage/a/e:C	(Ljava/lang/Class;)Lcom/tencent/luggage/a/d;
    //   8885: checkcast 182	com/tencent/mm/plugin/appbrand/n/a
    //   8888: ldc2_w 183
    //   8891: ldc2_w 390
    //   8894: invokestatic 68	java/lang/System:currentTimeMillis	()J
    //   8897: aload_0
    //   8898: getfield 176	com/tencent/mm/plugin/appbrand/l/a/b:ipE	J
    //   8901: lsub
    //   8902: invokeinterface 188 7 0
    //   8907: invokestatic 397	com/tencent/mm/sdk/platformtools/ah:getContext	()Landroid/content/Context;
    //   8910: invokestatic 403	com/tencent/mm/sdk/platformtools/at:getNetType	(Landroid/content/Context;)I
    //   8913: istore 11
    //   8915: iload 11
    //   8917: iconst_m1
    //   8918: if_icmpne +23 -> 8941
    //   8921: ldc 182
    //   8923: invokestatic 158	com/tencent/luggage/a/e:C	(Ljava/lang/Class;)Lcom/tencent/luggage/a/d;
    //   8926: checkcast 182	com/tencent/mm/plugin/appbrand/n/a
    //   8929: ldc2_w 183
    //   8932: ldc2_w 404
    //   8935: lconst_1
    //   8936: invokeinterface 188 7 0
    //   8941: ldc 92
    //   8943: ldc_w 407
    //   8946: iconst_1
    //   8947: anewarray 4	java/lang/Object
    //   8950: dup
    //   8951: iconst_0
    //   8952: iload 11
    //   8954: invokestatic 345	java/lang/Integer:valueOf	(I)Ljava/lang/Integer;
    //   8957: aastore
    //   8958: invokestatic 148	com/tencent/mm/sdk/platformtools/ab:i	(Ljava/lang/String;Ljava/lang/String;[Ljava/lang/Object;)V
    //   8961: goto -188 -> 8773
    //   8964: astore 15
    //   8966: ldc 92
    //   8968: aload 15
    //   8970: ldc_w 465
    //   8973: iconst_2
    //   8974: anewarray 4	java/lang/Object
    //   8977: dup
    //   8978: iconst_0
    //   8979: aload_0
    //   8980: getfield 58	com/tencent/mm/plugin/appbrand/l/a/b:uri	Ljava/lang/String;
    //   8983: aastore
    //   8984: dup
    //   8985: iconst_1
    //   8986: aload_0
    //   8987: getfield 60	com/tencent/mm/plugin/appbrand/l/a/b:filename	Ljava/lang/String;
    //   8990: aastore
    //   8991: invokestatic 100	com/tencent/mm/sdk/platformtools/ab:printErrStackTrace	(Ljava/lang/String;Ljava/lang/Throwable;Ljava/lang/String;[Ljava/lang/Object;)V
    //   8994: goto -211 -> 8783
    //   8997: astore 16
    //   8999: ldc 92
    //   9001: aload 16
    //   9003: ldc_w 465
    //   9006: iconst_2
    //   9007: anewarray 4	java/lang/Object
    //   9010: dup
    //   9011: iconst_0
    //   9012: aload_0
    //   9013: getfield 58	com/tencent/mm/plugin/appbrand/l/a/b:uri	Ljava/lang/String;
    //   9016: aastore
    //   9017: dup
    //   9018: iconst_1
    //   9019: aload_0
    //   9020: getfield 60	com/tencent/mm/plugin/appbrand/l/a/b:filename	Ljava/lang/String;
    //   9023: aastore
    //   9024: invokestatic 100	com/tencent/mm/sdk/platformtools/ab:printErrStackTrace	(Ljava/lang/String;Ljava/lang/Throwable;Ljava/lang/String;[Ljava/lang/Object;)V
    //   9027: goto -234 -> 8793
    //   9030: astore 16
    //   9032: ldc 92
    //   9034: aload 16
    //   9036: ldc_w 467
    //   9039: iconst_2
    //   9040: anewarray 4	java/lang/Object
    //   9043: dup
    //   9044: iconst_0
    //   9045: aload_0
    //   9046: getfield 58	com/tencent/mm/plugin/appbrand/l/a/b:uri	Ljava/lang/String;
    //   9049: aastore
    //   9050: dup
    //   9051: iconst_1
    //   9052: aload_0
    //   9053: getfield 60	com/tencent/mm/plugin/appbrand/l/a/b:filename	Ljava/lang/String;
    //   9056: aastore
    //   9057: invokestatic 100	com/tencent/mm/sdk/platformtools/ab:printErrStackTrace	(Ljava/lang/String;Ljava/lang/Throwable;Ljava/lang/String;[Ljava/lang/Object;)V
    //   9060: goto -267 -> 8793
    //   9063: astore 16
    //   9065: ldc 92
    //   9067: aload 16
    //   9069: ldc_w 469
    //   9072: iconst_2
    //   9073: anewarray 4	java/lang/Object
    //   9076: dup
    //   9077: iconst_0
    //   9078: aload_0
    //   9079: getfield 58	com/tencent/mm/plugin/appbrand/l/a/b:uri	Ljava/lang/String;
    //   9082: aastore
    //   9083: dup
    //   9084: iconst_1
    //   9085: aload_0
    //   9086: getfield 60	com/tencent/mm/plugin/appbrand/l/a/b:filename	Ljava/lang/String;
    //   9089: aastore
    //   9090: invokestatic 100	com/tencent/mm/sdk/platformtools/ab:printErrStackTrace	(Ljava/lang/String;Ljava/lang/Throwable;Ljava/lang/String;[Ljava/lang/Object;)V
    //   9093: goto -300 -> 8793
    //   9096: astore 15
    //   9098: lconst_0
    //   9099: lstore 31
    //   9101: iload 26
    //   9103: istore 11
    //   9105: iload_3
    //   9106: istore 26
    //   9108: aload 14
    //   9110: astore 16
    //   9112: aload 19
    //   9114: astore 28
    //   9116: lload 31
    //   9118: lstore 41
    //   9120: iload 11
    //   9122: istore 23
    //   9124: aload 28
    //   9126: astore 17
    //   9128: aload 16
    //   9130: astore 21
    //   9132: iload 26
    //   9134: istore 6
    //   9136: ldc 182
    //   9138: invokestatic 158	com/tencent/luggage/a/e:C	(Ljava/lang/Class;)Lcom/tencent/luggage/a/d;
    //   9141: checkcast 182	com/tencent/mm/plugin/appbrand/n/a
    //   9144: ldc2_w 183
    //   9147: ldc2_w 582
    //   9150: lconst_1
    //   9151: invokeinterface 188 7 0
    //   9156: lload 31
    //   9158: lstore 41
    //   9160: iload 11
    //   9162: istore 23
    //   9164: aload 28
    //   9166: astore 17
    //   9168: aload 16
    //   9170: astore 21
    //   9172: iload 26
    //   9174: istore 6
    //   9176: ldc 92
    //   9178: aload 15
    //   9180: ldc_w 585
    //   9183: iconst_2
    //   9184: anewarray 4	java/lang/Object
    //   9187: dup
    //   9188: iconst_0
    //   9189: aload_0
    //   9190: getfield 58	com/tencent/mm/plugin/appbrand/l/a/b:uri	Ljava/lang/String;
    //   9193: aastore
    //   9194: dup
    //   9195: iconst_1
    //   9196: aload_0
    //   9197: getfield 60	com/tencent/mm/plugin/appbrand/l/a/b:filename	Ljava/lang/String;
    //   9200: aastore
    //   9201: invokestatic 100	com/tencent/mm/sdk/platformtools/ab:printErrStackTrace	(Ljava/lang/String;Ljava/lang/Throwable;Ljava/lang/String;[Ljava/lang/Object;)V
    //   9204: lload 31
    //   9206: lstore 41
    //   9208: iload 11
    //   9210: istore 23
    //   9212: aload 28
    //   9214: astore 17
    //   9216: aload 16
    //   9218: astore 21
    //   9220: iload 26
    //   9222: istore 6
    //   9224: aload_0
    //   9225: getfield 62	com/tencent/mm/plugin/appbrand/l/a/b:ipB	Lcom/tencent/mm/plugin/appbrand/l/a/a;
    //   9228: astore 12
    //   9230: lload 31
    //   9232: lstore 41
    //   9234: iload 11
    //   9236: istore 23
    //   9238: aload 28
    //   9240: astore 17
    //   9242: aload 16
    //   9244: astore 21
    //   9246: iload 26
    //   9248: istore 6
    //   9250: aload_0
    //   9251: getfield 60	com/tencent/mm/plugin/appbrand/l/a/b:filename	Ljava/lang/String;
    //   9254: astore 19
    //   9256: lload 31
    //   9258: lstore 41
    //   9260: iload 11
    //   9262: istore 23
    //   9264: aload 28
    //   9266: astore 17
    //   9268: aload 16
    //   9270: astore 21
    //   9272: iload 26
    //   9274: istore 6
    //   9276: aload_0
    //   9277: getfield 58	com/tencent/mm/plugin/appbrand/l/a/b:uri	Ljava/lang/String;
    //   9280: astore 18
    //   9282: lload 31
    //   9284: lstore 41
    //   9286: iload 11
    //   9288: istore 23
    //   9290: aload 28
    //   9292: astore 17
    //   9294: aload 16
    //   9296: astore 21
    //   9298: iload 26
    //   9300: istore 6
    //   9302: new 587	java/lang/StringBuilder
    //   9305: astore 20
    //   9307: lload 31
    //   9309: lstore 41
    //   9311: iload 11
    //   9313: istore 23
    //   9315: aload 28
    //   9317: astore 17
    //   9319: aload 16
    //   9321: astore 21
    //   9323: iload 26
    //   9325: istore 6
    //   9327: aload 20
    //   9329: invokespecial 588	java/lang/StringBuilder:<init>	()V
    //   9332: lload 31
    //   9334: lstore 41
    //   9336: iload 11
    //   9338: istore 23
    //   9340: aload 28
    //   9342: astore 17
    //   9344: aload 16
    //   9346: astore 21
    //   9348: iload 26
    //   9350: istore 6
    //   9352: aload 12
    //   9354: aload 19
    //   9356: aload 18
    //   9358: aload 20
    //   9360: aload 15
    //   9362: invokevirtual 591	java/lang/Exception:getMessage	()Ljava/lang/String;
    //   9365: invokevirtual 595	java/lang/StringBuilder:append	(Ljava/lang/String;)Ljava/lang/StringBuilder;
    //   9368: invokevirtual 596	java/lang/StringBuilder:toString	()Ljava/lang/String;
    //   9371: invokeinterface 133 4 0
    //   9376: iload 26
    //   9378: ifeq +137 -> 9515
    //   9381: ldc 152
    //   9383: invokestatic 158	com/tencent/luggage/a/e:C	(Ljava/lang/Class;)Lcom/tencent/luggage/a/d;
    //   9386: checkcast 152	com/tencent/mm/plugin/appbrand/l/o
    //   9389: aload_0
    //   9390: getfield 56	com/tencent/mm/plugin/appbrand/l/a/b:hvw	Lcom/tencent/mm/plugin/appbrand/jsapi/c;
    //   9393: invokeinterface 164 1 0
    //   9398: aload_0
    //   9399: getfield 166	com/tencent/mm/plugin/appbrand/l/a/b:ioR	Ljava/lang/String;
    //   9402: ldc 168
    //   9404: aload_0
    //   9405: getfield 58	com/tencent/mm/plugin/appbrand/l/a/b:uri	Ljava/lang/String;
    //   9408: lconst_0
    //   9409: lload 31
    //   9411: iload 11
    //   9413: iconst_1
    //   9414: aload_0
    //   9415: invokespecial 170	com/tencent/mm/plugin/appbrand/l/a/b:aID	()I
    //   9418: invokeinterface 174 12 0
    //   9423: ldc 182
    //   9425: invokestatic 158	com/tencent/luggage/a/e:C	(Ljava/lang/Class;)Lcom/tencent/luggage/a/d;
    //   9428: checkcast 182	com/tencent/mm/plugin/appbrand/n/a
    //   9431: ldc2_w 183
    //   9434: ldc2_w 279
    //   9437: lconst_1
    //   9438: invokeinterface 188 7 0
    //   9443: ldc 182
    //   9445: invokestatic 158	com/tencent/luggage/a/e:C	(Ljava/lang/Class;)Lcom/tencent/luggage/a/d;
    //   9448: checkcast 182	com/tencent/mm/plugin/appbrand/n/a
    //   9451: ldc2_w 183
    //   9454: ldc2_w 281
    //   9457: invokestatic 68	java/lang/System:currentTimeMillis	()J
    //   9460: aload_0
    //   9461: getfield 176	com/tencent/mm/plugin/appbrand/l/a/b:ipE	J
    //   9464: lsub
    //   9465: invokeinterface 188 7 0
    //   9470: aload 28
    //   9472: ifnull +8 -> 9480
    //   9475: aload 28
    //   9477: invokevirtual 287	java/io/FileOutputStream:close	()V
    //   9480: aload 16
    //   9482: ifnull +8 -> 9490
    //   9485: aload 16
    //   9487: invokevirtual 290	java/io/InputStream:close	()V
    //   9490: aload_0
    //   9491: invokevirtual 292	com/tencent/mm/plugin/appbrand/l/a/b:aIP	()V
    //   9494: aload_0
    //   9495: getfield 62	com/tencent/mm/plugin/appbrand/l/a/b:ipB	Lcom/tencent/mm/plugin/appbrand/l/a/a;
    //   9498: aload_0
    //   9499: getfield 294	com/tencent/mm/plugin/appbrand/l/a/b:hvr	Ljava/lang/String;
    //   9502: invokeinterface 297 2 0
    //   9507: ldc 116
    //   9509: invokestatic 75	com/tencent/matrix/trace/core/AppMethodBeat:o	(I)V
    //   9512: goto -9463 -> 49
    //   9515: ldc 152
    //   9517: invokestatic 158	com/tencent/luggage/a/e:C	(Ljava/lang/Class;)Lcom/tencent/luggage/a/d;
    //   9520: checkcast 152	com/tencent/mm/plugin/appbrand/l/o
    //   9523: aload_0
    //   9524: getfield 56	com/tencent/mm/plugin/appbrand/l/a/b:hvw	Lcom/tencent/mm/plugin/appbrand/jsapi/c;
    //   9527: invokeinterface 164 1 0
    //   9532: aload_0
    //   9533: getfield 166	com/tencent/mm/plugin/appbrand/l/a/b:ioR	Ljava/lang/String;
    //   9536: ldc 168
    //   9538: aload_0
    //   9539: getfield 58	com/tencent/mm/plugin/appbrand/l/a/b:uri	Ljava/lang/String;
    //   9542: lconst_0
    //   9543: lload 31
    //   9545: iload 11
    //   9547: iconst_2
    //   9548: aload_0
    //   9549: invokespecial 170	com/tencent/mm/plugin/appbrand/l/a/b:aID	()I
    //   9552: invokeinterface 174 12 0
    //   9557: ldc 182
    //   9559: invokestatic 158	com/tencent/luggage/a/e:C	(Ljava/lang/Class;)Lcom/tencent/luggage/a/d;
    //   9562: checkcast 182	com/tencent/mm/plugin/appbrand/n/a
    //   9565: ldc2_w 183
    //   9568: ldc2_w 388
    //   9571: lconst_1
    //   9572: invokeinterface 188 7 0
    //   9577: ldc 182
    //   9579: invokestatic 158	com/tencent/luggage/a/e:C	(Ljava/lang/Class;)Lcom/tencent/luggage/a/d;
    //   9582: checkcast 182	com/tencent/mm/plugin/appbrand/n/a
    //   9585: ldc2_w 183
    //   9588: ldc2_w 390
    //   9591: invokestatic 68	java/lang/System:currentTimeMillis	()J
    //   9594: aload_0
    //   9595: getfield 176	com/tencent/mm/plugin/appbrand/l/a/b:ipE	J
    //   9598: lsub
    //   9599: invokeinterface 188 7 0
    //   9604: invokestatic 397	com/tencent/mm/sdk/platformtools/ah:getContext	()Landroid/content/Context;
    //   9607: invokestatic 403	com/tencent/mm/sdk/platformtools/at:getNetType	(Landroid/content/Context;)I
    //   9610: istore 11
    //   9612: iload 11
    //   9614: iconst_m1
    //   9615: if_icmpne +23 -> 9638
    //   9618: ldc 182
    //   9620: invokestatic 158	com/tencent/luggage/a/e:C	(Ljava/lang/Class;)Lcom/tencent/luggage/a/d;
    //   9623: checkcast 182	com/tencent/mm/plugin/appbrand/n/a
    //   9626: ldc2_w 183
    //   9629: ldc2_w 404
    //   9632: lconst_1
    //   9633: invokeinterface 188 7 0
    //   9638: ldc 92
    //   9640: ldc_w 407
    //   9643: iconst_1
    //   9644: anewarray 4	java/lang/Object
    //   9647: dup
    //   9648: iconst_0
    //   9649: iload 11
    //   9651: invokestatic 345	java/lang/Integer:valueOf	(I)Ljava/lang/Integer;
    //   9654: aastore
    //   9655: invokestatic 148	com/tencent/mm/sdk/platformtools/ab:i	(Ljava/lang/String;Ljava/lang/String;[Ljava/lang/Object;)V
    //   9658: goto -188 -> 9470
    //   9661: astore 15
    //   9663: ldc 92
    //   9665: aload 15
    //   9667: ldc_w 465
    //   9670: iconst_2
    //   9671: anewarray 4	java/lang/Object
    //   9674: dup
    //   9675: iconst_0
    //   9676: aload_0
    //   9677: getfield 58	com/tencent/mm/plugin/appbrand/l/a/b:uri	Ljava/lang/String;
    //   9680: aastore
    //   9681: dup
    //   9682: iconst_1
    //   9683: aload_0
    //   9684: getfield 60	com/tencent/mm/plugin/appbrand/l/a/b:filename	Ljava/lang/String;
    //   9687: aastore
    //   9688: invokestatic 100	com/tencent/mm/sdk/platformtools/ab:printErrStackTrace	(Ljava/lang/String;Ljava/lang/Throwable;Ljava/lang/String;[Ljava/lang/Object;)V
    //   9691: goto -211 -> 9480
    //   9694: astore 16
    //   9696: ldc 92
    //   9698: aload 16
    //   9700: ldc_w 465
    //   9703: iconst_2
    //   9704: anewarray 4	java/lang/Object
    //   9707: dup
    //   9708: iconst_0
    //   9709: aload_0
    //   9710: getfield 58	com/tencent/mm/plugin/appbrand/l/a/b:uri	Ljava/lang/String;
    //   9713: aastore
    //   9714: dup
    //   9715: iconst_1
    //   9716: aload_0
    //   9717: getfield 60	com/tencent/mm/plugin/appbrand/l/a/b:filename	Ljava/lang/String;
    //   9720: aastore
    //   9721: invokestatic 100	com/tencent/mm/sdk/platformtools/ab:printErrStackTrace	(Ljava/lang/String;Ljava/lang/Throwable;Ljava/lang/String;[Ljava/lang/Object;)V
    //   9724: goto -234 -> 9490
    //   9727: astore 16
    //   9729: ldc 92
    //   9731: aload 16
    //   9733: ldc_w 467
    //   9736: iconst_2
    //   9737: anewarray 4	java/lang/Object
    //   9740: dup
    //   9741: iconst_0
    //   9742: aload_0
    //   9743: getfield 58	com/tencent/mm/plugin/appbrand/l/a/b:uri	Ljava/lang/String;
    //   9746: aastore
    //   9747: dup
    //   9748: iconst_1
    //   9749: aload_0
    //   9750: getfield 60	com/tencent/mm/plugin/appbrand/l/a/b:filename	Ljava/lang/String;
    //   9753: aastore
    //   9754: invokestatic 100	com/tencent/mm/sdk/platformtools/ab:printErrStackTrace	(Ljava/lang/String;Ljava/lang/Throwable;Ljava/lang/String;[Ljava/lang/Object;)V
    //   9757: goto -267 -> 9490
    //   9760: astore 16
    //   9762: ldc 92
    //   9764: aload 16
    //   9766: ldc_w 469
    //   9769: iconst_2
    //   9770: anewarray 4	java/lang/Object
    //   9773: dup
    //   9774: iconst_0
    //   9775: aload_0
    //   9776: getfield 58	com/tencent/mm/plugin/appbrand/l/a/b:uri	Ljava/lang/String;
    //   9779: aastore
    //   9780: dup
    //   9781: iconst_1
    //   9782: aload_0
    //   9783: getfield 60	com/tencent/mm/plugin/appbrand/l/a/b:filename	Ljava/lang/String;
    //   9786: aastore
    //   9787: invokestatic 100	com/tencent/mm/sdk/platformtools/ab:printErrStackTrace	(Ljava/lang/String;Ljava/lang/Throwable;Ljava/lang/String;[Ljava/lang/Object;)V
    //   9790: goto -300 -> 9490
    //   9793: astore 16
    //   9795: lconst_0
    //   9796: lstore 31
    //   9798: iload 27
    //   9800: istore 11
    //   9802: iload 4
    //   9804: istore 6
    //   9806: aload 20
    //   9808: astore 28
    //   9810: iload 6
    //   9812: ifeq +137 -> 9949
    //   9815: ldc 152
    //   9817: invokestatic 158	com/tencent/luggage/a/e:C	(Ljava/lang/Class;)Lcom/tencent/luggage/a/d;
    //   9820: checkcast 152	com/tencent/mm/plugin/appbrand/l/o
    //   9823: aload_0
    //   9824: getfield 56	com/tencent/mm/plugin/appbrand/l/a/b:hvw	Lcom/tencent/mm/plugin/appbrand/jsapi/c;
    //   9827: invokeinterface 164 1 0
    //   9832: aload_0
    //   9833: getfield 166	com/tencent/mm/plugin/appbrand/l/a/b:ioR	Ljava/lang/String;
    //   9836: ldc 168
    //   9838: aload_0
    //   9839: getfield 58	com/tencent/mm/plugin/appbrand/l/a/b:uri	Ljava/lang/String;
    //   9842: lconst_0
    //   9843: lload 31
    //   9845: iload 11
    //   9847: iconst_1
    //   9848: aload_0
    //   9849: invokespecial 170	com/tencent/mm/plugin/appbrand/l/a/b:aID	()I
    //   9852: invokeinterface 174 12 0
    //   9857: ldc 182
    //   9859: invokestatic 158	com/tencent/luggage/a/e:C	(Ljava/lang/Class;)Lcom/tencent/luggage/a/d;
    //   9862: checkcast 182	com/tencent/mm/plugin/appbrand/n/a
    //   9865: ldc2_w 183
    //   9868: ldc2_w 279
    //   9871: lconst_1
    //   9872: invokeinterface 188 7 0
    //   9877: ldc 182
    //   9879: invokestatic 158	com/tencent/luggage/a/e:C	(Ljava/lang/Class;)Lcom/tencent/luggage/a/d;
    //   9882: checkcast 182	com/tencent/mm/plugin/appbrand/n/a
    //   9885: ldc2_w 183
    //   9888: ldc2_w 281
    //   9891: invokestatic 68	java/lang/System:currentTimeMillis	()J
    //   9894: aload_0
    //   9895: getfield 176	com/tencent/mm/plugin/appbrand/l/a/b:ipE	J
    //   9898: lsub
    //   9899: invokeinterface 188 7 0
    //   9904: aload 28
    //   9906: ifnull +8 -> 9914
    //   9909: aload 28
    //   9911: invokevirtual 287	java/io/FileOutputStream:close	()V
    //   9914: aload 15
    //   9916: ifnull +8 -> 9924
    //   9919: aload 15
    //   9921: invokevirtual 290	java/io/InputStream:close	()V
    //   9924: aload_0
    //   9925: invokevirtual 292	com/tencent/mm/plugin/appbrand/l/a/b:aIP	()V
    //   9928: aload_0
    //   9929: getfield 62	com/tencent/mm/plugin/appbrand/l/a/b:ipB	Lcom/tencent/mm/plugin/appbrand/l/a/a;
    //   9932: aload_0
    //   9933: getfield 294	com/tencent/mm/plugin/appbrand/l/a/b:hvr	Ljava/lang/String;
    //   9936: invokeinterface 297 2 0
    //   9941: ldc 116
    //   9943: invokestatic 75	com/tencent/matrix/trace/core/AppMethodBeat:o	(I)V
    //   9946: aload 16
    //   9948: athrow
    //   9949: ldc 152
    //   9951: invokestatic 158	com/tencent/luggage/a/e:C	(Ljava/lang/Class;)Lcom/tencent/luggage/a/d;
    //   9954: checkcast 152	com/tencent/mm/plugin/appbrand/l/o
    //   9957: aload_0
    //   9958: getfield 56	com/tencent/mm/plugin/appbrand/l/a/b:hvw	Lcom/tencent/mm/plugin/appbrand/jsapi/c;
    //   9961: invokeinterface 164 1 0
    //   9966: aload_0
    //   9967: getfield 166	com/tencent/mm/plugin/appbrand/l/a/b:ioR	Ljava/lang/String;
    //   9970: ldc 168
    //   9972: aload_0
    //   9973: getfield 58	com/tencent/mm/plugin/appbrand/l/a/b:uri	Ljava/lang/String;
    //   9976: lconst_0
    //   9977: lload 31
    //   9979: iload 11
    //   9981: iconst_2
    //   9982: aload_0
    //   9983: invokespecial 170	com/tencent/mm/plugin/appbrand/l/a/b:aID	()I
    //   9986: invokeinterface 174 12 0
    //   9991: ldc 182
    //   9993: invokestatic 158	com/tencent/luggage/a/e:C	(Ljava/lang/Class;)Lcom/tencent/luggage/a/d;
    //   9996: checkcast 182	com/tencent/mm/plugin/appbrand/n/a
    //   9999: ldc2_w 183
    //   10002: ldc2_w 388
    //   10005: lconst_1
    //   10006: invokeinterface 188 7 0
    //   10011: ldc 182
    //   10013: invokestatic 158	com/tencent/luggage/a/e:C	(Ljava/lang/Class;)Lcom/tencent/luggage/a/d;
    //   10016: checkcast 182	com/tencent/mm/plugin/appbrand/n/a
    //   10019: ldc2_w 183
    //   10022: ldc2_w 390
    //   10025: invokestatic 68	java/lang/System:currentTimeMillis	()J
    //   10028: aload_0
    //   10029: getfield 176	com/tencent/mm/plugin/appbrand/l/a/b:ipE	J
    //   10032: lsub
    //   10033: invokeinterface 188 7 0
    //   10038: invokestatic 397	com/tencent/mm/sdk/platformtools/ah:getContext	()Landroid/content/Context;
    //   10041: invokestatic 403	com/tencent/mm/sdk/platformtools/at:getNetType	(Landroid/content/Context;)I
    //   10044: istore 11
    //   10046: iload 11
    //   10048: iconst_m1
    //   10049: if_icmpne +23 -> 10072
    //   10052: ldc 182
    //   10054: invokestatic 158	com/tencent/luggage/a/e:C	(Ljava/lang/Class;)Lcom/tencent/luggage/a/d;
    //   10057: checkcast 182	com/tencent/mm/plugin/appbrand/n/a
    //   10060: ldc2_w 183
    //   10063: ldc2_w 404
    //   10066: lconst_1
    //   10067: invokeinterface 188 7 0
    //   10072: ldc 92
    //   10074: ldc_w 407
    //   10077: iconst_1
    //   10078: anewarray 4	java/lang/Object
    //   10081: dup
    //   10082: iconst_0
    //   10083: iload 11
    //   10085: invokestatic 345	java/lang/Integer:valueOf	(I)Ljava/lang/Integer;
    //   10088: aastore
    //   10089: invokestatic 148	com/tencent/mm/sdk/platformtools/ab:i	(Ljava/lang/String;Ljava/lang/String;[Ljava/lang/Object;)V
    //   10092: goto -188 -> 9904
    //   10095: astore 28
    //   10097: ldc 92
    //   10099: aload 28
    //   10101: ldc_w 465
    //   10104: iconst_2
    //   10105: anewarray 4	java/lang/Object
    //   10108: dup
    //   10109: iconst_0
    //   10110: aload_0
    //   10111: getfield 58	com/tencent/mm/plugin/appbrand/l/a/b:uri	Ljava/lang/String;
    //   10114: aastore
    //   10115: dup
    //   10116: iconst_1
    //   10117: aload_0
    //   10118: getfield 60	com/tencent/mm/plugin/appbrand/l/a/b:filename	Ljava/lang/String;
    //   10121: aastore
    //   10122: invokestatic 100	com/tencent/mm/sdk/platformtools/ab:printErrStackTrace	(Ljava/lang/String;Ljava/lang/Throwable;Ljava/lang/String;[Ljava/lang/Object;)V
    //   10125: goto -211 -> 9914
    //   10128: astore 15
    //   10130: ldc 92
    //   10132: aload 15
    //   10134: ldc_w 465
    //   10137: iconst_2
    //   10138: anewarray 4	java/lang/Object
    //   10141: dup
    //   10142: iconst_0
    //   10143: aload_0
    //   10144: getfield 58	com/tencent/mm/plugin/appbrand/l/a/b:uri	Ljava/lang/String;
    //   10147: aastore
    //   10148: dup
    //   10149: iconst_1
    //   10150: aload_0
    //   10151: getfield 60	com/tencent/mm/plugin/appbrand/l/a/b:filename	Ljava/lang/String;
    //   10154: aastore
    //   10155: invokestatic 100	com/tencent/mm/sdk/platformtools/ab:printErrStackTrace	(Ljava/lang/String;Ljava/lang/Throwable;Ljava/lang/String;[Ljava/lang/Object;)V
    //   10158: goto -234 -> 9924
    //   10161: astore 15
    //   10163: ldc 92
    //   10165: aload 15
    //   10167: ldc_w 467
    //   10170: iconst_2
    //   10171: anewarray 4	java/lang/Object
    //   10174: dup
    //   10175: iconst_0
    //   10176: aload_0
    //   10177: getfield 58	com/tencent/mm/plugin/appbrand/l/a/b:uri	Ljava/lang/String;
    //   10180: aastore
    //   10181: dup
    //   10182: iconst_1
    //   10183: aload_0
    //   10184: getfield 60	com/tencent/mm/plugin/appbrand/l/a/b:filename	Ljava/lang/String;
    //   10187: aastore
    //   10188: invokestatic 100	com/tencent/mm/sdk/platformtools/ab:printErrStackTrace	(Ljava/lang/String;Ljava/lang/Throwable;Ljava/lang/String;[Ljava/lang/Object;)V
    //   10191: goto -267 -> 9924
    //   10194: astore 15
    //   10196: ldc 92
    //   10198: aload 15
    //   10200: ldc_w 469
    //   10203: iconst_2
    //   10204: anewarray 4	java/lang/Object
    //   10207: dup
    //   10208: iconst_0
    //   10209: aload_0
    //   10210: getfield 58	com/tencent/mm/plugin/appbrand/l/a/b:uri	Ljava/lang/String;
    //   10213: aastore
    //   10214: dup
    //   10215: iconst_1
    //   10216: aload_0
    //   10217: getfield 60	com/tencent/mm/plugin/appbrand/l/a/b:filename	Ljava/lang/String;
    //   10220: aastore
    //   10221: invokestatic 100	com/tencent/mm/sdk/platformtools/ab:printErrStackTrace	(Ljava/lang/String;Ljava/lang/Throwable;Ljava/lang/String;[Ljava/lang/Object;)V
    //   10224: goto -300 -> 9924
    //   10227: astore 28
    //   10229: aload 16
    //   10231: astore 15
    //   10233: lconst_0
    //   10234: lstore 31
    //   10236: aload 28
    //   10238: astore 16
    //   10240: aload 20
    //   10242: astore 28
    //   10244: iload 4
    //   10246: istore 6
    //   10248: goto -438 -> 9810
    //   10251: astore 28
    //   10253: aload 16
    //   10255: astore 21
    //   10257: lconst_0
    //   10258: lstore 31
    //   10260: aload 28
    //   10262: astore 16
    //   10264: aload 15
    //   10266: astore 28
    //   10268: aload 21
    //   10270: astore 15
    //   10272: iload 4
    //   10274: istore 6
    //   10276: goto -466 -> 9810
    //   10279: astore 28
    //   10281: aload 15
    //   10283: astore 21
    //   10285: aload 16
    //   10287: astore 15
    //   10289: aload 28
    //   10291: astore 16
    //   10293: aload 21
    //   10295: astore 28
    //   10297: iload 4
    //   10299: istore 6
    //   10301: goto -491 -> 9810
    //   10304: astore 21
    //   10306: aload 12
    //   10308: astore 28
    //   10310: aload 16
    //   10312: astore 15
    //   10314: lload 37
    //   10316: lstore 31
    //   10318: aload 21
    //   10320: astore 16
    //   10322: iload 4
    //   10324: istore 6
    //   10326: goto -516 -> 9810
    //   10329: astore 28
    //   10331: aload 16
    //   10333: astore 21
    //   10335: aload 28
    //   10337: astore 16
    //   10339: aload 15
    //   10341: astore 28
    //   10343: aload 21
    //   10345: astore 15
    //   10347: goto -537 -> 9810
    //   10350: astore 28
    //   10352: aload 16
    //   10354: astore 21
    //   10356: aload 28
    //   10358: astore 16
    //   10360: aload 21
    //   10362: astore 28
    //   10364: goto -554 -> 9810
    //   10367: astore 16
    //   10369: lload 41
    //   10371: lstore 31
    //   10373: iload 23
    //   10375: istore 11
    //   10377: aload 17
    //   10379: astore 28
    //   10381: aload 21
    //   10383: astore 15
    //   10385: goto -575 -> 9810
    //   10388: astore 15
    //   10390: lconst_0
    //   10391: lstore 31
    //   10393: aload 19
    //   10395: astore 28
    //   10397: iload_3
    //   10398: istore 26
    //   10400: goto -1284 -> 9116
    //   10403: astore 28
    //   10405: aload 15
    //   10407: astore 21
    //   10409: lconst_0
    //   10410: lstore 31
    //   10412: aload 28
    //   10414: astore 15
    //   10416: aload 21
    //   10418: astore 28
    //   10420: iload_3
    //   10421: istore 26
    //   10423: goto -1307 -> 9116
    //   10426: astore 28
    //   10428: aload 15
    //   10430: astore 21
    //   10432: aload 28
    //   10434: astore 15
    //   10436: aload 21
    //   10438: astore 28
    //   10440: iload_3
    //   10441: istore 26
    //   10443: goto -1327 -> 9116
    //   10446: astore 15
    //   10448: aload 21
    //   10450: astore 28
    //   10452: lload 39
    //   10454: lstore 31
    //   10456: iload_3
    //   10457: istore 26
    //   10459: goto -1343 -> 9116
    //   10462: astore 21
    //   10464: aload 15
    //   10466: astore 28
    //   10468: aload 21
    //   10470: astore 15
    //   10472: iload 6
    //   10474: istore 26
    //   10476: goto -1360 -> 9116
    //   10479: astore 15
    //   10481: lconst_0
    //   10482: lstore 31
    //   10484: aload 18
    //   10486: astore 28
    //   10488: iload_2
    //   10489: istore 26
    //   10491: goto -1940 -> 8551
    //   10494: astore 28
    //   10496: aload 15
    //   10498: astore 21
    //   10500: lconst_0
    //   10501: lstore 31
    //   10503: aload 28
    //   10505: astore 15
    //   10507: aload 21
    //   10509: astore 28
    //   10511: iload_2
    //   10512: istore 26
    //   10514: goto -1963 -> 8551
    //   10517: astore 21
    //   10519: aload 15
    //   10521: astore 28
    //   10523: aload 21
    //   10525: astore 15
    //   10527: iload_2
    //   10528: istore 26
    //   10530: goto -1979 -> 8551
    //   10533: astore 15
    //   10535: aload 17
    //   10537: astore 28
    //   10539: lload 41
    //   10541: lstore 31
    //   10543: iload_2
    //   10544: istore 26
    //   10546: goto -1995 -> 8551
    //   10549: astore 28
    //   10551: aload 15
    //   10553: astore 21
    //   10555: aload 28
    //   10557: astore 15
    //   10559: aload 21
    //   10561: astore 28
    //   10563: iload 6
    //   10565: istore 26
    //   10567: goto -2016 -> 8551
    //   10570: astore 15
    //   10572: lconst_0
    //   10573: lstore 31
    //   10575: aload 17
    //   10577: astore 28
    //   10579: iload_1
    //   10580: istore 26
    //   10582: goto -2596 -> 7986
    //   10585: astore 21
    //   10587: aload 15
    //   10589: astore 28
    //   10591: lconst_0
    //   10592: lstore 31
    //   10594: aload 21
    //   10596: astore 15
    //   10598: iload_1
    //   10599: istore 26
    //   10601: goto -2615 -> 7986
    //   10604: astore 28
    //   10606: aload 15
    //   10608: astore 21
    //   10610: aload 28
    //   10612: astore 15
    //   10614: aload 21
    //   10616: astore 28
    //   10618: iload_1
    //   10619: istore 26
    //   10621: goto -2635 -> 7986
    //   10624: astore 15
    //   10626: aload 20
    //   10628: astore 28
    //   10630: lload 43
    //   10632: lstore 31
    //   10634: iload_1
    //   10635: istore 26
    //   10637: goto -2651 -> 7986
    //   10640: astore 21
    //   10642: aload 15
    //   10644: astore 28
    //   10646: aload 21
    //   10648: astore 15
    //   10650: iload 6
    //   10652: istore 26
    //   10654: goto -2668 -> 7986
    //   10657: astore 15
    //   10659: lconst_0
    //   10660: lstore 31
    //   10662: aload 21
    //   10664: astore 28
    //   10666: iload 5
    //   10668: istore 26
    //   10670: goto -3249 -> 7421
    //   10673: astore 21
    //   10675: aload 15
    //   10677: astore 28
    //   10679: lconst_0
    //   10680: lstore 31
    //   10682: aload 21
    //   10684: astore 15
    //   10686: iload 5
    //   10688: istore 26
    //   10690: goto -3269 -> 7421
    //   10693: astore 21
    //   10695: aload 15
    //   10697: astore 28
    //   10699: aload 21
    //   10701: astore 15
    //   10703: iload 5
    //   10705: istore 26
    //   10707: goto -3286 -> 7421
    //   10710: astore 15
    //   10712: aload 19
    //   10714: astore 28
    //   10716: lload 45
    //   10718: lstore 31
    //   10720: iload 5
    //   10722: istore 26
    //   10724: goto -3303 -> 7421
    //   10727: astore 21
    //   10729: aload 15
    //   10731: astore 28
    //   10733: aload 21
    //   10735: astore 15
    //   10737: iload 6
    //   10739: istore 26
    //   10741: goto -3320 -> 7421
    //   10744: astore 28
    //   10746: aconst_null
    //   10747: astore 21
    //   10749: aload 16
    //   10751: astore 15
    //   10753: lconst_0
    //   10754: lstore 31
    //   10756: iconst_0
    //   10757: istore 6
    //   10759: aload 21
    //   10761: astore 16
    //   10763: goto -9674 -> 1089
    //   10766: astore 28
    //   10768: aload 16
    //   10770: astore 21
    //   10772: lconst_0
    //   10773: lstore 31
    //   10775: iconst_0
    //   10776: istore 6
    //   10778: aload 15
    //   10780: astore 16
    //   10782: aload 21
    //   10784: astore 15
    //   10786: goto -9697 -> 1089
    //   10789: astore 28
    //   10791: aload 16
    //   10793: astore 21
    //   10795: iconst_0
    //   10796: istore 6
    //   10798: aload 15
    //   10800: astore 16
    //   10802: aload 21
    //   10804: astore 15
    //   10806: goto -9717 -> 1089
    //   10809: astore 28
    //   10811: aload 15
    //   10813: astore 21
    //   10815: aload 16
    //   10817: astore 15
    //   10819: aload 21
    //   10821: astore 16
    //   10823: goto -9734 -> 1089
    //   10826: iload 23
    //   10828: istore 6
    //   10830: goto -6382 -> 4448
    //   10833: aconst_null
    //   10834: astore 15
    //   10836: lconst_0
    //   10837: lstore 31
    //   10839: goto -4966 -> 5873
    //
    // Exception table:
    //   from	to	target	type
    //   298	316	1071	java/io/UnsupportedEncodingException
    //   340	345	1071	java/io/UnsupportedEncodingException
    //   369	378	1071	java/io/UnsupportedEncodingException
    //   402	427	1071	java/io/UnsupportedEncodingException
    //   451	463	1071	java/io/UnsupportedEncodingException
    //   487	497	1071	java/io/UnsupportedEncodingException
    //   521	528	1071	java/io/UnsupportedEncodingException
    //   552	569	1071	java/io/UnsupportedEncodingException
    //   593	604	1071	java/io/UnsupportedEncodingException
    //   628	636	1071	java/io/UnsupportedEncodingException
    //   660	671	1071	java/io/UnsupportedEncodingException
    //   695	706	1071	java/io/UnsupportedEncodingException
    //   730	738	1071	java/io/UnsupportedEncodingException
    //   762	773	1071	java/io/UnsupportedEncodingException
    //   797	804	1071	java/io/UnsupportedEncodingException
    //   828	844	1071	java/io/UnsupportedEncodingException
    //   868	884	1071	java/io/UnsupportedEncodingException
    //   908	918	1071	java/io/UnsupportedEncodingException
    //   942	954	1071	java/io/UnsupportedEncodingException
    //   978	1005	1071	java/io/UnsupportedEncodingException
    //   1029	1068	1071	java/io/UnsupportedEncodingException
    //   1318	1332	1071	java/io/UnsupportedEncodingException
    //   1356	1365	1071	java/io/UnsupportedEncodingException
    //   1389	1400	1071	java/io/UnsupportedEncodingException
    //   1424	1434	1071	java/io/UnsupportedEncodingException
    //   1458	1470	1071	java/io/UnsupportedEncodingException
    //   1494	1501	1071	java/io/UnsupportedEncodingException
    //   1525	1532	1071	java/io/UnsupportedEncodingException
    //   1561	1568	1071	java/io/UnsupportedEncodingException
    //   1592	1601	1071	java/io/UnsupportedEncodingException
    //   1632	1653	1071	java/io/UnsupportedEncodingException
    //   1677	1686	1071	java/io/UnsupportedEncodingException
    //   1733	1753	1071	java/io/UnsupportedEncodingException
    //   1777	1805	1071	java/io/UnsupportedEncodingException
    //   1829	1840	1071	java/io/UnsupportedEncodingException
    //   1872	1906	1071	java/io/UnsupportedEncodingException
    //   1930	1938	1071	java/io/UnsupportedEncodingException
    //   1962	1971	1071	java/io/UnsupportedEncodingException
    //   1995	2003	1071	java/io/UnsupportedEncodingException
    //   2027	2033	1071	java/io/UnsupportedEncodingException
    //   2057	2065	1071	java/io/UnsupportedEncodingException
    //   2094	2114	1071	java/io/UnsupportedEncodingException
    //   2138	2159	1071	java/io/UnsupportedEncodingException
    //   2296	2310	1071	java/io/UnsupportedEncodingException
    //   2334	2341	1071	java/io/UnsupportedEncodingException
    //   2365	2373	1071	java/io/UnsupportedEncodingException
    //   2400	2407	1071	java/io/UnsupportedEncodingException
    //   2563	2597	1071	java/io/UnsupportedEncodingException
    //   2621	2627	1071	java/io/UnsupportedEncodingException
    //   2651	2655	1071	java/io/UnsupportedEncodingException
    //   2846	2855	1071	java/io/UnsupportedEncodingException
    //   2884	2891	1071	java/io/UnsupportedEncodingException
    //   2915	2928	1071	java/io/UnsupportedEncodingException
    //   2952	2972	1071	java/io/UnsupportedEncodingException
    //   2996	3016	1071	java/io/UnsupportedEncodingException
    //   3203	3218	1071	java/io/UnsupportedEncodingException
    //   3238	3243	1071	java/io/UnsupportedEncodingException
    //   3263	3275	1071	java/io/UnsupportedEncodingException
    //   3564	3580	1071	java/io/UnsupportedEncodingException
    //   3600	3609	1071	java/io/UnsupportedEncodingException
    //   3629	3634	1071	java/io/UnsupportedEncodingException
    //   3654	3660	1071	java/io/UnsupportedEncodingException
    //   3680	3693	1071	java/io/UnsupportedEncodingException
    //   3726	3740	1071	java/io/UnsupportedEncodingException
    //   3760	3775	1071	java/io/UnsupportedEncodingException
    //   3795	3800	1071	java/io/UnsupportedEncodingException
    //   3820	3832	1071	java/io/UnsupportedEncodingException
    //   3865	3879	1071	java/io/UnsupportedEncodingException
    //   3905	3914	1071	java/io/UnsupportedEncodingException
    //   3941	3950	1071	java/io/UnsupportedEncodingException
    //   3203	3218	3700	java/lang/Exception
    //   3238	3243	3700	java/lang/Exception
    //   3263	3275	3700	java/lang/Exception
    //   3564	3580	3700	java/lang/Exception
    //   3600	3609	3700	java/lang/Exception
    //   3629	3634	3700	java/lang/Exception
    //   3654	3660	3700	java/lang/Exception
    //   3680	3693	3700	java/lang/Exception
    //   3905	3914	3700	java/lang/Exception
    //   3760	3775	3839	java/lang/Exception
    //   3795	3800	3839	java/lang/Exception
    //   3820	3832	3839	java/lang/Exception
    //   3941	3950	3839	java/lang/Exception
    //   3514	3519	3957	java/io/IOException
    //   3514	3519	3990	java/lang/ArrayIndexOutOfBoundsException
    //   3514	3519	4023	java/lang/Throwable
    //   4283	4288	4313	java/io/IOException
    //   4283	4288	4346	java/lang/ArrayIndexOutOfBoundsException
    //   4283	4288	4379	java/lang/Throwable
    //   4643	4648	4683	java/io/IOException
    //   4653	4658	4716	java/io/IOException
    //   4653	4658	4749	java/lang/ArrayIndexOutOfBoundsException
    //   4653	4658	4782	java/lang/Throwable
    //   5696	5701	5736	java/io/IOException
    //   5706	5711	5769	java/io/IOException
    //   5706	5711	5802	java/lang/ArrayIndexOutOfBoundsException
    //   5706	5711	5835	java/lang/Throwable
    //   4896	4903	6563	java/io/UnsupportedEncodingException
    //   4951	4963	6563	java/io/UnsupportedEncodingException
    //   5022	5041	6563	java/io/UnsupportedEncodingException
    //   5093	5129	6563	java/io/UnsupportedEncodingException
    //   5184	5191	6563	java/io/UnsupportedEncodingException
    //   5239	5254	6563	java/io/UnsupportedEncodingException
    //   5302	5322	6563	java/io/UnsupportedEncodingException
    //   5370	5390	6563	java/io/UnsupportedEncodingException
    //   5438	5443	6563	java/io/UnsupportedEncodingException
    //   5491	5496	6563	java/io/UnsupportedEncodingException
    //   5544	5553	6563	java/io/UnsupportedEncodingException
    //   5921	5928	6563	java/io/UnsupportedEncodingException
    //   5976	5997	6563	java/io/UnsupportedEncodingException
    //   6045	6055	6563	java/io/UnsupportedEncodingException
    //   6117	6145	6563	java/io/UnsupportedEncodingException
    //   6385	6394	6563	java/io/UnsupportedEncodingException
    //   6446	6468	6563	java/io/UnsupportedEncodingException
    //   6516	6560	6563	java/io/UnsupportedEncodingException
    //   6631	6640	6563	java/io/UnsupportedEncodingException
    //   6695	6704	6563	java/io/UnsupportedEncodingException
    //   6759	6768	6563	java/io/UnsupportedEncodingException
    //   6823	6842	6563	java/io/UnsupportedEncodingException
    //   6280	6285	6994	java/io/IOException
    //   6290	6295	7027	java/io/IOException
    //   6290	6295	7060	java/lang/ArrayIndexOutOfBoundsException
    //   6290	6295	7093	java/lang/Throwable
    //   1254	1259	7272	java/io/IOException
    //   1264	1269	7305	java/io/IOException
    //   1264	1269	7338	java/lang/ArrayIndexOutOfBoundsException
    //   1264	1269	7371	java/lang/Throwable
    //   298	316	7404	java/io/FileNotFoundException
    //   340	345	7404	java/io/FileNotFoundException
    //   369	378	7404	java/io/FileNotFoundException
    //   402	427	7404	java/io/FileNotFoundException
    //   451	463	7404	java/io/FileNotFoundException
    //   487	497	7404	java/io/FileNotFoundException
    //   521	528	7404	java/io/FileNotFoundException
    //   552	569	7404	java/io/FileNotFoundException
    //   593	604	7404	java/io/FileNotFoundException
    //   628	636	7404	java/io/FileNotFoundException
    //   660	671	7404	java/io/FileNotFoundException
    //   695	706	7404	java/io/FileNotFoundException
    //   730	738	7404	java/io/FileNotFoundException
    //   762	773	7404	java/io/FileNotFoundException
    //   797	804	7404	java/io/FileNotFoundException
    //   828	844	7404	java/io/FileNotFoundException
    //   868	884	7404	java/io/FileNotFoundException
    //   908	918	7404	java/io/FileNotFoundException
    //   942	954	7404	java/io/FileNotFoundException
    //   978	1005	7404	java/io/FileNotFoundException
    //   1029	1068	7404	java/io/FileNotFoundException
    //   1318	1332	7404	java/io/FileNotFoundException
    //   1356	1365	7404	java/io/FileNotFoundException
    //   1389	1400	7404	java/io/FileNotFoundException
    //   1424	1434	7404	java/io/FileNotFoundException
    //   1458	1470	7404	java/io/FileNotFoundException
    //   1494	1501	7404	java/io/FileNotFoundException
    //   1525	1532	7404	java/io/FileNotFoundException
    //   1561	1568	7404	java/io/FileNotFoundException
    //   1592	1601	7404	java/io/FileNotFoundException
    //   1632	1653	7404	java/io/FileNotFoundException
    //   1677	1686	7404	java/io/FileNotFoundException
    //   1733	1753	7404	java/io/FileNotFoundException
    //   1777	1805	7404	java/io/FileNotFoundException
    //   1829	1840	7404	java/io/FileNotFoundException
    //   1872	1906	7404	java/io/FileNotFoundException
    //   1930	1938	7404	java/io/FileNotFoundException
    //   1962	1971	7404	java/io/FileNotFoundException
    //   1995	2003	7404	java/io/FileNotFoundException
    //   2027	2033	7404	java/io/FileNotFoundException
    //   2057	2065	7404	java/io/FileNotFoundException
    //   2094	2114	7404	java/io/FileNotFoundException
    //   2138	2159	7404	java/io/FileNotFoundException
    //   2296	2310	7404	java/io/FileNotFoundException
    //   2334	2341	7404	java/io/FileNotFoundException
    //   2365	2373	7404	java/io/FileNotFoundException
    //   2400	2407	7404	java/io/FileNotFoundException
    //   2563	2597	7404	java/io/FileNotFoundException
    //   2621	2627	7404	java/io/FileNotFoundException
    //   2651	2655	7404	java/io/FileNotFoundException
    //   2846	2855	7404	java/io/FileNotFoundException
    //   2884	2891	7404	java/io/FileNotFoundException
    //   2915	2928	7404	java/io/FileNotFoundException
    //   2952	2972	7404	java/io/FileNotFoundException
    //   2996	3016	7404	java/io/FileNotFoundException
    //   3203	3218	7404	java/io/FileNotFoundException
    //   3238	3243	7404	java/io/FileNotFoundException
    //   3263	3275	7404	java/io/FileNotFoundException
    //   3564	3580	7404	java/io/FileNotFoundException
    //   3600	3609	7404	java/io/FileNotFoundException
    //   3629	3634	7404	java/io/FileNotFoundException
    //   3654	3660	7404	java/io/FileNotFoundException
    //   3680	3693	7404	java/io/FileNotFoundException
    //   3726	3740	7404	java/io/FileNotFoundException
    //   3760	3775	7404	java/io/FileNotFoundException
    //   3795	3800	7404	java/io/FileNotFoundException
    //   3820	3832	7404	java/io/FileNotFoundException
    //   3865	3879	7404	java/io/FileNotFoundException
    //   3905	3914	7404	java/io/FileNotFoundException
    //   3941	3950	7404	java/io/FileNotFoundException
    //   7648	7653	7834	java/io/IOException
    //   7658	7663	7867	java/io/IOException
    //   7658	7663	7900	java/lang/ArrayIndexOutOfBoundsException
    //   7658	7663	7933	java/lang/Throwable
    //   298	316	7966	javax/net/ssl/SSLHandshakeException
    //   340	345	7966	javax/net/ssl/SSLHandshakeException
    //   369	378	7966	javax/net/ssl/SSLHandshakeException
    //   402	427	7966	javax/net/ssl/SSLHandshakeException
    //   451	463	7966	javax/net/ssl/SSLHandshakeException
    //   487	497	7966	javax/net/ssl/SSLHandshakeException
    //   521	528	7966	javax/net/ssl/SSLHandshakeException
    //   552	569	7966	javax/net/ssl/SSLHandshakeException
    //   593	604	7966	javax/net/ssl/SSLHandshakeException
    //   628	636	7966	javax/net/ssl/SSLHandshakeException
    //   660	671	7966	javax/net/ssl/SSLHandshakeException
    //   695	706	7966	javax/net/ssl/SSLHandshakeException
    //   730	738	7966	javax/net/ssl/SSLHandshakeException
    //   762	773	7966	javax/net/ssl/SSLHandshakeException
    //   797	804	7966	javax/net/ssl/SSLHandshakeException
    //   828	844	7966	javax/net/ssl/SSLHandshakeException
    //   868	884	7966	javax/net/ssl/SSLHandshakeException
    //   908	918	7966	javax/net/ssl/SSLHandshakeException
    //   942	954	7966	javax/net/ssl/SSLHandshakeException
    //   978	1005	7966	javax/net/ssl/SSLHandshakeException
    //   1029	1068	7966	javax/net/ssl/SSLHandshakeException
    //   1318	1332	7966	javax/net/ssl/SSLHandshakeException
    //   1356	1365	7966	javax/net/ssl/SSLHandshakeException
    //   1389	1400	7966	javax/net/ssl/SSLHandshakeException
    //   1424	1434	7966	javax/net/ssl/SSLHandshakeException
    //   1458	1470	7966	javax/net/ssl/SSLHandshakeException
    //   1494	1501	7966	javax/net/ssl/SSLHandshakeException
    //   1525	1532	7966	javax/net/ssl/SSLHandshakeException
    //   1561	1568	7966	javax/net/ssl/SSLHandshakeException
    //   1592	1601	7966	javax/net/ssl/SSLHandshakeException
    //   1632	1653	7966	javax/net/ssl/SSLHandshakeException
    //   1677	1686	7966	javax/net/ssl/SSLHandshakeException
    //   1733	1753	7966	javax/net/ssl/SSLHandshakeException
    //   1777	1805	7966	javax/net/ssl/SSLHandshakeException
    //   1829	1840	7966	javax/net/ssl/SSLHandshakeException
    //   1872	1906	7966	javax/net/ssl/SSLHandshakeException
    //   1930	1938	7966	javax/net/ssl/SSLHandshakeException
    //   1962	1971	7966	javax/net/ssl/SSLHandshakeException
    //   1995	2003	7966	javax/net/ssl/SSLHandshakeException
    //   2027	2033	7966	javax/net/ssl/SSLHandshakeException
    //   2057	2065	7966	javax/net/ssl/SSLHandshakeException
    //   2094	2114	7966	javax/net/ssl/SSLHandshakeException
    //   2138	2159	7966	javax/net/ssl/SSLHandshakeException
    //   2296	2310	7966	javax/net/ssl/SSLHandshakeException
    //   2334	2341	7966	javax/net/ssl/SSLHandshakeException
    //   2365	2373	7966	javax/net/ssl/SSLHandshakeException
    //   2400	2407	7966	javax/net/ssl/SSLHandshakeException
    //   2563	2597	7966	javax/net/ssl/SSLHandshakeException
    //   2621	2627	7966	javax/net/ssl/SSLHandshakeException
    //   2651	2655	7966	javax/net/ssl/SSLHandshakeException
    //   2846	2855	7966	javax/net/ssl/SSLHandshakeException
    //   2884	2891	7966	javax/net/ssl/SSLHandshakeException
    //   2915	2928	7966	javax/net/ssl/SSLHandshakeException
    //   2952	2972	7966	javax/net/ssl/SSLHandshakeException
    //   2996	3016	7966	javax/net/ssl/SSLHandshakeException
    //   3203	3218	7966	javax/net/ssl/SSLHandshakeException
    //   3238	3243	7966	javax/net/ssl/SSLHandshakeException
    //   3263	3275	7966	javax/net/ssl/SSLHandshakeException
    //   3564	3580	7966	javax/net/ssl/SSLHandshakeException
    //   3600	3609	7966	javax/net/ssl/SSLHandshakeException
    //   3629	3634	7966	javax/net/ssl/SSLHandshakeException
    //   3654	3660	7966	javax/net/ssl/SSLHandshakeException
    //   3680	3693	7966	javax/net/ssl/SSLHandshakeException
    //   3726	3740	7966	javax/net/ssl/SSLHandshakeException
    //   3760	3775	7966	javax/net/ssl/SSLHandshakeException
    //   3795	3800	7966	javax/net/ssl/SSLHandshakeException
    //   3820	3832	7966	javax/net/ssl/SSLHandshakeException
    //   3865	3879	7966	javax/net/ssl/SSLHandshakeException
    //   3905	3914	7966	javax/net/ssl/SSLHandshakeException
    //   3941	3950	7966	javax/net/ssl/SSLHandshakeException
    //   8213	8218	8399	java/io/IOException
    //   8223	8228	8432	java/io/IOException
    //   8223	8228	8465	java/lang/ArrayIndexOutOfBoundsException
    //   8223	8228	8498	java/lang/Throwable
    //   298	316	8531	java/net/SocketTimeoutException
    //   340	345	8531	java/net/SocketTimeoutException
    //   369	378	8531	java/net/SocketTimeoutException
    //   402	427	8531	java/net/SocketTimeoutException
    //   451	463	8531	java/net/SocketTimeoutException
    //   487	497	8531	java/net/SocketTimeoutException
    //   521	528	8531	java/net/SocketTimeoutException
    //   552	569	8531	java/net/SocketTimeoutException
    //   593	604	8531	java/net/SocketTimeoutException
    //   628	636	8531	java/net/SocketTimeoutException
    //   660	671	8531	java/net/SocketTimeoutException
    //   695	706	8531	java/net/SocketTimeoutException
    //   730	738	8531	java/net/SocketTimeoutException
    //   762	773	8531	java/net/SocketTimeoutException
    //   797	804	8531	java/net/SocketTimeoutException
    //   828	844	8531	java/net/SocketTimeoutException
    //   868	884	8531	java/net/SocketTimeoutException
    //   908	918	8531	java/net/SocketTimeoutException
    //   942	954	8531	java/net/SocketTimeoutException
    //   978	1005	8531	java/net/SocketTimeoutException
    //   1029	1068	8531	java/net/SocketTimeoutException
    //   1318	1332	8531	java/net/SocketTimeoutException
    //   1356	1365	8531	java/net/SocketTimeoutException
    //   1389	1400	8531	java/net/SocketTimeoutException
    //   1424	1434	8531	java/net/SocketTimeoutException
    //   1458	1470	8531	java/net/SocketTimeoutException
    //   1494	1501	8531	java/net/SocketTimeoutException
    //   1525	1532	8531	java/net/SocketTimeoutException
    //   1561	1568	8531	java/net/SocketTimeoutException
    //   1592	1601	8531	java/net/SocketTimeoutException
    //   1632	1653	8531	java/net/SocketTimeoutException
    //   1677	1686	8531	java/net/SocketTimeoutException
    //   1733	1753	8531	java/net/SocketTimeoutException
    //   1777	1805	8531	java/net/SocketTimeoutException
    //   1829	1840	8531	java/net/SocketTimeoutException
    //   1872	1906	8531	java/net/SocketTimeoutException
    //   1930	1938	8531	java/net/SocketTimeoutException
    //   1962	1971	8531	java/net/SocketTimeoutException
    //   1995	2003	8531	java/net/SocketTimeoutException
    //   2027	2033	8531	java/net/SocketTimeoutException
    //   2057	2065	8531	java/net/SocketTimeoutException
    //   2094	2114	8531	java/net/SocketTimeoutException
    //   2138	2159	8531	java/net/SocketTimeoutException
    //   2296	2310	8531	java/net/SocketTimeoutException
    //   2334	2341	8531	java/net/SocketTimeoutException
    //   2365	2373	8531	java/net/SocketTimeoutException
    //   2400	2407	8531	java/net/SocketTimeoutException
    //   2563	2597	8531	java/net/SocketTimeoutException
    //   2621	2627	8531	java/net/SocketTimeoutException
    //   2651	2655	8531	java/net/SocketTimeoutException
    //   2846	2855	8531	java/net/SocketTimeoutException
    //   2884	2891	8531	java/net/SocketTimeoutException
    //   2915	2928	8531	java/net/SocketTimeoutException
    //   2952	2972	8531	java/net/SocketTimeoutException
    //   2996	3016	8531	java/net/SocketTimeoutException
    //   3203	3218	8531	java/net/SocketTimeoutException
    //   3238	3243	8531	java/net/SocketTimeoutException
    //   3263	3275	8531	java/net/SocketTimeoutException
    //   3564	3580	8531	java/net/SocketTimeoutException
    //   3600	3609	8531	java/net/SocketTimeoutException
    //   3629	3634	8531	java/net/SocketTimeoutException
    //   3654	3660	8531	java/net/SocketTimeoutException
    //   3680	3693	8531	java/net/SocketTimeoutException
    //   3726	3740	8531	java/net/SocketTimeoutException
    //   3760	3775	8531	java/net/SocketTimeoutException
    //   3795	3800	8531	java/net/SocketTimeoutException
    //   3820	3832	8531	java/net/SocketTimeoutException
    //   3865	3879	8531	java/net/SocketTimeoutException
    //   3905	3914	8531	java/net/SocketTimeoutException
    //   3941	3950	8531	java/net/SocketTimeoutException
    //   8778	8783	8964	java/io/IOException
    //   8788	8793	8997	java/io/IOException
    //   8788	8793	9030	java/lang/ArrayIndexOutOfBoundsException
    //   8788	8793	9063	java/lang/Throwable
    //   298	316	9096	java/lang/Exception
    //   340	345	9096	java/lang/Exception
    //   369	378	9096	java/lang/Exception
    //   402	427	9096	java/lang/Exception
    //   451	463	9096	java/lang/Exception
    //   487	497	9096	java/lang/Exception
    //   521	528	9096	java/lang/Exception
    //   552	569	9096	java/lang/Exception
    //   593	604	9096	java/lang/Exception
    //   628	636	9096	java/lang/Exception
    //   660	671	9096	java/lang/Exception
    //   695	706	9096	java/lang/Exception
    //   730	738	9096	java/lang/Exception
    //   762	773	9096	java/lang/Exception
    //   797	804	9096	java/lang/Exception
    //   828	844	9096	java/lang/Exception
    //   868	884	9096	java/lang/Exception
    //   908	918	9096	java/lang/Exception
    //   942	954	9096	java/lang/Exception
    //   978	1005	9096	java/lang/Exception
    //   1029	1068	9096	java/lang/Exception
    //   1318	1332	9096	java/lang/Exception
    //   1356	1365	9096	java/lang/Exception
    //   1389	1400	9096	java/lang/Exception
    //   1424	1434	9096	java/lang/Exception
    //   1458	1470	9096	java/lang/Exception
    //   1494	1501	9096	java/lang/Exception
    //   1525	1532	9096	java/lang/Exception
    //   1561	1568	9096	java/lang/Exception
    //   1592	1601	9096	java/lang/Exception
    //   1632	1653	9096	java/lang/Exception
    //   1677	1686	9096	java/lang/Exception
    //   1733	1753	9096	java/lang/Exception
    //   1777	1805	9096	java/lang/Exception
    //   1829	1840	9096	java/lang/Exception
    //   1872	1906	9096	java/lang/Exception
    //   1930	1938	9096	java/lang/Exception
    //   1962	1971	9096	java/lang/Exception
    //   1995	2003	9096	java/lang/Exception
    //   2027	2033	9096	java/lang/Exception
    //   2057	2065	9096	java/lang/Exception
    //   2094	2114	9096	java/lang/Exception
    //   2138	2159	9096	java/lang/Exception
    //   2296	2310	9096	java/lang/Exception
    //   2334	2341	9096	java/lang/Exception
    //   2365	2373	9096	java/lang/Exception
    //   2400	2407	9096	java/lang/Exception
    //   2563	2597	9096	java/lang/Exception
    //   2621	2627	9096	java/lang/Exception
    //   2651	2655	9096	java/lang/Exception
    //   2846	2855	9096	java/lang/Exception
    //   2884	2891	9096	java/lang/Exception
    //   2915	2928	9096	java/lang/Exception
    //   2952	2972	9096	java/lang/Exception
    //   2996	3016	9096	java/lang/Exception
    //   3726	3740	9096	java/lang/Exception
    //   3865	3879	9096	java/lang/Exception
    //   9475	9480	9661	java/io/IOException
    //   9485	9490	9694	java/io/IOException
    //   9485	9490	9727	java/lang/ArrayIndexOutOfBoundsException
    //   9485	9490	9760	java/lang/Throwable
    //   298	316	9793	finally
    //   340	345	9793	finally
    //   369	378	9793	finally
    //   402	427	9793	finally
    //   451	463	9793	finally
    //   487	497	9793	finally
    //   521	528	9793	finally
    //   552	569	9793	finally
    //   593	604	9793	finally
    //   628	636	9793	finally
    //   660	671	9793	finally
    //   695	706	9793	finally
    //   730	738	9793	finally
    //   762	773	9793	finally
    //   797	804	9793	finally
    //   828	844	9793	finally
    //   868	884	9793	finally
    //   908	918	9793	finally
    //   942	954	9793	finally
    //   978	1005	9793	finally
    //   1029	1068	9793	finally
    //   1318	1332	9793	finally
    //   1356	1365	9793	finally
    //   1389	1400	9793	finally
    //   1424	1434	9793	finally
    //   1458	1470	9793	finally
    //   1494	1501	9793	finally
    //   1525	1532	9793	finally
    //   1561	1568	9793	finally
    //   1592	1601	9793	finally
    //   1632	1653	9793	finally
    //   1677	1686	9793	finally
    //   1733	1753	9793	finally
    //   1777	1805	9793	finally
    //   1829	1840	9793	finally
    //   1872	1906	9793	finally
    //   1930	1938	9793	finally
    //   1962	1971	9793	finally
    //   1995	2003	9793	finally
    //   2027	2033	9793	finally
    //   2057	2065	9793	finally
    //   2094	2114	9793	finally
    //   2138	2159	9793	finally
    //   2296	2310	9793	finally
    //   2334	2341	9793	finally
    //   2365	2373	9793	finally
    //   2400	2407	9793	finally
    //   2563	2597	9793	finally
    //   2621	2627	9793	finally
    //   2651	2655	9793	finally
    //   2846	2855	9793	finally
    //   2884	2891	9793	finally
    //   2915	2928	9793	finally
    //   2952	2972	9793	finally
    //   2996	3016	9793	finally
    //   3203	3218	9793	finally
    //   3238	3243	9793	finally
    //   3263	3275	9793	finally
    //   3564	3580	9793	finally
    //   3600	3609	9793	finally
    //   3629	3634	9793	finally
    //   3654	3660	9793	finally
    //   3680	3693	9793	finally
    //   3726	3740	9793	finally
    //   3760	3775	9793	finally
    //   3795	3800	9793	finally
    //   3820	3832	9793	finally
    //   3865	3879	9793	finally
    //   3905	3914	9793	finally
    //   3941	3950	9793	finally
    //   9909	9914	10095	java/io/IOException
    //   9919	9924	10128	java/io/IOException
    //   9919	9924	10161	java/lang/ArrayIndexOutOfBoundsException
    //   9919	9924	10194	java/lang/Throwable
    //   3279	3367	10227	finally
    //   4056	4136	10227	finally
    //   4417	4428	10227	finally
    //   4433	4442	10251	finally
    //   4448	4457	10279	finally
    //   4463	4500	10279	finally
    //   4815	4825	10279	finally
    //   5868	5873	10279	finally
    //   4896	4903	10304	finally
    //   4951	4963	10304	finally
    //   5022	5041	10304	finally
    //   5093	5129	10304	finally
    //   5184	5191	10304	finally
    //   5239	5254	10304	finally
    //   5302	5322	10304	finally
    //   5370	5390	10304	finally
    //   5438	5443	10304	finally
    //   5491	5496	10304	finally
    //   5544	5553	10304	finally
    //   5921	5928	10304	finally
    //   5976	5997	10304	finally
    //   6045	6055	10304	finally
    //   6117	6145	10304	finally
    //   6385	6394	10304	finally
    //   6446	6468	10304	finally
    //   6516	6560	10304	finally
    //   6631	6640	10304	finally
    //   6695	6704	10304	finally
    //   6759	6768	10304	finally
    //   6823	6842	10304	finally
    //   6148	6181	10329	finally
    //   1089	1155	10350	finally
    //   7441	7461	10367	finally
    //   7481	7509	10367	finally
    //   7529	7549	10367	finally
    //   8006	8026	10367	finally
    //   8046	8074	10367	finally
    //   8094	8114	10367	finally
    //   8571	8591	10367	finally
    //   8611	8639	10367	finally
    //   8659	8679	10367	finally
    //   9136	9156	10367	finally
    //   9176	9204	10367	finally
    //   9224	9230	10367	finally
    //   9250	9256	10367	finally
    //   9276	9282	10367	finally
    //   9302	9307	10367	finally
    //   9327	9332	10367	finally
    //   9352	9376	10367	finally
    //   3279	3367	10388	java/lang/Exception
    //   4056	4136	10388	java/lang/Exception
    //   4417	4428	10388	java/lang/Exception
    //   4433	4442	10403	java/lang/Exception
    //   4448	4457	10426	java/lang/Exception
    //   4463	4500	10426	java/lang/Exception
    //   4815	4825	10426	java/lang/Exception
    //   5868	5873	10426	java/lang/Exception
    //   4896	4903	10446	java/lang/Exception
    //   4951	4963	10446	java/lang/Exception
    //   5022	5041	10446	java/lang/Exception
    //   5093	5129	10446	java/lang/Exception
    //   5184	5191	10446	java/lang/Exception
    //   5239	5254	10446	java/lang/Exception
    //   5302	5322	10446	java/lang/Exception
    //   5370	5390	10446	java/lang/Exception
    //   5438	5443	10446	java/lang/Exception
    //   5491	5496	10446	java/lang/Exception
    //   5544	5553	10446	java/lang/Exception
    //   5921	5928	10446	java/lang/Exception
    //   5976	5997	10446	java/lang/Exception
    //   6045	6055	10446	java/lang/Exception
    //   6117	6145	10446	java/lang/Exception
    //   6385	6394	10446	java/lang/Exception
    //   6446	6468	10446	java/lang/Exception
    //   6516	6560	10446	java/lang/Exception
    //   6631	6640	10446	java/lang/Exception
    //   6695	6704	10446	java/lang/Exception
    //   6759	6768	10446	java/lang/Exception
    //   6823	6842	10446	java/lang/Exception
    //   6148	6181	10462	java/lang/Exception
    //   3279	3367	10479	java/net/SocketTimeoutException
    //   4056	4136	10479	java/net/SocketTimeoutException
    //   4417	4428	10479	java/net/SocketTimeoutException
    //   4433	4442	10494	java/net/SocketTimeoutException
    //   4448	4457	10517	java/net/SocketTimeoutException
    //   4463	4500	10517	java/net/SocketTimeoutException
    //   4815	4825	10517	java/net/SocketTimeoutException
    //   5868	5873	10517	java/net/SocketTimeoutException
    //   4896	4903	10533	java/net/SocketTimeoutException
    //   4951	4963	10533	java/net/SocketTimeoutException
    //   5022	5041	10533	java/net/SocketTimeoutException
    //   5093	5129	10533	java/net/SocketTimeoutException
    //   5184	5191	10533	java/net/SocketTimeoutException
    //   5239	5254	10533	java/net/SocketTimeoutException
    //   5302	5322	10533	java/net/SocketTimeoutException
    //   5370	5390	10533	java/net/SocketTimeoutException
    //   5438	5443	10533	java/net/SocketTimeoutException
    //   5491	5496	10533	java/net/SocketTimeoutException
    //   5544	5553	10533	java/net/SocketTimeoutException
    //   5921	5928	10533	java/net/SocketTimeoutException
    //   5976	5997	10533	java/net/SocketTimeoutException
    //   6045	6055	10533	java/net/SocketTimeoutException
    //   6117	6145	10533	java/net/SocketTimeoutException
    //   6385	6394	10533	java/net/SocketTimeoutException
    //   6446	6468	10533	java/net/SocketTimeoutException
    //   6516	6560	10533	java/net/SocketTimeoutException
    //   6631	6640	10533	java/net/SocketTimeoutException
    //   6695	6704	10533	java/net/SocketTimeoutException
    //   6759	6768	10533	java/net/SocketTimeoutException
    //   6823	6842	10533	java/net/SocketTimeoutException
    //   6148	6181	10549	java/net/SocketTimeoutException
    //   3279	3367	10570	javax/net/ssl/SSLHandshakeException
    //   4056	4136	10570	javax/net/ssl/SSLHandshakeException
    //   4417	4428	10570	javax/net/ssl/SSLHandshakeException
    //   4433	4442	10585	javax/net/ssl/SSLHandshakeException
    //   4448	4457	10604	javax/net/ssl/SSLHandshakeException
    //   4463	4500	10604	javax/net/ssl/SSLHandshakeException
    //   4815	4825	10604	javax/net/ssl/SSLHandshakeException
    //   5868	5873	10604	javax/net/ssl/SSLHandshakeException
    //   4896	4903	10624	javax/net/ssl/SSLHandshakeException
    //   4951	4963	10624	javax/net/ssl/SSLHandshakeException
    //   5022	5041	10624	javax/net/ssl/SSLHandshakeException
    //   5093	5129	10624	javax/net/ssl/SSLHandshakeException
    //   5184	5191	10624	javax/net/ssl/SSLHandshakeException
    //   5239	5254	10624	javax/net/ssl/SSLHandshakeException
    //   5302	5322	10624	javax/net/ssl/SSLHandshakeException
    //   5370	5390	10624	javax/net/ssl/SSLHandshakeException
    //   5438	5443	10624	javax/net/ssl/SSLHandshakeException
    //   5491	5496	10624	javax/net/ssl/SSLHandshakeException
    //   5544	5553	10624	javax/net/ssl/SSLHandshakeException
    //   5921	5928	10624	javax/net/ssl/SSLHandshakeException
    //   5976	5997	10624	javax/net/ssl/SSLHandshakeException
    //   6045	6055	10624	javax/net/ssl/SSLHandshakeException
    //   6117	6145	10624	javax/net/ssl/SSLHandshakeException
    //   6385	6394	10624	javax/net/ssl/SSLHandshakeException
    //   6446	6468	10624	javax/net/ssl/SSLHandshakeException
    //   6516	6560	10624	javax/net/ssl/SSLHandshakeException
    //   6631	6640	10624	javax/net/ssl/SSLHandshakeException
    //   6695	6704	10624	javax/net/ssl/SSLHandshakeException
    //   6759	6768	10624	javax/net/ssl/SSLHandshakeException
    //   6823	6842	10624	javax/net/ssl/SSLHandshakeException
    //   6148	6181	10640	javax/net/ssl/SSLHandshakeException
    //   3279	3367	10657	java/io/FileNotFoundException
    //   4056	4136	10657	java/io/FileNotFoundException
    //   4417	4428	10657	java/io/FileNotFoundException
    //   4433	4442	10673	java/io/FileNotFoundException
    //   4448	4457	10693	java/io/FileNotFoundException
    //   4463	4500	10693	java/io/FileNotFoundException
    //   4815	4825	10693	java/io/FileNotFoundException
    //   5868	5873	10693	java/io/FileNotFoundException
    //   4896	4903	10710	java/io/FileNotFoundException
    //   4951	4963	10710	java/io/FileNotFoundException
    //   5022	5041	10710	java/io/FileNotFoundException
    //   5093	5129	10710	java/io/FileNotFoundException
    //   5184	5191	10710	java/io/FileNotFoundException
    //   5239	5254	10710	java/io/FileNotFoundException
    //   5302	5322	10710	java/io/FileNotFoundException
    //   5370	5390	10710	java/io/FileNotFoundException
    //   5438	5443	10710	java/io/FileNotFoundException
    //   5491	5496	10710	java/io/FileNotFoundException
    //   5544	5553	10710	java/io/FileNotFoundException
    //   5921	5928	10710	java/io/FileNotFoundException
    //   5976	5997	10710	java/io/FileNotFoundException
    //   6045	6055	10710	java/io/FileNotFoundException
    //   6117	6145	10710	java/io/FileNotFoundException
    //   6385	6394	10710	java/io/FileNotFoundException
    //   6446	6468	10710	java/io/FileNotFoundException
    //   6516	6560	10710	java/io/FileNotFoundException
    //   6631	6640	10710	java/io/FileNotFoundException
    //   6695	6704	10710	java/io/FileNotFoundException
    //   6759	6768	10710	java/io/FileNotFoundException
    //   6823	6842	10710	java/io/FileNotFoundException
    //   6148	6181	10727	java/io/FileNotFoundException
    //   3279	3367	10744	java/io/UnsupportedEncodingException
    //   4056	4136	10744	java/io/UnsupportedEncodingException
    //   4417	4428	10744	java/io/UnsupportedEncodingException
    //   4433	4442	10766	java/io/UnsupportedEncodingException
    //   4448	4457	10789	java/io/UnsupportedEncodingException
    //   4463	4500	10789	java/io/UnsupportedEncodingException
    //   4815	4825	10789	java/io/UnsupportedEncodingException
    //   5868	5873	10789	java/io/UnsupportedEncodingException
    //   6148	6181	10809	java/io/UnsupportedEncodingException
  }
}

/* Location:           C:\Users\Lin\Downloads\dex-tools-2.1-SNAPSHOT\dex-tools-2.1-SNAPSHOT\classes6-dex2jar.jar
 * Qualified Name:     com.tencent.mm.plugin.appbrand.l.a.b
 * JD-Core Version:    0.6.2
 */