package com.tencent.mm.model.d;

public final class b$3
  implements Runnable
{
  public b$3(b paramb, String paramString)
  {
  }

  // ERROR //
  public final void run()
  {
    // Byte code:
    //   0: sipush 16393
    //   3: invokestatic 33	com/tencent/matrix/trace/core/AppMethodBeat:i	(I)V
    //   6: aload_0
    //   7: getfield 16	com/tencent/mm/model/d/b$3:fpv	Lcom/tencent/mm/model/d/b;
    //   10: astore_1
    //   11: new 35	java/lang/StringBuilder
    //   14: dup
    //   15: invokespecial 36	java/lang/StringBuilder:<init>	()V
    //   18: invokestatic 40	com/tencent/mm/model/d/b:access$000	()Ljava/lang/String;
    //   21: invokevirtual 44	java/lang/StringBuilder:append	(Ljava/lang/String;)Ljava/lang/StringBuilder;
    //   24: ldc 46
    //   26: invokevirtual 44	java/lang/StringBuilder:append	(Ljava/lang/String;)Ljava/lang/StringBuilder;
    //   29: invokevirtual 49	java/lang/StringBuilder:toString	()Ljava/lang/String;
    //   32: astore_2
    //   33: new 35	java/lang/StringBuilder
    //   36: dup
    //   37: invokespecial 36	java/lang/StringBuilder:<init>	()V
    //   40: aload_0
    //   41: getfield 18	com/tencent/mm/model/d/b$3:fpw	Ljava/lang/String;
    //   44: invokevirtual 44	java/lang/StringBuilder:append	(Ljava/lang/String;)Ljava/lang/StringBuilder;
    //   47: ldc 51
    //   49: invokevirtual 44	java/lang/StringBuilder:append	(Ljava/lang/String;)Ljava/lang/StringBuilder;
    //   52: invokevirtual 49	java/lang/StringBuilder:toString	()Ljava/lang/String;
    //   55: astore_3
    //   56: invokestatic 57	com/tencent/mm/compatible/util/f:Mn	()Z
    //   59: ifne +17 -> 76
    //   62: ldc 59
    //   64: ldc 61
    //   66: invokestatic 66	com/tencent/mm/sdk/platformtools/ab:i	(Ljava/lang/String;Ljava/lang/String;)V
    //   69: sipush 16393
    //   72: invokestatic 69	com/tencent/matrix/trace/core/AppMethodBeat:o	(I)V
    //   75: return
    //   76: new 71	java/io/File
    //   79: astore 4
    //   81: aload 4
    //   83: getstatic 74	com/tencent/mm/model/d/b:fpk	Ljava/lang/String;
    //   86: invokespecial 77	java/io/File:<init>	(Ljava/lang/String;)V
    //   89: aload 4
    //   91: invokevirtual 80	java/io/File:exists	()Z
    //   94: ifne +9 -> 103
    //   97: aload 4
    //   99: invokevirtual 83	java/io/File:mkdirs	()Z
    //   102: pop
    //   103: new 71	java/io/File
    //   106: astore 4
    //   108: aload 4
    //   110: getstatic 74	com/tencent/mm/model/d/b:fpk	Ljava/lang/String;
    //   113: ldc 46
    //   115: invokespecial 85	java/io/File:<init>	(Ljava/lang/String;Ljava/lang/String;)V
    //   118: aload_1
    //   119: aload 4
    //   121: iconst_0
    //   122: invokevirtual 89	com/tencent/mm/model/d/b:b	(Ljava/io/File;Z)V
    //   125: new 71	java/io/File
    //   128: dup
    //   129: aload_2
    //   130: invokespecial 77	java/io/File:<init>	(Ljava/lang/String;)V
    //   133: astore 4
    //   135: aload 4
    //   137: invokevirtual 93	java/io/File:length	()J
    //   140: aload_1
    //   141: getfield 97	com/tencent/mm/model/d/b:fpp	J
    //   144: lcmp
    //   145: ifle +17 -> 162
    //   148: ldc 59
    //   150: ldc 99
    //   152: invokestatic 102	com/tencent/mm/sdk/platformtools/ab:e	(Ljava/lang/String;Ljava/lang/String;)V
    //   155: aload_1
    //   156: aload 4
    //   158: iconst_1
    //   159: invokevirtual 89	com/tencent/mm/model/d/b:b	(Ljava/io/File;Z)V
    //   162: new 104	java/io/RandomAccessFile
    //   165: astore 4
    //   167: aload 4
    //   169: aload_2
    //   170: ldc 106
    //   172: invokespecial 107	java/io/RandomAccessFile:<init>	(Ljava/lang/String;Ljava/lang/String;)V
    //   175: aload 4
    //   177: astore_2
    //   178: aload 4
    //   180: aload 4
    //   182: invokevirtual 108	java/io/RandomAccessFile:length	()J
    //   185: invokevirtual 112	java/io/RandomAccessFile:seek	(J)V
    //   188: aload 4
    //   190: astore_2
    //   191: aload 4
    //   193: aload_3
    //   194: invokevirtual 118	java/lang/String:getBytes	()[B
    //   197: invokestatic 124	com/tencent/mm/cf/e:ce	([B)[B
    //   200: invokevirtual 128	java/io/RandomAccessFile:write	([B)V
    //   203: aload 4
    //   205: invokevirtual 131	java/io/RandomAccessFile:close	()V
    //   208: aload_1
    //   209: new 71	java/io/File
    //   212: dup
    //   213: new 35	java/lang/StringBuilder
    //   216: dup
    //   217: invokespecial 36	java/lang/StringBuilder:<init>	()V
    //   220: getstatic 74	com/tencent/mm/model/d/b:fpk	Ljava/lang/String;
    //   223: invokevirtual 44	java/lang/StringBuilder:append	(Ljava/lang/String;)Ljava/lang/StringBuilder;
    //   226: ldc 46
    //   228: invokevirtual 44	java/lang/StringBuilder:append	(Ljava/lang/String;)Ljava/lang/StringBuilder;
    //   231: invokevirtual 49	java/lang/StringBuilder:toString	()Ljava/lang/String;
    //   234: invokespecial 77	java/io/File:<init>	(Ljava/lang/String;)V
    //   237: invokevirtual 135	com/tencent/mm/model/d/b:z	(Ljava/io/File;)V
    //   240: sipush 16393
    //   243: invokestatic 69	com/tencent/matrix/trace/core/AppMethodBeat:o	(I)V
    //   246: goto -171 -> 75
    //   249: astore 4
    //   251: ldc 59
    //   253: ldc 137
    //   255: invokestatic 102	com/tencent/mm/sdk/platformtools/ab:e	(Ljava/lang/String;Ljava/lang/String;)V
    //   258: goto -133 -> 125
    //   261: astore_2
    //   262: ldc 59
    //   264: aload_2
    //   265: ldc 139
    //   267: iconst_0
    //   268: anewarray 4	java/lang/Object
    //   271: invokestatic 143	com/tencent/mm/sdk/platformtools/ab:printErrStackTrace	(Ljava/lang/String;Ljava/lang/Throwable;Ljava/lang/String;[Ljava/lang/Object;)V
    //   274: goto -66 -> 208
    //   277: astore_3
    //   278: aconst_null
    //   279: astore 4
    //   281: aload 4
    //   283: astore_2
    //   284: ldc 59
    //   286: aload_3
    //   287: ldc 139
    //   289: iconst_0
    //   290: anewarray 4	java/lang/Object
    //   293: invokestatic 143	com/tencent/mm/sdk/platformtools/ab:printErrStackTrace	(Ljava/lang/String;Ljava/lang/Throwable;Ljava/lang/String;[Ljava/lang/Object;)V
    //   296: aload 4
    //   298: ifnull -90 -> 208
    //   301: aload 4
    //   303: invokevirtual 131	java/io/RandomAccessFile:close	()V
    //   306: goto -98 -> 208
    //   309: astore_2
    //   310: ldc 59
    //   312: aload_2
    //   313: ldc 139
    //   315: iconst_0
    //   316: anewarray 4	java/lang/Object
    //   319: invokestatic 143	com/tencent/mm/sdk/platformtools/ab:printErrStackTrace	(Ljava/lang/String;Ljava/lang/Throwable;Ljava/lang/String;[Ljava/lang/Object;)V
    //   322: goto -114 -> 208
    //   325: astore 4
    //   327: aconst_null
    //   328: astore_2
    //   329: aload_2
    //   330: ifnull +7 -> 337
    //   333: aload_2
    //   334: invokevirtual 131	java/io/RandomAccessFile:close	()V
    //   337: sipush 16393
    //   340: invokestatic 69	com/tencent/matrix/trace/core/AppMethodBeat:o	(I)V
    //   343: aload 4
    //   345: athrow
    //   346: astore_2
    //   347: ldc 59
    //   349: aload_2
    //   350: ldc 139
    //   352: iconst_0
    //   353: anewarray 4	java/lang/Object
    //   356: invokestatic 143	com/tencent/mm/sdk/platformtools/ab:printErrStackTrace	(Ljava/lang/String;Ljava/lang/Throwable;Ljava/lang/String;[Ljava/lang/Object;)V
    //   359: goto -22 -> 337
    //   362: astore 4
    //   364: goto -35 -> 329
    //   367: astore_3
    //   368: goto -87 -> 281
    //
    // Exception table:
    //   from	to	target	type
    //   76	103	249	java/lang/Exception
    //   103	125	249	java/lang/Exception
    //   203	208	261	java/lang/Exception
    //   162	175	277	java/io/IOException
    //   301	306	309	java/lang/Exception
    //   162	175	325	finally
    //   333	337	346	java/lang/Exception
    //   178	188	362	finally
    //   191	203	362	finally
    //   284	296	362	finally
    //   178	188	367	java/io/IOException
    //   191	203	367	java/io/IOException
  }
}

/* Location:           C:\Users\Lin\Downloads\dex-tools-2.1-SNAPSHOT\dex-tools-2.1-SNAPSHOT\classes2-dex2jar.jar
 * Qualified Name:     com.tencent.mm.model.d.b.3
 * JD-Core Version:    0.6.2
 */