package com.tencent.mm.plugin.normsg.b;

public final class a$c
{
  // ERROR //
  static boolean bVZ()
  {
    // Byte code:
    //   0: iconst_1
    //   1: istore_0
    //   2: sipush 10368
    //   5: invokestatic 20	com/tencent/matrix/trace/core/AppMethodBeat:i	(I)V
    //   8: new 22	java/lang/StringBuilder
    //   11: dup
    //   12: invokespecial 23	java/lang/StringBuilder:<init>	()V
    //   15: astore_1
    //   16: aload_1
    //   17: ldc 25
    //   19: invokestatic 31	com/tencent/mm/plugin/normsg/b/d:TQ	(Ljava/lang/String;)Ljava/lang/String;
    //   22: invokevirtual 35	java/lang/StringBuilder:append	(Ljava/lang/String;)Ljava/lang/StringBuilder;
    //   25: pop
    //   26: aload_1
    //   27: invokevirtual 39	java/lang/StringBuilder:toString	()Ljava/lang/String;
    //   30: astore_2
    //   31: aload_1
    //   32: iconst_0
    //   33: aload_1
    //   34: invokevirtual 43	java/lang/StringBuilder:length	()I
    //   37: invokevirtual 47	java/lang/StringBuilder:delete	(II)Ljava/lang/StringBuilder;
    //   40: pop
    //   41: aload_1
    //   42: ldc 2
    //   44: invokevirtual 50	java/lang/Object:hashCode	()I
    //   47: bipush 31
    //   49: iushr
    //   50: iconst_1
    //   51: ior
    //   52: iconst_1
    //   53: ixor
    //   54: invokevirtual 53	java/lang/StringBuilder:append	(I)Ljava/lang/StringBuilder;
    //   57: pop
    //   58: aload_1
    //   59: invokevirtual 39	java/lang/StringBuilder:toString	()Ljava/lang/String;
    //   62: aload_2
    //   63: aload_1
    //   64: invokevirtual 39	java/lang/StringBuilder:toString	()Ljava/lang/String;
    //   67: invokestatic 57	com/tencent/mm/plugin/normsg/b/a:fw	(Ljava/lang/String;Ljava/lang/String;)Ljava/lang/String;
    //   70: invokevirtual 63	java/lang/String:equals	(Ljava/lang/Object;)Z
    //   73: ifne +11 -> 84
    //   76: sipush 10368
    //   79: invokestatic 66	com/tencent/matrix/trace/core/AppMethodBeat:o	(I)V
    //   82: iload_0
    //   83: ireturn
    //   84: sipush 10368
    //   87: invokestatic 66	com/tencent/matrix/trace/core/AppMethodBeat:o	(I)V
    //   90: iconst_0
    //   91: istore_0
    //   92: goto -10 -> 82
    //   95: astore_2
    //   96: aload_1
    //   97: invokevirtual 39	java/lang/StringBuilder:toString	()Ljava/lang/String;
    //   100: astore_2
    //   101: aload_1
    //   102: iconst_0
    //   103: aload_1
    //   104: invokevirtual 43	java/lang/StringBuilder:length	()I
    //   107: invokevirtual 47	java/lang/StringBuilder:delete	(II)Ljava/lang/StringBuilder;
    //   110: pop
    //   111: aload_1
    //   112: ldc 2
    //   114: invokevirtual 50	java/lang/Object:hashCode	()I
    //   117: bipush 31
    //   119: iushr
    //   120: iconst_1
    //   121: ior
    //   122: iconst_1
    //   123: ixor
    //   124: invokevirtual 53	java/lang/StringBuilder:append	(I)Ljava/lang/StringBuilder;
    //   127: pop
    //   128: aload_1
    //   129: invokevirtual 39	java/lang/StringBuilder:toString	()Ljava/lang/String;
    //   132: aload_2
    //   133: aload_1
    //   134: invokevirtual 39	java/lang/StringBuilder:toString	()Ljava/lang/String;
    //   137: invokestatic 57	com/tencent/mm/plugin/normsg/b/a:fw	(Ljava/lang/String;Ljava/lang/String;)Ljava/lang/String;
    //   140: invokevirtual 63	java/lang/String:equals	(Ljava/lang/Object;)Z
    //   143: ifne +12 -> 155
    //   146: sipush 10368
    //   149: invokestatic 66	com/tencent/matrix/trace/core/AppMethodBeat:o	(I)V
    //   152: goto -70 -> 82
    //   155: sipush 10368
    //   158: invokestatic 66	com/tencent/matrix/trace/core/AppMethodBeat:o	(I)V
    //   161: iconst_0
    //   162: istore_0
    //   163: goto -81 -> 82
    //
    // Exception table:
    //   from	to	target	type
    //   16	26	95	finally
  }

  // ERROR //
  public static int bWa()
  {
    // Byte code:
    //   0: sipush 10369
    //   3: invokestatic 20	com/tencent/matrix/trace/core/AppMethodBeat:i	(I)V
    //   6: new 22	java/lang/StringBuilder
    //   9: dup
    //   10: invokespecial 23	java/lang/StringBuilder:<init>	()V
    //   13: astore_0
    //   14: aload_0
    //   15: ldc 69
    //   17: invokestatic 31	com/tencent/mm/plugin/normsg/b/d:TQ	(Ljava/lang/String;)Ljava/lang/String;
    //   20: invokevirtual 35	java/lang/StringBuilder:append	(Ljava/lang/String;)Ljava/lang/StringBuilder;
    //   23: pop
    //   24: ldc 2
    //   26: invokevirtual 50	java/lang/Object:hashCode	()I
    //   29: bipush 31
    //   31: iushr
    //   32: iconst_1
    //   33: ior
    //   34: istore_1
    //   35: aload_0
    //   36: invokevirtual 39	java/lang/StringBuilder:toString	()Ljava/lang/String;
    //   39: astore_2
    //   40: iload_1
    //   41: ifeq +70 -> 111
    //   44: ldc 2
    //   46: invokevirtual 50	java/lang/Object:hashCode	()I
    //   49: istore_3
    //   50: iload_3
    //   51: bipush 31
    //   53: iushr
    //   54: iconst_1
    //   55: ior
    //   56: iconst_1
    //   57: ixor
    //   58: istore_1
    //   59: aload_0
    //   60: iconst_0
    //   61: aload_0
    //   62: invokevirtual 43	java/lang/StringBuilder:length	()I
    //   65: invokevirtual 47	java/lang/StringBuilder:delete	(II)Ljava/lang/StringBuilder;
    //   68: pop
    //   69: aload_0
    //   70: iload_1
    //   71: invokevirtual 53	java/lang/StringBuilder:append	(I)Ljava/lang/StringBuilder;
    //   74: pop
    //   75: aload_2
    //   76: aload_0
    //   77: invokevirtual 39	java/lang/StringBuilder:toString	()Ljava/lang/String;
    //   80: invokestatic 57	com/tencent/mm/plugin/normsg/b/a:fw	(Ljava/lang/String;Ljava/lang/String;)Ljava/lang/String;
    //   83: iload_1
    //   84: invokestatic 75	com/tencent/mm/sdk/platformtools/bo:getInt	(Ljava/lang/String;I)I
    //   87: istore_1
    //   88: sipush 10369
    //   91: invokestatic 66	com/tencent/matrix/trace/core/AppMethodBeat:o	(I)V
    //   94: iload_1
    //   95: ireturn
    //   96: astore_2
    //   97: aload_0
    //   98: iload_1
    //   99: invokevirtual 53	java/lang/StringBuilder:append	(I)Ljava/lang/StringBuilder;
    //   102: pop
    //   103: sipush 10369
    //   106: invokestatic 66	com/tencent/matrix/trace/core/AppMethodBeat:o	(I)V
    //   109: aload_2
    //   110: athrow
    //   111: sipush 10369
    //   114: invokestatic 66	com/tencent/matrix/trace/core/AppMethodBeat:o	(I)V
    //   117: goto -23 -> 94
    //   120: astore_2
    //   121: ldc 2
    //   123: invokevirtual 50	java/lang/Object:hashCode	()I
    //   126: bipush 31
    //   128: iushr
    //   129: iconst_1
    //   130: ior
    //   131: istore_1
    //   132: aload_0
    //   133: invokevirtual 39	java/lang/StringBuilder:toString	()Ljava/lang/String;
    //   136: astore_2
    //   137: iload_1
    //   138: ifeq +71 -> 209
    //   141: ldc 2
    //   143: invokevirtual 50	java/lang/Object:hashCode	()I
    //   146: istore_3
    //   147: iload_3
    //   148: bipush 31
    //   150: iushr
    //   151: iconst_1
    //   152: ior
    //   153: iconst_1
    //   154: ixor
    //   155: istore_1
    //   156: aload_0
    //   157: iconst_0
    //   158: aload_0
    //   159: invokevirtual 43	java/lang/StringBuilder:length	()I
    //   162: invokevirtual 47	java/lang/StringBuilder:delete	(II)Ljava/lang/StringBuilder;
    //   165: pop
    //   166: aload_0
    //   167: iload_1
    //   168: invokevirtual 53	java/lang/StringBuilder:append	(I)Ljava/lang/StringBuilder;
    //   171: pop
    //   172: aload_2
    //   173: aload_0
    //   174: invokevirtual 39	java/lang/StringBuilder:toString	()Ljava/lang/String;
    //   177: invokestatic 57	com/tencent/mm/plugin/normsg/b/a:fw	(Ljava/lang/String;Ljava/lang/String;)Ljava/lang/String;
    //   180: iload_1
    //   181: invokestatic 75	com/tencent/mm/sdk/platformtools/bo:getInt	(Ljava/lang/String;I)I
    //   184: istore_1
    //   185: sipush 10369
    //   188: invokestatic 66	com/tencent/matrix/trace/core/AppMethodBeat:o	(I)V
    //   191: goto -97 -> 94
    //   194: astore_2
    //   195: aload_0
    //   196: iload_1
    //   197: invokevirtual 53	java/lang/StringBuilder:append	(I)Ljava/lang/StringBuilder;
    //   200: pop
    //   201: sipush 10369
    //   204: invokestatic 66	com/tencent/matrix/trace/core/AppMethodBeat:o	(I)V
    //   207: aload_2
    //   208: athrow
    //   209: sipush 10369
    //   212: invokestatic 66	com/tencent/matrix/trace/core/AppMethodBeat:o	(I)V
    //   215: goto -121 -> 94
    //   218: astore_2
    //   219: goto -24 -> 195
    //   222: astore_2
    //   223: goto -126 -> 97
    //
    // Exception table:
    //   from	to	target	type
    //   44	50	96	finally
    //   14	24	120	finally
    //   141	147	194	finally
    //   156	166	218	finally
    //   59	69	222	finally
  }

  // ERROR //
  static boolean bWb()
  {
    // Byte code:
    //   0: iconst_1
    //   1: istore_0
    //   2: sipush 10370
    //   5: invokestatic 20	com/tencent/matrix/trace/core/AppMethodBeat:i	(I)V
    //   8: new 22	java/lang/StringBuilder
    //   11: dup
    //   12: invokespecial 23	java/lang/StringBuilder:<init>	()V
    //   15: astore_1
    //   16: aload_1
    //   17: ldc 78
    //   19: invokestatic 31	com/tencent/mm/plugin/normsg/b/d:TQ	(Ljava/lang/String;)Ljava/lang/String;
    //   22: invokevirtual 35	java/lang/StringBuilder:append	(Ljava/lang/String;)Ljava/lang/StringBuilder;
    //   25: pop
    //   26: aload_1
    //   27: invokevirtual 39	java/lang/StringBuilder:toString	()Ljava/lang/String;
    //   30: astore_2
    //   31: aload_1
    //   32: iconst_0
    //   33: aload_1
    //   34: invokevirtual 43	java/lang/StringBuilder:length	()I
    //   37: invokevirtual 47	java/lang/StringBuilder:delete	(II)Ljava/lang/StringBuilder;
    //   40: pop
    //   41: aload_1
    //   42: ldc 2
    //   44: invokevirtual 50	java/lang/Object:hashCode	()I
    //   47: bipush 31
    //   49: iushr
    //   50: iconst_1
    //   51: ior
    //   52: iconst_1
    //   53: ixor
    //   54: invokevirtual 53	java/lang/StringBuilder:append	(I)Ljava/lang/StringBuilder;
    //   57: pop
    //   58: aload_1
    //   59: invokevirtual 39	java/lang/StringBuilder:toString	()Ljava/lang/String;
    //   62: aload_2
    //   63: aload_1
    //   64: invokevirtual 39	java/lang/StringBuilder:toString	()Ljava/lang/String;
    //   67: invokestatic 57	com/tencent/mm/plugin/normsg/b/a:fw	(Ljava/lang/String;Ljava/lang/String;)Ljava/lang/String;
    //   70: invokevirtual 63	java/lang/String:equals	(Ljava/lang/Object;)Z
    //   73: ifne +11 -> 84
    //   76: sipush 10370
    //   79: invokestatic 66	com/tencent/matrix/trace/core/AppMethodBeat:o	(I)V
    //   82: iload_0
    //   83: ireturn
    //   84: sipush 10370
    //   87: invokestatic 66	com/tencent/matrix/trace/core/AppMethodBeat:o	(I)V
    //   90: iconst_0
    //   91: istore_0
    //   92: goto -10 -> 82
    //   95: astore_2
    //   96: aload_1
    //   97: invokevirtual 39	java/lang/StringBuilder:toString	()Ljava/lang/String;
    //   100: astore_2
    //   101: aload_1
    //   102: iconst_0
    //   103: aload_1
    //   104: invokevirtual 43	java/lang/StringBuilder:length	()I
    //   107: invokevirtual 47	java/lang/StringBuilder:delete	(II)Ljava/lang/StringBuilder;
    //   110: pop
    //   111: aload_1
    //   112: ldc 2
    //   114: invokevirtual 50	java/lang/Object:hashCode	()I
    //   117: bipush 31
    //   119: iushr
    //   120: iconst_1
    //   121: ior
    //   122: iconst_1
    //   123: ixor
    //   124: invokevirtual 53	java/lang/StringBuilder:append	(I)Ljava/lang/StringBuilder;
    //   127: pop
    //   128: aload_1
    //   129: invokevirtual 39	java/lang/StringBuilder:toString	()Ljava/lang/String;
    //   132: aload_2
    //   133: aload_1
    //   134: invokevirtual 39	java/lang/StringBuilder:toString	()Ljava/lang/String;
    //   137: invokestatic 57	com/tencent/mm/plugin/normsg/b/a:fw	(Ljava/lang/String;Ljava/lang/String;)Ljava/lang/String;
    //   140: invokevirtual 63	java/lang/String:equals	(Ljava/lang/Object;)Z
    //   143: ifne +12 -> 155
    //   146: sipush 10370
    //   149: invokestatic 66	com/tencent/matrix/trace/core/AppMethodBeat:o	(I)V
    //   152: goto -70 -> 82
    //   155: sipush 10370
    //   158: invokestatic 66	com/tencent/matrix/trace/core/AppMethodBeat:o	(I)V
    //   161: iconst_0
    //   162: istore_0
    //   163: goto -81 -> 82
    //
    // Exception table:
    //   from	to	target	type
    //   16	26	95	finally
  }

  // ERROR //
  public static boolean isEnabled()
  {
    // Byte code:
    //   0: iconst_1
    //   1: istore_0
    //   2: sipush 10367
    //   5: invokestatic 20	com/tencent/matrix/trace/core/AppMethodBeat:i	(I)V
    //   8: new 22	java/lang/StringBuilder
    //   11: dup
    //   12: invokespecial 23	java/lang/StringBuilder:<init>	()V
    //   15: astore_1
    //   16: aload_1
    //   17: ldc 81
    //   19: invokestatic 31	com/tencent/mm/plugin/normsg/b/d:TQ	(Ljava/lang/String;)Ljava/lang/String;
    //   22: invokevirtual 35	java/lang/StringBuilder:append	(Ljava/lang/String;)Ljava/lang/StringBuilder;
    //   25: pop
    //   26: aload_1
    //   27: invokevirtual 39	java/lang/StringBuilder:toString	()Ljava/lang/String;
    //   30: astore_2
    //   31: aload_1
    //   32: iconst_0
    //   33: aload_1
    //   34: invokevirtual 43	java/lang/StringBuilder:length	()I
    //   37: invokevirtual 47	java/lang/StringBuilder:delete	(II)Ljava/lang/StringBuilder;
    //   40: pop
    //   41: aload_1
    //   42: ldc 2
    //   44: invokevirtual 50	java/lang/Object:hashCode	()I
    //   47: bipush 31
    //   49: iushr
    //   50: iconst_1
    //   51: ior
    //   52: iconst_1
    //   53: ixor
    //   54: invokevirtual 53	java/lang/StringBuilder:append	(I)Ljava/lang/StringBuilder;
    //   57: pop
    //   58: aload_1
    //   59: invokevirtual 39	java/lang/StringBuilder:toString	()Ljava/lang/String;
    //   62: aload_2
    //   63: aload_1
    //   64: invokevirtual 39	java/lang/StringBuilder:toString	()Ljava/lang/String;
    //   67: invokestatic 57	com/tencent/mm/plugin/normsg/b/a:fw	(Ljava/lang/String;Ljava/lang/String;)Ljava/lang/String;
    //   70: invokevirtual 63	java/lang/String:equals	(Ljava/lang/Object;)Z
    //   73: ifne +11 -> 84
    //   76: sipush 10367
    //   79: invokestatic 66	com/tencent/matrix/trace/core/AppMethodBeat:o	(I)V
    //   82: iload_0
    //   83: ireturn
    //   84: sipush 10367
    //   87: invokestatic 66	com/tencent/matrix/trace/core/AppMethodBeat:o	(I)V
    //   90: iconst_0
    //   91: istore_0
    //   92: goto -10 -> 82
    //   95: astore_2
    //   96: aload_1
    //   97: invokevirtual 39	java/lang/StringBuilder:toString	()Ljava/lang/String;
    //   100: astore_2
    //   101: aload_1
    //   102: iconst_0
    //   103: aload_1
    //   104: invokevirtual 43	java/lang/StringBuilder:length	()I
    //   107: invokevirtual 47	java/lang/StringBuilder:delete	(II)Ljava/lang/StringBuilder;
    //   110: pop
    //   111: aload_1
    //   112: ldc 2
    //   114: invokevirtual 50	java/lang/Object:hashCode	()I
    //   117: bipush 31
    //   119: iushr
    //   120: iconst_1
    //   121: ior
    //   122: iconst_1
    //   123: ixor
    //   124: invokevirtual 53	java/lang/StringBuilder:append	(I)Ljava/lang/StringBuilder;
    //   127: pop
    //   128: aload_1
    //   129: invokevirtual 39	java/lang/StringBuilder:toString	()Ljava/lang/String;
    //   132: aload_2
    //   133: aload_1
    //   134: invokevirtual 39	java/lang/StringBuilder:toString	()Ljava/lang/String;
    //   137: invokestatic 57	com/tencent/mm/plugin/normsg/b/a:fw	(Ljava/lang/String;Ljava/lang/String;)Ljava/lang/String;
    //   140: invokevirtual 63	java/lang/String:equals	(Ljava/lang/Object;)Z
    //   143: ifne +12 -> 155
    //   146: sipush 10367
    //   149: invokestatic 66	com/tencent/matrix/trace/core/AppMethodBeat:o	(I)V
    //   152: goto -70 -> 82
    //   155: sipush 10367
    //   158: invokestatic 66	com/tencent/matrix/trace/core/AppMethodBeat:o	(I)V
    //   161: iconst_0
    //   162: istore_0
    //   163: goto -81 -> 82
    //
    // Exception table:
    //   from	to	target	type
    //   16	26	95	finally
  }
}

/* Location:           C:\Users\Lin\Downloads\dex-tools-2.1-SNAPSHOT\dex-tools-2.1-SNAPSHOT\classes7-dex2jar.jar
 * Qualified Name:     com.tencent.mm.plugin.normsg.b.a.c
 * JD-Core Version:    0.6.2
 */