package com.tencent.mm.booter;

public final class w$1
  implements Runnable
{
  public w$1(w paramw)
  {
  }

  // ERROR //
  public final void run()
  {
    // Byte code:
    //   0: sipush 15873
    //   3: invokestatic 27	com/tencent/matrix/trace/core/AppMethodBeat:i	(I)V
    //   6: invokestatic 33	com/tencent/mm/platformtools/ah:anU	()J
    //   9: lstore_1
    //   10: bipush 10
    //   12: invokestatic 38	android/os/Process:setThreadPriority	(I)V
    //   15: aload_0
    //   16: getfield 14	com/tencent/mm/booter/w$1:ecM	Lcom/tencent/mm/booter/w;
    //   19: astore_3
    //   20: getstatic 44	com/tencent/mm/sdk/platformtools/g:cdf	I
    //   23: istore 4
    //   25: invokestatic 50	com/tencent/mm/compatible/e/q:LM	()Ljava/lang/String;
    //   28: astore 5
    //   30: getstatic 55	com/tencent/mm/protocal/d:vxo	I
    //   33: istore 6
    //   35: invokestatic 60	com/tencent/mm/sdk/platformtools/aa:dor	()Ljava/lang/String;
    //   38: astore 7
    //   40: aload_3
    //   41: getfield 64	com/tencent/mm/booter/w:context	Landroid/content/Context;
    //   44: invokestatic 69	com/tencent/mm/sdk/platformtools/ah:doA	()Ljava/lang/String;
    //   47: iconst_0
    //   48: invokevirtual 75	android/content/Context:getSharedPreferences	(Ljava/lang/String;I)Landroid/content/SharedPreferences;
    //   51: ldc 77
    //   53: iconst_0
    //   54: invokeinterface 83 3 0
    //   59: istore 8
    //   61: aload_3
    //   62: getfield 64	com/tencent/mm/booter/w:context	Landroid/content/Context;
    //   65: invokestatic 69	com/tencent/mm/sdk/platformtools/ah:doA	()Ljava/lang/String;
    //   68: iconst_0
    //   69: invokevirtual 75	android/content/Context:getSharedPreferences	(Ljava/lang/String;I)Landroid/content/SharedPreferences;
    //   72: ldc 85
    //   74: iconst_0
    //   75: invokeinterface 83 3 0
    //   80: istore 9
    //   82: iload 8
    //   84: ifne +130 -> 214
    //   87: iload 9
    //   89: ifne +125 -> 214
    //   92: iconst_0
    //   93: istore 9
    //   95: new 87	java/lang/StringBuilder
    //   98: dup
    //   99: ldc 89
    //   101: invokespecial 92	java/lang/StringBuilder:<init>	(Ljava/lang/String;)V
    //   104: getstatic 44	com/tencent/mm/sdk/platformtools/g:cdf	I
    //   107: invokevirtual 96	java/lang/StringBuilder:append	(I)Ljava/lang/StringBuilder;
    //   110: ldc 98
    //   112: invokevirtual 101	java/lang/StringBuilder:append	(Ljava/lang/String;)Ljava/lang/StringBuilder;
    //   115: aload 5
    //   117: invokevirtual 101	java/lang/StringBuilder:append	(Ljava/lang/String;)Ljava/lang/StringBuilder;
    //   120: ldc 103
    //   122: invokevirtual 101	java/lang/StringBuilder:append	(Ljava/lang/String;)Ljava/lang/StringBuilder;
    //   125: iload 6
    //   127: invokevirtual 96	java/lang/StringBuilder:append	(I)Ljava/lang/StringBuilder;
    //   130: ldc 105
    //   132: invokevirtual 101	java/lang/StringBuilder:append	(Ljava/lang/String;)Ljava/lang/StringBuilder;
    //   135: ldc 107
    //   137: invokevirtual 101	java/lang/StringBuilder:append	(Ljava/lang/String;)Ljava/lang/StringBuilder;
    //   140: ldc 109
    //   142: invokevirtual 101	java/lang/StringBuilder:append	(Ljava/lang/String;)Ljava/lang/StringBuilder;
    //   145: aload 7
    //   147: invokevirtual 101	java/lang/StringBuilder:append	(Ljava/lang/String;)Ljava/lang/StringBuilder;
    //   150: ldc 111
    //   152: invokevirtual 101	java/lang/StringBuilder:append	(Ljava/lang/String;)Ljava/lang/StringBuilder;
    //   155: iload 9
    //   157: invokevirtual 96	java/lang/StringBuilder:append	(I)Ljava/lang/StringBuilder;
    //   160: invokevirtual 114	java/lang/StringBuilder:toString	()Ljava/lang/String;
    //   163: astore_3
    //   164: ldc 116
    //   166: ldc 118
    //   168: iconst_3
    //   169: anewarray 4	java/lang/Object
    //   172: dup
    //   173: iconst_0
    //   174: invokestatic 124	java/lang/Thread:currentThread	()Ljava/lang/Thread;
    //   177: invokevirtual 127	java/lang/Thread:getName	()Ljava/lang/String;
    //   180: aastore
    //   181: dup
    //   182: iconst_1
    //   183: invokestatic 131	android/os/Process:myTid	()I
    //   186: invokestatic 135	android/os/Process:getThreadPriority	(I)I
    //   189: invokestatic 141	java/lang/Integer:valueOf	(I)Ljava/lang/Integer;
    //   192: aastore
    //   193: dup
    //   194: iconst_2
    //   195: aload_3
    //   196: aastore
    //   197: invokestatic 146	com/tencent/mm/sdk/platformtools/ab:i	(Ljava/lang/String;Ljava/lang/String;[Ljava/lang/Object;)V
    //   200: aload_3
    //   201: invokestatic 150	com/tencent/mm/platformtools/ah:isNullOrNil	(Ljava/lang/String;)Z
    //   204: ifeq +35 -> 239
    //   207: sipush 15873
    //   210: invokestatic 153	com/tencent/matrix/trace/core/AppMethodBeat:o	(I)V
    //   213: return
    //   214: iload 8
    //   216: iload 4
    //   218: if_icmpne +15 -> 233
    //   221: iload 9
    //   223: iload 6
    //   225: if_icmpne +8 -> 233
    //   228: aconst_null
    //   229: astore_3
    //   230: goto -66 -> 164
    //   233: iconst_1
    //   234: istore 9
    //   236: goto -141 -> 95
    //   239: aload_3
    //   240: aconst_null
    //   241: invokestatic 159	com/tencent/mm/network/b:a	(Ljava/lang/String;Lcom/tencent/mm/network/b$b;)Lcom/tencent/mm/network/u;
    //   244: astore 7
    //   246: aload 7
    //   248: sipush 10000
    //   251: invokevirtual 164	com/tencent/mm/network/u:setConnectTimeout	(I)V
    //   254: aload 7
    //   256: sipush 10000
    //   259: invokevirtual 167	com/tencent/mm/network/u:setReadTimeout	(I)V
    //   262: aload 7
    //   264: invokevirtual 170	com/tencent/mm/network/u:connect	()V
    //   267: aload 7
    //   269: invokevirtual 173	com/tencent/mm/network/u:getResponseCode	()I
    //   272: istore 9
    //   274: iload 9
    //   276: sipush 200
    //   279: if_icmpne +77 -> 356
    //   282: aload_0
    //   283: getfield 14	com/tencent/mm/booter/w$1:ecM	Lcom/tencent/mm/booter/w;
    //   286: astore 5
    //   288: getstatic 44	com/tencent/mm/sdk/platformtools/g:cdf	I
    //   291: istore 8
    //   293: getstatic 55	com/tencent/mm/protocal/d:vxo	I
    //   296: istore 6
    //   298: aload 5
    //   300: getfield 64	com/tencent/mm/booter/w:context	Landroid/content/Context;
    //   303: invokestatic 69	com/tencent/mm/sdk/platformtools/ah:doA	()Ljava/lang/String;
    //   306: iconst_0
    //   307: invokevirtual 75	android/content/Context:getSharedPreferences	(Ljava/lang/String;I)Landroid/content/SharedPreferences;
    //   310: astore 5
    //   312: aload 5
    //   314: invokeinterface 177 1 0
    //   319: ldc 77
    //   321: iload 8
    //   323: invokeinterface 183 3 0
    //   328: invokeinterface 187 1 0
    //   333: pop
    //   334: aload 5
    //   336: invokeinterface 177 1 0
    //   341: ldc 85
    //   343: iload 6
    //   345: invokeinterface 183 3 0
    //   350: invokeinterface 187 1 0
    //   355: pop
    //   356: ldc 116
    //   358: ldc 189
    //   360: iconst_3
    //   361: anewarray 4	java/lang/Object
    //   364: dup
    //   365: iconst_0
    //   366: lload_1
    //   367: invokestatic 193	com/tencent/mm/platformtools/ah:gb	(J)J
    //   370: invokestatic 198	java/lang/Long:valueOf	(J)Ljava/lang/Long;
    //   373: aastore
    //   374: dup
    //   375: iconst_1
    //   376: iload 9
    //   378: invokestatic 141	java/lang/Integer:valueOf	(I)Ljava/lang/Integer;
    //   381: aastore
    //   382: dup
    //   383: iconst_2
    //   384: aload_3
    //   385: aastore
    //   386: invokestatic 201	com/tencent/mm/sdk/platformtools/ab:d	(Ljava/lang/String;Ljava/lang/String;[Ljava/lang/Object;)V
    //   389: aload 7
    //   391: ifnull +11 -> 402
    //   394: aload 7
    //   396: getfield 205	com/tencent/mm/network/u:connection	Ljava/net/HttpURLConnection;
    //   399: invokevirtual 210	java/net/HttpURLConnection:disconnect	()V
    //   402: sipush 15873
    //   405: invokestatic 153	com/tencent/matrix/trace/core/AppMethodBeat:o	(I)V
    //   408: goto -195 -> 213
    //   411: astore 5
    //   413: aconst_null
    //   414: astore 7
    //   416: ldc 116
    //   418: aload 5
    //   420: ldc 212
    //   422: iconst_0
    //   423: anewarray 4	java/lang/Object
    //   426: invokestatic 216	com/tencent/mm/sdk/platformtools/ab:printErrStackTrace	(Ljava/lang/String;Ljava/lang/Throwable;Ljava/lang/String;[Ljava/lang/Object;)V
    //   429: ldc 116
    //   431: ldc 218
    //   433: iconst_1
    //   434: anewarray 4	java/lang/Object
    //   437: dup
    //   438: iconst_0
    //   439: aload_3
    //   440: aastore
    //   441: invokestatic 221	com/tencent/mm/sdk/platformtools/ab:e	(Ljava/lang/String;Ljava/lang/String;[Ljava/lang/Object;)V
    //   444: goto -55 -> 389
    //   447: astore 5
    //   449: goto -33 -> 416
    //
    // Exception table:
    //   from	to	target	type
    //   239	246	411	java/lang/Exception
    //   246	274	447	java/lang/Exception
    //   282	356	447	java/lang/Exception
    //   356	389	447	java/lang/Exception
  }
}

/* Location:           C:\Users\Lin\Downloads\dex-tools-2.1-SNAPSHOT\dex-tools-2.1-SNAPSHOT\classes8-dex2jar.jar
 * Qualified Name:     com.tencent.mm.booter.w.1
 * JD-Core Version:    0.6.2
 */