package android.support.v7.widget;

import android.os.AsyncTask;

final class e$e extends AsyncTask<Object, Void, Void>
{
  e$e(e parame)
  {
  }

  // ERROR //
  private Void b(Object[] paramArrayOfObject)
  {
    // Byte code:
    //   0: iconst_0
    //   1: istore_2
    //   2: aload_1
    //   3: iconst_0
    //   4: aaload
    //   5: checkcast 30	java/util/List
    //   8: astore_3
    //   9: aload_1
    //   10: iconst_1
    //   11: aaload
    //   12: checkcast 32	java/lang/String
    //   15: astore_1
    //   16: aload_0
    //   17: getfield 14	android/support/v7/widget/e$e:aez	Landroid/support/v7/widget/e;
    //   20: getfield 36	android/support/v7/widget/e:mContext	Landroid/content/Context;
    //   23: aload_1
    //   24: iconst_0
    //   25: invokevirtual 42	android/content/Context:openFileOutput	(Ljava/lang/String;I)Ljava/io/FileOutputStream;
    //   28: astore_1
    //   29: invokestatic 48	android/util/Xml:newSerializer	()Lorg/xmlpull/v1/XmlSerializer;
    //   32: astore 4
    //   34: aload 4
    //   36: aload_1
    //   37: aconst_null
    //   38: invokeinterface 54 3 0
    //   43: aload 4
    //   45: ldc 56
    //   47: getstatic 62	java/lang/Boolean:TRUE	Ljava/lang/Boolean;
    //   50: invokeinterface 66 3 0
    //   55: aload 4
    //   57: aconst_null
    //   58: ldc 68
    //   60: invokeinterface 72 3 0
    //   65: pop
    //   66: aload_3
    //   67: invokeinterface 76 1 0
    //   72: istore 5
    //   74: iload_2
    //   75: iload 5
    //   77: if_icmpge +107 -> 184
    //   80: aload_3
    //   81: iconst_0
    //   82: invokeinterface 80 2 0
    //   87: checkcast 82	android/support/v7/widget/e$c
    //   90: astore 6
    //   92: aload 4
    //   94: aconst_null
    //   95: ldc 84
    //   97: invokeinterface 72 3 0
    //   102: pop
    //   103: aload 4
    //   105: aconst_null
    //   106: ldc 86
    //   108: aload 6
    //   110: getfield 90	android/support/v7/widget/e$c:aey	Landroid/content/ComponentName;
    //   113: invokevirtual 96	android/content/ComponentName:flattenToString	()Ljava/lang/String;
    //   116: invokeinterface 100 4 0
    //   121: pop
    //   122: aload 4
    //   124: aconst_null
    //   125: ldc 102
    //   127: aload 6
    //   129: getfield 105	android/support/v7/widget/e$c:time	J
    //   132: invokestatic 109	java/lang/String:valueOf	(J)Ljava/lang/String;
    //   135: invokeinterface 100 4 0
    //   140: pop
    //   141: aload 4
    //   143: aconst_null
    //   144: ldc 111
    //   146: aload 6
    //   148: getfield 114	android/support/v7/widget/e$c:weight	F
    //   151: invokestatic 117	java/lang/String:valueOf	(F)Ljava/lang/String;
    //   154: invokeinterface 100 4 0
    //   159: pop
    //   160: aload 4
    //   162: aconst_null
    //   163: ldc 84
    //   165: invokeinterface 120 3 0
    //   170: pop
    //   171: iinc 2 1
    //   174: goto -100 -> 74
    //   177: astore_1
    //   178: getstatic 124	android/support/v7/widget/e:LOG_TAG	Ljava/lang/String;
    //   181: astore_1
    //   182: aconst_null
    //   183: areturn
    //   184: aload 4
    //   186: aconst_null
    //   187: ldc 68
    //   189: invokeinterface 120 3 0
    //   194: pop
    //   195: aload 4
    //   197: invokeinterface 127 1 0
    //   202: aload_0
    //   203: getfield 14	android/support/v7/widget/e$e:aez	Landroid/support/v7/widget/e;
    //   206: iconst_1
    //   207: putfield 131	android/support/v7/widget/e:aet	Z
    //   210: aload_1
    //   211: ifnull -29 -> 182
    //   214: aload_1
    //   215: invokevirtual 136	java/io/FileOutputStream:close	()V
    //   218: goto -36 -> 182
    //   221: astore_1
    //   222: goto -40 -> 182
    //   225: astore_3
    //   226: getstatic 124	android/support/v7/widget/e:LOG_TAG	Ljava/lang/String;
    //   229: astore_3
    //   230: new 138	java/lang/StringBuilder
    //   233: astore_3
    //   234: aload_3
    //   235: ldc 140
    //   237: invokespecial 143	java/lang/StringBuilder:<init>	(Ljava/lang/String;)V
    //   240: aload_3
    //   241: aload_0
    //   242: getfield 14	android/support/v7/widget/e$e:aez	Landroid/support/v7/widget/e;
    //   245: getfield 146	android/support/v7/widget/e:aeq	Ljava/lang/String;
    //   248: invokevirtual 150	java/lang/StringBuilder:append	(Ljava/lang/String;)Ljava/lang/StringBuilder;
    //   251: pop
    //   252: aload_0
    //   253: getfield 14	android/support/v7/widget/e$e:aez	Landroid/support/v7/widget/e;
    //   256: iconst_1
    //   257: putfield 131	android/support/v7/widget/e:aet	Z
    //   260: aload_1
    //   261: ifnull -79 -> 182
    //   264: aload_1
    //   265: invokevirtual 136	java/io/FileOutputStream:close	()V
    //   268: goto -86 -> 182
    //   271: astore_1
    //   272: goto -90 -> 182
    //   275: astore_3
    //   276: getstatic 124	android/support/v7/widget/e:LOG_TAG	Ljava/lang/String;
    //   279: astore_3
    //   280: new 138	java/lang/StringBuilder
    //   283: astore_3
    //   284: aload_3
    //   285: ldc 140
    //   287: invokespecial 143	java/lang/StringBuilder:<init>	(Ljava/lang/String;)V
    //   290: aload_3
    //   291: aload_0
    //   292: getfield 14	android/support/v7/widget/e$e:aez	Landroid/support/v7/widget/e;
    //   295: getfield 146	android/support/v7/widget/e:aeq	Ljava/lang/String;
    //   298: invokevirtual 150	java/lang/StringBuilder:append	(Ljava/lang/String;)Ljava/lang/StringBuilder;
    //   301: pop
    //   302: aload_0
    //   303: getfield 14	android/support/v7/widget/e$e:aez	Landroid/support/v7/widget/e;
    //   306: iconst_1
    //   307: putfield 131	android/support/v7/widget/e:aet	Z
    //   310: aload_1
    //   311: ifnull -129 -> 182
    //   314: aload_1
    //   315: invokevirtual 136	java/io/FileOutputStream:close	()V
    //   318: goto -136 -> 182
    //   321: astore_1
    //   322: goto -140 -> 182
    //   325: astore_3
    //   326: getstatic 124	android/support/v7/widget/e:LOG_TAG	Ljava/lang/String;
    //   329: astore_3
    //   330: new 138	java/lang/StringBuilder
    //   333: astore_3
    //   334: aload_3
    //   335: ldc 140
    //   337: invokespecial 143	java/lang/StringBuilder:<init>	(Ljava/lang/String;)V
    //   340: aload_3
    //   341: aload_0
    //   342: getfield 14	android/support/v7/widget/e$e:aez	Landroid/support/v7/widget/e;
    //   345: getfield 146	android/support/v7/widget/e:aeq	Ljava/lang/String;
    //   348: invokevirtual 150	java/lang/StringBuilder:append	(Ljava/lang/String;)Ljava/lang/StringBuilder;
    //   351: pop
    //   352: aload_0
    //   353: getfield 14	android/support/v7/widget/e$e:aez	Landroid/support/v7/widget/e;
    //   356: iconst_1
    //   357: putfield 131	android/support/v7/widget/e:aet	Z
    //   360: aload_1
    //   361: ifnull -179 -> 182
    //   364: aload_1
    //   365: invokevirtual 136	java/io/FileOutputStream:close	()V
    //   368: goto -186 -> 182
    //   371: astore_1
    //   372: goto -190 -> 182
    //   375: astore_3
    //   376: aload_0
    //   377: getfield 14	android/support/v7/widget/e$e:aez	Landroid/support/v7/widget/e;
    //   380: iconst_1
    //   381: putfield 131	android/support/v7/widget/e:aet	Z
    //   384: aload_1
    //   385: ifnull +7 -> 392
    //   388: aload_1
    //   389: invokevirtual 136	java/io/FileOutputStream:close	()V
    //   392: aload_3
    //   393: athrow
    //   394: astore_1
    //   395: goto -3 -> 392
    //
    // Exception table:
    //   from	to	target	type
    //   16	29	177	java/io/FileNotFoundException
    //   214	218	221	java/io/IOException
    //   34	74	225	java/lang/IllegalArgumentException
    //   80	171	225	java/lang/IllegalArgumentException
    //   184	202	225	java/lang/IllegalArgumentException
    //   264	268	271	java/io/IOException
    //   34	74	275	java/lang/IllegalStateException
    //   80	171	275	java/lang/IllegalStateException
    //   184	202	275	java/lang/IllegalStateException
    //   314	318	321	java/io/IOException
    //   34	74	325	java/io/IOException
    //   80	171	325	java/io/IOException
    //   184	202	325	java/io/IOException
    //   364	368	371	java/io/IOException
    //   34	74	375	finally
    //   80	171	375	finally
    //   184	202	375	finally
    //   226	252	375	finally
    //   276	302	375	finally
    //   326	352	375	finally
    //   388	392	394	java/io/IOException
  }
}

/* Location:           C:\Users\Lin\Downloads\dex-tools-2.1-SNAPSHOT\dex-tools-2.1-SNAPSHOT\classes-dex2jar.jar
 * Qualified Name:     android.support.v7.widget.e.e
 * JD-Core Version:    0.6.2
 */