package org.apache.commons.a;

public final class c
{
  public static final char DIR_SEPARATOR;
  public static final String LINE_SEPARATOR;

  // ERROR //
  static
  {
    // Byte code:
    //   0: aconst_null
    //   1: astore_0
    //   2: ldc 13
    //   4: invokestatic 19	com/tencent/matrix/trace/core/AppMethodBeat:i	(I)V
    //   7: getstatic 24	java/io/File:separatorChar	C
    //   10: i2c
    //   11: putstatic 26	org/apache/commons/a/c:DIR_SEPARATOR	C
    //   14: new 28	org/apache/commons/a/a/b
    //   17: dup
    //   18: iconst_0
    //   19: invokespecial 32	org/apache/commons/a/a/b:<init>	(B)V
    //   22: astore_1
    //   23: new 34	java/io/PrintWriter
    //   26: astore_2
    //   27: aload_2
    //   28: aload_1
    //   29: invokespecial 37	java/io/PrintWriter:<init>	(Ljava/io/Writer;)V
    //   32: aload_2
    //   33: invokevirtual 40	java/io/PrintWriter:println	()V
    //   36: aload_1
    //   37: invokevirtual 44	org/apache/commons/a/a/b:toString	()Ljava/lang/String;
    //   40: putstatic 46	org/apache/commons/a/c:LINE_SEPARATOR	Ljava/lang/String;
    //   43: aload_2
    //   44: invokevirtual 49	java/io/PrintWriter:close	()V
    //   47: aload_1
    //   48: invokevirtual 50	org/apache/commons/a/a/b:close	()V
    //   51: ldc 13
    //   53: invokestatic 53	com/tencent/matrix/trace/core/AppMethodBeat:o	(I)V
    //   56: return
    //   57: astore_3
    //   58: ldc 13
    //   60: invokestatic 53	com/tencent/matrix/trace/core/AppMethodBeat:o	(I)V
    //   63: aload_3
    //   64: athrow
    //   65: astore 4
    //   67: aload_3
    //   68: ifnull +57 -> 125
    //   71: aload_2
    //   72: invokevirtual 49	java/io/PrintWriter:close	()V
    //   75: ldc 13
    //   77: invokestatic 53	com/tencent/matrix/trace/core/AppMethodBeat:o	(I)V
    //   80: aload 4
    //   82: athrow
    //   83: astore_3
    //   84: ldc 13
    //   86: invokestatic 53	com/tencent/matrix/trace/core/AppMethodBeat:o	(I)V
    //   89: aload_3
    //   90: athrow
    //   91: astore 4
    //   93: aload_3
    //   94: ifnull +47 -> 141
    //   97: aload_1
    //   98: invokevirtual 50	org/apache/commons/a/a/b:close	()V
    //   101: ldc 13
    //   103: invokestatic 53	com/tencent/matrix/trace/core/AppMethodBeat:o	(I)V
    //   106: aload 4
    //   108: athrow
    //   109: astore_2
    //   110: aload_3
    //   111: aload_2
    //   112: invokevirtual 57	java/lang/Throwable:addSuppressed	(Ljava/lang/Throwable;)V
    //   115: goto -40 -> 75
    //   118: astore 4
    //   120: aload_0
    //   121: astore_3
    //   122: goto -29 -> 93
    //   125: aload_2
    //   126: invokevirtual 49	java/io/PrintWriter:close	()V
    //   129: goto -54 -> 75
    //   132: astore_0
    //   133: aload_3
    //   134: aload_0
    //   135: invokevirtual 57	java/lang/Throwable:addSuppressed	(Ljava/lang/Throwable;)V
    //   138: goto -37 -> 101
    //   141: aload_1
    //   142: invokevirtual 50	org/apache/commons/a/a/b:close	()V
    //   145: goto -44 -> 101
    //   148: astore 4
    //   150: aconst_null
    //   151: astore_3
    //   152: goto -85 -> 67
    //
    // Exception table:
    //   from	to	target	type
    //   32	43	57	java/lang/Throwable
    //   58	65	65	finally
    //   23	32	83	java/lang/Throwable
    //   43	47	83	java/lang/Throwable
    //   75	83	83	java/lang/Throwable
    //   110	115	83	java/lang/Throwable
    //   125	129	83	java/lang/Throwable
    //   84	91	91	finally
    //   71	75	109	java/lang/Throwable
    //   23	32	118	finally
    //   43	47	118	finally
    //   71	75	118	finally
    //   75	83	118	finally
    //   110	115	118	finally
    //   125	129	118	finally
    //   97	101	132	java/lang/Throwable
    //   32	43	148	finally
  }

  // ERROR //
  public static byte[] toByteArray(java.io.InputStream paramInputStream)
  {
    // Byte code:
    //   0: ldc 61
    //   2: invokestatic 19	com/tencent/matrix/trace/core/AppMethodBeat:i	(I)V
    //   5: new 63	org/apache/commons/a/a/a
    //   8: dup
    //   9: invokespecial 65	org/apache/commons/a/a/a:<init>	()V
    //   12: astore_1
    //   13: aconst_null
    //   14: astore_2
    //   15: sipush 4096
    //   18: newarray byte
    //   20: astore_3
    //   21: aload_0
    //   22: aload_3
    //   23: invokevirtual 71	java/io/InputStream:read	([B)I
    //   26: istore 4
    //   28: iconst_m1
    //   29: iload 4
    //   31: if_icmpeq +38 -> 69
    //   34: aload_1
    //   35: aload_3
    //   36: iconst_0
    //   37: iload 4
    //   39: invokevirtual 77	java/io/OutputStream:write	([BII)V
    //   42: goto -21 -> 21
    //   45: astore_2
    //   46: ldc 61
    //   48: invokestatic 53	com/tencent/matrix/trace/core/AppMethodBeat:o	(I)V
    //   51: aload_2
    //   52: athrow
    //   53: astore_0
    //   54: aload_2
    //   55: ifnull +39 -> 94
    //   58: aload_1
    //   59: invokevirtual 78	org/apache/commons/a/a/a:close	()V
    //   62: ldc 61
    //   64: invokestatic 53	com/tencent/matrix/trace/core/AppMethodBeat:o	(I)V
    //   67: aload_0
    //   68: athrow
    //   69: aload_1
    //   70: invokevirtual 81	org/apache/commons/a/a/a:toByteArray	()[B
    //   73: astore_0
    //   74: aload_1
    //   75: invokevirtual 78	org/apache/commons/a/a/a:close	()V
    //   78: ldc 61
    //   80: invokestatic 53	com/tencent/matrix/trace/core/AppMethodBeat:o	(I)V
    //   83: aload_0
    //   84: areturn
    //   85: astore_1
    //   86: aload_2
    //   87: aload_1
    //   88: invokevirtual 57	java/lang/Throwable:addSuppressed	(Ljava/lang/Throwable;)V
    //   91: goto -29 -> 62
    //   94: aload_1
    //   95: invokevirtual 78	org/apache/commons/a/a/a:close	()V
    //   98: goto -36 -> 62
    //   101: astore_0
    //   102: goto -48 -> 54
    //
    // Exception table:
    //   from	to	target	type
    //   15	21	45	java/lang/Throwable
    //   21	28	45	java/lang/Throwable
    //   34	42	45	java/lang/Throwable
    //   69	74	45	java/lang/Throwable
    //   46	53	53	finally
    //   58	62	85	java/lang/Throwable
    //   15	21	101	finally
    //   21	28	101	finally
    //   34	42	101	finally
    //   69	74	101	finally
  }
}

/* Location:           C:\Users\Lin\Downloads\dex-tools-2.1-SNAPSHOT\dex-tools-2.1-SNAPSHOT\classes4-dex2jar.jar
 * Qualified Name:     org.apache.commons.a.c
 * JD-Core Version:    0.6.2
 */