package a.i.b.a.c.e.b;

import a.i.b.a.c.e.a.a;
import a.i.b.a.c.e.a.aa;
import a.i.b.a.c.e.a.ae;
import a.i.b.a.c.e.a.c;
import a.i.b.a.c.e.a.e;
import a.i.b.a.c.e.a.o;
import a.i.b.a.c.e.a.s;
import a.i.b.a.c.e.a.u;
import a.i.b.a.c.g.d;
import a.i.b.a.c.g.g;
import a.i.b.a.c.g.i;
import a.i.b.a.c.g.i.a;
import a.i.b.a.c.g.i.f;
import a.i.b.a.c.g.z.a;
import com.tencent.matrix.trace.core.AppMethodBeat;
import java.util.List;

public final class b
{
  public static final i.f<a.o, b.c> BxA;
  public static final i.f<a.o, Integer> BxB;
  public static final i.f<a.u, b.e> BxC;
  public static final i.f<a.u, Integer> BxD;
  public static final i.f<a.aa, List<a.a>> BxE;
  public static final i.f<a.aa, Boolean> BxF;
  public static final i.f<a.ae, List<a.a>> BxG;
  public static final i.f<a.c, Integer> BxH;
  public static final i.f<a.c, List<a.u>> BxI;
  public static final i.f<a.c, Integer> BxJ;
  public static final i.f<a.s, Integer> BxK;
  public static final i.f<a.s, List<a.u>> BxL;
  public static final i.f<a.e, b.c> Bxz;

  static
  {
    AppMethodBeat.i(121297);
    Bxz = i.a(a.e.edC(), b.c.egQ(), b.c.egQ(), 100, z.a.BBb, b.c.class);
    BxA = i.a(a.o.eek(), b.c.egQ(), b.c.egQ(), 100, z.a.BBb, b.c.class);
    BxB = i.a(a.o.eek(), Integer.valueOf(0), null, 101, z.a.BAV, Integer.class);
    BxC = i.a(a.u.eey(), b.e.egV(), b.e.egV(), 100, z.a.BBb, b.e.class);
    BxD = i.a(a.u.eey(), Integer.valueOf(0), null, 101, z.a.BAV, Integer.class);
    BxE = i.a(a.aa.eeX(), a.a.ecx(), 100, z.a.BBb, a.a.class);
    BxF = i.a(a.aa.eeX(), Boolean.FALSE, null, 101, z.a.BAY, Boolean.class);
    BxG = i.a(a.ae.efE(), a.a.ecx(), 100, z.a.BBb, a.a.class);
    BxH = i.a(a.c.edi(), Integer.valueOf(0), null, 101, z.a.BAV, Integer.class);
    BxI = i.a(a.c.edi(), a.u.eey(), 102, z.a.BBb, a.u.class);
    BxJ = i.a(a.c.edi(), Integer.valueOf(0), null, 103, z.a.BAV, Integer.class);
    BxK = i.a(a.s.eeu(), Integer.valueOf(0), null, 101, z.a.BAV, Integer.class);
    BxL = i.a(a.s.eeu(), a.u.eey(), 102, z.a.BBb, a.u.class);
    AppMethodBeat.o(121297);
  }

  public static void a(g paramg)
  {
    AppMethodBeat.i(121296);
    paramg.a(Bxz);
    paramg.a(BxA);
    paramg.a(BxB);
    paramg.a(BxC);
    paramg.a(BxD);
    paramg.a(BxE);
    paramg.a(BxF);
    paramg.a(BxG);
    paramg.a(BxH);
    paramg.a(BxI);
    paramg.a(BxJ);
    paramg.a(BxK);
    paramg.a(BxL);
    AppMethodBeat.o(121296);
  }

  public static final class a$a extends i.a<b.a, a>
    implements b.b
  {
    private int BsD;
    private int Buf;
    private int BxN;

    // ERROR //
    private a C(a.i.b.a.c.g.e parame, g paramg)
    {
      // Byte code:
      //   0: ldc 24
      //   2: invokestatic 30	com/tencent/matrix/trace/core/AppMethodBeat:i	(I)V
      //   5: aconst_null
      //   6: astore_3
      //   7: getstatic 34	a/i/b/a/c/e/b/b$a:BsC	La/i/b/a/c/g/s;
      //   10: aload_1
      //   11: aload_2
      //   12: invokeinterface 39 3 0
      //   17: checkcast 9	a/i/b/a/c/e/b/b$a
      //   20: astore_1
      //   21: aload_0
      //   22: aload_1
      //   23: invokevirtual 43	a/i/b/a/c/e/b/b$a$a:c	(La/i/b/a/c/e/b/b$a;)La/i/b/a/c/e/b/b$a$a;
      //   26: pop
      //   27: ldc 24
      //   29: invokestatic 46	com/tencent/matrix/trace/core/AppMethodBeat:o	(I)V
      //   32: aload_0
      //   33: areturn
      //   34: astore_1
      //   35: aload_1
      //   36: getfield 50	a/i/b/a/c/g/k:BzY	La/i/b/a/c/g/q;
      //   39: checkcast 9	a/i/b/a/c/e/b/b$a
      //   42: astore_2
      //   43: ldc 24
      //   45: invokestatic 46	com/tencent/matrix/trace/core/AppMethodBeat:o	(I)V
      //   48: aload_1
      //   49: athrow
      //   50: astore_1
      //   51: aload_2
      //   52: ifnull +9 -> 61
      //   55: aload_0
      //   56: aload_2
      //   57: invokevirtual 43	a/i/b/a/c/e/b/b$a$a:c	(La/i/b/a/c/e/b/b$a;)La/i/b/a/c/e/b/b$a$a;
      //   60: pop
      //   61: ldc 24
      //   63: invokestatic 46	com/tencent/matrix/trace/core/AppMethodBeat:o	(I)V
      //   66: aload_1
      //   67: athrow
      //   68: astore_1
      //   69: aload_3
      //   70: astore_2
      //   71: goto -20 -> 51
      //
      // Exception table:
      //   from	to	target	type
      //   7	21	34	a/i/b/a/c/g/k
      //   43	50	50	finally
      //   7	21	68	finally
      //   35	43	68	finally
    }

    private a Ul(int paramInt)
    {
      this.BsD |= 1;
      this.Buf = paramInt;
      return this;
    }

    private a Um(int paramInt)
    {
      this.BsD |= 2;
      this.BxN = paramInt;
      return this;
    }

    private a egN()
    {
      AppMethodBeat.i(121164);
      a locala = new a().c(egO());
      AppMethodBeat.o(121164);
      return locala;
    }

    public final a c(b.a parama)
    {
      AppMethodBeat.i(121166);
      if (parama == b.a.egK())
        AppMethodBeat.o(121166);
      while (true)
      {
        return this;
        if (parama.edW())
          Ul(parama.Buf);
        if (parama.egL())
          Um(parama.BxN);
        this.BsB = this.BsB.a(b.a.b(parama));
        AppMethodBeat.o(121166);
      }
    }

    public final b.a egO()
    {
      int i = 1;
      AppMethodBeat.i(121165);
      b.a locala = new b.a(this, (byte)0);
      int j = this.BsD;
      if ((j & 0x1) == 1);
      while (true)
      {
        b.a.a(locala, this.Buf);
        int k = i;
        if ((j & 0x2) == 2)
          k = i | 0x2;
        b.a.b(locala, this.BxN);
        b.a.c(locala, k);
        AppMethodBeat.o(121165);
        return locala;
        i = 0;
      }
    }

    public final boolean isInitialized()
    {
      return true;
    }
  }
}

/* Location:           C:\Users\Lin\Downloads\dex-tools-2.1-SNAPSHOT\dex-tools-2.1-SNAPSHOT\classes-dex2jar.jar
 * Qualified Name:     a.i.b.a.c.e.b.b
 * JD-Core Version:    0.6.2
 */