package com.tencent.mm.plugin.dbbackup.a;

public final class b
{
  // ERROR //
  public static boolean Ii(java.lang.String paramString)
  {
    // Byte code:
    //   0: iconst_1
    //   1: istore_1
    //   2: aconst_null
    //   3: astore_2
    //   4: aconst_null
    //   5: astore_3
    //   6: sipush 19032
    //   9: invokestatic 14	com/tencent/matrix/trace/core/AppMethodBeat:i	(I)V
    //   12: new 16	com/tencent/mm/vfs/b
    //   15: dup
    //   16: invokestatic 22	com/tencent/mm/sdk/platformtools/ah:getContext	()Landroid/content/Context;
    //   19: ldc 24
    //   21: invokevirtual 30	android/content/Context:getFileStreamPath	(Ljava/lang/String;)Ljava/io/File;
    //   24: invokespecial 34	com/tencent/mm/vfs/b:<init>	(Ljava/io/File;)V
    //   27: astore 4
    //   29: new 16	com/tencent/mm/vfs/b
    //   32: dup
    //   33: new 36	java/lang/StringBuilder
    //   36: dup
    //   37: invokespecial 39	java/lang/StringBuilder:<init>	()V
    //   40: aload 4
    //   42: getfield 43	com/tencent/mm/vfs/b:mUri	Landroid/net/Uri;
    //   45: invokestatic 49	com/tencent/mm/vfs/j:w	(Landroid/net/Uri;)Ljava/lang/String;
    //   48: invokevirtual 53	java/lang/StringBuilder:append	(Ljava/lang/String;)Ljava/lang/StringBuilder;
    //   51: ldc 55
    //   53: invokevirtual 53	java/lang/StringBuilder:append	(Ljava/lang/String;)Ljava/lang/StringBuilder;
    //   56: invokevirtual 59	java/lang/StringBuilder:toString	()Ljava/lang/String;
    //   59: invokespecial 62	com/tencent/mm/vfs/b:<init>	(Ljava/lang/String;)V
    //   62: astore 5
    //   64: new 64	javax/crypto/spec/SecretKeySpec
    //   67: dup
    //   68: ldc 66
    //   70: invokevirtual 72	java/lang/String:getBytes	()[B
    //   73: ldc 74
    //   75: invokespecial 77	javax/crypto/spec/SecretKeySpec:<init>	([BLjava/lang/String;)V
    //   78: astore 6
    //   80: ldc 74
    //   82: invokestatic 83	javax/crypto/Cipher:getInstance	(Ljava/lang/String;)Ljavax/crypto/Cipher;
    //   85: astore 7
    //   87: new 85	java/util/LinkedHashSet
    //   90: dup
    //   91: invokespecial 86	java/util/LinkedHashSet:<init>	()V
    //   94: astore 8
    //   96: aload 7
    //   98: iconst_2
    //   99: aload 6
    //   101: invokevirtual 90	javax/crypto/Cipher:init	(ILjava/security/Key;)V
    //   104: new 92	java/io/BufferedReader
    //   107: astore 9
    //   109: new 94	java/io/InputStreamReader
    //   112: astore 10
    //   114: new 96	javax/crypto/CipherInputStream
    //   117: astore 11
    //   119: aload 11
    //   121: aload 4
    //   123: invokestatic 102	com/tencent/mm/vfs/e:p	(Lcom/tencent/mm/vfs/b;)Ljava/io/InputStream;
    //   126: aload 7
    //   128: invokespecial 105	javax/crypto/CipherInputStream:<init>	(Ljava/io/InputStream;Ljavax/crypto/Cipher;)V
    //   131: aload 10
    //   133: aload 11
    //   135: invokespecial 108	java/io/InputStreamReader:<init>	(Ljava/io/InputStream;)V
    //   138: aload 9
    //   140: aload 10
    //   142: invokespecial 111	java/io/BufferedReader:<init>	(Ljava/io/Reader;)V
    //   145: aload 9
    //   147: astore 11
    //   149: aload 9
    //   151: invokevirtual 114	java/io/BufferedReader:readLine	()Ljava/lang/String;
    //   154: astore 10
    //   156: aload 10
    //   158: ifnull +251 -> 409
    //   161: aload 9
    //   163: astore 11
    //   165: aload 10
    //   167: aload_0
    //   168: invokevirtual 118	java/lang/String:equals	(Ljava/lang/Object;)Z
    //   171: ifeq +51 -> 222
    //   174: aload 9
    //   176: astore 11
    //   178: ldc 120
    //   180: ldc 122
    //   182: invokestatic 127	com/tencent/mm/sdk/platformtools/ab:i	(Ljava/lang/String;Ljava/lang/String;)V
    //   185: aload 9
    //   187: invokestatic 133	com/tencent/mm/sdk/platformtools/bo:b	(Ljava/io/Closeable;)V
    //   190: sipush 19032
    //   193: invokestatic 136	com/tencent/matrix/trace/core/AppMethodBeat:o	(I)V
    //   196: iload_1
    //   197: ireturn
    //   198: astore_0
    //   199: ldc 120
    //   201: aload_0
    //   202: ldc 138
    //   204: iconst_0
    //   205: anewarray 4	java/lang/Object
    //   208: invokestatic 142	com/tencent/mm/sdk/platformtools/ab:printErrStackTrace	(Ljava/lang/String;Ljava/lang/Throwable;Ljava/lang/String;[Ljava/lang/Object;)V
    //   211: sipush 19032
    //   214: invokestatic 136	com/tencent/matrix/trace/core/AppMethodBeat:o	(I)V
    //   217: iconst_0
    //   218: istore_1
    //   219: goto -23 -> 196
    //   222: aload 9
    //   224: astore 11
    //   226: aload 8
    //   228: aload 10
    //   230: invokevirtual 145	java/util/LinkedHashSet:add	(Ljava/lang/Object;)Z
    //   233: pop
    //   234: goto -89 -> 145
    //   237: astore 10
    //   239: aload 9
    //   241: astore 11
    //   243: ldc 120
    //   245: aload 10
    //   247: ldc 147
    //   249: iconst_0
    //   250: anewarray 4	java/lang/Object
    //   253: invokestatic 142	com/tencent/mm/sdk/platformtools/ab:printErrStackTrace	(Ljava/lang/String;Ljava/lang/Throwable;Ljava/lang/String;[Ljava/lang/Object;)V
    //   256: aload 9
    //   258: invokestatic 133	com/tencent/mm/sdk/platformtools/bo:b	(Ljava/io/Closeable;)V
    //   261: aload_2
    //   262: astore 11
    //   264: aload 7
    //   266: iconst_1
    //   267: aload 6
    //   269: invokevirtual 90	javax/crypto/Cipher:init	(ILjava/security/Key;)V
    //   272: aload_2
    //   273: astore 11
    //   275: new 149	java/io/PrintWriter
    //   278: astore 9
    //   280: aload_2
    //   281: astore 11
    //   283: new 151	java/io/OutputStreamWriter
    //   286: astore 6
    //   288: aload_2
    //   289: astore 11
    //   291: new 153	javax/crypto/CipherOutputStream
    //   294: astore 10
    //   296: aload_2
    //   297: astore 11
    //   299: aload 10
    //   301: aload 5
    //   303: invokestatic 157	com/tencent/mm/vfs/e:q	(Lcom/tencent/mm/vfs/b;)Ljava/io/OutputStream;
    //   306: aload 7
    //   308: invokespecial 160	javax/crypto/CipherOutputStream:<init>	(Ljava/io/OutputStream;Ljavax/crypto/Cipher;)V
    //   311: aload_2
    //   312: astore 11
    //   314: aload 6
    //   316: aload 10
    //   318: invokespecial 163	java/io/OutputStreamWriter:<init>	(Ljava/io/OutputStream;)V
    //   321: aload_2
    //   322: astore 11
    //   324: aload 9
    //   326: aload 6
    //   328: invokespecial 166	java/io/PrintWriter:<init>	(Ljava/io/Writer;)V
    //   331: aload 9
    //   333: aload_0
    //   334: invokevirtual 169	java/io/PrintWriter:println	(Ljava/lang/String;)V
    //   337: aload 8
    //   339: invokevirtual 173	java/util/LinkedHashSet:iterator	()Ljava/util/Iterator;
    //   342: astore_0
    //   343: aload_0
    //   344: invokeinterface 179 1 0
    //   349: ifeq +85 -> 434
    //   352: aload 9
    //   354: aload_0
    //   355: invokeinterface 183 1 0
    //   360: checkcast 68	java/lang/String
    //   363: invokevirtual 169	java/io/PrintWriter:println	(Ljava/lang/String;)V
    //   366: goto -23 -> 343
    //   369: astore 11
    //   371: aload 9
    //   373: astore_0
    //   374: aload 11
    //   376: astore 9
    //   378: aload_0
    //   379: astore 11
    //   381: ldc 120
    //   383: aload 9
    //   385: ldc 185
    //   387: iconst_0
    //   388: anewarray 4	java/lang/Object
    //   391: invokestatic 142	com/tencent/mm/sdk/platformtools/ab:printErrStackTrace	(Ljava/lang/String;Ljava/lang/Throwable;Ljava/lang/String;[Ljava/lang/Object;)V
    //   394: aload_0
    //   395: invokestatic 133	com/tencent/mm/sdk/platformtools/bo:b	(Ljava/io/Closeable;)V
    //   398: sipush 19032
    //   401: invokestatic 136	com/tencent/matrix/trace/core/AppMethodBeat:o	(I)V
    //   404: iconst_0
    //   405: istore_1
    //   406: goto -210 -> 196
    //   409: aload 9
    //   411: invokestatic 133	com/tencent/mm/sdk/platformtools/bo:b	(Ljava/io/Closeable;)V
    //   414: goto -153 -> 261
    //   417: astore_0
    //   418: aconst_null
    //   419: astore 11
    //   421: aload 11
    //   423: invokestatic 133	com/tencent/mm/sdk/platformtools/bo:b	(Ljava/io/Closeable;)V
    //   426: sipush 19032
    //   429: invokestatic 136	com/tencent/matrix/trace/core/AppMethodBeat:o	(I)V
    //   432: aload_0
    //   433: athrow
    //   434: aload 9
    //   436: invokevirtual 188	java/io/PrintWriter:close	()V
    //   439: aload_2
    //   440: astore 11
    //   442: aload 4
    //   444: invokevirtual 191	com/tencent/mm/vfs/b:delete	()Z
    //   447: pop
    //   448: aload_2
    //   449: astore 11
    //   451: aload 5
    //   453: aload 4
    //   455: invokevirtual 194	com/tencent/mm/vfs/b:o	(Lcom/tencent/mm/vfs/b;)Z
    //   458: istore_1
    //   459: aload_2
    //   460: astore 11
    //   462: ldc 120
    //   464: ldc 196
    //   466: iload_1
    //   467: invokestatic 200	java/lang/String:valueOf	(Z)Ljava/lang/String;
    //   470: invokevirtual 204	java/lang/String:concat	(Ljava/lang/String;)Ljava/lang/String;
    //   473: invokestatic 127	com/tencent/mm/sdk/platformtools/ab:i	(Ljava/lang/String;Ljava/lang/String;)V
    //   476: aconst_null
    //   477: invokestatic 133	com/tencent/mm/sdk/platformtools/bo:b	(Ljava/io/Closeable;)V
    //   480: sipush 19032
    //   483: invokestatic 136	com/tencent/matrix/trace/core/AppMethodBeat:o	(I)V
    //   486: goto -290 -> 196
    //   489: astore_0
    //   490: aload 11
    //   492: invokestatic 133	com/tencent/mm/sdk/platformtools/bo:b	(Ljava/io/Closeable;)V
    //   495: sipush 19032
    //   498: invokestatic 136	com/tencent/matrix/trace/core/AppMethodBeat:o	(I)V
    //   501: aload_0
    //   502: athrow
    //   503: astore_0
    //   504: aload 9
    //   506: astore 11
    //   508: goto -18 -> 490
    //   511: astore 9
    //   513: aload_3
    //   514: astore_0
    //   515: goto -137 -> 378
    //   518: astore_0
    //   519: goto -98 -> 421
    //   522: astore 10
    //   524: aconst_null
    //   525: astore 9
    //   527: goto -288 -> 239
    //
    // Exception table:
    //   from	to	target	type
    //   80	87	198	java/lang/Exception
    //   149	156	237	java/lang/Exception
    //   165	174	237	java/lang/Exception
    //   178	185	237	java/lang/Exception
    //   226	234	237	java/lang/Exception
    //   331	343	369	java/lang/Exception
    //   343	366	369	java/lang/Exception
    //   434	439	369	java/lang/Exception
    //   96	145	417	finally
    //   264	272	489	finally
    //   275	280	489	finally
    //   283	288	489	finally
    //   291	296	489	finally
    //   299	311	489	finally
    //   314	321	489	finally
    //   324	331	489	finally
    //   381	394	489	finally
    //   442	448	489	finally
    //   451	459	489	finally
    //   462	476	489	finally
    //   331	343	503	finally
    //   343	366	503	finally
    //   434	439	503	finally
    //   264	272	511	java/lang/Exception
    //   275	280	511	java/lang/Exception
    //   283	288	511	java/lang/Exception
    //   291	296	511	java/lang/Exception
    //   299	311	511	java/lang/Exception
    //   314	321	511	java/lang/Exception
    //   324	331	511	java/lang/Exception
    //   442	448	511	java/lang/Exception
    //   451	459	511	java/lang/Exception
    //   462	476	511	java/lang/Exception
    //   149	156	518	finally
    //   165	174	518	finally
    //   178	185	518	finally
    //   226	234	518	finally
    //   243	256	518	finally
    //   96	145	522	java/lang/Exception
  }

  // ERROR //
  public static java.util.Collection<java.lang.String> bib()
  {
    // Byte code:
    //   0: aconst_null
    //   1: astore_0
    //   2: aconst_null
    //   3: astore_1
    //   4: sipush 19031
    //   7: invokestatic 14	com/tencent/matrix/trace/core/AppMethodBeat:i	(I)V
    //   10: new 16	com/tencent/mm/vfs/b
    //   13: dup
    //   14: invokestatic 22	com/tencent/mm/sdk/platformtools/ah:getContext	()Landroid/content/Context;
    //   17: ldc 24
    //   19: invokevirtual 30	android/content/Context:getFileStreamPath	(Ljava/lang/String;)Ljava/io/File;
    //   22: invokespecial 34	com/tencent/mm/vfs/b:<init>	(Ljava/io/File;)V
    //   25: astore_2
    //   26: new 16	com/tencent/mm/vfs/b
    //   29: dup
    //   30: getstatic 213	com/tencent/mm/compatible/util/e:eSn	Ljava/lang/String;
    //   33: ldc 215
    //   35: invokespecial 217	com/tencent/mm/vfs/b:<init>	(Ljava/lang/String;Ljava/lang/String;)V
    //   38: astore_3
    //   39: ldc 120
    //   41: ldc 219
    //   43: invokestatic 127	com/tencent/mm/sdk/platformtools/ab:i	(Ljava/lang/String;Ljava/lang/String;)V
    //   46: new 85	java/util/LinkedHashSet
    //   49: dup
    //   50: invokespecial 86	java/util/LinkedHashSet:<init>	()V
    //   53: astore 4
    //   55: aload 4
    //   57: invokestatic 224	com/tencent/mm/compatible/e/q:LK	()Ljava/lang/String;
    //   60: invokevirtual 145	java/util/LinkedHashSet:add	(Ljava/lang/Object;)Z
    //   63: pop
    //   64: aload 4
    //   66: invokestatic 22	com/tencent/mm/sdk/platformtools/ah:getContext	()Landroid/content/Context;
    //   69: invokestatic 228	com/tencent/mm/compatible/e/q:getDeviceID	(Landroid/content/Context;)Ljava/lang/String;
    //   72: invokevirtual 145	java/util/LinkedHashSet:add	(Ljava/lang/Object;)Z
    //   75: pop
    //   76: aload_3
    //   77: invokevirtual 231	com/tencent/mm/vfs/b:exists	()Z
    //   80: ifne +145 -> 225
    //   83: ldc 120
    //   85: ldc 233
    //   87: invokestatic 127	com/tencent/mm/sdk/platformtools/ab:i	(Ljava/lang/String;Ljava/lang/String;)V
    //   90: aload_2
    //   91: invokevirtual 231	com/tencent/mm/vfs/b:exists	()Z
    //   94: ifeq +284 -> 378
    //   97: aload_0
    //   98: astore 5
    //   100: ldc 74
    //   102: invokestatic 83	javax/crypto/Cipher:getInstance	(Ljava/lang/String;)Ljavax/crypto/Cipher;
    //   105: astore_3
    //   106: aload_0
    //   107: astore 5
    //   109: new 64	javax/crypto/spec/SecretKeySpec
    //   112: astore 6
    //   114: aload_0
    //   115: astore 5
    //   117: aload 6
    //   119: ldc 66
    //   121: invokevirtual 72	java/lang/String:getBytes	()[B
    //   124: ldc 74
    //   126: invokespecial 77	javax/crypto/spec/SecretKeySpec:<init>	([BLjava/lang/String;)V
    //   129: aload_0
    //   130: astore 5
    //   132: aload_3
    //   133: iconst_2
    //   134: aload 6
    //   136: invokevirtual 90	javax/crypto/Cipher:init	(ILjava/security/Key;)V
    //   139: aload_0
    //   140: astore 5
    //   142: new 92	java/io/BufferedReader
    //   145: astore 6
    //   147: aload_0
    //   148: astore 5
    //   150: new 94	java/io/InputStreamReader
    //   153: astore 7
    //   155: aload_0
    //   156: astore 5
    //   158: new 96	javax/crypto/CipherInputStream
    //   161: astore 8
    //   163: aload_0
    //   164: astore 5
    //   166: aload 8
    //   168: aload_2
    //   169: invokestatic 102	com/tencent/mm/vfs/e:p	(Lcom/tencent/mm/vfs/b;)Ljava/io/InputStream;
    //   172: aload_3
    //   173: invokespecial 105	javax/crypto/CipherInputStream:<init>	(Ljava/io/InputStream;Ljavax/crypto/Cipher;)V
    //   176: aload_0
    //   177: astore 5
    //   179: aload 7
    //   181: aload 8
    //   183: invokespecial 108	java/io/InputStreamReader:<init>	(Ljava/io/InputStream;)V
    //   186: aload_0
    //   187: astore 5
    //   189: aload 6
    //   191: aload 7
    //   193: invokespecial 111	java/io/BufferedReader:<init>	(Ljava/io/Reader;)V
    //   196: iconst_0
    //   197: istore 9
    //   199: aload 6
    //   201: invokevirtual 114	java/io/BufferedReader:readLine	()Ljava/lang/String;
    //   204: astore 5
    //   206: aload 5
    //   208: ifnull +150 -> 358
    //   211: aload 4
    //   213: aload 5
    //   215: invokevirtual 145	java/util/LinkedHashSet:add	(Ljava/lang/Object;)Z
    //   218: pop
    //   219: iinc 9 1
    //   222: goto -23 -> 199
    //   225: new 92	java/io/BufferedReader
    //   228: astore 6
    //   230: new 235	com/tencent/mm/vfs/g
    //   233: astore 5
    //   235: aload 5
    //   237: aload_3
    //   238: invokespecial 238	com/tencent/mm/vfs/g:<init>	(Lcom/tencent/mm/vfs/b;)V
    //   241: aload 6
    //   243: aload 5
    //   245: invokespecial 111	java/io/BufferedReader:<init>	(Ljava/io/Reader;)V
    //   248: iconst_0
    //   249: istore 9
    //   251: aload 6
    //   253: astore 5
    //   255: aload 6
    //   257: invokevirtual 114	java/io/BufferedReader:readLine	()Ljava/lang/String;
    //   260: astore_3
    //   261: aload_3
    //   262: ifnull +20 -> 282
    //   265: aload 6
    //   267: astore 5
    //   269: aload 4
    //   271: aload_3
    //   272: invokevirtual 145	java/util/LinkedHashSet:add	(Ljava/lang/Object;)Z
    //   275: pop
    //   276: iinc 9 1
    //   279: goto -28 -> 251
    //   282: aload 6
    //   284: astore 5
    //   286: ldc 120
    //   288: ldc 240
    //   290: iload 9
    //   292: invokestatic 243	java/lang/String:valueOf	(I)Ljava/lang/String;
    //   295: invokevirtual 204	java/lang/String:concat	(Ljava/lang/String;)Ljava/lang/String;
    //   298: invokestatic 127	com/tencent/mm/sdk/platformtools/ab:i	(Ljava/lang/String;Ljava/lang/String;)V
    //   301: aload 6
    //   303: invokestatic 133	com/tencent/mm/sdk/platformtools/bo:b	(Ljava/io/Closeable;)V
    //   306: goto -216 -> 90
    //   309: astore_3
    //   310: aconst_null
    //   311: astore 6
    //   313: aload 6
    //   315: astore 5
    //   317: ldc 120
    //   319: aload_3
    //   320: ldc 245
    //   322: iconst_0
    //   323: anewarray 4	java/lang/Object
    //   326: invokestatic 142	com/tencent/mm/sdk/platformtools/ab:printErrStackTrace	(Ljava/lang/String;Ljava/lang/Throwable;Ljava/lang/String;[Ljava/lang/Object;)V
    //   329: aload 6
    //   331: invokestatic 133	com/tencent/mm/sdk/platformtools/bo:b	(Ljava/io/Closeable;)V
    //   334: goto -244 -> 90
    //   337: astore 5
    //   339: aconst_null
    //   340: astore 6
    //   342: aload 5
    //   344: astore_3
    //   345: aload 6
    //   347: invokestatic 133	com/tencent/mm/sdk/platformtools/bo:b	(Ljava/io/Closeable;)V
    //   350: sipush 19031
    //   353: invokestatic 136	com/tencent/matrix/trace/core/AppMethodBeat:o	(I)V
    //   356: aload_3
    //   357: athrow
    //   358: ldc 120
    //   360: ldc 247
    //   362: iload 9
    //   364: invokestatic 243	java/lang/String:valueOf	(I)Ljava/lang/String;
    //   367: invokevirtual 204	java/lang/String:concat	(Ljava/lang/String;)Ljava/lang/String;
    //   370: invokestatic 127	com/tencent/mm/sdk/platformtools/ab:i	(Ljava/lang/String;Ljava/lang/String;)V
    //   373: aload 6
    //   375: invokestatic 133	com/tencent/mm/sdk/platformtools/bo:b	(Ljava/io/Closeable;)V
    //   378: aload 4
    //   380: ldc 249
    //   382: invokevirtual 145	java/util/LinkedHashSet:add	(Ljava/lang/Object;)Z
    //   385: pop
    //   386: sipush 19031
    //   389: invokestatic 136	com/tencent/matrix/trace/core/AppMethodBeat:o	(I)V
    //   392: aload 4
    //   394: areturn
    //   395: astore_3
    //   396: aload_1
    //   397: astore 6
    //   399: aload 6
    //   401: astore 5
    //   403: ldc 120
    //   405: aload_3
    //   406: ldc 147
    //   408: iconst_0
    //   409: anewarray 4	java/lang/Object
    //   412: invokestatic 142	com/tencent/mm/sdk/platformtools/ab:printErrStackTrace	(Ljava/lang/String;Ljava/lang/Throwable;Ljava/lang/String;[Ljava/lang/Object;)V
    //   415: aload 6
    //   417: invokestatic 133	com/tencent/mm/sdk/platformtools/bo:b	(Ljava/io/Closeable;)V
    //   420: goto -42 -> 378
    //   423: astore_3
    //   424: aload 5
    //   426: astore 6
    //   428: aload_3
    //   429: astore 5
    //   431: aload 6
    //   433: invokestatic 133	com/tencent/mm/sdk/platformtools/bo:b	(Ljava/io/Closeable;)V
    //   436: sipush 19031
    //   439: invokestatic 136	com/tencent/matrix/trace/core/AppMethodBeat:o	(I)V
    //   442: aload 5
    //   444: athrow
    //   445: astore 5
    //   447: goto -16 -> 431
    //   450: astore_3
    //   451: goto -52 -> 399
    //   454: astore_3
    //   455: aload 5
    //   457: astore 6
    //   459: goto -114 -> 345
    //   462: astore_3
    //   463: goto -150 -> 313
    //
    // Exception table:
    //   from	to	target	type
    //   225	248	309	java/lang/Exception
    //   225	248	337	finally
    //   100	106	395	java/lang/Exception
    //   109	114	395	java/lang/Exception
    //   117	129	395	java/lang/Exception
    //   132	139	395	java/lang/Exception
    //   142	147	395	java/lang/Exception
    //   150	155	395	java/lang/Exception
    //   158	163	395	java/lang/Exception
    //   166	176	395	java/lang/Exception
    //   179	186	395	java/lang/Exception
    //   189	196	395	java/lang/Exception
    //   100	106	423	finally
    //   109	114	423	finally
    //   117	129	423	finally
    //   132	139	423	finally
    //   142	147	423	finally
    //   150	155	423	finally
    //   158	163	423	finally
    //   166	176	423	finally
    //   179	186	423	finally
    //   189	196	423	finally
    //   403	415	423	finally
    //   199	206	445	finally
    //   211	219	445	finally
    //   358	373	445	finally
    //   199	206	450	java/lang/Exception
    //   211	219	450	java/lang/Exception
    //   358	373	450	java/lang/Exception
    //   255	261	454	finally
    //   269	276	454	finally
    //   286	301	454	finally
    //   317	329	454	finally
    //   255	261	462	java/lang/Exception
    //   269	276	462	java/lang/Exception
    //   286	301	462	java/lang/Exception
  }
}

/* Location:           C:\Users\Lin\Downloads\dex-tools-2.1-SNAPSHOT\dex-tools-2.1-SNAPSHOT\classes4-dex2jar.jar
 * Qualified Name:     com.tencent.mm.plugin.dbbackup.a.b
 * JD-Core Version:    0.6.2
 */