package com.tencent.mm.plugin.brandservice.ui.timeline.video.a;

import a.l;
import com.tencent.mm.ui.base.n.d;

@l(dWo={1, 1, 13}, dWp={""}, dWq={"<anonymous>", "", "menuItem", "Landroid/view/MenuItem;", "kotlin.jvm.PlatformType", "index", "", "onMMMenuItemSelected"})
public final class g$b
  implements n.d
{
  public g$b(g paramg)
  {
  }

  // ERROR //
  public final void onMMMenuItemSelected(android.view.MenuItem paramMenuItem, int paramInt)
  {
    // Byte code:
    //   0: aconst_null
    //   1: astore_3
    //   2: aconst_null
    //   3: astore 4
    //   5: aconst_null
    //   6: astore 5
    //   8: sipush 15339
    //   11: invokestatic 45	com/tencent/matrix/trace/core/AppMethodBeat:i	(I)V
    //   14: aload_1
    //   15: ldc 46
    //   17: invokestatic 52	a/f/b/j:o	(Ljava/lang/Object;Ljava/lang/String;)V
    //   20: aload_1
    //   21: invokeinterface 58 1 0
    //   26: istore_2
    //   27: iload_2
    //   28: aload_0
    //   29: getfield 28	com/tencent/mm/plugin/brandservice/ui/timeline/video/a/g$b:jYV	Lcom/tencent/mm/plugin/brandservice/ui/timeline/video/a/g;
    //   32: getfield 62	com/tencent/mm/plugin/brandservice/ui/timeline/video/a/g:jYN	I
    //   35: if_icmpne +50 -> 85
    //   38: getstatic 68	com/tencent/mm/plugin/brandservice/ui/timeline/video/a/a:jYp	Lcom/tencent/mm/plugin/brandservice/ui/timeline/video/a/a;
    //   41: astore_1
    //   42: aload_0
    //   43: getfield 28	com/tencent/mm/plugin/brandservice/ui/timeline/video/a/g$b:jYV	Lcom/tencent/mm/plugin/brandservice/ui/timeline/video/a/g;
    //   46: invokevirtual 72	com/tencent/mm/plugin/brandservice/ui/timeline/video/a/g:aYo	()Lcom/tencent/mm/plugin/brandservice/ui/timeline/video/BizVideoDetailUI;
    //   49: astore_1
    //   50: aload_1
    //   51: ifnonnull +6 -> 57
    //   54: invokestatic 75	a/f/b/j:dWJ	()V
    //   57: aload_1
    //   58: checkcast 77	android/content/Context
    //   61: aload_0
    //   62: getfield 28	com/tencent/mm/plugin/brandservice/ui/timeline/video/a/g$b:jYV	Lcom/tencent/mm/plugin/brandservice/ui/timeline/video/a/g;
    //   65: invokestatic 81	com/tencent/mm/plugin/brandservice/ui/timeline/video/a/g:a	(Lcom/tencent/mm/plugin/brandservice/ui/timeline/video/a/g;)Lcom/tencent/mm/af/r;
    //   68: aload_0
    //   69: getfield 28	com/tencent/mm/plugin/brandservice/ui/timeline/video/a/g$b:jYV	Lcom/tencent/mm/plugin/brandservice/ui/timeline/video/a/g;
    //   72: invokestatic 85	com/tencent/mm/plugin/brandservice/ui/timeline/video/a/g:b	(Lcom/tencent/mm/plugin/brandservice/ui/timeline/video/a/g;)Lcom/tencent/mm/plugin/brandservice/ui/timeline/video/b;
    //   75: invokestatic 88	com/tencent/mm/plugin/brandservice/ui/timeline/video/a/a:a	(Landroid/content/Context;Lcom/tencent/mm/af/r;Lcom/tencent/mm/plugin/brandservice/ui/timeline/video/b;)V
    //   78: sipush 15339
    //   81: invokestatic 90	com/tencent/matrix/trace/core/AppMethodBeat:o	(I)V
    //   84: return
    //   85: iload_2
    //   86: aload_0
    //   87: getfield 28	com/tencent/mm/plugin/brandservice/ui/timeline/video/a/g$b:jYV	Lcom/tencent/mm/plugin/brandservice/ui/timeline/video/a/g;
    //   90: getfield 93	com/tencent/mm/plugin/brandservice/ui/timeline/video/a/g:jYO	I
    //   93: if_icmpne +1359 -> 1452
    //   96: aload_0
    //   97: getfield 28	com/tencent/mm/plugin/brandservice/ui/timeline/video/a/g$b:jYV	Lcom/tencent/mm/plugin/brandservice/ui/timeline/video/a/g;
    //   100: astore 4
    //   102: aload 4
    //   104: getfield 97	com/tencent/mm/plugin/brandservice/ui/timeline/video/a/g:TAG	Ljava/lang/String;
    //   107: ldc 99
    //   109: invokestatic 104	com/tencent/mm/sdk/platformtools/ab:i	(Ljava/lang/String;Ljava/lang/String;)V
    //   112: aload 4
    //   114: getfield 108	com/tencent/mm/plugin/brandservice/ui/timeline/video/a/g:hiC	Ljava/lang/ref/WeakReference;
    //   117: astore_1
    //   118: aload_1
    //   119: ifnonnull +8 -> 127
    //   122: ldc 110
    //   124: invokestatic 114	a/f/b/j:avw	(Ljava/lang/String;)V
    //   127: aload_1
    //   128: invokevirtual 120	java/lang/ref/WeakReference:get	()Ljava/lang/Object;
    //   131: ifnull +52 -> 183
    //   134: aload 4
    //   136: getfield 108	com/tencent/mm/plugin/brandservice/ui/timeline/video/a/g:hiC	Ljava/lang/ref/WeakReference;
    //   139: astore_1
    //   140: aload_1
    //   141: ifnonnull +8 -> 149
    //   144: ldc 110
    //   146: invokestatic 114	a/f/b/j:avw	(Ljava/lang/String;)V
    //   149: aload_1
    //   150: invokevirtual 120	java/lang/ref/WeakReference:get	()Ljava/lang/Object;
    //   153: checkcast 122	com/tencent/mm/plugin/brandservice/ui/timeline/video/BizVideoDetailUI
    //   156: astore_1
    //   157: aload_1
    //   158: ifnull +44 -> 202
    //   161: aload_1
    //   162: invokevirtual 126	com/tencent/mm/plugin/brandservice/ui/timeline/video/BizVideoDetailUI:isFinishing	()Z
    //   165: invokestatic 132	java/lang/Boolean:valueOf	(Z)Ljava/lang/Boolean;
    //   168: astore_1
    //   169: aload_1
    //   170: ifnonnull +6 -> 176
    //   173: invokestatic 75	a/f/b/j:dWJ	()V
    //   176: aload_1
    //   177: invokevirtual 135	java/lang/Boolean:booleanValue	()Z
    //   180: ifeq +27 -> 207
    //   183: aload 4
    //   185: getfield 97	com/tencent/mm/plugin/brandservice/ui/timeline/video/a/g:TAG	Ljava/lang/String;
    //   188: ldc 137
    //   190: invokestatic 104	com/tencent/mm/sdk/platformtools/ab:i	(Ljava/lang/String;Ljava/lang/String;)V
    //   193: sipush 15339
    //   196: invokestatic 90	com/tencent/matrix/trace/core/AppMethodBeat:o	(I)V
    //   199: goto -115 -> 84
    //   202: aconst_null
    //   203: astore_1
    //   204: goto -35 -> 169
    //   207: new 139	android/content/Intent
    //   210: dup
    //   211: invokespecial 140	android/content/Intent:<init>	()V
    //   214: astore_3
    //   215: aload 4
    //   217: getfield 144	com/tencent/mm/plugin/brandservice/ui/timeline/video/a/g:jVG	Lcom/tencent/mm/af/r;
    //   220: astore_1
    //   221: aload_1
    //   222: ifnonnull +8 -> 230
    //   225: ldc 146
    //   227: invokestatic 114	a/f/b/j:avw	(Ljava/lang/String;)V
    //   230: aload_1
    //   231: getfield 152	com/tencent/mm/af/r:fjT	Lcom/tencent/mm/af/p;
    //   234: getfield 157	com/tencent/mm/af/p:videoWidth	I
    //   237: istore 6
    //   239: iload 6
    //   241: istore_2
    //   242: iload 6
    //   244: ifgt +7 -> 251
    //   247: sipush 150
    //   250: istore_2
    //   251: aload_3
    //   252: ldc 159
    //   254: iload_2
    //   255: invokevirtual 163	android/content/Intent:putExtra	(Ljava/lang/String;I)Landroid/content/Intent;
    //   258: pop
    //   259: aload_3
    //   260: ldc 165
    //   262: iload_2
    //   263: invokevirtual 163	android/content/Intent:putExtra	(Ljava/lang/String;I)Landroid/content/Intent;
    //   266: pop
    //   267: aload 4
    //   269: getfield 169	com/tencent/mm/plugin/brandservice/ui/timeline/video/a/g:jWx	Lcom/tencent/mm/plugin/brandservice/ui/timeline/video/b;
    //   272: astore_1
    //   273: aload_1
    //   274: ifnonnull +8 -> 282
    //   277: ldc 171
    //   279: invokestatic 114	a/f/b/j:avw	(Ljava/lang/String;)V
    //   282: aload_1
    //   283: invokevirtual 176	com/tencent/mm/plugin/brandservice/ui/timeline/video/b:aYp	()Z
    //   286: ifeq +971 -> 1257
    //   289: aload 4
    //   291: getfield 169	com/tencent/mm/plugin/brandservice/ui/timeline/video/a/g:jWx	Lcom/tencent/mm/plugin/brandservice/ui/timeline/video/b;
    //   294: astore_1
    //   295: aload_1
    //   296: ifnonnull +8 -> 304
    //   299: ldc 171
    //   301: invokestatic 114	a/f/b/j:avw	(Ljava/lang/String;)V
    //   304: aload_1
    //   305: getfield 180	com/tencent/mm/plugin/brandservice/ui/timeline/video/b:jVI	Lcom/tencent/mm/protocal/protobuf/bac;
    //   308: astore_1
    //   309: aload_1
    //   310: ifnull +937 -> 1247
    //   313: aload_1
    //   314: getfield 185	com/tencent/mm/protocal/protobuf/bac:title	Ljava/lang/String;
    //   317: astore_1
    //   318: aload_3
    //   319: ldc 187
    //   321: aload_1
    //   322: invokevirtual 190	android/content/Intent:putExtra	(Ljava/lang/String;Ljava/lang/String;)Landroid/content/Intent;
    //   325: pop
    //   326: aload 4
    //   328: getfield 169	com/tencent/mm/plugin/brandservice/ui/timeline/video/a/g:jWx	Lcom/tencent/mm/plugin/brandservice/ui/timeline/video/b;
    //   331: astore_1
    //   332: aload_1
    //   333: ifnonnull +8 -> 341
    //   336: ldc 171
    //   338: invokestatic 114	a/f/b/j:avw	(Ljava/lang/String;)V
    //   341: aload_1
    //   342: getfield 180	com/tencent/mm/plugin/brandservice/ui/timeline/video/b:jVI	Lcom/tencent/mm/protocal/protobuf/bac;
    //   345: astore_1
    //   346: aload_1
    //   347: ifnull +905 -> 1252
    //   350: aload_1
    //   351: getfield 193	com/tencent/mm/protocal/protobuf/bac:fjx	Ljava/lang/String;
    //   354: astore_1
    //   355: aload_3
    //   356: ldc 195
    //   358: aload_1
    //   359: invokevirtual 190	android/content/Intent:putExtra	(Ljava/lang/String;Ljava/lang/String;)Landroid/content/Intent;
    //   362: pop
    //   363: aload 4
    //   365: getfield 169	com/tencent/mm/plugin/brandservice/ui/timeline/video/a/g:jWx	Lcom/tencent/mm/plugin/brandservice/ui/timeline/video/b;
    //   368: astore_1
    //   369: aload_1
    //   370: ifnonnull +8 -> 378
    //   373: ldc 171
    //   375: invokestatic 114	a/f/b/j:avw	(Ljava/lang/String;)V
    //   378: aload_3
    //   379: ldc 197
    //   381: aload_1
    //   382: getfield 200	com/tencent/mm/plugin/brandservice/ui/timeline/video/b:url	Ljava/lang/String;
    //   385: invokevirtual 190	android/content/Intent:putExtra	(Ljava/lang/String;Ljava/lang/String;)Landroid/content/Intent;
    //   388: pop
    //   389: aload 4
    //   391: getfield 144	com/tencent/mm/plugin/brandservice/ui/timeline/video/a/g:jVG	Lcom/tencent/mm/af/r;
    //   394: astore_1
    //   395: aload_1
    //   396: ifnonnull +8 -> 404
    //   399: ldc 146
    //   401: invokestatic 114	a/f/b/j:avw	(Ljava/lang/String;)V
    //   404: aload_1
    //   405: getfield 203	com/tencent/mm/af/r:fjS	Ljava/lang/String;
    //   408: astore_1
    //   409: aload 4
    //   411: getfield 144	com/tencent/mm/plugin/brandservice/ui/timeline/video/a/g:jVG	Lcom/tencent/mm/af/r;
    //   414: astore 7
    //   416: aload 7
    //   418: ifnonnull +8 -> 426
    //   421: ldc 146
    //   423: invokestatic 114	a/f/b/j:avw	(Ljava/lang/String;)V
    //   426: aload 7
    //   428: getfield 206	com/tencent/mm/af/r:cwG	Ljava/lang/String;
    //   431: invokestatic 212	com/tencent/mm/sdk/platformtools/bo:isNullOrNil	(Ljava/lang/String;)Z
    //   434: ifne +884 -> 1318
    //   437: aload 4
    //   439: getfield 144	com/tencent/mm/plugin/brandservice/ui/timeline/video/a/g:jVG	Lcom/tencent/mm/af/r;
    //   442: astore 7
    //   444: aload 7
    //   446: ifnonnull +8 -> 454
    //   449: ldc 146
    //   451: invokestatic 114	a/f/b/j:avw	(Ljava/lang/String;)V
    //   454: aload_3
    //   455: ldc 214
    //   457: aload 7
    //   459: getfield 206	com/tencent/mm/af/r:cwG	Ljava/lang/String;
    //   462: invokevirtual 190	android/content/Intent:putExtra	(Ljava/lang/String;Ljava/lang/String;)Landroid/content/Intent;
    //   465: pop
    //   466: aload 4
    //   468: getfield 144	com/tencent/mm/plugin/brandservice/ui/timeline/video/a/g:jVG	Lcom/tencent/mm/af/r;
    //   471: astore 7
    //   473: aload 7
    //   475: ifnonnull +8 -> 483
    //   478: ldc 146
    //   480: invokestatic 114	a/f/b/j:avw	(Ljava/lang/String;)V
    //   483: aload_3
    //   484: ldc 216
    //   486: aload 7
    //   488: getfield 219	com/tencent/mm/af/r:fjR	Ljava/lang/String;
    //   491: invokevirtual 190	android/content/Intent:putExtra	(Ljava/lang/String;Ljava/lang/String;)Landroid/content/Intent;
    //   494: pop
    //   495: aload_3
    //   496: ldc 221
    //   498: iconst_1
    //   499: invokevirtual 163	android/content/Intent:putExtra	(Ljava/lang/String;I)Landroid/content/Intent;
    //   502: pop
    //   503: aload 4
    //   505: getfield 169	com/tencent/mm/plugin/brandservice/ui/timeline/video/a/g:jWx	Lcom/tencent/mm/plugin/brandservice/ui/timeline/video/b;
    //   508: astore 7
    //   510: aload 7
    //   512: ifnonnull +8 -> 520
    //   515: ldc 171
    //   517: invokestatic 114	a/f/b/j:avw	(Ljava/lang/String;)V
    //   520: aload_3
    //   521: ldc 223
    //   523: aload 7
    //   525: getfield 200	com/tencent/mm/plugin/brandservice/ui/timeline/video/b:url	Ljava/lang/String;
    //   528: invokevirtual 190	android/content/Intent:putExtra	(Ljava/lang/String;Ljava/lang/String;)Landroid/content/Intent;
    //   531: pop
    //   532: aload_3
    //   533: ldc 225
    //   535: aload_1
    //   536: invokevirtual 190	android/content/Intent:putExtra	(Ljava/lang/String;Ljava/lang/String;)Landroid/content/Intent;
    //   539: pop
    //   540: aload_3
    //   541: ldc 227
    //   543: iconst_1
    //   544: invokevirtual 230	android/content/Intent:putExtra	(Ljava/lang/String;Z)Landroid/content/Intent;
    //   547: pop
    //   548: aload_1
    //   549: invokestatic 236	com/tencent/mm/model/v:nW	(Ljava/lang/String;)Ljava/lang/String;
    //   552: astore 7
    //   554: invokestatic 240	com/tencent/mm/model/v:Zp	()Lcom/tencent/mm/model/v;
    //   557: aload 7
    //   559: iconst_1
    //   560: invokevirtual 244	com/tencent/mm/model/v:y	(Ljava/lang/String;Z)Lcom/tencent/mm/model/v$b;
    //   563: astore 8
    //   565: aload 8
    //   567: ldc 246
    //   569: iconst_2
    //   570: invokestatic 251	java/lang/Integer:valueOf	(I)Ljava/lang/Integer;
    //   573: invokevirtual 257	com/tencent/mm/model/v$b:j	(Ljava/lang/String;Ljava/lang/Object;)Lcom/tencent/mm/model/v$b;
    //   576: pop
    //   577: aload 4
    //   579: getfield 144	com/tencent/mm/plugin/brandservice/ui/timeline/video/a/g:jVG	Lcom/tencent/mm/af/r;
    //   582: astore_1
    //   583: aload_1
    //   584: ifnonnull +8 -> 592
    //   587: ldc 146
    //   589: invokestatic 114	a/f/b/j:avw	(Ljava/lang/String;)V
    //   592: aload 8
    //   594: ldc_w 259
    //   597: aload_1
    //   598: invokevirtual 263	com/tencent/mm/af/r:HE	()Ljava/lang/String;
    //   601: invokevirtual 257	com/tencent/mm/model/v$b:j	(Ljava/lang/String;Ljava/lang/Object;)Lcom/tencent/mm/model/v$b;
    //   604: pop
    //   605: aload 4
    //   607: getfield 144	com/tencent/mm/plugin/brandservice/ui/timeline/video/a/g:jVG	Lcom/tencent/mm/af/r;
    //   610: astore_1
    //   611: aload_1
    //   612: ifnonnull +8 -> 620
    //   615: ldc 146
    //   617: invokestatic 114	a/f/b/j:avw	(Ljava/lang/String;)V
    //   620: aload 8
    //   622: ldc_w 265
    //   625: aload_1
    //   626: getfield 268	com/tencent/mm/af/r:fjQ	I
    //   629: invokestatic 251	java/lang/Integer:valueOf	(I)Ljava/lang/Integer;
    //   632: invokevirtual 257	com/tencent/mm/model/v$b:j	(Ljava/lang/String;Ljava/lang/Object;)Lcom/tencent/mm/model/v$b;
    //   635: pop
    //   636: aload 4
    //   638: getfield 144	com/tencent/mm/plugin/brandservice/ui/timeline/video/a/g:jVG	Lcom/tencent/mm/af/r;
    //   641: astore_1
    //   642: aload_1
    //   643: ifnonnull +8 -> 651
    //   646: ldc 146
    //   648: invokestatic 114	a/f/b/j:avw	(Ljava/lang/String;)V
    //   651: aload 8
    //   653: ldc_w 270
    //   656: aload_1
    //   657: getfield 203	com/tencent/mm/af/r:fjS	Ljava/lang/String;
    //   660: invokevirtual 257	com/tencent/mm/model/v$b:j	(Ljava/lang/String;Ljava/lang/Object;)Lcom/tencent/mm/model/v$b;
    //   663: pop
    //   664: aload 4
    //   666: getfield 144	com/tencent/mm/plugin/brandservice/ui/timeline/video/a/g:jVG	Lcom/tencent/mm/af/r;
    //   669: astore_1
    //   670: aload_1
    //   671: ifnonnull +8 -> 679
    //   674: ldc 146
    //   676: invokestatic 114	a/f/b/j:avw	(Ljava/lang/String;)V
    //   679: aload 8
    //   681: ldc_w 272
    //   684: aload_1
    //   685: invokevirtual 263	com/tencent/mm/af/r:HE	()Ljava/lang/String;
    //   688: invokevirtual 257	com/tencent/mm/model/v$b:j	(Ljava/lang/String;Ljava/lang/Object;)Lcom/tencent/mm/model/v$b;
    //   691: pop
    //   692: aload 4
    //   694: getfield 169	com/tencent/mm/plugin/brandservice/ui/timeline/video/a/g:jWx	Lcom/tencent/mm/plugin/brandservice/ui/timeline/video/b;
    //   697: astore_1
    //   698: aload_1
    //   699: ifnonnull +8 -> 707
    //   702: ldc 171
    //   704: invokestatic 114	a/f/b/j:avw	(Ljava/lang/String;)V
    //   707: aload 8
    //   709: ldc_w 273
    //   712: aload_1
    //   713: getfield 200	com/tencent/mm/plugin/brandservice/ui/timeline/video/b:url	Ljava/lang/String;
    //   716: invokevirtual 257	com/tencent/mm/model/v$b:j	(Ljava/lang/String;Ljava/lang/Object;)Lcom/tencent/mm/model/v$b;
    //   719: pop
    //   720: aload 4
    //   722: getfield 169	com/tencent/mm/plugin/brandservice/ui/timeline/video/a/g:jWx	Lcom/tencent/mm/plugin/brandservice/ui/timeline/video/b;
    //   725: astore_1
    //   726: aload_1
    //   727: ifnonnull +8 -> 735
    //   730: ldc 171
    //   732: invokestatic 114	a/f/b/j:avw	(Ljava/lang/String;)V
    //   735: aload 8
    //   737: ldc_w 275
    //   740: aload_1
    //   741: getfield 200	com/tencent/mm/plugin/brandservice/ui/timeline/video/b:url	Ljava/lang/String;
    //   744: invokevirtual 257	com/tencent/mm/model/v$b:j	(Ljava/lang/String;Ljava/lang/Object;)Lcom/tencent/mm/model/v$b;
    //   747: pop
    //   748: aload 4
    //   750: getfield 144	com/tencent/mm/plugin/brandservice/ui/timeline/video/a/g:jVG	Lcom/tencent/mm/af/r;
    //   753: astore_1
    //   754: aload_1
    //   755: ifnonnull +8 -> 763
    //   758: ldc 146
    //   760: invokestatic 114	a/f/b/j:avw	(Ljava/lang/String;)V
    //   763: aload_1
    //   764: getfield 152	com/tencent/mm/af/r:fjT	Lcom/tencent/mm/af/p;
    //   767: getfield 278	com/tencent/mm/af/p:type	I
    //   770: istore_2
    //   771: iload_2
    //   772: iconst_m1
    //   773: if_icmpeq +374 -> 1147
    //   776: aload 8
    //   778: ldc_w 280
    //   781: iload_2
    //   782: invokestatic 251	java/lang/Integer:valueOf	(I)Ljava/lang/Integer;
    //   785: invokevirtual 257	com/tencent/mm/model/v$b:j	(Ljava/lang/String;Ljava/lang/Object;)Lcom/tencent/mm/model/v$b;
    //   788: pop
    //   789: aload 4
    //   791: getfield 144	com/tencent/mm/plugin/brandservice/ui/timeline/video/a/g:jVG	Lcom/tencent/mm/af/r;
    //   794: astore_1
    //   795: aload_1
    //   796: ifnonnull +8 -> 804
    //   799: ldc 146
    //   801: invokestatic 114	a/f/b/j:avw	(Ljava/lang/String;)V
    //   804: aload_1
    //   805: getfield 152	com/tencent/mm/af/r:fjT	Lcom/tencent/mm/af/p;
    //   808: getfield 278	com/tencent/mm/af/p:type	I
    //   811: iconst_5
    //   812: if_icmpne +321 -> 1133
    //   815: aload 4
    //   817: getfield 144	com/tencent/mm/plugin/brandservice/ui/timeline/video/a/g:jVG	Lcom/tencent/mm/af/r;
    //   820: astore_1
    //   821: aload_1
    //   822: ifnonnull +8 -> 830
    //   825: ldc 146
    //   827: invokestatic 114	a/f/b/j:avw	(Ljava/lang/String;)V
    //   830: aload 8
    //   832: ldc_w 282
    //   835: aload_1
    //   836: getfield 152	com/tencent/mm/af/r:fjT	Lcom/tencent/mm/af/p;
    //   839: getfield 285	com/tencent/mm/af/p:fgd	Ljava/lang/String;
    //   842: invokevirtual 257	com/tencent/mm/model/v$b:j	(Ljava/lang/String;Ljava/lang/Object;)Lcom/tencent/mm/model/v$b;
    //   845: pop
    //   846: aload 4
    //   848: getfield 144	com/tencent/mm/plugin/brandservice/ui/timeline/video/a/g:jVG	Lcom/tencent/mm/af/r;
    //   851: astore_1
    //   852: aload_1
    //   853: ifnonnull +8 -> 861
    //   856: ldc 146
    //   858: invokestatic 114	a/f/b/j:avw	(Ljava/lang/String;)V
    //   861: aload 8
    //   863: ldc_w 287
    //   866: aload_1
    //   867: getfield 152	com/tencent/mm/af/r:fjT	Lcom/tencent/mm/af/p;
    //   870: getfield 291	com/tencent/mm/af/p:time	J
    //   873: l2i
    //   874: invokestatic 251	java/lang/Integer:valueOf	(I)Ljava/lang/Integer;
    //   877: invokevirtual 257	com/tencent/mm/model/v$b:j	(Ljava/lang/String;Ljava/lang/Object;)Lcom/tencent/mm/model/v$b;
    //   880: pop
    //   881: aload 4
    //   883: getfield 144	com/tencent/mm/plugin/brandservice/ui/timeline/video/a/g:jVG	Lcom/tencent/mm/af/r;
    //   886: astore_1
    //   887: aload_1
    //   888: ifnonnull +8 -> 896
    //   891: ldc 146
    //   893: invokestatic 114	a/f/b/j:avw	(Ljava/lang/String;)V
    //   896: aload 8
    //   898: ldc_w 293
    //   901: aload_1
    //   902: getfield 152	com/tencent/mm/af/r:fjT	Lcom/tencent/mm/af/p;
    //   905: getfield 296	com/tencent/mm/af/p:fjB	I
    //   908: invokestatic 251	java/lang/Integer:valueOf	(I)Ljava/lang/Integer;
    //   911: invokevirtual 257	com/tencent/mm/model/v$b:j	(Ljava/lang/String;Ljava/lang/Object;)Lcom/tencent/mm/model/v$b;
    //   914: pop
    //   915: aload 4
    //   917: getfield 169	com/tencent/mm/plugin/brandservice/ui/timeline/video/a/g:jWx	Lcom/tencent/mm/plugin/brandservice/ui/timeline/video/b;
    //   920: astore_1
    //   921: aload_1
    //   922: ifnonnull +8 -> 930
    //   925: ldc 171
    //   927: invokestatic 114	a/f/b/j:avw	(Ljava/lang/String;)V
    //   930: aload_1
    //   931: invokevirtual 176	com/tencent/mm/plugin/brandservice/ui/timeline/video/b:aYp	()Z
    //   934: ifeq +453 -> 1387
    //   937: aload 4
    //   939: getfield 169	com/tencent/mm/plugin/brandservice/ui/timeline/video/a/g:jWx	Lcom/tencent/mm/plugin/brandservice/ui/timeline/video/b;
    //   942: astore_1
    //   943: aload_1
    //   944: ifnonnull +8 -> 952
    //   947: ldc 171
    //   949: invokestatic 114	a/f/b/j:avw	(Ljava/lang/String;)V
    //   952: aload_1
    //   953: getfield 180	com/tencent/mm/plugin/brandservice/ui/timeline/video/b:jVI	Lcom/tencent/mm/protocal/protobuf/bac;
    //   956: astore_1
    //   957: aload_1
    //   958: ifnull +424 -> 1382
    //   961: aload_1
    //   962: getfield 299	com/tencent/mm/protocal/protobuf/bac:fjz	Ljava/lang/String;
    //   965: astore_1
    //   966: aload 8
    //   968: ldc_w 301
    //   971: aload_1
    //   972: invokevirtual 257	com/tencent/mm/model/v$b:j	(Ljava/lang/String;Ljava/lang/Object;)Lcom/tencent/mm/model/v$b;
    //   975: pop
    //   976: aload 4
    //   978: getfield 169	com/tencent/mm/plugin/brandservice/ui/timeline/video/a/g:jWx	Lcom/tencent/mm/plugin/brandservice/ui/timeline/video/b;
    //   981: astore_1
    //   982: aload_1
    //   983: ifnonnull +8 -> 991
    //   986: ldc 171
    //   988: invokestatic 114	a/f/b/j:avw	(Ljava/lang/String;)V
    //   991: aload_1
    //   992: getfield 180	com/tencent/mm/plugin/brandservice/ui/timeline/video/b:jVI	Lcom/tencent/mm/protocal/protobuf/bac;
    //   995: astore 9
    //   997: aload 5
    //   999: astore_1
    //   1000: aload 9
    //   1002: ifnull +9 -> 1011
    //   1005: aload 9
    //   1007: getfield 193	com/tencent/mm/protocal/protobuf/bac:fjx	Ljava/lang/String;
    //   1010: astore_1
    //   1011: aload 8
    //   1013: ldc_w 303
    //   1016: aload_1
    //   1017: invokevirtual 257	com/tencent/mm/model/v$b:j	(Ljava/lang/String;Ljava/lang/Object;)Lcom/tencent/mm/model/v$b;
    //   1020: pop
    //   1021: aload 4
    //   1023: getfield 144	com/tencent/mm/plugin/brandservice/ui/timeline/video/a/g:jVG	Lcom/tencent/mm/af/r;
    //   1026: astore_1
    //   1027: aload_1
    //   1028: ifnonnull +8 -> 1036
    //   1031: ldc 146
    //   1033: invokestatic 114	a/f/b/j:avw	(Ljava/lang/String;)V
    //   1036: aload 8
    //   1038: ldc_w 305
    //   1041: aload_1
    //   1042: getfield 152	com/tencent/mm/af/r:fjT	Lcom/tencent/mm/af/p;
    //   1045: getfield 157	com/tencent/mm/af/p:videoWidth	I
    //   1048: invokestatic 251	java/lang/Integer:valueOf	(I)Ljava/lang/Integer;
    //   1051: invokevirtual 257	com/tencent/mm/model/v$b:j	(Ljava/lang/String;Ljava/lang/Object;)Lcom/tencent/mm/model/v$b;
    //   1054: pop
    //   1055: aload 4
    //   1057: getfield 144	com/tencent/mm/plugin/brandservice/ui/timeline/video/a/g:jVG	Lcom/tencent/mm/af/r;
    //   1060: astore_1
    //   1061: aload_1
    //   1062: ifnonnull +8 -> 1070
    //   1065: ldc 146
    //   1067: invokestatic 114	a/f/b/j:avw	(Ljava/lang/String;)V
    //   1070: aload 8
    //   1072: ldc_w 307
    //   1075: aload_1
    //   1076: getfield 152	com/tencent/mm/af/r:fjT	Lcom/tencent/mm/af/p;
    //   1079: getfield 310	com/tencent/mm/af/p:videoHeight	I
    //   1082: invokestatic 251	java/lang/Integer:valueOf	(I)Ljava/lang/Integer;
    //   1085: invokevirtual 257	com/tencent/mm/model/v$b:j	(Ljava/lang/String;Ljava/lang/Object;)Lcom/tencent/mm/model/v$b;
    //   1088: pop
    //   1089: aload 8
    //   1091: ldc_w 312
    //   1094: iconst_1
    //   1095: invokestatic 251	java/lang/Integer:valueOf	(I)Ljava/lang/Integer;
    //   1098: invokevirtual 257	com/tencent/mm/model/v$b:j	(Ljava/lang/String;Ljava/lang/Object;)Lcom/tencent/mm/model/v$b;
    //   1101: pop
    //   1102: aload 4
    //   1104: getfield 144	com/tencent/mm/plugin/brandservice/ui/timeline/video/a/g:jVG	Lcom/tencent/mm/af/r;
    //   1107: astore_1
    //   1108: aload_1
    //   1109: ifnonnull +8 -> 1117
    //   1112: ldc 146
    //   1114: invokestatic 114	a/f/b/j:avw	(Ljava/lang/String;)V
    //   1117: aload 8
    //   1119: ldc_w 314
    //   1122: aload_1
    //   1123: getfield 317	com/tencent/mm/af/r:fgc	I
    //   1126: invokestatic 251	java/lang/Integer:valueOf	(I)Ljava/lang/Integer;
    //   1129: invokevirtual 257	com/tencent/mm/model/v$b:j	(Ljava/lang/String;Ljava/lang/Object;)Lcom/tencent/mm/model/v$b;
    //   1132: pop
    //   1133: aload 8
    //   1135: ldc_w 319
    //   1138: bipush 10
    //   1140: invokestatic 251	java/lang/Integer:valueOf	(I)Ljava/lang/Integer;
    //   1143: invokevirtual 257	com/tencent/mm/model/v$b:j	(Ljava/lang/String;Ljava/lang/Object;)Lcom/tencent/mm/model/v$b;
    //   1146: pop
    //   1147: aload_3
    //   1148: ldc_w 321
    //   1151: aload 7
    //   1153: invokevirtual 190	android/content/Intent:putExtra	(Ljava/lang/String;Ljava/lang/String;)Landroid/content/Intent;
    //   1156: pop
    //   1157: aload 4
    //   1159: getfield 108	com/tencent/mm/plugin/brandservice/ui/timeline/video/a/g:hiC	Ljava/lang/ref/WeakReference;
    //   1162: astore_1
    //   1163: aload_1
    //   1164: ifnonnull +8 -> 1172
    //   1167: ldc 110
    //   1169: invokestatic 114	a/f/b/j:avw	(Ljava/lang/String;)V
    //   1172: aload_1
    //   1173: invokevirtual 120	java/lang/ref/WeakReference:get	()Ljava/lang/Object;
    //   1176: astore_1
    //   1177: aload_1
    //   1178: ifnonnull +6 -> 1184
    //   1181: invokestatic 75	a/f/b/j:dWJ	()V
    //   1184: aload_1
    //   1185: ldc_w 323
    //   1188: invokestatic 52	a/f/b/j:o	(Ljava/lang/Object;Ljava/lang/String;)V
    //   1191: aload_1
    //   1192: checkcast 122	com/tencent/mm/plugin/brandservice/ui/timeline/video/BizVideoDetailUI
    //   1195: invokevirtual 327	com/tencent/mm/plugin/brandservice/ui/timeline/video/BizVideoDetailUI:getIntent	()Landroid/content/Intent;
    //   1198: astore_1
    //   1199: aload_1
    //   1200: ldc_w 329
    //   1203: invokestatic 52	a/f/b/j:o	(Ljava/lang/Object;Ljava/lang/String;)V
    //   1206: aload_3
    //   1207: ldc_w 331
    //   1210: aload_1
    //   1211: invokevirtual 335	android/content/Intent:getExtras	()Landroid/os/Bundle;
    //   1214: invokevirtual 338	android/content/Intent:putExtra	(Ljava/lang/String;Landroid/os/Bundle;)Landroid/content/Intent;
    //   1217: pop
    //   1218: aload 4
    //   1220: invokevirtual 72	com/tencent/mm/plugin/brandservice/ui/timeline/video/a/g:aYo	()Lcom/tencent/mm/plugin/brandservice/ui/timeline/video/BizVideoDetailUI;
    //   1223: checkcast 77	android/content/Context
    //   1226: ldc_w 340
    //   1229: ldc_w 342
    //   1232: aload_3
    //   1233: iconst_1
    //   1234: iconst_0
    //   1235: invokestatic 347	com/tencent/mm/bp/d:a	(Landroid/content/Context;Ljava/lang/String;Ljava/lang/String;Landroid/content/Intent;IZ)V
    //   1238: sipush 15339
    //   1241: invokestatic 90	com/tencent/matrix/trace/core/AppMethodBeat:o	(I)V
    //   1244: goto -1160 -> 84
    //   1247: aconst_null
    //   1248: astore_1
    //   1249: goto -931 -> 318
    //   1252: aconst_null
    //   1253: astore_1
    //   1254: goto -899 -> 355
    //   1257: aload 4
    //   1259: getfield 144	com/tencent/mm/plugin/brandservice/ui/timeline/video/a/g:jVG	Lcom/tencent/mm/af/r;
    //   1262: astore_1
    //   1263: aload_1
    //   1264: ifnonnull +8 -> 1272
    //   1267: ldc 146
    //   1269: invokestatic 114	a/f/b/j:avw	(Ljava/lang/String;)V
    //   1272: aload_3
    //   1273: ldc 187
    //   1275: aload_1
    //   1276: getfield 152	com/tencent/mm/af/r:fjT	Lcom/tencent/mm/af/p;
    //   1279: getfield 348	com/tencent/mm/af/p:title	Ljava/lang/String;
    //   1282: invokevirtual 190	android/content/Intent:putExtra	(Ljava/lang/String;Ljava/lang/String;)Landroid/content/Intent;
    //   1285: pop
    //   1286: aload 4
    //   1288: getfield 144	com/tencent/mm/plugin/brandservice/ui/timeline/video/a/g:jVG	Lcom/tencent/mm/af/r;
    //   1291: astore_1
    //   1292: aload_1
    //   1293: ifnonnull +8 -> 1301
    //   1296: ldc 146
    //   1298: invokestatic 114	a/f/b/j:avw	(Ljava/lang/String;)V
    //   1301: aload_3
    //   1302: ldc 195
    //   1304: aload_1
    //   1305: getfield 152	com/tencent/mm/af/r:fjT	Lcom/tencent/mm/af/p;
    //   1308: getfield 349	com/tencent/mm/af/p:fjx	Ljava/lang/String;
    //   1311: invokevirtual 190	android/content/Intent:putExtra	(Ljava/lang/String;Ljava/lang/String;)Landroid/content/Intent;
    //   1314: pop
    //   1315: goto -952 -> 363
    //   1318: aload 4
    //   1320: getfield 144	com/tencent/mm/plugin/brandservice/ui/timeline/video/a/g:jVG	Lcom/tencent/mm/af/r;
    //   1323: astore 7
    //   1325: aload 7
    //   1327: ifnonnull +8 -> 1335
    //   1330: ldc 146
    //   1332: invokestatic 114	a/f/b/j:avw	(Ljava/lang/String;)V
    //   1335: aload_3
    //   1336: ldc 214
    //   1338: aload 7
    //   1340: invokevirtual 263	com/tencent/mm/af/r:HE	()Ljava/lang/String;
    //   1343: invokevirtual 190	android/content/Intent:putExtra	(Ljava/lang/String;Ljava/lang/String;)Landroid/content/Intent;
    //   1346: pop
    //   1347: aload 4
    //   1349: getfield 144	com/tencent/mm/plugin/brandservice/ui/timeline/video/a/g:jVG	Lcom/tencent/mm/af/r;
    //   1352: astore 7
    //   1354: aload 7
    //   1356: ifnonnull +8 -> 1364
    //   1359: ldc 146
    //   1361: invokestatic 114	a/f/b/j:avw	(Ljava/lang/String;)V
    //   1364: aload_3
    //   1365: ldc 216
    //   1367: aload 7
    //   1369: invokevirtual 263	com/tencent/mm/af/r:HE	()Ljava/lang/String;
    //   1372: invokestatic 354	com/tencent/mm/model/s:mJ	(Ljava/lang/String;)Ljava/lang/String;
    //   1375: invokevirtual 190	android/content/Intent:putExtra	(Ljava/lang/String;Ljava/lang/String;)Landroid/content/Intent;
    //   1378: pop
    //   1379: goto -884 -> 495
    //   1382: aconst_null
    //   1383: astore_1
    //   1384: goto -418 -> 966
    //   1387: aload 4
    //   1389: getfield 144	com/tencent/mm/plugin/brandservice/ui/timeline/video/a/g:jVG	Lcom/tencent/mm/af/r;
    //   1392: astore_1
    //   1393: aload_1
    //   1394: ifnonnull +8 -> 1402
    //   1397: ldc 146
    //   1399: invokestatic 114	a/f/b/j:avw	(Ljava/lang/String;)V
    //   1402: aload 8
    //   1404: ldc_w 301
    //   1407: aload_1
    //   1408: getfield 152	com/tencent/mm/af/r:fjT	Lcom/tencent/mm/af/p;
    //   1411: getfield 355	com/tencent/mm/af/p:fjz	Ljava/lang/String;
    //   1414: invokevirtual 257	com/tencent/mm/model/v$b:j	(Ljava/lang/String;Ljava/lang/Object;)Lcom/tencent/mm/model/v$b;
    //   1417: pop
    //   1418: aload 4
    //   1420: getfield 144	com/tencent/mm/plugin/brandservice/ui/timeline/video/a/g:jVG	Lcom/tencent/mm/af/r;
    //   1423: astore_1
    //   1424: aload_1
    //   1425: ifnonnull +8 -> 1433
    //   1428: ldc 146
    //   1430: invokestatic 114	a/f/b/j:avw	(Ljava/lang/String;)V
    //   1433: aload 8
    //   1435: ldc_w 303
    //   1438: aload_1
    //   1439: getfield 152	com/tencent/mm/af/r:fjT	Lcom/tencent/mm/af/p;
    //   1442: getfield 349	com/tencent/mm/af/p:fjx	Ljava/lang/String;
    //   1445: invokevirtual 257	com/tencent/mm/model/v$b:j	(Ljava/lang/String;Ljava/lang/Object;)Lcom/tencent/mm/model/v$b;
    //   1448: pop
    //   1449: goto -428 -> 1021
    //   1452: iload_2
    //   1453: aload_0
    //   1454: getfield 28	com/tencent/mm/plugin/brandservice/ui/timeline/video/a/g$b:jYV	Lcom/tencent/mm/plugin/brandservice/ui/timeline/video/a/g;
    //   1457: getfield 358	com/tencent/mm/plugin/brandservice/ui/timeline/video/a/g:jYP	I
    //   1460: if_icmpne +547 -> 2007
    //   1463: aload_0
    //   1464: getfield 28	com/tencent/mm/plugin/brandservice/ui/timeline/video/a/g$b:jYV	Lcom/tencent/mm/plugin/brandservice/ui/timeline/video/a/g;
    //   1467: astore 7
    //   1469: new 360	com/tencent/mm/g/a/cl
    //   1472: dup
    //   1473: invokespecial 361	com/tencent/mm/g/a/cl:<init>	()V
    //   1476: astore 4
    //   1478: new 363	com/tencent/mm/plugin/webview/model/c$a
    //   1481: dup
    //   1482: invokespecial 364	com/tencent/mm/plugin/webview/model/c$a:<init>	()V
    //   1485: astore 5
    //   1487: aload 7
    //   1489: getfield 169	com/tencent/mm/plugin/brandservice/ui/timeline/video/a/g:jWx	Lcom/tencent/mm/plugin/brandservice/ui/timeline/video/b;
    //   1492: astore_1
    //   1493: aload_1
    //   1494: ifnonnull +8 -> 1502
    //   1497: ldc 171
    //   1499: invokestatic 114	a/f/b/j:avw	(Ljava/lang/String;)V
    //   1502: aload 5
    //   1504: aload_1
    //   1505: getfield 200	com/tencent/mm/plugin/brandservice/ui/timeline/video/b:url	Ljava/lang/String;
    //   1508: putfield 365	com/tencent/mm/plugin/webview/model/c$a:url	Ljava/lang/String;
    //   1511: aload 7
    //   1513: getfield 169	com/tencent/mm/plugin/brandservice/ui/timeline/video/a/g:jWx	Lcom/tencent/mm/plugin/brandservice/ui/timeline/video/b;
    //   1516: astore_1
    //   1517: aload_1
    //   1518: ifnonnull +8 -> 1526
    //   1521: ldc 171
    //   1523: invokestatic 114	a/f/b/j:avw	(Ljava/lang/String;)V
    //   1526: aload_1
    //   1527: invokevirtual 176	com/tencent/mm/plugin/brandservice/ui/timeline/video/b:aYp	()Z
    //   1530: ifeq +393 -> 1923
    //   1533: aload 7
    //   1535: getfield 169	com/tencent/mm/plugin/brandservice/ui/timeline/video/a/g:jWx	Lcom/tencent/mm/plugin/brandservice/ui/timeline/video/b;
    //   1538: astore_1
    //   1539: aload_1
    //   1540: ifnonnull +8 -> 1548
    //   1543: ldc 171
    //   1545: invokestatic 114	a/f/b/j:avw	(Ljava/lang/String;)V
    //   1548: aload_1
    //   1549: getfield 180	com/tencent/mm/plugin/brandservice/ui/timeline/video/b:jVI	Lcom/tencent/mm/protocal/protobuf/bac;
    //   1552: astore_1
    //   1553: aload_1
    //   1554: ifnull +359 -> 1913
    //   1557: aload_1
    //   1558: getfield 193	com/tencent/mm/protocal/protobuf/bac:fjx	Ljava/lang/String;
    //   1561: astore_1
    //   1562: aload 5
    //   1564: aload_1
    //   1565: putfield 368	com/tencent/mm/plugin/webview/model/c$a:thumbUrl	Ljava/lang/String;
    //   1568: aload 7
    //   1570: getfield 169	com/tencent/mm/plugin/brandservice/ui/timeline/video/a/g:jWx	Lcom/tencent/mm/plugin/brandservice/ui/timeline/video/b;
    //   1573: astore_1
    //   1574: aload_1
    //   1575: ifnonnull +8 -> 1583
    //   1578: ldc 171
    //   1580: invokestatic 114	a/f/b/j:avw	(Ljava/lang/String;)V
    //   1583: aload_1
    //   1584: getfield 180	com/tencent/mm/plugin/brandservice/ui/timeline/video/b:jVI	Lcom/tencent/mm/protocal/protobuf/bac;
    //   1587: astore_1
    //   1588: aload_1
    //   1589: ifnull +329 -> 1918
    //   1592: aload_1
    //   1593: getfield 185	com/tencent/mm/protocal/protobuf/bac:title	Ljava/lang/String;
    //   1596: astore_1
    //   1597: aload 5
    //   1599: aload_1
    //   1600: putfield 369	com/tencent/mm/plugin/webview/model/c$a:title	Ljava/lang/String;
    //   1603: aload 7
    //   1605: getfield 169	com/tencent/mm/plugin/brandservice/ui/timeline/video/a/g:jWx	Lcom/tencent/mm/plugin/brandservice/ui/timeline/video/b;
    //   1608: astore_1
    //   1609: aload_1
    //   1610: ifnonnull +8 -> 1618
    //   1613: ldc 171
    //   1615: invokestatic 114	a/f/b/j:avw	(Ljava/lang/String;)V
    //   1618: aload_1
    //   1619: getfield 180	com/tencent/mm/plugin/brandservice/ui/timeline/video/b:jVI	Lcom/tencent/mm/protocal/protobuf/bac;
    //   1622: astore 8
    //   1624: aload_3
    //   1625: astore_1
    //   1626: aload 8
    //   1628: ifnull +9 -> 1637
    //   1631: aload 8
    //   1633: getfield 299	com/tencent/mm/protocal/protobuf/bac:fjz	Ljava/lang/String;
    //   1636: astore_1
    //   1637: aload 5
    //   1639: aload_1
    //   1640: putfield 372	com/tencent/mm/plugin/webview/model/c$a:desc	Ljava/lang/String;
    //   1643: aload 7
    //   1645: getfield 144	com/tencent/mm/plugin/brandservice/ui/timeline/video/a/g:jVG	Lcom/tencent/mm/af/r;
    //   1648: astore_1
    //   1649: aload_1
    //   1650: ifnonnull +8 -> 1658
    //   1653: ldc 146
    //   1655: invokestatic 114	a/f/b/j:avw	(Ljava/lang/String;)V
    //   1658: aload_1
    //   1659: getfield 203	com/tencent/mm/af/r:fjS	Ljava/lang/String;
    //   1662: invokestatic 375	com/tencent/mm/sdk/platformtools/bo:nullAsNil	(Ljava/lang/String;)Ljava/lang/String;
    //   1665: invokestatic 236	com/tencent/mm/model/v:nW	(Ljava/lang/String;)Ljava/lang/String;
    //   1668: astore_1
    //   1669: invokestatic 240	com/tencent/mm/model/v:Zp	()Lcom/tencent/mm/model/v;
    //   1672: aload_1
    //   1673: iconst_1
    //   1674: invokevirtual 244	com/tencent/mm/model/v:y	(Ljava/lang/String;Z)Lcom/tencent/mm/model/v$b;
    //   1677: astore_1
    //   1678: aload_1
    //   1679: ifnonnull +6 -> 1685
    //   1682: invokestatic 75	a/f/b/j:dWJ	()V
    //   1685: aload_1
    //   1686: ldc 246
    //   1688: iconst_2
    //   1689: invokestatic 251	java/lang/Integer:valueOf	(I)Ljava/lang/Integer;
    //   1692: invokevirtual 257	com/tencent/mm/model/v$b:j	(Ljava/lang/String;Ljava/lang/Object;)Lcom/tencent/mm/model/v$b;
    //   1695: pop
    //   1696: aload 7
    //   1698: getfield 144	com/tencent/mm/plugin/brandservice/ui/timeline/video/a/g:jVG	Lcom/tencent/mm/af/r;
    //   1701: astore_3
    //   1702: aload_3
    //   1703: ifnonnull +8 -> 1711
    //   1706: ldc 146
    //   1708: invokestatic 114	a/f/b/j:avw	(Ljava/lang/String;)V
    //   1711: aload_1
    //   1712: ldc_w 259
    //   1715: aload_3
    //   1716: invokevirtual 263	com/tencent/mm/af/r:HE	()Ljava/lang/String;
    //   1719: invokevirtual 257	com/tencent/mm/model/v$b:j	(Ljava/lang/String;Ljava/lang/Object;)Lcom/tencent/mm/model/v$b;
    //   1722: pop
    //   1723: aload 7
    //   1725: getfield 144	com/tencent/mm/plugin/brandservice/ui/timeline/video/a/g:jVG	Lcom/tencent/mm/af/r;
    //   1728: astore_3
    //   1729: aload_3
    //   1730: ifnonnull +8 -> 1738
    //   1733: ldc 146
    //   1735: invokestatic 114	a/f/b/j:avw	(Ljava/lang/String;)V
    //   1738: aload_1
    //   1739: ldc_w 265
    //   1742: aload_3
    //   1743: getfield 268	com/tencent/mm/af/r:fjQ	I
    //   1746: invokestatic 251	java/lang/Integer:valueOf	(I)Ljava/lang/Integer;
    //   1749: invokevirtual 257	com/tencent/mm/model/v$b:j	(Ljava/lang/String;Ljava/lang/Object;)Lcom/tencent/mm/model/v$b;
    //   1752: pop
    //   1753: aload 7
    //   1755: getfield 144	com/tencent/mm/plugin/brandservice/ui/timeline/video/a/g:jVG	Lcom/tencent/mm/af/r;
    //   1758: astore_3
    //   1759: aload_3
    //   1760: ifnonnull +8 -> 1768
    //   1763: ldc 146
    //   1765: invokestatic 114	a/f/b/j:avw	(Ljava/lang/String;)V
    //   1768: aload_1
    //   1769: ldc_w 270
    //   1772: aload_3
    //   1773: getfield 203	com/tencent/mm/af/r:fjS	Ljava/lang/String;
    //   1776: invokevirtual 257	com/tencent/mm/model/v$b:j	(Ljava/lang/String;Ljava/lang/Object;)Lcom/tencent/mm/model/v$b;
    //   1779: pop
    //   1780: aload 7
    //   1782: getfield 144	com/tencent/mm/plugin/brandservice/ui/timeline/video/a/g:jVG	Lcom/tencent/mm/af/r;
    //   1785: astore_3
    //   1786: aload_3
    //   1787: ifnonnull +8 -> 1795
    //   1790: ldc 146
    //   1792: invokestatic 114	a/f/b/j:avw	(Ljava/lang/String;)V
    //   1795: aload_1
    //   1796: ldc_w 272
    //   1799: aload_3
    //   1800: invokevirtual 263	com/tencent/mm/af/r:HE	()Ljava/lang/String;
    //   1803: invokevirtual 257	com/tencent/mm/model/v$b:j	(Ljava/lang/String;Ljava/lang/Object;)Lcom/tencent/mm/model/v$b;
    //   1806: pop
    //   1807: aload 7
    //   1809: getfield 169	com/tencent/mm/plugin/brandservice/ui/timeline/video/a/g:jWx	Lcom/tencent/mm/plugin/brandservice/ui/timeline/video/b;
    //   1812: astore_3
    //   1813: aload_3
    //   1814: ifnonnull +8 -> 1822
    //   1817: ldc 171
    //   1819: invokestatic 114	a/f/b/j:avw	(Ljava/lang/String;)V
    //   1822: aload_1
    //   1823: ldc_w 275
    //   1826: aload_3
    //   1827: getfield 200	com/tencent/mm/plugin/brandservice/ui/timeline/video/b:url	Ljava/lang/String;
    //   1830: invokevirtual 257	com/tencent/mm/model/v$b:j	(Ljava/lang/String;Ljava/lang/Object;)Lcom/tencent/mm/model/v$b;
    //   1833: pop
    //   1834: aload 4
    //   1836: getfield 379	com/tencent/mm/g/a/cl:cvA	Lcom/tencent/mm/g/a/cl$a;
    //   1839: aload 7
    //   1841: invokevirtual 72	com/tencent/mm/plugin/brandservice/ui/timeline/video/a/g:aYo	()Lcom/tencent/mm/plugin/brandservice/ui/timeline/video/BizVideoDetailUI;
    //   1844: checkcast 381	android/app/Activity
    //   1847: putfield 387	com/tencent/mm/g/a/cl$a:activity	Landroid/app/Activity;
    //   1850: aload 4
    //   1852: getfield 379	com/tencent/mm/g/a/cl:cvA	Lcom/tencent/mm/g/a/cl$a;
    //   1855: bipush 36
    //   1857: putfield 390	com/tencent/mm/g/a/cl$a:cvH	I
    //   1860: aload 4
    //   1862: aload 5
    //   1864: invokestatic 395	com/tencent/mm/plugin/webview/model/c:a	(Lcom/tencent/mm/g/a/cl;Lcom/tencent/mm/plugin/webview/model/c$a;)Z
    //   1867: pop
    //   1868: getstatic 401	com/tencent/mm/sdk/b/a:xxA	Lcom/tencent/mm/sdk/b/a;
    //   1871: aload 4
    //   1873: checkcast 403	com/tencent/mm/sdk/b/b
    //   1876: invokevirtual 407	com/tencent/mm/sdk/b/a:m	(Lcom/tencent/mm/sdk/b/b;)Z
    //   1879: pop
    //   1880: aload 7
    //   1882: getfield 169	com/tencent/mm/plugin/brandservice/ui/timeline/video/a/g:jWx	Lcom/tencent/mm/plugin/brandservice/ui/timeline/video/b;
    //   1885: astore_1
    //   1886: aload_1
    //   1887: ifnonnull +8 -> 1895
    //   1890: ldc 171
    //   1892: invokestatic 114	a/f/b/j:avw	(Ljava/lang/String;)V
    //   1895: aload_1
    //   1896: getfield 411	com/tencent/mm/plugin/brandservice/ui/timeline/video/b:jVC	Lcom/tencent/mm/plugin/brandservice/ui/timeline/video/a/e;
    //   1899: bipush 24
    //   1901: invokevirtual 416	com/tencent/mm/plugin/brandservice/ui/timeline/video/a/e:sF	(I)V
    //   1904: sipush 15339
    //   1907: invokestatic 90	com/tencent/matrix/trace/core/AppMethodBeat:o	(I)V
    //   1910: goto -1826 -> 84
    //   1913: aconst_null
    //   1914: astore_1
    //   1915: goto -353 -> 1562
    //   1918: aconst_null
    //   1919: astore_1
    //   1920: goto -323 -> 1597
    //   1923: aload 7
    //   1925: getfield 144	com/tencent/mm/plugin/brandservice/ui/timeline/video/a/g:jVG	Lcom/tencent/mm/af/r;
    //   1928: astore_1
    //   1929: aload_1
    //   1930: ifnonnull +8 -> 1938
    //   1933: ldc 146
    //   1935: invokestatic 114	a/f/b/j:avw	(Ljava/lang/String;)V
    //   1938: aload 5
    //   1940: aload_1
    //   1941: getfield 152	com/tencent/mm/af/r:fjT	Lcom/tencent/mm/af/p;
    //   1944: getfield 349	com/tencent/mm/af/p:fjx	Ljava/lang/String;
    //   1947: putfield 368	com/tencent/mm/plugin/webview/model/c$a:thumbUrl	Ljava/lang/String;
    //   1950: aload 7
    //   1952: getfield 144	com/tencent/mm/plugin/brandservice/ui/timeline/video/a/g:jVG	Lcom/tencent/mm/af/r;
    //   1955: astore_1
    //   1956: aload_1
    //   1957: ifnonnull +8 -> 1965
    //   1960: ldc 146
    //   1962: invokestatic 114	a/f/b/j:avw	(Ljava/lang/String;)V
    //   1965: aload 5
    //   1967: aload_1
    //   1968: getfield 152	com/tencent/mm/af/r:fjT	Lcom/tencent/mm/af/p;
    //   1971: getfield 348	com/tencent/mm/af/p:title	Ljava/lang/String;
    //   1974: putfield 369	com/tencent/mm/plugin/webview/model/c$a:title	Ljava/lang/String;
    //   1977: aload 7
    //   1979: getfield 144	com/tencent/mm/plugin/brandservice/ui/timeline/video/a/g:jVG	Lcom/tencent/mm/af/r;
    //   1982: astore_1
    //   1983: aload_1
    //   1984: ifnonnull +8 -> 1992
    //   1987: ldc 146
    //   1989: invokestatic 114	a/f/b/j:avw	(Ljava/lang/String;)V
    //   1992: aload 5
    //   1994: aload_1
    //   1995: getfield 152	com/tencent/mm/af/r:fjT	Lcom/tencent/mm/af/p;
    //   1998: getfield 355	com/tencent/mm/af/p:fjz	Ljava/lang/String;
    //   2001: putfield 372	com/tencent/mm/plugin/webview/model/c$a:desc	Ljava/lang/String;
    //   2004: goto -361 -> 1643
    //   2007: iload_2
    //   2008: aload_0
    //   2009: getfield 28	com/tencent/mm/plugin/brandservice/ui/timeline/video/a/g$b:jYV	Lcom/tencent/mm/plugin/brandservice/ui/timeline/video/a/g;
    //   2012: getfield 419	com/tencent/mm/plugin/brandservice/ui/timeline/video/a/g:jYQ	I
    //   2015: if_icmpne +49 -> 2064
    //   2018: aload_0
    //   2019: getfield 28	com/tencent/mm/plugin/brandservice/ui/timeline/video/a/g$b:jYV	Lcom/tencent/mm/plugin/brandservice/ui/timeline/video/a/g;
    //   2022: invokevirtual 72	com/tencent/mm/plugin/brandservice/ui/timeline/video/a/g:aYo	()Lcom/tencent/mm/plugin/brandservice/ui/timeline/video/BizVideoDetailUI;
    //   2025: checkcast 77	android/content/Context
    //   2028: aload_0
    //   2029: getfield 28	com/tencent/mm/plugin/brandservice/ui/timeline/video/a/g$b:jYV	Lcom/tencent/mm/plugin/brandservice/ui/timeline/video/a/g;
    //   2032: invokestatic 81	com/tencent/mm/plugin/brandservice/ui/timeline/video/a/g:a	(Lcom/tencent/mm/plugin/brandservice/ui/timeline/video/a/g;)Lcom/tencent/mm/af/r;
    //   2035: getfield 152	com/tencent/mm/af/r:fjT	Lcom/tencent/mm/af/p;
    //   2038: getfield 348	com/tencent/mm/af/p:title	Ljava/lang/String;
    //   2041: new 421	com/tencent/mm/plugin/brandservice/ui/timeline/video/a/g$b$1
    //   2044: dup
    //   2045: aload_0
    //   2046: invokespecial 424	com/tencent/mm/plugin/brandservice/ui/timeline/video/a/g$b$1:<init>	(Lcom/tencent/mm/plugin/brandservice/ui/timeline/video/a/g$b;)V
    //   2049: checkcast 426	android/content/DialogInterface$OnClickListener
    //   2052: invokestatic 431	com/tencent/mm/plugin/webview/e/c:a	(Landroid/content/Context;Ljava/lang/String;Landroid/content/DialogInterface$OnClickListener;)V
    //   2055: sipush 15339
    //   2058: invokestatic 90	com/tencent/matrix/trace/core/AppMethodBeat:o	(I)V
    //   2061: goto -1977 -> 84
    //   2064: iload_2
    //   2065: aload_0
    //   2066: getfield 28	com/tencent/mm/plugin/brandservice/ui/timeline/video/a/g$b:jYV	Lcom/tencent/mm/plugin/brandservice/ui/timeline/video/a/g;
    //   2069: getfield 434	com/tencent/mm/plugin/brandservice/ui/timeline/video/a/g:jYR	I
    //   2072: if_icmpne +26 -> 2098
    //   2075: aload_0
    //   2076: getfield 28	com/tencent/mm/plugin/brandservice/ui/timeline/video/a/g$b:jYV	Lcom/tencent/mm/plugin/brandservice/ui/timeline/video/a/g;
    //   2079: invokestatic 85	com/tencent/mm/plugin/brandservice/ui/timeline/video/a/g:b	(Lcom/tencent/mm/plugin/brandservice/ui/timeline/video/a/g;)Lcom/tencent/mm/plugin/brandservice/ui/timeline/video/b;
    //   2082: iconst_2
    //   2083: ldc_w 435
    //   2086: invokevirtual 439	com/tencent/mm/plugin/brandservice/ui/timeline/video/b:ao	(ILjava/lang/String;)V
    //   2089: sipush 15339
    //   2092: invokestatic 90	com/tencent/matrix/trace/core/AppMethodBeat:o	(I)V
    //   2095: goto -2011 -> 84
    //   2098: iload_2
    //   2099: aload_0
    //   2100: getfield 28	com/tencent/mm/plugin/brandservice/ui/timeline/video/a/g$b:jYV	Lcom/tencent/mm/plugin/brandservice/ui/timeline/video/a/g;
    //   2103: getfield 442	com/tencent/mm/plugin/brandservice/ui/timeline/video/a/g:jYS	I
    //   2106: if_icmpne +170 -> 2276
    //   2109: aload_0
    //   2110: getfield 28	com/tencent/mm/plugin/brandservice/ui/timeline/video/a/g$b:jYV	Lcom/tencent/mm/plugin/brandservice/ui/timeline/video/a/g;
    //   2113: astore_1
    //   2114: aload_1
    //   2115: getfield 169	com/tencent/mm/plugin/brandservice/ui/timeline/video/a/g:jWx	Lcom/tencent/mm/plugin/brandservice/ui/timeline/video/b;
    //   2118: astore 5
    //   2120: aload 5
    //   2122: ifnonnull +8 -> 2130
    //   2125: ldc 171
    //   2127: invokestatic 114	a/f/b/j:avw	(Ljava/lang/String;)V
    //   2130: aload 5
    //   2132: getfield 443	com/tencent/mm/plugin/brandservice/ui/timeline/video/b:fgc	I
    //   2135: iconst_1
    //   2136: iand
    //   2137: ifeq +61 -> 2198
    //   2140: aload_1
    //   2141: getfield 97	com/tencent/mm/plugin/brandservice/ui/timeline/video/a/g:TAG	Ljava/lang/String;
    //   2144: astore 5
    //   2146: new 445	java/lang/StringBuilder
    //   2149: dup
    //   2150: ldc_w 447
    //   2153: invokespecial 449	java/lang/StringBuilder:<init>	(Ljava/lang/String;)V
    //   2156: astore 4
    //   2158: aload_1
    //   2159: getfield 169	com/tencent/mm/plugin/brandservice/ui/timeline/video/a/g:jWx	Lcom/tencent/mm/plugin/brandservice/ui/timeline/video/b;
    //   2162: astore_1
    //   2163: aload_1
    //   2164: ifnonnull +8 -> 2172
    //   2167: ldc 171
    //   2169: invokestatic 114	a/f/b/j:avw	(Ljava/lang/String;)V
    //   2172: aload 5
    //   2174: aload 4
    //   2176: aload_1
    //   2177: getfield 443	com/tencent/mm/plugin/brandservice/ui/timeline/video/b:fgc	I
    //   2180: invokevirtual 453	java/lang/StringBuilder:append	(I)Ljava/lang/StringBuilder;
    //   2183: invokevirtual 456	java/lang/StringBuilder:toString	()Ljava/lang/String;
    //   2186: invokestatic 459	com/tencent/mm/sdk/platformtools/ab:w	(Ljava/lang/String;Ljava/lang/String;)V
    //   2189: sipush 15339
    //   2192: invokestatic 90	com/tencent/matrix/trace/core/AppMethodBeat:o	(I)V
    //   2195: goto -2111 -> 84
    //   2198: new 139	android/content/Intent
    //   2201: dup
    //   2202: invokespecial 140	android/content/Intent:<init>	()V
    //   2205: astore 4
    //   2207: aload_1
    //   2208: getfield 169	com/tencent/mm/plugin/brandservice/ui/timeline/video/a/g:jWx	Lcom/tencent/mm/plugin/brandservice/ui/timeline/video/b;
    //   2211: astore 5
    //   2213: aload 5
    //   2215: ifnonnull +8 -> 2223
    //   2218: ldc 171
    //   2220: invokestatic 114	a/f/b/j:avw	(Ljava/lang/String;)V
    //   2223: aload 4
    //   2225: ldc_w 461
    //   2228: aload 5
    //   2230: invokevirtual 462	com/tencent/mm/plugin/brandservice/ui/timeline/video/b:HE	()Ljava/lang/String;
    //   2233: invokevirtual 190	android/content/Intent:putExtra	(Ljava/lang/String;Ljava/lang/String;)Landroid/content/Intent;
    //   2236: pop
    //   2237: aload 4
    //   2239: ldc_w 464
    //   2242: sipush 153
    //   2245: invokevirtual 163	android/content/Intent:putExtra	(Ljava/lang/String;I)Landroid/content/Intent;
    //   2248: pop
    //   2249: aload_1
    //   2250: invokevirtual 72	com/tencent/mm/plugin/brandservice/ui/timeline/video/a/g:aYo	()Lcom/tencent/mm/plugin/brandservice/ui/timeline/video/BizVideoDetailUI;
    //   2253: checkcast 77	android/content/Context
    //   2256: ldc_w 466
    //   2259: ldc_w 468
    //   2262: aload 4
    //   2264: invokestatic 471	com/tencent/mm/bp/d:b	(Landroid/content/Context;Ljava/lang/String;Ljava/lang/String;Landroid/content/Intent;)V
    //   2267: sipush 15339
    //   2270: invokestatic 90	com/tencent/matrix/trace/core/AppMethodBeat:o	(I)V
    //   2273: goto -2189 -> 84
    //   2276: iload_2
    //   2277: aload_0
    //   2278: getfield 28	com/tencent/mm/plugin/brandservice/ui/timeline/video/a/g$b:jYV	Lcom/tencent/mm/plugin/brandservice/ui/timeline/video/a/g;
    //   2281: getfield 474	com/tencent/mm/plugin/brandservice/ui/timeline/video/a/g:jYT	I
    //   2284: if_icmpne +234 -> 2518
    //   2287: aload_0
    //   2288: getfield 28	com/tencent/mm/plugin/brandservice/ui/timeline/video/a/g$b:jYV	Lcom/tencent/mm/plugin/brandservice/ui/timeline/video/a/g;
    //   2291: astore 5
    //   2293: aload 5
    //   2295: invokevirtual 477	com/tencent/mm/plugin/brandservice/ui/timeline/video/a/g:isFinished	()Z
    //   2298: ifeq +23 -> 2321
    //   2301: aload 5
    //   2303: getfield 97	com/tencent/mm/plugin/brandservice/ui/timeline/video/a/g:TAG	Ljava/lang/String;
    //   2306: ldc_w 479
    //   2309: invokestatic 482	com/tencent/mm/sdk/platformtools/ab:e	(Ljava/lang/String;Ljava/lang/String;)V
    //   2312: sipush 15339
    //   2315: invokestatic 90	com/tencent/matrix/trace/core/AppMethodBeat:o	(I)V
    //   2318: goto -2234 -> 84
    //   2321: aload 5
    //   2323: invokevirtual 72	com/tencent/mm/plugin/brandservice/ui/timeline/video/a/g:aYo	()Lcom/tencent/mm/plugin/brandservice/ui/timeline/video/BizVideoDetailUI;
    //   2326: astore_1
    //   2327: aload_1
    //   2328: ifnull +43 -> 2371
    //   2331: aload_1
    //   2332: invokevirtual 486	com/tencent/mm/plugin/brandservice/ui/timeline/video/BizVideoDetailUI:getApplication	()Landroid/app/Application;
    //   2335: astore_1
    //   2336: aload_1
    //   2337: ifnull +34 -> 2371
    //   2340: aload_1
    //   2341: ldc_w 488
    //   2344: invokevirtual 494	android/app/Application:getSystemService	(Ljava/lang/String;)Ljava/lang/Object;
    //   2347: astore_1
    //   2348: aload_1
    //   2349: ifnonnull +27 -> 2376
    //   2352: new 496	a/v
    //   2355: dup
    //   2356: ldc_w 498
    //   2359: invokespecial 499	a/v:<init>	(Ljava/lang/String;)V
    //   2362: astore_1
    //   2363: sipush 15339
    //   2366: invokestatic 90	com/tencent/matrix/trace/core/AppMethodBeat:o	(I)V
    //   2369: aload_1
    //   2370: athrow
    //   2371: aconst_null
    //   2372: astore_1
    //   2373: goto -25 -> 2348
    //   2376: aload_1
    //   2377: checkcast 501	android/text/ClipboardManager
    //   2380: astore_1
    //   2381: aload_1
    //   2382: ifnull +116 -> 2498
    //   2385: aload 5
    //   2387: getfield 169	com/tencent/mm/plugin/brandservice/ui/timeline/video/a/g:jWx	Lcom/tencent/mm/plugin/brandservice/ui/timeline/video/b;
    //   2390: astore 4
    //   2392: aload 4
    //   2394: ifnonnull +8 -> 2402
    //   2397: ldc 171
    //   2399: invokestatic 114	a/f/b/j:avw	(Ljava/lang/String;)V
    //   2402: aload_1
    //   2403: aload 4
    //   2405: getfield 504	com/tencent/mm/plugin/brandservice/ui/timeline/video/b:jVB	Ljava/lang/String;
    //   2408: checkcast 506	java/lang/CharSequence
    //   2411: invokevirtual 510	android/text/ClipboardManager:setText	(Ljava/lang/CharSequence;)V
    //   2414: aload 5
    //   2416: invokevirtual 72	com/tencent/mm/plugin/brandservice/ui/timeline/video/a/g:aYo	()Lcom/tencent/mm/plugin/brandservice/ui/timeline/video/BizVideoDetailUI;
    //   2419: checkcast 77	android/content/Context
    //   2422: astore 4
    //   2424: aload 5
    //   2426: invokevirtual 72	com/tencent/mm/plugin/brandservice/ui/timeline/video/a/g:aYo	()Lcom/tencent/mm/plugin/brandservice/ui/timeline/video/BizVideoDetailUI;
    //   2429: astore_1
    //   2430: aload_1
    //   2431: ifnull +62 -> 2493
    //   2434: aload_1
    //   2435: ldc_w 511
    //   2438: invokevirtual 515	com/tencent/mm/plugin/brandservice/ui/timeline/video/BizVideoDetailUI:getString	(I)Ljava/lang/String;
    //   2441: astore_1
    //   2442: aload 4
    //   2444: aload_1
    //   2445: checkcast 506	java/lang/CharSequence
    //   2448: iconst_0
    //   2449: invokestatic 521	android/widget/Toast:makeText	(Landroid/content/Context;Ljava/lang/CharSequence;I)Landroid/widget/Toast;
    //   2452: invokevirtual 524	android/widget/Toast:show	()V
    //   2455: sipush 15339
    //   2458: invokestatic 90	com/tencent/matrix/trace/core/AppMethodBeat:o	(I)V
    //   2461: goto -2377 -> 84
    //   2464: astore_1
    //   2465: aload 5
    //   2467: getfield 97	com/tencent/mm/plugin/brandservice/ui/timeline/video/a/g:TAG	Ljava/lang/String;
    //   2470: aload_1
    //   2471: checkcast 526	java/lang/Throwable
    //   2474: ldc_w 528
    //   2477: iconst_0
    //   2478: anewarray 4	java/lang/Object
    //   2481: invokestatic 532	com/tencent/mm/sdk/platformtools/ab:printErrStackTrace	(Ljava/lang/String;Ljava/lang/Throwable;Ljava/lang/String;[Ljava/lang/Object;)V
    //   2484: sipush 15339
    //   2487: invokestatic 90	com/tencent/matrix/trace/core/AppMethodBeat:o	(I)V
    //   2490: goto -2406 -> 84
    //   2493: aconst_null
    //   2494: astore_1
    //   2495: goto -53 -> 2442
    //   2498: aload 5
    //   2500: getfield 97	com/tencent/mm/plugin/brandservice/ui/timeline/video/a/g:TAG	Ljava/lang/String;
    //   2503: ldc_w 534
    //   2506: invokestatic 482	com/tencent/mm/sdk/platformtools/ab:e	(Ljava/lang/String;Ljava/lang/String;)V
    //   2509: sipush 15339
    //   2512: invokestatic 90	com/tencent/matrix/trace/core/AppMethodBeat:o	(I)V
    //   2515: goto -2431 -> 84
    //   2518: iload_2
    //   2519: aload_0
    //   2520: getfield 28	com/tencent/mm/plugin/brandservice/ui/timeline/video/a/g$b:jYV	Lcom/tencent/mm/plugin/brandservice/ui/timeline/video/a/g;
    //   2523: getfield 537	com/tencent/mm/plugin/brandservice/ui/timeline/video/a/g:jYU	I
    //   2526: if_icmpne +396 -> 2922
    //   2529: aload_0
    //   2530: getfield 28	com/tencent/mm/plugin/brandservice/ui/timeline/video/a/g$b:jYV	Lcom/tencent/mm/plugin/brandservice/ui/timeline/video/a/g;
    //   2533: astore_3
    //   2534: aload_3
    //   2535: getfield 144	com/tencent/mm/plugin/brandservice/ui/timeline/video/a/g:jVG	Lcom/tencent/mm/af/r;
    //   2538: astore_1
    //   2539: aload_1
    //   2540: ifnonnull +8 -> 2548
    //   2543: ldc 146
    //   2545: invokestatic 114	a/f/b/j:avw	(Ljava/lang/String;)V
    //   2548: aload_1
    //   2549: getfield 152	com/tencent/mm/af/r:fjT	Lcom/tencent/mm/af/p;
    //   2552: getfield 538	com/tencent/mm/af/p:url	Ljava/lang/String;
    //   2555: astore 7
    //   2557: aload 7
    //   2559: invokestatic 212	com/tencent/mm/sdk/platformtools/bo:isNullOrNil	(Ljava/lang/String;)Z
    //   2562: ifne +404 -> 2966
    //   2565: aload 7
    //   2567: invokestatic 544	android/net/Uri:parse	(Ljava/lang/String;)Landroid/net/Uri;
    //   2570: astore_1
    //   2571: aload_1
    //   2572: ldc_w 546
    //   2575: invokestatic 52	a/f/b/j:o	(Ljava/lang/Object;Ljava/lang/String;)V
    //   2578: aload_1
    //   2579: invokevirtual 549	android/net/Uri:getHost	()Ljava/lang/String;
    //   2582: astore_1
    //   2583: aload_1
    //   2584: invokestatic 212	com/tencent/mm/sdk/platformtools/bo:isNullOrNil	(Ljava/lang/String;)Z
    //   2587: ifne +291 -> 2878
    //   2590: aload_1
    //   2591: ifnonnull +6 -> 2597
    //   2594: invokestatic 75	a/f/b/j:dWJ	()V
    //   2597: aload_1
    //   2598: ldc_w 551
    //   2601: invokestatic 557	a/k/m:jb	(Ljava/lang/String;Ljava/lang/String;)Z
    //   2604: ifeq +274 -> 2878
    //   2607: getstatic 563	a/f/b/y:AVH	La/f/b/y;
    //   2610: astore_1
    //   2611: ldc_w 565
    //   2614: iconst_1
    //   2615: anewarray 4	java/lang/Object
    //   2618: dup
    //   2619: iconst_0
    //   2620: aload 7
    //   2622: ldc_w 567
    //   2625: invokestatic 573	com/tencent/mm/compatible/util/q:encode	(Ljava/lang/String;Ljava/lang/String;)Ljava/lang/String;
    //   2628: aastore
    //   2629: iconst_1
    //   2630: invokestatic 579	java/util/Arrays:copyOf	([Ljava/lang/Object;I)[Ljava/lang/Object;
    //   2633: invokestatic 585	java/lang/String:format	(Ljava/lang/String;[Ljava/lang/Object;)Ljava/lang/String;
    //   2636: astore_1
    //   2637: aload_1
    //   2638: ldc_w 587
    //   2641: invokestatic 52	a/f/b/j:o	(Ljava/lang/Object;Ljava/lang/String;)V
    //   2644: aload_1
    //   2645: invokestatic 212	com/tencent/mm/sdk/platformtools/bo:isNullOrNil	(Ljava/lang/String;)Z
    //   2648: ifeq +315 -> 2963
    //   2651: getstatic 563	a/f/b/y:AVH	La/f/b/y;
    //   2654: astore_1
    //   2655: ldc_w 589
    //   2658: iconst_1
    //   2659: anewarray 4	java/lang/Object
    //   2662: dup
    //   2663: iconst_0
    //   2664: bipush 34
    //   2666: invokestatic 251	java/lang/Integer:valueOf	(I)Ljava/lang/Integer;
    //   2669: aastore
    //   2670: iconst_1
    //   2671: invokestatic 579	java/util/Arrays:copyOf	([Ljava/lang/Object;I)[Ljava/lang/Object;
    //   2674: invokestatic 585	java/lang/String:format	(Ljava/lang/String;[Ljava/lang/Object;)Ljava/lang/String;
    //   2677: astore_1
    //   2678: aload_1
    //   2679: ldc_w 587
    //   2682: invokestatic 52	a/f/b/j:o	(Ljava/lang/Object;Ljava/lang/String;)V
    //   2685: new 139	android/content/Intent
    //   2688: dup
    //   2689: invokespecial 140	android/content/Intent:<init>	()V
    //   2692: astore 8
    //   2694: aload_3
    //   2695: invokevirtual 72	com/tencent/mm/plugin/brandservice/ui/timeline/video/a/g:aYo	()Lcom/tencent/mm/plugin/brandservice/ui/timeline/video/BizVideoDetailUI;
    //   2698: astore 5
    //   2700: aload 5
    //   2702: ifnull +181 -> 2883
    //   2705: aload 5
    //   2707: ldc_w 591
    //   2710: iconst_0
    //   2711: invokevirtual 595	com/tencent/mm/plugin/brandservice/ui/timeline/video/BizVideoDetailUI:getDir	(Ljava/lang/String;I)Ljava/io/File;
    //   2714: astore 5
    //   2716: aload 5
    //   2718: ifnull +9 -> 2727
    //   2721: aload 5
    //   2723: invokevirtual 600	java/io/File:mkdirs	()Z
    //   2726: pop
    //   2727: aload 5
    //   2729: ifnull +10 -> 2739
    //   2732: aload 5
    //   2734: invokevirtual 603	java/io/File:getAbsolutePath	()Ljava/lang/String;
    //   2737: astore 4
    //   2739: aload 4
    //   2741: ldc_w 605
    //   2744: invokestatic 609	a/f/b/j:u	(Ljava/lang/String;Ljava/lang/Object;)Ljava/lang/String;
    //   2747: astore 5
    //   2749: aload_3
    //   2750: invokevirtual 72	com/tencent/mm/plugin/brandservice/ui/timeline/video/a/g:aYo	()Lcom/tencent/mm/plugin/brandservice/ui/timeline/video/BizVideoDetailUI;
    //   2753: checkcast 381	android/app/Activity
    //   2756: invokestatic 615	com/tencent/mm/sdk/platformtools/bc:am	(Landroid/app/Activity;)Landroid/graphics/Bitmap;
    //   2759: bipush 75
    //   2761: getstatic 621	android/graphics/Bitmap$CompressFormat:JPEG	Landroid/graphics/Bitmap$CompressFormat;
    //   2764: aload 5
    //   2766: iconst_1
    //   2767: invokestatic 626	com/tencent/mm/sdk/platformtools/d:a	(Landroid/graphics/Bitmap;ILandroid/graphics/Bitmap$CompressFormat;Ljava/lang/String;Z)V
    //   2770: aload 8
    //   2772: ldc_w 628
    //   2775: aload 5
    //   2777: invokevirtual 190	android/content/Intent:putExtra	(Ljava/lang/String;Ljava/lang/String;)Landroid/content/Intent;
    //   2780: pop
    //   2781: aload 8
    //   2783: ldc_w 630
    //   2786: aload_1
    //   2787: invokevirtual 190	android/content/Intent:putExtra	(Ljava/lang/String;Ljava/lang/String;)Landroid/content/Intent;
    //   2790: pop
    //   2791: aload 8
    //   2793: ldc_w 632
    //   2796: aload 7
    //   2798: invokevirtual 190	android/content/Intent:putExtra	(Ljava/lang/String;Ljava/lang/String;)Landroid/content/Intent;
    //   2801: pop
    //   2802: aload_3
    //   2803: getfield 169	com/tencent/mm/plugin/brandservice/ui/timeline/video/a/g:jWx	Lcom/tencent/mm/plugin/brandservice/ui/timeline/video/b;
    //   2806: astore_1
    //   2807: aload_1
    //   2808: ifnonnull +8 -> 2816
    //   2811: ldc 171
    //   2813: invokestatic 114	a/f/b/j:avw	(Ljava/lang/String;)V
    //   2816: aload 8
    //   2818: ldc_w 634
    //   2821: aload_1
    //   2822: getfield 637	com/tencent/mm/plugin/brandservice/ui/timeline/video/b:scene	I
    //   2825: invokevirtual 163	android/content/Intent:putExtra	(Ljava/lang/String;I)Landroid/content/Intent;
    //   2828: pop
    //   2829: aload 8
    //   2831: ldc_w 639
    //   2834: iconst_0
    //   2835: invokevirtual 230	android/content/Intent:putExtra	(Ljava/lang/String;Z)Landroid/content/Intent;
    //   2838: pop
    //   2839: aload_3
    //   2840: invokevirtual 72	com/tencent/mm/plugin/brandservice/ui/timeline/video/a/g:aYo	()Lcom/tencent/mm/plugin/brandservice/ui/timeline/video/BizVideoDetailUI;
    //   2843: checkcast 77	android/content/Context
    //   2846: ldc_w 641
    //   2849: ldc_w 643
    //   2852: aload 8
    //   2854: invokestatic 471	com/tencent/mm/bp/d:b	(Landroid/content/Context;Ljava/lang/String;Ljava/lang/String;Landroid/content/Intent;)V
    //   2857: sipush 15339
    //   2860: invokestatic 90	com/tencent/matrix/trace/core/AppMethodBeat:o	(I)V
    //   2863: goto -2779 -> 84
    //   2866: astore_1
    //   2867: aload_3
    //   2868: getfield 97	com/tencent/mm/plugin/brandservice/ui/timeline/video/a/g:TAG	Ljava/lang/String;
    //   2871: aload_1
    //   2872: invokevirtual 646	java/io/UnsupportedEncodingException:getMessage	()Ljava/lang/String;
    //   2875: invokestatic 482	com/tencent/mm/sdk/platformtools/ab:e	(Ljava/lang/String;Ljava/lang/String;)V
    //   2878: aconst_null
    //   2879: astore_1
    //   2880: goto -236 -> 2644
    //   2883: aconst_null
    //   2884: astore 5
    //   2886: goto -170 -> 2716
    //   2889: astore 5
    //   2891: aload_3
    //   2892: getfield 97	com/tencent/mm/plugin/brandservice/ui/timeline/video/a/g:TAG	Ljava/lang/String;
    //   2895: new 445	java/lang/StringBuilder
    //   2898: dup
    //   2899: ldc_w 648
    //   2902: invokespecial 449	java/lang/StringBuilder:<init>	(Ljava/lang/String;)V
    //   2905: aload 5
    //   2907: invokevirtual 649	java/io/IOException:getMessage	()Ljava/lang/String;
    //   2910: invokevirtual 652	java/lang/StringBuilder:append	(Ljava/lang/String;)Ljava/lang/StringBuilder;
    //   2913: invokevirtual 456	java/lang/StringBuilder:toString	()Ljava/lang/String;
    //   2916: invokestatic 482	com/tencent/mm/sdk/platformtools/ab:e	(Ljava/lang/String;Ljava/lang/String;)V
    //   2919: goto -138 -> 2781
    //   2922: aload_0
    //   2923: getfield 28	com/tencent/mm/plugin/brandservice/ui/timeline/video/a/g$b:jYV	Lcom/tencent/mm/plugin/brandservice/ui/timeline/video/a/g;
    //   2926: getfield 97	com/tencent/mm/plugin/brandservice/ui/timeline/video/a/g:TAG	Ljava/lang/String;
    //   2929: new 445	java/lang/StringBuilder
    //   2932: dup
    //   2933: ldc_w 654
    //   2936: invokespecial 449	java/lang/StringBuilder:<init>	(Ljava/lang/String;)V
    //   2939: aload_1
    //   2940: invokeinterface 58 1 0
    //   2945: invokevirtual 453	java/lang/StringBuilder:append	(I)Ljava/lang/StringBuilder;
    //   2948: invokevirtual 456	java/lang/StringBuilder:toString	()Ljava/lang/String;
    //   2951: invokestatic 459	com/tencent/mm/sdk/platformtools/ab:w	(Ljava/lang/String;Ljava/lang/String;)V
    //   2954: sipush 15339
    //   2957: invokestatic 90	com/tencent/matrix/trace/core/AppMethodBeat:o	(I)V
    //   2960: goto -2876 -> 84
    //   2963: goto -278 -> 2685
    //   2966: aconst_null
    //   2967: astore_1
    //   2968: goto -385 -> 2583
    //
    // Exception table:
    //   from	to	target	type
    //   2385	2392	2464	java/lang/Exception
    //   2397	2402	2464	java/lang/Exception
    //   2402	2430	2464	java/lang/Exception
    //   2434	2442	2464	java/lang/Exception
    //   2442	2461	2464	java/lang/Exception
    //   2498	2509	2464	java/lang/Exception
    //   2607	2644	2866	java/io/UnsupportedEncodingException
    //   2694	2700	2889	java/io/IOException
    //   2705	2716	2889	java/io/IOException
    //   2721	2727	2889	java/io/IOException
    //   2732	2739	2889	java/io/IOException
    //   2739	2781	2889	java/io/IOException
  }
}

/* Location:           C:\Users\Lin\Downloads\dex-tools-2.1-SNAPSHOT\dex-tools-2.1-SNAPSHOT\classes6-dex2jar.jar
 * Qualified Name:     com.tencent.mm.plugin.brandservice.ui.timeline.video.a.g.b
 * JD-Core Version:    0.6.2
 */