package com.tencent.mm.plugin.emoji.d;

import com.tencent.mm.at.a.c.b;

public final class a
  implements b
{
  // ERROR //
  public final com.tencent.mm.at.a.d.b sE(java.lang.String paramString)
  {
    // Byte code:
    //   0: ldc 32
    //   2: invokestatic 38	com/tencent/matrix/trace/core/AppMethodBeat:i	(I)V
    //   5: ldc 40
    //   7: astore_2
    //   8: aload_2
    //   9: astore_3
    //   10: aload_2
    //   11: astore 4
    //   13: aload_2
    //   14: astore 5
    //   16: aload_2
    //   17: astore 6
    //   19: aload_2
    //   20: astore 7
    //   22: aload_2
    //   23: astore 8
    //   25: aload_2
    //   26: astore 9
    //   28: aload_2
    //   29: astore 10
    //   31: new 42	com/tencent/mm/network/b$b
    //   34: astore 11
    //   36: aload_2
    //   37: astore_3
    //   38: aload_2
    //   39: astore 4
    //   41: aload_2
    //   42: astore 5
    //   44: aload_2
    //   45: astore 6
    //   47: aload_2
    //   48: astore 7
    //   50: aload_2
    //   51: astore 8
    //   53: aload_2
    //   54: astore 9
    //   56: aload_2
    //   57: astore 10
    //   59: aload 11
    //   61: aload_1
    //   62: invokespecial 45	com/tencent/mm/network/b$b:<init>	(Ljava/lang/String;)V
    //   65: aload_2
    //   66: astore 12
    //   68: aload_2
    //   69: astore_3
    //   70: aload_2
    //   71: astore 4
    //   73: aload_2
    //   74: astore 5
    //   76: aload_2
    //   77: astore 6
    //   79: aload_2
    //   80: astore 7
    //   82: aload_2
    //   83: astore 8
    //   85: aload_2
    //   86: astore 9
    //   88: aload_2
    //   89: astore 10
    //   91: aload 11
    //   93: getfield 49	com/tencent/mm/network/b$b:ip	Ljava/lang/String;
    //   96: invokestatic 55	com/tencent/mm/sdk/platformtools/bo:isNullOrNil	(Ljava/lang/String;)Z
    //   99: ifne +33 -> 132
    //   102: aload_2
    //   103: astore_3
    //   104: aload_2
    //   105: astore 4
    //   107: aload_2
    //   108: astore 5
    //   110: aload_2
    //   111: astore 6
    //   113: aload_2
    //   114: astore 7
    //   116: aload_2
    //   117: astore 8
    //   119: aload_2
    //   120: astore 9
    //   122: aload_2
    //   123: astore 10
    //   125: aload 11
    //   127: getfield 49	com/tencent/mm/network/b$b:ip	Ljava/lang/String;
    //   130: astore 12
    //   132: aload 12
    //   134: astore_3
    //   135: aload 12
    //   137: astore 4
    //   139: aload 12
    //   141: astore 5
    //   143: aload 12
    //   145: astore 6
    //   147: aload 12
    //   149: astore 7
    //   151: aload 12
    //   153: astore 8
    //   155: aload 12
    //   157: astore 9
    //   159: aload 12
    //   161: astore 10
    //   163: aload 11
    //   165: getfield 49	com/tencent/mm/network/b$b:ip	Ljava/lang/String;
    //   168: astore_2
    //   169: aload 11
    //   171: getfield 59	com/tencent/mm/network/b$b:gcI	I
    //   174: istore 13
    //   176: aload_1
    //   177: aload 11
    //   179: invokestatic 63	com/tencent/mm/plugin/emoji/d/a$a:c	(Ljava/lang/String;Lcom/tencent/mm/network/b$b;)Lcom/tencent/mm/at/a/d/b;
    //   182: astore 9
    //   184: aload 9
    //   186: astore_1
    //   187: ldc 32
    //   189: invokestatic 66	com/tencent/matrix/trace/core/AppMethodBeat:o	(I)V
    //   192: aload_1
    //   193: areturn
    //   194: astore 9
    //   196: iconst_0
    //   197: istore 13
    //   199: ldc 40
    //   201: astore_2
    //   202: aload_3
    //   203: astore 12
    //   205: ldc 68
    //   207: ldc 70
    //   209: iconst_5
    //   210: anewarray 4	java/lang/Object
    //   213: dup
    //   214: iconst_0
    //   215: aload_1
    //   216: aastore
    //   217: dup
    //   218: iconst_1
    //   219: aload 12
    //   221: aastore
    //   222: dup
    //   223: iconst_2
    //   224: aload_2
    //   225: aastore
    //   226: dup
    //   227: iconst_3
    //   228: iload 13
    //   230: invokestatic 76	java/lang/Integer:valueOf	(I)Ljava/lang/Integer;
    //   233: aastore
    //   234: dup
    //   235: iconst_4
    //   236: aload 9
    //   238: invokestatic 80	com/tencent/mm/sdk/platformtools/bo:l	(Ljava/lang/Throwable;)Ljava/lang/String;
    //   241: aastore
    //   242: invokestatic 86	com/tencent/mm/sdk/platformtools/ab:e	(Ljava/lang/String;Ljava/lang/String;[Ljava/lang/Object;)V
    //   245: getstatic 92	com/tencent/mm/plugin/report/service/h:pYm	Lcom/tencent/mm/plugin/report/service/h;
    //   248: ldc2_w 93
    //   251: ldc2_w 95
    //   254: lconst_1
    //   255: iconst_0
    //   256: invokevirtual 100	com/tencent/mm/plugin/report/service/h:a	(JJJZ)V
    //   259: aload 12
    //   261: astore_1
    //   262: iload 13
    //   264: iconst_1
    //   265: if_icmpne +16 -> 281
    //   268: invokestatic 106	com/tencent/mm/sdk/platformtools/ah:getContext	()Landroid/content/Context;
    //   271: invokestatic 112	com/tencent/mm/sdk/platformtools/at:isConnected	(Landroid/content/Context;)Z
    //   274: ifeq +7 -> 281
    //   277: aload_1
    //   278: invokestatic 117	com/tencent/mm/network/b:reportFailIp	(Ljava/lang/String;)V
    //   281: new 119	com/tencent/mm/at/a/d/b
    //   284: dup
    //   285: aconst_null
    //   286: aconst_null
    //   287: invokespecial 122	com/tencent/mm/at/a/d/b:<init>	([BLjava/lang/String;)V
    //   290: astore_1
    //   291: ldc 32
    //   293: invokestatic 66	com/tencent/matrix/trace/core/AppMethodBeat:o	(I)V
    //   296: goto -104 -> 192
    //   299: astore 9
    //   301: iconst_0
    //   302: istore 13
    //   304: ldc 40
    //   306: astore_2
    //   307: aload 4
    //   309: astore 12
    //   311: ldc 68
    //   313: ldc 70
    //   315: iconst_5
    //   316: anewarray 4	java/lang/Object
    //   319: dup
    //   320: iconst_0
    //   321: aload_1
    //   322: aastore
    //   323: dup
    //   324: iconst_1
    //   325: aload 12
    //   327: aastore
    //   328: dup
    //   329: iconst_2
    //   330: aload_2
    //   331: aastore
    //   332: dup
    //   333: iconst_3
    //   334: iload 13
    //   336: invokestatic 76	java/lang/Integer:valueOf	(I)Ljava/lang/Integer;
    //   339: aastore
    //   340: dup
    //   341: iconst_4
    //   342: aload 9
    //   344: invokestatic 80	com/tencent/mm/sdk/platformtools/bo:l	(Ljava/lang/Throwable;)Ljava/lang/String;
    //   347: aastore
    //   348: invokestatic 86	com/tencent/mm/sdk/platformtools/ab:e	(Ljava/lang/String;Ljava/lang/String;[Ljava/lang/Object;)V
    //   351: getstatic 92	com/tencent/mm/plugin/report/service/h:pYm	Lcom/tencent/mm/plugin/report/service/h;
    //   354: ldc2_w 93
    //   357: lconst_0
    //   358: lconst_1
    //   359: iconst_0
    //   360: invokevirtual 100	com/tencent/mm/plugin/report/service/h:a	(JJJZ)V
    //   363: aload 12
    //   365: astore_1
    //   366: goto -104 -> 262
    //   369: astore 9
    //   371: iconst_0
    //   372: istore 13
    //   374: ldc 40
    //   376: astore_2
    //   377: aload 5
    //   379: astore 12
    //   381: ldc 68
    //   383: ldc 70
    //   385: iconst_5
    //   386: anewarray 4	java/lang/Object
    //   389: dup
    //   390: iconst_0
    //   391: aload_1
    //   392: aastore
    //   393: dup
    //   394: iconst_1
    //   395: aload 12
    //   397: aastore
    //   398: dup
    //   399: iconst_2
    //   400: aload_2
    //   401: aastore
    //   402: dup
    //   403: iconst_3
    //   404: iload 13
    //   406: invokestatic 76	java/lang/Integer:valueOf	(I)Ljava/lang/Integer;
    //   409: aastore
    //   410: dup
    //   411: iconst_4
    //   412: aload 9
    //   414: invokestatic 80	com/tencent/mm/sdk/platformtools/bo:l	(Ljava/lang/Throwable;)Ljava/lang/String;
    //   417: aastore
    //   418: invokestatic 86	com/tencent/mm/sdk/platformtools/ab:e	(Ljava/lang/String;Ljava/lang/String;[Ljava/lang/Object;)V
    //   421: getstatic 92	com/tencent/mm/plugin/report/service/h:pYm	Lcom/tencent/mm/plugin/report/service/h;
    //   424: ldc2_w 93
    //   427: lconst_1
    //   428: lconst_1
    //   429: iconst_0
    //   430: invokevirtual 100	com/tencent/mm/plugin/report/service/h:a	(JJJZ)V
    //   433: aload 12
    //   435: astore_1
    //   436: goto -174 -> 262
    //   439: astore 9
    //   441: iconst_0
    //   442: istore 13
    //   444: ldc 40
    //   446: astore_2
    //   447: aload 6
    //   449: astore 12
    //   451: ldc 68
    //   453: ldc 70
    //   455: iconst_5
    //   456: anewarray 4	java/lang/Object
    //   459: dup
    //   460: iconst_0
    //   461: aload_1
    //   462: aastore
    //   463: dup
    //   464: iconst_1
    //   465: aload 12
    //   467: aastore
    //   468: dup
    //   469: iconst_2
    //   470: aload_2
    //   471: aastore
    //   472: dup
    //   473: iconst_3
    //   474: iload 13
    //   476: invokestatic 76	java/lang/Integer:valueOf	(I)Ljava/lang/Integer;
    //   479: aastore
    //   480: dup
    //   481: iconst_4
    //   482: aload 9
    //   484: invokestatic 80	com/tencent/mm/sdk/platformtools/bo:l	(Ljava/lang/Throwable;)Ljava/lang/String;
    //   487: aastore
    //   488: invokestatic 86	com/tencent/mm/sdk/platformtools/ab:e	(Ljava/lang/String;Ljava/lang/String;[Ljava/lang/Object;)V
    //   491: getstatic 92	com/tencent/mm/plugin/report/service/h:pYm	Lcom/tencent/mm/plugin/report/service/h;
    //   494: ldc2_w 93
    //   497: ldc2_w 123
    //   500: lconst_1
    //   501: iconst_0
    //   502: invokevirtual 100	com/tencent/mm/plugin/report/service/h:a	(JJJZ)V
    //   505: aload 12
    //   507: astore_1
    //   508: goto -246 -> 262
    //   511: astore 9
    //   513: iconst_0
    //   514: istore 13
    //   516: ldc 40
    //   518: astore_2
    //   519: aload 7
    //   521: astore 12
    //   523: ldc 68
    //   525: ldc 70
    //   527: iconst_5
    //   528: anewarray 4	java/lang/Object
    //   531: dup
    //   532: iconst_0
    //   533: aload_1
    //   534: aastore
    //   535: dup
    //   536: iconst_1
    //   537: aload 12
    //   539: aastore
    //   540: dup
    //   541: iconst_2
    //   542: aload_2
    //   543: aastore
    //   544: dup
    //   545: iconst_3
    //   546: iload 13
    //   548: invokestatic 76	java/lang/Integer:valueOf	(I)Ljava/lang/Integer;
    //   551: aastore
    //   552: dup
    //   553: iconst_4
    //   554: aload 9
    //   556: invokestatic 80	com/tencent/mm/sdk/platformtools/bo:l	(Ljava/lang/Throwable;)Ljava/lang/String;
    //   559: aastore
    //   560: invokestatic 86	com/tencent/mm/sdk/platformtools/ab:e	(Ljava/lang/String;Ljava/lang/String;[Ljava/lang/Object;)V
    //   563: getstatic 92	com/tencent/mm/plugin/report/service/h:pYm	Lcom/tencent/mm/plugin/report/service/h;
    //   566: ldc2_w 93
    //   569: ldc2_w 125
    //   572: lconst_1
    //   573: iconst_0
    //   574: invokevirtual 100	com/tencent/mm/plugin/report/service/h:a	(JJJZ)V
    //   577: aload 12
    //   579: astore_1
    //   580: goto -318 -> 262
    //   583: astore 9
    //   585: iconst_0
    //   586: istore 13
    //   588: ldc 40
    //   590: astore_2
    //   591: aload 8
    //   593: astore 12
    //   595: ldc 68
    //   597: ldc 70
    //   599: iconst_5
    //   600: anewarray 4	java/lang/Object
    //   603: dup
    //   604: iconst_0
    //   605: aload_1
    //   606: aastore
    //   607: dup
    //   608: iconst_1
    //   609: aload 12
    //   611: aastore
    //   612: dup
    //   613: iconst_2
    //   614: aload_2
    //   615: aastore
    //   616: dup
    //   617: iconst_3
    //   618: iload 13
    //   620: invokestatic 76	java/lang/Integer:valueOf	(I)Ljava/lang/Integer;
    //   623: aastore
    //   624: dup
    //   625: iconst_4
    //   626: aload 9
    //   628: invokestatic 80	com/tencent/mm/sdk/platformtools/bo:l	(Ljava/lang/Throwable;)Ljava/lang/String;
    //   631: aastore
    //   632: invokestatic 86	com/tencent/mm/sdk/platformtools/ab:e	(Ljava/lang/String;Ljava/lang/String;[Ljava/lang/Object;)V
    //   635: getstatic 92	com/tencent/mm/plugin/report/service/h:pYm	Lcom/tencent/mm/plugin/report/service/h;
    //   638: ldc2_w 93
    //   641: ldc2_w 127
    //   644: lconst_1
    //   645: iconst_0
    //   646: invokevirtual 100	com/tencent/mm/plugin/report/service/h:a	(JJJZ)V
    //   649: aload 12
    //   651: astore_1
    //   652: goto -390 -> 262
    //   655: astore_3
    //   656: iconst_0
    //   657: istore 13
    //   659: ldc 40
    //   661: astore_2
    //   662: aload 9
    //   664: astore 12
    //   666: aload_3
    //   667: astore 9
    //   669: ldc 68
    //   671: ldc 70
    //   673: iconst_5
    //   674: anewarray 4	java/lang/Object
    //   677: dup
    //   678: iconst_0
    //   679: aload_1
    //   680: aastore
    //   681: dup
    //   682: iconst_1
    //   683: aload 12
    //   685: aastore
    //   686: dup
    //   687: iconst_2
    //   688: aload_2
    //   689: aastore
    //   690: dup
    //   691: iconst_3
    //   692: iload 13
    //   694: invokestatic 76	java/lang/Integer:valueOf	(I)Ljava/lang/Integer;
    //   697: aastore
    //   698: dup
    //   699: iconst_4
    //   700: aload 9
    //   702: invokestatic 80	com/tencent/mm/sdk/platformtools/bo:l	(Ljava/lang/Throwable;)Ljava/lang/String;
    //   705: aastore
    //   706: invokestatic 86	com/tencent/mm/sdk/platformtools/ab:e	(Ljava/lang/String;Ljava/lang/String;[Ljava/lang/Object;)V
    //   709: getstatic 92	com/tencent/mm/plugin/report/service/h:pYm	Lcom/tencent/mm/plugin/report/service/h;
    //   712: ldc2_w 93
    //   715: ldc2_w 129
    //   718: lconst_1
    //   719: iconst_0
    //   720: invokevirtual 100	com/tencent/mm/plugin/report/service/h:a	(JJJZ)V
    //   723: aload 12
    //   725: astore_1
    //   726: goto -464 -> 262
    //   729: astore 9
    //   731: iconst_0
    //   732: istore 13
    //   734: ldc 40
    //   736: astore_2
    //   737: aload 10
    //   739: astore 12
    //   741: ldc 68
    //   743: ldc 70
    //   745: iconst_5
    //   746: anewarray 4	java/lang/Object
    //   749: dup
    //   750: iconst_0
    //   751: aload_1
    //   752: aastore
    //   753: dup
    //   754: iconst_1
    //   755: aload 12
    //   757: aastore
    //   758: dup
    //   759: iconst_2
    //   760: aload_2
    //   761: aastore
    //   762: dup
    //   763: iconst_3
    //   764: iload 13
    //   766: invokestatic 76	java/lang/Integer:valueOf	(I)Ljava/lang/Integer;
    //   769: aastore
    //   770: dup
    //   771: iconst_4
    //   772: aload 9
    //   774: invokestatic 80	com/tencent/mm/sdk/platformtools/bo:l	(Ljava/lang/Throwable;)Ljava/lang/String;
    //   777: aastore
    //   778: invokestatic 86	com/tencent/mm/sdk/platformtools/ab:e	(Ljava/lang/String;Ljava/lang/String;[Ljava/lang/Object;)V
    //   781: getstatic 92	com/tencent/mm/plugin/report/service/h:pYm	Lcom/tencent/mm/plugin/report/service/h;
    //   784: ldc2_w 93
    //   787: ldc2_w 131
    //   790: lconst_1
    //   791: iconst_0
    //   792: invokevirtual 100	com/tencent/mm/plugin/report/service/h:a	(JJJZ)V
    //   795: aload 12
    //   797: astore_1
    //   798: goto -536 -> 262
    //   801: astore 9
    //   803: iconst_0
    //   804: istore 13
    //   806: goto -65 -> 741
    //   809: astore 9
    //   811: goto -70 -> 741
    //   814: astore 9
    //   816: iconst_0
    //   817: istore 13
    //   819: goto -150 -> 669
    //   822: astore 9
    //   824: goto -155 -> 669
    //   827: astore 9
    //   829: iconst_0
    //   830: istore 13
    //   832: goto -237 -> 595
    //   835: astore 9
    //   837: goto -242 -> 595
    //   840: astore 9
    //   842: iconst_0
    //   843: istore 13
    //   845: goto -322 -> 523
    //   848: astore 9
    //   850: goto -327 -> 523
    //   853: astore 9
    //   855: iconst_0
    //   856: istore 13
    //   858: goto -407 -> 451
    //   861: astore 9
    //   863: goto -412 -> 451
    //   866: astore 9
    //   868: iconst_0
    //   869: istore 13
    //   871: goto -490 -> 381
    //   874: astore 9
    //   876: goto -495 -> 381
    //   879: astore 9
    //   881: iconst_0
    //   882: istore 13
    //   884: goto -573 -> 311
    //   887: astore 9
    //   889: goto -578 -> 311
    //   892: astore 9
    //   894: iconst_0
    //   895: istore 13
    //   897: goto -692 -> 205
    //   900: astore 9
    //   902: goto -697 -> 205
    //
    // Exception table:
    //   from	to	target	type
    //   31	36	194	java/net/ProtocolException
    //   59	65	194	java/net/ProtocolException
    //   91	102	194	java/net/ProtocolException
    //   125	132	194	java/net/ProtocolException
    //   163	169	194	java/net/ProtocolException
    //   31	36	299	java/lang/InterruptedException
    //   59	65	299	java/lang/InterruptedException
    //   91	102	299	java/lang/InterruptedException
    //   125	132	299	java/lang/InterruptedException
    //   163	169	299	java/lang/InterruptedException
    //   31	36	369	java/net/UnknownHostException
    //   59	65	369	java/net/UnknownHostException
    //   91	102	369	java/net/UnknownHostException
    //   125	132	369	java/net/UnknownHostException
    //   163	169	369	java/net/UnknownHostException
    //   31	36	439	javax/net/ssl/SSLHandshakeException
    //   59	65	439	javax/net/ssl/SSLHandshakeException
    //   91	102	439	javax/net/ssl/SSLHandshakeException
    //   125	132	439	javax/net/ssl/SSLHandshakeException
    //   163	169	439	javax/net/ssl/SSLHandshakeException
    //   31	36	511	java/net/SocketException
    //   59	65	511	java/net/SocketException
    //   91	102	511	java/net/SocketException
    //   125	132	511	java/net/SocketException
    //   163	169	511	java/net/SocketException
    //   31	36	583	java/net/SocketTimeoutException
    //   59	65	583	java/net/SocketTimeoutException
    //   91	102	583	java/net/SocketTimeoutException
    //   125	132	583	java/net/SocketTimeoutException
    //   163	169	583	java/net/SocketTimeoutException
    //   31	36	655	java/io/IOException
    //   59	65	655	java/io/IOException
    //   91	102	655	java/io/IOException
    //   125	132	655	java/io/IOException
    //   163	169	655	java/io/IOException
    //   31	36	729	java/lang/Exception
    //   59	65	729	java/lang/Exception
    //   91	102	729	java/lang/Exception
    //   125	132	729	java/lang/Exception
    //   163	169	729	java/lang/Exception
    //   169	176	801	java/lang/Exception
    //   176	184	809	java/lang/Exception
    //   169	176	814	java/io/IOException
    //   176	184	822	java/io/IOException
    //   169	176	827	java/net/SocketTimeoutException
    //   176	184	835	java/net/SocketTimeoutException
    //   169	176	840	java/net/SocketException
    //   176	184	848	java/net/SocketException
    //   169	176	853	javax/net/ssl/SSLHandshakeException
    //   176	184	861	javax/net/ssl/SSLHandshakeException
    //   169	176	866	java/net/UnknownHostException
    //   176	184	874	java/net/UnknownHostException
    //   169	176	879	java/lang/InterruptedException
    //   176	184	887	java/lang/InterruptedException
    //   169	176	892	java/net/ProtocolException
    //   176	184	900	java/net/ProtocolException
  }
}

/* Location:           C:\Users\Lin\Downloads\dex-tools-2.1-SNAPSHOT\dex-tools-2.1-SNAPSHOT\classes3-dex2jar.jar
 * Qualified Name:     com.tencent.mm.plugin.emoji.d.a
 * JD-Core Version:    0.6.2
 */