package com.tencent.tencentmap.mapsdk.maps.a;

final class ej
  implements Runnable
{
  ej(ec paramec)
  {
  }

  // ERROR //
  public final void run()
  {
    // Byte code:
    //   0: iconst_0
    //   1: istore_1
    //   2: iconst_0
    //   3: istore_2
    //   4: ldc 20
    //   6: invokestatic 26	com/tencent/matrix/trace/core/AppMethodBeat:i	(I)V
    //   9: invokestatic 32	android/os/SystemClock:elapsedRealtime	()J
    //   12: lstore_3
    //   13: new 34	com/tencent/tencentmap/mapsdk/maps/a/du
    //   16: astore 5
    //   18: aload 5
    //   20: invokespecial 35	com/tencent/tencentmap/mapsdk/maps/a/du:<init>	()V
    //   23: aload_0
    //   24: getfield 12	com/tencent/tencentmap/mapsdk/maps/a/ej:a	Lcom/tencent/tencentmap/mapsdk/maps/a/ec;
    //   27: invokestatic 41	com/tencent/tencentmap/mapsdk/maps/a/ec:d	(Lcom/tencent/tencentmap/mapsdk/maps/a/ec;)Ljava/util/Map;
    //   30: invokeinterface 47 1 0
    //   35: invokeinterface 53 1 0
    //   40: astore 6
    //   42: aload 6
    //   44: invokeinterface 59 1 0
    //   49: ifeq +83 -> 132
    //   52: aload 6
    //   54: invokeinterface 63 1 0
    //   59: checkcast 65	com/tencent/tencentmap/mapsdk/maps/a/dy
    //   62: aload 5
    //   64: invokevirtual 68	com/tencent/tencentmap/mapsdk/maps/a/dy:a	(Lcom/tencent/tencentmap/mapsdk/maps/a/du;)V
    //   67: goto -25 -> 42
    //   70: astore 6
    //   72: iload_2
    //   73: istore 7
    //   75: aload_0
    //   76: getfield 12	com/tencent/tencentmap/mapsdk/maps/a/ej:a	Lcom/tencent/tencentmap/mapsdk/maps/a/ec;
    //   79: invokestatic 74	com/tencent/tencentmap/mapsdk/maps/a/ce:b	()Ljava/lang/String;
    //   82: invokestatic 77	com/tencent/tencentmap/mapsdk/maps/a/ec:a	(Lcom/tencent/tencentmap/mapsdk/maps/a/ec;Ljava/lang/String;)Lcom/tencent/tencentmap/mapsdk/maps/a/ec$a;
    //   85: astore 6
    //   87: aload 6
    //   89: invokestatic 32	android/os/SystemClock:elapsedRealtime	()J
    //   92: putfield 82	com/tencent/tencentmap/mapsdk/maps/a/ec$a:a	J
    //   95: aload 6
    //   97: iload 7
    //   99: putfield 85	com/tencent/tencentmap/mapsdk/maps/a/ec$a:b	I
    //   102: aload_0
    //   103: getfield 12	com/tencent/tencentmap/mapsdk/maps/a/ej:a	Lcom/tencent/tencentmap/mapsdk/maps/a/ec;
    //   106: invokestatic 88	com/tencent/tencentmap/mapsdk/maps/a/ec:e	(Lcom/tencent/tencentmap/mapsdk/maps/a/ec;)V
    //   109: aload_0
    //   110: getfield 12	com/tencent/tencentmap/mapsdk/maps/a/ej:a	Lcom/tencent/tencentmap/mapsdk/maps/a/ec;
    //   113: invokestatic 92	com/tencent/tencentmap/mapsdk/maps/a/ec:c	(Lcom/tencent/tencentmap/mapsdk/maps/a/ec;)Landroid/os/Handler;
    //   116: aload_0
    //   117: getfield 12	com/tencent/tencentmap/mapsdk/maps/a/ej:a	Lcom/tencent/tencentmap/mapsdk/maps/a/ec;
    //   120: invokestatic 95	com/tencent/tencentmap/mapsdk/maps/a/ec:b	(Lcom/tencent/tencentmap/mapsdk/maps/a/ec;)Ljava/lang/Runnable;
    //   123: invokevirtual 101	android/os/Handler:removeCallbacks	(Ljava/lang/Runnable;)V
    //   126: ldc 20
    //   128: invokestatic 104	com/tencent/matrix/trace/core/AppMethodBeat:o	(I)V
    //   131: return
    //   132: aload 5
    //   134: invokevirtual 107	com/tencent/tencentmap/mapsdk/maps/a/du:a	()[B
    //   137: astore 6
    //   139: aload 6
    //   141: invokestatic 112	com/tencent/tencentmap/mapsdk/maps/a/eu:a	([B)Z
    //   144: ifne +318 -> 462
    //   147: ldc 114
    //   149: iconst_0
    //   150: aconst_null
    //   151: aload 6
    //   153: sipush 15000
    //   156: invokestatic 116	com/tencent/tencentmap/mapsdk/maps/a/eu:d	()Ljava/lang/String;
    //   159: iconst_0
    //   160: invokestatic 121	com/tencent/tencentmap/mapsdk/maps/a/en:d	()Lcom/tencent/tencentmap/mapsdk/maps/a/en;
    //   163: invokevirtual 125	com/tencent/tencentmap/mapsdk/maps/a/en:f	()Lcom/tencent/tencentmap/mapsdk/maps/a/cd;
    //   166: invokestatic 130	com/tencent/tencentmap/mapsdk/maps/a/cs:a	(Ljava/lang/String;ZLjava/util/Map;[BILjava/lang/String;ZLcom/tencent/tencentmap/mapsdk/maps/a/cd;)Lcom/tencent/tencentmap/mapsdk/maps/a/cs;
    //   169: astore 6
    //   171: aload 6
    //   173: invokestatic 133	com/tencent/tencentmap/mapsdk/maps/a/ec:f	()I
    //   176: invokevirtual 135	com/tencent/tencentmap/mapsdk/maps/a/cs:a	(I)V
    //   179: aload 6
    //   181: ldc 137
    //   183: invokevirtual 140	com/tencent/tencentmap/mapsdk/maps/a/cs:a	(Ljava/lang/String;)V
    //   186: aload 6
    //   188: invokevirtual 143	com/tencent/tencentmap/mapsdk/maps/a/cs:a	()Lcom/tencent/tencentmap/mapsdk/maps/a/cv;
    //   191: astore 8
    //   193: aload 8
    //   195: getfield 147	com/tencent/tencentmap/mapsdk/maps/a/cv:a	I
    //   198: istore 7
    //   200: aload 8
    //   202: getfield 147	com/tencent/tencentmap/mapsdk/maps/a/cv:a	I
    //   205: ifne +108 -> 313
    //   208: aload 8
    //   210: getfield 149	com/tencent/tencentmap/mapsdk/maps/a/cv:c	I
    //   213: sipush 200
    //   216: if_icmpne +97 -> 313
    //   219: aload 8
    //   221: getfield 152	com/tencent/tencentmap/mapsdk/maps/a/cv:d	[B
    //   224: invokestatic 112	com/tencent/tencentmap/mapsdk/maps/a/eu:a	([B)Z
    //   227: istore 9
    //   229: iload 9
    //   231: ifne +82 -> 313
    //   234: new 154	java/lang/String
    //   237: astore 5
    //   239: aload 5
    //   241: aload 8
    //   243: getfield 152	com/tencent/tencentmap/mapsdk/maps/a/cv:d	[B
    //   246: invokespecial 157	java/lang/String:<init>	([B)V
    //   249: new 159	org/json/JSONObject
    //   252: astore 8
    //   254: aload 8
    //   256: aload 5
    //   258: invokespecial 161	org/json/JSONObject:<init>	(Ljava/lang/String;)V
    //   261: invokestatic 163	com/tencent/tencentmap/mapsdk/maps/a/ce:e	()V
    //   264: aload_0
    //   265: getfield 12	com/tencent/tencentmap/mapsdk/maps/a/ej:a	Lcom/tencent/tencentmap/mapsdk/maps/a/ec;
    //   268: invokestatic 41	com/tencent/tencentmap/mapsdk/maps/a/ec:d	(Lcom/tencent/tencentmap/mapsdk/maps/a/ec;)Ljava/util/Map;
    //   271: invokeinterface 47 1 0
    //   276: invokeinterface 53 1 0
    //   281: astore 5
    //   283: aload 5
    //   285: invokeinterface 59 1 0
    //   290: ifeq +23 -> 313
    //   293: aload 5
    //   295: invokeinterface 63 1 0
    //   300: checkcast 65	com/tencent/tencentmap/mapsdk/maps/a/dy
    //   303: aload 8
    //   305: invokevirtual 166	com/tencent/tencentmap/mapsdk/maps/a/dy:a	(Lorg/json/JSONObject;)V
    //   308: goto -25 -> 283
    //   311: astore 5
    //   313: aload 6
    //   315: invokestatic 32	android/os/SystemClock:elapsedRealtime	()J
    //   318: lload_3
    //   319: lsub
    //   320: putfield 169	com/tencent/tencentmap/mapsdk/maps/a/cs:k	J
    //   323: aload 6
    //   325: iconst_0
    //   326: invokevirtual 172	com/tencent/tencentmap/mapsdk/maps/a/cs:a	(Z)V
    //   329: aload_0
    //   330: getfield 12	com/tencent/tencentmap/mapsdk/maps/a/ej:a	Lcom/tencent/tencentmap/mapsdk/maps/a/ec;
    //   333: invokestatic 74	com/tencent/tencentmap/mapsdk/maps/a/ce:b	()Ljava/lang/String;
    //   336: invokestatic 77	com/tencent/tencentmap/mapsdk/maps/a/ec:a	(Lcom/tencent/tencentmap/mapsdk/maps/a/ec;Ljava/lang/String;)Lcom/tencent/tencentmap/mapsdk/maps/a/ec$a;
    //   339: astore 6
    //   341: aload 6
    //   343: invokestatic 32	android/os/SystemClock:elapsedRealtime	()J
    //   346: putfield 82	com/tencent/tencentmap/mapsdk/maps/a/ec$a:a	J
    //   349: aload 6
    //   351: iload 7
    //   353: putfield 85	com/tencent/tencentmap/mapsdk/maps/a/ec$a:b	I
    //   356: aload_0
    //   357: getfield 12	com/tencent/tencentmap/mapsdk/maps/a/ej:a	Lcom/tencent/tencentmap/mapsdk/maps/a/ec;
    //   360: invokestatic 88	com/tencent/tencentmap/mapsdk/maps/a/ec:e	(Lcom/tencent/tencentmap/mapsdk/maps/a/ec;)V
    //   363: aload_0
    //   364: getfield 12	com/tencent/tencentmap/mapsdk/maps/a/ej:a	Lcom/tencent/tencentmap/mapsdk/maps/a/ec;
    //   367: invokestatic 92	com/tencent/tencentmap/mapsdk/maps/a/ec:c	(Lcom/tencent/tencentmap/mapsdk/maps/a/ec;)Landroid/os/Handler;
    //   370: aload_0
    //   371: getfield 12	com/tencent/tencentmap/mapsdk/maps/a/ej:a	Lcom/tencent/tencentmap/mapsdk/maps/a/ec;
    //   374: invokestatic 95	com/tencent/tencentmap/mapsdk/maps/a/ec:b	(Lcom/tencent/tencentmap/mapsdk/maps/a/ec;)Ljava/lang/Runnable;
    //   377: invokevirtual 101	android/os/Handler:removeCallbacks	(Ljava/lang/Runnable;)V
    //   380: ldc 20
    //   382: invokestatic 104	com/tencent/matrix/trace/core/AppMethodBeat:o	(I)V
    //   385: goto -254 -> 131
    //   388: astore 6
    //   390: iload_1
    //   391: istore 7
    //   393: aload_0
    //   394: getfield 12	com/tencent/tencentmap/mapsdk/maps/a/ej:a	Lcom/tencent/tencentmap/mapsdk/maps/a/ec;
    //   397: invokestatic 74	com/tencent/tencentmap/mapsdk/maps/a/ce:b	()Ljava/lang/String;
    //   400: invokestatic 77	com/tencent/tencentmap/mapsdk/maps/a/ec:a	(Lcom/tencent/tencentmap/mapsdk/maps/a/ec;Ljava/lang/String;)Lcom/tencent/tencentmap/mapsdk/maps/a/ec$a;
    //   403: astore 5
    //   405: aload 5
    //   407: invokestatic 32	android/os/SystemClock:elapsedRealtime	()J
    //   410: putfield 82	com/tencent/tencentmap/mapsdk/maps/a/ec$a:a	J
    //   413: aload 5
    //   415: iload 7
    //   417: putfield 85	com/tencent/tencentmap/mapsdk/maps/a/ec$a:b	I
    //   420: aload_0
    //   421: getfield 12	com/tencent/tencentmap/mapsdk/maps/a/ej:a	Lcom/tencent/tencentmap/mapsdk/maps/a/ec;
    //   424: invokestatic 88	com/tencent/tencentmap/mapsdk/maps/a/ec:e	(Lcom/tencent/tencentmap/mapsdk/maps/a/ec;)V
    //   427: aload_0
    //   428: getfield 12	com/tencent/tencentmap/mapsdk/maps/a/ej:a	Lcom/tencent/tencentmap/mapsdk/maps/a/ec;
    //   431: invokestatic 92	com/tencent/tencentmap/mapsdk/maps/a/ec:c	(Lcom/tencent/tencentmap/mapsdk/maps/a/ec;)Landroid/os/Handler;
    //   434: aload_0
    //   435: getfield 12	com/tencent/tencentmap/mapsdk/maps/a/ej:a	Lcom/tencent/tencentmap/mapsdk/maps/a/ec;
    //   438: invokestatic 95	com/tencent/tencentmap/mapsdk/maps/a/ec:b	(Lcom/tencent/tencentmap/mapsdk/maps/a/ec;)Ljava/lang/Runnable;
    //   441: invokevirtual 101	android/os/Handler:removeCallbacks	(Ljava/lang/Runnable;)V
    //   444: ldc 20
    //   446: invokestatic 104	com/tencent/matrix/trace/core/AppMethodBeat:o	(I)V
    //   449: aload 6
    //   451: athrow
    //   452: astore 6
    //   454: goto -61 -> 393
    //   457: astore 6
    //   459: goto -384 -> 75
    //   462: iconst_0
    //   463: istore 7
    //   465: goto -136 -> 329
    //
    // Exception table:
    //   from	to	target	type
    //   13	42	70	java/lang/Throwable
    //   42	67	70	java/lang/Throwable
    //   132	200	70	java/lang/Throwable
    //   234	283	311	java/lang/Throwable
    //   283	308	311	java/lang/Throwable
    //   13	42	388	finally
    //   42	67	388	finally
    //   132	200	388	finally
    //   200	229	452	finally
    //   234	283	452	finally
    //   283	308	452	finally
    //   313	329	452	finally
    //   200	229	457	java/lang/Throwable
    //   313	329	457	java/lang/Throwable
  }
}

/* Location:           C:\Users\Lin\Downloads\dex-tools-2.1-SNAPSHOT\dex-tools-2.1-SNAPSHOT\classes2-dex2jar.jar
 * Qualified Name:     com.tencent.tencentmap.mapsdk.maps.a.ej
 * JD-Core Version:    0.6.2
 */