package com.tencent.tencentmap.mapsdk.maps.a;

import android.content.Context;
import android.content.pm.ApplicationInfo;
import android.content.pm.PackageManager;
import android.content.pm.PackageManager.NameNotFoundException;
import android.os.AsyncTask;
import android.os.Bundle;
import com.tencent.matrix.trace.core.AppMethodBeat;
import java.lang.ref.WeakReference;
import org.json.JSONObject;

public class jt
{
  private Context a;
  private WeakReference<jt.b> b;

  public jt(Context paramContext, jt.b paramb)
  {
    AppMethodBeat.i(100106);
    this.a = paramContext;
    this.b = new WeakReference(paramb);
    AppMethodBeat.o(100106);
  }

  private int a(String paramString, int paramInt)
  {
    AppMethodBeat.i(100108);
    paramString = new JSONObject(paramString);
    int i = paramInt;
    if (paramString.optInt("error", -1) == 0)
    {
      paramString = paramString.optJSONObject("info");
      i = paramInt;
      if (paramString != null)
        i = paramString.optInt("scenic", paramInt);
    }
    AppMethodBeat.o(100108);
    return i;
  }

  private String a(Context paramContext)
  {
    AppMethodBeat.i(100109);
    if (paramContext == null)
    {
      paramContext = "";
      AppMethodBeat.o(100109);
    }
    while (true)
    {
      return paramContext;
      String str = paramContext.getPackageName();
      Object localObject = null;
      try
      {
        paramContext = paramContext.getPackageManager().getApplicationInfo(str, 128);
        if (paramContext == null)
        {
          paramContext = "";
          AppMethodBeat.o(100109);
          continue;
        }
        if (paramContext.metaData == null)
        {
          paramContext = "";
          AppMethodBeat.o(100109);
          continue;
        }
        paramContext = paramContext.metaData.getString(ic.b);
        AppMethodBeat.o(100109);
      }
      catch (PackageManager.NameNotFoundException paramContext)
      {
        while (true)
          paramContext = localObject;
      }
    }
  }

  public void a()
  {
    AppMethodBeat.i(100107);
    new a(null).execute(new Context[] { this.a });
    AppMethodBeat.o(100107);
  }

  class a extends AsyncTask<Context, Void, Void>
  {
    private a()
    {
    }

    // ERROR //
    protected Void a(Context[] paramArrayOfContext)
    {
      // Byte code:
      //   0: iconst_0
      //   1: istore_2
      //   2: iconst_0
      //   3: istore_3
      //   4: iconst_0
      //   5: istore 4
      //   7: ldc 24
      //   9: invokestatic 30	com/tencent/matrix/trace/core/AppMethodBeat:i	(I)V
      //   12: invokestatic 35	com/tencent/tencentmap/mapsdk/maps/a/jp:a	()I
      //   15: istore 5
      //   17: new 37	java/lang/StringBuilder
      //   20: dup
      //   21: invokespecial 38	java/lang/StringBuilder:<init>	()V
      //   24: astore 6
      //   26: aload 6
      //   28: ldc 40
      //   30: invokevirtual 44	java/lang/StringBuilder:append	(Ljava/lang/String;)Ljava/lang/StringBuilder;
      //   33: pop
      //   34: aload 6
      //   36: ldc 46
      //   38: invokevirtual 44	java/lang/StringBuilder:append	(Ljava/lang/String;)Ljava/lang/StringBuilder;
      //   41: pop
      //   42: aload_1
      //   43: ifnull +27 -> 70
      //   46: aload_1
      //   47: arraylength
      //   48: ifle +22 -> 70
      //   51: aload 6
      //   53: aload_0
      //   54: getfield 13	com/tencent/tencentmap/mapsdk/maps/a/jt$a:a	Lcom/tencent/tencentmap/mapsdk/maps/a/jt;
      //   57: aload_1
      //   58: iconst_0
      //   59: aaload
      //   60: invokevirtual 52	android/content/Context:getApplicationContext	()Landroid/content/Context;
      //   63: invokestatic 55	com/tencent/tencentmap/mapsdk/maps/a/jt:a	(Lcom/tencent/tencentmap/mapsdk/maps/a/jt;Landroid/content/Context;)Ljava/lang/String;
      //   66: invokevirtual 44	java/lang/StringBuilder:append	(Ljava/lang/String;)Ljava/lang/StringBuilder;
      //   69: pop
      //   70: new 57	java/net/URL
      //   73: astore_1
      //   74: aload_1
      //   75: aload 6
      //   77: invokevirtual 61	java/lang/StringBuilder:toString	()Ljava/lang/String;
      //   80: invokespecial 64	java/net/URL:<init>	(Ljava/lang/String;)V
      //   83: aload_1
      //   84: invokevirtual 68	java/net/URL:openConnection	()Ljava/net/URLConnection;
      //   87: checkcast 70	javax/net/ssl/HttpsURLConnection
      //   90: astore_1
      //   91: aload_1
      //   92: sipush 3000
      //   95: invokevirtual 73	javax/net/ssl/HttpsURLConnection:setConnectTimeout	(I)V
      //   98: aload_1
      //   99: invokevirtual 76	javax/net/ssl/HttpsURLConnection:connect	()V
      //   102: aload_1
      //   103: invokevirtual 80	javax/net/ssl/HttpsURLConnection:getInputStream	()Ljava/io/InputStream;
      //   106: astore 6
      //   108: aload 6
      //   110: invokestatic 85	com/tencent/tencentmap/mapsdk/a/v:a	(Ljava/io/InputStream;)[B
      //   113: astore 7
      //   115: aload 7
      //   117: ifnull +13 -> 130
      //   120: aload 7
      //   122: arraylength
      //   123: istore 8
      //   125: iload 8
      //   127: ifne +123 -> 250
      //   130: aload_1
      //   131: ifnull +7 -> 138
      //   134: aload_1
      //   135: invokevirtual 88	javax/net/ssl/HttpsURLConnection:disconnect	()V
      //   138: aload 6
      //   140: ifnull +8 -> 148
      //   143: aload 6
      //   145: invokestatic 91	com/tencent/tencentmap/mapsdk/a/v:a	(Ljava/io/Closeable;)V
      //   148: iload 4
      //   150: istore_2
      //   151: iload 5
      //   153: invokestatic 35	com/tencent/tencentmap/mapsdk/maps/a/jp:a	()I
      //   156: if_icmpeq +5 -> 161
      //   159: iconst_1
      //   160: istore_2
      //   161: iload_2
      //   162: ifeq +81 -> 243
      //   165: aload_0
      //   166: getfield 13	com/tencent/tencentmap/mapsdk/maps/a/jt$a:a	Lcom/tencent/tencentmap/mapsdk/maps/a/jt;
      //   169: invokestatic 94	com/tencent/tencentmap/mapsdk/maps/a/jt:a	(Lcom/tencent/tencentmap/mapsdk/maps/a/jt;)Landroid/content/Context;
      //   172: ifnull +71 -> 243
      //   175: aload_0
      //   176: getfield 13	com/tencent/tencentmap/mapsdk/maps/a/jt$a:a	Lcom/tencent/tencentmap/mapsdk/maps/a/jt;
      //   179: invokestatic 94	com/tencent/tencentmap/mapsdk/maps/a/jt:a	(Lcom/tencent/tencentmap/mapsdk/maps/a/jt;)Landroid/content/Context;
      //   182: iload 5
      //   184: invokestatic 97	com/tencent/tencentmap/mapsdk/maps/a/jp:a	(Landroid/content/Context;I)V
      //   187: aload_0
      //   188: getfield 13	com/tencent/tencentmap/mapsdk/maps/a/jt$a:a	Lcom/tencent/tencentmap/mapsdk/maps/a/jt;
      //   191: invokestatic 94	com/tencent/tencentmap/mapsdk/maps/a/jt:a	(Lcom/tencent/tencentmap/mapsdk/maps/a/jt;)Landroid/content/Context;
      //   194: invokestatic 102	com/tencent/tencentmap/mapsdk/maps/a/ll:a	(Landroid/content/Context;)Lcom/tencent/tencentmap/mapsdk/maps/a/ll;
      //   197: iconst_1
      //   198: invokevirtual 105	com/tencent/tencentmap/mapsdk/maps/a/ll:a	(I)Z
      //   201: pop
      //   202: aload_0
      //   203: getfield 13	com/tencent/tencentmap/mapsdk/maps/a/jt$a:a	Lcom/tencent/tencentmap/mapsdk/maps/a/jt;
      //   206: invokestatic 109	com/tencent/tencentmap/mapsdk/maps/a/jt:b	(Lcom/tencent/tencentmap/mapsdk/maps/a/jt;)Ljava/lang/ref/WeakReference;
      //   209: ifnull +34 -> 243
      //   212: aload_0
      //   213: getfield 13	com/tencent/tencentmap/mapsdk/maps/a/jt$a:a	Lcom/tencent/tencentmap/mapsdk/maps/a/jt;
      //   216: invokestatic 109	com/tencent/tencentmap/mapsdk/maps/a/jt:b	(Lcom/tencent/tencentmap/mapsdk/maps/a/jt;)Ljava/lang/ref/WeakReference;
      //   219: invokevirtual 115	java/lang/ref/WeakReference:get	()Ljava/lang/Object;
      //   222: ifnull +21 -> 243
      //   225: aload_0
      //   226: getfield 13	com/tencent/tencentmap/mapsdk/maps/a/jt$a:a	Lcom/tencent/tencentmap/mapsdk/maps/a/jt;
      //   229: invokestatic 109	com/tencent/tencentmap/mapsdk/maps/a/jt:b	(Lcom/tencent/tencentmap/mapsdk/maps/a/jt;)Ljava/lang/ref/WeakReference;
      //   232: invokevirtual 115	java/lang/ref/WeakReference:get	()Ljava/lang/Object;
      //   235: checkcast 117	com/tencent/tencentmap/mapsdk/maps/a/jt$b
      //   238: invokeinterface 120 1 0
      //   243: ldc 24
      //   245: invokestatic 123	com/tencent/matrix/trace/core/AppMethodBeat:o	(I)V
      //   248: aconst_null
      //   249: areturn
      //   250: new 125	java/lang/String
      //   253: astore 9
      //   255: aload 9
      //   257: aload 7
      //   259: invokespecial 128	java/lang/String:<init>	([B)V
      //   262: aload_0
      //   263: getfield 13	com/tencent/tencentmap/mapsdk/maps/a/jt$a:a	Lcom/tencent/tencentmap/mapsdk/maps/a/jt;
      //   266: aload 9
      //   268: iload 5
      //   270: invokestatic 131	com/tencent/tencentmap/mapsdk/maps/a/jt:a	(Lcom/tencent/tencentmap/mapsdk/maps/a/jt;Ljava/lang/String;I)I
      //   273: istore 4
      //   275: aload_1
      //   276: ifnull +7 -> 283
      //   279: aload_1
      //   280: invokevirtual 88	javax/net/ssl/HttpsURLConnection:disconnect	()V
      //   283: aload 6
      //   285: ifnull +8 -> 293
      //   288: aload 6
      //   290: invokestatic 91	com/tencent/tencentmap/mapsdk/a/v:a	(Ljava/io/Closeable;)V
      //   293: iload 4
      //   295: invokestatic 35	com/tencent/tencentmap/mapsdk/maps/a/jp:a	()I
      //   298: if_icmpeq +5 -> 303
      //   301: iconst_1
      //   302: istore_2
      //   303: iload_2
      //   304: ifeq +81 -> 385
      //   307: aload_0
      //   308: getfield 13	com/tencent/tencentmap/mapsdk/maps/a/jt$a:a	Lcom/tencent/tencentmap/mapsdk/maps/a/jt;
      //   311: invokestatic 94	com/tencent/tencentmap/mapsdk/maps/a/jt:a	(Lcom/tencent/tencentmap/mapsdk/maps/a/jt;)Landroid/content/Context;
      //   314: ifnull +71 -> 385
      //   317: aload_0
      //   318: getfield 13	com/tencent/tencentmap/mapsdk/maps/a/jt$a:a	Lcom/tencent/tencentmap/mapsdk/maps/a/jt;
      //   321: invokestatic 94	com/tencent/tencentmap/mapsdk/maps/a/jt:a	(Lcom/tencent/tencentmap/mapsdk/maps/a/jt;)Landroid/content/Context;
      //   324: iload 4
      //   326: invokestatic 97	com/tencent/tencentmap/mapsdk/maps/a/jp:a	(Landroid/content/Context;I)V
      //   329: aload_0
      //   330: getfield 13	com/tencent/tencentmap/mapsdk/maps/a/jt$a:a	Lcom/tencent/tencentmap/mapsdk/maps/a/jt;
      //   333: invokestatic 94	com/tencent/tencentmap/mapsdk/maps/a/jt:a	(Lcom/tencent/tencentmap/mapsdk/maps/a/jt;)Landroid/content/Context;
      //   336: invokestatic 102	com/tencent/tencentmap/mapsdk/maps/a/ll:a	(Landroid/content/Context;)Lcom/tencent/tencentmap/mapsdk/maps/a/ll;
      //   339: iconst_1
      //   340: invokevirtual 105	com/tencent/tencentmap/mapsdk/maps/a/ll:a	(I)Z
      //   343: pop
      //   344: aload_0
      //   345: getfield 13	com/tencent/tencentmap/mapsdk/maps/a/jt$a:a	Lcom/tencent/tencentmap/mapsdk/maps/a/jt;
      //   348: invokestatic 109	com/tencent/tencentmap/mapsdk/maps/a/jt:b	(Lcom/tencent/tencentmap/mapsdk/maps/a/jt;)Ljava/lang/ref/WeakReference;
      //   351: ifnull +34 -> 385
      //   354: aload_0
      //   355: getfield 13	com/tencent/tencentmap/mapsdk/maps/a/jt$a:a	Lcom/tencent/tencentmap/mapsdk/maps/a/jt;
      //   358: invokestatic 109	com/tencent/tencentmap/mapsdk/maps/a/jt:b	(Lcom/tencent/tencentmap/mapsdk/maps/a/jt;)Ljava/lang/ref/WeakReference;
      //   361: invokevirtual 115	java/lang/ref/WeakReference:get	()Ljava/lang/Object;
      //   364: ifnull +21 -> 385
      //   367: aload_0
      //   368: getfield 13	com/tencent/tencentmap/mapsdk/maps/a/jt$a:a	Lcom/tencent/tencentmap/mapsdk/maps/a/jt;
      //   371: invokestatic 109	com/tencent/tencentmap/mapsdk/maps/a/jt:b	(Lcom/tencent/tencentmap/mapsdk/maps/a/jt;)Ljava/lang/ref/WeakReference;
      //   374: invokevirtual 115	java/lang/ref/WeakReference:get	()Ljava/lang/Object;
      //   377: checkcast 117	com/tencent/tencentmap/mapsdk/maps/a/jt$b
      //   380: invokeinterface 120 1 0
      //   385: ldc 24
      //   387: invokestatic 123	com/tencent/matrix/trace/core/AppMethodBeat:o	(I)V
      //   390: goto -142 -> 248
      //   393: astore 9
      //   395: aconst_null
      //   396: astore 6
      //   398: aconst_null
      //   399: astore_1
      //   400: new 37	java/lang/StringBuilder
      //   403: astore 7
      //   405: aload 7
      //   407: ldc 133
      //   409: invokespecial 134	java/lang/StringBuilder:<init>	(Ljava/lang/String;)V
      //   412: aload 7
      //   414: aload 9
      //   416: invokevirtual 135	java/lang/Throwable:toString	()Ljava/lang/String;
      //   419: invokevirtual 44	java/lang/StringBuilder:append	(Ljava/lang/String;)Ljava/lang/StringBuilder;
      //   422: pop
      //   423: aload_1
      //   424: ifnull +7 -> 431
      //   427: aload_1
      //   428: invokevirtual 88	javax/net/ssl/HttpsURLConnection:disconnect	()V
      //   431: aload 6
      //   433: ifnull +8 -> 441
      //   436: aload 6
      //   438: invokestatic 91	com/tencent/tencentmap/mapsdk/a/v:a	(Ljava/io/Closeable;)V
      //   441: iload_3
      //   442: istore_2
      //   443: iload 5
      //   445: invokestatic 35	com/tencent/tencentmap/mapsdk/maps/a/jp:a	()I
      //   448: if_icmpeq +5 -> 453
      //   451: iconst_1
      //   452: istore_2
      //   453: iload_2
      //   454: ifeq -69 -> 385
      //   457: aload_0
      //   458: getfield 13	com/tencent/tencentmap/mapsdk/maps/a/jt$a:a	Lcom/tencent/tencentmap/mapsdk/maps/a/jt;
      //   461: invokestatic 94	com/tencent/tencentmap/mapsdk/maps/a/jt:a	(Lcom/tencent/tencentmap/mapsdk/maps/a/jt;)Landroid/content/Context;
      //   464: ifnull -79 -> 385
      //   467: aload_0
      //   468: getfield 13	com/tencent/tencentmap/mapsdk/maps/a/jt$a:a	Lcom/tencent/tencentmap/mapsdk/maps/a/jt;
      //   471: invokestatic 94	com/tencent/tencentmap/mapsdk/maps/a/jt:a	(Lcom/tencent/tencentmap/mapsdk/maps/a/jt;)Landroid/content/Context;
      //   474: iload 5
      //   476: invokestatic 97	com/tencent/tencentmap/mapsdk/maps/a/jp:a	(Landroid/content/Context;I)V
      //   479: aload_0
      //   480: getfield 13	com/tencent/tencentmap/mapsdk/maps/a/jt$a:a	Lcom/tencent/tencentmap/mapsdk/maps/a/jt;
      //   483: invokestatic 94	com/tencent/tencentmap/mapsdk/maps/a/jt:a	(Lcom/tencent/tencentmap/mapsdk/maps/a/jt;)Landroid/content/Context;
      //   486: invokestatic 102	com/tencent/tencentmap/mapsdk/maps/a/ll:a	(Landroid/content/Context;)Lcom/tencent/tencentmap/mapsdk/maps/a/ll;
      //   489: iconst_1
      //   490: invokevirtual 105	com/tencent/tencentmap/mapsdk/maps/a/ll:a	(I)Z
      //   493: pop
      //   494: aload_0
      //   495: getfield 13	com/tencent/tencentmap/mapsdk/maps/a/jt$a:a	Lcom/tencent/tencentmap/mapsdk/maps/a/jt;
      //   498: invokestatic 109	com/tencent/tencentmap/mapsdk/maps/a/jt:b	(Lcom/tencent/tencentmap/mapsdk/maps/a/jt;)Ljava/lang/ref/WeakReference;
      //   501: ifnull -116 -> 385
      //   504: aload_0
      //   505: getfield 13	com/tencent/tencentmap/mapsdk/maps/a/jt$a:a	Lcom/tencent/tencentmap/mapsdk/maps/a/jt;
      //   508: invokestatic 109	com/tencent/tencentmap/mapsdk/maps/a/jt:b	(Lcom/tencent/tencentmap/mapsdk/maps/a/jt;)Ljava/lang/ref/WeakReference;
      //   511: invokevirtual 115	java/lang/ref/WeakReference:get	()Ljava/lang/Object;
      //   514: ifnull -129 -> 385
      //   517: aload_0
      //   518: getfield 13	com/tencent/tencentmap/mapsdk/maps/a/jt$a:a	Lcom/tencent/tencentmap/mapsdk/maps/a/jt;
      //   521: invokestatic 109	com/tencent/tencentmap/mapsdk/maps/a/jt:b	(Lcom/tencent/tencentmap/mapsdk/maps/a/jt;)Ljava/lang/ref/WeakReference;
      //   524: invokevirtual 115	java/lang/ref/WeakReference:get	()Ljava/lang/Object;
      //   527: checkcast 117	com/tencent/tencentmap/mapsdk/maps/a/jt$b
      //   530: invokeinterface 120 1 0
      //   535: goto -150 -> 385
      //   538: astore 9
      //   540: aconst_null
      //   541: astore 6
      //   543: aconst_null
      //   544: astore_1
      //   545: aload_1
      //   546: ifnull +7 -> 553
      //   549: aload_1
      //   550: invokevirtual 88	javax/net/ssl/HttpsURLConnection:disconnect	()V
      //   553: aload 6
      //   555: ifnull +8 -> 563
      //   558: aload 6
      //   560: invokestatic 91	com/tencent/tencentmap/mapsdk/a/v:a	(Ljava/io/Closeable;)V
      //   563: iload 5
      //   565: invokestatic 35	com/tencent/tencentmap/mapsdk/maps/a/jp:a	()I
      //   568: if_icmpeq +95 -> 663
      //   571: iconst_1
      //   572: istore_2
      //   573: iload_2
      //   574: ifeq +81 -> 655
      //   577: aload_0
      //   578: getfield 13	com/tencent/tencentmap/mapsdk/maps/a/jt$a:a	Lcom/tencent/tencentmap/mapsdk/maps/a/jt;
      //   581: invokestatic 94	com/tencent/tencentmap/mapsdk/maps/a/jt:a	(Lcom/tencent/tencentmap/mapsdk/maps/a/jt;)Landroid/content/Context;
      //   584: ifnull +71 -> 655
      //   587: aload_0
      //   588: getfield 13	com/tencent/tencentmap/mapsdk/maps/a/jt$a:a	Lcom/tencent/tencentmap/mapsdk/maps/a/jt;
      //   591: invokestatic 94	com/tencent/tencentmap/mapsdk/maps/a/jt:a	(Lcom/tencent/tencentmap/mapsdk/maps/a/jt;)Landroid/content/Context;
      //   594: iload 5
      //   596: invokestatic 97	com/tencent/tencentmap/mapsdk/maps/a/jp:a	(Landroid/content/Context;I)V
      //   599: aload_0
      //   600: getfield 13	com/tencent/tencentmap/mapsdk/maps/a/jt$a:a	Lcom/tencent/tencentmap/mapsdk/maps/a/jt;
      //   603: invokestatic 94	com/tencent/tencentmap/mapsdk/maps/a/jt:a	(Lcom/tencent/tencentmap/mapsdk/maps/a/jt;)Landroid/content/Context;
      //   606: invokestatic 102	com/tencent/tencentmap/mapsdk/maps/a/ll:a	(Landroid/content/Context;)Lcom/tencent/tencentmap/mapsdk/maps/a/ll;
      //   609: iconst_1
      //   610: invokevirtual 105	com/tencent/tencentmap/mapsdk/maps/a/ll:a	(I)Z
      //   613: pop
      //   614: aload_0
      //   615: getfield 13	com/tencent/tencentmap/mapsdk/maps/a/jt$a:a	Lcom/tencent/tencentmap/mapsdk/maps/a/jt;
      //   618: invokestatic 109	com/tencent/tencentmap/mapsdk/maps/a/jt:b	(Lcom/tencent/tencentmap/mapsdk/maps/a/jt;)Ljava/lang/ref/WeakReference;
      //   621: ifnull +34 -> 655
      //   624: aload_0
      //   625: getfield 13	com/tencent/tencentmap/mapsdk/maps/a/jt$a:a	Lcom/tencent/tencentmap/mapsdk/maps/a/jt;
      //   628: invokestatic 109	com/tencent/tencentmap/mapsdk/maps/a/jt:b	(Lcom/tencent/tencentmap/mapsdk/maps/a/jt;)Ljava/lang/ref/WeakReference;
      //   631: invokevirtual 115	java/lang/ref/WeakReference:get	()Ljava/lang/Object;
      //   634: ifnull +21 -> 655
      //   637: aload_0
      //   638: getfield 13	com/tencent/tencentmap/mapsdk/maps/a/jt$a:a	Lcom/tencent/tencentmap/mapsdk/maps/a/jt;
      //   641: invokestatic 109	com/tencent/tencentmap/mapsdk/maps/a/jt:b	(Lcom/tencent/tencentmap/mapsdk/maps/a/jt;)Ljava/lang/ref/WeakReference;
      //   644: invokevirtual 115	java/lang/ref/WeakReference:get	()Ljava/lang/Object;
      //   647: checkcast 117	com/tencent/tencentmap/mapsdk/maps/a/jt$b
      //   650: invokeinterface 120 1 0
      //   655: ldc 24
      //   657: invokestatic 123	com/tencent/matrix/trace/core/AppMethodBeat:o	(I)V
      //   660: aload 9
      //   662: athrow
      //   663: iconst_0
      //   664: istore_2
      //   665: goto -92 -> 573
      //   668: astore 9
      //   670: aconst_null
      //   671: astore 6
      //   673: goto -128 -> 545
      //   676: astore 9
      //   678: goto -133 -> 545
      //   681: astore 9
      //   683: goto -138 -> 545
      //   686: astore 9
      //   688: aconst_null
      //   689: astore 6
      //   691: goto -291 -> 400
      //   694: astore 9
      //   696: goto -296 -> 400
      //
      // Exception table:
      //   from	to	target	type
      //   70	91	393	java/lang/Throwable
      //   70	91	538	finally
      //   91	108	668	finally
      //   108	115	676	finally
      //   120	125	676	finally
      //   250	275	676	finally
      //   400	423	681	finally
      //   91	108	686	java/lang/Throwable
      //   108	115	694	java/lang/Throwable
      //   120	125	694	java/lang/Throwable
      //   250	275	694	java/lang/Throwable
    }
  }
}

/* Location:           C:\Users\Lin\Downloads\dex-tools-2.1-SNAPSHOT\dex-tools-2.1-SNAPSHOT\classes4-dex2jar.jar
 * Qualified Name:     com.tencent.tencentmap.mapsdk.maps.a.jt
 * JD-Core Version:    0.6.2
 */