package com.tencent.tencentmap.mapsdk.maps.a;

import android.content.Context;
import android.database.Cursor;
import android.database.sqlite.SQLiteDatabase;
import com.tencent.matrix.trace.core.AppMethodBeat;
import java.util.ArrayList;
import java.util.List;

public final class p
{
  public long a;
  public byte[] b;
  private int c;
  private int d;
  private long e;
  private long f;

  public p()
  {
    this.a = -1L;
    this.c = -1;
    this.d = -1;
    this.e = -1L;
    this.b = null;
    this.f = 0L;
  }

  public p(long paramLong, byte[] paramArrayOfByte)
  {
    AppMethodBeat.i(100522);
    this.a = -1L;
    this.c = -1;
    this.d = -1;
    this.e = -1L;
    this.b = null;
    this.f = 0L;
    this.c = 1;
    this.d = 3;
    this.e = paramLong;
    this.b = paramArrayOfByte;
    if (paramArrayOfByte != null)
      this.f = paramArrayOfByte.length;
    AppMethodBeat.o(100522);
  }

  // ERROR //
  public static int a(Context paramContext, int[] paramArrayOfInt)
  {
    // Byte code:
    //   0: iconst_m1
    //   1: istore_2
    //   2: iconst_0
    //   3: istore_3
    //   4: ldc 2
    //   6: monitorenter
    //   7: ldc 47
    //   9: invokestatic 40	com/tencent/matrix/trace/core/AppMethodBeat:i	(I)V
    //   12: ldc 49
    //   14: iconst_0
    //   15: anewarray 4	java/lang/Object
    //   18: invokestatic 54	com/tencent/tencentmap/mapsdk/maps/a/ag:b	(Ljava/lang/String;[Ljava/lang/Object;)V
    //   21: aload_0
    //   22: ifnonnull +22 -> 44
    //   25: ldc 56
    //   27: iconst_0
    //   28: anewarray 4	java/lang/Object
    //   31: invokestatic 58	com/tencent/tencentmap/mapsdk/maps/a/ag:a	(Ljava/lang/String;[Ljava/lang/Object;)V
    //   34: ldc 47
    //   36: invokestatic 43	com/tencent/matrix/trace/core/AppMethodBeat:o	(I)V
    //   39: ldc 2
    //   41: monitorexit
    //   42: iload_2
    //   43: ireturn
    //   44: ldc2_w 18
    //   47: ldc2_w 59
    //   50: lcmp
    //   51: ifle +13 -> 64
    //   54: ldc 47
    //   56: invokestatic 43	com/tencent/matrix/trace/core/AppMethodBeat:o	(I)V
    //   59: iconst_0
    //   60: istore_2
    //   61: goto -22 -> 39
    //   64: aload_1
    //   65: ifnull +212 -> 277
    //   68: aload_1
    //   69: arraylength
    //   70: ifle +207 -> 277
    //   73: ldc 62
    //   75: astore 4
    //   77: iload_3
    //   78: aload_1
    //   79: arraylength
    //   80: if_icmpge +42 -> 122
    //   83: new 64	java/lang/StringBuilder
    //   86: astore 5
    //   88: aload 5
    //   90: invokespecial 65	java/lang/StringBuilder:<init>	()V
    //   93: aload 5
    //   95: aload 4
    //   97: invokevirtual 69	java/lang/StringBuilder:append	(Ljava/lang/String;)Ljava/lang/StringBuilder;
    //   100: ldc 71
    //   102: invokevirtual 69	java/lang/StringBuilder:append	(Ljava/lang/String;)Ljava/lang/StringBuilder;
    //   105: aload_1
    //   106: iload_3
    //   107: iaload
    //   108: invokevirtual 74	java/lang/StringBuilder:append	(I)Ljava/lang/StringBuilder;
    //   111: invokevirtual 78	java/lang/StringBuilder:toString	()Ljava/lang/String;
    //   114: astore 4
    //   116: iinc 3 1
    //   119: goto -42 -> 77
    //   122: aload 4
    //   124: iconst_4
    //   125: invokevirtual 84	java/lang/String:substring	(I)Ljava/lang/String;
    //   128: astore_1
    //   129: new 64	java/lang/StringBuilder
    //   132: astore 4
    //   134: aload 4
    //   136: invokespecial 65	java/lang/StringBuilder:<init>	()V
    //   139: aload 4
    //   141: ldc 86
    //   143: invokevirtual 69	java/lang/StringBuilder:append	(Ljava/lang/String;)Ljava/lang/StringBuilder;
    //   146: ldc 88
    //   148: invokevirtual 69	java/lang/StringBuilder:append	(Ljava/lang/String;)Ljava/lang/StringBuilder;
    //   151: aload_1
    //   152: invokevirtual 69	java/lang/StringBuilder:append	(Ljava/lang/String;)Ljava/lang/StringBuilder;
    //   155: ldc 90
    //   157: invokevirtual 69	java/lang/StringBuilder:append	(Ljava/lang/String;)Ljava/lang/StringBuilder;
    //   160: invokevirtual 78	java/lang/StringBuilder:toString	()Ljava/lang/String;
    //   163: astore_1
    //   164: ldc 92
    //   166: aload_1
    //   167: invokestatic 96	java/lang/String:valueOf	(Ljava/lang/Object;)Ljava/lang/String;
    //   170: invokevirtual 100	java/lang/String:concat	(Ljava/lang/String;)Ljava/lang/String;
    //   173: iconst_0
    //   174: anewarray 4	java/lang/Object
    //   177: invokestatic 54	com/tencent/tencentmap/mapsdk/maps/a/ag:b	(Ljava/lang/String;[Ljava/lang/Object;)V
    //   180: aload_0
    //   181: invokestatic 105	com/tencent/tencentmap/mapsdk/maps/a/r:a	(Landroid/content/Context;)Lcom/tencent/tencentmap/mapsdk/maps/a/r;
    //   184: invokevirtual 109	com/tencent/tencentmap/mapsdk/maps/a/r:getWritableDatabase	()Landroid/database/sqlite/SQLiteDatabase;
    //   187: ldc 111
    //   189: aload_1
    //   190: aconst_null
    //   191: invokevirtual 117	android/database/sqlite/SQLiteDatabase:delete	(Ljava/lang/String;Ljava/lang/String;[Ljava/lang/String;)I
    //   194: istore_3
    //   195: ldc 119
    //   197: iload_3
    //   198: invokestatic 121	java/lang/String:valueOf	(I)Ljava/lang/String;
    //   201: invokevirtual 100	java/lang/String:concat	(Ljava/lang/String;)Ljava/lang/String;
    //   204: iconst_0
    //   205: anewarray 4	java/lang/Object
    //   208: invokestatic 54	com/tencent/tencentmap/mapsdk/maps/a/ag:b	(Ljava/lang/String;[Ljava/lang/Object;)V
    //   211: ldc 123
    //   213: iconst_0
    //   214: anewarray 4	java/lang/Object
    //   217: invokestatic 54	com/tencent/tencentmap/mapsdk/maps/a/ag:b	(Ljava/lang/String;[Ljava/lang/Object;)V
    //   220: iload_3
    //   221: istore_2
    //   222: ldc 47
    //   224: invokestatic 43	com/tencent/matrix/trace/core/AppMethodBeat:o	(I)V
    //   227: goto -188 -> 39
    //   230: astore_0
    //   231: ldc 2
    //   233: monitorexit
    //   234: aload_0
    //   235: athrow
    //   236: astore_0
    //   237: aload_0
    //   238: invokevirtual 126	java/lang/Throwable:getMessage	()Ljava/lang/String;
    //   241: iconst_0
    //   242: anewarray 4	java/lang/Object
    //   245: invokestatic 54	com/tencent/tencentmap/mapsdk/maps/a/ag:b	(Ljava/lang/String;[Ljava/lang/Object;)V
    //   248: ldc 123
    //   250: iconst_0
    //   251: anewarray 4	java/lang/Object
    //   254: invokestatic 54	com/tencent/tencentmap/mapsdk/maps/a/ag:b	(Ljava/lang/String;[Ljava/lang/Object;)V
    //   257: goto -35 -> 222
    //   260: astore_0
    //   261: ldc 123
    //   263: iconst_0
    //   264: anewarray 4	java/lang/Object
    //   267: invokestatic 54	com/tencent/tencentmap/mapsdk/maps/a/ag:b	(Ljava/lang/String;[Ljava/lang/Object;)V
    //   270: ldc 47
    //   272: invokestatic 43	com/tencent/matrix/trace/core/AppMethodBeat:o	(I)V
    //   275: aload_0
    //   276: athrow
    //   277: ldc 86
    //   279: astore_1
    //   280: goto -116 -> 164
    //
    // Exception table:
    //   from	to	target	type
    //   7	21	230	finally
    //   25	39	230	finally
    //   54	59	230	finally
    //   68	73	230	finally
    //   77	116	230	finally
    //   122	164	230	finally
    //   164	180	230	finally
    //   211	220	230	finally
    //   222	227	230	finally
    //   248	257	230	finally
    //   261	277	230	finally
    //   180	211	236	java/lang/Throwable
    //   180	211	260	finally
    //   237	248	260	finally
  }

  // ERROR //
  public static int a(Context paramContext, java.lang.Long[] paramArrayOfLong)
  {
    // Byte code:
    //   0: iconst_0
    //   1: istore_2
    //   2: ldc 2
    //   4: monitorenter
    //   5: ldc 128
    //   7: invokestatic 40	com/tencent/matrix/trace/core/AppMethodBeat:i	(I)V
    //   10: ldc 130
    //   12: iconst_0
    //   13: anewarray 4	java/lang/Object
    //   16: invokestatic 54	com/tencent/tencentmap/mapsdk/maps/a/ag:b	(Ljava/lang/String;[Ljava/lang/Object;)V
    //   19: aload_0
    //   20: ifnonnull +24 -> 44
    //   23: ldc 132
    //   25: iconst_0
    //   26: anewarray 4	java/lang/Object
    //   29: invokestatic 134	com/tencent/tencentmap/mapsdk/maps/a/ag:d	(Ljava/lang/String;[Ljava/lang/Object;)V
    //   32: iconst_m1
    //   33: istore_3
    //   34: ldc 128
    //   36: invokestatic 43	com/tencent/matrix/trace/core/AppMethodBeat:o	(I)V
    //   39: ldc 2
    //   41: monitorexit
    //   42: iload_3
    //   43: ireturn
    //   44: aload_1
    //   45: ifnull +8 -> 53
    //   48: aload_1
    //   49: arraylength
    //   50: ifgt +13 -> 63
    //   53: ldc 128
    //   55: invokestatic 43	com/tencent/matrix/trace/core/AppMethodBeat:o	(I)V
    //   58: iconst_0
    //   59: istore_3
    //   60: goto -21 -> 39
    //   63: iload_2
    //   64: istore_3
    //   65: aload_0
    //   66: invokestatic 105	com/tencent/tencentmap/mapsdk/maps/a/r:a	(Landroid/content/Context;)Lcom/tencent/tencentmap/mapsdk/maps/a/r;
    //   69: invokevirtual 109	com/tencent/tencentmap/mapsdk/maps/a/r:getWritableDatabase	()Landroid/database/sqlite/SQLiteDatabase;
    //   72: astore_0
    //   73: iload_2
    //   74: istore_3
    //   75: new 136	java/lang/StringBuffer
    //   78: astore 4
    //   80: iload_2
    //   81: istore_3
    //   82: aload 4
    //   84: invokespecial 137	java/lang/StringBuffer:<init>	()V
    //   87: iconst_0
    //   88: istore 5
    //   90: iconst_0
    //   91: istore_3
    //   92: iload_3
    //   93: istore_2
    //   94: iload 5
    //   96: aload_1
    //   97: arraylength
    //   98: if_icmpge +116 -> 214
    //   101: iload_3
    //   102: istore_2
    //   103: aload 4
    //   105: ldc 139
    //   107: aload_1
    //   108: iload 5
    //   110: aaload
    //   111: invokevirtual 145	java/lang/Long:longValue	()J
    //   114: invokestatic 148	java/lang/String:valueOf	(J)Ljava/lang/String;
    //   117: invokevirtual 100	java/lang/String:concat	(Ljava/lang/String;)Ljava/lang/String;
    //   120: invokevirtual 151	java/lang/StringBuffer:append	(Ljava/lang/String;)Ljava/lang/StringBuffer;
    //   123: pop
    //   124: iload_3
    //   125: istore_2
    //   126: iload 5
    //   128: ifle +78 -> 206
    //   131: iload_3
    //   132: istore_2
    //   133: iload 5
    //   135: bipush 25
    //   137: irem
    //   138: ifne +68 -> 206
    //   141: iload_3
    //   142: istore_2
    //   143: ldc 153
    //   145: iload 5
    //   147: invokestatic 121	java/lang/String:valueOf	(I)Ljava/lang/String;
    //   150: invokevirtual 100	java/lang/String:concat	(Ljava/lang/String;)Ljava/lang/String;
    //   153: iconst_0
    //   154: anewarray 4	java/lang/Object
    //   157: invokestatic 54	com/tencent/tencentmap/mapsdk/maps/a/ag:b	(Ljava/lang/String;[Ljava/lang/Object;)V
    //   160: iload_3
    //   161: istore_2
    //   162: iload_3
    //   163: aload_0
    //   164: ldc 111
    //   166: aload 4
    //   168: iconst_4
    //   169: invokevirtual 154	java/lang/StringBuffer:substring	(I)Ljava/lang/String;
    //   172: aconst_null
    //   173: invokevirtual 117	android/database/sqlite/SQLiteDatabase:delete	(Ljava/lang/String;Ljava/lang/String;[Ljava/lang/String;)I
    //   176: iadd
    //   177: istore_3
    //   178: iload_3
    //   179: istore_2
    //   180: aload 4
    //   182: iconst_0
    //   183: invokevirtual 157	java/lang/StringBuffer:setLength	(I)V
    //   186: iload_3
    //   187: istore_2
    //   188: ldc 159
    //   190: iload_3
    //   191: invokestatic 121	java/lang/String:valueOf	(I)Ljava/lang/String;
    //   194: invokevirtual 100	java/lang/String:concat	(Ljava/lang/String;)Ljava/lang/String;
    //   197: iconst_0
    //   198: anewarray 4	java/lang/Object
    //   201: invokestatic 54	com/tencent/tencentmap/mapsdk/maps/a/ag:b	(Ljava/lang/String;[Ljava/lang/Object;)V
    //   204: iload_3
    //   205: istore_2
    //   206: iinc 5 1
    //   209: iload_2
    //   210: istore_3
    //   211: goto -119 -> 92
    //   214: iload_3
    //   215: istore_2
    //   216: aload 4
    //   218: invokevirtual 163	java/lang/StringBuffer:length	()I
    //   221: ifle +123 -> 344
    //   224: iload_3
    //   225: istore_2
    //   226: aload_0
    //   227: ldc 111
    //   229: aload 4
    //   231: iconst_4
    //   232: invokevirtual 154	java/lang/StringBuffer:substring	(I)Ljava/lang/String;
    //   235: aconst_null
    //   236: invokevirtual 117	android/database/sqlite/SQLiteDatabase:delete	(Ljava/lang/String;Ljava/lang/String;[Ljava/lang/String;)I
    //   239: istore 5
    //   241: iload 5
    //   243: iload_3
    //   244: iadd
    //   245: istore_2
    //   246: iload_2
    //   247: istore_3
    //   248: aload 4
    //   250: iconst_0
    //   251: invokevirtual 157	java/lang/StringBuffer:setLength	(I)V
    //   254: iload_2
    //   255: istore_3
    //   256: ldc 165
    //   258: iload_2
    //   259: invokestatic 121	java/lang/String:valueOf	(I)Ljava/lang/String;
    //   262: invokevirtual 100	java/lang/String:concat	(Ljava/lang/String;)Ljava/lang/String;
    //   265: iconst_0
    //   266: anewarray 4	java/lang/Object
    //   269: invokestatic 58	com/tencent/tencentmap/mapsdk/maps/a/ag:a	(Ljava/lang/String;[Ljava/lang/Object;)V
    //   272: ldc 167
    //   274: iconst_0
    //   275: anewarray 4	java/lang/Object
    //   278: invokestatic 54	com/tencent/tencentmap/mapsdk/maps/a/ag:b	(Ljava/lang/String;[Ljava/lang/Object;)V
    //   281: iload_2
    //   282: istore_3
    //   283: ldc 128
    //   285: invokestatic 43	com/tencent/matrix/trace/core/AppMethodBeat:o	(I)V
    //   288: goto -249 -> 39
    //   291: astore_0
    //   292: ldc 2
    //   294: monitorexit
    //   295: aload_0
    //   296: athrow
    //   297: astore_0
    //   298: aload_0
    //   299: invokevirtual 126	java/lang/Throwable:getMessage	()Ljava/lang/String;
    //   302: iconst_0
    //   303: anewarray 4	java/lang/Object
    //   306: invokestatic 134	com/tencent/tencentmap/mapsdk/maps/a/ag:d	(Ljava/lang/String;[Ljava/lang/Object;)V
    //   309: ldc 167
    //   311: iconst_0
    //   312: anewarray 4	java/lang/Object
    //   315: invokestatic 54	com/tencent/tencentmap/mapsdk/maps/a/ag:b	(Ljava/lang/String;[Ljava/lang/Object;)V
    //   318: goto -35 -> 283
    //   321: astore_0
    //   322: ldc 167
    //   324: iconst_0
    //   325: anewarray 4	java/lang/Object
    //   328: invokestatic 54	com/tencent/tencentmap/mapsdk/maps/a/ag:b	(Ljava/lang/String;[Ljava/lang/Object;)V
    //   331: ldc 128
    //   333: invokestatic 43	com/tencent/matrix/trace/core/AppMethodBeat:o	(I)V
    //   336: aload_0
    //   337: athrow
    //   338: astore_0
    //   339: iload_2
    //   340: istore_3
    //   341: goto -43 -> 298
    //   344: iload_3
    //   345: istore_2
    //   346: goto -92 -> 254
    //
    // Exception table:
    //   from	to	target	type
    //   5	19	291	finally
    //   23	32	291	finally
    //   34	39	291	finally
    //   48	53	291	finally
    //   53	58	291	finally
    //   272	281	291	finally
    //   283	288	291	finally
    //   309	318	291	finally
    //   322	338	291	finally
    //   65	73	297	java/lang/Throwable
    //   75	80	297	java/lang/Throwable
    //   82	87	297	java/lang/Throwable
    //   248	254	297	java/lang/Throwable
    //   256	272	297	java/lang/Throwable
    //   65	73	321	finally
    //   75	80	321	finally
    //   82	87	321	finally
    //   94	101	321	finally
    //   103	124	321	finally
    //   143	160	321	finally
    //   162	178	321	finally
    //   180	186	321	finally
    //   188	204	321	finally
    //   216	224	321	finally
    //   226	241	321	finally
    //   248	254	321	finally
    //   256	272	321	finally
    //   298	309	321	finally
    //   94	101	338	java/lang/Throwable
    //   103	124	338	java/lang/Throwable
    //   143	160	338	java/lang/Throwable
    //   162	178	338	java/lang/Throwable
    //   180	186	338	java/lang/Throwable
    //   188	204	338	java/lang/Throwable
    //   216	224	338	java/lang/Throwable
    //   226	241	338	java/lang/Throwable
  }

  // ERROR //
  public static List a(Context paramContext)
  {
    // Byte code:
    //   0: aconst_null
    //   1: astore_1
    //   2: ldc 2
    //   4: monitorenter
    //   5: ldc 171
    //   7: invokestatic 40	com/tencent/matrix/trace/core/AppMethodBeat:i	(I)V
    //   10: ldc 173
    //   12: iconst_0
    //   13: anewarray 4	java/lang/Object
    //   16: invokestatic 54	com/tencent/tencentmap/mapsdk/maps/a/ag:b	(Ljava/lang/String;[Ljava/lang/Object;)V
    //   19: aload_0
    //   20: ifnonnull +24 -> 44
    //   23: ldc 175
    //   25: iconst_0
    //   26: anewarray 4	java/lang/Object
    //   29: invokestatic 134	com/tencent/tencentmap/mapsdk/maps/a/ag:d	(Ljava/lang/String;[Ljava/lang/Object;)V
    //   32: ldc 171
    //   34: invokestatic 43	com/tencent/matrix/trace/core/AppMethodBeat:o	(I)V
    //   37: aconst_null
    //   38: astore_0
    //   39: ldc 2
    //   41: monitorexit
    //   42: aload_0
    //   43: areturn
    //   44: aload_0
    //   45: invokestatic 105	com/tencent/tencentmap/mapsdk/maps/a/r:a	(Landroid/content/Context;)Lcom/tencent/tencentmap/mapsdk/maps/a/r;
    //   48: invokevirtual 109	com/tencent/tencentmap/mapsdk/maps/a/r:getWritableDatabase	()Landroid/database/sqlite/SQLiteDatabase;
    //   51: ldc 177
    //   53: aconst_null
    //   54: aconst_null
    //   55: aconst_null
    //   56: aconst_null
    //   57: aconst_null
    //   58: ldc 179
    //   60: ldc 181
    //   62: invokevirtual 185	android/database/sqlite/SQLiteDatabase:query	(Ljava/lang/String;[Ljava/lang/String;Ljava/lang/String;[Ljava/lang/String;Ljava/lang/String;Ljava/lang/String;Ljava/lang/String;Ljava/lang/String;)Landroid/database/Cursor;
    //   65: astore_2
    //   66: aload_1
    //   67: astore_0
    //   68: aload_2
    //   69: invokeinterface 191 1 0
    //   74: ifeq +125 -> 199
    //   77: new 193	java/util/ArrayList
    //   80: astore_0
    //   81: aload_0
    //   82: invokespecial 194	java/util/ArrayList:<init>	()V
    //   85: aload_0
    //   86: aload_2
    //   87: aload_2
    //   88: ldc 196
    //   90: invokeinterface 200 2 0
    //   95: invokeinterface 204 2 0
    //   100: invokestatic 209	java/lang/Integer:valueOf	(I)Ljava/lang/Integer;
    //   103: invokeinterface 215 2 0
    //   108: pop
    //   109: aload_0
    //   110: aload_2
    //   111: aload_2
    //   112: ldc 217
    //   114: invokeinterface 200 2 0
    //   119: invokeinterface 220 2 0
    //   124: invokeinterface 215 2 0
    //   129: pop
    //   130: aload_0
    //   131: aload_2
    //   132: aload_2
    //   133: ldc 222
    //   135: invokeinterface 200 2 0
    //   140: invokeinterface 226 2 0
    //   145: invokestatic 229	java/lang/Long:valueOf	(J)Ljava/lang/Long;
    //   148: invokeinterface 215 2 0
    //   153: pop
    //   154: aload_0
    //   155: aload_2
    //   156: aload_2
    //   157: ldc 231
    //   159: invokeinterface 200 2 0
    //   164: invokeinterface 235 2 0
    //   169: invokeinterface 215 2 0
    //   174: pop
    //   175: aload_0
    //   176: aload_2
    //   177: aload_2
    //   178: ldc 237
    //   180: invokeinterface 200 2 0
    //   185: invokeinterface 204 2 0
    //   190: invokestatic 209	java/lang/Integer:valueOf	(I)Ljava/lang/Integer;
    //   193: invokeinterface 215 2 0
    //   198: pop
    //   199: aload_0
    //   200: ifnull +12 -> 212
    //   203: ldc 239
    //   205: iconst_0
    //   206: anewarray 4	java/lang/Object
    //   209: invokestatic 58	com/tencent/tencentmap/mapsdk/maps/a/ag:a	(Ljava/lang/String;[Ljava/lang/Object;)V
    //   212: aload_2
    //   213: ifnull +18 -> 231
    //   216: aload_2
    //   217: invokeinterface 242 1 0
    //   222: ifne +9 -> 231
    //   225: aload_2
    //   226: invokeinterface 245 1 0
    //   231: ldc 247
    //   233: iconst_0
    //   234: anewarray 4	java/lang/Object
    //   237: invokestatic 54	com/tencent/tencentmap/mapsdk/maps/a/ag:b	(Ljava/lang/String;[Ljava/lang/Object;)V
    //   240: ldc 171
    //   242: invokestatic 43	com/tencent/matrix/trace/core/AppMethodBeat:o	(I)V
    //   245: goto -206 -> 39
    //   248: astore_0
    //   249: ldc 2
    //   251: monitorexit
    //   252: aload_0
    //   253: athrow
    //   254: astore_0
    //   255: aconst_null
    //   256: astore_0
    //   257: aconst_null
    //   258: astore_2
    //   259: aload_2
    //   260: ifnull +18 -> 278
    //   263: aload_2
    //   264: invokeinterface 242 1 0
    //   269: ifne +9 -> 278
    //   272: aload_2
    //   273: invokeinterface 245 1 0
    //   278: ldc 247
    //   280: iconst_0
    //   281: anewarray 4	java/lang/Object
    //   284: invokestatic 54	com/tencent/tencentmap/mapsdk/maps/a/ag:b	(Ljava/lang/String;[Ljava/lang/Object;)V
    //   287: goto -47 -> 240
    //   290: astore_0
    //   291: aconst_null
    //   292: astore_2
    //   293: aload_2
    //   294: ifnull +18 -> 312
    //   297: aload_2
    //   298: invokeinterface 242 1 0
    //   303: ifne +9 -> 312
    //   306: aload_2
    //   307: invokeinterface 245 1 0
    //   312: ldc 247
    //   314: iconst_0
    //   315: anewarray 4	java/lang/Object
    //   318: invokestatic 54	com/tencent/tencentmap/mapsdk/maps/a/ag:b	(Ljava/lang/String;[Ljava/lang/Object;)V
    //   321: ldc 171
    //   323: invokestatic 43	com/tencent/matrix/trace/core/AppMethodBeat:o	(I)V
    //   326: aload_0
    //   327: athrow
    //   328: astore_0
    //   329: goto -36 -> 293
    //   332: astore_0
    //   333: aconst_null
    //   334: astore_0
    //   335: goto -76 -> 259
    //   338: astore_1
    //   339: goto -80 -> 259
    //   342: astore_1
    //   343: goto -84 -> 259
    //
    // Exception table:
    //   from	to	target	type
    //   5	19	248	finally
    //   23	37	248	finally
    //   216	231	248	finally
    //   231	240	248	finally
    //   240	245	248	finally
    //   263	278	248	finally
    //   278	287	248	finally
    //   297	312	248	finally
    //   312	328	248	finally
    //   44	66	254	java/lang/Exception
    //   44	66	290	finally
    //   68	85	328	finally
    //   85	199	328	finally
    //   203	212	328	finally
    //   68	85	332	java/lang/Exception
    //   85	199	338	java/lang/Exception
    //   203	212	342	java/lang/Exception
  }

  public static List<p> a(Context paramContext, int[] paramArrayOfInt, int paramInt)
  {
    try
    {
      AppMethodBeat.i(100529);
      paramContext = b(paramContext, paramArrayOfInt, paramInt);
      AppMethodBeat.o(100529);
      return paramContext;
    }
    finally
    {
      paramContext = finally;
    }
    throw paramContext;
  }

  private static List<p> a(Cursor paramCursor)
  {
    AppMethodBeat.i(100530);
    ag.b(" in AnalyticsDAO.paserCursor() start", new Object[0]);
    if (paramCursor == null)
    {
      paramCursor = null;
      AppMethodBeat.o(100530);
    }
    while (true)
    {
      return paramCursor;
      ArrayList localArrayList = new ArrayList();
      int i = paramCursor.getColumnIndex("_id");
      int j = paramCursor.getColumnIndex("_prority");
      int k = paramCursor.getColumnIndex("_time");
      int m = paramCursor.getColumnIndex("_type");
      int n = paramCursor.getColumnIndex("_datas");
      int i1 = paramCursor.getColumnIndex("_length");
      while (paramCursor.moveToNext())
      {
        p localp = new p();
        localp.a = paramCursor.getLong(i);
        localp.b = paramCursor.getBlob(n);
        localp.d = paramCursor.getInt(j);
        localp.e = paramCursor.getLong(k);
        localp.c = paramCursor.getInt(m);
        localp.f = paramCursor.getLong(i1);
        localArrayList.add(localp);
      }
      ag.b(" in AnalyticsDAO.paserCursor() end", new Object[0]);
      AppMethodBeat.o(100530);
      paramCursor = localArrayList;
    }
  }

  public static boolean a(Context paramContext, String paramString)
  {
    boolean bool1 = false;
    boolean bool2 = false;
    boolean bool3 = false;
    while (true)
    {
      try
      {
        AppMethodBeat.i(100525);
        ag.b(" AnalyticsDAO.deleteReqData() start", new Object[0]);
        if (paramContext == null)
        {
          ag.a(" delete() context is null arg", new Object[0]);
          AppMethodBeat.o(100525);
          return bool3;
        }
        if ((paramString == null) || (paramString.trim().equals("")))
        {
          AppMethodBeat.o(100525);
          continue;
        }
      }
      finally
      {
      }
      StringBuilder localStringBuilder = new java/lang/StringBuilder;
      localStringBuilder.<init>("_rid = '");
      paramString = paramString + "' ";
      ag.b(" delete where: ".concat(String.valueOf(paramString)), new Object[0]);
      try
      {
        int i = r.a(paramContext).getWritableDatabase().delete("t_req_data", paramString, null);
        ag.b(" deleted num: ".concat(String.valueOf(i)), new Object[0]);
        bool3 = bool1;
        if (i == 1)
          bool3 = true;
        ag.b(" AnalyticsDAO.deleteReqData() end", new Object[0]);
        AppMethodBeat.o(100525);
      }
      catch (Throwable paramContext)
      {
        while (true)
        {
          ag.b(paramContext.getMessage(), new Object[0]);
          ag.b(" AnalyticsDAO.deleteReqData() end", new Object[0]);
          bool3 = bool2;
        }
      }
      finally
      {
        ag.b(" AnalyticsDAO.deleteReqData() end", new Object[0]);
        AppMethodBeat.o(100525);
      }
    }
    throw paramContext;
  }

  // ERROR //
  public static boolean a(Context paramContext, List<p> paramList)
  {
    // Byte code:
    //   0: ldc 2
    //   2: monitorenter
    //   3: ldc_w 288
    //   6: invokestatic 40	com/tencent/matrix/trace/core/AppMethodBeat:i	(I)V
    //   9: ldc_w 290
    //   12: iconst_0
    //   13: anewarray 4	java/lang/Object
    //   16: invokestatic 54	com/tencent/tencentmap/mapsdk/maps/a/ag:b	(Ljava/lang/String;[Ljava/lang/Object;)V
    //   19: aload_0
    //   20: ifnull +7 -> 27
    //   23: aload_1
    //   24: ifnonnull +26 -> 50
    //   27: ldc_w 292
    //   30: iconst_0
    //   31: anewarray 4	java/lang/Object
    //   34: invokestatic 134	com/tencent/tencentmap/mapsdk/maps/a/ag:d	(Ljava/lang/String;[Ljava/lang/Object;)V
    //   37: ldc_w 288
    //   40: invokestatic 43	com/tencent/matrix/trace/core/AppMethodBeat:o	(I)V
    //   43: iconst_0
    //   44: istore_2
    //   45: ldc 2
    //   47: monitorexit
    //   48: iload_2
    //   49: ireturn
    //   50: aload_1
    //   51: invokeinterface 295 1 0
    //   56: ifgt +24 -> 80
    //   59: ldc_w 297
    //   62: iconst_0
    //   63: anewarray 4	java/lang/Object
    //   66: invokestatic 54	com/tencent/tencentmap/mapsdk/maps/a/ag:b	(Ljava/lang/String;[Ljava/lang/Object;)V
    //   69: ldc_w 288
    //   72: invokestatic 43	com/tencent/matrix/trace/core/AppMethodBeat:o	(I)V
    //   75: iconst_1
    //   76: istore_2
    //   77: goto -32 -> 45
    //   80: aconst_null
    //   81: astore_3
    //   82: aload_0
    //   83: invokestatic 105	com/tencent/tencentmap/mapsdk/maps/a/r:a	(Landroid/content/Context;)Lcom/tencent/tencentmap/mapsdk/maps/a/r;
    //   86: invokevirtual 109	com/tencent/tencentmap/mapsdk/maps/a/r:getWritableDatabase	()Landroid/database/sqlite/SQLiteDatabase;
    //   89: astore_0
    //   90: aload_0
    //   91: invokevirtual 300	android/database/sqlite/SQLiteDatabase:beginTransaction	()V
    //   94: iconst_0
    //   95: istore 4
    //   97: iload 4
    //   99: aload_1
    //   100: invokeinterface 295 1 0
    //   105: if_icmpge +159 -> 264
    //   108: aload_1
    //   109: iload 4
    //   111: invokeinterface 304 2 0
    //   116: checkcast 2	com/tencent/tencentmap/mapsdk/maps/a/p
    //   119: astore_3
    //   120: new 306	android/content/ContentValues
    //   123: astore 5
    //   125: aload 5
    //   127: invokespecial 307	android/content/ContentValues:<init>	()V
    //   130: aload_3
    //   131: getfield 21	com/tencent/tencentmap/mapsdk/maps/a/p:a	J
    //   134: lconst_0
    //   135: lcmp
    //   136: ifle +17 -> 153
    //   139: aload 5
    //   141: ldc 196
    //   143: aload_3
    //   144: getfield 21	com/tencent/tencentmap/mapsdk/maps/a/p:a	J
    //   147: invokestatic 229	java/lang/Long:valueOf	(J)Ljava/lang/Long;
    //   150: invokevirtual 311	android/content/ContentValues:put	(Ljava/lang/String;Ljava/lang/Long;)V
    //   153: aload 5
    //   155: ldc_w 259
    //   158: aload_3
    //   159: getfield 25	com/tencent/tencentmap/mapsdk/maps/a/p:d	I
    //   162: invokestatic 209	java/lang/Integer:valueOf	(I)Ljava/lang/Integer;
    //   165: invokevirtual 314	android/content/ContentValues:put	(Ljava/lang/String;Ljava/lang/Integer;)V
    //   168: aload 5
    //   170: ldc 222
    //   172: aload_3
    //   173: getfield 27	com/tencent/tencentmap/mapsdk/maps/a/p:e	J
    //   176: invokestatic 229	java/lang/Long:valueOf	(J)Ljava/lang/Long;
    //   179: invokevirtual 311	android/content/ContentValues:put	(Ljava/lang/String;Ljava/lang/Long;)V
    //   182: aload 5
    //   184: ldc_w 261
    //   187: aload_3
    //   188: getfield 23	com/tencent/tencentmap/mapsdk/maps/a/p:c	I
    //   191: invokestatic 209	java/lang/Integer:valueOf	(I)Ljava/lang/Integer;
    //   194: invokevirtual 314	android/content/ContentValues:put	(Ljava/lang/String;Ljava/lang/Integer;)V
    //   197: aload 5
    //   199: ldc 231
    //   201: aload_3
    //   202: getfield 29	com/tencent/tencentmap/mapsdk/maps/a/p:b	[B
    //   205: invokevirtual 317	android/content/ContentValues:put	(Ljava/lang/String;[B)V
    //   208: aload 5
    //   210: ldc_w 263
    //   213: aload_3
    //   214: getfield 31	com/tencent/tencentmap/mapsdk/maps/a/p:f	J
    //   217: invokestatic 229	java/lang/Long:valueOf	(J)Ljava/lang/Long;
    //   220: invokevirtual 311	android/content/ContentValues:put	(Ljava/lang/String;Ljava/lang/Long;)V
    //   223: aload_0
    //   224: ldc 111
    //   226: ldc 196
    //   228: aload 5
    //   230: invokevirtual 321	android/database/sqlite/SQLiteDatabase:insert	(Ljava/lang/String;Ljava/lang/String;Landroid/content/ContentValues;)J
    //   233: lstore 6
    //   235: lload 6
    //   237: lconst_0
    //   238: lcmp
    //   239: ifge +13 -> 252
    //   242: ldc_w 323
    //   245: iconst_0
    //   246: anewarray 4	java/lang/Object
    //   249: invokestatic 134	com/tencent/tencentmap/mapsdk/maps/a/ag:d	(Ljava/lang/String;[Ljava/lang/Object;)V
    //   252: aload_3
    //   253: lload 6
    //   255: putfield 21	com/tencent/tencentmap/mapsdk/maps/a/p:a	J
    //   258: iinc 4 1
    //   261: goto -164 -> 97
    //   264: aload_0
    //   265: invokevirtual 326	android/database/sqlite/SQLiteDatabase:setTransactionSuccessful	()V
    //   268: aload_0
    //   269: invokevirtual 329	android/database/sqlite/SQLiteDatabase:endTransaction	()V
    //   272: ldc_w 331
    //   275: iconst_0
    //   276: anewarray 4	java/lang/Object
    //   279: invokestatic 54	com/tencent/tencentmap/mapsdk/maps/a/ag:b	(Ljava/lang/String;[Ljava/lang/Object;)V
    //   282: iconst_1
    //   283: istore_2
    //   284: ldc_w 288
    //   287: invokestatic 43	com/tencent/matrix/trace/core/AppMethodBeat:o	(I)V
    //   290: goto -245 -> 45
    //   293: astore_0
    //   294: ldc 2
    //   296: monitorexit
    //   297: aload_0
    //   298: athrow
    //   299: astore_0
    //   300: ldc_w 333
    //   303: iconst_0
    //   304: anewarray 4	java/lang/Object
    //   307: invokestatic 54	com/tencent/tencentmap/mapsdk/maps/a/ag:b	(Ljava/lang/String;[Ljava/lang/Object;)V
    //   310: goto -38 -> 272
    //   313: astore_0
    //   314: aload_3
    //   315: astore_0
    //   316: ldc_w 335
    //   319: iconst_0
    //   320: anewarray 4	java/lang/Object
    //   323: invokestatic 54	com/tencent/tencentmap/mapsdk/maps/a/ag:b	(Ljava/lang/String;[Ljava/lang/Object;)V
    //   326: aload_0
    //   327: invokevirtual 329	android/database/sqlite/SQLiteDatabase:endTransaction	()V
    //   330: ldc_w 331
    //   333: iconst_0
    //   334: anewarray 4	java/lang/Object
    //   337: invokestatic 54	com/tencent/tencentmap/mapsdk/maps/a/ag:b	(Ljava/lang/String;[Ljava/lang/Object;)V
    //   340: iconst_0
    //   341: istore_2
    //   342: goto -58 -> 284
    //   345: astore_0
    //   346: ldc_w 333
    //   349: iconst_0
    //   350: anewarray 4	java/lang/Object
    //   353: invokestatic 54	com/tencent/tencentmap/mapsdk/maps/a/ag:b	(Ljava/lang/String;[Ljava/lang/Object;)V
    //   356: goto -26 -> 330
    //   359: astore_1
    //   360: aconst_null
    //   361: astore_0
    //   362: aload_0
    //   363: invokevirtual 329	android/database/sqlite/SQLiteDatabase:endTransaction	()V
    //   366: ldc_w 331
    //   369: iconst_0
    //   370: anewarray 4	java/lang/Object
    //   373: invokestatic 54	com/tencent/tencentmap/mapsdk/maps/a/ag:b	(Ljava/lang/String;[Ljava/lang/Object;)V
    //   376: ldc_w 288
    //   379: invokestatic 43	com/tencent/matrix/trace/core/AppMethodBeat:o	(I)V
    //   382: aload_1
    //   383: athrow
    //   384: astore_0
    //   385: ldc_w 333
    //   388: iconst_0
    //   389: anewarray 4	java/lang/Object
    //   392: invokestatic 54	com/tencent/tencentmap/mapsdk/maps/a/ag:b	(Ljava/lang/String;[Ljava/lang/Object;)V
    //   395: goto -29 -> 366
    //   398: astore_1
    //   399: goto -37 -> 362
    //   402: astore_1
    //   403: goto -41 -> 362
    //   406: astore_1
    //   407: goto -91 -> 316
    //
    // Exception table:
    //   from	to	target	type
    //   3	19	293	finally
    //   27	43	293	finally
    //   50	75	293	finally
    //   268	272	293	finally
    //   272	282	293	finally
    //   284	290	293	finally
    //   300	310	293	finally
    //   326	330	293	finally
    //   330	340	293	finally
    //   346	356	293	finally
    //   362	366	293	finally
    //   366	384	293	finally
    //   385	395	293	finally
    //   268	272	299	java/lang/Exception
    //   82	90	313	java/lang/Throwable
    //   326	330	345	java/lang/Exception
    //   82	90	359	finally
    //   362	366	384	java/lang/Exception
    //   90	94	398	finally
    //   97	153	398	finally
    //   153	235	398	finally
    //   242	252	398	finally
    //   252	258	398	finally
    //   264	268	398	finally
    //   316	326	402	finally
    //   90	94	406	java/lang/Throwable
    //   97	153	406	java/lang/Throwable
    //   153	235	406	java/lang/Throwable
    //   242	252	406	java/lang/Throwable
    //   252	258	406	java/lang/Throwable
    //   264	268	406	java/lang/Throwable
  }

  // ERROR //
  public static boolean a(Context paramContext, byte[] paramArrayOfByte, String paramString, int paramInt)
  {
    // Byte code:
    //   0: iconst_0
    //   1: istore 4
    //   3: iconst_0
    //   4: istore 5
    //   6: iconst_0
    //   7: istore 6
    //   9: ldc 2
    //   11: monitorenter
    //   12: ldc_w 338
    //   15: invokestatic 40	com/tencent/matrix/trace/core/AppMethodBeat:i	(I)V
    //   18: ldc_w 340
    //   21: iconst_0
    //   22: anewarray 4	java/lang/Object
    //   25: invokestatic 54	com/tencent/tencentmap/mapsdk/maps/a/ag:b	(Ljava/lang/String;[Ljava/lang/Object;)V
    //   28: aload_0
    //   29: ifnull +11 -> 40
    //   32: aload_1
    //   33: ifnull +7 -> 40
    //   36: aload_2
    //   37: ifnonnull +25 -> 62
    //   40: ldc_w 342
    //   43: iconst_0
    //   44: anewarray 4	java/lang/Object
    //   47: invokestatic 134	com/tencent/tencentmap/mapsdk/maps/a/ag:d	(Ljava/lang/String;[Ljava/lang/Object;)V
    //   50: ldc_w 338
    //   53: invokestatic 43	com/tencent/matrix/trace/core/AppMethodBeat:o	(I)V
    //   56: ldc 2
    //   58: monitorexit
    //   59: iload 6
    //   61: ireturn
    //   62: aload_0
    //   63: invokestatic 105	com/tencent/tencentmap/mapsdk/maps/a/r:a	(Landroid/content/Context;)Lcom/tencent/tencentmap/mapsdk/maps/a/r;
    //   66: invokevirtual 109	com/tencent/tencentmap/mapsdk/maps/a/r:getWritableDatabase	()Landroid/database/sqlite/SQLiteDatabase;
    //   69: astore_0
    //   70: new 306	android/content/ContentValues
    //   73: astore 7
    //   75: aload 7
    //   77: invokespecial 307	android/content/ContentValues:<init>	()V
    //   80: aload 7
    //   82: ldc 217
    //   84: aload_2
    //   85: invokevirtual 345	android/content/ContentValues:put	(Ljava/lang/String;Ljava/lang/String;)V
    //   88: new 347	java/util/Date
    //   91: astore_2
    //   92: aload_2
    //   93: invokespecial 348	java/util/Date:<init>	()V
    //   96: aload 7
    //   98: ldc 222
    //   100: aload_2
    //   101: invokevirtual 351	java/util/Date:getTime	()J
    //   104: invokestatic 229	java/lang/Long:valueOf	(J)Ljava/lang/Long;
    //   107: invokevirtual 311	android/content/ContentValues:put	(Ljava/lang/String;Ljava/lang/Long;)V
    //   110: aload 7
    //   112: ldc 237
    //   114: iload_3
    //   115: invokestatic 209	java/lang/Integer:valueOf	(I)Ljava/lang/Integer;
    //   118: invokevirtual 314	android/content/ContentValues:put	(Ljava/lang/String;Ljava/lang/Integer;)V
    //   121: aload 7
    //   123: ldc 231
    //   125: aload_1
    //   126: invokevirtual 317	android/content/ContentValues:put	(Ljava/lang/String;[B)V
    //   129: aload_0
    //   130: ldc 177
    //   132: aconst_null
    //   133: aload 7
    //   135: invokevirtual 321	android/database/sqlite/SQLiteDatabase:insert	(Ljava/lang/String;Ljava/lang/String;Landroid/content/ContentValues;)J
    //   138: lconst_0
    //   139: lcmp
    //   140: ifge +42 -> 182
    //   143: ldc_w 353
    //   146: iconst_0
    //   147: anewarray 4	java/lang/Object
    //   150: invokestatic 134	com/tencent/tencentmap/mapsdk/maps/a/ag:d	(Ljava/lang/String;[Ljava/lang/Object;)V
    //   153: iload 4
    //   155: istore 6
    //   157: ldc_w 355
    //   160: iconst_0
    //   161: anewarray 4	java/lang/Object
    //   164: invokestatic 54	com/tencent/tencentmap/mapsdk/maps/a/ag:b	(Ljava/lang/String;[Ljava/lang/Object;)V
    //   167: ldc_w 338
    //   170: invokestatic 43	com/tencent/matrix/trace/core/AppMethodBeat:o	(I)V
    //   173: goto -117 -> 56
    //   176: astore_0
    //   177: ldc 2
    //   179: monitorexit
    //   180: aload_0
    //   181: athrow
    //   182: iconst_1
    //   183: istore 6
    //   185: goto -28 -> 157
    //   188: astore_0
    //   189: ldc_w 357
    //   192: iconst_0
    //   193: anewarray 4	java/lang/Object
    //   196: invokestatic 54	com/tencent/tencentmap/mapsdk/maps/a/ag:b	(Ljava/lang/String;[Ljava/lang/Object;)V
    //   199: ldc_w 355
    //   202: iconst_0
    //   203: anewarray 4	java/lang/Object
    //   206: invokestatic 54	com/tencent/tencentmap/mapsdk/maps/a/ag:b	(Ljava/lang/String;[Ljava/lang/Object;)V
    //   209: iload 5
    //   211: istore 6
    //   213: goto -46 -> 167
    //   216: astore_0
    //   217: ldc_w 355
    //   220: iconst_0
    //   221: anewarray 4	java/lang/Object
    //   224: invokestatic 54	com/tencent/tencentmap/mapsdk/maps/a/ag:b	(Ljava/lang/String;[Ljava/lang/Object;)V
    //   227: ldc_w 338
    //   230: invokestatic 43	com/tencent/matrix/trace/core/AppMethodBeat:o	(I)V
    //   233: aload_0
    //   234: athrow
    //
    // Exception table:
    //   from	to	target	type
    //   12	28	176	finally
    //   40	56	176	finally
    //   157	167	176	finally
    //   167	173	176	finally
    //   199	209	176	finally
    //   217	235	176	finally
    //   62	153	188	java/lang/Throwable
    //   62	153	216	finally
    //   189	199	216	finally
  }

  // ERROR //
  public static int b(Context paramContext, int[] paramArrayOfInt)
  {
    // Byte code:
    //   0: iconst_0
    //   1: istore_2
    //   2: iconst_0
    //   3: istore_3
    //   4: ldc 2
    //   6: monitorenter
    //   7: ldc_w 358
    //   10: invokestatic 40	com/tencent/matrix/trace/core/AppMethodBeat:i	(I)V
    //   13: ldc_w 360
    //   16: iconst_0
    //   17: anewarray 4	java/lang/Object
    //   20: invokestatic 54	com/tencent/tencentmap/mapsdk/maps/a/ag:b	(Ljava/lang/String;[Ljava/lang/Object;)V
    //   23: aload_0
    //   24: ifnonnull +26 -> 50
    //   27: ldc_w 362
    //   30: iconst_0
    //   31: anewarray 4	java/lang/Object
    //   34: invokestatic 58	com/tencent/tencentmap/mapsdk/maps/a/ag:a	(Ljava/lang/String;[Ljava/lang/Object;)V
    //   37: ldc_w 358
    //   40: invokestatic 43	com/tencent/matrix/trace/core/AppMethodBeat:o	(I)V
    //   43: iconst_m1
    //   44: istore_3
    //   45: ldc 2
    //   47: monitorexit
    //   48: iload_3
    //   49: ireturn
    //   50: ldc2_w 18
    //   53: ldc2_w 59
    //   56: lcmp
    //   57: ifle +18 -> 75
    //   60: ldc_w 358
    //   63: invokestatic 43	com/tencent/matrix/trace/core/AppMethodBeat:o	(I)V
    //   66: goto -21 -> 45
    //   69: astore_0
    //   70: ldc 2
    //   72: monitorexit
    //   73: aload_0
    //   74: athrow
    //   75: ldc 86
    //   77: astore 4
    //   79: aload 4
    //   81: astore 5
    //   83: aload_1
    //   84: ifnull +105 -> 189
    //   87: aload 4
    //   89: astore 5
    //   91: aload_1
    //   92: arraylength
    //   93: ifle +96 -> 189
    //   96: ldc 62
    //   98: astore 5
    //   100: iload_2
    //   101: istore_3
    //   102: iload_3
    //   103: aload_1
    //   104: arraylength
    //   105: if_icmpge +42 -> 147
    //   108: new 64	java/lang/StringBuilder
    //   111: astore 4
    //   113: aload 4
    //   115: invokespecial 65	java/lang/StringBuilder:<init>	()V
    //   118: aload 4
    //   120: aload 5
    //   122: invokevirtual 69	java/lang/StringBuilder:append	(Ljava/lang/String;)Ljava/lang/StringBuilder;
    //   125: ldc 71
    //   127: invokevirtual 69	java/lang/StringBuilder:append	(Ljava/lang/String;)Ljava/lang/StringBuilder;
    //   130: aload_1
    //   131: iload_3
    //   132: iaload
    //   133: invokevirtual 74	java/lang/StringBuilder:append	(I)Ljava/lang/StringBuilder;
    //   136: invokevirtual 78	java/lang/StringBuilder:toString	()Ljava/lang/String;
    //   139: astore 5
    //   141: iinc 3 1
    //   144: goto -42 -> 102
    //   147: aload 5
    //   149: iconst_4
    //   150: invokevirtual 84	java/lang/String:substring	(I)Ljava/lang/String;
    //   153: astore 5
    //   155: new 64	java/lang/StringBuilder
    //   158: astore_1
    //   159: aload_1
    //   160: invokespecial 65	java/lang/StringBuilder:<init>	()V
    //   163: aload_1
    //   164: ldc 86
    //   166: invokevirtual 69	java/lang/StringBuilder:append	(Ljava/lang/String;)Ljava/lang/StringBuilder;
    //   169: ldc 88
    //   171: invokevirtual 69	java/lang/StringBuilder:append	(Ljava/lang/String;)Ljava/lang/StringBuilder;
    //   174: aload 5
    //   176: invokevirtual 69	java/lang/StringBuilder:append	(Ljava/lang/String;)Ljava/lang/StringBuilder;
    //   179: ldc 90
    //   181: invokevirtual 69	java/lang/StringBuilder:append	(Ljava/lang/String;)Ljava/lang/StringBuilder;
    //   184: invokevirtual 78	java/lang/StringBuilder:toString	()Ljava/lang/String;
    //   187: astore 5
    //   189: ldc_w 364
    //   192: aload 5
    //   194: invokestatic 96	java/lang/String:valueOf	(Ljava/lang/Object;)Ljava/lang/String;
    //   197: invokevirtual 100	java/lang/String:concat	(Ljava/lang/String;)Ljava/lang/String;
    //   200: iconst_0
    //   201: anewarray 4	java/lang/Object
    //   204: invokestatic 54	com/tencent/tencentmap/mapsdk/maps/a/ag:b	(Ljava/lang/String;[Ljava/lang/Object;)V
    //   207: aload_0
    //   208: invokestatic 105	com/tencent/tencentmap/mapsdk/maps/a/r:a	(Landroid/content/Context;)Lcom/tencent/tencentmap/mapsdk/maps/a/r;
    //   211: invokevirtual 109	com/tencent/tencentmap/mapsdk/maps/a/r:getWritableDatabase	()Landroid/database/sqlite/SQLiteDatabase;
    //   214: ldc 111
    //   216: iconst_1
    //   217: anewarray 80	java/lang/String
    //   220: dup
    //   221: iconst_0
    //   222: ldc_w 366
    //   225: aastore
    //   226: aload 5
    //   228: aconst_null
    //   229: aconst_null
    //   230: aconst_null
    //   231: aconst_null
    //   232: invokevirtual 369	android/database/sqlite/SQLiteDatabase:query	(Ljava/lang/String;[Ljava/lang/String;Ljava/lang/String;[Ljava/lang/String;Ljava/lang/String;Ljava/lang/String;Ljava/lang/String;)Landroid/database/Cursor;
    //   235: astore_1
    //   236: aload_1
    //   237: astore_0
    //   238: aload_1
    //   239: invokeinterface 191 1 0
    //   244: pop
    //   245: aload_1
    //   246: astore_0
    //   247: aload_1
    //   248: aload_1
    //   249: ldc_w 371
    //   252: invokeinterface 200 2 0
    //   257: invokeinterface 204 2 0
    //   262: istore_3
    //   263: aload_1
    //   264: astore_0
    //   265: ldc_w 373
    //   268: iload_3
    //   269: invokestatic 121	java/lang/String:valueOf	(I)Ljava/lang/String;
    //   272: invokevirtual 100	java/lang/String:concat	(Ljava/lang/String;)Ljava/lang/String;
    //   275: iconst_0
    //   276: anewarray 4	java/lang/Object
    //   279: invokestatic 54	com/tencent/tencentmap/mapsdk/maps/a/ag:b	(Ljava/lang/String;[Ljava/lang/Object;)V
    //   282: aload_1
    //   283: ifnull +18 -> 301
    //   286: aload_1
    //   287: invokeinterface 242 1 0
    //   292: ifne +9 -> 301
    //   295: aload_1
    //   296: invokeinterface 245 1 0
    //   301: ldc_w 375
    //   304: iconst_0
    //   305: anewarray 4	java/lang/Object
    //   308: invokestatic 54	com/tencent/tencentmap/mapsdk/maps/a/ag:b	(Ljava/lang/String;[Ljava/lang/Object;)V
    //   311: ldc_w 358
    //   314: invokestatic 43	com/tencent/matrix/trace/core/AppMethodBeat:o	(I)V
    //   317: goto -272 -> 45
    //   320: astore 5
    //   322: aconst_null
    //   323: astore_1
    //   324: aload_1
    //   325: astore_0
    //   326: aload 5
    //   328: invokevirtual 126	java/lang/Throwable:getMessage	()Ljava/lang/String;
    //   331: iconst_0
    //   332: anewarray 4	java/lang/Object
    //   335: invokestatic 54	com/tencent/tencentmap/mapsdk/maps/a/ag:b	(Ljava/lang/String;[Ljava/lang/Object;)V
    //   338: aload_1
    //   339: ifnull +18 -> 357
    //   342: aload_1
    //   343: invokeinterface 242 1 0
    //   348: ifne +9 -> 357
    //   351: aload_1
    //   352: invokeinterface 245 1 0
    //   357: ldc_w 375
    //   360: iconst_0
    //   361: anewarray 4	java/lang/Object
    //   364: invokestatic 54	com/tencent/tencentmap/mapsdk/maps/a/ag:b	(Ljava/lang/String;[Ljava/lang/Object;)V
    //   367: iconst_m1
    //   368: istore_3
    //   369: goto -58 -> 311
    //   372: astore_1
    //   373: aconst_null
    //   374: astore_0
    //   375: aload_0
    //   376: ifnull +18 -> 394
    //   379: aload_0
    //   380: invokeinterface 242 1 0
    //   385: ifne +9 -> 394
    //   388: aload_0
    //   389: invokeinterface 245 1 0
    //   394: ldc_w 375
    //   397: iconst_0
    //   398: anewarray 4	java/lang/Object
    //   401: invokestatic 54	com/tencent/tencentmap/mapsdk/maps/a/ag:b	(Ljava/lang/String;[Ljava/lang/Object;)V
    //   404: ldc_w 358
    //   407: invokestatic 43	com/tencent/matrix/trace/core/AppMethodBeat:o	(I)V
    //   410: aload_1
    //   411: athrow
    //   412: astore_1
    //   413: goto -38 -> 375
    //   416: astore 5
    //   418: goto -94 -> 324
    //
    // Exception table:
    //   from	to	target	type
    //   7	23	69	finally
    //   27	43	69	finally
    //   60	66	69	finally
    //   91	96	69	finally
    //   102	141	69	finally
    //   147	189	69	finally
    //   189	207	69	finally
    //   286	301	69	finally
    //   301	311	69	finally
    //   311	317	69	finally
    //   342	357	69	finally
    //   357	367	69	finally
    //   379	394	69	finally
    //   394	412	69	finally
    //   207	236	320	java/lang/Throwable
    //   207	236	372	finally
    //   238	245	412	finally
    //   247	263	412	finally
    //   265	282	412	finally
    //   326	338	412	finally
    //   238	245	416	java/lang/Throwable
    //   247	263	416	java/lang/Throwable
    //   265	282	416	java/lang/Throwable
  }

  private static List<p> b(Context paramContext, int[] paramArrayOfInt, int paramInt)
  {
    try
    {
      AppMethodBeat.i(100532);
      paramContext = c(paramContext, paramArrayOfInt, paramInt);
      AppMethodBeat.o(100532);
      return paramContext;
    }
    finally
    {
      paramContext = finally;
    }
    throw paramContext;
  }

  // ERROR //
  private static List<p> c(Context paramContext, int[] paramArrayOfInt, int paramInt)
  {
    // Byte code:
    //   0: aconst_null
    //   1: astore_3
    //   2: iconst_0
    //   3: istore 4
    //   5: ldc 2
    //   7: monitorenter
    //   8: ldc_w 379
    //   11: invokestatic 40	com/tencent/matrix/trace/core/AppMethodBeat:i	(I)V
    //   14: ldc_w 381
    //   17: iconst_0
    //   18: anewarray 4	java/lang/Object
    //   21: invokestatic 54	com/tencent/tencentmap/mapsdk/maps/a/ag:b	(Ljava/lang/String;[Ljava/lang/Object;)V
    //   24: aload_0
    //   25: ifnull +93 -> 118
    //   28: ldc2_w 18
    //   31: lconst_0
    //   32: lcmp
    //   33: ifle +13 -> 46
    //   36: ldc2_w 18
    //   39: ldc2_w 18
    //   42: lcmp
    //   43: ifgt +75 -> 118
    //   46: ldc 62
    //   48: astore 5
    //   50: aload 5
    //   52: astore 6
    //   54: aload_1
    //   55: ifnull +114 -> 169
    //   58: aload 5
    //   60: astore 6
    //   62: aload_1
    //   63: arraylength
    //   64: ifle +105 -> 169
    //   67: ldc 62
    //   69: astore 6
    //   71: iload 4
    //   73: aload_1
    //   74: arraylength
    //   75: if_icmpge +66 -> 141
    //   78: new 64	java/lang/StringBuilder
    //   81: astore 5
    //   83: aload 5
    //   85: invokespecial 65	java/lang/StringBuilder:<init>	()V
    //   88: aload 5
    //   90: aload 6
    //   92: invokevirtual 69	java/lang/StringBuilder:append	(Ljava/lang/String;)Ljava/lang/StringBuilder;
    //   95: ldc 71
    //   97: invokevirtual 69	java/lang/StringBuilder:append	(Ljava/lang/String;)Ljava/lang/StringBuilder;
    //   100: aload_1
    //   101: iload 4
    //   103: iaload
    //   104: invokevirtual 74	java/lang/StringBuilder:append	(I)Ljava/lang/StringBuilder;
    //   107: invokevirtual 78	java/lang/StringBuilder:toString	()Ljava/lang/String;
    //   110: astore 6
    //   112: iinc 4 1
    //   115: goto -44 -> 71
    //   118: ldc_w 383
    //   121: iconst_0
    //   122: anewarray 4	java/lang/Object
    //   125: invokestatic 134	com/tencent/tencentmap/mapsdk/maps/a/ag:d	(Ljava/lang/String;[Ljava/lang/Object;)V
    //   128: ldc_w 379
    //   131: invokestatic 43	com/tencent/matrix/trace/core/AppMethodBeat:o	(I)V
    //   134: aconst_null
    //   135: astore_0
    //   136: ldc 2
    //   138: monitorexit
    //   139: aload_0
    //   140: areturn
    //   141: new 64	java/lang/StringBuilder
    //   144: astore_1
    //   145: aload_1
    //   146: invokespecial 65	java/lang/StringBuilder:<init>	()V
    //   149: aload_1
    //   150: ldc 62
    //   152: invokevirtual 69	java/lang/StringBuilder:append	(Ljava/lang/String;)Ljava/lang/StringBuilder;
    //   155: aload 6
    //   157: iconst_4
    //   158: invokevirtual 84	java/lang/String:substring	(I)Ljava/lang/String;
    //   161: invokevirtual 69	java/lang/StringBuilder:append	(Ljava/lang/String;)Ljava/lang/StringBuilder;
    //   164: invokevirtual 78	java/lang/StringBuilder:toString	()Ljava/lang/String;
    //   167: astore 6
    //   169: aload 6
    //   171: invokevirtual 384	java/lang/String:length	()I
    //   174: ifle +420 -> 594
    //   177: new 64	java/lang/StringBuilder
    //   180: astore_1
    //   181: aload_1
    //   182: ldc_w 386
    //   185: invokespecial 282	java/lang/StringBuilder:<init>	(Ljava/lang/String;)V
    //   188: aload_1
    //   189: aload 6
    //   191: invokevirtual 69	java/lang/StringBuilder:append	(Ljava/lang/String;)Ljava/lang/StringBuilder;
    //   194: ldc_w 388
    //   197: invokevirtual 69	java/lang/StringBuilder:append	(Ljava/lang/String;)Ljava/lang/StringBuilder;
    //   200: invokevirtual 78	java/lang/StringBuilder:toString	()Ljava/lang/String;
    //   203: astore 6
    //   205: aload 6
    //   207: astore_1
    //   208: ldc2_w 18
    //   211: lconst_0
    //   212: lcmp
    //   213: iflt +47 -> 260
    //   216: new 64	java/lang/StringBuilder
    //   219: astore_1
    //   220: aload_1
    //   221: invokespecial 65	java/lang/StringBuilder:<init>	()V
    //   224: aload_1
    //   225: aload 6
    //   227: invokevirtual 69	java/lang/StringBuilder:append	(Ljava/lang/String;)Ljava/lang/StringBuilder;
    //   230: astore 5
    //   232: aload 6
    //   234: invokevirtual 384	java/lang/String:length	()I
    //   237: ifle +364 -> 601
    //   240: ldc_w 390
    //   243: astore_1
    //   244: aload 5
    //   246: aload_1
    //   247: invokevirtual 69	java/lang/StringBuilder:append	(Ljava/lang/String;)Ljava/lang/StringBuilder;
    //   250: ldc_w 392
    //   253: invokevirtual 69	java/lang/StringBuilder:append	(Ljava/lang/String;)Ljava/lang/StringBuilder;
    //   256: invokevirtual 78	java/lang/StringBuilder:toString	()Ljava/lang/String;
    //   259: astore_1
    //   260: aload_1
    //   261: astore 6
    //   263: ldc2_w 18
    //   266: lconst_0
    //   267: lcmp
    //   268: iflt +49 -> 317
    //   271: new 64	java/lang/StringBuilder
    //   274: astore 6
    //   276: aload 6
    //   278: invokespecial 65	java/lang/StringBuilder:<init>	()V
    //   281: aload 6
    //   283: aload_1
    //   284: invokevirtual 69	java/lang/StringBuilder:append	(Ljava/lang/String;)Ljava/lang/StringBuilder;
    //   287: astore 6
    //   289: aload_1
    //   290: invokevirtual 384	java/lang/String:length	()I
    //   293: ifle +314 -> 607
    //   296: ldc_w 390
    //   299: astore_1
    //   300: aload 6
    //   302: aload_1
    //   303: invokevirtual 69	java/lang/StringBuilder:append	(Ljava/lang/String;)Ljava/lang/StringBuilder;
    //   306: ldc_w 394
    //   309: invokevirtual 69	java/lang/StringBuilder:append	(Ljava/lang/String;)Ljava/lang/StringBuilder;
    //   312: invokevirtual 78	java/lang/StringBuilder:toString	()Ljava/lang/String;
    //   315: astore 6
    //   317: new 64	java/lang/StringBuilder
    //   320: astore_1
    //   321: aload_1
    //   322: invokespecial 65	java/lang/StringBuilder:<init>	()V
    //   325: aload_1
    //   326: ldc 62
    //   328: invokevirtual 69	java/lang/StringBuilder:append	(Ljava/lang/String;)Ljava/lang/StringBuilder;
    //   331: ldc_w 396
    //   334: invokevirtual 69	java/lang/StringBuilder:append	(Ljava/lang/String;)Ljava/lang/StringBuilder;
    //   337: invokevirtual 78	java/lang/StringBuilder:toString	()Ljava/lang/String;
    //   340: astore_1
    //   341: new 64	java/lang/StringBuilder
    //   344: astore 5
    //   346: aload 5
    //   348: invokespecial 65	java/lang/StringBuilder:<init>	()V
    //   351: aload 5
    //   353: aload_1
    //   354: invokevirtual 69	java/lang/StringBuilder:append	(Ljava/lang/String;)Ljava/lang/StringBuilder;
    //   357: ldc 179
    //   359: invokevirtual 69	java/lang/StringBuilder:append	(Ljava/lang/String;)Ljava/lang/StringBuilder;
    //   362: invokevirtual 78	java/lang/StringBuilder:toString	()Ljava/lang/String;
    //   365: astore 5
    //   367: aload 5
    //   369: astore_1
    //   370: aload 5
    //   372: ldc_w 398
    //   375: invokevirtual 402	java/lang/String:endsWith	(Ljava/lang/String;)Z
    //   378: ifeq +17 -> 395
    //   381: aload 5
    //   383: iconst_0
    //   384: aload 5
    //   386: invokevirtual 384	java/lang/String:length	()I
    //   389: iconst_3
    //   390: isub
    //   391: invokevirtual 405	java/lang/String:substring	(II)Ljava/lang/String;
    //   394: astore_1
    //   395: ldc_w 407
    //   398: iconst_1
    //   399: anewarray 4	java/lang/Object
    //   402: dup
    //   403: iconst_0
    //   404: aload 6
    //   406: aastore
    //   407: invokestatic 54	com/tencent/tencentmap/mapsdk/maps/a/ag:b	(Ljava/lang/String;[Ljava/lang/Object;)V
    //   410: aload_0
    //   411: invokestatic 105	com/tencent/tencentmap/mapsdk/maps/a/r:a	(Landroid/content/Context;)Lcom/tencent/tencentmap/mapsdk/maps/a/r;
    //   414: invokevirtual 109	com/tencent/tencentmap/mapsdk/maps/a/r:getWritableDatabase	()Landroid/database/sqlite/SQLiteDatabase;
    //   417: astore 5
    //   419: iload_2
    //   420: iflt +193 -> 613
    //   423: iload_2
    //   424: invokestatic 121	java/lang/String:valueOf	(I)Ljava/lang/String;
    //   427: astore_0
    //   428: aload 5
    //   430: ldc 111
    //   432: aconst_null
    //   433: aload 6
    //   435: aconst_null
    //   436: aconst_null
    //   437: aconst_null
    //   438: aload_1
    //   439: aload_0
    //   440: invokevirtual 185	android/database/sqlite/SQLiteDatabase:query	(Ljava/lang/String;[Ljava/lang/String;Ljava/lang/String;[Ljava/lang/String;Ljava/lang/String;Ljava/lang/String;Ljava/lang/String;Ljava/lang/String;)Landroid/database/Cursor;
    //   443: astore_1
    //   444: aload_1
    //   445: astore 6
    //   447: new 64	java/lang/StringBuilder
    //   450: astore_0
    //   451: aload_1
    //   452: astore 6
    //   454: aload_0
    //   455: ldc_w 409
    //   458: invokespecial 282	java/lang/StringBuilder:<init>	(Ljava/lang/String;)V
    //   461: aload_1
    //   462: astore 6
    //   464: aload_0
    //   465: aload_1
    //   466: invokeinterface 412 1 0
    //   471: invokevirtual 74	java/lang/StringBuilder:append	(I)Ljava/lang/StringBuilder;
    //   474: invokevirtual 78	java/lang/StringBuilder:toString	()Ljava/lang/String;
    //   477: iconst_0
    //   478: anewarray 4	java/lang/Object
    //   481: invokestatic 58	com/tencent/tencentmap/mapsdk/maps/a/ag:a	(Ljava/lang/String;[Ljava/lang/Object;)V
    //   484: aload_3
    //   485: astore_0
    //   486: aload_1
    //   487: astore 6
    //   489: aload_1
    //   490: invokeinterface 412 1 0
    //   495: ifle +11 -> 506
    //   498: aload_1
    //   499: astore 6
    //   501: aload_1
    //   502: invokestatic 414	com/tencent/tencentmap/mapsdk/maps/a/p:a	(Landroid/database/Cursor;)Ljava/util/List;
    //   505: astore_0
    //   506: aload_0
    //   507: ifnull +43 -> 550
    //   510: aload_1
    //   511: astore 6
    //   513: new 64	java/lang/StringBuilder
    //   516: astore_3
    //   517: aload_1
    //   518: astore 6
    //   520: aload_3
    //   521: ldc_w 416
    //   524: invokespecial 282	java/lang/StringBuilder:<init>	(Ljava/lang/String;)V
    //   527: aload_1
    //   528: astore 6
    //   530: aload_3
    //   531: aload_0
    //   532: invokeinterface 295 1 0
    //   537: invokevirtual 74	java/lang/StringBuilder:append	(I)Ljava/lang/StringBuilder;
    //   540: invokevirtual 78	java/lang/StringBuilder:toString	()Ljava/lang/String;
    //   543: iconst_0
    //   544: anewarray 4	java/lang/Object
    //   547: invokestatic 58	com/tencent/tencentmap/mapsdk/maps/a/ag:a	(Ljava/lang/String;[Ljava/lang/Object;)V
    //   550: aload_1
    //   551: ifnull +18 -> 569
    //   554: aload_1
    //   555: invokeinterface 242 1 0
    //   560: ifne +9 -> 569
    //   563: aload_1
    //   564: invokeinterface 245 1 0
    //   569: ldc_w 418
    //   572: iconst_0
    //   573: anewarray 4	java/lang/Object
    //   576: invokestatic 54	com/tencent/tencentmap/mapsdk/maps/a/ag:b	(Ljava/lang/String;[Ljava/lang/Object;)V
    //   579: ldc_w 379
    //   582: invokestatic 43	com/tencent/matrix/trace/core/AppMethodBeat:o	(I)V
    //   585: goto -449 -> 136
    //   588: astore_0
    //   589: ldc 2
    //   591: monitorexit
    //   592: aload_0
    //   593: athrow
    //   594: ldc 62
    //   596: astore 6
    //   598: goto -393 -> 205
    //   601: ldc 62
    //   603: astore_1
    //   604: goto -360 -> 244
    //   607: ldc 62
    //   609: astore_1
    //   610: goto -310 -> 300
    //   613: aconst_null
    //   614: astore_0
    //   615: goto -187 -> 428
    //   618: astore_3
    //   619: aconst_null
    //   620: astore_1
    //   621: aconst_null
    //   622: astore_0
    //   623: aload_1
    //   624: astore 6
    //   626: aload_3
    //   627: invokevirtual 126	java/lang/Throwable:getMessage	()Ljava/lang/String;
    //   630: iconst_0
    //   631: anewarray 4	java/lang/Object
    //   634: invokestatic 54	com/tencent/tencentmap/mapsdk/maps/a/ag:b	(Ljava/lang/String;[Ljava/lang/Object;)V
    //   637: aload_1
    //   638: ifnull +18 -> 656
    //   641: aload_1
    //   642: invokeinterface 242 1 0
    //   647: ifne +9 -> 656
    //   650: aload_1
    //   651: invokeinterface 245 1 0
    //   656: ldc_w 418
    //   659: iconst_0
    //   660: anewarray 4	java/lang/Object
    //   663: invokestatic 54	com/tencent/tencentmap/mapsdk/maps/a/ag:b	(Ljava/lang/String;[Ljava/lang/Object;)V
    //   666: goto -87 -> 579
    //   669: astore_0
    //   670: aconst_null
    //   671: astore 6
    //   673: aload 6
    //   675: ifnull +20 -> 695
    //   678: aload 6
    //   680: invokeinterface 242 1 0
    //   685: ifne +10 -> 695
    //   688: aload 6
    //   690: invokeinterface 245 1 0
    //   695: ldc_w 418
    //   698: iconst_0
    //   699: anewarray 4	java/lang/Object
    //   702: invokestatic 54	com/tencent/tencentmap/mapsdk/maps/a/ag:b	(Ljava/lang/String;[Ljava/lang/Object;)V
    //   705: ldc_w 379
    //   708: invokestatic 43	com/tencent/matrix/trace/core/AppMethodBeat:o	(I)V
    //   711: aload_0
    //   712: athrow
    //   713: astore_0
    //   714: goto -41 -> 673
    //   717: astore_3
    //   718: aconst_null
    //   719: astore_0
    //   720: goto -97 -> 623
    //   723: astore_3
    //   724: goto -101 -> 623
    //
    // Exception table:
    //   from	to	target	type
    //   8	24	588	finally
    //   62	67	588	finally
    //   71	112	588	finally
    //   118	134	588	finally
    //   141	169	588	finally
    //   169	205	588	finally
    //   216	240	588	finally
    //   244	260	588	finally
    //   271	296	588	finally
    //   300	317	588	finally
    //   317	367	588	finally
    //   370	395	588	finally
    //   395	410	588	finally
    //   554	569	588	finally
    //   569	579	588	finally
    //   579	585	588	finally
    //   641	656	588	finally
    //   656	666	588	finally
    //   678	695	588	finally
    //   695	713	588	finally
    //   410	419	618	java/lang/Throwable
    //   423	428	618	java/lang/Throwable
    //   428	444	618	java/lang/Throwable
    //   410	419	669	finally
    //   423	428	669	finally
    //   428	444	669	finally
    //   447	451	713	finally
    //   454	461	713	finally
    //   464	484	713	finally
    //   489	498	713	finally
    //   501	506	713	finally
    //   513	517	713	finally
    //   520	527	713	finally
    //   530	550	713	finally
    //   626	637	713	finally
    //   447	451	717	java/lang/Throwable
    //   454	461	717	java/lang/Throwable
    //   464	484	717	java/lang/Throwable
    //   489	498	717	java/lang/Throwable
    //   501	506	717	java/lang/Throwable
    //   513	517	723	java/lang/Throwable
    //   520	527	723	java/lang/Throwable
    //   530	550	723	java/lang/Throwable
  }
}

/* Location:           C:\Users\Lin\Downloads\dex-tools-2.1-SNAPSHOT\dex-tools-2.1-SNAPSHOT\classes7-dex2jar.jar
 * Qualified Name:     com.tencent.tencentmap.mapsdk.maps.a.p
 * JD-Core Version:    0.6.2
 */