package com.tencent.tencentmap.mapsdk.maps.a;

import android.content.Context;

public final class u
  implements Runnable
{
  private static long a = 0L;
  private Context b = null;

  public u(Context paramContext)
  {
    this.b = paramContext;
  }

  private static long a()
  {
    try
    {
      long l = a;
      return l;
    }
    finally
    {
      localObject = finally;
      throw localObject;
    }
  }

  public static void a(long paramLong)
  {
    try
    {
      a = paramLong;
      return;
    }
    finally
    {
      localObject = finally;
      throw localObject;
    }
  }

  // ERROR //
  private static boolean a(Context paramContext)
  {
    // Byte code:
    //   0: iconst_0
    //   1: istore_1
    //   2: ldc 27
    //   4: invokestatic 33	com/tencent/matrix/trace/core/AppMethodBeat:i	(I)V
    //   7: aload_0
    //   8: ldc 35
    //   10: ldc 37
    //   12: invokestatic 42	com/tencent/tencentmap/mapsdk/a/a:b	(Landroid/content/Context;Ljava/lang/String;Ljava/lang/String;)Ljava/lang/String;
    //   15: invokestatic 48	java/lang/Integer:parseInt	(Ljava/lang/String;)I
    //   18: istore_2
    //   19: aload_0
    //   20: ldc 50
    //   22: ldc 52
    //   24: invokestatic 42	com/tencent/tencentmap/mapsdk/a/a:b	(Landroid/content/Context;Ljava/lang/String;Ljava/lang/String;)Ljava/lang/String;
    //   27: astore_3
    //   28: invokestatic 58	com/tencent/tencentmap/mapsdk/a/e:g	()Ljava/lang/String;
    //   31: aload_3
    //   32: invokevirtual 64	java/lang/String:equals	(Ljava/lang/Object;)Z
    //   35: ifne +12 -> 47
    //   38: aload_0
    //   39: invokestatic 58	com/tencent/tencentmap/mapsdk/a/e:g	()Ljava/lang/String;
    //   42: invokestatic 67	com/tencent/tencentmap/mapsdk/a/a:b	(Landroid/content/Context;Ljava/lang/String;)V
    //   45: iconst_0
    //   46: istore_2
    //   47: iload_2
    //   48: invokestatic 72	com/tencent/tencentmap/mapsdk/maps/a/v:a	()Lcom/tencent/tencentmap/mapsdk/maps/a/v;
    //   51: invokevirtual 76	com/tencent/tencentmap/mapsdk/maps/a/v:f	()I
    //   54: if_icmpgt +20 -> 74
    //   57: aload_0
    //   58: iload_2
    //   59: iconst_1
    //   60: iadd
    //   61: invokestatic 80	java/lang/String:valueOf	(I)Ljava/lang/String;
    //   64: invokestatic 82	com/tencent/tencentmap/mapsdk/a/a:a	(Landroid/content/Context;Ljava/lang/String;)V
    //   67: ldc 27
    //   69: invokestatic 85	com/tencent/matrix/trace/core/AppMethodBeat:o	(I)V
    //   72: iload_1
    //   73: ireturn
    //   74: iconst_1
    //   75: istore_1
    //   76: ldc 87
    //   78: iconst_0
    //   79: anewarray 4	java/lang/Object
    //   82: invokestatic 93	com/tencent/tencentmap/mapsdk/maps/a/ag:e	(Ljava/lang/String;[Ljava/lang/Object;)V
    //   85: iconst_1
    //   86: istore_1
    //   87: goto -20 -> 67
    //   90: astore_0
    //   91: iconst_0
    //   92: istore_1
    //   93: ldc 95
    //   95: iconst_0
    //   96: anewarray 4	java/lang/Object
    //   99: invokestatic 98	com/tencent/tencentmap/mapsdk/maps/a/ag:c	(Ljava/lang/String;[Ljava/lang/Object;)V
    //   102: goto -35 -> 67
    //   105: astore_0
    //   106: goto -13 -> 93
    //
    // Exception table:
    //   from	to	target	type
    //   7	28	90	java/lang/Exception
    //   28	45	90	java/lang/Exception
    //   47	67	90	java/lang/Exception
    //   76	85	105	java/lang/Exception
  }

  // ERROR //
  public final void run()
  {
    // Byte code:
    //   0: ldc 104
    //   2: invokestatic 33	com/tencent/matrix/trace/core/AppMethodBeat:i	(I)V
    //   5: aload_0
    //   6: getfield 21	com/tencent/tencentmap/mapsdk/maps/a/u:b	Landroid/content/Context;
    //   9: invokestatic 108	com/tencent/tencentmap/mapsdk/a/e:h	(Landroid/content/Context;)Lcom/tencent/tencentmap/mapsdk/maps/a/y;
    //   12: astore_1
    //   13: aload_1
    //   14: ifnull +54 -> 68
    //   17: aload_1
    //   18: invokevirtual 112	com/tencent/tencentmap/mapsdk/maps/a/y:b	()I
    //   21: bipush 101
    //   23: if_icmpne +45 -> 68
    //   26: aload_1
    //   27: invokevirtual 115	com/tencent/tencentmap/mapsdk/maps/a/y:c	()[B
    //   30: ifnull +38 -> 68
    //   33: aload_0
    //   34: getfield 21	com/tencent/tencentmap/mapsdk/maps/a/u:b	Landroid/content/Context;
    //   37: invokestatic 120	com/tencent/tencentmap/mapsdk/maps/a/t:a	(Landroid/content/Context;)Lcom/tencent/tencentmap/mapsdk/maps/a/t;
    //   40: invokevirtual 123	com/tencent/tencentmap/mapsdk/maps/a/t:f	()Lcom/tencent/tencentmap/mapsdk/maps/a/bd;
    //   43: astore_2
    //   44: aload_2
    //   45: ifnull +23 -> 68
    //   48: aload_2
    //   49: bipush 101
    //   51: aload_1
    //   52: invokevirtual 115	com/tencent/tencentmap/mapsdk/maps/a/y:c	()[B
    //   55: iconst_0
    //   56: invokevirtual 128	com/tencent/tencentmap/mapsdk/maps/a/bd:a	(I[BZ)V
    //   59: ldc 130
    //   61: iconst_0
    //   62: anewarray 4	java/lang/Object
    //   65: invokestatic 93	com/tencent/tencentmap/mapsdk/maps/a/ag:e	(Ljava/lang/String;[Ljava/lang/Object;)V
    //   68: aload_0
    //   69: getfield 21	com/tencent/tencentmap/mapsdk/maps/a/u:b	Landroid/content/Context;
    //   72: invokestatic 120	com/tencent/tencentmap/mapsdk/maps/a/t:a	(Landroid/content/Context;)Lcom/tencent/tencentmap/mapsdk/maps/a/t;
    //   75: astore_1
    //   76: aload_1
    //   77: invokevirtual 133	com/tencent/tencentmap/mapsdk/maps/a/t:j	()I
    //   80: ifne +184 -> 264
    //   83: ldc 135
    //   85: iconst_0
    //   86: anewarray 4	java/lang/Object
    //   89: invokestatic 93	com/tencent/tencentmap/mapsdk/maps/a/ag:e	(Ljava/lang/String;[Ljava/lang/Object;)V
    //   92: aload_1
    //   93: iconst_1
    //   94: invokevirtual 137	com/tencent/tencentmap/mapsdk/maps/a/t:a	(I)V
    //   97: aload_0
    //   98: getfield 21	com/tencent/tencentmap/mapsdk/maps/a/u:b	Landroid/content/Context;
    //   101: invokestatic 139	com/tencent/tencentmap/mapsdk/a/a:c	(Landroid/content/Context;)Z
    //   104: istore_3
    //   105: ldc 141
    //   107: iconst_1
    //   108: anewarray 4	java/lang/Object
    //   111: dup
    //   112: iconst_0
    //   113: iload_3
    //   114: invokestatic 146	java/lang/Boolean:valueOf	(Z)Ljava/lang/Boolean;
    //   117: aastore
    //   118: invokestatic 93	com/tencent/tencentmap/mapsdk/maps/a/ag:e	(Ljava/lang/String;[Ljava/lang/Object;)V
    //   121: iload_3
    //   122: ifeq +108 -> 230
    //   125: ldc 148
    //   127: iconst_1
    //   128: anewarray 4	java/lang/Object
    //   131: dup
    //   132: iconst_0
    //   133: aload_0
    //   134: getfield 21	com/tencent/tencentmap/mapsdk/maps/a/u:b	Landroid/content/Context;
    //   137: aconst_null
    //   138: invokestatic 153	com/tencent/tencentmap/mapsdk/maps/a/p:a	(Landroid/content/Context;[I)I
    //   141: invokestatic 156	java/lang/Integer:valueOf	(I)Ljava/lang/Integer;
    //   144: aastore
    //   145: invokestatic 93	com/tencent/tencentmap/mapsdk/maps/a/ag:e	(Ljava/lang/String;[Ljava/lang/Object;)V
    //   148: aload_1
    //   149: monitorenter
    //   150: ldc 158
    //   152: iconst_0
    //   153: anewarray 4	java/lang/Object
    //   156: invokestatic 93	com/tencent/tencentmap/mapsdk/maps/a/ag:e	(Ljava/lang/String;[Ljava/lang/Object;)V
    //   159: aload_1
    //   160: invokevirtual 161	com/tencent/tencentmap/mapsdk/maps/a/t:i	()[Lcom/tencent/tencentmap/mapsdk/maps/a/s;
    //   163: astore_2
    //   164: aload_1
    //   165: invokevirtual 163	com/tencent/tencentmap/mapsdk/maps/a/t:h	()V
    //   168: aload_1
    //   169: monitorexit
    //   170: aload_2
    //   171: ifnull +93 -> 264
    //   174: ldc 165
    //   176: iconst_0
    //   177: anewarray 4	java/lang/Object
    //   180: invokestatic 93	com/tencent/tencentmap/mapsdk/maps/a/ag:e	(Ljava/lang/String;[Ljava/lang/Object;)V
    //   183: aload_2
    //   184: arraylength
    //   185: istore 4
    //   187: iconst_0
    //   188: istore 5
    //   190: iload 5
    //   192: iload 4
    //   194: if_icmpge +70 -> 264
    //   197: aload_2
    //   198: iload 5
    //   200: aaload
    //   201: invokeinterface 169 1 0
    //   206: iinc 5 1
    //   209: goto -19 -> 190
    //   212: astore_2
    //   213: aload_2
    //   214: invokestatic 172	com/tencent/tencentmap/mapsdk/maps/a/ag:a	(Ljava/lang/Throwable;)V
    //   217: goto -149 -> 68
    //   220: astore_2
    //   221: aload_1
    //   222: monitorexit
    //   223: ldc 104
    //   225: invokestatic 85	com/tencent/matrix/trace/core/AppMethodBeat:o	(I)V
    //   228: aload_2
    //   229: athrow
    //   230: invokestatic 174	com/tencent/tencentmap/mapsdk/maps/a/u:a	()J
    //   233: lstore 6
    //   235: lload 6
    //   237: lconst_0
    //   238: lcmp
    //   239: ifle +25 -> 264
    //   242: ldc 176
    //   244: iconst_1
    //   245: anewarray 4	java/lang/Object
    //   248: dup
    //   249: iconst_0
    //   250: lload 6
    //   252: invokestatic 181	java/lang/Long:valueOf	(J)Ljava/lang/Long;
    //   255: aastore
    //   256: invokestatic 93	com/tencent/tencentmap/mapsdk/maps/a/ag:e	(Ljava/lang/String;[Ljava/lang/Object;)V
    //   259: lload 6
    //   261: invokestatic 186	java/lang/Thread:sleep	(J)V
    //   264: aload_1
    //   265: monitorenter
    //   266: ldc 188
    //   268: iconst_0
    //   269: anewarray 4	java/lang/Object
    //   272: invokestatic 93	com/tencent/tencentmap/mapsdk/maps/a/ag:e	(Ljava/lang/String;[Ljava/lang/Object;)V
    //   275: aload_1
    //   276: invokevirtual 161	com/tencent/tencentmap/mapsdk/maps/a/t:i	()[Lcom/tencent/tencentmap/mapsdk/maps/a/s;
    //   279: astore_2
    //   280: aload_1
    //   281: iconst_2
    //   282: invokevirtual 137	com/tencent/tencentmap/mapsdk/maps/a/t:a	(I)V
    //   285: aload_1
    //   286: monitorexit
    //   287: aload_2
    //   288: ifnull +59 -> 347
    //   291: ldc 190
    //   293: iconst_0
    //   294: anewarray 4	java/lang/Object
    //   297: invokestatic 93	com/tencent/tencentmap/mapsdk/maps/a/ag:e	(Ljava/lang/String;[Ljava/lang/Object;)V
    //   300: aload_2
    //   301: arraylength
    //   302: istore 4
    //   304: iconst_0
    //   305: istore 5
    //   307: iload 5
    //   309: iload 4
    //   311: if_icmpge +36 -> 347
    //   314: aload_2
    //   315: iload 5
    //   317: aaload
    //   318: invokeinterface 192 1 0
    //   323: iinc 5 1
    //   326: goto -19 -> 307
    //   329: astore_2
    //   330: aload_2
    //   331: invokestatic 172	com/tencent/tencentmap/mapsdk/maps/a/ag:a	(Ljava/lang/Throwable;)V
    //   334: goto -70 -> 264
    //   337: astore_2
    //   338: aload_1
    //   339: monitorexit
    //   340: ldc 104
    //   342: invokestatic 85	com/tencent/matrix/trace/core/AppMethodBeat:o	(I)V
    //   345: aload_2
    //   346: athrow
    //   347: invokestatic 72	com/tencent/tencentmap/mapsdk/maps/a/v:a	()Lcom/tencent/tencentmap/mapsdk/maps/a/v;
    //   350: invokevirtual 195	com/tencent/tencentmap/mapsdk/maps/a/v:g	()Z
    //   353: ifne +77 -> 430
    //   356: invokestatic 198	com/tencent/tencentmap/mapsdk/maps/a/t:c	()Lcom/tencent/tencentmap/mapsdk/maps/a/be;
    //   359: astore_2
    //   360: iconst_0
    //   361: istore 5
    //   363: aload_2
    //   364: ifnonnull +33 -> 397
    //   367: iinc 5 1
    //   370: iload 5
    //   372: iconst_5
    //   373: if_icmpge +24 -> 397
    //   376: ldc2_w 199
    //   379: invokestatic 186	java/lang/Thread:sleep	(J)V
    //   382: invokestatic 198	com/tencent/tencentmap/mapsdk/maps/a/t:c	()Lcom/tencent/tencentmap/mapsdk/maps/a/be;
    //   385: astore_2
    //   386: goto -23 -> 363
    //   389: astore_2
    //   390: aload_2
    //   391: invokestatic 172	com/tencent/tencentmap/mapsdk/maps/a/ag:a	(Ljava/lang/Throwable;)V
    //   394: goto -12 -> 382
    //   397: aload_2
    //   398: ifnull +117 -> 515
    //   401: aload_0
    //   402: getfield 21	com/tencent/tencentmap/mapsdk/maps/a/u:b	Landroid/content/Context;
    //   405: invokestatic 202	com/tencent/tencentmap/mapsdk/maps/a/u:a	(Landroid/content/Context;)Z
    //   408: ifeq +87 -> 495
    //   411: ldc 204
    //   413: iconst_0
    //   414: anewarray 4	java/lang/Object
    //   417: invokestatic 98	com/tencent/tencentmap/mapsdk/maps/a/ag:c	(Ljava/lang/String;[Ljava/lang/Object;)V
    //   420: aload_0
    //   421: getfield 21	com/tencent/tencentmap/mapsdk/maps/a/u:b	Landroid/content/Context;
    //   424: invokestatic 120	com/tencent/tencentmap/mapsdk/maps/a/t:a	(Landroid/content/Context;)Lcom/tencent/tencentmap/mapsdk/maps/a/t;
    //   427: invokevirtual 206	com/tencent/tencentmap/mapsdk/maps/a/t:b	()V
    //   430: ldc 208
    //   432: iconst_0
    //   433: anewarray 4	java/lang/Object
    //   436: invokestatic 210	com/tencent/tencentmap/mapsdk/maps/a/ag:h	(Ljava/lang/String;[Ljava/lang/Object;)V
    //   439: aload_1
    //   440: monitorenter
    //   441: aload_1
    //   442: invokevirtual 161	com/tencent/tencentmap/mapsdk/maps/a/t:i	()[Lcom/tencent/tencentmap/mapsdk/maps/a/s;
    //   445: astore_2
    //   446: aload_1
    //   447: iconst_3
    //   448: invokevirtual 137	com/tencent/tencentmap/mapsdk/maps/a/t:a	(I)V
    //   451: aload_1
    //   452: monitorexit
    //   453: aload_2
    //   454: ifnull +83 -> 537
    //   457: ldc 212
    //   459: iconst_0
    //   460: anewarray 4	java/lang/Object
    //   463: invokestatic 93	com/tencent/tencentmap/mapsdk/maps/a/ag:e	(Ljava/lang/String;[Ljava/lang/Object;)V
    //   466: aload_2
    //   467: arraylength
    //   468: istore 4
    //   470: iconst_0
    //   471: istore 5
    //   473: iload 5
    //   475: iload 4
    //   477: if_icmpge +60 -> 537
    //   480: aload_2
    //   481: iload 5
    //   483: aaload
    //   484: invokeinterface 213 1 0
    //   489: iinc 5 1
    //   492: goto -19 -> 473
    //   495: aload_2
    //   496: new 215	com/tencent/tencentmap/mapsdk/maps/a/bb
    //   499: dup
    //   500: aload_0
    //   501: getfield 21	com/tencent/tencentmap/mapsdk/maps/a/u:b	Landroid/content/Context;
    //   504: invokespecial 217	com/tencent/tencentmap/mapsdk/maps/a/bb:<init>	(Landroid/content/Context;)V
    //   507: invokeinterface 222 2 0
    //   512: goto -82 -> 430
    //   515: ldc 224
    //   517: iconst_0
    //   518: anewarray 4	java/lang/Object
    //   521: invokestatic 210	com/tencent/tencentmap/mapsdk/maps/a/ag:h	(Ljava/lang/String;[Ljava/lang/Object;)V
    //   524: goto -94 -> 430
    //   527: astore_2
    //   528: aload_1
    //   529: monitorexit
    //   530: ldc 104
    //   532: invokestatic 85	com/tencent/matrix/trace/core/AppMethodBeat:o	(I)V
    //   535: aload_2
    //   536: athrow
    //   537: aload_0
    //   538: getfield 21	com/tencent/tencentmap/mapsdk/maps/a/u:b	Landroid/content/Context;
    //   541: invokestatic 120	com/tencent/tencentmap/mapsdk/maps/a/t:a	(Landroid/content/Context;)Lcom/tencent/tencentmap/mapsdk/maps/a/t;
    //   544: invokevirtual 226	com/tencent/tencentmap/mapsdk/maps/a/t:e	()Lcom/tencent/tencentmap/mapsdk/maps/a/v;
    //   547: astore_2
    //   548: aload_2
    //   549: ifnonnull +18 -> 567
    //   552: ldc 228
    //   554: iconst_0
    //   555: anewarray 4	java/lang/Object
    //   558: invokestatic 231	com/tencent/tencentmap/mapsdk/maps/a/ag:d	(Ljava/lang/String;[Ljava/lang/Object;)V
    //   561: ldc 104
    //   563: invokestatic 85	com/tencent/matrix/trace/core/AppMethodBeat:o	(I)V
    //   566: return
    //   567: aload_2
    //   568: invokevirtual 233	com/tencent/tencentmap/mapsdk/maps/a/v:c	()I
    //   571: ldc 234
    //   573: imul
    //   574: i2l
    //   575: lstore 6
    //   577: lload 6
    //   579: lconst_0
    //   580: lcmp
    //   581: ifle +48 -> 629
    //   584: invokestatic 239	com/tencent/tencentmap/mapsdk/a/b:a	()Lcom/tencent/tencentmap/mapsdk/a/b;
    //   587: aload_0
    //   588: lload 6
    //   590: invokevirtual 242	com/tencent/tencentmap/mapsdk/a/b:a	(Ljava/lang/Runnable;J)V
    //   593: ldc 244
    //   595: iconst_1
    //   596: anewarray 4	java/lang/Object
    //   599: dup
    //   600: iconst_0
    //   601: lload 6
    //   603: invokestatic 181	java/lang/Long:valueOf	(J)Ljava/lang/Long;
    //   606: aastore
    //   607: invokestatic 210	com/tencent/tencentmap/mapsdk/maps/a/ag:h	(Ljava/lang/String;[Ljava/lang/Object;)V
    //   610: aload_0
    //   611: getfield 21	com/tencent/tencentmap/mapsdk/maps/a/u:b	Landroid/content/Context;
    //   614: invokestatic 120	com/tencent/tencentmap/mapsdk/maps/a/t:a	(Landroid/content/Context;)Lcom/tencent/tencentmap/mapsdk/maps/a/t;
    //   617: iconst_4
    //   618: invokevirtual 137	com/tencent/tencentmap/mapsdk/maps/a/t:a	(I)V
    //   621: ldc 104
    //   623: invokestatic 85	com/tencent/matrix/trace/core/AppMethodBeat:o	(I)V
    //   626: goto -60 -> 566
    //   629: ldc 246
    //   631: iconst_0
    //   632: anewarray 4	java/lang/Object
    //   635: invokestatic 210	com/tencent/tencentmap/mapsdk/maps/a/ag:h	(Ljava/lang/String;[Ljava/lang/Object;)V
    //   638: ldc 104
    //   640: invokestatic 85	com/tencent/matrix/trace/core/AppMethodBeat:o	(I)V
    //   643: goto -77 -> 566
    //
    // Exception table:
    //   from	to	target	type
    //   33	44	212	java/lang/Throwable
    //   48	68	212	java/lang/Throwable
    //   150	170	220	finally
    //   259	264	329	java/lang/InterruptedException
    //   266	287	337	finally
    //   376	382	389	java/lang/InterruptedException
    //   441	453	527	finally
  }
}

/* Location:           C:\Users\Lin\Downloads\dex-tools-2.1-SNAPSHOT\dex-tools-2.1-SNAPSHOT\classes2-dex2jar.jar
 * Qualified Name:     com.tencent.tencentmap.mapsdk.maps.a.u
 * JD-Core Version:    0.6.2
 */