package a.i.b.a.c.e;

import a.i.b.a.c.g.b;
import a.i.b.a.c.g.d;
import a.i.b.a.c.g.f;
import a.i.b.a.c.g.g;
import a.i.b.a.c.g.h;
import a.i.b.a.c.g.i;
import a.i.b.a.c.g.i.a;
import a.i.b.a.c.g.i.b;
import a.i.b.a.c.g.i.c;
import a.i.b.a.c.g.i.c.a;
import a.i.b.a.c.g.i.d;
import a.i.b.a.c.g.j.a;
import a.i.b.a.c.g.j.b;
import a.i.b.a.c.g.q;
import a.i.b.a.c.g.r;
import a.i.b.a.c.g.s;
import com.tencent.matrix.trace.core.AppMethodBeat;
import java.io.InputStream;
import java.util.ArrayList;
import java.util.Collections;
import java.util.List;

public final class a
{
  public static enum ae$b
    implements j.a
  {
    private static j.b<b> Btk;
    final int value;

    static
    {
      AppMethodBeat.i(120941);
      BvH = new b("IN", 0, 0);
      BvI = new b("OUT", 1, 1);
      BvJ = new b("INV", 2, 2);
      BvK = new b[] { BvH, BvI, BvJ };
      Btk = new a.ae.b.1();
      AppMethodBeat.o(120941);
    }

    private ae$b(int paramInt1, int paramInt2)
    {
      this.value = paramInt1;
    }

    public static b TT(int paramInt)
    {
      b localb;
      switch (paramInt)
      {
      default:
        localb = null;
      case 0:
      case 1:
      case 2:
      }
      while (true)
      {
        return localb;
        localb = BvH;
        continue;
        localb = BvI;
        continue;
        localb = BvJ;
      }
    }

    public final int edd()
    {
      return this.value;
    }
  }

  public static final class ag extends i
    implements a.ah
  {
    public static s<ag> BsC;
    private static final ag BvL;
    private final d BsB;
    private int BsD;
    private byte BsG = (byte)-1;
    private int BsH = -1;
    public List<a.aa> BvM;
    public int BvN;

    static
    {
      AppMethodBeat.i(120976);
      BsC = new a.ag.1();
      ag localag = new ag();
      BvL = localag;
      localag.ecA();
      AppMethodBeat.o(120976);
    }

    private ag()
    {
      this.BsB = d.Bzq;
    }

    // ERROR //
    private ag(a.i.b.a.c.g.e parame, g paramg)
    {
      // Byte code:
      //   0: aload_0
      //   1: invokespecial 54	a/i/b/a/c/g/i:<init>	()V
      //   4: ldc 71
      //   6: invokestatic 36	com/tencent/matrix/trace/core/AppMethodBeat:i	(I)V
      //   9: aload_0
      //   10: iconst_m1
      //   11: i2b
      //   12: putfield 56	a/i/b/a/c/e/a$ag:BsG	B
      //   15: aload_0
      //   16: iconst_m1
      //   17: putfield 58	a/i/b/a/c/e/a$ag:BsH	I
      //   20: aload_0
      //   21: invokespecial 49	a/i/b/a/c/e/a$ag:ecA	()V
      //   24: invokestatic 75	a/i/b/a/c/g/d:ehS	()La/i/b/a/c/g/d$b;
      //   27: astore_3
      //   28: aload_3
      //   29: iconst_1
      //   30: invokestatic 81	a/i/b/a/c/g/f:e	(Ljava/io/OutputStream;I)La/i/b/a/c/g/f;
      //   33: astore 4
      //   35: iconst_0
      //   36: istore 5
      //   38: iconst_0
      //   39: istore 6
      //   41: iload 5
      //   43: ifne +360 -> 403
      //   46: iload 6
      //   48: istore 7
      //   50: iload 6
      //   52: istore 8
      //   54: iload 6
      //   56: istore 9
      //   58: aload_1
      //   59: invokevirtual 87	a/i/b/a/c/g/e:vc	()I
      //   62: istore 10
      //   64: iload 10
      //   66: lookupswitch	default:+34->100, 0:+65->131, 10:+71->137, 16:+247->313
      //   101: iconst_3
      //   102: istore 7
      //   104: iload 6
      //   106: istore 8
      //   108: iload 6
      //   110: istore 9
      //   112: aload_0
      //   113: aload_1
      //   114: aload 4
      //   116: aload_2
      //   117: iload 10
      //   119: invokevirtual 91	a/i/b/a/c/e/a$ag:a	(La/i/b/a/c/g/e;La/i/b/a/c/g/f;La/i/b/a/c/g/g;I)Z
      //   122: ifne -81 -> 41
      //   125: iconst_1
      //   126: istore 5
      //   128: goto -87 -> 41
      //   131: iconst_1
      //   132: istore 5
      //   134: goto -93 -> 41
      //   137: iload 6
      //   139: istore 10
      //   141: iload 6
      //   143: iconst_1
      //   144: iand
      //   145: iconst_1
      //   146: if_icmpeq +61 -> 207
      //   149: iload 6
      //   151: istore 7
      //   153: iload 6
      //   155: istore 8
      //   157: iload 6
      //   159: istore 9
      //   161: new 93	java/util/ArrayList
      //   164: astore 11
      //   166: iload 6
      //   168: istore 7
      //   170: iload 6
      //   172: istore 8
      //   174: iload 6
      //   176: istore 9
      //   178: aload 11
      //   180: invokespecial 94	java/util/ArrayList:<init>	()V
      //   183: iload 6
      //   185: istore 7
      //   187: iload 6
      //   189: istore 8
      //   191: iload 6
      //   193: istore 9
      //   195: aload_0
      //   196: aload 11
      //   198: putfield 96	a/i/b/a/c/e/a$ag:BvM	Ljava/util/List;
      //   201: iload 6
      //   203: iconst_1
      //   204: ior
      //   205: istore 10
      //   207: iload 10
      //   209: istore 7
      //   211: iload 10
      //   213: istore 8
      //   215: iload 10
      //   217: istore 9
      //   219: aload_0
      //   220: getfield 96	a/i/b/a/c/e/a$ag:BvM	Ljava/util/List;
      //   223: aload_1
      //   224: getstatic 99	a/i/b/a/c/e/a$aa:BsC	La/i/b/a/c/g/s;
      //   227: aload_2
      //   228: invokevirtual 102	a/i/b/a/c/g/e:a	(La/i/b/a/c/g/s;La/i/b/a/c/g/g;)La/i/b/a/c/g/q;
      //   231: invokeinterface 108 2 0
      //   236: pop
      //   237: iload 10
      //   239: istore 6
      //   241: goto -200 -> 41
      //   244: astore_1
      //   245: iload 7
      //   247: istore 8
      //   249: aload_1
      //   250: aload_0
      //   251: putfield 112	a/i/b/a/c/g/k:BzY	La/i/b/a/c/g/q;
      //   254: iload 7
      //   256: istore 8
      //   258: ldc 71
      //   260: invokestatic 52	com/tencent/matrix/trace/core/AppMethodBeat:o	(I)V
      //   263: iload 7
      //   265: istore 8
      //   267: aload_1
      //   268: athrow
      //   269: astore_1
      //   270: iload 8
      //   272: iconst_1
      //   273: iand
      //   274: iconst_1
      //   275: if_icmpne +14 -> 289
      //   278: aload_0
      //   279: aload_0
      //   280: getfield 96	a/i/b/a/c/e/a$ag:BvM	Ljava/util/List;
      //   283: invokestatic 118	java/util/Collections:unmodifiableList	(Ljava/util/List;)Ljava/util/List;
      //   286: putfield 96	a/i/b/a/c/e/a$ag:BvM	Ljava/util/List;
      //   289: aload 4
      //   291: invokevirtual 121	a/i/b/a/c/g/f:flush	()V
      //   294: aload_0
      //   295: aload_3
      //   296: invokevirtual 127	a/i/b/a/c/g/d$b:ehW	()La/i/b/a/c/g/d;
      //   299: putfield 65	a/i/b/a/c/e/a$ag:BsB	La/i/b/a/c/g/d;
      //   302: aload_0
      //   303: invokevirtual 130	a/i/b/a/c/e/a$ag:eio	()V
      //   306: ldc 71
      //   308: invokestatic 52	com/tencent/matrix/trace/core/AppMethodBeat:o	(I)V
      //   311: aload_1
      //   312: athrow
      //   313: iload 6
      //   315: istore 7
      //   317: iload 6
      //   319: istore 8
      //   321: iload 6
      //   323: istore 9
      //   325: aload_0
      //   326: aload_0
      //   327: getfield 132	a/i/b/a/c/e/a$ag:BsD	I
      //   330: iconst_1
      //   331: ior
      //   332: putfield 132	a/i/b/a/c/e/a$ag:BsD	I
      //   335: iload 6
      //   337: istore 7
      //   339: iload 6
      //   341: istore 8
      //   343: iload 6
      //   345: istore 9
      //   347: aload_0
      //   348: aload_1
      //   349: invokevirtual 135	a/i/b/a/c/g/e:vd	()I
      //   352: putfield 137	a/i/b/a/c/e/a$ag:BvN	I
      //   355: goto -314 -> 41
      //   358: astore_2
      //   359: iload 9
      //   361: istore 8
      //   363: new 68	a/i/b/a/c/g/k
      //   366: astore_1
      //   367: iload 9
      //   369: istore 8
      //   371: aload_1
      //   372: aload_2
      //   373: invokevirtual 141	java/io/IOException:getMessage	()Ljava/lang/String;
      //   376: invokespecial 144	a/i/b/a/c/g/k:<init>	(Ljava/lang/String;)V
      //   379: iload 9
      //   381: istore 8
      //   383: aload_1
      //   384: aload_0
      //   385: putfield 112	a/i/b/a/c/g/k:BzY	La/i/b/a/c/g/q;
      //   388: iload 9
      //   390: istore 8
      //   392: ldc 71
      //   394: invokestatic 52	com/tencent/matrix/trace/core/AppMethodBeat:o	(I)V
      //   397: iload 9
      //   399: istore 8
      //   401: aload_1
      //   402: athrow
      //   403: iload 6
      //   405: iconst_1
      //   406: iand
      //   407: iconst_1
      //   408: if_icmpne +14 -> 422
      //   411: aload_0
      //   412: aload_0
      //   413: getfield 96	a/i/b/a/c/e/a$ag:BvM	Ljava/util/List;
      //   416: invokestatic 118	java/util/Collections:unmodifiableList	(Ljava/util/List;)Ljava/util/List;
      //   419: putfield 96	a/i/b/a/c/e/a$ag:BvM	Ljava/util/List;
      //   422: aload 4
      //   424: invokevirtual 121	a/i/b/a/c/g/f:flush	()V
      //   427: aload_0
      //   428: aload_3
      //   429: invokevirtual 127	a/i/b/a/c/g/d$b:ehW	()La/i/b/a/c/g/d;
      //   432: putfield 65	a/i/b/a/c/e/a$ag:BsB	La/i/b/a/c/g/d;
      //   435: aload_0
      //   436: invokevirtual 130	a/i/b/a/c/e/a$ag:eio	()V
      //   439: ldc 71
      //   441: invokestatic 52	com/tencent/matrix/trace/core/AppMethodBeat:o	(I)V
      //   444: return
      //   445: astore_1
      //   446: aload_0
      //   447: aload_3
      //   448: invokevirtual 127	a/i/b/a/c/g/d$b:ehW	()La/i/b/a/c/g/d;
      //   451: putfield 65	a/i/b/a/c/e/a$ag:BsB	La/i/b/a/c/g/d;
      //   454: goto -19 -> 435
      //   457: astore_1
      //   458: aload_0
      //   459: aload_3
      //   460: invokevirtual 127	a/i/b/a/c/g/d$b:ehW	()La/i/b/a/c/g/d;
      //   463: putfield 65	a/i/b/a/c/e/a$ag:BsB	La/i/b/a/c/g/d;
      //   466: ldc 71
      //   468: invokestatic 52	com/tencent/matrix/trace/core/AppMethodBeat:o	(I)V
      //   471: aload_1
      //   472: athrow
      //   473: astore_2
      //   474: aload_0
      //   475: aload_3
      //   476: invokevirtual 127	a/i/b/a/c/g/d$b:ehW	()La/i/b/a/c/g/d;
      //   479: putfield 65	a/i/b/a/c/e/a$ag:BsB	La/i/b/a/c/g/d;
      //   482: goto -180 -> 302
      //   485: astore_1
      //   486: aload_0
      //   487: aload_3
      //   488: invokevirtual 127	a/i/b/a/c/g/d$b:ehW	()La/i/b/a/c/g/d;
      //   491: putfield 65	a/i/b/a/c/e/a$ag:BsB	La/i/b/a/c/g/d;
      //   494: ldc 71
      //   496: invokestatic 52	com/tencent/matrix/trace/core/AppMethodBeat:o	(I)V
      //   499: aload_1
      //   500: athrow
      //
      // Exception table:
      //   from	to	target	type
      //   58	64	244	a/i/b/a/c/g/k
      //   112	125	244	a/i/b/a/c/g/k
      //   161	166	244	a/i/b/a/c/g/k
      //   178	183	244	a/i/b/a/c/g/k
      //   195	201	244	a/i/b/a/c/g/k
      //   219	237	244	a/i/b/a/c/g/k
      //   325	335	244	a/i/b/a/c/g/k
      //   347	355	244	a/i/b/a/c/g/k
      //   58	64	269	finally
      //   112	125	269	finally
      //   161	166	269	finally
      //   178	183	269	finally
      //   195	201	269	finally
      //   219	237	269	finally
      //   249	254	269	finally
      //   258	263	269	finally
      //   267	269	269	finally
      //   325	335	269	finally
      //   347	355	269	finally
      //   363	367	269	finally
      //   371	379	269	finally
      //   383	388	269	finally
      //   392	397	269	finally
      //   401	403	269	finally
      //   58	64	358	java/io/IOException
      //   112	125	358	java/io/IOException
      //   161	166	358	java/io/IOException
      //   178	183	358	java/io/IOException
      //   195	201	358	java/io/IOException
      //   219	237	358	java/io/IOException
      //   325	335	358	java/io/IOException
      //   347	355	358	java/io/IOException
      //   422	427	445	java/io/IOException
      //   422	427	457	finally
      //   289	294	473	java/io/IOException
      //   289	294	485	finally
    }

    private ag(i.a parama)
    {
      super();
      this.BsB = parama.BsB;
    }

    public static a.ag.a d(ag paramag)
    {
      AppMethodBeat.i(120973);
      paramag = a.ag.a.efR().g(paramag);
      AppMethodBeat.o(120973);
      return paramag;
    }

    private void ecA()
    {
      AppMethodBeat.i(120969);
      this.BvM = Collections.emptyList();
      this.BvN = -1;
      AppMethodBeat.o(120969);
    }

    public static ag efM()
    {
      return BvL;
    }

    public final void a(f paramf)
    {
      AppMethodBeat.i(120971);
      vq();
      for (int i = 0; i < this.BvM.size(); i++)
        paramf.a(1, (q)this.BvM.get(i));
      if ((this.BsD & 0x1) == 1)
        paramf.bq(2, this.BvN);
      paramf.d(this.BsB);
      AppMethodBeat.o(120971);
    }

    public final s<ag> ecy()
    {
      return BsC;
    }

    public final boolean efN()
    {
      boolean bool = true;
      if ((this.BsD & 0x1) == 1);
      while (true)
      {
        return bool;
        bool = false;
      }
    }

    public final boolean isInitialized()
    {
      boolean bool = false;
      AppMethodBeat.i(120970);
      int i = this.BsG;
      if (i == 1)
      {
        AppMethodBeat.o(120970);
        bool = true;
      }
      while (true)
      {
        return bool;
        if (i == 0)
        {
          AppMethodBeat.o(120970);
        }
        else
        {
          for (i = 0; ; i++)
          {
            if (i >= this.BvM.size())
              break label92;
            if (!((a.aa)this.BvM.get(i)).isInitialized())
            {
              this.BsG = ((byte)0);
              AppMethodBeat.o(120970);
              break;
            }
          }
          label92: this.BsG = ((byte)1);
          AppMethodBeat.o(120970);
          bool = true;
        }
      }
    }

    public final int vq()
    {
      AppMethodBeat.i(120972);
      int i = this.BsH;
      if (i != -1)
        AppMethodBeat.o(120972);
      while (true)
      {
        return i;
        int j = 0;
        i = 0;
        while (j < this.BvM.size())
        {
          i += f.c(1, (q)this.BvM.get(j));
          j++;
        }
        j = i;
        if ((this.BsD & 0x1) == 1)
          j = i + f.bs(2, this.BvN);
        i = this.BsB.size() + j;
        this.BsH = i;
        AppMethodBeat.o(120972);
      }
    }
  }

  public static final class c extends i.c<c>
    implements a.d
  {
    public static s<c> BsC;
    private static final c Btm;
    private final d BsB;
    private int BsD;
    private byte BsG = (byte)-1;
    private int BsH = -1;
    public int BsW;
    public List<Integer> BtA;
    private int BtB = -1;
    public a.ag BtC;
    public List<Integer> BtD;
    public a.am BtE;
    public int Btn;
    public int Bto;
    public List<a.ae> Btp;
    public List<a.aa> Btq;
    public List<Integer> Btr;
    private int Bts = -1;
    public List<Integer> Btt;
    private int Btu = -1;
    public List<a.e> Btv;
    public List<a.o> Btw;
    public List<a.u> Btx;
    public List<a.ab> Bty;
    public List<a.k> Btz;

    static
    {
      AppMethodBeat.i(120484);
      BsC = new a.c.1();
      c localc = new c();
      Btm = localc;
      localc.ecA();
      AppMethodBeat.o(120484);
    }

    private c()
    {
      this.BsB = d.Bzq;
    }

    // ERROR //
    private c(a.i.b.a.c.g.e parame, g paramg)
    {
      // Byte code:
      //   0: aload_0
      //   1: invokespecial 83	a/i/b/a/c/g/i$c:<init>	()V
      //   4: ldc 106
      //   6: invokestatic 65	com/tencent/matrix/trace/core/AppMethodBeat:i	(I)V
      //   9: aload_0
      //   10: iconst_m1
      //   11: putfield 85	a/i/b/a/c/e/a$c:Bts	I
      //   14: aload_0
      //   15: iconst_m1
      //   16: putfield 87	a/i/b/a/c/e/a$c:Btu	I
      //   19: aload_0
      //   20: iconst_m1
      //   21: putfield 89	a/i/b/a/c/e/a$c:BtB	I
      //   24: aload_0
      //   25: iconst_m1
      //   26: i2b
      //   27: putfield 91	a/i/b/a/c/e/a$c:BsG	B
      //   30: aload_0
      //   31: iconst_m1
      //   32: putfield 93	a/i/b/a/c/e/a$c:BsH	I
      //   35: aload_0
      //   36: invokespecial 78	a/i/b/a/c/e/a$c:ecA	()V
      //   39: iconst_0
      //   40: istore_3
      //   41: invokestatic 110	a/i/b/a/c/g/d:ehS	()La/i/b/a/c/g/d$b;
      //   44: astore 4
      //   46: aload 4
      //   48: iconst_1
      //   49: invokestatic 116	a/i/b/a/c/g/f:e	(Ljava/io/OutputStream;I)La/i/b/a/c/g/f;
      //   52: astore 5
      //   54: iconst_0
      //   55: istore 6
      //   57: iload 6
      //   59: ifne +2734 -> 2793
      //   62: iload_3
      //   63: istore 7
      //   65: iload_3
      //   66: istore 8
      //   68: iload_3
      //   69: istore 9
      //   71: aload_1
      //   72: invokevirtual 122	a/i/b/a/c/g/e:vc	()I
      //   75: istore 10
      //   77: iload 10
      //   79: lookupswitch	default:+177->256, 0:+205->284, 8:+211->290, 16:+549->628, 18:+690->769, 24:+864->943, 32:+903->982, 42:+942->1021, 50:+1039->1118, 56:+1136->1215, 58:+1232->1311, 66:+1406->1485, 74:+1506->1585, 82:+1606->1685, 90:+1706->1785, 106:+1806->1885, 128:+1906->1985, 130:+2005->2084, 242:+2182->2261, 248:+2310->2389, 250:+2409->2488, 258:+2586->2665
      //   257: istore 7
      //   259: iload_3
      //   260: istore 8
      //   262: iload_3
      //   263: istore 9
      //   265: aload_0
      //   266: aload_1
      //   267: aload 5
      //   269: aload_2
      //   270: iload 10
      //   272: invokevirtual 126	a/i/b/a/c/e/a$c:a	(La/i/b/a/c/g/e;La/i/b/a/c/g/f;La/i/b/a/c/g/g;I)Z
      //   275: ifne -218 -> 57
      //   278: iconst_1
      //   279: istore 6
      //   281: goto -224 -> 57
      //   284: iconst_1
      //   285: istore 6
      //   287: goto -230 -> 57
      //   290: iload_3
      //   291: istore 7
      //   293: iload_3
      //   294: istore 8
      //   296: iload_3
      //   297: istore 9
      //   299: aload_0
      //   300: aload_0
      //   301: getfield 128	a/i/b/a/c/e/a$c:BsD	I
      //   304: iconst_1
      //   305: ior
      //   306: putfield 128	a/i/b/a/c/e/a$c:BsD	I
      //   309: iload_3
      //   310: istore 7
      //   312: iload_3
      //   313: istore 8
      //   315: iload_3
      //   316: istore 9
      //   318: aload_0
      //   319: aload_1
      //   320: invokevirtual 131	a/i/b/a/c/g/e:vd	()I
      //   323: putfield 133	a/i/b/a/c/e/a$c:BsW	I
      //   326: goto -269 -> 57
      //   329: astore_1
      //   330: iload 7
      //   332: istore 8
      //   334: aload_1
      //   335: aload_0
      //   336: putfield 137	a/i/b/a/c/g/k:BzY	La/i/b/a/c/g/q;
      //   339: iload 7
      //   341: istore 8
      //   343: ldc 106
      //   345: invokestatic 81	com/tencent/matrix/trace/core/AppMethodBeat:o	(I)V
      //   348: iload 7
      //   350: istore 8
      //   352: aload_1
      //   353: athrow
      //   354: astore_1
      //   355: iload 8
      //   357: bipush 32
      //   359: iand
      //   360: bipush 32
      //   362: if_icmpne +14 -> 376
      //   365: aload_0
      //   366: aload_0
      //   367: getfield 139	a/i/b/a/c/e/a$c:Btr	Ljava/util/List;
      //   370: invokestatic 145	java/util/Collections:unmodifiableList	(Ljava/util/List;)Ljava/util/List;
      //   373: putfield 139	a/i/b/a/c/e/a$c:Btr	Ljava/util/List;
      //   376: iload 8
      //   378: bipush 8
      //   380: iand
      //   381: bipush 8
      //   383: if_icmpne +14 -> 397
      //   386: aload_0
      //   387: aload_0
      //   388: getfield 147	a/i/b/a/c/e/a$c:Btp	Ljava/util/List;
      //   391: invokestatic 145	java/util/Collections:unmodifiableList	(Ljava/util/List;)Ljava/util/List;
      //   394: putfield 147	a/i/b/a/c/e/a$c:Btp	Ljava/util/List;
      //   397: iload 8
      //   399: bipush 16
      //   401: iand
      //   402: bipush 16
      //   404: if_icmpne +14 -> 418
      //   407: aload_0
      //   408: aload_0
      //   409: getfield 149	a/i/b/a/c/e/a$c:Btq	Ljava/util/List;
      //   412: invokestatic 145	java/util/Collections:unmodifiableList	(Ljava/util/List;)Ljava/util/List;
      //   415: putfield 149	a/i/b/a/c/e/a$c:Btq	Ljava/util/List;
      //   418: iload 8
      //   420: bipush 64
      //   422: iand
      //   423: bipush 64
      //   425: if_icmpne +14 -> 439
      //   428: aload_0
      //   429: aload_0
      //   430: getfield 151	a/i/b/a/c/e/a$c:Btt	Ljava/util/List;
      //   433: invokestatic 145	java/util/Collections:unmodifiableList	(Ljava/util/List;)Ljava/util/List;
      //   436: putfield 151	a/i/b/a/c/e/a$c:Btt	Ljava/util/List;
      //   439: iload 8
      //   441: sipush 128
      //   444: iand
      //   445: sipush 128
      //   448: if_icmpne +14 -> 462
      //   451: aload_0
      //   452: aload_0
      //   453: getfield 153	a/i/b/a/c/e/a$c:Btv	Ljava/util/List;
      //   456: invokestatic 145	java/util/Collections:unmodifiableList	(Ljava/util/List;)Ljava/util/List;
      //   459: putfield 153	a/i/b/a/c/e/a$c:Btv	Ljava/util/List;
      //   462: iload 8
      //   464: sipush 256
      //   467: iand
      //   468: sipush 256
      //   471: if_icmpne +14 -> 485
      //   474: aload_0
      //   475: aload_0
      //   476: getfield 155	a/i/b/a/c/e/a$c:Btw	Ljava/util/List;
      //   479: invokestatic 145	java/util/Collections:unmodifiableList	(Ljava/util/List;)Ljava/util/List;
      //   482: putfield 155	a/i/b/a/c/e/a$c:Btw	Ljava/util/List;
      //   485: iload 8
      //   487: sipush 512
      //   490: iand
      //   491: sipush 512
      //   494: if_icmpne +14 -> 508
      //   497: aload_0
      //   498: aload_0
      //   499: getfield 157	a/i/b/a/c/e/a$c:Btx	Ljava/util/List;
      //   502: invokestatic 145	java/util/Collections:unmodifiableList	(Ljava/util/List;)Ljava/util/List;
      //   505: putfield 157	a/i/b/a/c/e/a$c:Btx	Ljava/util/List;
      //   508: iload 8
      //   510: sipush 1024
      //   513: iand
      //   514: sipush 1024
      //   517: if_icmpne +14 -> 531
      //   520: aload_0
      //   521: aload_0
      //   522: getfield 159	a/i/b/a/c/e/a$c:Bty	Ljava/util/List;
      //   525: invokestatic 145	java/util/Collections:unmodifiableList	(Ljava/util/List;)Ljava/util/List;
      //   528: putfield 159	a/i/b/a/c/e/a$c:Bty	Ljava/util/List;
      //   531: iload 8
      //   533: sipush 2048
      //   536: iand
      //   537: sipush 2048
      //   540: if_icmpne +14 -> 554
      //   543: aload_0
      //   544: aload_0
      //   545: getfield 161	a/i/b/a/c/e/a$c:Btz	Ljava/util/List;
      //   548: invokestatic 145	java/util/Collections:unmodifiableList	(Ljava/util/List;)Ljava/util/List;
      //   551: putfield 161	a/i/b/a/c/e/a$c:Btz	Ljava/util/List;
      //   554: iload 8
      //   556: sipush 4096
      //   559: iand
      //   560: sipush 4096
      //   563: if_icmpne +14 -> 577
      //   566: aload_0
      //   567: aload_0
      //   568: getfield 163	a/i/b/a/c/e/a$c:BtA	Ljava/util/List;
      //   571: invokestatic 145	java/util/Collections:unmodifiableList	(Ljava/util/List;)Ljava/util/List;
      //   574: putfield 163	a/i/b/a/c/e/a$c:BtA	Ljava/util/List;
      //   577: iload 8
      //   579: sipush 16384
      //   582: iand
      //   583: sipush 16384
      //   586: if_icmpne +14 -> 600
      //   589: aload_0
      //   590: aload_0
      //   591: getfield 165	a/i/b/a/c/e/a$c:BtD	Ljava/util/List;
      //   594: invokestatic 145	java/util/Collections:unmodifiableList	(Ljava/util/List;)Ljava/util/List;
      //   597: putfield 165	a/i/b/a/c/e/a$c:BtD	Ljava/util/List;
      //   600: aload 5
      //   602: invokevirtual 168	a/i/b/a/c/g/f:flush	()V
      //   605: aload_0
      //   606: aload 4
      //   608: invokevirtual 174	a/i/b/a/c/g/d$b:ehW	()La/i/b/a/c/g/d;
      //   611: putfield 100	a/i/b/a/c/e/a$c:BsB	La/i/b/a/c/g/d;
      //   614: aload_0
      //   615: getfield 178	a/i/b/a/c/g/i$c:BzI	La/i/b/a/c/g/h;
      //   618: invokevirtual 183	a/i/b/a/c/g/h:eii	()V
      //   621: ldc 106
      //   623: invokestatic 81	com/tencent/matrix/trace/core/AppMethodBeat:o	(I)V
      //   626: aload_1
      //   627: athrow
      //   628: iload_3
      //   629: istore 10
      //   631: iload_3
      //   632: bipush 32
      //   634: iand
      //   635: bipush 32
      //   637: if_icmpeq +52 -> 689
      //   640: iload_3
      //   641: istore 7
      //   643: iload_3
      //   644: istore 8
      //   646: iload_3
      //   647: istore 9
      //   649: new 185	java/util/ArrayList
      //   652: astore 11
      //   654: iload_3
      //   655: istore 7
      //   657: iload_3
      //   658: istore 8
      //   660: iload_3
      //   661: istore 9
      //   663: aload 11
      //   665: invokespecial 186	java/util/ArrayList:<init>	()V
      //   668: iload_3
      //   669: istore 7
      //   671: iload_3
      //   672: istore 8
      //   674: iload_3
      //   675: istore 9
      //   677: aload_0
      //   678: aload 11
      //   680: putfield 139	a/i/b/a/c/e/a$c:Btr	Ljava/util/List;
      //   683: iload_3
      //   684: bipush 32
      //   686: ior
      //   687: istore 10
      //   689: iload 10
      //   691: istore 7
      //   693: iload 10
      //   695: istore 8
      //   697: iload 10
      //   699: istore 9
      //   701: aload_0
      //   702: getfield 139	a/i/b/a/c/e/a$c:Btr	Ljava/util/List;
      //   705: aload_1
      //   706: invokevirtual 131	a/i/b/a/c/g/e:vd	()I
      //   709: invokestatic 192	java/lang/Integer:valueOf	(I)Ljava/lang/Integer;
      //   712: invokeinterface 198 2 0
      //   717: pop
      //   718: iload 10
      //   720: istore_3
      //   721: goto -664 -> 57
      //   724: astore_2
      //   725: iload 9
      //   727: istore 8
      //   729: new 103	a/i/b/a/c/g/k
      //   732: astore_1
      //   733: iload 9
      //   735: istore 8
      //   737: aload_1
      //   738: aload_2
      //   739: invokevirtual 202	java/io/IOException:getMessage	()Ljava/lang/String;
      //   742: invokespecial 205	a/i/b/a/c/g/k:<init>	(Ljava/lang/String;)V
      //   745: iload 9
      //   747: istore 8
      //   749: aload_1
      //   750: aload_0
      //   751: putfield 137	a/i/b/a/c/g/k:BzY	La/i/b/a/c/g/q;
      //   754: iload 9
      //   756: istore 8
      //   758: ldc 106
      //   760: invokestatic 81	com/tencent/matrix/trace/core/AppMethodBeat:o	(I)V
      //   763: iload 9
      //   765: istore 8
      //   767: aload_1
      //   768: athrow
      //   769: iload_3
      //   770: istore 7
      //   772: iload_3
      //   773: istore 8
      //   775: iload_3
      //   776: istore 9
      //   778: aload_1
      //   779: aload_1
      //   780: invokevirtual 131	a/i/b/a/c/g/e:vd	()I
      //   783: invokevirtual 209	a/i/b/a/c/g/e:fo	(I)I
      //   786: istore 12
      //   788: iload_3
      //   789: istore 10
      //   791: iload_3
      //   792: bipush 32
      //   794: iand
      //   795: bipush 32
      //   797: if_icmpeq +71 -> 868
      //   800: iload_3
      //   801: istore 7
      //   803: iload_3
      //   804: istore 8
      //   806: iload_3
      //   807: istore 9
      //   809: iload_3
      //   810: istore 10
      //   812: aload_1
      //   813: invokevirtual 212	a/i/b/a/c/g/e:vg	()I
      //   816: ifle +52 -> 868
      //   819: iload_3
      //   820: istore 7
      //   822: iload_3
      //   823: istore 8
      //   825: iload_3
      //   826: istore 9
      //   828: new 185	java/util/ArrayList
      //   831: astore 11
      //   833: iload_3
      //   834: istore 7
      //   836: iload_3
      //   837: istore 8
      //   839: iload_3
      //   840: istore 9
      //   842: aload 11
      //   844: invokespecial 186	java/util/ArrayList:<init>	()V
      //   847: iload_3
      //   848: istore 7
      //   850: iload_3
      //   851: istore 8
      //   853: iload_3
      //   854: istore 9
      //   856: aload_0
      //   857: aload 11
      //   859: putfield 139	a/i/b/a/c/e/a$c:Btr	Ljava/util/List;
      //   862: iload_3
      //   863: bipush 32
      //   865: ior
      //   866: istore 10
      //   868: iload 10
      //   870: istore 7
      //   872: iload 10
      //   874: istore 8
      //   876: iload 10
      //   878: istore 9
      //   880: aload_1
      //   881: invokevirtual 212	a/i/b/a/c/g/e:vg	()I
      //   884: ifle +35 -> 919
      //   887: iload 10
      //   889: istore 7
      //   891: iload 10
      //   893: istore 8
      //   895: iload 10
      //   897: istore 9
      //   899: aload_0
      //   900: getfield 139	a/i/b/a/c/e/a$c:Btr	Ljava/util/List;
      //   903: aload_1
      //   904: invokevirtual 131	a/i/b/a/c/g/e:vd	()I
      //   907: invokestatic 192	java/lang/Integer:valueOf	(I)Ljava/lang/Integer;
      //   910: invokeinterface 198 2 0
      //   915: pop
      //   916: goto -48 -> 868
      //   919: iload 10
      //   921: istore 7
      //   923: iload 10
      //   925: istore 8
      //   927: iload 10
      //   929: istore 9
      //   931: aload_1
      //   932: iload 12
      //   934: invokevirtual 215	a/i/b/a/c/g/e:fp	(I)V
      //   937: iload 10
      //   939: istore_3
      //   940: goto -883 -> 57
      //   943: iload_3
      //   944: istore 7
      //   946: iload_3
      //   947: istore 8
      //   949: iload_3
      //   950: istore 9
      //   952: aload_0
      //   953: aload_0
      //   954: getfield 128	a/i/b/a/c/e/a$c:BsD	I
      //   957: iconst_2
      //   958: ior
      //   959: putfield 128	a/i/b/a/c/e/a$c:BsD	I
      //   962: iload_3
      //   963: istore 7
      //   965: iload_3
      //   966: istore 8
      //   968: iload_3
      //   969: istore 9
      //   971: aload_0
      //   972: aload_1
      //   973: invokevirtual 131	a/i/b/a/c/g/e:vd	()I
      //   976: putfield 217	a/i/b/a/c/e/a$c:Btn	I
      //   979: goto -922 -> 57
      //   982: iload_3
      //   983: istore 7
      //   985: iload_3
      //   986: istore 8
      //   988: iload_3
      //   989: istore 9
      //   991: aload_0
      //   992: aload_0
      //   993: getfield 128	a/i/b/a/c/e/a$c:BsD	I
      //   996: iconst_4
      //   997: ior
      //   998: putfield 128	a/i/b/a/c/e/a$c:BsD	I
      //   1001: iload_3
      //   1002: istore 7
      //   1004: iload_3
      //   1005: istore 8
      //   1007: iload_3
      //   1008: istore 9
      //   1010: aload_0
      //   1011: aload_1
      //   1012: invokevirtual 131	a/i/b/a/c/g/e:vd	()I
      //   1015: putfield 219	a/i/b/a/c/e/a$c:Bto	I
      //   1018: goto -961 -> 57
      //   1021: iload_3
      //   1022: istore 10
      //   1024: iload_3
      //   1025: bipush 8
      //   1027: iand
      //   1028: bipush 8
      //   1030: if_icmpeq +52 -> 1082
      //   1033: iload_3
      //   1034: istore 7
      //   1036: iload_3
      //   1037: istore 8
      //   1039: iload_3
      //   1040: istore 9
      //   1042: new 185	java/util/ArrayList
      //   1045: astore 11
      //   1047: iload_3
      //   1048: istore 7
      //   1050: iload_3
      //   1051: istore 8
      //   1053: iload_3
      //   1054: istore 9
      //   1056: aload 11
      //   1058: invokespecial 186	java/util/ArrayList:<init>	()V
      //   1061: iload_3
      //   1062: istore 7
      //   1064: iload_3
      //   1065: istore 8
      //   1067: iload_3
      //   1068: istore 9
      //   1070: aload_0
      //   1071: aload 11
      //   1073: putfield 147	a/i/b/a/c/e/a$c:Btp	Ljava/util/List;
      //   1076: iload_3
      //   1077: bipush 8
      //   1079: ior
      //   1080: istore 10
      //   1082: iload 10
      //   1084: istore 7
      //   1086: iload 10
      //   1088: istore 8
      //   1090: iload 10
      //   1092: istore 9
      //   1094: aload_0
      //   1095: getfield 147	a/i/b/a/c/e/a$c:Btp	Ljava/util/List;
      //   1098: aload_1
      //   1099: getstatic 222	a/i/b/a/c/e/a$ae:BsC	La/i/b/a/c/g/s;
      //   1102: aload_2
      //   1103: invokevirtual 225	a/i/b/a/c/g/e:a	(La/i/b/a/c/g/s;La/i/b/a/c/g/g;)La/i/b/a/c/g/q;
      //   1106: invokeinterface 198 2 0
      //   1111: pop
      //   1112: iload 10
      //   1114: istore_3
      //   1115: goto -1058 -> 57
      //   1118: iload_3
      //   1119: istore 10
      //   1121: iload_3
      //   1122: bipush 16
      //   1124: iand
      //   1125: bipush 16
      //   1127: if_icmpeq +52 -> 1179
      //   1130: iload_3
      //   1131: istore 7
      //   1133: iload_3
      //   1134: istore 8
      //   1136: iload_3
      //   1137: istore 9
      //   1139: new 185	java/util/ArrayList
      //   1142: astore 11
      //   1144: iload_3
      //   1145: istore 7
      //   1147: iload_3
      //   1148: istore 8
      //   1150: iload_3
      //   1151: istore 9
      //   1153: aload 11
      //   1155: invokespecial 186	java/util/ArrayList:<init>	()V
      //   1158: iload_3
      //   1159: istore 7
      //   1161: iload_3
      //   1162: istore 8
      //   1164: iload_3
      //   1165: istore 9
      //   1167: aload_0
      //   1168: aload 11
      //   1170: putfield 149	a/i/b/a/c/e/a$c:Btq	Ljava/util/List;
      //   1173: iload_3
      //   1174: bipush 16
      //   1176: ior
      //   1177: istore 10
      //   1179: iload 10
      //   1181: istore 7
      //   1183: iload 10
      //   1185: istore 8
      //   1187: iload 10
      //   1189: istore 9
      //   1191: aload_0
      //   1192: getfield 149	a/i/b/a/c/e/a$c:Btq	Ljava/util/List;
      //   1195: aload_1
      //   1196: getstatic 228	a/i/b/a/c/e/a$aa:BsC	La/i/b/a/c/g/s;
      //   1199: aload_2
      //   1200: invokevirtual 225	a/i/b/a/c/g/e:a	(La/i/b/a/c/g/s;La/i/b/a/c/g/g;)La/i/b/a/c/g/q;
      //   1203: invokeinterface 198 2 0
      //   1208: pop
      //   1209: iload 10
      //   1211: istore_3
      //   1212: goto -1155 -> 57
      //   1215: iload_3
      //   1216: istore 10
      //   1218: iload_3
      //   1219: bipush 64
      //   1221: iand
      //   1222: bipush 64
      //   1224: if_icmpeq +52 -> 1276
      //   1227: iload_3
      //   1228: istore 7
      //   1230: iload_3
      //   1231: istore 8
      //   1233: iload_3
      //   1234: istore 9
      //   1236: new 185	java/util/ArrayList
      //   1239: astore 11
      //   1241: iload_3
      //   1242: istore 7
      //   1244: iload_3
      //   1245: istore 8
      //   1247: iload_3
      //   1248: istore 9
      //   1250: aload 11
      //   1252: invokespecial 186	java/util/ArrayList:<init>	()V
      //   1255: iload_3
      //   1256: istore 7
      //   1258: iload_3
      //   1259: istore 8
      //   1261: iload_3
      //   1262: istore 9
      //   1264: aload_0
      //   1265: aload 11
      //   1267: putfield 151	a/i/b/a/c/e/a$c:Btt	Ljava/util/List;
      //   1270: iload_3
      //   1271: bipush 64
      //   1273: ior
      //   1274: istore 10
      //   1276: iload 10
      //   1278: istore 7
      //   1280: iload 10
      //   1282: istore 8
      //   1284: iload 10
      //   1286: istore 9
      //   1288: aload_0
      //   1289: getfield 151	a/i/b/a/c/e/a$c:Btt	Ljava/util/List;
      //   1292: aload_1
      //   1293: invokevirtual 131	a/i/b/a/c/g/e:vd	()I
      //   1296: invokestatic 192	java/lang/Integer:valueOf	(I)Ljava/lang/Integer;
      //   1299: invokeinterface 198 2 0
      //   1304: pop
      //   1305: iload 10
      //   1307: istore_3
      //   1308: goto -1251 -> 57
      //   1311: iload_3
      //   1312: istore 7
      //   1314: iload_3
      //   1315: istore 8
      //   1317: iload_3
      //   1318: istore 9
      //   1320: aload_1
      //   1321: aload_1
      //   1322: invokevirtual 131	a/i/b/a/c/g/e:vd	()I
      //   1325: invokevirtual 209	a/i/b/a/c/g/e:fo	(I)I
      //   1328: istore 12
      //   1330: iload_3
      //   1331: istore 10
      //   1333: iload_3
      //   1334: bipush 64
      //   1336: iand
      //   1337: bipush 64
      //   1339: if_icmpeq +71 -> 1410
      //   1342: iload_3
      //   1343: istore 7
      //   1345: iload_3
      //   1346: istore 8
      //   1348: iload_3
      //   1349: istore 9
      //   1351: iload_3
      //   1352: istore 10
      //   1354: aload_1
      //   1355: invokevirtual 212	a/i/b/a/c/g/e:vg	()I
      //   1358: ifle +52 -> 1410
      //   1361: iload_3
      //   1362: istore 7
      //   1364: iload_3
      //   1365: istore 8
      //   1367: iload_3
      //   1368: istore 9
      //   1370: new 185	java/util/ArrayList
      //   1373: astore 11
      //   1375: iload_3
      //   1376: istore 7
      //   1378: iload_3
      //   1379: istore 8
      //   1381: iload_3
      //   1382: istore 9
      //   1384: aload 11
      //   1386: invokespecial 186	java/util/ArrayList:<init>	()V
      //   1389: iload_3
      //   1390: istore 7
      //   1392: iload_3
      //   1393: istore 8
      //   1395: iload_3
      //   1396: istore 9
      //   1398: aload_0
      //   1399: aload 11
      //   1401: putfield 151	a/i/b/a/c/e/a$c:Btt	Ljava/util/List;
      //   1404: iload_3
      //   1405: bipush 64
      //   1407: ior
      //   1408: istore 10
      //   1410: iload 10
      //   1412: istore 7
      //   1414: iload 10
      //   1416: istore 8
      //   1418: iload 10
      //   1420: istore 9
      //   1422: aload_1
      //   1423: invokevirtual 212	a/i/b/a/c/g/e:vg	()I
      //   1426: ifle +35 -> 1461
      //   1429: iload 10
      //   1431: istore 7
      //   1433: iload 10
      //   1435: istore 8
      //   1437: iload 10
      //   1439: istore 9
      //   1441: aload_0
      //   1442: getfield 151	a/i/b/a/c/e/a$c:Btt	Ljava/util/List;
      //   1445: aload_1
      //   1446: invokevirtual 131	a/i/b/a/c/g/e:vd	()I
      //   1449: invokestatic 192	java/lang/Integer:valueOf	(I)Ljava/lang/Integer;
      //   1452: invokeinterface 198 2 0
      //   1457: pop
      //   1458: goto -48 -> 1410
      //   1461: iload 10
      //   1463: istore 7
      //   1465: iload 10
      //   1467: istore 8
      //   1469: iload 10
      //   1471: istore 9
      //   1473: aload_1
      //   1474: iload 12
      //   1476: invokevirtual 215	a/i/b/a/c/g/e:fp	(I)V
      //   1479: iload 10
      //   1481: istore_3
      //   1482: goto -1425 -> 57
      //   1485: iload_3
      //   1486: istore 10
      //   1488: iload_3
      //   1489: sipush 128
      //   1492: iand
      //   1493: sipush 128
      //   1496: if_icmpeq +53 -> 1549
      //   1499: iload_3
      //   1500: istore 7
      //   1502: iload_3
      //   1503: istore 8
      //   1505: iload_3
      //   1506: istore 9
      //   1508: new 185	java/util/ArrayList
      //   1511: astore 11
      //   1513: iload_3
      //   1514: istore 7
      //   1516: iload_3
      //   1517: istore 8
      //   1519: iload_3
      //   1520: istore 9
      //   1522: aload 11
      //   1524: invokespecial 186	java/util/ArrayList:<init>	()V
      //   1527: iload_3
      //   1528: istore 7
      //   1530: iload_3
      //   1531: istore 8
      //   1533: iload_3
      //   1534: istore 9
      //   1536: aload_0
      //   1537: aload 11
      //   1539: putfield 153	a/i/b/a/c/e/a$c:Btv	Ljava/util/List;
      //   1542: iload_3
      //   1543: sipush 128
      //   1546: ior
      //   1547: istore 10
      //   1549: iload 10
      //   1551: istore 7
      //   1553: iload 10
      //   1555: istore 8
      //   1557: iload 10
      //   1559: istore 9
      //   1561: aload_0
      //   1562: getfield 153	a/i/b/a/c/e/a$c:Btv	Ljava/util/List;
      //   1565: aload_1
      //   1566: getstatic 231	a/i/b/a/c/e/a$e:BsC	La/i/b/a/c/g/s;
      //   1569: aload_2
      //   1570: invokevirtual 225	a/i/b/a/c/g/e:a	(La/i/b/a/c/g/s;La/i/b/a/c/g/g;)La/i/b/a/c/g/q;
      //   1573: invokeinterface 198 2 0
      //   1578: pop
      //   1579: iload 10
      //   1581: istore_3
      //   1582: goto -1525 -> 57
      //   1585: iload_3
      //   1586: istore 10
      //   1588: iload_3
      //   1589: sipush 256
      //   1592: iand
      //   1593: sipush 256
      //   1596: if_icmpeq +53 -> 1649
      //   1599: iload_3
      //   1600: istore 7
      //   1602: iload_3
      //   1603: istore 8
      //   1605: iload_3
      //   1606: istore 9
      //   1608: new 185	java/util/ArrayList
      //   1611: astore 11
      //   1613: iload_3
      //   1614: istore 7
      //   1616: iload_3
      //   1617: istore 8
      //   1619: iload_3
      //   1620: istore 9
      //   1622: aload 11
      //   1624: invokespecial 186	java/util/ArrayList:<init>	()V
      //   1627: iload_3
      //   1628: istore 7
      //   1630: iload_3
      //   1631: istore 8
      //   1633: iload_3
      //   1634: istore 9
      //   1636: aload_0
      //   1637: aload 11
      //   1639: putfield 155	a/i/b/a/c/e/a$c:Btw	Ljava/util/List;
      //   1642: iload_3
      //   1643: sipush 256
      //   1646: ior
      //   1647: istore 10
      //   1649: iload 10
      //   1651: istore 7
      //   1653: iload 10
      //   1655: istore 8
      //   1657: iload 10
      //   1659: istore 9
      //   1661: aload_0
      //   1662: getfield 155	a/i/b/a/c/e/a$c:Btw	Ljava/util/List;
      //   1665: aload_1
      //   1666: getstatic 234	a/i/b/a/c/e/a$o:BsC	La/i/b/a/c/g/s;
      //   1669: aload_2
      //   1670: invokevirtual 225	a/i/b/a/c/g/e:a	(La/i/b/a/c/g/s;La/i/b/a/c/g/g;)La/i/b/a/c/g/q;
      //   1673: invokeinterface 198 2 0
      //   1678: pop
      //   1679: iload 10
      //   1681: istore_3
      //   1682: goto -1625 -> 57
      //   1685: iload_3
      //   1686: istore 10
      //   1688: iload_3
      //   1689: sipush 512
      //   1692: iand
      //   1693: sipush 512
      //   1696: if_icmpeq +53 -> 1749
      //   1699: iload_3
      //   1700: istore 7
      //   1702: iload_3
      //   1703: istore 8
      //   1705: iload_3
      //   1706: istore 9
      //   1708: new 185	java/util/ArrayList
      //   1711: astore 11
      //   1713: iload_3
      //   1714: istore 7
      //   1716: iload_3
      //   1717: istore 8
      //   1719: iload_3
      //   1720: istore 9
      //   1722: aload 11
      //   1724: invokespecial 186	java/util/ArrayList:<init>	()V
      //   1727: iload_3
      //   1728: istore 7
      //   1730: iload_3
      //   1731: istore 8
      //   1733: iload_3
      //   1734: istore 9
      //   1736: aload_0
      //   1737: aload 11
      //   1739: putfield 157	a/i/b/a/c/e/a$c:Btx	Ljava/util/List;
      //   1742: iload_3
      //   1743: sipush 512
      //   1746: ior
      //   1747: istore 10
      //   1749: iload 10
      //   1751: istore 7
      //   1753: iload 10
      //   1755: istore 8
      //   1757: iload 10
      //   1759: istore 9
      //   1761: aload_0
      //   1762: getfield 157	a/i/b/a/c/e/a$c:Btx	Ljava/util/List;
      //   1765: aload_1
      //   1766: getstatic 237	a/i/b/a/c/e/a$u:BsC	La/i/b/a/c/g/s;
      //   1769: aload_2
      //   1770: invokevirtual 225	a/i/b/a/c/g/e:a	(La/i/b/a/c/g/s;La/i/b/a/c/g/g;)La/i/b/a/c/g/q;
      //   1773: invokeinterface 198 2 0
      //   1778: pop
      //   1779: iload 10
      //   1781: istore_3
      //   1782: goto -1725 -> 57
      //   1785: iload_3
      //   1786: istore 10
      //   1788: iload_3
      //   1789: sipush 1024
      //   1792: iand
      //   1793: sipush 1024
      //   1796: if_icmpeq +53 -> 1849
      //   1799: iload_3
      //   1800: istore 7
      //   1802: iload_3
      //   1803: istore 8
      //   1805: iload_3
      //   1806: istore 9
      //   1808: new 185	java/util/ArrayList
      //   1811: astore 11
      //   1813: iload_3
      //   1814: istore 7
      //   1816: iload_3
      //   1817: istore 8
      //   1819: iload_3
      //   1820: istore 9
      //   1822: aload 11
      //   1824: invokespecial 186	java/util/ArrayList:<init>	()V
      //   1827: iload_3
      //   1828: istore 7
      //   1830: iload_3
      //   1831: istore 8
      //   1833: iload_3
      //   1834: istore 9
      //   1836: aload_0
      //   1837: aload 11
      //   1839: putfield 159	a/i/b/a/c/e/a$c:Bty	Ljava/util/List;
      //   1842: iload_3
      //   1843: sipush 1024
      //   1846: ior
      //   1847: istore 10
      //   1849: iload 10
      //   1851: istore 7
      //   1853: iload 10
      //   1855: istore 8
      //   1857: iload 10
      //   1859: istore 9
      //   1861: aload_0
      //   1862: getfield 159	a/i/b/a/c/e/a$c:Bty	Ljava/util/List;
      //   1865: aload_1
      //   1866: getstatic 240	a/i/b/a/c/e/a$ab:BsC	La/i/b/a/c/g/s;
      //   1869: aload_2
      //   1870: invokevirtual 225	a/i/b/a/c/g/e:a	(La/i/b/a/c/g/s;La/i/b/a/c/g/g;)La/i/b/a/c/g/q;
      //   1873: invokeinterface 198 2 0
      //   1878: pop
      //   1879: iload 10
      //   1881: istore_3
      //   1882: goto -1825 -> 57
      //   1885: iload_3
      //   1886: istore 10
      //   1888: iload_3
      //   1889: sipush 2048
      //   1892: iand
      //   1893: sipush 2048
      //   1896: if_icmpeq +53 -> 1949
      //   1899: iload_3
      //   1900: istore 7
      //   1902: iload_3
      //   1903: istore 8
      //   1905: iload_3
      //   1906: istore 9
      //   1908: new 185	java/util/ArrayList
      //   1911: astore 11
      //   1913: iload_3
      //   1914: istore 7
      //   1916: iload_3
      //   1917: istore 8
      //   1919: iload_3
      //   1920: istore 9
      //   1922: aload 11
      //   1924: invokespecial 186	java/util/ArrayList:<init>	()V
      //   1927: iload_3
      //   1928: istore 7
      //   1930: iload_3
      //   1931: istore 8
      //   1933: iload_3
      //   1934: istore 9
      //   1936: aload_0
      //   1937: aload 11
      //   1939: putfield 161	a/i/b/a/c/e/a$c:Btz	Ljava/util/List;
      //   1942: iload_3
      //   1943: sipush 2048
      //   1946: ior
      //   1947: istore 10
      //   1949: iload 10
      //   1951: istore 7
      //   1953: iload 10
      //   1955: istore 8
      //   1957: iload 10
      //   1959: istore 9
      //   1961: aload_0
      //   1962: getfield 161	a/i/b/a/c/e/a$c:Btz	Ljava/util/List;
      //   1965: aload_1
      //   1966: getstatic 243	a/i/b/a/c/e/a$k:BsC	La/i/b/a/c/g/s;
      //   1969: aload_2
      //   1970: invokevirtual 225	a/i/b/a/c/g/e:a	(La/i/b/a/c/g/s;La/i/b/a/c/g/g;)La/i/b/a/c/g/q;
      //   1973: invokeinterface 198 2 0
      //   1978: pop
      //   1979: iload 10
      //   1981: istore_3
      //   1982: goto -1925 -> 57
      //   1985: iload_3
      //   1986: istore 10
      //   1988: iload_3
      //   1989: sipush 4096
      //   1992: iand
      //   1993: sipush 4096
      //   1996: if_icmpeq +53 -> 2049
      //   1999: iload_3
      //   2000: istore 7
      //   2002: iload_3
      //   2003: istore 8
      //   2005: iload_3
      //   2006: istore 9
      //   2008: new 185	java/util/ArrayList
      //   2011: astore 11
      //   2013: iload_3
      //   2014: istore 7
      //   2016: iload_3
      //   2017: istore 8
      //   2019: iload_3
      //   2020: istore 9
      //   2022: aload 11
      //   2024: invokespecial 186	java/util/ArrayList:<init>	()V
      //   2027: iload_3
      //   2028: istore 7
      //   2030: iload_3
      //   2031: istore 8
      //   2033: iload_3
      //   2034: istore 9
      //   2036: aload_0
      //   2037: aload 11
      //   2039: putfield 163	a/i/b/a/c/e/a$c:BtA	Ljava/util/List;
      //   2042: iload_3
      //   2043: sipush 4096
      //   2046: ior
      //   2047: istore 10
      //   2049: iload 10
      //   2051: istore 7
      //   2053: iload 10
      //   2055: istore 8
      //   2057: iload 10
      //   2059: istore 9
      //   2061: aload_0
      //   2062: getfield 163	a/i/b/a/c/e/a$c:BtA	Ljava/util/List;
      //   2065: aload_1
      //   2066: invokevirtual 131	a/i/b/a/c/g/e:vd	()I
      //   2069: invokestatic 192	java/lang/Integer:valueOf	(I)Ljava/lang/Integer;
      //   2072: invokeinterface 198 2 0
      //   2077: pop
      //   2078: iload 10
      //   2080: istore_3
      //   2081: goto -2024 -> 57
      //   2084: iload_3
      //   2085: istore 7
      //   2087: iload_3
      //   2088: istore 8
      //   2090: iload_3
      //   2091: istore 9
      //   2093: aload_1
      //   2094: aload_1
      //   2095: invokevirtual 131	a/i/b/a/c/g/e:vd	()I
      //   2098: invokevirtual 209	a/i/b/a/c/g/e:fo	(I)I
      //   2101: istore 12
      //   2103: iload_3
      //   2104: istore 10
      //   2106: iload_3
      //   2107: sipush 4096
      //   2110: iand
      //   2111: sipush 4096
      //   2114: if_icmpeq +72 -> 2186
      //   2117: iload_3
      //   2118: istore 7
      //   2120: iload_3
      //   2121: istore 8
      //   2123: iload_3
      //   2124: istore 9
      //   2126: iload_3
      //   2127: istore 10
      //   2129: aload_1
      //   2130: invokevirtual 212	a/i/b/a/c/g/e:vg	()I
      //   2133: ifle +53 -> 2186
      //   2136: iload_3
      //   2137: istore 7
      //   2139: iload_3
      //   2140: istore 8
      //   2142: iload_3
      //   2143: istore 9
      //   2145: new 185	java/util/ArrayList
      //   2148: astore 11
      //   2150: iload_3
      //   2151: istore 7
      //   2153: iload_3
      //   2154: istore 8
      //   2156: iload_3
      //   2157: istore 9
      //   2159: aload 11
      //   2161: invokespecial 186	java/util/ArrayList:<init>	()V
      //   2164: iload_3
      //   2165: istore 7
      //   2167: iload_3
      //   2168: istore 8
      //   2170: iload_3
      //   2171: istore 9
      //   2173: aload_0
      //   2174: aload 11
      //   2176: putfield 163	a/i/b/a/c/e/a$c:BtA	Ljava/util/List;
      //   2179: iload_3
      //   2180: sipush 4096
      //   2183: ior
      //   2184: istore 10
      //   2186: iload 10
      //   2188: istore 7
      //   2190: iload 10
      //   2192: istore 8
      //   2194: iload 10
      //   2196: istore 9
      //   2198: aload_1
      //   2199: invokevirtual 212	a/i/b/a/c/g/e:vg	()I
      //   2202: ifle +35 -> 2237
      //   2205: iload 10
      //   2207: istore 7
      //   2209: iload 10
      //   2211: istore 8
      //   2213: iload 10
      //   2215: istore 9
      //   2217: aload_0
      //   2218: getfield 163	a/i/b/a/c/e/a$c:BtA	Ljava/util/List;
      //   2221: aload_1
      //   2222: invokevirtual 131	a/i/b/a/c/g/e:vd	()I
      //   2225: invokestatic 192	java/lang/Integer:valueOf	(I)Ljava/lang/Integer;
      //   2228: invokeinterface 198 2 0
      //   2233: pop
      //   2234: goto -48 -> 2186
      //   2237: iload 10
      //   2239: istore 7
      //   2241: iload 10
      //   2243: istore 8
      //   2245: iload 10
      //   2247: istore 9
      //   2249: aload_1
      //   2250: iload 12
      //   2252: invokevirtual 215	a/i/b/a/c/g/e:fp	(I)V
      //   2255: iload 10
      //   2257: istore_3
      //   2258: goto -2201 -> 57
      //   2261: iload_3
      //   2262: istore 7
      //   2264: iload_3
      //   2265: istore 8
      //   2267: iload_3
      //   2268: istore 9
      //   2270: aload_0
      //   2271: getfield 128	a/i/b/a/c/e/a$c:BsD	I
      //   2274: bipush 8
      //   2276: iand
      //   2277: bipush 8
      //   2279: if_icmpne +841 -> 3120
      //   2282: iload_3
      //   2283: istore 7
      //   2285: iload_3
      //   2286: istore 8
      //   2288: iload_3
      //   2289: istore 9
      //   2291: aload_0
      //   2292: getfield 245	a/i/b/a/c/e/a$c:BtC	La/i/b/a/c/e/a$ag;
      //   2295: invokestatic 251	a/i/b/a/c/e/a$ag:d	(La/i/b/a/c/e/a$ag;)La/i/b/a/c/e/a$ag$a;
      //   2298: astore 11
      //   2300: iload_3
      //   2301: istore 7
      //   2303: iload_3
      //   2304: istore 8
      //   2306: iload_3
      //   2307: istore 9
      //   2309: aload_0
      //   2310: aload_1
      //   2311: getstatic 252	a/i/b/a/c/e/a$ag:BsC	La/i/b/a/c/g/s;
      //   2314: aload_2
      //   2315: invokevirtual 225	a/i/b/a/c/g/e:a	(La/i/b/a/c/g/s;La/i/b/a/c/g/g;)La/i/b/a/c/g/q;
      //   2318: checkcast 247	a/i/b/a/c/e/a$ag
      //   2321: putfield 245	a/i/b/a/c/e/a$c:BtC	La/i/b/a/c/e/a$ag;
      //   2324: aload 11
      //   2326: ifnull +40 -> 2366
      //   2329: iload_3
      //   2330: istore 7
      //   2332: iload_3
      //   2333: istore 8
      //   2335: iload_3
      //   2336: istore 9
      //   2338: aload 11
      //   2340: aload_0
      //   2341: getfield 245	a/i/b/a/c/e/a$c:BtC	La/i/b/a/c/e/a$ag;
      //   2344: invokevirtual 257	a/i/b/a/c/e/a$ag$a:g	(La/i/b/a/c/e/a$ag;)La/i/b/a/c/e/a$ag$a;
      //   2347: pop
      //   2348: iload_3
      //   2349: istore 7
      //   2351: iload_3
      //   2352: istore 8
      //   2354: iload_3
      //   2355: istore 9
      //   2357: aload_0
      //   2358: aload 11
      //   2360: invokevirtual 261	a/i/b/a/c/e/a$ag$a:efP	()La/i/b/a/c/e/a$ag;
      //   2363: putfield 245	a/i/b/a/c/e/a$c:BtC	La/i/b/a/c/e/a$ag;
      //   2366: iload_3
      //   2367: istore 7
      //   2369: iload_3
      //   2370: istore 8
      //   2372: iload_3
      //   2373: istore 9
      //   2375: aload_0
      //   2376: aload_0
      //   2377: getfield 128	a/i/b/a/c/e/a$c:BsD	I
      //   2380: bipush 8
      //   2382: ior
      //   2383: putfield 128	a/i/b/a/c/e/a$c:BsD	I
      //   2386: goto -2329 -> 57
      //   2389: iload_3
      //   2390: istore 10
      //   2392: iload_3
      //   2393: sipush 16384
      //   2396: iand
      //   2397: sipush 16384
      //   2400: if_icmpeq +53 -> 2453
      //   2403: iload_3
      //   2404: istore 7
      //   2406: iload_3
      //   2407: istore 8
      //   2409: iload_3
      //   2410: istore 9
      //   2412: new 185	java/util/ArrayList
      //   2415: astore 11
      //   2417: iload_3
      //   2418: istore 7
      //   2420: iload_3
      //   2421: istore 8
      //   2423: iload_3
      //   2424: istore 9
      //   2426: aload 11
      //   2428: invokespecial 186	java/util/ArrayList:<init>	()V
      //   2431: iload_3
      //   2432: istore 7
      //   2434: iload_3
      //   2435: istore 8
      //   2437: iload_3
      //   2438: istore 9
      //   2440: aload_0
      //   2441: aload 11
      //   2443: putfield 165	a/i/b/a/c/e/a$c:BtD	Ljava/util/List;
      //   2446: iload_3
      //   2447: sipush 16384
      //   2450: ior
      //   2451: istore 10
      //   2453: iload 10
      //   2455: istore 7
      //   2457: iload 10
      //   2459: istore 8
      //   2461: iload 10
      //   2463: istore 9
      //   2465: aload_0
      //   2466: getfield 165	a/i/b/a/c/e/a$c:BtD	Ljava/util/List;
      //   2469: aload_1
      //   2470: invokevirtual 131	a/i/b/a/c/g/e:vd	()I
      //   2473: invokestatic 192	java/lang/Integer:valueOf	(I)Ljava/lang/Integer;
      //   2476: invokeinterface 198 2 0
      //   2481: pop
      //   2482: iload 10
      //   2484: istore_3
      //   2485: goto -2428 -> 57
      //   2488: iload_3
      //   2489: istore 7
      //   2491: iload_3
      //   2492: istore 8
      //   2494: iload_3
      //   2495: istore 9
      //   2497: aload_1
      //   2498: aload_1
      //   2499: invokevirtual 131	a/i/b/a/c/g/e:vd	()I
      //   2502: invokevirtual 209	a/i/b/a/c/g/e:fo	(I)I
      //   2505: istore 12
      //   2507: iload_3
      //   2508: istore 10
      //   2510: iload_3
      //   2511: sipush 16384
      //   2514: iand
      //   2515: sipush 16384
      //   2518: if_icmpeq +72 -> 2590
      //   2521: iload_3
      //   2522: istore 7
      //   2524: iload_3
      //   2525: istore 8
      //   2527: iload_3
      //   2528: istore 9
      //   2530: iload_3
      //   2531: istore 10
      //   2533: aload_1
      //   2534: invokevirtual 212	a/i/b/a/c/g/e:vg	()I
      //   2537: ifle +53 -> 2590
      //   2540: iload_3
      //   2541: istore 7
      //   2543: iload_3
      //   2544: istore 8
      //   2546: iload_3
      //   2547: istore 9
      //   2549: new 185	java/util/ArrayList
      //   2552: astore 11
      //   2554: iload_3
      //   2555: istore 7
      //   2557: iload_3
      //   2558: istore 8
      //   2560: iload_3
      //   2561: istore 9
      //   2563: aload 11
      //   2565: invokespecial 186	java/util/ArrayList:<init>	()V
      //   2568: iload_3
      //   2569: istore 7
      //   2571: iload_3
      //   2572: istore 8
      //   2574: iload_3
      //   2575: istore 9
      //   2577: aload_0
      //   2578: aload 11
      //   2580: putfield 165	a/i/b/a/c/e/a$c:BtD	Ljava/util/List;
      //   2583: iload_3
      //   2584: sipush 16384
      //   2587: ior
      //   2588: istore 10
      //   2590: iload 10
      //   2592: istore 7
      //   2594: iload 10
      //   2596: istore 8
      //   2598: iload 10
      //   2600: istore 9
      //   2602: aload_1
      //   2603: invokevirtual 212	a/i/b/a/c/g/e:vg	()I
      //   2606: ifle +35 -> 2641
      //   2609: iload 10
      //   2611: istore 7
      //   2613: iload 10
      //   2615: istore 8
      //   2617: iload 10
      //   2619: istore 9
      //   2621: aload_0
      //   2622: getfield 165	a/i/b/a/c/e/a$c:BtD	Ljava/util/List;
      //   2625: aload_1
      //   2626: invokevirtual 131	a/i/b/a/c/g/e:vd	()I
      //   2629: invokestatic 192	java/lang/Integer:valueOf	(I)Ljava/lang/Integer;
      //   2632: invokeinterface 198 2 0
      //   2637: pop
      //   2638: goto -48 -> 2590
      //   2641: iload 10
      //   2643: istore 7
      //   2645: iload 10
      //   2647: istore 8
      //   2649: iload 10
      //   2651: istore 9
      //   2653: aload_1
      //   2654: iload 12
      //   2656: invokevirtual 215	a/i/b/a/c/g/e:fp	(I)V
      //   2659: iload 10
      //   2661: istore_3
      //   2662: goto -2605 -> 57
      //   2665: iload_3
      //   2666: istore 7
      //   2668: iload_3
      //   2669: istore 8
      //   2671: iload_3
      //   2672: istore 9
      //   2674: aload_0
      //   2675: getfield 128	a/i/b/a/c/e/a$c:BsD	I
      //   2678: bipush 16
      //   2680: iand
      //   2681: bipush 16
      //   2683: if_icmpne +431 -> 3114
      //   2686: iload_3
      //   2687: istore 7
      //   2689: iload_3
      //   2690: istore 8
      //   2692: iload_3
      //   2693: istore 9
      //   2695: aload_0
      //   2696: getfield 263	a/i/b/a/c/e/a$c:BtE	La/i/b/a/c/e/a$am;
      //   2699: invokestatic 268	a/i/b/a/c/e/a$am:c	(La/i/b/a/c/e/a$am;)La/i/b/a/c/e/a$am$a;
      //   2702: astore 11
      //   2704: iload_3
      //   2705: istore 7
      //   2707: iload_3
      //   2708: istore 8
      //   2710: iload_3
      //   2711: istore 9
      //   2713: aload_0
      //   2714: aload_1
      //   2715: getstatic 269	a/i/b/a/c/e/a$am:BsC	La/i/b/a/c/g/s;
      //   2718: aload_2
      //   2719: invokevirtual 225	a/i/b/a/c/g/e:a	(La/i/b/a/c/g/s;La/i/b/a/c/g/g;)La/i/b/a/c/g/q;
      //   2722: checkcast 265	a/i/b/a/c/e/a$am
      //   2725: putfield 263	a/i/b/a/c/e/a$c:BtE	La/i/b/a/c/e/a$am;
      //   2728: aload 11
      //   2730: ifnull +40 -> 2770
      //   2733: iload_3
      //   2734: istore 7
      //   2736: iload_3
      //   2737: istore 8
      //   2739: iload_3
      //   2740: istore 9
      //   2742: aload 11
      //   2744: aload_0
      //   2745: getfield 263	a/i/b/a/c/e/a$c:BtE	La/i/b/a/c/e/a$am;
      //   2748: invokevirtual 274	a/i/b/a/c/e/a$am$a:f	(La/i/b/a/c/e/a$am;)La/i/b/a/c/e/a$am$a;
      //   2751: pop
      //   2752: iload_3
      //   2753: istore 7
      //   2755: iload_3
      //   2756: istore 8
      //   2758: iload_3
      //   2759: istore 9
      //   2761: aload_0
      //   2762: aload 11
      //   2764: invokevirtual 278	a/i/b/a/c/e/a$am$a:egk	()La/i/b/a/c/e/a$am;
      //   2767: putfield 263	a/i/b/a/c/e/a$c:BtE	La/i/b/a/c/e/a$am;
      //   2770: iload_3
      //   2771: istore 7
      //   2773: iload_3
      //   2774: istore 8
      //   2776: iload_3
      //   2777: istore 9
      //   2779: aload_0
      //   2780: aload_0
      //   2781: getfield 128	a/i/b/a/c/e/a$c:BsD	I
      //   2784: bipush 16
      //   2786: ior
      //   2787: putfield 128	a/i/b/a/c/e/a$c:BsD	I
      //   2790: goto -2733 -> 57
      //   2793: iload_3
      //   2794: bipush 32
      //   2796: iand
      //   2797: bipush 32
      //   2799: if_icmpne +14 -> 2813
      //   2802: aload_0
      //   2803: aload_0
      //   2804: getfield 139	a/i/b/a/c/e/a$c:Btr	Ljava/util/List;
      //   2807: invokestatic 145	java/util/Collections:unmodifiableList	(Ljava/util/List;)Ljava/util/List;
      //   2810: putfield 139	a/i/b/a/c/e/a$c:Btr	Ljava/util/List;
      //   2813: iload_3
      //   2814: bipush 8
      //   2816: iand
      //   2817: bipush 8
      //   2819: if_icmpne +14 -> 2833
      //   2822: aload_0
      //   2823: aload_0
      //   2824: getfield 147	a/i/b/a/c/e/a$c:Btp	Ljava/util/List;
      //   2827: invokestatic 145	java/util/Collections:unmodifiableList	(Ljava/util/List;)Ljava/util/List;
      //   2830: putfield 147	a/i/b/a/c/e/a$c:Btp	Ljava/util/List;
      //   2833: iload_3
      //   2834: bipush 16
      //   2836: iand
      //   2837: bipush 16
      //   2839: if_icmpne +14 -> 2853
      //   2842: aload_0
      //   2843: aload_0
      //   2844: getfield 149	a/i/b/a/c/e/a$c:Btq	Ljava/util/List;
      //   2847: invokestatic 145	java/util/Collections:unmodifiableList	(Ljava/util/List;)Ljava/util/List;
      //   2850: putfield 149	a/i/b/a/c/e/a$c:Btq	Ljava/util/List;
      //   2853: iload_3
      //   2854: bipush 64
      //   2856: iand
      //   2857: bipush 64
      //   2859: if_icmpne +14 -> 2873
      //   2862: aload_0
      //   2863: aload_0
      //   2864: getfield 151	a/i/b/a/c/e/a$c:Btt	Ljava/util/List;
      //   2867: invokestatic 145	java/util/Collections:unmodifiableList	(Ljava/util/List;)Ljava/util/List;
      //   2870: putfield 151	a/i/b/a/c/e/a$c:Btt	Ljava/util/List;
      //   2873: iload_3
      //   2874: sipush 128
      //   2877: iand
      //   2878: sipush 128
      //   2881: if_icmpne +14 -> 2895
      //   2884: aload_0
      //   2885: aload_0
      //   2886: getfield 153	a/i/b/a/c/e/a$c:Btv	Ljava/util/List;
      //   2889: invokestatic 145	java/util/Collections:unmodifiableList	(Ljava/util/List;)Ljava/util/List;
      //   2892: putfield 153	a/i/b/a/c/e/a$c:Btv	Ljava/util/List;
      //   2895: iload_3
      //   2896: sipush 256
      //   2899: iand
      //   2900: sipush 256
      //   2903: if_icmpne +14 -> 2917
      //   2906: aload_0
      //   2907: aload_0
      //   2908: getfield 155	a/i/b/a/c/e/a$c:Btw	Ljava/util/List;
      //   2911: invokestatic 145	java/util/Collections:unmodifiableList	(Ljava/util/List;)Ljava/util/List;
      //   2914: putfield 155	a/i/b/a/c/e/a$c:Btw	Ljava/util/List;
      //   2917: iload_3
      //   2918: sipush 512
      //   2921: iand
      //   2922: sipush 512
      //   2925: if_icmpne +14 -> 2939
      //   2928: aload_0
      //   2929: aload_0
      //   2930: getfield 157	a/i/b/a/c/e/a$c:Btx	Ljava/util/List;
      //   2933: invokestatic 145	java/util/Collections:unmodifiableList	(Ljava/util/List;)Ljava/util/List;
      //   2936: putfield 157	a/i/b/a/c/e/a$c:Btx	Ljava/util/List;
      //   2939: iload_3
      //   2940: sipush 1024
      //   2943: iand
      //   2944: sipush 1024
      //   2947: if_icmpne +14 -> 2961
      //   2950: aload_0
      //   2951: aload_0
      //   2952: getfield 159	a/i/b/a/c/e/a$c:Bty	Ljava/util/List;
      //   2955: invokestatic 145	java/util/Collections:unmodifiableList	(Ljava/util/List;)Ljava/util/List;
      //   2958: putfield 159	a/i/b/a/c/e/a$c:Bty	Ljava/util/List;
      //   2961: iload_3
      //   2962: sipush 2048
      //   2965: iand
      //   2966: sipush 2048
      //   2969: if_icmpne +14 -> 2983
      //   2972: aload_0
      //   2973: aload_0
      //   2974: getfield 161	a/i/b/a/c/e/a$c:Btz	Ljava/util/List;
      //   2977: invokestatic 145	java/util/Collections:unmodifiableList	(Ljava/util/List;)Ljava/util/List;
      //   2980: putfield 161	a/i/b/a/c/e/a$c:Btz	Ljava/util/List;
      //   2983: iload_3
      //   2984: sipush 4096
      //   2987: iand
      //   2988: sipush 4096
      //   2991: if_icmpne +14 -> 3005
      //   2994: aload_0
      //   2995: aload_0
      //   2996: getfield 163	a/i/b/a/c/e/a$c:BtA	Ljava/util/List;
      //   2999: invokestatic 145	java/util/Collections:unmodifiableList	(Ljava/util/List;)Ljava/util/List;
      //   3002: putfield 163	a/i/b/a/c/e/a$c:BtA	Ljava/util/List;
      //   3005: iload_3
      //   3006: sipush 16384
      //   3009: iand
      //   3010: sipush 16384
      //   3013: if_icmpne +14 -> 3027
      //   3016: aload_0
      //   3017: aload_0
      //   3018: getfield 165	a/i/b/a/c/e/a$c:BtD	Ljava/util/List;
      //   3021: invokestatic 145	java/util/Collections:unmodifiableList	(Ljava/util/List;)Ljava/util/List;
      //   3024: putfield 165	a/i/b/a/c/e/a$c:BtD	Ljava/util/List;
      //   3027: aload 5
      //   3029: invokevirtual 168	a/i/b/a/c/g/f:flush	()V
      //   3032: aload_0
      //   3033: aload 4
      //   3035: invokevirtual 174	a/i/b/a/c/g/d$b:ehW	()La/i/b/a/c/g/d;
      //   3038: putfield 100	a/i/b/a/c/e/a$c:BsB	La/i/b/a/c/g/d;
      //   3041: aload_0
      //   3042: getfield 178	a/i/b/a/c/g/i$c:BzI	La/i/b/a/c/g/h;
      //   3045: invokevirtual 183	a/i/b/a/c/g/h:eii	()V
      //   3048: ldc 106
      //   3050: invokestatic 81	com/tencent/matrix/trace/core/AppMethodBeat:o	(I)V
      //   3053: return
      //   3054: astore_1
      //   3055: aload_0
      //   3056: aload 4
      //   3058: invokevirtual 174	a/i/b/a/c/g/d$b:ehW	()La/i/b/a/c/g/d;
      //   3061: putfield 100	a/i/b/a/c/e/a$c:BsB	La/i/b/a/c/g/d;
      //   3064: goto -23 -> 3041
      //   3067: astore_1
      //   3068: aload_0
      //   3069: aload 4
      //   3071: invokevirtual 174	a/i/b/a/c/g/d$b:ehW	()La/i/b/a/c/g/d;
      //   3074: putfield 100	a/i/b/a/c/e/a$c:BsB	La/i/b/a/c/g/d;
      //   3077: ldc 106
      //   3079: invokestatic 81	com/tencent/matrix/trace/core/AppMethodBeat:o	(I)V
      //   3082: aload_1
      //   3083: athrow
      //   3084: astore_2
      //   3085: aload_0
      //   3086: aload 4
      //   3088: invokevirtual 174	a/i/b/a/c/g/d$b:ehW	()La/i/b/a/c/g/d;
      //   3091: putfield 100	a/i/b/a/c/e/a$c:BsB	La/i/b/a/c/g/d;
      //   3094: goto -2480 -> 614
      //   3097: astore_1
      //   3098: aload_0
      //   3099: aload 4
      //   3101: invokevirtual 174	a/i/b/a/c/g/d$b:ehW	()La/i/b/a/c/g/d;
      //   3104: putfield 100	a/i/b/a/c/e/a$c:BsB	La/i/b/a/c/g/d;
      //   3107: ldc 106
      //   3109: invokestatic 81	com/tencent/matrix/trace/core/AppMethodBeat:o	(I)V
      //   3112: aload_1
      //   3113: athrow
      //   3114: aconst_null
      //   3115: astore 11
      //   3117: goto -413 -> 2704
      //   3120: aconst_null
      //   3121: astore 11
      //   3123: goto -823 -> 2300
      //
      // Exception table:
      //   from	to	target	type
      //   71	77	329	a/i/b/a/c/g/k
      //   265	278	329	a/i/b/a/c/g/k
      //   299	309	329	a/i/b/a/c/g/k
      //   318	326	329	a/i/b/a/c/g/k
      //   649	654	329	a/i/b/a/c/g/k
      //   663	668	329	a/i/b/a/c/g/k
      //   677	683	329	a/i/b/a/c/g/k
      //   701	718	329	a/i/b/a/c/g/k
      //   778	788	329	a/i/b/a/c/g/k
      //   812	819	329	a/i/b/a/c/g/k
      //   828	833	329	a/i/b/a/c/g/k
      //   842	847	329	a/i/b/a/c/g/k
      //   856	862	329	a/i/b/a/c/g/k
      //   880	887	329	a/i/b/a/c/g/k
      //   899	916	329	a/i/b/a/c/g/k
      //   931	937	329	a/i/b/a/c/g/k
      //   952	962	329	a/i/b/a/c/g/k
      //   971	979	329	a/i/b/a/c/g/k
      //   991	1001	329	a/i/b/a/c/g/k
      //   1010	1018	329	a/i/b/a/c/g/k
      //   1042	1047	329	a/i/b/a/c/g/k
      //   1056	1061	329	a/i/b/a/c/g/k
      //   1070	1076	329	a/i/b/a/c/g/k
      //   1094	1112	329	a/i/b/a/c/g/k
      //   1139	1144	329	a/i/b/a/c/g/k
      //   1153	1158	329	a/i/b/a/c/g/k
      //   1167	1173	329	a/i/b/a/c/g/k
      //   1191	1209	329	a/i/b/a/c/g/k
      //   1236	1241	329	a/i/b/a/c/g/k
      //   1250	1255	329	a/i/b/a/c/g/k
      //   1264	1270	329	a/i/b/a/c/g/k
      //   1288	1305	329	a/i/b/a/c/g/k
      //   1320	1330	329	a/i/b/a/c/g/k
      //   1354	1361	329	a/i/b/a/c/g/k
      //   1370	1375	329	a/i/b/a/c/g/k
      //   1384	1389	329	a/i/b/a/c/g/k
      //   1398	1404	329	a/i/b/a/c/g/k
      //   1422	1429	329	a/i/b/a/c/g/k
      //   1441	1458	329	a/i/b/a/c/g/k
      //   1473	1479	329	a/i/b/a/c/g/k
      //   1508	1513	329	a/i/b/a/c/g/k
      //   1522	1527	329	a/i/b/a/c/g/k
      //   1536	1542	329	a/i/b/a/c/g/k
      //   1561	1579	329	a/i/b/a/c/g/k
      //   1608	1613	329	a/i/b/a/c/g/k
      //   1622	1627	329	a/i/b/a/c/g/k
      //   1636	1642	329	a/i/b/a/c/g/k
      //   1661	1679	329	a/i/b/a/c/g/k
      //   1708	1713	329	a/i/b/a/c/g/k
      //   1722	1727	329	a/i/b/a/c/g/k
      //   1736	1742	329	a/i/b/a/c/g/k
      //   1761	1779	329	a/i/b/a/c/g/k
      //   1808	1813	329	a/i/b/a/c/g/k
      //   1822	1827	329	a/i/b/a/c/g/k
      //   1836	1842	329	a/i/b/a/c/g/k
      //   1861	1879	329	a/i/b/a/c/g/k
      //   1908	1913	329	a/i/b/a/c/g/k
      //   1922	1927	329	a/i/b/a/c/g/k
      //   1936	1942	329	a/i/b/a/c/g/k
      //   1961	1979	329	a/i/b/a/c/g/k
      //   2008	2013	329	a/i/b/a/c/g/k
      //   2022	2027	329	a/i/b/a/c/g/k
      //   2036	2042	329	a/i/b/a/c/g/k
      //   2061	2078	329	a/i/b/a/c/g/k
      //   2093	2103	329	a/i/b/a/c/g/k
      //   2129	2136	329	a/i/b/a/c/g/k
      //   2145	2150	329	a/i/b/a/c/g/k
      //   2159	2164	329	a/i/b/a/c/g/k
      //   2173	2179	329	a/i/b/a/c/g/k
      //   2198	2205	329	a/i/b/a/c/g/k
      //   2217	2234	329	a/i/b/a/c/g/k
      //   2249	2255	329	a/i/b/a/c/g/k
      //   2270	2282	329	a/i/b/a/c/g/k
      //   2291	2300	329	a/i/b/a/c/g/k
      //   2309	2324	329	a/i/b/a/c/g/k
      //   2338	2348	329	a/i/b/a/c/g/k
      //   2357	2366	329	a/i/b/a/c/g/k
      //   2375	2386	329	a/i/b/a/c/g/k
      //   2412	2417	329	a/i/b/a/c/g/k
      //   2426	2431	329	a/i/b/a/c/g/k
      //   2440	2446	329	a/i/b/a/c/g/k
      //   2465	2482	329	a/i/b/a/c/g/k
      //   2497	2507	329	a/i/b/a/c/g/k
      //   2533	2540	329	a/i/b/a/c/g/k
      //   2549	2554	329	a/i/b/a/c/g/k
      //   2563	2568	329	a/i/b/a/c/g/k
      //   2577	2583	329	a/i/b/a/c/g/k
      //   2602	2609	329	a/i/b/a/c/g/k
      //   2621	2638	329	a/i/b/a/c/g/k
      //   2653	2659	329	a/i/b/a/c/g/k
      //   2674	2686	329	a/i/b/a/c/g/k
      //   2695	2704	329	a/i/b/a/c/g/k
      //   2713	2728	329	a/i/b/a/c/g/k
      //   2742	2752	329	a/i/b/a/c/g/k
      //   2761	2770	329	a/i/b/a/c/g/k
      //   2779	2790	329	a/i/b/a/c/g/k
      //   71	77	354	finally
      //   265	278	354	finally
      //   299	309	354	finally
      //   318	326	354	finally
      //   334	339	354	finally
      //   343	348	354	finally
      //   352	354	354	finally
      //   649	654	354	finally
      //   663	668	354	finally
      //   677	683	354	finally
      //   701	718	354	finally
      //   729	733	354	finally
      //   737	745	354	finally
      //   749	754	354	finally
      //   758	763	354	finally
      //   767	769	354	finally
      //   778	788	354	finally
      //   812	819	354	finally
      //   828	833	354	finally
      //   842	847	354	finally
      //   856	862	354	finally
      //   880	887	354	finally
      //   899	916	354	finally
      //   931	937	354	finally
      //   952	962	354	finally
      //   971	979	354	finally
      //   991	1001	354	finally
      //   1010	1018	354	finally
      //   1042	1047	354	finally
      //   1056	1061	354	finally
      //   1070	1076	354	finally
      //   1094	1112	354	finally
      //   1139	1144	354	finally
      //   1153	1158	354	finally
      //   1167	1173	354	finally
      //   1191	1209	354	finally
      //   1236	1241	354	finally
      //   1250	1255	354	finally
      //   1264	1270	354	finally
      //   1288	1305	354	finally
      //   1320	1330	354	finally
      //   1354	1361	354	finally
      //   1370	1375	354	finally
      //   1384	1389	354	finally
      //   1398	1404	354	finally
      //   1422	1429	354	finally
      //   1441	1458	354	finally
      //   1473	1479	354	finally
      //   1508	1513	354	finally
      //   1522	1527	354	finally
      //   1536	1542	354	finally
      //   1561	1579	354	finally
      //   1608	1613	354	finally
      //   1622	1627	354	finally
      //   1636	1642	354	finally
      //   1661	1679	354	finally
      //   1708	1713	354	finally
      //   1722	1727	354	finally
      //   1736	1742	354	finally
      //   1761	1779	354	finally
      //   1808	1813	354	finally
      //   1822	1827	354	finally
      //   1836	1842	354	finally
      //   1861	1879	354	finally
      //   1908	1913	354	finally
      //   1922	1927	354	finally
      //   1936	1942	354	finally
      //   1961	1979	354	finally
      //   2008	2013	354	finally
      //   2022	2027	354	finally
      //   2036	2042	354	finally
      //   2061	2078	354	finally
      //   2093	2103	354	finally
      //   2129	2136	354	finally
      //   2145	2150	354	finally
      //   2159	2164	354	finally
      //   2173	2179	354	finally
      //   2198	2205	354	finally
      //   2217	2234	354	finally
      //   2249	2255	354	finally
      //   2270	2282	354	finally
      //   2291	2300	354	finally
      //   2309	2324	354	finally
      //   2338	2348	354	finally
      //   2357	2366	354	finally
      //   2375	2386	354	finally
      //   2412	2417	354	finally
      //   2426	2431	354	finally
      //   2440	2446	354	finally
      //   2465	2482	354	finally
      //   2497	2507	354	finally
      //   2533	2540	354	finally
      //   2549	2554	354	finally
      //   2563	2568	354	finally
      //   2577	2583	354	finally
      //   2602	2609	354	finally
      //   2621	2638	354	finally
      //   2653	2659	354	finally
      //   2674	2686	354	finally
      //   2695	2704	354	finally
      //   2713	2728	354	finally
      //   2742	2752	354	finally
      //   2761	2770	354	finally
      //   2779	2790	354	finally
      //   71	77	724	java/io/IOException
      //   265	278	724	java/io/IOException
      //   299	309	724	java/io/IOException
      //   318	326	724	java/io/IOException
      //   649	654	724	java/io/IOException
      //   663	668	724	java/io/IOException
      //   677	683	724	java/io/IOException
      //   701	718	724	java/io/IOException
      //   778	788	724	java/io/IOException
      //   812	819	724	java/io/IOException
      //   828	833	724	java/io/IOException
      //   842	847	724	java/io/IOException
      //   856	862	724	java/io/IOException
      //   880	887	724	java/io/IOException
      //   899	916	724	java/io/IOException
      //   931	937	724	java/io/IOException
      //   952	962	724	java/io/IOException
      //   971	979	724	java/io/IOException
      //   991	1001	724	java/io/IOException
      //   1010	1018	724	java/io/IOException
      //   1042	1047	724	java/io/IOException
      //   1056	1061	724	java/io/IOException
      //   1070	1076	724	java/io/IOException
      //   1094	1112	724	java/io/IOException
      //   1139	1144	724	java/io/IOException
      //   1153	1158	724	java/io/IOException
      //   1167	1173	724	java/io/IOException
      //   1191	1209	724	java/io/IOException
      //   1236	1241	724	java/io/IOException
      //   1250	1255	724	java/io/IOException
      //   1264	1270	724	java/io/IOException
      //   1288	1305	724	java/io/IOException
      //   1320	1330	724	java/io/IOException
      //   1354	1361	724	java/io/IOException
      //   1370	1375	724	java/io/IOException
      //   1384	1389	724	java/io/IOException
      //   1398	1404	724	java/io/IOException
      //   1422	1429	724	java/io/IOException
      //   1441	1458	724	java/io/IOException
      //   1473	1479	724	java/io/IOException
      //   1508	1513	724	java/io/IOException
      //   1522	1527	724	java/io/IOException
      //   1536	1542	724	java/io/IOException
      //   1561	1579	724	java/io/IOException
      //   1608	1613	724	java/io/IOException
      //   1622	1627	724	java/io/IOException
      //   1636	1642	724	java/io/IOException
      //   1661	1679	724	java/io/IOException
      //   1708	1713	724	java/io/IOException
      //   1722	1727	724	java/io/IOException
      //   1736	1742	724	java/io/IOException
      //   1761	1779	724	java/io/IOException
      //   1808	1813	724	java/io/IOException
      //   1822	1827	724	java/io/IOException
      //   1836	1842	724	java/io/IOException
      //   1861	1879	724	java/io/IOException
      //   1908	1913	724	java/io/IOException
      //   1922	1927	724	java/io/IOException
      //   1936	1942	724	java/io/IOException
      //   1961	1979	724	java/io/IOException
      //   2008	2013	724	java/io/IOException
      //   2022	2027	724	java/io/IOException
      //   2036	2042	724	java/io/IOException
      //   2061	2078	724	java/io/IOException
      //   2093	2103	724	java/io/IOException
      //   2129	2136	724	java/io/IOException
      //   2145	2150	724	java/io/IOException
      //   2159	2164	724	java/io/IOException
      //   2173	2179	724	java/io/IOException
      //   2198	2205	724	java/io/IOException
      //   2217	2234	724	java/io/IOException
      //   2249	2255	724	java/io/IOException
      //   2270	2282	724	java/io/IOException
      //   2291	2300	724	java/io/IOException
      //   2309	2324	724	java/io/IOException
      //   2338	2348	724	java/io/IOException
      //   2357	2366	724	java/io/IOException
      //   2375	2386	724	java/io/IOException
      //   2412	2417	724	java/io/IOException
      //   2426	2431	724	java/io/IOException
      //   2440	2446	724	java/io/IOException
      //   2465	2482	724	java/io/IOException
      //   2497	2507	724	java/io/IOException
      //   2533	2540	724	java/io/IOException
      //   2549	2554	724	java/io/IOException
      //   2563	2568	724	java/io/IOException
      //   2577	2583	724	java/io/IOException
      //   2602	2609	724	java/io/IOException
      //   2621	2638	724	java/io/IOException
      //   2653	2659	724	java/io/IOException
      //   2674	2686	724	java/io/IOException
      //   2695	2704	724	java/io/IOException
      //   2713	2728	724	java/io/IOException
      //   2742	2752	724	java/io/IOException
      //   2761	2770	724	java/io/IOException
      //   2779	2790	724	java/io/IOException
      //   3027	3032	3054	java/io/IOException
      //   3027	3032	3067	finally
      //   600	605	3084	java/io/IOException
      //   600	605	3097	finally
    }

    private c(i.b<c, ?> paramb)
    {
      super();
      this.BsB = paramb.BsB;
    }

    public static c a(InputStream paramInputStream, g paramg)
    {
      AppMethodBeat.i(120481);
      paramInputStream = (c)BsC.j(paramInputStream, paramg);
      AppMethodBeat.o(120481);
      return paramInputStream;
    }

    private void ecA()
    {
      AppMethodBeat.i(120477);
      this.BsW = 6;
      this.Btn = 0;
      this.Bto = 0;
      this.Btp = Collections.emptyList();
      this.Btq = Collections.emptyList();
      this.Btr = Collections.emptyList();
      this.Btt = Collections.emptyList();
      this.Btv = Collections.emptyList();
      this.Btw = Collections.emptyList();
      this.Btx = Collections.emptyList();
      this.Bty = Collections.emptyList();
      this.Btz = Collections.emptyList();
      this.BtA = Collections.emptyList();
      this.BtC = a.ag.efM();
      this.BtD = Collections.emptyList();
      this.BtE = a.am.egi();
      AppMethodBeat.o(120477);
    }

    public static c edi()
    {
      return Btm;
    }

    public final void a(f paramf)
    {
      int i = 0;
      AppMethodBeat.i(120479);
      vq();
      i.c.a locala = eip();
      if ((this.BsD & 0x1) == 1)
        paramf.bq(1, this.BsW);
      if (this.Btr.size() > 0)
      {
        paramf.fw(18);
        paramf.fw(this.Bts);
      }
      for (int j = 0; j < this.Btr.size(); j++)
        paramf.Uy(((Integer)this.Btr.get(j)).intValue());
      if ((this.BsD & 0x2) == 2)
        paramf.bq(3, this.Btn);
      if ((this.BsD & 0x4) == 4)
        paramf.bq(4, this.Bto);
      for (j = 0; j < this.Btp.size(); j++)
        paramf.a(5, (q)this.Btp.get(j));
      for (j = 0; j < this.Btq.size(); j++)
        paramf.a(6, (q)this.Btq.get(j));
      if (this.Btt.size() > 0)
      {
        paramf.fw(58);
        paramf.fw(this.Btu);
      }
      for (j = 0; j < this.Btt.size(); j++)
        paramf.Uy(((Integer)this.Btt.get(j)).intValue());
      for (j = 0; j < this.Btv.size(); j++)
        paramf.a(8, (q)this.Btv.get(j));
      for (j = 0; j < this.Btw.size(); j++)
        paramf.a(9, (q)this.Btw.get(j));
      for (j = 0; j < this.Btx.size(); j++)
        paramf.a(10, (q)this.Btx.get(j));
      for (j = 0; j < this.Bty.size(); j++)
        paramf.a(11, (q)this.Bty.get(j));
      for (j = 0; j < this.Btz.size(); j++)
        paramf.a(13, (q)this.Btz.get(j));
      if (this.BtA.size() > 0)
      {
        paramf.fw(130);
        paramf.fw(this.BtB);
      }
      for (j = 0; j < this.BtA.size(); j++)
        paramf.Uy(((Integer)this.BtA.get(j)).intValue());
      j = i;
      if ((this.BsD & 0x8) == 8)
        paramf.a(30, this.BtC);
      for (j = i; j < this.BtD.size(); j++)
        paramf.bq(31, ((Integer)this.BtD.get(j)).intValue());
      if ((this.BsD & 0x10) == 16)
        paramf.a(32, this.BtE);
      locala.b(19000, paramf);
      paramf.d(this.BsB);
      AppMethodBeat.o(120479);
    }

    public final boolean ecY()
    {
      boolean bool = true;
      if ((this.BsD & 0x1) == 1);
      while (true)
      {
        return bool;
        bool = false;
      }
    }

    public final s<c> ecy()
    {
      return BsC;
    }

    public final boolean edj()
    {
      if ((this.BsD & 0x2) == 2);
      for (boolean bool = true; ; bool = false)
        return bool;
    }

    public final boolean edk()
    {
      if ((this.BsD & 0x4) == 4);
      for (boolean bool = true; ; bool = false)
        return bool;
    }

    public final boolean edl()
    {
      if ((this.BsD & 0x8) == 8);
      for (boolean bool = true; ; bool = false)
        return bool;
    }

    public final boolean edm()
    {
      if ((this.BsD & 0x10) == 16);
      for (boolean bool = true; ; bool = false)
        return bool;
    }

    public final boolean isInitialized()
    {
      boolean bool = false;
      AppMethodBeat.i(120478);
      int i = this.BsG;
      if (i == 1)
      {
        AppMethodBeat.o(120478);
        bool = true;
      }
      while (true)
      {
        return bool;
        if (i == 0)
        {
          AppMethodBeat.o(120478);
        }
        else if (!edj())
        {
          this.BsG = ((byte)0);
          AppMethodBeat.o(120478);
        }
        else
        {
          for (i = 0; ; i++)
          {
            if (i >= this.Btp.size())
              break label118;
            if (!((a.ae)this.Btp.get(i)).isInitialized())
            {
              this.BsG = ((byte)0);
              AppMethodBeat.o(120478);
              break;
            }
          }
          label118: for (i = 0; ; i++)
          {
            if (i >= this.Btq.size())
              break label173;
            if (!((a.aa)this.Btq.get(i)).isInitialized())
            {
              this.BsG = ((byte)0);
              AppMethodBeat.o(120478);
              break;
            }
          }
          label173: for (i = 0; ; i++)
          {
            if (i >= this.Btv.size())
              break label228;
            if (!((a.e)this.Btv.get(i)).isInitialized())
            {
              this.BsG = ((byte)0);
              AppMethodBeat.o(120478);
              break;
            }
          }
          label228: for (i = 0; ; i++)
          {
            if (i >= this.Btw.size())
              break label283;
            if (!((a.o)this.Btw.get(i)).isInitialized())
            {
              this.BsG = ((byte)0);
              AppMethodBeat.o(120478);
              break;
            }
          }
          label283: for (i = 0; ; i++)
          {
            if (i >= this.Btx.size())
              break label338;
            if (!((a.u)this.Btx.get(i)).isInitialized())
            {
              this.BsG = ((byte)0);
              AppMethodBeat.o(120478);
              break;
            }
          }
          label338: for (i = 0; ; i++)
          {
            if (i >= this.Bty.size())
              break label393;
            if (!((a.ab)this.Bty.get(i)).isInitialized())
            {
              this.BsG = ((byte)0);
              AppMethodBeat.o(120478);
              break;
            }
          }
          label393: for (i = 0; ; i++)
          {
            if (i >= this.Btz.size())
              break label448;
            if (!((a.k)this.Btz.get(i)).isInitialized())
            {
              this.BsG = ((byte)0);
              AppMethodBeat.o(120478);
              break;
            }
          }
          label448: if ((edl()) && (!this.BtC.isInitialized()))
          {
            this.BsG = ((byte)0);
            AppMethodBeat.o(120478);
          }
          else if (!this.BzI.isInitialized())
          {
            this.BsG = ((byte)0);
            AppMethodBeat.o(120478);
          }
          else
          {
            this.BsG = ((byte)1);
            AppMethodBeat.o(120478);
            bool = true;
          }
        }
      }
    }

    public final int vq()
    {
      AppMethodBeat.i(120480);
      int i = this.BsH;
      if (i != -1)
      {
        AppMethodBeat.o(120480);
        return i;
      }
      if ((this.BsD & 0x1) == 1);
      for (i = f.bs(1, this.BsW) + 0; ; i = 0)
      {
        int j = 0;
        int k = 0;
        while (j < this.Btr.size())
        {
          k += f.ft(((Integer)this.Btr.get(j)).intValue());
          j++;
        }
        j = i + k;
        i = j;
        if (!this.Btr.isEmpty())
          i = j + 1 + f.ft(k);
        this.Bts = k;
        k = i;
        if ((this.BsD & 0x2) == 2)
          k = i + f.bs(3, this.Btn);
        i = k;
        if ((this.BsD & 0x4) == 4)
          i = k + f.bs(4, this.Bto);
        for (k = 0; k < this.Btp.size(); k++)
          i += f.c(5, (q)this.Btp.get(k));
        for (k = 0; k < this.Btq.size(); k++)
          i += f.c(6, (q)this.Btq.get(k));
        j = 0;
        k = 0;
        while (j < this.Btt.size())
        {
          k += f.ft(((Integer)this.Btt.get(j)).intValue());
          j++;
        }
        j = i + k;
        i = j;
        if (!this.Btt.isEmpty())
          i = j + 1 + f.ft(k);
        this.Btu = k;
        for (k = 0; k < this.Btv.size(); k++)
          i += f.c(8, (q)this.Btv.get(k));
        for (k = 0; k < this.Btw.size(); k++)
          i += f.c(9, (q)this.Btw.get(k));
        for (k = 0; k < this.Btx.size(); k++)
          i += f.c(10, (q)this.Btx.get(k));
        for (k = 0; k < this.Bty.size(); k++)
          i += f.c(11, (q)this.Bty.get(k));
        for (k = 0; k < this.Btz.size(); k++)
          i += f.c(13, (q)this.Btz.get(k));
        j = 0;
        k = 0;
        while (j < this.BtA.size())
        {
          k += f.ft(((Integer)this.BtA.get(j)).intValue());
          j++;
        }
        j = i + k;
        i = j;
        if (!this.BtA.isEmpty())
          i = j + 2 + f.ft(k);
        this.BtB = k;
        if ((this.BsD & 0x8) == 8)
          i += f.c(30, this.BtC);
        while (true)
        {
          j = 0;
          int m;
          for (k = 0; j < this.BtD.size(); k = m + k)
          {
            m = f.ft(((Integer)this.BtD.get(j)).intValue());
            j++;
          }
          k = i + k + this.BtD.size() * 2;
          i = k;
          if ((this.BsD & 0x10) == 16)
            i = k + f.c(32, this.BtE);
          i = i + this.BzI.vq() + this.BsB.size();
          this.BsH = i;
          AppMethodBeat.o(120480);
          break;
        }
      }
    }
  }

  public static abstract interface f extends i.d
  {
  }

  public static enum i$b
    implements j.a
  {
    private static j.b<b> Btk;
    final int value;

    static
    {
      AppMethodBeat.i(120564);
      BtW = new b("RETURNS_CONSTANT", 0, 0);
      BtX = new b("CALLS", 1, 1);
      BtY = new b("RETURNS_NOT_NULL", 2, 2);
      BtZ = new b[] { BtW, BtX, BtY };
      Btk = new a.i.b.1();
      AppMethodBeat.o(120564);
    }

    private i$b(int paramInt1, int paramInt2)
    {
      this.value = paramInt1;
    }

    public static b Td(int paramInt)
    {
      b localb;
      switch (paramInt)
      {
      default:
        localb = null;
      case 0:
      case 1:
      case 2:
      }
      while (true)
      {
        return localb;
        localb = BtW;
        continue;
        localb = BtX;
        continue;
        localb = BtY;
      }
    }

    public final int edd()
    {
      return this.value;
    }
  }

  public static final class w$a extends i.a<a.w, a>
    implements a.x
  {
    private int BsD;
    private List<a.w.b> BuO;

    private w$a()
    {
      AppMethodBeat.i(120741);
      this.BuO = Collections.emptyList();
      AppMethodBeat.o(120741);
    }

    private a eeH()
    {
      AppMethodBeat.i(120742);
      a locala = new a().d(eeI());
      AppMethodBeat.o(120742);
      return locala;
    }

    private void eeJ()
    {
      AppMethodBeat.i(120747);
      if ((this.BsD & 0x1) != 1)
      {
        this.BuO = new ArrayList(this.BuO);
        this.BsD |= 1;
      }
      AppMethodBeat.o(120747);
    }

    // ERROR //
    private a p(a.i.b.a.c.g.e parame, g paramg)
    {
      // Byte code:
      //   0: ldc 66
      //   2: invokestatic 26	com/tencent/matrix/trace/core/AppMethodBeat:i	(I)V
      //   5: aconst_null
      //   6: astore_3
      //   7: getstatic 70	a/i/b/a/c/e/a$w:BsC	La/i/b/a/c/g/s;
      //   10: aload_1
      //   11: aload_2
      //   12: invokeinterface 75 3 0
      //   17: checkcast 9	a/i/b/a/c/e/a$w
      //   20: astore_1
      //   21: aload_0
      //   22: aload_1
      //   23: invokevirtual 50	a/i/b/a/c/e/a$w$a:d	(La/i/b/a/c/e/a$w;)La/i/b/a/c/e/a$w$a;
      //   26: pop
      //   27: ldc 66
      //   29: invokestatic 37	com/tencent/matrix/trace/core/AppMethodBeat:o	(I)V
      //   32: aload_0
      //   33: areturn
      //   34: astore_1
      //   35: aload_1
      //   36: getfield 79	a/i/b/a/c/g/k:BzY	La/i/b/a/c/g/q;
      //   39: checkcast 9	a/i/b/a/c/e/a$w
      //   42: astore_2
      //   43: ldc 66
      //   45: invokestatic 37	com/tencent/matrix/trace/core/AppMethodBeat:o	(I)V
      //   48: aload_1
      //   49: athrow
      //   50: astore_1
      //   51: aload_2
      //   52: ifnull +9 -> 61
      //   55: aload_0
      //   56: aload_2
      //   57: invokevirtual 50	a/i/b/a/c/e/a$w$a:d	(La/i/b/a/c/e/a$w;)La/i/b/a/c/e/a$w$a;
      //   60: pop
      //   61: ldc 66
      //   63: invokestatic 37	com/tencent/matrix/trace/core/AppMethodBeat:o	(I)V
      //   66: aload_1
      //   67: athrow
      //   68: astore_1
      //   69: aload_3
      //   70: astore_2
      //   71: goto -20 -> 51
      //
      // Exception table:
      //   from	to	target	type
      //   7	21	34	a/i/b/a/c/g/k
      //   43	50	50	finally
      //   7	21	68	finally
      //   35	43	68	finally
    }

    public final a d(a.w paramw)
    {
      AppMethodBeat.i(120744);
      if (paramw == a.w.eeF())
      {
        AppMethodBeat.o(120744);
        return this;
      }
      if (!a.w.b(paramw).isEmpty())
      {
        if (!this.BuO.isEmpty())
          break label85;
        this.BuO = a.w.b(paramw);
        this.BsD &= -2;
      }
      while (true)
      {
        this.BsB = this.BsB.a(a.w.c(paramw));
        AppMethodBeat.o(120744);
        break;
        label85: eeJ();
        this.BuO.addAll(a.w.b(paramw));
      }
    }

    public final a.w eeI()
    {
      AppMethodBeat.i(120743);
      a.w localw = new a.w(this, (byte)0);
      if ((this.BsD & 0x1) == 1)
      {
        this.BuO = Collections.unmodifiableList(this.BuO);
        this.BsD &= -2;
      }
      a.w.a(localw, this.BuO);
      AppMethodBeat.o(120743);
      return localw;
    }

    public final boolean isInitialized()
    {
      boolean bool = false;
      AppMethodBeat.i(120745);
      int i = 0;
      if (i < this.BuO.size())
        if (!((a.w.b)this.BuO.get(i)).isInitialized())
          AppMethodBeat.o(120745);
      while (true)
      {
        return bool;
        i++;
        break;
        bool = true;
        AppMethodBeat.o(120745);
      }
    }
  }

  public static abstract interface x extends r
  {
  }
}

/* Location:           C:\Users\Lin\Downloads\dex-tools-2.1-SNAPSHOT\dex-tools-2.1-SNAPSHOT\classes6-dex2jar.jar
 * Qualified Name:     a.i.b.a.c.e.a
 * JD-Core Version:    0.6.2
 */