package com.tencent.tmassistantsdk.network;

import com.qq.taf.jce.JceStruct;

class PostHttpRequest$1
  implements Runnable
{
  PostHttpRequest$1(PostHttpRequest paramPostHttpRequest, JceStruct paramJceStruct)
  {
  }

  // ERROR //
  public void run()
  {
    // Byte code:
    //   0: ldc 35
    //   2: invokestatic 41	com/tencent/matrix/trace/core/AppMethodBeat:i	(I)V
    //   5: aload_0
    //   6: getfield 21	com/tencent/tmassistantsdk/network/PostHttpRequest$1:val$sendRequest	Lcom/qq/taf/jce/JceStruct;
    //   9: invokestatic 47	com/tencent/tmassistantsdk/protocol/ProtocolPackage:buildRequest	(Lcom/qq/taf/jce/JceStruct;)Lcom/tencent/tmassistantsdk/protocol/jce/Request;
    //   12: astore_1
    //   13: aload_1
    //   14: invokestatic 51	com/tencent/tmassistantsdk/protocol/ProtocolPackage:buildPostData	(Lcom/tencent/tmassistantsdk/protocol/jce/Request;)[B
    //   17: astore_2
    //   18: aload_0
    //   19: getfield 19	com/tencent/tmassistantsdk/network/PostHttpRequest$1:this$0	Lcom/tencent/tmassistantsdk/network/PostHttpRequest;
    //   22: new 53	org/apache/http/client/methods/HttpPost
    //   25: dup
    //   26: ldc 55
    //   28: invokespecial 58	org/apache/http/client/methods/HttpPost:<init>	(Ljava/lang/String;)V
    //   31: putfield 62	com/tencent/tmassistantsdk/network/PostHttpRequest:mHttpPost	Lorg/apache/http/client/methods/HttpPost;
    //   34: aload_0
    //   35: getfield 19	com/tencent/tmassistantsdk/network/PostHttpRequest$1:this$0	Lcom/tencent/tmassistantsdk/network/PostHttpRequest;
    //   38: getfield 62	com/tencent/tmassistantsdk/network/PostHttpRequest:mHttpPost	Lorg/apache/http/client/methods/HttpPost;
    //   41: ldc 64
    //   43: ldc 66
    //   45: invokevirtual 70	org/apache/http/client/methods/HttpPost:addHeader	(Ljava/lang/String;Ljava/lang/String;)V
    //   48: aload_0
    //   49: getfield 19	com/tencent/tmassistantsdk/network/PostHttpRequest$1:this$0	Lcom/tencent/tmassistantsdk/network/PostHttpRequest;
    //   52: getfield 62	com/tencent/tmassistantsdk/network/PostHttpRequest:mHttpPost	Lorg/apache/http/client/methods/HttpPost;
    //   55: new 72	org/apache/http/entity/ByteArrayEntity
    //   58: dup
    //   59: aload_2
    //   60: invokespecial 75	org/apache/http/entity/ByteArrayEntity:<init>	([B)V
    //   63: invokevirtual 79	org/apache/http/client/methods/HttpPost:setEntity	(Lorg/apache/http/HttpEntity;)V
    //   66: invokestatic 85	com/tencent/tmassistantsdk/downloadservice/HttpClientUtil:createHttpClient	()Lorg/apache/http/client/HttpClient;
    //   69: astore_3
    //   70: aload_3
    //   71: astore_2
    //   72: aload_3
    //   73: invokestatic 89	com/tencent/tmassistantsdk/downloadservice/HttpClientUtil:setProxy	(Lorg/apache/http/client/HttpClient;)V
    //   76: aload_3
    //   77: astore_2
    //   78: aload_3
    //   79: aload_0
    //   80: getfield 19	com/tencent/tmassistantsdk/network/PostHttpRequest$1:this$0	Lcom/tencent/tmassistantsdk/network/PostHttpRequest;
    //   83: getfield 62	com/tencent/tmassistantsdk/network/PostHttpRequest:mHttpPost	Lorg/apache/http/client/methods/HttpPost;
    //   86: invokeinterface 95 2 0
    //   91: astore 4
    //   93: aload 4
    //   95: ifnull +295 -> 390
    //   98: aload_3
    //   99: astore_2
    //   100: aload 4
    //   102: invokeinterface 101 1 0
    //   107: invokeinterface 107 1 0
    //   112: sipush 200
    //   115: if_icmpne +275 -> 390
    //   118: aload_3
    //   119: astore_2
    //   120: aload 4
    //   122: invokeinterface 111 1 0
    //   127: astore 5
    //   129: aload 5
    //   131: ifnull +259 -> 390
    //   134: aload_3
    //   135: astore_2
    //   136: new 113	org/apache/http/util/ByteArrayBuffer
    //   139: astore 4
    //   141: aload_3
    //   142: astore_2
    //   143: aload 4
    //   145: aload 5
    //   147: invokeinterface 119 1 0
    //   152: l2i
    //   153: invokespecial 121	org/apache/http/util/ByteArrayBuffer:<init>	(I)V
    //   156: aload_3
    //   157: astore_2
    //   158: aload 5
    //   160: invokeinterface 125 1 0
    //   165: astore 6
    //   167: aload_3
    //   168: astore_2
    //   169: sipush 2048
    //   172: newarray byte
    //   174: astore 5
    //   176: aload_3
    //   177: astore_2
    //   178: aload 6
    //   180: aload 5
    //   182: invokevirtual 131	java/io/InputStream:read	([B)I
    //   185: istore 7
    //   187: iload 7
    //   189: iconst_m1
    //   190: if_icmpeq +78 -> 268
    //   193: aload_3
    //   194: astore_2
    //   195: aload 4
    //   197: aload 5
    //   199: iconst_0
    //   200: iload 7
    //   202: invokevirtual 135	org/apache/http/util/ByteArrayBuffer:append	([BII)V
    //   205: goto -29 -> 176
    //   208: astore 4
    //   210: aload_3
    //   211: astore_2
    //   212: ldc 137
    //   214: aload 4
    //   216: ldc 139
    //   218: iconst_0
    //   219: anewarray 4	java/lang/Object
    //   222: invokestatic 145	com/tencent/mm/sdk/platformtools/ab:printErrStackTrace	(Ljava/lang/String;Ljava/lang/Throwable;Ljava/lang/String;[Ljava/lang/Object;)V
    //   225: aload_3
    //   226: astore_2
    //   227: aload_0
    //   228: getfield 19	com/tencent/tmassistantsdk/network/PostHttpRequest$1:this$0	Lcom/tencent/tmassistantsdk/network/PostHttpRequest;
    //   231: aload_1
    //   232: aconst_null
    //   233: sipush 601
    //   236: invokevirtual 149	com/tencent/tmassistantsdk/network/PostHttpRequest:onFinished	(Lcom/qq/taf/jce/JceStruct;Lcom/qq/taf/jce/JceStruct;I)V
    //   239: aload_0
    //   240: getfield 19	com/tencent/tmassistantsdk/network/PostHttpRequest$1:this$0	Lcom/tencent/tmassistantsdk/network/PostHttpRequest;
    //   243: aconst_null
    //   244: putfield 62	com/tencent/tmassistantsdk/network/PostHttpRequest:mHttpPost	Lorg/apache/http/client/methods/HttpPost;
    //   247: aload_3
    //   248: ifnull +404 -> 652
    //   251: aload_3
    //   252: invokeinterface 153 1 0
    //   257: invokeinterface 158 1 0
    //   262: ldc 35
    //   264: invokestatic 161	com/tencent/matrix/trace/core/AppMethodBeat:o	(I)V
    //   267: return
    //   268: aload_3
    //   269: astore_2
    //   270: aload 4
    //   272: invokevirtual 165	org/apache/http/util/ByteArrayBuffer:buffer	()[B
    //   275: astore 4
    //   277: aload 4
    //   279: ifnull +111 -> 390
    //   282: aload_3
    //   283: astore_2
    //   284: aload 4
    //   286: arraylength
    //   287: iconst_4
    //   288: if_icmple +102 -> 390
    //   291: aload_3
    //   292: astore_2
    //   293: aload 4
    //   295: invokestatic 169	com/tencent/tmassistantsdk/protocol/ProtocolPackage:unpackPackage	([B)Lcom/tencent/tmassistantsdk/protocol/jce/Response;
    //   298: astore 5
    //   300: aload 5
    //   302: ifnull +88 -> 390
    //   305: aload_3
    //   306: astore_2
    //   307: aload 5
    //   309: getfield 175	com/tencent/tmassistantsdk/protocol/jce/Response:body	[B
    //   312: ifnull +78 -> 390
    //   315: aload_3
    //   316: astore_2
    //   317: aload_0
    //   318: getfield 21	com/tencent/tmassistantsdk/network/PostHttpRequest$1:val$sendRequest	Lcom/qq/taf/jce/JceStruct;
    //   321: aload 5
    //   323: getfield 175	com/tencent/tmassistantsdk/protocol/jce/Response:body	[B
    //   326: invokestatic 179	com/tencent/tmassistantsdk/protocol/ProtocolPackage:unpageageJceResponse	(Lcom/qq/taf/jce/JceStruct;[B)Lcom/qq/taf/jce/JceStruct;
    //   329: astore 4
    //   331: aload 4
    //   333: ifnull +57 -> 390
    //   336: aload_3
    //   337: astore_2
    //   338: aload_0
    //   339: getfield 19	com/tencent/tmassistantsdk/network/PostHttpRequest$1:this$0	Lcom/tencent/tmassistantsdk/network/PostHttpRequest;
    //   342: aload_0
    //   343: getfield 21	com/tencent/tmassistantsdk/network/PostHttpRequest$1:val$sendRequest	Lcom/qq/taf/jce/JceStruct;
    //   346: aload 4
    //   348: aload 5
    //   350: getfield 183	com/tencent/tmassistantsdk/protocol/jce/Response:head	Lcom/tencent/tmassistantsdk/protocol/jce/RspHead;
    //   353: getfield 189	com/tencent/tmassistantsdk/protocol/jce/RspHead:ret	I
    //   356: invokevirtual 149	com/tencent/tmassistantsdk/network/PostHttpRequest:onFinished	(Lcom/qq/taf/jce/JceStruct;Lcom/qq/taf/jce/JceStruct;I)V
    //   359: aload_0
    //   360: getfield 19	com/tencent/tmassistantsdk/network/PostHttpRequest$1:this$0	Lcom/tencent/tmassistantsdk/network/PostHttpRequest;
    //   363: aconst_null
    //   364: putfield 62	com/tencent/tmassistantsdk/network/PostHttpRequest:mHttpPost	Lorg/apache/http/client/methods/HttpPost;
    //   367: aload_3
    //   368: ifnull +14 -> 382
    //   371: aload_3
    //   372: invokeinterface 153 1 0
    //   377: invokeinterface 158 1 0
    //   382: ldc 35
    //   384: invokestatic 161	com/tencent/matrix/trace/core/AppMethodBeat:o	(I)V
    //   387: goto -120 -> 267
    //   390: aload_0
    //   391: getfield 19	com/tencent/tmassistantsdk/network/PostHttpRequest$1:this$0	Lcom/tencent/tmassistantsdk/network/PostHttpRequest;
    //   394: aconst_null
    //   395: putfield 62	com/tencent/tmassistantsdk/network/PostHttpRequest:mHttpPost	Lorg/apache/http/client/methods/HttpPost;
    //   398: aload_3
    //   399: ifnull +253 -> 652
    //   402: aload_3
    //   403: invokeinterface 153 1 0
    //   408: invokeinterface 158 1 0
    //   413: ldc 35
    //   415: invokestatic 161	com/tencent/matrix/trace/core/AppMethodBeat:o	(I)V
    //   418: goto -151 -> 267
    //   421: astore 4
    //   423: aconst_null
    //   424: astore_3
    //   425: aload_3
    //   426: astore_2
    //   427: ldc 137
    //   429: aload 4
    //   431: ldc 139
    //   433: iconst_0
    //   434: anewarray 4	java/lang/Object
    //   437: invokestatic 145	com/tencent/mm/sdk/platformtools/ab:printErrStackTrace	(Ljava/lang/String;Ljava/lang/Throwable;Ljava/lang/String;[Ljava/lang/Object;)V
    //   440: aload_3
    //   441: astore_2
    //   442: aload_0
    //   443: getfield 19	com/tencent/tmassistantsdk/network/PostHttpRequest$1:this$0	Lcom/tencent/tmassistantsdk/network/PostHttpRequest;
    //   446: aload_1
    //   447: aconst_null
    //   448: iconst_1
    //   449: invokevirtual 149	com/tencent/tmassistantsdk/network/PostHttpRequest:onFinished	(Lcom/qq/taf/jce/JceStruct;Lcom/qq/taf/jce/JceStruct;I)V
    //   452: aload_0
    //   453: getfield 19	com/tencent/tmassistantsdk/network/PostHttpRequest$1:this$0	Lcom/tencent/tmassistantsdk/network/PostHttpRequest;
    //   456: aconst_null
    //   457: putfield 62	com/tencent/tmassistantsdk/network/PostHttpRequest:mHttpPost	Lorg/apache/http/client/methods/HttpPost;
    //   460: aload_3
    //   461: ifnull +191 -> 652
    //   464: aload_3
    //   465: invokeinterface 153 1 0
    //   470: invokeinterface 158 1 0
    //   475: ldc 35
    //   477: invokestatic 161	com/tencent/matrix/trace/core/AppMethodBeat:o	(I)V
    //   480: goto -213 -> 267
    //   483: astore 4
    //   485: aconst_null
    //   486: astore_3
    //   487: aload_3
    //   488: astore_2
    //   489: ldc 137
    //   491: aload 4
    //   493: ldc 139
    //   495: iconst_0
    //   496: anewarray 4	java/lang/Object
    //   499: invokestatic 145	com/tencent/mm/sdk/platformtools/ab:printErrStackTrace	(Ljava/lang/String;Ljava/lang/Throwable;Ljava/lang/String;[Ljava/lang/Object;)V
    //   502: aload_3
    //   503: astore_2
    //   504: aload_0
    //   505: getfield 19	com/tencent/tmassistantsdk/network/PostHttpRequest$1:this$0	Lcom/tencent/tmassistantsdk/network/PostHttpRequest;
    //   508: aload_1
    //   509: aconst_null
    //   510: sipush 602
    //   513: invokevirtual 149	com/tencent/tmassistantsdk/network/PostHttpRequest:onFinished	(Lcom/qq/taf/jce/JceStruct;Lcom/qq/taf/jce/JceStruct;I)V
    //   516: aload_0
    //   517: getfield 19	com/tencent/tmassistantsdk/network/PostHttpRequest$1:this$0	Lcom/tencent/tmassistantsdk/network/PostHttpRequest;
    //   520: aconst_null
    //   521: putfield 62	com/tencent/tmassistantsdk/network/PostHttpRequest:mHttpPost	Lorg/apache/http/client/methods/HttpPost;
    //   524: aload_3
    //   525: ifnull +127 -> 652
    //   528: aload_3
    //   529: invokeinterface 153 1 0
    //   534: invokeinterface 158 1 0
    //   539: ldc 35
    //   541: invokestatic 161	com/tencent/matrix/trace/core/AppMethodBeat:o	(I)V
    //   544: goto -277 -> 267
    //   547: astore 4
    //   549: aconst_null
    //   550: astore_3
    //   551: aload_3
    //   552: astore_2
    //   553: ldc 137
    //   555: aload 4
    //   557: ldc 139
    //   559: iconst_0
    //   560: anewarray 4	java/lang/Object
    //   563: invokestatic 145	com/tencent/mm/sdk/platformtools/ab:printErrStackTrace	(Ljava/lang/String;Ljava/lang/Throwable;Ljava/lang/String;[Ljava/lang/Object;)V
    //   566: aload_3
    //   567: astore_2
    //   568: aload_0
    //   569: getfield 19	com/tencent/tmassistantsdk/network/PostHttpRequest$1:this$0	Lcom/tencent/tmassistantsdk/network/PostHttpRequest;
    //   572: aload_0
    //   573: getfield 21	com/tencent/tmassistantsdk/network/PostHttpRequest$1:val$sendRequest	Lcom/qq/taf/jce/JceStruct;
    //   576: aconst_null
    //   577: sipush 604
    //   580: invokevirtual 149	com/tencent/tmassistantsdk/network/PostHttpRequest:onFinished	(Lcom/qq/taf/jce/JceStruct;Lcom/qq/taf/jce/JceStruct;I)V
    //   583: aload_0
    //   584: getfield 19	com/tencent/tmassistantsdk/network/PostHttpRequest$1:this$0	Lcom/tencent/tmassistantsdk/network/PostHttpRequest;
    //   587: aconst_null
    //   588: putfield 62	com/tencent/tmassistantsdk/network/PostHttpRequest:mHttpPost	Lorg/apache/http/client/methods/HttpPost;
    //   591: aload_3
    //   592: ifnull +60 -> 652
    //   595: aload_3
    //   596: invokeinterface 153 1 0
    //   601: invokeinterface 158 1 0
    //   606: ldc 35
    //   608: invokestatic 161	com/tencent/matrix/trace/core/AppMethodBeat:o	(I)V
    //   611: goto -344 -> 267
    //   614: astore_2
    //   615: aconst_null
    //   616: astore 4
    //   618: aload_2
    //   619: astore_3
    //   620: aload_0
    //   621: getfield 19	com/tencent/tmassistantsdk/network/PostHttpRequest$1:this$0	Lcom/tencent/tmassistantsdk/network/PostHttpRequest;
    //   624: aconst_null
    //   625: putfield 62	com/tencent/tmassistantsdk/network/PostHttpRequest:mHttpPost	Lorg/apache/http/client/methods/HttpPost;
    //   628: aload 4
    //   630: ifnull +15 -> 645
    //   633: aload 4
    //   635: invokeinterface 153 1 0
    //   640: invokeinterface 158 1 0
    //   645: ldc 35
    //   647: invokestatic 161	com/tencent/matrix/trace/core/AppMethodBeat:o	(I)V
    //   650: aload_3
    //   651: athrow
    //   652: ldc 35
    //   654: invokestatic 161	com/tencent/matrix/trace/core/AppMethodBeat:o	(I)V
    //   657: goto -390 -> 267
    //   660: astore_3
    //   661: aload_2
    //   662: astore 4
    //   664: goto -44 -> 620
    //   667: astore 4
    //   669: goto -118 -> 551
    //   672: astore 4
    //   674: goto -187 -> 487
    //   677: astore 4
    //   679: goto -254 -> 425
    //   682: astore 4
    //   684: aconst_null
    //   685: astore_3
    //   686: goto -476 -> 210
    //
    // Exception table:
    //   from	to	target	type
    //   72	76	208	org/apache/http/conn/ConnectTimeoutException
    //   78	93	208	org/apache/http/conn/ConnectTimeoutException
    //   100	118	208	org/apache/http/conn/ConnectTimeoutException
    //   120	129	208	org/apache/http/conn/ConnectTimeoutException
    //   136	141	208	org/apache/http/conn/ConnectTimeoutException
    //   143	156	208	org/apache/http/conn/ConnectTimeoutException
    //   158	167	208	org/apache/http/conn/ConnectTimeoutException
    //   169	176	208	org/apache/http/conn/ConnectTimeoutException
    //   178	187	208	org/apache/http/conn/ConnectTimeoutException
    //   195	205	208	org/apache/http/conn/ConnectTimeoutException
    //   270	277	208	org/apache/http/conn/ConnectTimeoutException
    //   284	291	208	org/apache/http/conn/ConnectTimeoutException
    //   293	300	208	org/apache/http/conn/ConnectTimeoutException
    //   307	315	208	org/apache/http/conn/ConnectTimeoutException
    //   317	331	208	org/apache/http/conn/ConnectTimeoutException
    //   338	359	208	org/apache/http/conn/ConnectTimeoutException
    //   66	70	421	java/net/ConnectException
    //   66	70	483	java/net/SocketTimeoutException
    //   66	70	547	java/lang/Exception
    //   66	70	614	finally
    //   72	76	660	finally
    //   78	93	660	finally
    //   100	118	660	finally
    //   120	129	660	finally
    //   136	141	660	finally
    //   143	156	660	finally
    //   158	167	660	finally
    //   169	176	660	finally
    //   178	187	660	finally
    //   195	205	660	finally
    //   212	225	660	finally
    //   227	239	660	finally
    //   270	277	660	finally
    //   284	291	660	finally
    //   293	300	660	finally
    //   307	315	660	finally
    //   317	331	660	finally
    //   338	359	660	finally
    //   427	440	660	finally
    //   442	452	660	finally
    //   489	502	660	finally
    //   504	516	660	finally
    //   553	566	660	finally
    //   568	583	660	finally
    //   72	76	667	java/lang/Exception
    //   78	93	667	java/lang/Exception
    //   100	118	667	java/lang/Exception
    //   120	129	667	java/lang/Exception
    //   136	141	667	java/lang/Exception
    //   143	156	667	java/lang/Exception
    //   158	167	667	java/lang/Exception
    //   169	176	667	java/lang/Exception
    //   178	187	667	java/lang/Exception
    //   195	205	667	java/lang/Exception
    //   270	277	667	java/lang/Exception
    //   284	291	667	java/lang/Exception
    //   293	300	667	java/lang/Exception
    //   307	315	667	java/lang/Exception
    //   317	331	667	java/lang/Exception
    //   338	359	667	java/lang/Exception
    //   72	76	672	java/net/SocketTimeoutException
    //   78	93	672	java/net/SocketTimeoutException
    //   100	118	672	java/net/SocketTimeoutException
    //   120	129	672	java/net/SocketTimeoutException
    //   136	141	672	java/net/SocketTimeoutException
    //   143	156	672	java/net/SocketTimeoutException
    //   158	167	672	java/net/SocketTimeoutException
    //   169	176	672	java/net/SocketTimeoutException
    //   178	187	672	java/net/SocketTimeoutException
    //   195	205	672	java/net/SocketTimeoutException
    //   270	277	672	java/net/SocketTimeoutException
    //   284	291	672	java/net/SocketTimeoutException
    //   293	300	672	java/net/SocketTimeoutException
    //   307	315	672	java/net/SocketTimeoutException
    //   317	331	672	java/net/SocketTimeoutException
    //   338	359	672	java/net/SocketTimeoutException
    //   72	76	677	java/net/ConnectException
    //   78	93	677	java/net/ConnectException
    //   100	118	677	java/net/ConnectException
    //   120	129	677	java/net/ConnectException
    //   136	141	677	java/net/ConnectException
    //   143	156	677	java/net/ConnectException
    //   158	167	677	java/net/ConnectException
    //   169	176	677	java/net/ConnectException
    //   178	187	677	java/net/ConnectException
    //   195	205	677	java/net/ConnectException
    //   270	277	677	java/net/ConnectException
    //   284	291	677	java/net/ConnectException
    //   293	300	677	java/net/ConnectException
    //   307	315	677	java/net/ConnectException
    //   317	331	677	java/net/ConnectException
    //   338	359	677	java/net/ConnectException
    //   66	70	682	org/apache/http/conn/ConnectTimeoutException
  }
}

/* Location:           C:\Users\Lin\Downloads\dex-tools-2.1-SNAPSHOT\dex-tools-2.1-SNAPSHOT\classes-dex2jar.jar
 * Qualified Name:     com.tencent.tmassistantsdk.network.PostHttpRequest.1
 * JD-Core Version:    0.6.2
 */