package com.tencent.mm.ah;

import com.tencent.matrix.trace.core.AppMethodBeat;
import com.tencent.mm.model.ao.a;
import com.tencent.mm.model.ao.e;
import com.tencent.mm.sdk.platformtools.az.a;
import com.tencent.mm.sdk.platformtools.bo;
import java.util.Set;

final class c$b
  implements az.a
{
  public boolean frq = false;
  public h frs = null;
  public byte[] frt = null;

  public c$b(c paramc, h paramh)
  {
    this.frs = paramh;
  }

  // ERROR //
  public final boolean acf()
  {
    // Byte code:
    //   0: ldc 42
    //   2: invokestatic 48	com/tencent/matrix/trace/core/AppMethodBeat:i	(I)V
    //   5: aload_0
    //   6: getfield 26	com/tencent/mm/ah/c$b:frs	Lcom/tencent/mm/ah/h;
    //   9: ifnonnull +12 -> 21
    //   12: iconst_0
    //   13: istore_1
    //   14: ldc 42
    //   16: invokestatic 51	com/tencent/matrix/trace/core/AppMethodBeat:o	(I)V
    //   19: iload_1
    //   20: ireturn
    //   21: invokestatic 57	com/tencent/mm/sdk/platformtools/ah:getContext	()Landroid/content/Context;
    //   24: invokestatic 63	com/tencent/mm/sdk/platformtools/at:isNetworkConnected	(Landroid/content/Context;)Z
    //   27: ifne +13 -> 40
    //   30: ldc 65
    //   32: ldc 67
    //   34: invokestatic 73	com/tencent/mm/sdk/platformtools/ab:w	(Ljava/lang/String;Ljava/lang/String;)V
    //   37: invokestatic 76	com/tencent/mm/sdk/platformtools/ab:dot	()V
    //   40: aload_0
    //   41: getfield 26	com/tencent/mm/ah/c$b:frs	Lcom/tencent/mm/ah/h;
    //   44: invokevirtual 82	com/tencent/mm/ah/h:acl	()Ljava/lang/String;
    //   47: astore_2
    //   48: ldc 84
    //   50: invokestatic 90	com/tencent/mm/kernel/g:K	(Ljava/lang/Class;)Lcom/tencent/mm/kernel/c/a;
    //   53: checkcast 84	com/tencent/mm/plugin/emoji/b/c
    //   56: invokeinterface 93 1 0
    //   61: istore_1
    //   62: ldc 95
    //   64: invokestatic 90	com/tencent/mm/kernel/g:K	(Ljava/lang/Class;)Lcom/tencent/mm/kernel/c/a;
    //   67: checkcast 95	com/tencent/mm/plugin/expt/a/a
    //   70: getstatic 101	com/tencent/mm/plugin/expt/a/a$a:lJe	Lcom/tencent/mm/plugin/expt/a/a$a;
    //   73: iconst_0
    //   74: invokeinterface 105 3 0
    //   79: istore_3
    //   80: iload_1
    //   81: ifeq +4294 -> 4375
    //   84: iload_3
    //   85: ifeq +4290 -> 4375
    //   88: ldc 65
    //   90: ldc 107
    //   92: invokestatic 109	com/tencent/mm/sdk/platformtools/ab:i	(Ljava/lang/String;Ljava/lang/String;)V
    //   95: aload_2
    //   96: ldc 111
    //   98: invokevirtual 117	java/lang/String:contains	(Ljava/lang/CharSequence;)Z
    //   101: ifeq +1151 -> 1252
    //   104: new 119	java/lang/StringBuilder
    //   107: dup
    //   108: invokespecial 120	java/lang/StringBuilder:<init>	()V
    //   111: aload_2
    //   112: invokevirtual 124	java/lang/StringBuilder:append	(Ljava/lang/String;)Ljava/lang/StringBuilder;
    //   115: ldc 126
    //   117: invokevirtual 124	java/lang/StringBuilder:append	(Ljava/lang/String;)Ljava/lang/StringBuilder;
    //   120: invokevirtual 129	java/lang/StringBuilder:toString	()Ljava/lang/String;
    //   123: astore 4
    //   125: getstatic 135	com/tencent/mm/plugin/report/service/h:pYm	Lcom/tencent/mm/plugin/report/service/h;
    //   128: ldc2_w 136
    //   131: ldc2_w 138
    //   134: lconst_1
    //   135: invokevirtual 143	com/tencent/mm/plugin/report/service/h:k	(JJJ)V
    //   138: aload 4
    //   140: astore_2
    //   141: ldc 145
    //   143: astore 5
    //   145: invokestatic 149	com/tencent/mm/kernel/g:RN	()Lcom/tencent/mm/kernel/a;
    //   148: invokevirtual 154	com/tencent/mm/kernel/a:QY	()Z
    //   151: ifeq +64 -> 215
    //   154: getstatic 160	com/tencent/mm/protocal/d:vxo	I
    //   157: istore 6
    //   159: invokestatic 149	com/tencent/mm/kernel/g:RN	()Lcom/tencent/mm/kernel/a;
    //   162: pop
    //   163: ldc 162
    //   165: iconst_4
    //   166: anewarray 4	java/lang/Object
    //   169: dup
    //   170: iconst_0
    //   171: iload 6
    //   173: invokestatic 168	java/lang/Integer:valueOf	(I)Ljava/lang/Integer;
    //   176: aastore
    //   177: dup
    //   178: iconst_1
    //   179: invokestatic 172	com/tencent/mm/kernel/a:QF	()I
    //   182: invokestatic 178	com/tencent/mm/a/p:getString	(I)Ljava/lang/String;
    //   185: aastore
    //   186: dup
    //   187: iconst_2
    //   188: invokestatic 57	com/tencent/mm/sdk/platformtools/ah:getContext	()Landroid/content/Context;
    //   191: invokestatic 182	com/tencent/mm/sdk/platformtools/at:getNetTypeForStat	(Landroid/content/Context;)I
    //   194: invokestatic 168	java/lang/Integer:valueOf	(I)Ljava/lang/Integer;
    //   197: aastore
    //   198: dup
    //   199: iconst_3
    //   200: invokestatic 57	com/tencent/mm/sdk/platformtools/ah:getContext	()Landroid/content/Context;
    //   203: invokestatic 185	com/tencent/mm/sdk/platformtools/at:getStrength	(Landroid/content/Context;)I
    //   206: invokestatic 168	java/lang/Integer:valueOf	(I)Ljava/lang/Integer;
    //   209: aastore
    //   210: invokestatic 189	java/lang/String:format	(Ljava/lang/String;[Ljava/lang/Object;)Ljava/lang/String;
    //   213: astore 5
    //   215: ldc 65
    //   217: ldc 191
    //   219: iconst_2
    //   220: anewarray 4	java/lang/Object
    //   223: dup
    //   224: iconst_0
    //   225: aload_0
    //   226: getfield 26	com/tencent/mm/ah/c$b:frs	Lcom/tencent/mm/ah/h;
    //   229: invokevirtual 194	com/tencent/mm/ah/h:getUsername	()Ljava/lang/String;
    //   232: aastore
    //   233: dup
    //   234: iconst_1
    //   235: aload 5
    //   237: aastore
    //   238: invokestatic 198	com/tencent/mm/sdk/platformtools/ab:d	(Ljava/lang/String;Ljava/lang/String;[Ljava/lang/Object;)V
    //   241: aload_0
    //   242: aconst_null
    //   243: putfield 28	com/tencent/mm/ah/c$b:frt	[B
    //   246: aconst_null
    //   247: astore 7
    //   249: aconst_null
    //   250: astore 8
    //   252: aconst_null
    //   253: astore 9
    //   255: aconst_null
    //   256: astore 10
    //   258: new 200	java/io/ByteArrayOutputStream
    //   261: dup
    //   262: invokespecial 201	java/io/ByteArrayOutputStream:<init>	()V
    //   265: astore 11
    //   267: aconst_null
    //   268: astore 12
    //   270: aconst_null
    //   271: astore 13
    //   273: aconst_null
    //   274: astore 14
    //   276: aconst_null
    //   277: astore 15
    //   279: getstatic 135	com/tencent/mm/plugin/report/service/h:pYm	Lcom/tencent/mm/plugin/report/service/h;
    //   282: ldc2_w 136
    //   285: ldc2_w 202
    //   288: lconst_1
    //   289: iconst_1
    //   290: invokevirtual 206	com/tencent/mm/plugin/report/service/h:a	(JJJZ)V
    //   293: aload 15
    //   295: astore 16
    //   297: aload 11
    //   299: astore 17
    //   301: aload 12
    //   303: astore 18
    //   305: aload 11
    //   307: astore 19
    //   309: aload 13
    //   311: astore 20
    //   313: aload 11
    //   315: astore 21
    //   317: aload 14
    //   319: astore 22
    //   321: aload 11
    //   323: astore 23
    //   325: aload_2
    //   326: aconst_null
    //   327: invokestatic 211	com/tencent/mm/network/b:a	(Ljava/lang/String;Lcom/tencent/mm/network/b$b;)Lcom/tencent/mm/network/u;
    //   330: astore 4
    //   332: aload 15
    //   334: astore 16
    //   336: aload 11
    //   338: astore 17
    //   340: aload 4
    //   342: astore 10
    //   344: aload 12
    //   346: astore 18
    //   348: aload 11
    //   350: astore 19
    //   352: aload 4
    //   354: astore 7
    //   356: aload 13
    //   358: astore 20
    //   360: aload 11
    //   362: astore 21
    //   364: aload 4
    //   366: astore 8
    //   368: aload 14
    //   370: astore 22
    //   372: aload 11
    //   374: astore 23
    //   376: aload 4
    //   378: astore 9
    //   380: aload 4
    //   382: ldc 213
    //   384: invokevirtual 219	com/tencent/mm/network/u:setRequestMethod	(Ljava/lang/String;)V
    //   387: aload 15
    //   389: astore 16
    //   391: aload 11
    //   393: astore 17
    //   395: aload 4
    //   397: astore 10
    //   399: aload 12
    //   401: astore 18
    //   403: aload 11
    //   405: astore 19
    //   407: aload 4
    //   409: astore 7
    //   411: aload 13
    //   413: astore 20
    //   415: aload 11
    //   417: astore 21
    //   419: aload 4
    //   421: astore 8
    //   423: aload 14
    //   425: astore 22
    //   427: aload 11
    //   429: astore 23
    //   431: aload 4
    //   433: astore 9
    //   435: aload 4
    //   437: ldc 221
    //   439: aload 5
    //   441: invokevirtual 224	com/tencent/mm/network/u:setRequestProperty	(Ljava/lang/String;Ljava/lang/String;)V
    //   444: aload 15
    //   446: astore 16
    //   448: aload 11
    //   450: astore 17
    //   452: aload 4
    //   454: astore 10
    //   456: aload 12
    //   458: astore 18
    //   460: aload 11
    //   462: astore 19
    //   464: aload 4
    //   466: astore 7
    //   468: aload 13
    //   470: astore 20
    //   472: aload 11
    //   474: astore 21
    //   476: aload 4
    //   478: astore 8
    //   480: aload 14
    //   482: astore 22
    //   484: aload 11
    //   486: astore 23
    //   488: aload 4
    //   490: astore 9
    //   492: aload 4
    //   494: sipush 5000
    //   497: invokevirtual 227	com/tencent/mm/network/u:setConnectTimeout	(I)V
    //   500: aload 15
    //   502: astore 16
    //   504: aload 11
    //   506: astore 17
    //   508: aload 4
    //   510: astore 10
    //   512: aload 12
    //   514: astore 18
    //   516: aload 11
    //   518: astore 19
    //   520: aload 4
    //   522: astore 7
    //   524: aload 13
    //   526: astore 20
    //   528: aload 11
    //   530: astore 21
    //   532: aload 4
    //   534: astore 8
    //   536: aload 14
    //   538: astore 22
    //   540: aload 11
    //   542: astore 23
    //   544: aload 4
    //   546: astore 9
    //   548: aload 4
    //   550: sipush 5000
    //   553: invokevirtual 230	com/tencent/mm/network/u:setReadTimeout	(I)V
    //   556: aload 15
    //   558: astore 16
    //   560: aload 11
    //   562: astore 17
    //   564: aload 4
    //   566: astore 10
    //   568: aload 12
    //   570: astore 18
    //   572: aload 11
    //   574: astore 19
    //   576: aload 4
    //   578: astore 7
    //   580: aload 13
    //   582: astore 20
    //   584: aload 11
    //   586: astore 21
    //   588: aload 4
    //   590: astore 8
    //   592: aload 14
    //   594: astore 22
    //   596: aload 11
    //   598: astore 23
    //   600: aload 4
    //   602: astore 9
    //   604: aload 4
    //   606: invokestatic 233	com/tencent/mm/network/b:a	(Lcom/tencent/mm/network/u;)I
    //   609: ifeq +2325 -> 2934
    //   612: aload 15
    //   614: astore 16
    //   616: aload 11
    //   618: astore 17
    //   620: aload 4
    //   622: astore 10
    //   624: aload 12
    //   626: astore 18
    //   628: aload 11
    //   630: astore 19
    //   632: aload 4
    //   634: astore 7
    //   636: aload 13
    //   638: astore 20
    //   640: aload 11
    //   642: astore 21
    //   644: aload 4
    //   646: astore 8
    //   648: aload 14
    //   650: astore 22
    //   652: aload 11
    //   654: astore 23
    //   656: aload 4
    //   658: astore 9
    //   660: aload 4
    //   662: invokevirtual 236	com/tencent/mm/network/u:getResponseCode	()I
    //   665: istore 6
    //   667: aload 15
    //   669: astore 16
    //   671: aload 11
    //   673: astore 17
    //   675: aload 4
    //   677: astore 10
    //   679: aload 12
    //   681: astore 18
    //   683: aload 11
    //   685: astore 19
    //   687: aload 4
    //   689: astore 7
    //   691: aload 13
    //   693: astore 20
    //   695: aload 11
    //   697: astore 21
    //   699: aload 4
    //   701: astore 8
    //   703: aload 14
    //   705: astore 22
    //   707: aload 11
    //   709: astore 23
    //   711: aload 4
    //   713: astore 9
    //   715: aload 4
    //   717: invokevirtual 240	com/tencent/mm/network/u:getHeaderFields	()Ljava/util/Map;
    //   720: astore 5
    //   722: aload 5
    //   724: ifnull +553 -> 1277
    //   727: aload 15
    //   729: astore 16
    //   731: aload 11
    //   733: astore 17
    //   735: aload 4
    //   737: astore 10
    //   739: aload 12
    //   741: astore 18
    //   743: aload 11
    //   745: astore 19
    //   747: aload 4
    //   749: astore 7
    //   751: aload 13
    //   753: astore 20
    //   755: aload 11
    //   757: astore 21
    //   759: aload 4
    //   761: astore 8
    //   763: aload 14
    //   765: astore 22
    //   767: aload 11
    //   769: astore 23
    //   771: aload 4
    //   773: astore 9
    //   775: aload 5
    //   777: ldc 242
    //   779: invokeinterface 248 2 0
    //   784: checkcast 250	java/util/List
    //   787: astore 5
    //   789: aload 5
    //   791: ifnull +492 -> 1283
    //   794: aload 15
    //   796: astore 16
    //   798: aload 11
    //   800: astore 17
    //   802: aload 4
    //   804: astore 10
    //   806: aload 12
    //   808: astore 18
    //   810: aload 11
    //   812: astore 19
    //   814: aload 4
    //   816: astore 7
    //   818: aload 13
    //   820: astore 20
    //   822: aload 11
    //   824: astore 21
    //   826: aload 4
    //   828: astore 8
    //   830: aload 14
    //   832: astore 22
    //   834: aload 11
    //   836: astore 23
    //   838: aload 4
    //   840: astore 9
    //   842: aload 5
    //   844: invokeinterface 253 1 0
    //   849: ifle +434 -> 1283
    //   852: aload 15
    //   854: astore 16
    //   856: aload 11
    //   858: astore 17
    //   860: aload 4
    //   862: astore 10
    //   864: aload 12
    //   866: astore 18
    //   868: aload 11
    //   870: astore 19
    //   872: aload 4
    //   874: astore 7
    //   876: aload 13
    //   878: astore 20
    //   880: aload 11
    //   882: astore 21
    //   884: aload 4
    //   886: astore 8
    //   888: aload 14
    //   890: astore 22
    //   892: aload 11
    //   894: astore 23
    //   896: aload 4
    //   898: astore 9
    //   900: aload 5
    //   902: iconst_0
    //   903: invokeinterface 256 2 0
    //   908: checkcast 113	java/lang/String
    //   911: astore 5
    //   913: aload 15
    //   915: astore 16
    //   917: aload 11
    //   919: astore 17
    //   921: aload 4
    //   923: astore 10
    //   925: aload 12
    //   927: astore 18
    //   929: aload 11
    //   931: astore 19
    //   933: aload 4
    //   935: astore 7
    //   937: aload 13
    //   939: astore 20
    //   941: aload 11
    //   943: astore 21
    //   945: aload 4
    //   947: astore 8
    //   949: aload 14
    //   951: astore 22
    //   953: aload 11
    //   955: astore 23
    //   957: aload 4
    //   959: astore 9
    //   961: ldc 65
    //   963: ldc_w 258
    //   966: iconst_3
    //   967: anewarray 4	java/lang/Object
    //   970: dup
    //   971: iconst_0
    //   972: aload_2
    //   973: aastore
    //   974: dup
    //   975: iconst_1
    //   976: iload 6
    //   978: invokestatic 168	java/lang/Integer:valueOf	(I)Ljava/lang/Integer;
    //   981: aastore
    //   982: dup
    //   983: iconst_2
    //   984: aload 5
    //   986: aastore
    //   987: invokestatic 261	com/tencent/mm/sdk/platformtools/ab:e	(Ljava/lang/String;Ljava/lang/String;[Ljava/lang/Object;)V
    //   990: iload 6
    //   992: lookupswitch	default:+44->1036, 404:+298->1290, 502:+738->1730, 503:+1140->2132, 504:+1542->2534
    //   1037: dconst_1
    //   1038: astore 16
    //   1040: aload 11
    //   1042: astore 17
    //   1044: aload 4
    //   1046: astore 10
    //   1048: aload 12
    //   1050: astore 18
    //   1052: aload 11
    //   1054: astore 19
    //   1056: aload 4
    //   1058: astore 7
    //   1060: aload 13
    //   1062: astore 20
    //   1064: aload 11
    //   1066: astore 21
    //   1068: aload 4
    //   1070: astore 8
    //   1072: aload 14
    //   1074: astore 22
    //   1076: aload 11
    //   1078: astore 23
    //   1080: aload 4
    //   1082: astore 9
    //   1084: getstatic 135	com/tencent/mm/plugin/report/service/h:pYm	Lcom/tencent/mm/plugin/report/service/h;
    //   1087: ldc2_w 136
    //   1090: ldc2_w 262
    //   1093: lconst_1
    //   1094: iconst_1
    //   1095: invokevirtual 206	com/tencent/mm/plugin/report/service/h:a	(JJJZ)V
    //   1098: aload 15
    //   1100: astore 16
    //   1102: aload 11
    //   1104: astore 17
    //   1106: aload 4
    //   1108: astore 10
    //   1110: aload 12
    //   1112: astore 18
    //   1114: aload 11
    //   1116: astore 19
    //   1118: aload 4
    //   1120: astore 7
    //   1122: aload 13
    //   1124: astore 20
    //   1126: aload 11
    //   1128: astore 21
    //   1130: aload 4
    //   1132: astore 8
    //   1134: aload 14
    //   1136: astore 22
    //   1138: aload 11
    //   1140: astore 23
    //   1142: aload 4
    //   1144: astore 9
    //   1146: getstatic 135	com/tencent/mm/plugin/report/service/h:pYm	Lcom/tencent/mm/plugin/report/service/h;
    //   1149: sipush 14058
    //   1152: bipush 10
    //   1154: anewarray 4	java/lang/Object
    //   1157: dup
    //   1158: iconst_0
    //   1159: ldc_w 264
    //   1162: invokestatic 168	java/lang/Integer:valueOf	(I)Ljava/lang/Integer;
    //   1165: aastore
    //   1166: dup
    //   1167: iconst_1
    //   1168: iload 6
    //   1170: invokestatic 168	java/lang/Integer:valueOf	(I)Ljava/lang/Integer;
    //   1173: aastore
    //   1174: dup
    //   1175: iconst_2
    //   1176: ldc 145
    //   1178: aastore
    //   1179: dup
    //   1180: iconst_3
    //   1181: iconst_0
    //   1182: invokestatic 168	java/lang/Integer:valueOf	(I)Ljava/lang/Integer;
    //   1185: aastore
    //   1186: dup
    //   1187: iconst_4
    //   1188: aload_0
    //   1189: getfield 26	com/tencent/mm/ah/c$b:frs	Lcom/tencent/mm/ah/h;
    //   1192: invokevirtual 194	com/tencent/mm/ah/h:getUsername	()Ljava/lang/String;
    //   1195: aastore
    //   1196: dup
    //   1197: iconst_5
    //   1198: aload 4
    //   1200: getfield 268	com/tencent/mm/network/u:gdF	Ljava/lang/String;
    //   1203: aastore
    //   1204: dup
    //   1205: bipush 6
    //   1207: aload 4
    //   1209: getfield 271	com/tencent/mm/network/u:gcI	I
    //   1212: invokestatic 168	java/lang/Integer:valueOf	(I)Ljava/lang/Integer;
    //   1215: aastore
    //   1216: dup
    //   1217: bipush 7
    //   1219: aload 4
    //   1221: getfield 275	com/tencent/mm/network/u:url	Ljava/net/URL;
    //   1224: invokevirtual 280	java/net/URL:getHost	()Ljava/lang/String;
    //   1227: aastore
    //   1228: dup
    //   1229: bipush 8
    //   1231: aload_2
    //   1232: aastore
    //   1233: dup
    //   1234: bipush 9
    //   1236: aload 5
    //   1238: aastore
    //   1239: invokevirtual 283	com/tencent/mm/plugin/report/service/h:e	(I[Ljava/lang/Object;)V
    //   1242: iconst_1
    //   1243: istore_1
    //   1244: ldc 42
    //   1246: invokestatic 51	com/tencent/matrix/trace/core/AppMethodBeat:o	(I)V
    //   1249: goto -1230 -> 19
    //   1252: new 119	java/lang/StringBuilder
    //   1255: dup
    //   1256: invokespecial 120	java/lang/StringBuilder:<init>	()V
    //   1259: aload_2
    //   1260: invokevirtual 124	java/lang/StringBuilder:append	(Ljava/lang/String;)Ljava/lang/StringBuilder;
    //   1263: ldc_w 285
    //   1266: invokevirtual 124	java/lang/StringBuilder:append	(Ljava/lang/String;)Ljava/lang/StringBuilder;
    //   1269: invokevirtual 129	java/lang/StringBuilder:toString	()Ljava/lang/String;
    //   1272: astore 4
    //   1274: goto -1149 -> 125
    //   1277: aconst_null
    //   1278: astore 5
    //   1280: goto -491 -> 789
    //   1283: ldc 145
    //   1285: astore 5
    //   1287: goto -374 -> 913
    //   1290: aload 15
    //   1292: astore 16
    //   1294: aload 11
    //   1296: astore 17
    //   1298: aload 4
    //   1300: astore 10
    //   1302: aload 12
    //   1304: astore 18
    //   1306: aload 11
    //   1308: astore 19
    //   1310: aload 4
    //   1312: astore 7
    //   1314: aload 13
    //   1316: astore 20
    //   1318: aload 11
    //   1320: astore 21
    //   1322: aload 4
    //   1324: astore 8
    //   1326: aload 14
    //   1328: astore 22
    //   1330: aload 11
    //   1332: astore 23
    //   1334: aload 4
    //   1336: astore 9
    //   1338: getstatic 135	com/tencent/mm/plugin/report/service/h:pYm	Lcom/tencent/mm/plugin/report/service/h;
    //   1341: ldc2_w 136
    //   1344: ldc2_w 286
    //   1347: lconst_1
    //   1348: iconst_1
    //   1349: invokevirtual 206	com/tencent/mm/plugin/report/service/h:a	(JJJZ)V
    //   1352: aload 15
    //   1354: astore 16
    //   1356: aload 11
    //   1358: astore 17
    //   1360: aload 4
    //   1362: astore 10
    //   1364: aload 12
    //   1366: astore 18
    //   1368: aload 11
    //   1370: astore 19
    //   1372: aload 4
    //   1374: astore 7
    //   1376: aload 13
    //   1378: astore 20
    //   1380: aload 11
    //   1382: astore 21
    //   1384: aload 4
    //   1386: astore 8
    //   1388: aload 14
    //   1390: astore 22
    //   1392: aload 11
    //   1394: astore 23
    //   1396: aload 4
    //   1398: astore 9
    //   1400: getstatic 135	com/tencent/mm/plugin/report/service/h:pYm	Lcom/tencent/mm/plugin/report/service/h;
    //   1403: sipush 14058
    //   1406: bipush 10
    //   1408: anewarray 4	java/lang/Object
    //   1411: dup
    //   1412: iconst_0
    //   1413: ldc_w 264
    //   1416: invokestatic 168	java/lang/Integer:valueOf	(I)Ljava/lang/Integer;
    //   1419: aastore
    //   1420: dup
    //   1421: iconst_1
    //   1422: iload 6
    //   1424: invokestatic 168	java/lang/Integer:valueOf	(I)Ljava/lang/Integer;
    //   1427: aastore
    //   1428: dup
    //   1429: iconst_2
    //   1430: ldc 145
    //   1432: aastore
    //   1433: dup
    //   1434: iconst_3
    //   1435: iconst_0
    //   1436: invokestatic 168	java/lang/Integer:valueOf	(I)Ljava/lang/Integer;
    //   1439: aastore
    //   1440: dup
    //   1441: iconst_4
    //   1442: aload_0
    //   1443: getfield 26	com/tencent/mm/ah/c$b:frs	Lcom/tencent/mm/ah/h;
    //   1446: invokevirtual 194	com/tencent/mm/ah/h:getUsername	()Ljava/lang/String;
    //   1449: aastore
    //   1450: dup
    //   1451: iconst_5
    //   1452: aload 4
    //   1454: getfield 268	com/tencent/mm/network/u:gdF	Ljava/lang/String;
    //   1457: aastore
    //   1458: dup
    //   1459: bipush 6
    //   1461: aload 4
    //   1463: getfield 271	com/tencent/mm/network/u:gcI	I
    //   1466: invokestatic 168	java/lang/Integer:valueOf	(I)Ljava/lang/Integer;
    //   1469: aastore
    //   1470: dup
    //   1471: bipush 7
    //   1473: aload 4
    //   1475: getfield 275	com/tencent/mm/network/u:url	Ljava/net/URL;
    //   1478: invokevirtual 280	java/net/URL:getHost	()Ljava/lang/String;
    //   1481: aastore
    //   1482: dup
    //   1483: bipush 8
    //   1485: aload_2
    //   1486: aastore
    //   1487: dup
    //   1488: bipush 9
    //   1490: aload 5
    //   1492: aastore
    //   1493: invokevirtual 283	com/tencent/mm/plugin/report/service/h:e	(I[Ljava/lang/Object;)V
    //   1496: goto -254 -> 1242
    //   1499: astore 18
    //   1501: getstatic 135	com/tencent/mm/plugin/report/service/h:pYm	Lcom/tencent/mm/plugin/report/service/h;
    //   1504: ldc2_w 136
    //   1507: lconst_1
    //   1508: lconst_1
    //   1509: iconst_1
    //   1510: invokevirtual 206	com/tencent/mm/plugin/report/service/h:a	(JJJZ)V
    //   1513: getstatic 135	com/tencent/mm/plugin/report/service/h:pYm	Lcom/tencent/mm/plugin/report/service/h;
    //   1516: astore 20
    //   1518: aload 18
    //   1520: invokevirtual 290	java/net/ProtocolException:getMessage	()Ljava/lang/String;
    //   1523: astore 7
    //   1525: aload_0
    //   1526: getfield 26	com/tencent/mm/ah/c$b:frs	Lcom/tencent/mm/ah/h;
    //   1529: invokevirtual 194	com/tencent/mm/ah/h:getUsername	()Ljava/lang/String;
    //   1532: astore 22
    //   1534: aload 10
    //   1536: ifnonnull +2636 -> 4172
    //   1539: ldc_w 292
    //   1542: astore 4
    //   1544: aload 10
    //   1546: ifnonnull +2636 -> 4182
    //   1549: ldc_w 292
    //   1552: astore 11
    //   1554: aload 10
    //   1556: ifnonnull +2639 -> 4195
    //   1559: ldc_w 292
    //   1562: astore 5
    //   1564: aload 20
    //   1566: sipush 14058
    //   1569: bipush 10
    //   1571: anewarray 4	java/lang/Object
    //   1574: dup
    //   1575: iconst_0
    //   1576: ldc_w 264
    //   1579: invokestatic 168	java/lang/Integer:valueOf	(I)Ljava/lang/Integer;
    //   1582: aastore
    //   1583: dup
    //   1584: iconst_1
    //   1585: sipush 10001
    //   1588: invokestatic 168	java/lang/Integer:valueOf	(I)Ljava/lang/Integer;
    //   1591: aastore
    //   1592: dup
    //   1593: iconst_2
    //   1594: aload 7
    //   1596: aastore
    //   1597: dup
    //   1598: iconst_3
    //   1599: iconst_0
    //   1600: invokestatic 168	java/lang/Integer:valueOf	(I)Ljava/lang/Integer;
    //   1603: aastore
    //   1604: dup
    //   1605: iconst_4
    //   1606: aload 22
    //   1608: aastore
    //   1609: dup
    //   1610: iconst_5
    //   1611: aload 4
    //   1613: aastore
    //   1614: dup
    //   1615: bipush 6
    //   1617: aload 11
    //   1619: aastore
    //   1620: dup
    //   1621: bipush 7
    //   1623: aload 5
    //   1625: aastore
    //   1626: dup
    //   1627: bipush 8
    //   1629: aload_2
    //   1630: aastore
    //   1631: dup
    //   1632: bipush 9
    //   1634: ldc 145
    //   1636: aastore
    //   1637: invokevirtual 283	com/tencent/mm/plugin/report/service/h:e	(I[Ljava/lang/Object;)V
    //   1640: ldc 65
    //   1642: ldc_w 294
    //   1645: iconst_3
    //   1646: anewarray 4	java/lang/Object
    //   1649: dup
    //   1650: iconst_0
    //   1651: aload_2
    //   1652: aastore
    //   1653: dup
    //   1654: iconst_1
    //   1655: aload 18
    //   1657: invokevirtual 298	java/lang/Object:getClass	()Ljava/lang/Class;
    //   1660: invokevirtual 303	java/lang/Class:getSimpleName	()Ljava/lang/String;
    //   1663: aastore
    //   1664: dup
    //   1665: iconst_2
    //   1666: aload 18
    //   1668: invokevirtual 290	java/net/ProtocolException:getMessage	()Ljava/lang/String;
    //   1671: aastore
    //   1672: invokestatic 261	com/tencent/mm/sdk/platformtools/ab:e	(Ljava/lang/String;Ljava/lang/String;[Ljava/lang/Object;)V
    //   1675: aload 10
    //   1677: astore 5
    //   1679: aload 17
    //   1681: astore 4
    //   1683: aload 16
    //   1685: astore 11
    //   1687: aload 5
    //   1689: ifnull +11 -> 1700
    //   1692: aload 5
    //   1694: getfield 307	com/tencent/mm/network/u:connection	Ljava/net/HttpURLConnection;
    //   1697: invokevirtual 312	java/net/HttpURLConnection:disconnect	()V
    //   1700: aload 11
    //   1702: ifnull +8 -> 1710
    //   1705: aload 11
    //   1707: invokevirtual 317	java/io/InputStream:close	()V
    //   1710: aload 4
    //   1712: ifnull +8 -> 1720
    //   1715: aload 4
    //   1717: invokevirtual 318	java/io/ByteArrayOutputStream:close	()V
    //   1720: iconst_1
    //   1721: istore_1
    //   1722: ldc 42
    //   1724: invokestatic 51	com/tencent/matrix/trace/core/AppMethodBeat:o	(I)V
    //   1727: goto -1708 -> 19
    //   1730: aload 15
    //   1732: astore 16
    //   1734: aload 11
    //   1736: astore 17
    //   1738: aload 4
    //   1740: astore 10
    //   1742: aload 12
    //   1744: astore 18
    //   1746: aload 11
    //   1748: astore 19
    //   1750: aload 4
    //   1752: astore 7
    //   1754: aload 13
    //   1756: astore 20
    //   1758: aload 11
    //   1760: astore 21
    //   1762: aload 4
    //   1764: astore 8
    //   1766: aload 14
    //   1768: astore 22
    //   1770: aload 11
    //   1772: astore 23
    //   1774: aload 4
    //   1776: astore 9
    //   1778: getstatic 135	com/tencent/mm/plugin/report/service/h:pYm	Lcom/tencent/mm/plugin/report/service/h;
    //   1781: ldc2_w 136
    //   1784: ldc2_w 319
    //   1787: lconst_1
    //   1788: iconst_1
    //   1789: invokevirtual 206	com/tencent/mm/plugin/report/service/h:a	(JJJZ)V
    //   1792: aload 15
    //   1794: astore 16
    //   1796: aload 11
    //   1798: astore 17
    //   1800: aload 4
    //   1802: astore 10
    //   1804: aload 12
    //   1806: astore 18
    //   1808: aload 11
    //   1810: astore 19
    //   1812: aload 4
    //   1814: astore 7
    //   1816: aload 13
    //   1818: astore 20
    //   1820: aload 11
    //   1822: astore 21
    //   1824: aload 4
    //   1826: astore 8
    //   1828: aload 14
    //   1830: astore 22
    //   1832: aload 11
    //   1834: astore 23
    //   1836: aload 4
    //   1838: astore 9
    //   1840: getstatic 135	com/tencent/mm/plugin/report/service/h:pYm	Lcom/tencent/mm/plugin/report/service/h;
    //   1843: sipush 14058
    //   1846: bipush 10
    //   1848: anewarray 4	java/lang/Object
    //   1851: dup
    //   1852: iconst_0
    //   1853: ldc_w 264
    //   1856: invokestatic 168	java/lang/Integer:valueOf	(I)Ljava/lang/Integer;
    //   1859: aastore
    //   1860: dup
    //   1861: iconst_1
    //   1862: iload 6
    //   1864: invokestatic 168	java/lang/Integer:valueOf	(I)Ljava/lang/Integer;
    //   1867: aastore
    //   1868: dup
    //   1869: iconst_2
    //   1870: ldc 145
    //   1872: aastore
    //   1873: dup
    //   1874: iconst_3
    //   1875: iconst_0
    //   1876: invokestatic 168	java/lang/Integer:valueOf	(I)Ljava/lang/Integer;
    //   1879: aastore
    //   1880: dup
    //   1881: iconst_4
    //   1882: aload_0
    //   1883: getfield 26	com/tencent/mm/ah/c$b:frs	Lcom/tencent/mm/ah/h;
    //   1886: invokevirtual 194	com/tencent/mm/ah/h:getUsername	()Ljava/lang/String;
    //   1889: aastore
    //   1890: dup
    //   1891: iconst_5
    //   1892: aload 4
    //   1894: getfield 268	com/tencent/mm/network/u:gdF	Ljava/lang/String;
    //   1897: aastore
    //   1898: dup
    //   1899: bipush 6
    //   1901: aload 4
    //   1903: getfield 271	com/tencent/mm/network/u:gcI	I
    //   1906: invokestatic 168	java/lang/Integer:valueOf	(I)Ljava/lang/Integer;
    //   1909: aastore
    //   1910: dup
    //   1911: bipush 7
    //   1913: aload 4
    //   1915: getfield 275	com/tencent/mm/network/u:url	Ljava/net/URL;
    //   1918: invokevirtual 280	java/net/URL:getHost	()Ljava/lang/String;
    //   1921: aastore
    //   1922: dup
    //   1923: bipush 8
    //   1925: aload_2
    //   1926: aastore
    //   1927: dup
    //   1928: bipush 9
    //   1930: aload 5
    //   1932: aastore
    //   1933: invokevirtual 283	com/tencent/mm/plugin/report/service/h:e	(I[Ljava/lang/Object;)V
    //   1936: goto -694 -> 1242
    //   1939: astore 10
    //   1941: getstatic 135	com/tencent/mm/plugin/report/service/h:pYm	Lcom/tencent/mm/plugin/report/service/h;
    //   1944: ldc2_w 136
    //   1947: ldc2_w 321
    //   1950: lconst_1
    //   1951: iconst_1
    //   1952: invokevirtual 206	com/tencent/mm/plugin/report/service/h:a	(JJJZ)V
    //   1955: getstatic 135	com/tencent/mm/plugin/report/service/h:pYm	Lcom/tencent/mm/plugin/report/service/h;
    //   1958: astore 22
    //   1960: aload 10
    //   1962: invokevirtual 323	java/net/SocketTimeoutException:getMessage	()Ljava/lang/String;
    //   1965: astore 20
    //   1967: aload_0
    //   1968: getfield 26	com/tencent/mm/ah/c$b:frs	Lcom/tencent/mm/ah/h;
    //   1971: invokevirtual 194	com/tencent/mm/ah/h:getUsername	()Ljava/lang/String;
    //   1974: astore 16
    //   1976: aload 7
    //   1978: ifnonnull +2230 -> 4208
    //   1981: ldc_w 292
    //   1984: astore 4
    //   1986: aload 7
    //   1988: ifnonnull +2230 -> 4218
    //   1991: ldc_w 292
    //   1994: astore 11
    //   1996: aload 7
    //   1998: ifnonnull +2233 -> 4231
    //   2001: ldc_w 292
    //   2004: astore 5
    //   2006: aload 22
    //   2008: sipush 14058
    //   2011: bipush 10
    //   2013: anewarray 4	java/lang/Object
    //   2016: dup
    //   2017: iconst_0
    //   2018: ldc_w 264
    //   2021: invokestatic 168	java/lang/Integer:valueOf	(I)Ljava/lang/Integer;
    //   2024: aastore
    //   2025: dup
    //   2026: iconst_1
    //   2027: sipush 10002
    //   2030: invokestatic 168	java/lang/Integer:valueOf	(I)Ljava/lang/Integer;
    //   2033: aastore
    //   2034: dup
    //   2035: iconst_2
    //   2036: aload 20
    //   2038: aastore
    //   2039: dup
    //   2040: iconst_3
    //   2041: iconst_0
    //   2042: invokestatic 168	java/lang/Integer:valueOf	(I)Ljava/lang/Integer;
    //   2045: aastore
    //   2046: dup
    //   2047: iconst_4
    //   2048: aload 16
    //   2050: aastore
    //   2051: dup
    //   2052: iconst_5
    //   2053: aload 4
    //   2055: aastore
    //   2056: dup
    //   2057: bipush 6
    //   2059: aload 11
    //   2061: aastore
    //   2062: dup
    //   2063: bipush 7
    //   2065: aload 5
    //   2067: aastore
    //   2068: dup
    //   2069: bipush 8
    //   2071: aload_2
    //   2072: aastore
    //   2073: dup
    //   2074: bipush 9
    //   2076: ldc 145
    //   2078: aastore
    //   2079: invokevirtual 283	com/tencent/mm/plugin/report/service/h:e	(I[Ljava/lang/Object;)V
    //   2082: ldc 65
    //   2084: ldc_w 294
    //   2087: iconst_3
    //   2088: anewarray 4	java/lang/Object
    //   2091: dup
    //   2092: iconst_0
    //   2093: aload_2
    //   2094: aastore
    //   2095: dup
    //   2096: iconst_1
    //   2097: aload 10
    //   2099: invokevirtual 298	java/lang/Object:getClass	()Ljava/lang/Class;
    //   2102: invokevirtual 303	java/lang/Class:getSimpleName	()Ljava/lang/String;
    //   2105: aastore
    //   2106: dup
    //   2107: iconst_2
    //   2108: aload 10
    //   2110: invokevirtual 323	java/net/SocketTimeoutException:getMessage	()Ljava/lang/String;
    //   2113: aastore
    //   2114: invokestatic 261	com/tencent/mm/sdk/platformtools/ab:e	(Ljava/lang/String;Ljava/lang/String;[Ljava/lang/Object;)V
    //   2117: aload 18
    //   2119: astore 11
    //   2121: aload 19
    //   2123: astore 4
    //   2125: aload 7
    //   2127: astore 5
    //   2129: goto -442 -> 1687
    //   2132: aload 15
    //   2134: astore 16
    //   2136: aload 11
    //   2138: astore 17
    //   2140: aload 4
    //   2142: astore 10
    //   2144: aload 12
    //   2146: astore 18
    //   2148: aload 11
    //   2150: astore 19
    //   2152: aload 4
    //   2154: astore 7
    //   2156: aload 13
    //   2158: astore 20
    //   2160: aload 11
    //   2162: astore 21
    //   2164: aload 4
    //   2166: astore 8
    //   2168: aload 14
    //   2170: astore 22
    //   2172: aload 11
    //   2174: astore 23
    //   2176: aload 4
    //   2178: astore 9
    //   2180: getstatic 135	com/tencent/mm/plugin/report/service/h:pYm	Lcom/tencent/mm/plugin/report/service/h;
    //   2183: ldc2_w 136
    //   2186: ldc2_w 324
    //   2189: lconst_1
    //   2190: iconst_1
    //   2191: invokevirtual 206	com/tencent/mm/plugin/report/service/h:a	(JJJZ)V
    //   2194: aload 15
    //   2196: astore 16
    //   2198: aload 11
    //   2200: astore 17
    //   2202: aload 4
    //   2204: astore 10
    //   2206: aload 12
    //   2208: astore 18
    //   2210: aload 11
    //   2212: astore 19
    //   2214: aload 4
    //   2216: astore 7
    //   2218: aload 13
    //   2220: astore 20
    //   2222: aload 11
    //   2224: astore 21
    //   2226: aload 4
    //   2228: astore 8
    //   2230: aload 14
    //   2232: astore 22
    //   2234: aload 11
    //   2236: astore 23
    //   2238: aload 4
    //   2240: astore 9
    //   2242: getstatic 135	com/tencent/mm/plugin/report/service/h:pYm	Lcom/tencent/mm/plugin/report/service/h;
    //   2245: sipush 14058
    //   2248: bipush 10
    //   2250: anewarray 4	java/lang/Object
    //   2253: dup
    //   2254: iconst_0
    //   2255: ldc_w 264
    //   2258: invokestatic 168	java/lang/Integer:valueOf	(I)Ljava/lang/Integer;
    //   2261: aastore
    //   2262: dup
    //   2263: iconst_1
    //   2264: iload 6
    //   2266: invokestatic 168	java/lang/Integer:valueOf	(I)Ljava/lang/Integer;
    //   2269: aastore
    //   2270: dup
    //   2271: iconst_2
    //   2272: ldc 145
    //   2274: aastore
    //   2275: dup
    //   2276: iconst_3
    //   2277: iconst_0
    //   2278: invokestatic 168	java/lang/Integer:valueOf	(I)Ljava/lang/Integer;
    //   2281: aastore
    //   2282: dup
    //   2283: iconst_4
    //   2284: aload_0
    //   2285: getfield 26	com/tencent/mm/ah/c$b:frs	Lcom/tencent/mm/ah/h;
    //   2288: invokevirtual 194	com/tencent/mm/ah/h:getUsername	()Ljava/lang/String;
    //   2291: aastore
    //   2292: dup
    //   2293: iconst_5
    //   2294: aload 4
    //   2296: getfield 268	com/tencent/mm/network/u:gdF	Ljava/lang/String;
    //   2299: aastore
    //   2300: dup
    //   2301: bipush 6
    //   2303: aload 4
    //   2305: getfield 271	com/tencent/mm/network/u:gcI	I
    //   2308: invokestatic 168	java/lang/Integer:valueOf	(I)Ljava/lang/Integer;
    //   2311: aastore
    //   2312: dup
    //   2313: bipush 7
    //   2315: aload 4
    //   2317: getfield 275	com/tencent/mm/network/u:url	Ljava/net/URL;
    //   2320: invokevirtual 280	java/net/URL:getHost	()Ljava/lang/String;
    //   2323: aastore
    //   2324: dup
    //   2325: bipush 8
    //   2327: aload_2
    //   2328: aastore
    //   2329: dup
    //   2330: bipush 9
    //   2332: aload 5
    //   2334: aastore
    //   2335: invokevirtual 283	com/tencent/mm/plugin/report/service/h:e	(I[Ljava/lang/Object;)V
    //   2338: goto -1096 -> 1242
    //   2341: astore 16
    //   2343: getstatic 135	com/tencent/mm/plugin/report/service/h:pYm	Lcom/tencent/mm/plugin/report/service/h;
    //   2346: ldc2_w 136
    //   2349: ldc2_w 326
    //   2352: lconst_1
    //   2353: iconst_1
    //   2354: invokevirtual 206	com/tencent/mm/plugin/report/service/h:a	(JJJZ)V
    //   2357: getstatic 135	com/tencent/mm/plugin/report/service/h:pYm	Lcom/tencent/mm/plugin/report/service/h;
    //   2360: astore 10
    //   2362: aload 16
    //   2364: invokevirtual 328	java/io/IOException:getMessage	()Ljava/lang/String;
    //   2367: astore 7
    //   2369: aload_0
    //   2370: getfield 26	com/tencent/mm/ah/c$b:frs	Lcom/tencent/mm/ah/h;
    //   2373: invokevirtual 194	com/tencent/mm/ah/h:getUsername	()Ljava/lang/String;
    //   2376: astore 18
    //   2378: aload 8
    //   2380: ifnonnull +1864 -> 4244
    //   2383: ldc_w 292
    //   2386: astore 4
    //   2388: aload 8
    //   2390: ifnonnull +1864 -> 4254
    //   2393: ldc_w 292
    //   2396: astore 11
    //   2398: aload 8
    //   2400: ifnonnull +1867 -> 4267
    //   2403: ldc_w 292
    //   2406: astore 5
    //   2408: aload 10
    //   2410: sipush 14058
    //   2413: bipush 10
    //   2415: anewarray 4	java/lang/Object
    //   2418: dup
    //   2419: iconst_0
    //   2420: ldc_w 264
    //   2423: invokestatic 168	java/lang/Integer:valueOf	(I)Ljava/lang/Integer;
    //   2426: aastore
    //   2427: dup
    //   2428: iconst_1
    //   2429: sipush 10003
    //   2432: invokestatic 168	java/lang/Integer:valueOf	(I)Ljava/lang/Integer;
    //   2435: aastore
    //   2436: dup
    //   2437: iconst_2
    //   2438: aload 7
    //   2440: aastore
    //   2441: dup
    //   2442: iconst_3
    //   2443: iconst_0
    //   2444: invokestatic 168	java/lang/Integer:valueOf	(I)Ljava/lang/Integer;
    //   2447: aastore
    //   2448: dup
    //   2449: iconst_4
    //   2450: aload 18
    //   2452: aastore
    //   2453: dup
    //   2454: iconst_5
    //   2455: aload 4
    //   2457: aastore
    //   2458: dup
    //   2459: bipush 6
    //   2461: aload 11
    //   2463: aastore
    //   2464: dup
    //   2465: bipush 7
    //   2467: aload 5
    //   2469: aastore
    //   2470: dup
    //   2471: bipush 8
    //   2473: aload_2
    //   2474: aastore
    //   2475: dup
    //   2476: bipush 9
    //   2478: ldc 145
    //   2480: aastore
    //   2481: invokevirtual 283	com/tencent/mm/plugin/report/service/h:e	(I[Ljava/lang/Object;)V
    //   2484: ldc 65
    //   2486: ldc_w 294
    //   2489: iconst_3
    //   2490: anewarray 4	java/lang/Object
    //   2493: dup
    //   2494: iconst_0
    //   2495: aload_2
    //   2496: aastore
    //   2497: dup
    //   2498: iconst_1
    //   2499: aload 16
    //   2501: invokevirtual 298	java/lang/Object:getClass	()Ljava/lang/Class;
    //   2504: invokevirtual 303	java/lang/Class:getSimpleName	()Ljava/lang/String;
    //   2507: aastore
    //   2508: dup
    //   2509: iconst_2
    //   2510: aload 16
    //   2512: invokevirtual 328	java/io/IOException:getMessage	()Ljava/lang/String;
    //   2515: aastore
    //   2516: invokestatic 261	com/tencent/mm/sdk/platformtools/ab:e	(Ljava/lang/String;Ljava/lang/String;[Ljava/lang/Object;)V
    //   2519: aload 20
    //   2521: astore 11
    //   2523: aload 21
    //   2525: astore 4
    //   2527: aload 8
    //   2529: astore 5
    //   2531: goto -844 -> 1687
    //   2534: aload 15
    //   2536: astore 16
    //   2538: aload 11
    //   2540: astore 17
    //   2542: aload 4
    //   2544: astore 10
    //   2546: aload 12
    //   2548: astore 18
    //   2550: aload 11
    //   2552: astore 19
    //   2554: aload 4
    //   2556: astore 7
    //   2558: aload 13
    //   2560: astore 20
    //   2562: aload 11
    //   2564: astore 21
    //   2566: aload 4
    //   2568: astore 8
    //   2570: aload 14
    //   2572: astore 22
    //   2574: aload 11
    //   2576: astore 23
    //   2578: aload 4
    //   2580: astore 9
    //   2582: getstatic 135	com/tencent/mm/plugin/report/service/h:pYm	Lcom/tencent/mm/plugin/report/service/h;
    //   2585: ldc2_w 136
    //   2588: ldc2_w 329
    //   2591: lconst_1
    //   2592: iconst_1
    //   2593: invokevirtual 206	com/tencent/mm/plugin/report/service/h:a	(JJJZ)V
    //   2596: aload 15
    //   2598: astore 16
    //   2600: aload 11
    //   2602: astore 17
    //   2604: aload 4
    //   2606: astore 10
    //   2608: aload 12
    //   2610: astore 18
    //   2612: aload 11
    //   2614: astore 19
    //   2616: aload 4
    //   2618: astore 7
    //   2620: aload 13
    //   2622: astore 20
    //   2624: aload 11
    //   2626: astore 21
    //   2628: aload 4
    //   2630: astore 8
    //   2632: aload 14
    //   2634: astore 22
    //   2636: aload 11
    //   2638: astore 23
    //   2640: aload 4
    //   2642: astore 9
    //   2644: getstatic 135	com/tencent/mm/plugin/report/service/h:pYm	Lcom/tencent/mm/plugin/report/service/h;
    //   2647: sipush 14058
    //   2650: bipush 10
    //   2652: anewarray 4	java/lang/Object
    //   2655: dup
    //   2656: iconst_0
    //   2657: ldc_w 264
    //   2660: invokestatic 168	java/lang/Integer:valueOf	(I)Ljava/lang/Integer;
    //   2663: aastore
    //   2664: dup
    //   2665: iconst_1
    //   2666: iload 6
    //   2668: invokestatic 168	java/lang/Integer:valueOf	(I)Ljava/lang/Integer;
    //   2671: aastore
    //   2672: dup
    //   2673: iconst_2
    //   2674: ldc 145
    //   2676: aastore
    //   2677: dup
    //   2678: iconst_3
    //   2679: iconst_0
    //   2680: invokestatic 168	java/lang/Integer:valueOf	(I)Ljava/lang/Integer;
    //   2683: aastore
    //   2684: dup
    //   2685: iconst_4
    //   2686: aload_0
    //   2687: getfield 26	com/tencent/mm/ah/c$b:frs	Lcom/tencent/mm/ah/h;
    //   2690: invokevirtual 194	com/tencent/mm/ah/h:getUsername	()Ljava/lang/String;
    //   2693: aastore
    //   2694: dup
    //   2695: iconst_5
    //   2696: aload 4
    //   2698: getfield 268	com/tencent/mm/network/u:gdF	Ljava/lang/String;
    //   2701: aastore
    //   2702: dup
    //   2703: bipush 6
    //   2705: aload 4
    //   2707: getfield 271	com/tencent/mm/network/u:gcI	I
    //   2710: invokestatic 168	java/lang/Integer:valueOf	(I)Ljava/lang/Integer;
    //   2713: aastore
    //   2714: dup
    //   2715: bipush 7
    //   2717: aload 4
    //   2719: getfield 275	com/tencent/mm/network/u:url	Ljava/net/URL;
    //   2722: invokevirtual 280	java/net/URL:getHost	()Ljava/lang/String;
    //   2725: aastore
    //   2726: dup
    //   2727: bipush 8
    //   2729: aload_2
    //   2730: aastore
    //   2731: dup
    //   2732: bipush 9
    //   2734: aload 5
    //   2736: aastore
    //   2737: invokevirtual 283	com/tencent/mm/plugin/report/service/h:e	(I[Ljava/lang/Object;)V
    //   2740: goto -1498 -> 1242
    //   2743: astore 18
    //   2745: getstatic 135	com/tencent/mm/plugin/report/service/h:pYm	Lcom/tencent/mm/plugin/report/service/h;
    //   2748: ldc2_w 136
    //   2751: lconst_0
    //   2752: lconst_1
    //   2753: iconst_1
    //   2754: invokevirtual 206	com/tencent/mm/plugin/report/service/h:a	(JJJZ)V
    //   2757: getstatic 135	com/tencent/mm/plugin/report/service/h:pYm	Lcom/tencent/mm/plugin/report/service/h;
    //   2760: astore 16
    //   2762: aload 18
    //   2764: invokevirtual 331	java/lang/Exception:getMessage	()Ljava/lang/String;
    //   2767: astore 10
    //   2769: aload_0
    //   2770: getfield 26	com/tencent/mm/ah/c$b:frs	Lcom/tencent/mm/ah/h;
    //   2773: invokevirtual 194	com/tencent/mm/ah/h:getUsername	()Ljava/lang/String;
    //   2776: astore 7
    //   2778: aload 9
    //   2780: ifnonnull +1500 -> 4280
    //   2783: ldc_w 292
    //   2786: astore 4
    //   2788: aload 9
    //   2790: ifnonnull +1500 -> 4290
    //   2793: ldc_w 292
    //   2796: astore 11
    //   2798: aload 9
    //   2800: ifnonnull +1503 -> 4303
    //   2803: ldc_w 292
    //   2806: astore 5
    //   2808: aload 16
    //   2810: sipush 14058
    //   2813: bipush 10
    //   2815: anewarray 4	java/lang/Object
    //   2818: dup
    //   2819: iconst_0
    //   2820: ldc_w 264
    //   2823: invokestatic 168	java/lang/Integer:valueOf	(I)Ljava/lang/Integer;
    //   2826: aastore
    //   2827: dup
    //   2828: iconst_1
    //   2829: sipush 10003
    //   2832: invokestatic 168	java/lang/Integer:valueOf	(I)Ljava/lang/Integer;
    //   2835: aastore
    //   2836: dup
    //   2837: iconst_2
    //   2838: aload 10
    //   2840: aastore
    //   2841: dup
    //   2842: iconst_3
    //   2843: iconst_0
    //   2844: invokestatic 168	java/lang/Integer:valueOf	(I)Ljava/lang/Integer;
    //   2847: aastore
    //   2848: dup
    //   2849: iconst_4
    //   2850: aload 7
    //   2852: aastore
    //   2853: dup
    //   2854: iconst_5
    //   2855: aload 4
    //   2857: aastore
    //   2858: dup
    //   2859: bipush 6
    //   2861: aload 11
    //   2863: aastore
    //   2864: dup
    //   2865: bipush 7
    //   2867: aload 5
    //   2869: aastore
    //   2870: dup
    //   2871: bipush 8
    //   2873: aload_2
    //   2874: aastore
    //   2875: dup
    //   2876: bipush 9
    //   2878: ldc 145
    //   2880: aastore
    //   2881: invokevirtual 283	com/tencent/mm/plugin/report/service/h:e	(I[Ljava/lang/Object;)V
    //   2884: ldc 65
    //   2886: ldc_w 294
    //   2889: iconst_3
    //   2890: anewarray 4	java/lang/Object
    //   2893: dup
    //   2894: iconst_0
    //   2895: aload_2
    //   2896: aastore
    //   2897: dup
    //   2898: iconst_1
    //   2899: aload 18
    //   2901: invokevirtual 298	java/lang/Object:getClass	()Ljava/lang/Class;
    //   2904: invokevirtual 303	java/lang/Class:getSimpleName	()Ljava/lang/String;
    //   2907: aastore
    //   2908: dup
    //   2909: iconst_2
    //   2910: aload 18
    //   2912: invokevirtual 331	java/lang/Exception:getMessage	()Ljava/lang/String;
    //   2915: aastore
    //   2916: invokestatic 261	com/tencent/mm/sdk/platformtools/ab:e	(Ljava/lang/String;Ljava/lang/String;[Ljava/lang/Object;)V
    //   2919: aload 22
    //   2921: astore 11
    //   2923: aload 23
    //   2925: astore 4
    //   2927: aload 9
    //   2929: astore 5
    //   2931: goto -1244 -> 1687
    //   2934: aload 15
    //   2936: astore 16
    //   2938: aload 11
    //   2940: astore 17
    //   2942: aload 4
    //   2944: astore 10
    //   2946: aload 12
    //   2948: astore 18
    //   2950: aload 11
    //   2952: astore 19
    //   2954: aload 4
    //   2956: astore 7
    //   2958: aload 13
    //   2960: astore 20
    //   2962: aload 11
    //   2964: astore 21
    //   2966: aload 4
    //   2968: astore 8
    //   2970: aload 14
    //   2972: astore 22
    //   2974: aload 11
    //   2976: astore 23
    //   2978: aload 4
    //   2980: astore 9
    //   2982: aload 4
    //   2984: ldc_w 333
    //   2987: iconst_0
    //   2988: invokevirtual 337	com/tencent/mm/network/u:getHeaderFieldInt	(Ljava/lang/String;I)I
    //   2991: iconst_1
    //   2992: if_icmpne +250 -> 3242
    //   2995: iconst_1
    //   2996: istore_1
    //   2997: aload 15
    //   2999: astore 16
    //   3001: aload 11
    //   3003: astore 17
    //   3005: aload 4
    //   3007: astore 10
    //   3009: aload 12
    //   3011: astore 18
    //   3013: aload 11
    //   3015: astore 19
    //   3017: aload 4
    //   3019: astore 7
    //   3021: aload 13
    //   3023: astore 20
    //   3025: aload 11
    //   3027: astore 21
    //   3029: aload 4
    //   3031: astore 8
    //   3033: aload 14
    //   3035: astore 22
    //   3037: aload 11
    //   3039: astore 23
    //   3041: aload 4
    //   3043: astore 9
    //   3045: aload_0
    //   3046: iload_1
    //   3047: putfield 30	com/tencent/mm/ah/c$b:frq	Z
    //   3050: aload 15
    //   3052: astore 16
    //   3054: aload 11
    //   3056: astore 17
    //   3058: aload 4
    //   3060: astore 10
    //   3062: aload 12
    //   3064: astore 18
    //   3066: aload 11
    //   3068: astore 19
    //   3070: aload 4
    //   3072: astore 7
    //   3074: aload 13
    //   3076: astore 20
    //   3078: aload 11
    //   3080: astore 21
    //   3082: aload 4
    //   3084: astore 8
    //   3086: aload 14
    //   3088: astore 22
    //   3090: aload 11
    //   3092: astore 23
    //   3094: aload 4
    //   3096: astore 9
    //   3098: aload 4
    //   3100: getfield 307	com/tencent/mm/network/u:connection	Ljava/net/HttpURLConnection;
    //   3103: invokevirtual 340	java/net/HttpURLConnection:getContentLength	()I
    //   3106: istore 6
    //   3108: aload 15
    //   3110: astore 16
    //   3112: aload 11
    //   3114: astore 17
    //   3116: aload 4
    //   3118: astore 10
    //   3120: aload 12
    //   3122: astore 18
    //   3124: aload 11
    //   3126: astore 19
    //   3128: aload 4
    //   3130: astore 7
    //   3132: aload 13
    //   3134: astore 20
    //   3136: aload 11
    //   3138: astore 21
    //   3140: aload 4
    //   3142: astore 8
    //   3144: aload 14
    //   3146: astore 22
    //   3148: aload 11
    //   3150: astore 23
    //   3152: aload 4
    //   3154: astore 9
    //   3156: aload 4
    //   3158: invokevirtual 344	com/tencent/mm/network/u:getInputStream	()Ljava/io/InputStream;
    //   3161: astore 5
    //   3163: aload 5
    //   3165: ifnonnull +82 -> 3247
    //   3168: aload 5
    //   3170: astore 16
    //   3172: aload 11
    //   3174: astore 17
    //   3176: aload 4
    //   3178: astore 10
    //   3180: aload 5
    //   3182: astore 18
    //   3184: aload 11
    //   3186: astore 19
    //   3188: aload 4
    //   3190: astore 7
    //   3192: aload 5
    //   3194: astore 20
    //   3196: aload 11
    //   3198: astore 21
    //   3200: aload 4
    //   3202: astore 8
    //   3204: aload 5
    //   3206: astore 22
    //   3208: aload 11
    //   3210: astore 23
    //   3212: aload 4
    //   3214: astore 9
    //   3216: ldc 65
    //   3218: ldc_w 346
    //   3221: iconst_1
    //   3222: anewarray 4	java/lang/Object
    //   3225: dup
    //   3226: iconst_0
    //   3227: aload_2
    //   3228: aastore
    //   3229: invokestatic 198	com/tencent/mm/sdk/platformtools/ab:d	(Ljava/lang/String;Ljava/lang/String;[Ljava/lang/Object;)V
    //   3232: iconst_1
    //   3233: istore_1
    //   3234: ldc 42
    //   3236: invokestatic 51	com/tencent/matrix/trace/core/AppMethodBeat:o	(I)V
    //   3239: goto -3220 -> 19
    //   3242: iconst_0
    //   3243: istore_1
    //   3244: goto -247 -> 2997
    //   3247: aload 5
    //   3249: astore 16
    //   3251: aload 11
    //   3253: astore 17
    //   3255: aload 4
    //   3257: astore 10
    //   3259: aload 5
    //   3261: astore 18
    //   3263: aload 11
    //   3265: astore 19
    //   3267: aload 4
    //   3269: astore 7
    //   3271: aload 5
    //   3273: astore 20
    //   3275: aload 11
    //   3277: astore 21
    //   3279: aload 4
    //   3281: astore 8
    //   3283: aload 5
    //   3285: astore 22
    //   3287: aload 11
    //   3289: astore 23
    //   3291: aload 4
    //   3293: astore 9
    //   3295: sipush 1024
    //   3298: newarray byte
    //   3300: astore 15
    //   3302: aload 5
    //   3304: astore 16
    //   3306: aload 11
    //   3308: astore 17
    //   3310: aload 4
    //   3312: astore 10
    //   3314: aload 5
    //   3316: astore 18
    //   3318: aload 11
    //   3320: astore 19
    //   3322: aload 4
    //   3324: astore 7
    //   3326: aload 5
    //   3328: astore 20
    //   3330: aload 11
    //   3332: astore 21
    //   3334: aload 4
    //   3336: astore 8
    //   3338: aload 5
    //   3340: astore 22
    //   3342: aload 11
    //   3344: astore 23
    //   3346: aload 4
    //   3348: astore 9
    //   3350: aload 5
    //   3352: aload 15
    //   3354: invokevirtual 350	java/io/InputStream:read	([B)I
    //   3357: istore 24
    //   3359: iload 24
    //   3361: iconst_m1
    //   3362: if_icmpeq +64 -> 3426
    //   3365: aload 5
    //   3367: astore 16
    //   3369: aload 11
    //   3371: astore 17
    //   3373: aload 4
    //   3375: astore 10
    //   3377: aload 5
    //   3379: astore 18
    //   3381: aload 11
    //   3383: astore 19
    //   3385: aload 4
    //   3387: astore 7
    //   3389: aload 5
    //   3391: astore 20
    //   3393: aload 11
    //   3395: astore 21
    //   3397: aload 4
    //   3399: astore 8
    //   3401: aload 5
    //   3403: astore 22
    //   3405: aload 11
    //   3407: astore 23
    //   3409: aload 4
    //   3411: astore 9
    //   3413: aload 11
    //   3415: aload 15
    //   3417: iconst_0
    //   3418: iload 24
    //   3420: invokevirtual 354	java/io/ByteArrayOutputStream:write	([BII)V
    //   3423: goto -121 -> 3302
    //   3426: aload 5
    //   3428: astore 16
    //   3430: aload 11
    //   3432: astore 17
    //   3434: aload 4
    //   3436: astore 10
    //   3438: aload 5
    //   3440: astore 18
    //   3442: aload 11
    //   3444: astore 19
    //   3446: aload 4
    //   3448: astore 7
    //   3450: aload 5
    //   3452: astore 20
    //   3454: aload 11
    //   3456: astore 21
    //   3458: aload 4
    //   3460: astore 8
    //   3462: aload 5
    //   3464: astore 22
    //   3466: aload 11
    //   3468: astore 23
    //   3470: aload 4
    //   3472: astore 9
    //   3474: getstatic 135	com/tencent/mm/plugin/report/service/h:pYm	Lcom/tencent/mm/plugin/report/service/h;
    //   3477: ldc2_w 136
    //   3480: ldc2_w 355
    //   3483: lconst_1
    //   3484: iconst_1
    //   3485: invokevirtual 206	com/tencent/mm/plugin/report/service/h:a	(JJJZ)V
    //   3488: aload 5
    //   3490: astore 16
    //   3492: aload 11
    //   3494: astore 17
    //   3496: aload 4
    //   3498: astore 10
    //   3500: aload 5
    //   3502: astore 18
    //   3504: aload 11
    //   3506: astore 19
    //   3508: aload 4
    //   3510: astore 7
    //   3512: aload 5
    //   3514: astore 20
    //   3516: aload 11
    //   3518: astore 21
    //   3520: aload 4
    //   3522: astore 8
    //   3524: aload 5
    //   3526: astore 22
    //   3528: aload 11
    //   3530: astore 23
    //   3532: aload 4
    //   3534: astore 9
    //   3536: invokestatic 361	com/tencent/mm/sdk/a/b:dnO	()Z
    //   3539: ifeq +149 -> 3688
    //   3542: aload 5
    //   3544: astore 16
    //   3546: aload 11
    //   3548: astore 17
    //   3550: aload 4
    //   3552: astore 10
    //   3554: aload 5
    //   3556: astore 18
    //   3558: aload 11
    //   3560: astore 19
    //   3562: aload 4
    //   3564: astore 7
    //   3566: aload 5
    //   3568: astore 20
    //   3570: aload 11
    //   3572: astore 21
    //   3574: aload 4
    //   3576: astore 8
    //   3578: aload 5
    //   3580: astore 22
    //   3582: aload 11
    //   3584: astore 23
    //   3586: aload 4
    //   3588: astore 9
    //   3590: getstatic 135	com/tencent/mm/plugin/report/service/h:pYm	Lcom/tencent/mm/plugin/report/service/h;
    //   3593: sipush 14058
    //   3596: bipush 10
    //   3598: anewarray 4	java/lang/Object
    //   3601: dup
    //   3602: iconst_0
    //   3603: ldc_w 264
    //   3606: invokestatic 168	java/lang/Integer:valueOf	(I)Ljava/lang/Integer;
    //   3609: aastore
    //   3610: dup
    //   3611: iconst_1
    //   3612: sipush 20000
    //   3615: invokestatic 168	java/lang/Integer:valueOf	(I)Ljava/lang/Integer;
    //   3618: aastore
    //   3619: dup
    //   3620: iconst_2
    //   3621: ldc 145
    //   3623: aastore
    //   3624: dup
    //   3625: iconst_3
    //   3626: iload 6
    //   3628: invokestatic 168	java/lang/Integer:valueOf	(I)Ljava/lang/Integer;
    //   3631: aastore
    //   3632: dup
    //   3633: iconst_4
    //   3634: aload_0
    //   3635: getfield 26	com/tencent/mm/ah/c$b:frs	Lcom/tencent/mm/ah/h;
    //   3638: invokevirtual 194	com/tencent/mm/ah/h:getUsername	()Ljava/lang/String;
    //   3641: aastore
    //   3642: dup
    //   3643: iconst_5
    //   3644: aload 4
    //   3646: getfield 268	com/tencent/mm/network/u:gdF	Ljava/lang/String;
    //   3649: aastore
    //   3650: dup
    //   3651: bipush 6
    //   3653: aload 4
    //   3655: getfield 271	com/tencent/mm/network/u:gcI	I
    //   3658: invokestatic 168	java/lang/Integer:valueOf	(I)Ljava/lang/Integer;
    //   3661: aastore
    //   3662: dup
    //   3663: bipush 7
    //   3665: aload 4
    //   3667: getfield 275	com/tencent/mm/network/u:url	Ljava/net/URL;
    //   3670: invokevirtual 280	java/net/URL:getHost	()Ljava/lang/String;
    //   3673: aastore
    //   3674: dup
    //   3675: bipush 8
    //   3677: aload_2
    //   3678: aastore
    //   3679: dup
    //   3680: bipush 9
    //   3682: ldc 145
    //   3684: aastore
    //   3685: invokevirtual 283	com/tencent/mm/plugin/report/service/h:e	(I[Ljava/lang/Object;)V
    //   3688: aload 5
    //   3690: astore 16
    //   3692: aload 11
    //   3694: astore 17
    //   3696: aload 4
    //   3698: astore 10
    //   3700: aload 5
    //   3702: astore 18
    //   3704: aload 11
    //   3706: astore 19
    //   3708: aload 4
    //   3710: astore 7
    //   3712: aload 5
    //   3714: astore 20
    //   3716: aload 11
    //   3718: astore 21
    //   3720: aload 4
    //   3722: astore 8
    //   3724: aload 5
    //   3726: astore 22
    //   3728: aload 11
    //   3730: astore 23
    //   3732: aload 4
    //   3734: astore 9
    //   3736: aload_0
    //   3737: aload 11
    //   3739: invokevirtual 365	java/io/ByteArrayOutputStream:toByteArray	()[B
    //   3742: putfield 28	com/tencent/mm/ah/c$b:frt	[B
    //   3745: aload 5
    //   3747: astore 16
    //   3749: aload 11
    //   3751: astore 17
    //   3753: aload 4
    //   3755: astore 10
    //   3757: aload 5
    //   3759: astore 18
    //   3761: aload 11
    //   3763: astore 19
    //   3765: aload 4
    //   3767: astore 7
    //   3769: aload 5
    //   3771: astore 20
    //   3773: aload 11
    //   3775: astore 21
    //   3777: aload 4
    //   3779: astore 8
    //   3781: aload 5
    //   3783: astore 22
    //   3785: aload 11
    //   3787: astore 23
    //   3789: aload 4
    //   3791: astore 9
    //   3793: aload 11
    //   3795: invokevirtual 318	java/io/ByteArrayOutputStream:close	()V
    //   3798: aconst_null
    //   3799: astore 12
    //   3801: aconst_null
    //   3802: astore 13
    //   3804: aconst_null
    //   3805: astore 14
    //   3807: aconst_null
    //   3808: astore 25
    //   3810: aconst_null
    //   3811: astore 15
    //   3813: aload 5
    //   3815: astore 16
    //   3817: aload 15
    //   3819: astore 17
    //   3821: aload 4
    //   3823: astore 10
    //   3825: aload 5
    //   3827: astore 18
    //   3829: aload 13
    //   3831: astore 19
    //   3833: aload 4
    //   3835: astore 7
    //   3837: aload 5
    //   3839: astore 20
    //   3841: aload 14
    //   3843: astore 21
    //   3845: aload 4
    //   3847: astore 8
    //   3849: aload 5
    //   3851: astore 22
    //   3853: aload 25
    //   3855: astore 23
    //   3857: aload 4
    //   3859: astore 9
    //   3861: aload 4
    //   3863: getfield 307	com/tencent/mm/network/u:connection	Ljava/net/HttpURLConnection;
    //   3866: invokevirtual 312	java/net/HttpURLConnection:disconnect	()V
    //   3869: aconst_null
    //   3870: astore 26
    //   3872: aconst_null
    //   3873: astore 27
    //   3875: aconst_null
    //   3876: astore 28
    //   3878: aconst_null
    //   3879: astore 29
    //   3881: aconst_null
    //   3882: astore 30
    //   3884: aload 5
    //   3886: astore 16
    //   3888: aload 15
    //   3890: astore 17
    //   3892: aload 30
    //   3894: astore 10
    //   3896: aload 5
    //   3898: astore 18
    //   3900: aload 13
    //   3902: astore 19
    //   3904: aload 27
    //   3906: astore 7
    //   3908: aload 5
    //   3910: astore 20
    //   3912: aload 14
    //   3914: astore 21
    //   3916: aload 28
    //   3918: astore 8
    //   3920: aload 5
    //   3922: astore 22
    //   3924: aload 25
    //   3926: astore 23
    //   3928: aload 29
    //   3930: astore 9
    //   3932: aload 5
    //   3934: invokevirtual 317	java/io/InputStream:close	()V
    //   3937: aconst_null
    //   3938: astore 31
    //   3940: aconst_null
    //   3941: astore 32
    //   3943: aconst_null
    //   3944: astore 33
    //   3946: aconst_null
    //   3947: astore 34
    //   3949: aconst_null
    //   3950: astore 35
    //   3952: aload 31
    //   3954: astore 11
    //   3956: aload 12
    //   3958: astore 4
    //   3960: aload 26
    //   3962: astore 5
    //   3964: iload 6
    //   3966: ifle -2279 -> 1687
    //   3969: aload 35
    //   3971: astore 16
    //   3973: aload 15
    //   3975: astore 17
    //   3977: aload 30
    //   3979: astore 10
    //   3981: aload 31
    //   3983: astore 11
    //   3985: aload 12
    //   3987: astore 4
    //   3989: aload 26
    //   3991: astore 5
    //   3993: aload 32
    //   3995: astore 18
    //   3997: aload 13
    //   3999: astore 19
    //   4001: aload 27
    //   4003: astore 7
    //   4005: aload 33
    //   4007: astore 20
    //   4009: aload 14
    //   4011: astore 21
    //   4013: aload 28
    //   4015: astore 8
    //   4017: aload 34
    //   4019: astore 22
    //   4021: aload 25
    //   4023: astore 23
    //   4025: aload 29
    //   4027: astore 9
    //   4029: aload_0
    //   4030: getfield 28	com/tencent/mm/ah/c$b:frt	[B
    //   4033: arraylength
    //   4034: iload 6
    //   4036: if_icmpge -2349 -> 1687
    //   4039: aload 35
    //   4041: astore 16
    //   4043: aload 15
    //   4045: astore 17
    //   4047: aload 30
    //   4049: astore 10
    //   4051: aload 32
    //   4053: astore 18
    //   4055: aload 13
    //   4057: astore 19
    //   4059: aload 27
    //   4061: astore 7
    //   4063: aload 33
    //   4065: astore 20
    //   4067: aload 14
    //   4069: astore 21
    //   4071: aload 28
    //   4073: astore 8
    //   4075: aload 34
    //   4077: astore 22
    //   4079: aload 25
    //   4081: astore 23
    //   4083: aload 29
    //   4085: astore 9
    //   4087: getstatic 135	com/tencent/mm/plugin/report/service/h:pYm	Lcom/tencent/mm/plugin/report/service/h;
    //   4090: ldc2_w 136
    //   4093: ldc2_w 366
    //   4096: lconst_1
    //   4097: iconst_1
    //   4098: invokevirtual 206	com/tencent/mm/plugin/report/service/h:a	(JJJZ)V
    //   4101: aload 35
    //   4103: astore 16
    //   4105: aload 15
    //   4107: astore 17
    //   4109: aload 30
    //   4111: astore 10
    //   4113: aload 32
    //   4115: astore 18
    //   4117: aload 13
    //   4119: astore 19
    //   4121: aload 27
    //   4123: astore 7
    //   4125: aload 33
    //   4127: astore 20
    //   4129: aload 14
    //   4131: astore 21
    //   4133: aload 28
    //   4135: astore 8
    //   4137: aload 34
    //   4139: astore 22
    //   4141: aload 25
    //   4143: astore 23
    //   4145: aload 29
    //   4147: astore 9
    //   4149: ldc 65
    //   4151: ldc_w 369
    //   4154: invokestatic 371	com/tencent/mm/sdk/platformtools/ab:e	(Ljava/lang/String;Ljava/lang/String;)V
    //   4157: aload 31
    //   4159: astore 11
    //   4161: aload 12
    //   4163: astore 4
    //   4165: aload 26
    //   4167: astore 5
    //   4169: goto -2482 -> 1687
    //   4172: aload 10
    //   4174: getfield 268	com/tencent/mm/network/u:gdF	Ljava/lang/String;
    //   4177: astore 4
    //   4179: goto -2635 -> 1544
    //   4182: aload 10
    //   4184: getfield 271	com/tencent/mm/network/u:gcI	I
    //   4187: invokestatic 168	java/lang/Integer:valueOf	(I)Ljava/lang/Integer;
    //   4190: astore 11
    //   4192: goto -2638 -> 1554
    //   4195: aload 10
    //   4197: getfield 275	com/tencent/mm/network/u:url	Ljava/net/URL;
    //   4200: invokevirtual 280	java/net/URL:getHost	()Ljava/lang/String;
    //   4203: astore 5
    //   4205: goto -2641 -> 1564
    //   4208: aload 7
    //   4210: getfield 268	com/tencent/mm/network/u:gdF	Ljava/lang/String;
    //   4213: astore 4
    //   4215: goto -2229 -> 1986
    //   4218: aload 7
    //   4220: getfield 271	com/tencent/mm/network/u:gcI	I
    //   4223: invokestatic 168	java/lang/Integer:valueOf	(I)Ljava/lang/Integer;
    //   4226: astore 11
    //   4228: goto -2232 -> 1996
    //   4231: aload 7
    //   4233: getfield 275	com/tencent/mm/network/u:url	Ljava/net/URL;
    //   4236: invokevirtual 280	java/net/URL:getHost	()Ljava/lang/String;
    //   4239: astore 5
    //   4241: goto -2235 -> 2006
    //   4244: aload 8
    //   4246: getfield 268	com/tencent/mm/network/u:gdF	Ljava/lang/String;
    //   4249: astore 4
    //   4251: goto -1863 -> 2388
    //   4254: aload 8
    //   4256: getfield 271	com/tencent/mm/network/u:gcI	I
    //   4259: invokestatic 168	java/lang/Integer:valueOf	(I)Ljava/lang/Integer;
    //   4262: astore 11
    //   4264: goto -1866 -> 2398
    //   4267: aload 8
    //   4269: getfield 275	com/tencent/mm/network/u:url	Ljava/net/URL;
    //   4272: invokevirtual 280	java/net/URL:getHost	()Ljava/lang/String;
    //   4275: astore 5
    //   4277: goto -1869 -> 2408
    //   4280: aload 9
    //   4282: getfield 268	com/tencent/mm/network/u:gdF	Ljava/lang/String;
    //   4285: astore 4
    //   4287: goto -1499 -> 2788
    //   4290: aload 9
    //   4292: getfield 271	com/tencent/mm/network/u:gcI	I
    //   4295: invokestatic 168	java/lang/Integer:valueOf	(I)Ljava/lang/Integer;
    //   4298: astore 11
    //   4300: goto -1502 -> 2798
    //   4303: aload 9
    //   4305: getfield 275	com/tencent/mm/network/u:url	Ljava/net/URL;
    //   4308: invokevirtual 280	java/net/URL:getHost	()Ljava/lang/String;
    //   4311: astore 5
    //   4313: goto -1505 -> 2808
    //   4316: astore 4
    //   4318: ldc 65
    //   4320: ldc_w 373
    //   4323: iconst_1
    //   4324: anewarray 4	java/lang/Object
    //   4327: dup
    //   4328: iconst_0
    //   4329: aload 4
    //   4331: invokestatic 379	com/tencent/mm/sdk/platformtools/bo:l	(Ljava/lang/Throwable;)Ljava/lang/String;
    //   4334: aastore
    //   4335: invokestatic 261	com/tencent/mm/sdk/platformtools/ab:e	(Ljava/lang/String;Ljava/lang/String;[Ljava/lang/Object;)V
    //   4338: ldc 65
    //   4340: ldc_w 381
    //   4343: iconst_1
    //   4344: anewarray 4	java/lang/Object
    //   4347: dup
    //   4348: iconst_0
    //   4349: aload 4
    //   4351: invokevirtual 331	java/lang/Exception:getMessage	()Ljava/lang/String;
    //   4354: aastore
    //   4355: invokestatic 261	com/tencent/mm/sdk/platformtools/ab:e	(Ljava/lang/String;Ljava/lang/String;[Ljava/lang/Object;)V
    //   4358: getstatic 135	com/tencent/mm/plugin/report/service/h:pYm	Lcom/tencent/mm/plugin/report/service/h;
    //   4361: ldc2_w 136
    //   4364: ldc2_w 382
    //   4367: lconst_1
    //   4368: iconst_1
    //   4369: invokevirtual 206	com/tencent/mm/plugin/report/service/h:a	(JJJZ)V
    //   4372: goto -2652 -> 1720
    //   4375: goto -4234 -> 141
    //
    // Exception table:
    //   from	to	target	type
    //   325	332	1499	java/net/ProtocolException
    //   380	387	1499	java/net/ProtocolException
    //   435	444	1499	java/net/ProtocolException
    //   492	500	1499	java/net/ProtocolException
    //   548	556	1499	java/net/ProtocolException
    //   604	612	1499	java/net/ProtocolException
    //   660	667	1499	java/net/ProtocolException
    //   715	722	1499	java/net/ProtocolException
    //   775	789	1499	java/net/ProtocolException
    //   842	852	1499	java/net/ProtocolException
    //   900	913	1499	java/net/ProtocolException
    //   961	990	1499	java/net/ProtocolException
    //   1084	1098	1499	java/net/ProtocolException
    //   1146	1242	1499	java/net/ProtocolException
    //   1338	1352	1499	java/net/ProtocolException
    //   1400	1496	1499	java/net/ProtocolException
    //   1778	1792	1499	java/net/ProtocolException
    //   1840	1936	1499	java/net/ProtocolException
    //   2180	2194	1499	java/net/ProtocolException
    //   2242	2338	1499	java/net/ProtocolException
    //   2582	2596	1499	java/net/ProtocolException
    //   2644	2740	1499	java/net/ProtocolException
    //   2982	2995	1499	java/net/ProtocolException
    //   3045	3050	1499	java/net/ProtocolException
    //   3098	3108	1499	java/net/ProtocolException
    //   3156	3163	1499	java/net/ProtocolException
    //   3216	3232	1499	java/net/ProtocolException
    //   3295	3302	1499	java/net/ProtocolException
    //   3350	3359	1499	java/net/ProtocolException
    //   3413	3423	1499	java/net/ProtocolException
    //   3474	3488	1499	java/net/ProtocolException
    //   3536	3542	1499	java/net/ProtocolException
    //   3590	3688	1499	java/net/ProtocolException
    //   3736	3745	1499	java/net/ProtocolException
    //   3793	3798	1499	java/net/ProtocolException
    //   3861	3869	1499	java/net/ProtocolException
    //   3932	3937	1499	java/net/ProtocolException
    //   4029	4039	1499	java/net/ProtocolException
    //   4087	4101	1499	java/net/ProtocolException
    //   4149	4157	1499	java/net/ProtocolException
    //   325	332	1939	java/net/SocketTimeoutException
    //   380	387	1939	java/net/SocketTimeoutException
    //   435	444	1939	java/net/SocketTimeoutException
    //   492	500	1939	java/net/SocketTimeoutException
    //   548	556	1939	java/net/SocketTimeoutException
    //   604	612	1939	java/net/SocketTimeoutException
    //   660	667	1939	java/net/SocketTimeoutException
    //   715	722	1939	java/net/SocketTimeoutException
    //   775	789	1939	java/net/SocketTimeoutException
    //   842	852	1939	java/net/SocketTimeoutException
    //   900	913	1939	java/net/SocketTimeoutException
    //   961	990	1939	java/net/SocketTimeoutException
    //   1084	1098	1939	java/net/SocketTimeoutException
    //   1146	1242	1939	java/net/SocketTimeoutException
    //   1338	1352	1939	java/net/SocketTimeoutException
    //   1400	1496	1939	java/net/SocketTimeoutException
    //   1778	1792	1939	java/net/SocketTimeoutException
    //   1840	1936	1939	java/net/SocketTimeoutException
    //   2180	2194	1939	java/net/SocketTimeoutException
    //   2242	2338	1939	java/net/SocketTimeoutException
    //   2582	2596	1939	java/net/SocketTimeoutException
    //   2644	2740	1939	java/net/SocketTimeoutException
    //   2982	2995	1939	java/net/SocketTimeoutException
    //   3045	3050	1939	java/net/SocketTimeoutException
    //   3098	3108	1939	java/net/SocketTimeoutException
    //   3156	3163	1939	java/net/SocketTimeoutException
    //   3216	3232	1939	java/net/SocketTimeoutException
    //   3295	3302	1939	java/net/SocketTimeoutException
    //   3350	3359	1939	java/net/SocketTimeoutException
    //   3413	3423	1939	java/net/SocketTimeoutException
    //   3474	3488	1939	java/net/SocketTimeoutException
    //   3536	3542	1939	java/net/SocketTimeoutException
    //   3590	3688	1939	java/net/SocketTimeoutException
    //   3736	3745	1939	java/net/SocketTimeoutException
    //   3793	3798	1939	java/net/SocketTimeoutException
    //   3861	3869	1939	java/net/SocketTimeoutException
    //   3932	3937	1939	java/net/SocketTimeoutException
    //   4029	4039	1939	java/net/SocketTimeoutException
    //   4087	4101	1939	java/net/SocketTimeoutException
    //   4149	4157	1939	java/net/SocketTimeoutException
    //   325	332	2341	java/io/IOException
    //   380	387	2341	java/io/IOException
    //   435	444	2341	java/io/IOException
    //   492	500	2341	java/io/IOException
    //   548	556	2341	java/io/IOException
    //   604	612	2341	java/io/IOException
    //   660	667	2341	java/io/IOException
    //   715	722	2341	java/io/IOException
    //   775	789	2341	java/io/IOException
    //   842	852	2341	java/io/IOException
    //   900	913	2341	java/io/IOException
    //   961	990	2341	java/io/IOException
    //   1084	1098	2341	java/io/IOException
    //   1146	1242	2341	java/io/IOException
    //   1338	1352	2341	java/io/IOException
    //   1400	1496	2341	java/io/IOException
    //   1778	1792	2341	java/io/IOException
    //   1840	1936	2341	java/io/IOException
    //   2180	2194	2341	java/io/IOException
    //   2242	2338	2341	java/io/IOException
    //   2582	2596	2341	java/io/IOException
    //   2644	2740	2341	java/io/IOException
    //   2982	2995	2341	java/io/IOException
    //   3045	3050	2341	java/io/IOException
    //   3098	3108	2341	java/io/IOException
    //   3156	3163	2341	java/io/IOException
    //   3216	3232	2341	java/io/IOException
    //   3295	3302	2341	java/io/IOException
    //   3350	3359	2341	java/io/IOException
    //   3413	3423	2341	java/io/IOException
    //   3474	3488	2341	java/io/IOException
    //   3536	3542	2341	java/io/IOException
    //   3590	3688	2341	java/io/IOException
    //   3736	3745	2341	java/io/IOException
    //   3793	3798	2341	java/io/IOException
    //   3861	3869	2341	java/io/IOException
    //   3932	3937	2341	java/io/IOException
    //   4029	4039	2341	java/io/IOException
    //   4087	4101	2341	java/io/IOException
    //   4149	4157	2341	java/io/IOException
    //   325	332	2743	java/lang/Exception
    //   380	387	2743	java/lang/Exception
    //   435	444	2743	java/lang/Exception
    //   492	500	2743	java/lang/Exception
    //   548	556	2743	java/lang/Exception
    //   604	612	2743	java/lang/Exception
    //   660	667	2743	java/lang/Exception
    //   715	722	2743	java/lang/Exception
    //   775	789	2743	java/lang/Exception
    //   842	852	2743	java/lang/Exception
    //   900	913	2743	java/lang/Exception
    //   961	990	2743	java/lang/Exception
    //   1084	1098	2743	java/lang/Exception
    //   1146	1242	2743	java/lang/Exception
    //   1338	1352	2743	java/lang/Exception
    //   1400	1496	2743	java/lang/Exception
    //   1778	1792	2743	java/lang/Exception
    //   1840	1936	2743	java/lang/Exception
    //   2180	2194	2743	java/lang/Exception
    //   2242	2338	2743	java/lang/Exception
    //   2582	2596	2743	java/lang/Exception
    //   2644	2740	2743	java/lang/Exception
    //   2982	2995	2743	java/lang/Exception
    //   3045	3050	2743	java/lang/Exception
    //   3098	3108	2743	java/lang/Exception
    //   3156	3163	2743	java/lang/Exception
    //   3216	3232	2743	java/lang/Exception
    //   3295	3302	2743	java/lang/Exception
    //   3350	3359	2743	java/lang/Exception
    //   3413	3423	2743	java/lang/Exception
    //   3474	3488	2743	java/lang/Exception
    //   3536	3542	2743	java/lang/Exception
    //   3590	3688	2743	java/lang/Exception
    //   3736	3745	2743	java/lang/Exception
    //   3793	3798	2743	java/lang/Exception
    //   3861	3869	2743	java/lang/Exception
    //   3932	3937	2743	java/lang/Exception
    //   4029	4039	2743	java/lang/Exception
    //   4087	4101	2743	java/lang/Exception
    //   4149	4157	2743	java/lang/Exception
    //   1692	1700	4316	java/lang/Exception
    //   1705	1710	4316	java/lang/Exception
    //   1715	1720	4316	java/lang/Exception
  }

  public final boolean acg()
  {
    AppMethodBeat.i(77857);
    if ((this.frs == null) || (bo.isNullOrNil(this.frs.getUsername())))
      AppMethodBeat.o(77857);
    while (true)
    {
      return false;
      if (bo.cb(this.frt))
      {
        this.frl.frd.remove(this.frs.getUsername());
        com.tencent.mm.plugin.report.service.h.pYm.a(138L, 10L, 1L, true);
        AppMethodBeat.o(77857);
      }
      else
      {
        if (ao.a.flv != null)
          ao.a.flv.cm(this.frt.length, 0);
        this.frl.a(new c.a(this.frl, this.frs, this.frt, this.frq));
        AppMethodBeat.o(77857);
      }
    }
  }
}

/* Location:           C:\Users\Lin\Downloads\dex-tools-2.1-SNAPSHOT\dex-tools-2.1-SNAPSHOT\classes5-dex2jar.jar
 * Qualified Name:     com.tencent.mm.ah.c.b
 * JD-Core Version:    0.6.2
 */