package com.tencent.matrix.resource;

import android.content.Context;
import android.content.Intent;
import com.tencent.matrix.resource.analyzer.model.a;

public class CanaryWorkerService extends MatrixJobIntentService
{
  public static void a(Context paramContext, a parama)
  {
    Intent localIntent = new Intent(paramContext, CanaryWorkerService.class);
    localIntent.setAction("com.tencent.matrix.resource.worker.action.SHRINK_HPROF");
    localIntent.putExtra("com.tencent.matrix.resource.worker.param.HEAPDUMP", parama);
    a(paramContext, CanaryWorkerService.class, -84148995, localIntent);
  }

  // ERROR //
  protected final void l(Intent paramIntent)
  {
    // Byte code:
    //   0: aload_1
    //   1: ifnull +770 -> 771
    //   4: ldc 18
    //   6: aload_1
    //   7: invokevirtual 42	android/content/Intent:getAction	()Ljava/lang/String;
    //   10: invokevirtual 48	java/lang/String:equals	(Ljava/lang/Object;)Z
    //   13: ifeq +758 -> 771
    //   16: aload_1
    //   17: ldc 24
    //   19: invokevirtual 52	android/content/Intent:getSerializableExtra	(Ljava/lang/String;)Ljava/io/Serializable;
    //   22: checkcast 54	com/tencent/matrix/resource/analyzer/model/a
    //   25: astore_2
    //   26: aload_2
    //   27: ifnull +807 -> 834
    //   30: aload_2
    //   31: getfield 58	com/tencent/matrix/resource/analyzer/model/a:bWS	Ljava/io/File;
    //   34: invokevirtual 64	java/io/File:getParentFile	()Ljava/io/File;
    //   37: astore_1
    //   38: aload_2
    //   39: getfield 58	com/tencent/matrix/resource/analyzer/model/a:bWS	Ljava/io/File;
    //   42: invokevirtual 67	java/io/File:getName	()Ljava/lang/String;
    //   45: astore_3
    //   46: aload_3
    //   47: iconst_0
    //   48: aload_3
    //   49: ldc 69
    //   51: invokevirtual 73	java/lang/String:indexOf	(Ljava/lang/String;)I
    //   54: invokevirtual 77	java/lang/String:substring	(II)Ljava/lang/String;
    //   57: astore_3
    //   58: new 60	java/io/File
    //   61: dup
    //   62: aload_1
    //   63: new 79	java/lang/StringBuilder
    //   66: dup
    //   67: invokespecial 80	java/lang/StringBuilder:<init>	()V
    //   70: aload_3
    //   71: invokevirtual 84	java/lang/StringBuilder:append	(Ljava/lang/String;)Ljava/lang/StringBuilder;
    //   74: ldc 86
    //   76: invokevirtual 84	java/lang/StringBuilder:append	(Ljava/lang/String;)Ljava/lang/StringBuilder;
    //   79: invokevirtual 89	java/lang/StringBuilder:toString	()Ljava/lang/String;
    //   82: invokespecial 92	java/io/File:<init>	(Ljava/io/File;Ljava/lang/String;)V
    //   85: astore 4
    //   87: new 79	java/lang/StringBuilder
    //   90: dup
    //   91: ldc 94
    //   93: invokespecial 97	java/lang/StringBuilder:<init>	(Ljava/lang/String;)V
    //   96: invokestatic 103	android/os/Process:myPid	()I
    //   99: invokevirtual 106	java/lang/StringBuilder:append	(I)Ljava/lang/StringBuilder;
    //   102: invokevirtual 89	java/lang/StringBuilder:toString	()Ljava/lang/String;
    //   105: astore 5
    //   107: new 79	java/lang/StringBuilder
    //   110: dup
    //   111: invokespecial 80	java/lang/StringBuilder:<init>	()V
    //   114: astore_3
    //   115: aload_3
    //   116: aload 5
    //   118: invokevirtual 84	java/lang/StringBuilder:append	(Ljava/lang/String;)Ljava/lang/StringBuilder;
    //   121: bipush 95
    //   123: invokevirtual 109	java/lang/StringBuilder:append	(C)Ljava/lang/StringBuilder;
    //   126: new 111	java/text/SimpleDateFormat
    //   129: dup
    //   130: ldc 113
    //   132: getstatic 119	java/util/Locale:ENGLISH	Ljava/util/Locale;
    //   135: invokespecial 122	java/text/SimpleDateFormat:<init>	(Ljava/lang/String;Ljava/util/Locale;)V
    //   138: new 124	java/util/Date
    //   141: dup
    //   142: invokespecial 125	java/util/Date:<init>	()V
    //   145: invokevirtual 129	java/text/SimpleDateFormat:format	(Ljava/util/Date;)Ljava/lang/String;
    //   148: invokevirtual 84	java/lang/StringBuilder:append	(Ljava/lang/String;)Ljava/lang/StringBuilder;
    //   151: ldc 131
    //   153: invokevirtual 84	java/lang/StringBuilder:append	(Ljava/lang/String;)Ljava/lang/StringBuilder;
    //   156: pop
    //   157: new 60	java/io/File
    //   160: dup
    //   161: aload_1
    //   162: aload_3
    //   163: invokevirtual 89	java/lang/StringBuilder:toString	()Ljava/lang/String;
    //   166: invokespecial 92	java/io/File:<init>	(Ljava/io/File;Ljava/lang/String;)V
    //   169: astore 6
    //   171: aload_2
    //   172: getfield 58	com/tencent/matrix/resource/analyzer/model/a:bWS	Ljava/io/File;
    //   175: astore 7
    //   177: invokestatic 137	java/lang/System:currentTimeMillis	()J
    //   180: lstore 8
    //   182: new 139	com/tencent/matrix/resource/c/a
    //   185: astore_1
    //   186: aload_1
    //   187: invokespecial 140	com/tencent/matrix/resource/c/a:<init>	()V
    //   190: new 142	java/io/FileInputStream
    //   193: astore 5
    //   195: aload 5
    //   197: aload 7
    //   199: invokespecial 145	java/io/FileInputStream:<init>	(Ljava/io/File;)V
    //   202: new 147	java/io/BufferedOutputStream
    //   205: astore_3
    //   206: new 149	java/io/FileOutputStream
    //   209: astore 10
    //   211: aload 10
    //   213: aload 4
    //   215: invokespecial 150	java/io/FileOutputStream:<init>	(Ljava/io/File;)V
    //   218: aload_3
    //   219: aload 10
    //   221: invokespecial 153	java/io/BufferedOutputStream:<init>	(Ljava/io/OutputStream;)V
    //   224: new 155	com/tencent/matrix/resource/c/c
    //   227: astore 10
    //   229: new 157	java/io/BufferedInputStream
    //   232: astore 11
    //   234: aload 11
    //   236: aload 5
    //   238: invokespecial 160	java/io/BufferedInputStream:<init>	(Ljava/io/InputStream;)V
    //   241: aload 10
    //   243: aload 11
    //   245: invokespecial 161	com/tencent/matrix/resource/c/c:<init>	(Ljava/io/InputStream;)V
    //   248: new 163	com/tencent/matrix/resource/c/a$b
    //   251: astore 11
    //   253: aload 11
    //   255: aload_1
    //   256: invokespecial 166	com/tencent/matrix/resource/c/a$b:<init>	(Lcom/tencent/matrix/resource/c/a;)V
    //   259: aload 10
    //   261: aload 11
    //   263: invokevirtual 169	com/tencent/matrix/resource/c/c:a	(Lcom/tencent/matrix/resource/c/d;)V
    //   266: aload 5
    //   268: invokevirtual 173	java/io/FileInputStream:getChannel	()Ljava/nio/channels/FileChannel;
    //   271: lconst_0
    //   272: invokevirtual 179	java/nio/channels/FileChannel:position	(J)Ljava/nio/channels/FileChannel;
    //   275: pop
    //   276: new 181	com/tencent/matrix/resource/c/a$c
    //   279: astore 11
    //   281: aload 11
    //   283: aload_1
    //   284: invokespecial 182	com/tencent/matrix/resource/c/a$c:<init>	(Lcom/tencent/matrix/resource/c/a;)V
    //   287: aload 10
    //   289: aload 11
    //   291: invokevirtual 169	com/tencent/matrix/resource/c/c:a	(Lcom/tencent/matrix/resource/c/d;)V
    //   294: aload 5
    //   296: invokevirtual 173	java/io/FileInputStream:getChannel	()Ljava/nio/channels/FileChannel;
    //   299: lconst_0
    //   300: invokevirtual 179	java/nio/channels/FileChannel:position	(J)Ljava/nio/channels/FileChannel;
    //   303: pop
    //   304: new 184	com/tencent/matrix/resource/c/a$a
    //   307: astore 11
    //   309: new 186	com/tencent/matrix/resource/c/e
    //   312: astore 12
    //   314: aload 12
    //   316: aload_3
    //   317: invokespecial 187	com/tencent/matrix/resource/c/e:<init>	(Ljava/io/OutputStream;)V
    //   320: aload 11
    //   322: aload_1
    //   323: aload 12
    //   325: invokespecial 190	com/tencent/matrix/resource/c/a$a:<init>	(Lcom/tencent/matrix/resource/c/a;Lcom/tencent/matrix/resource/c/e;)V
    //   328: aload 10
    //   330: aload 11
    //   332: invokevirtual 169	com/tencent/matrix/resource/c/c:a	(Lcom/tencent/matrix/resource/c/d;)V
    //   335: aload_3
    //   336: invokevirtual 195	java/io/OutputStream:close	()V
    //   339: aload 5
    //   341: invokevirtual 196	java/io/FileInputStream:close	()V
    //   344: ldc 198
    //   346: ldc 200
    //   348: iconst_5
    //   349: anewarray 202	java/lang/Object
    //   352: dup
    //   353: iconst_0
    //   354: aload 7
    //   356: invokevirtual 205	java/io/File:getPath	()Ljava/lang/String;
    //   359: aastore
    //   360: dup
    //   361: iconst_1
    //   362: aload 7
    //   364: invokevirtual 208	java/io/File:length	()J
    //   367: ldc2_w 209
    //   370: ldiv
    //   371: invokestatic 216	java/lang/Long:valueOf	(J)Ljava/lang/Long;
    //   374: aastore
    //   375: dup
    //   376: iconst_2
    //   377: aload 4
    //   379: invokevirtual 205	java/io/File:getPath	()Ljava/lang/String;
    //   382: aastore
    //   383: dup
    //   384: iconst_3
    //   385: aload 4
    //   387: invokevirtual 208	java/io/File:length	()J
    //   390: ldc2_w 209
    //   393: ldiv
    //   394: invokestatic 216	java/lang/Long:valueOf	(J)Ljava/lang/Long;
    //   397: aastore
    //   398: dup
    //   399: iconst_4
    //   400: invokestatic 137	java/lang/System:currentTimeMillis	()J
    //   403: lload 8
    //   405: lsub
    //   406: invokestatic 216	java/lang/Long:valueOf	(J)Ljava/lang/Long;
    //   409: aastore
    //   410: invokestatic 222	com/tencent/matrix/d/c:i	(Ljava/lang/String;Ljava/lang/String;[Ljava/lang/Object;)V
    //   413: new 224	java/util/zip/ZipOutputStream
    //   416: astore_3
    //   417: new 147	java/io/BufferedOutputStream
    //   420: astore 5
    //   422: new 149	java/io/FileOutputStream
    //   425: astore_1
    //   426: aload_1
    //   427: aload 6
    //   429: invokespecial 150	java/io/FileOutputStream:<init>	(Ljava/io/File;)V
    //   432: aload 5
    //   434: aload_1
    //   435: invokespecial 153	java/io/BufferedOutputStream:<init>	(Ljava/io/OutputStream;)V
    //   438: aload_3
    //   439: aload 5
    //   441: invokespecial 225	java/util/zip/ZipOutputStream:<init>	(Ljava/io/OutputStream;)V
    //   444: aload_3
    //   445: astore_1
    //   446: new 227	java/util/zip/ZipEntry
    //   449: astore 10
    //   451: aload_3
    //   452: astore_1
    //   453: aload 10
    //   455: ldc 229
    //   457: invokespecial 230	java/util/zip/ZipEntry:<init>	(Ljava/lang/String;)V
    //   460: aload_3
    //   461: astore_1
    //   462: new 227	java/util/zip/ZipEntry
    //   465: astore 5
    //   467: aload_3
    //   468: astore_1
    //   469: aload 5
    //   471: aload 4
    //   473: invokevirtual 67	java/io/File:getName	()Ljava/lang/String;
    //   476: invokespecial 230	java/util/zip/ZipEntry:<init>	(Ljava/lang/String;)V
    //   479: aload_3
    //   480: astore_1
    //   481: aload_3
    //   482: aload 10
    //   484: invokevirtual 234	java/util/zip/ZipOutputStream:putNextEntry	(Ljava/util/zip/ZipEntry;)V
    //   487: aload_3
    //   488: astore_1
    //   489: new 236	java/io/PrintWriter
    //   492: astore 10
    //   494: aload_3
    //   495: astore_1
    //   496: new 238	java/io/OutputStreamWriter
    //   499: astore 11
    //   501: aload_3
    //   502: astore_1
    //   503: aload 11
    //   505: aload_3
    //   506: ldc 240
    //   508: invokestatic 246	java/nio/charset/Charset:forName	(Ljava/lang/String;)Ljava/nio/charset/Charset;
    //   511: invokespecial 249	java/io/OutputStreamWriter:<init>	(Ljava/io/OutputStream;Ljava/nio/charset/Charset;)V
    //   514: aload_3
    //   515: astore_1
    //   516: aload 10
    //   518: aload 11
    //   520: invokespecial 252	java/io/PrintWriter:<init>	(Ljava/io/Writer;)V
    //   523: aload_3
    //   524: astore_1
    //   525: aload 10
    //   527: ldc 254
    //   529: invokevirtual 257	java/io/PrintWriter:println	(Ljava/lang/String;)V
    //   532: aload_3
    //   533: astore_1
    //   534: new 79	java/lang/StringBuilder
    //   537: astore 11
    //   539: aload_3
    //   540: astore_1
    //   541: aload 11
    //   543: ldc_w 259
    //   546: invokespecial 97	java/lang/StringBuilder:<init>	(Ljava/lang/String;)V
    //   549: aload_3
    //   550: astore_1
    //   551: aload 10
    //   553: aload 11
    //   555: getstatic 265	android/os/Build$VERSION:SDK_INT	I
    //   558: invokevirtual 106	java/lang/StringBuilder:append	(I)Ljava/lang/StringBuilder;
    //   561: invokevirtual 89	java/lang/StringBuilder:toString	()Ljava/lang/String;
    //   564: invokevirtual 257	java/io/PrintWriter:println	(Ljava/lang/String;)V
    //   567: aload_3
    //   568: astore_1
    //   569: new 79	java/lang/StringBuilder
    //   572: astore 11
    //   574: aload_3
    //   575: astore_1
    //   576: aload 11
    //   578: ldc_w 267
    //   581: invokespecial 97	java/lang/StringBuilder:<init>	(Ljava/lang/String;)V
    //   584: aload_3
    //   585: astore_1
    //   586: aload 10
    //   588: aload 11
    //   590: getstatic 273	android/os/Build:MANUFACTURER	Ljava/lang/String;
    //   593: invokevirtual 84	java/lang/StringBuilder:append	(Ljava/lang/String;)Ljava/lang/StringBuilder;
    //   596: invokevirtual 89	java/lang/StringBuilder:toString	()Ljava/lang/String;
    //   599: invokevirtual 257	java/io/PrintWriter:println	(Ljava/lang/String;)V
    //   602: aload_3
    //   603: astore_1
    //   604: new 79	java/lang/StringBuilder
    //   607: astore 11
    //   609: aload_3
    //   610: astore_1
    //   611: aload 11
    //   613: ldc_w 275
    //   616: invokespecial 97	java/lang/StringBuilder:<init>	(Ljava/lang/String;)V
    //   619: aload_3
    //   620: astore_1
    //   621: aload 10
    //   623: aload 11
    //   625: aload 5
    //   627: invokevirtual 276	java/util/zip/ZipEntry:getName	()Ljava/lang/String;
    //   630: invokevirtual 84	java/lang/StringBuilder:append	(Ljava/lang/String;)Ljava/lang/StringBuilder;
    //   633: invokevirtual 89	java/lang/StringBuilder:toString	()Ljava/lang/String;
    //   636: invokevirtual 257	java/io/PrintWriter:println	(Ljava/lang/String;)V
    //   639: aload_3
    //   640: astore_1
    //   641: new 79	java/lang/StringBuilder
    //   644: astore 11
    //   646: aload_3
    //   647: astore_1
    //   648: aload 11
    //   650: ldc_w 278
    //   653: invokespecial 97	java/lang/StringBuilder:<init>	(Ljava/lang/String;)V
    //   656: aload_3
    //   657: astore_1
    //   658: aload 10
    //   660: aload 11
    //   662: aload_2
    //   663: getfield 281	com/tencent/matrix/resource/analyzer/model/a:bWT	Ljava/lang/String;
    //   666: invokevirtual 84	java/lang/StringBuilder:append	(Ljava/lang/String;)Ljava/lang/StringBuilder;
    //   669: invokevirtual 89	java/lang/StringBuilder:toString	()Ljava/lang/String;
    //   672: invokevirtual 257	java/io/PrintWriter:println	(Ljava/lang/String;)V
    //   675: aload_3
    //   676: astore_1
    //   677: aload 10
    //   679: invokevirtual 284	java/io/PrintWriter:flush	()V
    //   682: aload_3
    //   683: astore_1
    //   684: aload_3
    //   685: invokevirtual 287	java/util/zip/ZipOutputStream:closeEntry	()V
    //   688: aload_3
    //   689: astore_1
    //   690: aload_3
    //   691: aload 5
    //   693: invokevirtual 234	java/util/zip/ZipOutputStream:putNextEntry	(Ljava/util/zip/ZipEntry;)V
    //   696: aload_3
    //   697: astore_1
    //   698: aload 4
    //   700: aload_3
    //   701: invokestatic 292	com/tencent/matrix/resource/a/a/c:a	(Ljava/io/File;Ljava/io/OutputStream;)V
    //   704: aload_3
    //   705: astore_1
    //   706: aload_3
    //   707: invokevirtual 287	java/util/zip/ZipOutputStream:closeEntry	()V
    //   710: aload_3
    //   711: astore_1
    //   712: aload 4
    //   714: invokevirtual 296	java/io/File:delete	()Z
    //   717: pop
    //   718: aload_3
    //   719: astore_1
    //   720: aload 7
    //   722: invokevirtual 296	java/io/File:delete	()Z
    //   725: pop
    //   726: aload_3
    //   727: astore_1
    //   728: ldc 198
    //   730: ldc_w 298
    //   733: iconst_1
    //   734: anewarray 202	java/lang/Object
    //   737: dup
    //   738: iconst_0
    //   739: invokestatic 137	java/lang/System:currentTimeMillis	()J
    //   742: lload 8
    //   744: lsub
    //   745: invokestatic 216	java/lang/Long:valueOf	(J)Ljava/lang/Long;
    //   748: aastore
    //   749: invokestatic 222	com/tencent/matrix/d/c:i	(Ljava/lang/String;Ljava/lang/String;[Ljava/lang/Object;)V
    //   752: aload_3
    //   753: astore_1
    //   754: aload_0
    //   755: aload 6
    //   757: invokevirtual 301	java/io/File:getAbsolutePath	()Ljava/lang/String;
    //   760: aload_2
    //   761: getfield 304	com/tencent/matrix/resource/analyzer/model/a:mActivityName	Ljava/lang/String;
    //   764: invokestatic 310	com/tencent/matrix/resource/CanaryResultService:d	(Landroid/content/Context;Ljava/lang/String;Ljava/lang/String;)V
    //   767: aload_3
    //   768: invokestatic 314	com/tencent/matrix/resource/a/a/c:ah	(Ljava/lang/Object;)V
    //   771: return
    //   772: astore_1
    //   773: aconst_null
    //   774: astore_3
    //   775: aconst_null
    //   776: astore 5
    //   778: aload_3
    //   779: ifnull +7 -> 786
    //   782: aload_3
    //   783: invokevirtual 195	java/io/OutputStream:close	()V
    //   786: aload 5
    //   788: ifnull +8 -> 796
    //   791: aload 5
    //   793: invokevirtual 196	java/io/FileInputStream:close	()V
    //   796: aload_1
    //   797: athrow
    //   798: astore 5
    //   800: aconst_null
    //   801: astore_3
    //   802: aload_3
    //   803: astore_1
    //   804: ldc 198
    //   806: aload 5
    //   808: ldc_w 316
    //   811: iconst_0
    //   812: anewarray 202	java/lang/Object
    //   815: invokestatic 320	com/tencent/matrix/d/c:printErrStackTrace	(Ljava/lang/String;Ljava/lang/Throwable;Ljava/lang/String;[Ljava/lang/Object;)V
    //   818: aload_3
    //   819: invokestatic 314	com/tencent/matrix/resource/a/a/c:ah	(Ljava/lang/Object;)V
    //   822: goto -51 -> 771
    //   825: astore_3
    //   826: aconst_null
    //   827: astore_1
    //   828: aload_1
    //   829: invokestatic 314	com/tencent/matrix/resource/a/a/c:ah	(Ljava/lang/Object;)V
    //   832: aload_3
    //   833: athrow
    //   834: ldc 198
    //   836: ldc_w 322
    //   839: iconst_0
    //   840: anewarray 202	java/lang/Object
    //   843: invokestatic 325	com/tencent/matrix/d/c:e	(Ljava/lang/String;Ljava/lang/String;[Ljava/lang/Object;)V
    //   846: goto -75 -> 771
    //   849: astore_1
    //   850: goto -511 -> 339
    //   853: astore_1
    //   854: goto -510 -> 344
    //   857: astore_3
    //   858: goto -72 -> 786
    //   861: astore_3
    //   862: goto -66 -> 796
    //   865: astore_3
    //   866: goto -38 -> 828
    //   869: astore 5
    //   871: goto -69 -> 802
    //   874: astore_1
    //   875: aconst_null
    //   876: astore_3
    //   877: goto -99 -> 778
    //   880: astore_1
    //   881: goto -103 -> 778
    //
    // Exception table:
    //   from	to	target	type
    //   190	202	772	finally
    //   177	190	798	java/io/IOException
    //   335	339	798	java/io/IOException
    //   339	344	798	java/io/IOException
    //   344	444	798	java/io/IOException
    //   782	786	798	java/io/IOException
    //   791	796	798	java/io/IOException
    //   796	798	798	java/io/IOException
    //   177	190	825	finally
    //   335	339	825	finally
    //   339	344	825	finally
    //   344	444	825	finally
    //   782	786	825	finally
    //   791	796	825	finally
    //   796	798	825	finally
    //   335	339	849	java/lang/Throwable
    //   339	344	853	java/lang/Throwable
    //   782	786	857	java/lang/Throwable
    //   791	796	861	java/lang/Throwable
    //   446	451	865	finally
    //   453	460	865	finally
    //   462	467	865	finally
    //   469	479	865	finally
    //   481	487	865	finally
    //   489	494	865	finally
    //   496	501	865	finally
    //   503	514	865	finally
    //   516	523	865	finally
    //   525	532	865	finally
    //   534	539	865	finally
    //   541	549	865	finally
    //   551	567	865	finally
    //   569	574	865	finally
    //   576	584	865	finally
    //   586	602	865	finally
    //   604	609	865	finally
    //   611	619	865	finally
    //   621	639	865	finally
    //   641	646	865	finally
    //   648	656	865	finally
    //   658	675	865	finally
    //   677	682	865	finally
    //   684	688	865	finally
    //   690	696	865	finally
    //   698	704	865	finally
    //   706	710	865	finally
    //   712	718	865	finally
    //   720	726	865	finally
    //   728	752	865	finally
    //   754	767	865	finally
    //   804	818	865	finally
    //   446	451	869	java/io/IOException
    //   453	460	869	java/io/IOException
    //   462	467	869	java/io/IOException
    //   469	479	869	java/io/IOException
    //   481	487	869	java/io/IOException
    //   489	494	869	java/io/IOException
    //   496	501	869	java/io/IOException
    //   503	514	869	java/io/IOException
    //   516	523	869	java/io/IOException
    //   525	532	869	java/io/IOException
    //   534	539	869	java/io/IOException
    //   541	549	869	java/io/IOException
    //   551	567	869	java/io/IOException
    //   569	574	869	java/io/IOException
    //   576	584	869	java/io/IOException
    //   586	602	869	java/io/IOException
    //   604	609	869	java/io/IOException
    //   611	619	869	java/io/IOException
    //   621	639	869	java/io/IOException
    //   641	646	869	java/io/IOException
    //   648	656	869	java/io/IOException
    //   658	675	869	java/io/IOException
    //   677	682	869	java/io/IOException
    //   684	688	869	java/io/IOException
    //   690	696	869	java/io/IOException
    //   698	704	869	java/io/IOException
    //   706	710	869	java/io/IOException
    //   712	718	869	java/io/IOException
    //   720	726	869	java/io/IOException
    //   728	752	869	java/io/IOException
    //   754	767	869	java/io/IOException
    //   202	224	874	finally
    //   224	335	880	finally
  }
}

/* Location:           C:\Users\Lin\Downloads\dex-tools-2.1-SNAPSHOT\dex-tools-2.1-SNAPSHOT\classes-dex2jar.jar
 * Qualified Name:     com.tencent.matrix.resource.CanaryWorkerService
 * JD-Core Version:    0.6.2
 */