package com.tencent.mm.plugin.emojicapture.ui.capture;

import a.f.a.b;
import a.f.b.k;
import a.l;
import a.y;
import com.tencent.matrix.trace.core.AppMethodBeat;
import com.tencent.mm.media.widget.camerarecordview.a.a;
import com.tencent.mm.plugin.mmsight.ui.MMSightCircularProgressBar.a;
import com.tencent.mm.sdk.platformtools.ab;

@l(dWo={1, 1, 13}, dWp={""}, dWq={"<anonymous>", "", "onProgressFinish"})
final class CaptureContainer$1$a
  implements MMSightCircularProgressBar.a
{
  CaptureContainer$1$a(CaptureContainer.1 param1)
  {
  }

  public final void bnW()
  {
    // Byte code:
    //   0: sipush 2945
    //   3: invokestatic 39	com/tencent/matrix/trace/core/AppMethodBeat:i	(I)V
    //   6: aload_0
    //   7: getfield 29	com/tencent/mm/plugin/emojicapture/ui/capture/CaptureContainer$1$a:lmu	Lcom/tencent/mm/plugin/emojicapture/ui/capture/CaptureContainer$1;
    //   10: getfield 43	com/tencent/mm/plugin/emojicapture/ui/capture/CaptureContainer$1:lmt	Lcom/tencent/mm/plugin/emojicapture/ui/capture/CaptureContainer;
    //   13: invokestatic 49	com/tencent/mm/plugin/emojicapture/ui/capture/CaptureContainer:e	(Lcom/tencent/mm/plugin/emojicapture/ui/capture/CaptureContainer;)Ljava/lang/String;
    //   16: ldc 51
    //   18: invokestatic 56	com/tencent/mm/sdk/platformtools/ab:i	(Ljava/lang/String;Ljava/lang/String;)V
    //   21: aload_0
    //   22: getfield 29	com/tencent/mm/plugin/emojicapture/ui/capture/CaptureContainer$1$a:lmu	Lcom/tencent/mm/plugin/emojicapture/ui/capture/CaptureContainer$1;
    //   25: getfield 43	com/tencent/mm/plugin/emojicapture/ui/capture/CaptureContainer$1:lmt	Lcom/tencent/mm/plugin/emojicapture/ui/capture/CaptureContainer;
    //   28: aload_0
    //   29: getfield 29	com/tencent/mm/plugin/emojicapture/ui/capture/CaptureContainer$1$a:lmu	Lcom/tencent/mm/plugin/emojicapture/ui/capture/CaptureContainer$1;
    //   32: getfield 43	com/tencent/mm/plugin/emojicapture/ui/capture/CaptureContainer$1:lmt	Lcom/tencent/mm/plugin/emojicapture/ui/capture/CaptureContainer;
    //   35: new 13	com/tencent/mm/plugin/emojicapture/ui/capture/CaptureContainer$1$a$1
    //   38: dup
    //   39: aload_0
    //   40: invokespecial 59	com/tencent/mm/plugin/emojicapture/ui/capture/CaptureContainer$1$a$1:<init>	(Lcom/tencent/mm/plugin/emojicapture/ui/capture/CaptureContainer$1$a;)V
    //   43: checkcast 61	a/f/a/b
    //   46: invokevirtual 65	com/tencent/mm/plugin/emojicapture/ui/capture/CaptureContainer:a	(La/f/a/b;)Z
    //   49: invokestatic 68	com/tencent/mm/plugin/emojicapture/ui/capture/CaptureContainer:a	(Lcom/tencent/mm/plugin/emojicapture/ui/capture/CaptureContainer;Z)V
    //   52: sipush 2945
    //   55: invokestatic 71	com/tencent/matrix/trace/core/AppMethodBeat:o	(I)V
    //   58: return
  }
}

/* Location:           C:\Users\Lin\Downloads\dex-tools-2.1-SNAPSHOT\dex-tools-2.1-SNAPSHOT\classes8-dex2jar.jar
 * Qualified Name:     com.tencent.mm.plugin.emojicapture.ui.capture.CaptureContainer.1.a
 * JD-Core Version:    0.6.2
 */