package com.tencent.mm.plugin.readerapp.c;

import android.database.Cursor;
import com.tencent.matrix.trace.core.AppMethodBeat;
import com.tencent.mm.ai.d;
import com.tencent.mm.ai.e.c;
import com.tencent.mm.cd.h;
import com.tencent.mm.g.c.at;
import com.tencent.mm.model.bl;
import com.tencent.mm.model.bm;
import com.tencent.mm.model.r;
import com.tencent.mm.plugin.messenger.foundation.a.j;
import com.tencent.mm.sdk.platformtools.ab;
import com.tencent.mm.storage.ak;
import com.tencent.mm.storage.be;
import java.util.Iterator;
import java.util.List;

public final class c
  implements d
{
  public static boolean cdX()
  {
    AppMethodBeat.i(76757);
    boolean bool;
    if ((r.YF() & 0x400) == 0)
    {
      bool = true;
      AppMethodBeat.o(76757);
    }
    while (true)
    {
      return bool;
      bool = false;
      AppMethodBeat.o(76757);
    }
  }

  public final void a(e.c paramc)
  {
    AppMethodBeat.i(76758);
    Object localObject1 = (String)paramc.fsY;
    ab.i("MicroMsg.ReaderAppMsgExtension", "[onPreDelMessage] functionId:%s", new Object[] { localObject1 });
    try
    {
      localObject2 = g.cdZ();
      localObject3 = ((bm)localObject2).R((String)localObject1, 20);
      if ((localObject3 == null) || (((List)localObject3).size() == 0))
        AppMethodBeat.o(76758);
      while (true)
      {
        return;
        paramc = (bl)((List)localObject3).get(0);
        Iterator localIterator = ((List)localObject3).iterator();
        while (localIterator.hasNext())
        {
          localObject3 = (bl)localIterator.next();
          if (((bl)localObject3).fnd != 1)
            break label513;
          paramc = (e.c)localObject3;
        }
        if (((bm)localObject2).fni.delete(bm.kH(20), "reserved3=?", new String[] { localObject1 }) >= 0)
          ((bm)localObject2).doNotify();
        localObject3 = new java/lang/StringBuilder;
        ((StringBuilder)localObject3).<init>();
        localObject3 = bm.oH(bm.kH(20)) + " where istop = 1  group by time ORDER BY time DESC  limit 2";
        ab.i("MicroMsg.ReaderAppInfoStorage", "processConversationAfterDeleteInfo, sql is %s", new Object[] { localObject3 });
        localObject1 = ((bm)localObject2).fni.a((String)localObject3, null, 2);
        if (((Cursor)localObject1).moveToFirst())
          break;
        ((Cursor)localObject1).close();
        paramc = new com/tencent/mm/storage/ak;
        paramc.<init>();
        paramc.setUsername(bl.kG(20));
        paramc.setContent("");
        paramc.eD(0L);
        paramc.hO(0);
        paramc.hM(0);
        ((j)com.tencent.mm.kernel.g.K(j.class)).XR().a(paramc, bl.kG(20));
        AppMethodBeat.o(76758);
      }
    }
    catch (Exception paramc)
    {
      label513: 
      while (true)
      {
        Object localObject3;
        ab.e("MicroMsg.ReaderAppMsgExtension", "[onPreDelMessage] Exception:%s", new Object[] { paramc });
        AppMethodBeat.o(76758);
        continue;
        Object localObject2 = ((j)com.tencent.mm.kernel.g.K(j.class)).XR().aoZ(bl.kG(20));
        if (localObject2 == null)
        {
          ab.e("MicroMsg.ReaderAppInfoStorage", "[processConversationAfterDeleteInfo] originConv[%s] is null!", new Object[] { bl.kG(20) });
          AppMethodBeat.o(76758);
        }
        else
        {
          localObject3 = new com/tencent/mm/model/bl;
          ((bl)localObject3).<init>();
          ((bl)localObject3).d((Cursor)localObject1);
          ((Cursor)localObject1).close();
          localObject1 = new com/tencent/mm/storage/ak;
          ((ak)localObject1).<init>();
          ((ak)localObject1).setUsername(bl.kG(20));
          ((ak)localObject1).setContent(((bl)localObject3).getTitle());
          ((ak)localObject1).eD(((bl)localObject3).time);
          ((ak)localObject1).hO(0);
          if ((((at)localObject2).field_unReadCount > 0) && (paramc != null) && (((at)localObject2).field_content.equals(paramc.getTitle())))
            ((ak)localObject1).hM(((at)localObject2).field_unReadCount - 1);
          while (true)
          {
            ((j)com.tencent.mm.kernel.g.K(j.class)).XR().a((ak)localObject1, bl.kG(20));
            AppMethodBeat.o(76758);
            break;
            ((ak)localObject1).hM(0);
          }
        }
      }
    }
  }

  // ERROR //
  public final com.tencent.mm.ai.e.b b(com.tencent.mm.ai.e.a parama)
  {
    // Byte code:
    //   0: ldc 223
    //   2: invokestatic 20	com/tencent/matrix/trace/core/AppMethodBeat:i	(I)V
    //   5: aload_1
    //   6: getfield 229	com/tencent/mm/ai/e$a:eAB	Lcom/tencent/mm/protocal/protobuf/cm;
    //   9: astore_2
    //   10: aload_1
    //   11: getfield 230	com/tencent/mm/ai/e$a:fsY	Ljava/lang/Object;
    //   14: ifnonnull +61 -> 75
    //   17: new 112	java/lang/StringBuilder
    //   20: dup
    //   21: ldc 232
    //   23: invokespecial 234	java/lang/StringBuilder:<init>	(Ljava/lang/String;)V
    //   26: invokestatic 240	java/lang/System:currentTimeMillis	()J
    //   29: ldc2_w 241
    //   32: ldiv
    //   33: invokevirtual 245	java/lang/StringBuilder:append	(J)Ljava/lang/StringBuilder;
    //   36: invokevirtual 127	java/lang/StringBuilder:toString	()Ljava/lang/String;
    //   39: astore_1
    //   40: ldc 44
    //   42: ldc 247
    //   44: iconst_1
    //   45: anewarray 4	java/lang/Object
    //   48: dup
    //   49: iconst_0
    //   50: aload_1
    //   51: aastore
    //   52: invokestatic 250	com/tencent/mm/sdk/platformtools/ab:w	(Ljava/lang/String;Ljava/lang/String;[Ljava/lang/Object;)V
    //   55: aload_2
    //   56: ifnonnull +33 -> 89
    //   59: ldc 44
    //   61: ldc 252
    //   63: invokestatic 255	com/tencent/mm/sdk/platformtools/ab:e	(Ljava/lang/String;Ljava/lang/String;)V
    //   66: aconst_null
    //   67: astore_1
    //   68: ldc 223
    //   70: invokestatic 29	com/tencent/matrix/trace/core/AppMethodBeat:o	(I)V
    //   73: aload_1
    //   74: areturn
    //   75: aload_1
    //   76: getfield 230	com/tencent/mm/ai/e$a:fsY	Ljava/lang/Object;
    //   79: checkcast 257	com/tencent/mm/ai/d$b
    //   82: getfield 260	com/tencent/mm/ai/d$b:fsT	Ljava/lang/String;
    //   85: astore_1
    //   86: goto -31 -> 55
    //   89: getstatic 266	com/tencent/mm/plugin/report/service/h:pYm	Lcom/tencent/mm/plugin/report/service/h;
    //   92: sipush 13440
    //   95: iconst_1
    //   96: anewarray 4	java/lang/Object
    //   99: dup
    //   100: iconst_0
    //   101: iconst_1
    //   102: invokestatic 272	java/lang/Integer:valueOf	(I)Ljava/lang/Integer;
    //   105: aastore
    //   106: invokevirtual 275	com/tencent/mm/plugin/report/service/h:e	(I[Ljava/lang/Object;)V
    //   109: invokestatic 57	com/tencent/mm/plugin/readerapp/c/g:cdZ	()Lcom/tencent/mm/model/bm;
    //   112: astore_3
    //   113: new 112	java/lang/StringBuilder
    //   116: dup
    //   117: ldc_w 277
    //   120: invokespecial 234	java/lang/StringBuilder:<init>	(Ljava/lang/String;)V
    //   123: bipush 20
    //   125: invokestatic 99	com/tencent/mm/model/bm:kH	(I)Ljava/lang/String;
    //   128: invokevirtual 121	java/lang/StringBuilder:append	(Ljava/lang/String;)Ljava/lang/StringBuilder;
    //   131: ldc_w 279
    //   134: invokevirtual 121	java/lang/StringBuilder:append	(Ljava/lang/String;)Ljava/lang/StringBuilder;
    //   137: aload_1
    //   138: invokestatic 282	com/tencent/mm/cd/h:escape	(Ljava/lang/String;)Ljava/lang/String;
    //   141: invokevirtual 121	java/lang/StringBuilder:append	(Ljava/lang/String;)Ljava/lang/StringBuilder;
    //   144: invokevirtual 127	java/lang/StringBuilder:toString	()Ljava/lang/String;
    //   147: astore 4
    //   149: ldc 129
    //   151: ldc_w 284
    //   154: iconst_1
    //   155: anewarray 4	java/lang/Object
    //   158: dup
    //   159: iconst_0
    //   160: aload 4
    //   162: aastore
    //   163: invokestatic 286	com/tencent/mm/sdk/platformtools/ab:d	(Ljava/lang/String;Ljava/lang/String;[Ljava/lang/Object;)V
    //   166: aload_3
    //   167: getfield 95	com/tencent/mm/model/bm:fni	Lcom/tencent/mm/cd/h;
    //   170: bipush 20
    //   172: invokestatic 99	com/tencent/mm/model/bm:kH	(I)Ljava/lang/String;
    //   175: aload 4
    //   177: invokevirtual 290	com/tencent/mm/cd/h:hY	(Ljava/lang/String;Ljava/lang/String;)Z
    //   180: ifeq +7 -> 187
    //   183: aload_3
    //   184: invokevirtual 110	com/tencent/mm/model/bm:doNotify	()V
    //   187: aload_2
    //   188: getfield 296	com/tencent/mm/protocal/protobuf/cm:vED	Lcom/tencent/mm/protocal/protobuf/bts;
    //   191: invokestatic 301	com/tencent/mm/platformtools/aa:a	(Lcom/tencent/mm/protocal/protobuf/bts;)Ljava/lang/String;
    //   194: astore 4
    //   196: aload_2
    //   197: getfield 304	com/tencent/mm/protocal/protobuf/cm:pcX	I
    //   200: i2l
    //   201: lstore 5
    //   203: ldc 44
    //   205: ldc_w 306
    //   208: iconst_2
    //   209: anewarray 4	java/lang/Object
    //   212: dup
    //   213: iconst_0
    //   214: aload_2
    //   215: getfield 304	com/tencent/mm/protocal/protobuf/cm:pcX	I
    //   218: invokestatic 272	java/lang/Integer:valueOf	(I)Ljava/lang/Integer;
    //   221: aastore
    //   222: dup
    //   223: iconst_1
    //   224: aload 4
    //   226: aastore
    //   227: invokestatic 286	com/tencent/mm/sdk/platformtools/ab:d	(Ljava/lang/String;Ljava/lang/String;[Ljava/lang/Object;)V
    //   230: new 308	java/text/SimpleDateFormat
    //   233: dup
    //   234: ldc_w 310
    //   237: invokespecial 311	java/text/SimpleDateFormat:<init>	(Ljava/lang/String;)V
    //   240: astore 7
    //   242: iconst_0
    //   243: istore 8
    //   245: new 313	java/util/ArrayList
    //   248: dup
    //   249: invokespecial 314	java/util/ArrayList:<init>	()V
    //   252: astore 9
    //   254: iconst_0
    //   255: istore 10
    //   257: aload 4
    //   259: ldc_w 316
    //   262: invokestatic 322	com/tencent/mm/sdk/platformtools/br:z	(Ljava/lang/String;Ljava/lang/String;)Ljava/util/Map;
    //   265: astore 11
    //   267: aload 11
    //   269: ifnonnull +13 -> 282
    //   272: aconst_null
    //   273: astore_1
    //   274: ldc 223
    //   276: invokestatic 29	com/tencent/matrix/trace/core/AppMethodBeat:o	(I)V
    //   279: goto -206 -> 73
    //   282: iconst_0
    //   283: istore 12
    //   285: iconst_0
    //   286: istore 10
    //   288: iload 12
    //   290: ifgt +2640 -> 2930
    //   293: new 112	java/lang/StringBuilder
    //   296: astore_3
    //   297: aload_3
    //   298: ldc_w 324
    //   301: invokespecial 234	java/lang/StringBuilder:<init>	(Ljava/lang/String;)V
    //   304: iload 12
    //   306: ifle +805 -> 1111
    //   309: iload 12
    //   311: invokestatic 272	java/lang/Integer:valueOf	(I)Ljava/lang/Integer;
    //   314: astore 4
    //   316: aload_3
    //   317: aload 4
    //   319: invokevirtual 327	java/lang/StringBuilder:append	(Ljava/lang/Object;)Ljava/lang/StringBuilder;
    //   322: invokevirtual 127	java/lang/StringBuilder:toString	()Ljava/lang/String;
    //   325: astore 4
    //   327: new 112	java/lang/StringBuilder
    //   330: astore_3
    //   331: aload_3
    //   332: invokespecial 113	java/lang/StringBuilder:<init>	()V
    //   335: aload 11
    //   337: aload_3
    //   338: aload 4
    //   340: invokevirtual 121	java/lang/StringBuilder:append	(Ljava/lang/String;)Ljava/lang/StringBuilder;
    //   343: ldc_w 329
    //   346: invokevirtual 121	java/lang/StringBuilder:append	(Ljava/lang/String;)Ljava/lang/StringBuilder;
    //   349: invokevirtual 127	java/lang/StringBuilder:toString	()Ljava/lang/String;
    //   352: invokeinterface 334 2 0
    //   357: checkcast 42	java/lang/String
    //   360: iconst_0
    //   361: invokestatic 340	com/tencent/mm/sdk/platformtools/bo:getInt	(Ljava/lang/String;I)I
    //   364: istore 13
    //   366: iload 13
    //   368: ifne +750 -> 1118
    //   371: new 112	java/lang/StringBuilder
    //   374: astore_1
    //   375: aload_1
    //   376: ldc_w 342
    //   379: invokespecial 234	java/lang/StringBuilder:<init>	(Ljava/lang/String;)V
    //   382: ldc 44
    //   384: aload_1
    //   385: aload 4
    //   387: invokevirtual 121	java/lang/StringBuilder:append	(Ljava/lang/String;)Ljava/lang/StringBuilder;
    //   390: ldc_w 344
    //   393: invokevirtual 121	java/lang/StringBuilder:append	(Ljava/lang/String;)Ljava/lang/StringBuilder;
    //   396: invokevirtual 127	java/lang/StringBuilder:toString	()Ljava/lang/String;
    //   399: invokestatic 255	com/tencent/mm/sdk/platformtools/ab:e	(Ljava/lang/String;Ljava/lang/String;)V
    //   402: iload 10
    //   404: istore 13
    //   406: invokestatic 346	com/tencent/mm/plugin/readerapp/c/c:cdX	()Z
    //   409: istore 14
    //   411: ldc 44
    //   413: new 112	java/lang/StringBuilder
    //   416: dup
    //   417: ldc_w 348
    //   420: invokespecial 234	java/lang/StringBuilder:<init>	(Ljava/lang/String;)V
    //   423: iload 13
    //   425: invokevirtual 351	java/lang/StringBuilder:append	(I)Ljava/lang/StringBuilder;
    //   428: ldc_w 353
    //   431: invokevirtual 121	java/lang/StringBuilder:append	(Ljava/lang/String;)Ljava/lang/StringBuilder;
    //   434: iload 14
    //   436: invokevirtual 356	java/lang/StringBuilder:append	(Z)Ljava/lang/StringBuilder;
    //   439: invokevirtual 127	java/lang/StringBuilder:toString	()Ljava/lang/String;
    //   442: invokestatic 358	com/tencent/mm/sdk/platformtools/ab:d	(Ljava/lang/String;Ljava/lang/String;)V
    //   445: aload 9
    //   447: invokeinterface 78 1 0
    //   452: astore_1
    //   453: aload_1
    //   454: invokeinterface 83 1 0
    //   459: ifeq +2915 -> 3374
    //   462: aload_1
    //   463: invokeinterface 87 1 0
    //   468: checkcast 74	com/tencent/mm/model/bl
    //   471: astore 4
    //   473: aload 4
    //   475: invokevirtual 203	com/tencent/mm/model/bl:getTitle	()Ljava/lang/String;
    //   478: invokestatic 362	com/tencent/mm/sdk/platformtools/bo:isNullOrNil	(Ljava/lang/String;)Z
    //   481: ifeq +2456 -> 2937
    //   484: ldc 44
    //   486: new 112	java/lang/StringBuilder
    //   489: dup
    //   490: ldc_w 364
    //   493: invokespecial 234	java/lang/StringBuilder:<init>	(Ljava/lang/String;)V
    //   496: aload 4
    //   498: invokevirtual 367	com/tencent/mm/model/bl:aaj	()Ljava/lang/String;
    //   501: invokevirtual 121	java/lang/StringBuilder:append	(Ljava/lang/String;)Ljava/lang/StringBuilder;
    //   504: ldc_w 369
    //   507: invokevirtual 121	java/lang/StringBuilder:append	(Ljava/lang/String;)Ljava/lang/StringBuilder;
    //   510: aload 4
    //   512: getfield 372	com/tencent/mm/model/bl:type	I
    //   515: invokevirtual 351	java/lang/StringBuilder:append	(I)Ljava/lang/StringBuilder;
    //   518: invokevirtual 127	java/lang/StringBuilder:toString	()Ljava/lang/String;
    //   521: invokestatic 255	com/tencent/mm/sdk/platformtools/ab:e	(Ljava/lang/String;Ljava/lang/String;)V
    //   524: iconst_0
    //   525: istore 10
    //   527: aload 9
    //   529: invokeinterface 68 1 0
    //   534: ifle +2816 -> 3350
    //   537: iload 10
    //   539: ifeq +2811 -> 3350
    //   542: iconst_0
    //   543: istore 8
    //   545: aconst_null
    //   546: astore_1
    //   547: iconst_0
    //   548: istore 10
    //   550: iload 10
    //   552: aload 9
    //   554: invokeinterface 68 1 0
    //   559: if_icmpge +2468 -> 3027
    //   562: invokestatic 57	com/tencent/mm/plugin/readerapp/c/g:cdZ	()Lcom/tencent/mm/model/bm;
    //   565: astore 15
    //   567: aload 9
    //   569: iload 10
    //   571: invokeinterface 72 2 0
    //   576: checkcast 74	com/tencent/mm/model/bl
    //   579: astore_3
    //   580: aload_3
    //   581: ifnull +2440 -> 3021
    //   584: aload_3
    //   585: iconst_m1
    //   586: putfield 375	com/tencent/mm/model/bl:bJt	I
    //   589: new 377	android/content/ContentValues
    //   592: dup
    //   593: invokespecial 378	android/content/ContentValues:<init>	()V
    //   596: astore 16
    //   598: aload_3
    //   599: getfield 375	com/tencent/mm/model/bl:bJt	I
    //   602: iconst_1
    //   603: iand
    //   604: ifeq +15 -> 619
    //   607: aload 16
    //   609: ldc_w 380
    //   612: aload_3
    //   613: invokevirtual 367	com/tencent/mm/model/bl:aaj	()Ljava/lang/String;
    //   616: invokevirtual 383	android/content/ContentValues:put	(Ljava/lang/String;Ljava/lang/String;)V
    //   619: aload_3
    //   620: getfield 375	com/tencent/mm/model/bl:bJt	I
    //   623: iconst_2
    //   624: iand
    //   625: ifeq +18 -> 643
    //   628: aload 16
    //   630: ldc_w 384
    //   633: aload_3
    //   634: getfield 207	com/tencent/mm/model/bl:time	J
    //   637: invokestatic 389	java/lang/Long:valueOf	(J)Ljava/lang/Long;
    //   640: invokevirtual 392	android/content/ContentValues:put	(Ljava/lang/String;Ljava/lang/Long;)V
    //   643: aload_3
    //   644: getfield 375	com/tencent/mm/model/bl:bJt	I
    //   647: iconst_4
    //   648: iand
    //   649: ifeq +18 -> 667
    //   652: aload 16
    //   654: ldc_w 393
    //   657: aload_3
    //   658: getfield 372	com/tencent/mm/model/bl:type	I
    //   661: invokestatic 272	java/lang/Integer:valueOf	(I)Ljava/lang/Integer;
    //   664: invokevirtual 396	android/content/ContentValues:put	(Ljava/lang/String;Ljava/lang/Integer;)V
    //   667: aload_3
    //   668: getfield 375	com/tencent/mm/model/bl:bJt	I
    //   671: bipush 8
    //   673: iand
    //   674: ifeq +15 -> 689
    //   677: aload 16
    //   679: ldc_w 398
    //   682: aload_3
    //   683: invokevirtual 401	com/tencent/mm/model/bl:getName	()Ljava/lang/String;
    //   686: invokevirtual 383	android/content/ContentValues:put	(Ljava/lang/String;Ljava/lang/String;)V
    //   689: aload_3
    //   690: getfield 375	com/tencent/mm/model/bl:bJt	I
    //   693: bipush 16
    //   695: iand
    //   696: ifeq +15 -> 711
    //   699: aload 16
    //   701: ldc_w 403
    //   704: aload_3
    //   705: invokevirtual 203	com/tencent/mm/model/bl:getTitle	()Ljava/lang/String;
    //   708: invokevirtual 383	android/content/ContentValues:put	(Ljava/lang/String;Ljava/lang/String;)V
    //   711: aload_3
    //   712: getfield 375	com/tencent/mm/model/bl:bJt	I
    //   715: bipush 32
    //   717: iand
    //   718: ifeq +15 -> 733
    //   721: aload 16
    //   723: ldc_w 405
    //   726: aload_3
    //   727: invokevirtual 408	com/tencent/mm/model/bl:getUrl	()Ljava/lang/String;
    //   730: invokevirtual 383	android/content/ContentValues:put	(Ljava/lang/String;Ljava/lang/String;)V
    //   733: aload_3
    //   734: getfield 375	com/tencent/mm/model/bl:bJt	I
    //   737: bipush 64
    //   739: iand
    //   740: ifeq +15 -> 755
    //   743: aload 16
    //   745: ldc_w 410
    //   748: aload_3
    //   749: invokevirtual 413	com/tencent/mm/model/bl:aak	()Ljava/lang/String;
    //   752: invokevirtual 383	android/content/ContentValues:put	(Ljava/lang/String;Ljava/lang/String;)V
    //   755: aload_3
    //   756: getfield 375	com/tencent/mm/model/bl:bJt	I
    //   759: sipush 128
    //   762: iand
    //   763: ifeq +24 -> 787
    //   766: aload_3
    //   767: getfield 416	com/tencent/mm/model/bl:fmZ	Ljava/lang/String;
    //   770: ifnonnull +2224 -> 2994
    //   773: ldc 154
    //   775: astore 4
    //   777: aload 16
    //   779: ldc_w 418
    //   782: aload 4
    //   784: invokevirtual 383	android/content/ContentValues:put	(Ljava/lang/String;Ljava/lang/String;)V
    //   787: aload_3
    //   788: getfield 375	com/tencent/mm/model/bl:bJt	I
    //   791: sipush 256
    //   794: iand
    //   795: ifeq +18 -> 813
    //   798: aload 16
    //   800: ldc_w 420
    //   803: aload_3
    //   804: getfield 423	com/tencent/mm/model/bl:fna	J
    //   807: invokestatic 389	java/lang/Long:valueOf	(J)Ljava/lang/Long;
    //   810: invokevirtual 392	android/content/ContentValues:put	(Ljava/lang/String;Ljava/lang/Long;)V
    //   813: aload_3
    //   814: getfield 375	com/tencent/mm/model/bl:bJt	I
    //   817: sipush 512
    //   820: iand
    //   821: ifeq +15 -> 836
    //   824: aload 16
    //   826: ldc_w 425
    //   829: aload_3
    //   830: invokevirtual 428	com/tencent/mm/model/bl:aal	()Ljava/lang/String;
    //   833: invokevirtual 383	android/content/ContentValues:put	(Ljava/lang/String;Ljava/lang/String;)V
    //   836: aload_3
    //   837: getfield 375	com/tencent/mm/model/bl:bJt	I
    //   840: sipush 1024
    //   843: iand
    //   844: ifeq +15 -> 859
    //   847: aload 16
    //   849: ldc_w 430
    //   852: aload_3
    //   853: invokevirtual 433	com/tencent/mm/model/bl:aam	()Ljava/lang/String;
    //   856: invokevirtual 383	android/content/ContentValues:put	(Ljava/lang/String;Ljava/lang/String;)V
    //   859: aload_3
    //   860: getfield 375	com/tencent/mm/model/bl:bJt	I
    //   863: sipush 2048
    //   866: iand
    //   867: ifeq +18 -> 885
    //   870: aload 16
    //   872: ldc_w 435
    //   875: aload_3
    //   876: getfield 91	com/tencent/mm/model/bl:fnd	I
    //   879: invokestatic 272	java/lang/Integer:valueOf	(I)Ljava/lang/Integer;
    //   882: invokevirtual 396	android/content/ContentValues:put	(Ljava/lang/String;Ljava/lang/Integer;)V
    //   885: aload_3
    //   886: getfield 375	com/tencent/mm/model/bl:bJt	I
    //   889: sipush 4096
    //   892: iand
    //   893: ifeq +15 -> 908
    //   896: aload 16
    //   898: ldc_w 437
    //   901: aload_3
    //   902: invokevirtual 440	com/tencent/mm/model/bl:aan	()Ljava/lang/String;
    //   905: invokevirtual 383	android/content/ContentValues:put	(Ljava/lang/String;Ljava/lang/String;)V
    //   908: aload_3
    //   909: getfield 375	com/tencent/mm/model/bl:bJt	I
    //   912: sipush 8192
    //   915: iand
    //   916: ifeq +15 -> 931
    //   919: aload 16
    //   921: ldc_w 442
    //   924: aload_3
    //   925: invokevirtual 445	com/tencent/mm/model/bl:getDigest	()Ljava/lang/String;
    //   928: invokevirtual 383	android/content/ContentValues:put	(Ljava/lang/String;Ljava/lang/String;)V
    //   931: aload_3
    //   932: getfield 375	com/tencent/mm/model/bl:bJt	I
    //   935: sipush 16384
    //   938: iand
    //   939: ifeq +18 -> 957
    //   942: aload 16
    //   944: ldc_w 447
    //   947: aload_3
    //   948: getfield 450	com/tencent/mm/model/bl:fne	I
    //   951: invokestatic 272	java/lang/Integer:valueOf	(I)Ljava/lang/Integer;
    //   954: invokevirtual 396	android/content/ContentValues:put	(Ljava/lang/String;Ljava/lang/Integer;)V
    //   957: aload_3
    //   958: getfield 375	com/tencent/mm/model/bl:bJt	I
    //   961: ldc_w 451
    //   964: iand
    //   965: ifeq +18 -> 983
    //   968: aload 16
    //   970: ldc_w 453
    //   973: aload_3
    //   974: getfield 456	com/tencent/mm/model/bl:fnf	J
    //   977: invokestatic 389	java/lang/Long:valueOf	(J)Ljava/lang/Long;
    //   980: invokevirtual 392	android/content/ContentValues:put	(Ljava/lang/String;Ljava/lang/Long;)V
    //   983: aload_3
    //   984: getfield 375	com/tencent/mm/model/bl:bJt	I
    //   987: ldc_w 457
    //   990: iand
    //   991: ifeq +24 -> 1015
    //   994: aload_3
    //   995: getfield 460	com/tencent/mm/model/bl:fng	Ljava/lang/String;
    //   998: ifnonnull +2005 -> 3003
    //   1001: ldc 154
    //   1003: astore 4
    //   1005: aload 16
    //   1007: ldc_w 462
    //   1010: aload 4
    //   1012: invokevirtual 383	android/content/ContentValues:put	(Ljava/lang/String;Ljava/lang/String;)V
    //   1015: aload_3
    //   1016: getfield 375	com/tencent/mm/model/bl:bJt	I
    //   1019: ldc_w 463
    //   1022: iand
    //   1023: ifeq +24 -> 1047
    //   1026: aload_3
    //   1027: getfield 466	com/tencent/mm/model/bl:fnh	Ljava/lang/String;
    //   1030: ifnonnull +1982 -> 3012
    //   1033: ldc 154
    //   1035: astore 4
    //   1037: aload 16
    //   1039: ldc_w 468
    //   1042: aload 4
    //   1044: invokevirtual 383	android/content/ContentValues:put	(Ljava/lang/String;Ljava/lang/String;)V
    //   1047: aload 15
    //   1049: getfield 95	com/tencent/mm/model/bm:fni	Lcom/tencent/mm/cd/h;
    //   1052: aload_3
    //   1053: getfield 372	com/tencent/mm/model/bl:type	I
    //   1056: invokestatic 99	com/tencent/mm/model/bm:kH	(I)Ljava/lang/String;
    //   1059: ldc_w 380
    //   1062: aload 16
    //   1064: invokevirtual 472	com/tencent/mm/cd/h:insert	(Ljava/lang/String;Ljava/lang/String;Landroid/content/ContentValues;)J
    //   1067: l2i
    //   1068: iconst_m1
    //   1069: if_icmpeq +1952 -> 3021
    //   1072: iconst_1
    //   1073: istore 17
    //   1075: iload 17
    //   1077: ifeq +2294 -> 3371
    //   1080: aload_1
    //   1081: ifnonnull +2287 -> 3368
    //   1084: aload 9
    //   1086: iload 10
    //   1088: invokeinterface 72 2 0
    //   1093: checkcast 74	com/tencent/mm/model/bl
    //   1096: astore_1
    //   1097: aload_1
    //   1098: iconst_1
    //   1099: putfield 91	com/tencent/mm/model/bl:fnd	I
    //   1102: iinc 8 1
    //   1105: iinc 10 1
    //   1108: goto -558 -> 550
    //   1111: ldc 154
    //   1113: astore 4
    //   1115: goto -799 -> 316
    //   1118: iload 13
    //   1120: bipush 20
    //   1122: if_icmpeq +53 -> 1175
    //   1125: iload 13
    //   1127: bipush 11
    //   1129: if_icmpeq +46 -> 1175
    //   1132: new 112	java/lang/StringBuilder
    //   1135: astore_1
    //   1136: aload_1
    //   1137: ldc_w 342
    //   1140: invokespecial 234	java/lang/StringBuilder:<init>	(Ljava/lang/String;)V
    //   1143: ldc 44
    //   1145: aload_1
    //   1146: aload 4
    //   1148: invokevirtual 121	java/lang/StringBuilder:append	(Ljava/lang/String;)Ljava/lang/StringBuilder;
    //   1151: ldc_w 474
    //   1154: invokevirtual 121	java/lang/StringBuilder:append	(Ljava/lang/String;)Ljava/lang/StringBuilder;
    //   1157: iload 13
    //   1159: invokevirtual 351	java/lang/StringBuilder:append	(I)Ljava/lang/StringBuilder;
    //   1162: invokevirtual 127	java/lang/StringBuilder:toString	()Ljava/lang/String;
    //   1165: invokestatic 255	com/tencent/mm/sdk/platformtools/ab:e	(Ljava/lang/String;Ljava/lang/String;)V
    //   1168: iload 10
    //   1170: istore 13
    //   1172: goto -766 -> 406
    //   1175: iload 13
    //   1177: istore 10
    //   1179: iload 12
    //   1181: istore 8
    //   1183: new 112	java/lang/StringBuilder
    //   1186: astore_3
    //   1187: iload 13
    //   1189: istore 10
    //   1191: iload 12
    //   1193: istore 8
    //   1195: aload_3
    //   1196: invokespecial 113	java/lang/StringBuilder:<init>	()V
    //   1199: iload 13
    //   1201: istore 10
    //   1203: iload 12
    //   1205: istore 8
    //   1207: aload 11
    //   1209: aload_3
    //   1210: aload 4
    //   1212: invokevirtual 121	java/lang/StringBuilder:append	(Ljava/lang/String;)Ljava/lang/StringBuilder;
    //   1215: ldc_w 476
    //   1218: invokevirtual 121	java/lang/StringBuilder:append	(Ljava/lang/String;)Ljava/lang/StringBuilder;
    //   1221: invokevirtual 127	java/lang/StringBuilder:toString	()Ljava/lang/String;
    //   1224: invokeinterface 334 2 0
    //   1229: checkcast 42	java/lang/String
    //   1232: astore 18
    //   1234: iload 13
    //   1236: istore 10
    //   1238: iload 12
    //   1240: istore 8
    //   1242: aload 18
    //   1244: invokestatic 362	com/tencent/mm/sdk/platformtools/bo:isNullOrNil	(Ljava/lang/String;)Z
    //   1247: ifeq +61 -> 1308
    //   1250: iload 13
    //   1252: istore 10
    //   1254: iload 12
    //   1256: istore 8
    //   1258: new 112	java/lang/StringBuilder
    //   1261: astore_1
    //   1262: iload 13
    //   1264: istore 10
    //   1266: iload 12
    //   1268: istore 8
    //   1270: aload_1
    //   1271: ldc_w 342
    //   1274: invokespecial 234	java/lang/StringBuilder:<init>	(Ljava/lang/String;)V
    //   1277: iload 13
    //   1279: istore 10
    //   1281: iload 12
    //   1283: istore 8
    //   1285: ldc 44
    //   1287: aload_1
    //   1288: aload 4
    //   1290: invokevirtual 121	java/lang/StringBuilder:append	(Ljava/lang/String;)Ljava/lang/StringBuilder;
    //   1293: ldc_w 478
    //   1296: invokevirtual 121	java/lang/StringBuilder:append	(Ljava/lang/String;)Ljava/lang/StringBuilder;
    //   1299: invokevirtual 127	java/lang/StringBuilder:toString	()Ljava/lang/String;
    //   1302: invokestatic 255	com/tencent/mm/sdk/platformtools/ab:e	(Ljava/lang/String;Ljava/lang/String;)V
    //   1305: goto -899 -> 406
    //   1308: iload 13
    //   1310: istore 10
    //   1312: iload 12
    //   1314: istore 8
    //   1316: new 112	java/lang/StringBuilder
    //   1319: astore_3
    //   1320: iload 13
    //   1322: istore 10
    //   1324: iload 12
    //   1326: istore 8
    //   1328: aload_3
    //   1329: invokespecial 113	java/lang/StringBuilder:<init>	()V
    //   1332: iload 13
    //   1334: istore 10
    //   1336: iload 12
    //   1338: istore 8
    //   1340: aload 11
    //   1342: aload_3
    //   1343: aload 4
    //   1345: invokevirtual 121	java/lang/StringBuilder:append	(Ljava/lang/String;)Ljava/lang/StringBuilder;
    //   1348: ldc_w 480
    //   1351: invokevirtual 121	java/lang/StringBuilder:append	(Ljava/lang/String;)Ljava/lang/StringBuilder;
    //   1354: invokevirtual 127	java/lang/StringBuilder:toString	()Ljava/lang/String;
    //   1357: invokeinterface 334 2 0
    //   1362: checkcast 42	java/lang/String
    //   1365: astore 19
    //   1367: iload 13
    //   1369: istore 10
    //   1371: iload 12
    //   1373: istore 8
    //   1375: new 112	java/lang/StringBuilder
    //   1378: astore_3
    //   1379: iload 13
    //   1381: istore 10
    //   1383: iload 12
    //   1385: istore 8
    //   1387: aload_3
    //   1388: invokespecial 113	java/lang/StringBuilder:<init>	()V
    //   1391: iload 13
    //   1393: istore 10
    //   1395: iload 12
    //   1397: istore 8
    //   1399: aload 11
    //   1401: aload_3
    //   1402: aload 4
    //   1404: invokevirtual 121	java/lang/StringBuilder:append	(Ljava/lang/String;)Ljava/lang/StringBuilder;
    //   1407: ldc_w 482
    //   1410: invokevirtual 121	java/lang/StringBuilder:append	(Ljava/lang/String;)Ljava/lang/StringBuilder;
    //   1413: invokevirtual 127	java/lang/StringBuilder:toString	()Ljava/lang/String;
    //   1416: invokeinterface 334 2 0
    //   1421: checkcast 42	java/lang/String
    //   1424: astore 16
    //   1426: iload 13
    //   1428: istore 10
    //   1430: iload 12
    //   1432: istore 8
    //   1434: new 112	java/lang/StringBuilder
    //   1437: astore_3
    //   1438: iload 13
    //   1440: istore 10
    //   1442: iload 12
    //   1444: istore 8
    //   1446: aload_3
    //   1447: invokespecial 113	java/lang/StringBuilder:<init>	()V
    //   1450: iload 13
    //   1452: istore 10
    //   1454: iload 12
    //   1456: istore 8
    //   1458: aload 11
    //   1460: aload_3
    //   1461: aload 4
    //   1463: invokevirtual 121	java/lang/StringBuilder:append	(Ljava/lang/String;)Ljava/lang/StringBuilder;
    //   1466: ldc_w 484
    //   1469: invokevirtual 121	java/lang/StringBuilder:append	(Ljava/lang/String;)Ljava/lang/StringBuilder;
    //   1472: invokevirtual 127	java/lang/StringBuilder:toString	()Ljava/lang/String;
    //   1475: invokeinterface 334 2 0
    //   1480: checkcast 42	java/lang/String
    //   1483: iconst_0
    //   1484: invokestatic 340	com/tencent/mm/sdk/platformtools/bo:getInt	(Ljava/lang/String;I)I
    //   1487: istore 20
    //   1489: iload 20
    //   1491: ifne +61 -> 1552
    //   1494: iload 13
    //   1496: istore 10
    //   1498: iload 12
    //   1500: istore 8
    //   1502: new 112	java/lang/StringBuilder
    //   1505: astore_1
    //   1506: iload 13
    //   1508: istore 10
    //   1510: iload 12
    //   1512: istore 8
    //   1514: aload_1
    //   1515: ldc_w 342
    //   1518: invokespecial 234	java/lang/StringBuilder:<init>	(Ljava/lang/String;)V
    //   1521: iload 13
    //   1523: istore 10
    //   1525: iload 12
    //   1527: istore 8
    //   1529: ldc 44
    //   1531: aload_1
    //   1532: aload 4
    //   1534: invokevirtual 121	java/lang/StringBuilder:append	(Ljava/lang/String;)Ljava/lang/StringBuilder;
    //   1537: ldc_w 486
    //   1540: invokevirtual 121	java/lang/StringBuilder:append	(Ljava/lang/String;)Ljava/lang/StringBuilder;
    //   1543: invokevirtual 127	java/lang/StringBuilder:toString	()Ljava/lang/String;
    //   1546: invokestatic 255	com/tencent/mm/sdk/platformtools/ab:e	(Ljava/lang/String;Ljava/lang/String;)V
    //   1549: goto -1143 -> 406
    //   1552: iload 20
    //   1554: iconst_1
    //   1555: if_icmple +1144 -> 2699
    //   1558: iload 13
    //   1560: istore 10
    //   1562: iload 12
    //   1564: istore 8
    //   1566: new 112	java/lang/StringBuilder
    //   1569: astore_3
    //   1570: iload 13
    //   1572: istore 10
    //   1574: iload 12
    //   1576: istore 8
    //   1578: aload_3
    //   1579: invokespecial 113	java/lang/StringBuilder:<init>	()V
    //   1582: iload 13
    //   1584: istore 10
    //   1586: iload 12
    //   1588: istore 8
    //   1590: aload_3
    //   1591: aload 4
    //   1593: invokevirtual 121	java/lang/StringBuilder:append	(Ljava/lang/String;)Ljava/lang/StringBuilder;
    //   1596: astore_3
    //   1597: iload 13
    //   1599: bipush 20
    //   1601: if_icmpne +1090 -> 2691
    //   1604: ldc_w 488
    //   1607: astore 4
    //   1609: iload 13
    //   1611: istore 10
    //   1613: iload 12
    //   1615: istore 8
    //   1617: aload_3
    //   1618: aload 4
    //   1620: invokevirtual 121	java/lang/StringBuilder:append	(Ljava/lang/String;)Ljava/lang/StringBuilder;
    //   1623: invokevirtual 127	java/lang/StringBuilder:toString	()Ljava/lang/String;
    //   1626: astore 4
    //   1628: iconst_0
    //   1629: istore 17
    //   1631: iload 17
    //   1633: iload 20
    //   1635: if_icmpge +1285 -> 2920
    //   1638: iload 13
    //   1640: istore 10
    //   1642: iload 12
    //   1644: istore 8
    //   1646: new 112	java/lang/StringBuilder
    //   1649: astore_3
    //   1650: iload 13
    //   1652: istore 10
    //   1654: iload 12
    //   1656: istore 8
    //   1658: aload_3
    //   1659: invokespecial 113	java/lang/StringBuilder:<init>	()V
    //   1662: iload 13
    //   1664: istore 10
    //   1666: iload 12
    //   1668: istore 8
    //   1670: aload_3
    //   1671: aload 4
    //   1673: invokevirtual 121	java/lang/StringBuilder:append	(Ljava/lang/String;)Ljava/lang/StringBuilder;
    //   1676: astore 15
    //   1678: iload 17
    //   1680: ifle +1071 -> 2751
    //   1683: iload 13
    //   1685: istore 10
    //   1687: iload 12
    //   1689: istore 8
    //   1691: iload 17
    //   1693: invokestatic 272	java/lang/Integer:valueOf	(I)Ljava/lang/Integer;
    //   1696: astore_3
    //   1697: iload 13
    //   1699: istore 10
    //   1701: iload 12
    //   1703: istore 8
    //   1705: aload 15
    //   1707: aload_3
    //   1708: invokevirtual 327	java/lang/StringBuilder:append	(Ljava/lang/Object;)Ljava/lang/StringBuilder;
    //   1711: invokevirtual 127	java/lang/StringBuilder:toString	()Ljava/lang/String;
    //   1714: astore 21
    //   1716: iload 13
    //   1718: istore 10
    //   1720: iload 12
    //   1722: istore 8
    //   1724: new 74	com/tencent/mm/model/bl
    //   1727: astore 22
    //   1729: iload 13
    //   1731: istore 10
    //   1733: iload 12
    //   1735: istore 8
    //   1737: aload 22
    //   1739: invokespecial 196	com/tencent/mm/model/bl:<init>	()V
    //   1742: iload 13
    //   1744: istore 10
    //   1746: iload 12
    //   1748: istore 8
    //   1750: aload 22
    //   1752: aload_2
    //   1753: getfield 491	com/tencent/mm/protocal/protobuf/cm:ptD	I
    //   1756: i2l
    //   1757: putfield 456	com/tencent/mm/model/bl:fnf	J
    //   1760: iload 13
    //   1762: istore 10
    //   1764: iload 12
    //   1766: istore 8
    //   1768: new 112	java/lang/StringBuilder
    //   1771: astore_3
    //   1772: iload 13
    //   1774: istore 10
    //   1776: iload 12
    //   1778: istore 8
    //   1780: aload_3
    //   1781: invokespecial 113	java/lang/StringBuilder:<init>	()V
    //   1784: iload 13
    //   1786: istore 10
    //   1788: iload 12
    //   1790: istore 8
    //   1792: aload 22
    //   1794: aload 11
    //   1796: aload_3
    //   1797: aload 21
    //   1799: invokevirtual 121	java/lang/StringBuilder:append	(Ljava/lang/String;)Ljava/lang/StringBuilder;
    //   1802: ldc_w 493
    //   1805: invokevirtual 121	java/lang/StringBuilder:append	(Ljava/lang/String;)Ljava/lang/StringBuilder;
    //   1808: invokevirtual 127	java/lang/StringBuilder:toString	()Ljava/lang/String;
    //   1811: invokeinterface 334 2 0
    //   1816: checkcast 42	java/lang/String
    //   1819: putfield 495	com/tencent/mm/model/bl:title	Ljava/lang/String;
    //   1822: iload 17
    //   1824: ifne +939 -> 2763
    //   1827: iload 13
    //   1829: istore 10
    //   1831: iload 12
    //   1833: istore 8
    //   1835: aload 22
    //   1837: iconst_1
    //   1838: putfield 91	com/tencent/mm/model/bl:fnd	I
    //   1841: iload 13
    //   1843: istore 10
    //   1845: iload 12
    //   1847: istore 8
    //   1849: aload 22
    //   1851: aload 19
    //   1853: putfield 498	com/tencent/mm/model/bl:fjx	Ljava/lang/String;
    //   1856: iload 13
    //   1858: istore 10
    //   1860: iload 12
    //   1862: istore 8
    //   1864: aload 16
    //   1866: invokestatic 362	com/tencent/mm/sdk/platformtools/bo:isNullOrNil	(Ljava/lang/String;)Z
    //   1869: ifeq +888 -> 2757
    //   1872: iload 13
    //   1874: istore 10
    //   1876: iload 12
    //   1878: istore 8
    //   1880: new 112	java/lang/StringBuilder
    //   1883: astore_3
    //   1884: iload 13
    //   1886: istore 10
    //   1888: iload 12
    //   1890: istore 8
    //   1892: aload_3
    //   1893: invokespecial 113	java/lang/StringBuilder:<init>	()V
    //   1896: iload 13
    //   1898: istore 10
    //   1900: iload 12
    //   1902: istore 8
    //   1904: aload 11
    //   1906: aload_3
    //   1907: aload 21
    //   1909: invokevirtual 121	java/lang/StringBuilder:append	(Ljava/lang/String;)Ljava/lang/StringBuilder;
    //   1912: ldc_w 500
    //   1915: invokevirtual 121	java/lang/StringBuilder:append	(Ljava/lang/String;)Ljava/lang/StringBuilder;
    //   1918: invokevirtual 127	java/lang/StringBuilder:toString	()Ljava/lang/String;
    //   1921: invokeinterface 334 2 0
    //   1926: checkcast 42	java/lang/String
    //   1929: astore_3
    //   1930: iload 13
    //   1932: istore 10
    //   1934: iload 12
    //   1936: istore 8
    //   1938: aload 22
    //   1940: aload_3
    //   1941: putfield 503	com/tencent/mm/model/bl:fjz	Ljava/lang/String;
    //   1944: iload 13
    //   1946: istore 10
    //   1948: iload 12
    //   1950: istore 8
    //   1952: new 112	java/lang/StringBuilder
    //   1955: astore_3
    //   1956: iload 13
    //   1958: istore 10
    //   1960: iload 12
    //   1962: istore 8
    //   1964: aload_3
    //   1965: invokespecial 113	java/lang/StringBuilder:<init>	()V
    //   1968: iload 13
    //   1970: istore 10
    //   1972: iload 12
    //   1974: istore 8
    //   1976: aload 11
    //   1978: aload_3
    //   1979: aload 21
    //   1981: invokevirtual 121	java/lang/StringBuilder:append	(Ljava/lang/String;)Ljava/lang/StringBuilder;
    //   1984: ldc_w 505
    //   1987: invokevirtual 121	java/lang/StringBuilder:append	(Ljava/lang/String;)Ljava/lang/StringBuilder;
    //   1990: invokevirtual 127	java/lang/StringBuilder:toString	()Ljava/lang/String;
    //   1993: invokeinterface 508 2 0
    //   1998: ifeq +916 -> 2914
    //   2001: iconst_1
    //   2002: istore 23
    //   2004: iload 13
    //   2006: istore 10
    //   2008: iload 12
    //   2010: istore 8
    //   2012: aload 22
    //   2014: iload 23
    //   2016: putfield 450	com/tencent/mm/model/bl:fne	I
    //   2019: iload 13
    //   2021: istore 10
    //   2023: iload 12
    //   2025: istore 8
    //   2027: new 112	java/lang/StringBuilder
    //   2030: astore_3
    //   2031: iload 13
    //   2033: istore 10
    //   2035: iload 12
    //   2037: istore 8
    //   2039: aload_3
    //   2040: invokespecial 113	java/lang/StringBuilder:<init>	()V
    //   2043: iload 13
    //   2045: istore 10
    //   2047: iload 12
    //   2049: istore 8
    //   2051: aload 22
    //   2053: aload 11
    //   2055: aload_3
    //   2056: aload 21
    //   2058: invokevirtual 121	java/lang/StringBuilder:append	(Ljava/lang/String;)Ljava/lang/StringBuilder;
    //   2061: ldc_w 510
    //   2064: invokevirtual 121	java/lang/StringBuilder:append	(Ljava/lang/String;)Ljava/lang/StringBuilder;
    //   2067: invokevirtual 127	java/lang/StringBuilder:toString	()Ljava/lang/String;
    //   2070: invokeinterface 334 2 0
    //   2075: checkcast 42	java/lang/String
    //   2078: putfield 512	com/tencent/mm/model/bl:url	Ljava/lang/String;
    //   2081: iload 13
    //   2083: istore 10
    //   2085: iload 12
    //   2087: istore 8
    //   2089: new 112	java/lang/StringBuilder
    //   2092: astore_3
    //   2093: iload 13
    //   2095: istore 10
    //   2097: iload 12
    //   2099: istore 8
    //   2101: aload_3
    //   2102: invokespecial 113	java/lang/StringBuilder:<init>	()V
    //   2105: iload 13
    //   2107: istore 10
    //   2109: iload 12
    //   2111: istore 8
    //   2113: aload 22
    //   2115: aload 11
    //   2117: aload_3
    //   2118: aload 21
    //   2120: invokevirtual 121	java/lang/StringBuilder:append	(Ljava/lang/String;)Ljava/lang/StringBuilder;
    //   2123: ldc_w 514
    //   2126: invokevirtual 121	java/lang/StringBuilder:append	(Ljava/lang/String;)Ljava/lang/StringBuilder;
    //   2129: invokevirtual 127	java/lang/StringBuilder:toString	()Ljava/lang/String;
    //   2132: invokeinterface 334 2 0
    //   2137: checkcast 42	java/lang/String
    //   2140: putfield 517	com/tencent/mm/model/bl:fmY	Ljava/lang/String;
    //   2143: iload 13
    //   2145: istore 10
    //   2147: iload 12
    //   2149: istore 8
    //   2151: new 112	java/lang/StringBuilder
    //   2154: astore_3
    //   2155: iload 13
    //   2157: istore 10
    //   2159: iload 12
    //   2161: istore 8
    //   2163: aload_3
    //   2164: invokespecial 113	java/lang/StringBuilder:<init>	()V
    //   2167: iload 13
    //   2169: istore 10
    //   2171: iload 12
    //   2173: istore 8
    //   2175: aload 22
    //   2177: aload 11
    //   2179: aload_3
    //   2180: aload 21
    //   2182: invokevirtual 121	java/lang/StringBuilder:append	(Ljava/lang/String;)Ljava/lang/StringBuilder;
    //   2185: ldc_w 519
    //   2188: invokevirtual 121	java/lang/StringBuilder:append	(Ljava/lang/String;)Ljava/lang/StringBuilder;
    //   2191: invokevirtual 127	java/lang/StringBuilder:toString	()Ljava/lang/String;
    //   2194: invokeinterface 334 2 0
    //   2199: checkcast 42	java/lang/String
    //   2202: putfield 416	com/tencent/mm/model/bl:fmZ	Ljava/lang/String;
    //   2205: iload 13
    //   2207: istore 10
    //   2209: iload 12
    //   2211: istore 8
    //   2213: new 112	java/lang/StringBuilder
    //   2216: astore_3
    //   2217: iload 13
    //   2219: istore 10
    //   2221: iload 12
    //   2223: istore 8
    //   2225: aload_3
    //   2226: invokespecial 113	java/lang/StringBuilder:<init>	()V
    //   2229: iload 13
    //   2231: istore 10
    //   2233: iload 12
    //   2235: istore 8
    //   2237: aload 22
    //   2239: aload 11
    //   2241: aload_3
    //   2242: aload 21
    //   2244: invokevirtual 121	java/lang/StringBuilder:append	(Ljava/lang/String;)Ljava/lang/StringBuilder;
    //   2247: ldc_w 521
    //   2250: invokevirtual 121	java/lang/StringBuilder:append	(Ljava/lang/String;)Ljava/lang/StringBuilder;
    //   2253: invokevirtual 127	java/lang/StringBuilder:toString	()Ljava/lang/String;
    //   2256: invokeinterface 334 2 0
    //   2261: checkcast 42	java/lang/String
    //   2264: lconst_0
    //   2265: invokestatic 525	com/tencent/mm/sdk/platformtools/bo:getLong	(Ljava/lang/String;J)J
    //   2268: putfield 423	com/tencent/mm/model/bl:fna	J
    //   2271: iload 13
    //   2273: istore 10
    //   2275: iload 12
    //   2277: istore 8
    //   2279: new 112	java/lang/StringBuilder
    //   2282: astore_3
    //   2283: iload 13
    //   2285: istore 10
    //   2287: iload 12
    //   2289: istore 8
    //   2291: aload_3
    //   2292: invokespecial 113	java/lang/StringBuilder:<init>	()V
    //   2295: iload 13
    //   2297: istore 10
    //   2299: iload 12
    //   2301: istore 8
    //   2303: aload 11
    //   2305: aload_3
    //   2306: aload 21
    //   2308: invokevirtual 121	java/lang/StringBuilder:append	(Ljava/lang/String;)Ljava/lang/StringBuilder;
    //   2311: ldc_w 527
    //   2314: invokevirtual 121	java/lang/StringBuilder:append	(Ljava/lang/String;)Ljava/lang/StringBuilder;
    //   2317: invokevirtual 127	java/lang/StringBuilder:toString	()Ljava/lang/String;
    //   2320: invokeinterface 334 2 0
    //   2325: checkcast 42	java/lang/String
    //   2328: astore 15
    //   2330: aload 15
    //   2332: ifnull +24 -> 2356
    //   2335: aload 15
    //   2337: astore_3
    //   2338: iload 13
    //   2340: istore 10
    //   2342: iload 12
    //   2344: istore 8
    //   2346: ldc 154
    //   2348: aload 15
    //   2350: invokevirtual 220	java/lang/String:equals	(Ljava/lang/Object;)Z
    //   2353: ifeq +109 -> 2462
    //   2356: iload 13
    //   2358: istore 10
    //   2360: iload 12
    //   2362: istore 8
    //   2364: new 529	java/util/Date
    //   2367: astore_3
    //   2368: iload 13
    //   2370: istore 10
    //   2372: iload 12
    //   2374: istore 8
    //   2376: aload_3
    //   2377: invokestatic 240	java/lang/System:currentTimeMillis	()J
    //   2380: iload 17
    //   2382: i2l
    //   2383: ladd
    //   2384: invokespecial 531	java/util/Date:<init>	(J)V
    //   2387: iload 13
    //   2389: istore 10
    //   2391: iload 12
    //   2393: istore 8
    //   2395: new 112	java/lang/StringBuilder
    //   2398: astore 15
    //   2400: iload 13
    //   2402: istore 10
    //   2404: iload 12
    //   2406: istore 8
    //   2408: aload 15
    //   2410: ldc_w 533
    //   2413: invokespecial 234	java/lang/StringBuilder:<init>	(Ljava/lang/String;)V
    //   2416: iload 13
    //   2418: istore 10
    //   2420: iload 12
    //   2422: istore 8
    //   2424: aload 15
    //   2426: aload 7
    //   2428: aload_3
    //   2429: invokevirtual 537	java/text/SimpleDateFormat:format	(Ljava/util/Date;)Ljava/lang/String;
    //   2432: invokevirtual 121	java/lang/StringBuilder:append	(Ljava/lang/String;)Ljava/lang/StringBuilder;
    //   2435: invokevirtual 127	java/lang/StringBuilder:toString	()Ljava/lang/String;
    //   2438: astore_3
    //   2439: iload 13
    //   2441: istore 10
    //   2443: iload 12
    //   2445: istore 8
    //   2447: ldc 44
    //   2449: ldc_w 539
    //   2452: aload_3
    //   2453: invokestatic 542	java/lang/String:valueOf	(Ljava/lang/Object;)Ljava/lang/String;
    //   2456: invokevirtual 545	java/lang/String:concat	(Ljava/lang/String;)Ljava/lang/String;
    //   2459: invokestatic 358	com/tencent/mm/sdk/platformtools/ab:d	(Ljava/lang/String;Ljava/lang/String;)V
    //   2462: iload 13
    //   2464: istore 10
    //   2466: iload 12
    //   2468: istore 8
    //   2470: aload 22
    //   2472: aload_3
    //   2473: putfield 548	com/tencent/mm/model/bl:fmX	Ljava/lang/String;
    //   2476: iload 13
    //   2478: istore 10
    //   2480: iload 12
    //   2482: istore 8
    //   2484: new 112	java/lang/StringBuilder
    //   2487: astore_3
    //   2488: iload 13
    //   2490: istore 10
    //   2492: iload 12
    //   2494: istore 8
    //   2496: aload_3
    //   2497: invokespecial 113	java/lang/StringBuilder:<init>	()V
    //   2500: iload 13
    //   2502: istore 10
    //   2504: iload 12
    //   2506: istore 8
    //   2508: aload 22
    //   2510: aload 11
    //   2512: aload_3
    //   2513: aload 21
    //   2515: invokevirtual 121	java/lang/StringBuilder:append	(Ljava/lang/String;)Ljava/lang/StringBuilder;
    //   2518: ldc_w 550
    //   2521: invokevirtual 121	java/lang/StringBuilder:append	(Ljava/lang/String;)Ljava/lang/StringBuilder;
    //   2524: invokevirtual 127	java/lang/StringBuilder:toString	()Ljava/lang/String;
    //   2527: invokeinterface 334 2 0
    //   2532: checkcast 42	java/lang/String
    //   2535: putfield 553	com/tencent/mm/model/bl:fnb	Ljava/lang/String;
    //   2538: iload 13
    //   2540: istore 10
    //   2542: iload 12
    //   2544: istore 8
    //   2546: new 112	java/lang/StringBuilder
    //   2549: astore_3
    //   2550: iload 13
    //   2552: istore 10
    //   2554: iload 12
    //   2556: istore 8
    //   2558: aload_3
    //   2559: invokespecial 113	java/lang/StringBuilder:<init>	()V
    //   2562: iload 13
    //   2564: istore 10
    //   2566: iload 12
    //   2568: istore 8
    //   2570: aload 22
    //   2572: aload 11
    //   2574: aload_3
    //   2575: aload 21
    //   2577: invokevirtual 121	java/lang/StringBuilder:append	(Ljava/lang/String;)Ljava/lang/StringBuilder;
    //   2580: ldc_w 555
    //   2583: invokevirtual 121	java/lang/StringBuilder:append	(Ljava/lang/String;)Ljava/lang/StringBuilder;
    //   2586: invokevirtual 127	java/lang/StringBuilder:toString	()Ljava/lang/String;
    //   2589: invokeinterface 334 2 0
    //   2594: checkcast 42	java/lang/String
    //   2597: putfield 558	com/tencent/mm/model/bl:fnc	Ljava/lang/String;
    //   2600: iload 13
    //   2602: istore 10
    //   2604: iload 12
    //   2606: istore 8
    //   2608: aload 22
    //   2610: iload 12
    //   2612: i2l
    //   2613: lload 5
    //   2615: ldc2_w 241
    //   2618: lmul
    //   2619: ladd
    //   2620: putfield 207	com/tencent/mm/model/bl:time	J
    //   2623: iload 13
    //   2625: istore 10
    //   2627: iload 12
    //   2629: istore 8
    //   2631: aload 22
    //   2633: iload 13
    //   2635: putfield 372	com/tencent/mm/model/bl:type	I
    //   2638: iload 13
    //   2640: istore 10
    //   2642: iload 12
    //   2644: istore 8
    //   2646: aload 22
    //   2648: aload 18
    //   2650: putfield 560	com/tencent/mm/model/bl:name	Ljava/lang/String;
    //   2653: iload 13
    //   2655: istore 10
    //   2657: iload 12
    //   2659: istore 8
    //   2661: aload 22
    //   2663: aload_1
    //   2664: putfield 460	com/tencent/mm/model/bl:fng	Ljava/lang/String;
    //   2667: iload 13
    //   2669: istore 10
    //   2671: iload 12
    //   2673: istore 8
    //   2675: aload 9
    //   2677: aload 22
    //   2679: invokeinterface 563 2 0
    //   2684: pop
    //   2685: iinc 17 1
    //   2688: goto -1057 -> 1631
    //   2691: ldc_w 565
    //   2694: astore 4
    //   2696: goto -1087 -> 1609
    //   2699: iload 13
    //   2701: istore 10
    //   2703: iload 12
    //   2705: istore 8
    //   2707: new 112	java/lang/StringBuilder
    //   2710: astore_3
    //   2711: iload 13
    //   2713: istore 10
    //   2715: iload 12
    //   2717: istore 8
    //   2719: aload_3
    //   2720: invokespecial 113	java/lang/StringBuilder:<init>	()V
    //   2723: iload 13
    //   2725: istore 10
    //   2727: iload 12
    //   2729: istore 8
    //   2731: aload_3
    //   2732: aload 4
    //   2734: invokevirtual 121	java/lang/StringBuilder:append	(Ljava/lang/String;)Ljava/lang/StringBuilder;
    //   2737: ldc_w 565
    //   2740: invokevirtual 121	java/lang/StringBuilder:append	(Ljava/lang/String;)Ljava/lang/StringBuilder;
    //   2743: invokevirtual 127	java/lang/StringBuilder:toString	()Ljava/lang/String;
    //   2746: astore 4
    //   2748: goto -1120 -> 1628
    //   2751: ldc 154
    //   2753: astore_3
    //   2754: goto -1057 -> 1697
    //   2757: aload 16
    //   2759: astore_3
    //   2760: goto -830 -> 1930
    //   2763: iload 13
    //   2765: istore 10
    //   2767: iload 12
    //   2769: istore 8
    //   2771: new 112	java/lang/StringBuilder
    //   2774: astore_3
    //   2775: iload 13
    //   2777: istore 10
    //   2779: iload 12
    //   2781: istore 8
    //   2783: aload_3
    //   2784: invokespecial 113	java/lang/StringBuilder:<init>	()V
    //   2787: iload 13
    //   2789: istore 10
    //   2791: iload 12
    //   2793: istore 8
    //   2795: aload 22
    //   2797: aload 11
    //   2799: aload_3
    //   2800: aload 21
    //   2802: invokevirtual 121	java/lang/StringBuilder:append	(Ljava/lang/String;)Ljava/lang/StringBuilder;
    //   2805: ldc_w 567
    //   2808: invokevirtual 121	java/lang/StringBuilder:append	(Ljava/lang/String;)Ljava/lang/StringBuilder;
    //   2811: invokevirtual 127	java/lang/StringBuilder:toString	()Ljava/lang/String;
    //   2814: invokeinterface 334 2 0
    //   2819: checkcast 42	java/lang/String
    //   2822: putfield 498	com/tencent/mm/model/bl:fjx	Ljava/lang/String;
    //   2825: iload 13
    //   2827: istore 10
    //   2829: iload 12
    //   2831: istore 8
    //   2833: new 112	java/lang/StringBuilder
    //   2836: astore_3
    //   2837: iload 13
    //   2839: istore 10
    //   2841: iload 12
    //   2843: istore 8
    //   2845: aload_3
    //   2846: invokespecial 113	java/lang/StringBuilder:<init>	()V
    //   2849: iload 13
    //   2851: istore 10
    //   2853: iload 12
    //   2855: istore 8
    //   2857: aload 22
    //   2859: aload 11
    //   2861: aload_3
    //   2862: aload 21
    //   2864: invokevirtual 121	java/lang/StringBuilder:append	(Ljava/lang/String;)Ljava/lang/StringBuilder;
    //   2867: ldc_w 500
    //   2870: invokevirtual 121	java/lang/StringBuilder:append	(Ljava/lang/String;)Ljava/lang/StringBuilder;
    //   2873: invokevirtual 127	java/lang/StringBuilder:toString	()Ljava/lang/String;
    //   2876: invokeinterface 334 2 0
    //   2881: checkcast 42	java/lang/String
    //   2884: putfield 503	com/tencent/mm/model/bl:fjz	Ljava/lang/String;
    //   2887: goto -943 -> 1944
    //   2890: astore_1
    //   2891: iload 10
    //   2893: istore 13
    //   2895: iload 8
    //   2897: istore 12
    //   2899: ldc 44
    //   2901: aload_1
    //   2902: ldc 154
    //   2904: iconst_0
    //   2905: anewarray 4	java/lang/Object
    //   2908: invokestatic 571	com/tencent/mm/sdk/platformtools/ab:printErrStackTrace	(Ljava/lang/String;Ljava/lang/Throwable;Ljava/lang/String;[Ljava/lang/Object;)V
    //   2911: goto -2505 -> 406
    //   2914: iconst_0
    //   2915: istore 23
    //   2917: goto -913 -> 2004
    //   2920: iinc 12 1
    //   2923: iload 13
    //   2925: istore 10
    //   2927: goto -2639 -> 288
    //   2930: iload 10
    //   2932: istore 13
    //   2934: goto -2528 -> 406
    //   2937: aload 4
    //   2939: invokevirtual 408	com/tencent/mm/model/bl:getUrl	()Ljava/lang/String;
    //   2942: invokestatic 362	com/tencent/mm/sdk/platformtools/bo:isNullOrNil	(Ljava/lang/String;)Z
    //   2945: ifeq -2492 -> 453
    //   2948: ldc 44
    //   2950: new 112	java/lang/StringBuilder
    //   2953: dup
    //   2954: ldc_w 573
    //   2957: invokespecial 234	java/lang/StringBuilder:<init>	(Ljava/lang/String;)V
    //   2960: aload 4
    //   2962: invokevirtual 367	com/tencent/mm/model/bl:aaj	()Ljava/lang/String;
    //   2965: invokevirtual 121	java/lang/StringBuilder:append	(Ljava/lang/String;)Ljava/lang/StringBuilder;
    //   2968: ldc_w 369
    //   2971: invokevirtual 121	java/lang/StringBuilder:append	(Ljava/lang/String;)Ljava/lang/StringBuilder;
    //   2974: aload 4
    //   2976: getfield 372	com/tencent/mm/model/bl:type	I
    //   2979: invokevirtual 351	java/lang/StringBuilder:append	(I)Ljava/lang/StringBuilder;
    //   2982: invokevirtual 127	java/lang/StringBuilder:toString	()Ljava/lang/String;
    //   2985: invokestatic 255	com/tencent/mm/sdk/platformtools/ab:e	(Ljava/lang/String;Ljava/lang/String;)V
    //   2988: iconst_0
    //   2989: istore 10
    //   2991: goto -2464 -> 527
    //   2994: aload_3
    //   2995: getfield 416	com/tencent/mm/model/bl:fmZ	Ljava/lang/String;
    //   2998: astore 4
    //   3000: goto -2223 -> 777
    //   3003: aload_3
    //   3004: getfield 460	com/tencent/mm/model/bl:fng	Ljava/lang/String;
    //   3007: astore 4
    //   3009: goto -2004 -> 1005
    //   3012: aload_3
    //   3013: getfield 466	com/tencent/mm/model/bl:fnh	Ljava/lang/String;
    //   3016: astore 4
    //   3018: goto -1981 -> 1037
    //   3021: iconst_0
    //   3022: istore 17
    //   3024: goto -1949 -> 1075
    //   3027: ldc 44
    //   3029: ldc_w 575
    //   3032: iconst_2
    //   3033: anewarray 4	java/lang/Object
    //   3036: dup
    //   3037: iconst_0
    //   3038: iload 8
    //   3040: invokestatic 272	java/lang/Integer:valueOf	(I)Ljava/lang/Integer;
    //   3043: aastore
    //   3044: dup
    //   3045: iconst_1
    //   3046: iload 12
    //   3048: invokestatic 272	java/lang/Integer:valueOf	(I)Ljava/lang/Integer;
    //   3051: aastore
    //   3052: invokestatic 51	com/tencent/mm/sdk/platformtools/ab:i	(Ljava/lang/String;Ljava/lang/String;[Ljava/lang/Object;)V
    //   3055: iload 8
    //   3057: ifle +275 -> 3332
    //   3060: ldc 169
    //   3062: invokestatic 175	com/tencent/mm/kernel/g:K	(Ljava/lang/Class;)Lcom/tencent/mm/kernel/c/a;
    //   3065: checkcast 169	com/tencent/mm/plugin/messenger/foundation/a/j
    //   3068: invokeinterface 179 1 0
    //   3073: iload 13
    //   3075: invokestatic 148	com/tencent/mm/model/bl:kG	(I)Ljava/lang/String;
    //   3078: invokeinterface 193 2 0
    //   3083: astore 4
    //   3085: aload 4
    //   3087: ifnull +19 -> 3106
    //   3090: aload 4
    //   3092: getfield 578	com/tencent/mm/g/c/at:field_username	Ljava/lang/String;
    //   3095: iload 13
    //   3097: invokestatic 148	com/tencent/mm/model/bl:kG	(I)Ljava/lang/String;
    //   3100: invokevirtual 220	java/lang/String:equals	(Ljava/lang/Object;)Z
    //   3103: ifne +163 -> 3266
    //   3106: new 144	com/tencent/mm/storage/ak
    //   3109: dup
    //   3110: invokespecial 145	com/tencent/mm/storage/ak:<init>	()V
    //   3113: astore_3
    //   3114: aload_3
    //   3115: iload 13
    //   3117: invokestatic 148	com/tencent/mm/model/bl:kG	(I)Ljava/lang/String;
    //   3120: invokevirtual 152	com/tencent/mm/storage/ak:setUsername	(Ljava/lang/String;)V
    //   3123: aload_1
    //   3124: ifnonnull +124 -> 3248
    //   3127: ldc 154
    //   3129: astore 4
    //   3131: aload_3
    //   3132: aload 4
    //   3134: invokevirtual 157	com/tencent/mm/storage/ak:setContent	(Ljava/lang/String;)V
    //   3137: aload_1
    //   3138: ifnonnull +119 -> 3257
    //   3141: invokestatic 581	com/tencent/mm/sdk/platformtools/bo:anU	()J
    //   3144: lstore 5
    //   3146: aload_3
    //   3147: lload 5
    //   3149: invokevirtual 161	com/tencent/mm/storage/ak:eD	(J)V
    //   3152: aload_3
    //   3153: iconst_0
    //   3154: invokevirtual 164	com/tencent/mm/storage/ak:hO	(I)V
    //   3157: aload_3
    //   3158: iload 12
    //   3160: invokevirtual 167	com/tencent/mm/storage/ak:hM	(I)V
    //   3163: ldc 169
    //   3165: invokestatic 175	com/tencent/mm/kernel/g:K	(Ljava/lang/Class;)Lcom/tencent/mm/kernel/c/a;
    //   3168: checkcast 169	com/tencent/mm/plugin/messenger/foundation/a/j
    //   3171: invokeinterface 179 1 0
    //   3176: aload_3
    //   3177: invokeinterface 584 2 0
    //   3182: pop2
    //   3183: invokestatic 57	com/tencent/mm/plugin/readerapp/c/g:cdZ	()Lcom/tencent/mm/model/bm;
    //   3186: invokevirtual 110	com/tencent/mm/model/bm:doNotify	()V
    //   3189: aload_1
    //   3190: invokevirtual 203	com/tencent/mm/model/bl:getTitle	()Ljava/lang/String;
    //   3193: astore 4
    //   3195: new 586	com/tencent/mm/storage/bi
    //   3198: dup
    //   3199: invokespecial 587	com/tencent/mm/storage/bi:<init>	()V
    //   3202: astore_1
    //   3203: aload_1
    //   3204: aload 4
    //   3206: invokevirtual 588	com/tencent/mm/storage/bi:setContent	(Ljava/lang/String;)V
    //   3209: aload_1
    //   3210: iload 13
    //   3212: invokestatic 148	com/tencent/mm/model/bl:kG	(I)Ljava/lang/String;
    //   3215: invokevirtual 591	com/tencent/mm/storage/bi:ju	(Ljava/lang/String;)V
    //   3218: aload_1
    //   3219: iconst_1
    //   3220: invokevirtual 594	com/tencent/mm/storage/bi:setType	(I)V
    //   3223: aload_1
    //   3224: ldc2_w 595
    //   3227: invokevirtual 599	com/tencent/mm/storage/bi:setMsgId	(J)V
    //   3230: new 601	com/tencent/mm/ai/e$b
    //   3233: dup
    //   3234: aload_1
    //   3235: iconst_1
    //   3236: invokespecial 604	com/tencent/mm/ai/e$b:<init>	(Lcom/tencent/mm/storage/bi;Z)V
    //   3239: astore_1
    //   3240: ldc 223
    //   3242: invokestatic 29	com/tencent/matrix/trace/core/AppMethodBeat:o	(I)V
    //   3245: goto -3172 -> 73
    //   3248: aload_1
    //   3249: invokevirtual 203	com/tencent/mm/model/bl:getTitle	()Ljava/lang/String;
    //   3252: astore 4
    //   3254: goto -123 -> 3131
    //   3257: aload_1
    //   3258: getfield 207	com/tencent/mm/model/bl:time	J
    //   3261: lstore 5
    //   3263: goto -117 -> 3146
    //   3266: aload 4
    //   3268: aload_1
    //   3269: invokevirtual 203	com/tencent/mm/model/bl:getTitle	()Ljava/lang/String;
    //   3272: invokevirtual 157	com/tencent/mm/storage/ak:setContent	(Ljava/lang/String;)V
    //   3275: aload 4
    //   3277: aload_1
    //   3278: getfield 207	com/tencent/mm/model/bl:time	J
    //   3281: invokevirtual 161	com/tencent/mm/storage/ak:eD	(J)V
    //   3284: aload 4
    //   3286: iconst_0
    //   3287: invokevirtual 164	com/tencent/mm/storage/ak:hO	(I)V
    //   3290: aload 4
    //   3292: aload 4
    //   3294: getfield 212	com/tencent/mm/g/c/at:field_unReadCount	I
    //   3297: iload 12
    //   3299: iadd
    //   3300: invokevirtual 167	com/tencent/mm/storage/ak:hM	(I)V
    //   3303: ldc 169
    //   3305: invokestatic 175	com/tencent/mm/kernel/g:K	(Ljava/lang/Class;)Lcom/tencent/mm/kernel/c/a;
    //   3308: checkcast 169	com/tencent/mm/plugin/messenger/foundation/a/j
    //   3311: invokeinterface 179 1 0
    //   3316: aload 4
    //   3318: iload 13
    //   3320: invokestatic 148	com/tencent/mm/model/bl:kG	(I)Ljava/lang/String;
    //   3323: invokeinterface 184 3 0
    //   3328: pop
    //   3329: goto -146 -> 3183
    //   3332: ldc 44
    //   3334: ldc_w 606
    //   3337: invokestatic 255	com/tencent/mm/sdk/platformtools/ab:e	(Ljava/lang/String;Ljava/lang/String;)V
    //   3340: aconst_null
    //   3341: astore_1
    //   3342: ldc 223
    //   3344: invokestatic 29	com/tencent/matrix/trace/core/AppMethodBeat:o	(I)V
    //   3347: goto -3274 -> 73
    //   3350: aconst_null
    //   3351: astore_1
    //   3352: ldc 223
    //   3354: invokestatic 29	com/tencent/matrix/trace/core/AppMethodBeat:o	(I)V
    //   3357: goto -3284 -> 73
    //   3360: astore_1
    //   3361: iload 10
    //   3363: istore 13
    //   3365: goto -466 -> 2899
    //   3368: goto -2266 -> 1102
    //   3371: goto -2266 -> 1105
    //   3374: iconst_1
    //   3375: istore 10
    //   3377: goto -2850 -> 527
    //
    // Exception table:
    //   from	to	target	type
    //   257	267	2890	java/lang/Exception
    //   1183	1187	2890	java/lang/Exception
    //   1195	1199	2890	java/lang/Exception
    //   1207	1234	2890	java/lang/Exception
    //   1242	1250	2890	java/lang/Exception
    //   1258	1262	2890	java/lang/Exception
    //   1270	1277	2890	java/lang/Exception
    //   1285	1305	2890	java/lang/Exception
    //   1316	1320	2890	java/lang/Exception
    //   1328	1332	2890	java/lang/Exception
    //   1340	1367	2890	java/lang/Exception
    //   1375	1379	2890	java/lang/Exception
    //   1387	1391	2890	java/lang/Exception
    //   1399	1426	2890	java/lang/Exception
    //   1434	1438	2890	java/lang/Exception
    //   1446	1450	2890	java/lang/Exception
    //   1458	1489	2890	java/lang/Exception
    //   1502	1506	2890	java/lang/Exception
    //   1514	1521	2890	java/lang/Exception
    //   1529	1549	2890	java/lang/Exception
    //   1566	1570	2890	java/lang/Exception
    //   1578	1582	2890	java/lang/Exception
    //   1590	1597	2890	java/lang/Exception
    //   1617	1628	2890	java/lang/Exception
    //   1646	1650	2890	java/lang/Exception
    //   1658	1662	2890	java/lang/Exception
    //   1670	1678	2890	java/lang/Exception
    //   1691	1697	2890	java/lang/Exception
    //   1705	1716	2890	java/lang/Exception
    //   1724	1729	2890	java/lang/Exception
    //   1737	1742	2890	java/lang/Exception
    //   1750	1760	2890	java/lang/Exception
    //   1768	1772	2890	java/lang/Exception
    //   1780	1784	2890	java/lang/Exception
    //   1792	1822	2890	java/lang/Exception
    //   1835	1841	2890	java/lang/Exception
    //   1849	1856	2890	java/lang/Exception
    //   1864	1872	2890	java/lang/Exception
    //   1880	1884	2890	java/lang/Exception
    //   1892	1896	2890	java/lang/Exception
    //   1904	1930	2890	java/lang/Exception
    //   1938	1944	2890	java/lang/Exception
    //   1952	1956	2890	java/lang/Exception
    //   1964	1968	2890	java/lang/Exception
    //   1976	2001	2890	java/lang/Exception
    //   2012	2019	2890	java/lang/Exception
    //   2027	2031	2890	java/lang/Exception
    //   2039	2043	2890	java/lang/Exception
    //   2051	2081	2890	java/lang/Exception
    //   2089	2093	2890	java/lang/Exception
    //   2101	2105	2890	java/lang/Exception
    //   2113	2143	2890	java/lang/Exception
    //   2151	2155	2890	java/lang/Exception
    //   2163	2167	2890	java/lang/Exception
    //   2175	2205	2890	java/lang/Exception
    //   2213	2217	2890	java/lang/Exception
    //   2225	2229	2890	java/lang/Exception
    //   2237	2271	2890	java/lang/Exception
    //   2279	2283	2890	java/lang/Exception
    //   2291	2295	2890	java/lang/Exception
    //   2303	2330	2890	java/lang/Exception
    //   2346	2356	2890	java/lang/Exception
    //   2364	2368	2890	java/lang/Exception
    //   2376	2387	2890	java/lang/Exception
    //   2395	2400	2890	java/lang/Exception
    //   2408	2416	2890	java/lang/Exception
    //   2424	2439	2890	java/lang/Exception
    //   2447	2462	2890	java/lang/Exception
    //   2470	2476	2890	java/lang/Exception
    //   2484	2488	2890	java/lang/Exception
    //   2496	2500	2890	java/lang/Exception
    //   2508	2538	2890	java/lang/Exception
    //   2546	2550	2890	java/lang/Exception
    //   2558	2562	2890	java/lang/Exception
    //   2570	2600	2890	java/lang/Exception
    //   2608	2623	2890	java/lang/Exception
    //   2631	2638	2890	java/lang/Exception
    //   2646	2653	2890	java/lang/Exception
    //   2661	2667	2890	java/lang/Exception
    //   2675	2685	2890	java/lang/Exception
    //   2707	2711	2890	java/lang/Exception
    //   2719	2723	2890	java/lang/Exception
    //   2731	2748	2890	java/lang/Exception
    //   2771	2775	2890	java/lang/Exception
    //   2783	2787	2890	java/lang/Exception
    //   2795	2825	2890	java/lang/Exception
    //   2833	2837	2890	java/lang/Exception
    //   2845	2849	2890	java/lang/Exception
    //   2857	2887	2890	java/lang/Exception
    //   293	304	3360	java/lang/Exception
    //   309	316	3360	java/lang/Exception
    //   316	366	3360	java/lang/Exception
    //   371	402	3360	java/lang/Exception
    //   1132	1168	3360	java/lang/Exception
  }
}

/* Location:           C:\Users\Lin\Downloads\dex-tools-2.1-SNAPSHOT\dex-tools-2.1-SNAPSHOT\classes4-dex2jar.jar
 * Qualified Name:     com.tencent.mm.plugin.readerapp.c.c
 * JD-Core Version:    0.6.2
 */