package com.tencent.mm.plugin.wallet_core.model;

import java.util.Map;

final class r$7$1
  implements Runnable
{
  r$7$1(r.7 param7, Map paramMap)
  {
  }

  // ERROR //
  public final void run()
  {
    // Byte code:
    //   0: ldc 29
    //   2: invokestatic 35	com/tencent/matrix/trace/core/AppMethodBeat:i	(I)V
    //   5: aconst_null
    //   6: astore_1
    //   7: aload_0
    //   8: getfield 21	com/tencent/mm/plugin/wallet_core/model/r$7$1:tCg	Ljava/util/Map;
    //   11: ldc 37
    //   13: invokeinterface 43 2 0
    //   18: checkcast 45	java/lang/String
    //   21: astore_2
    //   22: aload_0
    //   23: getfield 21	com/tencent/mm/plugin/wallet_core/model/r$7$1:tCg	Ljava/util/Map;
    //   26: ldc 47
    //   28: invokeinterface 43 2 0
    //   33: checkcast 45	java/lang/String
    //   36: astore_3
    //   37: aload_0
    //   38: getfield 21	com/tencent/mm/plugin/wallet_core/model/r$7$1:tCg	Ljava/util/Map;
    //   41: ldc 49
    //   43: invokeinterface 43 2 0
    //   48: checkcast 45	java/lang/String
    //   51: astore 4
    //   53: aload_0
    //   54: getfield 21	com/tencent/mm/plugin/wallet_core/model/r$7$1:tCg	Ljava/util/Map;
    //   57: ldc 51
    //   59: invokeinterface 43 2 0
    //   64: checkcast 45	java/lang/String
    //   67: astore 5
    //   69: aload_2
    //   70: ldc 53
    //   72: invokestatic 59	java/net/URLDecoder:decode	(Ljava/lang/String;Ljava/lang/String;)Ljava/lang/String;
    //   75: astore 6
    //   77: aload_3
    //   78: invokestatic 65	com/tencent/mm/sdk/platformtools/bo:isNullOrNil	(Ljava/lang/String;)Z
    //   81: ifne +341 -> 422
    //   84: aload_3
    //   85: invokestatic 71	com/tencent/mm/model/r:Yz	()Ljava/lang/String;
    //   88: invokevirtual 75	java/lang/String:equals	(Ljava/lang/Object;)Z
    //   91: ifne +331 -> 422
    //   94: aload_3
    //   95: astore_2
    //   96: aload_3
    //   97: invokestatic 80	com/tencent/mm/model/t:kH	(Ljava/lang/String;)Z
    //   100: ifeq +328 -> 428
    //   103: aload_3
    //   104: astore_2
    //   105: ldc 82
    //   107: ldc 84
    //   109: iconst_5
    //   110: anewarray 4	java/lang/Object
    //   113: dup
    //   114: iconst_0
    //   115: invokestatic 71	com/tencent/mm/model/r:Yz	()Ljava/lang/String;
    //   118: aastore
    //   119: dup
    //   120: iconst_1
    //   121: aload_3
    //   122: aastore
    //   123: dup
    //   124: iconst_2
    //   125: aload 4
    //   127: aastore
    //   128: dup
    //   129: iconst_3
    //   130: aload_2
    //   131: aastore
    //   132: dup
    //   133: iconst_4
    //   134: aload 5
    //   136: aastore
    //   137: invokestatic 89	com/tencent/mm/sdk/platformtools/ab:i	(Ljava/lang/String;Ljava/lang/String;[Ljava/lang/Object;)V
    //   140: aload 6
    //   142: invokestatic 95	com/tencent/mm/af/j$b:me	(Ljava/lang/String;)Lcom/tencent/mm/af/j$b;
    //   145: astore 5
    //   147: ldc 82
    //   149: ldc 97
    //   151: iconst_2
    //   152: anewarray 4	java/lang/Object
    //   155: dup
    //   156: iconst_0
    //   157: aload 6
    //   159: aastore
    //   160: dup
    //   161: iconst_1
    //   162: aload 5
    //   164: aastore
    //   165: invokestatic 89	com/tencent/mm/sdk/platformtools/ab:i	(Ljava/lang/String;Ljava/lang/String;[Ljava/lang/Object;)V
    //   168: new 99	java/util/ArrayList
    //   171: astore_3
    //   172: aload_3
    //   173: invokespecial 100	java/util/ArrayList:<init>	()V
    //   176: aload 5
    //   178: ifnull +497 -> 675
    //   181: ldc 102
    //   183: invokestatic 108	com/tencent/mm/kernel/g:K	(Ljava/lang/Class;)Lcom/tencent/mm/kernel/c/a;
    //   186: checkcast 102	com/tencent/mm/plugin/messenger/foundation/a/j
    //   189: invokeinterface 112 1 0
    //   194: aload_2
    //   195: invokeinterface 118 2 0
    //   200: astore_2
    //   201: aload_2
    //   202: ifnull +277 -> 479
    //   205: aload_2
    //   206: astore 4
    //   208: aload_2
    //   209: invokeinterface 124 1 0
    //   214: ifeq +265 -> 479
    //   217: aload_2
    //   218: astore 4
    //   220: new 126	com/tencent/mm/storage/bi
    //   223: astore 7
    //   225: aload_2
    //   226: astore 4
    //   228: aload 7
    //   230: invokespecial 127	com/tencent/mm/storage/bi:<init>	()V
    //   233: aload_2
    //   234: astore 4
    //   236: aload 7
    //   238: aload_2
    //   239: invokevirtual 131	com/tencent/mm/storage/bi:d	(Landroid/database/Cursor;)V
    //   242: aload_2
    //   243: astore 4
    //   245: aload 7
    //   247: getfield 137	com/tencent/mm/g/c/cy:field_content	Ljava/lang/String;
    //   250: invokestatic 95	com/tencent/mm/af/j$b:me	(Ljava/lang/String;)Lcom/tencent/mm/af/j$b;
    //   253: astore_1
    //   254: aload_1
    //   255: ifnull -50 -> 205
    //   258: aload_2
    //   259: astore 4
    //   261: aload_1
    //   262: getfield 140	com/tencent/mm/af/j$b:fib	Ljava/lang/String;
    //   265: invokestatic 65	com/tencent/mm/sdk/platformtools/bo:isNullOrNil	(Ljava/lang/String;)Z
    //   268: ifne -63 -> 205
    //   271: aload_2
    //   272: astore 4
    //   274: aload_1
    //   275: getfield 140	com/tencent/mm/af/j$b:fib	Ljava/lang/String;
    //   278: aload 5
    //   280: getfield 140	com/tencent/mm/af/j$b:fib	Ljava/lang/String;
    //   283: invokevirtual 75	java/lang/String:equals	(Ljava/lang/Object;)Z
    //   286: ifeq -81 -> 205
    //   289: aload_2
    //   290: astore 4
    //   292: ldc 82
    //   294: ldc 142
    //   296: iconst_3
    //   297: anewarray 4	java/lang/Object
    //   300: dup
    //   301: iconst_0
    //   302: aload 7
    //   304: getfield 146	com/tencent/mm/g/c/cy:field_msgId	J
    //   307: invokestatic 152	java/lang/Long:valueOf	(J)Ljava/lang/Long;
    //   310: aastore
    //   311: dup
    //   312: iconst_1
    //   313: aload 7
    //   315: getfield 155	com/tencent/mm/g/c/cy:field_talker	Ljava/lang/String;
    //   318: aastore
    //   319: dup
    //   320: iconst_2
    //   321: aload 7
    //   323: getfield 159	com/tencent/mm/g/c/cy:field_isSend	I
    //   326: invokestatic 164	java/lang/Integer:valueOf	(I)Ljava/lang/Integer;
    //   329: aastore
    //   330: invokestatic 89	com/tencent/mm/sdk/platformtools/ab:i	(Ljava/lang/String;Ljava/lang/String;[Ljava/lang/Object;)V
    //   333: aload_2
    //   334: astore 4
    //   336: aload 7
    //   338: getfield 155	com/tencent/mm/g/c/cy:field_talker	Ljava/lang/String;
    //   341: invokestatic 80	com/tencent/mm/model/t:kH	(Ljava/lang/String;)Z
    //   344: ifeq +102 -> 446
    //   347: aload_2
    //   348: astore 4
    //   350: aload 7
    //   352: aload 6
    //   354: aload 7
    //   356: getfield 137	com/tencent/mm/g/c/cy:field_content	Ljava/lang/String;
    //   359: invokestatic 170	com/tencent/mm/model/bf:oy	(Ljava/lang/String;)Ljava/lang/String;
    //   362: invokestatic 173	com/tencent/mm/model/bf:al	(Ljava/lang/String;Ljava/lang/String;)Ljava/lang/String;
    //   365: invokevirtual 177	com/tencent/mm/storage/bi:setContent	(Ljava/lang/String;)V
    //   368: aload_2
    //   369: astore 4
    //   371: aload_3
    //   372: aload 7
    //   374: invokeinterface 182 2 0
    //   379: pop
    //   380: goto -175 -> 205
    //   383: astore_3
    //   384: aload_2
    //   385: astore 4
    //   387: ldc 82
    //   389: aload_3
    //   390: ldc 184
    //   392: iconst_1
    //   393: anewarray 4	java/lang/Object
    //   396: dup
    //   397: iconst_0
    //   398: aload_3
    //   399: invokevirtual 187	java/lang/Exception:getMessage	()Ljava/lang/String;
    //   402: aastore
    //   403: invokestatic 191	com/tencent/mm/sdk/platformtools/ab:printErrStackTrace	(Ljava/lang/String;Ljava/lang/Throwable;Ljava/lang/String;[Ljava/lang/Object;)V
    //   406: aload_2
    //   407: ifnull +225 -> 632
    //   410: aload_2
    //   411: invokeinterface 194 1 0
    //   416: ldc 29
    //   418: invokestatic 197	com/tencent/matrix/trace/core/AppMethodBeat:o	(I)V
    //   421: return
    //   422: aload 4
    //   424: astore_2
    //   425: goto -329 -> 96
    //   428: aload 4
    //   430: invokestatic 80	com/tencent/mm/model/t:kH	(Ljava/lang/String;)Z
    //   433: istore 8
    //   435: iload 8
    //   437: ifeq +243 -> 680
    //   440: aload 4
    //   442: astore_2
    //   443: goto -338 -> 105
    //   446: aload_2
    //   447: astore 4
    //   449: aload 7
    //   451: aload 6
    //   453: invokevirtual 177	com/tencent/mm/storage/bi:setContent	(Ljava/lang/String;)V
    //   456: goto -88 -> 368
    //   459: astore_2
    //   460: aload 4
    //   462: ifnull +10 -> 472
    //   465: aload 4
    //   467: invokeinterface 194 1 0
    //   472: ldc 29
    //   474: invokestatic 197	com/tencent/matrix/trace/core/AppMethodBeat:o	(I)V
    //   477: aload_2
    //   478: athrow
    //   479: aload_2
    //   480: astore 4
    //   482: aload_2
    //   483: ifnull +12 -> 495
    //   486: aload_2
    //   487: invokeinterface 194 1 0
    //   492: aconst_null
    //   493: astore 4
    //   495: aload 4
    //   497: astore_2
    //   498: ldc 82
    //   500: ldc 199
    //   502: iconst_1
    //   503: anewarray 4	java/lang/Object
    //   506: dup
    //   507: iconst_0
    //   508: aload_3
    //   509: aastore
    //   510: invokestatic 89	com/tencent/mm/sdk/platformtools/ab:i	(Ljava/lang/String;Ljava/lang/String;[Ljava/lang/Object;)V
    //   513: aload_3
    //   514: invokeinterface 203 1 0
    //   519: ifle +95 -> 614
    //   522: aload_3
    //   523: invokeinterface 207 1 0
    //   528: astore 4
    //   530: aload 4
    //   532: invokeinterface 212 1 0
    //   537: ifeq +77 -> 614
    //   540: aload 4
    //   542: invokeinterface 216 1 0
    //   547: checkcast 126	com/tencent/mm/storage/bi
    //   550: astore_3
    //   551: ldc 82
    //   553: ldc 218
    //   555: iconst_2
    //   556: anewarray 4	java/lang/Object
    //   559: dup
    //   560: iconst_0
    //   561: aload_3
    //   562: getfield 146	com/tencent/mm/g/c/cy:field_msgId	J
    //   565: invokestatic 152	java/lang/Long:valueOf	(J)Ljava/lang/Long;
    //   568: aastore
    //   569: dup
    //   570: iconst_1
    //   571: aload_3
    //   572: getfield 137	com/tencent/mm/g/c/cy:field_content	Ljava/lang/String;
    //   575: aastore
    //   576: invokestatic 89	com/tencent/mm/sdk/platformtools/ab:i	(Ljava/lang/String;Ljava/lang/String;[Ljava/lang/Object;)V
    //   579: ldc 102
    //   581: invokestatic 108	com/tencent/mm/kernel/g:K	(Ljava/lang/Class;)Lcom/tencent/mm/kernel/c/a;
    //   584: checkcast 102	com/tencent/mm/plugin/messenger/foundation/a/j
    //   587: invokeinterface 112 1 0
    //   592: aload_3
    //   593: getfield 146	com/tencent/mm/g/c/cy:field_msgId	J
    //   596: aload_3
    //   597: invokeinterface 221 4 0
    //   602: goto -72 -> 530
    //   605: astore_3
    //   606: goto -222 -> 384
    //   609: astore 4
    //   611: goto -113 -> 498
    //   614: aload_2
    //   615: ifnull +17 -> 632
    //   618: aload_2
    //   619: invokeinterface 194 1 0
    //   624: ldc 29
    //   626: invokestatic 197	com/tencent/matrix/trace/core/AppMethodBeat:o	(I)V
    //   629: goto -208 -> 421
    //   632: ldc 29
    //   634: invokestatic 197	com/tencent/matrix/trace/core/AppMethodBeat:o	(I)V
    //   637: goto -216 -> 421
    //   640: astore_2
    //   641: aload_1
    //   642: astore 4
    //   644: goto -184 -> 460
    //   647: astore_3
    //   648: aload_2
    //   649: astore 4
    //   651: aload_3
    //   652: astore_2
    //   653: goto -193 -> 460
    //   656: astore 4
    //   658: aload_2
    //   659: astore_3
    //   660: aload 4
    //   662: astore_2
    //   663: aload_3
    //   664: astore 4
    //   666: goto -206 -> 460
    //   669: astore_3
    //   670: aconst_null
    //   671: astore_2
    //   672: goto -288 -> 384
    //   675: aconst_null
    //   676: astore_2
    //   677: goto -198 -> 479
    //   680: goto -575 -> 105
    //
    // Exception table:
    //   from	to	target	type
    //   208	217	383	java/lang/Exception
    //   220	225	383	java/lang/Exception
    //   228	233	383	java/lang/Exception
    //   236	242	383	java/lang/Exception
    //   245	254	383	java/lang/Exception
    //   261	271	383	java/lang/Exception
    //   274	289	383	java/lang/Exception
    //   292	333	383	java/lang/Exception
    //   336	347	383	java/lang/Exception
    //   350	368	383	java/lang/Exception
    //   371	380	383	java/lang/Exception
    //   449	456	383	java/lang/Exception
    //   208	217	459	finally
    //   220	225	459	finally
    //   228	233	459	finally
    //   236	242	459	finally
    //   245	254	459	finally
    //   261	271	459	finally
    //   274	289	459	finally
    //   292	333	459	finally
    //   336	347	459	finally
    //   350	368	459	finally
    //   371	380	459	finally
    //   387	406	459	finally
    //   449	456	459	finally
    //   498	530	605	java/lang/Exception
    //   530	602	605	java/lang/Exception
    //   486	492	609	java/lang/Exception
    //   7	94	640	finally
    //   96	103	640	finally
    //   105	176	640	finally
    //   181	201	640	finally
    //   428	435	640	finally
    //   486	492	647	finally
    //   498	530	656	finally
    //   530	602	656	finally
    //   7	94	669	java/lang/Exception
    //   96	103	669	java/lang/Exception
    //   105	176	669	java/lang/Exception
    //   181	201	669	java/lang/Exception
    //   428	435	669	java/lang/Exception
  }
}

/* Location:           C:\Users\Lin\Downloads\dex-tools-2.1-SNAPSHOT\dex-tools-2.1-SNAPSHOT\classes8-dex2jar.jar
 * Qualified Name:     com.tencent.mm.plugin.wallet_core.model.r.7.1
 * JD-Core Version:    0.6.2
 */